Workbook
Name _bdm.146e958bbea04416b86a4d5943392c04.edm: Model!$M$100
Name _bdm.bf5a9ed53fe44c598e3cfb84ac34b21f.edm: Integrity!$F$37
Name Case_Scenario: Cover!$F$22
Name Company_Cyclical_Multiples_Data: 'Multiples Data'!$C$14:$H$26
Name Company_Name: Cover!$F$19
Name Company_Rev_Methodology: 'Revenue Build'!$C$7
Name Cost_of_Debt: WACC!$G$17
Name Cost_of_Equity: WACC!$G$25
Name Cost_of_Preferred: WACC!$G$10
Name Current_Date: Cover!$F$27
Name Cycle_Period_Toggle: Valuation!$G$221
Name Cycle_Toggle: Valuation!$G$220
Name Cyclical_LTM_NTM_Toggle: Valuation!$G$222
Name Cyclical_Peer_Group_Toggle: Valuation!$G$223
Name Data: Model!$C$25:$AK$159
Name Diluted_Shares: Cover!$F$35
Name Discount_Rate: WACC!$O$13
Name Div_Yield: Cover!$F$34
Name ERP: WACC!$G$7
Name Fiscal_Periods: Model!$C$25:$AG$25
Name Header_Row: $IV$11:$ROW$17
Name Hun: Cover!$F$41
Name IQRAF17: $AF$18:$AF$269
Name IQRC117: $C$118
Name IQRC12: $C$13
Name IQRC121: $C$122
Name IQRC123: $C$124
Name IQRC124: $C$125
Name IQRC125: $C$126
Name IQRC126: $C$127
Name IQRC5: $C$6:$C$13
Name IQRC94: $C$95
Name IQRCIQIDLocaterI13: 'CIQ ID Locater'!$K$14:$O$14
Name IQRCIQIDLocaterI14: 'CIQ ID Locater'!$K$15:$O$15
Name IQRCIQIDLocaterI15: 'CIQ ID Locater'!$K$16:$O$16
Name IQRCIQIDLocaterI16: 'CIQ ID Locater'!$K$17:$O$17
Name IQRCIQIDLocaterI17: 'CIQ ID Locater'!$K$18:$N$18
Name IQRCIQIDLocaterI18: 'CIQ ID Locater'!$K$19:$O$19
Name IQRCIQIDLocaterI19: 'CIQ ID Locater'!$K$20:$O$20
Name IQRCIQIDLocaterI20: 'CIQ ID Locater'!$K$21:$O$21
Name IQRCIQIDLocaterI21: 'CIQ ID Locater'!$K$22:$O$22
Name IQRCIQIDLocaterI22: 'CIQ ID Locater'!$K$23:$O$23
Name IQRCIQIDLocaterI23: 'CIQ ID Locater'!$K$24:$O$24
Name IQRCIQIDLocaterI24: 'CIQ ID Locater'!$K$25:$O$25
Name IQRCIQIDLocaterI25: 'CIQ ID Locater'!$K$26:$O$26
Name IQRCIQIDLocaterI26: 'CIQ ID Locater'!$K$27:$O$27
Name IQRCIQIDLocaterI27: 'CIQ ID Locater'!$K$28:$O$28
Name IQRCIQIDLocaterI28: 'CIQ ID Locater'!$K$29:$L$29
Name IQRCIQIDLocaterI29: 'CIQ ID Locater'!$K$30
Name IQRCIQIDLocaterO13: 'CIQ ID Locater'!$Q$14:$U$14
Name IQRCIQIDLocaterO14: 'CIQ ID Locater'!$Q$15:$U$15
Name IQRCIQIDLocaterO15: 'CIQ ID Locater'!$Q$16:$U$16
Name IQRCIQIDLocaterO16: 'CIQ ID Locater'!$Q$17:$U$17
Name IQRCIQIDLocaterO17: 'CIQ ID Locater'!$Q$18:$T$18
Name IQRCIQIDLocaterO18: 'CIQ ID Locater'!$Q$19:$U$19
Name IQRCIQIDLocaterO19: 'CIQ ID Locater'!$Q$20:$U$20
Name IQRCIQIDLocaterO20: 'CIQ ID Locater'!$Q$21:$U$21
Name IQRCIQIDLocaterO21: 'CIQ ID Locater'!$Q$22:$U$22
Name IQRCIQIDLocaterO22: 'CIQ ID Locater'!$Q$23:$U$23
Name IQRCIQIDLocaterO23: 'CIQ ID Locater'!$Q$24:$U$24

Sheet Intro
B1: William C. Dunkelberg Owl Fund - Valuation Workbook
A3: x | B3: INSTRUCTIONS - Please Read
B4: There are many tabs within the workbook, all of which are relevant and important to completing a proper valuation for your target company. Before beginning, ensure that your Excel options menu (under the 'Formulas' tab) is set up correctly, as shown in the picture to the right. Regardless of whether you set 'Workbook Calculation' to "Automatic" or "Automatic except for data tables," hit the F9 key when making changes to data tables to ensure all tables update. All values throughout the workbook are color-coded (blue, black or green) to allow for easier navigation & recognition. The 'Drivers' and 'Revenue Build' tabs are used to conduct a scenario analysis (Bull, Bear & Base cases). Input the assumptions in the appropriate cells and select your 'Active Case' in the Revenue Build tab (using the drop down menu in cell C9). READ ALL COMMENTS THROUGHOUT THE WORKBOOK (denoted by red triangles in the upper right corner of cells) as they will help you complete certain parts of the model! Make sure to change existing comments & input YOUR OWN to inform others of your assumptions. The 'Summary' tab combines everything into "report-ready" format. When submitting the final model with your Initiating Coverage Report, hide / remove this 'Intro' tab, but keep all other tabs visible. Be wary of copying or filling down the line with formulas. Formulas in quarterly periods will likely not be applicable or correct in an annual column. Additionally, not every quarterly formula will work for other quarterly columns (e.g. QoQ growth for 1Q would use 4Q as a base, which is 2 columns away vs other quarters using bases 1 column to the left). It is very important that you do not change the name of line items. Other items in the workbook are linked to values based on that nomenclature. You should have all the core items that you need and any extranneous items can be grouped in the "Other" row for that section. We can't contruct a schedule to project every little item every company reports, so we schedule the ones that every company has and group the rest together. For quick navigation, "X's" are placed in the left-hand columns of each worksheet. Use "CTRL + pg dn/pg up" to jump around the workbook. When attempting to locate a cell's precedents (i.e. to jump to the linked cells), use " CTRL + [ ". Hit the F5 key (or CTRL + G) and then "ENTER" to return to the original cell. Stay consistent with modeling best practices (i.e. consistent color-coding for input values, formulas, linked cells, etc.) if you make any changes to the model. You may delete this tab before finalizing.

Sheet Cover
C1: =Company_Name&" - "&MID(CELL("filename",A1),FIND("]",CELL("filename",A1))+1,255)&": "&Case_Scenario&" Case" -> Lowe's Companies, Inc. - Cover: Base Case | Q1: Font Toggle
C2: $ in Millions Except Per Share Data | Q2: Working
R3: x
A4: x | C4: Model Assumptions: | I4: Return Summary:
I6: Discounted Cash Flow Analysis | N6: Multiple Analysis
I8: Exit Multiple Method | N8: EV/EBITDA Method
I9: Implied Enterprise Value: | L9: =Valuation!K65 | P9: Target Price: | Q9: % Return:
I10: Implied Equity Value: | L10: =Valuation!K72
N11: 1 Year LTM EV/EBITDA | P11: =Valuation!N137 | Q11: =Valuation!N138
I12: Implied Share Price: | L12: =Valuation!K76
I13: % Return: | L13: =Valuation!K77 | N13: 2009-2018 Late Cycle EV/EBITDA | P13: =Valuation!N215 | Q13: =Valuation!N216
I15: Perpetuity Growth Method | N15: P/E Multiple Method
I16: Implied Enterprise Value: | L16: =Valuation!R65 | P16: Target Price: | Q16: % Return:
I17: Implied Equity Value: | L17: =Valuation!R72
N18: 1 Year LTM P/E | P18: =Valuation!F126 | Q18: =Valuation!F127
C19: Company Name | F19: Apple Inc. | I19: Implied Share Price: | L19: =Valuation!R76
C20: Ticker | F20: AAPL | I20: % Return: | L20: =Valuation!R77 | N20: 2009-2018 Late Cycle P/E | P20: =Valuation!F204 | Q20: =Valuation!F205
C22: Case Scenario | F22: Base | I22: Table of Contents
C24: Last Fiscal Year | F24: 46022 | I24: Cover
C25: Next Fiscal Year | F25: =Last_FYE+365 -> 46387 | I25: Summary
C26: Last Fiscal Quarter Reported | F26: 2Q | I26: Football Field
C27: Current Valuation Date | F27: 45903 | I27: Integrity
I28: Revenue Build
C29: Current Share Price | F29: 233.18 | I29: Model
C30: 52-Week High | F30: 215.22 | I30: Segment Analysis
C31: 52-Week Low | F31: 146.72 | I31: Drivers
I32: WACC
C33: Effective Tax Rate | F33: =IF(Last_FQR="1Q",Model!U71,IF(Last_FQR="2Q",Model!V71,IF(Last_FQR="3Q",Model!W71,Model!X71))) -> 0.24436655 | I33: Valuation
C34: Dividend Yield | F34: =IF(Last_FQR="1Q",Model!U265,IF(Last_FQR="2Q",Model!V265,IF(Last_FQR="3Q",Model!W265,Model!X265))) -> 0.01277896 | I34: Comparables
C35: Diluted Shares Outstanding (MRQ) | F35: =IF(Last_FQR="1Q",Model!U284,IF(Last_FQR="2Q",Model!V284,IF(Last_FQR="3Q",Model!W284,Model!X284))) -> 707 | I35: Charts
I36: Benchmark
C37: Model Type | F37: Top Down | I37: Multiples Data
I38: Pre-Earnings
I39: Post-Earnings
A42: x
C43: Model Color Legend | I43: Constants
C44: Blue = Hard-Coded Value (historical values & assumptions) | I44: Reference | J44: Type | K44: Name | L44: Value
C45: Black = Formulas | I45: Million | J45: (#) | K45: Mil | L45: 1000000
C46: Green = Linked Value (from separate worksheet) | I46: Thousand | J46: (#) | K46: Thou | L46: 1000
C47: Red = Unique Formula / Anomaly | I47: Hundred | J47: (#) | K47: Hun | L47: 100
A48: x
C49: Tab Color Codes
C51: Summary
C53: Model
A54: x
C55: Supporting/Auxiliary
C57: Valuation
C59: Comps
C61: RBG Codes for Model
C63: 0-0-255 | F63: Hard-Coded Numbers
C65: 0-128-0 | F65: Linked Numbers
C67: 255-223-159 | F67: Owl Fund Gold
C69: 255-255-153 | F69: Drivers / Assumptions
C71: 118-0-0 | F71: Owl Fund Red
C73: 0-56-96 | F73: Section Headers
C75: 192-222-246 | F75: Sub-Section Headers
C77: 215-215-215 | F77: Historical Quarters
C79: 235-235-235 | F79: Projected Quarters
C81: 255-255-255 | F81: Annuals
A83: x | B83: x | C83: END

Sheet Summary
C1: =Company_Name&" - "&MID(CELL("filename",A1),FIND("]",CELL("filename",A1))+1,255)&": "&Case_Scenario&" Case" -> Lowe's Companies, Inc. - Summary: Base Case
C2: =Cover!C2 -> $ in Millions Except Per Share Data
C4: Year: | T4: =Model!J24 -> 2023 | U4: =Model!O24 -> 2024 | V4: =Model!T24 -> 2025 | W4: =Model!Y24 -> 2026 | X4: =Model!AD24 -> 2027 | Y4: =Model!AE24 -> 2028 | Z4: =Model!AF24 -> 2029 | AA4: =Model!AG24 -> 2030
G5: Quarterly | T5: Annuals | AC5: CAGR | AE5: CAGR
A6: x | C6: ="Consolidated "&Model!C25 -> Consolidated Income Statement | G6: =Model!P25 -> 1Q25 | H6: =Model!Q25 -> 2Q25 | I6: =Model!R25 -> 3Q25 | J6: =Model!S25 -> 4Q25 | K6: =Model!U25 -> 1Q26 | L6: =Model!V25 -> 2Q26 | M6: =Model!W25 -> 3Q26e | N6: =Model!X25 -> 4Q26e | O6: =Model!Z25 -> 1Q27e | P6: =Model!AA25 -> 2Q27e | Q6: =Model!AB25 -> 3Q27e | R6: =Model!AC25 -> 4Q27e | T6: =Model!J25 -> 2023 | U6: =Model!O25 -> 2024 | V6: =Model!T25 -> 2025 | W6: =Model!Y25 -> 2026e | X6: =Model!AD25 -> 2027e | Y6: =Model!AE25 -> 2028e | Z6: =Model!AF25 -> 2029e | AA6: =Model!AG25 -> 2030e | AC6: Historical | AE6: Projected
C8: =Model!C28 -> Revenue | G8: =Model!P28 -> 19675 | H8: =Model!Q28 -> 27302 | I8: =Model!R28 -> 22309 | J8: =Model!S28 -> 20311 | K8: =Model!U28 -> 24422 | L8: =Model!V28 -> 27570 | M8: =Model!W28 -> 22918 | N8: =Model!X28 -> 21772.1 | O8: =Model!Z28 -> 25691.078 | P8: =Model!AA28 -> 29287.829 | Q8: =Model!AB28 -> 25773.289 | R8: =Model!AC28 -> 24484.625 | T8: =Model!J28 -> 71309 | U8: =Model!O28 -> 72148 | V8: =Model!T28 -> 89597 | W8: =Model!Y28 -> 96682.1 | X8: =Model!AD28 -> 105236.82 | Y8: =Model!AE28 -> 107341.56 | Z8: =Model!AF28 -> 109488.39 | AA8: =Model!AG28 -> 111678.16 | AC8: =IFERROR((V8/T8)^(1/(V$4-T$4))-1,"N/A") -> 0.12091985 | AE8: =IFERROR((AA8/V8)^(1/(AA$4-V$4))-1,"N/A") -> 0.045044909
C9: YoY % Growth | K9: =K8/G8-1 -> 0.24127065 | L9: =L8/H8-1 -> 0.0098161307 | M9: =M8/I8-1 -> 0.0272984 | N9: =N8/J8-1 -> 0.071936389 | O9: =O8/K8-1 -> 0.05196454 | P9: =P8/L8-1 -> 0.062307904 | Q9: =Q8/M8-1 -> 0.1245872 | R9: =R8/N8-1 -> 0.1245872 | U9: =IF(ISERROR(U8/T8-1),"NA",(U8/T8-1)) -> 0.011765696 | V9: =IF(ISERROR(V8/U8-1),"NA",(V8/U8-1)) -> 0.24185009 | W9: =IF(ISERROR(W8/V8-1),"NA",(W8/V8-1)) -> 0.079077424 | X9: =IF(ISERROR(X8/W8-1),"NA",(X8/W8-1)) -> 0.088482991 | Y9: =IF(ISERROR(Y8/X8-1),"NA",(Y8/X8-1)) -> 0.02 | Z9: =IF(ISERROR(Z8/Y8-1),"NA",(Z8/Y8-1)) -> 0.02 | AA9: =IF(ISERROR(AA8/Z8-1),"NA",(AA8/Z8-1)) -> 0.02
C11: =Model!C30 -> Gross Profit | G11: =Model!P30 -> 6513 | H11: =Model!Q30 -> 9304 | I11: =Model!R30 -> 7300 | J11: =Model!S30 -> 6466 | K11: =Model!U30 -> 8130 | L11: =Model!V30 -> 9312 | M11: =Model!W30 -> 7587 | N11: =Model!X30 -> 2830.373 | O11: =Model!Z30 -> 3596.7509 | P11: =Model!AA30 -> 4246.7352 | Q11: =Model!AB30 -> 3092.7947 | R11: =Model!AC30 -> 3305.4244 | T11: =Model!J30 -> 22908 | U11: =Model!O30 -> 22943 | V11: =Model!T30 -> 29583 | W11: =Model!Y30 -> 27859.373 | X11: =Model!AD30 -> 14241.705 | Y11: =Model!AE30 -> 14920.477 | Z11: =Model!AF30 -> 15328.374 | AA11: =Model!AG30 -> 15858.298 | AC11: =IFERROR((V11/T11)^(1/(V$4-T$4))-1,"N/A") -> 0.1363903 | AE11: =IFERROR((AA11/V11)^(1/(AA$4-V$4))-1,"N/A") -> -0.11723954
C12: % Margin | G12: =G11/G$8 -> 0.33102922 | H12: =H11/H$8 -> 0.3407809 | I12: =I11/I$8 -> 0.3272222 | J12: =J11/J$8 -> 0.31834966 | K12: =K11/K$8 -> 0.33289657 | L12: =L11/L$8 -> 0.33775843 | M12: =M11/M$8 -> 0.33104983 | N12: =N11/N$8 -> 0.13 | ... R12: =R11/R$8 -> 0.135 | T12: =T11/T$8 -> 0.32124977 | U12: =U11/U$8 -> 0.31799911 | V12: =V11/V$8 -> 0.33017847 | W12: =W11/W$8 -> 0.28815441 | X12: =X11/X$8 -> 0.13533006 | Y12: =Y11/Y$8 -> 0.139 | Z12: =Z11/Z$8 -> 0.14 | AA12: =AA11/AA$8 -> 0.142
C13: YoY % Growth | K13: =K11/G11-1 -> 0.24827269 | L13: =L11/H11-1 -> 0.00085984523 | M13: =M11/I11-1 -> 0.039315068 | N13: =N11/J11-1 -> -0.56226833 | O13: =O11/K11-1 -> -0.55759521 | P13: =P11/L11-1 -> -0.54395026 | Q13: =Q11/M11-1 -> -0.59235604 | R13: =R11/N11-1 -> 0.16784055 | U13: =U11/T11-1 -> 0.0015278505 | V13: =V11/U11-1 -> 0.28941289 | W13: =W11/V11-1 -> -0.058264104 | X13: =X11/W11-1 -> -0.48880022 | Y13: =Y11/X11-1 -> 0.047660817 | Z13: =Z11/Y11-1 -> 0.027338129 | AA13: =AA11/Z11-1 -> 0.034571429
C15: =Model!C36 -> EBIT | G15: =Model!P36 -> 1991 | H15: =Model!Q36 -> 3957 | I15: =Model!R36 -> 2175 | J15: =Model!S36 -> 2769 | K15: =Model!U36 -> 3245 | L15: =Model!V36 -> 4210 | M15: =Model!W36 -> 2789 | N15: =Model!X36 -> -2290.6765 | O15: =Model!Z36 -> -2515.6105 | P15: =Model!AA36 -> -2679.8778 | Q15: =Model!AB36 -> -2919.5613 | R15: =Model!AC36 -> -2425.104 | T15: =Model!J36 -> 4018 | U15: =Model!O36 -> 6314 | V15: =Model!T36 -> 10892 | W15: =Model!Y36 -> 7953.3235 | X15: =Model!AD36 -> -10540.154 | Y15: =Model!AE36 -> -9578.1136 | Z15: =Model!AF36 -> -9246.1514 | AA15: =Model!AG36 -> -8671.5229 | AC15: =IFERROR((V15/T15)^(1/(V$4-T$4))-1,"N/A") -> 0.64645115 | AE15: =IFERROR((AA15/V15)^(1/(AA$4-V$4))-1,"N/A") -> -1.9554271
C16: Margin | G16: =G15/G$8 -> 0.10119441 | H16: =H15/H$8 -> 0.14493444 | I16: =I15/I$8 -> 0.097494285 | J16: =J15/J$8 -> 0.13633007 | K16: =K15/K$8 -> 0.132872 | L16: =L15/L$8 -> 0.15270221 | M16: =M15/M$8 -> 0.12169474 | N16: =N15/N$8 -> -0.10521156 | ... R16: =R15/R$8 -> -0.099045993 | T16: =T15/T$8 -> 0.056346324 | U16: =U15/U$8 -> 0.087514553 | V16: =V15/V$8 -> 0.12156657 | W16: =W15/W$8 -> 0.082262627 | X16: =X15/X$8 -> -0.10015652 | Y16: =Y15/Y$8 -> -0.089230245 | Z16: =Z15/Z$8 -> -0.084448694 | AA16: =AA15/AA$8 -> -0.077647439
C17: YoY % Growth | K17: =K15/G15-1 -> 0.62983425 | L17: =L15/H15-1 -> 0.063937326 | M17: =M15/I15-1 -> 0.28229885 | N17: =N15/J15-1 -> -1.8272577 | O17: =O15/K15-1 -> -1.7752267 | P17: =P15/L15-1 -> -1.6365505 | Q17: =Q15/M15-1 -> -2.046813 | R17: =R15/N15-1 -> 0.058684624 | U17: =U15/T15-1 -> 0.57142857 | V17: =V15/U15-1 -> 0.72505543 | W17: =W15/V15-1 -> -0.26980137 | X17: =X15/W15-1 -> -2.3252515 | Y17: =Y15/X15-1 -> -0.09127382 | Z17: =Z15/Y15-1 -> -0.034658402 | AA17: =AA15/Z15-1 -> -0.062147864
C19: =Model!C45 -> Net Income (Loss) | G19: =Model!P45 -> 1337 | H19: =Model!Q45 -> 2828 | I19: =Model!R45 -> 692 | J19: =Model!S45 -> 978 | K19: =Model!U45 -> 2321 | L19: =Model!V45 -> 3018 | M19: =Model!W45 -> 1896 | N19: =Model!X45 | O19: =Model!Z45 | P19: =Model!AA45 | Q19: =Model!AB45 | R19: =Model!AC45 | T19: =Model!J45 -> 2314 | U19: =Model!O45 -> 4281 | V19: =Model!T45 -> 5835 | W19: =Model!Y45 | X19: =Model!AD45 | Y19: =Model!AE45 | Z19: =Model!AF45 | AA19: =Model!AG45 | AC19: =IFERROR((V19/T19)^(1/(V$4-T$4))-1,"N/A") -> 0.58795705 | AE19: =IFERROR((AA19/V19)^(1/(AA$4-V$4))-1,"N/A") -> N/A
C20: Margin | G20: =G19/G$8 -> 0.067954257 | H20: =H19/H$8 -> 0.10358216 | I20: =I19/I$8 -> 0.031018871 | J20: =J19/J$8 -> 0.048151248 | K20: =K19/K$8 -> 0.095037261 | L20: =L19/L$8 -> 0.10946681 | M20: =M19/M$8 -> 0.082729732 | N20: =N19/N$8 | ... R20: =R19/R$8 | T20: =T19/T$8 -> 0.032450322 | U20: =U19/U$8 -> 0.059336364 | V20: =V19/V$8 -> 0.065124948 | W20: =W19/W$8 | X20: =X19/X$8 | Y20: =Y19/Y$8 | Z20: =Z19/Z$8 | AA20: =AA19/AA$8
C21: YoY % Growth | K21: =K19/G19-1 -> 0.73597607 | L21: =L19/H19-1 -> 0.06718529 | M21: =M19/I19-1 -> 1.7398844 | N21: =N19/J19-1 | O21: =O19/K19-1 | P21: =P19/L19-1 | Q21: =Q19/M19-1 | R21: =R19/N19-1 | U21: =U19/T19-1 -> 0.85004322 | V21: =V19/U19-1 -> 0.3629993 | W21: =W19/V19-1 | X21: =X19/W19-1 | Y21: =Y19/X19-1 | Z21: =Z19/Y19-1 | AA21: =AA19/Z19-1
C23: =Model!C57 -> Adj. EPS (Diluted) | G23: =Model!P57 -> 1.7785185 | H23: =Model!Q57 -> 3.7656441 | I23: =Model!R57 -> 1.9877719 | J23: =Model!S57 -> 1.304 | K23: =Model!U57 -> 3.2236111 | L23: =Model!V57 -> 4.2687412 | M23: =Model!W57 -> 2.7297688 | N23: =Model!X57 | O23: =Model!Z57 | P23: =Model!AA57 | Q23: =Model!AB57 | R23: =Model!AC57 | T23: =Model!J57 -> 5.1942447 | U23: =Model!O57 -> 5.5799001 | V23: =Model!T57 -> 8.8758267 | W23: =Model!Y57 | X23: =Model!AD57 | Y23: =Model!AE57 | Z23: =Model!AF57 | AA23: =Model!AG57 | AC23: =IFERROR((V23/T23)^(1/(V$4-T$4))-1,"N/A") -> 0.30720351 | AE23: =IFERROR((AA23/V23)^(1/(AA$4-V$4))-1,"N/A") -> N/A
C24: YoY % Growth | K24: =K23/G23-1 -> 0.81252603 | L24: =L23/H23-1 -> 0.13360186 | M24: =M23/I23-1 -> 0.37328071 | N24: =N23/J23-1 | O24: =O23/K23-1 | P24: =P23/L23-1 | Q24: =Q23/M23-1 | R24: =R23/N23-1 | U24: =IF(ISERROR(U23/T23-1),"NA",(U23/T23-1)) -> 0.074246681 | V24: =IF(ISERROR(V23/U23-1),"NA",(V23/U23-1)) -> 0.59067841 | W24: =IF(ISERROR(W23/V23-1),"NA",(W23/V23-1)) -> NA | X24: =IF(ISERROR(X23/W23-1),"NA",(X23/W23-1)) -> NA | Y24: =IF(ISERROR(Y23/X23-1),"NA",(Y23/X23-1)) -> NA | Z24: =IF(ISERROR(Z23/Y23-1),"NA",(Z23/Y23-1)) -> NA | AA24: =IF(ISERROR(AA23/Z23-1),"NA",(AA23/Z23-1)) -> NA
C27: =Model!C61 -> EBITDA | G27: =Model!P61 -> 2324.56 | H27: =Model!Q61 -> 4291.53 | I27: =Model!R61 -> 3336.78 | J27: =Model!S61 -> 3159 | K27: =Model!U61 -> 3636 | L27: =Model!V61 -> 4619 | M27: =Model!W61 -> 3207 | N27: =Model!X61 | O27: =Model!Z61 | P27: =Model!AA61 | Q27: =Model!AB61 | R27: =Model!AC61 | T27: =Model!J61 -> 7341.59 | U27: =Model!O61 -> 7764.5 | V27: =Model!T61 -> 13111.87 | W27: =Model!Y61 | X27: =Model!AD61 | Y27: =Model!AE61 | Z27: =Model!AF61 | AA27: =Model!AG61 | AC27: =IFERROR((V27/T27)^(1/(V$4-T$4))-1,"N/A") -> 0.33640242 | AE27: =IFERROR((AA27/V27)^(1/(AA$4-V$4))-1,"N/A") -> N/A
C28: Margin | G28: =G27/G$8 -> 0.1181479 | H28: =H27/H$8 -> 0.15718739 | I28: =I27/I$8 -> 0.14957103 | J28: =J27/J$8 -> 0.15553149 | K28: =K27/K$8 -> 0.14888216 | L28: =L27/L$8 -> 0.16753718 | M28: =M27/M$8 -> 0.13993368 | N28: =N27/N$8 | ... R28: =R27/R$8 | T28: =T27/T$8 -> 0.10295461 | U28: =U27/U$8 -> 0.10761906 | V28: =V27/V$8 -> 0.14634273 | W28: =W27/W$8 | X28: =X27/X$8 | Y28: =Y27/Y$8 | Z28: =Z27/Z$8 | AA28: =AA27/AA$8
C29: YoY % Growth | K29: =K27/G27-1 -> 0.56416698 | L29: =L27/H27-1 -> 0.076306119 | M29: =M27/I27-1 -> -0.038893784 | N29: =N27/J27-1 | O29: =O27/K27-1 | P29: =P27/L27-1 | Q29: =Q27/M27-1 | R29: =R27/N27-1 | U29: =U27/T27-1 -> 0.057604688 | V29: =V27/U27-1 -> 0.6886947 | W29: =W27/V27-1 | X29: =X27/W27-1 | Y29: =Y27/X27-1 | Z29: =Z27/Y27-1 | AA29: =AA27/Z27-1
G31: =G$5 -> Quarterly | T31: =T$5 -> Annuals
A32: x | C32: ="Consolidated "&Model!C118 -> Consolidated Balance Sheet | G32: =G$6 -> 1Q25 | H32: =H$6 -> 2Q25 | I32: =I$6 -> 3Q25 | J32: =J$6 -> 4Q25 | K32: =K$6 -> 1Q26 | L32: =L$6 -> 2Q26 | M32: =M$6 -> 3Q26e | N32: =N$6 -> 4Q26e | ... R32: =R$6 -> 4Q27e | T32: =T$6 -> 2023 | U32: =U$6 -> 2024 | V32: =V$6 -> 2025 | W32: =W$6 -> 2026e | X32: =X$6 -> 2027e | Y32: =Y$6 -> 2028e | Z32: =Z$6 -> 2029e | AA32: =AA$6 -> 2030e
C34: =Model!C120 -> Cash & Cash Equivalents | G34: =Model!P120 -> 6156 | H34: =Model!Q120 -> 12726 | I34: =Model!R120 -> 10101 | J34: =Model!S120 -> 5196 | K34: =Model!U120 -> 7146 | L34: =Model!V120 -> 6255 | M34: =Model!W120 -> 6673 | N34: =Model!X120 | O34: =Model!Z120 | P34: =Model!AA120 | Q34: =Model!AB120 | R34: =Model!AC120 | T34: =Model!J120 -> 729 | U34: =Model!O120 -> 876 | V34: =Model!T120 -> 5196 | W34: =Model!Y120 | X34: =Model!AD120 | Y34: =Model!AE120 | Z34: =Model!AF120 | AA34: =Model!AG120
C35: =Model!C121 -> Accounts Receivable | G35: =Model!P121 -> 0 | H35: =Model!Q121 -> 0 | I35: =Model!R121 -> 0 | J35: =Model!S121 -> 0 | K35: =Model!U121 -> 0 | L35: =Model!V121 -> 0 | M35: =Model!W121 -> 0 | N35: =Model!X121 -> 0 | O35: =Model!Z121 -> 0 | P35: =Model!AA121 -> 0 | Q35: =Model!AB121 -> 0 | R35: =Model!AC121 -> 0 | T35: =Model!J121 -> 0 | U35: =Model!O121 -> 0 | V35: =Model!T121 -> 0 | W35: =Model!Y121 -> 0 | X35: =Model!AD121 -> 0 | Y35: =Model!AE121 -> 0 | Z35: =Model!AF121 -> 0 | AA35: =Model!AG121 -> 0
C36: =Model!C122 -> Inventory | G36: =Model!P122 -> 14283 | H36: =Model!Q122 -> 13831 | I36: =Model!R122 -> 15712 | J36: =Model!S122 -> 16193 | K36: =Model!U122 -> 18382 | L36: =Model!V122 -> 17322 | M36: =Model!W122 -> 16685 | N36: =Model!X122 -> 18529.95 | O36: =Model!Z122 -> 23065.506 | P36: =Model!AA122 -> 22014.148 | Q36: =Model!AB122 -> 20954.805 | R36: =Model!AC122 -> 20718.783 | T36: =Model!J122 -> 12561 | U36: =Model!O122 -> 13179 | V36: =Model!T122 -> 16193 | W36: =Model!Y122 -> 18529.95 | X36: =Model!AD122 -> 20718.783 | Y36: =Model!AE122 -> 21269.509 | Z36: =Model!AF122 -> 21669.702 | AA36: =Model!AG122 -> 22051.693
C37: =Model!C123 -> Prepaid & Other Current Assets | G37: =Model!P123 -> 1487 | H37: =Model!Q123 -> 1160 | I37: =Model!R123 -> 1103 | J37: =Model!S123 -> 937 | K37: =Model!U123 -> 1288 | L37: =Model!V123 -> 1506 | M37: =Model!W123 -> 1491 | N37: =Model!X123 -> 0 | O37: =Model!Z123 -> 1849.7576 | P37: =Model!AA123 -> 2108.7237 | Q37: =Model!AB123 -> 1855.6768 | R37: =Model!AC123 -> 1762.893 | T37: =Model!J123 -> 938 | U37: =Model!O123 -> 1263 | V37: =Model!T123 -> 937 | W37: =Model!Y123 -> 0 | X37: =Model!AD123 -> 1762.893 | Y37: =Model!AE123 -> 1932.148 | Z37: =Model!AF123 -> 1970.791 | AA37: =Model!AG123 -> 2010.2068
C38: =Model!C124 -> Total Current Assets | G38: =SUM(G34:G37) -> 21926 | H38: =SUM(H34:H37) -> 27717 | I38: =SUM(I34:I37) -> 26916 | J38: =SUM(J34:J37) -> 22326 | K38: =SUM(K34:K37) -> 26816 | L38: =SUM(L34:L37) -> 25083 | M38: =SUM(M34:M37) -> 24849 | N38: =SUM(N34:N37) | ... R38: =SUM(R34:R37) | T38: =SUM(T34:T37) -> 14228 | U38: =SUM(U34:U37) -> 15318 | V38: =SUM(V34:V37) -> 22326 | W38: =SUM(W34:W37) | X38: =SUM(X34:X37) | Y38: =SUM(Y34:Y37) | Z38: =SUM(Z34:Z37) | AA38: =SUM(AA34:AA37)
C40: =Model!C126 -> PP&E, Net | G40: =Model!P126 -> 18501 | H40: =Model!Q126 -> 18612 | I40: =Model!R126 -> 18683 | J40: =Model!S126 -> 22987 | K40: =Model!U126 -> 19059 | L40: =Model!V126 -> 19031 | M40: =Model!W126 -> 18925 | N40: =Model!X126 -> 18963.938 | O40: =Model!Z126 -> 19248.655 | P40: =Model!AA126 -> 19556.136 | Q40: =Model!AB126 -> 19652.049 | R40: =Model!AC126 -> 19724.377 | T40: =Model!J126 -> 18432 | U40: =Model!O126 -> 18669 | V40: =Model!T126 -> 22987 | W40: =Model!Y126 -> 18963.938 | X40: =Model!AD126 -> 19724.377 | Y40: =Model!AE126 -> 20451.053 | Z40: =Model!AF126 -> 21168.345 | AA40: =Model!AG126 -> 21989.466
C41: =Model!C127 -> Intangible Assets, Net | G41: =Model!P127 -> 0 | H41: =Model!Q127 -> 0 | I41: =Model!R127 -> 0 | J41: =Model!S127 -> 0 | K41: =Model!U127 -> 0 | L41: =Model!V127 -> 0 | M41: =Model!W127 -> 0 | N41: =Model!X127 -> 0 | O41: =Model!Z127 -> 0 | P41: =Model!AA127 -> 0 | Q41: =Model!AB127 -> 0 | R41: =Model!AC127 -> 0 | T41: =Model!J127 -> 0 | U41: =Model!O127 -> 0 | V41: =Model!T127 -> 0 | W41: =Model!Y127 -> 0 | X41: =Model!AD127 -> 0 | Y41: =Model!AE127 -> 0 | Z41: =Model!AF127 -> 0 | AA41: =Model!AG127 -> 0
C42: =Model!C128 -> Goodwill | G42: =Model!P128 -> 0 | H42: =Model!Q128 -> 0 | I42: =Model!R128 -> 0 | J42: =Model!S128 -> 311 | K42: =Model!U128 -> 0 | L42: =Model!V128 -> 0 | M42: =Model!W128 -> 0 | N42: =Model!X128 -> 0 | O42: =Model!Z128 -> 0 | P42: =Model!AA128 -> 0 | Q42: =Model!AB128 -> 0 | R42: =Model!AC128 -> 0 | T42: =Model!J128 -> 303 | U42: =Model!O128 -> 303 | V42: =Model!T128 -> 311 | W42: =Model!Y128 -> 0 | X42: =Model!AD128 -> 0 | Y42: =Model!AE128 -> 0 | Z42: =Model!AF128 -> 0 | AA42: =Model!AG128 -> 0
C43: =Model!C129 -> Other Non-Current Assets | G43: =Model!P129 -> 5405 | H43: =Model!Q129 -> 5434 | I43: =Model!R129 -> 5281 | J43: =Model!S129 -> 1111 | K43: =Model!U129 -> 5325 | L43: =Model!V129 -> 5290 | M43: =Model!W129 -> 5626 | N43: =Model!X129 -> 5738.52 | O43: =Model!Z129 -> 5853.2904 | P43: =Model!AA129 -> 5970.3562 | Q43: =Model!AB129 -> 6089.7633 | R43: =Model!AC129 -> 6211.5586 | T43: =Model!J129 -> 1545 | U43: =Model!O129 -> 5181 | V43: =Model!T129 -> 1111 | W43: =Model!Y129 -> 5738.52 | X43: =Model!AD129 -> 6211.5586 | Y43: =Model!AE129 -> 6335.7898 | Z43: =Model!AF129 -> 6462.5056 | AA43: =Model!AG129 -> 6591.7557
C44: =Model!C130 -> Total Non-Current Assets | G44: =SUM(G40:G43) -> 23906 | H44: =SUM(H40:H43) -> 24046 | I44: =SUM(I40:I43) -> 23964 | J44: =SUM(J40:J43) -> 24409 | K44: =SUM(K40:K43) -> 24384 | L44: =SUM(L40:L43) -> 24321 | M44: =SUM(M40:M43) -> 24551 | N44: =SUM(N40:N43) -> 24702.458 | ... R44: =SUM(R40:R43) -> 25935.936 | T44: =SUM(T40:T43) -> 20280 | U44: =SUM(U40:U43) -> 24153 | V44: =SUM(V40:V43) -> 24409 | W44: =SUM(W40:W43) -> 24702.458 | X44: =SUM(X40:X43) -> 25935.936 | Y44: =SUM(Y40:Y43) -> 26786.843 | Z44: =SUM(Z40:Z43) -> 27630.851 | AA44: =SUM(AA40:AA43) -> 28581.221
C46: =Model!C132 -> Total Assets | G46: =SUM(G38,G44) -> 45832 | H46: =SUM(H38,H44) -> 51763 | I46: =SUM(I38,I44) -> 50880 | J46: =SUM(J38,J44) -> 46735 | K46: =SUM(K38,K44) -> 51200 | L46: =SUM(L38,L44) -> 49404 | M46: =SUM(M38,M44) -> 49400 | N46: =SUM(N38,N44) | ... R46: =SUM(R38,R44) | T46: =SUM(T38,T44) -> 34508 | U46: =SUM(U38,U44) -> 39471 | V46: =SUM(V38,V44) -> 46735 | W46: =SUM(W38,W44) | X46: =SUM(X38,X44) | Y46: =SUM(Y38,Y44) | Z46: =SUM(Z38,Z44) | AA46: =SUM(AA38,AA44)
C48: =Model!C134 -> Accounts Payable | G48: =Model!P134 -> 10841 | H48: =Model!Q134 -> 12916 | I48: =Model!R134 -> 12759 | J48: =Model!S134 -> 10884 | K48: =Model!U134 -> 13964 | L48: =Model!V134 -> 12011 | M48: =Model!W134 -> 11334 | N48: =Model!X134 -> 11323.859 | O48: =Model!Z134 -> 14082.099 | P48: =Model!AA134 -> 13208.489 | Q48: =Model!AB134 -> 13065.937 | R48: =Model!AC134 -> 12661.479 | T48: =Model!J134 -> 8279 | U48: =Model!O134 -> 7659 | V48: =Model!T134 -> 10884 | W48: =Model!Y134 -> 11323.859 | X48: =Model!AD134 -> 12661.479 | Y48: =Model!AE134 -> 13673.256 | Z48: =Model!AF134 -> 13930.523 | AA48: =Model!AG134 -> 14176.089
C49: =Model!C135 -> Accrued Liabilities | G49: =Model!P135 -> 982 | H49: =Model!Q135 -> 1139 | I49: =Model!R135 -> 1117 | J49: =Model!S135 -> 2411 | K49: =Model!U135 -> 1312 | L49: =Model!V135 -> 1331 | M49: =Model!W135 -> 1353 | N49: =Model!X135 -> 947.08635 | O49: =Model!Z135 -> 1104.7164 | P49: =Model!AA135 -> 1252.0547 | Q49: =Model!AB135 -> 1134.0247 | R49: =Model!AC135 -> 1058.96 | T49: =Model!J135 -> 662 | U49: =Model!O135 -> 684 | V49: =Model!T135 -> 2411 | W49: =Model!Y135 -> 947.08635 | X49: =Model!AD135 -> 1058.96 | Y49: =Model!AE135 -> 1201.4741 | Z49: =Model!AF135 -> 1224.0802 | AA49: =Model!AG135 -> 1245.6582
C50: =Model!C136 -> Other Current Liabilities | G50: =Model!P136 -> 5898 | H50: =Model!Q136 -> 6706 | I50: =Model!R136 -> 5079 | J50: =Model!S136 -> 3614 | K50: =Model!U136 -> 6278 | L50: =Model!V136 -> 6978 | M50: =Model!W136 -> 6795 | N50: =Model!X136 -> 9470.8635 | O50: =Model!Z136 -> 9721.5039 | P50: =Model!AA136 -> 11018.081 | Q50: =Model!AB136 -> 11340.247 | R50: =Model!AC136 -> 10589.6 | T50: =Model!J136 -> 4446 | U50: =Model!O136 -> 6242 | V50: =Model!T136 -> 3614 | W50: =Model!Y136 -> 9470.8635 | X50: =Model!AD136 -> 10589.6 | Y50: =Model!AE136 -> 11090.53 | Z50: =Model!AF136 -> 11299.202 | AA50: =Model!AG136 -> 11498.383
C51: =Model!C137 -> Total Current Liabilities (Excl. Debt) | G51: =SUM(G48:G50) -> 17721 | H51: =SUM(H48:H50) -> 20761 | I51: =SUM(I48:I50) -> 18955 | J51: =SUM(J48:J50) -> 16909 | K51: =SUM(K48:K50) -> 21554 | L51: =SUM(L48:L50) -> 20320 | M51: =SUM(M48:M50) -> 19482 | N51: =SUM(N48:N50) -> 21741.808 | ... R51: =SUM(R48:R50) -> 24310.039 | T51: =SUM(T48:T50) -> 13387 | U51: =SUM(U48:U50) -> 14585 | V51: =SUM(V48:V50) -> 16909 | W51: =SUM(W48:W50) -> 21741.808 | X51: =SUM(X48:X50) -> 24310.039 | Y51: =SUM(Y48:Y50) -> 25965.26 | Z51: =SUM(Z48:Z50) -> 26453.805 | AA51: =SUM(AA48:AA50) -> 26920.13
C53: =Model!C139 -> Revolver | G53: =Model!P139 -> 0 | H53: =Model!Q139 -> 0 | I53: =Model!R139 -> 0 | J53: =Model!S139 -> 0 | K53: =Model!U139 -> 0 | L53: =Model!V139 -> 0 | M53: =Model!W139 -> 0 | N53: =Model!X139 | O53: =Model!Z139 | P53: =Model!AA139 | Q53: =Model!AB139 | R53: =Model!AC139 | T53: =Model!J139 -> 0 | U53: =Model!O139 -> 0 | V53: =Model!T139 -> 0 | W53: =Model!Y139 | X53: =Model!AD139 | Y53: =Model!AE139 | Z53: =Model!AF139 | AA53: =Model!AG139
C54: =Model!C140 -> LT Debt (Incl. Current Portion) | G54: =Model!P140 -> 20804 | H54: =Model!Q140 -> 20806 | I54: =Model!R140 -> 21794 | J54: =Model!S140 -> 26211 | K54: =Model!U140 -> 23244 | L54: =Model!V140 -> 23311 | M54: =Model!W140 -> 25233 | N54: =Model!X140 -> 24733 | O54: =Model!Z140 -> 24233 | P54: =Model!AA140 -> 23733 | Q54: =Model!AB140 -> 23233 | R54: =Model!AC140 -> 22733 | T54: =Model!J140 -> 15501 | U54: =Model!O140 -> 17365 | V54: =Model!T140 -> 26211 | W54: =Model!Y140 -> 24733 | X54: =Model!AD140 -> 22733 | Y54: =Model!AE140 -> 21333 | Z54: =Model!AF140 -> 20033 | AA54: =Model!AG140 -> 18833
C55: =Model!C141 -> Deferred Income Taxes | G55: =Model!P141 -> 0 | H55: =Model!Q141 -> 0 | I55: =Model!R141 -> 0 | J55: =Model!S141 -> 168 | K55: =Model!U141 -> 0 | L55: =Model!V141 -> 0 | M55: =Model!W141 -> 0 | N55: =Model!X141 -> 0 | O55: =Model!Z141 -> 0 | P55: =Model!AA141 -> 0 | Q55: =Model!AB141 -> 0 | R55: =Model!AC141 -> 0 | T55: =Model!J141 -> 0 | U55: =Model!O141 -> 0 | V55: =Model!T141 -> 168 | W55: =Model!Y141 -> 0 | X55: =Model!AD141 -> 0 | Y55: =Model!AE141 -> 0 | Z55: =Model!AF141 -> 0 | AA55: =Model!AG141 -> 0
C56: =Model!C142 -> Other Non-Current Liabilities | G56: =Model!P142 -> 5591 | H56: =Model!Q142 -> 5840 | I56: =Model!R142 -> 6058 | J56: =Model!S142 -> 2010 | K56: =Model!U142 -> 5957 | L56: =Model!V142 -> 5948 | M56: =Model!W142 -> 6261 | N56: =Model!X142 -> 6261 | O56: =Model!Z142 -> 6261 | P56: =Model!AA142 -> 6261 | Q56: =Model!AB142 -> 6261 | R56: =Model!AC142 -> 6261 | T56: =Model!J142 -> 1976 | U56: =Model!O142 -> 5549 | V56: =Model!T142 -> 2010 | W56: =Model!Y142 -> 6261 | X56: =Model!AD142 -> 6261 | Y56: =Model!AE142 -> 6261 | Z56: =Model!AF142 -> 6261 | AA56: =Model!AG142 -> 6261
C57: =Model!C143 -> Total Non-Current Liabilities | G57: =SUM(G53:G56) -> 26395 | H57: {=INDEX(Data,MATCH($C57,Line_Items,0),MATCH(H$32,Fiscal_Periods,0))} -> 26646 | I57: {=INDEX(Data,MATCH($C57,Line_Items,0),MATCH(I$32,Fiscal_Periods,0))} -> 27852 | J57: {=INDEX(Data,MATCH($C57,Line_Items,0),MATCH(J$32,Fiscal_Periods,0))} -> 28389 | K57: {=INDEX(Data,MATCH($C57,Line_Items,0),MATCH(K$32,Fiscal_Periods,0))} -> 29201 | L57: {=INDEX(Data,MATCH($C57,Line_Items,0),MATCH(L$32,Fiscal_Periods,0))} -> 29259 | M57: {=INDEX(Data,MATCH($C57,Line_Items,0),MATCH(M$32,Fiscal_Periods,0))} -> 31494 | N57: =INDEX(Data,MATCH($C57,Line_Items,0),MATCH(N$32,Fiscal_Periods,0)) | O57: =INDEX(Data,MATCH($C57,Line_Items,0),MATCH(O$32,Fiscal_Periods,0)) | P57: =INDEX(Data,MATCH($C57,Line_Items,0),MATCH(P$32,Fiscal_Periods,0)) | Q57: =INDEX(Data,MATCH($C57,Line_Items,0),MATCH(Q$32,Fiscal_Periods,0)) | R57: =INDEX(Data,MATCH($C57,Line_Items,0),MATCH(R$32,Fiscal_Periods,0)) | T57: {=INDEX(Data,MATCH($C57,Line_Items,0),MATCH(T$32,Fiscal_Periods,0))} -> 17477 | U57: {=INDEX(Data,MATCH($C57,Line_Items,0),MATCH(U$32,Fiscal_Periods,0))} -> 22914 | V57: {=INDEX(Data,MATCH($C57,Line_Items,0),MATCH(V$32,Fiscal_Periods,0))} -> 28389 | W57: =INDEX(Data,MATCH($C57,Line_Items,0),MATCH(W$32,Fiscal_Periods,0)) | X57: =INDEX(Data,MATCH($C57,Line_Items,0),MATCH(X$32,Fiscal_Periods,0)) | Y57: =INDEX(Data,MATCH($C57,Line_Items,0),MATCH(Y$32,Fiscal_Periods,0)) | Z57: =INDEX(Data,MATCH($C57,Line_Items,0),MATCH(Z$32,Fiscal_Periods,0)) | AA57: =INDEX(Data,MATCH($C57,Line_Items,0),MATCH(AA$32,Fiscal_Periods,0))
C59: =Model!C145 -> Total Liabilities | G59: =SUM(G51,G57) -> 44116 | H59: =SUM(H51,H57) -> 47407 | I59: =SUM(I51,I57) -> 46807 | J59: =SUM(J51,J57) -> 45298 | K59: =SUM(K51,K57) -> 50755 | L59: =SUM(L51,L57) -> 49579 | M59: =SUM(M51,M57) -> 50976 | N59: =SUM(N51,N57) | ... R59: =SUM(R51,R57) | T59: =SUM(T51,T57) -> 30864 | U59: =SUM(U51,U57) -> 37499 | V59: =SUM(V51,V57) -> 45298 | W59: =SUM(W51,W57) | X59: =SUM(X51,X57) | Y59: =SUM(Y51,Y57) | Z59: =SUM(Z51,Z57) | AA59: =SUM(AA51,AA57)
C61: =Model!C147 -> Common Stock & APIC | G61: =Model!P147 -> 387 | H61: =Model!Q147 -> 507 | I61: =Model!R147 -> 376 | J61: =Model!S147 -> 456 | K61: =Model!U147 -> 358 | L61: =Model!V147 -> 350 | M61: =Model!W147 -> 343 | N61: =Model!X147 -> 394.3 | O61: =Model!Z147 -> 454.834 | P61: =Model!AA147 -> 523.84276 | Q61: =Model!AB147 -> 584.57047 | R61: =Model!AC147 -> 642.26179 | T61: =Model!J147 -> 401 | U61: =Model!O147 -> 381 | V61: =Model!T147 -> 456 | W61: =Model!Y147 -> 394.3 | X61: =Model!AD147 -> 642.26179 | Y61: =Model!AE147 -> 895.18282 | Z61: =Model!AF147 -> 1153.1623 | AA61: =Model!AG147 -> 1416.3013
C62: =Model!C148 -> Retained Earnings | G62: =Model!P148 -> 1722 | H62: =Model!Q148 -> 4134 | I62: =Model!R148 -> 3942 | J62: =Model!S148 -> 1117 | K62: =Model!U148 -> 98 | L62: =Model!V148 -> -460 | M62: =Model!W148 -> -1913 | N62: =Model!X148 | O62: =Model!Z148 | P62: =Model!AA148 | Q62: =Model!AB148 | R62: =Model!AC148 | T62: =Model!J148 -> 3452 | U62: =Model!O148 -> 1727 | V62: =Model!T148 -> 1117 | W62: =Model!Y148 | X62: =Model!AD148 | Y62: =Model!AE148 | Z62: =Model!AF148 | AA62: =Model!AG148
C63: =Model!C149 -> Treasury Stock | G63: =Model!P149 -> 0 | H63: =Model!Q149 -> 0 | I63: =Model!R149 -> 0 | J63: =Model!S149 -> 0 | K63: =Model!U149 -> 0 | L63: =Model!V149 -> 0 | M63: =Model!W149 -> 0 | N63: =Model!X149 -> -500 | O63: =Model!Z149 -> -1000 | P63: =Model!AA149 -> -1500 | Q63: =Model!AB149 -> -2000 | R63: =Model!AC149 -> -2500 | T63: =Model!J149 -> 0 | U63: =Model!O149 -> 0 | V63: =Model!T149 -> 0 | W63: =Model!Y149 -> -500 | X63: =Model!AD149 -> -2500 | Y63: =Model!AE149 -> -5500 | Z63: =Model!AF149 -> -8500 | AA63: =Model!AG149 -> -11500
C64: =Model!C150 -> Accumulated Other Comprehensive Income (AOCI) | G64: =Model!P150 -> -393 | H64: =Model!Q150 -> -285 | I64: =Model!R150 -> -245 | J64: =Model!S150 -> -136 | K64: =Model!U150 -> -11 | L64: =Model!V150 -> -65 | M64: =Model!W150 -> -6 | N64: =Model!X150 -> -6 | O64: =Model!Z150 -> -6 | P64: =Model!AA150 -> -6 | Q64: =Model!AB150 -> -6 | R64: =Model!AC150 -> -6 | T64: =Model!J150 -> -209 | U64: =Model!O150 -> -136 | V64: =Model!T150 -> -136 | W64: =Model!Y150 -> -6 | X64: =Model!AD150 -> -6 | Y64: =Model!AE150 -> -6 | Z64: =Model!AF150 -> -6 | AA64: =Model!AG150 -> -6
C65: =Model!C151 -> Total Shareholder's Equity | G65: =SUM(G61:G64) -> 1716 | H65: =SUM(H61:H64) -> 4356 | I65: =SUM(I61:I64) -> 4073 | J65: =SUM(J61:J64) -> 1437 | K65: =SUM(K61:K64) -> 445 | L65: =SUM(L61:L64) -> -175 | M65: =SUM(M61:M64) -> -1576 | N65: =SUM(N61:N64) | ... R65: =SUM(R61:R64) | T65: =SUM(T61:T64) -> 3644 | U65: =SUM(U61:U64) -> 1972 | V65: =SUM(V61:V64) -> 1437 | W65: =SUM(W61:W64) | X65: =SUM(X61:X64) | Y65: =SUM(Y61:Y64) | Z65: =SUM(Z61:Z64) | AA65: =SUM(AA61:AA64)
C67: =Model!C153 -> Noncontrolling Interests | G67: =Model!P153 -> 0 | H67: =Model!Q153 -> 0 | I67: =Model!R153 -> 0 | J67: =Model!S153 -> 0 | K67: =Model!U153 -> 0 | L67: =Model!V153 -> 0 | M67: =Model!W153 -> 0 | N67: =Model!X153 -> 0 | O67: =Model!Z153 -> 0 | P67: =Model!AA153 -> 0 | Q67: =Model!AB153 -> 0 | R67: =Model!AC153 -> 0 | T67: =Model!J153 -> 0 | U67: =Model!O153 -> 0 | V67: =Model!T153 -> 0 | W67: =Model!Y153 -> 0 | X67: =Model!AD153 -> 0 | Y67: =Model!AE153 -> 0 | Z67: =Model!AF153 -> 0 | AA67: =Model!AG153 -> 0
C68: =Model!C154 -> Total Equity | G68: =SUM(G65,G67) -> 1716 | H68: =SUM(H65,H67) -> 4356 | I68: =SUM(I65,I67) -> 4073 | J68: =SUM(J65,J67) -> 1437 | K68: =SUM(K65,K67) -> 445 | L68: =SUM(L65,L67) -> -175 | M68: =SUM(M65,M67) -> -1576 | N68: =SUM(N65,N67) | ... R68: =SUM(R65,R67) | T68: =SUM(T65,T67) -> 3644 | U68: =SUM(U65,U67) -> 1972 | V68: =SUM(V65,V67) -> 1437 | W68: =SUM(W65,W67) | X68: =SUM(X65,X67) | Y68: =SUM(Y65,Y67) | Z68: =SUM(Z65,Z67) | AA68: =SUM(AA65,AA67)
C70: =Model!C156 -> Total Liabilities & Shareholder's Equity | G70: =SUM(G59,G68) -> 45832 | H70: =SUM(H59,H68) -> 51763 | I70: =SUM(I59,I68) -> 50880 | J70: =SUM(J59,J68) -> 46735 | K70: =SUM(K59,K68) -> 51200 | L70: =SUM(L59,L68) -> 49404 | M70: =SUM(M59,M68) -> 49400 | N70: =SUM(N59,N68) | ... R70: =SUM(R59,R68) | T70: =SUM(T59,T68) -> 34508 | U70: =SUM(U59,U68) -> 39471 | V70: =SUM(V59,V68) -> 46735 | W70: =SUM(W59,W68) | X70: =SUM(X59,X68) | Y70: =SUM(Y59,Y68) | Z70: =SUM(Z59,Z68) | AA70: =SUM(AA59,AA68)
G72: =G$5 -> Quarterly | T72: =T$31 -> Annuals
A73: x | C73: Ratio Analysis | G73: =G$6 -> 1Q25 | H73: =H$6 -> 2Q25 | I73: =I$6 -> 3Q25 | J73: =J$6 -> 4Q25 | K73: =K$6 -> 1Q26 | L73: =L$6 -> 2Q26 | M73: =M$6 -> 3Q26e | N73: =N$6 -> 4Q26e | ... R73: =R$6 -> 4Q27e | T73: =T$6 -> 2023 | U73: =U$6 -> 2024 | V73: =V$6 -> 2025 | W73: =W$6 -> 2026e | X73: =X$6 -> 2027e | Y73: =Y$6 -> 2028e | Z73: =Z$6 -> 2029e | AA73: =AA$6 -> 2030e
C75: Profitability
C76: Gross Margin | G76: =G12 -> 0.33102922 | H76: =H12 -> 0.3407809 | I76: =I12 -> 0.3272222 | J76: =J12 -> 0.31834966 | K76: =K12 -> 0.33289657 | L76: =L12 -> 0.33775843 | M76: =M12 -> 0.33104983 | N76: =N12 -> 0.13 | ... R76: =R12 -> 0.135 | T76: =T12 -> 0.32124977 | U76: =U12 -> 0.31799911 | V76: =V12 -> 0.33017847 | W76: =W12 -> 0.28815441 | X76: =X12 -> 0.13533006 | Y76: =Y12 -> 0.139 | Z76: =Z12 -> 0.14 | AA76: =AA12 -> 0.142
C77: EBITDA Margin | G77: =G28 -> 0.1181479 | H77: =H28 -> 0.15718739 | I77: =I28 -> 0.14957103 | J77: =J28 -> 0.15553149 | K77: =K28 -> 0.14888216 | L77: =L28 -> 0.16753718 | M77: =M28 -> 0.13993368 | N77: =N28 | ... R77: =R28 | T77: =T28 -> 0.10295461 | U77: =U28 -> 0.10761906 | V77: =V28 -> 0.14634273 | W77: =W28 | X77: =X28 | Y77: =Y28 | Z77: =Z28 | AA77: =AA28
C78: EBIT Margin | G78: =G16 -> 0.10119441 | H78: =H16 -> 0.14493444 | I78: =I16 -> 0.097494285 | J78: =J16 -> 0.13633007 | K78: =K16 -> 0.132872 | L78: =L16 -> 0.15270221 | M78: =M16 -> 0.12169474 | N78: =N16 -> -0.10521156 | ... R78: =R16 -> -0.099045993 | T78: =T16 -> 0.056346324 | U78: =U16 -> 0.087514553 | V78: =V16 -> 0.12156657 | W78: =W16 -> 0.082262627 | X78: =X16 -> -0.10015652 | Y78: =Y16 -> -0.089230245 | Z78: =Z16 -> -0.084448694 | AA78: =AA16 -> -0.077647439
C79: Net Profit Margin | G79: =G20 -> 0.067954257 | H79: =H20 -> 0.10358216 | I79: =I20 -> 0.031018871 | J79: =J20 -> 0.048151248 | K79: =K20 -> 0.095037261 | L79: =L20 -> 0.10946681 | M79: =M20 -> 0.082729732 | N79: =N20 | ... R79: =R20 | T79: =T20 -> 0.032450322 | U79: =U20 -> 0.059336364 | V79: =V20 -> 0.065124948 | W79: =W20 | X79: =X20 | Y79: =Y20 | Z79: =Z20 | AA79: =AA20
C80: Return on Assets (ROA) | G80: =G19/G46 -> 0.029171758 | H80: =H19/H46 -> 0.054633619 | I80: =I19/I46 -> 0.013600629 | J80: =J19/J46 -> 0.0209265 | K80: =K19/K46 -> 0.045332031 | L80: =L19/L46 -> 0.061088171 | M80: =M19/M46 -> 0.038380567 | N80: =N19/N46 | ... R80: =R19/R46 | T80: =T19/T46 -> 0.067056914 | U80: =U19/U46 -> 0.10845938 | V80: =V19/V46 -> 0.12485289 | W80: =W19/W46 | X80: =X19/X46 | Y80: =Y19/Y46 | Z80: =Z19/Z46 | AA80: =AA19/AA46
C81: Return on Equity (ROE) | G81: =G19*4/G68 -> 3.1165501 | H81: =H19*4/H68 -> 2.5968779 | I81: =I19*4/I68 -> 0.67959735 | J81: =J19*4/J68 -> 2.7223382 | K81: =K19*4/K68 -> 20.862921 | L81: =L19*4/L68 -> -68.982857 | M81: =M19*4/M68 -> -4.8121827 | N81: =N19*4/N68 | ... R81: =R19*4/R68 | T81: =T19/T68 -> 0.63501647 | U81: =U19/U68 -> 2.1708925 | V81: =V19/V68 -> 4.0605428 | W81: =W19/W68 | X81: =X19/X68 | Y81: =Y19/Y68 | Z81: =Z19/Z68 | AA81: =AA19/AA68
C82: Return on Invested Capital (ROIC) | G82: =G19*4/(G53+G54+G68) -> 0.2374778 | H82: =H19*4/(H53+H54+H68) -> 0.44956681 | I82: =I19*4/(I53+I54+I68) -> 0.10700893 | J82: =J19*4/(J53+J54+J68) -> 0.14149306 | K82: =K19*4/(K53+K54+K68) -> 0.39191186 | L82: =L19*4/(L53+L54+L68) -> 0.52178423 | M82: =M19*4/(M53+M54+M68) -> 0.32058165 | N82: =N19*4/(N53+N54+N68) | ... S82: =S19*4/(S53+S54+S68) -> #DIV/0! | T82: =T19/(T53+T54+T68) -> 0.12086707 | U82: =U19/(U53+U54+U68) -> 0.22138905 | V82: =V19/(V53+V54+V68) -> 0.21104601 | W82: =W19/(W53+W54+W68) | X82: =X19/(X53+X54+X68) | Y82: =Y19/(Y53+Y54+Y68) | Z82: =Z19/(Z53+Z54+Z68) | AA82: =AA19/(AA53+AA54+AA68)
C84: Coverage
C85: Interest Expense | G85: =-Model!P39 -> 205 | H85: =-Model!Q39 -> 219 | I85: =-Model!R39 -> 221 | J85: =-Model!S39 -> 204 | K85: =-Model!U39 -> 211 | L85: =-Model!V39 -> 216 | M85: =-Model!W39 -> 223 | N85: =-Model!X39 | O85: =-Model!Z39 | P85: =-Model!AA39 | Q85: =-Model!AB39 | R85: =-Model!AC39 | T85: =-Model!J39 -> 624 | U85: =-Model!O39 -> 691 | V85: =-Model!T39 -> 849 | W85: =-Model!Y39 | X85: =-Model!AD39 | Y85: =-Model!AE39 | Z85: =-Model!AF39 | AA85: =-Model!AG39
C86: Capital Expenditures | G86: =Model!P193 -> 328 | H86: =Model!Q193 -> 382 | I86: =Model!R193 -> 462 | J86: =Model!S193 -> 557 | K86: =Model!U193 -> 461 | L86: =Model!V193 -> 385 | M86: =Model!W193 -> 410 | N86: =Model!X193 -> 370.1257 | O86: =Model!Z193 -> 616.58587 | P86: =Model!AA193 -> 644.33224 | Q86: =Model!AB193 -> 438.14592 | R86: =Model!AC193 -> 416.23862 | T86: =Model!J193 -> 1174 | U86: =Model!O193 -> 1484 | V86: =Model!T193 -> 1729 | W86: =Model!Y193 -> 1626.1257 | X86: =Model!AD193 -> 2115.3027 | Y86: =Model!AE193 -> 2146.8312 | Z86: =Model!AF193 -> 2189.7678 | AA86: =Model!AG193 -> 2345.2413
C87: EBIT / Interest Expense | G87: =IF(ISERROR(G15/G85),"N/A",(G15/G85)) -> 9.7121951 | H87: =IF(ISERROR(H15/H85),"N/A",(H15/H85)) -> 18.068493 | I87: =IF(ISERROR(I15/I85),"N/A",(I15/I85)) -> 9.841629 | J87: =IF(ISERROR(J15/J85),"N/A",(J15/J85)) -> 13.573529 | K87: =IF(ISERROR(K15/K85),"N/A",(K15/K85)) -> 15.379147 | L87: =IF(ISERROR(L15/L85),"N/A",(L15/L85)) -> 19.490741 | M87: =IF(ISERROR(M15/M85),"N/A",(M15/M85)) -> 12.506726 | N87: =IF(ISERROR(N15/N85),"N/A",(N15/N85)) -> N/A | ... R87: =IF(ISERROR(R15/R85),"N/A",(R15/R85)) -> N/A | T87: =IF(ISERROR(T15/T85),"N/A",(T15/T85)) -> 6.4391026 | U87: =IF(ISERROR(U15/U85),"N/A",(U15/U85)) -> 9.1374819 | V87: =IF(ISERROR(V15/V85),"N/A",(V15/V85)) -> 12.829211 | W87: =IF(ISERROR(W15/W85),"N/A",(W15/W85)) -> N/A | X87: =IF(ISERROR(X15/X85),"N/A",(X15/X85)) -> N/A | Y87: =IF(ISERROR(Y15/Y85),"N/A",(Y15/Y85)) -> N/A | Z87: =IF(ISERROR(Z15/Z85),"N/A",(Z15/Z85)) -> N/A | AA87: =IF(ISERROR(AA15/AA85),"N/A",(AA15/AA85)) -> N/A
C88: EBITDA / Interest Expense | G88: =IF(ISERROR(G27/G85),"N/A",(G27/G85)) -> 11.339317 | H88: =IF(ISERROR(H27/H85),"N/A",(H27/H85)) -> 19.596027 | I88: =IF(ISERROR(I27/I85),"N/A",(I27/I85)) -> 15.098552 | J88: =IF(ISERROR(J27/J85),"N/A",(J27/J85)) -> 15.485294 | K88: =IF(ISERROR(K27/K85),"N/A",(K27/K85)) -> 17.232227 | L88: =IF(ISERROR(L27/L85),"N/A",(L27/L85)) -> 21.384259 | M88: =IF(ISERROR(M27/M85),"N/A",(M27/M85)) -> 14.381166 | N88: =IF(ISERROR(N27/N85),"N/A",(N27/N85)) -> N/A | ... R88: =IF(ISERROR(R27/R85),"N/A",(R27/R85)) -> N/A | T88: =IF(ISERROR(T27/T85),"N/A",(T27/T85)) -> 11.765369 | U88: =IF(ISERROR(U27/U85),"N/A",(U27/U85)) -> 11.236614 | V88: =IF(ISERROR(V27/V85),"N/A",(V27/V85)) -> 15.443899 | W88: =IF(ISERROR(W27/W85),"N/A",(W27/W85)) -> N/A | X88: =IF(ISERROR(X27/X85),"N/A",(X27/X85)) -> N/A | Y88: =IF(ISERROR(Y27/Y85),"N/A",(Y27/Y85)) -> N/A | Z88: =IF(ISERROR(Z27/Z85),"N/A",(Z27/Z85)) -> N/A | AA88: =IF(ISERROR(AA27/AA85),"N/A",(AA27/AA85)) -> N/A
C89: (EBITDA - CapEx) / Interest Expense | G89: =IF(ISERROR((G27-G86)/G85),"N/A",((G27-G86)/G85)) -> 9.7393171 | H89: =IF(ISERROR((H27-H86)/H85),"N/A",((H27-H86)/H85)) -> 17.851735 | I89: =IF(ISERROR((I27-I86)/I85),"N/A",((I27-I86)/I85)) -> 13.008054 | J89: =IF(ISERROR((J27-J86)/J85),"N/A",((J27-J86)/J85)) -> 12.754902 | K89: =IF(ISERROR((K27-K86)/K85),"N/A",((K27-K86)/K85)) -> 15.047393 | L89: =IF(ISERROR((L27-L86)/L85),"N/A",((L27-L86)/L85)) -> 19.601852 | M89: =IF(ISERROR((M27-M86)/M85),"N/A",((M27-M86)/M85)) -> 12.542601 | N89: =IF(ISERROR((N27-N86)/N85),"N/A",((N27-N86)/N85)) -> N/A | ... R89: =IF(ISERROR((R27-R86)/R85),"N/A",((R27-R86)/R85)) -> N/A | T89: =IF(ISERROR((T27-T86)/T85),"N/A",((T27-T86)/T85)) -> 9.8839583 | U89: =IF(ISERROR((U27-U86)/U85),"N/A",((U27-U86)/U85)) -> 9.0890014 | V89: =IF(ISERROR((V27-V86)/V85),"N/A",((V27-V86)/V85)) -> 13.407385 | W89: =IF(ISERROR((W27-W86)/W85),"N/A",((W27-W86)/W85)) -> N/A | X89: =IF(ISERROR((X27-X86)/X85),"N/A",((X27-X86)/X85)) -> N/A | Y89: =IF(ISERROR((Y27-Y86)/Y85),"N/A",((Y27-Y86)/Y85)) -> N/A | Z89: =IF(ISERROR((Z27-Z86)/Z85),"N/A",((Z27-Z86)/Z85)) -> N/A | AA89: =IF(ISERROR((AA27-AA86)/AA85),"N/A",((AA27-AA86)/AA85)) -> N/A
C91: Leverage
C92: Total Debt / EBITDA | G92: =IF(ISERROR((G53+G54)/G27),"NA",((G53+G54)/G27)) -> 8.9496507 | H92: =IF(ISERROR((H53+H54)/H27),"NA",((H53+H54)/H27)) -> 4.8481544 | I92: =IF(ISERROR((I53+I54)/I27),"NA",((I53+I54)/I27)) -> 6.5314465 | J92: =IF(ISERROR((J53+J54)/J27),"NA",((J53+J54)/J27)) -> 8.297246 | K92: =IF(ISERROR((K53+K54)/K27),"NA",((K53+K54)/K27)) -> 6.3927393 | L92: =IF(ISERROR((L53+L54)/L27),"NA",((L53+L54)/L27)) -> 5.0467634 | M92: =IF(ISERROR((M53+M54)/M27),"NA",((M53+M54)/M27)) -> 7.868101 | N92: =IF(ISERROR((N53+N54)/N27),"NA",((N53+N54)/N27)) -> NA | ... R92: =IF(ISERROR((R53+R54)/R27),"NA",((R53+R54)/R27)) -> NA | T92: =IF(ISERROR((T53+T54)/T27),"NA",((T53+T54)/T27)) -> 2.1113955 | U92: =IF(ISERROR((U53+U54)/U27),"NA",((U53+U54)/U27)) -> 2.2364608 | V92: =IF(ISERROR((V53+V54)/V27),"NA",((V53+V54)/V27)) -> 1.9990284 | W92: =IF(ISERROR((W53+W54)/W27),"NA",((W53+W54)/W27)) -> NA | X92: =IF(ISERROR((X53+X54)/X27),"NA",((X53+X54)/X27)) -> NA | Y92: =IF(ISERROR((Y53+Y54)/Y27),"NA",((Y53+Y54)/Y27)) -> NA | Z92: =IF(ISERROR((Z53+Z54)/Z27),"NA",((Z53+Z54)/Z27)) -> NA | AA92: =IF(ISERROR((AA53+AA54)/AA27),"NA",((AA53+AA54)/AA27)) -> NA
C93: Total Debt / Equity | G93: =IF(ISERROR((G53+G54)/G68),"NA",((G53+G54)/G68)) -> 12.123543 | H93: =IF(ISERROR((H53+H54)/H68),"NA",((H53+H54)/H68)) -> 4.7764004 | I93: =IF(ISERROR((I53+I54)/I68),"NA",((I53+I54)/I68)) -> 5.350847 | J93: =IF(ISERROR((J53+J54)/J68),"NA",((J53+J54)/J68)) -> 18.240084 | K93: =IF(ISERROR((K53+K54)/K68),"NA",((K53+K54)/K68)) -> 52.233708 | L93: =IF(ISERROR((L53+L54)/L68),"NA",((L53+L54)/L68)) -> -133.20571 | M93: =IF(ISERROR((M53+M54)/M68),"NA",((M53+M54)/M68)) -> -16.010787 | N93: =IF(ISERROR((N53+N54)/N68),"NA",((N53+N54)/N68)) -> NA | ... R93: =IF(ISERROR((R53+R54)/R68),"NA",((R53+R54)/R68)) -> NA | T93: =IF(ISERROR((T53+T54)/T68),"NA",((T53+T54)/T68)) -> 4.2538419 | U93: =IF(ISERROR((U53+U54)/U68),"NA",((U53+U54)/U68)) -> 8.8057809 | V93: =IF(ISERROR((V53+V54)/V68),"NA",((V53+V54)/V68)) -> 18.240084 | W93: =IF(ISERROR((W53+W54)/W68),"NA",((W53+W54)/W68)) -> NA | X93: =IF(ISERROR((X53+X54)/X68),"NA",((X53+X54)/X68)) -> NA | Y93: =IF(ISERROR((Y53+Y54)/Y68),"NA",((Y53+Y54)/Y68)) -> NA | Z93: =IF(ISERROR((Z53+Z54)/Z68),"NA",((Z53+Z54)/Z68)) -> NA | AA93: =IF(ISERROR((AA53+AA54)/AA68),"NA",((AA53+AA54)/AA68)) -> NA
C94: Total Debt / Total Assets | G94: =IF(ISERROR((G53+G54)/G46),"NA",((G53+G54)/G46)) -> 0.45391866 | H94: =IF(ISERROR((H53+H54)/H46),"NA",((H53+H54)/H46)) -> 0.40194734 | I94: =IF(ISERROR((I53+I54)/I46),"NA",((I53+I54)/I46)) -> 0.42834119 | J94: =IF(ISERROR((J53+J54)/J46),"NA",((J53+J54)/J46)) -> 0.56084305 | K94: =IF(ISERROR((K53+K54)/K46),"NA",((K53+K54)/K46)) -> 0.45398437 | L94: =IF(ISERROR((L53+L54)/L46),"NA",((L53+L54)/L46)) -> 0.47184439 | M94: =IF(ISERROR((M53+M54)/M46),"NA",((M53+M54)/M46)) -> 0.51078947 | N94: =IF(ISERROR((N53+N54)/N46),"NA",((N53+N54)/N46)) -> NA | ... R94: =IF(ISERROR((R53+R54)/R46),"NA",((R53+R54)/R46)) -> NA | T94: =IF(ISERROR((T53+T54)/T46),"NA",((T53+T54)/T46)) -> 0.44920019 | U94: =IF(ISERROR((U53+U54)/U46),"NA",((U53+U54)/U46)) -> 0.43994325 | V94: =IF(ISERROR((V53+V54)/V46),"NA",((V53+V54)/V46)) -> 0.56084305 | W94: =IF(ISERROR((W53+W54)/W46),"NA",((W53+W54)/W46)) -> NA | X94: =IF(ISERROR((X53+X54)/X46),"NA",((X53+X54)/X46)) -> NA | Y94: =IF(ISERROR((Y53+Y54)/Y46),"NA",((Y53+Y54)/Y46)) -> NA | Z94: =IF(ISERROR((Z53+Z54)/Z46),"NA",((Z53+Z54)/Z46)) -> NA | AA94: =IF(ISERROR((AA53+AA54)/AA46),"NA",((AA53+AA54)/AA46)) -> NA
C96: Efficiency
C97: Asset Turnover | G97: =G8/G46 -> 0.42928522 | H97: =H8/H46 -> 0.52744238 | I97: =I8/I46 -> 0.43846305 | J97: =J8/J46 -> 0.43459934 | K97: =K8/K46 -> 0.47699219 | L97: =L8/L46 -> 0.55805198 | M97: =M8/M46 -> 0.46392713 | N97: =N8/N46 | ... R97: =R8/R46 | T97: =T8/T46 -> 2.0664484 | U97: =U8/U46 -> 1.8278736 | V97: =V8/V46 -> 1.9171285 | W97: =W8/W46 | X97: =X8/X46 | Y97: =Y8/Y46 | Z97: =Z8/Z46 | AA97: =AA8/AA46
C98: =Model!C182 -> Days Sales Outstanding | G98: =Model!P182 -> 0 | H98: =Model!Q182 -> 0 | I98: =Model!R182 -> 0 | J98: =Model!S182 -> 0 | K98: =Model!U182 -> 0 | L98: =Model!V182 -> 0 | M98: =Model!W182 -> 0 | N98: =Model!X182 -> 0 | O98: =Model!Z182 -> 0 | P98: =Model!AA182 -> 0 | Q98: =Model!AB182 -> 0 | R98: =Model!AC182 -> 0 | T98: =Model!J182 -> 0 | U98: =Model!O182 -> 0 | V98: =Model!T182 -> 0 | W98: =Model!Y182 -> 0 | X98: =Model!AD182 -> 0 | Y98: =Model!AE182 -> 0 | Z98: =Model!AF182 -> 0 | AA98: =Model!AG182 -> 0
C99: =Model!C183 -> Days Inventory Outstanding | G99: =Model!P183 -> 93.890746 | H99: =Model!Q183 -> 71.073842 | I99: =Model!R183 -> 90.544207 | J99: =Model!S183 -> 106.00433 | K99: =Model!U183 -> 95.499325 | L99: =Model!V183 -> 88.976449 | M99: =Model!W183 -> 102.03653 | N99: =Model!X183 -> 90 | O99: =Model!Z183 -> 95 | P99: =Model!AA183 -> 80 | Q99: =Model!AB183 -> 85 | R99: =Model!AC183 -> 90 | T99: =Model!J183 -> 94.551197 | U99: =Model!O183 -> 95.468956 | V99: =Model!T183 -> 89.318992 | W99: =Model!Y183 -> 92.076247 | X99: =Model!AD183 -> 78.933008 | Y99: =Model!AE183 -> 84 | Z99: =Model!AF183 -> 84 | AA99: =Model!AG183 -> 84
C100: =Model!C184 -> Days Payables Outstanding | G100: =Model!P184 -> 63.250266 | H100: =Model!Q184 -> 60.05909 | I100: =Model!R184 -> 78.689453 | J100: =Model!S184 -> 78.553846 | K100: =Model!U184 -> 68.632458 | L100: =Model!V184 -> 64.731214 | M100: =Model!W184 -> 70.045659 | N100: =Model!X184 -> 55 | O100: =Model!Z184 -> 58 | P100: =Model!AA184 -> 48 | Q100: =Model!AB184 -> 53 | R100: =Model!AC184 -> 55 | T100: =Model!J184 -> 69.285242 | U100: =Model!O184 -> 59.113606 | V100: =Model!T184 -> 56.388468 | W100: =Model!Y184 -> 58.889474 | X100: =Model!AD184 -> 48.236838 | Y100: =Model!AE184 -> 54 | Z100: =Model!AF184 -> 54 | AA100: =Model!AG184 -> 54
C101: Cash Conversion Cycle | G101: =G98+G99-G100 -> 30.64048 | H101: =H98+H99-H100 -> 11.014752 | I101: =I98+I99-I100 -> 11.854754 | J101: =J98+J99-J100 -> 27.450488 | K101: =K98+K99-K100 -> 26.866867 | L101: =L98+L99-L100 -> 24.245235 | M101: =M98+M99-M100 -> 31.990868 | N101: =N98+N99-N100 -> 35 | ... R101: =R98+R99-R100 -> 35 | T101: =T98+T99-T100 -> 25.265955 | U101: =U98+U99-U100 -> 36.35535 | V101: =V98+V99-V100 -> 32.930525 | W101: =W98+W99-W100 -> 33.186773 | X101: =X98+X99-X100 -> 30.69617 | Y101: =Y98+Y99-Y100 -> 30 | Z101: =Z98+Z99-Z100 -> 30 | AA101: =AA98+AA99-AA100 -> 30
C103: Liquidity
C104: Current Ratio | G104: =IF(ISERROR(G38/G51),"NA",(G38/G51)) -> 1.2372891 | H104: =IF(ISERROR(H38/H51),"NA",(H38/H51)) -> 1.3350513 | I104: =IF(ISERROR(I38/I51),"NA",(I38/I51)) -> 1.4199947 | J104: =IF(ISERROR(J38/J51),"NA",(J38/J51)) -> 1.3203619 | K104: =IF(ISERROR(K38/K51),"NA",(K38/K51)) -> 1.244131 | L104: =IF(ISERROR(L38/L51),"NA",(L38/L51)) -> 1.2343996 | M104: =IF(ISERROR(M38/M51),"NA",(M38/M51)) -> 1.2754851 | N104: =IF(ISERROR(N38/N51),"NA",(N38/N51)) -> NA | ... R104: =IF(ISERROR(R38/R51),"NA",(R38/R51)) -> NA | T104: =IF(ISERROR(T38/T51),"NA",(T38/T51)) -> 1.0628221 | U104: =IF(ISERROR(U38/U51),"NA",(U38/U51)) -> 1.0502571 | V104: =IF(ISERROR(V38/V51),"NA",(V38/V51)) -> 1.3203619 | W104: =IF(ISERROR(W38/W51),"NA",(W38/W51)) -> NA | X104: =IF(ISERROR(X38/X51),"NA",(X38/X51)) -> NA | Y104: =IF(ISERROR(Y38/Y51),"NA",(Y38/Y51)) -> NA | Z104: =IF(ISERROR(Z38/Z51),"NA",(Z38/Z51)) -> NA | AA104: =IF(ISERROR(AA38/AA51),"NA",(AA38/AA51)) -> NA
C105: Quick Ratio | G105: =IF(ISERROR((G34+G35)/G51),"NA",((G34+G35)/G51)) -> 0.34738446 | H105: =IF(ISERROR((H34+H35)/H51),"NA",((H34+H35)/H51)) -> 0.61297625 | I105: =IF(ISERROR((I34+I35)/I51),"NA",((I34+I35)/I51)) -> 0.5328937 | J105: =IF(ISERROR((J34+J35)/J51),"NA",((J34+J35)/J51)) -> 0.30729197 | K105: =IF(ISERROR((K34+K35)/K51),"NA",((K34+K35)/K51)) -> 0.33153939 | L105: =IF(ISERROR((L34+L35)/L51),"NA",((L34+L35)/L51)) -> 0.3078248 | M105: =IF(ISERROR((M34+M35)/M51),"NA",((M34+M35)/M51)) -> 0.3425213 | N105: =IF(ISERROR((N34+N35)/N51),"NA",((N34+N35)/N51)) -> NA | ... R105: =IF(ISERROR((R34+R35)/R51),"NA",((R34+R35)/R51)) -> NA | T105: =IF(ISERROR((T34+T35)/T51),"NA",((T34+T35)/T51)) -> 0.054455815 | U105: =IF(ISERROR((U34+U35)/U51),"NA",((U34+U35)/U51)) -> 0.060061707 | V105: =IF(ISERROR((V34+V35)/V51),"NA",((V34+V35)/V51)) -> 0.30729197 | W105: =IF(ISERROR((W34+W35)/W51),"NA",((W34+W35)/W51)) -> NA | X105: =IF(ISERROR((X34+X35)/X51),"NA",((X34+X35)/X51)) -> NA | Y105: =IF(ISERROR((Y34+Y35)/Y51),"NA",((Y34+Y35)/Y51)) -> NA | Z105: =IF(ISERROR((Z34+Z35)/Z51),"NA",((Z34+Z35)/Z51)) -> NA | AA105: =IF(ISERROR((AA34+AA35)/AA51),"NA",((AA34+AA35)/AA51)) -> NA
C106: Cash Ratio | G106: =IF(ISERROR(G34/G51),"NA",(G34/G51)) -> 0.34738446 | H106: =IF(ISERROR(H34/H51),"NA",(H34/H51)) -> 0.61297625 | I106: =IF(ISERROR(I34/I51),"NA",(I34/I51)) -> 0.5328937 | J106: =IF(ISERROR(J34/J51),"NA",(J34/J51)) -> 0.30729197 | K106: =IF(ISERROR(K34/K51),"NA",(K34/K51)) -> 0.33153939 | L106: =IF(ISERROR(L34/L51),"NA",(L34/L51)) -> 0.3078248 | M106: =IF(ISERROR(M34/M51),"NA",(M34/M51)) -> 0.3425213 | N106: =IF(ISERROR(N34/N51),"NA",(N34/N51)) -> NA | ... R106: =IF(ISERROR(R34/R51),"NA",(R34/R51)) -> NA | T106: =IF(ISERROR(T34/T51),"NA",(T34/T51)) -> 0.054455815 | U106: =IF(ISERROR(U34/U51),"NA",(U34/U51)) -> 0.060061707 | V106: =IF(ISERROR(V34/V51),"NA",(V34/V51)) -> 0.30729197 | W106: =IF(ISERROR(W34/W51),"NA",(W34/W51)) -> NA | X106: =IF(ISERROR(X34/X51),"NA",(X34/X51)) -> NA | Y106: =IF(ISERROR(Y34/Y51),"NA",(Y34/Y51)) -> NA | Z106: =IF(ISERROR(Z34/Z51),"NA",(Z34/Z51)) -> NA | AA106: =IF(ISERROR(AA34/AA51),"NA",(AA34/AA51)) -> NA
A110: x

Sheet Model Output
B1: =Company_Name&" "&"("&Ticker&")"&" Valuation Overview" -> Lowe's Companies, Inc. (LOW) Valuation Overview | K1: Price Target Scenario: | N1: =Case_Scenario&" Case" -> Base Case | R1: Base Case Check | S1: =IF(N1="Base Case","","Check!") | Y1: P/E
B2: =Cover!C2 -> $ in Millions Except Per Share Data | K2: Current Share Price: | O2: =Share_Price -> 233.18 | Y2: EV/EBITDA
K3: Valuation Date: | O3: =Current_Date -> 45903
B4: ="Multiples Analysis "&"("&S21&")" -> Multiples Analysis (P/E) | I4: Return Summary
I6: Exit Multiple Method
I7: =Cover!I9 -> Implied Enterprise Value: | N7: =Cover!L9
I8: =Cover!I10 -> Implied Equity Value: | N8: =Cover!L10
I9: =Cover!I12 -> Implied Share Price: | N9: =Cover!L12
I10: =Cover!I13 -> % Return: | N10: =Cover!L13
I12: =Cover!I15 -> Perpetuity Growth Method
I13: =Cover!I16 -> Implied Enterprise Value: | N13: =Cover!L16
I14: =Cover!I17 -> Implied Equity Value: | N14: =Cover!L17
I15: =Cover!I19 -> Implied Share Price: | N15: =Cover!L19
I16: =Cover!I20 -> % Return: | N16: =Cover!L20
E18: Annuals | M18: CAGR | O18: CAGR
B19: Consolidated Financials | E19: =Summary!U6 -> 2024 | F19: =Summary!V6 -> 2025 | G19: =Summary!W6 -> 2026e | H19: =Summary!X6 -> 2027e | I19: =Summary!Y6 -> 2028e | J19: =Summary!Z6 -> 2029e | K19: =Summary!AA6 -> 2030e | M19: Historical | O19: Projected
B21: =Summary!C8 -> Revenue | D21: =Summary!T8 -> 71309 | E21: =Summary!U8 -> 72148 | F21: =Summary!V8 -> 89597 | G21: =Summary!W8 -> 96682.1 | H21: =Summary!X8 -> 105236.82 | I21: =Summary!Y8 -> 107341.56 | J21: =Summary!Z8 -> 109488.39 | K21: =Summary!AA8 -> 111678.16 | M21: =Summary!AC8 -> 0.12091985 | O21: =Summary!AE8 -> 0.045044909 | R21: Multiple Toggle | S21: P/E
B22: =Summary!C9 -> YoY % Growth | E22: =Summary!U9 -> 0.011765696 | F22: =Summary!V9 -> 0.24185009 | G22: =Summary!W9 -> 0.079077424 | H22: =Summary!X9 -> 0.088482991 | I22: =Summary!Y9 -> 0.02 | J22: =Summary!Z9 -> 0.02 | K22: =Summary!AA9 -> 0.02
R23: Multiples Analysis | S23: EV/EBITDA | T23: P/E | U23: Chart
B24: =Summary!C11 -> Gross Profit | D24: =Summary!T11 -> 22908 | E24: =Summary!U11 -> 22943 | F24: =Summary!V11 -> 29583 | G24: =Summary!W11 -> 27859.373 | H24: =Summary!X11 -> 14241.705 | I24: =Summary!Y11 -> 14920.477 | J24: =Summary!Z11 -> 15328.374 | K24: =Summary!AA11 -> 15858.298 | M24: =Summary!AC11 -> 0.1363903 | O24: =Summary!AE11 -> -0.11723954 | R24: Entry Multiple | S24: =Valuation!D12 -> 12.4849 | T24: =Valuation!D11 -> 18.6398 | U24: =IF($S$21=$S$23,S24,T24) -> 18.6398
B25: =Summary!C12 -> % Margin | E25: =Summary!U12 -> 0.31799911 | F25: =Summary!V12 -> 0.33017847 | G25: =Summary!W12 -> 0.28815441 | H25: =Summary!X12 -> 0.13533006 | I25: =Summary!Y12 -> 0.139 | J25: =Summary!Z12 -> 0.14 | K25: =Summary!AA12 -> 0.142 | R25: =Model!Y25 -> 2026e | S25: =(Comparables!H10*S30)/(Model!Y61) | T25: =(Comparables!$G$10*S30)/Summary!W19 | U25: =IF($S$21=$S$23,S25,T25)
B26: =Summary!C13 -> YoY % Growth | E26: =Summary!U13 -> 0.0015278505 | F26: =Summary!V13 -> 0.28941289 | G26: =Summary!W13 -> -0.058264104 | H26: =Summary!X13 -> -0.48880022 | I26: =Summary!Y13 -> 0.047660817 | J26: =Summary!Z13 -> 0.027338129 | K26: =Summary!AA13 -> 0.034571429 | R26: =Summary!AA6 -> 2030e | S26: =(Comparables!H10*S30)/(Model!AG61) | T26: =(Comparables!$G$10*S30)/Summary!AA19 | U26: =IF($S$21=$S$23,S26,T26)
R27: Exit Multiple | S27: =Valuation!K60 -> 13 | T27: =Valuation!K72/Summary!AA19 | U27: =IF($S$21=$S$23,S27,T27)
B28: =Summary!C27 -> EBITDA | D28: =Summary!T27 -> 7341.59 | E28: =Summary!U27 -> 7764.5 | F28: =Summary!V27 -> 13111.87 | G28: =Summary!W27 | H28: =Summary!X27 | I28: =Summary!Y27 | J28: =Summary!Z27 | K28: =Summary!AA27 | M28: =Summary!AC27 -> 0.33640242 | O28: =Summary!AE27 -> N/A | R28: Implied PGM | S28: =Valuation!K79 | T28: =Valuation!R72/Summary!AA19 | U28: =IF($S$21=$S$23,S28,T28)
B29: =Summary!C28 -> Margin | E29: =Summary!U28 -> 0.10761906 | F29: =Summary!V28 -> 0.14634273 | G29: =Summary!W28 | H29: =Summary!X28 | I29: =Summary!Y28 | J29: =Summary!Z28 | K29: =Summary!AA28
B30: =Summary!C29 -> YoY % Growth | E30: =Summary!U17 -> 0.57142857 | F30: =Summary!V17 -> 0.72505543 | G30: =Summary!W29 | H30: =Summary!X29 | I30: =Summary!Y29 | J30: =Summary!Z29 | K30: =Summary!AA29 | R30: Financials Multiplier | S30: =IF($B$2="$ in Millions Except Per Share Data",1,IF($B$2="$ in Thousands Except Per Share Data",1000,IF($B$2="$ in Billions Except Per Share Data",0.001,0))) -> 1
B32: =Summary!C19 -> Net Income (Loss) | D32: =Summary!T19 -> 2314 | E32: =Summary!U19 -> 4281 | F32: =Summary!V19 -> 5835 | G32: =Summary!W19 | H32: =Summary!X19 | I32: =Summary!Y19 | J32: =Summary!Z19 | K32: =Summary!AA19 | M32: =Summary!AC19 -> 0.58795705 | O32: =Summary!AE19 -> N/A
B33: =Summary!C20 -> Margin | E33: =Summary!U20 -> 0.059336364 | F33: =Summary!V20 -> 0.065124948 | G33: =Summary!W20 | H33: =Summary!X20 | I33: =Summary!Y20 | J33: =Summary!Z20 | K33: =Summary!AA20
B34: =Summary!C21 -> YoY % Growth | E34: =Summary!U21 -> 0.85004322 | F34: =Summary!V21 -> 0.3629993 | G34: =Summary!W21 | H34: =Summary!X21 | I34: =Summary!Y21 | J34: =Summary!Z21 | K34: =Summary!AA21
B36: =Summary!C23 -> Adj. EPS (Diluted) | D36: =Summary!T23 -> 5.1942447 | E36: =Summary!U23 -> 5.5799001 | F36: =Summary!V23 -> 8.8758267 | G36: =Summary!W23 | H36: =Summary!X23 | I36: =Summary!Y23 | J36: =Summary!Z23 | K36: =Summary!AA23 | M36: =Summary!AC23 -> 0.30720351 | O36: =Summary!AE23 -> N/A
B37: =Summary!C24 -> YoY % Growth | E37: =Summary!U24 -> 0.074246681 | F37: =Summary!V24 -> 0.59067841 | G37: =Summary!W24 -> NA | H37: =Summary!X24 -> NA | I37: =Summary!Y24 -> NA | J37: =Summary!Z24 -> NA | K37: =Summary!AA24 -> NA
B39: Free Cash Flow | D39: =Model!J112 -> 3799 | E39: =Model!O112 -> 2821 | F39: =Model!T112 -> 5715 | G39: =Model!Y112 | H39: =Model!AD112 | I39: =Model!AE112 | J39: =Model!AF112 | K39: =Model!AG112 | M39: =IFERROR((F39/D39)^(1/2)-1,"N/A") -> 0.22651671 | O39: =IFERROR((K39/G39)^(1/4)-1,"N/A") -> N/A
B40: YoY % Growth | E40: =E39/D39-1 -> -0.25743617 | F40: =F39/E39-1 -> 1.0258773 | G40: =G39/F39-1 | H40: =H39/G39-1 | I40: =I39/H39-1 | J40: =J39/I39-1 | K40: =K39/J39-1
E42: Annuals | M42: Average | O42: Average
B43: Capitalization and Key Ratios | E43: =E19 -> 2024 | F43: =F19 -> 2025 | G43: =G19 -> 2026e | H43: =H19 -> 2027e | I43: =I19 -> 2028e | J43: =J19 -> 2029e | K43: =K19 -> 2030e | M43: Historical | O43: Projected
B44: =Summary!C91 -> Leverage
B45: =Summary!C92 -> Total Debt / EBITDA | D45: =Summary!T92 -> 2.1113955 | E45: =Summary!U92 -> 2.2364608 | F45: =Summary!V92 -> 1.9990284 | G45: =Summary!W92 -> NA | H45: =Summary!X92 -> NA | I45: =Summary!Y92 -> NA | J45: =Summary!Z92 -> NA | K45: =Summary!AA92 -> NA | M45: =AVERAGE(D45:F45) -> 2.1156282 | O45: =AVERAGE(G45:K45)
B46: =Summary!C93 -> Total Debt / Equity | D46: =Summary!T93 -> 4.2538419 | E46: =Summary!U93 -> 8.8057809 | F46: =Summary!V93 -> 18.240084 | G46: =Summary!W93 -> NA | H46: =Summary!X93 -> NA | I46: =Summary!Y93 -> NA | J46: =Summary!Z93 -> NA | K46: =Summary!AA93 -> NA | M46: =AVERAGE(D46:F46) -> 10.433235 | O46: =AVERAGE(G46:K46)
B47: =Summary!C94 -> Total Debt / Total Assets | D47: =Summary!T94 -> 0.44920019 | E47: =Summary!U94 -> 0.43994325 | F47: =Summary!V94 -> 0.56084305 | G47: =Summary!W94 -> NA | H47: =Summary!X94 -> NA | I47: =Summary!Y94 -> NA | J47: =Summary!Z94 -> NA | K47: =Summary!AA94 -> NA | M47: =AVERAGE(D47:F47) -> 0.48332883 | O47: =AVERAGE(G47:K47)
B49: =Summary!C103 -> Liquidity
B50: =Summary!C104 -> Current Ratio | D50: =Summary!T104 -> 1.0628221 | E50: =Summary!U104 -> 1.0502571 | F50: =Summary!V104 -> 1.3203619 | G50: =Summary!W104 -> NA | H50: =Summary!X104 -> NA | I50: =Summary!Y104 -> NA | J50: =Summary!Z104 -> NA | K50: =Summary!AA104 -> NA | M50: =AVERAGE(D50:F50) -> 1.1444804 | O50: =AVERAGE(G50:K50)
B51: =Summary!C105 -> Quick Ratio | D51: =Summary!T105 -> 0.054455815 | E51: =Summary!U105 -> 0.060061707 | F51: =Summary!V105 -> 0.30729197 | G51: =Summary!W105 -> NA | H51: =Summary!X105 -> NA | I51: =Summary!Y105 -> NA | J51: =Summary!Z105 -> NA | K51: =Summary!AA105 -> NA | M51: =AVERAGE(D51:F51) -> 0.14060317 | O51: =AVERAGE(G51:K51)
B52: =Summary!C106 -> Cash Ratio | D52: =Summary!T106 -> 0.054455815 | E52: =Summary!U106 -> 0.060061707 | F52: =Summary!V106 -> 0.30729197 | G52: =Summary!W106 -> NA | H52: =Summary!X106 -> NA | I52: =Summary!Y106 -> NA | J52: =Summary!Z106 -> NA | K52: =Summary!AA106 -> NA | M52: =AVERAGE(D52:F52) -> 0.14060317 | O52: =AVERAGE(G52:K52)
B54: =Summary!C75 -> Profitability
B55: =Summary!C80 -> Return on Assets (ROA) | D55: =Summary!T80 -> 0.067056914 | E55: =Summary!U80 -> 0.10845938 | F55: =Summary!V80 -> 0.12485289 | G55: =Summary!W80 | H55: =Summary!X80 | I55: =Summary!Y80 | J55: =Summary!Z80 | K55: =Summary!AA80 | M55: =AVERAGE(D55:F55) -> 0.10012306 | O55: =AVERAGE(G55:K55)
B56: =Summary!C81 -> Return on Equity (ROE) | D56: =Summary!T81 -> 0.63501647 | E56: =Summary!U81 -> 2.1708925 | F56: =Summary!V81 -> 4.0605428 | G56: =Summary!W81 | H56: =Summary!X81 | I56: =Summary!Y81 | J56: =Summary!Z81 | K56: =Summary!AA81 | M56: =AVERAGE(D56:F56) -> 2.2888173 | O56: =AVERAGE(G56:K56)
B57: Return on Inv. Capital (ROIC) | D57: =Summary!T82 -> 0.12086707 | E57: =Summary!U82 -> 0.22138905 | F57: =Summary!V82 -> 0.21104601 | G57: =Summary!W82 | H57: =Summary!X82 | I57: =Summary!Y82 | J57: =Summary!Z82 | K57: =Summary!AA82 | M57: =AVERAGE(D57:F57) -> 0.18443404 | O57: =AVERAGE(G57:K57)
B59: =Summary!C84 -> Coverage
B60: Interest Expense | D60: =Summary!T85 -> 624 | E60: =Summary!U85 -> 691 | F60: =Summary!V85 -> 849 | G60: =Summary!W85 | H60: =Summary!X85 | I60: =Summary!Y85 | J60: =Summary!Z85 | K60: =Summary!AA85 | M60: =AVERAGE(D60:F60) -> 721.33333 | O60: =AVERAGE(G60:K60)
B61: Capital Expenditures | D61: =Summary!T86 -> 1174 | E61: =Summary!U86 -> 1484 | F61: =Summary!V86 -> 1729 | G61: =Summary!W86 -> 1626.1257 | H61: =Summary!X86 -> 2115.3027 | I61: =Summary!Y86 -> 2146.8312 | J61: =Summary!Z86 -> 2189.7678 | K61: =Summary!AA86 -> 2345.2413 | M61: =AVERAGE(D61:F61) -> 1462.3333 | O61: =AVERAGE(G61:K61) -> 2084.6537
B62: EBIT / Interest | D62: =Summary!T87 -> 6.4391026 | E62: =Summary!U87 -> 9.1374819 | F62: =Summary!V87 -> 12.829211 | G62: =Summary!W87 -> N/A | H62: =Summary!X87 -> N/A | I62: =Summary!Y87 -> N/A | J62: =Summary!Z87 -> N/A | K62: =Summary!AA87 -> N/A | M62: =AVERAGE(D62:F62) -> 9.4685984 | O62: =AVERAGE(G62:K62)
B63: EBITDA / Interest | D63: =Summary!T88 -> 11.765369 | E63: =Summary!U88 -> 11.236614 | F63: =Summary!V88 -> 15.443899 | G63: =Summary!W88 -> N/A | H63: =Summary!X88 -> N/A | I63: =Summary!Y88 -> N/A | J63: =Summary!Z88 -> N/A | K63: =Summary!AA88 -> N/A | M63: =AVERAGE(D63:F63) -> 12.815294 | O63: =AVERAGE(G63:K63)
B64: (EBITDA - CapEx) / Interest | D64: =Summary!T89 -> 9.8839583 | E64: =Summary!U89 -> 9.0890014 | F64: =Summary!V89 -> 13.407385 | G64: =Summary!W89 -> N/A | H64: =Summary!X89 -> N/A | I64: =Summary!Y89 -> N/A | J64: =Summary!Z89 -> N/A | K64: =Summary!AA89 -> N/A | M64: =AVERAGE(D64:F64) -> 10.793448 | O64: =AVERAGE(G64:K64)
B66: =Summary!C96 -> Efficiency
B67: =Summary!C97 -> Asset Turnover | D67: =Summary!T97 -> 2.0664484 | E67: =Summary!U97 -> 1.8278736 | F67: =Summary!V97 -> 1.9171285 | G67: =Summary!W97 | H67: =Summary!X97 | I67: =Summary!Y97 | J67: =Summary!Z97 | K67: =Summary!AA97 | M67: =AVERAGE(D67:F67) -> 1.9371502 | O67: =AVERAGE(G67:K67)
B68: =Summary!C98 -> Days Sales Outstanding | D68: =Summary!T98 -> 0 | E68: =Summary!U98 -> 0 | F68: =Summary!V98 -> 0 | G68: =Summary!W98 -> 0 | H68: =Summary!X98 -> 0 | I68: =Summary!Y98 -> 0 | J68: =Summary!Z98 -> 0 | K68: =Summary!AA98 -> 0 | M68: =AVERAGE(D68:F68) | O68: =AVERAGE(G68:K68)
B69: =Summary!C99 -> Days Inventory Outstanding | D69: =Summary!T99 -> 94.551197 | E69: =Summary!U99 -> 95.468956 | F69: =Summary!V99 -> 89.318992 | G69: =Summary!W99 -> 92.076247 | H69: =Summary!X99 -> 78.933008 | I69: =Summary!Y99 -> 84 | J69: =Summary!Z99 -> 84 | K69: =Summary!AA99 -> 84 | M69: =AVERAGE(D69:F69) -> 93.113049 | O69: =AVERAGE(G69:K69) -> 84.601851
B70: =Summary!C100 -> Days Payables Outstanding | D70: =Summary!T100 -> 69.285242 | E70: =Summary!U100 -> 59.113606 | F70: =Summary!V100 -> 56.388468 | G70: =Summary!W100 -> 58.889474 | H70: =Summary!X100 -> 48.236838 | I70: =Summary!Y100 -> 54 | J70: =Summary!Z100 -> 54 | K70: =Summary!AA100 -> 54 | M70: =AVERAGE(D70:F70) -> 61.595772 | O70: =AVERAGE(G70:K70) -> 53.825262
B71: =Summary!C101 -> Cash Conversion Cycle | D71: =Summary!T101 -> 25.265955 | E71: =Summary!U101 -> 36.35535 | F71: =Summary!V101 -> 32.930525 | G71: =Summary!W101 -> 33.186773 | H71: =Summary!X101 -> 30.69617 | I71: =Summary!Y101 -> 30 | J71: =Summary!Z101 -> 30 | K71: =Summary!AA101 -> 30 | M71: =AVERAGE(D71:F71) -> 31.517277 | O71: =AVERAGE(G71:K71) -> 30.776589

Sheet Football Field
C1: =Company_Name&" - "&MID(CELL("filename",A1),FIND("]",CELL("filename",A1))+1,255)&": "&Case_Scenario&" Case" -> Lowe's Companies, Inc. - Football Field: Base Case
C2: =Cover!C2 -> $ in Millions Except Per Share Data
A4: x | O4: Valuation Method: | T4: Downside | U4: Delta | V4: Upside | W4: x
O5: =TEXT(Valuation!E108,"0.0%")&" - "&TEXT(Valuation!E110,"0.0%")&" WACC"&" & "&TEXT(Valuation!G106,"0.0%")&" - "&TEXT(Valuation!I106,"0.0%")&" PGR" -> 8.4% - 9.4% WACC & 1.5% - 2.5% PGR | T5: =Valuation!G108 -> 195.04955 | U5: =V5-T5 -> 20.385916 | V5: =Valuation!I110 -> 215.43546
O6: =TEXT(Valuation!E100,"0.0%")&" - "&TEXT(Valuation!E102,"0.0%")&" WACC"&" & "&TEXT(Valuation!G98,"0.0x")&" - "&TEXT(Valuation!I98,"0.0x")&" Exit Multiple" -> 8.4% - 9.4% WACC & 12.0x - 14.0x Exit Multiple | T6: =Valuation!G100 -> 250.78262 | U6: =V6-T6 -> 27.264041 | V6: =Valuation!I102 -> 278.04666
O8: =Valuation!F184&": "&TEXT(Valuation!G185,"0.0x")&" - "&TEXT(Valuation!I185,"0.0x") -> NTM EV/EBITDA Spread to Comps: 12.0x - 14.0x | T8: =Valuation!G187 -> 209.23348 | U8: =V8-T8 -> 100.49025 | V8: =Valuation!I189 -> 309.72373
O9: =Valuation!F176&": "&TEXT(Valuation!G177,"0.0x")&" - "&TEXT(Valuation!I177,"0.0x") -> NTM EV/EBITDA: 11.4x - 13.4x | T9: =Valuation!G179 -> 197.97414 | U9: =V9-T9 -> 97.988172 | V9: =Valuation!I181 -> 295.96231
O10: =Valuation!F168&": "&TEXT(Valuation!G169,"0.0x")&" - "&TEXT(Valuation!I169,"0.0x") -> NTM P/E Spread to Comps: 18.3x - 20.3x | T10: =Valuation!G171 -> 241.4239 | U10: =V10-T10 -> 85.926567 | V10: =Valuation!I173 -> 327.35047
O11: =Valuation!F160&": "&TEXT(Valuation!G161,"0.0x")&" - "&TEXT(Valuation!I161,"0.0x") -> NTM P/E: 17.8x - 19.8x | T11: =Valuation!G163 -> 234.48845 | U11: =V11-T11 -> 84.385357 | V11: =Valuation!I165 -> 318.87381
O13: =Valuation!F260&": "&TEXT(Valuation!G261,"0.0x")&" - "&TEXT(Valuation!I261,"0.0x") -> 2009-2018 Early Cycle EV/EBITDA Spread to Comps: 11.7x - 13.7x | T13: =Valuation!G263 -> 202.21364 | U13: =V13-T13 -> 39.300331 | V13: =Valuation!I263 -> 241.51397
O14: =Valuation!F252&": "&TEXT(Valuation!G253,"0.0x")&" - "&TEXT(Valuation!I253,"0.0x") -> 2009-2018 Early Cycle EV/EBITDA: 6.4x - 8.4x | T14: =Valuation!G255 -> 99.103102 | U14: =V14-T14 -> 39.300331 | V14: =Valuation!I255 -> 138.40343
O15: =Valuation!F244&": "&TEXT(Valuation!G245,"0.0x")&" - "&TEXT(Valuation!I245,"0.0x") -> 2009-2018 Early Cycle P/E Spread to Comps: 20.2x - 22.2x | T15: =Valuation!G247 -> 267.04261 | U15: =V15-T15 -> 26.408301 | V15: =Valuation!I247 -> 293.45091
O16: =Valuation!F236&": "&TEXT(Valuation!G237,"0.0x")&" - "&TEXT(Valuation!I237,"0.0x") -> 2009-2018 Early Cycle P/E: 15.5x - 17.5x | T16: =Valuation!G239 -> 205.30919 | U16: =V16-T16 -> 26.408301 | V16: =Valuation!I239 -> 231.71749
O18: 52-Week Price Range: | T18: =Share_Price_Low -> 146.72 | U18: =V18-T18 -> 68.5 | V18: =Share_Price_High -> 215.22
O19: Median Value: | T19: =MEDIAN(T5:T18) -> 205.30919 | U19: =MEDIAN(U5:U18) -> 39.300331 | V19: =MEDIAN(V5:V18) -> 278.04666
A20: x | O20: Implied Return (%): | T20: =T19/Share_Price-1 -> -0.11952488 | V20: =V19/Share_Price-1 -> 0.19241212
T22: Reference Points for Price Axis
U24: Price
A25: x | T25: High | U25: =MAX(V5:V18)*1.1 -> 360.08551 | W25: x
T26: Low | U26: =MIN(T5:T18)*0.9 -> 89.192792
A30: x

Sheet Integrity
C1: =Company_Name&" - "&MID(CELL("filename",A1),FIND("]",CELL("filename",A1))+1,255) -> Lowe's Companies, Inc. - Integrity
C3: Integrity
C4: Metric
C6: Model:
C7: Balance Sheet Check: | D7: =SUM(Model!F158:AG158)
C8: Base Case: | D8: =IF(Case_Scenario="Base","OK!","Check!") -> OK!
C9: Interest Expense: | D9: =IF(Model!C8="On","OK!","CHECK - OFF") -> OK!
C10: Valuation Date:
C12: Formatting:
C13: Valuation Sensitivity Tables: | D13: =SUM(Valuation!F92,Valuation!K92,Valuation!P92,Valuation!F151:F155,Valuation!L151:L155,Valuation!F227:F231,Valuation!L227:L231) -> 0.00024017932
C14: WACC Tables: | D14: =SUM(WACC!Q20,WACC!N33:N37) -> -0.00258654
C16: Font Toggles:
C17: Cover: | D17: =Cover!$Q$2 -> Working
C18: Revenue Build: | D18: ='Revenue Build'!$C$22 -> Working
C19: Model: | D19: =Model!$C$5 -> Working
C20: WACC | D20: =WACC!R5 -> Working
C21: Valuation: | D21: =Valuation!$R$2 -> Working
C23: Change Log
C24: Date | D24: Version | E24: Operator | F24: Revisions
C25: 44476 | D25: v01 | E25: Nate Latimer | F25: Top Down / Bottom Up toggle integration and Capital IQ comps sheet w/ ID Locator
C26: 44476 | D26: v02 | E26: Carson Shaner | F26: Formulas for EBIT/EBITDA margins on earnings sheets
C27: 44480 | D27: v03 | E27: Nate Latimer | F27: Historical driver adjustments to reflect Top Down / Bottom Up Toggle
C28: 44488 | D28: v04 | E28: Nate Latimer | F28: Bug fixes to model output, comps sheet and WACC Comps Relevered Beta
C29: 44489 | D29: v05 | E29: Lilianna Ruby | F29: Changed the year end driver in 2021 and 2022 to correctly pull operating margins
C30: 44491 | D30: v06 | E30: Lilianna Ruby | F30: Changed the first page to add 365 to your previous fiscal year
C31: 44496 | D31: v07 | E31: Carson Shaner | F31: Changed Model Output FCF formula, broke apart D&A for historical periods, added checks for EPS & EBITDA in Valuation sensitivity tables, added segment D&A breakdown, linked and fixed SOTP valuation
C32: 44503 | D32: v08 | E32: Lilianna Ruby | F32: Changed average of comps on valuation tab to average all peers not just the first one
C33: 44512 | D33: v09 | E33: Lilianna Ruby | F33: Rolled model forward to reflect 3Q'21. Also changed the multiples tab so the quarters roll forward and end on correct date.
C34: 44522 | D34: v10 | E34: Lilianna Ruby | F34: Fully fixed the multiples tab so it is automatic and fully functional. Also fixed definition of NTM_EPS and NTM_EBITDA
C35: 44582 | D35: v13 | E35: Carson Shaner | F35: Changed EPS, EBITDA, shares, tax rate, etc., to formulas so we do not have to hardcode them.
C36: 44584 | D36: v14 | E36: Lilianna Ruby | F36: Changed discount factor to mid year
... C47: 45581 | D47: v25 | E47: Conor McCabe | F47: Added font toggle to integrity tab for WACC tab. Formatted Comparables Tab.

Sheet Revenue Build
C1: =Company_Name&" - "&MID(CELL("filename",A1),FIND("]",CELL("filename",A1))+1,255)&": "&Case_Scenario&" Case" -> Lowe's Companies, Inc. - Revenue Build: Base Case
C2: =Cover!C2 -> $ in Millions Except Per Share Data
A4: x | C4: Segments
C6: =C30&" Methodology" -> Total Company Revenue Methodology
C7: Segment
C8: =C32&" Methodology" -> Home Improvement Retail Revenue Methodology
C9: =IF(Company_Rev_Methodology="Segment","Segment",IF(Company_Rev_Methodology="Activity-Based","Activity-Based",IF(Company_Rev_Methodology="Backlog","Backlog",IF(Company_Rev_Methodology="Mixed",D9,"--")))) -> Segment | D9: Backlog
C10: =C35&" Methodology" -> Segment 2 Revenue Methodology
C11: =IF(Company_Rev_Methodology="Segment","Segment",IF(Company_Rev_Methodology="Activity-Based","Activity-Based",IF(Company_Rev_Methodology="Backlog","Backlog",IF(Company_Rev_Methodology="Mixed",D11,"--")))) -> Segment | D11: Activity-Based
C12: =C38&" Methodology" -> Segment 3 Revenue Methodology
C13: =IF(Company_Rev_Methodology="Segment","Segment",IF(Company_Rev_Methodology="Activity-Based","Activity-Based",IF(Company_Rev_Methodology="Backlog","Backlog",IF(Company_Rev_Methodology="Mixed",D13,"--")))) -> Segment | D13: Segment
C14: =C41&" Methodology" -> Segment 4 Revenue Methodology
C15: =IF(Company_Rev_Methodology="Segment","Segment",IF(Company_Rev_Methodology="Activity-Based","Activity-Based",IF(Company_Rev_Methodology="Backlog","Backlog",IF(Company_Rev_Methodology="Mixed",D15,"--")))) -> Segment | D15: Segment
C16: =C44&" Methodology" -> Segment 5 Revenue Methodology
C17: =IF(Company_Rev_Methodology="Segment","Segment",IF(Company_Rev_Methodology="Activity-Based","Activity-Based",IF(Company_Rev_Methodology="Backlog","Backlog",IF(Company_Rev_Methodology="Mixed",D17,"--")))) -> Segment | D17: Segment
C18: =C47&" Methodology" -> Segment 6 Revenue Methodology
C19: =IF(Company_Rev_Methodology="Segment","Segment",IF(Company_Rev_Methodology="Activity-Based","Activity-Based",IF(Company_Rev_Methodology="Backlog","Backlog",IF(Company_Rev_Methodology="Mixed",D19,"--")))) -> Segment | D19: Segment
C21: Font Toggle
C22: Working
C24: Annual vs. Quarterly
C25: Quarterly
J26: 1 | O26: 2 | T26: 3 | Y26: 4 | AD26: 5 | AE26: 6 | AF26: 7 | AG26: 8
AI27: CAGR
A28: x | C28: Summary | F28: =Model!F$25 -> 1Q23 | G28: =Model!G$25 -> 2Q23 | H28: =Model!H$25 -> 3Q23 | I28: =Model!I$25 -> 4Q23 | J28: =Model!J$25 -> 2023 | K28: =Model!K$25 -> 1Q24 | L28: =Model!L$25 -> 2Q24 | M28: =Model!M$25 -> 3Q24 | ... AG28: =Model!AG$25 -> 2030e | AI28: Historical | AJ28: Projected
C30: Total Company Revenue | F30: ='Segment Analysis'!F7 -> 17360 | G30: ='Segment Analysis'!G7 -> 20888 | H30: ='Segment Analysis'!H7 -> 17415 | I30: ='Segment Analysis'!I7 -> 15646 | J30: ='Segment Analysis'!J7 -> 71309 | K30: ='Segment Analysis'!K7 -> 17741 | L30: ='Segment Analysis'!L7 -> 20992 | M30: ='Segment Analysis'!M7 -> 17388 | ... W30: ='Segment Analysis'!W7 -> 22918 | X30: =SUM(X32,X35,X38,X41,X44,X47,) -> 21772.1 | Y30: =SUM(U30:X30) -> 96682.1 | Z30: =SUM(Z32,Z35,Z38,Z41,Z44,Z47,) -> 25691.078 | AA30: =SUM(AA32,AA35,AA38,AA41,AA44,AA47,) -> 29287.829 | AB30: =SUM(AB32,AB35,AB38,AB41,AB44,AB47,) -> 25773.289 | AC30: =SUM(AC32,AC35,AC38,AC41,AC44,AC47,) -> 24484.625 | AD30: =SUM(Z30:AC30) -> 105236.82 | AE30: =SUM(AE32,AE35,AE38,AE41,AE44,AE47,) -> 107341.56 | AF30: =SUM(AF32,AF35,AF38,AF41,AF44,AF47,) -> 109488.39 | AG30: =SUM(AG32,AG35,AG38,AG41,AG44,AG47,) -> 111678.16 | AI30: =IFERROR((T30/J30)^(1/3)-1,"--") -> 0.079070221 | AJ30: =IFERROR((AG30/T30)^(1/5)-1,"--") -> 0.045044909
C31: =IF($C$25="Quarterly","% Growth QoQ","% Growth YoY") -> % Growth QoQ | G31: =IF($C$25="Annual",'Segment Analysis'!G172,'Segment Analysis'!G192) -> 0.20322581 | H31: =IF($C$25="Annual",'Segment Analysis'!H172,'Segment Analysis'!H192) -> -0.16626771 | I31: =IF($C$25="Annual",'Segment Analysis'!I172,'Segment Analysis'!I192) -> -0.1015791 | K31: =IF($C$25="Annual",'Segment Analysis'!K172,'Segment Analysis'!K192) -> 0.13390004 | L31: =IF($C$25="Annual",'Segment Analysis'!L172,'Segment Analysis'!L192) -> 0.18324784 | M31: =IF($C$25="Annual",'Segment Analysis'!M172,'Segment Analysis'!M192) -> -0.17168445 | N31: =IF($C$25="Annual",'Segment Analysis'!N172,'Segment Analysis'!N192) -> -0.078272372 | O31: =IF($C$25="Annual",'Segment Analysis'!O172,'Segment Analysis'!O192) -> 0 | P31: =IF($C$25="Annual",'Segment Analysis'!P172,'Segment Analysis'!P192) -> 0.2276159 | Q31: =IF($C$25="Annual",'Segment Analysis'!Q172,'Segment Analysis'!Q192) -> 0.3876493 | R31: =IF($C$25="Annual",'Segment Analysis'!R172,'Segment Analysis'!R192) -> -0.18288038 | ... W31: =IF($C$25="Annual",'Segment Analysis'!W172,'Segment Analysis'!W192) -> -0.16873413 | X31: =IFERROR(X30/W30-1,"--") -> -0.05 | Y31: =IFERROR(Y30/T30-1,"--") -> 0.079077424 | Z31: =IFERROR(Z30/X30-1,"--") -> 0.18 | AA31: =IFERROR(AA30/Z30-1,"--") -> 0.14 | AB31: =IFERROR(AB30/AA30-1,"--") -> -0.12 | AC31: =IFERROR(AC30/AB30-1,"--") -> -0.05 | AD31: =IFERROR(AD30/Y30-1,"--") -> 0.088482991 | AE31: =IFERROR(AE30/AD30-1,"--") -> 0.02 | AF31: =IFERROR(AF30/AE30-1,"--") -> 0.02 | AG31: =IFERROR(AG30/AF30-1,"--") -> 0.02
C32: ='Segment Analysis'!C8 -> Home Improvement Retail Revenue | F32: ='Segment Analysis'!F8 -> 17360 | G32: ='Segment Analysis'!G8 -> 20888 | H32: ='Segment Analysis'!H8 -> 17415 | I32: ='Segment Analysis'!I8 -> 15646 | J32: ='Segment Analysis'!J8 -> 71309 | K32: ='Segment Analysis'!K8 -> 17741 | L32: ='Segment Analysis'!L8 -> 20992 | M32: ='Segment Analysis'!M8 -> 17388 | ... W32: ='Segment Analysis'!W8 -> 22918 | X32: =IF(Segment1_Rev_Methodology="Segment",X53,IF(Segment1_Rev_Methodology="Activity-Based",X91,IF(Segment1_Rev_Methodology="Backlog",X165,"--"))) -> 21772.1 | Y32: =SUM(U32:X32) -> 96682.1 | Z32: =IF(Segment1_Rev_Methodology="Segment",Z53,IF(Segment1_Rev_Methodology="Activity-Based",Z91,IF(Segment1_Rev_Methodology="Backlog",Z165,"--"))) -> 25691.078 | AA32: =IF(Segment1_Rev_Methodology="Segment",AA53,IF(Segment1_Rev_Methodology="Activity-Based",AA91,IF(Segment1_Rev_Methodology="Backlog",AA165,"--"))) -> 29287.829 | AB32: =IF(Segment1_Rev_Methodology="Segment",AB53,IF(Segment1_Rev_Methodology="Activity-Based",AB91,IF(Segment1_Rev_Methodology="Backlog",AB165,"--"))) -> 25773.289 | AC32: =IF(Segment1_Rev_Methodology="Segment",AC53,IF(Segment1_Rev_Methodology="Activity-Based",AC91,IF(Segment1_Rev_Methodology="Backlog",AC165,"--"))) -> 24484.625 | AD32: =SUM(Z32:AC32) -> 105236.82 | AE32: =IF(Segment1_Rev_Methodology="Segment",AE53,IF(Segment1_Rev_Methodology="Activity-Based",AE91,IF(Segment1_Rev_Methodology="Backlog",AE165,"--"))) -> 107341.56 | AF32: =IF(Segment1_Rev_Methodology="Segment",AF53,IF(Segment1_Rev_Methodology="Activity-Based",AF91,IF(Segment1_Rev_Methodology="Backlog",AF165,"--"))) -> 109488.39 | AG32: =IF(Segment1_Rev_Methodology="Segment",AG53,IF(Segment1_Rev_Methodology="Activity-Based",AG91,IF(Segment1_Rev_Methodology="Backlog",AG165,"--"))) -> 111678.16 | AI32: =IFERROR((T32/J32)^(1/3)-1,"--") -> 0.079070221 | AJ32: =IFERROR((AG32/T32)^(1/5)-1,"--") -> 0.045044909
C33: =IF($C$25="Quarterly","% Growth QoQ","% Growth YoY") -> % Growth QoQ | G33: =IF($C$25="Annual",'Segment Analysis'!G173,'Segment Analysis'!G193) -> 0.20322581 | H33: =IF($C$25="Annual",'Segment Analysis'!H173,'Segment Analysis'!H193) -> -0.16626771 | I33: =IF($C$25="Annual",'Segment Analysis'!I173,'Segment Analysis'!I193) -> -0.1015791 | K33: =IF($C$25="Annual",'Segment Analysis'!K173,'Segment Analysis'!K193) -> 0.13390004 | L33: =IF($C$25="Annual",'Segment Analysis'!L173,'Segment Analysis'!L193) -> 0.18324784 | M33: =IF($C$25="Annual",'Segment Analysis'!M173,'Segment Analysis'!M193) -> -0.17168445 | N33: =IF($C$25="Annual",'Segment Analysis'!N173,'Segment Analysis'!N193) -> -0.078272372 | O33: =IF($C$25="Annual",'Segment Analysis'!O173,'Segment Analysis'!O193) -> 0 | P33: =IF($C$25="Annual",'Segment Analysis'!P173,'Segment Analysis'!P193) -> 0.2276159 | Q33: =IF($C$25="Annual",'Segment Analysis'!Q173,'Segment Analysis'!Q193) -> 0.3876493 | R33: =IF($C$25="Annual",'Segment Analysis'!R173,'Segment Analysis'!R193) -> -0.18288038 | ... W33: =IF($C$25="Annual",'Segment Analysis'!W173,'Segment Analysis'!W193) -> -0.16873413 | X33: =IFERROR(X32/W32-1,"--") -> -0.05 | Y33: =IFERROR(Y32/T32-1,"--") -> 0.079077424 | Z33: =IFERROR(Z32/X32-1,"--") -> 0.18 | AA33: =IFERROR(AA32/Z32-1,"--") -> 0.14 | AB33: =IFERROR(AB32/AA32-1,"--") -> -0.12 | AC33: =IFERROR(AC32/AB32-1,"--") -> -0.05 | AD33: =IFERROR(AD32/Y32-1,"--") -> 0.088482991 | AE33: =IFERROR(AE32/AD32-1,"--") -> 0.02 | AF33: =IFERROR(AF32/AE32-1,"--") -> 0.02 | AG33: =IFERROR(AG32/AF32-1,"--") -> 0.02
C34: % of Total Revenue | F34: ='Segment Analysis'!F16 -> 1 | G34: ='Segment Analysis'!G16 -> 1 | H34: ='Segment Analysis'!H16 -> 1 | I34: ='Segment Analysis'!I16 -> 1 | J34: ='Segment Analysis'!J16 -> 1 | K34: ='Segment Analysis'!K16 -> 1 | L34: ='Segment Analysis'!L16 -> 1 | M34: ='Segment Analysis'!M16 -> 1 | ... W34: ='Segment Analysis'!W16 -> 1 | X34: =X32/X$30 -> 1 | Y34: =Y32/Y$30 -> 1 | Z34: =Z32/Z$30 -> 1 | AA34: =AA32/AA$30 -> 1 | AB34: =AB32/AB$30 -> 1 | AC34: =AC32/AC$30 -> 1 | AD34: =AD32/AD$30 -> 1 | AE34: =AE32/AE$30 -> 1 | ... AG34: =AG32/AG$30 -> 1
C35: ='Segment Analysis'!C9 -> Segment 2 Revenue | F35: ='Segment Analysis'!F9 -> 0 | G35: ='Segment Analysis'!G9 -> 0 | H35: ='Segment Analysis'!H9 -> 0 | I35: ='Segment Analysis'!I9 -> 0 | J35: ='Segment Analysis'!J9 -> 0 | K35: ='Segment Analysis'!K9 -> 0 | L35: ='Segment Analysis'!L9 -> 0 | M35: ='Segment Analysis'!M9 -> 0 | ... W35: ='Segment Analysis'!W9 -> 0 | X35: =IF(Segment2_Rev_Methodology="Segment",X59,IF(Segment2_Rev_Methodology="Activity-Based",X103,IF(Segment2_Rev_Methodology="Backlog",X177,"--"))) -> 0 | Y35: =SUM(U35:X35) -> 0 | Z35: =IF(Segment2_Rev_Methodology="Segment",Z59,IF(Segment2_Rev_Methodology="Activity-Based",Z103,IF(Segment2_Rev_Methodology="Backlog",Z177,"--"))) -> 0 | AA35: =IF(Segment2_Rev_Methodology="Segment",AA59,IF(Segment2_Rev_Methodology="Activity-Based",AA103,IF(Segment2_Rev_Methodology="Backlog",AA177,"--"))) -> 0 | AB35: =IF(Segment2_Rev_Methodology="Segment",AB59,IF(Segment2_Rev_Methodology="Activity-Based",AB103,IF(Segment2_Rev_Methodology="Backlog",AB177,"--"))) -> 0 | AC35: =IF(Segment2_Rev_Methodology="Segment",AC59,IF(Segment2_Rev_Methodology="Activity-Based",AC103,IF(Segment2_Rev_Methodology="Backlog",AC177,"--"))) -> 0 | AD35: =SUM(Z35:AC35) -> 0 | AE35: =IF(Segment2_Rev_Methodology="Segment",AE59,IF(Segment2_Rev_Methodology="Activity-Based",AE103,IF(Segment2_Rev_Methodology="Backlog",AE177,"--"))) -> 0 | AF35: =IF(Segment2_Rev_Methodology="Segment",AF59,IF(Segment2_Rev_Methodology="Activity-Based",AF103,IF(Segment2_Rev_Methodology="Backlog",AF177,"--"))) -> 0 | AG35: =IF(Segment2_Rev_Methodology="Segment",AG59,IF(Segment2_Rev_Methodology="Activity-Based",AG103,IF(Segment2_Rev_Methodology="Backlog",AG177,"--"))) -> 0 | AI35: =IFERROR((T35/J35)^(1/3)-1,"--") -> -- | AJ35: =IFERROR((AG35/T35)^(1/5)-1,"--") -> --
C36: % Growth | G36: =IF($C$25="Annual",'Segment Analysis'!G174,'Segment Analysis'!G194) -> N/A | H36: =IF($C$25="Annual",'Segment Analysis'!H174,'Segment Analysis'!H194) -> N/A | I36: =IF($C$25="Annual",'Segment Analysis'!I174,'Segment Analysis'!I194) -> N/A | K36: =IF($C$25="Annual",'Segment Analysis'!K174,'Segment Analysis'!K194) -> N/A | L36: =IF($C$25="Annual",'Segment Analysis'!L174,'Segment Analysis'!L194) -> N/A | M36: =IF($C$25="Annual",'Segment Analysis'!M174,'Segment Analysis'!M194) -> N/A | N36: =IF($C$25="Annual",'Segment Analysis'!N174,'Segment Analysis'!N194) -> N/A | O36: ='Segment Analysis'!O174 -> N/A | P36: =IF($C$25="Annual",'Segment Analysis'!P174,'Segment Analysis'!P194) -> N/A | Q36: =IF($C$25="Annual",'Segment Analysis'!Q174,'Segment Analysis'!Q194) -> N/A | R36: =IF($C$25="Annual",'Segment Analysis'!R174,'Segment Analysis'!R194) -> N/A | S36: =IF($C$25="Annual",'Segment Analysis'!S174,'Segment Analysis'!S194) -> N/A | T36: ='Segment Analysis'!T174 -> N/A | U36: =IF($C$25="Annual",'Segment Analysis'!U174,'Segment Analysis'!U194) -> N/A | V36: =IF($C$25="Annual",'Segment Analysis'!V174,'Segment Analysis'!V194) -> N/A | W36: =IF($C$25="Annual",'Segment Analysis'!W174,'Segment Analysis'!W194) -> N/A | X36: =IFERROR(X35/W35-1,"--") -> -- | Y36: =IFERROR(Y35/T35-1,"--") -> -- | Z36: =IFERROR(Z35/X35-1,"--") -> -- | AA36: =IFERROR(AA35/Z35-1,"--") -> -- | AB36: =IFERROR(AB35/AA35-1,"--") -> -- | AC36: =IFERROR(AC35/AB35-1,"--") -> -- | AD36: =IFERROR(AD35/Y35-1,"--") -> -- | AE36: =IFERROR(AE35/AD35-1,"--") -> -- | AF36: =IFERROR(AF35/AE35-1,"--") -> -- | AG36: =IFERROR(AG35/AF35-1,"--") -> --
C37: % of Total Revenue | F37: ='Segment Analysis'!F17 -> 0 | G37: ='Segment Analysis'!G17 -> 0 | H37: ='Segment Analysis'!H17 -> 0 | I37: ='Segment Analysis'!I17 -> 0 | J37: ='Segment Analysis'!J17 -> 0 | K37: ='Segment Analysis'!K17 -> 0 | L37: ='Segment Analysis'!L17 -> 0 | M37: ='Segment Analysis'!M17 -> 0 | ... W37: ='Segment Analysis'!W17 -> 0 | X37: =X35/X$30 -> 0 | Y37: =Y35/Y$30 | Z37: =Z35/Z$30 | AA37: =AA35/AA$30 | AB37: =AB35/AB$30 | AC37: =AC35/AC$30 | AD37: =AD35/AD$30 | AE37: =AE35/AE$30 | ... AG37: =AG35/AG$30
C38: ='Segment Analysis'!C10 -> Segment 3 Revenue | F38: ='Segment Analysis'!F10 -> 0 | G38: ='Segment Analysis'!G10 -> 0 | H38: ='Segment Analysis'!H10 -> 0 | I38: ='Segment Analysis'!I10 -> 0 | J38: ='Segment Analysis'!J10 -> 0 | K38: ='Segment Analysis'!K10 -> 0 | L38: ='Segment Analysis'!L10 -> 0 | M38: ='Segment Analysis'!M10 -> 0 | ... W38: ='Segment Analysis'!W10 -> 0 | X38: =IF(Segment3_Rev_Methodology="Segment",X65,IF(Segment3_Rev_Methodology="Activity-Based",X115,IF(Segment3_Rev_Methodology="Backlog",X189,"--"))) -> 0 | Y38: =SUM(U38:X38) -> 0 | Z38: =IF(Segment3_Rev_Methodology="Segment",Z65,IF(Segment3_Rev_Methodology="Activity-Based",Z115,IF(Segment3_Rev_Methodology="Backlog",Z189,"--"))) -> 0 | AA38: =IF(Segment3_Rev_Methodology="Segment",AA65,IF(Segment3_Rev_Methodology="Activity-Based",AA115,IF(Segment3_Rev_Methodology="Backlog",AA189,"--"))) -> 0 | AB38: =IF(Segment3_Rev_Methodology="Segment",AB65,IF(Segment3_Rev_Methodology="Activity-Based",AB115,IF(Segment3_Rev_Methodology="Backlog",AB189,"--"))) -> 0 | AC38: =IF(Segment3_Rev_Methodology="Segment",AC65,IF(Segment3_Rev_Methodology="Activity-Based",AC115,IF(Segment3_Rev_Methodology="Backlog",AC189,"--"))) -> 0 | AD38: =SUM(Z38:AC38) -> 0 | AE38: =IF(Segment3_Rev_Methodology="Segment",AE65,IF(Segment3_Rev_Methodology="Activity-Based",AE115,IF(Segment3_Rev_Methodology="Backlog",AE189,"--"))) -> 0 | AF38: =IF(Segment3_Rev_Methodology="Segment",AF65,IF(Segment3_Rev_Methodology="Activity-Based",AF115,IF(Segment3_Rev_Methodology="Backlog",AF189,"--"))) -> 0 | AG38: =IF(Segment3_Rev_Methodology="Segment",AG65,IF(Segment3_Rev_Methodology="Activity-Based",AG115,IF(Segment3_Rev_Methodology="Backlog",AG189,"--"))) -> 0 | AI38: =IFERROR((T38/J38)^(1/3)-1,"--") -> -- | AJ38: =IFERROR((AG38/T38)^(1/5)-1,"--") -> --
C39: % Growth | G39: =IF($C$25="Annual",'Segment Analysis'!G175,'Segment Analysis'!G195) -> N/A | H39: =IF($C$25="Annual",'Segment Analysis'!H175,'Segment Analysis'!H195) -> N/A | I39: =IF($C$25="Annual",'Segment Analysis'!I175,'Segment Analysis'!I195) -> N/A | K39: =IF($C$25="Annual",'Segment Analysis'!K175,'Segment Analysis'!K195) -> N/A | L39: =IF($C$25="Annual",'Segment Analysis'!L175,'Segment Analysis'!L195) -> N/A | M39: =IF($C$25="Annual",'Segment Analysis'!M175,'Segment Analysis'!M195) -> N/A | N39: =IF($C$25="Annual",'Segment Analysis'!N175,'Segment Analysis'!N195) -> N/A | O39: =IF($C$25="Annual",'Segment Analysis'!O175,'Segment Analysis'!O195) -> 0 | P39: =IF($C$25="Annual",'Segment Analysis'!P175,'Segment Analysis'!P195) -> N/A | Q39: =IF($C$25="Annual",'Segment Analysis'!Q175,'Segment Analysis'!Q195) -> N/A | R39: =IF($C$25="Annual",'Segment Analysis'!R175,'Segment Analysis'!R195) -> N/A | ... W39: =IF($C$25="Annual",'Segment Analysis'!W175,'Segment Analysis'!W195) -> N/A | X39: =IFERROR(X38/W38-1,"--") -> -- | Y39: =IFERROR(Y38/T38-1,"--") -> -- | Z39: =IFERROR(Z38/X38-1,"--") -> -- | AA39: =IFERROR(AA38/Z38-1,"--") -> -- | AB39: =IFERROR(AB38/AA38-1,"--") -> -- | AC39: =IFERROR(AC38/AB38-1,"--") -> -- | AD39: =IFERROR(AD38/Y38-1,"--") -> -- | AE39: =IFERROR(AE38/AD38-1,"--") -> -- | AF39: =IFERROR(AF38/AE38-1,"--") -> -- | AG39: =IFERROR(AG38/AF38-1,"--") -> --
C40: % of Total Revenue | F40: ='Segment Analysis'!F18 -> 0 | G40: ='Segment Analysis'!G18 -> 0 | H40: ='Segment Analysis'!H18 -> 0 | I40: ='Segment Analysis'!I18 -> 0 | J40: ='Segment Analysis'!J18 -> 0 | K40: ='Segment Analysis'!K18 -> 0 | L40: ='Segment Analysis'!L18 -> 0 | M40: ='Segment Analysis'!M18 -> 0 | ... W40: ='Segment Analysis'!W18 -> 0 | X40: =X38/X$30 -> 0 | Y40: =Y38/Y$30 | Z40: =Z38/Z$30 | AA40: =AA38/AA$30 | AB40: =AB38/AB$30 | AC40: =AC38/AC$30 | AD40: =AD38/AD$30 | AE40: =AE38/AE$30 | ... AG40: =AG38/AG$30
C41: ='Segment Analysis'!C11 -> Segment 4 Revenue | F41: ='Segment Analysis'!F11 -> 0 | G41: ='Segment Analysis'!G11 -> 0 | H41: ='Segment Analysis'!H11 -> 0 | I41: ='Segment Analysis'!I11 -> 0 | J41: ='Segment Analysis'!J11 -> 0 | K41: ='Segment Analysis'!K11 -> 0 | L41: ='Segment Analysis'!L11 -> 0 | M41: ='Segment Analysis'!M11 -> 0 | ... W41: ='Segment Analysis'!W11 -> 0 | X41: =IF(Segment4_Rev_Methodology="Segment",X71,IF(Segment4_Rev_Methodology="Activity-Based",X127,IF(Segment4_Rev_Methodology="Backlog",X201,"--"))) -> 0 | Y41: =SUM(U41:X41) -> 0 | Z41: =IF(Segment4_Rev_Methodology="Segment",Z71,IF(Segment4_Rev_Methodology="Activity-Based",Z127,IF(Segment4_Rev_Methodology="Backlog",Z201,"--"))) -> 0 | AA41: =IF(Segment4_Rev_Methodology="Segment",AA71,IF(Segment4_Rev_Methodology="Activity-Based",AA127,IF(Segment4_Rev_Methodology="Backlog",AA201,"--"))) -> 0 | AB41: =IF(Segment4_Rev_Methodology="Segment",AB71,IF(Segment4_Rev_Methodology="Activity-Based",AB127,IF(Segment4_Rev_Methodology="Backlog",AB201,"--"))) -> 0 | AC41: =IF(Segment4_Rev_Methodology="Segment",AC71,IF(Segment4_Rev_Methodology="Activity-Based",AC127,IF(Segment4_Rev_Methodology="Backlog",AC201,"--"))) -> 0 | AD41: =SUM(Z41:AC41) -> 0 | AE41: =IF(Segment4_Rev_Methodology="Segment",AE71,IF(Segment4_Rev_Methodology="Activity-Based",AE127,IF(Segment4_Rev_Methodology="Backlog",AE201,"--"))) -> 0 | AF41: =IF(Segment4_Rev_Methodology="Segment",AF71,IF(Segment4_Rev_Methodology="Activity-Based",AF127,IF(Segment4_Rev_Methodology="Backlog",AF201,"--"))) -> 0 | AG41: =IF(Segment4_Rev_Methodology="Segment",AG71,IF(Segment4_Rev_Methodology="Activity-Based",AG127,IF(Segment4_Rev_Methodology="Backlog",AG201,"--"))) -> 0 | AI41: =IFERROR((T41/J41)^(1/3)-1,"--") -> -- | AJ41: =IFERROR((AG41/T41)^(1/5)-1,"--") -> --
C42: % Growth | G42: =IF($C$25="Annual",'Segment Analysis'!G176,'Segment Analysis'!G196) -> N/A | H42: =IF($C$25="Annual",'Segment Analysis'!H176,'Segment Analysis'!H196) -> N/A | I42: =IF($C$25="Annual",'Segment Analysis'!I176,'Segment Analysis'!I196) -> N/A | K42: =IF($C$25="Annual",'Segment Analysis'!K176,'Segment Analysis'!K196) -> N/A | L42: =IF($C$25="Annual",'Segment Analysis'!L176,'Segment Analysis'!L196) -> N/A | M42: =IF($C$25="Annual",'Segment Analysis'!M176,'Segment Analysis'!M196) -> N/A | N42: =IF($C$25="Annual",'Segment Analysis'!N176,'Segment Analysis'!N196) -> N/A | O42: =IF($C$25="Annual",'Segment Analysis'!O176,'Segment Analysis'!O196) -> 0 | P42: =IF($C$25="Annual",'Segment Analysis'!P176,'Segment Analysis'!P196) -> N/A | Q42: =IF($C$25="Annual",'Segment Analysis'!Q176,'Segment Analysis'!Q196) -> N/A | R42: =IF($C$25="Annual",'Segment Analysis'!R176,'Segment Analysis'!R196) -> N/A | ... W42: =IF($C$25="Annual",'Segment Analysis'!W176,'Segment Analysis'!W196) -> N/A | X42: =IFERROR(X41/W41-1,"--") -> -- | Y42: =IFERROR(Y41/T41-1,"--") -> -- | Z42: =IFERROR(Z41/X41-1,"--") -> -- | AA42: =IFERROR(AA41/Z41-1,"--") -> -- | AB42: =IFERROR(AB41/AA41-1,"--") -> -- | AC42: =IFERROR(AC41/AB41-1,"--") -> -- | AD42: =IFERROR(AD41/Y41-1,"--") -> -- | AE42: =IFERROR(AE41/AD41-1,"--") -> -- | AF42: =IFERROR(AF41/AE41-1,"--") -> -- | AG42: =IFERROR(AG41/AF41-1,"--") -> --
C43: % of Total Revenue | F43: ='Segment Analysis'!F19 -> 0 | G43: ='Segment Analysis'!G19 -> 0 | H43: ='Segment Analysis'!H19 -> 0 | I43: ='Segment Analysis'!I19 -> 0 | J43: ='Segment Analysis'!J19 -> 0 | K43: ='Segment Analysis'!K19 -> 0 | L43: ='Segment Analysis'!L19 -> 0 | M43: ='Segment Analysis'!M19 -> 0 | ... W43: ='Segment Analysis'!W19 -> 0 | X43: =X41/X$30 -> 0 | Y43: =Y41/Y$30 | Z43: =Z41/Z$30 | AA43: =AA41/AA$30 | AB43: =AB41/AB$30 | AC43: =AC41/AC$30 | AD43: =AD41/AD$30 | AE43: =AE41/AE$30 | ... AG43: =AG41/AG$30
C44: ='Segment Analysis'!C12 -> Segment 5 Revenue | F44: ='Segment Analysis'!F12 -> 0 | G44: ='Segment Analysis'!G12 -> 0 | H44: ='Segment Analysis'!H12 -> 0 | I44: ='Segment Analysis'!I12 -> 0 | J44: ='Segment Analysis'!J12 -> 0 | K44: ='Segment Analysis'!K12 -> 0 | L44: ='Segment Analysis'!L12 -> 0 | M44: ='Segment Analysis'!M12 -> 0 | ... W44: ='Segment Analysis'!W12 -> 0 | X44: =IF(Segment5_Rev_Methodology="Segment",X77,IF(Segment5_Rev_Methodology="Activity-Based",X139,IF(Segment5_Rev_Methodology="Backlog",X213,"--"))) -> 0 | Y44: =SUM(U44:X44) -> 0 | Z44: =IF(Segment5_Rev_Methodology="Segment",Z77,IF(Segment5_Rev_Methodology="Activity-Based",Z139,IF(Segment5_Rev_Methodology="Backlog",Z213,"--"))) -> 0 | AA44: =IF(Segment5_Rev_Methodology="Segment",AA77,IF(Segment5_Rev_Methodology="Activity-Based",AA139,IF(Segment5_Rev_Methodology="Backlog",AA213,"--"))) -> 0 | AB44: =IF(Segment5_Rev_Methodology="Segment",AB77,IF(Segment5_Rev_Methodology="Activity-Based",AB139,IF(Segment5_Rev_Methodology="Backlog",AB213,"--"))) -> 0 | AC44: =IF(Segment5_Rev_Methodology="Segment",AC77,IF(Segment5_Rev_Methodology="Activity-Based",AC139,IF(Segment5_Rev_Methodology="Backlog",AC213,"--"))) -> 0 | AD44: =SUM(Z44:AC44) -> 0 | AE44: =IF(Segment5_Rev_Methodology="Segment",AE77,IF(Segment5_Rev_Methodology="Activity-Based",AE139,IF(Segment5_Rev_Methodology="Backlog",AE213,"--"))) -> 0 | AF44: =IF(Segment5_Rev_Methodology="Segment",AF77,IF(Segment5_Rev_Methodology="Activity-Based",AF139,IF(Segment5_Rev_Methodology="Backlog",AF213,"--"))) -> 0 | AG44: =IF(Segment5_Rev_Methodology="Segment",AG77,IF(Segment5_Rev_Methodology="Activity-Based",AG139,IF(Segment5_Rev_Methodology="Backlog",AG213,"--"))) -> 0 | AI44: =IFERROR((T44/J44)^(1/3)-1,"--") -> -- | AJ44: =IFERROR((AG44/T44)^(1/5)-1,"--") -> --
C45: % Growth | G45: =IF($C$25="Annual",'Segment Analysis'!G177,'Segment Analysis'!G197) -> N/A | H45: =IF($C$25="Annual",'Segment Analysis'!H177,'Segment Analysis'!H197) -> N/A | I45: =IF($C$25="Annual",'Segment Analysis'!I177,'Segment Analysis'!I197) -> N/A | K45: =IF($C$25="Annual",'Segment Analysis'!K177,'Segment Analysis'!K197) -> N/A | L45: =IF($C$25="Annual",'Segment Analysis'!L177,'Segment Analysis'!L197) -> N/A | M45: =IF($C$25="Annual",'Segment Analysis'!M177,'Segment Analysis'!M197) -> N/A | N45: =IF($C$25="Annual",'Segment Analysis'!N177,'Segment Analysis'!N197) -> N/A | O45: =IF($C$25="Annual",'Segment Analysis'!O177,'Segment Analysis'!O197) -> 0 | P45: =IF($C$25="Annual",'Segment Analysis'!P177,'Segment Analysis'!P197) -> N/A | Q45: =IF($C$25="Annual",'Segment Analysis'!Q177,'Segment Analysis'!Q197) -> N/A | R45: =IF($C$25="Annual",'Segment Analysis'!R177,'Segment Analysis'!R197) -> N/A | ... W45: =IF($C$25="Annual",'Segment Analysis'!W177,'Segment Analysis'!W197) -> N/A | X45: =IFERROR(X44/W44-1,"--") -> -- | Y45: =IFERROR(Y44/T44-1,"--") -> -- | Z45: =IFERROR(Z44/X44-1,"--") -> -- | AA45: =IFERROR(AA44/Z44-1,"--") -> -- | AB45: =IFERROR(AB44/AA44-1,"--") -> -- | AC45: =IFERROR(AC44/AB44-1,"--") -> -- | AD45: =IFERROR(AD44/Y44-1,"--") -> -- | AE45: =IFERROR(AE44/AD44-1,"--") -> -- | AF45: =IFERROR(AF44/AE44-1,"--") -> -- | AG45: =IFERROR(AG44/AF44-1,"--") -> --
C46: % of Total Revenue | F46: ='Segment Analysis'!F20 -> 0 | G46: ='Segment Analysis'!G20 -> 0 | H46: ='Segment Analysis'!H20 -> 0 | I46: ='Segment Analysis'!I20 -> 0 | J46: ='Segment Analysis'!J20 -> 0 | K46: ='Segment Analysis'!K20 -> 0 | L46: ='Segment Analysis'!L20 -> 0 | M46: ='Segment Analysis'!M20 -> 0 | ... W46: ='Segment Analysis'!W20 -> 0 | X46: =X44/X$30 -> 0 | Y46: =Y44/Y$30 | Z46: =Z44/Z$30 | AA46: =AA44/AA$30 | AB46: =AB44/AB$30 | AC46: =AC44/AC$30 | AD46: =AD44/AD$30 | AE46: =AE44/AE$30 | ... AG46: =AG44/AG$30
C47: ='Segment Analysis'!C13 -> Segment 6 Revenue | F47: ='Segment Analysis'!F13 -> 0 | G47: ='Segment Analysis'!G13 -> 0 | H47: ='Segment Analysis'!H13 -> 0 | I47: ='Segment Analysis'!I13 -> 0 | J47: ='Segment Analysis'!J13 -> 0 | K47: ='Segment Analysis'!K13 -> 0 | L47: ='Segment Analysis'!L13 -> 0 | M47: ='Segment Analysis'!M13 -> 0 | ... W47: ='Segment Analysis'!W13 -> 0 | X47: =IF(Segment6_Rev_Methodology="Segment",X83,IF(Segment6_Rev_Methodology="Activity-Based",X151,IF(Segment6_Rev_Methodology="Backlog",X225,"--"))) -> 0 | Y47: =SUM(U47:X47) -> 0 | Z47: =IF(Segment6_Rev_Methodology="Segment",Z83,IF(Segment6_Rev_Methodology="Activity-Based",Z151,IF(Segment6_Rev_Methodology="Backlog",Z225,"--"))) -> 0 | AA47: =IF(Segment6_Rev_Methodology="Segment",AA83,IF(Segment6_Rev_Methodology="Activity-Based",AA151,IF(Segment6_Rev_Methodology="Backlog",AA225,"--"))) -> 0 | AB47: =IF(Segment6_Rev_Methodology="Segment",AB83,IF(Segment6_Rev_Methodology="Activity-Based",AB151,IF(Segment6_Rev_Methodology="Backlog",AB225,"--"))) -> 0 | AC47: =IF(Segment6_Rev_Methodology="Segment",AC83,IF(Segment6_Rev_Methodology="Activity-Based",AC151,IF(Segment6_Rev_Methodology="Backlog",AC225,"--"))) -> 0 | AD47: =SUM(Z47:AC47) -> 0 | AE47: =IF(Segment6_Rev_Methodology="Segment",AE83,IF(Segment6_Rev_Methodology="Activity-Based",AE151,IF(Segment6_Rev_Methodology="Backlog",AE225,"--"))) -> 0 | AF47: =IF(Segment6_Rev_Methodology="Segment",AF83,IF(Segment6_Rev_Methodology="Activity-Based",AF151,IF(Segment6_Rev_Methodology="Backlog",AF225,"--"))) -> 0 | AG47: =IF(Segment6_Rev_Methodology="Segment",AG83,IF(Segment6_Rev_Methodology="Activity-Based",AG151,IF(Segment6_Rev_Methodology="Backlog",AG225,"--"))) -> 0 | AI47: =IFERROR((T47/J47)^(1/3)-1,"--") -> -- | AJ47: =IFERROR((AG47/T47)^(1/5)-1,"--") -> --
C48: % Growth | G48: =IF($C$25="Annual",'Segment Analysis'!G198,'Segment Analysis'!G198) -> N/A | H48: =IF($C$25="Annual",'Segment Analysis'!H198,'Segment Analysis'!H198) -> N/A | I48: =IF($C$25="Annual",'Segment Analysis'!I198,'Segment Analysis'!I198) -> N/A | K48: =IF($C$25="Annual",'Segment Analysis'!K198,'Segment Analysis'!K198) -> N/A | L48: =IF($C$25="Annual",'Segment Analysis'!L198,'Segment Analysis'!L198) -> N/A | M48: =IF($C$25="Annual",'Segment Analysis'!M198,'Segment Analysis'!M198) -> N/A | N48: =IF($C$25="Annual",'Segment Analysis'!N198,'Segment Analysis'!N198) -> N/A | O48: =IF($C$25="Annual",'Segment Analysis'!O198,'Segment Analysis'!O198) -> 0 | P48: =IF($C$25="Annual",'Segment Analysis'!P198,'Segment Analysis'!P198) -> N/A | Q48: =IF($C$25="Annual",'Segment Analysis'!Q198,'Segment Analysis'!Q198) -> N/A | R48: =IF($C$25="Annual",'Segment Analysis'!R198,'Segment Analysis'!R198) -> N/A | ... W48: =IF($C$25="Annual",'Segment Analysis'!W198,'Segment Analysis'!W198) -> N/A | X48: =IFERROR(X47/W47-1,"--") -> -- | Y48: =IFERROR(Y47/T47-1,"--") -> -- | Z48: =IFERROR(Z47/X47-1,"--") -> -- | AA48: =IFERROR(AA47/Z47-1,"--") -> -- | AB48: =IFERROR(AB47/AA47-1,"--") -> -- | AC48: =IFERROR(AC47/AB47-1,"--") -> -- | AD48: =IFERROR(AD47/Y47-1,"--") -> -- | AE48: =IFERROR(AE47/AD47-1,"--") -> -- | AF48: =IFERROR(AF47/AE47-1,"--") -> -- | AG48: =IFERROR(AG47/AF47-1,"--") -> --
C49: % of Total Revenue | F49: ='Segment Analysis'!F21 -> 0 | G49: ='Segment Analysis'!G21 -> 0 | H49: ='Segment Analysis'!H21 -> 0 | I49: ='Segment Analysis'!I21 -> 0 | J49: ='Segment Analysis'!J21 -> 0 | K49: ='Segment Analysis'!K21 -> 0 | L49: ='Segment Analysis'!L21 -> 0 | M49: ='Segment Analysis'!M21 -> 0 | ... W49: ='Segment Analysis'!W21 -> 0 | X49: =X47/X$30 -> 0 | Y49: =Y47/Y$30 | Z49: =Z47/Z$30 | AA49: =AA47/AA$30 | AB49: =AB47/AB$30 | AC49: =AC47/AC$30 | AD49: =AD47/AD$30 | AE49: =AE47/AE$30 | ... AG49: =AG47/AG$30
A51: x | C51: Growth Rate | F51: =F$28 -> 1Q23 | G51: =G$28 -> 2Q23 | H51: =H$28 -> 3Q23 | I51: =I$28 -> 4Q23 | J51: =J$28 -> 2023 | K51: =K$28 -> 1Q24 | L51: =L$28 -> 2Q24 | M51: =M$28 -> 3Q24 | ... AG51: =AG$28 -> 2030e | AH51: x
C53: =C32 -> Home Improvement Retail Revenue | F53: =F32 -> 17360 | G53: =G32 -> 20888 | H53: =H32 -> 17415 | I53: =I32 -> 15646 | J53: =J32 -> 71309 | K53: =K32 -> 17741 | L53: =L32 -> 20992 | M53: =M32 -> 17388 | ... W53: =W32 -> 22918 | X53: =IF($C$25="Quarterly",W53*(1+X54),S53*(1+X54)) -> 21772.1 | Y53: =SUM(U53:X53) -> 96682.1 | Z53: =IF($C$25="Quarterly",X53*(1+Z54),U53*(1+Z54)) -> 25691.078 | AA53: =IF($C$25="Quarterly",Z53*(1+AA54),V53*(1+AA54)) -> 29287.829 | AB53: =IF($C$25="Quarterly",AA53*(1+AB54),W53*(1+AB54)) -> 25773.289 | AC53: =IF($C$25="Quarterly",AB53*(1+AC54),X53*(1+AC54)) -> 24484.625 | AD53: =SUM(Z53:AC53) -> 105236.82 | AE53: =AD53*(1+AE54) -> 107341.56 | AF53: =AE53*(1+AF54) -> 109488.39 | AG53: =AF53*(1+AG54) -> 111678.16
C54: =IF($C$25="Quarterly","% Growth QoQ","% Growth YoY") -> % Growth QoQ | G54: =G33 -> 0.20322581 | H54: =H33 -> -0.16626771 | I54: =I33 -> -0.1015791 | J54: =J33 | K54: =K33 -> 0.13390004 | L54: =L33 -> 0.18324784 | M54: =M33 -> -0.17168445 | N54: =N33 -> -0.078272372 | ... W54: =W33 -> -0.16873413 | X54: =IF(Case_Scenario="Bull",X55,IF(Case_Scenario="Base",X56,IF(Case_Scenario="bear",X57,"N/A"))) -> -0.05 | Z54: =IF(Case_Scenario="Bull",Z55,IF(Case_Scenario="Base",Z56,IF(Case_Scenario="bear",Z57,"N/A"))) -> 0.18 | AA54: =IF(Case_Scenario="Bull",AA55,IF(Case_Scenario="Base",AA56,IF(Case_Scenario="bear",AA57,"N/A"))) -> 0.14 | AB54: =IF(Case_Scenario="Bull",AB55,IF(Case_Scenario="Base",AB56,IF(Case_Scenario="bear",AB57,"N/A"))) -> -0.12 | AC54: =IF(Case_Scenario="Bull",AC55,IF(Case_Scenario="Base",AC56,IF(Case_Scenario="bear",AC57,"N/A"))) -> -0.05 | AE54: =IF(Case_Scenario="Bull",AE55,IF(Case_Scenario="Base",AE56,IF(Case_Scenario="bear",AE57,"N/A"))) -> 0.02 | AF54: =IF(Case_Scenario="Bull",AF55,IF(Case_Scenario="Base",AF56,IF(Case_Scenario="bear",AF57,"N/A"))) -> 0.02 | AG54: =IF(Case_Scenario="Bull",AG55,IF(Case_Scenario="Base",AG56,IF(Case_Scenario="bear",AG57,"N/A"))) -> 0.02
C55: Bull Case | X55: -0.05 | Z55: 0.12 | AA55: 0.17 | AB55: -0.1 | AC55: -0.05 | AE55: 0.02 | AF55: 0.02 | AG55: 0.02
C56: Base Case | X56: -0.05 | Z56: 0.18 | AA56: 0.14 | AB56: -0.12 | AC56: -0.05 | AE56: 0.02 | AF56: 0.02 | AG56: 0.02
C57: Bear Case | X57: -0.05 | Z57: 0.12 | AA57: 0.1 | AB57: -0.05 | AC57: -0.05 | AE57: 0.02 | AF57: 0.03 | AG57: 0.03
A59: x | C59: =C35 -> Segment 2 Revenue | F59: =F35 -> 0 | G59: =G35 | H59: =H35 | I59: =I35 | J59: =J35 | K59: =K35 | L59: =L35 | M59: =M35 | ... W59: =W35 | X59: =IF($C$25="Quarterly",W59*(1+X60),S59*(1+X60)) -> 0 | Y59: =SUM(U59:X59) -> 0 | Z59: =IF($C$25="Quarterly",X59*(1+Z60),U59*(1+Z60)) -> 0 | AA59: =IF($C$25="Quarterly",Z59*(1+AA60),V59*(1+AA60)) -> 0 | AB59: =IF($C$25="Quarterly",AA59*(1+AB60),W59*(1+AB60)) | AC59: =IF($C$25="Quarterly",AB59*(1+AC60),X59*(1+AC60)) | AD59: =SUM(Z59:AC59) -> 0 | AE59: =AD59*(1+AE60) -> 0 | AF59: =AE59*(1+AF60) | AG59: =AF59*(1+AG60)
C60: =IF($C$25="Quarterly","% Growth QoQ","% Growth YoY") -> % Growth QoQ | G60: =G36 -> N/A | H60: =H36 -> N/A | I60: =I36 -> N/A | J60: =J36 | K60: =K36 -> N/A | L60: =L36 -> N/A | M60: =M36 -> N/A | N60: =N36 -> N/A | ... W60: =W36 -> N/A | X60: =IF(Case_Scenario="Bull",X61,IF(Case_Scenario="Base",X62,IF(Case_Scenario="bear",X63,"N/A"))) -> 0.05 | Z60: =IF(Case_Scenario="Bull",Z61,IF(Case_Scenario="Base",Z62,IF(Case_Scenario="bear",Z63,"N/A"))) -> 0.05 | AA60: =IF(Case_Scenario="Bull",AA61,IF(Case_Scenario="Base",AA62,IF(Case_Scenario="bear",AA63,"N/A"))) -> 0.05 | AB60: =IF(Case_Scenario="Bull",AB61,IF(Case_Scenario="Base",AB62,IF(Case_Scenario="bear",AB63,"N/A"))) -> 0.05 | AC60: =IF(Case_Scenario="Bull",AC61,IF(Case_Scenario="Base",AC62,IF(Case_Scenario="bear",AC63,"N/A"))) -> 0.05 | AE60: =IF(Case_Scenario="Bull",AE61,IF(Case_Scenario="Base",AE62,IF(Case_Scenario="bear",AE63,"N/A"))) -> 0.05 | AF60: =IF(Case_Scenario="Bull",AF61,IF(Case_Scenario="Base",AF62,IF(Case_Scenario="bear",AF63,"N/A"))) -> 0.05 | AG60: =IF(Case_Scenario="Bull",AG61,IF(Case_Scenario="Base",AG62,IF(Case_Scenario="bear",AG63,"N/A"))) -> 0.05
C61: Bull Case | X61: 0.1 | Z61: 0.1 | AA61: 0.1 | AB61: 0.1 | AC61: 0.1 | AE61: 0.1 | AF61: 0.1 | AG61: 0.1
C62: Base Case | X62: 0.05 | Z62: 0.05 | AA62: 0.05 | AB62: 0.05 | AC62: 0.05 | AE62: 0.05 | AF62: 0.05 | AG62: 0.05
C63: Bear Case | X63: 0 | Z63: 0 | AA63: 0 | AB63: 0 | AC63: 0 | AE63: 0 | AF63: 0 | AG63: 0
A65: x | C65: =C38 -> Segment 3 Revenue | F65: =F38 -> 0 | G65: =G38 | H65: =H38 | I65: =I38 | J65: =J38 | K65: =K38 | L65: =L38 | M65: =M38 | ... W65: =W38 | X65: =IF($C$25="Quarterly",W65*(1+X66),S65*(1+X66)) -> 0 | Y65: =SUM(U65:X65) -> 0 | Z65: =IF($C$25="Quarterly",X65*(1+Z66),U65*(1+Z66)) -> 0 | AA65: =IF($C$25="Quarterly",Z65*(1+AA66),V65*(1+AA66)) -> 0 | AB65: =IF($C$25="Quarterly",AA65*(1+AB66),W65*(1+AB66)) | AC65: =IF($C$25="Quarterly",AB65*(1+AC66),X65*(1+AC66)) | AD65: =SUM(Z65:AC65) -> 0 | AE65: =AD65*(1+AE66) -> 0 | AF65: =AE65*(1+AF66) | AG65: =AF65*(1+AG66)
C66: =IF($C$25="Quarterly","% Growth QoQ","% Growth YoY") -> % Growth QoQ | G66: =G39 -> N/A | H66: =H39 -> N/A | I66: =I39 -> N/A | J66: =J39 | K66: =K39 -> N/A | L66: =L39 -> N/A | M66: =M39 -> N/A | N66: =N39 -> N/A | ... W66: =W39 -> N/A | X66: =IF(Case_Scenario="Bull",X67,IF(Case_Scenario="Base",X68,IF(Case_Scenario="bear",X69,"N/A"))) -> 0.05 | Z66: =IF(Case_Scenario="Bull",Z67,IF(Case_Scenario="Base",Z68,IF(Case_Scenario="bear",Z69,"N/A"))) -> 0.05 | AA66: =IF(Case_Scenario="Bull",AA67,IF(Case_Scenario="Base",AA68,IF(Case_Scenario="bear",AA69,"N/A"))) -> 0.05 | AB66: =IF(Case_Scenario="Bull",AB67,IF(Case_Scenario="Base",AB68,IF(Case_Scenario="bear",AB69,"N/A"))) -> 0.05 | AC66: =IF(Case_Scenario="Bull",AC67,IF(Case_Scenario="Base",AC68,IF(Case_Scenario="bear",AC69,"N/A"))) -> 0.05 | AE66: =IF(Case_Scenario="Bull",AE67,IF(Case_Scenario="Base",AE68,IF(Case_Scenario="bear",AE69,"N/A"))) -> 0.05 | AF66: =IF(Case_Scenario="Bull",AF67,IF(Case_Scenario="Base",AF68,IF(Case_Scenario="bear",AF69,"N/A"))) -> 0.05 | AG66: =IF(Case_Scenario="Bull",AG67,IF(Case_Scenario="Base",AG68,IF(Case_Scenario="bear",AG69,"N/A"))) -> 0.05
C67: Bull Case | X67: 0.1 | Z67: 0.1 | AA67: 0.1 | AB67: 0.1 | AC67: 0.1 | AE67: 0.1 | AF67: 0.1 | AG67: 0.1
C68: Base Case | X68: 0.05 | Z68: 0.05 | AA68: 0.05 | AB68: 0.05 | AC68: 0.05 | AE68: 0.05 | AF68: 0.05 | AG68: 0.05
C69: Bear Case | X69: 0 | Z69: 0 | AA69: 0 | AB69: 0 | AC69: 0 | AE69: 0 | AF69: 0 | AG69: 0
A71: x | C71: =C41 -> Segment 4 Revenue | F71: =F41 -> 0 | G71: =G41 | H71: =H41 | I71: =I41 | J71: =J41 | K71: =K41 | L71: =L41 | M71: =M41 | ... W71: =W41 | X71: =IF($C$25="Quarterly",W71*(1+X72),S71*(1+X72)) -> 0 | Y71: =SUM(U71:X71) -> 0 | Z71: =IF($C$25="Quarterly",X71*(1+Z72),U71*(1+Z72)) -> 0 | AA71: =IF($C$25="Quarterly",Z71*(1+AA72),V71*(1+AA72)) -> 0 | AB71: =IF($C$25="Quarterly",AA71*(1+AB72),W71*(1+AB72)) | AC71: =IF($C$25="Quarterly",AB71*(1+AC72),X71*(1+AC72)) | AD71: =SUM(Z71:AC71) -> 0 | AE71: =AD71*(1+AE72) -> 0 | AF71: =AE71*(1+AF72) | AG71: =AF71*(1+AG72)
C72: =IF($C$25="Quarterly","% Growth QoQ","% Growth YoY") -> % Growth QoQ | G72: =G42 -> N/A | H72: =H42 -> N/A | I72: =I42 -> N/A | J72: =J42 | K72: =K42 -> N/A | L72: =L42 -> N/A | M72: =M42 -> N/A | N72: =N42 -> N/A | ... W72: =W42 -> N/A | X72: =IF(Case_Scenario="Bull",X73,IF(Case_Scenario="Base",X74,IF(Case_Scenario="bear",X75,"N/A"))) -> 0.05 | Z72: =IF(Case_Scenario="Bull",Z73,IF(Case_Scenario="Base",Z74,IF(Case_Scenario="bear",Z75,"N/A"))) -> 0.05 | AA72: =IF(Case_Scenario="Bull",AA73,IF(Case_Scenario="Base",AA74,IF(Case_Scenario="bear",AA75,"N/A"))) -> 0.05 | AB72: =IF(Case_Scenario="Bull",AB73,IF(Case_Scenario="Base",AB74,IF(Case_Scenario="bear",AB75,"N/A"))) -> 0.05 | AC72: =IF(Case_Scenario="Bull",AC73,IF(Case_Scenario="Base",AC74,IF(Case_Scenario="bear",AC75,"N/A"))) -> 0.05 | AE72: =IF(Case_Scenario="Bull",AE73,IF(Case_Scenario="Base",AE74,IF(Case_Scenario="bear",AE75,"N/A"))) -> 0.05 | AF72: =IF(Case_Scenario="Bull",AF73,IF(Case_Scenario="Base",AF74,IF(Case_Scenario="bear",AF75,"N/A"))) -> 0.05 | AG72: =IF(Case_Scenario="Bull",AG73,IF(Case_Scenario="Base",AG74,IF(Case_Scenario="bear",AG75,"N/A"))) -> 0.05
C73: Bull Case | X73: 0.1 | Z73: 0.1 | AA73: 0.1 | AB73: 0.1 | AC73: 0.1 | AE73: 0.1 | AF73: 0.1 | AG73: 0.1
C74: Base Case | X74: 0.05 | Z74: 0.05 | AA74: 0.05 | AB74: 0.05 | AC74: 0.05 | AE74: 0.05 | AF74: 0.05 | AG74: 0.05
C75: Bear Case | X75: 0 | Z75: 0 | AA75: 0 | AB75: 0 | AC75: 0 | AE75: 0 | AF75: 0 | AG75: 0
A77: x | C77: =C44 -> Segment 5 Revenue | F77: =F44 -> 0 | G77: =G44 | H77: =H44 | I77: =I44 | J77: =J44 | K77: =K44 | L77: =L44 | M77: =M44 | ... W77: =W44 | X77: =IF($C$25="Quarterly",W77*(1+X78),S77*(1+X78)) -> 0 | Y77: =SUM(U77:X77) -> 0 | Z77: =IF($C$25="Quarterly",X77*(1+Z78),U77*(1+Z78)) -> 0 | AA77: =IF($C$25="Quarterly",Z77*(1+AA78),V77*(1+AA78)) -> 0 | AB77: =IF($C$25="Quarterly",AA77*(1+AB78),W77*(1+AB78)) | AC77: =IF($C$25="Quarterly",AB77*(1+AC78),X77*(1+AC78)) | AD77: =SUM(Z77:AC77) -> 0 | AE77: =AD77*(1+AE78) -> 0 | AF77: =AE77*(1+AF78) | AG77: =AF77*(1+AG78)
C78: =IF($C$25="Quarterly","% Growth QoQ","% Growth YoY") -> % Growth QoQ | G78: =G45 -> N/A | H78: =H45 -> N/A | I78: =I45 -> N/A | J78: =J45 | K78: =K45 -> N/A | L78: =L45 -> N/A | M78: =M45 -> N/A | N78: =N45 -> N/A | ... W78: =W45 -> N/A | X78: =IF(Case_Scenario="Bull",X79,IF(Case_Scenario="Base",X80,IF(Case_Scenario="bear",X81,"N/A"))) -> 0.05 | Z78: =IF(Case_Scenario="Bull",Z79,IF(Case_Scenario="Base",Z80,IF(Case_Scenario="bear",Z81,"N/A"))) -> 0.05 | AA78: =IF(Case_Scenario="Bull",AA79,IF(Case_Scenario="Base",AA80,IF(Case_Scenario="bear",AA81,"N/A"))) -> 0.05 | AB78: =IF(Case_Scenario="Bull",AB79,IF(Case_Scenario="Base",AB80,IF(Case_Scenario="bear",AB81,"N/A"))) -> 0.05 | AC78: =IF(Case_Scenario="Bull",AC79,IF(Case_Scenario="Base",AC80,IF(Case_Scenario="bear",AC81,"N/A"))) -> 0.05 | AE78: =IF(Case_Scenario="Bull",AE79,IF(Case_Scenario="Base",AE80,IF(Case_Scenario="bear",AE81,"N/A"))) -> 0.05 | AF78: =IF(Case_Scenario="Bull",AF79,IF(Case_Scenario="Base",AF80,IF(Case_Scenario="bear",AF81,"N/A"))) -> 0.05 | AG78: =IF(Case_Scenario="Bull",AG79,IF(Case_Scenario="Base",AG80,IF(Case_Scenario="bear",AG81,"N/A"))) -> 0.05
C79: Bull Case | X79: 0.1 | Z79: 0.1 | AA79: 0.1 | AB79: 0.1 | AC79: 0.1 | AE79: 0.1 | AF79: 0.1 | AG79: 0.1
C80: Base Case | X80: 0.05 | Z80: 0.05 | AA80: 0.05 | AB80: 0.05 | AC80: 0.05 | AE80: 0.05 | AF80: 0.05 | AG80: 0.05
C81: Bear Case | X81: 0 | Z81: 0 | AA81: 0 | AB81: 0 | AC81: 0 | AE81: 0 | AF81: 0 | AG81: 0
A83: x | C83: =C47 -> Segment 6 Revenue | F83: =F47 -> 0 | G83: =G47 | H83: =H47 | I83: =I47 | J83: =J47 | K83: =K47 | L83: =L47 | M83: =M47 | ... W83: =W47 | X83: =IF($C$25="Quarterly",W83*(1+X84),S83*(1+X84)) -> 0 | Y83: =SUM(U83:X83) -> 0 | Z83: =IF($C$25="Quarterly",X83*(1+Z84),U83*(1+Z84)) -> 0 | AA83: =IF($C$25="Quarterly",Z83*(1+AA84),V83*(1+AA84)) -> 0 | AB83: =IF($C$25="Quarterly",AA83*(1+AB84),W83*(1+AB84)) | AC83: =IF($C$25="Quarterly",AB83*(1+AC84),X83*(1+AC84)) | AD83: =SUM(Z83:AC83) -> 0 | AE83: =AD83*(1+AE84) -> 0 | AF83: =AE83*(1+AF84) | AG83: =AF83*(1+AG84)
C84: =IF($C$25="Quarterly","% Growth QoQ","% Growth YoY") -> % Growth QoQ | G84: =G48 -> N/A | H84: =H48 -> N/A | I84: =I48 -> N/A | J84: =J48 | K84: =K48 -> N/A | L84: =L48 -> N/A | M84: =M48 -> N/A | N84: =N48 -> N/A | ... W84: =W48 -> N/A | X84: =IF(Case_Scenario="Bull",X85,IF(Case_Scenario="Base",X86,IF(Case_Scenario="bear",X87,"N/A"))) -> 0 | Z84: =IF(Case_Scenario="Bull",Z85,IF(Case_Scenario="Base",Z86,IF(Case_Scenario="bear",Z87,"N/A"))) -> 0 | AA84: =IF(Case_Scenario="Bull",AA85,IF(Case_Scenario="Base",AA86,IF(Case_Scenario="bear",AA87,"N/A"))) -> 0 | AB84: =IF(Case_Scenario="Bull",AB85,IF(Case_Scenario="Base",AB86,IF(Case_Scenario="bear",AB87,"N/A"))) -> 0 | AC84: =IF(Case_Scenario="Bull",AC85,IF(Case_Scenario="Base",AC86,IF(Case_Scenario="bear",AC87,"N/A"))) -> 0 | AE84: =IF(Case_Scenario="Bull",AE85,IF(Case_Scenario="Base",AE86,IF(Case_Scenario="bear",AE87,"N/A"))) -> 0 | AF84: =IF(Case_Scenario="Bull",AF85,IF(Case_Scenario="Base",AF86,IF(Case_Scenario="bear",AF87,"N/A"))) -> 0 | AG84: =IF(Case_Scenario="Bull",AG85,IF(Case_Scenario="Base",AG86,IF(Case_Scenario="bear",AG87,"N/A"))) -> 0
C85: Bull Case | X85: =W85 -> 0 | Z85: =X85 -> 0 | AA85: =Z85 -> 0 | AB85: =AA85 | AC85: =AB85 | AE85: =AC85 -> 0 | AF85: =AE85 -> 0 | AG85: =AF85
C86: Base Case | X86: =W86 | Z86: =X86 | AA86: =Z86 -> 0 | AB86: =AA86 | AC86: =AB86 | AE86: =AC86 | AF86: =AE86 -> 0 | AG86: =AF86
C87: Bear Case | X87: =W87 | Z87: =X87 | AA87: =Z87 -> 0 | AB87: =AA87 | AC87: =AB87 | AE87: =AC87 | AF87: =AE87 -> 0 | AG87: =AF87
A89: x | C89: Activity-Based Growth | F89: =F$28 -> 1Q23 | G89: =G$28 -> 2Q23 | H89: =H$28 -> 3Q23 | I89: =I$28 -> 4Q23 | J89: =J$28 -> 2023 | K89: =K$28 -> 1Q24 | L89: =L$28 -> 2Q24 | M89: =M$28 -> 3Q24 | ... AG89: =AG$28 -> 2030e | AH89: x
C91: =C32 -> Home Improvement Retail Revenue | F91: =F32 -> 17360 | G91: =G32 -> 20888 | H91: =H32 -> 17415 | I91: =I32 -> 15646 | J91: =J32 -> 71309 | K91: =K32 -> 17741 | L91: =L32 -> 20992 | M91: =M32 -> 17388 | ... W91: =W32 -> 22918 | X91: =X92*X97 -> 25267.095 | Y91: =SUM(U91:X91) -> 100177.1 | Z91: =Z92*Z97 -> 27856.972 | AA91: =AA92*AA97 -> 30712.312 | AB91: =AB92*AB97 -> 33860.324 | AC91: =AC92*AC97 -> 37331.007 | AD91: =SUM(Z91:AC91) -> 129760.62 | AE91: =AE92*AE97 -> 143061.08 | AF91: =AF92*AF97 -> 157724.84 | AG91: =AG92*AG97 -> 173891.63
C92: Volume | F92: 220 | G92: 220 | H92: 220 | I92: 220 | J92: =SUM(F92:I92) -> 880 | K92: 220 | L92: 220 | M92: 220 | N92: 220 | O92: =SUM(K92:N92) -> 880 | P92: 220 | Q92: 220 | R92: 220 | S92: 220 | T92: =SUM(P92:S92) -> 880 | U92: 220 | V92: 220 | W92: 220 | X92: =W92*(1+X93) -> 231 | Y92: =SUM(U92:X92) -> 891 | Z92: =X92*(1+Z93) -> 242.55 | AA92: =Z92*(1+AA93) -> 254.6775 | AB92: =AA92*(1+AB93) -> 267.41138 | AC92: =AB92*(1+AC93) -> 280.78194 | AD92: =SUM(Z92:AC92) -> 1045.4208 | AE92: =AD92*(1+AE93) -> 1097.6919 | AF92: =AE92*(1+AF93) -> 1152.5765 | AG92: =AF92*(1+AG93) -> 1210.2053
C93: % Volume Growth | G93: =IFERROR(G92/F92-1,"--") -> 0 | H93: =IFERROR(H92/G92-1,"--") | I93: =IFERROR(I92/H92-1,"--") | K93: =IFERROR(K92/I92-1,"--") -> 0 | L93: =IFERROR(L92/K92-1,"--") -> 0 | M93: =IFERROR(M92/L92-1,"--") | N93: =IFERROR(N92/M92-1,"--") | O93: =IFERROR(O92/J92-1,"--") -> 0 | P93: =IFERROR(P92/N92-1,"--") -> 0 | Q93: =IFERROR(Q92/P92-1,"--") -> 0 | R93: =IFERROR(R92/Q92-1,"--") | S93: =IFERROR(S92/R92-1,"--") | T93: =IFERROR(T92/O92-1,"--") -> 0 | U93: =IFERROR(U92/S92-1,"--") -> 0 | V93: =IFERROR(V92/U92-1,"--") -> 0 | W93: =IFERROR(W92/V92-1,"--") | X93: =IF(Case_Scenario="Bull",X94,IF(Case_Scenario="Base",X95,IF(Case_Scenario="bear",X96,"N/A"))) -> 0.05 | Z93: =IF(Case_Scenario="Bull",Z94,IF(Case_Scenario="Base",Z95,IF(Case_Scenario="bear",Z96,"N/A"))) -> 0.05 | AA93: =IF(Case_Scenario="Bull",AA94,IF(Case_Scenario="Base",AA95,IF(Case_Scenario="bear",AA96,"N/A"))) -> 0.05 | AB93: =IF(Case_Scenario="Bull",AB94,IF(Case_Scenario="Base",AB95,IF(Case_Scenario="bear",AB96,"N/A"))) -> 0.05 | AC93: =IF(Case_Scenario="Bull",AC94,IF(Case_Scenario="Base",AC95,IF(Case_Scenario="bear",AC96,"N/A"))) -> 0.05 | AE93: =IF(Case_Scenario="Bull",AE94,IF(Case_Scenario="Base",AE95,IF(Case_Scenario="bear",AE96,"N/A"))) -> 0.05 | AF93: =IF(Case_Scenario="Bull",AF94,IF(Case_Scenario="Base",AF95,IF(Case_Scenario="bear",AF96,"N/A"))) -> 0.05 | AG93: =IF(Case_Scenario="Bull",AG94,IF(Case_Scenario="Base",AG95,IF(Case_Scenario="bear",AG96,"N/A"))) -> 0.05
C94: Bull Case | X94: 0.1 | Z94: 0.1 | AA94: 0.1 | AB94: 0.1 | AC94: 0.1 | AE94: 0.1 | AF94: 0.1 | AG94: 0.1
C95: Base Case | X95: 0.05 | Z95: 0.05 | AA95: 0.05 | AB95: 0.05 | AC95: 0.05 | AE95: 0.05 | AF95: 0.05 | AG95: 0.05
C96: Bear Case | X96: 0 | Z96: 0 | AA96: 0 | AB96: 0 | AC96: 0 | AE96: 0 | AF96: 0 | AG96: 0
C97: Price | F97: =IFERROR(F91/F92,"--") -> 78.909091 | G97: =IFERROR(G91/G92,"--") -> 94.945455 | H97: =IFERROR(H91/H92,"--") -> 79.159091 | I97: =IFERROR(I91/I92,"--") -> 71.118182 | J97: =IFERROR(J91/J92,"--") -> 81.032955 | K97: =IFERROR(K91/K92,"--") -> 80.640909 | L97: =IFERROR(L91/L92,"--") -> 95.418182 | M97: =IFERROR(M91/M92,"--") -> 79.036364 | ... W97: =IFERROR(W91/W92,"--") -> 104.17273 | X97: =W97*(1+X98) -> 109.38136 | Y97: =Y91/Y92 -> 112.43221 | Z97: =X97*(1+Z98) -> 114.85043 | AA97: =Z97*(1+AA98) -> 120.59295 | AB97: =AA97*(1+AB98) -> 126.6226 | AC97: =AB97*(1+AC98) -> 132.95373 | AD97: =AD91/AD92 -> 124.12285 | AE97: =AD97*(1+AE98) -> 130.329 | AF97: =AE97*(1+AF98) -> 136.84545 | AG97: =AF97*(1+AG98) -> 143.68772
C98: % Price Growth | G98: =IFERROR(G97/F97-1,"--") -> 0.20322581 | H98: =IFERROR(H97/G97-1,"--") -> -0.16626771 | I98: =IFERROR(I97/H97-1,"--") -> -0.1015791 | K98: =IFERROR(K97/I97-1,"--") -> 0.13390004 | L98: =IFERROR(L97/K97-1,"--") -> 0.18324784 | M98: =IFERROR(M97/L97-1,"--") -> -0.17168445 | N98: =IFERROR(N97/M97-1,"--") -> -0.078272372 | O98: =IFERROR(O97/J97-1,"--") -> 0.011765696 | P98: =IFERROR(P97/N97-1,"--") -> 0.2276159 | Q98: =IFERROR(Q97/P97-1,"--") -> 0.3876493 | R98: =IFERROR(R97/Q97-1,"--") -> -0.18288038 | S98: =IFERROR(S97/R97-1,"--") -> -0.089560267 | T98: =IFERROR(T97/O97-1,"--") -> 0.24185009 | U98: =IFERROR(U97/S97-1,"--") -> 0.20240264 | V98: =IFERROR(V97/U97-1,"--") -> 0.12890017 | W98: =IFERROR(W97/V97-1,"--") -> -0.16873413 | X98: =IF(Case_Scenario="Bull",X99,IF(Case_Scenario="Base",X100,IF(Case_Scenario="bear",X101,"N/A"))) -> 0.05 | Z98: =IF(Case_Scenario="Bull",Z99,IF(Case_Scenario="Base",Z100,IF(Case_Scenario="bear",Z101,"N/A"))) -> 0.05 | AA98: =IF(Case_Scenario="Bull",AA99,IF(Case_Scenario="Base",AA100,IF(Case_Scenario="bear",AA101,"N/A"))) -> 0.05 | AB98: =IF(Case_Scenario="Bull",AB99,IF(Case_Scenario="Base",AB100,IF(Case_Scenario="bear",AB101,"N/A"))) -> 0.05 | AC98: =IF(Case_Scenario="Bull",AC99,IF(Case_Scenario="Base",AC100,IF(Case_Scenario="bear",AC101,"N/A"))) -> 0.05 | AE98: =IF(Case_Scenario="Bull",AE99,IF(Case_Scenario="Base",AE100,IF(Case_Scenario="bear",AE101,"N/A"))) -> 0.05 | AF98: =IF(Case_Scenario="Bull",AF99,IF(Case_Scenario="Base",AF100,IF(Case_Scenario="bear",AF101,"N/A"))) -> 0.05 | AG98: =IF(Case_Scenario="Bull",AG99,IF(Case_Scenario="Base",AG100,IF(Case_Scenario="bear",AG101,"N/A"))) -> 0.05
C99: Bull Case | X99: 0.1 | Z99: 0.1 | AA99: 0.1 | AB99: 0.1 | AC99: 0.1 | AE99: 0.1 | AF99: 0.1 | AG99: 0.1
C100: Base Case | X100: 0.05 | Z100: 0.05 | AA100: 0.05 | AB100: 0.05 | AC100: 0.05 | AE100: 0.05 | AF100: 0.05 | AG100: 0.05
C101: Bear Case | X101: 0 | Z101: 0 | AA101: 0 | AB101: 0 | AC101: 0 | AE101: 0 | AF101: 0 | AG101: 0
A103: x | C103: =C35 -> Segment 2 Revenue | F103: =F35 -> 0 | G103: =G35 | H103: =H35 | I103: =I35 | J103: =J35 | K103: =K35 | L103: =L35 | M103: =M35 | ... W103: =W35 | X103: =X104*X109 -> 0 | Y103: =SUM(U103:X103) -> 0 | Z103: =Z104*Z109 -> 0 | AA103: =AA104*AA109 | AB103: =AB104*AB109 | AC103: =AC104*AC109 | AD103: =SUM(Z103:AC103) -> 0 | AE103: =AE104*AE109 -> 0 | AF103: =AF104*AF109 | AG103: =AG104*AG109
C104: Volume | F104: 220 | G104: 220 | H104: 220 | I104: 220 | J104: =SUM(F104:I104) -> 880 | K104: 220 | L104: 220 | M104: 220 | N104: 220 | O104: =SUM(K104:N104) -> 880 | P104: 220 | Q104: 220 | R104: 220 | S104: 220 | T104: =SUM(P104:S104) -> 880 | U104: 220 | V104: 220 | W104: 220 | X104: =W104*(1+X105) -> 231 | Y104: =SUM(U104:X104) -> 891 | Z104: =X104*(1+Z105) -> 242.55 | AA104: =Z104*(1+AA105) -> 254.6775 | AB104: =AA104*(1+AB105) -> 267.41138 | AC104: =AB104*(1+AC105) -> 280.78194 | AD104: =SUM(Z104:AC104) -> 1045.4208 | AE104: =AD104*(1+AE105) -> 1097.6919 | AF104: =AE104*(1+AF105) -> 1152.5765 | AG104: =AF104*(1+AG105) -> 1210.2053
C105: % Volume Growth | G105: =IFERROR(G104/F104-1,"--") -> 0 | H105: =IFERROR(H104/G104-1,"--") | I105: =IFERROR(I104/H104-1,"--") | K105: =IFERROR(K104/I104-1,"--") -> 0 | L105: =IFERROR(L104/K104-1,"--") -> 0 | M105: =IFERROR(M104/L104-1,"--") | N105: =IFERROR(N104/M104-1,"--") | O105: =IFERROR(O104/J104-1,"--") -> 0 | P105: =IFERROR(P104/N104-1,"--") -> 0 | Q105: =IFERROR(Q104/P104-1,"--") -> 0 | R105: =IFERROR(R104/Q104-1,"--") | S105: =IFERROR(S104/R104-1,"--") | T105: =IFERROR(T104/O104-1,"--") -> 0 | U105: =IFERROR(U104/S104-1,"--") -> 0 | V105: =IFERROR(V104/U104-1,"--") -> 0 | W105: =IFERROR(W104/V104-1,"--") | X105: =IF(Case_Scenario="Bull",X106,IF(Case_Scenario="Base",X107,IF(Case_Scenario="bear",X108,"N/A"))) -> 0.05 | Z105: =IF(Case_Scenario="Bull",Z106,IF(Case_Scenario="Base",Z107,IF(Case_Scenario="bear",Z108,"N/A"))) -> 0.05 | AA105: =IF(Case_Scenario="Bull",AA106,IF(Case_Scenario="Base",AA107,IF(Case_Scenario="bear",AA108,"N/A"))) -> 0.05 | AB105: =IF(Case_Scenario="Bull",AB106,IF(Case_Scenario="Base",AB107,IF(Case_Scenario="bear",AB108,"N/A"))) -> 0.05 | AC105: =IF(Case_Scenario="Bull",AC106,IF(Case_Scenario="Base",AC107,IF(Case_Scenario="bear",AC108,"N/A"))) -> 0.05 | AE105: =IF(Case_Scenario="Bull",AE106,IF(Case_Scenario="Base",AE107,IF(Case_Scenario="bear",AE108,"N/A"))) -> 0.05 | AF105: =IF(Case_Scenario="Bull",AF106,IF(Case_Scenario="Base",AF107,IF(Case_Scenario="bear",AF108,"N/A"))) -> 0.05 | AG105: =IF(Case_Scenario="Bull",AG106,IF(Case_Scenario="Base",AG107,IF(Case_Scenario="bear",AG108,"N/A"))) -> 0.05
C106: Bull Case | X106: 0.1 | Z106: 0.1 | AA106: 0.1 | AB106: 0.1 | AC106: 0.1 | AE106: 0.1 | AF106: 0.1 | AG106: 0.1
C107: Base Case | X107: 0.05 | Z107: 0.05 | AA107: 0.05 | AB107: 0.05 | AC107: 0.05 | AE107: 0.05 | AF107: 0.05 | AG107: 0.05
C108: Bear Case | X108: 0 | Z108: 0 | AA108: 0 | AB108: 0 | AC108: 0 | AE108: 0 | AF108: 0 | AG108: 0
C109: Price | F109: =IFERROR(F103/F104,"--") -> 0 | G109: =IFERROR(G103/G104,"--") | H109: =IFERROR(H103/H104,"--") | I109: =IFERROR(I103/I104,"--") | J109: =IFERROR(J103/J104,"--") | K109: =IFERROR(K103/K104,"--") | L109: =IFERROR(L103/L104,"--") | M109: =IFERROR(M103/M104,"--") | ... W109: =IFERROR(W103/W104,"--") | X109: =W109*(1+X110) -> 0 | Y109: =Y103/Y104 -> 0 | Z109: =X109*(1+Z110) -> 0 | AA109: =Z109*(1+AA110) -> 0 | AB109: =AA109*(1+AB110) | AC109: =AB109*(1+AC110) | AD109: =AD103/AD104 -> 0 | AE109: =AD109*(1+AE110) -> 0 | AF109: =AE109*(1+AF110) | AG109: =AF109*(1+AG110)
C110: % Price Growth | G110: =IFERROR(G109/F109-1,"--") -> -- | H110: =IFERROR(H109/G109-1,"--") -> -- | I110: =IFERROR(I109/H109-1,"--") -> -- | K110: =IFERROR(K109/I109-1,"--") -> -- | L110: =IFERROR(L109/K109-1,"--") -> -- | M110: =IFERROR(M109/L109-1,"--") -> -- | N110: =IFERROR(N109/M109-1,"--") -> -- | O110: =IFERROR(O109/J109-1,"--") -> -- | P110: =IFERROR(P109/N109-1,"--") -> -- | Q110: =IFERROR(Q109/P109-1,"--") -> -- | R110: =IFERROR(R109/Q109-1,"--") -> -- | S110: =IFERROR(S109/R109-1,"--") -> -- | T110: =IFERROR(T109/O109-1,"--") -> -- | U110: =IFERROR(U109/S109-1,"--") -> -- | V110: =IFERROR(V109/U109-1,"--") -> -- | W110: =IFERROR(W109/V109-1,"--") -> -- | X110: =IF(Case_Scenario="Bull",X111,IF(Case_Scenario="Base",X112,IF(Case_Scenario="bear",X113,"N/A"))) -> 0.05 | Z110: =IF(Case_Scenario="Bull",Z111,IF(Case_Scenario="Base",Z112,IF(Case_Scenario="bear",Z113,"N/A"))) -> 0.05 | AA110: =IF(Case_Scenario="Bull",AA111,IF(Case_Scenario="Base",AA112,IF(Case_Scenario="bear",AA113,"N/A"))) -> 0.05 | AB110: =IF(Case_Scenario="Bull",AB111,IF(Case_Scenario="Base",AB112,IF(Case_Scenario="bear",AB113,"N/A"))) -> 0.05 | AC110: =IF(Case_Scenario="Bull",AC111,IF(Case_Scenario="Base",AC112,IF(Case_Scenario="bear",AC113,"N/A"))) -> 0.05 | AE110: =IF(Case_Scenario="Bull",AE111,IF(Case_Scenario="Base",AE112,IF(Case_Scenario="bear",AE113,"N/A"))) -> 0.05 | AF110: =IF(Case_Scenario="Bull",AF111,IF(Case_Scenario="Base",AF112,IF(Case_Scenario="bear",AF113,"N/A"))) -> 0.05 | AG110: =IF(Case_Scenario="Bull",AG111,IF(Case_Scenario="Base",AG112,IF(Case_Scenario="bear",AG113,"N/A"))) -> 0.05
C111: Bull Case | X111: 0.1 | Z111: 0.1 | AA111: 0.1 | AB111: 0.1 | AC111: 0.1 | AE111: 0.1 | AF111: 0.1 | AG111: 0.1
C112: Base Case | X112: 0.05 | Z112: 0.05 | AA112: 0.05 | AB112: 0.05 | AC112: 0.05 | AE112: 0.05 | AF112: 0.05 | AG112: 0.05
C113: Bear Case | X113: 0 | Z113: 0 | AA113: 0 | AB113: 0 | AC113: 0 | AE113: 0 | AF113: 0 | AG113: 0
A115: x | C115: =C38 -> Segment 3 Revenue | F115: =F38 -> 0 | G115: =G38 | H115: =H38 | I115: =I38 | J115: =J38 | K115: =K38 | L115: =L38 | M115: =M38 | ... W115: =W38 | X115: =X116*X121 -> 0 | Y115: =SUM(U115:X115) -> 0 | Z115: =Z116*Z121 -> 0 | AA115: =AA116*AA121 | AB115: =AB116*AB121 | AC115: =AC116*AC121 | AD115: =SUM(Z115:AC115) -> 0 | AE115: =AE116*AE121 -> 0 | AF115: =AF116*AF121 | AG115: =AG116*AG121
C116: Volume | F116: 220 | G116: 220 | H116: 220 | I116: 220 | J116: =SUM(F116:I116) -> 880 | K116: 220 | L116: 220 | M116: 220 | N116: 220 | O116: =SUM(K116:N116) -> 880 | P116: 220 | Q116: 220 | R116: 220 | S116: 220 | T116: =SUM(P116:S116) -> 880 | U116: 220 | V116: 220 | W116: 220 | X116: =W116*(1+X117) -> 231 | Y116: =SUM(U116:X116) -> 891 | Z116: =X116*(1+Z117) -> 242.55 | AA116: =Z116*(1+AA117) -> 254.6775 | AB116: =AA116*(1+AB117) -> 267.41138 | AC116: =AB116*(1+AC117) -> 280.78194 | AD116: =SUM(Z116:AC116) -> 1045.4208 | AE116: =AD116*(1+AE117) -> 1097.6919 | AF116: =AE116*(1+AF117) -> 1152.5765 | AG116: =AF116*(1+AG117) -> 1210.2053
...

Sheet Model
C1: =Company_Name&" - "&MID(CELL("filename",A1),FIND("]",CELL("filename",A1))+1,255)&": "&Case_Scenario&" Case" -> Lowe's Companies, Inc. - Model: Base Case
C2: =Cover!C2 -> $ in Millions Except Per Share Data
C4: Font Toggle
C5: Working
C7: Interest Expense Toggle
C8: On
A10: x | C10: Shortcuts
C11: =$C$25 -> Income Statement
C12: =$C$73 -> Cash Flow Statement
C13: =$C$118 -> Balance Sheet
C14: =$C$160 -> Working Capital Schedule
C15: =$C$190 -> PP&E / Depreciation Schedule
C16: =$C$204 -> Amortization Schedule
C17: =$C$216 -> Other Long-Term Items Schedule
C18: =$C$234 -> Shareholder's Equity Schedule
C19: =$C$275 -> Shares Outstanding Schedule
C20: =$C$286 -> Debt and Interest Schedule
J23: 1 | O23: 2 | T23: 3 | Y23: 4 | AD23: 5 | AE23: 6 | AF23: 7 | AG23: 8
F24: =G24 -> 2023 | G24: =H24 -> 2023 | H24: =I24 -> 2023 | I24: =J24 -> 2023 | J24: =O24-1 -> 2023 | K24: =L24 -> 2024 | L24: =M24 -> 2024 | M24: =N24 -> 2024 | N24: =O24 -> 2024 | O24: =T24-1 -> 2024 | P24: =Q24 -> 2025 | Q24: =R24 -> 2025 | R24: =S24 -> 2025 | S24: =T24 -> 2025 | T24: =YEAR(Last_FYE) -> 2025 | U24: =V24 -> 2026 | V24: =W24 -> 2026 | W24: =X24 -> 2026 | X24: =Y24 -> 2026 | Y24: =T24+1 -> 2026 | Z24: =AA24 -> 2027 | AA24: =AB24 -> 2027 | AB24: =AC24 -> 2027 | AC24: =AD24 -> 2027 | AD24: =Y24+1 -> 2027 | AE24: =AD24+1 -> 2028 | AF24: =AE24+1 -> 2029 | AG24: =AF24+1 -> 2030
A25: x | C25: Income Statement | F25: ="1Q"&RIGHT(F24,2) -> 1Q23 | G25: ="2Q"&RIGHT(G24,2) -> 2Q23 | H25: ="3Q"&RIGHT(H24,2) -> 3Q23 | I25: ="4Q"&RIGHT(I24,2) -> 4Q23 | J25: =J24 -> 2023 | K25: ="1Q"&RIGHT(K24,2) -> 1Q24 | L25: ="2Q"&RIGHT(L24,2) -> 2Q24 | M25: ="3Q"&RIGHT(M24,2) -> 3Q24 | N25: ="4Q"&RIGHT(N24,2) -> 4Q24 | O25: =O24 -> 2024 | P25: ="1Q"&RIGHT(P24,2) -> 1Q25 | Q25: ="2Q"&RIGHT(Q24,2) -> 2Q25 | R25: ="3Q"&RIGHT(R24,2) -> 3Q25 | S25: ="4Q"&RIGHT(S24,2) -> 4Q25 | T25: =T24 -> 2025 | U25: =IF(Last_FQR="4Q","1Q"&RIGHT(U24,2)&"e","1Q"&RIGHT(U24,2)) -> 1Q26 | V25: =IF(Last_FQR="4Q","2Q"&RIGHT(W24,2)&"e",IF(Last_FQR="1Q","2Q"&RIGHT(W24,2)&"e","2Q"&RIGHT(W24,2))) -> 2Q26 | W25: =IF(Last_FQR="4Q","3Q"&RIGHT(W24,2)&"e",IF(Last_FQR="1Q","3Q"&RIGHT(W24,2)&"e",IF(Last_FQR="2Q","3Q"&RIGHT(W24,2)&"e","3Q"&RIGHT(W24,2)))) -> 3Q26e | X25: ="4Q"&RIGHT(U24,2)&"e" -> 4Q26e | Y25: =Y24&"e" -> 2026e | Z25: ="1Q"&RIGHT(Z24,2)&"e" -> 1Q27e | AA25: ="2Q"&RIGHT(AA24,2)&"e" -> 2Q27e | AB25: ="3Q"&RIGHT(AB24,2)&"e" -> 3Q27e | AC25: ="4Q"&RIGHT(AC24,2)&"e" -> 4Q27e | AD25: =AD24&"e" -> 2027e | AE25: =AE24&"e" -> 2028e | AF25: =AF24&"e" -> 2029e | AG25: =AG24&"e" -> 2030e | AH25: x
C26: Days In Period | F26: 91 | G26: 91 | H26: 92 | I26: 92 | J26: =SUM(F26:I26) -> 366 | K26: 90 | L26: 91 | M26: 92 | N26: 92 | O26: =SUM(K26:N26) -> 365 | P26: 90 | Q26: 91 | R26: 92 | S26: 92 | T26: =SUM(P26:S26) -> 365 | U26: 90 | V26: 91 | W26: 92 | X26: 92 | Y26: =SUM(U26:X26) -> 365 | Z26: 91 | AA26: 91 | AB26: 92 | AC26: 92 | AD26: =SUM(Z26:AC26) -> 366 | AE26: 365 | AF26: 365 | AG26: 365
C28: Revenue | F28: ='Segment Analysis'!F7 -> 117154 | G28: ='Segment Analysis'!G7 -> 94836 | H28: ='Segment Analysis'!H7 -> 81797 | I28: ='Segment Analysis'!I7 -> 89498 | J28: =SUM(F28:I28) -> 383285 | K28: ='Segment Analysis'!K7 -> 119575 | L28: ='Segment Analysis'!L7 -> 90753 | M28: ='Segment Analysis'!M7 -> 85777 | N28: ='Segment Analysis'!N7 -> 94930 | O28: =SUM(K28:N28) -> 391035 | P28: ='Segment Analysis'!P7 -> 124300 | Q28: ='Segment Analysis'!Q7 -> 95359 | R28: ='Segment Analysis'!R7 -> 94036 | S28: ='Segment Analysis'!S7 -> 102466 | T28: =SUM(P28:S28) -> 416161 | U28: ='Segment Analysis'!U7 -> 143756 | V28: ='Segment Analysis'!V7 -> 111184 | W28: ='Segment Analysis'!W7 -> 22918 | X28: ='Segment Analysis'!X7 -> 21772.1 | Y28: =SUM(U28:X28) -> 96682.1 | Z28: ='Segment Analysis'!Z7 -> 25691.078 | AA28: ='Segment Analysis'!AA7 -> 29287.829 | AB28: ='Segment Analysis'!AB7 -> 25773.289 | AC28: ='Segment Analysis'!AC7 -> 24484.625 | AD28: =SUM(Z28:AC28) -> 105236.82 | AE28: ='Segment Analysis'!AE7 -> 107341.56 | AF28: ='Segment Analysis'!AF7 -> 109488.39 | AG28: ='Segment Analysis'!AG7 -> 111678.16
C29: Cost of Goods Sold | F29: -66822 | G29: -52860 | H29: -45384 | I29: =-214137-SUM(F29:H29) -> -49071 | J29: =SUM(F29:I29) -> -48401 | K29: -64720 | L29: -48482 | M29: -46099 | N29: -51051 | O29: =SUM(K29:N29) -> -49205 | P29: =-13162 -> -13162 | Q29: =-17998 -> -17998 | R29: =-15009 -> -15009 | S29: -54125 | T29: =SUM(P29:S29) -> -60014 | U29: =-16292 -> -16292 | V29: =-18258 -> -18258 | W29: -15331 | X29: =IF(Cover!$F$37="Bottom Up",(X30-X28),(-X28*(1-X66))) -> -18941.727 | Y29: =SUM(U29:X29) -> -68822.727 | Z29: =IF(Cover!$F$37="Bottom Up",(Z30-Z28),(-Z28*(1-Z66))) -> -22094.327 | AA29: =IF(Cover!$F$37="Bottom Up",(AA30-AA28),(-AA28*(1-AA66))) -> -25041.094 | AB29: =IF(Cover!$F$37="Bottom Up",(AB30-AB28),(-AB28*(1-AB66))) -> -22680.495 | AC29: =IF(Cover!$F$37="Bottom Up",(AC30-AC28),(-AC28*(1-AC66))) -> -21179.201 | AD29: =SUM(Z29:AC29) -> -90995.116 | AE29: =IF(Cover!$F$37="Bottom Up",(AE30-AE28),(-AE28*(1-AE66))) -> -92421.081 | AF29: =IF(Cover!$F$37="Bottom Up",(AF30-AF28),(-AF28*(1-AF66))) -> -94160.014 | AG29: =IF(Cover!$F$37="Bottom Up",(AG30-AG28),(-AG28*(1-AG66))) -> -95819.858
C30: Gross Profit | F30: =SUM(F28:F29) -> 50332 | G30: =SUM(G28:G29) -> 41976 | H30: =SUM(H28:H29) -> 36413 | I30: =SUM(I28:I29) -> 40427 | J30: =SUM(F30:I30) -> 169148 | K30: =SUM(K28:K29) -> 54855 | L30: =SUM(L28:L29) -> 42271 | M30: =SUM(M28:M29) -> 39678 | N30: =SUM(N28:N29) -> 43879 | O30: =SUM(K30:N30) -> 180683 | P30: =SUM(P28:P29) -> 111138 | Q30: =SUM(Q28:Q29) -> 77361 | R30: =SUM(R28:R29) -> 79027 | S30: =SUM(S28:S29) -> 48341 | T30: =SUM(P30:S30) -> 315867 | U30: =SUM(U28:U29) -> 127464 | V30: =SUM(V28:V29) -> 92926 | W30: =SUM(W28:W29) -> 7587 | X30: =IF(Cover!$F$37="Bottom Up",(X36-SUM(X32:X33,X35)),X28+X29) -> 2830.373 | Y30: =SUM(U30:X30) -> 27859.373 | Z30: =IF(Cover!$F$37="Bottom Up",(Z36-SUM(Z32:Z33,Z35)),Z28+Z29) -> 3596.7509 | AA30: =IF(Cover!$F$37="Bottom Up",(AA36-SUM(AA32:AA33,AA35)),AA28+AA29) -> 4246.7352 | AB30: =IF(Cover!$F$37="Bottom Up",(AB36-SUM(AB32:AB33,AB35)),AB28+AB29) -> 3092.7947 | AC30: =IF(Cover!$F$37="Bottom Up",(AC36-SUM(AC32:AC33,AC35)),AC28+AC29) -> 3305.4244 | AD30: =SUM(Z30:AC30) -> 14241.705 | AE30: =IF(Cover!$F$37="Bottom Up",(AE36-SUM(AE32:AE33,AE35)),AE28+AE29) -> 14920.477 | AF30: =IF(Cover!$F$37="Bottom Up",(AF36-SUM(AF32:AF33,AF35)),AF28+AF29) -> 15328.374 | AG30: =IF(Cover!$F$37="Bottom Up",(AG36-SUM(AG32:AG33,AG35)),AG28+AG29) -> 15858.298
C32: Selling, General & Administration (SG&A) | F32: -6607 | G32: -6201 | H32: -5973 | I32: =-24932-SUM(F32:H32) -> -6151 | J32: =SUM(F32:I32) -> -17413 | K32: -6786 | L32: -6468 | M32: -6320 | N32: -6523 | O32: =SUM(K32:N32) -> -15367 | P32: =-4196 -> -4196 | Q32: =-5020 -> -5020 | R32: =-4770 -> -4770 | S32: -7048 | T32: =SUM(P32:S32) -> -17293 | U32: -7492 | V32: =-4693 -> -4693 | W32: -4373 | X32: =X67*X$28 -> -4789.862 | Y32: =SUM(U32:X32) -> -18349.862 | Z32: =Z67*Z$28 -> -5780.4925 | AA32: =AA67*AA$28 -> -6589.7615 | AB32: =AB67*AB$28 -> -5670.1237 | AC32: =AC67*AC$28 -> -5386.6175 | AD32: =SUM(Z32:AC32) -> -23426.995 | AE32: =AE67*AE$28 -> -23078.435 | AF32: =AF67*AF$28 -> -23102.05 | AG32: =AG67*AG$28 -> -23005.7
C33: Research & Development (R&D) | F33: -7709 | G33: -7457 | H33: -7442 | I33: -7307 | J33: =SUM(F33:I33) | K33: -7696 | L33: -7903 | M33: -8006 | N33: -7765 | O33: =SUM(K33:N33) | P33: -8268 | Q33: -8550 | R33: -8866 | S33: -8866 | T33: =SUM(P33:S33) | U33: -10887 | V33: -11419 | W33: 0 | X33: =X68*X$28 | Y33: =SUM(U33:X33) | Z33: =Z68*Z$28 -> 0 | AA33: =AA68*AA$28 | AB33: =AB68*AB$28 | AC33: =AC68*AC$28 | AD33: =SUM(Z33:AC33) | AE33: =AE68*AE$28 -> 0 | AF33: =AF68*AF$28 | AG33: =AG68*AG$28
C34: Depreciation & Amortization | F34: 0 | G34: 0 | H34: 0 | I34: =0-SUM(F34:H34) -> 1e-12 | J34: =SUM(F34:I34) -> -1477 | K34: 0 | L34: 0 | M34: 0 | N34: 0 | O34: =SUM(K34:N34) -> -1262 | P34: =-326 -> -326 | Q34: =-327 -> -327 | R34: =-355 -> -355 | S34: 0 | T34: =SUM(P34:S34) -> -1398 | U34: 0 | V34: 0 | W34: -425 | X34: =-X76 -> -331.1875 | Y34: =SUM(U34:X34) -> -1556.1875 | Z34: =-Z76 -> -331.86892 | AA34: =-AA76 -> -336.85147 | AB34: =-AB76 -> -342.23238 | AC34: =-AC76 -> -343.91087 | AD34: =SUM(Z34:AC34) -> -1354.8636 | AE34: =-AE76 -> -1420.1552 | AF34: =-AF76 -> -1472.4758 | AG34: =-AG76 -> -1524.1209
C35: Other Operating Income (Expense) | F35: 0 | G35: 0 | H35: 0 | I35: 0 | J35: =SUM(F35:I35) | K35: 0 | L35: 0 | M35: 0 | N35: 0 | O35: =SUM(K35:N35) | P35: -55516 | Q35: -33875 | R35: -36834 | S35: 0 | T35: =SUM(P35:S35) | U35: -58233 | V35: -40929 | W35: 0 | X35: =X69*X$28 -> 0 | Y35: =SUM(U35:X35) | Z35: =Z69*Z$28 -> 0 | AA35: =AA69*AA$28 | AB35: =AB69*AB$28 | AC35: =AC69*AC$28 | AD35: =SUM(Z35:AC35) | AE35: =AE69*AE$28 -> 0 | AF35: =AF69*AF$28 | AG35: =AG69*AG$28
C36: EBIT | F36: =IF($C$34="Depreciation & Amortization (incl. in SG&A)",F30+SUM(F32:F33,F35),F30+SUM(F32:F35)) -> 36016 | G36: =IF($C$34="Depreciation & Amortization (incl. in SG&A)",G30+SUM(G32:G33,G35),G30+SUM(G32:G35)) -> 28318 | H36: =IF($C$34="Depreciation & Amortization (incl. in SG&A)",H30+SUM(H32:H33,H35),H30+SUM(H32:H35)) -> 22998 | I36: =IF($C$34="Depreciation & Amortization (incl. in SG&A)",I30+SUM(I32:I33,I35),I30+SUM(I32:I35)) -> 26969 | J36: =SUM(F36:I36) -> 114301 | K36: =IF($C$34="Depreciation & Amortization (incl. in SG&A)",K30+SUM(K32:K33,K35),K30+SUM(K32:K35)) -> 40373 | L36: =IF($C$34="Depreciation & Amortization (incl. in SG&A)",L30+SUM(L32:L33,L35),L30+SUM(L32:L35)) -> 27900 | M36: =IF($C$34="Depreciation & Amortization (incl. in SG&A)",M30+SUM(M32:M33,M35),M30+SUM(M32:M35)) -> 25352 | N36: =IF($C$34="Depreciation & Amortization (incl. in SG&A)",N30+SUM(N32:N33,N35),N30+SUM(N32:N35)) -> 29591 | O36: =SUM(K36:N36) -> 123216 | P36: =IF($C$34="Depreciation & Amortization (incl. in SG&A)",P30+SUM(P32:P33,P35),P30+SUM(P32:P35)) -> 42832 | Q36: =IF($C$34="Depreciation & Amortization (incl. in SG&A)",Q30+SUM(Q32:Q33,Q35),Q30+SUM(Q32:Q35)) -> 29589 | R36: =IF($C$34="Depreciation & Amortization (incl. in SG&A)",R30+SUM(R32:R33,R35),R30+SUM(R32:R35)) -> 28202 | S36: =IF($C$34="Depreciation & Amortization (incl. in SG&A)",S30+SUM(S32:S33,S35),S30+SUM(S32:S35)) -> 32427 | T36: =SUM(P36:S36) -> 133050 | U36: =IF($C$34="Depreciation & Amortization (incl. in SG&A)",U30+SUM(U32:U33,U35),U30+SUM(U32:U35)) -> 50852 | V36: =IF($C$34="Depreciation & Amortization (incl. in SG&A)",V30+SUM(V32:V33,V35),V30+SUM(V32:V35)) -> 35885 | W36: =IF($C$34="Depreciation & Amortization (incl. in SG&A)",W30+SUM(W32:W33,W35),W30+SUM(W32:W35)) -> 2789 | X36: =IF(Cover!$F$37="Bottom Up",'Segment Analysis'!X33,IF($C$34="Depreciation & Amortization (incl. in SG&A)",X30+SUM(X32:X33,X35),X30+SUM(X32:X35))) -> -2290.6765 | Y36: =SUM(U36:X36) -> 7953.3235 | Z36: =IF(Cover!$F$37="Bottom Up",'Segment Analysis'!Z33,IF($C$34="Depreciation & Amortization (incl. in SG&A)",Z30+SUM(Z32:Z33,Z35),Z30+SUM(Z32:Z35))) -> -2515.6105 | AA36: =IF(Cover!$F$37="Bottom Up",'Segment Analysis'!AA33,IF($C$34="Depreciation & Amortization (incl. in SG&A)",AA30+SUM(AA32:AA33,AA35),AA30+SUM(AA32:AA35))) -> -2679.8778 | AB36: =IF(Cover!$F$37="Bottom Up",'Segment Analysis'!AB33,IF($C$34="Depreciation & Amortization (incl. in SG&A)",AB30+SUM(AB32:AB33,AB35),AB30+SUM(AB32:AB35))) -> -2919.5613 | AC36: =IF(Cover!$F$37="Bottom Up",'Segment Analysis'!AC33,IF($C$34="Depreciation & Amortization (incl. in SG&A)",AC30+SUM(AC32:AC33,AC35),AC30+SUM(AC32:AC35))) -> -2425.104 | AD36: =SUM(Z36:AC36) -> -10540.154 | AE36: =IF(Cover!$F$37="Bottom Up",'Segment Analysis'!AE33,IF($C$34="Depreciation & Amortization (incl. in SG&A)",AE30+SUM(AE32:AE33,AE35),AE30+SUM(AE32:AE35))) -> -9578.1136 | AF36: =IF(Cover!$F$37="Bottom Up",'Segment Analysis'!AF33,IF($C$34="Depreciation & Amortization (incl. in SG&A)",AF30+SUM(AF32:AF33,AF35),AF30+SUM(AF32:AF35))) -> -9246.1514 | AG36: =IF(Cover!$F$37="Bottom Up",'Segment Analysis'!AG33,IF($C$34="Depreciation & Amortization (incl. in SG&A)",AG30+SUM(AG32:AG33,AG35),AG30+SUM(AG32:AG35))) -> -8671.5229
C38: Interest Income | F38: 0 | G38: 0 | H38: 0 | I38: 0 | J38: =SUM(F38:I38) -> 0 | K38: 0 | L38: 0 | M38: 0 | N38: 0 | O38: =SUM(K38:N38) -> 0 | P38: 0 | Q38: 0 | R38: 0 | S38: 0 | T38: =SUM(P38:S38) -> 0 | U38: 0 | V38: 0 | W38: 0 | X38: =X329 | Y38: =SUM(U38:X38) | Z38: =Z329 | AA38: =AA329 | AB38: =AB329 | AC38: =AC329 | AD38: =SUM(Z38:AC38) | AE38: =AE329 | AF38: =AF329 | AG38: =AG329
C39: Interest (Expense) | F39: -1003 | G39: -930 | H39: -998 | I39: =-3933-SUM(F39:H39) -> -1002 | J39: =SUM(F39:I39) -> -624 | K39: -162 | L39: -169 | M39: -177 | N39: -183 | O39: =SUM(K39:N39) -> -691 | P39: -205 | Q39: =-219 -> -219 | R39: -221 | S39: -204 | T39: =SUM(P39:S39) -> -849 | U39: -211 | V39: =-216 -> -216 | W39: -223 | X39: =X322 | Y39: =SUM(U39:X39) | Z39: =Z322 | AA39: =AA322 | AB39: =AB322 | AC39: =AC322 | AD39: =SUM(Z39:AC39) | AE39: =AE322 | AF39: =AF322 | AG39: =AG322
C40: Goodwill Impairment | F40: 0 | G40: 0 | H40: 0 | I40: 0 | J40: =SUM(F40:I40) | K40: 0 | L40: 0 | M40: 0 | N40: 0 | O40: =SUM(K40:N40) | P40: 0 | Q40: 0 | R40: 0 | S40: 0 | T40: =SUM(P40:S40) | U40: 0 | V40: 0 | W40: 0 | X40: =Drivers!X62 -> 0 | Y40: =SUM(U40:X40) | Z40: =Drivers!Z62 -> 0 | AA40: =Drivers!AA62 -> 0 | AB40: =Drivers!AB62 -> 0 | AC40: =Drivers!AC62 -> 0 | AD40: =SUM(Z40:AC40) | AE40: =Drivers!AE62 -> 0 | AF40: =Drivers!AF62 -> 0 | AG40: =Drivers!AG62 -> 0
C41: Other Non-Operating Income (Expense) | F41: 610 | G41: 994 | H41: 733 | I41: 1031 | J41: =SUM(F41:I41) | K41: 112 | L41: 327 | M41: 319 | N41: 202 | O41: =SUM(K41:N41) | P41: -43 | Q41: -60 | R41: 50 | S41: 581 | T41: =SUM(P41:S41) -> -2305 | U41: 361 | V41: 164 | W41: 0 | X41: =X70*X28 -> 0 | Y41: =SUM(U41:X41) | Z41: =Z70*Z28 -> 0 | AA41: =AA70*AA28 | AB41: =AB70*AB28 | AC41: =AC70*AC28 | AD41: =SUM(Z41:AC41) | AE41: =AE70*AE28 -> 0 | AF41: =AF70*AF28 | AG41: =AG70*AG28
C42: Pre-Tax Income (Loss) | F42: =F36+SUM(F38:F41) -> 35623 | G42: =G36+SUM(G38:G41) -> 28382 | H42: =H36+SUM(H38:H41) -> 22733 | I42: =I36+SUM(I38:I41) -> 26998 | J42: =SUM(F42:I42) -> 113736 | K42: =K36+SUM(K38:K41) -> 40323 | L42: =L36+SUM(L38:L41) -> 28058 | M42: =M36+SUM(M38:M41) -> 25494 | N42: =N36+SUM(N38:N41) -> 29610 | O42: =SUM(K42:N42) -> 123485 | P42: =P36+SUM(P38:P41) -> 42584 | Q42: =Q36+SUM(Q38:Q41) -> 29310 | R42: =IF($C$8="On",R36+SUM(R38:R41),IF($C$8="off",R36+SUM(R40:R41),"N/A")) -> 28031 | S42: =IF($C$8="On",S36+SUM(S38:S41),IF($C$8="off",S36+SUM(S40:S41),"N/A")) -> 32804 | T42: =SUM(P42:S42) -> 132729 | U42: =U36+SUM(U38:U41) -> 51002 | V42: =V36+SUM(V38:V41) -> 35833 | W42: =IF($C$8="On",W36+SUM(W38:W41),IF($C$8="off",W36+SUM(W40:W41),"N/A")) -> 2566 | X42: =IF($C$8="On",X36+SUM(X38:X41),IF($C$8="off",X36+SUM(X40:X41),"N/A")) | Y42: =SUM(U42:X42) | Z42: =IF($C$8="On",Z36+SUM(Z38:Z41),IF($C$8="off",Z36+SUM(Z40:Z41),"N/A")) | AA42: =IF($C$8="On",AA36+SUM(AA38:AA41),IF($C$8="off",AA36+SUM(AA40:AA41),"N/A")) | AB42: =IF($C$8="On",AB36+SUM(AB38:AB41),IF($C$8="off",AB36+SUM(AB40:AB41),"N/A")) | AC42: =IF($C$8="On",AC36+SUM(AC38:AC41),IF($C$8="off",AC36+SUM(AC40:AC41),"N/A")) | AD42: =SUM(Z42:AC42) | AE42: =IF($C$8="On",AE36+SUM(AE38:AE41),IF($C$8="off",AE36+SUM(AE40:AE41),"N/A")) | AF42: =IF($C$8="On",AF36+SUM(AF38:AF41),IF($C$8="off",AF36+SUM(AF40:AF41),"N/A")) | AG42: =IF($C$8="On",AG36+SUM(AG38:AG41),IF($C$8="off",AG36+SUM(AG40:AG41),"N/A"))
C44: Income Tax Benefit (Expense) | F44: -5625 | G44: -4222 | H44: -2852 | I44: =-16741-SUM(F44:H44) -> -4042 | J44: =SUM(F44:I44) -> -1080 | K44: -6407 | L44: -4422 | M44: -4046 | N44: -14874 | O44: =SUM(K44:N44) -> -1342 | P44: -6254 | Q44: -4530 | R44: -4597 | S44: -5338 | T44: =SUM(P44:S44) -> -1903 | U44: -8905 | V44: -11534 | W44: -670 | X44: =-X71*X42 | Y44: =SUM(U44:X44) | Z44: =-Z71*Z42 | AA44: =-AA71*AA42 | AB44: =-AB71*AB42 | AC44: =-AC71*AC42 | AD44: =SUM(Z44:AC44) | AE44: =-AE71*AE42 | AF44: =-AF71*AF42 | AG44: =-AG71*AG42
C45: Net Income (Loss) | F45: =F42+F44 -> 29998 | G45: =G42+G44 -> 24160 | H45: =H42+H44 -> 19881 | I45: =I42+I44 -> 22956 | J45: =SUM(F45:I45) -> 96995 | K45: =K42+K44 -> 33916 | L45: =L42+L44 -> 23636 | M45: =M42+M44 -> 21448 | N45: =N42+N44 -> 14736 | O45: =SUM(K45:N45) -> 93736 | P45: =P42+P44 -> 36330 | Q45: =Q42+Q44 -> 24780 | R45: =R42+R44 -> 23434 | S45: =S42+S44 -> 27466 | T45: =SUM(P45:S45) -> 112010 | U45: =U42+U44 -> 42097 | V45: =V42+V44 -> 24299 | W45: =W42+W44 -> 1896 | X45: =X42+X44 | Y45: =SUM(U45:X45) | Z45: =Z42+Z44 | AA45: =AA42+AA44 | AB45: =AB42+AB44 | AC45: =AC42+AC44 | AD45: =SUM(Z45:AC45) | AE45: =AE42+AE44 | AF45: =AF42+AF44 | AG45: =AG42+AG44
C47: Pre-Tax Adjustments | F47: 0 | G47: 0 | H47: 0 | I47: 0 | J47: =SUM(F47:I47) -> 0 | K47: 0 | L47: 0 | M47: 0 | N47: 0 | O47: =SUM(K47:N47) -> 0 | P47: 0 | Q47: 0 | R47: 0 | S47: 0 | T47: =SUM(P47:S47) -> 0 | U47: 0 | V47: 0 | W47: 0 | X47: 0 | Y47: =SUM(U47:X47) -> 0 | Z47: 0 | AA47: 0 | AB47: 0 | AC47: 0 | AD47: =SUM(Z47:AC47) -> 0 | AE47: 0 | AF47: 0 | AG47: 0
C48: Post-Tax Adjustments | F48: 0 | G48: 0 | H48: 0 | I48: 0 | J48: =SUM(F48:I48) -> 0 | K48: 0 | L48: 0 | M48: 0 | N48: 0 | O48: =SUM(K48:N48) -> 0 | P48: 0 | Q48: 0 | R48: 0 | S48: 0 | T48: =SUM(P48:S48) -> 0 | U48: 0 | V48: 0 | W48: 0 | X48: 0 | Y48: =SUM(U48:X48) | Z48: 0 | AA48: 0 | AB48: 0 | AC48: 0 | AD48: =SUM(Z48:AC48) | AE48: 0 | AF48: 0 | AG48: 0
C49: Discontinued Operations | F49: 0 | G49: 0 | H49: 0 | I49: 0 | J49: =SUM(F49:I49) -> 0 | K49: 0 | L49: 0 | M49: 0 | N49: 0 | O49: =SUM(K49:N49) -> 0 | P49: 0 | Q49: 0 | R49: 0 | S49: 0 | T49: =SUM(P49:S49) -> 0 | U49: 0 | V49: 0 | W49: 0 | X49: 0 | Y49: =SUM(U49:X49) | Z49: 0 | AA49: 0 | AB49: 0 | AC49: 0 | AD49: =SUM(Z49:AC49) | AE49: 0 | AF49: 0 | AG49: 0
C50: Income (Loss) due to Non-Controlling Interest | F50: 0 | G50: 0 | H50: 0 | I50: 0 | J50: =SUM(F50:I50) -> 0 | K50: 0 | L50: 0 | M50: 0 | N50: 0 | O50: =SUM(K50:N50) -> 0 | P50: 0 | Q50: 0 | R50: 0 | S50: 0 | T50: =SUM(P50:S50) -> 0 | U50: 0 | V50: 0 | W50: -7 | X50: 0 | Y50: =SUM(U50:X50) -> -7 | Z50: 0 | AA50: 0 | AB50: 0 | AC50: 0 | AD50: =SUM(Z50:AC50) | AE50: 0 | AF50: 0 | AG50: 0
C51: Adj. Net Income (Loss) | F51: =SUM(F45:F50) -> 29998 | G51: =SUM(G45:G50) -> 24160 | H51: =SUM(H45:H50) -> 19881 | I51: =SUM(I45:I50) -> 22956 | J51: =SUM(F51:I51) -> 96995 | K51: =SUM(K45:K50) -> 33916 | L51: =SUM(L45:L50) -> 23636 | M51: =SUM(M45:M50) -> 21448 | N51: =SUM(N45:N50) -> 14736 | O51: =SUM(K51:N51) -> 93736 | P51: =SUM(P45:P50) -> 36330 | Q51: =SUM(Q45:Q50) -> 24780 | R51: =SUM(R45:R50) -> 23434 | S51: =SUM(S45:S50) -> 27466 | T51: =SUM(P51:S51) -> 112010 | U51: =SUM(U45:U50) -> 42097 | V51: =SUM(V45:V50) -> 24299 | W51: =SUM(W45:W50) -> 1889 | X51: =SUM(X45:X50) | Y51: =SUM(U51:X51) | Z51: =SUM(Z45:Z50) | AA51: =SUM(AA45:AA50) | AB51: =SUM(AB45:AB50) | AC51: =SUM(AC45:AC50) | AD51: =SUM(Z51:AC51) | AE51: =SUM(AE45:AE50) | AF51: =SUM(AF45:AF50) | AG51: =SUM(AG45:AG50)
C53: GAAP EPS (Basic) | F53: =(F45)/F282 -> 36.361212 | G53: =(G45)/G282 -> 29.717097 | H53: =(H45)/H282 -> 24.666253 | I53: =(I45)/I282 -> 28.659176 | J53: =J45/J282 -> 2.8888889 | K53: =(K45)/K282 -> 41.110303 | L53: =(L45)/L282 -> 29.072571 | M53: =(M45)/M282 -> 26.610422 | N53: =(N45)/N282 -> 18.397004 | O53: =O45/O282 -> 5.3445693 | P53: =(P45)/P282 -> 48.119205 | Q53: =(Q45)/Q282 -> 32.952128 | R53: =(R45)/R282 -> 31.162234 | S53: =(S45)/S282 -> 36.719251 | T53: =T45/T282 -> 7.8008021 | U53: =(U45)/U282 -> 58.630919 | V53: =(V45)/V282 -> 34.466667 | W53: =(W45)/W282 -> 2.7478261 | X53: =X45/X282 | Y53: =Y45/Y282 | Z53: =Z45/Z282 | AA53: =AA45/AA282 | AB53: =AB45/AB282 | AC53: =AC45/AC282 | AD53: =AD45/AD282 | AE53: =AE45/AE282 | ... AG53: =AG45/AG282
C54: GAAP EPS (Diluted) | F54: =(F45)/F284 -> 36.317191 | G54: =(G45)/G284 -> 29.68059 | H54: =(H45)/H284 -> 24.635688 | I54: =(I45)/I284 -> 28.659176 | J54: =J45/J284 -> 2.8888889 | K54: =(K45)/K284 -> 41.060533 | L54: =(L45)/L284 -> 29.036855 | M54: =(M45)/M284 -> 26.577447 | N54: =(N45)/N284 -> 18.397004 | O54: =O45/O284 -> 5.3445693 | P54: =(P45)/P284 -> 48.055556 | Q54: =(Q45)/Q284 -> 32.908367 | R54: =(R45)/R284 -> 31.079576 | S54: =(S45)/S284 -> 36.621333 | T54: =T45/T284 -> 7.78 | U54: =(U45)/U284 -> 58.468056 | V54: =(V45)/V284 -> 34.369165 | W54: =(W45)/W284 -> 2.7398844 | X54: =X45/X284 | Y54: =Y45/Y284 | Z54: =Z45/Z284 | AA54: =AA45/AA284 | AB54: =AB45/AB284 | AC54: =AC45/AC284 | AD54: =AD45/AD284 | AE54: =AE45/AE284 | ... AG54: =AG45/AG284
C56: Adj. EPS (Basic) | F56: =F51/F282 -> 36.361212 | G56: =G51/G282 -> 29.717097 | H56: =H51/H282 -> 24.666253 | I56: =I51/I282 -> 28.659176 | J56: =J51/J282 -> 5.1942447 | K56: =K51/K282 -> 41.110303 | L56: =L51/L282 -> 29.072571 | M56: =M51/M282 -> 26.610422 | ... AG56: =AG51/AG282
C57: Adj. EPS (Diluted) | F57: =F51/F284 -> 36.317191 | G57: =G51/G284 -> 29.68059 | H57: =H51/H284 -> 24.635688 | I57: =I51/I284 -> 28.659176 | J57: =J51/J284 -> 5.1942447 | K57: =K51/K284 -> 41.060533 | L57: =L51/L284 -> 29.036855 | M57: =M51/M284 -> 26.577447 | ... AG57: =AG51/AG284
C59: EBIT | F59: =F51-F44-F41-F40-F39-F38 -> 36016 | G59: =G51-G44-G41-G40-G39-G38 -> 28318 | H59: =H51-H44-H41-H40-H39-H38 -> 22998 | I59: =I51-I44-I41-I40-I39-I38 -> 26969 | J59: =SUM(F59:I59) -> 5864.59 | K59: =K51-K44-K41-K40-K39-K38 -> 40373 | L59: =L51-L44-L41-L40-L39-L38 -> 27900 | M59: =M51-M44-M41-M40-M39-M38 -> 25352 | N59: =N51-N44-N41-N40-N39-N38 -> 29591 | O59: =SUM(K59:N59) -> 6502.5 | P59: =P51-P44-P41-P40-P39-P38 -> 42832 | Q59: =Q51-Q44-Q41-Q40-Q39-Q38 -> 29589 | R59: =R51-R44-R41-R40-R39-R38 -> 28202 | S59: =S51-S44-S41-S40-S39-S38 -> 32427 | T59: =SUM(P59:S59) -> 11713.87 | U59: =U51-U44-U41-U40-U39-U38 -> 50852 | V59: =V51-V44-V41-V40-V39-V38 -> 35885 | W59: =W51-W44-W41-W40-W39-W38 -> 2782 | X59: =X51-X44-X41-X40-X39-X38 | Y59: =SUM(U59:X59) | Z59: =Z51-Z44-Z41-Z40-Z39-Z38 | AA59: =AA51-AA44-AA41-AA40-AA39-AA38 | AB59: =AB51-AB44-AB41-AB40-AB39-AB38 | AC59: =AC51-AC44-AC41-AC40-AC39-AC38 | AD59: =SUM(Z59:AC59) | AE59: =AE51-AE44-AE41-AE40-AE39-AE38 | AF59: =AF51-AF44-AF41-AF40-AF39-AF38 | AG59: =AG51-AG44-AG41-AG40-AG39-AG38
C60: Depreciation & Amortization | F60: =-F34 -> 1e-12 | G60: =-G34 -> 1e-12 | H60: =-H34 -> 1e-12 | I60: =-I34 -> 339 | J60: =SUM(F60:I60) -> 1477 | K60: =-K34 -> 1e-12 | L60: =-L34 -> 1e-12 | M60: =-M34 -> 1e-12 | N60: =-N34 -> 1e-12 | O60: =SUM(K60:N60) -> 1262 | P60: =-P34 -> 326 | Q60: =-Q34 -> 327 | R60: =-R34 -> 355 | S60: =-S34 -> 1e-12 | T60: =SUM(P60:S60) -> 1398 | U60: =-U34 -> 1e-12 | V60: =-V34 -> 1e-12 | W60: =-W34 -> 425 | X60: =-X34 -> 331.1875 | Y60: =SUM(U60:X60) -> 1556.1875 | Z60: =-Z34 -> 331.86892 | AA60: =-AA34 -> 336.85147 | AB60: =-AB34 -> 342.23238 | AC60: =-AC34 -> 343.91087 | AD60: =SUM(Z60:AC60) -> 1354.8636 | AE60: =-AE34 -> 1420.1552 | AF60: =-AF34 -> 1472.4758 | AG60: =-AG34 -> 1524.1209
C61: EBITDA | F61: =SUM(F59:F60) -> 36016 | G61: =SUM(G59:G60) -> 28318 | H61: =SUM(H59:H60) -> 22998 | I61: =SUM(I59:I60) -> 27308 | J61: =SUM(F61:I61) -> 7341.59 | K61: =SUM(K59:K60) -> 40373 | L61: =SUM(L59:L60) -> 27900 | M61: =SUM(M59:M60) -> 25352 | N61: =SUM(N59:N60) -> 29591 | O61: =SUM(K61:N61) -> 7764.5 | P61: =SUM(P59:P60) -> 43158 | Q61: =SUM(Q59:Q60) -> 29916 | R61: =SUM(R59:R60) -> 28557 | S61: =SUM(S59:S60) -> 32427 | T61: =SUM(P61:S61) -> 13111.87 | U61: =SUM(U59:U60) -> 50852 | V61: =SUM(V59:V60) -> 35885 | W61: =SUM(W59:W60) -> 3207 | X61: =SUM(X59:X60) | Y61: =SUM(U61:X61) | Z61: =SUM(Z59:Z60) | AA61: =SUM(AA59:AA60) | AB61: =SUM(AB59:AB60) | AC61: =SUM(AC59:AC60) | AD61: =SUM(Z61:AC61) | AE61: =SUM(AE59:AE60) | AF61: =SUM(AF59:AF60) | AG61: =SUM(AG59:AG60)
C63: Income Statement Analysis | F63: =F$25 -> 1e-12 | G63: =G$25 -> 1e-12 | H63: =H$25 -> 1e-12 | I63: =I$25 -> 1e-12 | J63: =J$25 -> 2023 | K63: =K$25 -> 1e-12 | L63: =L$25 -> 1e-12 | M63: =M$25 -> 1e-12 | ... AG63: =AG$25 -> 2030e | AH63: x
A64: x | C64: Drivers
C66: Gross Margin | F66: =F30/F28 -> 0.42962255 | G66: =G30/G28 -> 0.44261673 | H66: =H30/H28 -> 0.44516303 | I66: =I30/I28 -> 0.45170842 | J66: =J30/J28 -> 0.32124977 | K66: =K30/K28 -> 0.45874974 | L66: =L30/L28 -> 0.46578075 | M66: =M30/M28 -> 0.46257155 | ... W66: =W30/W28 -> 0.33104983 | X66: =IF(Cover!$F$37="Bottom Up",(X30/X28),Drivers!X7) -> 0.13 | Y66: =Y30/Y28 -> 0.28815441 | Z66: =IF(Cover!$F$37="Bottom Up",(Z30/Z28),Drivers!Z7) -> 0.14 | AA66: =IF(Cover!$F$37="Bottom Up",(AA30/AA28),Drivers!AA7) -> 0.145 | AB66: =IF(Cover!$F$37="Bottom Up",(AB30/AB28),Drivers!AB7) -> 0.12 | AC66: =IF(Cover!$F$37="Bottom Up",(AC30/AC28),Drivers!AC7) -> 0.135 | AD66: =AD30/AD28 -> 0.13533006 | AE66: =IF(Cover!$F$37="Bottom Up",(AE30/AE28),Drivers!AE7) -> 0.139 | AF66: =IF(Cover!$F$37="Bottom Up",(AF30/AF28),Drivers!AF7) -> 0.14 | AG66: =IF(Cover!$F$37="Bottom Up",(AG30/AG28),Drivers!AG7) -> 0.142
C67: SG&A as % of Revenue | F67: =F32/F28 -> -0.056395855 | G67: =G32/G28 -> -0.065386562 | H67: =H32/H28 -> -0.073022238 | I67: =I32/I28 -> -0.068727793 | J67: =J32/J28 -> -0.24419078 | K67: =K32/K28 -> -0.056750993 | L67: =L32/L28 -> -0.071270371 | M67: =M32/M28 -> -0.073679425 | ... W67: =W32/W28 -> -0.19081072 | X67: =Drivers!X40 -> -0.22 | Y67: =Y32/Y28 -> -0.18979586 | Z67: =Drivers!Z40 -> -0.225 | AA67: =Drivers!AA40 -> -0.225 | AB67: =Drivers!AB40 -> -0.22 | AC67: =Drivers!AC40 -> -0.22 | AD67: =AD32/AD28 -> -0.22261215 | AE67: =Drivers!AE40 -> -0.215 | AF67: =Drivers!AF40 -> -0.211 | AG67: =Drivers!AG40 -> -0.206
C68: R&D as a % of Revenue | F68: =F33/F28 -> -0.065802277 | G68: =G33/G28 -> -0.078630478 | H68: =H33/H28 -> -0.090981332 | I68: =I33/I28 -> -0.081644283 | J68: =J33/J28 | K68: =K33/K28 -> -0.06436128 | L68: =L33/L28 -> -0.087082521 | M68: =M33/M28 -> -0.093335043 | ... W68: =W33/W28 | X68: =Drivers!X45 -> 0 | Y68: =Y33/Y28 -> 0 | Z68: =Drivers!Z45 -> 0 | AA68: =Drivers!AA45 -> 0 | AB68: =Drivers!AB45 -> 0 | AC68: =Drivers!AC45 -> 0 | AD68: =AD33/AD28 -> 0 | AE68: =Drivers!AE45 -> 0 | AF68: =Drivers!AF45 -> 0 | AG68: =Drivers!AG45 -> 0
C69: Other Operating Income as a % of Revenue | F69: =F35/F28 -> 1e-12 | G69: =G35/G28 -> 1e-12 | H69: =H35/H28 -> 1e-12 | I69: =I35/I28 -> 1e-12 | J69: =J35/J28 | K69: =K35/K28 -> 1e-12 | L69: =L35/L28 -> 1e-12 | M69: =M35/M28 -> 1e-12 | ... W69: =W35/W28 | X69: =Drivers!X50 -> 0 | Y69: =Y35/Y28 -> 0 | Z69: =Drivers!Z50 -> 0 | AA69: =Drivers!AA50 -> 0 | AB69: =Drivers!AB50 -> 0 | AC69: =Drivers!AC50 -> 0 | AD69: =AD35/AD28 -> 0 | AE69: =Drivers!AE50 -> 0 | AF69: =Drivers!AF50 -> 0 | AG69: =Drivers!AG50 -> 0
C70: Other Non-Operating Income as a % of Revenue | F70: =F41/F28 -> 0.0052068218 | G70: =G41/G28 -> 0.010481252 | H70: =H41/H28 -> 0.0089612088 | I70: =I41/I28 -> 0.01151981 | J70: =J41/J28 | K70: =K41/K28 -> 0.00093665064 | L70: =L41/L28 -> 0.0036031867 | M70: =M41/M28 -> 0.0037189456 | ... W70: =W41/W28 | X70: =Drivers!X57 -> 0 | Y70: =Y41/Y28 -> 0 | Z70: =Drivers!Z57 -> 0 | AA70: =Drivers!AA57 -> 0 | AB70: =Drivers!AB57 -> 0 | AC70: =Drivers!AC57 -> 0 | AD70: =AD41/AD28 -> 0 | AE70: =Drivers!AE57 -> 0 | AF70: =Drivers!AF57 -> 0 | AG70: =Drivers!AG57 -> 0
C71: Tax Rate | F71: =-F44/F42 -> 0.1579036 | G71: =-G44/G42 -> 0.14875625 | H71: =-H44/H42 -> 0.12545638 | I71: =-I44/I42 -> 0.14971479 | J71: =-J44/J42 -> 0.3182086 | K71: =-K44/K42 -> 0.15889195 | L71: =-L44/L42 -> 0.15760211 | M71: =-M44/M42 -> 0.15870401 | ... W71: =-W44/W42 -> 0.26110678 | X71: =Drivers!X64 -> 0.24 | Y71: =-Y44/Y42 | Z71: =Drivers!Z64 -> 0.24 | AA71: =Drivers!AA64 -> 0.24 | AB71: =Drivers!AB64 -> 0.24 | AC71: =Drivers!AC64 -> 0.24 | AD71: =-AD44/AD42 | AE71: =Drivers!AE64 -> 0.24 | AF71: =Drivers!AF64 -> 0.24 | AG71: =Drivers!AG64 -> 0.24
A73: x | C73: Cash Flow Statement | F73: =F$25 -> 1e-12 | G73: =G$63 -> 2Q23 | H73: =H$63 -> 3Q23 | I73: =I$63 -> 4Q23 | J73: =J$63 -> 2023 | K73: =K$63 -> 1Q24 | L73: =L$63 -> 2Q24 | M73: =M$63 -> 3Q24 | N73: =N$63 -> 4Q24 | ... AG73: =AG$63 -> 2030e | AH73: x
C75: Net Income | X75: =X45 | Y75: =SUM(U75:X75) | Z75: =Z45 | AA75: =AA45 | AB75: =AB45 | AC75: =AC45 | AD75: =SUM(Z75:AC75) | AE75: =AE45 | AF75: =AF45 | AG75: =AG45
C76: Depreciation & Amortization | X76: =-(X194+X208) -> 331.1875 | Y76: =SUM(U76:X76) -> 331.1875 | Z76: =-(Z194+Z208) -> 331.86892 | AA76: =-(AA194+AA208) -> 336.85147 | AB76: =-(AB194+AB208) -> 342.23238 | AC76: =-(AC194+AC208) -> 343.91087 | AD76: =SUM(Z76:AC76) -> 1354.8636 | AE76: =-(AE194+AE208) -> 1420.1552 | AF76: =-(AF194+AF208) -> 1472.4758 | AG76: =-(AG194+AG208) -> 1524.1209
C77: Stock-Based Compensation | X77: =X246 -> 51.3 | Y77: =SUM(U77:X77) -> 51.3 | Z77: =Z246 -> 60.534 | AA77: =AA246 -> 69.00876 | AB77: =AB246 -> 60.727709 | AC77: =AC246 -> 57.691323 | AD77: =SUM(Z77:AC77) -> 247.96179 | AE77: =AE246 -> 252.92103 | AF77: =AF246 -> 257.97945 | AG77: =AG246 -> 263.13904
C78: (Increase)/Decrease in Working Capital | X78: =X174 -> 1905.8581 | Y78: =SUM(U78:X78) -> 1905.8581 | Z78: =Z174 -> -3218.8031 | AA78: =AA174 -> 1362.698 | AB78: =AB174 -> 1373.9746 | AC78: =AC174 -> -901.36477 | AD78: =SUM(Z78:AC78) -> -1383.4953 | AE78: =AE174 -> 935.23976 | AF78: =AF174 -> 49.70914 | AG78: =AG174 -> 44.917897
C79: (Increase)/Decrease in LT Items | X79: =X228 -> -112.52 | Y79: =SUM(U79:X79) -> -112.52 | Z79: =Z228 -> -114.7704 | AA79: =AA228 -> -117.06581 | AB79: =AB228 -> -119.40712 | AC79: =AC228 -> -121.79527 | AD79: =SUM(Z79:AC79) -> -473.0386 | AE79: =AE228 -> -124.23117 | AF79: =AF228 -> -126.7158 | AG79: =AG228 -> -129.25011
C80: Net Cash From Operating Activities | X80: =SUM(X75:X79) | Y80: =SUM(U80:X80) | Z80: =SUM(Z75:Z79) | AA80: =SUM(AA75:AA79) | AB80: =SUM(AB75:AB79) | AC80: =SUM(AC75:AC79) | AD80: =SUM(Z80:AC80) | AE80: =SUM(AE75:AE79) | AF80: =SUM(AF75:AF79) | AG80: =SUM(AG75:AG79)
C82: Capital Expenditures | X82: =-X193 -> -370.1257 | Y82: =SUM(U82:X82) -> -370.1257 | Z82: =-Z193 -> -616.58587 | AA82: =-AA193 -> -644.33224 | AB82: =-AB193 -> -438.14592 | AC82: =-AC193 -> -416.23862 | AD82: =SUM(Z82:AC82) -> -2115.3027 | AE82: =-AE193 -> -2146.8312 | AF82: =-AF193 -> -2189.7678 | AG82: =-AG193 -> -2345.2413
C83: Purchases of Intangibles | X83: =-X207 -> 0 | Y83: =SUM(U83:X83) | Z83: =-Z207 -> 0 | AA83: =-AA207 | AB83: =-AB207 | AC83: =-AC207 | AD83: =SUM(Z83:AC83) | AE83: =-AE207 -> 0 | AF83: =-AF207 | AG83: =-AG207
C84: Proceeds From/(Acquisitions of) Businesses | X84: =Drivers!X97 -> 0 | Y84: =SUM(U84:X84) | Z84: =Drivers!Z97 -> 0 | AA84: =Drivers!AA97 -> 0 | AB84: =Drivers!AB97 -> 0 | AC84: =Drivers!AC97 -> 0 | AD84: =SUM(Z84:AC84) | AE84: =Drivers!AE97 -> 0 | AF84: =Drivers!AF97 -> 0 | AG84: =Drivers!AG97 -> 0
C85: Net Cash From Investment Activities | X85: =SUM(X82:X84) -> -370.1257 | Y85: =SUM(U85:X85) -> -370.1257 | Z85: =SUM(Z82:Z84) -> -616.58587 | AA85: =SUM(AA82:AA84) -> -644.33224 | AB85: =SUM(AB82:AB84) -> -438.14592 | AC85: =SUM(AC82:AC84) -> -416.23862 | AD85: =SUM(Z85:AC85) -> -2115.3027 | AE85: =SUM(AE82:AE84) -> -2146.8312 | AF85: =SUM(AF82:AF84) -> -2189.7678 | AG85: =SUM(AG82:AG84) -> -2345.2413
C87: Cash Flow Available for Financing Activities | X87: =SUM(X80,X85) | Y87: =SUM(U87:X87) | Z87: =SUM(Z80,Z85) | AA87: =SUM(AA80,AA85) | AB87: =SUM(AB80,AB85) | AC87: =SUM(AC80,AC85) | AD87: =SUM(Z87:AC87) | AE87: =SUM(AE80,AE85) | AF87: =SUM(AF80,AF85) | AG87: =SUM(AG80,AG85)
C89: Issuance/(Repayment) of Revolver | X89: =X303 | Y89: =SUM(U89:X89) | Z89: =Z303 | AA89: =AA303 | AB89: =AB303 | AC89: =AC303 | AD89: =SUM(Z89:AC89) | AE89: =AE303 | AF89: =AF303 | AG89: =AG303
C90: Issuance of Debt | X90: =X308 -> 0 | Y90: =SUM(U90:X90) | Z90: =Z308 -> 0 | AA90: =AA308 | AB90: =AB308 | AC90: =AC308 | AD90: =SUM(Z90:AC90) | AE90: =AE308 -> 0 | AF90: =AF308 | AG90: =AG308
C91: (Repayment of Debt) | X91: =X309 -> -500 | Y91: =SUM(U91:X91) -> -500 | Z91: =Z309 -> -500 | AA91: =AA309 -> -500 | AB91: =AB309 -> -500 | AC91: =AC309 -> -500 | AD91: =SUM(Z91:AC91) -> -2000 | AE91: =AE309 -> -1400 | AF91: =AF309 -> -1300 | AG91: =AG309 -> -1200
C92: Issuance of Equity | X92: =X245 -> 0 | Y92: =SUM(U92:X92) | Z92: =Z245 -> 0 | AA92: =AA245 | AB92: =AB245 | AC92: =AC245 | AD92: =SUM(Z92:AC92) | AE92: =AE245 -> 0 | AF92: =AF245 | AG92: =AG245
C93: (Repurchase) of Equity | X93: =-X241 -> -500 | Y93: =SUM(U93:X93) -> -500 | Z93: =-Z241 -> -500 | AA93: =-AA241 -> -500 | AB93: =-AB241 -> -500 | AC93: =-AC241 -> -500 | AD93: =SUM(Z93:AC93) -> -2000 | AE93: =-AE241 -> -3000 | AF93: =-AF241 -> -3000 | AG93: =-AG241 -> -3000
C94: Dividends Issued | X94: =-X267 -> -519.8 | Y94: =SUM(U94:X94) -> -519.8 | Z94: =-Z267 -> -506 | AA94: =-AA267 -> -494.5 | AB94: =-AB267 -> -647.45 | AC94: =-AC267 -> -597.77 | AD94: =SUM(Z94:AC94) -> -2245.72 | AE94: =-AE267 -> -2470.292 | AF94: =-AF267 -> -2717.3212 | AG94: =-AG267 -> -2989.0533
C95: Change in Noncontrolling Interests | X95: =Drivers!X106 -> 0 | Y95: =SUM(U95:X95) | Z95: =Drivers!Z106 -> 0 | AA95: =Drivers!AA106 -> 0 | AB95: =Drivers!AB106 -> 0 | AC95: =Drivers!AC106 -> 0 | AD95: =SUM(Z95:AC95) | AE95: =Drivers!AE106 -> 0 | AF95: =Drivers!AF106 -> 0 | AG95: =Drivers!AG106 -> 0
C96: Net Cash From Financing Activities | X96: =SUM(X89:X95) | Y96: =SUM(U96:X96) | Z96: =SUM(Z89:Z95) | AA96: =SUM(AA89:AA95) | AB96: =SUM(AB89:AB95) | AC96: =SUM(AC89:AC95) | AD96: =SUM(Z96:AC96) | AE96: =SUM(AE89:AE95) | AF96: =SUM(AF89:AF95) | AG96: =SUM(AG89:AG95)
C98: Effect of FX Rate Changes on Cash | X98: =Drivers!X108 -> 0 | Y98: =SUM(U98:X98) -> 0 | Z98: =Drivers!Z108 -> 0 | AA98: =Drivers!AA108 -> 0 | AB98: =Drivers!AB108 -> 0 | AC98: =Drivers!AC108 -> 0 | AD98: =SUM(Z98:AC98) -> 0 | AE98: =Drivers!AE108 -> 0 | AF98: =Drivers!AF108 -> 0 | AG98: =Drivers!AG108 -> 0
C99: Beginning Cash Adjustments | X99: 0 | Y99: =SUM(U99:X99) | Z99: 0 | AA99: 0 | AB99: 0 | AC99: 0 | AD99: =SUM(Z99:AC99) | AE99: 0 | AF99: 0 | AG99: 0
C100: Ending Cash Adjustments | X100: 0 | Y100: =SUM(U100:X100) | Z100: 0 | AA100: 0 | AB100: 0 | AC100: 0 | AD100: =SUM(Z100:AC100) | AE100: 0 | AF100: 0 | AG100: 0
C102: Beginning Cash Balance | X102: =W104+X99 -> 6673 | Y102: =X102 -> 6673 | Z102: =Y104+Z99 | AA102: =Z104+AA99 | AB102: =AA104+AB99 | AC102: =AB104+AC99 | AD102: =Z102 | AE102: =AD104+AE99 | AF102: =AE104+AF99 | AG102: =AF104+AG99
C103: Net Change in Cash | X103: =SUM(X87,X96,X98,X100) | Y103: =SUM(U103:X103) | Z103: =SUM(Z87,Z96,Z98,Z100) | AA103: =SUM(AA87,AA96,AA98,AA100) | AB103: =SUM(AB87,AB96,AB98,AB100) | AC103: =SUM(AC87,AC96,AC98,AC100) | AD103: =SUM(Z103:AC103) | AE103: =SUM(AE87,AE96,AE98,AE100) | AF103: =SUM(AF87,AF96,AF98,AF100) | AG103: =SUM(AG87,AG96,AG98,AG100)
C104: Ending Cash Balance | W104: 6673 | X104: =SUM(X102:X103) | Y104: =SUM(Y102:Y103) | Z104: =SUM(Z102:Z103) | AA104: =SUM(AA102:AA103) | AB104: =SUM(AB102:AB103) | AC104: =SUM(AC102:AC103) | AD104: =SUM(AD102:AD103) | AE104: =SUM(AE102:AE103) | ... AG104: =SUM(AG102:AG103)
A106: x | C106: Free Cash Flow Analysis | AH106: x
C108: Net Income | F108: =F45 -> 29998 | G108: =G45 -> 24160 | H108: =H45 -> 19881 | I108: =I45 -> 22956 | J108: =J45 -> 2314 | K108: =K45 -> 33916 | L108: =L45 -> 23636 | M108: =M45 -> 21448 | ... AG108: =AG45
C109: Depreciation & Amortization | F109: =-F194+-F208 -> 1e-12 | G109: =-G194+-G208 -> 1e-12 | H109: =-H194+-H208 -> 1e-12 | I109: =-I194+-I208 -> 1e-12 | J109: =SUM(F109:I109) -> 1477 | K109: =-K194+-K208 -> 1e-12 | L109: =-L194+-L208 -> 1e-12 | M109: =-M194+-M208 -> 1e-12 | N109: =-N194+-N208 -> 1e-12 | O109: =SUM(K109:N109) -> 1262 | P109: =-P194+-P208 -> 326 | Q109: =-Q194+-Q208 -> 327 | R109: =-R194+-R208 -> 355 | S109: =-S194+-S208 -> 1e-12 | T109: =SUM(P109:S109) -> 1398 | U109: =-U194+-U208 -> 1e-12 | V109: =-V194+-V208 -> 1e-12 | W109: =-W194+-W208 -> 425 | X109: =-X194+-X208 -> 331.1875 | Y109: =SUM(U109:X109) -> 1556.1875 | Z109: =-Z194+-Z208 -> 331.86892 | AA109: =-AA194+-AA208 -> 336.85147 | AB109: =-AB194+-AB208 -> 342.23238 | AC109: =-AC194+-AC208 -> 343.91087 | AD109: =SUM(Z109:AC109) -> 1354.8636 | AE109: =-AE194+-AE208 -> 1420.1552 | AF109: =-AF194+-AF208 -> 1472.4758 | AG109: =-AG194+-AG208 -> 1524.1209
C110: Change in Operating Working Capital | F110: =F178 -> 1e-12 | G110: =G178 -> 9819 | H110: =H178 -> -2272 | I110: =I178 -> -8642 | J110: =SUM(F110:I110) -> 1182 | K110: =K178 -> 32723 | L110: =L178 -> -10757 | M110: =M178 -> 930 | N110: =N178 -> 6746 | O110: =SUM(K110:N110) -> -1238 | P110: =P178 -> 30880 | Q110: =Q178 -> -3639 | R110: =R178 -> -4829 | S110: =S178 -> 7899 | T110: =SUM(P110:S110) -> 211 | U110: =U178 -> 30100 | V110: =V178 -> -4528 | W110: =W178 -> -40 | X110: =X178 -> -1855.0918 | Y110: =SUM(U110:X110) -> -1897.0918 | Z110: =Z178 -> -1777.3159 | AA110: =AA178 -> 177.74838 | AB110: =AB178 -> 916.79161 | AC110: =AC178 -> -168.43685 | AD110: =SUM(Z110:AC110) -> -851.21278 | AE110: =AE178 -> 461.05133 | AF110: =AF178 -> -142.92602 | AG110: =AG178 -> -136.42553
C111: Capital Expenditures | F111: =-F193 -> -224 | G111: =-G193 -> -319 | H111: =-H193 -> -303 | I111: =-I193 -> -328 | J111: =SUM(F111:I111) -> -1174 | K111: =-K193 -> -205 | L111: =-L193 -> -321 | M111: =-M193 -> -401 | N111: =-N193 -> -557 | O111: =SUM(K111:N111) -> -1484 | P111: =-P193 -> -328 | Q111: =-Q193 -> -382 | R111: =-R193 -> -462 | S111: =-S193 -> -557 | T111: =SUM(P111:S111) -> -1729 | U111: =-U193 -> -461 | V111: =-V193 -> -385 | W111: =-W193 -> -410 | X111: =-X193 -> -370.1257 | Y111: =SUM(U111:X111) -> -1626.1257 | Z111: =-Z193 -> -616.58587 | AA111: =-AA193 -> -644.33224 | AB111: =-AB193 -> -438.14592 | AC111: =-AC193 -> -416.23862 | AD111: =SUM(Z111:AC111) -> -2115.3027 | AE111: =-AE193 -> -2146.8312 | AF111: =-AF193 -> -2189.7678 | AG111: =-AG193 -> -2345.2413
C112: Free Cash Flow (FCF) | F112: =SUM(F108:F111) -> 29774 | G112: =SUM(G108:G111) -> 33660 | H112: =SUM(H108:H111) -> 17306 | I112: =SUM(I108:I111) -> 13986 | J112: =SUM(J108:J111) -> 3799 | K112: =SUM(K108:K111) -> 66434 | L112: =SUM(L108:L111) -> 12558 | M112: =SUM(M108:M111) -> 21977 | ... AG112: =SUM(AG108:AG111)
C114: Free Cash Flow Margin | F114: =F112/F28 -> 0.25414412 | G114: =G112/G28 -> 0.35492851 | H114: =H112/H28 -> 0.21157255 | I114: =I112/I28 -> 0.15627165 | J114: =J112/J28 -> 0.053275183 | K114: =K112/K28 -> 0.55558436 | L114: =L112/L28 -> 0.13837559 | M114: =M112/M28 -> 0.25621087 | ... AG114: =AG112/AG28
C115: Free Cash Flow per Share | F115: =F112/F282 -> 36.089697 | G115: =G112/G282 -> 41.402214 | H115: =H112/H282 -> 21.471464 | I115: =I112/I282 -> 17.460674 | J115: =J112/J282 -> 4.7428215 | K115: =K112/K282 -> 80.526061 | L115: =L112/L282 -> 15.446494 | M115: =M112/M282 -> 27.266749 | ... AG115: =AG112/AG282
C116: Free Cash Flow Yield | F116: =F115*4/F239 -> 1.678981 | G116: =G115*4/G239 -> 1.804018 | H116: =H115*4/H239 -> 0.89773028 | I116: =I115*4/I239 -> 0.62768668 | J116: =J115/J239 -> 0.050449911 | K116: =K115*4/K239 -> 3.1470859 | L116: =L115*4/L239 -> 0.60226121 | M116: =M115*4/M239 -> 1.0060603 | N116: =N115*4/N239 -> 0.99169006 | O116: =O115/O239 -> 0.033829723 | P116: =P115*4/P239 -> 3.6046657 | Q116: =Q115*4/Q239 -> 1.1354482 | R116: =R115*4/R239 -> 0.5813789 | S116: =S115*4/S239 -> 0.88841269 | T116: =T115/T239 -> 0.04539176 | U116: =U115*4/U239 -> 2.1934328 | V116: =V115*4/V239 -> 0.57612305 | W116: =W115*4/W239 -> 0.052559611 | X116: =X115*4/X239 | Y116: =Y115/Y239 | Z116: =Z115*4/Z239 | AA116: =AA115*4/AA239 | AB116: =AB115*4/AB239 | AC116: =AC115*4/AC239 | AD116: =AD115/AD239 | AE116: =AE115/AE239 | AF116: =AF115/AF239 | AG116: =AG115/AG239
A118: x | C118: Balance Sheet | F118: =F$25 -> 1e-12 | G118: =G$63 -> 2Q23 | H118: =H$63 -> 3Q23 | I118: =I$63 -> 4Q23 | J118: =J$63 -> 2023 | K118: =K$63 -> 1Q24 | L118: =L$63 -> 2Q24 | M118: =M$63 -> 3Q24 | N118: =N$63 -> 4Q24 | ... AG118: =AG$63 -> 2030e | AH118: x
C120: Cash & Cash Equivalents | F120: =1565+205 -> 1770 | G120: =2251+391 -> 2642 | H120: =1668+208 -> 1876 | I120: =511+218 -> 729 | J120: =I120 -> 729 | K120: =2973+190 -> 3163 | L120: =1796+275 -> 2071 | M120: =794+127 -> 921 | N120: =716+160 -> 876 | O120: =N120 -> 876 | P120: 30299 | Q120: 28162 | R120: 36269 | S120: 45317 | T120: =S120 -> 5196 | U120: =6692+454 -> 7146 | V120: =4835+1420 -> 6255 | W120: =6121+552 -> 6673 | X120: =X104 | Y120: =X120 -> #REF! | Z120: =Z104 -> #REF! | AA120: =AA104 | AB120: =AB104 | AC120: =AC104 | AD120: =AC120 -> #REF! | AE120: =AE104 -> #REF! | AF120: =AF104 | AG120: =AG104
C121: Accounts Receivable | F121: 23752 | G121: 17936 | H121: 19549 | I121: 23194 | J121: =I121 | K121: 23194 | L121: 21837 | M121: 22795 | N121: 29639 | O121: =N121 | P121: 29639 | Q121: 26136 | R121: 27557 | S121: 39921 | T121: =S121 | U121: 39921 | V121: 30339 | W121: 0 | X121: =X162 -> 0 | Y121: =X121 -> 0 | Z121: =Z162 -> 0 | AA121: =AA162 -> 0 | AB121: =AB162 -> 0 | AC121: =AC162 -> 0 | AD121: =AC121 -> 0 | AE121: =AE162 -> 0 | AF121: =AF162 -> 0 | AG121: =AG162 -> 0
C122: Inventory | F122: 6820 | G122: 7482 | H122: 7351 | I122: 6511 | J122: =I122 -> 12561 | K122: 6511 | L122: 6232 | M122: 6165 | N122: 6911 | O122: =N122 -> 13179 | P122: 6911 | Q122: 6269 | R122: 5925 | S122: 5875 | T122: =S122 -> 16193 | U122: 5875 | V122: 6747 | W122: 16685 | X122: =X163 -> 18529.95 | Y122: =X122 -> 18529.95 | Z122: =Z163 -> 23065.506 | AA122: =AA163 -> 22014.148 | AB122: =AB163 -> 20954.805 | AC122: =AC163 -> 20718.783 | AD122: =AC122 -> 20718.783 | AE122: =AE163 -> 21269.509 | AF122: =AF163 -> 21669.702 | AG122: =AG163 -> 22051.693
C123: Prepaid & Other Current Assets | F123: 77670 | G123: 62808 | H123: 67351 | I123: 73101 | J123: =I123 -> 938 | K123: 73227 | L123: 67652 | M123: 70910 | N123: 86138 | O123: =N123 -> 1263 | P123: 66391 | Q123: 58107 | R123: 52740 | S123: 56844 | T123: =S123 -> 937 | U123: 66991 | V123: 61456 | W123: 1491 | X123: =X164 -> 0 | Y123: =X123 -> 0 | Z123: =Z164 -> 1849.7576 | AA123: =AA164 -> 2108.7237 | AB123: =AB164 -> 1855.6768 | AC123: =AC164 -> 1762.893 | AD123: =AC123 -> 1762.893 | AE123: =AE164 -> 1932.148 | AF123: =AF164 -> 1970.791 | AG123: =AG164 -> 2010.2068
C124: Total Current Assets | F124: =SUM(F120:F123) -> 110012 | G124: =SUM(G120:G123) -> 90868 | H124: =SUM(H120:H123) -> 96127 | I124: =SUM(I120:I123) -> 103535 | J124: =I124 -> 14228 | K124: =SUM(K120:K123) -> 106095 | L124: =SUM(L120:L123) -> 97792 | M124: =SUM(M120:M123) -> 100791 | N124: =SUM(N120:N123) -> 123564 | O124: =N124 -> 15318 | P124: =SUM(P120:P123) -> 133240 | Q124: =SUM(Q120:Q123) -> 118674 | R124: =SUM(R120:R123) -> 122491 | S124: =SUM(S120:S123) -> 147957 | T124: =S124 -> 22326 | U124: =SUM(U120:U123) -> 119933 | V124: =SUM(V120:V123) -> 104797 | W124: =SUM(W120:W123) -> 24849 | X124: =SUM(X120:X123) | Y124: =X124 | Z124: =SUM(Z120:Z123) -> #REF! | AA124: =SUM(AA120:AA123) | AB124: =SUM(AB120:AB123) | AC124: =SUM(AC120:AC123) | AD124: =AC124 | AE124: =SUM(AE120:AE123) -> #REF! | AF124: =SUM(AF120:AF123) | AG124: =SUM(AG120:AG123)
C126: PP&E, Net | F126: 42951 | G126: 43398 | H126: 43550 | I126: 43666 | J126: =I126 -> 18432 | K126: 43666 | L126: 43546 | M126: 44502 | N126: 46069 | O126: =N126 -> 18669 | P126: 46069 | Q126: 46876 | R126: 48508 | S126: 50159 | T126: =S126 -> 22987 | U126: 50159 | V126: 50116 | W126: 18925 | X126: =X196 -> 18963.938 | Y126: =X126 -> 18963.938 | Z126: =Z196 -> 19248.655 | AA126: =AA196 -> 19556.136 | AB126: =AB196 -> 19652.049 | AC126: =AC196 -> 19724.377 | AD126: =AC126 -> 19724.377 | AE126: =AE196 -> 20451.053 | AF126: =AF196 -> 21168.345 | AG126: =AG196 -> 21989.466
C127: Intangible Assets, Net | F127: 0 | G127: 0 | H127: 0 | I127: 0 | J127: =I127 | K127: 0 | L127: 0 | M127: 0 | N127: 0 | O127: =N127 | P127: 0 | Q127: 0 | R127: 13301 | S127: 13301 | T127: =S127 | U127: 25797 | V127: 25797 | W127: 0 | X127: =X210 -> 0 | Y127: =X127 -> 0 | Z127: =Z210 -> 0 | AA127: =AA210 -> 0 | AB127: =AB210 -> 0 | AC127: =AC210 -> 0 | AD127: =AC127 -> 0 | AE127: =AE210 -> 0 | AF127: =AF210 -> 0 | AG127: =AG210 -> 0
C128: Goodwill | F128: 0 | G128: 0 | H128: 0 | I128: 0 | J128: =I128 -> 303 | K128: 0 | L128: 0 | M128: 0 | N128: 0 | O128: =N128 -> 303 | P128: 0 | Q128: 0 | R128: 0 | S128: 0 | T128: =S128 -> 311 | U128: 0 | V128: 0 | W128: 0 | X128: =X218 -> 0 | Y128: =X128 -> 0 | Z128: =Z218 -> 0 | AA128: =AA218 -> 0 | AB128: =AB218 -> 0 | AC128: =AC218 -> 0 | AD128: =AC128 -> 0 | AE128: =AE218 -> 0 | AF128: =AF218 -> 0 | AG128: =AG218 -> 0
...

Sheet Segment Analysis
C1: =Company_Name&" - "&MID(CELL("filename",A1),FIND("]",CELL("filename",A1))+1,255)&": "&Case_Scenario&" Case" -> Lowe's Companies, Inc. - Segment Analysis: Base Case
C2: =Cover!C2 -> $ in Millions Except Per Share Data
C5: Segment Analysis | F5: =Model!F63 -> 1Q23 | G5: =Model!G63 -> 2Q23 | H5: =Model!H63 -> 3Q23 | I5: =Model!I63 -> 4Q23 | J5: =Model!J63 -> 2023 | K5: =Model!K63 -> 1Q24 | L5: =Model!L63 -> 2Q24 | M5: =Model!M63 -> 3Q24 | ... AG5: =Model!AG63 -> 2030e
C6: Drivers
C7: Total Company Revenue | F7: =SUM(F8:F13) -> 117154 | G7: =SUM(G8:G13) -> 94836 | H7: =SUM(H8:H13) -> 81797 | I7: =SUM(I8:I13) -> 89498 | J7: =SUM(F7:I7) -> 71309 | K7: =SUM(K8:K13) -> 119575 | L7: =SUM(L8:L13) -> 90753 | M7: =SUM(M8:M13) -> 85777 | N7: =SUM(N8:N13) -> 94930 | O7: =SUM(K7:N7) -> 72148 | P7: =SUM(P8:P13) -> 124300 | Q7: =SUM(Q8:Q13) -> 95359 | R7: =SUM(R8:R13) -> 94036 | S7: =SUM(S8:S13) -> 102466 | T7: =SUM(P7:S7) -> 89597 | U7: =SUM(U8:U13) -> 143756 | V7: =SUM(V8:V13) -> 111184 | W7: =SUM(W8:W13) -> 22918 | X7: =SUM(X8:X13) -> 21772.1 | Y7: =SUM(U7:X7) -> 96682.1 | Z7: =SUM(Z8:Z13) -> 25691.078 | AA7: =SUM(AA8:AA13) -> 29287.829 | AB7: =SUM(AB8:AB13) -> 25773.289 | AC7: =SUM(AC8:AC13) -> 24484.625 | AD7: =SUM(Z7:AC7) -> 105236.82 | AE7: =SUM(AE8:AE13) -> 107341.56 | AF7: =SUM(AF8:AF13) -> 109488.39 | AG7: =SUM(AG8:AG13) -> 111678.16
C8: =C16&" Revenue" -> Services Revenue | F8: 20766 | G8: 20907 | H8: 21213 | I8: =85200-SUM(F8:H8) -> 22314 | J8: =SUM(F8:I8) -> 71309 | K8: 23117 | L8: 23867 | M8: 24213 | N8: 24972 | O8: =SUM(K8:N8) -> 72148 | P8: 26340 | Q8: 26645 | R8: 27423 | S8: 28750 | T8: =SUM(P8:S8) -> 89597 | U8: 30013 | V8: 30976 | W8: 22918 | X8: ='Revenue Build'!X32 -> 21772.1 | Y8: =SUM(U8:X8) -> 96682.1 | Z8: ='Revenue Build'!Z32 -> 25691.078 | AA8: ='Revenue Build'!AA32 -> 29287.829 | AB8: ='Revenue Build'!AB32 -> 25773.289 | AC8: ='Revenue Build'!AC32 -> 24484.625 | AD8: =SUM(Z8:AC8) -> 105236.82 | AE8: ='Revenue Build'!AE32 -> 107341.56 | AF8: ='Revenue Build'!AF32 -> 109488.39 | AG8: ='Revenue Build'!AG32 -> 111678.16
C9: =C17&" Revenue" -> iPhone Revenue | F9: 65775 | G9: 51334 | H9: 39669 | I9: 43805 | J9: =SUM(F9:I9) | K9: 69702 | L9: 45963 | M9: 39296 | N9: 46222 | O9: =SUM(K9:N9) | P9: 69138 | Q9: 46841 | R9: 44582 | S9: 49025 | T9: =SUM(P9:S9) | U9: 85269 | V9: 56994 | W9: 0 | X9: ='Revenue Build'!X35 -> 0 | Y9: =SUM(U9:X9) | Z9: ='Revenue Build'!Z35 -> 0 | AA9: ='Revenue Build'!AA35 -> 0 | AB9: ='Revenue Build'!AB35 -> 0 | AC9: ='Revenue Build'!AC35 -> 0 | AD9: =SUM(Z9:AC9) | AE9: ='Revenue Build'!AE35 -> 0 | AF9: ='Revenue Build'!AF35 -> 0 | AG9: ='Revenue Build'!AG35 -> 0
C10: =C18&" Revenue" -> Mac Revenue | F10: 7735 | G10: 7168 | H10: 6840 | I10: 7614 | J10: =SUM(F10:I10) | K10: 7780 | L10: 7451 | M10: 7009 | N10: 7744 | O10: =SUM(K10:N10) | P10: 8987 | Q10: 7949 | R10: 8046 | S10: 8726 | T10: =SUM(P10:S10) | U10: 8386 | V10: 8399 | W10: 0 | X10: ='Revenue Build'!X38 -> 0 | Y10: =SUM(U10:X10) | Z10: ='Revenue Build'!Z38 -> 0 | AA10: ='Revenue Build'!AA38 -> 0 | AB10: ='Revenue Build'!AB38 -> 0 | AC10: ='Revenue Build'!AC38 -> 0 | AD10: =SUM(Z10:AC10) | AE10: ='Revenue Build'!AE38 -> 0 | AF10: ='Revenue Build'!AF38 -> 0 | AG10: ='Revenue Build'!AG38 -> 0
C11: =C19&" Revenue" -> iPad Revenue | F11: 9396 | G11: 6670 | H11: 5791 | I11: 6443 | J11: =SUM(F11:I11) | K11: 7023 | L11: 5559 | M11: 7162 | N11: 6950 | O11: =SUM(K11:N11) | P11: 8088 | Q11: 6402 | R11: 6581 | S11: 6952 | T11: =SUM(P11:S11) | U11: 8595 | V11: 6914 | W11: 0 | X11: ='Revenue Build'!X41 -> 0 | Y11: =SUM(U11:X11) | Z11: ='Revenue Build'!Z41 -> 0 | AA11: ='Revenue Build'!AA41 -> 0 | AB11: ='Revenue Build'!AB41 -> 0 | AC11: ='Revenue Build'!AC41 -> 0 | AD11: =SUM(Z11:AC11) | AE11: ='Revenue Build'!AE41 -> 0 | AF11: ='Revenue Build'!AF41 -> 0 | AG11: ='Revenue Build'!AG41 -> 0
C12: =C20&" Revenue" -> Wearables, Home and Accessories Revenue | F12: 13482 | G12: 8757 | H12: 8284 | I12: 9322 | J12: =SUM(F12:I12) | K12: 11953 | L12: 7913 | M12: 8097 | N12: 9042 | O12: =SUM(K12:N12) | P12: 11747 | Q12: 7522 | R12: 7404 | S12: 9013 | T12: =SUM(P12:S12) | U12: 11493 | V12: 7901 | W12: 0 | X12: ='Revenue Build'!X44 -> 0 | Y12: =SUM(U12:X12) | Z12: ='Revenue Build'!Z44 -> 0 | AA12: ='Revenue Build'!AA44 -> 0 | AB12: ='Revenue Build'!AB44 -> 0 | AC12: ='Revenue Build'!AC44 -> 0 | AD12: =SUM(Z12:AC12) | AE12: ='Revenue Build'!AE44 -> 0 | AF12: ='Revenue Build'!AF44 -> 0 | AG12: ='Revenue Build'!AG44 -> 0
C13: =C21&" Revenue" -> Segment 6 Revenue | F13: 0 | G13: 0 | H13: 0 | I13: 0 | J13: =SUM(F13:I13) | K13: 0 | L13: 0 | M13: 0 | N13: 0 | O13: =SUM(K13:N13) | P13: 0 | Q13: 0 | R13: 0 | S13: 0 | T13: =SUM(P13:S13) | U13: 0 | V13: 0 | W13: 0 | X13: ='Revenue Build'!X47 -> 0 | Y13: =SUM(U13:X13) | Z13: ='Revenue Build'!Z47 -> 0 | AA13: ='Revenue Build'!AA47 -> 0 | AB13: ='Revenue Build'!AB47 -> 0 | AC13: ='Revenue Build'!AC47 -> 0 | AD13: =SUM(Z13:AC13) | AE13: ='Revenue Build'!AE47 -> 0 | AF13: ='Revenue Build'!AF47 -> 0 | AG13: ='Revenue Build'!AG47 -> 0
C15: Revenue Mix
C16: Services | F16: =IFERROR(F8/F$7,"N/A") -> 1 | G16: =IFERROR(G8/G$7,"N/A") -> 1 | H16: =IFERROR(H8/H$7,"N/A") -> 1 | I16: =IFERROR(I8/I$7,"N/A") -> 1 | J16: =IFERROR(J8/J$7,"N/A") -> 1 | K16: =IFERROR(K8/K$7,"N/A") -> 1 | L16: =IFERROR(L8/L$7,"N/A") -> 1 | M16: =IFERROR(M8/M$7,"N/A") -> 1 | ... AG16: =IFERROR(AG8/AG$7,"N/A") -> 1
C17: iPhone | F17: =IFERROR(F9/F$7,"N/A") -> 0 | G17: =IFERROR(G9/G$7,"N/A") | H17: =IFERROR(H9/H$7,"N/A") | I17: =IFERROR(I9/I$7,"N/A") | J17: =IFERROR(J9/J$7,"N/A") | K17: =IFERROR(K9/K$7,"N/A") | L17: =IFERROR(L9/L$7,"N/A") | M17: =IFERROR(M9/M$7,"N/A") | ... AG17: =IFERROR(AG9/AG$7,"N/A")
C18: Mac | F18: =IFERROR(F10/F$7,"N/A") -> 0 | G18: =IFERROR(G10/G$7,"N/A") | H18: =IFERROR(H10/H$7,"N/A") | I18: =IFERROR(I10/I$7,"N/A") | J18: =IFERROR(J10/J$7,"N/A") | K18: =IFERROR(K10/K$7,"N/A") | L18: =IFERROR(L10/L$7,"N/A") | M18: =IFERROR(M10/M$7,"N/A") | ... AG18: =IFERROR(AG10/AG$7,"N/A")
C19: Other / Reconciliation | F19: =IFERROR(F11/F$7,"N/A") -> 0 | G19: =IFERROR(G11/G$7,"N/A") | H19: =IFERROR(H11/H$7,"N/A") | I19: =IFERROR(I11/I$7,"N/A") | J19: =IFERROR(J11/J$7,"N/A") | K19: =IFERROR(K11/K$7,"N/A") | L19: =IFERROR(L11/L$7,"N/A") | M19: =IFERROR(M11/M$7,"N/A") | ... AG19: =IFERROR(AG11/AG$7,"N/A")
C20: Wearables, Home and Accessories | F20: =IFERROR(F12/F$7,"N/A") -> 0 | G20: =IFERROR(G12/G$7,"N/A") | H20: =IFERROR(H12/H$7,"N/A") | I20: =IFERROR(I12/I$7,"N/A") | J20: =IFERROR(J12/J$7,"N/A") | K20: =IFERROR(K12/K$7,"N/A") | L20: =IFERROR(L12/L$7,"N/A") | M20: =IFERROR(M12/M$7,"N/A") | ... AG20: =IFERROR(AG12/AG$7,"N/A")
C21: Segment 6 | F21: =IFERROR(F13/F$7,"N/A") -> 0 | G21: =IFERROR(G13/G$7,"N/A") | H21: =IFERROR(H13/H$7,"N/A") | I21: =IFERROR(I13/I$7,"N/A") | J21: =IFERROR(J13/J$7,"N/A") | K21: =IFERROR(K13/K$7,"N/A") | L21: =IFERROR(L13/L$7,"N/A") | M21: =IFERROR(M13/M$7,"N/A") | ... AG21: =IFERROR(AG13/AG$7,"N/A")
C23: "" | F23: =SUM(F24:F26) -> 1e-12 | G23: =SUM(G24:G26) -> 1e-12 | H23: =SUM(H24:H26) -> 1e-12 | I23: =SUM(I24:I26) -> 1e-12 | J23: =SUM(F23:I23) -> 0 | K23: =SUM(K24:K26) -> 1e-12 | L23: =SUM(L24:L26) -> 1e-12 | M23: =SUM(M24:M26) -> 1e-12 | N23: =SUM(N24:N26) -> 1e-12 | O23: =SUM(K23:N23) -> 0 | P23: =SUM(P24:P26) -> 1e-12 | Q23: =SUM(Q24:Q26) -> 1e-12 | R23: =SUM(R24:R26) -> 1e-12 | S23: =SUM(S24:S26) -> 1e-12 | T23: =SUM(P23:S23) -> 0 | U23: =SUM(U24:U26) -> 1e-12 | V23: =SUM(V24:V26) -> 1e-12 | W23: =SUM(W24:W26) | X23: =SUM(X24:X26) | Y23: =SUM(U23:X23) -> 0 | Z23: =SUM(Z24:Z26) -> 0 | AA23: =SUM(AA24:AA26) | AB23: =SUM(AB24:AB26) | AC23: =SUM(AC24:AC26) | AD23: =SUM(Z23:AC23) -> 0 | AE23: =SUM(AE24:AE26) -> 0 | AF23: =SUM(AF24:AF26) | AG23: =SUM(AG24:AG26)
C24: =C29&" Revenue" -> Boeing Military Aircraft Revenue | F24: 0 | G24: 0 | H24: 0 | I24: 0 | J24: =SUM(F24:I24) | K24: 0 | L24: 0 | M24: 0 | N24: 0 | O24: =SUM(K24:N24) | P24: 0 | Q24: 0 | R24: 0 | S24: 0 | T24: =SUM(P24:S24) | U24: 0 | V24: 0 | W24: 0 | X24: 0 | Y24: =SUM(U24:X24) | Z24: 0 | AA24: 0 | AB24: 0 | AC24: 0 | AD24: =SUM(Z24:AC24) | AE24: 0 | AF24: 0 | AG24: 0
C25: =C30&" Revenue" -> Network & Space Systems Revenue | F25: 0 | G25: 0 | H25: 0 | I25: 0 | J25: =SUM(F25:I25) | K25: 0 | L25: 0 | M25: 0 | N25: 0 | O25: =SUM(K25:N25) | P25: 0 | Q25: 0 | R25: 0 | S25: 0 | T25: =SUM(P25:S25) | U25: 0 | V25: 0 | W25: 0 | X25: 0 | Y25: =SUM(U25:X25) | Z25: 0 | AA25: 0 | AB25: 0 | AC25: 0 | AD25: =SUM(Z25:AC25) | AE25: 0 | AF25: 0 | AG25: 0
C26: =C31&" Revenue" -> Global Services & Support Revenue | F26: 0 | G26: 0 | H26: 0 | I26: 0 | J26: =SUM(F26:I26) | K26: 0 | L26: 0 | M26: 0 | N26: 0 | O26: =SUM(K26:N26) | P26: 0 | Q26: 0 | R26: 0 | S26: 0 | T26: =SUM(P26:S26) | U26: 0 | V26: 0 | W26: 0 | X26: 0 | Y26: =SUM(U26:X26) | Z26: 0 | AA26: 0 | AB26: 0 | AC26: 0 | AD26: =SUM(Z26:AC26) | AE26: 0 | AF26: 0 | AG26: 0
C28: ""
C29: Boeing Military Aircraft | F29: =IFERROR(F24/F$23,"N/A") -> N/A | G29: =IFERROR(G24/G$23,"N/A") -> N/A | H29: =IFERROR(H24/H$23,"N/A") -> N/A | I29: =IFERROR(I24/I$23,"N/A") -> N/A | J29: =IFERROR(J24/J$23,"N/A") -> N/A | K29: =IFERROR(K24/K$23,"N/A") -> N/A | L29: =IFERROR(L24/L$23,"N/A") -> N/A | M29: =IFERROR(M24/M$23,"N/A") -> N/A | ... AG29: =IFERROR(AG24/AG$23,"N/A") -> N/A
C30: Network & Space Systems | F30: =IFERROR(F25/F$23,"N/A") -> N/A | G30: =IFERROR(G25/G$23,"N/A") -> N/A | H30: =IFERROR(H25/H$23,"N/A") -> N/A | I30: =IFERROR(I25/I$23,"N/A") -> N/A | J30: =IFERROR(J25/J$23,"N/A") -> N/A | K30: =IFERROR(K25/K$23,"N/A") -> N/A | L30: =IFERROR(L25/L$23,"N/A") -> N/A | M30: =IFERROR(M25/M$23,"N/A") -> N/A | ... AG30: =IFERROR(AG25/AG$23,"N/A") -> N/A
C31: Global Services & Support | F31: =IFERROR(F26/F$23,"N/A") -> N/A | G31: =IFERROR(G26/G$23,"N/A") -> N/A | H31: =IFERROR(H26/H$23,"N/A") -> N/A | I31: =IFERROR(I26/I$23,"N/A") -> N/A | J31: =IFERROR(J26/J$23,"N/A") -> N/A | K31: =IFERROR(K26/K$23,"N/A") -> N/A | L31: =IFERROR(L26/L$23,"N/A") -> N/A | M31: =IFERROR(M26/M$23,"N/A") -> N/A | ... AG31: =IFERROR(AG26/AG$23,"N/A") -> N/A
C33: Total Company Operating Income | F33: =SUM(F34:F39) -> 36016 | G33: =SUM(G34:G39) -> 28318 | H33: =SUM(H34:H39) -> 22998 | I33: =SUM(I34:I39) -> 26969 | J33: =SUM(F33:I33) -> 4018 | K33: =SUM(K34:K39) -> 40373 | L33: =SUM(L34:L39) -> 27900 | M33: =SUM(M34:M39) -> 25352 | N33: =SUM(N34:N39) -> 29591 | O33: =SUM(K33:N33) -> 6314 | P33: =SUM(P34:P39) -> 42832 | Q33: =SUM(Q34:Q39) -> 29589 | R33: =SUM(R34:R39) -> 28202 | S33: =SUM(S34:S39) -> 32427 | T33: =SUM(P33:S33) -> 11950.3 | U33: =SUM(U34:U39) -> 50852 | V33: =SUM(V34:V39) -> 35885 | W33: =W34 -> 2789 | X33: =SUM(X34:X39) -> 2830.373 | Y33: =SUM(U33:X33) -> 11161.243 | Z33: =SUM(Z34:Z39) -> 3596.7509 | AA33: =SUM(AA34:AA39) -> 4246.7352 | AB33: =SUM(AB34:AB39) -> 3092.7947 | AC33: =SUM(AC34:AC39) -> 3305.4244 | AD33: =SUM(Z33:AC33) -> 14241.705 | AE33: =SUM(AE34:AE39) -> 14920.477 | AF33: =SUM(AF34:AF39) -> 15328.374 | AG33: =SUM(AG34:AG39) -> 15858.298
C34: =C16&" Operating Income" -> Americas Segment Operating Income | F34: 17864 | G34: 13927 | H34: 13117 | I34: =60508-SUM(F34:H34) -> 15600 | J34: =SUM(F34:I34) -> 4018 | K34: 20357 | L34: 15074 | M34: 15209 | N34: 17016 | O34: =SUM(K34:N34) -> 6314 | P34: 21509 | Q34: 16774 | R34: 16511 | S34: 17686 | T34: =SUM(P34:S34) -> 11950.3 | U34: 23953 | V34: 19373 | W34: 2789 | X34: =X8*Drivers!X$7 -> 2830.373 | Y34: =SUM(U34:X34) -> 11161.243 | Z34: =Z8*Drivers!Z$7 -> 3596.7509 | AA34: =AA8*Drivers!AA$7 -> 4246.7352 | AB34: =AB8*Drivers!AB$7 -> 3092.7947 | AC34: =AC8*Drivers!AC$7 -> 3305.4244 | AD34: =SUM(Z34:AC34) -> 14241.705 | AE34: =AE8*Drivers!AE$7 -> 14920.477 | AF34: =AF8*Drivers!AF$7 -> 15328.374 | AG34: =AG8*Drivers!AG$7 -> 15858.298
C35: =C17&" Operating Income" -> Greater China Segment Operating Income | F35: 10437 | G35: 7531 | H35: 6207 | I35: 6153 | J35: =SUM(F35:I35) | K35: 8622 | L35: 6700 | M35: 5562 | N35: 6198 | O35: =SUM(K35:N35) | P35: 8160 | Q35: 6626 | R35: 5822 | S35: 6309 | T35: =SUM(P35:S35) | U35: 11792 | V35: 9189 | W35: 0 | X35: =X9*Drivers!X$12 -> 0 | Y35: =SUM(U35:X35) | Z35: =Z9*Drivers!Z$12 -> 0 | AA35: =AA9*Drivers!AA$12 -> 0 | AB35: =AB9*Drivers!AB$12 -> 0 | AC35: =AC9*Drivers!AC$12 -> 0 | AD35: =SUM(Z35:AC35) | AE35: =AE9*Drivers!AE$12 -> 0 | AF35: =AF9*Drivers!AF$12 -> 0 | AG35: =AG9*Drivers!AG$12 -> 0
C36: =C18&" Operating Income" -> Japan Segment Operating Income | F36: 3236 | G36: 3394 | H36: 2443 | I36: 2815 | J36: =SUM(F36:I36) | K36: 3819 | L36: 3135 | M36: 2544 | N36: 2956 | O36: =SUM(K36:N36) | P36: 4314 | Q36: 3434 | R36: 2872 | S36: 3335 | T36: =SUM(P36:S36) | U36: 4613 | V36: 3839 | W36: 0 | X36: =X10*Drivers!X17 -> 0 | Y36: =SUM(U36:X36) | Z36: =Z10*Drivers!Z$17 -> 0 | AA36: =AA10*Drivers!AA$17 -> 0 | AB36: =AB10*Drivers!AB$17 -> 0 | AC36: =AC10*Drivers!AC$17 -> 0 | AD36: =SUM(Z36:AC36) | AE36: =AE10*Drivers!AE$17 -> 0 | AF36: =AF10*Drivers!AF$17 -> 0 | AG36: =AG10*Drivers!AG$17 -> 0
C37: =C19&" Operating Income" -> Other / Reconciliation Operating Income | F37: 4479 | G37: 3466 | H37: 1231 | I37: 2401 | J37: =SUM(F37:I37) | K37: 7575 | L37: 2991 | M37: 2037 | N37: 3421 | O37: =SUM(K37:N37) | P37: 8849 | Q37: 2755 | R37: 2997 | S37: 5097 | T37: =SUM(P37:S37) | U37: 10494 | V37: 3484 | W37: 0 | X37: =X11*Drivers!X$22 -> 0 | Y37: =SUM(U37:X37) | Z37: =Z11*Drivers!Z$22 -> 0 | AA37: =AA11*Drivers!AA$22 -> 0 | AB37: =AB11*Drivers!AB$22 -> 0 | AC37: =AC11*Drivers!AC$22 -> 0 | AD37: =SUM(Z37:AC37) | AE37: =AE11*Drivers!AE$22 -> 0 | AF37: =AF11*Drivers!AF$22 -> 0 | AG37: =AG11*Drivers!AG$22 -> 0
C38: =C20&" Operating Income" -> Segment 5 Operating Income | F38: 0 | G38: 0 | H38: 0 | I38: 0 | J38: =SUM(F38:I38) | K38: 0 | L38: 0 | M38: 0 | N38: 0 | O38: =SUM(K38:N38) | P38: 0 | Q38: 0 | R38: 0 | S38: 0 | T38: =SUM(P38:S38) | U38: 0 | V38: 0 | W38: 0 | X38: =X12*Drivers!X$27 -> 0 | Y38: =SUM(U38:X38) | Z38: =Z12*Drivers!Z$27 -> 0 | AA38: =AA12*Drivers!AA$27 -> 0 | AB38: =AB12*Drivers!AB$27 -> 0 | AC38: =AC12*Drivers!AC$27 -> 0 | AD38: =SUM(Z38:AC38) | AE38: =AE12*Drivers!AE$27 -> 0 | AF38: =AF12*Drivers!AF$27 -> 0 | AG38: =AG12*Drivers!AG$27 -> 0
C39: =C21&" Operating Income" -> Segment 6 Operating Income | F39: 0 | G39: 0 | H39: 0 | I39: 0 | J39: =SUM(F39:I39) | K39: 0 | L39: 0 | M39: 0 | N39: 0 | O39: =SUM(K39:N39) | P39: 0 | Q39: 0 | R39: 0 | S39: 0 | T39: =SUM(P39:S39) | U39: 0 | V39: 0 | W39: 0 | X39: =X13*Drivers!X$32 -> 0 | Y39: =SUM(U39:X39) | Z39: =Z13*Drivers!Z$32 -> 0 | AA39: =AA13*Drivers!AA$32 -> 0 | AB39: =AB13*Drivers!AB$32 -> 0 | AC39: =AC13*Drivers!AC$32 -> 0 | AD39: =SUM(Z39:AC39) | AE39: =AE13*Drivers!AE$32 -> 0 | AF39: =AF13*Drivers!AF$32 -> 0 | AG39: =AG13*Drivers!AG$32 -> 0
C41: Operating Income Check | F41: =F33-SUM(F34:F39) -> 1e-12 | G41: =G33-SUM(G34:G39) -> 1e-12 | H41: =H33-SUM(H34:H39) -> 1e-12 | I41: =I33-SUM(I34:I39) -> 1e-12 | J41: =J33-SUM(J34:J39) | K41: =K33-SUM(K34:K39) -> 1e-12 | L41: =L33-SUM(L34:L39) -> 1e-12 | M41: =M33-SUM(M34:M39) -> 1e-12 | ... AG41: =AG33-SUM(AG34:AG39)
C43: Operating Income Mix
C44: =C16 -> Home Improvement Retail | F44: =IFERROR(F34/F$33,"N/A") -> 1 | G44: =IFERROR(G34/G$33,"N/A") -> 1 | H44: =IFERROR(H34/H$33,"N/A") -> 1 | I44: =IFERROR(I34/I$33,"N/A") -> 1 | J44: =IFERROR(J34/J$33,"N/A") -> 1 | K44: =IFERROR(K34/K$33,"N/A") -> 1 | L44: =IFERROR(L34/L$33,"N/A") -> 1 | M44: =IFERROR(M34/M$33,"N/A") -> 1 | ... AG44: =IFERROR(AG34/AG$33,"N/A") -> 1
C45: =C17 -> Segment 2 | F45: =IFERROR(F35/F$33,"N/A") -> 0 | G45: =IFERROR(G35/G$33,"N/A") | H45: =IFERROR(H35/H$33,"N/A") | I45: =IFERROR(I35/I$33,"N/A") | J45: =IFERROR(J35/J$33,"N/A") | K45: =IFERROR(K35/K$33,"N/A") | L45: =IFERROR(L35/L$33,"N/A") | M45: =IFERROR(M35/M$33,"N/A") | ... AG45: =IFERROR(AG35/AG$33,"N/A")
C46: =C18 -> Segment 3 | F46: =IFERROR(F36/F$33,"N/A") -> 0 | G46: =IFERROR(G36/G$33,"N/A") | H46: =IFERROR(H36/H$33,"N/A") | I46: =IFERROR(I36/I$33,"N/A") | J46: =IFERROR(J36/J$33,"N/A") | K46: =IFERROR(K36/K$33,"N/A") | L46: =IFERROR(L36/L$33,"N/A") | M46: =IFERROR(M36/M$33,"N/A") | ... AG46: =IFERROR(AG36/AG$33,"N/A")
C47: =C19 -> Segment 4 | F47: =IFERROR(F37/F$33,"N/A") -> 0 | G47: =IFERROR(G37/G$33,"N/A") | H47: =IFERROR(H37/H$33,"N/A") | I47: =IFERROR(I37/I$33,"N/A") | J47: =IFERROR(J37/J$33,"N/A") | K47: =IFERROR(K37/K$33,"N/A") | L47: =IFERROR(L37/L$33,"N/A") | M47: =IFERROR(M37/M$33,"N/A") | ... AG47: =IFERROR(AG37/AG$33,"N/A")
C48: =C20 -> Segment 5 | F48: =IFERROR(F38/F$33,"N/A") -> 0 | G48: =IFERROR(G38/G$33,"N/A") | H48: =IFERROR(H38/H$33,"N/A") | I48: =IFERROR(I38/I$33,"N/A") | J48: =IFERROR(J38/J$33,"N/A") | K48: =IFERROR(K38/K$33,"N/A") | L48: =IFERROR(L38/L$33,"N/A") | M48: =IFERROR(M38/M$33,"N/A") | ... AG48: =IFERROR(AG38/AG$33,"N/A")
C49: =C21 -> Segment 6 | F49: =IFERROR(F39/F$33,"N/A") -> 0 | G49: =IFERROR(G39/G$33,"N/A") | H49: =IFERROR(H39/H$33,"N/A") | I49: =IFERROR(I39/I$33,"N/A") | J49: =IFERROR(J39/J$33,"N/A") | K49: =IFERROR(K39/K$33,"N/A") | L49: =IFERROR(L39/L$33,"N/A") | M49: =IFERROR(M39/M$33,"N/A") | ... AG49: =IFERROR(AG39/AG$33,"N/A")
C51: Total D&A | F51: =SUM(F52:F57) -> 1e-12 | G51: =SUM(G52:G57) -> 1e-12 | H51: =SUM(H52:H57) -> 1e-12 | I51: =SUM(I52:I57) -> 1e-12 | J51: =SUM(J52:J57) -> 1477 | K51: =SUM(K52:K57) -> 1e-12 | L51: =SUM(L52:L57) -> 1e-12 | M51: =SUM(M52:M57) -> 1e-12 | ... W51: =SUM(W52:W57) -> 425 | X51: =Model!X76 -> 331.1875 | Y51: =SUM(Y52:Y57) -> 1556.1875 | Z51: =Model!Z76 -> 331.86892 | AA51: =Model!AA76 -> 336.85147 | AB51: =Model!AB76 -> 342.23238 | AC51: =Model!AC76 -> 343.91087 | AD51: =SUM(AD52:AD57) -> 1354.8636 | AE51: =Model!AE76 -> 1420.1552 | AF51: =Model!AF76 -> 1472.4758 | AG51: =Model!AG76 -> 1524.1209
C52: =C16&" D&A" -> Home Improvement Retail D&A | F52: 0 | G52: 0 | H52: 0 | I52: 0 | J52: =SUM(F52:I52) -> 1477 | K52: 0 | L52: 0 | M52: 0 | N52: 0 | O52: =SUM(K52:N52) -> 1262 | P52: 0 | Q52: 0 | R52: 0 | S52: 0 | T52: =SUM(P52:S52) -> 1398 | U52: 0 | V52: 0 | W52: 425 | X52: =X62*X$51 -> 331.1875 | Y52: =SUM(U52:X52) -> 1556.1875 | Z52: =Z62*Z$51 -> 331.86892 | AA52: =AA62*AA$51 -> 336.85147 | AB52: =AB62*AB$51 -> 342.23238 | AC52: =AC62*AC$51 -> 343.91087 | AD52: =SUM(Z52:AC52) -> 1354.8636 | AE52: =AE62*AE$51 -> 1420.1552 | AF52: =AF62*AF$51 -> 1472.4758 | AG52: =AG62*AG$51 -> 1524.1209
C53: =C17&" D&A" -> Segment 2 D&A | F53: 0 | G53: 0 | H53: 0 | I53: 0 | J53: =SUM(F53:I53) | K53: 0 | L53: 0 | M53: 0 | N53: 0 | O53: =SUM(K53:N53) | P53: 0 | Q53: 0 | R53: 0 | S53: 0 | T53: =SUM(P53:S53) | U53: 0 | V53: 0 | W53: 0 | X53: =X63*X$51 | Y53: =SUM(U53:X53) | Z53: =Z63*Z$51 -> 0 | AA53: =AA63*AA$51 | AB53: =AB63*AB$51 | AC53: =AC63*AC$51 | AD53: =SUM(Z53:AC53) | AE53: =AE63*AE$51 -> 0 | AF53: =AF63*AF$51 | AG53: =AG63*AG$51
C54: =C18&" D&A" -> Segment 3 D&A | F54: 0 | G54: 0 | H54: 0 | I54: 0 | J54: =SUM(F54:I54) | K54: 0 | L54: 0 | M54: 0 | N54: 0 | O54: =SUM(K54:N54) | P54: 0 | Q54: 0 | R54: 0 | S54: 0 | T54: =SUM(P54:S54) | U54: 0 | V54: 0 | W54: 0 | X54: =X64*X$51 | Y54: =SUM(U54:X54) | Z54: =Z64*Z$51 -> 0 | AA54: =AA64*AA$51 | AB54: =AB64*AB$51 | AC54: =AC64*AC$51 | AD54: =SUM(Z54:AC54) | AE54: =AE64*AE$51 -> 0 | AF54: =AF64*AF$51 | AG54: =AG64*AG$51
C55: =C19&" D&A" -> Segment 4 D&A | F55: 0 | G55: 0 | H55: 0 | I55: 0 | J55: =SUM(F55:I55) | K55: 0 | L55: 0 | M55: 0 | N55: 0 | O55: =SUM(K55:N55) | P55: 0 | Q55: 0 | R55: 0 | S55: 0 | T55: =SUM(P55:S55) | U55: 0 | V55: 0 | W55: 0 | X55: =X65*X$51 | Y55: =SUM(U55:X55) | Z55: =Z65*Z$51 -> 0 | AA55: =AA65*AA$51 | AB55: =AB65*AB$51 | AC55: =AC65*AC$51 | AD55: =SUM(Z55:AC55) | AE55: =AE65*AE$51 -> 0 | AF55: =AF65*AF$51 | AG55: =AG65*AG$51
C56: =C20&" D&A" -> Segment 5 D&A | F56: 0 | G56: 0 | H56: 0 | I56: 0 | J56: =SUM(F56:I56) | K56: 0 | L56: 0 | M56: 0 | N56: 0 | O56: =SUM(K56:N56) | P56: 0 | Q56: 0 | R56: 0 | S56: 0 | T56: =SUM(P56:S56) | U56: 0 | V56: 0 | W56: 0 | X56: =X66*X$51 | Y56: =SUM(U56:X56) | Z56: =Z66*Z$51 -> 0 | AA56: =AA66*AA$51 | AB56: =AB66*AB$51 | AC56: =AC66*AC$51 | AD56: =SUM(Z56:AC56) | AE56: =AE66*AE$51 -> 0 | AF56: =AF66*AF$51 | AG56: =AG66*AG$51
C57: =C21&" D&A" -> Segment 6 D&A | F57: 0 | G57: 0 | H57: 0 | I57: 0 | J57: =SUM(F57:I57) | K57: 0 | L57: 0 | M57: 0 | N57: 0 | O57: =SUM(K57:N57) | P57: 0 | Q57: 0 | R57: 0 | S57: 0 | T57: =SUM(P57:S57) | U57: 0 | V57: 0 | W57: 0 | X57: =X67*X$51 | Y57: =SUM(U57:X57) | Z57: =Z67*Z$51 -> 0 | AA57: =AA67*AA$51 | AB57: =AB67*AB$51 | AC57: =AC67*AC$51 | AD57: =SUM(Z57:AC57) | AE57: =AE67*AE$51 -> 0 | AF57: =AF67*AF$51 | AG57: =AG67*AG$51
C59: D&A Check | F59: =F51-Model!F60 -> 1e-12 | G59: =G51-Model!G60 -> 1e-12 | H59: =H51-Model!H60 -> 1e-12 | I59: =I51-Model!I60 -> 1e-12 | J59: =J51-Model!J60 -> 0 | K59: =K51-Model!K60 -> 1e-12 | L59: =L51-Model!L60 -> 1e-12 | M59: =M51-Model!M60 -> 1e-12 | ... W59: =W51-Model!W60 -> 0 | X59: =X51-SUM(X52:X57) -> 0 | Y59: =Y51-SUM(Y52:Y57) | Z59: =Z51-SUM(Z52:Z57) | AA59: =AA51-SUM(AA52:AA57) | AB59: =AB51-SUM(AB52:AB57) | AC59: =AC51-SUM(AC52:AC57) | AD59: =AD51-SUM(AD52:AD57) | AE59: =AE51-SUM(AE52:AE57) | ... AG59: =AG51-SUM(AG52:AG57)
C61: Segment D&A Mix
C62: =C16 -> Home Improvement Retail | F62: =IFERROR(F52/F$51,"N/A") -> 1 | G62: =IFERROR(G52/G$51,"N/A") -> 1 | H62: =IFERROR(H52/H$51,"N/A") -> 1 | I62: =IFERROR(I52/I$51,"N/A") -> 1 | J62: =IFERROR(J52/J$51,"N/A") -> 1 | K62: =IFERROR(K52/K$51,"N/A") -> 1 | L62: =IFERROR(L52/L$51,"N/A") -> 1 | M62: =IFERROR(M52/M$51,"N/A") -> 1 | ... W62: =IFERROR(W52/W$51,"N/A") -> 1 | X62: =Drivers!X78 -> 1 | Y62: =Y52/Y$51 -> 1 | Z62: =Drivers!Z78 -> 1 | AA62: =Drivers!AA78 -> 1 | AB62: =Drivers!AB78 -> 1 | AC62: =Drivers!AC78 -> 1 | AD62: =AD52/AD$51 -> 1 | AE62: =Drivers!AE78 -> 1 | AF62: =Drivers!AF78 -> 1 | AG62: =Drivers!AG78 -> 1
C63: =C17 -> Segment 2 | F63: =IFERROR(F53/F$51,"N/A") -> 0 | G63: =IFERROR(G53/G$51,"N/A") | H63: =IFERROR(H53/H$51,"N/A") | I63: =IFERROR(I53/I$51,"N/A") | J63: =IFERROR(J53/J$51,"N/A") | K63: =IFERROR(K53/K$51,"N/A") | L63: =IFERROR(L53/L$51,"N/A") | M63: =IFERROR(M53/M$51,"N/A") | ... W63: =IFERROR(W53/W$51,"N/A") | X63: =Drivers!X79 -> 0 | Y63: =Y53/Y$51 | Z63: =Drivers!Z79 -> 0 | AA63: =Drivers!AA79 -> 0 | AB63: =Drivers!AB79 -> 0 | AC63: =Drivers!AC79 -> 0 | AD63: =AD53/AD$51 | AE63: =Drivers!AE79 -> 0 | AF63: =Drivers!AF79 -> 0 | AG63: =Drivers!AG79 -> 0
C64: =C18 -> Segment 3 | F64: =IFERROR(F54/F$51,"N/A") -> 0 | G64: =IFERROR(G54/G$51,"N/A") | H64: =IFERROR(H54/H$51,"N/A") | I64: =IFERROR(I54/I$51,"N/A") | J64: =IFERROR(J54/J$51,"N/A") | K64: =IFERROR(K54/K$51,"N/A") | L64: =IFERROR(L54/L$51,"N/A") | M64: =IFERROR(M54/M$51,"N/A") | ... W64: =IFERROR(W54/W$51,"N/A") | X64: =Drivers!X80 -> 0 | Y64: =Y54/Y$51 | Z64: =Drivers!Z80 -> 0 | AA64: =Drivers!AA80 -> 0 | AB64: =Drivers!AB80 -> 0 | AC64: =Drivers!AC80 -> 0 | AD64: =AD54/AD$51 | AE64: =Drivers!AE80 -> 0 | AF64: =Drivers!AF80 -> 0 | AG64: =Drivers!AG80 -> 0
C65: =C19 -> Segment 4 | F65: =IFERROR(F55/F$51,"N/A") -> 0 | G65: =IFERROR(G55/G$51,"N/A") | H65: =IFERROR(H55/H$51,"N/A") | I65: =IFERROR(I55/I$51,"N/A") | J65: =IFERROR(J55/J$51,"N/A") | K65: =IFERROR(K55/K$51,"N/A") | L65: =IFERROR(L55/L$51,"N/A") | M65: =IFERROR(M55/M$51,"N/A") | ... W65: =IFERROR(W55/W$51,"N/A") | X65: =Drivers!X81 -> 0 | Y65: =Y55/Y$51 | Z65: =Drivers!Z81 -> 0 | AA65: =Drivers!AA81 -> 0 | AB65: =Drivers!AB81 -> 0 | AC65: =Drivers!AC81 -> 0 | AD65: =AD55/AD$51 | AE65: =Drivers!AE81 -> 0 | AF65: =Drivers!AF81 -> 0 | AG65: =Drivers!AG81 -> 0
C66: =C20 -> Segment 5 | F66: =IFERROR(F56/F$51,"N/A") -> 0 | G66: =IFERROR(G56/G$51,"N/A") | H66: =IFERROR(H56/H$51,"N/A") | I66: =IFERROR(I56/I$51,"N/A") | J66: =IFERROR(J56/J$51,"N/A") | K66: =IFERROR(K56/K$51,"N/A") | L66: =IFERROR(L56/L$51,"N/A") | M66: =IFERROR(M56/M$51,"N/A") | ... W66: =IFERROR(W56/W$51,"N/A") | X66: =Drivers!X82 -> 0 | Y66: =Y56/Y$51 | Z66: =Drivers!Z82 -> 0 | AA66: =Drivers!AA82 -> 0 | AB66: =Drivers!AB82 -> 0 | AC66: =Drivers!AC82 -> 0 | AD66: =AD56/AD$51 | AE66: =Drivers!AE82 -> 0 | AF66: =Drivers!AF82 -> 0 | AG66: =Drivers!AG82 -> 0
C67: =C21 -> Segment 6 | F67: =IFERROR(F57/F$51,"N/A") -> 0 | G67: =IFERROR(G57/G$51,"N/A") | H67: =IFERROR(H57/H$51,"N/A") | I67: =IFERROR(I57/I$51,"N/A") | J67: =IFERROR(J57/J$51,"N/A") | K67: =IFERROR(K57/K$51,"N/A") | L67: =IFERROR(L57/L$51,"N/A") | M67: =IFERROR(M57/M$51,"N/A") | ... W67: =IFERROR(W57/W$51,"N/A") | X67: =Drivers!X83 -> 0 | Y67: =Y57/Y$51 | Z67: =Drivers!Z83 -> 0 | AA67: =Drivers!AA83 -> 0 | AB67: =Drivers!AB83 -> 0 | AC67: =Drivers!AC83 -> 0 | AD67: =AD57/AD$51 | AE67: =Drivers!AE83 -> 0 | AF67: =Drivers!AF83 -> 0 | AG67: =Drivers!AG83 -> 0
C69: Total EBITDA Proxy | F69: =F51+F33 -> 1825 | G69: =G51+G33 -> 2508 | H69: =H51+H33 -> 1390 | I69: =I51+I33 -> -228 | J69: =J51+J33 -> 5495 | K69: =K51+K33 -> 1719 | L69: =L51+L33 -> 2692 | M69: =M51+M33 -> 1868 | ... AG69: =AG51+AG33 -> 17382.419
C70: =C16&" EBITDA" -> Home Improvement Retail EBITDA | F70: =F52+F34 -> 17864 | G70: =G52+G34 -> 13927 | H70: =H52+H34 -> 13117 | I70: =I52+I34 -> 15600 | J70: =J52+J34 -> 5495 | K70: =K52+K34 -> 20357 | L70: =L52+L34 -> 15074 | M70: =M52+M34 -> 15209 | ... AG70: =AG52+AG34 -> 17382.419
C71: =C17&" EBITDA" -> Segment 2 EBITDA | F71: =F53+F35 -> 10437 | G71: =G53+G35 -> 7531 | H71: =H53+H35 -> 6207 | I71: =I53+I35 -> 6153 | J71: =J53+J35 | K71: =K53+K35 -> 8622 | L71: =L53+L35 -> 6700 | M71: =M53+M35 -> 5562 | ... AG71: =AG53+AG35
C72: =C18&" EBITDA" -> Segment 3 EBITDA | F72: =F54+F36 -> 3236 | G72: =G54+G36 -> 3394 | H72: =H54+H36 -> 2443 | I72: =I54+I36 -> 2815 | J72: =J54+J36 | K72: =K54+K36 -> 3819 | L72: =L54+L36 -> 3135 | M72: =M54+M36 -> 2544 | ... AG72: =AG54+AG36
C73: =C19&" EBITDA" -> Segment 4 EBITDA | F73: =F55+F37 -> 4479 | G73: =G55+G37 -> 3466 | H73: =H55+H37 -> 1231 | I73: =I55+I37 -> 2401 | J73: =J55+J37 | K73: =K55+K37 -> 7575 | L73: =L55+L37 -> 2991 | M73: =M55+M37 -> 2037 | ... AG73: =AG55+AG37
C74: =C20&" EBITDA" -> Segment 5 EBITDA | F74: =F56+F38 -> 1e-12 | G74: =G56+G38 -> 1e-12 | H74: =H56+H38 -> 1e-12 | I74: =I56+I38 -> 1e-12 | J74: =J56+J38 | K74: =K56+K38 -> 1e-12 | L74: =L56+L38 -> 1e-12 | M74: =M56+M38 -> 1e-12 | ... AG74: =AG56+AG38
C75: =C21&" EBITDA" -> Segment 6 EBITDA | F75: =F57+F39 -> 1e-12 | G75: =G57+G39 -> 1e-12 | H75: =H57+H39 -> 1e-12 | I75: =I57+I39 -> 1e-12 | J75: =J57+J39 | K75: =K57+K39 -> 1e-12 | L75: =L57+L39 -> 1e-12 | M75: =M57+M39 -> 1e-12 | ... AG75: =AG57+AG39
C77: EBITDA Mix
C78: =C16 -> Home Improvement Retail | F78: =IFERROR(F70/F$69,"N/A") -> 1 | G78: =IFERROR(G70/G$69,"N/A") -> 1 | H78: =IFERROR(H70/H$69,"N/A") -> 1 | I78: =IFERROR(I70/I$69,"N/A") -> 1 | J78: =IFERROR(J70/J$69,"N/A") -> 1 | K78: =IFERROR(K70/K$69,"N/A") -> 1 | L78: =IFERROR(L70/L$69,"N/A") -> 1 | M78: =IFERROR(M70/M$69,"N/A") -> 1 | ... AG78: =IFERROR(AG70/AG$69,"N/A") -> 1
C79: =C17 -> Segment 2 | F79: =IFERROR(F71/F$69,"N/A") -> 0 | G79: =IFERROR(G71/G$69,"N/A") | H79: =IFERROR(H71/H$69,"N/A") | I79: =IFERROR(I71/I$69,"N/A") | J79: =IFERROR(J71/J$69,"N/A") | K79: =IFERROR(K71/K$69,"N/A") | L79: =IFERROR(L71/L$69,"N/A") | M79: =IFERROR(M71/M$69,"N/A") | ... AG79: =IFERROR(AG71/AG$69,"N/A")
C80: =C18 -> Segment 3 | F80: =IFERROR(F72/F$69,"N/A") -> 0 | G80: =IFERROR(G72/G$69,"N/A") | H80: =IFERROR(H72/H$69,"N/A") | I80: =IFERROR(I72/I$69,"N/A") | J80: =IFERROR(J72/J$69,"N/A") | K80: =IFERROR(K72/K$69,"N/A") | L80: =IFERROR(L72/L$69,"N/A") | M80: =IFERROR(M72/M$69,"N/A") | ... AG80: =IFERROR(AG72/AG$69,"N/A")
C81: =C19 -> Segment 4 | F81: =IFERROR(F73/F$69,"N/A") -> 0 | G81: =IFERROR(G73/G$69,"N/A") | H81: =IFERROR(H73/H$69,"N/A") | I81: =IFERROR(I73/I$69,"N/A") | J81: =IFERROR(J73/J$69,"N/A") | K81: =IFERROR(K73/K$69,"N/A") | L81: =IFERROR(L73/L$69,"N/A") | M81: =IFERROR(M73/M$69,"N/A") | ... AG81: =IFERROR(AG73/AG$69,"N/A")
C82: =C20 -> Segment 5 | F82: =IFERROR(F74/F$69,"N/A") -> 0 | G82: =IFERROR(G74/G$69,"N/A") | H82: =IFERROR(H74/H$69,"N/A") | I82: =IFERROR(I74/I$69,"N/A") | J82: =IFERROR(J74/J$69,"N/A") | K82: =IFERROR(K74/K$69,"N/A") | L82: =IFERROR(L74/L$69,"N/A") | M82: =IFERROR(M74/M$69,"N/A") | ... AG82: =IFERROR(AG74/AG$69,"N/A")
C83: =C21 -> Segment 6 | F83: =IFERROR(F75/F$69,"N/A") -> 0 | G83: =IFERROR(G75/G$69,"N/A") | H83: =IFERROR(H75/H$69,"N/A") | I83: =IFERROR(I75/I$69,"N/A") | J83: =IFERROR(J75/J$69,"N/A") | K83: =IFERROR(K75/K$69,"N/A") | L83: =IFERROR(L75/L$69,"N/A") | M83: =IFERROR(M75/M$69,"N/A") | ... AG83: =IFERROR(AG75/AG$69,"N/A")
C86: Geographic Breakdown
C88: Total Company Revenue | F88: =SUM(F89:F93) -> 1e-12 | G88: =SUM(G89:G93) -> 1e-12 | H88: =SUM(H89:H93) -> 1e-12 | I88: =SUM(I89:I93) -> 1e-12 | J88: =SUM(F88:I88) -> 0 | K88: =SUM(K89:K93) -> 1e-12 | L88: =SUM(L89:L93) -> 1e-12 | M88: =SUM(M89:M93) -> 1e-12 | N88: =SUM(N89:N93) -> 1e-12 | O88: =SUM(K88:N88) -> 0 | P88: =SUM(P89:P93) -> 1e-12 | Q88: =SUM(Q89:Q93) -> 1e-12 | R88: =SUM(R89:R93) -> 1e-12 | S88: =SUM(S89:S93) -> 1e-12 | T88: =SUM(P88:S88) -> 0 | U88: =SUM(U89:U93) -> 1e-12 | V88: =SUM(V89:V93) -> 1e-12 | W88: =SUM(W89:W93) | X88: =SUM(X89:X93) | Y88: =SUM(U88:X88) -> 0 | Z88: =SUM(Z89:Z93) -> 0 | AA88: =SUM(AA89:AA93) | AB88: =SUM(AB89:AB93) | AC88: =SUM(AC89:AC93) | AD88: =SUM(Z88:AC88) -> 0 | AE88: =SUM(AE89:AE93) -> 0 | AF88: =SUM(AF89:AF93) | AG88: =SUM(AG89:AG93)
C89: North America | F89: 0 | G89: 0 | H89: 0 | I89: 0 | J89: =SUM(F89:I89) | K89: 0 | L89: 0 | M89: 0 | N89: 0 | O89: =SUM(K89:N89) | P89: 0 | Q89: 0 | R89: 0 | S89: 0 | T89: =SUM(P89:S89) | U89: 0 | V89: 0 | W89: 0 | X89: 0 | Y89: =SUM(U89:X89) | Z89: 0 | AA89: 0 | AB89: 0 | AC89: 0 | AD89: =SUM(Z89:AC89) | AE89: 0 | AF89: 0 | AG89: 0
