Workbook
Name _bdm.146e958bbea04416b86a4d5943392c04.edm: Model!$M$100
Name _bdm.bf5a9ed53fe44c598e3cfb84ac34b21f.edm: Integrity!$F$36
Name Case_Scenario: Cover!$F$22
Name Company_Cyclical_Multiples_Data: 'Multiples Data'!$C$14:$H$26
Name Company_Name: Cover!$F$19
Name Company_Rev_Methodology: 'Revenue Build'!$C$7
Name Cost_of_Debt: WACC!$G$17
Name Cost_of_Equity: WACC!$G$25
Name Cost_of_Preferred: WACC!$G$10
Name Current_Date: Cover!$F$27
Name Cycle_Period_Toggle: Valuation!$G$225
Name Cycle_Toggle: Valuation!$G$224
Name Cyclical_LTM_NTM_Toggle: Valuation!$G$226
Name Cyclical_Peer_Group_Toggle: Valuation!$G$227
Name Data: Model!$C$25:$AK$160
Name Diluted_Shares: Cover!$F$35
Name Discount_Rate: WACC!$O$13
Name Div_Yield: Cover!$F$34
Name ERP: WACC!$G$7
Name Fiscal_Periods: Model!$C$25:$AG$25
Name Hun: Cover!$F$41
Name IQRCIQIDLocaterI12: 'CIQ ID Locater'!$J$12:$N$12
Name IQRCIQIDLocaterI13: 'CIQ ID Locater'!$J$13:$N$13
Name IQRCIQIDLocaterI14: 'CIQ ID Locater'!$J$14:$N$14
Name IQRCIQIDLocaterI15: 'CIQ ID Locater'!$J$15:$N$15
Name IQRCIQIDLocaterI16: 'CIQ ID Locater'!$J$16:$N$16
Name IQRCIQIDLocaterI17: 'CIQ ID Locater'!$J$17:$N$17
Name IQRCIQIDLocaterI18: 'CIQ ID Locater'!$J$18:$N$18
Name IQRCIQIDLocaterI19: 'CIQ ID Locater'!$J$19:$N$19
Name IQRCIQIDLocaterI20: 'CIQ ID Locater'!$J$20:$N$20
Name IQRCIQIDLocaterI21: 'CIQ ID Locater'!$J$21:$L$21
Name IQRCIQIDLocaterI22: 'CIQ ID Locater'!$J$22:$N$22
Name IQRCIQIDLocaterI23: 'CIQ ID Locater'!$J$23:$N$23
Name IQRCIQIDLocaterI24: 'CIQ ID Locater'!$J$24:$N$24
Name IQRCIQIDLocaterI25: 'CIQ ID Locater'!$J$25:$N$25
Name IQRCIQIDLocaterI26: 'CIQ ID Locater'!$J$26:$N$26
Name IQRCIQIDLocaterI27: 'CIQ ID Locater'!$J$27:$N$27
Name IQRCIQIDLocaterI28: 'CIQ ID Locater'!$J$28:$K$28
Name IQRCIQIDLocaterI29: 'CIQ ID Locater'!$J$29
Name IQRCIQIDLocaterO12: 'CIQ ID Locater'!$P$12:$T$12
Name IQRCIQIDLocaterO13: 'CIQ ID Locater'!$P$13:$T$13
Name IQRCIQIDLocaterO14: 'CIQ ID Locater'!$P$14:$T$14
Name IQRCIQIDLocaterO15: 'CIQ ID Locater'!$P$15:$T$15
Name IQRCIQIDLocaterO16: 'CIQ ID Locater'!$P$16:$T$16
Name IQRCIQIDLocaterO17: 'CIQ ID Locater'!$P$17:$T$17
Name IQRCIQIDLocaterO18: 'CIQ ID Locater'!$P$18:$T$18
Name IQRCIQIDLocaterO19: 'CIQ ID Locater'!$P$19:$T$19
Name IQRCIQIDLocaterO20: 'CIQ ID Locater'!$P$20:$T$20
Name IQRCIQIDLocaterO21: 'CIQ ID Locater'!$P$21:$R$21
Name IQRCIQIDLocaterO22: 'CIQ ID Locater'!$P$22:$T$22
Name IQRCIQIDLocaterO23: 'CIQ ID Locater'!$P$23:$T$23
Name IQRCIQIDLocaterO24: 'CIQ ID Locater'!$P$24:$T$24
Name IQRCIQIDLocaterO25: 'CIQ ID Locater'!$P$25:$T$25
Name IQRCIQIDLocaterO26: 'CIQ ID Locater'!$P$26:$T$26
Name IQRCIQIDLocaterO27: 'CIQ ID Locater'!$P$27:$T$27
Name IQRCIQIDLocaterO28: 'CIQ ID Locater'!$P$28:$Q$28
Name IQRCIQIDLocaterO29: 'CIQ ID Locater'!$P$29
Name IQRCompaniesH13: 'CIQ ID Locater'!$J$12:$N$12
Name IQRCompaniesH14: 'CIQ ID Locater'!$J$13:$N$13
Name IQRCompaniesH15: 'CIQ ID Locater'!$J$14:$N$14

Sheet Cover
C1: =Company_Name&" - "&MID(CELL("filename",A1),FIND("]",CELL("filename",A1))+1,255)&": "&Case_Scenario&" Case" -> Jefferies Financial Group Inc. - Cover: Base Case | Q1: Font Toggle
C2: $ in Millions Except Per Share Data | Q2: Report
R3: x
A4: x | C4: Model Assumptions: | I4: Return Summary:
I6: Dividend Discount Model | N6: Multiple Analysis
I8: Exit Multiple Method | N8: EV/EBITDA Method
I9: Implied Enterprise Value: | L9: =Valuation!K69 -> 15177.212 | P9: Target Price: | Q9: % Return:
I10: Implied Equity Value: | L10: =Valuation!K76 -> 15177.212
N11: 1 Year LTM EV/EBITDA | P11: =Valuation!N141 -> 85.73526 | Q11: =Valuation!N142 -> 1.2544113
I12: Implied Share Price: | L12: =Valuation!K80 -> 68.136855
I13: % Return: | L13: =Valuation!K81 -> 0.79166065 | N13: 2009-2018 Late Cycle EV/EBITDA | P13: =Valuation!N219 -> 22.922881 | Q13: =Valuation!N220 -> -0.39724216
I15: Dividend Discount Model | N15: P/E Multiple Method
I16: Implied Enterprise Value: | L16: =Valuation!R69 -> 16987.417 | P16: Target Price: | Q16: % Return:
I17: Implied Equity Value: | L17: =Valuation!R76 -> 16987.417
N18: 1 Year LTM P/E | P18: =Valuation!F130 -> 122.96551 | Q18: =Valuation!F131 -> 2.2333818
C19: Company Name | F19: Jefferies Financial Group Inc. | I19: Implied Share Price: | L19: =Valuation!R80 -> 76.263622
C20: Ticker | F20: JEF | I20: % Return: | L20: =Valuation!R81 -> 1.0053543 | N20: 2009-2018 Late Cycle P/E | P20: =Valuation!F208 -> 131.11759 | Q20: =Valuation!F209 -> 2.447741
C22: Case Scenario | F22: Base | I22: Table of Contents
C24: Last Fiscal Year | F24: 45992 | I24: Cover
C25: Next Fiscal Year | F25: =Last_FYE+365 -> 46357 | I25: Summary
C26: Last Fiscal Quarter Reported | F26: 4Q | I26: Football Field
C27: Current Valuation Date | F27: 46091 | I27: Integrity
I28: Revenue Build
C29: Current Share Price | F29: 38.03 | I29: Model
C30: 52-Week High | F30: 17.04 | I30: Segment Analysis
C31: 52-Week Low | F31: 35.72 | I31: Drivers
I32: WACC
C33: Effective Tax Rate | F33: =IF(Last_FQR="1Q",Model!P71,IF(Last_FQR="2Q",Model!Q71,IF(Last_FQR="3Q",Model!R71,Model!S71))) -> 0.18721229 | I33: Valuation
C34: Dividend Yield | F34: =IF(Last_FQR="1Q",Model!U268,IF(Last_FQR="2Q",Model!V268,IF(Last_FQR="3Q",Model!W268,Model!X268))) -> 0.048216782 | I34: Comparables
C35: Diluted Shares Outstanding (MRQ) | F35: =IF(Last_FQR="1Q",Model!P287,IF(Last_FQR="2Q",Model!Q287,IF(Last_FQR="3Q",Model!R287,Model!S287))) -> 222.746 | I35: Charts
I36: Benchmark
C37: Model Type | F37: Top Down | I37: Multiples Data
I38: Pre-Earnings
I39: Post-Earnings
A42: x
C43: Model Color Legend | I43: Constants
C44: Blue = Hard-Coded Value (historical values & assumptions) | I44: Reference | J44: Type | K44: Name | L44: Value
C45: Black = Formulas | I45: Million | J45: (#) | K45: Mil | L45: 1000000
C46: Green = Linked Value (from separate worksheet) | I46: Thousand | J46: (#) | K46: Thou | L46: 1000
C47: Red = Unique Formula / Anomaly | I47: Hundred | J47: (#) | K47: Hun | L47: 100
A48: x
C49: Tab Color Codes
C51: Summary
C53: Model
A54: x
C55: Supporting/Auxiliary
C57: Valuation
C59: Comps
C61: RBG Codes for Model
C63: 0-0-255 | F63: Hard-Coded Numbers
C65: 0-128-0 | F65: Linked Numbers
C67: 255-223-159 | F67: Owl Fund Gold
C69: 255-255-153 | F69: Drivers / Assumptions
C71: 118-0-0 | F71: Owl Fund Red
C73: 0-56-96 | F73: Section Headers
C75: 192-222-246 | F75: Sub-Section Headers
C77: 215-215-215 | F77: Historical Quarters
C79: 235-235-235 | F79: Projected Quarters
C81: 255-255-255 | F81: Annuals
A83: x | B83: x | C83: END

Sheet Summary
C1: =Company_Name&" - "&MID(CELL("filename",A1),FIND("]",CELL("filename",A1))+1,255)&": "&Case_Scenario&" Case" -> Jefferies Financial Group Inc. - Summary: Base Case
C2: =Cover!C2 -> $ in Millions Except Per Share Data
C4: Year: | T4: =Model!J24 -> 2023 | U4: =Model!O24 -> 2024 | V4: =Model!T24 -> 2025 | W4: =Model!Y24 -> 2026 | X4: =Model!AD24 -> 2027 | Y4: =Model!AE24 -> 2028 | Z4: =Model!AF24 -> 2029 | AA4: =Model!AG24 -> 2030
G5: Quarterly | T5: Annuals | AC5: CAGR | AE5: CAGR
A6: x | C6: ="Consolidated "&Model!C25 -> Consolidated Income Statement | G6: =Model!P25 -> 1Q25 | H6: =Model!Q25 -> 2Q25 | I6: =Model!R25 -> 3Q25 | J6: =Model!S25 -> 4Q25 | K6: =Model!U25 -> 1Q26e | L6: =Model!V25 -> 2Q26e | M6: =Model!W25 -> 3Q26 | N6: =Model!X25 -> 4Q26e | O6: =Model!Z25 -> 1Q27e | P6: =Model!AA25 -> 2Q27e | Q6: =Model!AB25 -> 3Q27e | R6: =Model!AC25 -> 4Q27e | T6: =Model!J25 -> 2023 | U6: =Model!O25 -> 2024 | V6: =Model!T25 -> 2025 | W6: =Model!Y25 -> 2026e | X6: =Model!AD25 -> 2027e | Y6: =Model!AE25 -> 2028e | Z6: =Model!AF25 -> 2029e | AA6: =Model!AG25 -> 2030e | AC6: Historical | AE6: Projected
C8: =Model!C28 -> Revenue | G8: =Model!P28 -> 2472.864 | H8: =Model!Q28 -> 2494.315 | I8: =Model!R28 -> 2907.674 | J8: =Model!S28 -> 2948.824 | K8: =Model!U28 -> 2742.8525 | L8: =Model!V28 -> 2804.4553 | M8: =Model!W28 -> 3225.2028 | N8: =Model!X28 -> 3219.018 | O8: =Model!Z28 -> 2948.7114 | P8: =Model!AA28 -> 3086.9714 | Q8: =Model!AB28 -> 3511.4181 | R8: =Model!AC28 -> 3473.729 | T8: =Model!J28 -> 7441.38 | U8: =Model!O28 -> 10515.069 | V8: =Model!T28 -> 10823.677 | W8: =Model!Y28 -> 11991.529 | X8: =Model!AD28 -> 13020.83 | Y8: =Model!AE28 -> 13894.991 | Z8: =Model!AF28 -> 14550.917 | AA8: =Model!AG28 -> 14977.126 | AC8: =IFERROR((V8/T8)^(1/(V$4-T$4))-1,"N/A") -> 0.20603711 | AE8: =IFERROR((AA8/V8)^(1/(AA$4-V$4))-1,"N/A") -> 0.067113784
C9: YoY % Growth | K9: =K8/G8-1 -> 0.10918049 | L9: =L8/H8-1 -> 0.12433886 | M9: =M8/I8-1 -> 0.1092037 | N9: =N8/J8-1 -> 0.091627703 | O9: =O8/K8-1 -> 0.075052853 | P9: =P8/L8-1 -> 0.10073833 | Q9: =Q8/M8-1 -> 0.088743357 | R9: =R8/N8-1 -> 0.079126933 | U9: =IF(ISERROR(U8/T8-1),"NA",(U8/T8-1)) -> 0.41305363 | V9: =IF(ISERROR(V8/U8-1),"NA",(V8/U8-1)) -> 0.029349118 | W9: =IF(ISERROR(W8/V8-1),"NA",(W8/V8-1)) -> 0.10789785 | X9: =IF(ISERROR(X8/W8-1),"NA",(X8/W8-1)) -> 0.085835711 | Y9: =IF(ISERROR(Y8/X8-1),"NA",(Y8/X8-1)) -> 0.067135576 | Z9: =IF(ISERROR(Z8/Y8-1),"NA",(Z8/Y8-1)) -> 0.047205916 | AA9: =IF(ISERROR(AA8/Z8-1),"NA",(AA8/Z8-1)) -> 0.029290872
C11: =Model!C30 -> Net Revenue | G11: =Model!P30 -> 1593.019 | H11: =Model!Q30 -> 1634.447 | I11: =Model!R30 -> 2047.432 | J11: =Model!S30 -> 2068.853 | K11: =Model!U30 -> 1901.7557 | L11: =Model!V30 -> 1909.5563 | M11: =Model!W30 -> 2275.2515 | N11: =Model!X30 -> 2296.619 | O11: =Model!Z30 -> 2067.0293 | P11: =Model!AA30 -> 2192.3393 | Q11: =Model!AB30 -> 2603.8359 | R11: =Model!AC30 -> 2553.1968 | T11: =Model!J30 -> 4700.398 | U11: =Model!O30 -> 7034.803 | V11: =Model!T30 -> 7343.751 | W11: =Model!Y30 -> 8383.1825 | X11: =Model!AD30 -> 9416.4013 | Y11: =Model!AE30 -> 17136.804 | Z11: =Model!AF30 -> 17477.729 | AA11: =Model!AG30 -> 17588.938 | AC11: =IFERROR((V11/T11)^(1/(V$4-T$4))-1,"N/A") -> 0.24994716 | AE11: =IFERROR((AA11/V11)^(1/(AA$4-V$4))-1,"N/A") -> -0.0044007877
C12: % Margin | G12: =G11/G$8 -> 0.6442 | H12: =H11/H$8 -> 0.65526888 | I12: =I11/I$8 -> 0.70414771 | J12: =J11/J$8 -> 0.70158578 | K12: =K11/K$8 -> 0.69334962 | L12: =L11/L$8 -> 0.68090095 | M12: =M11/M$8 -> 0.70546 | N12: =N11/N$8 -> 0.71345329 | ... R12: =R11/R$8 -> 0.73500174 | T12: =T11/T$8 -> 0.63165676 | U12: =U11/U$8 -> 0.6690211 | V12: =V11/V$8 -> 0.67848948 | W12: =W11/W$8 -> 0.69909207 | X12: =X11/X$8 -> 0.72317981 | Y12: =Y11/Y$8 -> 0.81400555 | Z12: =Z11/Z$8 -> 0.8051149 | AA12: =AA11/AA$8 -> 0.79463636
C13: YoY % Growth | K13: =K11/G11-1 -> 0.19380606 | L13: =L11/H11-1 -> 0.16831948 | M13: =M11/I11-1 -> 0.11127086 | N13: =N11/J11-1 -> 0.11009287 | O13: =O11/K11-1 -> 0.086905762 | P13: =P11/L11-1 -> 0.14808832 | Q13: =Q11/M11-1 -> 0.14441674 | R13: =R11/N11-1 -> 0.11171983 | U13: =U11/T11-1 -> 0.49663986 | V13: =V11/U11-1 -> 0.043917079 | W13: =W11/V11-1 -> 0.14153959 | X13: =X11/W11-1 -> 0.12324899 | Y13: =Y11/X11-1 -> 0.033966301 | Z13: =Z11/Y11-1 -> 0.019894361 | AA13: =AA11/Z11-1 -> 0.0063628991
C15: =Model!C36 -> EBIT | G15: =Model!P36 -> 151.065 | H15: =Model!Q36 -> 134.901 | I15: =Model!R36 -> 331.815 | J15: =Model!S36 -> 200.505 | K15: =Model!U36 -> 292.56286 | L15: =Model!V36 -> 304.63348 | M15: =Model!W36 -> 359.57675 | N15: =Model!X36 -> 355.9426 | O15: =Model!Z36 -> 323.22138 | P15: =Model!AA36 -> 363.16369 | Q15: =Model!AB36 -> 486.00622 | R15: =Model!AC36 -> 512.82612 | T15: =Model!J36 -> 312.997 | U15: =Model!O36 -> 954.493 | V15: =Model!T36 -> 818.286 | W15: =Model!Y36 -> 1312.7157 | X15: =Model!AD36 -> 1685.2174 | Y15: =Model!AE36 -> 3110.8208 | Z15: =Model!AF36 -> 3232.3522 | AA15: =Model!AG36 -> 3112.2301 | AC15: =IFERROR((V15/T15)^(1/(V$4-T$4))-1,"N/A") -> 0.61689744 | AE15: =IFERROR((AA15/V15)^(1/(AA$4-V$4))-1,"N/A") -> -0.22943319
C16: Margin | G16: =G15/G$8 -> 0.061089085 | H16: =H15/H$8 -> 0.054083386 | I16: =I15/I$8 -> 0.11411699 | J16: =J15/J$8 -> 0.067994902 | K16: =K15/K$8 -> 0.10666372 | L16: =L15/L$8 -> 0.10862483 | M16: =M15/M$8 -> 0.11148966 | N16: =N15/N$8 -> 0.1105749 | ... R16: =R15/R$8 -> 0.14762986 | T16: =T15/T$8 -> 0.042061687 | U16: =U15/U$8 -> 0.090773822 | V16: =V15/V$8 -> 0.07560148 | W16: =W15/W$8 -> 0.10947026 | X16: =X15/X$8 -> 0.12942473 | Y16: =Y15/Y$8 -> 0.14776533 | Z16: =Z15/Z$8 -> 0.14889891 | AA16: =AA15/AA$8 -> 0.14060491
C17: YoY % Growth | K17: =K15/G15-1 -> 0.93666875 | L17: =L15/H15-1 -> 1.2582003 | M17: =M15/I15-1 -> 0.083666355 | N17: =N15/J15-1 -> 0.77523055 | O17: =O15/K15-1 -> 0.10479292 | P17: =P15/L15-1 -> 0.19213321 | Q17: =Q15/M15-1 -> 0.35160634 | R17: =R15/N15-1 -> 0.4407551 | U17: =U15/T15-1 -> 2.0495276 | V17: =V15/U15-1 -> -0.14270089 | W17: =W15/V15-1 -> 0.60422603 | X17: =X15/W15-1 -> 0.28376419 | Y17: =Y15/X15-1 -> -0.04733965 | Z17: =Z15/Y15-1 -> 0.039067308 | AA17: =AA15/Z15-1 -> -0.037162443
C19: =Model!C45 -> Net Income (Loss) | G19: =Model!P45 -> 136.849 | H19: =Model!Q45 -> 91.395 | I19: =Model!R45 -> 242.504 | J19: =Model!S45 -> 162.968 | K19: =Model!U45 -> 424.59742 | L19: =Model!V45 -> 459.46574 | M19: =Model!W45 -> 556.81753 | N19: =Model!X45 -> 600.76235 | O19: =Model!Z45 -> 429.86838 | P19: =Model!AA45 -> 513.32841 | Q19: =Model!AB45 -> 692.89705 | R19: =Model!AC45 -> 796.63206 | T19: =Model!J45 -> 221.117 | U19: =Model!O45 -> 661.299 | V19: =Model!T45 -> 633.716 | W19: =Model!Y45 -> 2041.643 | X19: =Model!AD45 -> 2432.7259 | Y19: =Model!AE45 -> 2333.1156 | Z19: =Model!AF45 -> 2424.2642 | AA19: =Model!AG45 -> 2334.1726 | AC19: =IFERROR((V19/T19)^(1/(V$4-T$4))-1,"N/A") -> 0.69291935 | AE19: =IFERROR((AA19/V19)^(1/(AA$4-V$4))-1,"N/A") -> -0.27015037
C20: Margin | G20: =G19/G$8 -> 0.055340286 | H20: =H19/H$8 -> 0.036641322 | I20: =I19/I$8 -> 0.083401372 | J20: =J19/J$8 -> 0.055265421 | K20: =K19/K$8 -> 0.10595883 | L20: =L19/L$8 -> 0.10514652 | M20: =M19/M$8 -> 0.10674655 | N20: =N19/N$8 -> 0.10813321 | ... R20: =R19/R$8 -> 0.13710279 | T20: =T19/T$8 -> 0.029714515 | U20: =U19/U$8 -> 0.0628906 | V20: =V19/V$8 -> 0.058549049 | W20: =W19/W$8 -> 0.1066189 | X20: =X19/X$8 -> 0.12056161 | Y20: =Y19/Y$8 -> 0.110824 | Z20: =Z19/Z$8 -> 0.11167419 | AA20: =AA19/AA$8 -> 0.10545369
C21: YoY % Growth | K21: =K19/G19-1 -> -0.81385748 | L21: =L19/H19-1 -> -0.81742411 | M21: =M19/I19-1 -> -0.82002154 | N21: =N19/J19-1 -> -0.82224299 | O21: =O19/K19-1 -> 0.012414007 | P21: =P19/L19-1 -> 0.11722893 | Q21: =Q19/M19-1 -> 0.244388 | R21: =R19/N19-1 -> 0.32603525 | U21: =U19/T19-1 -> 1.9907198 | V21: =V19/U19-1 -> -0.041710331 | W21: =W19/V19-1 -> -0.81886023 | X21: =X19/W19-1 -> 0.19155301 | Y21: =Y19/X19-1 -> -0.040945957 | Z21: =Z19/Y19-1 -> 0.039067308 | AA21: =AA19/Z19-1 -> -0.037162443
C23: =Model!C57 -> Adj. EPS (Diluted) | G23: =Model!P57 -> 0.57448482 | H23: =Model!Q57 -> 0.39665701 | I23: =Model!R57 -> 1.0057068 | J23: =Model!S57 -> 0.62085066 | K23: =Model!U57 -> 1.7209234 | L23: =Model!V57 -> 1.8891797 | M23: =Model!W57 -> 2.4111437 | N23: =Model!X57 -> 2.6493809 | O23: =Model!Z57 -> 2.0839822 | P23: =Model!AA57 -> 2.2818863 | Q23: =Model!AB57 -> 3.765282 | R23: =Model!AC57 -> 4.5622886 | T23: =Model!J57 -> 0.94143039 | U23: =Model!O57 -> 2.7800045 | V23: =Model!T57 -> 2.5987148 | W23: =Model!Y57 -> 8.6101474 | X23: =Model!AD57 -> 12.353374 | Y23: =Model!AE57 -> 13.270804 | Z23: =Model!AF57 -> 14.142717 | AA23: =Model!AG57 -> 13.927518 | AC23: =IFERROR((V23/T23)^(1/(V$4-T$4))-1,"N/A") -> 0.66144206 | AE23: =IFERROR((AA23/V23)^(1/(AA$4-V$4))-1,"N/A") -> -0.22685961
C24: YoY % Growth | K24: =K23/G23-1 -> -0.83150542 | L24: =L23/H23-1 -> -0.83319912 | M24: =M23/I23-1 -> -0.82538262 | N24: =N23/J23-1 -> -0.82410201 | O24: =O23/K23-1 -> 0.21096742 | P24: =P23/L23-1 -> 0.20787151 | Q24: =Q23/M23-1 -> 0.56161658 | R24: =R23/N23-1 -> 0.72202066 | U24: =IF(ISERROR(U23/T23-1),"NA",(U23/T23-1)) -> 1.9529581 | V24: =IF(ISERROR(V23/U23-1),"NA",(V23/U23-1)) -> -0.065212015 | W24: =IF(ISERROR(W23/V23-1),"NA",(W23/V23-1)) -> -0.82922327 | X24: =IF(ISERROR(X23/W23-1),"NA",(X23/W23-1)) -> 0.43474593 | Y24: =IF(ISERROR(Y23/X23-1),"NA",(Y23/X23-1)) -> 0.074265558 | Z24: =IF(ISERROR(Z23/Y23-1),"NA",(Z23/Y23-1)) -> 0.065701543 | AA24: =IF(ISERROR(AA23/Z23-1),"NA",(AA23/Z23-1)) -> -0.015216239
C27: =Model!C61 -> EBITDA | G27: =Model!P61 -> 172.997 | H27: =Model!Q61 -> 183.776 | I27: =Model!R61 -> 366.527 | J27: =Model!S61 -> 231.639 | K27: =Model!U61 -> 567.45455 | L27: =Model!V61 -> 643.65199 | M27: =Model!W61 -> 773.93172 | N27: =Model!X61 -> 812.72041 | O27: =Model!Z61 -> 598.26973 | P27: =Model!AA61 -> 710.05986 | Q27: =Model!AB61 -> 950.0348 | R27: =Model!AC61 -> 1087.7121 | T27: =Model!J61 -> 425.882 | U27: =Model!O61 -> 1105.407 | V27: =Model!T61 -> 954.939 | W27: =Model!Y61 -> 2797.7587 | X27: =Model!AD61 -> 3346.0765 | Y27: =Model!AE61 -> 3157.2841 | Z27: =Model!AF61 -> 3253.925 | AA27: =Model!AG61 -> 3102.5611 | AC27: =IFERROR((V27/T27)^(1/(V$4-T$4))-1,"N/A") -> 0.49741843 | AE27: =IFERROR((AA27/V27)^(1/(AA$4-V$4))-1,"N/A") -> -0.23173679
C28: Margin | G28: =G27/G$8 -> 0.069958154 | H28: =H27/H$8 -> 0.073677944 | I28: =I27/I$8 -> 0.12605505 | J28: =J27/J$8 -> 0.07855301 | K28: =K27/K$8 -> 0.14160901 | L28: =L27/L$8 -> 0.14729666 | M28: =M27/M$8 -> 0.14836915 | N28: =N27/N$8 -> 0.14628424 | ... R28: =R27/R$8 -> 0.18719856 | T28: =T27/T$8 -> 0.057231589 | U28: =U27/U$8 -> 0.10512599 | V28: =V27/V$8 -> 0.088226857 | W28: =W27/W$8 -> 0.14610485 | X28: =X27/X$8 -> 0.16582566 | Y28: =Y27/Y$8 -> 0.14997235 | Z28: =Z27/Z$8 -> 0.14989267 | AA28: =AA27/AA$8 -> 0.14016809
C29: YoY % Growth | K29: =K27/G27-1 -> -0.75511006 | L29: =L27/H27-1 -> -0.75329126 | M29: =M27/I27-1 -> -0.759486 | N29: =N27/J27-1 -> -0.76431642 | O29: =O27/K27-1 -> 0.054304226 | P29: =P27/L27-1 -> 0.10317356 | Q29: =Q27/M27-1 -> 0.22754344 | R29: =R27/N27-1 -> 0.33835958 | U29: =U27/T27-1 -> 1.5955711 | V29: =V27/U27-1 -> -0.13612 | W29: =W27/V27-1 -> -0.75865402 | X29: =X27/W27-1 -> 0.19598469 | Y29: =Y27/X27-1 -> -0.056422037 | Z29: =Z27/Y27-1 -> 0.030608859 | AA29: =AA27/Z27-1 -> -0.0465173
G31: =G$5 -> Quarterly | T31: =T$5 -> Annuals
A32: x | C32: ="Consolidated "&Model!C118 -> Consolidated Balance Sheet | G32: =G$6 -> 1Q25 | H32: =H$6 -> 2Q25 | I32: =I$6 -> 3Q25 | J32: =J$6 -> 4Q25 | K32: =K$6 -> 1Q26e | L32: =L$6 -> 2Q26e | M32: =M$6 -> 3Q26 | N32: =N$6 -> 4Q26e | ... R32: =R$6 -> 4Q27e | T32: =T$6 -> 2023 | U32: =U$6 -> 2024 | V32: =V$6 -> 2025 | W32: =W$6 -> 2026e | X32: =X$6 -> 2027e | Y32: =Y$6 -> 2028e | Z32: =Z$6 -> 2029e | AA32: =AA$6 -> 2030e
C34: =Model!C120 -> Cash & Cash Equivalents | G34: =Model!P120 -> 11176.343 | H34: =Model!Q120 -> 11260.403 | I34: =Model!R120 -> 11458.472 | J34: =Model!S120 -> 14043.889 | K34: =Model!U120 -> 10920.875 | L34: =Model!V120 -> 7054.6019 | M34: =Model!W120 -> 4564.8948 | N34: =Model!X120 -> 3427.7628 | O34: =Model!Z120 -> -89.421945 | P34: =Model!AA120 -> 6885.2868 | Q34: =Model!AB120 -> 5225.7751 | R34: =Model!AC120 -> 4200.5393 | T34: =Model!J120 -> 8526.363 | U34: =Model!O120 -> 12153.414 | V34: =Model!T120 -> 14043.889 | W34: =Model!Y120 -> 3427.7628 | X34: =Model!AD120 -> 4200.5393 | Y34: =Model!AE120 -> 837.3867 | Z34: =Model!AF120 -> 3766.0503 | AA34: =Model!AG120 -> 5400.0619
C35: =Model!C121 -> Accounts Receivable | G35: =Model!P121 -> 6703.258 | H35: =Model!Q121 -> 6225.189 | I35: =Model!R121 -> 6627.64 | J35: =Model!S121 -> 8556.388 | K35: =Model!U121 -> 6911.9883 | L35: =Model!V121 -> 6955.0491 | M35: =Model!W121 -> 7869.4947 | N35: =Model!X121 -> 7725.6431 | O35: =Model!Z121 -> 7430.7528 | P35: =Model!AA121 -> 7655.6891 | Q35: =Model!AB121 -> 8567.8601 | R35: =Model!AC121 -> 8336.9496 | T35: =Model!J121 -> 4716.299 | U35: =Model!O121 -> 5824.844 | V35: =Model!T121 -> 8556.388 | W35: =Model!Y121 -> 7725.6431 | X35: =Model!AD121 -> 8336.9496 | Y35: =Model!AE121 -> 9170.6939 | Z35: =Model!AF121 -> 9458.0958 | AA35: =Model!AG121 -> 9735.1316
C36: =Model!C122 -> Inventory | G36: =Model!P122 -> 0 | H36: =Model!Q122 -> 0 | I36: =Model!R122 -> 0 | J36: =Model!S122 -> 0 | K36: =Model!U122 -> 0 | L36: =Model!V122 -> 0 | M36: =Model!W122 -> 0 | N36: =Model!X122 -> 0 | O36: =Model!Z122 -> 0 | P36: =Model!AA122 -> 0 | Q36: =Model!AB122 -> 0 | R36: =Model!AC122 -> 0 | T36: =Model!J122 -> 0 | U36: =Model!O122 -> 0 | V36: =Model!T122 -> 0 | W36: =Model!Y122 -> 0 | X36: =Model!AD122 -> 0 | Y36: =Model!AE122 -> 0 | Z36: =Model!AF122 -> 0 | AA36: =Model!AG122 -> 0
C37: =Model!C123 -> Prepaid & Other Current Assets | G37: =Model!P123 -> 45950.985 | H37: =Model!Q123 -> 43438.891 | I37: =Model!R123 -> 44833.717 | J37: =Model!S123 -> 47081.324 | K37: =Model!U123 -> 50334.698 | L37: =Model!V123 -> 58997.556 | M37: =Model!W123 -> 63208.339 | N37: =Model!X123 -> 66708.665 | O37: =Model!Z123 -> 67969.214 | P37: =Model!AA123 -> 64201.312 | Q37: =Model!AB123 -> 67282.81 | R37: =Model!AC123 -> 70459.2 | T37: =Model!J123 -> 37552.851 | U37: =Model!O123 -> 40235.206 | V37: =Model!T123 -> 47081.324 | W37: =Model!Y123 -> 66708.665 | X37: =Model!AD123 -> 70459.2 | Y37: =Model!AE123 -> 77211.716 | Z37: =Model!AF123 -> 78168.048 | AA37: =Model!AG123 -> 80448.789
C38: =Model!C124 -> Total Current Assets | G38: =SUM(G34:G37) -> 63830.586 | H38: =SUM(H34:H37) -> 60924.483 | I38: =SUM(I34:I37) -> 62919.829 | J38: =SUM(J34:J37) -> 69681.601 | K38: =SUM(K34:K37) -> 71353.698 | L38: =SUM(L34:L37) -> 76889.178 | M38: =SUM(M34:M37) -> 80500.903 | N38: =SUM(N34:N37) -> 83470.257 | ... R38: =SUM(R34:R37) -> 88604.874 | T38: =SUM(T34:T37) -> 50795.513 | U38: =SUM(U34:U37) -> 58213.464 | V38: =SUM(V34:V37) -> 69681.601 | W38: =SUM(W34:W37) -> 83470.257 | X38: =SUM(X34:X37) -> 88604.874 | Y38: =SUM(Y34:Y37) -> 91943.713 | Z38: =SUM(Z34:Z37) -> 96044.537 | AA38: =SUM(AA34:AA37) -> 100236.33
C40: =Model!C125 -> PP&E, Net | G40: =Model!P126 -> 1217.202 | H40: =Model!Q126 -> 1235.343 | I40: =Model!R126 -> 1255 | J40: =Model!S126 -> 1246.47 | K40: =Model!U126 -> 1250.5117 | L40: =Model!V126 -> 1254.4012 | M40: =Model!W126 -> 1252.1224 | N40: =Model!X126 -> 1250.7918 | O40: =Model!Z126 -> 1251.9023 | P40: =Model!AA126 -> 1251.6051 | Q40: =Model!AB126 -> 1244.9303 | R40: =Model!AC126 -> 1238.5756 | T40: =Model!J126 -> 1065.68 | U40: =Model!O126 -> 1194.72 | V40: =Model!T126 -> 1246.47 | W40: =Model!Y126 -> 1250.7918 | X40: =Model!AD126 -> 1238.5756 | Y40: =Model!AE126 -> 1212.2213 | Z40: =Model!AF126 -> 1172.1541 | AA40: =Model!AG126 -> 1117.4596
C41: =Model!C127 -> Intangible Assets, Net | G41: =Model!P127 -> 0 | H41: =Model!Q127 -> 0 | I41: =Model!R127 -> 0 | J41: =Model!S127 -> 0 | K41: =Model!U127 -> 0 | L41: =Model!V127 -> 0 | M41: =Model!W127 -> 0 | N41: =Model!X127 -> 0 | O41: =Model!Z127 -> 0 | P41: =Model!AA127 -> 0 | Q41: =Model!AB127 -> 0 | R41: =Model!AC127 -> 0 | T41: =Model!J127 -> 0 | U41: =Model!O127 -> 0 | V41: =Model!T127 -> 0 | W41: =Model!Y127 -> 0 | X41: =Model!AD127 -> 0 | Y41: =Model!AE127 -> 0 | Z41: =Model!AF127 -> 0 | AA41: =Model!AG127 -> 0
C42: =Model!C128 -> Goodwill | G42: =Model!P128 -> 1824.647 | H42: =Model!Q128 -> 1842.114 | I42: =Model!R128 -> 1840.432 | J42: =Model!S128 -> 1837.57 | K42: =Model!U128 -> 1837.57 | L42: =Model!V128 -> 1837.57 | M42: =Model!W128 -> 1837.57 | N42: =Model!X128 -> 1837.57 | O42: =Model!Z128 -> 1837.57 | P42: =Model!AA128 -> 1837.57 | Q42: =Model!AB128 -> 1837.57 | R42: =Model!AC128 -> 1837.57 | T42: =Model!J128 -> 1847.856 | U42: =Model!O128 -> 1827.938 | V42: =Model!T128 -> 1837.57 | W42: =Model!Y128 -> 1837.57 | X42: =Model!AD128 -> 1837.57 | Y42: =Model!AE128 -> 1837.57 | Z42: =Model!AF128 -> 1837.57 | AA42: =Model!AG128 -> 1837.57
C43: =Model!C129 -> Other Non-Current Assets | G43: =Model!P129 -> 3346.456 | H43: =Model!Q129 -> 3283.404 | I43: =Model!R129 -> 3304.448 | J43: =Model!S129 -> 3246.706 | K43: =Model!U129 -> 3311.6401 | L43: =Model!V129 -> 3377.8729 | M43: =Model!W129 -> 3445.4304 | N43: =Model!X129 -> 3514.339 | O43: =Model!Z129 -> 3584.6258 | P43: =Model!AA129 -> 3656.3183 | Q43: =Model!AB129 -> 3729.4446 | R43: =Model!AC129 -> 3804.0335 | T43: =Model!J129 -> 4196.112 | U43: =Model!O129 -> 3124.187 | V43: =Model!T129 -> 3246.706 | W43: =Model!Y129 -> 3514.339 | X43: =Model!AD129 -> 3804.0335 | Y43: =Model!AE129 -> 4089.3361 | Z43: =Model!AF129 -> 4498.2697 | AA43: =Model!AG129 -> 4880.6226
C44: =Model!C130 -> Total Non-Current Assets | G44: =SUM(G40:G43) -> 6388.305 | H44: =SUM(H40:H43) -> 6360.861 | I44: =SUM(I40:I43) -> 6399.88 | J44: =SUM(J40:J43) -> 6330.746 | K44: =SUM(K40:K43) -> 6399.7219 | L44: =SUM(L40:L43) -> 6469.8441 | M44: =SUM(M40:M43) -> 6535.1228 | N44: =SUM(N40:N43) -> 6602.7007 | ... R44: =SUM(R40:R43) -> 6880.1791 | T44: =SUM(T40:T43) -> 7109.648 | U44: =SUM(U40:U43) -> 6146.845 | V44: =SUM(V40:V43) -> 6330.746 | W44: =SUM(W40:W43) -> 6602.7007 | X44: =SUM(X40:X43) -> 6880.1791 | Y44: =SUM(Y40:Y43) -> 7139.1274 | Z44: =SUM(Z40:Z43) -> 7507.9938 | AA44: =SUM(AA40:AA43) -> 7835.6522
C46: =Model!C132 -> Total Assets | G46: =SUM(G38,G44) -> 70218.891 | H46: =SUM(H38,H44) -> 67285.344 | I46: =SUM(I38,I44) -> 69319.709 | J46: =SUM(J38,J44) -> 76012.347 | K46: =SUM(K38,K44) -> 88243.888 | L46: =SUM(L38,L44) -> 94035.503 | M46: =SUM(M38,M44) -> 97895.447 | N46: =SUM(N38,N44) -> 101113.21 | ... R46: =SUM(R38,R44) -> 107314.86 | T46: =SUM(T38,T44) -> 57905.161 | U46: =SUM(U38,U44) -> 64360.309 | V46: =SUM(V38,V44) -> 76012.347 | W46: =SUM(W38,W44) -> 101113.21 | X46: =SUM(X38,X44) -> 107314.86 | Y46: =SUM(Y38,Y44) -> 111675.08 | Z46: =SUM(Z38,Z44) -> 117278.53 | AA46: =SUM(AA38,AA44) -> 122824.38
C48: =Model!C134 -> Short Term Borrowings | T48: =Model!J134 -> 989.715 | U48: =Model!O134 -> 443.16 | V48: =Model!T134 -> 1767.206 | W48: =Model!Y134 -> 1762.118 | X48: =Model!AD134 -> 1878.8771 | Y48: =Model!AE134 -> 1931.6675 | Z48: =Model!AF134 -> 2010.1515 | AA48: =Model!AG134 -> 2111.0136
C49: =Model!C135 -> Accounts Payable | G49: =Model!P135 -> 8344.09 | H49: =Model!Q135 -> 8076.672 | I49: =Model!R135 -> 8128.541 | J49: =Model!S135 -> 12171.814 | K49: =Model!U135 -> 7679.987 | L49: =Model!V135 -> 7712.252 | M49: =Model!W135 -> 8063.0069 | N49: =Model!X135 -> 8530.3976 | O49: =Model!Z135 -> 8256.392 | P49: =Model!AA135 -> 8489.1714 | Q49: =Model!AB135 -> 8778.5452 | R49: =Model!AC135 -> 9205.3818 | T49: =Model!J135 -> 7698.367 | U49: =Model!O135 -> 7760.342 | V49: =Model!T135 -> 12171.814 | W49: =Model!Y135 -> 8530.3976 | X49: =Model!AD135 -> 9205.3818 | Y49: =Model!AE135 -> 10143.343 | Z49: =Model!AF135 -> 10767.678 | AA49: =Model!AG135 -> 11157.959
C50: =Model!C136 -> Securities Loaned | G50: =Model!P136 -> 2501.643 | H50: =Model!Q136 -> 2041.795 | I50: =Model!R136 -> 2498.013 | J50: =Model!S136 -> 2540.759 | K50: =Model!U136 -> 2605.7099 | L50: =Model!V136 -> 2580.0989 | M50: =Model!W136 -> 2838.1784 | N50: =Model!X136 -> 2832.7358 | O50: =Model!Z136 -> 2801.2758 | P50: =Model!AA136 -> 2840.0137 | Q50: =Model!AB136 -> 3090.0479 | R50: =Model!AC136 -> 3056.8815 | T50: =Model!J136 -> 1840.518 | U50: =Model!O136 -> 2540.861 | V50: =Model!T136 -> 2540.759 | W50: =Model!Y136 -> 2832.7358 | X50: =Model!AD136 -> 3056.8815 | Y50: =Model!AE136 -> 3543.2227 | Z50: =Model!AF136 -> 3783.2383 | AA50: =Model!AG136 -> 3894.0527
C51: =Model!C137 -> Other Current Liabilities | G51: =Model!P137 -> 33145.954 | H51: =Model!Q137 -> 30117.227 | I51: =Model!R137 -> 30946.877 | J51: =Model!S137 -> 32994.068 | K51: =Model!U137 -> 30171.378 | L51: =Model!V137 -> 30849.008 | M51: =Model!W137 -> 30639.426 | N51: =Model!X137 -> 28971.162 | O51: =Model!Z137 -> 32435.826 | P51: =Model!AA137 -> 33956.685 | Q51: =Model!AB137 -> 33358.472 | R51: =Model!AC137 -> 31263.561 | T51: =Model!J137 -> 27875.268 | U51: =Model!O137 -> 29859.988 | V51: =Model!T137 -> 32994.068 | W51: =Model!Y137 -> 28971.162 | X51: =Model!AD137 -> 31263.561 | Y51: =Model!AE137 -> 35154.327 | Z51: =Model!AF137 -> 36668.31 | AA51: =Model!AG137 -> 38341.442
C52: =Model!C138 -> Total Current Liabilities (Excl. Debt) | G52: =SUM(G49:G51) -> 43991.687 | H52: =SUM(H49:H51) -> 40235.694 | I52: =SUM(I49:I51) -> 41573.431 | J52: =SUM(J49:J51) -> 47706.641 | K52: =SUM(K49:K51) -> 40457.075 | L52: =SUM(L49:L51) -> 41141.359 | M52: =SUM(M49:M51) -> 41540.611 | N52: =SUM(N49:N51) -> 40334.295 | ... R52: =SUM(R49:R51) -> 43525.824 | T52: =SUM(T48:T51) -> 38403.868 | U52: =SUM(U48:U51) -> 40604.351 | V52: =SUM(V48:V51) -> 49473.847 | W52: =SUM(W48:W51) -> 71375.816 | X52: =SUM(X48:X51) -> 74684.104 | Y52: =SUM(Y48:Y51) -> 75930.997 | Z52: =SUM(Z48:Z51) -> 78423.602 | AA52: =SUM(AA48:AA51) -> 81020.776
C54: =Model!C140 -> Revolver | G54: =Model!P140 -> 0 | H54: =Model!Q140 -> 0 | I54: =Model!R140 -> 0 | J54: =Model!S140 -> 0 | K54: =Model!U140 -> 0 | L54: =Model!V140 -> 0 | M54: =Model!W140 -> 0 | N54: =Model!X140 -> 0 | O54: =Model!Z140 -> 2269.8897 | P54: =Model!AA140 -> 0 | Q54: =Model!AB140 -> 0 | R54: =Model!AC140 -> 0 | T54: =Model!J140 -> 0 | U54: =Model!O140 -> 0 | V54: =Model!T140 -> 0 | W54: =Model!Y140 -> 0 | X54: =Model!AD140 -> 0 | Y54: =Model!AE140 -> 0 | Z54: =Model!AF140 -> 0 | AA54: =Model!AG140 -> 0
C55: =Model!C141 -> LT Debt (Incl. Current Portion) | G55: =Model!P141 -> 14785.553 | H55: =Model!Q141 -> 15351.967 | I55: =Model!R141 -> 16013.634 | J55: =Model!S141 -> 15895.891 | K55: =Model!U141 -> 16145.891 | L55: =Model!V141 -> 16395.891 | M55: =Model!W141 -> 16645.891 | N55: =Model!X141 -> 16895.891 | O55: =Model!Z141 -> 17145.891 | P55: =Model!AA141 -> 17395.891 | Q55: =Model!AB141 -> 17645.891 | R55: =Model!AC141 -> 17895.891 | T55: =Model!J141 -> 9698.752 | U55: =Model!O141 -> 13530.565 | V55: =Model!T141 -> 15895.891 | W55: =Model!Y141 -> 16895.891 | X55: =Model!AD141 -> 17895.891 | Y55: =Model!AE141 -> 19395.891 | Z55: =Model!AF141 -> 20895.891 | AA55: =Model!AG141 -> 22395.891
C56: =Model!C142 -> Deferred Income Taxes | G56: =Model!P142 -> 0 | H56: =Model!Q142 -> 0 | I56: =Model!R142 -> 0 | J56: =Model!S142 -> 0 | K56: =Model!U142 -> 0 | L56: =Model!V142 -> 0 | M56: =Model!W142 -> 0 | N56: =Model!X142 -> 0 | O56: =Model!Z142 -> 0 | P56: =Model!AA142 -> 0 | Q56: =Model!AB142 -> 0 | R56: =Model!AC142 -> 0 | T56: =Model!J142 -> 0 | U56: =Model!O142 -> 0 | V56: =Model!T142 -> 0 | W56: =Model!Y142 -> 0 | X56: =Model!AD142 -> 0 | Y56: =Model!AE142 -> 0 | Z56: =Model!AF142 -> 0 | AA56: =Model!AG142 -> 0
C57: =Model!C143 -> Other Non-Current Liabilities | G57: =Model!P143 -> 0 | H57: =Model!Q143 -> 0 | I57: =Model!R143 -> 0 | J57: =Model!S143 -> 0 | K57: =Model!U143 -> 0 | L57: =Model!V143 -> 0 | M57: =Model!W143 -> 0 | N57: =Model!X143 -> 0 | O57: =Model!Z143 -> 0 | P57: =Model!AA143 -> 0 | Q57: =Model!AB143 -> 0 | R57: =Model!AC143 -> 0 | T57: =Model!J143 -> 0 | U57: =Model!O143 -> 0 | V57: =Model!T143 -> 0 | W57: =Model!Y143 -> 0 | X57: =Model!AD143 -> 0 | Y57: =Model!AE143 -> 0 | Z57: =Model!AF143 -> 0 | AA57: =Model!AG143 -> 0
C58: =Model!C144 -> Total Non-Current Liabilities | G58: =SUM(G54:G57) -> 14785.553 | H58: {=INDEX(Data,MATCH($C58,Line_Items,0),MATCH(H$32,Fiscal_Periods,0))} -> 15351.967 | I58: {=INDEX(Data,MATCH($C58,Line_Items,0),MATCH(I$32,Fiscal_Periods,0))} -> 16013.634 | J58: {=INDEX(Data,MATCH($C58,Line_Items,0),MATCH(J$32,Fiscal_Periods,0))} -> 15895.891 | K58: {=INDEX(Data,MATCH($C58,Line_Items,0),MATCH(K$32,Fiscal_Periods,0))} -> 16145.891 | L58: {=INDEX(Data,MATCH($C58,Line_Items,0),MATCH(L$32,Fiscal_Periods,0))} -> 16395.891 | M58: {=INDEX(Data,MATCH($C58,Line_Items,0),MATCH(M$32,Fiscal_Periods,0))} -> 16645.891 | N58: {=INDEX(Data,MATCH($C58,Line_Items,0),MATCH(N$32,Fiscal_Periods,0))} -> 16895.891 | O58: {=INDEX(Data,MATCH($C58,Line_Items,0),MATCH(O$32,Fiscal_Periods,0))} -> 19415.781 | ... R58: {=INDEX(Data,MATCH($C58,Line_Items,0),MATCH(R$32,Fiscal_Periods,0))} -> 17895.891 | T58: {=INDEX(Data,MATCH($C58,Line_Items,0),MATCH(T$32,Fiscal_Periods,0))} -> 9698.752 | U58: {=INDEX(Data,MATCH($C58,Line_Items,0),MATCH(U$32,Fiscal_Periods,0))} -> 13530.565 | V58: {=INDEX(Data,MATCH($C58,Line_Items,0),MATCH(V$32,Fiscal_Periods,0))} -> 15895.891 | W58: {=INDEX(Data,MATCH($C58,Line_Items,0),MATCH(W$32,Fiscal_Periods,0))} -> 16895.891 | X58: {=INDEX(Data,MATCH($C58,Line_Items,0),MATCH(X$32,Fiscal_Periods,0))} -> 17895.891 | Y58: {=INDEX(Data,MATCH($C58,Line_Items,0),MATCH(Y$32,Fiscal_Periods,0))} -> 19395.891 | Z58: {=INDEX(Data,MATCH($C58,Line_Items,0),MATCH(Z$32,Fiscal_Periods,0))} -> 20895.891 | AA58: {=INDEX(Data,MATCH($C58,Line_Items,0),MATCH(AA$32,Fiscal_Periods,0))} -> 22395.891
C60: =Model!C146 -> Total Liabilities | G60: =SUM(G52,G58) -> 58777.24 | H60: =SUM(H52,H58) -> 55587.661 | I60: =SUM(I52,I58) -> 57587.065 | J60: =SUM(J52,J58) -> 63602.532 | K60: =SUM(K52,K58) -> 75251.981 | L60: =SUM(L52,L58) -> 80500.362 | M60: =SUM(M52,M58) -> 83831.291 | N60: =SUM(N52,N58) -> 86509.588 | ... R60: =SUM(R52,R58) -> 90701.118 | T60: =SUM(T52,T58) -> 48102.62 | U60: =SUM(U52,U58) -> 54134.916 | V60: =SUM(V52,V58) -> 65369.738 | W60: =SUM(W52,W58) -> 88271.707 | X60: =SUM(X52,X58) -> 92579.995 | Y60: =SUM(Y52,Y58) -> 95326.888 | Z60: =SUM(Z52,Z58) -> 99319.493 | AA60: =SUM(AA52,AA58) -> 103416.67
C62: =Model!C148 -> Common Stock & APIC | G62: =Model!P148 -> 2300.443 | H62: =Model!Q148 -> 2335.685 | I62: =Model!R148 -> 2351.744 | J62: =Model!S148 -> 2384.305 | K62: =Model!U148 -> 3095.5359 | L62: =Model!V148 -> 3114.9533 | M62: =Model!W148 -> 3137.2839 | N62: =Model!X148 -> 3159.5717 | O62: =Model!Z148 -> 3098.5479 | P62: =Model!AA148 -> 3160.6414 | Q62: =Model!AB148 -> 3266.3937 | R62: =Model!AC148 -> 3331.165 | T62: =Model!J148 -> 2255.528 | U62: =Model!O148 -> 2309.758 | V62: =Model!T148 -> 2384.305 | W62: =Model!Y148 -> 3159.5717 | X62: =Model!AD148 -> 3331.165 | Y62: =Model!AE148 -> 3427.3708 | Z62: =Model!AF148 -> 3528.1181 | AA62: =Model!AG148 -> 3631.8164
C63: =Model!C149 -> Retained Earnings | G63: =Model!P149 -> 8311.857 | H63: =Model!Q149 -> 8309.035 | I63: =Model!R149 -> 8461.907 | J63: =Model!S149 -> 8574.825 | K63: =Model!U149 -> 8888.1824 | L63: =Model!V149 -> 9234.3682 | M63: =Model!W149 -> 9678.9857 | N63: =Model!X149 -> 10167.512 | O63: =Model!Z149 -> 10463.892 | P63: =Model!AA149 -> 10841.285 | Q63: =Model!AB149 -> 11399.542 | R63: =Model!AC149 -> 12061.491 | T63: =Model!J149 -> 7849.844 | U63: =Model!O149 -> 8270.145 | V63: =Model!T149 -> 8574.825 | W63: =Model!Y149 -> 10167.512 | X63: =Model!AD149 -> 12061.491 | Y63: =Model!AE149 -> 13753.497 | Z63: =Model!AF149 -> 15440.486 | AA63: =Model!AG149 -> 16963.655
C64: =Model!C150 -> Treasury & Preferred Stock | G64: =Model!P150 -> 0 | H64: =Model!Q150 -> 0 | I64: =Model!R150 -> 0 | J64: =Model!S150 -> 0 | K64: =Model!U150 -> -40 | L64: =Model!V150 -> -80 | M64: =Model!W150 -> -120 | N64: =Model!X150 -> -160 | O64: =Model!Z150 -> -200 | P64: =Model!AA150 -> -240 | Q64: =Model!AB150 -> -280 | R64: =Model!AC150 -> -320 | T64: =Model!J150 -> 0 | U64: =Model!O150 -> 0 | V64: =Model!T150 -> 0 | W64: =Model!Y150 -> -160 | X64: =Model!AD150 -> -320 | Y64: =Model!AE150 -> -480 | Z64: =Model!AF150 -> -640 | AA64: =Model!AG150 -> -800
C65: =Model!C151 -> Accumulated Other Comprehensive Income (AOCI) | G65: =Model!P151 -> -408.072 | H65: =Model!Q151 -> -339.695 | I65: =Model!R151 -> -374.927 | J65: =Model!S151 -> -384.434 | K65: =Model!U151 -> -384.434 | L65: =Model!V151 -> -384.434 | M65: =Model!W151 -> -384.434 | N65: =Model!X151 -> -384.434 | O65: =Model!Z151 -> -384.434 | P65: =Model!AA151 -> -384.434 | Q65: =Model!AB151 -> -384.434 | R65: =Model!AC151 -> -384.434 | T65: =Model!J151 -> -395.545 | U65: =Model!O151 -> -423.131 | V65: =Model!T151 -> -384.434 | W65: =Model!Y151 -> -384.434 | X65: =Model!AD151 -> -384.434 | Y65: =Model!AE151 -> -384.434 | Z65: =Model!AF151 -> -384.434 | AA65: =Model!AG151 -> -384.434
C66: =Model!C152 -> Total Shareholder's Equity | G66: =SUM(G62:G65) -> 10204.228 | H66: =SUM(H62:H65) -> 10305.025 | I66: =SUM(I62:I65) -> 10438.724 | J66: =SUM(J62:J65) -> 10574.696 | K66: =SUM(K62:K65) -> 11555.772 | L66: =SUM(L62:L65) -> 11878.838 | M66: =SUM(M62:M65) -> 12303.604 | N66: =SUM(N62:N65) -> 12773.591 | ... R66: =SUM(R62:R65) -> 14666.954 | T66: =SUM(T62:T65) -> 9709.827 | U66: =SUM(U62:U65) -> 10156.772 | V66: =SUM(V62:V65) -> 10574.696 | W66: =SUM(W62:W65) -> 12773.591 | X66: =SUM(X62:X65) -> 14666.954 | Y66: =SUM(Y62:Y65) -> 16280.282 | Z66: =SUM(Z62:Z65) -> 17891.125 | AA66: =SUM(AA62:AA65) -> 19339.796
C68: =Model!C154 -> Noncontrolling Interests | G68: =Model!P154 -> 64.211 | H68: =Model!Q154 -> 77.149 | I68: =Model!R154 -> 62.186 | J68: =Model!S154 -> 67.507 | K68: =Model!U154 -> 67.507 | L68: =Model!V154 -> 67.507 | M68: =Model!W154 -> 67.507 | N68: =Model!X154 -> 67.507 | O68: =Model!Z154 -> 67.507 | P68: =Model!AA154 -> 67.507 | Q68: =Model!AB154 -> 67.507 | R68: =Model!AC154 -> 67.507 | T68: =Model!J154 -> 92.308 | U68: =Model!O154 -> 68.215 | V68: =Model!T154 -> 67.507 | W68: =Model!Y154 -> 67.507 | X68: =Model!AD154 -> 67.507 | Y68: =Model!AE154 -> 67.507 | Z68: =Model!AF154 -> 67.507 | AA68: =Model!AG154 -> 67.507
C69: =Model!C155 -> Total Equity | G69: =SUM(G66,G68) -> 10268.439 | H69: =SUM(H66,H68) -> 10382.174 | I69: =SUM(I66,I68) -> 10500.91 | J69: =SUM(J66,J68) -> 10642.203 | K69: =SUM(K66,K68) -> 11623.279 | L69: =SUM(L66,L68) -> 11946.345 | M69: =SUM(M66,M68) -> 12371.111 | N69: =SUM(N66,N68) -> 12841.098 | ... R69: =SUM(R66,R68) -> 14734.461 | T69: =SUM(T66,T68) -> 9802.135 | U69: =SUM(U66,U68) -> 10224.987 | V69: =SUM(V66,V68) -> 10642.203 | W69: =SUM(W66,W68) -> 12841.098 | X69: =SUM(X66,X68) -> 14734.461 | Y69: =SUM(Y66,Y68) -> 16347.789 | Z69: =SUM(Z66,Z68) -> 17958.632 | AA69: =SUM(AA66,AA68) -> 19407.303
C71: =Model!C157 -> Total Liabilities & Shareholder's Equity | G71: =SUM(G60,G69) -> 69045.679 | H71: =SUM(H60,H69) -> 65969.835 | I71: =SUM(I60,I69) -> 68087.975 | J71: =SUM(J60,J69) -> 74244.735 | K71: =SUM(K60,K69) -> 86875.26 | L71: =SUM(L60,L69) -> 92446.707 | M71: =SUM(M60,M69) -> 96202.402 | N71: =SUM(N60,N69) -> 99350.687 | ... R71: =SUM(R60,R69) -> 105435.58 | T71: =SUM(T60,T69) -> 57904.755 | U71: =SUM(U60,U69) -> 64359.903 | V71: =SUM(V60,V69) -> 76011.941 | W71: =SUM(W60,W69) -> 101112.8 | X71: =SUM(X60,X69) -> 107314.46 | Y71: =SUM(Y60,Y69) -> 111674.68 | Z71: =SUM(Z60,Z69) -> 117278.12 | AA71: =SUM(AA60,AA69) -> 122823.97
G73: =G$5 -> Quarterly | T73: =T$31 -> Annuals
A74: x | C74: Ratio Analysis | G74: =G$6 -> 1Q25 | H74: =H$6 -> 2Q25 | I74: =I$6 -> 3Q25 | J74: =J$6 -> 4Q25 | K74: =K$6 -> 1Q26e | L74: =L$6 -> 2Q26e | M74: =M$6 -> 3Q26 | N74: =N$6 -> 4Q26e | ... R74: =R$6 -> 4Q27e | T74: =T$6 -> 2023 | U74: =U$6 -> 2024 | V74: =V$6 -> 2025 | W74: =W$6 -> 2026e | X74: =X$6 -> 2027e | Y74: =Y$6 -> 2028e | Z74: =Z$6 -> 2029e | AA74: =AA$6 -> 2030e
C76: Profitability
C77: Gross Margin | G77: =G12 -> 0.6442 | H77: =H12 -> 0.65526888 | I77: =I12 -> 0.70414771 | J77: =J12 -> 0.70158578 | K77: =K12 -> 0.69334962 | L77: =L12 -> 0.68090095 | M77: =M12 -> 0.70546 | N77: =N12 -> 0.71345329 | ... R77: =R12 -> 0.73500174 | T77: =T12 -> 0.63165676 | U77: =U12 -> 0.6690211 | V77: =V12 -> 0.67848948 | W77: =W12 -> 0.69909207 | X77: =X12 -> 0.72317981 | Y77: =Y12 -> 0.81400555 | Z77: =Z12 -> 0.8051149 | AA77: =AA12 -> 0.79463636
C78: EBITDA Margin | G78: =G28 -> 0.069958154 | H78: =H28 -> 0.073677944 | I78: =I28 -> 0.12605505 | J78: =J28 -> 0.07855301 | K78: =K28 -> 0.14160901 | L78: =L28 -> 0.14729666 | M78: =M28 -> 0.14836915 | N78: =N28 -> 0.14628424 | ... R78: =R28 -> 0.18719856 | T78: =T28 -> 0.057231589 | U78: =U28 -> 0.10512599 | V78: =V28 -> 0.088226857 | W78: =W28 -> 0.14610485 | X78: =X28 -> 0.16582566 | Y78: =Y28 -> 0.14997235 | Z78: =Z28 -> 0.14989267 | AA78: =AA28 -> 0.14016809
C79: EBIT Margin | G79: =G16 -> 0.061089085 | H79: =H16 -> 0.054083386 | I79: =I16 -> 0.11411699 | J79: =J16 -> 0.067994902 | K79: =K16 -> 0.10666372 | L79: =L16 -> 0.10862483 | M79: =M16 -> 0.11148966 | N79: =N16 -> 0.1105749 | ... R79: =R16 -> 0.14762986 | T79: =T16 -> 0.042061687 | U79: =U16 -> 0.090773822 | V79: =V16 -> 0.07560148 | W79: =W16 -> 0.10947026 | X79: =X16 -> 0.12942473 | Y79: =Y16 -> 0.14776533 | Z79: =Z16 -> 0.14889891 | AA79: =AA16 -> 0.14060491
C80: Net Profit Margin | G80: =G20 -> 0.055340286 | H80: =H20 -> 0.036641322 | I80: =I20 -> 0.083401372 | J80: =J20 -> 0.055265421 | K80: =K20 -> 0.10595883 | L80: =L20 -> 0.10514652 | M80: =M20 -> 0.10674655 | N80: =N20 -> 0.10813321 | ... R80: =R20 -> 0.13710279 | T80: =T20 -> 0.029714515 | U80: =U20 -> 0.0628906 | V80: =V20 -> 0.058549049 | W80: =W20 -> 0.1066189 | X80: =X20 -> 0.12056161 | Y80: =Y20 -> 0.110824 | Z80: =Z20 -> 0.11167419 | AA80: =AA20 -> 0.10545369
C81: Return on Assets (ROA) | G81: =G19/G46 -> 0.0019488915 | H81: =H19/H46 -> 0.0013583196 | I81: =I19/I46 -> 0.0034983413 | J81: =J19/J46 -> 0.0021439675 | K81: =K19/K46 -> 0.0048116355 | L81: =L19/L46 -> 0.004886088 | M81: =M19/M46 -> 0.0056878797 | N81: =N19/N46 -> 0.0059414823 | ... R81: =R19/R46 -> 0.0074233153 | T81: =T19/T46 -> 0.0038186061 | U81: =U19/U46 -> 0.010274951 | V81: =V19/V46 -> 0.008337014 | W81: =W19/W46 -> 0.020191655 | X81: =X19/X46 -> 0.022669049 | Y81: =Y19/Y46 -> 0.020891998 | Z81: =Z19/Z46 -> 0.020670997 | AA81: =AA19/AA46 -> 0.019004148
C82: Return on Equity (ROE) | G82: =G19*4/G69 -> 0.05330859 | H82: =H19*4/H69 -> 0.035212278 | I82: =I19*4/I69 -> 0.09237447 | J82: =J19*4/J69 -> 0.061253483 | K82: =K19*4/K69 -> 0.14611967 | L82: =L19*4/L69 -> 0.15384312 | M82: =M19*4/M69 -> 0.180038 | N82: =N19*4/N69 -> 0.18713737 | ... R82: =R19*4/R69 -> 0.21626364 | T82: =T19/T69 -> 0.022558045 | U82: =U19/U69 -> 0.064674801 | V82: =V19/V69 -> 0.059547445 | W82: =W19/W69 -> 0.15899287 | X82: =X19/X69 -> 0.1651045 | Y82: =Y19/Y69 -> 0.1427175 | Z82: =Z19/Z69 -> 0.13499158 | AA82: =AA19/AA69 -> 0.1202729
C83: Return on Invested Capital (ROIC) | G83: =G19*4/(G54+G55+G69) -> 0.021848654 | H83: =H19*4/(H54+H55+H69) -> 0.014206031 | I83: =I19*4/(I54+I55+I69) -> 0.036584299 | J83: =J19*4/(J54+J55+J69) -> 0.024563633 | K83: =K19*4/(K54+K55+K69) -> 0.061160981 | L83: =L19*4/(L54+L55+L69) -> 0.064845377 | M83: =M19*4/(M54+M55+M69) -> 0.076757415 | N83: =N19*4/(N54+N55+N69) -> 0.080810111 | ... S83: =S19*4/(S54+S55+S69) -> #DIV/0! | T83: =T19/(T54+T55+T69) -> 0.011338818 | U83: =U19/(U54+U55+U69) -> 0.027837661 | V83: =V19/(V54+V55+V69) -> 0.023879484 | W83: =W19/(W54+W55+W69) -> 0.068656683 | X83: =X19/(X54+X55+X69) -> 0.07455408 | Y83: =Y19/(Y54+Y55+Y69) -> 0.065273515 | Z83: =Z19/(Z54+Z55+Z69) -> 0.062393358 | AA83: =AA19/(AA54+AA55+AA69) -> 0.055837183
C85: Coverage
C86: Interest Expense | G86: =-Model!P39 -> 0 | H86: =-Model!Q39 -> 0 | I86: =-Model!R39 -> 0 | J86: =-Model!S39 -> 0 | K86: =-Model!U39 -> 0 | L86: =-Model!V39 -> 0 | M86: =-Model!W39 -> 0 | N86: =-Model!X39 -> 0 | O86: =-Model!Z39 -> 0 | P86: =-Model!AA39 -> 0 | Q86: =-Model!AB39 -> 0 | R86: =-Model!AC39 -> 0 | T86: =-Model!J39 -> 0 | U86: =-Model!O39 -> 0 | V86: =-Model!T39 -> 0 | W86: =-Model!Y39 -> 0 | X86: =-Model!AD39 -> 0 | Y86: =-Model!AE39 -> 0 | Z86: =-Model!AF39 -> 0 | AA86: =-Model!AG39 -> 0
C87: Capital Expenditures | G87: =Model!P196 -> -49.578 | H87: =Model!Q196 -> -49.422 | I87: =Model!R196 -> -56 | J87: =Model!S196 -> -18 | K87: =Model!U196 -> -41.142788 | L87: =Model!V196 -> -42.066829 | M87: =Model!W196 -> -48.378041 | N87: =Model!X196 -> -48.28527 | O87: =Model!Z196 -> -44.230671 | P87: =Model!AA196 -> -46.304571 | Q87: =Model!AB196 -> -52.671271 | R87: =Model!AC196 -> -52.105935 | T87: =Model!J196 -> -91 | U87: =Model!O196 -> -173 | V87: =Model!T196 -> -173 | W87: =Model!Y196 -> -179.87293 | X87: =Model!AD196 -> -195.31245 | Y87: =Model!AE196 -> -208.42486 | Z87: =Model!AF196 -> -218.26375 | AA87: =Model!AG196 -> -224.65688
C88: EBIT / Interest Expense | G88: =IF(ISERROR(G15/G86),"N/A",(G15/G86)) -> N/A | H88: =IF(ISERROR(H15/H86),"N/A",(H15/H86)) -> N/A | I88: =IF(ISERROR(I15/I86),"N/A",(I15/I86)) -> N/A | J88: =IF(ISERROR(J15/J86),"N/A",(J15/J86)) -> N/A | K88: =IF(ISERROR(K15/K86),"N/A",(K15/K86)) -> N/A | L88: =IF(ISERROR(L15/L86),"N/A",(L15/L86)) -> N/A | M88: =IF(ISERROR(M15/M86),"N/A",(M15/M86)) -> N/A | N88: =IF(ISERROR(N15/N86),"N/A",(N15/N86)) -> N/A | ... R88: =IF(ISERROR(R15/R86),"N/A",(R15/R86)) -> N/A | T88: =IF(ISERROR(T15/T86),"N/A",(T15/T86)) -> N/A | U88: =IF(ISERROR(U15/U86),"N/A",(U15/U86)) -> N/A | V88: =IF(ISERROR(V15/V86),"N/A",(V15/V86)) -> N/A | W88: =IF(ISERROR(W15/W86),"N/A",(W15/W86)) -> N/A | X88: =IF(ISERROR(X15/X86),"N/A",(X15/X86)) -> N/A | Y88: =IF(ISERROR(Y15/Y86),"N/A",(Y15/Y86)) -> N/A | Z88: =IF(ISERROR(Z15/Z86),"N/A",(Z15/Z86)) -> N/A | AA88: =IF(ISERROR(AA15/AA86),"N/A",(AA15/AA86)) -> N/A
C89: EBITDA / Interest Expense | G89: =IF(ISERROR(G27/G86),"N/A",(G27/G86)) -> N/A | H89: =IF(ISERROR(H27/H86),"N/A",(H27/H86)) -> N/A | I89: =IF(ISERROR(I27/I86),"N/A",(I27/I86)) -> N/A | J89: =IF(ISERROR(J27/J86),"N/A",(J27/J86)) -> N/A | K89: =IF(ISERROR(K27/K86),"N/A",(K27/K86)) -> N/A | L89: =IF(ISERROR(L27/L86),"N/A",(L27/L86)) -> N/A | M89: =IF(ISERROR(M27/M86),"N/A",(M27/M86)) -> N/A | N89: =IF(ISERROR(N27/N86),"N/A",(N27/N86)) -> N/A | ... R89: =IF(ISERROR(R27/R86),"N/A",(R27/R86)) -> N/A | T89: =IF(ISERROR(T27/T86),"N/A",(T27/T86)) -> N/A | U89: =IF(ISERROR(U27/U86),"N/A",(U27/U86)) -> N/A | V89: =IF(ISERROR(V27/V86),"N/A",(V27/V86)) -> N/A | W89: =IF(ISERROR(W27/W86),"N/A",(W27/W86)) -> N/A | X89: =IF(ISERROR(X27/X86),"N/A",(X27/X86)) -> N/A | Y89: =IF(ISERROR(Y27/Y86),"N/A",(Y27/Y86)) -> N/A | Z89: =IF(ISERROR(Z27/Z86),"N/A",(Z27/Z86)) -> N/A | AA89: =IF(ISERROR(AA27/AA86),"N/A",(AA27/AA86)) -> N/A
C90: (EBITDA - CapEx) / Interest Expense | G90: =IF(ISERROR((G27-G87)/G86),"N/A",((G27-G87)/G86)) -> N/A | H90: =IF(ISERROR((H27-H87)/H86),"N/A",((H27-H87)/H86)) -> N/A | I90: =IF(ISERROR((I27-I87)/I86),"N/A",((I27-I87)/I86)) -> N/A | J90: =IF(ISERROR((J27-J87)/J86),"N/A",((J27-J87)/J86)) -> N/A | K90: =IF(ISERROR((K27-K87)/K86),"N/A",((K27-K87)/K86)) -> N/A | L90: =IF(ISERROR((L27-L87)/L86),"N/A",((L27-L87)/L86)) -> N/A | M90: =IF(ISERROR((M27-M87)/M86),"N/A",((M27-M87)/M86)) -> N/A | N90: =IF(ISERROR((N27-N87)/N86),"N/A",((N27-N87)/N86)) -> N/A | ... R90: =IF(ISERROR((R27-R87)/R86),"N/A",((R27-R87)/R86)) -> N/A | T90: =IF(ISERROR((T27-T87)/T86),"N/A",((T27-T87)/T86)) -> N/A | U90: =IF(ISERROR((U27-U87)/U86),"N/A",((U27-U87)/U86)) -> N/A | V90: =IF(ISERROR((V27-V87)/V86),"N/A",((V27-V87)/V86)) -> N/A | W90: =IF(ISERROR((W27-W87)/W86),"N/A",((W27-W87)/W86)) -> N/A | X90: =IF(ISERROR((X27-X87)/X86),"N/A",((X27-X87)/X86)) -> N/A | Y90: =IF(ISERROR((Y27-Y87)/Y86),"N/A",((Y27-Y87)/Y86)) -> N/A | Z90: =IF(ISERROR((Z27-Z87)/Z86),"N/A",((Z27-Z87)/Z86)) -> N/A | AA90: =IF(ISERROR((AA27-AA87)/AA86),"N/A",((AA27-AA87)/AA86)) -> N/A
C92: Leverage
C93: Total Debt / EBITDA | G93: =IF(ISERROR((G54+G55)/G27),"NA",((G54+G55)/G27)) -> 85.467106 | H93: =IF(ISERROR((H54+H55)/H27),"NA",((H54+H55)/H27)) -> 83.5363 | I93: =IF(ISERROR((I54+I55)/I27),"NA",((I54+I55)/I27)) -> 43.690189 | J93: =IF(ISERROR((J54+J55)/J27),"NA",((J54+J55)/J27)) -> 68.623552 | K93: =IF(ISERROR((K54+K55)/K27),"NA",((K54+K55)/K27)) -> 28.453188 | L93: =IF(ISERROR((L54+L55)/L27),"NA",((L54+L55)/L27)) -> 25.473224 | M93: =IF(ISERROR((M54+M55)/M27),"NA",((M54+M55)/M27)) -> 21.508216 | N93: =IF(ISERROR((N54+N55)/N27),"NA",((N54+N55)/N27)) -> 20.789303 | ... R93: =IF(ISERROR((R54+R55)/R27),"NA",((R54+R55)/R27)) -> 16.452782 | T93: =IF(ISERROR((T54+T55)/T27),"NA",((T54+T55)/T27)) -> 22.773332 | U93: =IF(ISERROR((U54+U55)/U27),"NA",((U54+U55)/U27)) -> 12.240347 | V93: =IF(ISERROR((V54+V55)/V27),"NA",((V54+V55)/V27)) -> 16.645975 | W93: =IF(ISERROR((W54+W55)/W27),"NA",((W54+W55)/W27)) -> 6.0390809 | X93: =IF(ISERROR((X54+X55)/X27),"NA",((X54+X55)/X27)) -> 5.3483209 | Y93: =IF(ISERROR((Y54+Y55)/Y27),"NA",((Y54+Y55)/Y27)) -> 6.1432201 | Z93: =IF(ISERROR((Z54+Z55)/Z27),"NA",((Z54+Z55)/Z27)) -> 6.4217495 | AA93: =IF(ISERROR((AA54+AA55)/AA27),"NA",((AA54+AA55)/AA27)) -> 7.2185172
C94: Total Debt / Equity | G94: =IF(ISERROR((G54+G55)/G69),"NA",((G54+G55)/G69)) -> 1.4399027 | H94: =IF(ISERROR((H54+H55)/H69),"NA",((H54+H55)/H69)) -> 1.4786852 | I94: =IF(ISERROR((I54+I55)/I69),"NA",((I54+I55)/I69)) -> 1.5249758 | J94: =IF(ISERROR((J54+J55)/J69),"NA",((J54+J55)/J69)) -> 1.4936655 | K94: =IF(ISERROR((K54+K55)/K69),"NA",((K54+K55)/K69)) -> 1.3890995 | L94: =IF(ISERROR((L54+L55)/L69),"NA",((L54+L55)/L69)) -> 1.3724609 | M94: =IF(ISERROR((M54+M55)/M69),"NA",((M54+M55)/M69)) -> 1.3455453 | N94: =IF(ISERROR((N54+N55)/N69),"NA",((N54+N55)/N69)) -> 1.3157668 | ... R94: =IF(ISERROR((R54+R55)/R69),"NA",((R54+R55)/R69)) -> 1.2145602 | T94: =IF(ISERROR((T54+T55)/T69),"NA",((T54+T55)/T69)) -> 0.98945301 | U94: =IF(ISERROR((U54+U55)/U69),"NA",((U54+U55)/U69)) -> 1.3232843 | V94: =IF(ISERROR((V54+V55)/V69),"NA",((V54+V55)/V69)) -> 1.4936655 | W94: =IF(ISERROR((W54+W55)/W69),"NA",((W54+W55)/W69)) -> 1.3157668 | X94: =IF(ISERROR((X54+X55)/X69),"NA",((X54+X55)/X69)) -> 1.2145602 | Y94: =IF(ISERROR((Y54+Y55)/Y69),"NA",((Y54+Y55)/Y69)) -> 1.1864535 | Z94: =IF(ISERROR((Z54+Z55)/Z69),"NA",((Z54+Z55)/Z69)) -> 1.1635569 | AA94: =IF(ISERROR((AA54+AA55)/AA69),"NA",((AA54+AA55)/AA69)) -> 1.153993
C95: Total Debt / Total Assets | G95: =IF(ISERROR((G54+G55)/G46),"NA",((G54+G55)/G46)) -> 0.21056375 | H95: =IF(ISERROR((H54+H55)/H46),"NA",((H54+H55)/H46)) -> 0.22816212 | I95: =IF(ISERROR((I54+I55)/I46),"NA",((I54+I55)/I46)) -> 0.23101127 | J95: =IF(ISERROR((J54+J55)/J46),"NA",((J54+J55)/J46)) -> 0.20912249 | K95: =IF(ISERROR((K54+K55)/K46),"NA",((K54+K55)/K46)) -> 0.18296894 | L95: =IF(ISERROR((L54+L55)/L46),"NA",((L54+L55)/L46)) -> 0.17435852 | M95: =IF(ISERROR((M54+M55)/M46),"NA",((M54+M55)/M46)) -> 0.17003744 | N95: =IF(ISERROR((N54+N55)/N46),"NA",((N54+N55)/N46)) -> 0.16709875 | ... R95: =IF(ISERROR((R54+R55)/R46),"NA",((R54+R55)/R46)) -> 0.1667606 | T95: =IF(ISERROR((T54+T55)/T46),"NA",((T54+T55)/T46)) -> 0.16749374 | U95: =IF(ISERROR((U54+U55)/U46),"NA",((U54+U55)/U46)) -> 0.21023151 | V95: =IF(ISERROR((V54+V55)/V46),"NA",((V54+V55)/V46)) -> 0.20912249 | W95: =IF(ISERROR((W54+W55)/W46),"NA",((W54+W55)/W46)) -> 0.16709875 | X95: =IF(ISERROR((X54+X55)/X46),"NA",((X54+X55)/X46)) -> 0.1667606 | Y95: =IF(ISERROR((Y54+Y55)/Y46),"NA",((Y54+Y55)/Y46)) -> 0.17368146 | Z95: =IF(ISERROR((Z54+Z55)/Z46),"NA",((Z54+Z55)/Z46)) -> 0.1781732 | AA95: =IF(ISERROR((AA54+AA55)/AA46),"NA",((AA54+AA55)/AA46)) -> 0.18234077
C97: Efficiency
C98: Asset Turnover | G98: =G8/G46 -> 0.035216506 | H98: =H8/H46 -> 0.037070703 | I98: =I8/I46 -> 0.041945848 | J98: =J8/J46 -> 0.038794013 | K98: =K8/K46 -> 0.045410426 | L98: =L8/L46 -> 0.046469324 | M98: =M8/M46 -> 0.053283967 | N98: =N8/N46 -> 0.054945955 | ... R98: =R8/R46 -> 0.054144159 | T98: =T8/T46 -> 0.12850979 | U98: =U8/U46 -> 0.16337816 | V98: =V8/V46 -> 0.14239367 | W98: =W8/W46 -> 0.18938157 | X98: =X8/X46 -> 0.18802875 | Y98: =Y8/Y46 -> 0.18851511 | Z98: =Z8/Z46 -> 0.18510094 | AA98: =AA8/AA46 -> 0.18021322
C99: =Model!C184 -> Accounts Receivables as a % of Sales | G99: =Model!P184 -> 0.67768163 | H99: =Model!Q184 -> 0.62393773 | I99: =Model!R184 -> 0.56984036 | J99: =Model!S184 -> 0.72540681 | K99: =Model!U184 -> 0.63 | L99: =Model!V184 -> 0.62 | M99: =Model!W184 -> 0.61 | N99: =Model!X184 -> 0.6 | O99: =Model!Z184 -> 0.63 | P99: =Model!AA184 -> 0.62 | Q99: =Model!AB184 -> 0.61 | R99: =Model!AC184 -> 0.6 | T99: =Model!J184 -> 0.6337936 | U99: =Model!O184 -> 0.55395205 | V99: =Model!T184 -> 0.79052507 | W99: =Model!Y184 -> 0.64425841 | X99: =Model!AD184 -> 0.6402779 | Y99: =Model!AE184 -> 0.66 | Z99: =Model!AF184 -> 0.65 | AA99: =Model!AG184 -> 0.65
C100: =Model!C185 -> Mezzanine Debt as a % of Previous Liabilities | G100: =Model!P185 -> 7.4997807e-06 | H100: =Model!Q185 -> 6.7723051e-06 | I100: =Model!R185 -> 7.1349785e-06 | J100: =Model!S185 -> 6.9026027e-06 | K100: =Model!U185 -> 0 | L100: =Model!V185 -> 0 | M100: =Model!W185 -> 0 | N100: =Model!X185 -> 0 | O100: =Model!Z185 -> 0 | P100: =Model!AA185 -> 0 | Q100: =Model!AB185 -> 0 | R100: =Model!AC185 -> 0 | T100: =Model!J185 -> 8.4402887e-06 | U100: =Model!O185 -> 7.4997807e-06 | V100: =Model!T185 -> 0 | W100: =Model!Y185 -> 0 | X100: =Model!AD185 -> 0 | Y100: =Model!AE185 -> 0 | Z100: =Model!AF185 -> 0 | AA100: =Model!AG185 -> 0
C101: =Model!C186 -> Prepaid & Other Curernt Assets as a % of Previous Assets | G101: =Model!P186 -> 0.84882343 | H101: =Model!Q186 -> 0.72458478 | I101: =Model!R186 -> 0.78790051 | J101: =Model!S186 -> 0.8004524 | K101: =Model!U186 -> 0.77 | L101: =Model!V186 -> 0.77 | M101: =Model!W186 -> 0.77 | N101: =Model!X186 -> 0.78 | O101: =Model!Z186 -> 0.77 | P101: =Model!AA186 -> 0.77 | Q101: =Model!AB186 -> 0.77 | R101: =Model!AC186 -> 0.78 | T101: =Model!J186 -> 0.78068203 | U101: =Model!O186 -> 0.74323946 | V101: =Model!T186 -> 0.72023119 | W101: =Model!Y186 -> 0.75571967 | X101: =Model!AD186 -> 0.76106291 | Y101: =Model!AE186 -> 0.834 | Z101: =Model!AF186 -> 0.82 | AA101: =Model!AG186 -> 0.81
C102: Cash Conversion Cycle | G102: =G99+G100-G101 -> -0.1711343 | H102: =H99+H100-H101 -> -0.10064028 | I102: =I99+I100-I101 -> -0.21805302 | J102: =J99+J100-J101 -> -0.075038694 | K102: =K99+K100-K101 -> -0.14 | L102: =L99+L100-L101 -> -0.15 | M102: =M99+M100-M101 -> -0.16 | N102: =N99+N100-N101 -> -0.18 | ... R102: =R99+R100-R101 -> -0.18 | T102: =T99+T100-T101 -> -0.14687999 | U102: =U99+U100-U101 -> -0.18927992 | V102: =V99+V100-V101 -> 0.070293881 | W102: =W99+W100-W101 -> -0.059399047 | X102: =X99+X100-X101 -> -0.069966577 | Y102: =Y99+Y100-Y101 -> -0.174 | Z102: =Z99+Z100-Z101 -> -0.17 | AA102: =AA99+AA100-AA101 -> -0.16
C104: Liquidity
C105: Current Ratio | G105: =IF(ISERROR(G38/G52),"NA",(G38/G52)) -> 1.4509693 | H105: =IF(ISERROR(H38/H52),"NA",(H38/H52)) -> 1.5141899 | I105: =IF(ISERROR(I38/I52),"NA",(I38/I52)) -> 1.5134625 | J105: =IF(ISERROR(J38/J52),"NA",(J38/J52)) -> 1.4606269 | K105: =IF(ISERROR(K38/K52),"NA",(K38/K52)) -> 1.207214 | L105: =IF(ISERROR(L38/L52),"NA",(L38/L52)) -> 1.1994355 | M105: =IF(ISERROR(M38/M52),"NA",(M38/M52)) -> 1.1981904 | N105: =IF(ISERROR(N38/N52),"NA",(N38/N52)) -> 1.1990493 | ... R105: =IF(ISERROR(R38/R52),"NA",(R38/R52)) -> 1.2170125 | T105: =IF(ISERROR(T38/T52),"NA",(T38/T52)) -> 1.3226666 | U105: =IF(ISERROR(U38/U52),"NA",(U38/U52)) -> 1.4336755 | V105: =IF(ISERROR(V38/V52),"NA",(V38/V52)) -> 1.4084533 | W105: =IF(ISERROR(W38/W52),"NA",(W38/W52)) -> 1.1694473 | X105: =IF(ISERROR(X38/X52),"NA",(X38/X52)) -> 1.1863954 | Y105: =IF(ISERROR(Y38/Y52),"NA",(Y38/Y52)) -> 1.2108851 | Z105: =IF(ISERROR(Z38/Z52),"NA",(Z38/Z52)) -> 1.2246892 | AA105: =IF(ISERROR(AA38/AA52),"NA",(AA38/AA52)) -> 1.2371682
C106: Quick Ratio | G106: =IF(ISERROR((G34+G35)/G52),"NA",((G34+G35)/G52)) -> 0.40643136 | H106: =IF(ISERROR((H34+H35)/H52),"NA",((H34+H35)/H52)) -> 0.43457911 | I106: =IF(ISERROR((I34+I35)/I52),"NA",((I34+I35)/I52)) -> 0.43504016 | J106: =IF(ISERROR((J34+J35)/J52),"NA",((J34+J35)/J52)) -> 0.4737344 | K106: =IF(ISERROR((K34+K35)/K52),"NA",((K34+K35)/K52)) -> 0.35561479 | L106: =IF(ISERROR((L34+L35)/L52),"NA",((L34+L35)/L52)) -> 0.279101 | M106: =IF(ISERROR((M34+M35)/M52),"NA",((M34+M35)/M52)) -> 0.25738574 | N106: =IF(ISERROR((N34+N35)/N52),"NA",((N34+N35)/N52)) -> 0.24078008 | ... R106: =IF(ISERROR((R34+R35)/R52),"NA",((R34+R35)/R52)) -> 0.24923588 | T106: =IF(ISERROR((T34+T35)/T52),"NA",((T34+T35)/T52)) -> 0.34482626 | U106: =IF(ISERROR((U34+U35)/U52),"NA",((U34+U35)/U52)) -> 0.44276679 | V106: =IF(ISERROR((V34+V35)/V52),"NA",((V34+V35)/V52)) -> 0.45681261 | W106: =IF(ISERROR((W34+W35)/W52),"NA",((W34+W35)/W52)) -> 0.23483573 | X106: =IF(ISERROR((X34+X35)/X52),"NA",((X34+X35)/X52)) -> 0.24296569 | Y106: =IF(ISERROR((Y34+Y35)/Y52),"NA",((Y34+Y35)/Y52)) -> 0.19401823 | Z106: =IF(ISERROR((Z34+Z35)/Z52),"NA",((Z34+Z35)/Z52)) -> 0.22794781 | AA106: =IF(ISERROR((AA34+AA35)/AA52),"NA",((AA34+AA35)/AA52)) -> 0.24422793
C107: Cash Ratio | G107: =IF(ISERROR(G34/G52),"NA",(G34/G52)) -> 0.25405579 | H107: =IF(ISERROR(H34/H52),"NA",(H34/H52)) -> 0.27986104 | I107: =IF(ISERROR(I34/I52),"NA",(I34/I52)) -> 0.27562007 | J107: =IF(ISERROR(J34/J52),"NA",(J34/J52)) -> 0.29438017 | K107: =IF(ISERROR(K34/K52),"NA",(K34/K52)) -> 0.18476733 | L107: =IF(ISERROR(L34/L52),"NA",(L34/L52)) -> 0.11004852 | M107: =IF(ISERROR(M34/M52),"NA",(M34/M52)) -> 0.067944744 | N107: =IF(ISERROR(N34/N52),"NA",(N34/N52)) -> 0.049239776 | ... R107: =IF(ISERROR(R34/R52),"NA",(R34/R52)) -> 0.057695573 | T107: =IF(ISERROR(T34/T52),"NA",(T34/T52)) -> 0.22201834 | U107: =IF(ISERROR(U34/U52),"NA",(U34/U52)) -> 0.2993131 | V107: =IF(ISERROR(V34/V52),"NA",(V34/V52)) -> 0.28386491 | W107: =IF(ISERROR(W34/W52),"NA",(W34/W52)) -> 0.04802415 | X107: =IF(ISERROR(X34/X52),"NA",(X34/X52)) -> 0.056244088 | Y107: =IF(ISERROR(Y34/Y52),"NA",(Y34/Y52)) -> 0.011028259 | Z107: =IF(ISERROR(Z34/Z52),"NA",(Z34/Z52)) -> 0.0480219 | AA107: =IF(ISERROR(AA34/AA52),"NA",(AA34/AA52)) -> 0.066650336
A111: x

Sheet Model Output
B1: =Company_Name&" "&"("&Ticker&")"&" Valuation Overview" -> Jefferies Financial Group Inc. (JEF) Valuation Overview | K1: Price Target Scenario: | N1: =Case_Scenario&" Case" -> Base Case | R1: Base Case Check | S1: =IF(N1="Base Case","","Check!") | Y1: P/E
B2: =Cover!C2 -> $ in Millions Except Per Share Data | K2: Current Share Price: | O2: =Share_Price -> 38.03 | Y2: EV/EBITDA
K3: Valuation Date: | O3: =Current_Date -> 46091
B4: ="Multiples Analysis "&"("&S21&")" -> Multiples Analysis (P/E) | I4: Return Summary
I6: Exit Multiple Method
I7: =Cover!I9 -> Implied Enterprise Value: | N7: =Cover!L9 -> 15177.212
I8: =Cover!I10 -> Implied Equity Value: | N8: =Cover!L10 -> 15177.212
I9: =Cover!I12 -> Implied Share Price: | N9: =Cover!L12 -> 68.136855
I10: =Cover!I13 -> % Return: | N10: =Cover!L13 -> 0.79166065
I12: =Cover!I15 -> Dividend Discount Model
I13: =Cover!I16 -> Implied Enterprise Value: | N13: =Cover!L16 -> 16987.417
I14: =Cover!I17 -> Implied Equity Value: | N14: =Cover!L17 -> 16987.417
I15: =Cover!I19 -> Implied Share Price: | N15: =Cover!L19 -> 76.263622
I16: =Cover!I20 -> % Return: | N16: =Cover!L20 -> 1.0053543
E18: Annuals | M18: CAGR | O18: CAGR
B19: Consolidated Financials | E19: =Summary!U6 -> 2024 | F19: =Summary!V6 -> 2025 | G19: =Summary!W6 -> 2026e | H19: =Summary!X6 -> 2027e | I19: =Summary!Y6 -> 2028e | J19: =Summary!Z6 -> 2029e | K19: =Summary!AA6 -> 2030e | M19: Historical | O19: Projected
B21: =Summary!C8 -> Revenue | D21: =Summary!T8 -> 7441.38 | E21: =Summary!U8 -> 10515.069 | F21: =Summary!V8 -> 10823.677 | G21: =Summary!W8 -> 11991.529 | H21: =Summary!X8 -> 13020.83 | I21: =Summary!Y8 -> 13894.991 | J21: =Summary!Z8 -> 14550.917 | K21: =Summary!AA8 -> 14977.126 | M21: =Summary!AC8 -> 0.20603711 | O21: =Summary!AE8 -> 0.067113784 | R21: Multiple Toggle | S21: P/E
B22: =Summary!C9 -> YoY % Growth | E22: =Summary!U9 -> 0.41305363 | F22: =Summary!V9 -> 0.029349118 | G22: =Summary!W9 -> 0.10789785 | H22: =Summary!X9 -> 0.085835711 | I22: =Summary!Y9 -> 0.067135576 | J22: =Summary!Z9 -> 0.047205916 | K22: =Summary!AA9 -> 0.029290872
R23: Multiples Analysis | S23: EV/EBITDA | T23: P/E | U23: Chart
B24: =Summary!C11 -> Net Revenue | D24: =Summary!T11 -> 4700.398 | E24: =Summary!U11 -> 7034.803 | F24: =Summary!V11 -> 7343.751 | G24: =Summary!W11 -> 8383.1825 | H24: =Summary!X11 -> 9416.4013 | I24: =Summary!Y11 -> 17136.804 | J24: =Summary!Z11 -> 17477.729 | K24: =Summary!AA11 -> 17588.938 | M24: =Summary!AC11 -> 0.24994716 | O24: =Summary!AE11 -> -0.0044007877 | R24: Entry Multiple | S24: =Valuation!D12 -> 10.8796 | T24: =Valuation!D11 -> 8.3 | U24: =IF($S$21=$S$23,S24,T24) -> 8.3
B25: =Summary!C12 -> % Margin | E25: =Summary!U12 -> 0.6690211 | F25: =Summary!V12 -> 0.67848948 | G25: =Summary!W12 -> 0.69909207 | H25: =Summary!X12 -> 0.72317981 | I25: =Summary!Y12 -> 0.81400555 | J25: =Summary!Z12 -> 0.8051149 | K25: =Summary!AA12 -> 0.79463636 | R25: =Model!Y25 -> 2026e | S25: =('MM Banking Comparables'!$H$10*S30)/(Model!Y61) -> 6.0101681 | T25: =('MM Banking Comparables'!$G$10*S30)/Summary!W19 -> 5.6469253 | U25: =IF($S$21=$S$23,S25,T25) -> 5.6469253
B26: =Summary!C13 -> YoY % Growth | E26: =Summary!U13 -> 0.49663986 | F26: =Summary!V13 -> 0.043917079 | G26: =Summary!W13 -> 0.14153959 | H26: =Summary!X13 -> 0.12324899 | I26: =Summary!Y13 -> 0.033966301 | J26: =Summary!Z13 -> 0.019894361 | K26: =Summary!AA13 -> 0.0063628991 | R26: =Summary!AA6 -> 2030e | S26: =('MM Banking Comparables'!$H$10*S30)/(Model!AG61) -> 5.4197159 | T26: =('MM Banking Comparables'!$G$10*S30)/Summary!AA19 -> 4.9392259 | U26: =IF($S$21=$S$23,S26,T26) -> 4.9392259
R27: Exit Multiple | S27: =Valuation!K64 -> 8 | T27: =Valuation!K76/Summary!AA19 -> 6.5021807 | U27: =IF($S$21=$S$23,S27,T27) -> 6.5021807
B28: =Summary!C27 -> EBITDA | D28: =Summary!T27 -> 425.882 | E28: =Summary!U27 -> 1105.407 | F28: =Summary!V27 -> 954.939 | G28: =Summary!W27 -> 2797.7587 | H28: =Summary!X27 -> 3346.0765 | I28: =Summary!Y27 -> 3157.2841 | J28: =Summary!Z27 -> 3253.925 | K28: =Summary!AA27 -> 3102.5611 | M28: =Summary!AC15 -> 0.61689744 | O28: =Summary!AE15 -> -0.22943319 | R28: Implied PGM | S28: =Valuation!K83 -> 7.7503074 | T28: =Valuation!R76/Summary!AA19 -> 6.3350846 | U28: =IF($S$21=$S$23,S28,T28) -> 6.3350846
B29: =Summary!C28 -> Margin | E29: =Summary!U28 -> 0.10512599 | F29: =Summary!V28 -> 0.088226857 | G29: =Summary!W28 -> 0.14610485 | H29: =Summary!X28 -> 0.16582566 | I29: =Summary!Y28 -> 0.14997235 | J29: =Summary!Z28 -> 0.14989267 | K29: =Summary!AA28 -> 0.14016809
B30: =Summary!C29 -> YoY % Growth | E30: =Summary!U17 -> 2.0495276 | F30: =Summary!V17 -> -0.14270089 | G30: =Summary!W17 -> 0.60422603 | H30: =Summary!X17 -> 0.28376419 | I30: =Summary!Y17 -> -0.04733965 | J30: =Summary!Z17 -> 0.039067308 | K30: =Summary!AA17 -> -0.037162443 | R30: Financials Multiplier | S30: =IF($B$2="$ in Millions Except Per Share Data",1,IF($B$2="$ in Thousands Except Per Share Data",1000,IF($B$2="$ in Billions Except Per Share Data",0.001,0))) -> 1
B32: =Summary!C19 -> Net Income (Loss) | D32: =Summary!T19 -> 221.117 | E32: =Summary!U19 -> 661.299 | F32: =Summary!V19 -> 633.716 | G32: =Summary!W19 -> 2041.643 | H32: =Summary!X19 -> 2432.7259 | I32: =Summary!Y19 -> 2333.1156 | J32: =Summary!Z19 -> 2424.2642 | K32: =Summary!AA19 -> 2334.1726 | M32: =Summary!AC19 -> 0.69291935 | O32: =Summary!AE19 -> -0.27015037
B33: =Summary!C20 -> Margin | E33: =Summary!U20 -> 0.0628906 | F33: =Summary!V20 -> 0.058549049 | G33: =Summary!W20 -> 0.1066189 | H33: =Summary!X20 -> 0.12056161 | I33: =Summary!Y20 -> 0.110824 | J33: =Summary!Z20 -> 0.11167419 | K33: =Summary!AA20 -> 0.10545369
B34: =Summary!C21 -> YoY % Growth | E34: =Summary!U21 -> 1.9907198 | F34: =Summary!V21 -> -0.041710331 | G34: =Summary!W21 -> -0.81886023 | H34: =Summary!X21 -> 0.19155301 | I34: =Summary!Y21 -> -0.040945957 | J34: =Summary!Z21 -> 0.039067308 | K34: =Summary!AA21 -> -0.037162443
B36: =Summary!C23 -> Adj. EPS (Diluted) | D36: =Summary!T23 -> 0.94143039 | E36: =Summary!U23 -> 2.7800045 | F36: =Summary!V23 -> 2.5987148 | G36: =Summary!W23 -> 8.6101474 | H36: =Summary!X23 -> 12.353374 | I36: =Summary!Y23 -> 13.270804 | J36: =Summary!Z23 -> 14.142717 | K36: =Summary!AA23 -> 13.927518 | M36: =Summary!AC23 -> 0.66144206 | O36: =Summary!AE23 -> -0.22685961
B37: =Summary!C24 -> YoY % Growth | E37: =Summary!U24 -> 1.9529581 | F37: =Summary!V24 -> -0.065212015 | G37: =Summary!W24 -> -0.82922327 | H37: =Summary!X24 -> 0.43474593 | I37: =Summary!Y24 -> 0.074265558 | J37: =Summary!Z24 -> 0.065701543 | K37: =Summary!AA24 -> -0.015216239
B39: Free Cash Flow | D39: =Model!J112 -> -235.611 | E39: =Model!O112 -> -367.945 | F39: =Model!T112 -> 2332.925 | G39: =Model!Y112 -> -651.19216 | H39: =Model!AD112 -> 2033.0568 | I39: =Model!AE112 -> 1891.9183 | J39: =Model!AF112 -> 2457.1481 | K39: =Model!AG112 -> 2060.8546 | M39: =IFERROR((F39/D39)^(1/2)-1,"N/A") -> N/A | O39: =IFERROR((K39/G39)^(1/4)-1,"N/A") -> N/A
B40: YoY % Growth | E40: =E39/D39-1 -> 0.56166308 | F40: =F39/E39-1 -> -7.3404177 | G40: =G39/F39-1 -> -1.0502064 | H40: =H39/G39-1 -> -4.1220536 | I40: =I39/H39-1 -> -0.069421805 | J40: =J39/I39-1 -> 0.2987601 | K40: =K39/J39-1 -> -0.16128188
E42: Annuals | M42: Average | O42: Average
B43: Capitalization and Key Ratios | E43: =E19 -> 2024 | F43: =F19 -> 2025 | G43: =G19 -> 2026e | H43: =H19 -> 2027e | I43: =I19 -> 2028e | J43: =J19 -> 2029e | K43: =K19 -> 2030e | M43: Historical | O43: Projected
B44: =Summary!C92 -> Leverage
B45: =Summary!C93 -> Total Debt / EBITDA | D45: =Summary!T93 -> 22.773332 | E45: =Summary!U93 -> 12.240347 | F45: =Summary!V93 -> 16.645975 | G45: =Summary!W93 -> 6.0390809 | H45: =Summary!X93 -> 5.3483209 | I45: =Summary!Y93 -> 6.1432201 | J45: =Summary!Z93 -> 6.4217495 | K45: =Summary!AA93 -> 7.2185172 | M45: =AVERAGE(D45:F45) -> 17.219885 | O45: =AVERAGE(G45:K45) -> 6.2341777
B46: =Summary!C94 -> Total Debt / Equity | D46: =Summary!T94 -> 0.98945301 | E46: =Summary!U94 -> 1.3232843 | F46: =Summary!V94 -> 1.4936655 | G46: =Summary!W94 -> 1.3157668 | H46: =Summary!X94 -> 1.2145602 | I46: =Summary!Y94 -> 1.1864535 | J46: =Summary!Z94 -> 1.1635569 | K46: =Summary!AA94 -> 1.153993 | M46: =AVERAGE(D46:F46) -> 1.2688009 | O46: =AVERAGE(G46:K46) -> 1.2068661
B47: =Summary!C95 -> Total Debt / Total Assets | D47: =Summary!T95 -> 0.16749374 | E47: =Summary!U95 -> 0.21023151 | F47: =Summary!V95 -> 0.20912249 | G47: =Summary!W95 -> 0.16709875 | H47: =Summary!X95 -> 0.1667606 | I47: =Summary!Y95 -> 0.17368146 | J47: =Summary!Z95 -> 0.1781732 | K47: =Summary!AA95 -> 0.18234077 | M47: =AVERAGE(D47:F47) -> 0.19561591 | O47: =AVERAGE(G47:K47) -> 0.17361095
B49: =Summary!C104 -> Liquidity
B50: =Summary!C105 -> Current Ratio | D50: =Summary!T105 -> 1.3226666 | E50: =Summary!U105 -> 1.4336755 | F50: =Summary!V105 -> 1.4084533 | G50: =Summary!W105 -> 1.1694473 | H50: =Summary!X105 -> 1.1863954 | I50: =Summary!Y105 -> 1.2108851 | J50: =Summary!Z105 -> 1.2246892 | K50: =Summary!AA105 -> 1.2371682 | M50: =AVERAGE(D50:F50) -> 1.3882651 | O50: =AVERAGE(G50:K50) -> 1.205717
B51: =Summary!C106 -> Quick Ratio | D51: =Summary!T106 -> 0.34482626 | E51: =Summary!U106 -> 0.44276679 | F51: =Summary!V106 -> 0.45681261 | G51: =Summary!W106 -> 0.23483573 | H51: =Summary!X106 -> 0.24296569 | I51: =Summary!Y106 -> 0.19401823 | J51: =Summary!Z106 -> 0.22794781 | K51: =Summary!AA106 -> 0.24422793 | M51: =AVERAGE(D51:F51) -> 0.41480188 | O51: =AVERAGE(G51:K51) -> 0.22879908
B52: =Summary!C107 -> Cash Ratio | D52: =Summary!T107 -> 0.22201834 | E52: =Summary!U107 -> 0.2993131 | F52: =Summary!V107 -> 0.28386491 | G52: =Summary!W107 -> 0.04802415 | H52: =Summary!X107 -> 0.056244088 | I52: =Summary!Y107 -> 0.011028259 | J52: =Summary!Z107 -> 0.0480219 | K52: =Summary!AA107 -> 0.066650336 | M52: =AVERAGE(D52:F52) -> 0.26839878 | O52: =AVERAGE(G52:K52) -> 0.045993746
B54: =Summary!C76 -> Profitability
B55: =Summary!C81 -> Return on Assets (ROA) | D55: =Summary!T81 -> 0.0038186061 | E55: =Summary!U81 -> 0.010274951 | F55: =Summary!V81 -> 0.008337014 | G55: =Summary!W81 -> 0.020191655 | H55: =Summary!X81 -> 0.022669049 | I55: =Summary!Y81 -> 0.020891998 | J55: =Summary!Z81 -> 0.020670997 | K55: =Summary!AA81 -> 0.019004148 | M55: =AVERAGE(D55:F55) -> 0.0074768569 | O55: =AVERAGE(G55:K55) -> 0.020685569
B56: =Summary!C82 -> Return on Equity (ROE) | D56: =Summary!T82 -> 0.022558045 | E56: =Summary!U82 -> 0.064674801 | F56: =Summary!V82 -> 0.059547445 | G56: =Summary!W82 -> 0.15899287 | H56: =Summary!X82 -> 0.1651045 | I56: =Summary!Y82 -> 0.1427175 | J56: =Summary!Z82 -> 0.13499158 | K56: =Summary!AA82 -> 0.1202729 | M56: =AVERAGE(D56:F56) -> 0.048926764 | O56: =AVERAGE(G56:K56) -> 0.14441587
B57: Return on Inv. Capital (ROIC) | D57: =Summary!T83 -> 0.011338818 | E57: =Summary!U83 -> 0.027837661 | F57: =Summary!V83 -> 0.023879484 | G57: =Summary!W83 -> 0.068656683 | H57: =Summary!X83 -> 0.07455408 | I57: =Summary!Y83 -> 0.065273515 | J57: =Summary!Z83 -> 0.062393358 | K57: =Summary!AA83 -> 0.055837183 | M57: =AVERAGE(D57:F57) -> 0.021018654 | O57: =AVERAGE(G57:K57) -> 0.065342964
B59: =Summary!C85 -> Coverage
B60: Interest Expense | D60: =Summary!T86 -> 0 | E60: =Summary!U86 -> 0 | F60: =Summary!V86 -> 0 | G60: =Summary!W86 -> 0 | H60: =Summary!X86 -> 0 | I60: =Summary!Y86 -> 0 | J60: =Summary!Z86 -> 0 | K60: =Summary!AA86 -> 0 | M60: =AVERAGE(D60:F60) -> 0 | O60: =AVERAGE(G60:K60) -> 0
B61: Capital Expenditures | D61: =Summary!T87 -> -91 | E61: =Summary!U87 -> -173 | F61: =Summary!V87 -> -173 | G61: =Summary!W87 -> -179.87293 | H61: =Summary!X87 -> -195.31245 | I61: =Summary!Y87 -> -208.42486 | J61: =Summary!Z87 -> -218.26375 | K61: =Summary!AA87 -> -224.65688 | M61: =AVERAGE(D61:F61) -> -145.66667 | O61: =AVERAGE(G61:K61) -> -205.30617
B62: EBIT / Interest | D62: =Summary!T88 -> N/A | E62: =Summary!U88 -> N/A | F62: =Summary!V88 -> N/A | G62: =Summary!W88 -> N/A | H62: =Summary!X88 -> N/A | I62: =Summary!Y88 -> N/A | J62: =Summary!Z88 -> N/A | K62: =Summary!AA88 -> N/A | M62: =AVERAGE(D62:F62) -> #DIV/0! | O62: =AVERAGE(G62:K62) -> #DIV/0!
B63: EBITDA / Interest | D63: =Summary!T89 -> N/A | E63: =Summary!U89 -> N/A | F63: =Summary!V89 -> N/A | G63: =Summary!W89 -> N/A | H63: =Summary!X89 -> N/A | I63: =Summary!Y89 -> N/A | J63: =Summary!Z89 -> N/A | K63: =Summary!AA89 -> N/A | M63: =AVERAGE(D63:F63) -> #DIV/0! | O63: =AVERAGE(G63:K63) -> #DIV/0!
B64: (EBITDA - CapEx) / Interest | D64: =Summary!T90 -> N/A | E64: =Summary!U90 -> N/A | F64: =Summary!V90 -> N/A | G64: =Summary!W90 -> N/A | H64: =Summary!X90 -> N/A | I64: =Summary!Y90 -> N/A | J64: =Summary!Z90 -> N/A | K64: =Summary!AA90 -> N/A | M64: =AVERAGE(D64:F64) -> #DIV/0! | O64: =AVERAGE(G64:K64) -> #DIV/0!
B66: =Summary!C97 -> Efficiency
B67: =Summary!C98 -> Asset Turnover | D67: =Summary!T98 -> 0.12850979 | E67: =Summary!U98 -> 0.16337816 | F67: =Summary!V98 -> 0.14239367 | G67: =Summary!W98 -> 0.18938157 | H67: =Summary!X98 -> 0.18802875 | I67: =Summary!Y98 -> 0.18851511 | J67: =Summary!Z98 -> 0.18510094 | K67: =Summary!AA98 -> 0.18021322 | M67: =AVERAGE(D67:F67) -> 0.14476054 | O67: =AVERAGE(G67:K67) -> 0.18624792
B68: =Summary!C99 -> Accounts Receivables as a % of Sales | D68: =Summary!T99 -> 0.6337936 | E68: =Summary!U99 -> 0.55395205 | F68: =Summary!V99 -> 0.79052507 | G68: =Summary!W99 -> 0.64425841 | H68: =Summary!X99 -> 0.6402779 | I68: =Summary!Y99 -> 0.66 | J68: =Summary!Z99 -> 0.65 | K68: =Summary!AA99 -> 0.65 | M68: =AVERAGE(D68:F68) -> 0.65942357 | O68: =AVERAGE(G68:K68) -> 0.64890726
B69: =Summary!C100 -> Mezzanine Debt as a % of Previous Liabilities | D69: =Summary!T100 -> 8.4402887e-06 | E69: =Summary!U100 -> 7.4997807e-06 | F69: =Summary!V100 -> 0 | G69: =Summary!W100 -> 0 | H69: =Summary!X100 -> 0 | I69: =Summary!Y100 -> 0 | J69: =Summary!Z100 -> 0 | K69: =Summary!AA100 -> 0 | M69: =AVERAGE(D69:F69) -> 5.3133565e-06 | O69: =AVERAGE(G69:K69) -> 0
B70: =Summary!C101 -> Prepaid & Other Curernt Assets as a % of Previous Assets | D70: =Summary!T101 -> 0.78068203 | E70: =Summary!U101 -> 0.74323946 | F70: =Summary!V101 -> 0.72023119 | G70: =Summary!W101 -> 0.75571967 | H70: =Summary!X101 -> 0.76106291 | I70: =Summary!Y101 -> 0.834 | J70: =Summary!Z101 -> 0.82 | K70: =Summary!AA101 -> 0.81 | M70: =AVERAGE(D70:F70) -> 0.74805089 | O70: =AVERAGE(G70:K70) -> 0.79615652
B71: =Summary!C102 -> Cash Conversion Cycle | D71: =Summary!T102 -> -0.14687999 | E71: =Summary!U102 -> -0.18927992 | F71: =Summary!V102 -> 0.070293881 | G71: =Summary!W102 -> -0.059399047 | H71: =Summary!X102 -> -0.069966577 | I71: =Summary!Y102 -> -0.174 | J71: =Summary!Z102 -> -0.17 | K71: =Summary!AA102 -> -0.16 | M71: =AVERAGE(D71:F71) -> -0.088622009 | O71: =AVERAGE(G71:K71) -> -0.12667312

Sheet Football Field
C1: =Company_Name&" - "&MID(CELL("filename",A1),FIND("]",CELL("filename",A1))+1,255)&": "&Case_Scenario&" Case" -> Jefferies Financial Group Inc. - Football Field: Base Case
C2: =Cover!C2 -> $ in Millions Except Per Share Data
A4: x | O4: Valuation Method: | T4: Downside | U4: Delta | V4: Upside | W4: x
O5: =TEXT(Valuation!E112,"0.0%")&" - "&TEXT(Valuation!E114,"0.0%")&" WACC"&" & "&TEXT(Valuation!G110,"0.0%")&" - "&TEXT(Valuation!I110,"0.0%")&" PGR" -> 6.0% - 7.0% WACC & 1.5% - 2.5% PGR | T5: =Valuation!G112 -> 41.244955 | U5: =V5-T5 -> 5.1222677 | V5: =Valuation!I114 -> 46.367223
O6: =TEXT(Valuation!E104,"0.0%")&" - "&TEXT(Valuation!E106,"0.0%")&" WACC"&" & "&TEXT(Valuation!G102,"0.0x")&" - "&TEXT(Valuation!I102,"0.0x")&" Exit Multiple" -> 6.0% - 7.0% WACC & 7.0x - 9.0x Exit Multiple | T6: =Valuation!G104 -> 146.60999 | U6: =V6-T6 -> 0 | V6: =Valuation!I106 -> 146.60999
O8: =Valuation!F188&": "&TEXT(Valuation!G189,"0.0x")&" - "&TEXT(Valuation!I189,"0.0x") -> NTM EV/EBITDA Spread to Comps: 7.7x - 9.7x | T8: =Valuation!G191 -> 208.74373 | U8: =V8-T8 -> 57.314398 | V8: =Valuation!I193 -> 266.05813
O9: =Valuation!F180&": "&TEXT(Valuation!G181,"0.0x")&" - "&TEXT(Valuation!I181,"0.0x") -> NTM EV/EBITDA: 10.7x - 12.7x | T9: =Valuation!G183 -> 163.01762 | U9: =V9-T9 -> 47.153041 | V9: =Valuation!I185 -> 210.17066
O10: =Valuation!F172&": "&TEXT(Valuation!G173,"0.0x")&" - "&TEXT(Valuation!I173,"0.0x") -> NTM P/E Spread to Comps: 10.9x - 12.9x | T10: =Valuation!G175 -> 97.321811 | U10: =V10-T10 -> 47.650009 | V10: =Valuation!I177 -> 144.97182
O11: =Valuation!F164&": "&TEXT(Valuation!G165,"0.0x")&" - "&TEXT(Valuation!I165,"0.0x") -> NTM P/E: 13.2x - 15.2x | T11: =Valuation!G167 -> 102.86539 | U11: =V11-T11 -> 41.934357 | V11: =Valuation!I169 -> 144.79975
O13: =Valuation!F264&": "&TEXT(Valuation!G265,"0.0x")&" - "&TEXT(Valuation!I265,"0.0x") -> 2009-2018 Mid Cycle EV/EBITDA Spread to Comps: 4.7x - 6.7x | T13: =Valuation!G267 -> 258.99843 | U13: =V13-T13 -> 26.688662 | V13: =Valuation!I267 -> 285.6871
O14: =Valuation!F256&": "&TEXT(Valuation!G257,"0.0x")&" - "&TEXT(Valuation!I257,"0.0x") -> 2009-2018 Mid Cycle EV/EBITDA: 5.7x - 7.7x | T14: =Valuation!G259 -> 202.25742 | U14: =V14-T14 -> 26.688662 | V14: =Valuation!I259 -> 228.94608
O15: =Valuation!F248&": "&TEXT(Valuation!G249,"0.0x")&" - "&TEXT(Valuation!I249,"0.0x") -> 2009-2018 Mid Cycle P/E Spread to Comps: 13.6x - 15.6x | T15: =Valuation!G251 -> 100.5704 | U15: =V15-T15 -> 21.291496 | V15: =Valuation!I251 -> 121.86189
O16: =Valuation!F240&": "&TEXT(Valuation!G241,"0.0x")&" - "&TEXT(Valuation!I241,"0.0x") -> 2009-2018 Mid Cycle P/E: 14.1x - 16.1x | T16: =Valuation!G243 -> 123.8191 | U16: =V16-T16 -> 21.291496 | V16: =Valuation!I243 -> 145.11059
O18: 52-Week Price Range: | T18: =Share_Price_Low -> 35.72 | U18: =V18-T18 -> -18.68 | V18: =Share_Price_High -> 17.04
O19: Median Value: | T19: =MEDIAN(T5:T18) -> 123.8191 | U19: =MEDIAN(U5:U18) -> 26.688662 | V19: =MEDIAN(V5:V18) -> 145.11059
A20: x | O20: Implied Return (%): | T20: =T19/Share_Price-1 -> 2.2558269 | V20: =V19/Share_Price-1 -> 2.8156875
T22: Reference Points for Price Axis
U24: Price
A25: x | T25: High | U25: =MAX(V5:V18)*1.1 -> 314.2558 | W25: x
T26: Low | U26: =MIN(T5:T18)*0.9 -> 32.148
A30: x

Sheet Integrity
C1: =Company_Name&" - "&MID(CELL("filename",A1),FIND("]",CELL("filename",A1))+1,255) -> Jefferies Financial Group Inc. - Integrity
C3: Integrity
C4: Metric
C6: Model:
C7: Balance Sheet Check: | D7: =SUM(Model!F159:AG159) -> 0
C8: Base Case: | D8: =IF(Case_Scenario="Base","OK!","Check!") -> OK!
C9: Interest Expense: | D9: =IF(Model!C8="On","OK!","CHECK - OFF") -> OK!
C10: Valuation Date:
C12: Formatting:
C13: Valuation Sensitivity Tables: | D13: =SUM(Valuation!F96,Valuation!K96,Valuation!P96,Valuation!F155:F159,Valuation!L155:L159,Valuation!F231:F235,Valuation!L231:L235) -> 0
C14: WACC Tables: | D14: =SUM(WACC!Q20,WACC!N33:N37) -> 0.0065630836
C16: Font Toggles:
C17: Cover: | D17: =Cover!$Q$2 -> Report
C18: Revenue Build: | D18: ='Revenue Build'!$C$22 -> Report
C19: Model: | D19: =Model!$C$5 -> Report
C20: Valuation: | D20: =Valuation!$R$2 -> Report
C22: Change Log
C23: Date | D23: Version | E23: Operator | F23: Revisions
C24: 44476 | D24: v01 | E24: Nate Latimer | F24: Top Down / Bottom Up toggle integration and Capital IQ comps sheet w/ ID Locator
C25: 44476 | D25: v02 | E25: Carson Shaner | F25: Formulas for EBIT/EBITDA margins on earnings sheets
C26: 44480 | D26: v03 | E26: Nate Latimer | F26: Historical driver adjustments to reflect Top Down / Bottom Up Toggle
C27: 44488 | D27: v04 | E27: Nate Latimer | F27: Bug fixes to model output, comps sheet and WACC Comps Relevered Beta
C28: 44489 | D28: v05 | E28: Lilianna Ruby | F28: Changed the year end driver in 2021 and 2022 to correctly pull operating margins
C29: 44491 | D29: v06 | E29: Lilianna Ruby | F29: Changed the first page to add 365 to your previous fiscal year
C30: 44496 | D30: v07 | E30: Carson Shaner | F30: Changed Model Output FCF formula, broke apart D&A for historical periods, added checks for EPS & EBITDA in Valuation sensitivity tables, added segment D&A breakdown, linked and fixed SOTP valuation
C31: 44503 | D31: v08 | E31: Lilianna Ruby | F31: Changed average of comps on valuation tab to average all peers not just the first one
C32: 44512 | D32: v09 | E32: Lilianna Ruby | F32: Rolled model forward to reflect 3Q'21. Also changed the multiples tab so the quarters roll forward and end on correct date.
C33: 44522 | D33: v10 | E33: Lilianna Ruby | F33: Fully fixed the multiples tab so it is automatic and fully functional. Also fixed definition of NTM_EPS and NTM_EBITDA
C34: 44582 | D34: v13 | E34: Carson Shaner | F34: Changed EPS, EBITDA, shares, tax rate, etc., to formulas so we do not have to hardcode them.
C35: 44584 | D35: v14 | E35: Lilianna Ruby | F35: Changed discount factor to mid year
... C42: 45130 | D42: v21 | E42: Jacob George | F42: Fixed formulas for NTM EPS and NTM EBITDA on Valuation tab; previously wasn't summing values if last reported quarter was 4Q

Sheet Revenue Build
C1: =Company_Name&" - "&MID(CELL("filename",A1),FIND("]",CELL("filename",A1))+1,255)&": "&Case_Scenario&" Case" -> Jefferies Financial Group Inc. - Revenue Build: Base Case
C2: =Cover!C2 -> $ in Millions Except Per Share Data
A4: x | C4: Segments
C6: =C30&" Methodology" -> Total Company Revenue Methodology
C7: Segment
C8: =C32&" Methodology" -> Investment Banking Revenue Methodology
C9: =IF(Company_Rev_Methodology="Segment","Segment",IF(Company_Rev_Methodology="Activity-Based","Activity-Based",IF(Company_Rev_Methodology="Backlog","Backlog",IF(Company_Rev_Methodology="Mixed",D9,"--")))) -> Segment | D9: Backlog
C10: =C35&" Methodology" -> Principal Transactions Revenue Methodology
C11: =IF(Company_Rev_Methodology="Segment","Segment",IF(Company_Rev_Methodology="Activity-Based","Activity-Based",IF(Company_Rev_Methodology="Backlog","Backlog",IF(Company_Rev_Methodology="Mixed",D11,"--")))) -> Segment | D11: Activity-Based
C12: =C38&" Methodology" -> Revenue Methodology
C13: =IF(Company_Rev_Methodology="Segment","Segment",IF(Company_Rev_Methodology="Activity-Based","Activity-Based",IF(Company_Rev_Methodology="Backlog","Backlog",IF(Company_Rev_Methodology="Mixed",D13,"--")))) -> Segment | D13: Segment
C14: =C41&" Methodology" -> Revenue Methodology
C15: =IF(Company_Rev_Methodology="Segment","Segment",IF(Company_Rev_Methodology="Activity-Based","Activity-Based",IF(Company_Rev_Methodology="Backlog","Backlog",IF(Company_Rev_Methodology="Mixed",D15,"--")))) -> Segment | D15: Segment
C16: =C44&" Methodology" -> Revenue Methodology
C17: =IF(Company_Rev_Methodology="Segment","Segment",IF(Company_Rev_Methodology="Activity-Based","Activity-Based",IF(Company_Rev_Methodology="Backlog","Backlog",IF(Company_Rev_Methodology="Mixed",D17,"--")))) -> Segment | D17: Segment
C18: =C47&" Methodology" -> Revenue Methodology
C19: =IF(Company_Rev_Methodology="Segment","Segment",IF(Company_Rev_Methodology="Activity-Based","Activity-Based",IF(Company_Rev_Methodology="Backlog","Backlog",IF(Company_Rev_Methodology="Mixed",D19,"--")))) -> Segment | D19: Segment
C21: Font Toggle
C22: Report
C24: Annual vs. Quarterly
C25: Annual
J26: 1 | O26: 2 | T26: 3 | Y26: 4 | AD26: 5 | AE26: 6 | AF26: 7 | AG26: 8
AI27: CAGR
A28: x | C28: Summary | F28: =Model!F$25 -> 1Q23 | G28: =Model!G$25 -> 2Q23 | H28: =Model!H$25 -> 3Q23 | I28: =Model!I$25 -> 4Q23 | J28: =Model!J$25 -> 2023 | K28: =Model!K$25 -> 1Q24 | L28: =Model!L$25 -> 2Q24 | M28: =Model!M$25 -> 3Q24 | ... AG28: =Model!AG$25 -> 2030e | AI28: Historical | AJ28: Projected
C30: Total Company Revenue | F30: ='Segment Analysis'!F7 -> 1780.56 | G30: ='Segment Analysis'!G7 -> 1651.242 | H30: ='Segment Analysis'!H7 -> 2040.888 | I30: ='Segment Analysis'!I7 -> 1968.69 | J30: ='Segment Analysis'!J7 -> 7441.38 | K30: ='Segment Analysis'!K7 -> 2551.9 | L30: ='Segment Analysis'!L7 -> 2516.23 | M30: ='Segment Analysis'!M7 -> 2595.48 | ... T30: ='Segment Analysis'!T7 -> 10823.677 | U30: =SUM(U32,U35,U38,U41,U44,U47,) -> 2742.8525 | V30: =SUM(V32,V35,V38,V41,V44,V47,) -> 2804.4553 | W30: =SUM(W32,W35,W38,W41,W44,W47,) -> 3225.2028 | X30: =SUM(X32,X35,X38,X41,X44,X47,) -> 3219.018 | Y30: =SUM(U30:X30) -> 11991.529 | Z30: =SUM(Z32,Z35,Z38,Z41,Z44,Z47,) -> 2948.7114 | AA30: =SUM(AA32,AA35,AA38,AA41,AA44,AA47,) -> 3086.9714 | AB30: =SUM(AB32,AB35,AB38,AB41,AB44,AB47,) -> 3511.4181 | AC30: =SUM(AC32,AC35,AC38,AC41,AC44,AC47,) -> 3473.729 | AD30: =SUM(Z30:AC30) -> 13020.83 | AE30: =SUM(AE32,AE35,AE38,AE41,AE44,AE47,) -> 13894.991 | AF30: =SUM(AF32,AF35,AF38,AF41,AF44,AF47,) -> 14550.917 | AG30: =SUM(AG32,AG35,AG38,AG41,AG44,AG47,) -> 14977.126 | AI30: =IFERROR((T30/J30)^(1/3)-1,"--") -> 0.13302749 | AJ30: =IFERROR((AG30/T30)^(1/5)-1,"--") -> 0.067113784
C31: =IF($C$25="Quarterly","% Growth QoQ","% Growth YoY") -> % Growth YoY | G31: =IF($C$25="Annual",'Segment Analysis'!G172,'Segment Analysis'!G192) -> 0 | H31: =IF($C$25="Annual",'Segment Analysis'!H172,'Segment Analysis'!H192) -> 0 | I31: =IF($C$25="Annual",'Segment Analysis'!I172,'Segment Analysis'!I192) -> 0 | K31: =IF($C$25="Annual",'Segment Analysis'!K172,'Segment Analysis'!K192) -> 0.43320079 | L31: =IF($C$25="Annual",'Segment Analysis'!L172,'Segment Analysis'!L192) -> 0.52384084 | M31: =IF($C$25="Annual",'Segment Analysis'!M172,'Segment Analysis'!M192) -> 0.27174054 | N31: =IF($C$25="Annual",'Segment Analysis'!N172,'Segment Analysis'!N192) -> 0.44840427 | O31: =IF($C$25="Annual",'Segment Analysis'!O172,'Segment Analysis'!O192) -> 0.41305363 | P31: =IF($C$25="Annual",'Segment Analysis'!P172,'Segment Analysis'!P192) -> -0.030971433 | Q31: =IF($C$25="Annual",'Segment Analysis'!Q172,'Segment Analysis'!Q192) -> -0.0087094582 | R31: =IF($C$25="Annual",'Segment Analysis'!R172,'Segment Analysis'!R192) -> 0.12028372 | ... T31: =IF($C$25="Annual",'Segment Analysis'!T172,'Segment Analysis'!T192) -> 0.029349118 | U31: =IFERROR(U30/S30-1,"--") -> -0.069848689 | V31: =IFERROR(V30/U30-1,"--") -> 0.022459381 | W31: =IFERROR(W30/V30-1,"--") -> 0.15002823 | X31: =IFERROR(X30/W30-1,"--") -> -0.0019176407 | Y31: =IFERROR(Y30/T30-1,"--") -> 0.10789785 | Z31: =IFERROR(Z30/X30-1,"--") -> -0.083971744 | AA31: =IFERROR(AA30/Z30-1,"--") -> 0.046888275 | AB31: =IFERROR(AB30/AA30-1,"--") -> 0.13749614 | AC31: =IFERROR(AC30/AB30-1,"--") -> -0.010733293 | AD31: =IFERROR(AD30/Y30-1,"--") -> 0.085835711 | AE31: =IFERROR(AE30/AD30-1,"--") -> 0.067135576 | AF31: =IFERROR(AF30/AE30-1,"--") -> 0.047205916 | AG31: =IFERROR(AG30/AF30-1,"--") -> 0.029290872
C32: ='Segment Analysis'!C8 -> Investment Banking Revenue | F32: ='Segment Analysis'!F8 -> 1744.68 | G32: ='Segment Analysis'!G8 -> 1681.412 | H32: ='Segment Analysis'!H8 -> 2075.3 | I32: ='Segment Analysis'!I8 -> 1855.578 | J32: ='Segment Analysis'!J8 -> 7356.97 | K32: ='Segment Analysis'!K8 -> 2384.8 | L32: ='Segment Analysis'!L8 -> 2306.27 | M32: ='Segment Analysis'!M8 -> 2459.03 | ... T32: ='Segment Analysis'!T8 -> 10135.32 | U32: =IF(Segment1_Rev_Methodology="Segment",U53,IF(Segment1_Rev_Methodology="Activity-Based",U91,IF(Segment1_Rev_Methodology="Backlog",U165,"--"))) -> 2519.9342 | V32: =IF(Segment1_Rev_Methodology="Segment",V53,IF(Segment1_Rev_Methodology="Activity-Based",V91,IF(Segment1_Rev_Methodology="Backlog",V165,"--"))) -> 2642.1181 | W32: =IF(Segment1_Rev_Methodology="Segment",W53,IF(Segment1_Rev_Methodology="Activity-Based",W91,IF(Segment1_Rev_Methodology="Backlog",W165,"--"))) -> 3063.0856 | X32: =IF(Segment1_Rev_Methodology="Segment",X53,IF(Segment1_Rev_Methodology="Activity-Based",X91,IF(Segment1_Rev_Methodology="Backlog",X165,"--"))) -> 3034.8043 | Y32: =SUM(U32:X32) -> 11259.942 | Z32: =IF(Segment1_Rev_Methodology="Segment",Z53,IF(Segment1_Rev_Methodology="Activity-Based",Z91,IF(Segment1_Rev_Methodology="Backlog",Z165,"--"))) -> 2797.127 | AA32: =IF(Segment1_Rev_Methodology="Segment",AA53,IF(Segment1_Rev_Methodology="Activity-Based",AA91,IF(Segment1_Rev_Methodology="Backlog",AA165,"--"))) -> 2932.7511 | AB32: =IF(Segment1_Rev_Methodology="Segment",AB53,IF(Segment1_Rev_Methodology="Activity-Based",AB91,IF(Segment1_Rev_Methodology="Backlog",AB165,"--"))) -> 3338.7633 | AC32: =IF(Segment1_Rev_Methodology="Segment",AC53,IF(Segment1_Rev_Methodology="Activity-Based",AC91,IF(Segment1_Rev_Methodology="Backlog",AC165,"--"))) -> 3307.9367 | AD32: =SUM(Z32:AC32) -> 12376.578 | AE32: =IF(Segment1_Rev_Methodology="Segment",AE53,IF(Segment1_Rev_Methodology="Activity-Based",AE91,IF(Segment1_Rev_Methodology="Backlog",AE165,"--"))) -> 13366.704 | AF32: =IF(Segment1_Rev_Methodology="Segment",AF53,IF(Segment1_Rev_Methodology="Activity-Based",AF91,IF(Segment1_Rev_Methodology="Backlog",AF165,"--"))) -> 14101.873 | AG32: =IF(Segment1_Rev_Methodology="Segment",AG53,IF(Segment1_Rev_Methodology="Activity-Based",AG91,IF(Segment1_Rev_Methodology="Backlog",AG165,"--"))) -> 14595.439 | AI32: =IFERROR((T32/J32)^(1/3)-1,"--") -> 0.1127036 | AJ32: =IFERROR((AG32/T32)^(1/5)-1,"--") -> 0.075662274
C33: =IF($C$25="Quarterly","% Growth QoQ","% Growth YoY") -> % Growth YoY | G33: =IF($C$25="Annual",'Segment Analysis'!G173,'Segment Analysis'!G193) -> 0 | H33: =IF($C$25="Annual",'Segment Analysis'!H173,'Segment Analysis'!H193) -> 0 | I33: =IF($C$25="Annual",'Segment Analysis'!I173,'Segment Analysis'!I193) -> 0 | K33: =IF($C$25="Annual",'Segment Analysis'!K173,'Segment Analysis'!K193) -> 0.36689823 | L33: =IF($C$25="Annual",'Segment Analysis'!L173,'Segment Analysis'!L193) -> 0.37162694 | M33: =IF($C$25="Annual",'Segment Analysis'!M173,'Segment Analysis'!M193) -> 0.18490339 | N33: =IF($C$25="Annual",'Segment Analysis'!N173,'Segment Analysis'!N193) -> 0.40375075 | O33: =IF($C$25="Annual",'Segment Analysis'!O173,'Segment Analysis'!O193) -> 0.32593568 | P33: =IF($C$25="Annual",'Segment Analysis'!P173,'Segment Analysis'!P193) -> -0.048049732 | Q33: =IF($C$25="Annual",'Segment Analysis'!Q173,'Segment Analysis'!Q193) -> 0.022878501 | R33: =IF($C$25="Annual",'Segment Analysis'!R173,'Segment Analysis'!R193) -> 0.11717303 | ... T33: =IF($C$25="Annual",'Segment Analysis'!T173,'Segment Analysis'!T193) -> 0.039001139 | U33: =IFERROR(U32/S32-1,"--") -> -0.086620633 | V33: =IFERROR(V32/U32-1,"--") -> 0.048486929 | W33: =IFERROR(W32/V32-1,"--") -> 0.15932957 | X33: =IFERROR(X32/W32-1,"--") -> -0.0092329544 | Y33: =IFERROR(Y32/T32-1,"--") -> 0.1109607 | Z33: =IFERROR(Z32/X32-1,"--") -> -0.078317184 | AA33: =IFERROR(AA32/Z32-1,"--") -> 0.048486929 | AB33: =IFERROR(AB32/AA32-1,"--") -> 0.13844075 | AC33: =IFERROR(AC32/AB32-1,"--") -> -0.0092329544 | AD33: =IFERROR(AD32/Y32-1,"--") -> 0.099168879 | AE33: =IFERROR(AE32/AD32-1,"--") -> 0.08 | AF33: =IFERROR(AF32/AE32-1,"--") -> 0.055 | AG33: =IFERROR(AG32/AF32-1,"--") -> 0.035
C34: % of Total Revenue | F34: ='Segment Analysis'!F16 -> 0.97984904 | G34: ='Segment Analysis'!G16 -> 1.0182711 | H34: ='Segment Analysis'!H16 -> 1.0168613 | I34: ='Segment Analysis'!I16 -> 0.94254453 | J34: ='Segment Analysis'!J16 -> 0.98865667 | K34: ='Segment Analysis'!K16 -> 0.93451938 | L34: ='Segment Analysis'!L16 -> 0.91655771 | M34: ='Segment Analysis'!M16 -> 0.94742784 | ... T34: ='Segment Analysis'!T16 -> 0.93640267 | U34: =U32/U$30 -> 0.91872757 | V34: =V32/V$30 -> 0.94211453 | W34: =W32/W$30 -> 0.94973429 | X34: =X32/X$30 -> 0.94277333 | Y34: =Y32/Y$30 -> 0.93899141 | Z34: =Z32/Z$30 -> 0.94859299 | AA34: =AA32/AA$30 -> 0.95004154 | AB34: =AB32/AB$30 -> 0.95083048 | ... AG34: =AG32/AG$30 -> 0.97451534
C35: ='Segment Analysis'!C9 -> Principal Transactions Revenue | F35: ='Segment Analysis'!F9 -> 35.88 | G35: ='Segment Analysis'!G9 -> -30.17 | H35: ='Segment Analysis'!H9 -> -34.412 | I35: ='Segment Analysis'!I9 -> 113.112 | J35: ='Segment Analysis'!J9 -> 84.41 | K35: ='Segment Analysis'!K9 -> 167.1 | L35: ='Segment Analysis'!L9 -> 209.96 | M35: ='Segment Analysis'!M9 -> 136.45 | ... T35: ='Segment Analysis'!T9 -> 688.357 | U35: =IF(Segment2_Rev_Methodology="Segment",U59,IF(Segment2_Rev_Methodology="Activity-Based",U103,IF(Segment2_Rev_Methodology="Backlog",U177,"--"))) -> 222.9183 | V35: =IF(Segment2_Rev_Methodology="Segment",V59,IF(Segment2_Rev_Methodology="Activity-Based",V103,IF(Segment2_Rev_Methodology="Backlog",V177,"--"))) -> 162.3372 | W35: =IF(Segment2_Rev_Methodology="Segment",W59,IF(Segment2_Rev_Methodology="Activity-Based",W103,IF(Segment2_Rev_Methodology="Backlog",W177,"--"))) -> 162.11712 | X35: =IF(Segment2_Rev_Methodology="Segment",X59,IF(Segment2_Rev_Methodology="Activity-Based",X103,IF(Segment2_Rev_Methodology="Backlog",X177,"--"))) -> 184.21367 | Y35: =SUM(U35:X35) -> 731.58629 | Z35: =IF(Segment2_Rev_Methodology="Segment",Z59,IF(Segment2_Rev_Methodology="Activity-Based",Z103,IF(Segment2_Rev_Methodology="Backlog",Z177,"--"))) -> 151.58444 | AA35: =IF(Segment2_Rev_Methodology="Segment",AA59,IF(Segment2_Rev_Methodology="Activity-Based",AA103,IF(Segment2_Rev_Methodology="Backlog",AA177,"--"))) -> 154.22034 | AB35: =IF(Segment2_Rev_Methodology="Segment",AB59,IF(Segment2_Rev_Methodology="Activity-Based",AB103,IF(Segment2_Rev_Methodology="Backlog",AB177,"--"))) -> 172.65473 | AC35: =IF(Segment2_Rev_Methodology="Segment",AC59,IF(Segment2_Rev_Methodology="Activity-Based",AC103,IF(Segment2_Rev_Methodology="Backlog",AC177,"--"))) -> 165.7923 | AD35: =SUM(Z35:AC35) -> 644.25182 | AE35: =IF(Segment2_Rev_Methodology="Segment",AE59,IF(Segment2_Rev_Methodology="Activity-Based",AE103,IF(Segment2_Rev_Methodology="Backlog",AE177,"--"))) -> 528.28649 | AF35: =IF(Segment2_Rev_Methodology="Segment",AF59,IF(Segment2_Rev_Methodology="Activity-Based",AF103,IF(Segment2_Rev_Methodology="Backlog",AF177,"--"))) -> 449.04352 | AG35: =IF(Segment2_Rev_Methodology="Segment",AG59,IF(Segment2_Rev_Methodology="Activity-Based",AG103,IF(Segment2_Rev_Methodology="Backlog",AG177,"--"))) -> 381.68699 | AI35: =IFERROR((T35/J35)^(1/3)-1,"--") -> 1.0128277 | AJ35: =IFERROR((AG35/T35)^(1/5)-1,"--") -> -0.11125182
C36: % Growth | G36: =IF($C$25="Annual",'Segment Analysis'!G174,'Segment Analysis'!G194) -> 0 | H36: =IF($C$25="Annual",'Segment Analysis'!H174,'Segment Analysis'!H194) -> 0 | I36: =IF($C$25="Annual",'Segment Analysis'!I174,'Segment Analysis'!I194) -> 0 | K36: =IF($C$25="Annual",'Segment Analysis'!K174,'Segment Analysis'!K194) -> 3.6571906 | L36: =IF($C$25="Annual",'Segment Analysis'!L174,'Segment Analysis'!L194) -> -7.959231 | M36: =IF($C$25="Annual",'Segment Analysis'!M174,'Segment Analysis'!M194) -> -4.9651866 | N36: =IF($C$25="Annual",'Segment Analysis'!N174,'Segment Analysis'!N194) -> 1.1809357 | O36: ='Segment Analysis'!O174 -> 8.0060419 | P36: =IF($C$25="Annual",'Segment Analysis'!P174,'Segment Analysis'!P194) -> 0.21276481 | Q36: =IF($C$25="Annual",'Segment Analysis'!Q174,'Segment Analysis'!Q194) -> -0.35568203 | R36: =IF($C$25="Annual",'Segment Analysis'!R174,'Segment Analysis'!R194) -> 0.17634298 | S36: =IF($C$25="Annual",'Segment Analysis'!S174,'Segment Analysis'!S194) -> -0.23016336 | T36: ='Segment Analysis'!T174 -> -0.094505393 | U36: =IFERROR(U35/S35-1,"--") -> 0.17380405 | V36: =IFERROR(V35/U35-1,"--") -> -0.27176369 | W36: =IFERROR(W35/V35-1,"--") -> -0.0013556967 | X36: =IFERROR(X35/W35-1,"--") -> 0.13629992 | Y36: =IFERROR(Y35/T35-1,"--") -> 0.062800683 | Z36: =IFERROR(Z35/X35-1,"--") -> -0.17712706 | AA36: =IFERROR(AA35/Z35-1,"--") -> 0.017388961 | AB36: =IFERROR(AB35/AA35-1,"--") -> 0.11953282 | AC36: =IFERROR(AC35/AB35-1,"--") -> -0.039746549 | AD36: =IFERROR(AD35/Y35-1,"--") -> -0.11937685 | AE36: =IFERROR(AE35/AD35-1,"--") -> -0.18 | AF36: =IFERROR(AF35/AE35-1,"--") -> -0.15 | AG36: =IFERROR(AG35/AF35-1,"--") -> -0.15
C37: % of Total Revenue | F37: ='Segment Analysis'!F17 -> 0.020150964 | G37: ='Segment Analysis'!G17 -> -0.018271095 | H37: ='Segment Analysis'!H17 -> -0.016861288 | I37: ='Segment Analysis'!I17 -> 0.057455465 | J37: ='Segment Analysis'!J17 -> 0.011343326 | K37: ='Segment Analysis'!K17 -> 0.065480622 | L37: ='Segment Analysis'!L17 -> 0.083442293 | M37: ='Segment Analysis'!M17 -> 0.052572164 | ... T37: ='Segment Analysis'!T17 -> 0.063597334 | U37: =U35/U$30 -> 0.081272434 | V37: =V35/V$30 -> 0.057885466 | W37: =W35/W$30 -> 0.050265714 | X37: =X35/X$30 -> 0.057226667 | Y37: =Y35/Y$30 -> 0.061008594 | Z37: =Z35/Z$30 -> 0.051407012 | AA37: =AA35/AA$30 -> 0.049958461 | AB37: =AB35/AB$30 -> 0.049169518 | ... AG37: =AG35/AG$30 -> 0.025484662
C38: ='Segment Analysis'!C10 -> Revenue | F38: ='Segment Analysis'!F10 -> 0 | G38: ='Segment Analysis'!G10 -> 0 | H38: ='Segment Analysis'!H10 -> 0 | I38: ='Segment Analysis'!I10 -> 0 | J38: ='Segment Analysis'!J10 -> 0 | K38: ='Segment Analysis'!K10 -> 0 | L38: ='Segment Analysis'!L10 -> 0 | M38: ='Segment Analysis'!M10 -> 0 | ... T38: ='Segment Analysis'!T10 -> 0 | U38: =IF(Segment3_Rev_Methodology="Segment",U65,IF(Segment3_Rev_Methodology="Activity-Based",U115,IF(Segment3_Rev_Methodology="Backlog",U189,"--"))) -> 0 | V38: =IF(Segment3_Rev_Methodology="Segment",V65,IF(Segment3_Rev_Methodology="Activity-Based",V115,IF(Segment3_Rev_Methodology="Backlog",V189,"--"))) -> 0 | W38: =IF(Segment3_Rev_Methodology="Segment",W65,IF(Segment3_Rev_Methodology="Activity-Based",W115,IF(Segment3_Rev_Methodology="Backlog",W189,"--"))) -> 0 | X38: =IF(Segment3_Rev_Methodology="Segment",X65,IF(Segment3_Rev_Methodology="Activity-Based",X115,IF(Segment3_Rev_Methodology="Backlog",X189,"--"))) -> 0 | Y38: =SUM(U38:X38) -> 0 | Z38: =IF(Segment3_Rev_Methodology="Segment",Z65,IF(Segment3_Rev_Methodology="Activity-Based",Z115,IF(Segment3_Rev_Methodology="Backlog",Z189,"--"))) -> 0 | AA38: =IF(Segment3_Rev_Methodology="Segment",AA65,IF(Segment3_Rev_Methodology="Activity-Based",AA115,IF(Segment3_Rev_Methodology="Backlog",AA189,"--"))) -> 0 | AB38: =IF(Segment3_Rev_Methodology="Segment",AB65,IF(Segment3_Rev_Methodology="Activity-Based",AB115,IF(Segment3_Rev_Methodology="Backlog",AB189,"--"))) -> 0 | AC38: =IF(Segment3_Rev_Methodology="Segment",AC65,IF(Segment3_Rev_Methodology="Activity-Based",AC115,IF(Segment3_Rev_Methodology="Backlog",AC189,"--"))) -> 0 | AD38: =SUM(Z38:AC38) -> 0 | AE38: =IF(Segment3_Rev_Methodology="Segment",AE65,IF(Segment3_Rev_Methodology="Activity-Based",AE115,IF(Segment3_Rev_Methodology="Backlog",AE189,"--"))) -> 0 | AF38: =IF(Segment3_Rev_Methodology="Segment",AF65,IF(Segment3_Rev_Methodology="Activity-Based",AF115,IF(Segment3_Rev_Methodology="Backlog",AF189,"--"))) -> 0 | AG38: =IF(Segment3_Rev_Methodology="Segment",AG65,IF(Segment3_Rev_Methodology="Activity-Based",AG115,IF(Segment3_Rev_Methodology="Backlog",AG189,"--"))) -> 0 | AI38: =IFERROR((T38/J38)^(1/3)-1,"--") -> -- | AJ38: =IFERROR((AG38/T38)^(1/5)-1,"--") -> --
C39: % Growth | G39: =IF($C$25="Annual",'Segment Analysis'!G175,'Segment Analysis'!G195) -> 0 | H39: =IF($C$25="Annual",'Segment Analysis'!H175,'Segment Analysis'!H195) -> 0 | I39: =IF($C$25="Annual",'Segment Analysis'!I175,'Segment Analysis'!I195) -> 0 | K39: =IF($C$25="Annual",'Segment Analysis'!K175,'Segment Analysis'!K195) -> N/A | L39: =IF($C$25="Annual",'Segment Analysis'!L175,'Segment Analysis'!L195) -> N/A | M39: =IF($C$25="Annual",'Segment Analysis'!M175,'Segment Analysis'!M195) -> N/A | N39: =IF($C$25="Annual",'Segment Analysis'!N175,'Segment Analysis'!N195) -> N/A | O39: =IF($C$25="Annual",'Segment Analysis'!O175,'Segment Analysis'!O195) -> N/A | P39: =IF($C$25="Annual",'Segment Analysis'!P175,'Segment Analysis'!P195) -> N/A | Q39: =IF($C$25="Annual",'Segment Analysis'!Q175,'Segment Analysis'!Q195) -> N/A | R39: =IF($C$25="Annual",'Segment Analysis'!R175,'Segment Analysis'!R195) -> N/A | ... T39: =IF($C$25="Annual",'Segment Analysis'!T175,'Segment Analysis'!T195) -> N/A | U39: =IFERROR(U38/S38-1,"--") -> -- | V39: =IFERROR(V38/U38-1,"--") -> -- | W39: =IFERROR(W38/V38-1,"--") -> -- | X39: =IFERROR(X38/W38-1,"--") -> -- | Y39: =IFERROR(Y38/T38-1,"--") -> -- | Z39: =IFERROR(Z38/X38-1,"--") -> -- | AA39: =IFERROR(AA38/Z38-1,"--") -> -- | AB39: =IFERROR(AB38/AA38-1,"--") -> -- | AC39: =IFERROR(AC38/AB38-1,"--") -> -- | AD39: =IFERROR(AD38/Y38-1,"--") -> -- | AE39: =IFERROR(AE38/AD38-1,"--") -> -- | AF39: =IFERROR(AF38/AE38-1,"--") -> -- | AG39: =IFERROR(AG38/AF38-1,"--") -> --
C40: % of Total Revenue | F40: ='Segment Analysis'!F18 -> 0 | G40: ='Segment Analysis'!G18 -> 0 | H40: ='Segment Analysis'!H18 -> 0 | I40: ='Segment Analysis'!I18 -> 0 | J40: ='Segment Analysis'!J18 -> 0 | K40: ='Segment Analysis'!K18 -> 0 | L40: ='Segment Analysis'!L18 -> 0 | M40: ='Segment Analysis'!M18 -> 0 | ... T40: ='Segment Analysis'!T18 -> 0 | U40: =U38/U$30 -> 0 | V40: =V38/V$30 -> 0 | W40: =W38/W$30 -> 0 | X40: =X38/X$30 -> 0 | Y40: =Y38/Y$30 -> 0 | Z40: =Z38/Z$30 -> 0 | AA40: =AA38/AA$30 -> 0 | AB40: =AB38/AB$30 -> 0 | ... AG40: =AG38/AG$30 -> 0
C41: ='Segment Analysis'!C11 -> Revenue | F41: ='Segment Analysis'!F11 -> 0 | G41: ='Segment Analysis'!G11 -> 0 | H41: ='Segment Analysis'!H11 -> 0 | I41: ='Segment Analysis'!I11 -> 0 | J41: ='Segment Analysis'!J11 -> 0 | K41: ='Segment Analysis'!K11 -> 0 | L41: ='Segment Analysis'!L11 -> 0 | M41: ='Segment Analysis'!M11 -> 0 | ... T41: ='Segment Analysis'!T11 -> 0 | U41: =IF(Segment4_Rev_Methodology="Segment",U71,IF(Segment4_Rev_Methodology="Activity-Based",U127,IF(Segment4_Rev_Methodology="Backlog",U201,"--"))) -> 0 | V41: =IF(Segment4_Rev_Methodology="Segment",V71,IF(Segment4_Rev_Methodology="Activity-Based",V127,IF(Segment4_Rev_Methodology="Backlog",V201,"--"))) -> 0 | W41: =IF(Segment4_Rev_Methodology="Segment",W71,IF(Segment4_Rev_Methodology="Activity-Based",W127,IF(Segment4_Rev_Methodology="Backlog",W201,"--"))) -> 0 | X41: =IF(Segment4_Rev_Methodology="Segment",X71,IF(Segment4_Rev_Methodology="Activity-Based",X127,IF(Segment4_Rev_Methodology="Backlog",X201,"--"))) -> 0 | Y41: =SUM(U41:X41) -> 0 | Z41: =IF(Segment4_Rev_Methodology="Segment",Z71,IF(Segment4_Rev_Methodology="Activity-Based",Z127,IF(Segment4_Rev_Methodology="Backlog",Z201,"--"))) -> 0 | AA41: =IF(Segment4_Rev_Methodology="Segment",AA71,IF(Segment4_Rev_Methodology="Activity-Based",AA127,IF(Segment4_Rev_Methodology="Backlog",AA201,"--"))) -> 0 | AB41: =IF(Segment4_Rev_Methodology="Segment",AB71,IF(Segment4_Rev_Methodology="Activity-Based",AB127,IF(Segment4_Rev_Methodology="Backlog",AB201,"--"))) -> 0 | AC41: =IF(Segment4_Rev_Methodology="Segment",AC71,IF(Segment4_Rev_Methodology="Activity-Based",AC127,IF(Segment4_Rev_Methodology="Backlog",AC201,"--"))) -> 0 | AD41: =SUM(Z41:AC41) -> 0 | AE41: =IF(Segment4_Rev_Methodology="Segment",AE71,IF(Segment4_Rev_Methodology="Activity-Based",AE127,IF(Segment4_Rev_Methodology="Backlog",AE201,"--"))) -> 0 | AF41: =IF(Segment4_Rev_Methodology="Segment",AF71,IF(Segment4_Rev_Methodology="Activity-Based",AF127,IF(Segment4_Rev_Methodology="Backlog",AF201,"--"))) -> 0 | AG41: =IF(Segment4_Rev_Methodology="Segment",AG71,IF(Segment4_Rev_Methodology="Activity-Based",AG127,IF(Segment4_Rev_Methodology="Backlog",AG201,"--"))) -> 0 | AI41: =IFERROR((T41/J41)^(1/3)-1,"--") -> -- | AJ41: =IFERROR((AG41/T41)^(1/5)-1,"--") -> --
C42: % Growth | G42: =IF($C$25="Annual",'Segment Analysis'!G176,'Segment Analysis'!G196) -> 0 | H42: =IF($C$25="Annual",'Segment Analysis'!H176,'Segment Analysis'!H196) -> 0 | I42: =IF($C$25="Annual",'Segment Analysis'!I176,'Segment Analysis'!I196) -> 0 | K42: =IF($C$25="Annual",'Segment Analysis'!K176,'Segment Analysis'!K196) -> N/A | L42: =IF($C$25="Annual",'Segment Analysis'!L176,'Segment Analysis'!L196) -> N/A | M42: =IF($C$25="Annual",'Segment Analysis'!M176,'Segment Analysis'!M196) -> N/A | N42: =IF($C$25="Annual",'Segment Analysis'!N176,'Segment Analysis'!N196) -> N/A | O42: =IF($C$25="Annual",'Segment Analysis'!O176,'Segment Analysis'!O196) -> N/A | P42: =IF($C$25="Annual",'Segment Analysis'!P176,'Segment Analysis'!P196) -> N/A | Q42: =IF($C$25="Annual",'Segment Analysis'!Q176,'Segment Analysis'!Q196) -> N/A | R42: =IF($C$25="Annual",'Segment Analysis'!R176,'Segment Analysis'!R196) -> N/A | ... T42: =IF($C$25="Annual",'Segment Analysis'!T176,'Segment Analysis'!T196) -> N/A | U42: =IFERROR(U41/S41-1,"--") -> -- | V42: =IFERROR(V41/U41-1,"--") -> -- | W42: =IFERROR(W41/V41-1,"--") -> -- | X42: =IFERROR(X41/W41-1,"--") -> -- | Y42: =IFERROR(Y41/T41-1,"--") -> -- | Z42: =IFERROR(Z41/X41-1,"--") -> -- | AA42: =IFERROR(AA41/Z41-1,"--") -> -- | AB42: =IFERROR(AB41/AA41-1,"--") -> -- | AC42: =IFERROR(AC41/AB41-1,"--") -> -- | AD42: =IFERROR(AD41/Y41-1,"--") -> -- | AE42: =IFERROR(AE41/AD41-1,"--") -> -- | AF42: =IFERROR(AF41/AE41-1,"--") -> -- | AG42: =IFERROR(AG41/AF41-1,"--") -> --
C43: % of Total Revenue | F43: ='Segment Analysis'!F19 -> 0 | G43: ='Segment Analysis'!G19 -> 0 | H43: ='Segment Analysis'!H19 -> 0 | I43: ='Segment Analysis'!I19 -> 0 | J43: ='Segment Analysis'!J19 -> 0 | K43: ='Segment Analysis'!K19 -> 0 | L43: ='Segment Analysis'!L19 -> 0 | M43: ='Segment Analysis'!M19 -> 0 | ... T43: ='Segment Analysis'!T19 -> 0 | U43: =U41/U$30 -> 0 | V43: =V41/V$30 -> 0 | W43: =W41/W$30 -> 0 | X43: =X41/X$30 -> 0 | Y43: =Y41/Y$30 -> 0 | Z43: =Z41/Z$30 -> 0 | AA43: =AA41/AA$30 -> 0 | AB43: =AB41/AB$30 -> 0 | ... AG43: =AG41/AG$30 -> 0
C44: ='Segment Analysis'!C12 -> Revenue | F44: ='Segment Analysis'!F12 -> 0 | G44: ='Segment Analysis'!G12 -> 0 | H44: ='Segment Analysis'!H12 -> 0 | I44: ='Segment Analysis'!I12 -> 0 | J44: ='Segment Analysis'!J12 -> 0 | K44: ='Segment Analysis'!K12 -> 0 | L44: ='Segment Analysis'!L12 -> 0 | M44: ='Segment Analysis'!M12 -> 0 | ... T44: ='Segment Analysis'!T12 -> 0 | U44: =IF(Segment5_Rev_Methodology="Segment",U77,IF(Segment5_Rev_Methodology="Activity-Based",U139,IF(Segment5_Rev_Methodology="Backlog",U213,"--"))) -> 0 | V44: =IF(Segment5_Rev_Methodology="Segment",V77,IF(Segment5_Rev_Methodology="Activity-Based",V139,IF(Segment5_Rev_Methodology="Backlog",V213,"--"))) -> 0 | W44: =IF(Segment5_Rev_Methodology="Segment",W77,IF(Segment5_Rev_Methodology="Activity-Based",W139,IF(Segment5_Rev_Methodology="Backlog",W213,"--"))) -> 0 | X44: =IF(Segment5_Rev_Methodology="Segment",X77,IF(Segment5_Rev_Methodology="Activity-Based",X139,IF(Segment5_Rev_Methodology="Backlog",X213,"--"))) -> 0 | Y44: =SUM(U44:X44) -> 0 | Z44: =IF(Segment5_Rev_Methodology="Segment",Z77,IF(Segment5_Rev_Methodology="Activity-Based",Z139,IF(Segment5_Rev_Methodology="Backlog",Z213,"--"))) -> 0 | AA44: =IF(Segment5_Rev_Methodology="Segment",AA77,IF(Segment5_Rev_Methodology="Activity-Based",AA139,IF(Segment5_Rev_Methodology="Backlog",AA213,"--"))) -> 0 | AB44: =IF(Segment5_Rev_Methodology="Segment",AB77,IF(Segment5_Rev_Methodology="Activity-Based",AB139,IF(Segment5_Rev_Methodology="Backlog",AB213,"--"))) -> 0 | AC44: =IF(Segment5_Rev_Methodology="Segment",AC77,IF(Segment5_Rev_Methodology="Activity-Based",AC139,IF(Segment5_Rev_Methodology="Backlog",AC213,"--"))) -> 0 | AD44: =SUM(Z44:AC44) -> 0 | AE44: =IF(Segment5_Rev_Methodology="Segment",AE77,IF(Segment5_Rev_Methodology="Activity-Based",AE139,IF(Segment5_Rev_Methodology="Backlog",AE213,"--"))) -> 0 | AF44: =IF(Segment5_Rev_Methodology="Segment",AF77,IF(Segment5_Rev_Methodology="Activity-Based",AF139,IF(Segment5_Rev_Methodology="Backlog",AF213,"--"))) -> 0 | AG44: =IF(Segment5_Rev_Methodology="Segment",AG77,IF(Segment5_Rev_Methodology="Activity-Based",AG139,IF(Segment5_Rev_Methodology="Backlog",AG213,"--"))) -> 0 | AI44: =IFERROR((T44/J44)^(1/3)-1,"--") -> -- | AJ44: =IFERROR((AG44/T44)^(1/5)-1,"--") -> --
C45: % Growth | G45: =IF($C$25="Annual",'Segment Analysis'!G177,'Segment Analysis'!G197) -> 0 | H45: =IF($C$25="Annual",'Segment Analysis'!H177,'Segment Analysis'!H197) -> 0 | I45: =IF($C$25="Annual",'Segment Analysis'!I177,'Segment Analysis'!I197) -> 0 | K45: =IF($C$25="Annual",'Segment Analysis'!K177,'Segment Analysis'!K197) -> N/A | L45: =IF($C$25="Annual",'Segment Analysis'!L177,'Segment Analysis'!L197) -> N/A | M45: =IF($C$25="Annual",'Segment Analysis'!M177,'Segment Analysis'!M197) -> N/A | N45: =IF($C$25="Annual",'Segment Analysis'!N177,'Segment Analysis'!N197) -> N/A | O45: =IF($C$25="Annual",'Segment Analysis'!O177,'Segment Analysis'!O197) -> N/A | P45: =IF($C$25="Annual",'Segment Analysis'!P177,'Segment Analysis'!P197) -> N/A | Q45: =IF($C$25="Annual",'Segment Analysis'!Q177,'Segment Analysis'!Q197) -> N/A | R45: =IF($C$25="Annual",'Segment Analysis'!R177,'Segment Analysis'!R197) -> N/A | ... T45: =IF($C$25="Annual",'Segment Analysis'!T177,'Segment Analysis'!T197) -> N/A | U45: =IFERROR(U44/S44-1,"--") -> -- | V45: =IFERROR(V44/U44-1,"--") -> -- | W45: =IFERROR(W44/V44-1,"--") -> -- | X45: =IFERROR(X44/W44-1,"--") -> -- | Y45: =IFERROR(Y44/T44-1,"--") -> -- | Z45: =IFERROR(Z44/X44-1,"--") -> -- | AA45: =IFERROR(AA44/Z44-1,"--") -> -- | AB45: =IFERROR(AB44/AA44-1,"--") -> -- | AC45: =IFERROR(AC44/AB44-1,"--") -> -- | AD45: =IFERROR(AD44/Y44-1,"--") -> -- | AE45: =IFERROR(AE44/AD44-1,"--") -> -- | AF45: =IFERROR(AF44/AE44-1,"--") -> -- | AG45: =IFERROR(AG44/AF44-1,"--") -> --
C46: % of Total Revenue | F46: ='Segment Analysis'!F20 -> 0 | G46: ='Segment Analysis'!G20 -> 0 | H46: ='Segment Analysis'!H20 -> 0 | I46: ='Segment Analysis'!I20 -> 0 | J46: ='Segment Analysis'!J20 -> 0 | K46: ='Segment Analysis'!K20 -> 0 | L46: ='Segment Analysis'!L20 -> 0 | M46: ='Segment Analysis'!M20 -> 0 | ... T46: ='Segment Analysis'!T20 -> 0 | U46: =U44/U$30 -> 0 | V46: =V44/V$30 -> 0 | W46: =W44/W$30 -> 0 | X46: =X44/X$30 -> 0 | Y46: =Y44/Y$30 -> 0 | Z46: =Z44/Z$30 -> 0 | AA46: =AA44/AA$30 -> 0 | AB46: =AB44/AB$30 -> 0 | ... AG46: =AG44/AG$30 -> 0
C47: ='Segment Analysis'!C13 -> Revenue | F47: ='Segment Analysis'!F13 -> 0 | G47: ='Segment Analysis'!G13 -> 0 | H47: ='Segment Analysis'!H13 -> 0 | I47: ='Segment Analysis'!I13 -> 0 | J47: ='Segment Analysis'!J13 -> 0 | K47: ='Segment Analysis'!K13 -> 0 | L47: ='Segment Analysis'!L13 -> 0 | M47: ='Segment Analysis'!M13 -> 0 | ... T47: ='Segment Analysis'!T13 -> 0 | U47: =IF(Segment6_Rev_Methodology="Segment",U83,IF(Segment6_Rev_Methodology="Activity-Based",U151,IF(Segment6_Rev_Methodology="Backlog",U225,"--"))) -> 0 | V47: =IF(Segment6_Rev_Methodology="Segment",V83,IF(Segment6_Rev_Methodology="Activity-Based",V151,IF(Segment6_Rev_Methodology="Backlog",V225,"--"))) -> 0 | W47: =IF(Segment6_Rev_Methodology="Segment",W83,IF(Segment6_Rev_Methodology="Activity-Based",W151,IF(Segment6_Rev_Methodology="Backlog",W225,"--"))) -> 0 | X47: =IF(Segment6_Rev_Methodology="Segment",X83,IF(Segment6_Rev_Methodology="Activity-Based",X151,IF(Segment6_Rev_Methodology="Backlog",X225,"--"))) -> 0 | Y47: =SUM(U47:X47) -> 0 | Z47: =IF(Segment6_Rev_Methodology="Segment",Z83,IF(Segment6_Rev_Methodology="Activity-Based",Z151,IF(Segment6_Rev_Methodology="Backlog",Z225,"--"))) -> 0 | AA47: =IF(Segment6_Rev_Methodology="Segment",AA83,IF(Segment6_Rev_Methodology="Activity-Based",AA151,IF(Segment6_Rev_Methodology="Backlog",AA225,"--"))) -> 0 | AB47: =IF(Segment6_Rev_Methodology="Segment",AB83,IF(Segment6_Rev_Methodology="Activity-Based",AB151,IF(Segment6_Rev_Methodology="Backlog",AB225,"--"))) -> 0 | AC47: =IF(Segment6_Rev_Methodology="Segment",AC83,IF(Segment6_Rev_Methodology="Activity-Based",AC151,IF(Segment6_Rev_Methodology="Backlog",AC225,"--"))) -> 0 | AD47: =SUM(Z47:AC47) -> 0 | AE47: =IF(Segment6_Rev_Methodology="Segment",AE83,IF(Segment6_Rev_Methodology="Activity-Based",AE151,IF(Segment6_Rev_Methodology="Backlog",AE225,"--"))) -> 0 | AF47: =IF(Segment6_Rev_Methodology="Segment",AF83,IF(Segment6_Rev_Methodology="Activity-Based",AF151,IF(Segment6_Rev_Methodology="Backlog",AF225,"--"))) -> 0 | AG47: =IF(Segment6_Rev_Methodology="Segment",AG83,IF(Segment6_Rev_Methodology="Activity-Based",AG151,IF(Segment6_Rev_Methodology="Backlog",AG225,"--"))) -> 0 | AI47: =IFERROR((T47/J47)^(1/3)-1,"--") -> -- | AJ47: =IFERROR((AG47/T47)^(1/5)-1,"--") -> --
C48: % Growth | G48: =IF($C$25="Annual",'Segment Analysis'!G198,'Segment Analysis'!G198) -> N/A | H48: =IF($C$25="Annual",'Segment Analysis'!H198,'Segment Analysis'!H198) -> N/A | I48: =IF($C$25="Annual",'Segment Analysis'!I198,'Segment Analysis'!I198) -> N/A | K48: =IF($C$25="Annual",'Segment Analysis'!K198,'Segment Analysis'!K198) -> N/A | L48: =IF($C$25="Annual",'Segment Analysis'!L198,'Segment Analysis'!L198) -> N/A | M48: =IF($C$25="Annual",'Segment Analysis'!M198,'Segment Analysis'!M198) -> N/A | N48: =IF($C$25="Annual",'Segment Analysis'!N198,'Segment Analysis'!N198) -> N/A | O48: =IF($C$25="Annual",'Segment Analysis'!O198,'Segment Analysis'!O198) -> 0 | P48: =IF($C$25="Annual",'Segment Analysis'!P198,'Segment Analysis'!P198) -> N/A | Q48: =IF($C$25="Annual",'Segment Analysis'!Q198,'Segment Analysis'!Q198) -> N/A | R48: =IF($C$25="Annual",'Segment Analysis'!R198,'Segment Analysis'!R198) -> N/A | ... T48: =IF($C$25="Annual",'Segment Analysis'!T198,'Segment Analysis'!T198) -> 0 | U48: =IFERROR(U47/S47-1,"--") -> -- | V48: =IFERROR(V47/U47-1,"--") -> -- | W48: =IFERROR(W47/V47-1,"--") -> -- | X48: =IFERROR(X47/W47-1,"--") -> -- | Y48: =IFERROR(Y47/T47-1,"--") -> -- | Z48: =IFERROR(Z47/X47-1,"--") -> -- | AA48: =IFERROR(AA47/Z47-1,"--") -> -- | AB48: =IFERROR(AB47/AA47-1,"--") -> -- | AC48: =IFERROR(AC47/AB47-1,"--") -> -- | AD48: =IFERROR(AD47/Y47-1,"--") -> -- | AE48: =IFERROR(AE47/AD47-1,"--") -> -- | AF48: =IFERROR(AF47/AE47-1,"--") -> -- | AG48: =IFERROR(AG47/AF47-1,"--") -> --
C49: % of Total Revenue | F49: ='Segment Analysis'!F21 -> 0 | G49: ='Segment Analysis'!G21 -> 0 | H49: ='Segment Analysis'!H21 -> 0 | I49: ='Segment Analysis'!I21 -> 0 | J49: ='Segment Analysis'!J21 -> 0 | K49: ='Segment Analysis'!K21 -> 0 | L49: ='Segment Analysis'!L21 -> 0 | M49: ='Segment Analysis'!M21 -> 0 | ... T49: ='Segment Analysis'!T21 -> 0 | U49: =U47/U$30 -> 0 | V49: =V47/V$30 -> 0 | W49: =W47/W$30 -> 0 | X49: =X47/X$30 -> 0 | Y49: =Y47/Y$30 -> 0 | Z49: =Z47/Z$30 -> 0 | AA49: =AA47/AA$30 -> 0 | AB49: =AB47/AB$30 -> 0 | ... AG49: =AG47/AG$30 -> 0
A51: x | C51: Growth Rate | F51: =F$28 -> 1Q23 | G51: =G$28 -> 2Q23 | H51: =H$28 -> 3Q23 | I51: =I$28 -> 4Q23 | J51: =J$28 -> 2023 | K51: =K$28 -> 1Q24 | L51: =L$28 -> 2Q24 | M51: =M$28 -> 3Q24 | ... AG51: =AG$28 -> 2030e | AH51: x
C53: =C32 -> Investment Banking Revenue | F53: =F32 -> 1744.68 | G53: =G32 -> 1681.412 | H53: =H32 -> 2075.3 | I53: =I32 -> 1855.578 | J53: =J32 -> 7356.97 | K53: =K32 -> 2384.8 | L53: =L32 -> 2306.27 | M53: =M32 -> 2459.03 | ... T53: =T32 -> 10135.32 | U53: =IF($C$25="Quarterly",S53*(1+U54),P53*(1+U54)) -> 2519.9342 | V53: =IF($C$25="Quarterly",U53*(1+V54),Q53*(1+V54)) -> 2642.1181 | W53: =IF($C$25="Quarterly",V53*(1+W54),R53*(1+W54)) -> 3063.0856 | X53: =IF($C$25="Quarterly",W53*(1+X54),S53*(1+X54)) -> 3034.8043 | Y53: =SUM(U53:X53) -> 11259.942 | Z53: =IF($C$25="Quarterly",X53*(1+Z54),U53*(1+Z54)) -> 2797.127 | AA53: =IF($C$25="Quarterly",Z53*(1+AA54),V53*(1+AA54)) -> 2932.7511 | AB53: =IF($C$25="Quarterly",AA53*(1+AB54),W53*(1+AB54)) -> 3338.7633 | AC53: =IF($C$25="Quarterly",AB53*(1+AC54),X53*(1+AC54)) -> 3307.9367 | AD53: =SUM(Z53:AC53) -> 12376.578 | AE53: =AD53*(1+AE54) -> 13366.704 | AF53: =AE53*(1+AF54) -> 14101.873 | AG53: =AF53*(1+AG54) -> 14595.439
C54: =IF($C$25="Quarterly","% Growth QoQ","% Growth YoY") -> % Growth YoY | G54: =G33 -> 0 | H54: =H33 -> 0 | I54: =I33 -> 0 | J54: =J33 -> 0 | K54: =K33 -> 0.36689823 | L54: =L33 -> 0.37162694 | M54: =M33 -> 0.18490339 | N54: =N33 -> 0.40375075 | ... T54: =T33 -> 0.039001139 | U54: =IF(Case_Scenario="Bull",U55,IF(Case_Scenario="Base",U56,IF(Case_Scenario="bear",U57,"N/A"))) -> 0.11 | V54: =IF(Case_Scenario="Bull",V55,IF(Case_Scenario="Base",V56,IF(Case_Scenario="bear",V57,"N/A"))) -> 0.12 | W54: =IF(Case_Scenario="Bull",W55,IF(Case_Scenario="Base",W56,IF(Case_Scenario="bear",W57,"N/A"))) -> 0.115 | X54: =IF(Case_Scenario="Bull",X55,IF(Case_Scenario="Base",X56,IF(Case_Scenario="bear",X57,"N/A"))) -> 0.1 | Y54: =Y33 -> 0.1109607 | Z54: =IF(Case_Scenario="Bull",Z55,IF(Case_Scenario="Base",Z56,IF(Case_Scenario="bear",Z57,"N/A"))) -> 0.11 | AA54: =IF(Case_Scenario="Bull",AA55,IF(Case_Scenario="Base",AA56,IF(Case_Scenario="bear",AA57,"N/A"))) -> 0.11 | AB54: =IF(Case_Scenario="Bull",AB55,IF(Case_Scenario="Base",AB56,IF(Case_Scenario="bear",AB57,"N/A"))) -> 0.09 | AC54: =IF(Case_Scenario="Bull",AC55,IF(Case_Scenario="Base",AC56,IF(Case_Scenario="bear",AC57,"N/A"))) -> 0.09 | AD54: =AD33 -> 0.099168879 | AE54: =IF(Case_Scenario="Bull",AE55,IF(Case_Scenario="Base",AE56,IF(Case_Scenario="bear",AE57,"N/A"))) -> 0.08 | AF54: =IF(Case_Scenario="Bull",AF55,IF(Case_Scenario="Base",AF56,IF(Case_Scenario="bear",AF57,"N/A"))) -> 0.055 | AG54: =IF(Case_Scenario="Bull",AG55,IF(Case_Scenario="Base",AG56,IF(Case_Scenario="bear",AG57,"N/A"))) -> 0.035
C55: Bull Case | U55: =U56+0.015 -> 0.125 | V55: =V56+0.015 -> 0.135 | W55: =W56+0.015 -> 0.13 | X55: =X56+0.015 -> 0.115 | Z55: =Z56+0.015 -> 0.125 | AA55: =AA56+0.015 -> 0.125 | AB55: =AB56+0.015 -> 0.105 | AC55: =AC56+0.015 -> 0.105 | AE55: =AE56+0.01 -> 0.09 | AF55: =AF56+0.01 -> 0.065 | AG55: =AG56+0.01 -> 0.045
C56: Base Case | U56: 0.11 | V56: 0.12 | W56: 0.115 | X56: 0.1 | Z56: 0.11 | AA56: 0.11 | AB56: 0.09 | AC56: 0.09 | AE56: 0.08 | AF56: 0.055 | AG56: 0.035
C57: Bear Case | U57: =U56-0.02 -> 0.09 | V57: =V56-0.02 -> 0.1 | W57: 0.055 | X57: =X56-0.02 -> 0.08 | Z57: =Z56-0.02 -> 0.09 | AA57: =AA56-0.02 -> 0.09 | AB57: 0.055 | AC57: =AC56-0.02 -> 0.07 | AE57: 0.09 | AF57: 0.08 | AG57: 0.015
A59: x | C59: =C35 -> Principal Transactions Revenue | F59: =F35 -> 35.88 | G59: =G35 -> -30.17 | H59: =H35 -> -34.412 | I59: =I35 -> 113.112 | J59: =J35 -> 84.41 | K59: =K35 -> 167.1 | L59: =L35 -> 209.96 | M59: =M35 -> 136.45 | ... T59: =T35 -> 688.357 | U59: =IF($C$25="Quarterly",S59*(1+U60),P59*(1+U60)) -> 222.9183 | V59: =IF($C$25="Quarterly",U59*(1+V60),Q59*(1+V60)) -> 162.3372 | W59: =IF($C$25="Quarterly",V59*(1+W60),R59*(1+W60)) -> 162.11712 | X59: =IF($C$25="Quarterly",W59*(1+X60),S59*(1+X60)) -> 184.21367 | Y59: =SUM(U59:X59) -> 731.58629 | Z59: =IF($C$25="Quarterly",X59*(1+Z60),U59*(1+Z60)) -> 151.58444 | AA59: =IF($C$25="Quarterly",Z59*(1+AA60),V59*(1+AA60)) -> 154.22034 | AB59: =IF($C$25="Quarterly",AA59*(1+AB60),W59*(1+AB60)) -> 172.65473 | AC59: =IF($C$25="Quarterly",AB59*(1+AC60),X59*(1+AC60)) -> 165.7923 | AD59: =SUM(Z59:AC59) -> 644.25182 | AE59: =AD59*(1+AE60) -> 528.28649 | AF59: =AE59*(1+AF60) -> 449.04352 | AG59: =AF59*(1+AG60) -> 381.68699
C60: =IF($C$25="Quarterly","% Growth QoQ","% Growth YoY") -> % Growth YoY | G60: =G36 -> 0 | H60: =H36 -> 0 | I60: =I36 -> 0 | J60: =J36 -> 0 | K60: =K36 -> 3.6571906 | L60: =L36 -> -7.959231 | M60: =M36 -> -4.9651866 | N60: =N36 -> 1.1809357 | ... T60: =T36 -> -0.094505393 | U60: =IF(Case_Scenario="Bull",U61,IF(Case_Scenario="Base",U62,IF(Case_Scenario="bear",U63,"N/A"))) -> 0.1 | V60: =IF(Case_Scenario="Bull",V61,IF(Case_Scenario="Base",V62,IF(Case_Scenario="bear",V63,"N/A"))) -> 0.2 | W60: =IF(Case_Scenario="Bull",W61,IF(Case_Scenario="Base",W62,IF(Case_Scenario="bear",W63,"N/A"))) -> 0.01 | X60: =IF(Case_Scenario="Bull",X61,IF(Case_Scenario="Base",X62,IF(Case_Scenario="bear",X63,"N/A"))) -> -0.03 | Y60: =Y36 -> 0.062800683 | Z60: =IF(Case_Scenario="Bull",Z61,IF(Case_Scenario="Base",Z62,IF(Case_Scenario="bear",Z63,"N/A"))) -> -0.32 | AA60: =IF(Case_Scenario="Bull",AA61,IF(Case_Scenario="Base",AA62,IF(Case_Scenario="bear",AA63,"N/A"))) -> -0.05 | AB60: =IF(Case_Scenario="Bull",AB61,IF(Case_Scenario="Base",AB62,IF(Case_Scenario="bear",AB63,"N/A"))) -> 0.065 | AC60: =IF(Case_Scenario="Bull",AC61,IF(Case_Scenario="Base",AC62,IF(Case_Scenario="bear",AC63,"N/A"))) -> -0.1 | AD60: =AD36 -> -0.11937685 | AE60: =IF(Case_Scenario="Bull",AE61,IF(Case_Scenario="Base",AE62,IF(Case_Scenario="bear",AE63,"N/A"))) -> -0.18 | AF60: =IF(Case_Scenario="Bull",AF61,IF(Case_Scenario="Base",AF62,IF(Case_Scenario="bear",AF63,"N/A"))) -> -0.15 | AG60: =IF(Case_Scenario="Bull",AG61,IF(Case_Scenario="Base",AG62,IF(Case_Scenario="bear",AG63,"N/A"))) -> -0.15
C61: Bull Case | U61: =U62+0.01 -> 0.11 | V61: =V62+0.01 -> 0.21 | W61: =W62+0.01 -> 0.02 | X61: =X62+0.01 -> -0.02 | Z61: =Z62+0.01 -> -0.31 | AA61: =AA62+0.01 -> -0.04 | AB61: =AB62+0.01 -> 0.075 | AC61: =AC62+0.01 -> -0.09 | AE61: =AE62+0.01 -> -0.17 | AF61: =AF62+0.01 -> -0.14 | AG61: =AG62+0.01 -> -0.14
C62: Base Case | U62: 0.1 | V62: 0.2 | W62: 0.01 | X62: -0.03 | Z62: -0.32 | AA62: -0.05 | AB62: 0.065 | AC62: -0.1 | AE62: -0.18 | AF62: -0.15 | AG62: -0.15
C63: Bear Case | U63: =U62-0.02 -> 0.08 | V63: =V62-0.02 -> 0.18 | W63: =W62-0.02 -> -0.01 | X63: =X62-0.02 -> -0.05 | Z63: =Z62-0.02 -> -0.34 | AA63: =AA62-0.02 -> -0.07 | AB63: =AB62-0.02 -> 0.045 | AC63: =AC62-0.02 -> -0.12 | AE63: =AE62-0.02 -> -0.2 | AF63: =AF62-0.02 -> -0.17 | AG63: =AG62-0.02 -> -0.17
A65: x | C65: =C38 -> Revenue | F65: =F38 -> 0 | G65: =G38 -> 0 | H65: =H38 -> 0 | I65: =I38 -> 0 | J65: =J38 -> 0 | K65: =K38 -> 0 | L65: =L38 -> 0 | M65: =M38 -> 0 | ... T65: =T38 -> 0 | U65: =IF($C$25="Quarterly",S65*(1+U66),P65*(1+U66)) -> 0 | V65: =IF($C$25="Quarterly",U65*(1+V66),Q65*(1+V66)) -> 0 | W65: =IF($C$25="Quarterly",V65*(1+W66),R65*(1+W66)) -> 0 | X65: =IF($C$25="Quarterly",W65*(1+X66),S65*(1+X66)) -> 0 | Y65: =SUM(U65:X65) -> 0 | Z65: =IF($C$25="Quarterly",X65*(1+Z66),U65*(1+Z66)) -> 0 | AA65: =IF($C$25="Quarterly",Z65*(1+AA66),V65*(1+AA66)) -> 0 | AB65: =IF($C$25="Quarterly",AA65*(1+AB66),W65*(1+AB66)) -> 0 | AC65: =IF($C$25="Quarterly",AB65*(1+AC66),X65*(1+AC66)) -> 0 | AD65: =SUM(Z65:AC65) -> 0 | AE65: =AD65*(1+AE66) -> 0 | AF65: =AE65*(1+AF66) -> 0 | AG65: =AF65*(1+AG66) -> 0
C66: =IF($C$25="Quarterly","% Growth QoQ","% Growth YoY") -> % Growth YoY | G66: =G39 -> 0 | H66: =H39 -> 0 | I66: =I39 -> 0 | J66: =J39 -> 0 | K66: =K39 -> N/A | L66: =L39 -> N/A | M66: =M39 -> N/A | N66: =N39 -> N/A | ... T66: =T39 -> N/A | U66: =IF(Case_Scenario="Bull",U67,IF(Case_Scenario="Base",U68,IF(Case_Scenario="bear",U69,"N/A"))) -> 0 | V66: =IF(Case_Scenario="Bull",V67,IF(Case_Scenario="Base",V68,IF(Case_Scenario="bear",V69,"N/A"))) -> 0 | W66: =IF(Case_Scenario="Bull",W67,IF(Case_Scenario="Base",W68,IF(Case_Scenario="bear",W69,"N/A"))) -> 0 | X66: =IF(Case_Scenario="Bull",X67,IF(Case_Scenario="Base",X68,IF(Case_Scenario="bear",X69,"N/A"))) -> 0 | Z66: =IF(Case_Scenario="Bull",Z67,IF(Case_Scenario="Base",Z68,IF(Case_Scenario="bear",Z69,"N/A"))) -> 0 | AA66: =IF(Case_Scenario="Bull",AA67,IF(Case_Scenario="Base",AA68,IF(Case_Scenario="bear",AA69,"N/A"))) -> 0 | AB66: =IF(Case_Scenario="Bull",AB67,IF(Case_Scenario="Base",AB68,IF(Case_Scenario="bear",AB69,"N/A"))) -> 0 | AC66: =IF(Case_Scenario="Bull",AC67,IF(Case_Scenario="Base",AC68,IF(Case_Scenario="bear",AC69,"N/A"))) -> 0 | AE66: =IF(Case_Scenario="Bull",AE67,IF(Case_Scenario="Base",AE68,IF(Case_Scenario="bear",AE69,"N/A"))) -> 0 | AF66: =IF(Case_Scenario="Bull",AF67,IF(Case_Scenario="Base",AF68,IF(Case_Scenario="bear",AF69,"N/A"))) -> 0 | AG66: =IF(Case_Scenario="Bull",AG67,IF(Case_Scenario="Base",AG68,IF(Case_Scenario="bear",AG69,"N/A"))) -> 0
C67: Bull Case | U67: 0 | V67: 0 | W67: 0 | X67: 0 | Z67: 0 | AA67: 0 | AB67: 0 | AC67: 0 | AE67: 0 | AF67: 0 | AG67: 0
C68: Base Case | U68: 0 | V68: 0 | W68: 0 | X68: 0 | Z68: 0 | AA68: 0 | AB68: 0 | AC68: 0 | AE68: 0 | AF68: 0 | AG68: 0
C69: Bear Case | U69: 0 | V69: 0 | W69: 0 | X69: 0 | Z69: 0 | AA69: 0 | AB69: 0 | AC69: 0 | AE69: 0 | AF69: 0 | AG69: 0
A71: x | C71: =C41 -> Revenue | F71: =F41 -> 0 | G71: =G41 -> 0 | H71: =H41 -> 0 | I71: =I41 -> 0 | J71: =J41 -> 0 | K71: =K41 -> 0 | L71: =L41 -> 0 | M71: =M41 -> 0 | ... T71: =T41 -> 0 | U71: =IF($C$25="Quarterly",S71*(1+U72),P71*(1+U72)) -> 0 | V71: =IF($C$25="Quarterly",U71*(1+V72),Q71*(1+V72)) -> 0 | W71: =IF($C$25="Quarterly",V71*(1+W72),R71*(1+W72)) -> 0 | X71: =IF($C$25="Quarterly",W71*(1+X72),S71*(1+X72)) -> 0 | Y71: =SUM(U71:X71) -> 0 | Z71: =IF($C$25="Quarterly",X71*(1+Z72),U71*(1+Z72)) -> 0 | AA71: =IF($C$25="Quarterly",Z71*(1+AA72),V71*(1+AA72)) -> 0 | AB71: =IF($C$25="Quarterly",AA71*(1+AB72),W71*(1+AB72)) -> 0 | AC71: =IF($C$25="Quarterly",AB71*(1+AC72),X71*(1+AC72)) -> 0 | AD71: =SUM(Z71:AC71) -> 0 | AE71: =AD71*(1+AE72) -> 0 | AF71: =AE71*(1+AF72) -> 0 | AG71: =AF71*(1+AG72) -> 0
C72: =IF($C$25="Quarterly","% Growth QoQ","% Growth YoY") -> % Growth YoY | G72: =G42 -> 0 | H72: =H42 -> 0 | I72: =I42 -> 0 | J72: =J42 -> 0 | K72: =K42 -> N/A | L72: =L42 -> N/A | M72: =M42 -> N/A | N72: =N42 -> N/A | ... T72: =T42 -> N/A | U72: =IF(Case_Scenario="Bull",U73,IF(Case_Scenario="Base",U74,IF(Case_Scenario="bear",U75,"N/A"))) -> 0 | V72: =IF(Case_Scenario="Bull",V73,IF(Case_Scenario="Base",V74,IF(Case_Scenario="bear",V75,"N/A"))) -> 0 | W72: =IF(Case_Scenario="Bull",W73,IF(Case_Scenario="Base",W74,IF(Case_Scenario="bear",W75,"N/A"))) -> 0 | X72: =IF(Case_Scenario="Bull",X73,IF(Case_Scenario="Base",X74,IF(Case_Scenario="bear",X75,"N/A"))) -> 0 | Z72: =IF(Case_Scenario="Bull",Z73,IF(Case_Scenario="Base",Z74,IF(Case_Scenario="bear",Z75,"N/A"))) -> 0 | AA72: =IF(Case_Scenario="Bull",AA73,IF(Case_Scenario="Base",AA74,IF(Case_Scenario="bear",AA75,"N/A"))) -> 0 | AB72: =IF(Case_Scenario="Bull",AB73,IF(Case_Scenario="Base",AB74,IF(Case_Scenario="bear",AB75,"N/A"))) -> 0 | AC72: =IF(Case_Scenario="Bull",AC73,IF(Case_Scenario="Base",AC74,IF(Case_Scenario="bear",AC75,"N/A"))) -> 0 | AE72: =IF(Case_Scenario="Bull",AE73,IF(Case_Scenario="Base",AE74,IF(Case_Scenario="bear",AE75,"N/A"))) -> 0 | AF72: =IF(Case_Scenario="Bull",AF73,IF(Case_Scenario="Base",AF74,IF(Case_Scenario="bear",AF75,"N/A"))) -> 0 | AG72: =IF(Case_Scenario="Bull",AG73,IF(Case_Scenario="Base",AG74,IF(Case_Scenario="bear",AG75,"N/A"))) -> 0
C73: Bull Case | U73: 0 | V73: 0 | W73: 0 | X73: 0 | Z73: 0 | AA73: 0 | AB73: 0 | AC73: 0 | AE73: 0 | AF73: 0 | AG73: 0
C74: Base Case | U74: 0 | V74: 0 | W74: 0 | X74: 0 | Z74: 0 | AA74: 0 | AB74: 0 | AC74: 0 | AE74: 0 | AF74: 0 | AG74: 0
C75: Bear Case | U75: 0 | V75: 0 | W75: 0 | X75: 0 | Z75: 0 | AA75: 0 | AB75: 0 | AC75: 0 | AE75: 0 | AF75: 0 | AG75: 0
A77: x | C77: =C44 -> Revenue | F77: =F44 -> 0 | G77: =G44 -> 0 | H77: =H44 -> 0 | I77: =I44 -> 0 | J77: =J44 -> 0 | K77: =K44 -> 0 | L77: =L44 -> 0 | M77: =M44 -> 0 | ... T77: =T44 -> 0 | U77: =IF($C$25="Quarterly",S77*(1+U78),P77*(1+U78)) -> 0 | V77: =IF($C$25="Quarterly",U77*(1+V78),Q77*(1+V78)) -> 0 | W77: =IF($C$25="Quarterly",V77*(1+W78),R77*(1+W78)) -> 0 | X77: =IF($C$25="Quarterly",W77*(1+X78),S77*(1+X78)) -> 0 | Y77: =SUM(U77:X77) -> 0 | Z77: =IF($C$25="Quarterly",X77*(1+Z78),U77*(1+Z78)) -> 0 | AA77: =IF($C$25="Quarterly",Z77*(1+AA78),V77*(1+AA78)) -> 0 | AB77: =IF($C$25="Quarterly",AA77*(1+AB78),W77*(1+AB78)) -> 0 | AC77: =IF($C$25="Quarterly",AB77*(1+AC78),X77*(1+AC78)) -> 0 | AD77: =SUM(Z77:AC77) -> 0 | AE77: =AD77*(1+AE78) -> 0 | AF77: =AE77*(1+AF78) -> 0 | AG77: =AF77*(1+AG78) -> 0
C78: =IF($C$25="Quarterly","% Growth QoQ","% Growth YoY") -> % Growth YoY | G78: =G45 -> 0 | H78: =H45 -> 0 | I78: =I45 -> 0 | J78: =J45 -> 0 | K78: =K45 -> N/A | L78: =L45 -> N/A | M78: =M45 -> N/A | N78: =N45 -> N/A | ... T78: =T45 -> N/A | U78: =IF(Case_Scenario="Bull",U79,IF(Case_Scenario="Base",U80,IF(Case_Scenario="bear",U81,"N/A"))) -> 0 | V78: =IF(Case_Scenario="Bull",V79,IF(Case_Scenario="Base",V80,IF(Case_Scenario="bear",V81,"N/A"))) -> 0 | W78: =IF(Case_Scenario="Bull",W79,IF(Case_Scenario="Base",W80,IF(Case_Scenario="bear",W81,"N/A"))) -> 0 | X78: =IF(Case_Scenario="Bull",X79,IF(Case_Scenario="Base",X80,IF(Case_Scenario="bear",X81,"N/A"))) -> 0 | Z78: =IF(Case_Scenario="Bull",Z79,IF(Case_Scenario="Base",Z80,IF(Case_Scenario="bear",Z81,"N/A"))) -> 0 | AA78: =IF(Case_Scenario="Bull",AA79,IF(Case_Scenario="Base",AA80,IF(Case_Scenario="bear",AA81,"N/A"))) -> 0 | AB78: =IF(Case_Scenario="Bull",AB79,IF(Case_Scenario="Base",AB80,IF(Case_Scenario="bear",AB81,"N/A"))) -> 0 | AC78: =IF(Case_Scenario="Bull",AC79,IF(Case_Scenario="Base",AC80,IF(Case_Scenario="bear",AC81,"N/A"))) -> 0 | AE78: =IF(Case_Scenario="Bull",AE79,IF(Case_Scenario="Base",AE80,IF(Case_Scenario="bear",AE81,"N/A"))) -> 0 | AF78: =IF(Case_Scenario="Bull",AF79,IF(Case_Scenario="Base",AF80,IF(Case_Scenario="bear",AF81,"N/A"))) -> 0 | AG78: =IF(Case_Scenario="Bull",AG79,IF(Case_Scenario="Base",AG80,IF(Case_Scenario="bear",AG81,"N/A"))) -> 0
C79: Bull Case | U79: 0 | V79: 0 | W79: 0 | X79: 0 | Z79: 0 | AA79: 0 | AB79: 0 | AC79: 0 | AE79: 0 | AF79: 0 | AG79: 0
C80: Base Case | U80: 0 | V80: 0 | W80: 0 | X80: 0 | Z80: 0 | AA80: 0 | AB80: 0 | AC80: 0 | AE80: 0 | AF80: 0 | AG80: 0
C81: Bear Case | U81: 0 | V81: 0 | W81: 0 | X81: 0 | Z81: 0 | AA81: 0 | AB81: 0 | AC81: 0 | AE81: 0 | AF81: 0 | AG81: 0
A83: x | C83: =C47 -> Revenue | F83: =F47 -> 0 | G83: =G47 -> 0 | H83: =H47 -> 0 | I83: =I47 -> 0 | J83: =J47 -> 0 | K83: =K47 -> 0 | L83: =L47 -> 0 | M83: =M47 -> 0 | ... T83: =T47 -> 0 | U83: =IF($C$25="Quarterly",S83*(1+U84),P83*(1+U84)) -> 0 | V83: =IF($C$25="Quarterly",U83*(1+V84),Q83*(1+V84)) -> 0 | W83: =IF($C$25="Quarterly",V83*(1+W84),R83*(1+W84)) -> 0 | X83: =IF($C$25="Quarterly",W83*(1+X84),S83*(1+X84)) -> 0 | Y83: =SUM(U83:X83) -> 0 | Z83: =IF($C$25="Quarterly",X83*(1+Z84),U83*(1+Z84)) -> 0 | AA83: =IF($C$25="Quarterly",Z83*(1+AA84),V83*(1+AA84)) -> 0 | AB83: =IF($C$25="Quarterly",AA83*(1+AB84),W83*(1+AB84)) -> 0 | AC83: =IF($C$25="Quarterly",AB83*(1+AC84),X83*(1+AC84)) -> 0 | AD83: =SUM(Z83:AC83) -> 0 | AE83: =AD83*(1+AE84) -> 0 | AF83: =AE83*(1+AF84) -> 0 | AG83: =AF83*(1+AG84) -> 0
C84: =IF($C$25="Quarterly","% Growth QoQ","% Growth YoY") -> % Growth YoY | G84: =G48 -> N/A | H84: =H48 -> N/A | I84: =I48 -> N/A | J84: =J48 -> 0 | K84: =K48 -> N/A | L84: =L48 -> N/A | M84: =M48 -> N/A | N84: =N48 -> N/A | ... T84: =T48 -> 0 | U84: =IF(Case_Scenario="Bull",U85,IF(Case_Scenario="Base",U86,IF(Case_Scenario="bear",U87,"N/A"))) -> 0 | V84: =IF(Case_Scenario="Bull",V85,IF(Case_Scenario="Base",V86,IF(Case_Scenario="bear",V87,"N/A"))) -> 0 | W84: =IF(Case_Scenario="Bull",W85,IF(Case_Scenario="Base",W86,IF(Case_Scenario="bear",W87,"N/A"))) -> 0 | X84: =IF(Case_Scenario="Bull",X85,IF(Case_Scenario="Base",X86,IF(Case_Scenario="bear",X87,"N/A"))) -> 0 | Z84: =IF(Case_Scenario="Bull",Z85,IF(Case_Scenario="Base",Z86,IF(Case_Scenario="bear",Z87,"N/A"))) -> 0 | AA84: =IF(Case_Scenario="Bull",AA85,IF(Case_Scenario="Base",AA86,IF(Case_Scenario="bear",AA87,"N/A"))) -> 0 | AB84: =IF(Case_Scenario="Bull",AB85,IF(Case_Scenario="Base",AB86,IF(Case_Scenario="bear",AB87,"N/A"))) -> 0 | AC84: =IF(Case_Scenario="Bull",AC85,IF(Case_Scenario="Base",AC86,IF(Case_Scenario="bear",AC87,"N/A"))) -> 0 | AE84: =IF(Case_Scenario="Bull",AE85,IF(Case_Scenario="Base",AE86,IF(Case_Scenario="bear",AE87,"N/A"))) -> 0 | AF84: =IF(Case_Scenario="Bull",AF85,IF(Case_Scenario="Base",AF86,IF(Case_Scenario="bear",AF87,"N/A"))) -> 0 | AG84: =IF(Case_Scenario="Bull",AG85,IF(Case_Scenario="Base",AG86,IF(Case_Scenario="bear",AG87,"N/A"))) -> 0
C85: Bull Case | U85: =S85 -> 0 | V85: =U85 -> 0 | W85: =V85 -> 0 | X85: =W85 -> 0 | Z85: =X85 -> 0 | AA85: =Z85 -> 0 | AB85: =AA85 -> 0 | AC85: =AB85 -> 0 | AE85: =AC85 -> 0 | AF85: =AE85 -> 0 | AG85: =AF85 -> 0
C86: Base Case | U86: =T86 -> 0 | V86: =U86 -> 0 | W86: =V86 -> 0 | X86: =W86 -> 0 | Z86: =Y86 -> 0 | AA86: =Z86 -> 0 | AB86: =AA86 -> 0 | AC86: =AB86 -> 0 | AE86: =AC86 -> 0 | AF86: =AE86 -> 0 | AG86: =AF86 -> 0
C87: Bear Case | U87: =S87 -> 0 | V87: =U87 -> 0 | W87: =V87 -> 0 | X87: =W87 -> 0 | Z87: =X87 -> 0 | AA87: =Z87 -> 0 | AB87: =AA87 -> 0 | AC87: =AB87 -> 0 | AE87: =AC87 -> 0 | AF87: =AE87 -> 0 | AG87: =AF87 -> 0
A89: x | C89: Activity-Based Growth | F89: =F$28 -> 1Q23 | G89: =G$28 -> 2Q23 | H89: =H$28 -> 3Q23 | I89: =I$28 -> 4Q23 | J89: =J$28 -> 2023 | K89: =K$28 -> 1Q24 | L89: =L$28 -> 2Q24 | M89: =M$28 -> 3Q24 | ... AG89: =AG$28 -> 2030e | AH89: x
C91: =C32 -> Investment Banking Revenue | F91: =F32 -> 1744.68 | G91: =G32 -> 1681.412 | H91: =H32 -> 2075.3 | I91: =I32 -> 1855.578 | J91: =J32 -> 7356.97 | K91: =K32 -> 2384.8 | L91: =L32 -> 2306.27 | M91: =M32 -> 2459.03 | ... T91: =T32 -> 10135.32 | U91: =U92*U97 -> 3041.7016 | V91: =V92*V97 -> 3353.476 | W91: =W92*W97 -> 3697.2073 | X91: =X92*X97 -> 4076.171 | Y91: =SUM(U91:X91) -> 14168.556 | Z91: =Z92*Z97 -> 4493.9786 | AA91: =AA92*AA97 -> 4954.6114 | AB91: =AB92*AB97 -> 5462.459 | AC91: =AC92*AC97 -> 6022.3611 | AD91: =SUM(Z91:AC91) -> 20933.41 | AE91: =AE92*AE97 -> 23079.085 | AF91: =AF92*AF97 -> 25444.691 | AG91: =AG92*AG97 -> 28052.772
C92: Volume | F92: 220 | G92: 220 | H92: 220 | I92: 220 | J92: =SUM(F92:I92) -> 880 | K92: 220 | L92: 220 | M92: 220 | N92: 220 | O92: =SUM(K92:N92) -> 880 | P92: 220 | Q92: 220 | R92: 220 | S92: 220 | T92: =SUM(P92:S92) -> 880 | U92: =S92*(1+U93) -> 231 | V92: =U92*(1+V93) -> 242.55 | W92: =V92*(1+W93) -> 254.6775 | X92: =W92*(1+X93) -> 267.41138 | Y92: =SUM(U92:X92) -> 995.63887 | Z92: =X92*(1+Z93) -> 280.78194 | AA92: =Z92*(1+AA93) -> 294.82104 | AB92: =AA92*(1+AB93) -> 309.56209 | AC92: =AB92*(1+AC93) -> 325.0402 | AD92: =SUM(Z92:AC92) -> 1210.2053 | AE92: =AD92*(1+AE93) -> 1270.7155 | AF92: =AE92*(1+AF93) -> 1334.2513 | AG92: =AF92*(1+AG93) -> 1400.9639
C93: % Volume Growth | G93: =IFERROR(G92/F92-1,"--") -> 0 | H93: =IFERROR(H92/G92-1,"--") -> 0 | I93: =IFERROR(I92/H92-1,"--") -> 0 | K93: =IFERROR(K92/I92-1,"--") -> 0 | L93: =IFERROR(L92/K92-1,"--") -> 0 | M93: =IFERROR(M92/L92-1,"--") -> 0 | N93: =IFERROR(N92/M92-1,"--") -> 0 | O93: =IFERROR(O92/J92-1,"--") -> 0 | P93: =IFERROR(P92/N92-1,"--") -> 0 | Q93: =IFERROR(Q92/P92-1,"--") -> 0 | R93: =IFERROR(R92/Q92-1,"--") -> 0 | S93: =IFERROR(S92/R92-1,"--") -> 0 | T93: =IFERROR(T92/O92-1,"--") -> 0 | U93: =IF(Case_Scenario="Bull",U94,IF(Case_Scenario="Base",U95,IF(Case_Scenario="bear",U96,"N/A"))) -> 0.05 | V93: =IF(Case_Scenario="Bull",V94,IF(Case_Scenario="Base",V95,IF(Case_Scenario="bear",V96,"N/A"))) -> 0.05 | W93: =IF(Case_Scenario="Bull",W94,IF(Case_Scenario="Base",W95,IF(Case_Scenario="bear",W96,"N/A"))) -> 0.05 | X93: =IF(Case_Scenario="Bull",X94,IF(Case_Scenario="Base",X95,IF(Case_Scenario="bear",X96,"N/A"))) -> 0.05 | Z93: =IF(Case_Scenario="Bull",Z94,IF(Case_Scenario="Base",Z95,IF(Case_Scenario="bear",Z96,"N/A"))) -> 0.05 | AA93: =IF(Case_Scenario="Bull",AA94,IF(Case_Scenario="Base",AA95,IF(Case_Scenario="bear",AA96,"N/A"))) -> 0.05 | AB93: =IF(Case_Scenario="Bull",AB94,IF(Case_Scenario="Base",AB95,IF(Case_Scenario="bear",AB96,"N/A"))) -> 0.05 | AC93: =IF(Case_Scenario="Bull",AC94,IF(Case_Scenario="Base",AC95,IF(Case_Scenario="bear",AC96,"N/A"))) -> 0.05 | AE93: =IF(Case_Scenario="Bull",AE94,IF(Case_Scenario="Base",AE95,IF(Case_Scenario="bear",AE96,"N/A"))) -> 0.05 | AF93: =IF(Case_Scenario="Bull",AF94,IF(Case_Scenario="Base",AF95,IF(Case_Scenario="bear",AF96,"N/A"))) -> 0.05 | AG93: =IF(Case_Scenario="Bull",AG94,IF(Case_Scenario="Base",AG95,IF(Case_Scenario="bear",AG96,"N/A"))) -> 0.05
C94: Bull Case | U94: 0.1 | V94: 0.1 | W94: 0.1 | X94: 0.1 | Z94: 0.1 | AA94: 0.1 | AB94: 0.1 | AC94: 0.1 | AE94: 0.1 | AF94: 0.1 | AG94: 0.1
C95: Base Case | U95: 0.05 | V95: 0.05 | W95: 0.05 | X95: 0.05 | Z95: 0.05 | AA95: 0.05 | AB95: 0.05 | AC95: 0.05 | AE95: 0.05 | AF95: 0.05 | AG95: 0.05
C96: Bear Case | U96: 0 | V96: 0 | W96: 0 | X96: 0 | Z96: 0 | AA96: 0 | AB96: 0 | AC96: 0 | AE96: 0 | AF96: 0 | AG96: 0
C97: Price | F97: =IFERROR(F91/F92,"--") -> 7.9303636 | G97: =IFERROR(G91/G92,"--") -> 7.6427818 | H97: =IFERROR(H91/H92,"--") -> 9.4331818 | I97: =IFERROR(I91/I92,"--") -> 8.4344455 | J97: =IFERROR(J91/J92,"--") -> 8.3601932 | K97: =IFERROR(K91/K92,"--") -> 10.84 | L97: =IFERROR(L91/L92,"--") -> 10.483045 | M97: =IFERROR(M91/M92,"--") -> 11.177409 | ... T97: =IFERROR(T91/T92,"--") -> 11.517409 | U97: =S97*(1+U98) -> 13.167539 | V97: =U97*(1+V98) -> 13.825916 | W97: =V97*(1+W98) -> 14.517212 | X97: =W97*(1+X98) -> 15.243073 | Y97: =Y91/Y92 -> 14.230617 | Z97: =X97*(1+Z98) -> 16.005226 | AA97: =Z97*(1+AA98) -> 16.805488 | AB97: =AA97*(1+AB98) -> 17.645762 | AC97: =AB97*(1+AC98) -> 18.52805 | AD97: =AD91/AD92 -> 17.297404 | AE97: =AD97*(1+AE98) -> 18.162275 | AF97: =AE97*(1+AF98) -> 19.070388 | AG97: =AF97*(1+AG98) -> 20.023908
C98: % Price Growth | G98: =IFERROR(G97/F97-1,"--") -> -0.036263384 | H98: =IFERROR(H97/G97-1,"--") -> 0.23426025 | I98: =IFERROR(I97/H97-1,"--") -> -0.10587481 | K98: =IFERROR(K97/I97-1,"--") -> 0.28520601 | L98: =IFERROR(L97/K97-1,"--") -> -0.032929386 | M98: =IFERROR(M97/L97-1,"--") -> 0.066236824 | N98: =IFERROR(N97/M97-1,"--") -> 0.059266865 | O98: =IFERROR(O97/J97-1,"--") -> 0.32593568 | P98: =IFERROR(P97/N97-1,"--") -> -0.12844056 | Q98: =IFERROR(Q97/P97-1,"--") -> 0.039125438 | R98: =IFERROR(R97/Q97-1,"--") -> 0.16452836 | S98: =IFERROR(S97/R97-1,"--") -> 0.0042775053 | T98: =IFERROR(T97/O97-1,"--") -> 0.039001139 | U98: =IF(Case_Scenario="Bull",U99,IF(Case_Scenario="Base",U100,IF(Case_Scenario="bear",U101,"N/A"))) -> 0.05 | V98: =IF(Case_Scenario="Bull",V99,IF(Case_Scenario="Base",V100,IF(Case_Scenario="bear",V101,"N/A"))) -> 0.05 | W98: =IF(Case_Scenario="Bull",W99,IF(Case_Scenario="Base",W100,IF(Case_Scenario="bear",W101,"N/A"))) -> 0.05 | X98: =IF(Case_Scenario="Bull",X99,IF(Case_Scenario="Base",X100,IF(Case_Scenario="bear",X101,"N/A"))) -> 0.05 | Z98: =IF(Case_Scenario="Bull",Z99,IF(Case_Scenario="Base",Z100,IF(Case_Scenario="bear",Z101,"N/A"))) -> 0.05 | AA98: =IF(Case_Scenario="Bull",AA99,IF(Case_Scenario="Base",AA100,IF(Case_Scenario="bear",AA101,"N/A"))) -> 0.05 | AB98: =IF(Case_Scenario="Bull",AB99,IF(Case_Scenario="Base",AB100,IF(Case_Scenario="bear",AB101,"N/A"))) -> 0.05 | AC98: =IF(Case_Scenario="Bull",AC99,IF(Case_Scenario="Base",AC100,IF(Case_Scenario="bear",AC101,"N/A"))) -> 0.05 | AE98: =IF(Case_Scenario="Bull",AE99,IF(Case_Scenario="Base",AE100,IF(Case_Scenario="bear",AE101,"N/A"))) -> 0.05 | AF98: =IF(Case_Scenario="Bull",AF99,IF(Case_Scenario="Base",AF100,IF(Case_Scenario="bear",AF101,"N/A"))) -> 0.05 | AG98: =IF(Case_Scenario="Bull",AG99,IF(Case_Scenario="Base",AG100,IF(Case_Scenario="bear",AG101,"N/A"))) -> 0.05
C99: Bull Case | U99: 0.1 | V99: 0.1 | W99: 0.1 | X99: 0.1 | Z99: 0.1 | AA99: 0.1 | AB99: 0.1 | AC99: 0.1 | AE99: 0.1 | AF99: 0.1 | AG99: 0.1
C100: Base Case | U100: 0.05 | V100: 0.05 | W100: 0.05 | X100: 0.05 | Z100: 0.05 | AA100: 0.05 | AB100: 0.05 | AC100: 0.05 | AE100: 0.05 | AF100: 0.05 | AG100: 0.05
C101: Bear Case | U101: 0 | V101: 0 | W101: 0 | X101: 0 | Z101: 0 | AA101: 0 | AB101: 0 | AC101: 0 | AE101: 0 | AF101: 0 | AG101: 0
A103: x | C103: =C35 -> Principal Transactions Revenue | F103: =F35 -> 35.88 | G103: =G35 -> -30.17 | H103: =H35 -> -34.412 | I103: =I35 -> 113.112 | J103: =J35 -> 84.41 | K103: =K35 -> 167.1 | L103: =L35 -> 209.96 | M103: =M35 -> 136.45 | ... T103: =T35 -> 688.357 | U103: =U104*U109 -> 209.37688 | V103: =V104*V109 -> 230.83801 | W103: =W104*W109 -> 254.4989 | X103: =X104*X109 -> 280.58504 | Y103: =SUM(U103:X103) -> 975.29883 | Z103: =Z104*Z109 -> 309.34501 | AA103: =AA104*AA109 -> 341.05287 | AB103: =AB104*AB109 -> 376.01079 | AC103: =AC104*AC109 -> 414.5519 | AD103: =SUM(Z103:AC103) -> 1440.9606 | AE103: =AE104*AE109 -> 1588.659 | AF103: =AF104*AF109 -> 1751.4966 | AG103: =AG104*AG109 -> 1931.025
C104: Volume | F104: 220 | G104: 220 | H104: 220 | I104: 220 | J104: =SUM(F104:I104) -> 880 | K104: 220 | L104: 220 | M104: 220 | N104: 220 | O104: =SUM(K104:N104) -> 880 | P104: 220 | Q104: 220 | R104: 220 | S104: 220 | T104: =SUM(P104:S104) -> 880 | U104: =S104*(1+U105) -> 231 | V104: =U104*(1+V105) -> 242.55 | W104: =V104*(1+W105) -> 254.6775 | X104: =W104*(1+X105) -> 267.41138 | Y104: =SUM(U104:X104) -> 995.63887 | Z104: =X104*(1+Z105) -> 280.78194 | AA104: =Z104*(1+AA105) -> 294.82104 | AB104: =AA104*(1+AB105) -> 309.56209 | AC104: =AB104*(1+AC105) -> 325.0402 | AD104: =SUM(Z104:AC104) -> 1210.2053 | AE104: =AD104*(1+AE105) -> 1270.7155 | AF104: =AE104*(1+AF105) -> 1334.2513 | AG104: =AF104*(1+AG105) -> 1400.9639
C105: % Volume Growth | G105: =IFERROR(G104/F104-1,"--") -> 0 | H105: =IFERROR(H104/G104-1,"--") -> 0 | I105: =IFERROR(I104/H104-1,"--") -> 0 | K105: =IFERROR(K104/I104-1,"--") -> 0 | L105: =IFERROR(L104/K104-1,"--") -> 0 | M105: =IFERROR(M104/L104-1,"--") -> 0 | N105: =IFERROR(N104/M104-1,"--") -> 0 | O105: =IFERROR(O104/J104-1,"--") -> 0 | P105: =IFERROR(P104/N104-1,"--") -> 0 | Q105: =IFERROR(Q104/P104-1,"--") -> 0 | R105: =IFERROR(R104/Q104-1,"--") -> 0 | S105: =IFERROR(S104/R104-1,"--") -> 0 | T105: =IFERROR(T104/O104-1,"--") -> 0 | U105: =IF(Case_Scenario="Bull",U106,IF(Case_Scenario="Base",U107,IF(Case_Scenario="bear",U108,"N/A"))) -> 0.05 | V105: =IF(Case_Scenario="Bull",V106,IF(Case_Scenario="Base",V107,IF(Case_Scenario="bear",V108,"N/A"))) -> 0.05 | W105: =IF(Case_Scenario="Bull",W106,IF(Case_Scenario="Base",W107,IF(Case_Scenario="bear",W108,"N/A"))) -> 0.05 | X105: =IF(Case_Scenario="Bull",X106,IF(Case_Scenario="Base",X107,IF(Case_Scenario="bear",X108,"N/A"))) -> 0.05 | Z105: =IF(Case_Scenario="Bull",Z106,IF(Case_Scenario="Base",Z107,IF(Case_Scenario="bear",Z108,"N/A"))) -> 0.05 | AA105: =IF(Case_Scenario="Bull",AA106,IF(Case_Scenario="Base",AA107,IF(Case_Scenario="bear",AA108,"N/A"))) -> 0.05 | AB105: =IF(Case_Scenario="Bull",AB106,IF(Case_Scenario="Base",AB107,IF(Case_Scenario="bear",AB108,"N/A"))) -> 0.05 | AC105: =IF(Case_Scenario="Bull",AC106,IF(Case_Scenario="Base",AC107,IF(Case_Scenario="bear",AC108,"N/A"))) -> 0.05 | AE105: =IF(Case_Scenario="Bull",AE106,IF(Case_Scenario="Base",AE107,IF(Case_Scenario="bear",AE108,"N/A"))) -> 0.05 | AF105: =IF(Case_Scenario="Bull",AF106,IF(Case_Scenario="Base",AF107,IF(Case_Scenario="bear",AF108,"N/A"))) -> 0.05 | AG105: =IF(Case_Scenario="Bull",AG106,IF(Case_Scenario="Base",AG107,IF(Case_Scenario="bear",AG108,"N/A"))) -> 0.05
C106: Bull Case | U106: 0.1 | V106: 0.1 | W106: 0.1 | X106: 0.1 | Z106: 0.1 | AA106: 0.1 | AB106: 0.1 | AC106: 0.1 | AE106: 0.1 | AF106: 0.1 | AG106: 0.1
C107: Base Case | U107: 0.05 | V107: 0.05 | W107: 0.05 | X107: 0.05 | Z107: 0.05 | AA107: 0.05 | AB107: 0.05 | AC107: 0.05 | AE107: 0.05 | AF107: 0.05 | AG107: 0.05
C108: Bear Case | U108: 0 | V108: 0 | W108: 0 | X108: 0 | Z108: 0 | AA108: 0 | AB108: 0 | AC108: 0 | AE108: 0 | AF108: 0 | AG108: 0
C109: Price | F109: =IFERROR(F103/F104,"--") -> 0.16309091 | G109: =IFERROR(G103/G104,"--") -> -0.13713636 | H109: =IFERROR(H103/H104,"--") -> -0.15641818 | I109: =IFERROR(I103/I104,"--") -> 0.51414545 | J109: =IFERROR(J103/J104,"--") -> 0.095920455 | K109: =IFERROR(K103/K104,"--") -> 0.75954545 | L109: =IFERROR(L103/L104,"--") -> 0.95436364 | M109: =IFERROR(M103/M104,"--") -> 0.62022727 | ... T109: =IFERROR(T103/T104,"--") -> 0.78222386 | U109: =S109*(1+U110) -> 0.90639341 | V109: =U109*(1+V110) -> 0.95171308 | W109: =V109*(1+W110) -> 0.99929873 | X109: =W109*(1+X110) -> 1.0492637 | Y109: =Y103/Y104 -> 0.97957086 | Z109: =X109*(1+Z110) -> 1.1017269 | AA109: =Z109*(1+AA110) -> 1.1568132 | AB109: =AA109*(1+AB110) -> 1.2146539 | AC109: =AB109*(1+AC110) -> 1.2753865 | AD109: =AD103/AD104 -> 1.1906745 | AE109: =AD109*(1+AE110) -> 1.2502082 | AF109: =AE109*(1+AF110) -> 1.3127186 | AG109: =AF109*(1+AG110) -> 1.3783546
C110: % Price Growth | G110: =IFERROR(G109/F109-1,"--") -> -1.8408584 | H110: =IFERROR(H109/G109-1,"--") -> 0.14060325 | I110: =IFERROR(I109/H109-1,"--") -> -4.2869929 | K110: =IFERROR(K109/I109-1,"--") -> 0.47729684 | L110: =IFERROR(L109/K109-1,"--") -> 0.25649312 | M110: =IFERROR(M109/L109-1,"--") -> -0.35011431 | N110: =IFERROR(N109/M109-1,"--") -> 0.80791499 | O110: =IFERROR(O109/J109-1,"--") -> 8.0060419 | P110: =IFERROR(P109/N109-1,"--") -> -0.17851149 | Q110: =IFERROR(Q109/P109-1,"--") -> -0.33245005 | R110: =IFERROR(R109/Q109-1,"--") -> 0.18650808 | S110: =IFERROR(S109/R109-1,"--") -> 0.18315765 | T110: =IFERROR(T109/O109-1,"--") -> -0.094505393 | U110: =IF(Case_Scenario="Bull",U111,IF(Case_Scenario="Base",U112,IF(Case_Scenario="bear",U113,"N/A"))) -> 0.05 | V110: =IF(Case_Scenario="Bull",V111,IF(Case_Scenario="Base",V112,IF(Case_Scenario="bear",V113,"N/A"))) -> 0.05 | W110: =IF(Case_Scenario="Bull",W111,IF(Case_Scenario="Base",W112,IF(Case_Scenario="bear",W113,"N/A"))) -> 0.05 | X110: =IF(Case_Scenario="Bull",X111,IF(Case_Scenario="Base",X112,IF(Case_Scenario="bear",X113,"N/A"))) -> 0.05 | Z110: =IF(Case_Scenario="Bull",Z111,IF(Case_Scenario="Base",Z112,IF(Case_Scenario="bear",Z113,"N/A"))) -> 0.05 | AA110: =IF(Case_Scenario="Bull",AA111,IF(Case_Scenario="Base",AA112,IF(Case_Scenario="bear",AA113,"N/A"))) -> 0.05 | AB110: =IF(Case_Scenario="Bull",AB111,IF(Case_Scenario="Base",AB112,IF(Case_Scenario="bear",AB113,"N/A"))) -> 0.05 | AC110: =IF(Case_Scenario="Bull",AC111,IF(Case_Scenario="Base",AC112,IF(Case_Scenario="bear",AC113,"N/A"))) -> 0.05 | AE110: =IF(Case_Scenario="Bull",AE111,IF(Case_Scenario="Base",AE112,IF(Case_Scenario="bear",AE113,"N/A"))) -> 0.05 | AF110: =IF(Case_Scenario="Bull",AF111,IF(Case_Scenario="Base",AF112,IF(Case_Scenario="bear",AF113,"N/A"))) -> 0.05 | AG110: =IF(Case_Scenario="Bull",AG111,IF(Case_Scenario="Base",AG112,IF(Case_Scenario="bear",AG113,"N/A"))) -> 0.05
C111: Bull Case | U111: 0.1 | V111: 0.1 | W111: 0.1 | X111: 0.1 | Z111: 0.1 | AA111: 0.1 | AB111: 0.1 | AC111: 0.1 | AE111: 0.1 | AF111: 0.1 | AG111: 0.1
C112: Base Case | U112: 0.05 | V112: 0.05 | W112: 0.05 | X112: 0.05 | Z112: 0.05 | AA112: 0.05 | AB112: 0.05 | AC112: 0.05 | AE112: 0.05 | AF112: 0.05 | AG112: 0.05
C113: Bear Case | U113: 0 | V113: 0 | W113: 0 | X113: 0 | Z113: 0 | AA113: 0 | AB113: 0 | AC113: 0 | AE113: 0 | AF113: 0 | AG113: 0
A115: x | C115: =C38 -> Revenue | F115: =F38 -> 0 | G115: =G38 -> 0 | H115: =H38 -> 0 | I115: =I38 -> 0 | J115: =J38 -> 0 | K115: =K38 -> 0 | L115: =L38 -> 0 | M115: =M38 -> 0 | ... T115: =T38 -> 0 | U115: =U116*U121 -> 0 | V115: =V116*V121 -> 0 | W115: =W116*W121 -> 0 | X115: =X116*X121 -> 0 | Y115: =SUM(U115:X115) -> 0 | Z115: =Z116*Z121 -> 0 | AA115: =AA116*AA121 -> 0 | AB115: =AB116*AB121 -> 0 | AC115: =AC116*AC121 -> 0 | AD115: =SUM(Z115:AC115) -> 0 | AE115: =AE116*AE121 -> 0 | AF115: =AF116*AF121 -> 0 | AG115: =AG116*AG121 -> 0
C116: Volume | F116: 220 | G116: 220 | H116: 220 | I116: 220 | J116: =SUM(F116:I116) -> 880 | K116: 220 | L116: 220 | M116: 220 | N116: 220 | O116: =SUM(K116:N116) -> 880 | P116: 220 | Q116: 220 | R116: 220 | S116: 220 | T116: =SUM(P116:S116) -> 880 | U116: =S116*(1+U117) -> 231 | V116: =U116*(1+V117) -> 242.55 | W116: =V116*(1+W117) -> 254.6775 | X116: =W116*(1+X117) -> 267.41138 | Y116: =SUM(U116:X116) -> 995.63887 | Z116: =X116*(1+Z117) -> 280.78194 | AA116: =Z116*(1+AA117) -> 294.82104 | AB116: =AA116*(1+AB117) -> 309.56209 | AC116: =AB116*(1+AC117) -> 325.0402 | AD116: =SUM(Z116:AC116) -> 1210.2053 | AE116: =AD116*(1+AE117) -> 1270.7155 | AF116: =AE116*(1+AF117) -> 1334.2513 | AG116: =AF116*(1+AG117) -> 1400.9639
...

Sheet Model
C1: =Company_Name&" - "&MID(CELL("filename",A1),FIND("]",CELL("filename",A1))+1,255)&": "&Case_Scenario&" Case" -> Jefferies Financial Group Inc. - Model: Base Case
C2: =Cover!C2 -> $ in Millions Except Per Share Data
C4: Font Toggle
C5: Report
C7: Interest Expense Toggle
C8: On
A10: x | C10: Shortcuts
C11: =$C$25 -> Income Statement
C12: =$C$73 -> Cash Flow Statement
C13: =$C$118 -> Balance Sheet
C14: =$C$161 -> Working Capital Schedule
C15: =$C$193 -> PP&E / Depreciation Schedule
C16: =$C$207 -> Amortization Schedule
C17: =$C$219 -> Other Long-Term Items Schedule
C18: =$C$237 -> Shareholder's Equity Schedule
C19: =$C$278 -> Shares Outstanding Schedule
C20: =$C$289 -> Debt and Interest Schedule
J23: 1 | O23: 2 | T23: 3 | Y23: 4 | AD23: 5 | AE23: 6 | AF23: 7 | AG23: 8
F24: =G24 -> 2023 | G24: =H24 -> 2023 | H24: =I24 -> 2023 | I24: =J24 -> 2023 | J24: =O24-1 -> 2023 | K24: =L24 -> 2024 | L24: =M24 -> 2024 | M24: =N24 -> 2024 | N24: =O24 -> 2024 | O24: =T24-1 -> 2024 | P24: =Q24 -> 2025 | Q24: =R24 -> 2025 | R24: =S24 -> 2025 | S24: =T24 -> 2025 | T24: =YEAR(Last_FYE) -> 2025 | U24: =V24 -> 2026 | V24: =W24 -> 2026 | W24: =X24 -> 2026 | X24: =Y24 -> 2026 | Y24: =T24+1 -> 2026 | Z24: =AA24 -> 2027 | AA24: =AB24 -> 2027 | AB24: =AC24 -> 2027 | AC24: =AD24 -> 2027 | AD24: =Y24+1 -> 2027 | AE24: =AD24+1 -> 2028 | AF24: =AE24+1 -> 2029 | AG24: =AF24+1 -> 2030
A25: x | C25: Income Statement | F25: ="1Q"&RIGHT(F24,2) -> 1Q23 | G25: ="2Q"&RIGHT(G24,2) -> 2Q23 | H25: ="3Q"&RIGHT(H24,2) -> 3Q23 | I25: ="4Q"&RIGHT(I24,2) -> 4Q23 | J25: =J24 -> 2023 | K25: ="1Q"&RIGHT(K24,2) -> 1Q24 | L25: ="2Q"&RIGHT(L24,2) -> 2Q24 | M25: ="3Q"&RIGHT(M24,2) -> 3Q24 | N25: ="4Q"&RIGHT(N24,2) -> 4Q24 | O25: =O24 -> 2024 | P25: ="1Q"&RIGHT(P24,2) -> 1Q25 | Q25: ="2Q"&RIGHT(Q24,2) -> 2Q25 | R25: ="3Q"&RIGHT(R24,2) -> 3Q25 | S25: ="4Q"&RIGHT(S24,2) -> 4Q25 | T25: =T24 -> 2025 | U25: =IF(Last_FQR="4Q","1Q"&RIGHT(U24,2)&"e","1Q"&RIGHT(U24,2)) -> 1Q26e | V25: =IF(Last_FQR="4Q","2Q"&RIGHT(W24,2)&"e",IF(Last_FQR="1Q","2Q"&RIGHT(W24,2)&"e","2Q"&RIGHT(W24,2))) -> 2Q26e | W25: ="3Q"&RIGHT(W24,2) -> 3Q26 | X25: ="4Q"&RIGHT(U24,2)&"e" -> 4Q26e | Y25: =Y24&"e" -> 2026e | Z25: ="1Q"&RIGHT(Z24,2)&"e" -> 1Q27e | AA25: ="2Q"&RIGHT(AA24,2)&"e" -> 2Q27e | AB25: ="3Q"&RIGHT(AB24,2)&"e" -> 3Q27e | AC25: ="4Q"&RIGHT(AC24,2)&"e" -> 4Q27e | AD25: =AD24&"e" -> 2027e | AE25: =AE24&"e" -> 2028e | AF25: =AF24&"e" -> 2029e | AG25: =AG24&"e" -> 2030e | AH25: x
C26: Days In Period | F26: 90 | G26: 91 | H26: 92 | I26: 92 | J26: =SUM(F26:I26) -> 365 | K26: 90 | L26: 91 | M26: 92 | N26: 92 | O26: =SUM(K26:N26) -> 365 | P26: 90 | Q26: 91 | R26: 92 | S26: 92 | T26: =SUM(P26:S26) -> 365 | U26: 90 | V26: 91 | W26: 92 | X26: 92 | Y26: =SUM(U26:X26) -> 365 | Z26: 91 | AA26: 91 | AB26: 92 | AC26: 92 | AD26: =SUM(Z26:AC26) -> 366 | AE26: 365 | AF26: 365 | AG26: 365
C28: Revenue | F28: ='Segment Analysis'!F7 -> 1780.56 | G28: ='Segment Analysis'!G7 -> 1651.242 | H28: ='Segment Analysis'!H7 -> 2040.888 | I28: ='Segment Analysis'!I7 -> 1968.69 | J28: =SUM(F28:I28) -> 7441.38 | K28: ='Segment Analysis'!K7 -> 2551.9 | L28: ='Segment Analysis'!L7 -> 2516.23 | M28: ='Segment Analysis'!M7 -> 2595.48 | N28: ='Segment Analysis'!N7 -> 2851.459 | O28: =SUM(K28:N28) -> 10515.069 | P28: ='Segment Analysis'!P7 -> 2472.864 | Q28: ='Segment Analysis'!Q7 -> 2494.315 | R28: ='Segment Analysis'!R7 -> 2907.674 | S28: ='Segment Analysis'!S7 -> 2948.824 | T28: =SUM(P28:S28) -> 10823.677 | U28: ='Segment Analysis'!U7 -> 2742.8525 | V28: ='Segment Analysis'!V7 -> 2804.4553 | W28: ='Segment Analysis'!W7 -> 3225.2028 | X28: ='Segment Analysis'!X7 -> 3219.018 | Y28: =SUM(U28:X28) -> 11991.529 | Z28: ='Segment Analysis'!Z7 -> 2948.7114 | AA28: ='Segment Analysis'!AA7 -> 3086.9714 | AB28: ='Segment Analysis'!AB7 -> 3511.4181 | AC28: ='Segment Analysis'!AC7 -> 3473.729 | AD28: =SUM(Z28:AC28) -> 13020.83 | AE28: ='Segment Analysis'!AE7 -> 13894.991 | AF28: ='Segment Analysis'!AF7 -> 14550.917 | AG28: ='Segment Analysis'!AG7 -> 14977.126
C29: Interest Expense | F29: -823 | G29: -840 | H29: -806 | I29: -713 | J29: =SUM(F29:I29) -> -2740.982 | K29: -644 | L29: -859.851 | M29: -912.037 | N29: -894.639 | O29: =SUM(K29:N29) -> -3480.266 | P29: -879.845 | Q29: -859.868 | R29: -860.242 | S29: -879.971 | T29: =SUM(P29:S29) -> -3479.926 | U29: =U323 -> -841.09678 | V29: =V323 -> -894.899 | W29: =W323 -> -949.95123 | X29: =X323 -> -922.399 | Y29: =SUM(U29:X29) -> -3608.346 | Z29: =Z323 -> -881.68215 | AA29: =AA323 -> -894.63215 | AB29: =AB323 -> -907.58215 | AC29: =AC323 -> -920.53215 | AD29: =SUM(Z29:AC29) -> -3604.4286 | AE29: =AE325 -> -3915.6371 | AF29: =AF325 -> -4230.6371 | AG29: =AG325 -> -4545.6371
C30: Net Revenue | F30: =SUM(F28:F29) -> 1283.488 | G30: =SUM(G28:G29) -> 1037.67 | H30: =SUM(H28:H29) -> 1182.082 | I30: =SUM(I28:I29) -> 1197.158 | J30: =SUM(F30:I30) -> 4700.398 | K30: =SUM(K28:K29) -> 1738.161 | L30: =SUM(L28:L29) -> 1656.379 | M30: =SUM(M28:M29) -> 1683.443 | N30: =SUM(N28:N29) -> 1956.82 | O30: =SUM(K30:N30) -> 7034.803 | P30: =SUM(P28:P29) -> 1593.019 | Q30: =SUM(Q28:Q29) -> 1634.447 | R30: =SUM(R28:R29) -> 2047.432 | S30: =SUM(S28:S29) -> 2068.853 | T30: =SUM(P30:S30) -> 7343.751 | U30: =IF(Cover!$F$37="Bottom Up",(U36-SUM(U32:U33,U35)),U28+U29) -> 1901.7557 | V30: =IF(Cover!$F$37="Bottom Up",(V36-SUM(V32:V33,V35)),V28+V29) -> 1909.5563 | W30: =IF(Cover!$F$37="Bottom Up",(W36-SUM(W32:W33,W35)),W28+W29) -> 2275.2515 | X30: =IF(Cover!$F$37="Bottom Up",(X36-SUM(X32:X33,X35)),X28+X29) -> 2296.619 | Y30: =SUM(U30:X30) -> 8383.1825 | Z30: =IF(Cover!$F$37="Bottom Up",(Z36-SUM(Z32:Z33,Z35)),Z28+Z29) -> 2067.0293 | AA30: =IF(Cover!$F$37="Bottom Up",(AA36-SUM(AA32:AA33,AA35)),AA28+AA29) -> 2192.3393 | AB30: =IF(Cover!$F$37="Bottom Up",(AB36-SUM(AB32:AB33,AB35)),AB28+AB29) -> 2603.8359 | AC30: =IF(Cover!$F$37="Bottom Up",(AC36-SUM(AC32:AC33,AC35)),AC28+AC29) -> 2553.1968 | AD30: =SUM(Z30:AC30) -> 9416.4013 | AE30: =IF(Cover!$F$37="Bottom Up",(AE36-SUM(AE32:AE33,AE35)),AE28+AE29) -> 17136.804 | AF30: =IF(Cover!$F$37="Bottom Up",(AF36-SUM(AF32:AF33,AF35)),AF28+AF29) -> 17477.729 | AG30: =IF(Cover!$F$37="Bottom Up",(AG36-SUM(AG32:AG33,AG35)),AG28+AG29) -> 17588.938
C32: Compensation, Commissions, and Benefits | F32: -703.058 | G32: -575.868 | H32: -644.059 | I32: -612.287 | J32: =SUM(F32:I32) -> -2535.272 | K32: -926.871 | L32: -861.993 | M32: -889.098 | N32: -981.626 | O32: =SUM(K32:N32) -> -3659.588 | P32: -841.127 | Q32: -854.839 | R32: -1083.51 | S32: -1080.779 | T32: =SUM(P32:S32) -> -3860.255 | U32: =U67*U$30 -> -988.91298 | V32: =V67*V$30 -> -1002.517 | W32: =W67*W$30 -> -1194.507 | X32: =X67*X$30 -> -1182.7588 | Y32: =SUM(U32:X32) -> -4368.6958 | Z32: =Z67*Z$30 -> -1069.6876 | AA32: =AA67*AA$30 -> -1129.0547 | AB32: =AB67*AB$30 -> -1314.9371 | AC32: =AC67*AC$30 -> -1263.8324 | AD32: =SUM(Z32:AC32) -> -4777.5119 | AE32: =AE67*AE$30 -> -8799.7487 | AF32: =AF67*AF$30 -> -8931.1198 | AG32: =AG67*AG$30 -> -9058.3033
C33: Non-Compensation Expenses | F33: -333.38 | G33: -365.193 | H33: -362.757 | I33: -434.774 | J33: =SUM(F33:I33) -> -1496.104 | K33: -429.314 | L33: -437.776 | M33: -414.949 | N33: -515.156 | O33: =SUM(K33:N33) -> -1797.195 | P33: -441.713 | Q33: -479.017 | R33: -483.903 | S33: -597.216 | T33: =SUM(P33:S33) -> -2001.849 | U33: =U68*U$30 -> -451.66699 | V33: =V68*V$30 -> -458.29351 | W33: =W68*W$30 -> -546.06036 | X33: =X68*X$30 -> -574.15474 | Y33: =SUM(U33:X33) -> -2030.1756 | Z33: =Z68*Z$30 -> -496.08702 | AA33: =AA68*AA$30 -> -515.19972 | AB33: =AB68*AB$30 -> -598.88226 | AC33: =AC68*AC$30 -> -574.46929 | AD33: =SUM(Z33:AC33) -> -2184.6383 | AE33: =AE68*AE$30 -> -4027.1489 | AF33: =AF68*AF$30 -> -4107.2664 | AG33: =AG68*AG$30 -> -4221.3452
C34: Depreciation & Amortization | F34: -11123 | G34: -11589 | H34: -12131 | I34: -1135 | J34: =SUM(F34:I34) -> -112.201 | K34: -11684 | L34: -12038 | M34: -13442 | N34: -1811 | O34: =SUM(K34:N34) -> -190.326 | P34: -14262 | Q34: -15227 | R34: -16796 | S34: -3840 | T34: =SUM(P34:S34) -> -192.281 | U34: =U76 -> -45.184537 | V34: =V76 -> -45.956307 | W34: =W76 -> -46.099245 | X34: =X76 -> -46.954591 | Y34: =SUM(U34:X34) -> -184.19468 | Z34: =Z76 -> -45.341201 | AA34: =AA76 -> -46.007409 | AB34: =AB76 -> -45.996488 | AC34: =AC76 -> -45.75119 | AD34: =SUM(Z34:AC34) -> -183.09629 | AE34: =AE76 -> -182.07061 | AF34: =AF76 -> -178.19654 | AG34: =AG76 -> -169.96235
C35: Other Operating Income (Expense) | F35: -67791 | G35: -69373 | H35: -75022 | I35: -92553 | J35: =SUM(F35:I35) -> -243.824 | K35: -72633 | L35: -73785 | M35: -80977 | N35: -98893 | O35: =SUM(K35:N35) -> -433.201 | P35: -76976 | Q35: -80809 | R35: -88670 | S35: -109959 | T35: =SUM(P35:S35) -> -471.08 | U35: =U69*U$28 -> -123.42836 | V35: =V69*V$28 -> -98.155935 | W35: =W69*W$28 -> -129.00811 | X35: =X69*X$28 -> -136.80826 | Y35: =SUM(U35:X35) -> -487.40067 | Z35: =Z69*Z$28 -> -132.69201 | AA35: =AA69*AA$28 -> -138.91371 | AB35: =AB69*AB$28 -> -158.01381 | AC35: =AC69*AC$28 -> -156.3178 | AD35: =SUM(Z35:AC35) -> -585.93734 | AE35: =AE69*AE$28 -> -694.74954 | AF35: =AF69*AF$28 -> -727.54583 | AG35: =AG69*AG$28 -> -748.85628
C36: EBIT | F36: =IF($C$34="Depreciation & Amortization (incl. in SG&A)",F30+SUM(F32:F33,F35),F30+SUM(F32:F35)) -> 158.014 | G36: =IF($C$34="Depreciation & Amortization (incl. in SG&A)",G30+SUM(G32:G33,G35),G30+SUM(G32:G35)) -> 17.979 | H36: =IF($C$34="Depreciation & Amortization (incl. in SG&A)",H30+SUM(H32:H33,H35),H30+SUM(H32:H35)) -> 91.044 | I36: =IF($C$34="Depreciation & Amortization (incl. in SG&A)",I30+SUM(I32:I33,I35),I30+SUM(I32:I35)) -> 45.96 | J36: =SUM(F36:I36) -> 312.997 | K36: =IF($C$34="Depreciation & Amortization (incl. in SG&A)",K30+SUM(K32:K33,K35),K30+SUM(K32:K35)) -> 220.2 | L36: =IF($C$34="Depreciation & Amortization (incl. in SG&A)",L30+SUM(L32:L33,L35),L30+SUM(L32:L35)) -> 227.688 | M36: =IF($C$34="Depreciation & Amortization (incl. in SG&A)",M30+SUM(M32:M33,M35),M30+SUM(M32:M35)) -> 252.578 | N36: =IF($C$34="Depreciation & Amortization (incl. in SG&A)",N30+SUM(N32:N33,N35),N30+SUM(N32:N35)) -> 254.027 | O36: =SUM(K36:N36) -> 954.493 | P36: =IF($C$34="Depreciation & Amortization (incl. in SG&A)",P30+SUM(P32:P33,P35),P30+SUM(P32:P35)) -> 151.065 | Q36: =IF($C$34="Depreciation & Amortization (incl. in SG&A)",Q30+SUM(Q32:Q33,Q35),Q30+SUM(Q32:Q35)) -> 134.901 | R36: =IF($C$34="Depreciation & Amortization (incl. in SG&A)",R30+SUM(R32:R33,R35),R30+SUM(R32:R35)) -> 331.815 | S36: =IF($C$34="Depreciation & Amortization (incl. in SG&A)",S30+SUM(S32:S33,S35),S30+SUM(S32:S35)) -> 200.505 | T36: =SUM(P36:S36) -> 818.286 | U36: =IF(Cover!$F$37="Bottom Up",'Segment Analysis'!U33,IF($C$34="Depreciation & Amortization (incl. in SG&A)",U30+SUM(U32:U33,U35),U30+SUM(U32:U35))) -> 292.56286 | V36: =IF(Cover!$F$37="Bottom Up",'Segment Analysis'!V33,IF($C$34="Depreciation & Amortization (incl. in SG&A)",V30+SUM(V32:V33,V35),V30+SUM(V32:V35))) -> 304.63348 | W36: =IF(Cover!$F$37="Bottom Up",'Segment Analysis'!W33,IF($C$34="Depreciation & Amortization (incl. in SG&A)",W30+SUM(W32:W33,W35),W30+SUM(W32:W35))) -> 359.57675 | X36: =IF(Cover!$F$37="Bottom Up",'Segment Analysis'!X33,IF($C$34="Depreciation & Amortization (incl. in SG&A)",X30+SUM(X32:X33,X35),X30+SUM(X32:X35))) -> 355.9426 | Y36: =SUM(U36:X36) -> 1312.7157 | Z36: =IF(Cover!$F$37="Bottom Up",'Segment Analysis'!Z33,IF($C$34="Depreciation & Amortization (incl. in SG&A)",Z30+SUM(Z32:Z33,Z35),Z30+SUM(Z32:Z35))) -> 323.22138 | AA36: =IF(Cover!$F$37="Bottom Up",'Segment Analysis'!AA33,IF($C$34="Depreciation & Amortization (incl. in SG&A)",AA30+SUM(AA32:AA33,AA35),AA30+SUM(AA32:AA35))) -> 363.16369 | AB36: =IF(Cover!$F$37="Bottom Up",'Segment Analysis'!AB33,IF($C$34="Depreciation & Amortization (incl. in SG&A)",AB30+SUM(AB32:AB33,AB35),AB30+SUM(AB32:AB35))) -> 486.00622 | AC36: =IF(Cover!$F$37="Bottom Up",'Segment Analysis'!AC33,IF($C$34="Depreciation & Amortization (incl. in SG&A)",AC30+SUM(AC32:AC33,AC35),AC30+SUM(AC32:AC35))) -> 512.82612 | AD36: =SUM(Z36:AC36) -> 1685.2174 | AE36: =IF(Cover!$F$37="Bottom Up",'Segment Analysis'!AE33,IF($C$34="Depreciation & Amortization (incl. in SG&A)",AE30+SUM(AE32:AE33,AE35),AE30+SUM(AE32:AE35))) -> 3110.8208 | AF36: =IF(Cover!$F$37="Bottom Up",'Segment Analysis'!AF33,IF($C$34="Depreciation & Amortization (incl. in SG&A)",AF30+SUM(AF32:AF33,AF35),AF30+SUM(AF32:AF35))) -> 3232.3522 | AG36: =IF(Cover!$F$37="Bottom Up",'Segment Analysis'!AG33,IF($C$34="Depreciation & Amortization (incl. in SG&A)",AG30+SUM(AG32:AG33,AG35),AG30+SUM(AG32:AG35))) -> 3112.2301
C38: Interest Income | F38: 0 | G38: 0 | H38: 0 | I38: 0 | J38: =SUM(F38:I38) -> 0 | K38: 0 | L38: 0 | M38: 0 | N38: 0 | O38: =SUM(K38:N38) -> 0 | P38: 0 | Q38: 0 | R38: 0 | S38: 0 | T38: =SUM(P38:S38) -> 0 | U38: =U332 -> 0 | V38: =V332 -> 0 | W38: =W332 -> 0 | X38: =X332 -> 0 | Y38: =SUM(U38:X38) -> 0 | Z38: =Z332 -> 0 | AA38: =AA332 -> 0 | AB38: =AB332 -> 0 | AC38: =AC332 -> 0 | AD38: =SUM(Z38:AC38) -> 0 | AE38: =AE332 -> 0 | AF38: =AF332 -> 0 | AG38: =AG332 -> 0
C39: Interest (Expense) | F39: 0 | G39: 0 | H39: 0 | I39: 0 | J39: =SUM(F39:I39) -> 0 | K39: 0 | L39: 0 | M39: 0 | N39: 0 | O39: =SUM(K39:N39) -> 0 | P39: 0 | Q39: 0 | R39: 0 | S39: 0 | T39: =SUM(P39:S39) -> 0 | U39: 0 | V39: 0 | W39: 0 | X39: 0 | Y39: =SUM(U39:X39) -> 0 | Z39: 0 | AA39: 0 | AB39: 0 | AC39: 0 | AD39: 0 | AE39: 0 | AF39: 0 | AG39: 0
C40: Goodwill Impairment | F40: 0 | G40: 0 | H40: 0 | I40: 0 | J40: =SUM(F40:I40) -> 0 | K40: 0 | L40: 0 | M40: 0 | N40: 0 | O40: =SUM(K40:N40) -> 0 | P40: 0 | Q40: 0 | R40: 0 | S40: 0 | T40: =SUM(P40:S40) -> 0 | U40: =Drivers!U62 -> 0 | V40: =Drivers!V62 -> 0 | W40: =Drivers!W62 -> 0 | X40: =Drivers!X62 -> 0 | Y40: =SUM(U40:X40) -> 0 | Z40: =Drivers!Z62 -> 0 | AA40: =Drivers!AA62 -> 0 | AB40: =Drivers!AB62 -> 0 | AC40: =Drivers!AC62 -> 0 | AD40: =SUM(Z40:AC40) -> 0 | AE40: =Drivers!AE62 -> 0 | AF40: =Drivers!AF62 -> 0 | AG40: =Drivers!AG62 -> 0
C41: Other Non-Operating Income (Expense) | F41: -443 | G41: 61 | H41: 1031 | I41: 289 | J41: =SUM(F41:I41) -> 0 | K41: -2673 | L41: -18 | M41: -27 | N41: 468 | O41: =SUM(K41:N41) -> 0 | P41: 2749 | Q41: 1117 | R41: 10186 | S41: 1177 | T41: =SUM(P41:S41) -> 0 | U41: =U70*U28 -> 0 | V41: =V70*V28 -> 0 | W41: =W70*W28 -> 0 | X41: =X70*X28 -> 0 | Y41: =SUM(U41:X41) -> 0 | Z41: =Z70*Z28 -> 0 | AA41: =AA70*AA28 -> 0 | AB41: =AB70*AB28 -> 0 | AC41: =AC70*AC28 -> 0 | AD41: =SUM(Z41:AC41) -> 0 | AE41: =AE70*AE28 -> 0 | AF41: =AF70*AF28 -> 0 | AG41: =AG70*AG28 -> 0
C42: Pre-Tax Income (Loss) | F42: =F36+SUM(F38:F41) -> 158.014 | G42: =G36+SUM(G38:G41) -> 17.979 | H42: =H36+SUM(H38:H41) -> 91.044 | I42: =I36+SUM(I38:I41) -> 45.96 | J42: =SUM(F42:I42) -> 312.997 | K42: =K36+SUM(K38:K41) -> 220.2 | L42: =L36+SUM(L38:L41) -> 227.688 | M42: =IF($C$8="On",M36+SUM(M38:M41),IF($C$8="off",M36+SUM(M40:M41),"N/A")) -> 252.578 | N42: =IF($C$8="On",N36+SUM(N38:N41),IF($C$8="off",N36+SUM(N40:N41),"N/A")) -> 254.027 | O42: =SUM(K42:N42) -> 954.493 | P42: =P36+SUM(P38:P41) -> 151.065 | Q42: =Q36+SUM(Q38:Q41) -> 134.901 | R42: =IF($C$8="On",R36+SUM(R38:R41),IF($C$8="off",R36+SUM(R40:R41),"N/A")) -> 331.815 | S42: =IF($C$8="On",S36+SUM(S38:S41),IF($C$8="off",S36+SUM(S40:S41),"N/A")) -> 200.505 | T42: =SUM(P42:S42) -> 818.286 | U42: =IF($C$8="On",U36+SUM(U38:U41),IF($C$8="off",U36+SUM(U40:U41),"N/A")) -> 542.27001 | V42: =IF($C$8="On",V36+SUM(V38:V41),IF($C$8="off",V36+SUM(V40:V41),"N/A")) -> 618.39265 | W42: =IF($C$8="On",W36+SUM(W38:W41),IF($C$8="off",W36+SUM(W40:W41),"N/A")) -> 749.41794 | X42: =IF($C$8="On",X36+SUM(X38:X41),IF($C$8="off",X36+SUM(X40:X41),"N/A")) -> 808.56306 | Y42: =SUM(U42:X42) -> 2718.6437 | Z42: =IF($C$8="On",Z36+SUM(Z38:Z41),IF($C$8="off",Z36+SUM(Z40:Z41),"N/A")) -> 577.00453 | AA42: =IF($C$8="On",AA36+SUM(AA38:AA41),IF($C$8="off",AA36+SUM(AA40:AA41),"N/A")) -> 689.03143 | AB42: =IF($C$8="On",AB36+SUM(AB38:AB41),IF($C$8="off",AB36+SUM(AB40:AB41),"N/A")) -> 930.06315 | AC42: =IF($C$8="On",AC36+SUM(AC38:AC41),IF($C$8="off",AC36+SUM(AC40:AC41),"N/A")) -> 1069.3048 | AD42: =SUM(Z42:AC42) -> 3265.4039 | AE42: =IF($C$8="On",AE36+SUM(AE38:AE41),IF($C$8="off",AE36+SUM(AE40:AE41),"N/A")) -> 3110.8208 | AF42: =IF($C$8="On",AF36+SUM(AF38:AF41),IF($C$8="off",AF36+SUM(AF40:AF41),"N/A")) -> 3232.3522 | AG42: =IF($C$8="On",AG36+SUM(AG38:AG41),IF($C$8="off",AG36+SUM(AG40:AG41),"N/A")) -> 3112.2301
C44: Income Tax Benefit (Expense) | F44: -948 | G44: -804 | H44: -2306 | I44: =(-91.88-SUM(F44:H44)) -> -16.827 | J44: =SUM(F44:I44) -> -91.88 | K44: -2467 | L44: -1767 | M44: -2706 | N44: =(-293.194-SUM(K44:M44)) -> -86.117 | O44: =SUM(K44:N44) -> -293.194 | P44: -4553 | Q44: -2678 | R44: -6910 | S44: =+-184.57-SUM(P44:R44) -> -37.537 | T44: =SUM(P44:S44) -> -184.57 | U44: =-U71*U42 -> -117.67259 | V44: =-V71*V42 -> -158.92691 | W44: =-W71*W42 -> -192.60041 | X44: =-X71*X42 -> -207.80071 | Y44: =SUM(U44:X44) -> -677.00062 | Z44: =-Z71*Z42 -> -147.13616 | AA44: =-AA71*AA42 -> -175.70301 | AB44: =-AB71*AB42 -> -237.1661 | AC44: =-AC71*AC42 -> -272.67272 | AD44: =SUM(Z44:AC44) -> -832.67799 | AE44: =-AE71*AE42 -> -777.7052 | AF44: =-AF71*AF42 -> -808.08805 | AG44: =-AG71*AG42 -> -778.05753
C45: Net Income (Loss) | F45: =F42+F44 -> 129.32 | G45: =G42+G44 -> 8.744 | H45: =H42+H44 -> 53.92 | I45: =I42+I44 -> 29.133 | J45: =SUM(F45:I45) -> 221.117 | K45: =K42+K44 -> 164.241 | L45: =L42+L44 -> 154.581 | M45: =M42+M44 -> 174.567 | N45: =N42+N44 -> 167.91 | O45: =SUM(K45:N45) -> 661.299 | P45: =P42+P44 -> 136.849 | Q45: =Q42+Q44 -> 91.395 | R45: =R42+R44 -> 242.504 | S45: =S42+S44 -> 162.968 | T45: =SUM(P45:S45) -> 633.716 | U45: =U42+U44 -> 424.59742 | V45: =V42+V44 -> 459.46574 | W45: =W42+W44 -> 556.81753 | X45: =X42+X44 -> 600.76235 | Y45: =SUM(U45:X45) -> 2041.643 | Z45: =Z42+Z44 -> 429.86838 | AA45: =AA42+AA44 -> 513.32841 | AB45: =AB42+AB44 -> 692.89705 | AC45: =AC42+AC44 -> 796.63206 | AD45: =SUM(Z45:AC45) -> 2432.7259 | AE45: =AE42+AE44 -> 2333.1156 | AF45: =AF42+AF44 -> 2424.2642 | AG45: =AG42+AG44 -> 2334.1726
C47: Pre-Tax Adjustments | F47: 0 | G47: 0 | H47: 0 | I47: 0 | J47: =SUM(F47:I47) -> 0 | K47: 0 | L47: 0 | M47: 0 | N47: 0 | O47: =SUM(K47:N47) -> 0 | P47: 0 | Q47: 0 | R47: 0 | S47: 0 | T47: =SUM(P47:S47) -> 0 | U47: 0 | V47: 0 | W47: 0 | X47: 0 | Y47: =SUM(U47:X47) -> 0 | Z47: 0 | AA47: 0 | AB47: 0 | AC47: 0 | AD47: =SUM(Z47:AC47) -> 0 | AE47: 0 | AF47: 0 | AG47: 0
C48: Post-Tax Adjustments | F48: -2.016 | G48: -2.016 | H48: -6.3 | I48: =(-14.616-SUM(F48:H48)) -> -4.284 | J48: =SUM(F48:I48) -> -14.616 | K48: -14.189 | L48: -13.741 | M48: -20.785 | N48: =(-74.11-SUM(K48:M48)) -> -25.395 | O48: =SUM(K48:N48) -> -74.11 | P48: -16.039 | Q48: -11.046 | R48: -28.559 | S48: =+-79.684-SUM(P48:R48) -> -24.04 | T48: =SUM(P48:S48) -> -79.684 | U48: -20 | V48: -20 | W48: -20 | X48: -40 | Y48: =SUM(U48:X48) -> -100 | Z48: -20 | AA48: -20 | AB48: -20 | AC48: -20 | AD48: =SUM(Z48:AC48) -> -80 | AE48: -100 | AF48: -100 | AG48: -100
C49: Discontinued Operations | F49: 0 | G49: 0 | H49: 0 | I49: 0 | J49: =SUM(F49:I49) -> 0 | K49: 0 | L49: 0 | M49: 0 | N49: 0 | O49: =SUM(K49:N49) -> 3.667 | P49: 0 | Q49: 0 | R49: 0 | S49: -4.374 | T49: =SUM(P49:S49) -> -4.374 | U49: 0 | V49: 0 | W49: 0 | X49: 0 | Y49: =SUM(U49:X49) -> 0 | Z49: 0 | AA49: 0 | AB49: 0 | AC49: 0 | AD49: =SUM(Z49:AC49) -> 0 | AE49: 0 | AF49: 0 | AG49: 0
C50: Income (Loss) due to Non-Controlling Interest | F50: 6.311 | G50: 3.711 | H50: 4.226 | I50: =(15.3-SUM(F50:H50)) -> 1.052 | J50: =SUM(F50:I50) -> 15.3 | K50: 7.438 | L50: 4.79 | M50: 6.874 | N50: =(31.031-SUM(K50:M50)) -> 11.929 | O50: =SUM(K50:N50) -> 31.031 | P50: 6.983 | Q50: 7.668 | R50: 10.041 | S50: =28.43-SUM(P50:R50) -> 3.738 | T50: =SUM(P50:S50) -> 28.43 | U50: 0 | V50: 0 | W50: 0 | X50: 0 | Y50: =SUM(U50:X50) -> 0 | Z50: 0 | AA50: 0 | AB50: 0 | AC50: 0 | AD50: =SUM(Z50:AC50) -> 0 | AE50: 0 | AF50: 0 | AG50: 0
C51: Net Income Available to Common Shareholders | F51: =SUM(F45:F50) -> 133.615 | G51: =SUM(G45:G50) -> 10.439 | H51: =SUM(H45:H50) -> 51.846 | I51: =SUM(I45:I50) -> 25.901 | J51: =SUM(F51:I51) -> 221.801 | K51: =SUM(K45:K50) -> 149.599 | L51: =SUM(L45:L50) -> 145.67 | M51: =SUM(M45:M50) -> 167.019 | N51: =SUM(N45:N50) -> 159.599 | O51: =SUM(K51:N51) -> 621.887 | P51: =SUM(P45:P50) -> 127.793 | Q51: =SUM(Q45:Q50) -> 88.017 | R51: =SUM(R45:R50) -> 223.986 | S51: =SUM(S45:S50) -> 138.292 | T51: =SUM(P51:S51) -> 578.088 | U51: =SUM(U45:U50) -> 404.59742 | V51: =SUM(V45:V50) -> 439.46574 | W51: =SUM(W45:W50) -> 536.81753 | X51: =SUM(X45:X50) -> 560.76235 | Y51: =SUM(U51:X51) -> 1941.643 | Z51: =SUM(Z45:Z50) -> 409.86838 | AA51: =SUM(AA45:AA50) -> 493.32841 | AB51: =SUM(AB45:AB50) -> 672.89705 | AC51: =SUM(AC45:AC50) -> 776.63206 | AD51: =SUM(Z51:AC51) -> 2352.7259 | AE51: =SUM(AE45:AE50) -> 2233.1156 | AF51: =SUM(AF45:AF50) -> 2324.2642 | AG51: =SUM(AG45:AG50) -> 2234.1726
C53: GAAP EPS (Basic) | F53: =(F45)/F285 -> 0.5408593 | G53: =(G45)/G285 -> 0.036047624 | H53: =(H45)/H285 -> 0.23612565 | I53: =(I45)/I285 -> 0.12524451 | J53: =J45/J285 -> 0.94393597 | K53: =(K45)/K285 -> 0.74639394 | L53: =(L45)/L285 -> 0.70273354 | M53: =(M45)/M285 -> 0.81401432 | N53: =(N45)/N285 -> 0.77349721 | O53: =O45/O285 -> 3.0544988 | P53: =(P45)/P285 -> 0.63788362 | Q53: =(Q45)/Q285 -> 0.42490132 | R53: =(R45)/R285 -> 1.1263905 | S53: =(S45)/S285 -> 0.7576524 | T53: =T45/T285 -> 2.9474409 | U53: =U45/U285 -> 1.9031296 | V53: =V45/V285 -> 1.9922848 | W53: =W45/W285 -> 2.4247389 | X53: =X45/X285 -> 2.6273415 | Y53: =Y45/Y285 -> 8.9543248 | Z53: =Z45/Z285 -> 1.8964037 | AA53: =AA45/AA285 -> 2.2795018 | ... AG53: =AG45/AG285 -> 10.785668
C54: GAAP EPS (Diluted) | F54: =(F45)/F287 -> 0.52125194 | G54: =(G45)/G287 -> 0.035629734 | H54: =(H45)/H287 -> 0.23237273 | I54: =(I45)/I287 -> 0.12312146 | J54: =J45/J287 -> 0.93852716 | K54: =(K45)/K287 -> 0.72901714 | L54: =(L45)/L287 -> 0.68354514 | M54: =(M45)/M287 -> 0.78740545 | N54: =(N45)/N287 -> 0.75077129 | O54: =O45/O287 -> 2.9561869 | P54: =(P45)/P287 -> 0.61519546 | Q54: =(Q45)/Q287 -> 0.41188029 | R54: =(R45)/R287 -> 1.0888535 | S54: =(S45)/S287 -> 0.73163154 | T54: =T45/T287 -> 2.8487828 | U54: =U45/U287 -> 1.8059918 | V54: =V45/V287 -> 1.9751559 | W54: =W45/W287 -> 2.5009747 | X54: =X45/X287 -> 2.8383651 | Y54: =Y45/Y287 -> 9.0535939 | Z54: =Z45/Z287 -> 2.1856725 | AA54: =AA45/AA287 -> 2.3743961 | ... AG54: =AG45/AG287 -> 14.550904
C56: Adj. EPS (Basic) | F56: =F51/F285 -> 0.55882242 | G56: =G51/G285 -> 0.043035355 | H56: =H51/H285 -> 0.22704322 | I56: =I51/I285 -> 0.11134995 | J56: =J51/J285 -> 0.94685592 | K56: =K51/K285 -> 0.6798533 | L56: =L51/L285 -> 0.66222366 | M56: =M51/M285 -> 0.77881764 | ... AG56: =AG51/AG285 -> 10.323592
C57: Adj. EPS (Diluted) | F57: =F51/F287 -> 0.53856386 | G57: =G51/G287 -> 0.042536459 | H57: =H51/H287 -> 0.22343465 | I57: =I51/I287 -> 0.10946243 | J57: =J51/J287 -> 0.94143039 | K57: =K51/K287 -> 0.66402564 | L57: =L51/L287 -> 0.6441414 | M57: =M51/M287 -> 0.75335928 | ... AG57: =AG51/AG287 -> 13.927518
C59: EBIT | F59: =F51-F44-F41-F40-F39-F38 -> 162.309 | G59: =G51-G44-G41-G40-G39-G38 -> 19.674 | H59: =H51-H44-H41-H40-H39-H38 -> 88.97 | I59: =I51-I44-I41-I40-I39-I38 -> 42.728 | J59: =SUM(F59:I59) -> 313.681 | K59: =K51-K44-K41-K40-K39-K38 -> 205.558 | L59: =L51-L44-L41-L40-L39-L38 -> 218.777 | M59: =M51-M44-M41-M40-M39-M38 -> 245.03 | N59: =N51-N44-N41-N40-N39-N38 -> 245.716 | O59: =SUM(K59:N59) -> 915.081 | P59: =P51-P44-P41-P40-P39-P38 -> 142.009 | Q59: =Q51-Q44-Q41-Q40-Q39-Q38 -> 131.523 | R59: =R51-R44-R41-R40-R39-R38 -> 313.297 | S59: =S51-S44-S41-S40-S39-S38 -> 175.829 | T59: =SUM(P59:S59) -> 762.658 | U59: =U51-U44-U41-U40-U39-U38 -> 522.27001 | V59: =V51-V44-V41-V40-V39-V38 -> 598.39265 | W59: =W51-W44-W41-W40-W39-W38 -> 729.41794 | X59: =X51-X44-X41-X40-X39-X38 -> 768.56306 | Y59: =SUM(U59:X59) -> 2618.6437 | Z59: =Z51-Z44-Z41-Z40-Z39-Z38 -> 557.00453 | AA59: =AA51-AA44-AA41-AA40-AA39-AA38 -> 669.03143 | AB59: =AB51-AB44-AB41-AB40-AB39-AB38 -> 910.06315 | AC59: =AC51-AC44-AC41-AC40-AC39-AC38 -> 1049.3048 | AD59: =SUM(Z59:AC59) -> 3185.4039 | AE59: =AE51-AE44-AE41-AE40-AE39-AE38 -> 3010.8208 | AF59: =AF51-AF44-AF41-AF40-AF39-AF38 -> 3132.3522 | AG59: =AG51-AG44-AG41-AG40-AG39-AG38 -> 3012.2301
C60: Depreciation & Amortization | F60: =-F34 -> 33.292 | G60: =-G34 -> 25.31 | H60: =-H34 -> 25.288 | I60: =-I34 -> 28.311 | J60: =SUM(F60:I60) -> 112.201 | K60: =-K34 -> 43.202 | L60: =-L34 -> 49.946 | M60: =-M34 -> 45.977 | N60: =-N34 -> 51.201 | O60: =SUM(K60:N60) -> 190.326 | P60: =-P34 -> 30.988 | Q60: =-Q34 -> 52.253 | R60: =-R34 -> 53.23 | S60: =-S34 -> 55.81 | T60: =SUM(P60:S60) -> 192.281 | U60: =-U34 -> 45.184537 | V60: =-V34 -> 45.956307 | W60: =-W34 -> 46.099245 | X60: =-X34 -> 46.954591 | Y60: =SUM(U60:X60) -> 184.19468 | Z60: =-Z34 -> 45.341201 | AA60: =-AA34 -> 46.007409 | AB60: =-AB34 -> 45.996488 | AC60: =-AC34 -> 45.75119 | AD60: =SUM(Z60:AC60) -> 183.09629 | AE60: =-AE34 -> 182.07061 | AF60: =-AF34 -> 178.19654 | AG60: =-AG34 -> 169.96235
C61: EBITDA | F61: =SUM(F59:F60) -> 195.601 | G61: =SUM(G59:G60) -> 44.984 | H61: =SUM(H59:H60) -> 114.258 | I61: =SUM(I59:I60) -> 71.039 | J61: =SUM(F61:I61) -> 425.882 | K61: =SUM(K59:K60) -> 248.76 | L61: =SUM(L59:L60) -> 268.723 | M61: =SUM(M59:M60) -> 291.007 | N61: =SUM(N59:N60) -> 296.917 | O61: =SUM(K61:N61) -> 1105.407 | P61: =SUM(P59:P60) -> 172.997 | Q61: =SUM(Q59:Q60) -> 183.776 | R61: =SUM(R59:R60) -> 366.527 | S61: =SUM(S59:S60) -> 231.639 | T61: =SUM(P61:S61) -> 954.939 | U61: =SUM(U59:U60) -> 567.45455 | V61: =SUM(V59:V60) -> 643.65199 | W61: =SUM(W59:W60) -> 773.93172 | X61: =SUM(X59:X60) -> 812.72041 | Y61: =SUM(U61:X61) -> 2797.7587 | Z61: =SUM(Z59:Z60) -> 598.26973 | AA61: =SUM(AA59:AA60) -> 710.05986 | AB61: =SUM(AB59:AB60) -> 950.0348 | AC61: =SUM(AC59:AC60) -> 1087.7121 | AD61: =SUM(Z61:AC61) -> 3346.0765 | AE61: =SUM(AE59:AE60) -> 3157.2841 | AF61: =SUM(AF59:AF60) -> 3253.925 | AG61: =SUM(AG59:AG60) -> 3102.5611
C63: Income Statement Analysis | F63: =F$25 -> 1Q23 | G63: =G$25 -> 2Q23 | H63: =H$25 -> 3Q23 | I63: =I$25 -> 4Q23 | J63: =J$25 -> 2023 | K63: =K$25 -> 1Q24 | L63: =L$25 -> 2Q24 | M63: =M$25 -> 3Q24 | ... AG63: =AG$25 -> 2030e | AH63: x
A64: x | C64: Drivers
C66: Gross Margin | F66: =F30/F28 -> 0.72083389 | G66: =G30/G28 -> 0.62841788 | H66: =H30/H28 -> 0.57919984 | I66: =I30/I28 -> 0.60809879 | J66: =J30/J28 -> 0.63165676 | K66: =K30/K28 -> 0.68112426 | L66: =L30/L28 -> 0.65827806 | M66: =M30/M28 -> 0.64860565 | ... T66: =T30/T28 -> 0.67848948 | U66: =IF(Cover!$F$37="Bottom Up",(U30/U28),Drivers!U7) -> 1 | V66: =IF(Cover!$F$37="Bottom Up",(V30/V28),Drivers!V7) -> 1 | W66: =IF(Cover!$F$37="Bottom Up",(W30/W28),Drivers!W7) -> 1 | X66: =IF(Cover!$F$37="Bottom Up",(X30/X28),Drivers!X7) -> 1 | Y66: =Y30/Y28 -> 0.69909207 | Z66: =IF(Cover!$F$37="Bottom Up",(Z30/Z28),Drivers!Z7) -> 1 | AA66: =IF(Cover!$F$37="Bottom Up",(AA30/AA28),Drivers!AA7) -> 1 | AB66: =IF(Cover!$F$37="Bottom Up",(AB30/AB28),Drivers!AB7) -> 1 | AC66: =IF(Cover!$F$37="Bottom Up",(AC30/AC28),Drivers!AC7) -> 1 | AD66: =AD30/AD28 -> 0.72317981 | AE66: =IF(Cover!$F$37="Bottom Up",(AE30/AE28),Drivers!AE7) -> 1 | AF66: =IF(Cover!$F$37="Bottom Up",(AF30/AF28),Drivers!AF7) -> 1 | AG66: =IF(Cover!$F$37="Bottom Up",(AG30/AG28),Drivers!AG7) -> 1
C67: Compensation, Commissions, and Benefits as % of Net Revenue | F67: =F32/F30 -> -0.54777139 | G67: =G32/G30 -> -0.55496256 | H67: =H32/H30 -> -0.54485137 | I67: =I32/I30 -> -0.51145045 | J67: =J32/J30 -> -0.5393739 | K67: =K32/K30 -> -0.53324807 | L67: =L32/L30 -> -0.52040807 | M67: =M32/M30 -> -0.52814262 | ... T67: =T32/T30 -> -0.52565167 | U67: =Drivers!U40 -> -0.52 | V67: =Drivers!V40 -> -0.525 | W67: =Drivers!W40 -> -0.525 | X67: =Drivers!X40 -> -0.515 | Y67: =Y32/Y30 -> -0.52112618 | Z67: =Drivers!Z40 -> -0.5175 | AA67: =Drivers!AA40 -> -0.515 | AB67: =Drivers!AB40 -> -0.505 | AC67: =Drivers!AC40 -> -0.495 | AD67: =AD32/AD30 -> -0.5073607 | AE67: =Drivers!AE40 -> -0.5135 | AF67: =Drivers!AF40 -> -0.511 | AG67: =Drivers!AG40 -> -0.515
C68: Non-Compensation Benefts as a % of Net Revenue | F68: =F33/F30 -> -0.25974532 | G68: =G33/G30 -> -0.35193559 | H68: =H33/H30 -> -0.30687973 | I68: =I33/I30 -> -0.36317178 | J68: =J33/J30 -> -0.31829305 | K68: =K33/K30 -> -0.24699323 | L68: =L33/L30 -> -0.264297 | M68: =M33/M30 -> -0.2464883 | ... T68: =T33/T30 -> -0.27259217 | U68: =Drivers!U45 -> -0.2375 | V68: =Drivers!V45 -> -0.24 | W68: =Drivers!W45 -> -0.24 | X68: =Drivers!X45 -> -0.25 | Y68: =Y33/Y30 -> -0.24217242 | Z68: =Drivers!Z45 -> -0.24 | AA68: =Drivers!AA45 -> -0.235 | AB68: =Drivers!AB45 -> -0.23 | AC68: =Drivers!AC45 -> -0.225 | AD68: =AD33/AD30 -> -0.23200353 | AE68: =Drivers!AE45 -> -0.235 | AF68: =Drivers!AF45 -> -0.235 | AG68: =Drivers!AG45 -> -0.24
C69: Other Operating Income as a % of Revenue | F69: =F35/F28 -> -0.031307005 | G69: =G35/G28 -> -0.032290845 | H69: =H35/H28 -> -0.028876646 | I69: =I35/I28 -> -0.038515967 | J69: =J35/J28 -> -0.032765965 | K69: =K35/K28 -> -0.046464987 | L69: =L35/L28 -> -0.031386638 | M69: =M35/M28 -> -0.03114684 | ... T69: =T35/T28 -> -0.043523102 | U69: =Drivers!U50 -> -0.045 | V69: =Drivers!V50 -> -0.035 | W69: =Drivers!W50 -> -0.04 | X69: =Drivers!X50 -> -0.0425 | Y69: =Y35/Y28 -> -0.040645417 | Z69: =Drivers!Z50 -> -0.045 | AA69: =Drivers!AA50 -> -0.045 | AB69: =Drivers!AB50 -> -0.045 | AC69: =Drivers!AC50 -> -0.045 | AD69: =AD35/AD28 -> -0.045 | AE69: =Drivers!AE50 -> -0.05 | AF69: =Drivers!AF50 -> -0.05 | AG69: =Drivers!AG50 -> -0.05
C70: Other Non-Operating Income as a % of Revenue | F70: =F41/F28 -> 0 | G70: =G41/G28 -> 0 | H70: =H41/H28 -> 0 | I70: =I41/I28 -> 0 | J70: =J41/J28 -> 0 | K70: =K41/K28 -> 0 | L70: =L41/L28 -> 0 | M70: =M41/M28 -> 0 | ... T70: =T41/T28 -> 0 | U70: =Drivers!U57 -> 0 | V70: =Drivers!V57 -> 0 | W70: =Drivers!W57 -> 0 | X70: =Drivers!X57 -> 0 | Y70: =Y41/Y28 -> 0 | Z70: =Drivers!Z57 -> 0 | AA70: =Drivers!AA57 -> 0 | AB70: =Drivers!AB57 -> 0 | AC70: =Drivers!AC57 -> 0 | AD70: =AD41/AD28 -> 0 | AE70: =Drivers!AE57 -> 0 | AF70: =Drivers!AF57 -> 0 | AG70: =Drivers!AG57 -> 0
C71: Tax Rate | F71: =-F44/F42 -> 0.1815915 | G71: =-G44/G42 -> 0.51365482 | H71: =-H44/H42 -> 0.40775889 | I71: =-I44/I42 -> 0.36612272 | J71: =-J44/J42 -> 0.29354914 | K71: =-K44/K42 -> 0.25412807 | L71: =-L44/L42 -> 0.32108412 | M71: =-M44/M42 -> 0.30885905 | ... T71: =-T44/T42 -> 0.22555683 | U71: =Drivers!U64 -> 0.217 | V71: =Drivers!V64 -> 0.257 | W71: =Drivers!W64 -> 0.257 | X71: =Drivers!X64 -> 0.257 | Y71: =-Y44/Y42 -> 0.24902146 | Z71: =Drivers!Z64 -> 0.255 | AA71: =Drivers!AA64 -> 0.255 | AB71: =Drivers!AB64 -> 0.255 | AC71: =Drivers!AC64 -> 0.255 | AD71: =-AD44/AD42 -> 0.255 | AE71: =Drivers!AE64 -> 0.25 | AF71: =Drivers!AF64 -> 0.25 | AG71: =Drivers!AG64 -> 0.25
A73: x | C73: Cash Flow Statement | F73: =F$25 -> 1Q23 | G73: =G$63 -> 2Q23 | H73: =H$63 -> 3Q23 | I73: =I$63 -> 4Q23 | J73: =J$63 -> 2023 | K73: =K$63 -> 1Q24 | L73: =L$63 -> 2Q24 | M73: =M$63 -> 3Q24 | N73: =N$63 -> 4Q24 | ... AG73: =AG$63 -> 2030e | AH73: x
C75: Net Income | T75: =SUM(P75:S75) -> 0 | U75: =U45 -> 424.59742 | V75: =V45 -> 459.46574 | W75: =W45 -> 556.81753 | X75: =X45 -> 600.76235 | Y75: =SUM(U75:X75) -> 2041.643 | Z75: =Z45 -> 429.86838 | AA75: =AA45 -> 513.32841 | AB75: =AB45 -> 692.89705 | AC75: =AC45 -> 796.63206 | AD75: =SUM(Z75:AC75) -> 2432.7259 | AE75: =AE45 -> 2333.1156 | AF75: =AF45 -> 2424.2642 | AG75: =AG45 -> 2334.1726
C76: Depreciation & Amortization | F76: -33.292 | G76: -25.31 | H76: -25.288 | I76: -28.311 | K76: -43.202 | L76: -49.946 | M76: -45.977 | N76: -51.201 | P76: -30.988 | Q76: -52.253 | R76: -53.23 | S76: -55.81 | T76: =SUM(P76:S76) -> -192.281 | U76: =-(U197+U211) -> -45.184537 | V76: =-(V197+V211) -> -45.956307 | W76: =-(W197+W211) -> -46.099245 | X76: =-(X197+X211) -> -46.954591 | Y76: =SUM(U76:X76) -> -184.19468 | Z76: =-(Z197+Z211) -> -45.341201 | AA76: =-(AA197+AA211) -> -46.007409 | AB76: =-(AB197+AB211) -> -45.996488 | AC76: =-(AC197+AC211) -> -45.75119 | AD76: =SUM(Z76:AC76) -> -183.09629 | AE76: =-(AE197+AE211) -> -182.07061 | AF76: =-(AF197+AF211) -> -178.19654 | AG76: =-(AG197+AG211) -> -169.96235
C77: Stock-Based Compensation | F77: 13.726 | G77: 10.492 | H77: 11.258 | I77: 9.884 | K77: 20.215 | L77: 14.357 | M77: 13.377 | N77: 15.17 | P77: 35.637 | Q77: 18.193 | R77: 13.98 | S77: 20.417 | T77: =SUM(P77:S77) -> 88.227 | U77: =U249 -> 18.990899 | V77: =V249 -> 19.417423 | W77: =W249 -> 22.330585 | X77: =X249 -> 22.287763 | Y77: =SUM(U77:X77) -> 83.02667 | Z77: =Z249 -> 20.416221 | AA77: =AA249 -> 21.373502 | AB77: =AB249 -> 24.312276 | AC77: =AC249 -> 24.051325 | AD77: =SUM(Z77:AC77) -> 90.153323 | AE77: =AE249 -> 96.205819 | AF77: =AF249 -> 100.7473 | AG77: =AG249 -> 103.69828
C78: (Increase)/Decrease in Working Capital | T78: =SUM(P78:S78) -> 0 | U78: =U176 -> -9257.5248 | V78: =V176 -> -4183.2036 | W78: =W176 -> -2916.2541 | X78: =X176 -> -1608.7092 | Y78: =SUM(U78:X78) -> -12806.179 | Z78: =Z176 -> -5956.8789 | AA78: =AA176 -> 8868.967 | AB78: =AB176 -> -2267.8375 | AC78: =AC176 -> -1697.8035 | AD78: =SUM(Z78:AC78) -> -1053.5528 | AE78: =AE176 -> -5455.0982 | AF78: =AF176 -> 1320.445 | AG78: =AG176 -> 39.396822
C79: (Increase)/Decrease in LT Items | F79: 21.842 | G79: -83.388 | H79: 120.537 | I79: 40.793 | K79: -75.411 | L79: -72.44 | M79: -60.842 | N79: -55.987 | P79: 44.419 | Q79: -228.781 | R79: -249.748 | S79: -58.371 | T79: =SUM(P79:S79) -> -492.481 | U79: =U231 -> -64.93412 | V79: =V231 -> -66.232802 | W79: =W231 -> -67.557458 | X79: =X231 -> -68.908608 | Y79: =SUM(U79:X79) -> -267.63299 | Z79: =Z231 -> -70.28678 | AA79: =AA231 -> -71.692515 | AB79: =AB231 -> -73.126366 | AC79: =AC231 -> -74.588893 | AD79: =SUM(Z79:AC79) -> -289.69455 | AE79: =AE231 -> -285.30252 | AF79: =AF231 -> -408.93361 | AG79: =AG231 -> -382.35292
C80: Net Cash From Operating Activities | T80: =SUM(P80:S80) -> 0 | U80: =SUM(U75:U79) -> -3974.1223 | V80: =SUM(V75:V79) -> -4028.5392 | W80: =SUM(W75:W79) -> -2665.751 | X80: =SUM(X75:X79) -> -1318.2324 | Y80: =SUM(U80:X80) -> -11986.645 | Z80: =SUM(Z75:Z79) -> -5845.3423 | AA80: =SUM(AA75:AA79) -> 9060.0303 | AB80: =SUM(AB75:AB79) -> -1898.8489 | AC80: =SUM(AC75:AC79) -> -1228.4297 | AD80: =SUM(Z80:AC80) -> 87.409447 | AE80: =SUM(AE75:AE79) -> -4377.83 | AF80: =SUM(AF75:AF79) -> 2000.3137 | AG80: =SUM(AG75:AG79) -> 772.99603
C82: Capital Expenditures | F82: -25.152 | G82: -25.062 | H82: -29.996 | I82: -79.055 | K82: -96.241 | L82: -48.616 | M82: -35.797 | N82: -69.93 | P82: -49.578 | Q82: -43.669 | R82: -58.178 | S82: -56.042 | T82: =SUM(P82:S82) -> -207.467 | U82: =-U196 -> 41.142788 | V82: =-V196 -> 42.066829 | W82: =-W196 -> 48.378041 | X82: =-X196 -> 48.28527 | Y82: =SUM(U82:X82) -> 179.87293 | Z82: =-Z196 -> 44.230671 | AA82: =-AA196 -> 46.304571 | AB82: =-AB196 -> 52.671271 | AC82: =-AC196 -> 52.105935 | AD82: =SUM(Z82:AC82) -> 195.31245 | AE82: =-AE196 -> 208.42486 | AF82: =-AF196 -> 218.26375 | AG82: =-AG196 -> 224.65688
C83: Purchases of Intangibles | F83: 0 | G83: 0 | H83: 0 | I83: 0 | K83: 0 | L83: 0 | M83: 0 | N83: 0 | P83: 0 | Q83: 0 | R83: 0 | S83: 0 | T83: =SUM(P83:S83) -> 0 | U83: =-U210 -> 0 | V83: =-V210 -> 0 | W83: =-W210 -> 0 | X83: =-X210 -> 0 | Y83: =SUM(U83:X83) -> 0 | Z83: =-Z210 -> 0 | AA83: =-AA210 -> 0 | AB83: =-AB210 -> 0 | AC83: =-AC210 -> 0 | AD83: =SUM(Z83:AC83) -> 0 | AE83: =-AE210 -> 0 | AF83: =-AF210 -> 0 | AG83: =-AG210 -> 0
C84: Proceeds From/(Acquisitions of) Businesses | F84: 0 | G84: 0 | H84: 0 | I84: 0 | K84: 0 | L84: 0 | M84: 0 | N84: 0 | P84: 0 | Q84: 0 | R84: 0 | S84: 0 | T84: =SUM(P84:S84) -> 0 | U84: =Drivers!U97 -> 0 | V84: =Drivers!V97 -> 0 | W84: =Drivers!W97 -> 0 | X84: =Drivers!X97 -> 0 | Y84: =SUM(U84:X84) -> 0 | Z84: =Drivers!Z97 -> 0 | AA84: =Drivers!AA97 -> 0 | AB84: =Drivers!AB97 -> 0 | AC84: =Drivers!AC97 -> 0 | AD84: =SUM(Z84:AC84) -> 0 | AE84: =Drivers!AE97 -> 0 | AF84: =Drivers!AF97 -> 0 | AG84: =Drivers!AG97 -> 0
C85: Net Cash From Investment Activities | T85: =SUM(P85:S85) -> 0 | U85: =SUM(U82:U84) -> 41.142788 | V85: =SUM(V82:V84) -> 42.066829 | W85: =SUM(W82:W84) -> 48.378041 | X85: =SUM(X82:X84) -> 48.28527 | Y85: =SUM(U85:X85) -> 179.87293 | Z85: =SUM(Z82:Z84) -> 44.230671 | AA85: =SUM(AA82:AA84) -> 46.304571 | AB85: =SUM(AB82:AB84) -> 52.671271 | AC85: =SUM(AC82:AC84) -> 52.105935 | AD85: =SUM(Z85:AC85) -> 195.31245 | AE85: =SUM(AE82:AE84) -> 208.42486 | AF85: =SUM(AF82:AF84) -> 218.26375 | AG85: =SUM(AG82:AG84) -> 224.65688
C87: Cash Flow Available for Financing Activities | T87: =SUM(P87:S87) -> 0 | U87: =SUM(U80,U85) -> -3914.0144 | V87: =SUM(V80,V85) -> -3962.9927 | W87: =SUM(W80,W85) -> -2587.5072 | X87: =SUM(X80,X85) -> -1234.8959 | Y87: =SUM(U87:X87) -> -11699.41 | Z87: =SUM(Z80,Z85) -> -5782.1465 | AA87: =SUM(AA80,AA85) -> 9129.8145 | AB87: =SUM(AB80,AB85) -> -1816.3118 | AC87: =SUM(AC80,AC85) -> -1141.2726 | AD87: =SUM(Z87:AC87) -> 390.08364 | AE87: =SUM(AE80,AE85) -> -4062.0434 | AF87: =SUM(AF80,AF85) -> 2325.9392 | AG87: =SUM(AG80,AG85) -> 1105.0147
C89: Issuance/(Repayment) of Revolver | F89: -52 | G89: 368.2 | H89: 80 | I89: 5.932 | K89: 278.261 | L89: 339.576 | M89: 150.446 | N89: -1292.352 | P89: 591.704 | Q89: 300.281 | R89: -85.09 | S89: 515.966 | T89: =SUM(P89:S89) -> 1322.861 | U89: =U306 -> 0 | V89: =V306 -> 0 | W89: =W306 -> 0 | X89: =X306 -> 0 | Y89: =SUM(U89:X89) -> 0 | Z89: =Z306 -> 2269.8897 | AA89: =AA306 -> -2269.8897 | AB89: =AB306 -> 0 | AC89: =AC306 -> 0 | AD89: =SUM(Z89:AC89) -> 0 | AE89: =AE306 -> 0 | AF89: =AF306 -> 0 | AG89: =AG306 -> 0
C90: Issuance of Debt | H90: 990.6 | K90: 206.3 | L90: 3070 | M90: 3290 | N90: 3980 | P90: 350 | Q90: 350 | R90: 350 | S90: 1070 | T90: =SUM(P90:S90) -> 2120 | U90: =U311 -> 250 | V90: =V311 -> 250 | W90: =W311 -> 250 | X90: =X311 -> 250 | Y90: =SUM(U90:X90) -> 1000 | Z90: =Z311 -> 250 | AA90: =AA311 -> 250 | AB90: =AB311 -> 250 | AC90: =AC311 -> 250 | AD90: =SUM(Z90:AC90) -> 1000 | AE90: =AE311 -> 1500 | AF90: =AF311 -> 1500 | AG90: =AG311 -> 1500
C91: (Repayment of Debt) | F91: -235.766 | G91: -51.474 | H91: -584.405 | I91: -410.724 | K91: -317.794 | L91: -408.225 | M91: -1037.553 | N91: -664.081 | P91: -188.89 | Q91: -771.967 | R91: -797.565 | S91: -2301.016 | T91: =SUM(P91:S91) -> -4059.438 | U91: =U312 -> 0 | V91: =V312 -> 0 | W91: =W312 -> 0 | X91: =X312 -> 0 | Y91: =SUM(U91:X91) -> 0 | Z91: =Z312 -> 0 | AA91: =AA312 -> 0 | AB91: =AB312 -> 0 | AC91: =AC312 -> 0 | AD91: =SUM(Z91:AC91) -> 0 | AE91: =AE312 -> 0 | AF91: =AF312 -> 0 | AG91: =AG312 -> 0
C92: Issuance of Equity | T92: =SUM(P92:S92) -> 0 | U92: =U248 -> 692.24 | V92: =V248 -> 0 | W92: =W248 -> 0 | X92: =X248 -> 0 | Y92: =SUM(U92:X92) -> 692.24 | Z92: =Z248 -> -81.44 | AA92: =AA248 -> 40.72 | AB92: =AB248 -> 81.44 | AC92: =AC248 -> 40.72 | AD92: =SUM(Z92:AC92) -> 81.44 | AE92: =AE248 -> 0 | AF92: =AF248 -> 0 | AG92: =AG248 -> 0
C93: (Repurchase) of Equity | F93: -50.863 | G93: -114.129 | H93: -0.28 | I93: -4.13 | K93: -43.033 | L93: -0.946 | M93: -0.332 | N93: -0.001 | P93: -56.318 | Q93: -1.25 | R93: -0.918 | S93: -0.029 | T93: =SUM(P93:S93) -> -58.515 | U93: =-U244 -> -40 | V93: =-V244 -> -40 | W93: =-W244 -> -40 | X93: =-X244 -> -40 | Y93: =SUM(U93:X93) -> -160 | Z93: =-Z244 -> -40 | AA93: =-AA244 -> -40 | AB93: =-AB244 -> -40 | AC93: =-AC244 -> -40 | AD93: =SUM(Z93:AC93) -> -160 | AE93: =-AE244 -> -160 | AF93: =-AF244 -> -160 | AG93: =-AG244 -> -160
C94: Dividends Issued | F94: -68.769 | G94: -69.929 | H94: -69.919 | I94: -69.978 | K94: -69.909 | L94: -69.914 | M94: -81.569 | N94: -81.572 | P94: -92.735 | Q94: -94.319 | R94: -93.535 | S94: -93.541 | T94: =SUM(P94:S94) -> -374.13 | U94: =-U270 -> -111.24 | V94: =-V270 -> -113.28 | W94: =-W270 -> -112.2 | X94: =-X270 -> -112.236 | Y94: =SUM(U94:X94) -> -448.956 | Z94: =-Z270 -> -133.488 | AA94: =-AA270 -> -135.936 | AB94: =-AB270 -> -134.64 | AC94: =-AC270 -> -134.6832 | AD94: =SUM(Z94:AC94) -> -538.7472 | AE94: =-AE270 -> -641.10917 | AF94: =-AF270 -> -737.27554 | AG94: =-AG270 -> -811.0031
C95: Change in Noncontrolling Interests | T95: =SUM(P95:S95) -> 0 | U95: =Drivers!U106 -> 0 | V95: =Drivers!V106 -> 0 | W95: =Drivers!W106 -> 0 | X95: =Drivers!X106 -> 0 | Y95: =SUM(U95:X95) -> 0 | Z95: =Drivers!Z106 -> 0 | AA95: =Drivers!AA106 -> 0 | AB95: =Drivers!AB106 -> 0 | AC95: =Drivers!AC106 -> 0 | AD95: =SUM(Z95:AC95) -> 0 | AE95: =Drivers!AE106 -> 0 | AF95: =Drivers!AF106 -> 0 | AG95: =Drivers!AG106 -> 0
C96: Net Cash From Financing Activities | T96: =SUM(P96:S96) -> 0 | U96: =SUM(U89:U95) -> 791 | V96: =SUM(V89:V95) -> 96.72 | W96: =SUM(W89:W95) -> 97.8 | X96: =SUM(X89:X95) -> 97.764 | Y96: =SUM(U96:X96) -> 1083.284 | Z96: =SUM(Z89:Z95) -> 2264.9617 | AA96: =SUM(AA89:AA95) -> -2155.1057 | AB96: =SUM(AB89:AB95) -> 156.8 | AC96: =SUM(AC89:AC95) -> 116.0368 | AD96: =SUM(Z96:AC96) -> 382.6928 | AE96: =SUM(AE89:AE95) -> 698.89083 | AF96: =SUM(AF89:AF95) -> 602.72446 | AG96: =SUM(AG89:AG95) -> 528.9969
C98: Effect of FX Rate Changes on Cash | F98: 1.682 | G98: 0.975 | H98: -2.873 | K98: -1.683 | L98: 0.17 | M98: 20.414 | T98: =SUM(P98:S98) -> 0 | U98: =Drivers!U108 -> 0 | V98: =Drivers!V108 -> 0 | W98: =Drivers!W108 -> 0 | X98: =Drivers!X108 -> 0 | Y98: =SUM(U98:X98) -> 0 | Z98: =Drivers!Z108 -> 0 | AA98: =Drivers!AA108 -> 0 | AB98: =Drivers!AB108 -> 0 | AC98: =Drivers!AC108 -> 0 | AD98: =SUM(Z98:AC98) -> 0 | AE98: =Drivers!AE108 -> 0 | AF98: =Drivers!AF108 -> 0 | AG98: =Drivers!AG108 -> 0
C99: Beginning Cash Adjustments | F99: 0 | G99: 0 | H99: 0 | I99: 0 | K99: 0 | L99: 0 | M99: 0 | N99: 0 | P99: 0 | Q99: 0 | R99: 0 | S99: 0 | T99: =SUM(P99:S99) -> 0 | U99: 0 | V99: 0 | W99: 0 | X99: 0 | Y99: =SUM(U99:X99) -> 0 | Z99: 0 | AA99: 0 | AB99: 0 | AC99: 0 | AD99: =SUM(Z99:AC99) -> 0 | AE99: 0 | AF99: 0 | AG99: 0
C100: Ending Cash Adjustments | F100: 0 | G100: 0 | H100: 0 | I100: 0 | K100: 0 | L100: 0 | M100: 0 | N100: 0 | P100: 0 | Q100: 0 | R100: 0 | S100: 0 | T100: =SUM(P100:S100) -> 0 | U100: 0 | V100: 0 | W100: 0 | X100: 0 | Y100: =SUM(U100:X100) -> 0 | Z100: 0 | AA100: 0 | AB100: 0 | AC100: 0 | AD100: =SUM(Z100:AC100) -> 0 | AE100: 0 | AF100: 0 | AG100: 0
C102: Beginning Cash Balance | F102: 9703.109 | G102: 7508.508 | H102: 8004.88 | I102: 8817.357 | K102: 8526.363 | L102: 7615.691 | M102: 10841.622 | N102: 10573.471 | P102: 12153.414 | Q102: 11176.343 | R102: 11260.403 | S102: 11458.472 | T102: =+S104 -> 14043.889 | U102: =T104+U99 -> 14043.889 | V102: =U104+V99 -> 10920.875 | W102: =V104+W99 -> 7054.6019 | X102: =W104+X99 -> 4564.8948 | Y102: =IF(Last_FQR="1Q",U104,IF(Last_FQR="2Q",V104,IF(Last_FQR="3Q",W104,U102))) -> 14043.889 | Z102: =Y104+Z99 -> 3427.7628 | AA102: =Z104+AA99 -> -89.421945 | AB102: =AA104+AB99 -> 6885.2868 | AC102: =AB104+AC99 -> 5225.7751 | AD102: =Z102 -> 3427.7628 | AE102: =AD104+AE99 -> 4200.5393 | AF102: =AE104+AF99 -> 837.3867 | AG102: =AF104+AG99 -> 3766.0503
C103: Net Change in Cash | T103: =SUM(P103:S103) -> 0 | U103: =SUM(U87,U96,U98,U100) -> -3123.0144 | V103: =SUM(V87,V96,V98,V100) -> -3866.2727 | W103: =SUM(W87,W96,W98,W100) -> -2489.7072 | X103: =SUM(X87,X96,X98,X100) -> -1137.1319 | Y103: =SUM(U103:X103) -> -10616.126 | Z103: =SUM(Z87,Z96,Z98,Z100) -> -3517.1848 | AA103: =SUM(AA87,AA96,AA98,AA100) -> 6974.7088 | AB103: =SUM(AB87,AB96,AB98,AB100) -> -1659.5118 | AC103: =SUM(AC87,AC96,AC98,AC100) -> -1025.2358 | AD103: =SUM(Z103:AC103) -> 772.77644 | AE103: =SUM(AE87,AE96,AE98,AE100) -> -3363.1526 | AF103: =SUM(AF87,AF96,AF98,AF100) -> 2928.6636 | AG103: =SUM(AG87,AG96,AG98,AG100) -> 1634.0116
C104: Ending Cash Balance | F104: 7508.508 | G104: 8004.88 | H104: 8817.357 | I104: 8526.363 | K104: 7615.691 | L104: 10841.622 | M104: 10573.471 | N104: 12153.414 | P104: 11176.343 | Q104: 11260.403 | R104: 11458.472 | S104: =+S120 -> 14043.889 | T104: =SUM(T102:T103) -> 14043.889 | U104: =SUM(U102:U103) -> 10920.875 | V104: =SUM(V102:V103) -> 7054.6019 | W104: =SUM(W102:W103) -> 4564.8948 | X104: =SUM(X102:X103) -> 3427.7628 | Y104: =SUM(Y102:Y103) -> 3427.7628 | Z104: =SUM(Z102:Z103) -> -89.421945 | AA104: =SUM(AA102:AA103) -> 6885.2868 | ... AG104: =SUM(AG102:AG103) -> 5400.0619
A106: x | C106: Free Cash Flow Analysis | AH106: x
C108: Net Income | F108: =F45 -> 129.32 | G108: =G45 -> 8.744 | H108: =H45 -> 53.92 | I108: =I45 -> 29.133 | J108: =J45 -> 221.117 | K108: =K45 -> 164.241 | L108: =L45 -> 154.581 | M108: =M45 -> 174.567 | ... AG108: =AG45 -> 2334.1726
C109: Depreciation & Amortization | F109: =-F197+-F211 -> 33.292 | G109: =-G197+-G211 -> 25.31 | H109: =-H197+-H211 -> 25.288 | I109: =-I197+-I211 -> 28.311 | J109: =SUM(F109:I109) -> 112.201 | K109: =-K197+-K211 -> 43.202 | L109: =-L197+-L211 -> 49.946 | M109: =-M197+-M211 -> 45.977 | N109: =-N197+-N211 -> 51.201 | O109: =SUM(K109:N109) -> 190.326 | P109: =-P197+-P211 -> 30.988 | Q109: =-Q197+-Q211 -> 52.253 | R109: =-R197+-R211 -> 53.23 | S109: =-S197+-S211 -> 55.81 | T109: =SUM(P109:S109) -> 192.281 | U109: =-U197+-U211 -> -45.184537 | V109: =-V197+-V211 -> -45.956307 | W109: =-W197+-W211 -> -46.099245 | X109: =-X197+-X211 -> -46.954591 | Y109: =SUM(U109:X109) -> -184.19468 | Z109: =-Z197+-Z211 -> -45.341201 | AA109: =-AA197+-AA211 -> -46.007409 | AB109: =-AB197+-AB211 -> -45.996488 | AC109: =-AC197+-AC211 -> -45.75119 | AD109: =SUM(Z109:AC109) -> -183.09629 | AE109: =-AE197+-AE211 -> -182.07061 | AF109: =-AF197+-AF211 -> -178.19654 | AG109: =-AG197+-AG211 -> -169.96235
C110: Change in Operating Working Capital | F110: =F180 -> 0 | G110: =G180 -> 721.742 | H110: =H180 -> -926.429 | I110: =I180 -> -273.242 | J110: =SUM(F110:I110) -> -477.929 | K110: =K180 -> -312.874 | L110: =L180 -> -605.173 | M110: =M180 -> 950.294 | N110: =N180 -> -1078.817 | O110: =SUM(K110:N110) -> -1046.57 | P110: =P180 -> -294.666 | Q110: =Q180 -> 210.651 | R110: =R180 -> -350.582 | S110: =S180 -> 2114.525 | T110: =SUM(P110:S110) -> 1679.928 | U110: =U180 -> -2847.4273 | V110: =V180 -> 57.822993 | W110: =W180 -> -866.86143 | X110: =X180 -> 1075.965 | Y110: =SUM(U110:X110) -> -2226.4855 | Z110: =Z180 -> -209.2861 | AA110: =AA180 -> 76.461854 | AB110: =AB180 -> -925.96787 | AC110: =AC180 -> 1122.4699 | AD110: =SUM(Z110:AC110) -> 63.677755 | AE110: =AE180 -> 21.052609 | AF110: =AF180 -> 480.08213 | AG110: =AG180 -> 149.03169
C111: Capital Expenditures | F111: =F196 -> -25.152 | G111: =G196 -> -16.848 | H111: =H196 -> -26 | I111: =I196 -> -23 | J111: =SUM(F111:I111) -> -91 | K111: =K196 -> -96.241 | L111: =L196 -> 27.241 | M111: =M196 -> -53 | N111: =N196 -> -51 | O111: =SUM(K111:N111) -> -173 | P111: =P196 -> -49.578 | Q111: =Q196 -> -49.422 | R111: =R196 -> -56 | S111: =S196 -> -18 | T111: =SUM(P111:S111) -> -173 | U111: =U196 -> -41.142788 | V111: =V196 -> -42.066829 | W111: =W196 -> -48.378041 | X111: =X196 -> -48.28527 | Y111: =SUM(U111:X111) -> -179.87293 | Z111: =Z196 -> -44.230671 | AA111: =AA196 -> -46.304571 | AB111: =AB196 -> -52.671271 | AC111: =AC196 -> -52.105935 | AD111: =SUM(Z111:AC111) -> -195.31245 | AE111: =AE196 -> -208.42486 | AF111: =AF196 -> -218.26375 | AG111: =AG196 -> -224.65688
C112: Free Cash Flow (FCF) | F112: =SUM(F108:F111) -> 137.46 | G112: =SUM(G108:G111) -> 738.948 | H112: =SUM(H108:H111) -> -873.221 | I112: =SUM(I108:I111) -> -238.798 | J112: =SUM(J108:J111) -> -235.611 | K112: =SUM(K108:K111) -> -201.672 | L112: =SUM(L108:L111) -> -373.405 | M112: =SUM(M108:M111) -> 1117.838 | ... AG112: =SUM(AG108:AG111) -> 2060.8546
C114: Free Cash Flow Margin | F114: =F112/F28 -> 0.077200431 | G114: =G112/G28 -> 0.44751042 | H114: =H112/H28 -> -0.42786326 | I114: =I112/I28 -> -0.12129792 | J114: =J112/J28 -> -0.031662272 | K114: =K112/K28 -> -0.079028175 | L114: =L112/L28 -> -0.1483986 | M114: =M112/M28 -> 0.43068642 | ... AG114: =AG112/AG28 -> 0.093105675
C115: Free Cash Flow per Share | F115: =F112/F285 -> 0.57490349 | G115: =G112/G285 -> 3.046354 | H115: =H112/H285 -> -3.8239962 | I115: =I112/I285 -> -1.0266069 | J115: =J112/J285 -> -1.00581 | K115: =K112/K285 -> -0.91649928 | L115: =L112/L285 -> -1.6975192 | M115: =M112/M285 -> 5.2125324 | ... AG115: =AG112/AG285 -> 9.5227297
C116: Free Cash Flow Yield | F116: =F115*4/F242 -> 0.060500236 | G116: =G115*4/G242 -> 0.35065945 | H116: =H115*4/H242 -> -0.44029893 | I116: =I115*4/I242 -> -0.11515501 | J116: =J115/J242 -> -0.028180823 | K116: =K115*4/K242 -> -0.090228824 | L116: =L115*4/L242 -> -0.16699648 | M116: =M115*4/M242 -> 0.51203658 | N116: =N115*4/N242 -> -0.41210948 | O116: =O115/O242 -> -0.041827714 | P116: =P115*4/P242 -> -0.040661256 | Q116: =Q115*4/Q242 -> 0.070772342 | R116: =R115*4/R242 -> -0.025808042 | S116: =S115*4/S242 -> 1.0573718 | T116: =T115/T242 -> 0.13547161 | U116: =U115*4/U242 -> -0.95724733 | V116: =V115*4/V242 -> 0.17313815 | W116: =W115*4/W242 -> -0.18513695 | X116: =X115*4/X242 -> 0.66555346 | Y116: =Y115/Y242 -> -0.070138169 | Z116: =Z115*4/Z242 -> 0.050322179 | AA116: =AA115*4/AA242 -> 0.20893542 | AB116: =AB115*4/AB242 -> -0.15475205 | AC116: =AC115*4/AC242 -> 0.77878063 | AD116: =AD115/AD242 -> 0.22096596 | AE116: =AE115/AE242 -> 0.20716576 | AF116: =AF115/AF242 -> 0.27385661 | AG116: =AG115/AG242 -> 0.23385878
A118: x | C118: Balance Sheet | F118: =F$25 -> 1Q23 | G118: =G$63 -> 2Q23 | H118: =H$63 -> 3Q23 | I118: =I$63 -> 4Q23 | J118: =J$63 -> 2023 | K118: =K$63 -> 1Q24 | L118: =L$63 -> 2Q24 | M118: =M$63 -> 3Q24 | N118: =N$63 -> 4Q24 | ... AG118: =AG$63 -> 2030e | AH118: x
C120: Cash & Cash Equivalents | F120: 49343 | G120: 49529 | H120: 49605 | I120: 73387 | J120: =I120 -> 8526.363 | K120: 72852 | L120: 71178 | M120: 75091 | N120: 78779 | O120: =N120 -> 12153.414 | P120: 66207 | Q120: 57741 | R120: 66922 | S120: 86810 | T120: =S120 -> 14043.889 | U120: =U104 -> 10920.875 | V120: =V104 -> 7054.6019 | W120: =W104 -> 4564.8948 | X120: =X104 -> 3427.7628 | Y120: =X120 -> 3427.7628 | Z120: =Z104 -> -89.421945 | AA120: =AA104 -> 6885.2868 | AB120: =AB104 -> 5225.7751 | AC120: =AC104 -> 4200.5393 | AD120: =AC120 -> 4200.5393 | AE120: =AE104 -> 837.3867 | AF120: =AF104 -> 3766.0503 | AG120: =AG104 -> 5400.0619
C121: Accounts Receivable | F121: 37646 | G121: 39925 | H121: 43420 | I121: 52253 | J121: =I121 -> 4716.299 | K121: 47768 | L121: 50106 | M121: 51638 | N121: 55451 | O121: =N121 -> 5824.844 | P121: 54216 | Q121: 57415 | R121: 61175 | S121: 67729 | T121: =S121 -> 8556.388 | U121: =U163 -> 6911.9883 | V121: =V163 -> 6955.0491 | W121: =W163 -> 7869.4947 | X121: =X163 -> 7725.6431 | Y121: =X121 -> 7725.6431 | Z121: =Z163 -> 7430.7528 | AA121: =AA163 -> 7655.6891 | AB121: =AB163 -> 8567.8601 | AC121: =AC163 -> 8336.9496 | AD121: =AC121 -> 8336.9496 | AE121: =AE163 -> 9170.6939 | AF121: =AF163 -> 9458.0958 | AG121: =AG163 -> 9735.1316
C122: Inventory | F122: 34170 | G122: 36587 | H122: 35406 | I122: 33318 | J122: =I122 -> 0 | K122: 31147 | L122: 34109 | M122: 36103 | N122: 34214 | O122: =N122 -> 0 | P122: 35864 | Q122: 40825 | R122: 41494 | S122: 38325 | T122: =S122 -> 0 | U122: =U164 -> 0 | V122: =V164 -> 0 | W122: =W164 -> 0 | X122: =X164 -> 0 | Y122: =X122 -> 0 | Z122: =Z164 -> 0 | AA122: =AA164 -> 0 | AB122: =AB164 -> 0 | AC122: =AC164 -> 0 | AD122: =AC122 -> 0 | AE122: =AE164 -> 0 | AF122: =AF164 -> 0 | AG122: =AG164 -> 0
C123: Prepaid & Other Current Assets | F123: 15062 | G123: 14441 | H123: 14564 | I123: 13393 | J123: =I123 -> 37552.851 | K123: 12222 | L123: 17914 | M123: 12960 | N123: 22423 | O123: =N123 -> 40235.206 | P123: 28358 | Q123: 35439 | R123: 27275 | S123: 36219 | T123: =S123 -> 47081.324 | U123: =U165 -> 50334.698 | V123: =V165 -> 58997.556 | W123: =W165 -> 63208.339 | X123: =X165 -> 66708.665 | Y123: =X123 -> 66708.665 | Z123: =Z165 -> 67969.214 | AA123: =AA165 -> 64201.312 | AB123: =AB165 -> 67282.81 | AC123: =AC165 -> 70459.2 | AD123: =AC123 -> 70459.2 | AE123: =AE165 -> 77211.716 | AF123: =AF165 -> 78168.048 | AG123: =AG165 -> 80448.789
C124: Total Current Assets | F124: =SUM(F120:F123) -> 45790.592 | G124: =SUM(G120:G123) -> 47466.887 | H124: =SUM(H120:H123) -> 49823.332 | I124: =SUM(I120:I123) -> 50795.513 | J124: =I124 -> 50795.513 | K124: =SUM(K120:K123) -> 53217.637 | L124: =SUM(L120:L123) -> 56140.105 | M124: =SUM(M120:M123) -> 56949.483 | N124: =SUM(N120:N123) -> 58213.464 | O124: =N124 -> 58213.464 | P124: =SUM(P120:P123) -> 63830.586 | Q124: =SUM(Q120:Q123) -> 60924.483 | R124: =SUM(R120:R123) -> 62919.829 | S124: =SUM(S120:S123) -> 69681.601 | T124: =S124 -> 69681.601 | U124: =SUM(U120:U123) -> 71353.698 | V124: =SUM(V120:V123) -> 76889.178 | W124: =SUM(W120:W123) -> 80500.903 | X124: =SUM(X120:X123) -> 83470.257 | Y124: =X124 -> 83470.257 | Z124: =SUM(Z120:Z123) -> 78496.682 | AA124: =SUM(AA120:AA123) -> 82624.259 | AB124: =SUM(AB120:AB123) -> 85934.619 | AC124: =SUM(AC120:AC123) -> 88604.874 | AD124: =AC124 -> 88604.874 | AE124: =SUM(AE120:AE123) -> 91943.713 | AF124: =SUM(AF120:AF123) -> 96044.537 | AG124: =SUM(AG120:AG123) -> 100236.33
C125: PP&E, Net
F126: 904.064 | G126: 907.234 | H126: 929.903 | I126: 1065.68 | J126: =I126 -> 1065.68 | K126: 1103.49 | L126: 1206.489 | M126: 1229.028 | N126: 1194.72 | O126: =N126 -> 1194.72 | P126: 1217.202 | Q126: 1235.343 | R126: 1255 | S126: 1246.47 | T126: =S126 -> 1246.47 | U126: =U199 -> 1250.5117 | V126: =V199 -> 1254.4012 | W126: =W199 -> 1252.1224 | X126: =X199 -> 1250.7918 | Y126: =X126 -> 1250.7918 | Z126: =Z199 -> 1251.9023 | AA126: =AA199 -> 1251.6051 | AB126: =AB199 -> 1244.9303 | AC126: =AC199 -> 1238.5756 | AD126: =AC126 -> 1238.5756 | AE126: =AE199 -> 1212.2213 | AF126: =AF199 -> 1172.1541 | AG126: =AG199 -> 1117.4596
C127: Intangible Assets, Net | F127: 0 | G127: 0 | H127: 0 | I127: 6540 | J127: =I127 -> 0 | K127: 0 | L127: 0 | M127: 0 | N127: 7439 | O127: =N127 -> 0 | P127: 0 | Q127: 0 | R127: 0 | S127: 8034 | T127: =S127 -> 0 | U127: =U213 -> 0 | V127: =V213 -> 0 | W127: =W213 -> 0 | X127: =X213 -> 0 | Y127: =X127 -> 0 | Z127: =Z213 -> 0 | AA127: =AA213 -> 0 | AB127: =AB213 -> 0 | AC127: =AC213 -> 0 | AD127: =AC127 -> 0 | AE127: =AE213 -> 0 | AF127: =AF213 -> 0 | AG127: =AG213 -> 0
...

Sheet Segment Analysis
C1: =Company_Name&" - "&MID(CELL("filename",A1),FIND("]",CELL("filename",A1))+1,255)&": "&Case_Scenario&" Case" -> Jefferies Financial Group Inc. - Segment Analysis: Base Case
C2: =Cover!C2 -> $ in Millions Except Per Share Data
C5: Segment Analysis | F5: =Model!F63 -> 1Q23 | G5: =Model!G63 -> 2Q23 | H5: =Model!H63 -> 3Q23 | I5: =Model!I63 -> 4Q23 | J5: =Model!J63 -> 2023 | K5: =Model!K63 -> 1Q24 | L5: =Model!L63 -> 2Q24 | M5: =Model!M63 -> 3Q24 | ... AG5: =Model!AG63 -> 2030e
C6: Drivers
C7: Total Company Revenue | F7: =SUM(F8:F13) -> 1780.56 | G7: =SUM(G8:G13) -> 1651.242 | H7: =SUM(H8:H13) -> 2040.888 | I7: =SUM(I8:I13) -> 1968.69 | J7: =SUM(F7:I7) -> 7441.38 | K7: =SUM(K8:K13) -> 2551.9 | L7: =SUM(L8:L13) -> 2516.23 | M7: =SUM(M8:M13) -> 2595.48 | N7: =SUM(N8:N13) -> 2851.459 | O7: =SUM(K7:N7) -> 10515.069 | P7: =SUM(P8:P13) -> 2472.864 | Q7: =SUM(Q8:Q13) -> 2494.315 | R7: =SUM(R8:R13) -> 2907.674 | S7: =SUM(S8:S13) -> 2948.824 | T7: =SUM(P7:S7) -> 10823.677 | U7: =SUM(U8:U13) -> 2742.8525 | V7: =SUM(V8:V13) -> 2804.4553 | W7: =SUM(W8:W13) -> 3225.2028 | X7: =SUM(X8:X13) -> 3219.018 | Y7: =SUM(U7:X7) -> 11991.529 | Z7: =SUM(Z8:Z13) -> 2948.7114 | AA7: =SUM(AA8:AA13) -> 3086.9714 | AB7: =SUM(AB8:AB13) -> 3511.4181 | AC7: =SUM(AC8:AC13) -> 3473.729 | AD7: =SUM(Z7:AC7) -> 13020.83 | AE7: =SUM(AE8:AE13) -> 13894.991 | AF7: =SUM(AF8:AF13) -> 14550.917 | AG7: =SUM(AG8:AG13) -> 14977.126
C8: =C16&" Revenue" -> Investment Banking Revenue | F8: =502.79+497.24+213.27+531.38 -> 1744.68 | G8: =492.5+320.9+235.312+632.7 -> 1681.412 | H8: =600.19+353.37+223.7+898.04 -> 2075.3 | I8: =(2169.36+1413.28+905.66+2868.67)-SUM(F8:H8) -> 1855.578 | J8: =SUM(F8:I8) -> 7356.97 | K8: =679.1+640.7+245.5+819.5 -> 2384.8 | L8: =738.58+416.19+271.78+879.72 -> 2306.27 | M8: =927.1+324.05+936.78+271.1 -> 2459.03 | N8: =3309.06+1816.963+1085.349+3543.497-SUM(K8:M8) -> 2604.769 | O8: =SUM(K8:N8) -> 9754.869 | P8: =729.51+407.23+288.3+845.171 -> 2270.211 | Q8: =789.269+338.507+353.233+878.025 -> 2359.034 | R8: =1088.197+486.893+325.178+846.894 -> 2747.162 | S8: =+(3799.29+1610.96+1322.753+3402.317)-SUM(P8:R8) -> 2758.913 | T8: =SUM(P8:S8) -> 10135.32 | U8: ='Revenue Build'!U32 -> 2519.9342 | V8: ='Revenue Build'!V32 -> 2642.1181 | W8: ='Revenue Build'!W32 -> 3063.0856 | X8: ='Revenue Build'!X32 -> 3034.8043 | Y8: =SUM(U8:X8) -> 11259.942 | Z8: ='Revenue Build'!Z32 -> 2797.127 | AA8: ='Revenue Build'!AA32 -> 2932.7511 | AB8: ='Revenue Build'!AB32 -> 3338.7633 | AC8: ='Revenue Build'!AC32 -> 3307.9367 | AD8: =SUM(Z8:AC8) -> 12376.578 | AE8: ='Revenue Build'!AE32 -> 13366.704 | AF8: ='Revenue Build'!AF32 -> 14101.873 | AG8: ='Revenue Build'!AG32 -> 14595.439
C9: =C17 -> Principal Transactions Revenue | F9: =38.98+(-3.1) -> 35.88 | G9: =14+(-44.17) -> -30.17 | H9: =14.8+(-49.212) -> -34.412 | I9: =(82.57+1.84)-SUM(F9:H9) -> 113.112 | J9: =SUM(F9:I9) -> 84.41 | K9: =50.4+116.7 -> 167.1 | L9: =11.76+198.2 -> 209.96 | M9: =11.85+124.6 -> 136.45 | N9: =86.106+674.094-SUM(K9:M9) -> 246.69 | O9: =SUM(K9:N9) -> 760.2 | P9: =85.408+117.245 -> 202.653 | Q9: =20.076+115.205 -> 135.281 | R9: =13.079+147.433 -> 160.512 | S9: =130.673+557.684-SUM(P9:R9) -> 189.911 | T9: =SUM(P9:S9) -> 688.357 | U9: ='Revenue Build'!U35 -> 222.9183 | V9: ='Revenue Build'!V35 -> 162.3372 | W9: ='Revenue Build'!W35 -> 162.11712 | X9: ='Revenue Build'!X35 -> 184.21367 | Y9: =SUM(U9:X9) -> 731.58629 | Z9: ='Revenue Build'!Z35 -> 151.58444 | AA9: ='Revenue Build'!AA35 -> 154.22034 | AB9: ='Revenue Build'!AB35 -> 172.65473 | AC9: ='Revenue Build'!AC35 -> 165.7923 | AD9: =SUM(Z9:AC9) -> 644.25182 | AE9: ='Revenue Build'!AE35 -> 528.28649 | AF9: ='Revenue Build'!AF35 -> 449.04352 | AG9: ='Revenue Build'!AG35 -> 381.68699
