Workbook
Name _bdm.146e958bbea04416b86a4d5943392c04.edm: Model!$M$102
Name _bdm.bf5a9ed53fe44c598e3cfb84ac34b21f.edm: Integrity!$F$37
Name al: '[3]2010 Labor Rates 091130'!$A$161
Name al09salary: '[3]Salaries'!$G$13
Name al10salary: '[3]Salaries'!$K$13
Name alid: '[3]2010 Labor Rates 091130'!$E$168
Name alname: '[3]Salaries'!$A$13
Name aprpto: '[3]Vacation'!$I$56
Name augpto: '[3]Vacation'!$M$56
Name avg_Health_and_Welfare: '[4]PBCFringe'!$Q$22
Name bf: '[3]2010 Labor Rates 091130'!$A$239
Name bf09salary: '[3]Salaries'!$G$18
Name bf10salary: '[3]Salaries'!$K$18
Name bfid: '[3]2010 Labor Rates 091130'!$E$246
Name bfname: '[3]Salaries'!$A$18
Name Bonus_estimate_2011: '[4]PBCFringe'!$B$100
Name Case_Scenario: Cover!$F$22
Name cc: '[3]2010 Labor Rates 091130'!$A$135
Name cc09salary: '[3]Salaries'!$G$11
Name cc10salary: '[3]Salaries'!$K$11
Name ccid: '[3]2010 Labor Rates 091130'!$E$142
Name ccname: '[3]Salaries'!$A$11
Name Ccy: '[5]data'!$A$5
Name cf: '[3]2010 Labor Rates 091130'!$A$148
Name cf09salary: '[3]Salaries'!$G$12
Name cf10salary: '[3]Salaries'!$K$12
Name cfid: '[3]2010 Labor Rates 091130'!$E$155
Name cfname: '[3]Salaries'!$A$12
Name ck: '[3]2010 Labor Rates 091130'!$A$213
Name ck09salary: '[3]Salaries'!$G$17
Name ck10salary: '[3]Salaries'!$K$17
Name ckid: '[3]2010 Labor Rates 091130'!$E$220
Name ckname: '[3]Salaries'!$A$17
Name Company_Cyclical_Multiples_Data: 'Multiples Data'!$C$14:$H$26
Name Company_Name: Cover!$F$19
Name Company_Rev_Methodology: 'Revenue Build'!$C$7
Name Cost_of_Debt: WACC!$G$17
Name Cost_of_Equity: WACC!$G$25
Name Cost_of_Preferred: WACC!$G$10
Name cs: '[3]2010 Labor Rates 091130'!$A$252
Name cs09salary: '[3]Salaries'!$G$19
Name cs10salary: '[3]Salaries'!$K$19
Name csid: '[3]2010 Labor Rates 091130'!$E$259
Name csname: '[3]Salaries'!$A$19
Name Current_Date: Cover!$F$27
Name CV: '[3]2010 Labor Rates 091130'!$A$5
Name cv09salary: '[3]Salaries'!$G$2
Name cv10salary: '[3]Salaries'!$K$2
Name cvid: '[3]2010 Labor Rates 091130'!$E$12
Name cvname: '[3]Salaries'!$A$2
Name Cycle_Period_Toggle: Valuation!$G$221
Name Cycle_Toggle: Valuation!$G$220
Name Cyclical_LTM_NTM_Toggle: Valuation!$G$222
Name Cyclical_Peer_Group_Toggle: Valuation!$G$223
Name Data: Model!$C$25:$AK$162
Name decpto: '[3]Vacation'!$Q$56
Name Denominator: '[5]data'!$A$6
Name df09salary: '[3]Salaries'!$G$26
Name df10salary: '[3]Salaries'!$K$26
Name dff: '[9]Salaries'!$A$26

Sheet Cover
C1: =Company_Name&" - "&MID(CELL("filename",A1),FIND("]",CELL("filename",A1))+1,255)&": "&Case_Scenario&" Case" -> Republic Services, Inc. - Cover: Base Case | Q1: Font Toggle
C2: $ in Millions Except Per Share Data | Q2: Report
R3: x
A4: x | C4: Model Assumptions: | I4: Return Summary:
I6: Discounted Cash Flow Analysis | N6: Multiple Analysis
I8: Exit Multiple Method | N8: EV/EBITDA Method
I9: Implied Enterprise Value: | L9: =Valuation!K65 -> 89474.779 | P9: Target Price: | Q9: % Return:
I10: Implied Equity Value: | L10: =Valuation!K72 -> 76784.353
N11: 1 Year LTM EV/EBITDA | P11: =Valuation!O137 -> 230.35445 | Q11: =Valuation!O138 -> 0.11524791
I12: Implied Share Price: | L12: =Valuation!K76 -> 245.86728
I13: % Return: | L13: =Valuation!K77 -> 0.19035238 | N13: 2013-2022 Late Cycle EV/EBITDA | P13: =Valuation!O215 -> 212.86147 | Q13: =Valuation!O216 -> 0.030556621
I15: Perpetuity Growth Method | N15: P/E Multiple Method
I16: Implied Enterprise Value: | L16: =Valuation!S65 -> 95925.297 | P16: Target Price: | Q16: % Return:
I17: Implied Equity Value: | L17: =Valuation!S72 -> 83234.871
N18: 1 Year LTM P/E | P18: =Valuation!F126 -> #DIV/0! | Q18: =Valuation!F127 -> #DIV/0!
C19: Company Name | F19: Republic Services, Inc. | I19: Implied Share Price: | L19: =Valuation!S76 -> 266.52216
C20: Ticker | F20: RSG | I20: % Return: | L20: =Valuation!S77 -> 0.29035179 | N20: 2013-2022 Late Cycle P/E | P20: =Valuation!F204 -> #DIV/0! | Q20: =Valuation!F205 -> #DIV/0!
C22: Case Scenario | F22: Base | I22: Table of Contents
C24: Last Fiscal Year | F24: 45705 | I24: Cover
C25: Next Fiscal Year | F25: =Last_FYE+366 -> 46071 | I25: Summary
C26: Last Fiscal Quarter Reported | F26: 4Q | I26: Football Field
C27: Current Valuation Date | F27: 46145 | I27: Integrity
I28: Revenue Build
C29: Current Share Price | F29: 206.55 | I29: Model
C30: 52-Week High | F30: 258.75 | I30: Segment Analysis
C31: 52-Week Low | F31: 201.42 | I31: Drivers
I32: WACC
C33: Effective Tax Rate | F33: 0.1776 | I33: Valuation
C34: Dividend Yield | F34: 0.0116 | I34: Comparables
C35: Diluted Shares Outstanding (MRQ) | F35: =IF(Last_FQR="1Q",Model!U287,IF(Last_FQR="2Q",Model!V287,IF(Last_FQR="3Q",Model!W287,Model!X287))) -> 0 | I35: Charts
I36: Benchmark
C37: Model Type | F37: Top Down | I37: Multiples Data
I38: Pre-Earnings
I39: Post-Earnings
A42: x
C43: Model Color Legend | I43: Constants
C44: Blue = Hard-Coded Value (historical values & assumptions) | I44: Reference | J44: Type | K44: Name | L44: Value
C45: Black = Formulas | I45: Million | J45: (#) | K45: Mil | L45: 1000000
C46: Green = Linked Value (from separate worksheet) | I46: Thousand | J46: (#) | K46: Thou | L46: 1000
C47: Red = Unique Formula / Anomaly | I47: Hundred | J47: (#) | K47: Hun | L47: 100
A48: x
C49: Tab Color Codes
C51: Summary
C53: Model
A54: x
C55: Supporting/Auxiliary
C57: Valuation
C59: Comps
C61: RBG Codes for Model
C63: 0-0-255 | F63: Hard-Coded Numbers
C65: 0-128-0 | F65: Linked Numbers
C67: 255-223-159 | F67: Owl Fund Gold
C69: 255-255-153 | F69: Drivers / Assumptions
C71: 118-0-0 | F71: Owl Fund Red
C73: 0-56-96 | F73: Section Headers
C75: 192-222-246 | F75: Sub-Section Headers
C77: 215-215-215 | F77: Historical Quarters
C79: 235-235-235 | F79: Projected Quarters
C81: 255-255-255 | F81: Annuals
A83: x | B83: x | C83: END

Sheet Summary
C1: =Company_Name&" - "&MID(CELL("filename",A1),FIND("]",CELL("filename",A1))+1,255)&": "&Case_Scenario&" Case" -> Republic Services, Inc. - Summary: Base Case
C2: =Cover!C2 -> $ in Millions Except Per Share Data
C4: Year: | T4: =Model!J24 -> 2023 | U4: =Model!O24 -> 2024 | V4: =Model!T24 -> 2025 | W4: =Model!Y24 -> 2026 | X4: =Model!AD24 -> 2027 | Y4: =Model!AE24 -> 2028 | Z4: =Model!AF24 -> 2029 | AA4: =Model!AG24 -> 2030
G5: Quarterly | T5: Annuals | AC5: CAGR | AE5: CAGR
A6: x | C6: ="Consolidated "&Model!C25 -> Consolidated Income Statement | G6: =Model!P25 -> 1Q25 | H6: =Model!Q25 -> 2Q25 | I6: =Model!R25 -> 3Q25 | J6: =Model!S25 -> 4Q25 | K6: =Model!U25 -> 1Q26e | L6: =Model!V25 -> 2Q26e | M6: =Model!W25 -> 3Q26 | N6: =Model!X25 -> 4Q26e | O6: =Model!Z25 -> 1Q27e | P6: =Model!AA25 -> 2Q27e | Q6: =Model!AB25 -> 3Q27e | R6: =Model!AC25 -> 4Q27e | T6: =Model!J25 -> 2023 | U6: =Model!O25 -> 2024 | V6: =Model!T25 -> 2025 | W6: =Model!Y25 -> 2026e | X6: =Model!AD25 -> 2027e | Y6: =Model!AE25 -> 2028e | Z6: =Model!AF25 -> 2029e | AA6: =Model!AG25 -> 2030e | AC6: Historical | AE6: Projected
C8: =Model!C28 -> Revenue | G8: =Model!P28 -> 4009 | H8: =Model!Q28 -> 4235 | I8: =Model!R28 -> 4212 | J8: =Model!S28 -> 4136 | K8: =Model!U28 -> 4152.631 | L8: =Model!V28 -> 4379.486 | M8: =Model!W28 -> 4358.186 | N8: =Model!X28 -> 4435.8154 | O8: =Model!Z28 -> 4358.6652 | P8: =Model!AA28 -> 4593.3476 | Q8: =Model!AB28 -> 4573.9711 | R8: =Model!AC28 -> 4522.6788 | T8: =Model!J28 -> 14964.5 | U8: =Model!O28 -> 16031.9 | V8: =Model!T28 -> 16592 | W8: =Model!Y28 -> 17326.118 | X8: =Model!AD28 -> 18048.663 | Y8: =Model!AE28 -> 18921.749 | Z8: =Model!AF28 -> 19882.733 | AA8: =Model!AG28 -> 20839.079 | AC8: =IFERROR((V8/T8)^(1/(V$4-T$4))-1,"N/A") -> 0.052975495 | AE8: =IFERROR((AA8/V8)^(1/(AA$4-V$4))-1,"N/A") -> 0.046636692
C9: YoY % Growth | K9: =K8/G8-1 -> 0.035827139 | L9: =L8/H8-1 -> 0.034117119 | M9: =M8/I8-1 -> 0.034707028 | N9: =N8/J8-1 -> 0.072489227 | O9: =O8/K8-1 -> 0.049615333 | P9: =P8/L8-1 -> 0.048832572 | Q9: =Q8/M8-1 -> 0.049512595 | R9: =R8/N8-1 -> 0.019582282 | U9: =IF(ISERROR(U8/T8-1),"NA",(U8/T8-1)) -> 0.071328812 | V9: =IF(ISERROR(V8/U8-1),"NA",(V8/U8-1)) -> 0.034936595 | W9: =IF(ISERROR(W8/V8-1),"NA",(W8/V8-1)) -> 0.044245326 | X9: =IF(ISERROR(X8/W8-1),"NA",(X8/W8-1)) -> 0.041702602 | Y9: =IF(ISERROR(Y8/X8-1),"NA",(Y8/X8-1)) -> 0.048374028 | Z9: =IF(ISERROR(Z8/Y8-1),"NA",(Z8/Y8-1)) -> 0.050787257 | AA9: =IF(ISERROR(AA8/Z8-1),"NA",(AA8/Z8-1)) -> 0.048099317
C11: =Model!C30 -> Gross Profit | G11: =Model!P30 -> 4009 | H11: =Model!Q30 -> 4235 | I11: =Model!R30 -> 4212 | J11: =Model!S30 -> 4136 | K11: =Model!U30 -> 4152.631 | L11: =Model!V30 -> 4379.486 | M11: =Model!W30 -> 4358.186 | N11: =Model!X30 -> 1880.7857 | O11: =Model!Z30 -> 1865.5087 | P11: =Model!AA30 -> 1952.1727 | Q11: =Model!AB30 -> 1957.6596 | R11: =Model!AC30 -> 1935.7065 | T11: =Model!J30 -> 14964.5 | U11: =Model!O30 -> 16031.9 | V11: =Model!T30 -> 16592 | W11: =Model!Y30 -> 14771.089 | X11: =Model!AD30 -> 7711.0476 | Y11: =Model!AE30 -> 8155.2739 | Z11: =Model!AF30 -> 8509.8097 | AA11: =Model!AG30 -> 8919.1257 | AC11: =IFERROR((V11/T11)^(1/(V$4-T$4))-1,"N/A") -> 0.052975495 | AE11: =IFERROR((AA11/V11)^(1/(AA$4-V$4))-1,"N/A") -> -0.11674784
C12: % Margin | G12: =G11/G$8 -> 1 | H12: =H11/H$8 -> 1 | I12: =I11/I$8 -> 1 | J12: =J11/J$8 -> 1 | K12: =K11/K$8 -> 1 | L12: =L11/L$8 -> 1 | M12: =M11/M$8 -> 1 | N12: =N11/N$8 -> 0.424 | ... R12: =R11/R$8 -> 0.428 | T12: =T11/T$8 -> 1 | U12: =U11/U$8 -> 1 | V12: =V11/V$8 -> 1 | W12: =W11/W$8 -> 0.85253306 | X12: =X11/X$8 -> 0.42723651 | Y12: =Y11/Y$8 -> 0.431 | Z12: =Z11/Z$8 -> 0.428 | AA12: =AA11/AA$8 -> 0.428
C13: YoY % Growth | K13: =K11/G11-1 -> 0.035827139 | L13: =L11/H11-1 -> 0.034117119 | M13: =M11/I11-1 -> 0.034707028 | N13: =N11/J11-1 -> -0.54526457 | O13: =O11/K11-1 -> -0.55076464 | P13: =P11/L11-1 -> -0.55424616 | Q13: =Q11/M11-1 -> -0.55080861 | R13: =R11/N11-1 -> 0.029200983 | U13: =U11/T11-1 -> 0.071328812 | V13: =V11/U11-1 -> 0.034936595 | W13: =W11/V11-1 -> -0.10974634 | X13: =X11/W11-1 -> -0.47796349 | Y13: =Y11/X11-1 -> 0.057609075 | Z13: =Z11/Y11-1 -> 0.043473193 | AA13: =AA11/Z11-1 -> 0.048099317
C15: =Model!C36 -> EBIT | G15: =Model!P36 -> 4009 | H15: =Model!Q36 -> 4235 | I15: =Model!R36 -> 4212 | J15: =Model!S36 -> 4136 | K15: =Model!U36 -> 4152.631 | L15: =Model!V36 -> 4379.486 | M15: =Model!W36 -> 4358.186 | N15: =Model!X36 -> 893.95769 | O15: =Model!Z36 -> 887.68351 | P15: =Model!AA36 -> 974.754 | Q15: =Model!AB36 -> 981.59418 | R15: =Model!AC36 -> 950.48416 | T15: =Model!J36 -> 14964.5 | U15: =Model!O36 -> 16031.9 | V15: =Model!T36 -> 16592 | W15: =Model!Y36 -> 3829.2607 | X15: =Model!AD36 -> 3794.5159 | Y15: =Model!AE36 -> 4153.3135 | Z15: =Model!AF36 -> 4316.9821 | AA15: =Model!AG36 -> 4540.3607 | AC15: =IFERROR((V15/T15)^(1/(V$4-T$4))-1,"N/A") -> 0.052975495 | AE15: =IFERROR((AA15/V15)^(1/(AA$4-V$4))-1,"N/A") -> 0.043903065
C16: Margin | G16: =G15/G$8 -> 1 | H16: =H15/H$8 -> 1 | I16: =I15/I$8 -> 1 | J16: =J15/J$8 -> 1 | K16: =K15/K$8 -> 1 | L16: =L15/L$8 -> 1 | M16: =M15/M$8 -> 1 | N16: =N15/N$8 -> 0.20153176 | ... R16: =R15/R$8 -> 0.21015955 | T16: =T15/T$8 -> 1 | U16: =U15/U$8 -> 1 | V16: =V15/V$8 -> 1 | W16: =W15/W$8 -> 0.22101088 | X16: =X15/X$8 -> 0.21023806 | Y16: =Y15/Y$8 -> 0.21949945 | Z16: =Z15/Z$8 -> 0.21712217 | AA16: =AA15/AA$8 -> 0.21787723
C17: YoY % Growth | K17: =K15/G15-1 -> 0.035827139 | L17: =L15/H15-1 -> 0.034117119 | M17: =M15/I15-1 -> 0.034707028 | N17: =N15/J15-1 -> 0.11744711 | O17: =O15/K15-1 -> -0.063260368 | P17: =P15/L15-1 -> -0.030564327 | Q17: =Q15/M15-1 -> -0.00060254999 | R17: =R15/N15-1 -> 0.063231701 | U17: =U15/T15-1 -> 0.071328812 | V17: =V15/U15-1 -> 0.034936595 | W17: =W15/V15-1 -> 0.045503383 | X17: =X15/W15-1 -> -0.0090735113 | Y17: =Y15/X15-1 -> 0.094556896 | Z17: =Z15/Y15-1 -> 0.03940675 | AA17: =AA15/Z15-1 -> 0.051744161
C19: =Model!C45 -> Net Income (Loss) | G19: =Model!P45 -> 4009 | H19: =Model!Q45 -> 4235 | I19: =Model!R45 -> 4212 | J19: =Model!S45 -> 4136 | K19: =Model!U45 -> 4152.631 | L19: =Model!V45 -> 4379.486 | M19: =Model!W45 -> 4358.186 | N19: =Model!X45 -> 566.85193 | O19: =Model!Z45 -> 568.11173 | P19: =Model!AA45 -> 637.59271 | Q19: =Model!AB45 -> 647.98055 | R19: =Model!AC45 -> 628.44699 | T19: =Model!J45 -> 14964.5 | U19: =Model!O45 -> 16031.9 | V19: =Model!T45 -> 16592 | W19: =Model!Y45 -> 2596.1549 | X19: =Model!AD45 -> 2482.132 | Y19: =Model!AE45 -> 2803.4173 | Z19: =Model!AF45 -> 2919.2989 | AA19: =Model!AG45 -> 3107.5491 | AC19: =IFERROR((V19/T19)^(1/(V$4-T$4))-1,"N/A") -> 0.052975495 | AE19: =IFERROR((AA19/V19)^(1/(AA$4-V$4))-1,"N/A") -> 0.040618282
C20: Margin | G20: =G19/G$8 -> 1 | H20: =H19/H$8 -> 1 | I20: =I19/I$8 -> 1 | J20: =J19/J$8 -> 1 | K20: =K19/K$8 -> 1 | L20: =L19/L$8 -> 1 | M20: =M19/M$8 -> 1 | N20: =N19/N$8 -> 0.12778979 | ... R20: =R19/R$8 -> 0.13895459 | T20: =T19/T$8 -> 1 | U20: =U19/U$8 -> 1 | V20: =V19/V$8 -> 1 | W20: =W19/W$8 -> 0.14984054 | X20: =X19/X$8 -> 0.13752443 | Y20: =Y19/Y$8 -> 0.14815846 | Z20: =Z19/Z$8 -> 0.14682584 | AA20: =AA19/AA$8 -> 0.14912123
C21: YoY % Growth | K21: =K19/G19-1 -> 0.035827139 | L21: =L19/H19-1 -> 0.034117119 | M21: =M19/I19-1 -> 0.034707028 | N21: =N19/J19-1 -> 0.040095278 | O21: =O19/K19-1 -> -0.11042257 | P21: =P19/L19-1 -> -0.081921435 | Q21: =Q19/M19-1 -> -0.069242201 | R21: =R19/N19-1 -> 0.10866165 | U21: =U19/T19-1 -> 0.071328812 | V21: =V19/U19-1 -> 0.034936595 | W21: =W19/V19-1 -> 0.01945925 | X21: =X19/W19-1 -> -0.043919933 | Y21: =Y19/X19-1 -> 0.12943926 | Z21: =Z19/Y19-1 -> 0.041335835 | AA21: =AA19/Z19-1 -> 0.064484719
C23: =Model!C57 -> Adj. EPS (Diluted) | G23: =Model!P57 -> #DIV/0! | H23: =Model!Q57 -> #DIV/0! | I23: =Model!R57 -> #DIV/0! | J23: =Model!S57 -> #DIV/0! | K23: =Model!U57 -> #DIV/0! | L23: =Model!V57 -> #DIV/0! | M23: =Model!W57 -> #DIV/0! | N23: =Model!X57 -> 1.8150878 | O23: =Model!Z57 -> 1.8278218 | P23: =Model!AA57 -> 2.0612254 | Q23: =Model!AB57 -> 2.0948074 | R23: =Model!AC57 -> 2.0316588 | T23: =Model!J57 -> #DIV/0! | U23: =Model!O57 -> #DIV/0! | V23: =Model!T57 -> #DIV/0! | W23: =Model!Y57 -> 8.3010549 | X23: =Model!AD57 -> 8.0146684 | Y23: =Model!AE57 -> 9.1030862 | Z23: =Model!AF57 -> 9.5676296 | AA23: =Model!AG57 -> 10.283124 | AC23: =IFERROR((V23/T23)^(1/(V$4-T$4))-1,"N/A") -> N/A | AE23: =IFERROR((AA23/V23)^(1/(AA$4-V$4))-1,"N/A") -> 0.04917992
C24: YoY % Growth | K24: =K23/G23-1 -> #DIV/0! | L24: =L23/H23-1 -> #DIV/0! | M24: =M23/I23-1 -> #DIV/0! | N24: =N23/J23-1 -> 0.045090932 | O24: =O23/K23-1 -> -0.10330601 | P24: =P23/L23-1 -> -0.069832904 | Q24: =Q23/M23-1 -> -0.061199287 | R24: =R23/N23-1 -> 0.11931711 | U24: =IF(ISERROR(U23/T23-1),"NA",(U23/T23-1)) -> NA | V24: =IF(ISERROR(V23/U23-1),"NA",(V23/U23-1)) -> NA | W24: =IF(ISERROR(W23/V23-1),"NA",(W23/V23-1)) -> 0.026261562 | X24: =IF(ISERROR(X23/W23-1),"NA",(X23/W23-1)) -> -0.034500014 | Y24: =IF(ISERROR(Y23/X23-1),"NA",(Y23/X23-1)) -> 0.13580322 | Z24: =IF(ISERROR(Z23/Y23-1),"NA",(Z23/Y23-1)) -> 0.051031418 | AA24: =IF(ISERROR(AA23/Z23-1),"NA",(AA23/Z23-1)) -> 0.07478283
C27: =Model!C61 -> EBITDA | G27: =Model!P61 -> 4009 | H27: =Model!Q61 -> 4235 | I27: =Model!R61 -> 4212 | J27: =Model!S61 -> 4136 | K27: =Model!U61 -> 4152.631 | L27: =Model!V61 -> 4379.486 | M27: =Model!W61 -> 4358.186 | N27: =Model!X61 -> 1388.4102 | O27: =Model!Z61 -> 1372.9795 | P27: =Model!AA61 -> 1460.6845 | Q27: =Model!AB61 -> 1468.2447 | R27: =Model!AC61 -> 1438.2119 | T27: =Model!J61 -> 14964.5 | U27: =Model!O61 -> 16031.9 | V27: =Model!T61 -> 16592 | W27: =Model!Y61 -> 5679.7132 | X27: =Model!AD61 -> 5740.1206 | Y27: =Model!AE61 -> 6130.6467 | Z27: =Model!AF61 -> 6402.24 | AA27: =Model!AG61 -> 6731.0225 | AC27: =IFERROR((V27/T27)^(1/(V$4-T$4))-1,"N/A") -> 0.052975495 | AE27: =IFERROR((AA27/V27)^(1/(AA$4-V$4))-1,"N/A") -> 0.046809263
C28: Margin | G28: =G27/G$8 -> 1 | H28: =H27/H$8 -> 1 | I28: =I27/I$8 -> 1 | J28: =J27/J$8 -> 1 | K28: =K27/K$8 -> 1 | L28: =L27/L$8 -> 1 | M28: =M27/M$8 -> 1 | N28: =N27/N$8 -> 0.313 | ... R28: =R27/R$8 -> 0.318 | T28: =T27/T$8 -> 1 | U28: =U27/U$8 -> 1 | V28: =V27/V$8 -> 1 | W28: =W27/W$8 -> 0.32781221 | X28: =X27/X$8 -> 0.31803579 | Y28: =Y27/Y$8 -> 0.324 | Z28: =Z27/Z$8 -> 0.322 | AA28: =AA27/AA$8 -> 0.323
C29: YoY % Growth | K29: =K27/G27-1 -> 0.035827139 | L29: =L27/H27-1 -> 0.034117119 | M29: =M27/I27-1 -> 0.034707028 | N29: =N27/J27-1 -> 0.10366473 | O29: =O27/K27-1 -> -0.0062617817 | P29: =P27/L27-1 -> -0.0053125968 | Q29: =Q27/M27-1 -> 0.018775316 | R29: =R27/N27-1 -> 0.035869539 | U29: =U27/T27-1 -> 0.071328812 | V29: =V27/U27-1 -> 0.034936595 | W29: =W27/V27-1 -> 0.060677006 | X29: =X27/W27-1 -> 0.010635645 | Y29: =Y27/X27-1 -> 0.068034474 | Z29: =Z27/Y27-1 -> 0.044300916 | AA29: =AA27/Z27-1 -> 0.051354284
G31: =G$5 -> Quarterly | T31: =T$5 -> Annuals
A32: x | C32: ="Consolidated "&Model!C121 -> Consolidated Balance Sheet | G32: =G$6 -> 1Q25 | H32: =H$6 -> 2Q25 | I32: =I$6 -> 3Q25 | J32: =J$6 -> 4Q25 | K32: =K$6 -> 1Q26e | L32: =L$6 -> 2Q26e | M32: =M$6 -> 3Q26 | N32: =N$6 -> 4Q26e | ... R32: =R$6 -> 4Q27e | T32: =T$6 -> 2023 | U32: =U$6 -> 2024 | V32: =V$6 -> 2025 | W32: =W$6 -> 2026e | X32: =X$6 -> 2027e | Y32: =Y$6 -> 2028e | Z32: =Z$6 -> 2029e | AA32: =AA$6 -> 2030e
C34: =Model!C123 -> Cash & Cash Equivalents | G34: =Model!P123 -> 0 | H34: =Model!Q123 -> 0 | I34: =Model!R123 -> 0 | J34: =Model!S123 -> 0 | K34: =Model!U123 -> 0 | L34: =Model!V123 -> 0 | M34: =Model!W123 -> 0 | N34: =Model!X123 -> 58.332248 | O34: =Model!Z123 -> 57.317699 | P34: =Model!AA123 -> 60.40384 | Q34: =Model!AB123 -> 60.149034 | R34: =Model!AC123 -> 59.474526 | T34: =Model!J123 -> 0 | U34: =Model!O123 -> 0 | V34: =Model!T123 -> 0 | W34: =Model!Y123 -> 58.332248 | X34: =Model!AD123 -> 59.474526 | Y34: =Model!AE123 -> 248.82644 | Z34: =Model!AF123 -> 261.46365 | AA34: =Model!AG123 -> 274.03987
C35: =Model!C124 -> Accounts Receivable | G35: =Model!P124 -> 0 | H35: =Model!Q124 -> 0 | I35: =Model!R124 -> 0 | J35: =Model!S124 -> 0 | K35: =Model!U124 -> 0 | L35: =Model!V124 -> 0 | M35: =Model!W124 -> 0 | N35: =Model!X124 -> 2015.4031 | O35: =Model!Z124 -> 1973.3737 | P35: =Model!AA124 -> 2029.1491 | Q35: =Model!AB124 -> 2028.4567 | R35: =Model!AC124 -> 2030.2895 | T35: =Model!J124 -> 0 | U35: =Model!O124 -> 0 | V35: =Model!T124 -> 0 | W35: =Model!Y124 -> 2015.4031 | X35: =Model!AD124 -> 2030.2895 | Y35: =Model!AE124 -> 2156.561 | Z35: =Model!AF124 -> 2233.4029 | AA35: =Model!AG124 -> 2340.828
C36: =Model!C125 -> Inventory | G36: =Model!P125 -> 0 | H36: =Model!Q125 -> 0 | I36: =Model!R125 -> 0 | J36: =Model!S125 -> 0 | K36: =Model!U125 -> 0 | L36: =Model!V125 -> 0 | M36: =Model!W125 -> 0 | N36: =Model!X125 -> 0 | O36: =Model!Z125 -> 0 | P36: =Model!AA125 -> 0 | Q36: =Model!AB125 -> 0 | R36: =Model!AC125 -> 0 | T36: =Model!J125 -> 0 | U36: =Model!O125 -> 0 | V36: =Model!T125 -> 0 | W36: =Model!Y125 -> 0 | X36: =Model!AD125 -> 0 | Y36: =Model!AE125 -> 0 | Z36: =Model!AF125 -> 0 | AA36: =Model!AG125 -> 0
C37: =Model!C126 -> Prepaid & Other Current Assets | G37: =Model!P126 -> 0 | H37: =Model!Q126 -> 0 | I37: =Model!R126 -> 0 | J37: =Model!S126 -> 0 | K37: =Model!U126 -> 0 | L37: =Model!V126 -> 0 | M37: =Model!W126 -> 0 | N37: =Model!X126 -> 461.32481 | O37: =Model!Z126 -> 383.56253 | P37: =Model!AA126 -> 404.21459 | Q37: =Model!AB126 -> 402.50946 | R37: =Model!AC126 -> 397.99574 | T37: =Model!J126 -> 0 | U37: =Model!O126 -> 0 | V37: =Model!T126 -> 0 | W37: =Model!Y126 -> 461.32481 | X37: =Model!AD126 -> 397.99574 | Y37: =Model!AE126 -> 416.27848 | Z37: =Model!AF126 -> 437.42012 | AA37: =Model!AG126 -> 458.45973
C38: =Model!C127 -> Total Current Assets | G38: =SUM(G34:G37) -> 0 | H38: =SUM(H34:H37) -> 0 | I38: =SUM(I34:I37) -> 0 | J38: =SUM(J34:J37) -> 0 | K38: =SUM(K34:K37) -> 0 | L38: =SUM(L34:L37) -> 0 | M38: =SUM(M34:M37) -> 0 | N38: =SUM(N34:N37) -> 2535.0602 | ... R38: =SUM(R34:R37) -> 2487.7598 | T38: =SUM(T34:T37) -> 0 | U38: =SUM(U34:U37) -> 0 | V38: =SUM(V34:V37) -> 0 | W38: =SUM(W34:W37) -> 2535.0602 | X38: =SUM(X34:X37) -> 2487.7598 | Y38: =SUM(Y34:Y37) -> 2821.6659 | Z38: =SUM(Z34:Z37) -> 2932.2867 | AA38: =SUM(AA34:AA37) -> 3073.3276
C40: =Model!C129 -> PP&E, Net | G40: =Model!P129 -> 0 | H40: =Model!Q129 -> 0 | I40: =Model!R129 -> 0 | J40: =Model!S129 -> 0 | K40: =Model!U129 -> 0 | L40: =Model!V129 -> 0 | M40: =Model!W129 -> 0 | N40: =Model!X129 -> 12225.409 | O40: =Model!Z129 -> 12223.925 | P40: =Model!AA129 -> 12261.636 | Q40: =Model!AB129 -> 12278.123 | R40: =Model!AC129 -> 12319.548 | T40: =Model!J129 -> 0 | U40: =Model!O129 -> 0 | V40: =Model!T129 -> 0 | W40: =Model!Y129 -> 12225.409 | X40: =Model!AD129 -> 12319.548 | Y40: =Model!AE129 -> 12397.117 | Z40: =Model!AF129 -> 12427.382 | AA40: =Model!AG129 -> 12466.502
C41: =Model!C130 -> Intangible Assets, Net | G41: =Model!P130 -> 0 | H41: =Model!Q130 -> 0 | I41: =Model!R130 -> 0 | J41: =Model!S130 -> 0 | K41: =Model!U130 -> 0 | L41: =Model!V130 -> 0 | M41: =Model!W130 -> 0 | N41: =Model!X130 -> 0 | O41: =Model!Z130 -> 0 | P41: =Model!AA130 -> 0 | Q41: =Model!AB130 -> 0 | R41: =Model!AC130 -> 0 | T41: =Model!J130 -> 0 | U41: =Model!O130 -> 0 | V41: =Model!T130 -> 0 | W41: =Model!Y130 -> 0 | X41: =Model!AD130 -> 0 | Y41: =Model!AE130 -> 0 | Z41: =Model!AF130 -> 0 | AA41: =Model!AG130 -> 0
C42: =Model!C131 -> Goodwill | G42: =Model!P131 -> 0 | H42: =Model!Q131 -> 0 | I42: =Model!R131 -> 0 | J42: =Model!S131 -> 0 | K42: =Model!U131 -> 0 | L42: =Model!V131 -> 0 | M42: =Model!W131 -> 0 | N42: =Model!X131 -> 0 | O42: =Model!Z131 -> 0 | P42: =Model!AA131 -> 0 | Q42: =Model!AB131 -> 0 | R42: =Model!AC131 -> 0 | T42: =Model!J131 -> 0 | U42: =Model!O131 -> 0 | V42: =Model!T131 -> 0 | W42: =Model!Y131 -> 0 | X42: =Model!AD131 -> 0 | Y42: =Model!AE131 -> 0 | Z42: =Model!AF131 -> 0 | AA42: =Model!AG131 -> 0
C43: =Model!C132 -> Other Non-Current Assets | G43: =Model!P132 -> 0 | H43: =Model!Q132 -> 0 | I43: =Model!R132 -> 0 | J43: =Model!S132 -> 0 | K43: =Model!U132 -> 0 | L43: =Model!V132 -> 0 | M43: =Model!W132 -> 0 | N43: =Model!X132 -> 0 | O43: =Model!Z132 -> 0 | P43: =Model!AA132 -> 0 | Q43: =Model!AB132 -> 0 | R43: =Model!AC132 -> 0 | T43: =Model!J132 -> 0 | U43: =Model!O132 -> 0 | V43: =Model!T132 -> 0 | W43: =Model!Y132 -> 0 | X43: =Model!AD132 -> 0 | Y43: =Model!AE132 -> 0 | Z43: =Model!AF132 -> 0 | AA43: =Model!AG132 -> 0
C44: =Model!C133 -> Total Non-Current Assets | G44: =SUM(G40:G43) -> 0 | H44: =SUM(H40:H43) -> 0 | I44: =SUM(I40:I43) -> 0 | J44: =SUM(J40:J43) -> 0 | K44: =SUM(K40:K43) -> 0 | L44: =SUM(L40:L43) -> 0 | M44: =SUM(M40:M43) -> 0 | N44: =SUM(N40:N43) -> 31362.659 | ... R44: =SUM(R40:R43) -> 31821.827 | T44: =SUM(T40:T43) -> 0 | U44: =SUM(U40:U43) -> 0 | V44: =SUM(V40:V43) -> 0 | W44: =SUM(W40:W43) -> 31362.659 | X44: =SUM(X40:X43) -> 31821.827 | Y44: =SUM(Y40:Y43) -> 32056.277 | Z44: =SUM(Z40:Z43) -> 32251.627 | AA44: =SUM(AA40:AA43) -> 32474.78
C46: =Model!C135 -> Total Assets | G46: =SUM(G38,G44) -> 0 | H46: =SUM(H38,H44) -> 0 | I46: =SUM(I38,I44) -> 0 | J46: =SUM(J38,J44) -> 0 | K46: =SUM(K38,K44) -> 0 | L46: =SUM(L38,L44) -> 0 | M46: =SUM(M38,M44) -> 0 | N46: =SUM(N38,N44) -> 33897.72 | ... R46: =SUM(R38,R44) -> 34309.587 | T46: =SUM(T38,T44) -> 0 | U46: =SUM(U38,U44) -> 0 | V46: =SUM(V38,V44) -> 0 | W46: =SUM(W38,W44) -> 33897.72 | X46: =SUM(X38,X44) -> 34309.587 | Y46: =SUM(Y38,Y44) -> 34877.943 | Z46: =SUM(Z38,Z44) -> 35183.914 | AA46: =SUM(AA38,AA44) -> 35548.108
C48: =Model!C137 -> Accounts Payable | G48: =Model!P137 -> 0 | H48: =Model!Q137 -> 0 | I48: =Model!R137 -> 0 | J48: =Model!S137 -> 0 | K48: =Model!U137 -> 0 | L48: =Model!V137 -> 0 | M48: =Model!W137 -> 0 | N48: =Model!X137 -> 1305.2869 | O48: =Model!Z137 -> 1342.4689 | P48: =Model!AA137 -> 1407.6591 | Q48: =Model!AB137 -> 1379.2512 | R48: =Model!AC137 -> 1349.7247 | T48: =Model!J137 -> 0 | U48: =Model!O137 -> 0 | V48: =Model!T137 -> 0 | W48: =Model!Y137 -> 1305.2869 | X48: =Model!AD137 -> 1349.7247 | Y48: =Model!AE137 -> 1401.1166 | Z48: =Model!AF137 -> 1464.4586 | AA48: =Model!AG137 -> 1534.8981
C49: =Model!C138 -> Accrued Liabilities | G49: =Model!P138 -> 0 | H49: =Model!Q138 -> 0 | I49: =Model!R138 -> 0 | J49: =Model!S138 -> 0 | K49: =Model!U138 -> 0 | L49: =Model!V138 -> 0 | M49: =Model!W138 -> 0 | N49: =Model!X138 -> 153.30178 | O49: =Model!Z138 -> 139.61676 | P49: =Model!AA138 -> 147.90579 | Q49: =Model!AB138 -> 146.51344 | R49: =Model!AC138 -> 144.87045 | T49: =Model!J138 -> 0 | U49: =Model!O138 -> 0 | V49: =Model!T138 -> 0 | W49: =Model!Y138 -> 153.30178 | X49: =Model!AD138 -> 144.87045 | Y49: =Model!AE138 -> 150.73065 | Z49: =Model!AF138 -> 159.22093 | AA49: =Model!AG138 -> 166.87934
C50: =Model!C139 -> Other Current Liabilities | G50: =Model!P139 -> 0 | H50: =Model!Q139 -> 0 | I50: =Model!R139 -> 0 | J50: =Model!S139 -> 0 | K50: =Model!U139 -> 0 | L50: =Model!V139 -> 0 | M50: =Model!W139 -> 0 | N50: =Model!X139 -> 2810.5327 | O50: =Model!Z139 -> 2792.3353 | P50: =Model!AA139 -> 2958.1158 | Q50: =Model!AB139 -> 2930.2688 | R50: =Model!AC139 -> 2897.409 | T50: =Model!J139 -> 0 | U50: =Model!O139 -> 0 | V50: =Model!T139 -> 0 | W50: =Model!Y139 -> 2810.5327 | X50: =Model!AD139 -> 2897.409 | Y50: =Model!AE139 -> 3014.6131 | Z50: =Model!AF139 -> 3184.4185 | AA50: =Model!AG139 -> 3337.5869
C51: =Model!C140 -> Total Current Liabilities (Excl. Debt) | G51: =SUM(G48:G50) -> 0 | H51: =SUM(H48:H50) -> 0 | I51: =SUM(I48:I50) -> 0 | J51: =SUM(J48:J50) -> 0 | K51: =SUM(K48:K50) -> 0 | L51: =SUM(L48:L50) -> 0 | M51: =SUM(M48:M50) -> 0 | N51: =SUM(N48:N50) -> 4269.1214 | ... R51: =SUM(R48:R50) -> 4392.0041 | T51: =SUM(T48:T50) -> 0 | U51: =SUM(U48:U50) -> 0 | V51: =SUM(V48:V50) -> 0 | W51: =SUM(W48:W50) -> 4269.1214 | X51: =SUM(X48:X50) -> 4392.0041 | Y51: =SUM(Y48:Y50) -> 4566.4604 | Z51: =SUM(Z48:Z50) -> 4808.098 | AA51: =SUM(AA48:AA50) -> 5039.3643
C53: =Model!C142 -> Revolver | G53: =Model!P142 -> 0 | H53: =Model!Q142 -> 0 | I53: =Model!R142 -> 0 | J53: =Model!S142 -> 0 | K53: =Model!U142 -> 0 | L53: =Model!V142 -> 0 | M53: =Model!W142 -> 0 | N53: =Model!X142 -> 144.75856 | O53: =Model!Z142 -> 3375.1146 | P53: =Model!AA142 -> 293.00155 | Q53: =Model!AB142 -> 973.40359 | R53: =Model!AC142 -> 892.34028 | T53: =Model!J142 -> 0 | U53: =Model!O142 -> 0 | V53: =Model!T142 -> 0 | W53: =Model!Y142 -> 144.75856 | X53: =Model!AD142 -> 892.34028 | Y53: =Model!AE142 -> 1086.0882 | Z53: =Model!AF142 -> 1691.7654 | AA53: =Model!AG142 -> 2456.6647
C54: =Model!C143 -> LT Debt (Incl. Current Portion) | G54: =Model!P143 -> 0 | H54: =Model!Q143 -> 0 | I54: =Model!R143 -> 0 | J54: =Model!S143 -> 0 | K54: =Model!U143 -> 0 | L54: =Model!V143 -> 0 | M54: =Model!W143 -> 0 | N54: =Model!X143 -> 250 | O54: =Model!Z143 -> 250 | P54: =Model!AA143 -> -350 | Q54: =Model!AB143 -> -950 | R54: =Model!AC143 -> -1550 | T54: =Model!J143 -> 0 | U54: =Model!O143 -> 0 | V54: =Model!T143 -> 0 | W54: =Model!Y143 -> 250 | X54: =Model!AD143 -> -1550 | Y54: =Model!AE143 -> -1550 | Z54: =Model!AF143 -> -2150 | AA54: =Model!AG143 -> -2750
C55: =Model!C144 -> Deferred Income Taxes | G55: =Model!P144 -> 0 | H55: =Model!Q144 -> 0 | I55: =Model!R144 -> 0 | J55: =Model!S144 -> 0 | K55: =Model!U144 -> 0 | L55: =Model!V144 -> 0 | M55: =Model!W144 -> 0 | N55: =Model!X144 -> 1532.4 | O55: =Model!Z144 -> -1592.1112 | P55: =Model!AA144 -> 1783.0035 | Q55: =Model!AB144 -> 1783.0035 | R55: =Model!AC144 -> 2756.407 | T55: =Model!J144 -> 0 | U55: =Model!O144 -> 0 | V55: =Model!T144 -> 0 | W55: =Model!Y144 -> 1532.4 | X55: =Model!AD144 -> 2756.407 | Y55: =Model!AE144 -> 2756.407 | Z55: =Model!AF144 -> 2756.407 | AA55: =Model!AG144 -> 2756.407
C56: =Model!C145 -> Other Non-Current Liabilities | G56: =Model!P145 -> 0 | H56: =Model!Q145 -> 0 | I56: =Model!R145 -> 0 | J56: =Model!S145 -> 0 | K56: =Model!U145 -> 0 | L56: =Model!V145 -> 0 | M56: =Model!W145 -> 0 | N56: =Model!X145 -> 0 | O56: =Model!Z145 -> 0 | P56: =Model!AA145 -> 0 | Q56: =Model!AB145 -> 0 | R56: =Model!AC145 -> 0 | T56: =Model!J145 -> 0 | U56: =Model!O145 -> 0 | V56: =Model!T145 -> 0 | W56: =Model!Y145 -> 0 | X56: =Model!AD145 -> 0 | Y56: =Model!AE145 -> 0 | Z56: =Model!AF145 -> 0 | AA56: =Model!AG145 -> 0
C57: =Model!C146 -> Total Non-Current Liabilities | G57: =SUM(G53:G56) -> 0 | H57: {=INDEX(Data,MATCH($C57,Line_Items,0),MATCH(H$32,Fiscal_Periods,0))} -> 0 | I57: {=INDEX(Data,MATCH($C57,Line_Items,0),MATCH(I$32,Fiscal_Periods,0))} -> 0 | J57: {=INDEX(Data,MATCH($C57,Line_Items,0),MATCH(J$32,Fiscal_Periods,0))} -> 0 | K57: {=INDEX(Data,MATCH($C57,Line_Items,0),MATCH(K$32,Fiscal_Periods,0))} -> 0 | L57: {=INDEX(Data,MATCH($C57,Line_Items,0),MATCH(L$32,Fiscal_Periods,0))} -> 0 | M57: {=INDEX(Data,MATCH($C57,Line_Items,0),MATCH(M$32,Fiscal_Periods,0))} -> 0 | N57: {=INDEX(Data,MATCH($C57,Line_Items,0),MATCH(N$32,Fiscal_Periods,0))} -> 17843.159 | O57: {=INDEX(Data,MATCH($C57,Line_Items,0),MATCH(O$32,Fiscal_Periods,0))} -> 17949.003 | ... R57: {=INDEX(Data,MATCH($C57,Line_Items,0),MATCH(R$32,Fiscal_Periods,0))} -> 18014.747 | T57: {=INDEX(Data,MATCH($C57,Line_Items,0),MATCH(T$32,Fiscal_Periods,0))} -> 0 | U57: {=INDEX(Data,MATCH($C57,Line_Items,0),MATCH(U$32,Fiscal_Periods,0))} -> 0 | V57: {=INDEX(Data,MATCH($C57,Line_Items,0),MATCH(V$32,Fiscal_Periods,0))} -> 0 | W57: {=INDEX(Data,MATCH($C57,Line_Items,0),MATCH(W$32,Fiscal_Periods,0))} -> 17843.159 | X57: {=INDEX(Data,MATCH($C57,Line_Items,0),MATCH(X$32,Fiscal_Periods,0))} -> 18014.747 | Y57: {=INDEX(Data,MATCH($C57,Line_Items,0),MATCH(Y$32,Fiscal_Periods,0))} -> 18208.495 | Z57: {=INDEX(Data,MATCH($C57,Line_Items,0),MATCH(Z$32,Fiscal_Periods,0))} -> 18214.172 | AA57: {=INDEX(Data,MATCH($C57,Line_Items,0),MATCH(AA$32,Fiscal_Periods,0))} -> 18379.072
C59: =Model!C148 -> Total Liabilities | G59: =SUM(G51,G57) -> 0 | H59: =SUM(H51,H57) -> 0 | I59: =SUM(I51,I57) -> 0 | J59: =SUM(J51,J57) -> 0 | K59: =SUM(K51,K57) -> 0 | L59: =SUM(L51,L57) -> 0 | M59: =SUM(M51,M57) -> 0 | N59: =SUM(N51,N57) -> 22112.28 | ... R59: =SUM(R51,R57) -> 22406.751 | T59: =SUM(T51,T57) -> 0 | U59: =SUM(U51,U57) -> 0 | V59: =SUM(V51,V57) -> 0 | W59: =SUM(W51,W57) -> 22112.28 | X59: =SUM(X51,X57) -> 22406.751 | Y59: =SUM(Y51,Y57) -> 22774.956 | Z59: =SUM(Z51,Z57) -> 23022.27 | AA59: =SUM(AA51,AA57) -> 23418.436
C61: =Model!C150 -> Common Stock & APIC | G61: =Model!P150 -> 0 | H61: =Model!Q150 -> 0 | I61: =Model!R150 -> 0 | J61: =Model!S150 -> 0 | K61: =Model!U150 -> 0 | L61: =Model!V150 -> 0 | M61: =Model!W150 -> 0 | N61: =Model!X150 -> 0 | O61: =Model!Z150 -> 0 | P61: =Model!AA150 -> 0 | Q61: =Model!AB150 -> 0 | R61: =Model!AC150 -> 0 | T61: =Model!J150 -> 0 | U61: =Model!O150 -> 0 | V61: =Model!T150 -> 0 | W61: =Model!Y150 -> 0 | X61: =Model!AD150 -> 0 | Y61: =Model!AE150 -> 0 | Z61: =Model!AF150 -> 0 | AA61: =Model!AG150 -> 0
C62: =Model!C151 -> Retained Earnings | G62: =Model!P151 -> 0 | H62: =Model!Q151 -> 0 | I62: =Model!R151 -> 0 | J62: =Model!S151 -> 0 | K62: =Model!U151 -> 0 | L62: =Model!V151 -> 0 | M62: =Model!W151 -> 0 | N62: =Model!X151 -> 10689.852 | O62: =Model!Z151 -> 11058.864 | P62: =Model!AA151 -> 11298.256 | Q62: =Model!AB151 -> 11347.837 | R62: =Model!AC151 -> 11220.584 | T62: =Model!J151 -> 0 | U62: =Model!O151 -> 0 | V62: =Model!T151 -> 0 | W62: =Model!Y151 -> 10689.852 | X62: =Model!AD151 -> 11220.584 | Y62: =Model!AE151 -> 11877.461 | Z62: =Model!AF151 -> 12435.566 | AA62: =Model!AG151 -> 12945.802
C63: =Model!C152 -> Treasury Stock | G63: =Model!P152 -> 0 | H63: =Model!Q152 -> 0 | I63: =Model!R152 -> 0 | J63: =Model!S152 -> 0 | K63: =Model!U152 -> 0 | L63: =Model!V152 -> 0 | M63: =Model!W152 -> 0 | N63: =Model!X152 -> 0 | O63: =Model!Z152 -> -550 | P63: =Model!AA152 -> -550 | Q63: =Model!AB152 -> -550 | R63: =Model!AC152 -> -550 | T63: =Model!J152 -> 0 | U63: =Model!O152 -> 0 | V63: =Model!T152 -> 0 | W63: =Model!Y152 -> 0 | X63: =Model!AD152 -> -550 | Y63: =Model!AE152 -> -1150 | Z63: =Model!AF152 -> -1800 | AA63: =Model!AG152 -> -2500
C64: =Model!C153 -> Accumulated Other Comprehensive Income (AOCI) | G64: =Model!P153 -> 0 | H64: =Model!Q153 -> 0 | I64: =Model!R153 -> 0 | J64: =Model!S153 -> 0 | K64: =Model!U153 -> 0 | L64: =Model!V153 -> 0 | M64: =Model!W153 -> 0 | N64: =Model!X153 -> 0 | O64: =Model!Z153 -> 0 | P64: =Model!AA153 -> 0 | Q64: =Model!AB153 -> 0 | R64: =Model!AC153 -> 0 | T64: =Model!J153 -> 0 | U64: =Model!O153 -> 0 | V64: =Model!T153 -> 0 | W64: =Model!Y153 -> 0 | X64: =Model!AD153 -> 0 | Y64: =Model!AE153 -> 0 | Z64: =Model!AF153 -> 0 | AA64: =Model!AG153 -> 0
C65: =Model!C154 -> Total Shareholder's Equity | G65: =SUM(G61:G64) -> 0 | H65: =SUM(H61:H64) -> 0 | I65: =SUM(I61:I64) -> 0 | J65: =SUM(J61:J64) -> 0 | K65: =SUM(K61:K64) -> 0 | L65: =SUM(L61:L64) -> 0 | M65: =SUM(M61:M64) -> 0 | N65: =SUM(N61:N64) -> 11784.44 | ... R65: =SUM(R61:R64) -> 11901.835 | T65: =SUM(T61:T64) -> 0 | U65: =SUM(U61:U64) -> 0 | V65: =SUM(V61:V64) -> 0 | W65: =SUM(W61:W64) -> 11784.44 | X65: =SUM(X61:X64) -> 11901.835 | Y65: =SUM(Y61:Y64) -> 12101.987 | Z65: =SUM(Z61:Z64) -> 12160.643 | AA65: =SUM(AA61:AA64) -> 12128.672
C67: =Model!C156 -> Noncontrolling Interests | G67: =Model!P156 -> 0 | H67: =Model!Q156 -> 0 | I67: =Model!R156 -> 0 | J67: =Model!S156 -> 0 | K67: =Model!U156 -> 0 | L67: =Model!V156 -> 0 | M67: =Model!W156 -> 0 | N67: =Model!X156 -> 0 | O67: =Model!Z156 -> 0 | P67: =Model!AA156 -> 0 | Q67: =Model!AB156 -> 0 | R67: =Model!AC156 -> 0 | T67: =Model!J156 -> 0 | U67: =Model!O156 -> 0 | V67: =Model!T156 -> 0 | W67: =Model!Y156 -> 0 | X67: =Model!AD156 -> 0 | Y67: =Model!AE156 -> 0 | Z67: =Model!AF156 -> 0 | AA67: =Model!AG156 -> 0
C68: =Model!C157 -> Total Equity | G68: =SUM(G65,G67) -> 0 | H68: =SUM(H65,H67) -> 0 | I68: =SUM(I65,I67) -> 0 | J68: =SUM(J65,J67) -> 0 | K68: =SUM(K65,K67) -> 0 | L68: =SUM(L65,L67) -> 0 | M68: =SUM(M65,M67) -> 0 | N68: =SUM(N65,N67) -> 11785.44 | ... R68: =SUM(R65,R67) -> 11902.835 | T68: =SUM(T65,T67) -> 0 | U68: =SUM(U65,U67) -> 0 | V68: =SUM(V65,V67) -> 0 | W68: =SUM(W65,W67) -> 11785.44 | X68: =SUM(X65,X67) -> 11902.835 | Y68: =SUM(Y65,Y67) -> 12102.987 | Z68: =SUM(Z65,Z67) -> 12161.643 | AA68: =SUM(AA65,AA67) -> 12129.672
C70: =Model!C159 -> Total Liabilities & Shareholder's Equity | G70: =SUM(G59,G68) -> 0 | H70: =SUM(H59,H68) -> 0 | I70: =SUM(I59,I68) -> 0 | J70: =SUM(J59,J68) -> 0 | K70: =SUM(K59,K68) -> 0 | L70: =SUM(L59,L68) -> 0 | M70: =SUM(M59,M68) -> 0 | N70: =SUM(N59,N68) -> 33897.72 | ... R70: =SUM(R59,R68) -> 34309.587 | T70: =SUM(T59,T68) -> 0 | U70: =SUM(U59,U68) -> 0 | V70: =SUM(V59,V68) -> 0 | W70: =SUM(W59,W68) -> 33897.72 | X70: =SUM(X59,X68) -> 34309.587 | Y70: =SUM(Y59,Y68) -> 34877.943 | Z70: =SUM(Z59,Z68) -> 35183.914 | AA70: =SUM(AA59,AA68) -> 35548.108
G72: =G$5 -> Quarterly | T72: =T$31 -> Annuals
A73: x | C73: Ratio Analysis | G73: =G$6 -> 1Q25 | H73: =H$6 -> 2Q25 | I73: =I$6 -> 3Q25 | J73: =J$6 -> 4Q25 | K73: =K$6 -> 1Q26e | L73: =L$6 -> 2Q26e | M73: =M$6 -> 3Q26 | N73: =N$6 -> 4Q26e | ... R73: =R$6 -> 4Q27e | T73: =T$6 -> 2023 | U73: =U$6 -> 2024 | V73: =V$6 -> 2025 | W73: =W$6 -> 2026e | X73: =X$6 -> 2027e | Y73: =Y$6 -> 2028e | Z73: =Z$6 -> 2029e | AA73: =AA$6 -> 2030e
C75: Profitability
C76: Gross Margin | G76: =G12 -> 1 | H76: =H12 -> 1 | I76: =I12 -> 1 | J76: =J12 -> 1 | K76: =K12 -> 1 | L76: =L12 -> 1 | M76: =M12 -> 1 | N76: =N12 -> 0.424 | ... R76: =R12 -> 0.428 | T76: =T12 -> 1 | U76: =U12 -> 1 | V76: =V12 -> 1 | W76: =W12 -> 0.85253306 | X76: =X12 -> 0.42723651 | Y76: =Y12 -> 0.431 | Z76: =Z12 -> 0.428 | AA76: =AA12 -> 0.428
C77: EBITDA Margin | G77: =G28 -> 1 | H77: =H28 -> 1 | I77: =I28 -> 1 | J77: =J28 -> 1 | K77: =K28 -> 1 | L77: =L28 -> 1 | M77: =M28 -> 1 | N77: =N28 -> 0.313 | ... R77: =R28 -> 0.318 | T77: =T28 -> 1 | U77: =U28 -> 1 | V77: =V28 -> 1 | W77: =W28 -> 0.32781221 | X77: =X28 -> 0.31803579 | Y77: =Y28 -> 0.324 | Z77: =Z28 -> 0.322 | AA77: =AA28 -> 0.323
C78: EBIT Margin | G78: =G16 -> 1 | H78: =H16 -> 1 | I78: =I16 -> 1 | J78: =J16 -> 1 | K78: =K16 -> 1 | L78: =L16 -> 1 | M78: =M16 -> 1 | N78: =N16 -> 0.20153176 | ... R78: =R16 -> 0.21015955 | T78: =T16 -> 1 | U78: =U16 -> 1 | V78: =V16 -> 1 | W78: =W16 -> 0.22101088 | X78: =X16 -> 0.21023806 | Y78: =Y16 -> 0.21949945 | Z78: =Z16 -> 0.21712217 | AA78: =AA16 -> 0.21787723
C79: Net Profit Margin | G79: =G20 -> 1 | H79: =H20 -> 1 | I79: =I20 -> 1 | J79: =J20 -> 1 | K79: =K20 -> 1 | L79: =L20 -> 1 | M79: =M20 -> 1 | N79: =N20 -> 0.12778979 | ... R79: =R20 -> 0.13895459 | T79: =T20 -> 1 | U79: =U20 -> 1 | V79: =V20 -> 1 | W79: =W20 -> 0.14984054 | X79: =X20 -> 0.13752443 | Y79: =Y20 -> 0.14815846 | Z79: =Z20 -> 0.14682584 | AA79: =AA20 -> 0.14912123
C80: Return on Assets (ROA) | G80: =G19/G46 -> #DIV/0! | H80: =H19/H46 -> #DIV/0! | I80: =I19/I46 -> #DIV/0! | J80: =J19/J46 -> #DIV/0! | K80: =K19/K46 -> #DIV/0! | L80: =L19/L46 -> #DIV/0! | M80: =M19/M46 -> #DIV/0! | N80: =N19/N46 -> 0.016722421 | ... R80: =R19/R46 -> 0.01831695 | T80: =T19/T46 -> #DIV/0! | U80: =U19/U46 -> #DIV/0! | V80: =V19/V46 -> #DIV/0! | W80: =W19/W46 -> 0.076587893 | X80: =X19/X46 -> 0.072345143 | Y80: =Y19/Y46 -> 0.080377942 | Z80: =Z19/Z46 -> 0.082972545 | AA80: =AA19/AA46 -> 0.087418129
C81: Return on Equity (ROE) | G81: =G19*4/G68 -> #DIV/0! | H81: =H19*4/H68 -> #DIV/0! | I81: =I19*4/I68 -> #DIV/0! | J81: =J19*4/J68 -> #DIV/0! | K81: =K19*4/K68 -> #DIV/0! | L81: =L19*4/L68 -> #DIV/0! | M81: =M19*4/M68 -> #DIV/0! | N81: =N19*4/N68 -> 0.19239059 | ... R81: =R19*4/R68 -> 0.21119237 | T81: =T19/T68 -> #DIV/0! | U81: =U19/U68 -> #DIV/0! | V81: =V19/V68 -> #DIV/0! | W81: =W19/W68 -> 0.22028494 | X81: =X19/X68 -> 0.20853283 | Y81: =Y19/Y68 -> 0.23163019 | Z81: =Z19/Z68 -> 0.24004148 | AA81: =AA19/AA68 -> 0.25619399
C82: Return on Invested Capital (ROIC) | G82: =G19*4/(G53+G54+G68) -> #DIV/0! | H82: =H19*4/(H53+H54+H68) -> #DIV/0! | I82: =I19*4/(I53+I54+I68) -> #DIV/0! | J82: =J19*4/(J53+J54+J68) -> #DIV/0! | K82: =K19*4/(K53+K54+K68) -> #DIV/0! | L82: =L19*4/(L53+L54+L68) -> #DIV/0! | M82: =M19*4/(M53+M54+M68) -> #DIV/0! | N82: =N19*4/(N53+N54+N68) -> 0.092422018 | ... S82: =S19*4/(S53+S54+S68) -> #DIV/0! | T82: =T19/(T53+T54+T68) -> #DIV/0! | U82: =U19/(U53+U54+U68) -> #DIV/0! | V82: =V19/(V53+V54+V68) -> #DIV/0! | W82: =W19/(W53+W54+W68) -> 0.10582211 | X82: =X19/(X53+X54+X68) -> 0.10518321 | Y82: =Y19/(Y53+Y54+Y68) -> 0.11684763 | Z82: =Z19/(Z53+Z54+Z68) -> 0.12135223 | AA82: =AA19/(AA53+AA54+AA68) -> 0.12846773
C84: Coverage
C85: Interest Expense | G85: =-Model!P39 -> 0 | H85: =-Model!Q39 -> 0 | I85: =-Model!R39 -> 0 | J85: =-Model!S39 -> 0 | K85: =-Model!U39 -> 0 | L85: =-Model!V39 -> 0 | M85: =-Model!W39 -> 0 | N85: =-Model!X39 -> 1.225 | O85: =-Model!Z39 -> 2.5 | P85: =-Model!AA39 -> -0.5 | Q85: =-Model!AB39 -> -6.5 | R85: =-Model!AC39 -> -12.5 | T85: =-Model!J39 -> 0 | U85: =-Model!O39 -> 0 | V85: =-Model!T39 -> 0 | W85: =-Model!Y39 -> 1.225 | X85: =-Model!AD39 -> -17 | Y85: =-Model!AE39 -> -62 | Z85: =-Model!AF39 -> -74 | AA85: =-Model!AG39 -> -98
C86: Capital Expenditures | G86: =Model!P196 -> 0 | H86: =Model!Q196 -> 0 | I86: =Model!R196 -> 0 | J86: =Model!S196 -> 0 | K86: =Model!U196 -> 0 | L86: =Model!V196 -> 0 | M86: =Model!W196 -> 0 | N86: =Model!X196 -> 527.86204 | O86: =Model!Z196 -> 483.81183 | P86: =Model!AA196 -> 523.64162 | Q86: =Model!AB196 -> 503.13682 | R86: =Model!AC196 -> 529.15342 | T86: =Model!J196 -> 3807.2 | U86: =Model!O196 -> 0 | V86: =Model!T196 -> 0 | W86: =Model!Y196 -> 527.86204 | X86: =Model!AD196 -> 2039.7437 | Y86: =Model!AE196 -> 2054.902 | Z86: =Model!AF196 -> 2115.5228 | AA86: =Model!AG196 -> 2229.7814
C87: EBIT / Interest Expense | G87: =IF(ISERROR(G15/G85),"N/A",(G15/G85)) -> N/A | H87: =IF(ISERROR(H15/H85),"N/A",(H15/H85)) -> N/A | I87: =IF(ISERROR(I15/I85),"N/A",(I15/I85)) -> N/A | J87: =IF(ISERROR(J15/J85),"N/A",(J15/J85)) -> N/A | K87: =IF(ISERROR(K15/K85),"N/A",(K15/K85)) -> N/A | L87: =IF(ISERROR(L15/L85),"N/A",(L15/L85)) -> N/A | M87: =IF(ISERROR(M15/M85),"N/A",(M15/M85)) -> N/A | N87: =IF(ISERROR(N15/N85),"N/A",(N15/N85)) -> 7.3104803 | ... R87: =IF(ISERROR(R15/R85),"N/A",(R15/R85)) -> 8.5606067 | T87: =IF(ISERROR(T15/T85),"N/A",(T15/T85)) -> N/A | U87: =IF(ISERROR(U15/U85),"N/A",(U15/U85)) -> N/A | V87: =IF(ISERROR(V15/V85),"N/A",(V15/V85)) -> N/A | W87: =IF(ISERROR(W15/W85),"N/A",(W15/W85)) -> 6.9586939 | X87: =IF(ISERROR(X15/X85),"N/A",(X15/X85)) -> 7.9529591 | Y87: =IF(ISERROR(Y15/Y85),"N/A",(Y15/Y85)) -> 9.6114817 | Z87: =IF(ISERROR(Z15/Z85),"N/A",(Z15/Z85)) -> 10.275593 | AA87: =IF(ISERROR(AA15/AA85),"N/A",(AA15/AA85)) -> 11.462084
C88: EBITDA / Interest Expense | G88: =IF(ISERROR(G27/G85),"N/A",(G27/G85)) -> N/A | H88: =IF(ISERROR(H27/H85),"N/A",(H27/H85)) -> N/A | I88: =IF(ISERROR(I27/I85),"N/A",(I27/I85)) -> N/A | J88: =IF(ISERROR(J27/J85),"N/A",(J27/J85)) -> N/A | K88: =IF(ISERROR(K27/K85),"N/A",(K27/K85)) -> N/A | L88: =IF(ISERROR(L27/L85),"N/A",(L27/L85)) -> N/A | M88: =IF(ISERROR(M27/M85),"N/A",(M27/M85)) -> N/A | N88: =IF(ISERROR(N27/N85),"N/A",(N27/N85)) -> 11.353944 | ... R88: =IF(ISERROR(R27/R85),"N/A",(R27/R85)) -> 12.953363 | T88: =IF(ISERROR(T27/T85),"N/A",(T27/T85)) -> N/A | U88: =IF(ISERROR(U27/U85),"N/A",(U27/U85)) -> N/A | V88: =IF(ISERROR(V27/V85),"N/A",(V27/V85)) -> N/A | W88: =IF(ISERROR(W27/W85),"N/A",(W27/W85)) -> 10.321414 | X88: =IF(ISERROR(X27/X85),"N/A",(X27/X85)) -> 12.030769 | Y88: =IF(ISERROR(Y27/Y85),"N/A",(Y27/Y85)) -> 14.187371 | Z88: =IF(ISERROR(Z27/Z85),"N/A",(Z27/Z85)) -> 15.239075 | AA88: =IF(ISERROR(AA27/AA85),"N/A",(AA27/AA85)) -> 16.992382
C89: (EBITDA - CapEx) / Interest Expense | G89: =IF(ISERROR((G27-G86)/G85),"N/A",((G27-G86)/G85)) -> N/A | H89: =IF(ISERROR((H27-H86)/H85),"N/A",((H27-H86)/H85)) -> N/A | I89: =IF(ISERROR((I27-I86)/I85),"N/A",((I27-I86)/I85)) -> N/A | J89: =IF(ISERROR((J27-J86)/J85),"N/A",((J27-J86)/J85)) -> N/A | K89: =IF(ISERROR((K27-K86)/K85),"N/A",((K27-K86)/K85)) -> N/A | L89: =IF(ISERROR((L27-L86)/L85),"N/A",((L27-L86)/L85)) -> N/A | M89: =IF(ISERROR((M27-M86)/M85),"N/A",((M27-M86)/M85)) -> N/A | N89: =IF(ISERROR((N27-N86)/N85),"N/A",((N27-N86)/N85)) -> 7.0372688 | ... R89: =IF(ISERROR((R27-R86)/R85),"N/A",((R27-R86)/R85)) -> 8.1875029 | T89: =IF(ISERROR((T27-T86)/T85),"N/A",((T27-T86)/T85)) -> N/A | U89: =IF(ISERROR((U27-U86)/U85),"N/A",((U27-U86)/U85)) -> N/A | V89: =IF(ISERROR((V27-V86)/V85),"N/A",((V27-V86)/V85)) -> N/A | W89: =IF(ISERROR((W27-W86)/W85),"N/A",((W27-W86)/W85)) -> 4.5737281 | X89: =IF(ISERROR((X27-X86)/X85),"N/A",((X27-X86)/X85)) -> 7.7556526 | Y89: =IF(ISERROR((Y27-Y86)/Y85),"N/A",((Y27-Y86)/Y85)) -> 9.4319744 | Z89: =IF(ISERROR((Z27-Z86)/Z85),"N/A",((Z27-Z86)/Z85)) -> 10.203554 | AA89: =IF(ISERROR((AA27-AA86)/AA85),"N/A",((AA27-AA86)/AA85)) -> 11.363327
C91: Leverage
C92: Total Debt / EBITDA | G92: =IF(ISERROR((G53+G54)/G27),"NA",((G53+G54)/G27)) -> 0 | H92: =IF(ISERROR((H53+H54)/H27),"NA",((H53+H54)/H27)) -> 0 | I92: =IF(ISERROR((I53+I54)/I27),"NA",((I53+I54)/I27)) -> 0 | J92: =IF(ISERROR((J53+J54)/J27),"NA",((J53+J54)/J27)) -> 0 | K92: =IF(ISERROR((K53+K54)/K27),"NA",((K53+K54)/K27)) -> 0 | L92: =IF(ISERROR((L53+L54)/L27),"NA",((L53+L54)/L27)) -> 0 | M92: =IF(ISERROR((M53+M54)/M27),"NA",((M53+M54)/M27)) -> 0 | N92: =IF(ISERROR((N53+N54)/N27),"NA",((N53+N54)/N27)) -> 9.1815504 | ... R92: =IF(ISERROR((R53+R54)/R27),"NA",((R53+R54)/R27)) -> 8.1318619 | T92: =IF(ISERROR((T53+T54)/T27),"NA",((T53+T54)/T27)) -> 0 | U92: =IF(ISERROR((U53+U54)/U27),"NA",((U53+U54)/U27)) -> 0 | V92: =IF(ISERROR((V53+V54)/V27),"NA",((V53+V54)/V27)) -> 0 | W92: =IF(ISERROR((W53+W54)/W27),"NA",((W53+W54)/W27)) -> 2.244437 | X92: =IF(ISERROR((X53+X54)/X27),"NA",((X53+X54)/X27)) -> 2.0374729 | Y92: =IF(ISERROR((Y53+Y54)/Y27),"NA",((Y53+Y54)/Y27)) -> 1.9392878 | Z92: =IF(ISERROR((Z53+Z54)/Z27),"NA",((Z53+Z54)/Z27)) -> 1.8579068 | AA92: =IF(ISERROR((AA53+AA54)/AA27),"NA",((AA53+AA54)/AA27)) -> 1.7916542
C93: Total Debt / Equity | G93: =IF(ISERROR((G53+G54)/G68),"NA",((G53+G54)/G68)) -> NA | H93: =IF(ISERROR((H53+H54)/H68),"NA",((H53+H54)/H68)) -> NA | I93: =IF(ISERROR((I53+I54)/I68),"NA",((I53+I54)/I68)) -> NA | J93: =IF(ISERROR((J53+J54)/J68),"NA",((J53+J54)/J68)) -> NA | K93: =IF(ISERROR((K53+K54)/K68),"NA",((K53+K54)/K68)) -> NA | L93: =IF(ISERROR((L53+L54)/L68),"NA",((L53+L54)/L68)) -> NA | M93: =IF(ISERROR((M53+M54)/M68),"NA",((M53+M54)/M68)) -> NA | N93: =IF(ISERROR((N53+N54)/N68),"NA",((N53+N54)/N68)) -> 1.0816532 | ... R93: =IF(ISERROR((R53+R54)/R68),"NA",((R53+R54)/R68)) -> 0.98256759 | T93: =IF(ISERROR((T53+T54)/T68),"NA",((T53+T54)/T68)) -> NA | U93: =IF(ISERROR((U53+U54)/U68),"NA",((U53+U54)/U68)) -> NA | V93: =IF(ISERROR((V53+V54)/V68),"NA",((V53+V54)/V68)) -> NA | W93: =IF(ISERROR((W53+W54)/W68),"NA",((W53+W54)/W68)) -> 1.0816532 | X93: =IF(ISERROR((X53+X54)/X68),"NA",((X53+X54)/X68)) -> 0.98256759 | Y93: =IF(ISERROR((Y53+Y54)/Y68),"NA",((Y53+Y54)/Y68)) -> 0.98232675 | Z93: =IF(ISERROR((Z53+Z54)/Z68),"NA",((Z53+Z54)/Z68)) -> 0.97805575 | AA93: =IF(ISERROR((AA53+AA54)/AA68),"NA",((AA53+AA54)/AA68)) -> 0.99422844
C94: Total Debt / Total Assets | G94: =IF(ISERROR((G53+G54)/G46),"NA",((G53+G54)/G46)) -> NA | H94: =IF(ISERROR((H53+H54)/H46),"NA",((H53+H54)/H46)) -> NA | I94: =IF(ISERROR((I53+I54)/I46),"NA",((I53+I54)/I46)) -> NA | J94: =IF(ISERROR((J53+J54)/J46),"NA",((J53+J54)/J46)) -> NA | K94: =IF(ISERROR((K53+K54)/K46),"NA",((K53+K54)/K46)) -> NA | L94: =IF(ISERROR((L53+L54)/L46),"NA",((L53+L54)/L46)) -> NA | M94: =IF(ISERROR((M53+M54)/M46),"NA",((M53+M54)/M46)) -> NA | N94: =IF(ISERROR((N53+N54)/N46),"NA",((N53+N54)/N46)) -> 0.37606537 | ... R94: =IF(ISERROR((R53+R54)/R46),"NA",((R53+R54)/R46)) -> 0.34087674 | T94: =IF(ISERROR((T53+T54)/T46),"NA",((T53+T54)/T46)) -> NA | U94: =IF(ISERROR((U53+U54)/U46),"NA",((U53+U54)/U46)) -> NA | V94: =IF(ISERROR((V53+V54)/V46),"NA",((V53+V54)/V46)) -> NA | W94: =IF(ISERROR((W53+W54)/W46),"NA",((W53+W54)/W46)) -> 0.37606537 | X94: =IF(ISERROR((X53+X54)/X46),"NA",((X53+X54)/X46)) -> 0.34087674 | Y94: =IF(ISERROR((Y53+Y54)/Y46),"NA",((Y53+Y54)/Y46)) -> 0.34087699 | Z94: =IF(ISERROR((Z53+Z54)/Z46),"NA",((Z53+Z54)/Z46)) -> 0.33807397 | AA94: =IF(ISERROR((AA53+AA54)/AA46),"NA",((AA53+AA54)/AA46)) -> 0.33924913
C96: Efficiency
C97: Asset Turnover | G97: =G8/G46 -> #DIV/0! | H97: =H8/H46 -> #DIV/0! | I97: =I8/I46 -> #DIV/0! | J97: =J8/J46 -> #DIV/0! | K97: =K8/K46 -> #DIV/0! | L97: =L8/L46 -> #DIV/0! | M97: =M8/M46 -> #DIV/0! | N97: =N8/N46 -> 0.13085882 | ... R97: =R8/R46 -> 0.13181968 | T97: =T8/T46 -> #DIV/0! | U97: =U8/U46 -> #DIV/0! | V97: =V8/V46 -> #DIV/0! | W97: =W8/W46 -> 0.51112932 | X97: =X8/X46 -> 0.52605305 | Y97: =Y8/Y46 -> 0.54251333 | Z97: =Z8/Z46 -> 0.56510862 | AA97: =AA8/AA46 -> 0.58622189
C98: =Model!C185 -> Days Sales Outstanding | G98: =Model!P185 -> 0 | H98: =Model!Q185 -> 0 | I98: =Model!R185 -> 0 | J98: =Model!S185 -> 0 | K98: =Model!U185 -> 0 | L98: =Model!V185 -> 0 | M98: =Model!W185 -> 0 | N98: =Model!X185 -> 41.8 | O98: =Model!Z185 -> 41.2 | P98: =Model!AA185 -> 40.2 | Q98: =Model!AB185 -> 40.8 | R98: =Model!AC185 -> 41.3 | T98: =Model!J185 -> 0 | U98: =Model!O185 -> 0 | V98: =Model!T185 -> 0 | W98: =Model!Y185 -> 21.228706 | X98: =Model!AD185 -> 41.020311 | Y98: =Model!AE185 -> 41.6 | Z98: =Model!AF185 -> 41 | AA98: =Model!AG185 -> 41
C99: =Model!C186 -> Days Inventory Outstanding | G99: =Model!P186 -> #DIV/0! | H99: =Model!Q186 -> #DIV/0! | I99: =Model!R186 -> #DIV/0! | J99: =Model!S186 -> #DIV/0! | K99: =Model!U186 -> #DIV/0! | L99: =Model!V186 -> #DIV/0! | M99: =Model!W186 -> #DIV/0! | N99: =Model!X186 -> 0 | O99: =Model!Z186 -> 0 | P99: =Model!AA186 -> 0 | Q99: =Model!AB186 -> 0 | R99: =Model!AC186 -> 0 | T99: =Model!J186 -> #DIV/0! | U99: =Model!O186 -> #DIV/0! | V99: =Model!T186 -> #DIV/0! | W99: =Model!Y186 -> 0 | X99: =Model!AD186 -> 0 | Y99: =Model!AE186 -> 0 | Z99: =Model!AF186 -> 0 | AA99: =Model!AG186 -> 0
C100: =Model!C187 -> Days Payables Outstanding | G100: =Model!P187 -> #DIV/0! | H100: =Model!Q187 -> #DIV/0! | I100: =Model!R187 -> #DIV/0! | J100: =Model!S187 -> #DIV/0! | K100: =Model!U187 -> #DIV/0! | L100: =Model!V187 -> #DIV/0! | M100: =Model!W187 -> #DIV/0! | N100: =Model!X187 -> 47 | O100: =Model!Z187 -> 49 | P100: =Model!AA187 -> 48.5 | Q100: =Model!AB187 -> 48.5 | R100: =Model!AC187 -> 48 | T100: =Model!J187 -> #DIV/0! | U100: =Model!O187 -> #DIV/0! | V100: =Model!T187 -> #DIV/0! | W100: =Model!Y187 -> 93.233696 | X100: =Model!AD187 -> 46.999924 | Y100: =Model!AE187 -> 47.5 | Z100: =Model!AF187 -> 47 | AA100: =Model!AG187 -> 47
C101: Cash Conversion Cycle | G101: =G98+G99-G100 -> #DIV/0! | H101: =H98+H99-H100 -> #DIV/0! | I101: =I98+I99-I100 -> #DIV/0! | J101: =J98+J99-J100 -> #DIV/0! | K101: =K98+K99-K100 -> #DIV/0! | L101: =L98+L99-L100 -> #DIV/0! | M101: =M98+M99-M100 -> #DIV/0! | N101: =N98+N99-N100 -> -5.2 | ... R101: =R98+R99-R100 -> -6.7 | T101: =T98+T99-T100 -> #DIV/0! | U101: =U98+U99-U100 -> #DIV/0! | V101: =V98+V99-V100 -> #DIV/0! | W101: =W98+W99-W100 -> -72.00499 | X101: =X98+X99-X100 -> -5.979613 | Y101: =Y98+Y99-Y100 -> -5.9 | Z101: =Z98+Z99-Z100 -> -6 | AA101: =AA98+AA99-AA100 -> -6
C103: Liquidity
C104: Current Ratio | G104: =IF(ISERROR(G38/G51),"NA",(G38/G51)) -> NA | H104: =IF(ISERROR(H38/H51),"NA",(H38/H51)) -> NA | I104: =IF(ISERROR(I38/I51),"NA",(I38/I51)) -> NA | J104: =IF(ISERROR(J38/J51),"NA",(J38/J51)) -> NA | K104: =IF(ISERROR(K38/K51),"NA",(K38/K51)) -> NA | L104: =IF(ISERROR(L38/L51),"NA",(L38/L51)) -> NA | M104: =IF(ISERROR(M38/M51),"NA",(M38/M51)) -> NA | N104: =IF(ISERROR(N38/N51),"NA",(N38/N51)) -> 0.59381309 | ... R104: =IF(ISERROR(R38/R51),"NA",(R38/R51)) -> 0.5664293 | T104: =IF(ISERROR(T38/T51),"NA",(T38/T51)) -> NA | U104: =IF(ISERROR(U38/U51),"NA",(U38/U51)) -> NA | V104: =IF(ISERROR(V38/V51),"NA",(V38/V51)) -> NA | W104: =IF(ISERROR(W38/W51),"NA",(W38/W51)) -> 0.59381309 | X104: =IF(ISERROR(X38/X51),"NA",(X38/X51)) -> 0.5664293 | Y104: =IF(ISERROR(Y38/Y51),"NA",(Y38/Y51)) -> 0.61791096 | Z104: =IF(ISERROR(Z38/Z51),"NA",(Z38/Z51)) -> 0.60986416 | AA104: =IF(ISERROR(AA38/AA51),"NA",(AA38/AA51)) -> 0.60986416
C105: Quick Ratio | G105: =IF(ISERROR((G34+G35)/G51),"NA",((G34+G35)/G51)) -> NA | H105: =IF(ISERROR((H34+H35)/H51),"NA",((H34+H35)/H51)) -> NA | I105: =IF(ISERROR((I34+I35)/I51),"NA",((I34+I35)/I51)) -> NA | J105: =IF(ISERROR((J34+J35)/J51),"NA",((J34+J35)/J51)) -> NA | K105: =IF(ISERROR((K34+K35)/K51),"NA",((K34+K35)/K51)) -> NA | L105: =IF(ISERROR((L34+L35)/L51),"NA",((L34+L35)/L51)) -> NA | M105: =IF(ISERROR((M34+M35)/M51),"NA",((M34+M35)/M51)) -> NA | N105: =IF(ISERROR((N34+N35)/N51),"NA",((N34+N35)/N51)) -> 0.48575226 | ... R105: =IF(ISERROR((R34+R35)/R51),"NA",((R34+R35)/R51)) -> 0.47581104 | T105: =IF(ISERROR((T34+T35)/T51),"NA",((T34+T35)/T51)) -> NA | U105: =IF(ISERROR((U34+U35)/U51),"NA",((U34+U35)/U51)) -> NA | V105: =IF(ISERROR((V34+V35)/V51),"NA",((V34+V35)/V51)) -> NA | W105: =IF(ISERROR((W34+W35)/W51),"NA",((W34+W35)/W51)) -> 0.48575226 | X105: =IF(ISERROR((X34+X35)/X51),"NA",((X34+X35)/X51)) -> 0.47581104 | Y105: =IF(ISERROR((Y34+Y35)/Y51),"NA",((Y34+Y35)/Y51)) -> 0.52675097 | Z105: =IF(ISERROR((Z34+Z35)/Z51),"NA",((Z34+Z35)/Z51)) -> 0.51888845 | AA105: =IF(ISERROR((AA34+AA35)/AA51),"NA",((AA34+AA35)/AA51)) -> 0.51888845
C106: Cash Ratio | G106: =IF(ISERROR(G34/G51),"NA",(G34/G51)) -> NA | H106: =IF(ISERROR(H34/H51),"NA",(H34/H51)) -> NA | I106: =IF(ISERROR(I34/I51),"NA",(I34/I51)) -> NA | J106: =IF(ISERROR(J34/J51),"NA",(J34/J51)) -> NA | K106: =IF(ISERROR(K34/K51),"NA",(K34/K51)) -> NA | L106: =IF(ISERROR(L34/L51),"NA",(L34/L51)) -> NA | M106: =IF(ISERROR(M34/M51),"NA",(M34/M51)) -> NA | N106: =IF(ISERROR(N34/N51),"NA",(N34/N51)) -> 0.01366376 | ... R106: =IF(ISERROR(R34/R51),"NA",(R34/R51)) -> 0.013541546 | T106: =IF(ISERROR(T34/T51),"NA",(T34/T51)) -> NA | U106: =IF(ISERROR(U34/U51),"NA",(U34/U51)) -> NA | V106: =IF(ISERROR(V34/V51),"NA",(V34/V51)) -> NA | W106: =IF(ISERROR(W34/W51),"NA",(W34/W51)) -> 0.01366376 | X106: =IF(ISERROR(X34/X51),"NA",(X34/X51)) -> 0.013541546 | Y106: =IF(ISERROR(Y34/Y51),"NA",(Y34/Y51)) -> 0.054490003 | Z106: =IF(ISERROR(Z34/Z51),"NA",(Z34/Z51)) -> 0.05437985 | AA106: =IF(ISERROR(AA34/AA51),"NA",(AA34/AA51)) -> 0.05437985
A110: x

Sheet Model Output
B1: =Company_Name&" "&"("&Ticker&")"&" Valuation Overview" -> Republic Services, Inc. (RSG) Valuation Overview | K1: Price Target Scenario: | N1: =Case_Scenario&" Case" -> Base Case | R1: Base Case Check | S1: =IF(N1="Base Case","","Check!") | Y1: P/E
B2: =Cover!C2 -> $ in Millions Except Per Share Data | K2: Current Share Price: | O2: =Share_Price -> 206.55 | Y2: EV/EBITDA
K3: Valuation Date: | O3: =Current_Date -> 46145
B4: ="Multiples Analysis "&"("&S21&")" -> Multiples Analysis (P/E) | I4: Return Summary
I6: Exit Multiple Method
I7: =Cover!I9 -> Implied Enterprise Value: | N7: =Cover!L9 -> 89474.779
I8: =Cover!I10 -> Implied Equity Value: | N8: =Cover!L10 -> 76784.353
I9: =Cover!I12 -> Implied Share Price: | N9: =Cover!L12 -> 245.86728
I10: =Cover!I13 -> % Return: | N10: =Cover!L13 -> 0.19035238
I12: =Cover!I15 -> Perpetuity Growth Method
I13: =Cover!I16 -> Implied Enterprise Value: | N13: =Cover!L16 -> 95925.297
I14: =Cover!I17 -> Implied Equity Value: | N14: =Cover!L17 -> 83234.871
I15: =Cover!I19 -> Implied Share Price: | N15: =Cover!L19 -> 266.52216
I16: =Cover!I20 -> % Return: | N16: =Cover!L20 -> 0.29035179
E18: Annuals | M18: CAGR | O18: CAGR
B19: Consolidated Financials | E19: =Summary!U6 -> 2024 | F19: =Summary!V6 -> 2025 | G19: =Summary!W6 -> 2026e | H19: =Summary!X6 -> 2027e | I19: =Summary!Y6 -> 2028e | J19: =Summary!Z6 -> 2029e | K19: =Summary!AA6 -> 2030e | M19: Historical | O19: Projected
B21: =Summary!C8 -> Revenue | D21: =Summary!T8 -> 14964.5 | E21: =Summary!U8 -> 16031.9 | F21: =Summary!V8 -> 16592 | G21: =Summary!W8 -> 17326.118 | H21: =Summary!X8 -> 18048.663 | I21: =Summary!Y8 -> 18921.749 | J21: =Summary!Z8 -> 19882.733 | K21: =Summary!AA8 -> 20839.079 | M21: =Summary!AC8 -> 0.052975495 | O21: =Summary!AE8 -> 0.046636692 | R21: Multiple Toggle | S21: P/E
B22: =Summary!C9 -> YoY % Growth | E22: =Summary!U9 -> 0.071328812 | F22: =Summary!V9 -> 0.034936595 | G22: =Summary!W9 -> 0.044245326 | H22: =Summary!X9 -> 0.041702602 | I22: =Summary!Y9 -> 0.048374028 | J22: =Summary!Z9 -> 0.050787257 | K22: =Summary!AA9 -> 0.048099317
R23: Multiples Analysis | S23: EV/EBITDA | T23: P/E | U23: Chart
B24: =Summary!C11 -> Gross Profit | D24: =Summary!T11 -> 14964.5 | E24: =Summary!U11 -> 16031.9 | F24: =Summary!V11 -> 16592 | G24: =Summary!W11 -> 14771.089 | H24: =Summary!X11 -> 7711.0476 | I24: =Summary!Y11 -> 8155.2739 | J24: =Summary!Z11 -> 8509.8097 | K24: =Summary!AA11 -> 8919.1257 | M24: =Summary!AC11 -> 0.052975495 | O24: =Summary!AE11 -> -0.11674784 | R24: Entry Multiple | S24: =Valuation!D12 -> 14.516056 | T24: =Valuation!D11 -> 29.928045 | U24: =IF($S$21=$S$23,S24,T24) -> 29.928045
B25: =Summary!C12 -> % Margin | E25: =Summary!U12 -> 1 | F25: =Summary!V12 -> 1 | G25: =Summary!W12 -> 0.85253306 | H25: =Summary!X12 -> 0.42723651 | I25: =Summary!Y12 -> 0.431 | J25: =Summary!Z12 -> 0.428 | K25: =Summary!AA12 -> 0.428 | R25: =Model!Y25 -> 2026e | S25: =(Comparables!H10*S30)/(Model!Y61) -> 14.255962 | T25: =(Comparables!$G$10*S30)/Summary!W19 -> 26.018007 | U25: =IF($S$21=$S$23,S25,T25) -> 26.018007
B26: =Summary!C13 -> YoY % Growth | E26: =Summary!U13 -> 0.071328812 | F26: =Summary!V13 -> 0.034936595 | G26: =Summary!W13 -> -0.10974634 | H26: =Summary!X13 -> -0.47796349 | I26: =Summary!Y13 -> 0.057609075 | J26: =Summary!Z13 -> 0.043473193 | K26: =Summary!AA13 -> 0.048099317 | R26: =Summary!AA6 -> 2030e | S26: =(Comparables!H10*S30)/(Model!AG61) -> 12.029343 | T26: =(Comparables!$G$10*S30)/Summary!AA19 -> 21.736351 | U26: =IF($S$21=$S$23,S26,T26) -> 21.736351
R27: Exit Multiple | S27: =Valuation!K60 -> 14 | T27: =Valuation!K72/Summary!AA19 -> 24.708975 | U27: =IF($S$21=$S$23,S27,T27) -> 24.708975
B28: =Summary!C27 -> EBITDA | D28: =Summary!T27 -> 14964.5 | E28: =Summary!U27 -> 16031.9 | F28: =Summary!V27 -> 16592 | G28: =Summary!W27 -> 5679.7132 | H28: =Summary!X27 -> 5740.1206 | I28: =Summary!Y27 -> 6130.6467 | J28: =Summary!Z27 -> 6402.24 | K28: =Summary!AA27 -> 6731.0225 | M28: =Summary!AC27 -> 0.052975495 | O28: =Summary!AE27 -> 0.046809263 | R28: Implied PGM | S28: =Valuation!K79 -> 15.185435 | T28: =Valuation!S72/Summary!AA19 -> 26.784733 | U28: =IF($S$21=$S$23,S28,T28) -> 26.784733
B29: =Summary!C28 -> Margin | E29: =Summary!U28 -> 1 | F29: =Summary!V28 -> 1 | G29: =Summary!W28 -> 0.32781221 | H29: =Summary!X28 -> 0.31803579 | I29: =Summary!Y28 -> 0.324 | J29: =Summary!Z28 -> 0.322 | K29: =Summary!AA28 -> 0.323
B30: =Summary!C29 -> YoY % Growth | E30: =Summary!U17 -> 0.071328812 | F30: =Summary!V17 -> 0.034936595 | G30: =Summary!W29 -> 0.060677006 | H30: =Summary!X29 -> 0.010635645 | I30: =Summary!Y29 -> 0.068034474 | J30: =Summary!Z29 -> 0.044300916 | K30: =Summary!AA29 -> 0.051354284 | R30: Financials Multiplier | S30: =IF($B$2="$ in Millions Except Per Share Data",1,IF($B$2="$ in Thousands Except Per Share Data",1000,IF($B$2="$ in Billions Except Per Share Data",0.001,0))) -> 1
B32: =Summary!C19 -> Net Income (Loss) | D32: =Summary!T19 -> 14964.5 | E32: =Summary!U19 -> 16031.9 | F32: =Summary!V19 -> 16592 | G32: =Summary!W19 -> 2596.1549 | H32: =Summary!X19 -> 2482.132 | I32: =Summary!Y19 -> 2803.4173 | J32: =Summary!Z19 -> 2919.2989 | K32: =Summary!AA19 -> 3107.5491 | M32: =Summary!AC19 -> 0.052975495 | O32: =Summary!AE19 -> 0.040618282
B33: =Summary!C20 -> Margin | E33: =Summary!U20 -> 1 | F33: =Summary!V20 -> 1 | G33: =Summary!W20 -> 0.14984054 | H33: =Summary!X20 -> 0.13752443 | I33: =Summary!Y20 -> 0.14815846 | J33: =Summary!Z20 -> 0.14682584 | K33: =Summary!AA20 -> 0.14912123
B34: =Summary!C21 -> YoY % Growth | E34: =Summary!U21 -> 0.071328812 | F34: =Summary!V21 -> 0.034936595 | G34: =Summary!W21 -> 0.01945925 | H34: =Summary!X21 -> -0.043919933 | I34: =Summary!Y21 -> 0.12943926 | J34: =Summary!Z21 -> 0.041335835 | K34: =Summary!AA21 -> 0.064484719
B36: =Summary!C23 -> Adj. EPS (Diluted) | D36: =Summary!T23 -> #DIV/0! | E36: =Summary!U23 -> #DIV/0! | F36: =Summary!V23 -> #DIV/0! | G36: =Summary!W23 -> 8.3010549 | H36: =Summary!X23 -> 8.0146684 | I36: =Summary!Y23 -> 9.1030862 | J36: =Summary!Z23 -> 9.5676296 | K36: =Summary!AA23 -> 10.283124 | M36: =Summary!AC23 -> N/A | O36: =Summary!AE23 -> 0.04917992
B37: =Summary!C24 -> YoY % Growth | E37: =Summary!U24 -> NA | F37: =Summary!V24 -> NA | G37: =Summary!W24 -> 0.026261562 | H37: =Summary!X24 -> -0.034500014 | I37: =Summary!Y24 -> 0.13580322 | J37: =Summary!Z24 -> 0.051031418 | K37: =Summary!AA24 -> 0.07478283
B39: Free Cash Flow | D39: =Model!J115 -> 20273 | E39: =Model!O115 -> 16031.9 | F39: =Model!T115 -> 16592 | G39: =Model!Y115 -> 7446.2411 | H39: =Model!AD115 -> 6633.6955 | I39: =Model!AE115 -> 6904.0477 | J39: =Model!AF115 -> 7257.1309 | K39: =Model!AG115 -> 7648.7992 | M39: =IFERROR((F39/D39)^(1/2)-1,"N/A") -> -0.095329645 | O39: =IFERROR((K39/G39)^(1/4)-1,"N/A") -> 0.0067323883
B40: YoY % Growth | E40: =E39/D39-1 -> -0.20919943 | F40: =F39/E39-1 -> 0.034936595 | G40: =G39/F39-1 -> -0.14651371 | H40: =H39/G39-1 -> -0.10912158 | I40: =I39/H39-1 -> 0.040754379 | J40: =J39/I39-1 -> 0.051141482 | K40: =K39/J39-1 -> 0.053970128
E42: Annuals | M42: Average | O42: Average
B43: Capitalization and Key Ratios | E43: =E19 -> 2024 | F43: =F19 -> 2025 | G43: =G19 -> 2026e | H43: =H19 -> 2027e | I43: =I19 -> 2028e | J43: =J19 -> 2029e | K43: =K19 -> 2030e | M43: Historical | O43: Projected
B44: =Summary!C91 -> Leverage
B45: =Summary!C92 -> Total Debt / EBITDA | D45: =Summary!T92 -> 0 | E45: =Summary!U92 -> 0 | F45: =Summary!V92 -> 0 | G45: =Summary!W92 -> 2.244437 | H45: =Summary!X92 -> 2.0374729 | I45: =Summary!Y92 -> 1.9392878 | J45: =Summary!Z92 -> 1.8579068 | K45: =Summary!AA92 -> 1.7916542 | M45: =AVERAGE(D45:F45) -> 0 | O45: =AVERAGE(G45:K45) -> 1.9741517
B46: =Summary!C93 -> Total Debt / Equity | D46: =Summary!T93 -> NA | E46: =Summary!U93 -> NA | F46: =Summary!V93 -> NA | G46: =Summary!W93 -> 1.0816532 | H46: =Summary!X93 -> 0.98256759 | I46: =Summary!Y93 -> 0.98232675 | J46: =Summary!Z93 -> 0.97805575 | K46: =Summary!AA93 -> 0.99422844 | M46: =AVERAGE(D46:F46) -> #DIV/0! | O46: =AVERAGE(G46:K46) -> 1.0037663
B47: =Summary!C94 -> Total Debt / Total Assets | D47: =Summary!T94 -> NA | E47: =Summary!U94 -> NA | F47: =Summary!V94 -> NA | G47: =Summary!W94 -> 0.37606537 | H47: =Summary!X94 -> 0.34087674 | I47: =Summary!Y94 -> 0.34087699 | J47: =Summary!Z94 -> 0.33807397 | K47: =Summary!AA94 -> 0.33924913 | M47: =AVERAGE(D47:F47) -> #DIV/0! | O47: =AVERAGE(G47:K47) -> 0.34702844
B49: =Summary!C103 -> Liquidity
B50: =Summary!C104 -> Current Ratio | D50: =Summary!T104 -> NA | E50: =Summary!U104 -> NA | F50: =Summary!V104 -> NA | G50: =Summary!W104 -> 0.59381309 | H50: =Summary!X104 -> 0.5664293 | I50: =Summary!Y104 -> 0.61791096 | J50: =Summary!Z104 -> 0.60986416 | K50: =Summary!AA104 -> 0.60986416 | M50: =AVERAGE(D50:F50) -> #DIV/0! | O50: =AVERAGE(G50:K50) -> 0.59957633
B51: =Summary!C105 -> Quick Ratio | D51: =Summary!T105 -> NA | E51: =Summary!U105 -> NA | F51: =Summary!V105 -> NA | G51: =Summary!W105 -> 0.48575226 | H51: =Summary!X105 -> 0.47581104 | I51: =Summary!Y105 -> 0.52675097 | J51: =Summary!Z105 -> 0.51888845 | K51: =Summary!AA105 -> 0.51888845 | M51: =AVERAGE(D51:F51) -> #DIV/0! | O51: =AVERAGE(G51:K51) -> 0.50521823
B52: =Summary!C106 -> Cash Ratio | D52: =Summary!T106 -> NA | E52: =Summary!U106 -> NA | F52: =Summary!V106 -> NA | G52: =Summary!W106 -> 0.01366376 | H52: =Summary!X106 -> 0.013541546 | I52: =Summary!Y106 -> 0.054490003 | J52: =Summary!Z106 -> 0.05437985 | K52: =Summary!AA106 -> 0.05437985 | M52: =AVERAGE(D52:F52) -> #DIV/0! | O52: =AVERAGE(G52:K52) -> 0.038091002
B54: =Summary!C75 -> Profitability
B55: =Summary!C80 -> Return on Assets (ROA) | D55: =Summary!T80 -> #DIV/0! | E55: =Summary!U80 -> #DIV/0! | F55: =Summary!V80 -> #DIV/0! | G55: =Summary!W80 -> 0.076587893 | H55: =Summary!X80 -> 0.072345143 | I55: =Summary!Y80 -> 0.080377942 | J55: =Summary!Z80 -> 0.082972545 | K55: =Summary!AA80 -> 0.087418129 | M55: =AVERAGE(D55:F55) -> #DIV/0! | O55: =AVERAGE(G55:K55) -> 0.07994033
B56: =Summary!C81 -> Return on Equity (ROE) | D56: =Summary!T81 -> #DIV/0! | E56: =Summary!U81 -> #DIV/0! | F56: =Summary!V81 -> #DIV/0! | G56: =Summary!W81 -> 0.22028494 | H56: =Summary!X81 -> 0.20853283 | I56: =Summary!Y81 -> 0.23163019 | J56: =Summary!Z81 -> 0.24004148 | K56: =Summary!AA81 -> 0.25619399 | M56: =AVERAGE(D56:F56) -> #DIV/0! | O56: =AVERAGE(G56:K56) -> 0.23133669
B57: Return on Inv. Capital (ROIC) | D57: =Summary!T82 -> #DIV/0! | E57: =Summary!U82 -> #DIV/0! | F57: =Summary!V82 -> #DIV/0! | G57: =Summary!W82 -> 0.10582211 | H57: =Summary!X82 -> 0.10518321 | I57: =Summary!Y82 -> 0.11684763 | J57: =Summary!Z82 -> 0.12135223 | K57: =Summary!AA82 -> 0.12846773 | M57: =AVERAGE(D57:F57) -> #DIV/0! | O57: =AVERAGE(G57:K57) -> 0.11553458
B59: =Summary!C84 -> Coverage
B60: Interest Expense | D60: =Summary!T85 -> 0 | E60: =Summary!U85 -> 0 | F60: =Summary!V85 -> 0 | G60: =Summary!W85 -> 1.225 | H60: =Summary!X85 -> -17 | I60: =Summary!Y85 -> -62 | J60: =Summary!Z85 -> -74 | K60: =Summary!AA85 -> -98 | M60: =AVERAGE(D60:F60) -> 0 | O60: =AVERAGE(G60:K60) -> -49.955
B61: Capital Expenditures | D61: =Summary!T86 -> 3807.2 | E61: =Summary!U86 -> 0 | F61: =Summary!V86 -> 0 | G61: =Summary!W86 -> 527.86204 | H61: =Summary!X86 -> 2039.7437 | I61: =Summary!Y86 -> 2054.902 | J61: =Summary!Z86 -> 2115.5228 | K61: =Summary!AA86 -> 2229.7814 | M61: =AVERAGE(D61:F61) -> 1269.0667 | O61: =AVERAGE(G61:K61) -> 1793.5624
B62: EBIT / Interest | D62: =Summary!T87 -> N/A | E62: =Summary!U87 -> N/A | F62: =Summary!V87 -> N/A | G62: =Summary!W87 -> 6.9586939 | H62: =Summary!X87 -> 7.9529591 | I62: =Summary!Y87 -> 9.6114817 | J62: =Summary!Z87 -> 10.275593 | K62: =Summary!AA87 -> 11.462084 | M62: =AVERAGE(D62:F62) -> #DIV/0! | O62: =AVERAGE(G62:K62) -> 9.2521623
B63: EBITDA / Interest | D63: =Summary!T88 -> N/A | E63: =Summary!U88 -> N/A | F63: =Summary!V88 -> N/A | G63: =Summary!W88 -> 10.321414 | H63: =Summary!X88 -> 12.030769 | I63: =Summary!Y88 -> 14.187371 | J63: =Summary!Z88 -> 15.239075 | K63: =Summary!AA88 -> 16.992382 | M63: =AVERAGE(D63:F63) -> #DIV/0! | O63: =AVERAGE(G63:K63) -> 13.754202
B64: (EBITDA - CapEx) / Interest | D64: =Summary!T89 -> N/A | E64: =Summary!U89 -> N/A | F64: =Summary!V89 -> N/A | G64: =Summary!W89 -> 4.5737281 | H64: =Summary!X89 -> 7.7556526 | I64: =Summary!Y89 -> 9.4319744 | J64: =Summary!Z89 -> 10.203554 | K64: =Summary!AA89 -> 11.363327 | M64: =AVERAGE(D64:F64) -> #DIV/0! | O64: =AVERAGE(G64:K64) -> 8.6656472
B66: =Summary!C96 -> Efficiency
B67: =Summary!C97 -> Asset Turnover | D67: =Summary!T97 -> #DIV/0! | E67: =Summary!U97 -> #DIV/0! | F67: =Summary!V97 -> #DIV/0! | G67: =Summary!W97 -> 0.51112932 | H67: =Summary!X97 -> 0.52605305 | I67: =Summary!Y97 -> 0.54251333 | J67: =Summary!Z97 -> 0.56510862 | K67: =Summary!AA97 -> 0.58622189 | M67: =AVERAGE(D67:F67) -> #DIV/0! | O67: =AVERAGE(G67:K67) -> 0.54620524
B68: =Summary!C98 -> Days Sales Outstanding | D68: =Summary!T98 -> 0 | E68: =Summary!U98 -> 0 | F68: =Summary!V98 -> 0 | G68: =Summary!W98 -> 21.228706 | H68: =Summary!X98 -> 41.020311 | I68: =Summary!Y98 -> 41.6 | J68: =Summary!Z98 -> 41 | K68: =Summary!AA98 -> 41 | M68: =AVERAGE(D68:F68) -> 0 | O68: =AVERAGE(G68:K68) -> 37.169803
B69: =Summary!C99 -> Days Inventory Outstanding | D69: =Summary!T99 -> #DIV/0! | E69: =Summary!U99 -> #DIV/0! | F69: =Summary!V99 -> #DIV/0! | G69: =Summary!W99 -> 0 | H69: =Summary!X99 -> 0 | I69: =Summary!Y99 -> 0 | J69: =Summary!Z99 -> 0 | K69: =Summary!AA99 -> 0 | M69: =AVERAGE(D69:F69) -> #DIV/0! | O69: =AVERAGE(G69:K69) -> 0
B70: =Summary!C100 -> Days Payables Outstanding | D70: =Summary!T100 -> #DIV/0! | E70: =Summary!U100 -> #DIV/0! | F70: =Summary!V100 -> #DIV/0! | G70: =Summary!W100 -> 93.233696 | H70: =Summary!X100 -> 46.999924 | I70: =Summary!Y100 -> 47.5 | J70: =Summary!Z100 -> 47 | K70: =Summary!AA100 -> 47 | M70: =AVERAGE(D70:F70) -> #DIV/0! | O70: =AVERAGE(G70:K70) -> 56.346724
B71: =Summary!C101 -> Cash Conversion Cycle | D71: =Summary!T101 -> #DIV/0! | E71: =Summary!U101 -> #DIV/0! | F71: =Summary!V101 -> #DIV/0! | G71: =Summary!W101 -> -72.00499 | H71: =Summary!X101 -> -5.979613 | I71: =Summary!Y101 -> -5.9 | J71: =Summary!Z101 -> -6 | K71: =Summary!AA101 -> -6 | M71: =AVERAGE(D71:F71) -> #DIV/0! | O71: =AVERAGE(G71:K71) -> -19.176921

Sheet Football Field
C1: =Company_Name&" - "&MID(CELL("filename",A1),FIND("]",CELL("filename",A1))+1,255)&": "&Case_Scenario&" Case" -> Republic Services, Inc. - Football Field: Base Case
C2: =Cover!C2 -> $ in Millions Except Per Share Data
A4: x | O4: Valuation Method: | T4: Downside | U4: Delta | V4: Upside | W4: x
O5: =TEXT(Valuation!E108,"0.0%")&" - "&TEXT(Valuation!E110,"0.0%")&" WACC"&" & "&TEXT(Valuation!G106,"0.0%")&" - "&TEXT(Valuation!I106,"0.0%")&" PGR" -> #DIV/0! | T5: =Valuation!G108 -> 269.88986 | U5: =V5-T5 -> -6.6777133 | V5: =Valuation!I110 -> 263.21214
O6: =TEXT(Valuation!E100,"0.0%")&" - "&TEXT(Valuation!E102,"0.0%")&" WACC"&" & "&TEXT(Valuation!G98,"0.0x")&" - "&TEXT(Valuation!I98,"0.0x")&" Exit Multiple" -> #DIV/0! | T6: =Valuation!G100 -> 232.45368 | U6: =V6-T6 -> 26.311981 | V6: =Valuation!I102 -> 258.76566
O8: =Valuation!F184&": "&TEXT(Valuation!G185,"0.0x")&" - "&TEXT(Valuation!I185,"0.0x") -> NTM EV/EBITDA Spread to Comps: 13.5x - 15.5x | T8: =Valuation!G187 -> 184.16511 | U8: =V8-T8 -> 90.688419 | V8: =Valuation!I189 -> 274.85353
O9: =Valuation!F176&": "&TEXT(Valuation!G177,"0.0x")&" - "&TEXT(Valuation!I177,"0.0x") -> NTM EV/EBITDA: 13.6x - 15.6x | T9: =Valuation!G179 -> 186.59498 | U9: =V9-T9 -> 91.228391 | V9: =Valuation!I181 -> 277.82337
O10: =Valuation!F168&": "&TEXT(Valuation!G169,"0.0x")&" - "&TEXT(Valuation!I169,"0.0x") -> NTM P/E Spread to Comps: 27.2x - 31.2x | T10: =Valuation!G171 -> #DIV/0! | U10: =V10-T10 -> #DIV/0! | V10: =Valuation!I173 -> #DIV/0!
O11: =Valuation!F160&": "&TEXT(Valuation!G161,"0.0x")&" - "&TEXT(Valuation!I161,"0.0x") -> NTM P/E: 29.2x - 31.2x | T11: =Valuation!G163 -> #DIV/0! | U11: =V11-T11 -> #DIV/0! | V11: =Valuation!I165 -> #DIV/0!
T13: =Valuation!G263 -> 151.01425 | U13: =V13-T13 -> 33.327384 | V13: =Valuation!I263 -> 184.34163
O14: =Valuation!F252&": "&TEXT(Valuation!G253,"0.0x")&" - "&TEXT(Valuation!I253,"0.0x") -> 2006-2010 Late Cycle EV/EBITDA: 12.7x - 14.7x | T14: =Valuation!G255 -> 170.8513 | U14: =V14-T14 -> 33.327384 | V14: =Valuation!I255 -> 204.17868
O15: =Valuation!F244&": "&TEXT(Valuation!G245,"0.0x")&" - "&TEXT(Valuation!I245,"0.0x") -> 2006-2010 Late Cycle P/E Spread to Comps: 27.3x - 29.3x | T15: =Valuation!G247 -> #DIV/0! | U15: =V15-T15 -> #DIV/0! | V15: =Valuation!I247 -> #DIV/0!
O16: =Valuation!F236&": "&TEXT(Valuation!G237,"0.0x")&" - "&TEXT(Valuation!I237,"0.0x") -> 2006-2010 Late Cycle P/E: 27.6x - 29.6x | T16: =Valuation!G239 -> #DIV/0! | U16: =V16-T16 -> #DIV/0! | V16: =Valuation!I239 -> #DIV/0!
O18: 52-Week Price Range: | T18: =Share_Price_Low -> 201.42 | U18: =V18-T18 -> 57.33 | V18: =Share_Price_High -> 258.75
O19: Median Value: | T19: =MEDIAN(T5:T18) -> 203.08467 | U19: =MEDIAN(U5:U18) -> 33.327384 | V19: =MEDIAN(V5:V18) -> 258.76566
A20: x | O20: Implied Return (%): | T20: =T19/Share_Price-1 -> -0.016777216 | V20: =V19/Share_Price-1 -> 0.25279911
T22: Reference Points for Price Axis
U24: Price
A25: x | T25: High | U25: =MAX(V5:V18)*1.1 -> 313.24833 | W25: x
T26: Low | U26: =MIN(T5:T18)*0.9 -> 135.91282
A30: x

Sheet Integrity
C1: =Company_Name&" - "&MID(CELL("filename",A1),FIND("]",CELL("filename",A1))+1,255) -> Republic Services, Inc. - Integrity
C3: Integrity
C4: Metric
C6: Model:
C7: Balance Sheet Check: | D7: =IF(Case_Scenario="Base","OK!","Check!") -> OK!
C8: Base Case: | D8: =IF(Case_Scenario="Base","OK!","Check!") -> OK!
C9: Interest Expense: | D9: =IF(Model!C8="On","OK!","CHECK - OFF") -> OK!
C10: Valuation Date:
C12: Formatting:
C13: Valuation Sensitivity Tables: | D13: =SUM(Valuation!F92,Valuation!K92,Valuation!Q92,Valuation!F151:F155,Valuation!M151:M155,Valuation!F227:F231,Valuation!M227:M231) -> #DIV/0!
C14: WACC Tables: | D14: =SUM(WACC!Q20,WACC!N33:N37) -> #DIV/0!
C16: Font Toggles:
C17: Cover: | D17: =Cover!$Q$2 -> Report
C18: Revenue Build: | D18: ='Revenue Build'!$C$22 -> Report
C19: Model: | D19: =Model!$C$5 -> Report
C20: WACC | D20: =WACC!R5 -> Report
C21: Valuation: | D21: =Valuation!$S$2 -> Report
C23: Change Log
C24: Date | D24: Version | E24: Operator | F24: Revisions
C25: 44476 | D25: v01 | E25: Nate Latimer | F25: Top Down / Bottom Up toggle integration and Capital IQ comps sheet w/ ID Locator
C26: 44476 | D26: v02 | E26: Carson Shaner | F26: Formulas for EBIT/EBITDA margins on earnings sheets
C27: 44480 | D27: v03 | E27: Nate Latimer | F27: Historical driver adjustments to reflect Top Down / Bottom Up Toggle
C28: 44488 | D28: v04 | E28: Nate Latimer | F28: Bug fixes to model output, comps sheet and WACC Comps Relevered Beta
C29: 44489 | D29: v05 | E29: Lilianna Ruby | F29: Changed the year end driver in 2021 and 2022 to correctly pull operating margins
C30: 44491 | D30: v06 | E30: Lilianna Ruby | F30: Changed the first page to add 365 to your previous fiscal year
C31: 44496 | D31: v07 | E31: Carson Shaner | F31: Changed Model Output FCF formula, broke apart D&A for historical periods, added checks for EPS & EBITDA in Valuation sensitivity tables, added segment D&A breakdown, linked and fixed SOTP valuation
C32: 44503 | D32: v08 | E32: Lilianna Ruby | F32: Changed average of comps on valuation tab to average all peers not just the first one
C33: 44512 | D33: v09 | E33: Lilianna Ruby | F33: Rolled model forward to reflect 3Q'21. Also changed the multiples tab so the quarters roll forward and end on correct date.
C34: 44522 | D34: v10 | E34: Lilianna Ruby | F34: Fully fixed the multiples tab so it is automatic and fully functional. Also fixed definition of NTM_EPS and NTM_EBITDA
C35: 44582 | D35: v13 | E35: Carson Shaner | F35: Changed EPS, EBITDA, shares, tax rate, etc., to formulas so we do not have to hardcode them.
C36: 44584 | D36: v14 | E36: Lilianna Ruby | F36: Changed discount factor to mid year
... C47: 45581 | D47: v25 | E47: Conor McCabe | F47: Added font toggle to integrity tab for WACC tab. Formatted Comparables Tab.

Sheet Revenue Build
C1: =Company_Name&" - "&MID(CELL("filename",A1),FIND("]",CELL("filename",A1))+1,255)&": "&Case_Scenario&" Case" -> Republic Services, Inc. - Revenue Build: Base Case
C2: =Cover!C2 -> $ in Millions Except Per Share Data
A4: x | C4: Segments
C6: =C30&" Methodology" -> Total Company Revenue Methodology
C7: Segment
C8: =C32&" Methodology" -> Collection Revenue Methodology
C9: =IF(Company_Rev_Methodology="Segment","Segment",IF(Company_Rev_Methodology="Activity-Based","Activity-Based",IF(Company_Rev_Methodology="Backlog","Backlog",IF(Company_Rev_Methodology="Mixed",D9,"--")))) -> Segment | D9: Backlog
C10: =C35&" Methodology" -> Landfill Revenue Methodology
C11: =IF(Company_Rev_Methodology="Segment","Segment",IF(Company_Rev_Methodology="Activity-Based","Activity-Based",IF(Company_Rev_Methodology="Backlog","Backlog",IF(Company_Rev_Methodology="Mixed",D11,"--")))) -> Segment | D11: Activity-Based
C12: =C38&" Methodology" -> Environmental solutions Revenue Methodology
C13: =IF(Company_Rev_Methodology="Segment","Segment",IF(Company_Rev_Methodology="Activity-Based","Activity-Based",IF(Company_Rev_Methodology="Backlog","Backlog",IF(Company_Rev_Methodology="Mixed",D13,"--")))) -> Segment | D13: Segment
C14: =C41&" Methodology" -> Transfer Revenue Methodology
C15: =IF(Company_Rev_Methodology="Segment","Segment",IF(Company_Rev_Methodology="Activity-Based","Activity-Based",IF(Company_Rev_Methodology="Backlog","Backlog",IF(Company_Rev_Methodology="Mixed",D15,"--")))) -> Segment | D15: Segment
C16: =C44&" Methodology" -> Other Revenue Methodology
C17: =IF(Company_Rev_Methodology="Segment","Segment",IF(Company_Rev_Methodology="Activity-Based","Activity-Based",IF(Company_Rev_Methodology="Backlog","Backlog",IF(Company_Rev_Methodology="Mixed",D17,"--")))) -> Segment | D17: Segment
C18: =C47&" Methodology" -> Professional Services and Other Revenue Methodology
C19: =IF(Company_Rev_Methodology="Segment","Segment",IF(Company_Rev_Methodology="Activity-Based","Activity-Based",IF(Company_Rev_Methodology="Backlog","Backlog",IF(Company_Rev_Methodology="Mixed",D19,"--")))) -> Segment | D19: Segment
C21: Font Toggle
C22: Report
C24: Annual vs. Quarterly
C25: Annual
J26: 1 | O26: 2 | T26: 3 | Y26: 4 | AD26: 5 | AE26: 6 | AF26: 7 | AG26: 8
AI27: CAGR
A28: x | C28: Summary | F28: =Model!F$25 -> 1Q23 | G28: =Model!G$25 -> 2Q23 | H28: =Model!H$25 -> 3Q23 | I28: =Model!I$25 -> 4Q23 | J28: =Model!J$25 -> 2023 | K28: =Model!K$25 -> 1Q24 | L28: =Model!L$25 -> 2Q24 | M28: =Model!M$25 -> 3Q24 | ... AG28: =Model!AG$25 -> 2030e | AI28: Historical | AJ28: Projected
C30: Total Company Revenue | F30: ='Segment Analysis'!F8 -> 3581.1 | G30: ='Segment Analysis'!G8 -> 3725.9 | H30: ='Segment Analysis'!H8 -> 3825.9 | I30: ='Segment Analysis'!I8 -> 3831.6 | J30: ='Segment Analysis'!J8 -> 14964.5 | K30: ='Segment Analysis'!K8 -> 3861.7 | L30: ='Segment Analysis'!L8 -> 4048 | M30: ='Segment Analysis'!M8 -> 4076.2 | ... T30: ='Segment Analysis'!T8 -> 16592 | U30: =SUM(U32,U35,U38,U41,U44,U47,) -> 4152.631 | V30: =SUM(V32,V35,V38,V41,V44,V47,) -> 4379.486 | W30: =SUM(W32,W35,W38,W41,W44,W47,) -> 4358.186 | X30: =SUM(X32,X35,X38,X41,X44,X47,) -> 4310.51 | Y30: =SUM(U30:X30) -> 17200.813 | Z30: =SUM(Z32,Z35,Z38,Z41,Z44,Z47,) -> 4358.6652 | AA30: =SUM(AA32,AA35,AA38,AA41,AA44,AA47,) -> 4593.3476 | AB30: =SUM(AB32,AB35,AB38,AB41,AB44,AB47,) -> 4573.9711 | AC30: =SUM(AC32,AC35,AC38,AC41,AC44,AC47,) -> 4522.6788 | AD30: =SUM(Z30:AC30) -> 18048.663 | AE30: =SUM(AE32,AE35,AE38,AE41,AE44,AE47,) -> 18921.749 | AF30: =SUM(AF32,AF35,AF38,AF41,AF44,AF47,) -> 19882.733 | AG30: =SUM(AG32,AG35,AG38,AG41,AG44,AG47,) -> 20839.079 | AI30: =IFERROR((T30/J30)^(1/2)-1,"--") -> 0.052975495 | AJ30: =IFERROR((AG30/T30)^(1/5)-1,"--") -> 0.046636692
C31: =IF($C$25="Quarterly","% Growth QoQ","% Growth YoY") -> % Growth YoY | G31: =IF($C$25="Annual",'Segment Analysis'!G173,'Segment Analysis'!G193) -> N/A | H31: =IF($C$25="Annual",'Segment Analysis'!H173,'Segment Analysis'!H193) -> N/A | I31: =IF($C$25="Annual",'Segment Analysis'!I173,'Segment Analysis'!I193) -> N/A | K31: =IF($C$25="Annual",'Segment Analysis'!K173,'Segment Analysis'!K193) -> 0.078355812 | L31: =IF($C$25="Annual",'Segment Analysis'!L173,'Segment Analysis'!L193) -> 0.086448912 | M31: =IF($C$25="Annual",'Segment Analysis'!M173,'Segment Analysis'!M193) -> 0.065422515 | N31: =IF($C$25="Annual",'Segment Analysis'!N173,'Segment Analysis'!N193) -> 0.055955737 | O31: =IF($C$25="Annual",'Segment Analysis'!O173,'Segment Analysis'!O193) -> 0.071328812 | P31: =IF($C$25="Annual",'Segment Analysis'!P173,'Segment Analysis'!P193) -> 0.038143823 | Q31: =IF($C$25="Annual",'Segment Analysis'!Q173,'Segment Analysis'!Q193) -> 0.046195652 | R31: =IF($C$25="Annual",'Segment Analysis'!R173,'Segment Analysis'!R193) -> 0.033315343 | ... T31: =IF($C$25="Annual",'Segment Analysis'!T173,'Segment Analysis'!T193) -> 0.034936595 | U31: =IFERROR(U30/S30-1,"--") -> 0.0040210348 | V31: =IFERROR(V30/U30-1,"--") -> 0.054629222 | W31: =IFERROR(W30/V30-1,"--") -> -0.0048635844 | X31: =IFERROR(X30/W30-1,"--") -> -0.010939414 | Y31: =IFERROR(Y30/T30-1,"--") -> 0.036693165 | Z31: =IFERROR(Z30/X30-1,"--") -> 0.011171571 | AA31: =IFERROR(AA30/Z30-1,"--") -> 0.053842722 | AB31: =IFERROR(AB30/AA30-1,"--") -> -0.0042183758 | AC31: =IFERROR(AC30/AB30-1,"--") -> -0.011213947 | AD31: =IFERROR(AD30/Y30-1,"--") -> 0.049291255 | AE31: =IFERROR(AE30/AD30-1,"--") -> 0.048374028 | AF31: =IFERROR(AF30/AE30-1,"--") -> 0.050787257 | AG31: =IFERROR(AG30/AF30-1,"--") -> 0.048099317
C32: ='Segment Analysis'!C9 -> Collection Revenue | F32: ='Segment Analysis'!F9 -> 2458.4 | G32: ='Segment Analysis'!G9 -> 2543 | H32: ='Segment Analysis'!H9 -> 2616.5 | I32: ='Segment Analysis'!I9 -> 2635 | J32: ='Segment Analysis'!J9 -> 10252.9 | K32: ='Segment Analysis'!K9 -> 2662.8 | L32: ='Segment Analysis'!L9 -> 2722.8 | M32: ='Segment Analysis'!M9 -> 2741.8 | ... T32: ='Segment Analysis'!T9 -> 11233 | U32: =IF(Segment1_Rev_Methodology="Segment",U53,IF(Segment1_Rev_Methodology="Activity-Based",U91,IF(Segment1_Rev_Methodology="Backlog",U165,"--"))) -> 2841.748 | V32: =IF(Segment1_Rev_Methodology="Segment",V53,IF(Segment1_Rev_Methodology="Activity-Based",V91,IF(Segment1_Rev_Methodology="Backlog",V165,"--"))) -> 2932.058 | W32: =IF(Segment1_Rev_Methodology="Segment",W53,IF(Segment1_Rev_Methodology="Activity-Based",W91,IF(Segment1_Rev_Methodology="Backlog",W165,"--"))) -> 2945.565 | X32: =IF(Segment1_Rev_Methodology="Segment",X53,IF(Segment1_Rev_Methodology="Activity-Based",X91,IF(Segment1_Rev_Methodology="Backlog",X165,"--"))) -> 2954.819 | Y32: =SUM(U32:X32) -> 11674.19 | Z32: =IF(Segment1_Rev_Methodology="Segment",Z53,IF(Segment1_Rev_Methodology="Activity-Based",Z91,IF(Segment1_Rev_Methodology="Backlog",Z165,"--"))) -> 2983.8354 | AA32: =IF(Segment1_Rev_Methodology="Segment",AA53,IF(Segment1_Rev_Methodology="Activity-Based",AA91,IF(Segment1_Rev_Methodology="Backlog",AA165,"--"))) -> 3075.7288 | AB32: =IF(Segment1_Rev_Methodology="Segment",AB53,IF(Segment1_Rev_Methodology="Activity-Based",AB91,IF(Segment1_Rev_Methodology="Backlog",AB165,"--"))) -> 3095.7888 | AC32: =IF(Segment1_Rev_Methodology="Segment",AC53,IF(Segment1_Rev_Methodology="Activity-Based",AC91,IF(Segment1_Rev_Methodology="Backlog",AC165,"--"))) -> 3105.5148 | AD32: =SUM(Z32:AC32) -> 12260.868 | AE32: =IF(Segment1_Rev_Methodology="Segment",AE53,IF(Segment1_Rev_Methodology="Activity-Based",AE91,IF(Segment1_Rev_Methodology="Backlog",AE165,"--"))) -> 12849.389 | AF32: =IF(Segment1_Rev_Methodology="Segment",AF53,IF(Segment1_Rev_Methodology="Activity-Based",AF91,IF(Segment1_Rev_Methodology="Backlog",AF165,"--"))) -> 13504.708 | AG32: =IF(Segment1_Rev_Methodology="Segment",AG53,IF(Segment1_Rev_Methodology="Activity-Based",AG91,IF(Segment1_Rev_Methodology="Backlog",AG165,"--"))) -> 14098.916 | AI32: =IFERROR((T32/J32)^(1/2)-1,"--") -> 0.04670553 | AJ32: =IFERROR((AG32/T32)^(1/5)-1,"--") -> 0.046497005
C33: =IF($C$25="Quarterly","% Growth QoQ","% Growth YoY") -> % Growth YoY | G33: =IF($C$25="Annual",'Segment Analysis'!G174,'Segment Analysis'!G194) -> N/A | H33: =IF($C$25="Annual",'Segment Analysis'!H174,'Segment Analysis'!H194) -> N/A | I33: =IF($C$25="Annual",'Segment Analysis'!I174,'Segment Analysis'!I194) -> N/A | K33: =IF($C$25="Annual",'Segment Analysis'!K174,'Segment Analysis'!K194) -> 0.083143508 | L33: =IF($C$25="Annual",'Segment Analysis'!L174,'Segment Analysis'!L194) -> 0.070703893 | M33: =IF($C$25="Annual",'Segment Analysis'!M174,'Segment Analysis'!M194) -> 0.047888401 | N33: =IF($C$25="Annual",'Segment Analysis'!N174,'Segment Analysis'!N194) -> 0.035294118 | O33: =IF($C$25="Annual",'Segment Analysis'!O174,'Segment Analysis'!O194) -> 0.058763862 | P33: =IF($C$25="Annual",'Segment Analysis'!P174,'Segment Analysis'!P194) -> 0.030118672 | Q33: =IF($C$25="Annual",'Segment Analysis'!Q174,'Segment Analysis'!Q194) -> 0.036433084 | R33: =IF($C$25="Annual",'Segment Analysis'!R174,'Segment Analysis'!R194) -> 0.033992268 | ... T33: =IF($C$25="Annual",'Segment Analysis'!T174,'Segment Analysis'!T194) -> 0.034784531 | U33: =IFERROR(U32/S32-1,"--") -> 0.0030878927 | V33: =IFERROR(V32/U32-1,"--") -> 0.031779736 | W33: =IFERROR(W32/V32-1,"--") -> 0.0046066619 | X33: =IFERROR(X32/W32-1,"--") -> 0.0031416723 | Y33: =IFERROR(Y32/T32-1,"--") -> 0.03927624 | Z33: =IFERROR(Z32/X32-1,"--") -> 0.0098200262 | AA33: =IFERROR(AA32/Z32-1,"--") -> 0.030797088 | AB33: =IFERROR(AB32/AA32-1,"--") -> 0.0065220226 | AC33: =IFERROR(AC32/AB32-1,"--") -> 0.0031416723 | AD33: =IFERROR(AD32/Y32-1,"--") -> 0.050254264 | AE33: =IFERROR(AE32/AD32-1,"--") -> 0.048 | AF33: =IFERROR(AF32/AE32-1,"--") -> 0.051 | AG33: =IFERROR(AG32/AF32-1,"--") -> 0.044
C34: % of Total Revenue | F34: ='Segment Analysis'!F17 -> 0.68649298 | G34: ='Segment Analysis'!G17 -> 0.68251966 | H34: ='Segment Analysis'!H17 -> 0.68389137 | I34: ='Segment Analysis'!I17 -> 0.68770227 | J34: ='Segment Analysis'!J17 -> 0.68514818 | K34: ='Segment Analysis'!K17 -> 0.68954088 | L34: ='Segment Analysis'!L17 -> 0.67262846 | M34: ='Segment Analysis'!M17 -> 0.67263628 | ... T34: ='Segment Analysis'!T17 -> 0.67701302 | U34: =U32/U$30 -> 0.68432471 | V34: =V32/V$30 -> 0.6694982 | W34: =W32/W$30 -> 0.6758695 | X34: =X32/X$30 -> 0.68549174 | Y34: =Y32/Y$30 -> 0.6786999 | Z34: =Z32/Z$30 -> 0.6845755 | AA34: =AA32/AA$30 -> 0.66960508 | AB34: =AB32/AB$30 -> 0.67682737 | ... AG34: =AG32/AG$30 -> 0.67656136
C35: ='Segment Analysis'!C10 -> Landfill Revenue | F35: ='Segment Analysis'!F10 -> 392.6 | G35: ='Segment Analysis'!G10 -> 431 | H35: ='Segment Analysis'!H10 -> 436.3 | I35: ='Segment Analysis'!I10 -> 419.6 | J35: ='Segment Analysis'!J10 -> 1679.5 | K35: ='Segment Analysis'!K10 -> 404.4 | L35: ='Segment Analysis'!L10 -> 440.2 | M35: ='Segment Analysis'!M10 -> 452.8 | ... T35: ='Segment Analysis'!T10 -> 1920 | U35: =IF(Segment2_Rev_Methodology="Segment",U59,IF(Segment2_Rev_Methodology="Activity-Based",U103,IF(Segment2_Rev_Methodology="Backlog",U177,"--"))) -> 439.103 | V35: =IF(Segment2_Rev_Methodology="Segment",V59,IF(Segment2_Rev_Methodology="Activity-Based",V103,IF(Segment2_Rev_Methodology="Backlog",V177,"--"))) -> 519.612 | W35: =IF(Segment2_Rev_Methodology="Segment",W59,IF(Segment2_Rev_Methodology="Activity-Based",W103,IF(Segment2_Rev_Methodology="Backlog",W177,"--"))) -> 520.644 | X35: =IF(Segment2_Rev_Methodology="Segment",X59,IF(Segment2_Rev_Methodology="Activity-Based",X103,IF(Segment2_Rev_Methodology="Backlog",X177,"--"))) -> 488.949 | Y35: =SUM(U35:X35) -> 1968.308 | Z35: =IF(Segment2_Rev_Methodology="Segment",Z59,IF(Segment2_Rev_Methodology="Activity-Based",Z103,IF(Segment2_Rev_Methodology="Backlog",Z177,"--"))) -> 459.74084 | AA35: =IF(Segment2_Rev_Methodology="Segment",AA59,IF(Segment2_Rev_Methodology="Activity-Based",AA103,IF(Segment2_Rev_Methodology="Backlog",AA177,"--"))) -> 546.63182 | AB35: =IF(Segment2_Rev_Methodology="Segment",AB59,IF(Segment2_Rev_Methodology="Activity-Based",AB103,IF(Segment2_Rev_Methodology="Backlog",AB177,"--"))) -> 545.63491 | AC35: =IF(Segment2_Rev_Methodology="Segment",AC59,IF(Segment2_Rev_Methodology="Activity-Based",AC103,IF(Segment2_Rev_Methodology="Backlog",AC177,"--"))) -> 510.9517 | AD35: =SUM(Z35:AC35) -> 2062.9593 | AE35: =IF(Segment2_Rev_Methodology="Segment",AE59,IF(Segment2_Rev_Methodology="Activity-Based",AE103,IF(Segment2_Rev_Methodology="Backlog",AE177,"--"))) -> 2180.548 | AF35: =IF(Segment2_Rev_Methodology="Segment",AF59,IF(Segment2_Rev_Methodology="Activity-Based",AF103,IF(Segment2_Rev_Methodology="Backlog",AF177,"--"))) -> 2302.6586 | AG35: =IF(Segment2_Rev_Methodology="Segment",AG59,IF(Segment2_Rev_Methodology="Activity-Based",AG103,IF(Segment2_Rev_Methodology="Backlog",AG177,"--"))) -> 2427.0022 | AI35: =IFERROR((T35/J35)^(1/3)-1,"--") -> 0.04561966 | AJ35: =IFERROR((AG35/T35)^(1/5)-1,"--") -> 0.047981917
C36: % Growth | G36: =IF($C$25="Annual",'Segment Analysis'!G175,'Segment Analysis'!G195) -> N/A | H36: =IF($C$25="Annual",'Segment Analysis'!H175,'Segment Analysis'!H195) -> N/A | I36: =IF($C$25="Annual",'Segment Analysis'!I175,'Segment Analysis'!I195) -> N/A | K36: =IF($C$25="Annual",'Segment Analysis'!K175,'Segment Analysis'!K195) -> 0.030056037 | L36: =IF($C$25="Annual",'Segment Analysis'!L175,'Segment Analysis'!L195) -> 0.021345708 | M36: =IF($C$25="Annual",'Segment Analysis'!M175,'Segment Analysis'!M195) -> 0.037818015 | N36: =IF($C$25="Annual",'Segment Analysis'!N175,'Segment Analysis'!N195) -> 0.055767398 | O36: ='Segment Analysis'!O175 -> 0.036260792 | P36: =IF($C$25="Annual",'Segment Analysis'!P175,'Segment Analysis'!P195) -> 0.041048467 | Q36: =IF($C$25="Annual",'Segment Analysis'!Q175,'Segment Analysis'!Q195) -> 0.17219446 | R36: =IF($C$25="Annual",'Segment Analysis'!R175,'Segment Analysis'!R195) -> 0.13957597 | S36: =IF($C$25="Annual",'Segment Analysis'!S175,'Segment Analysis'!S195) -> 0.054176072 | T36: ='Segment Analysis'!T175 -> 0.10319467 | U36: =IFERROR(U35/S35-1,"--") -> -0.059736617 | V36: =IFERROR(V35/U35-1,"--") -> 0.18334878 | W36: =IFERROR(W35/V35-1,"--") -> 0.0019860973 | X36: =IFERROR(X35/W35-1,"--") -> -0.06087653 | Y36: =IFERROR(Y35/T35-1,"--") -> 0.025160417 | Z36: =IFERROR(Z35/X35-1,"--") -> -0.059736617 | AA36: =IFERROR(AA35/Z35-1,"--") -> 0.18899992 | AB36: =IFERROR(AB35/AA35-1,"--") -> -0.0018237358 | AC36: =IFERROR(AC35/AB35-1,"--") -> -0.06356486 | AD36: =IFERROR(AD35/Y35-1,"--") -> 0.048087638 | AE36: =IFERROR(AE35/AD35-1,"--") -> 0.057 | AF36: =IFERROR(AF35/AE35-1,"--") -> 0.056 | AG36: =IFERROR(AG35/AF35-1,"--") -> 0.054
C37: % of Total Revenue | F37: ='Segment Analysis'!F18 -> 0.10963112 | G37: ='Segment Analysis'!G18 -> 0.11567675 | H37: ='Segment Analysis'!H18 -> 0.11403853 | I37: ='Segment Analysis'!I18 -> 0.10951039 | J37: ='Segment Analysis'!J18 -> 0.11223228 | K37: ='Segment Analysis'!K18 -> 0.10472072 | L37: ='Segment Analysis'!L18 -> 0.10874506 | M37: ='Segment Analysis'!M18 -> 0.11108385 | ... T37: ='Segment Analysis'!T18 -> 0.11571842 | U37: =U35/U$30 -> 0.10574091 | V37: =V35/V$30 -> 0.1186468 | W37: =W35/W$30 -> 0.11946346 | X37: =X35/X$30 -> 0.11343182 | Y37: =Y35/Y$30 -> 0.1144311 | Z37: =Z35/Z$30 -> 0.10547744 | AA37: =AA35/AA$30 -> 0.11900511 | AB37: =AB35/AB$30 -> 0.11929129 | ... AG37: =AG35/AG$30 -> 0.11646399
C38: ='Segment Analysis'!C11 -> Environmental solutions Revenue | F38: ='Segment Analysis'!F11 -> 408.3 | G38: ='Segment Analysis'!G11 -> 398.3 | H38: ='Segment Analysis'!H11 -> 404.8 | I38: ='Segment Analysis'!I11 -> 413.4 | J38: ='Segment Analysis'!J11 -> 1624.8 | K38: ='Segment Analysis'!K11 -> 423.3 | L38: ='Segment Analysis'!L11 -> 472.6 | M38: ='Segment Analysis'!M11 -> 464.7 | ... T38: ='Segment Analysis'!T11 -> 1766 | U38: =IF(Segment3_Rev_Methodology="Segment",U65,IF(Segment3_Rev_Methodology="Activity-Based",U115,IF(Segment3_Rev_Methodology="Backlog",U189,"--"))) -> 463.368 | V38: =IF(Segment3_Rev_Methodology="Segment",V65,IF(Segment3_Rev_Methodology="Activity-Based",V115,IF(Segment3_Rev_Methodology="Backlog",V189,"--"))) -> 478.17 | W38: =IF(Segment3_Rev_Methodology="Segment",W65,IF(Segment3_Rev_Methodology="Activity-Based",W115,IF(Segment3_Rev_Methodology="Backlog",W189,"--"))) -> 449.021 | X38: =IF(Segment3_Rev_Methodology="Segment",X65,IF(Segment3_Rev_Methodology="Activity-Based",X115,IF(Segment3_Rev_Methodology="Backlog",X189,"--"))) -> 442.256 | Y38: =SUM(U38:X38) -> 1832.815 | Z38: =IF(Segment3_Rev_Methodology="Segment",Z65,IF(Segment3_Rev_Methodology="Activity-Based",Z115,IF(Segment3_Rev_Methodology="Backlog",Z189,"--"))) -> 489.31661 | AA38: =IF(Segment3_Rev_Methodology="Segment",AA65,IF(Segment3_Rev_Methodology="Activity-Based",AA115,IF(Segment3_Rev_Methodology="Backlog",AA189,"--"))) -> 502.55667 | AB38: =IF(Segment3_Rev_Methodology="Segment",AB65,IF(Segment3_Rev_Methodology="Activity-Based",AB115,IF(Segment3_Rev_Methodology="Backlog",AB189,"--"))) -> 471.02303 | AC38: =IF(Segment3_Rev_Methodology="Segment",AC65,IF(Segment3_Rev_Methodology="Activity-Based",AC115,IF(Segment3_Rev_Methodology="Backlog",AC189,"--"))) -> 463.92654 | AD38: =SUM(Z38:AC38) -> 1926.8229 | AE38: =IF(Segment3_Rev_Methodology="Segment",AE65,IF(Segment3_Rev_Methodology="Activity-Based",AE115,IF(Segment3_Rev_Methodology="Backlog",AE189,"--"))) -> 2025.0908 | AF38: =IF(Segment3_Rev_Methodology="Segment",AF65,IF(Segment3_Rev_Methodology="Activity-Based",AF115,IF(Segment3_Rev_Methodology="Backlog",AF189,"--"))) -> 2138.4959 | AG38: =IF(Segment3_Rev_Methodology="Segment",AG65,IF(Segment3_Rev_Methodology="Activity-Based",AG115,IF(Segment3_Rev_Methodology="Backlog",AG189,"--"))) -> 2288.1906 | AI38: =IFERROR((T38/J38)^(1/3)-1,"--") -> 0.028166848 | AJ38: =IFERROR((AG38/T38)^(1/5)-1,"--") -> 0.053174415
C39: % Growth | G39: =IF($C$25="Annual",'Segment Analysis'!G176,'Segment Analysis'!G196) -> N/A | H39: =IF($C$25="Annual",'Segment Analysis'!H176,'Segment Analysis'!H196) -> N/A | I39: =IF($C$25="Annual",'Segment Analysis'!I176,'Segment Analysis'!I196) -> N/A | K39: =IF($C$25="Annual",'Segment Analysis'!K176,'Segment Analysis'!K196) -> 0.036737693 | L39: =IF($C$25="Annual",'Segment Analysis'!L176,'Segment Analysis'!L196) -> 0.18654281 | M39: =IF($C$25="Annual",'Segment Analysis'!M176,'Segment Analysis'!M196) -> 0.14797431 | N39: =IF($C$25="Annual",'Segment Analysis'!N176,'Segment Analysis'!N196) -> 0.16594098 | O39: =IF($C$25="Annual",'Segment Analysis'!O176,'Segment Analysis'!O196) -> 0.13404727 | P39: =IF($C$25="Annual",'Segment Analysis'!P176,'Segment Analysis'!P196) -> 0.060713442 | Q39: =IF($C$25="Annual",'Segment Analysis'!Q176,'Segment Analysis'!Q196) -> -0.022429116 | R39: =IF($C$25="Annual",'Segment Analysis'!R176,'Segment Analysis'!R196) -> -0.068216053 | ... T39: =IF($C$25="Annual",'Segment Analysis'!T176,'Segment Analysis'!T196) -> -0.041571692 | U39: =IFERROR(U38/S38-1,"--") -> 0.098028436 | V39: =IFERROR(V38/U38-1,"--") -> 0.031944373 | W39: =IFERROR(W38/V38-1,"--") -> -0.060959491 | X39: =IFERROR(X38/W38-1,"--") -> -0.01506611 | Y39: =IFERROR(Y38/T38-1,"--") -> 0.037834088 | Z39: =IFERROR(Z38/X38-1,"--") -> 0.10641033 | AA39: =IFERROR(AA38/Z38-1,"--") -> 0.027058272 | AB39: =IFERROR(AB38/AA38-1,"--") -> -0.062746438 | AC39: =IFERROR(AC38/AB38-1,"--") -> -0.01506611 | AD39: =IFERROR(AD38/Y38-1,"--") -> 0.051291511 | AE39: =IFERROR(AE38/AD38-1,"--") -> 0.051 | AF39: =IFERROR(AF38/AE38-1,"--") -> 0.056 | AG39: =IFERROR(AG38/AF38-1,"--") -> 0.07
C40: % of Total Revenue | F40: ='Segment Analysis'!F19 -> 0.11401525 | G40: ='Segment Analysis'!G19 -> 0.10690035 | H40: ='Segment Analysis'!H19 -> 0.10580517 | I40: ='Segment Analysis'!I19 -> 0.10789226 | J40: ='Segment Analysis'!J19 -> 0.10857697 | K40: ='Segment Analysis'!K19 -> 0.10961494 | L40: ='Segment Analysis'!L19 -> 0.11674901 | M40: ='Segment Analysis'!M19 -> 0.11400324 | ... T40: ='Segment Analysis'!T19 -> 0.10643684 | U40: =U38/U$30 -> 0.1115842 | V40: =V38/V$30 -> 0.10918405 | W40: =W38/W$30 -> 0.10302933 | X40: =X38/X$30 -> 0.10259946 | Y40: =Y38/Y$30 -> 0.10655398 | Z40: =Z38/Z$30 -> 0.11226295 | AA40: =AA38/AA$30 -> 0.10940968 | AB40: =AB38/AB$30 -> 0.10297901 | ... AG40: =AG38/AG$30 -> 0.10980287
C41: ='Segment Analysis'!C12 -> Transfer Revenue | F41: ='Segment Analysis'!F12 -> 173.3 | G41: ='Segment Analysis'!G12 -> 197.3 | H41: ='Segment Analysis'!H12 -> 206.2 | I41: ='Segment Analysis'!I12 -> 188.2 | J41: ='Segment Analysis'!J12 -> 765 | K41: ='Segment Analysis'!K12 -> 182.8 | L41: ='Segment Analysis'!L12 -> 208.2 | M41: ='Segment Analysis'!M12 -> 211.6 | ... T41: ='Segment Analysis'!T12 -> 847 | U41: =IF(Segment4_Rev_Methodology="Segment",U71,IF(Segment4_Rev_Methodology="Activity-Based",U127,IF(Segment4_Rev_Methodology="Backlog",U201,"--"))) -> 196.46 | V41: =IF(Segment4_Rev_Methodology="Segment",V71,IF(Segment4_Rev_Methodology="Activity-Based",V127,IF(Segment4_Rev_Methodology="Backlog",V201,"--"))) -> 230.724 | W41: =IF(Segment4_Rev_Methodology="Segment",W71,IF(Segment4_Rev_Methodology="Activity-Based",W127,IF(Segment4_Rev_Methodology="Backlog",W201,"--"))) -> 233.856 | X41: =IF(Segment4_Rev_Methodology="Segment",X71,IF(Segment4_Rev_Methodology="Activity-Based",X127,IF(Segment4_Rev_Methodology="Backlog",X201,"--"))) -> 224.486 | Y41: =SUM(U41:X41) -> 885.526 | Z41: =IF(Segment4_Rev_Methodology="Segment",Z71,IF(Segment4_Rev_Methodology="Activity-Based",Z127,IF(Segment4_Rev_Methodology="Backlog",Z201,"--"))) -> 207.46176 | AA41: =IF(Segment4_Rev_Methodology="Segment",AA71,IF(Segment4_Rev_Methodology="Activity-Based",AA127,IF(Segment4_Rev_Methodology="Backlog",AA201,"--"))) -> 242.72165 | AB41: =IF(Segment4_Rev_Methodology="Segment",AB71,IF(Segment4_Rev_Methodology="Activity-Based",AB127,IF(Segment4_Rev_Methodology="Backlog",AB201,"--"))) -> 245.31494 | AC41: =IF(Segment4_Rev_Methodology="Segment",AC71,IF(Segment4_Rev_Methodology="Activity-Based",AC127,IF(Segment4_Rev_Methodology="Backlog",AC201,"--"))) -> 235.48581 | AD41: =SUM(Z41:AC41) -> 930.98417 | AE41: =IF(Segment4_Rev_Methodology="Segment",AE71,IF(Segment4_Rev_Methodology="Activity-Based",AE127,IF(Segment4_Rev_Methodology="Backlog",AE201,"--"))) -> 971.94747 | AF41: =IF(Segment4_Rev_Methodology="Segment",AF71,IF(Segment4_Rev_Methodology="Activity-Based",AF127,IF(Segment4_Rev_Methodology="Backlog",AF201,"--"))) -> 1021.5168 | AG41: =IF(Segment4_Rev_Methodology="Segment",AG71,IF(Segment4_Rev_Methodology="Activity-Based",AG127,IF(Segment4_Rev_Methodology="Backlog",AG201,"--"))) -> 1050.1193 | AI41: =IFERROR((T41/J41)^(1/3)-1,"--") -> 0.03452421 | AJ41: =IFERROR((AG41/T41)^(1/5)-1,"--") -> 0.043929193
C42: % Growth | G42: =IF($C$25="Annual",'Segment Analysis'!G177,'Segment Analysis'!G197) -> N/A | H42: =IF($C$25="Annual",'Segment Analysis'!H177,'Segment Analysis'!H197) -> N/A | I42: =IF($C$25="Annual",'Segment Analysis'!I177,'Segment Analysis'!I197) -> N/A | K42: =IF($C$25="Annual",'Segment Analysis'!K177,'Segment Analysis'!K197) -> 0.054818234 | L42: =IF($C$25="Annual",'Segment Analysis'!L177,'Segment Analysis'!L197) -> 0.055245819 | M42: =IF($C$25="Annual",'Segment Analysis'!M177,'Segment Analysis'!M197) -> 0.026188167 | N42: =IF($C$25="Annual",'Segment Analysis'!N177,'Segment Analysis'!N197) -> 0.078639745 | O42: =IF($C$25="Annual",'Segment Analysis'!O177,'Segment Analysis'!O197) -> 0.053071895 | P42: =IF($C$25="Annual",'Segment Analysis'!P177,'Segment Analysis'!P197) -> 0.028446389 | Q42: =IF($C$25="Annual",'Segment Analysis'!Q177,'Segment Analysis'!Q197) -> 0.061479347 | R42: =IF($C$25="Annual",'Segment Analysis'!R177,'Segment Analysis'!R197) -> 0.058601134 | ... T42: =IF($C$25="Annual",'Segment Analysis'!T177,'Segment Analysis'!T197) -> 0.051390268 | U42: =IFERROR(U41/S41-1,"--") -> -0.081962617 | V42: =IFERROR(V41/U41-1,"--") -> 0.174407 | W42: =IFERROR(W41/V41-1,"--") -> 0.013574661 | X42: =IFERROR(X41/W41-1,"--") -> -0.040067392 | Y42: =IFERROR(Y41/T41-1,"--") -> 0.045485242 | Z42: =IFERROR(Z41/X41-1,"--") -> -0.075836533 | AA42: =IFERROR(AA41/Z41-1,"--") -> 0.16995849 | AB42: =IFERROR(AB41/AA41-1,"--") -> 0.010684239 | AC42: =IFERROR(AC41/AB41-1,"--") -> -0.040067392 | AD42: =IFERROR(AD41/Y41-1,"--") -> 0.051334649 | AE42: =IFERROR(AE41/AD41-1,"--") -> 0.044 | AF42: =IFERROR(AF41/AE41-1,"--") -> 0.051 | AG42: =IFERROR(AG41/AF41-1,"--") -> 0.028
C43: % of Total Revenue | F43: ='Segment Analysis'!F20 -> 0.048392952 | G43: ='Segment Analysis'!G20 -> 0.052953649 | H43: ='Segment Analysis'!H20 -> 0.053895815 | I43: ='Segment Analysis'!I20 -> 0.049117862 | J43: ='Segment Analysis'!J20 -> 0.051120986 | K43: ='Segment Analysis'!K20 -> 0.047336665 | L43: ='Segment Analysis'!L20 -> 0.051432806 | M43: ='Segment Analysis'!M20 -> 0.051911094 | ... T43: ='Segment Analysis'!T20 -> 0.051048698 | U43: =U41/U$30 -> 0.047309766 | V43: =V41/V$30 -> 0.052682895 | W43: =W41/W$30 -> 0.053659022 | X43: =X41/X$30 -> 0.052078756 | Y43: =Y41/Y$30 -> 0.051481636 | Z43: =Z41/Z$30 -> 0.047597545 | AA43: =AA41/AA$30 -> 0.052841995 | AB43: =AB41/AB$30 -> 0.053632815 | ... AG43: =AG41/AG$30 -> 0.050391827
C44: ='Segment Analysis'!C13 -> Other Revenue | F44: ='Segment Analysis'!F13 -> 148.5 | G44: ='Segment Analysis'!G13 -> 156.3 | H44: ='Segment Analysis'!H13 -> 162.1 | I44: ='Segment Analysis'!I13 -> 175.4 | J44: ='Segment Analysis'!J13 -> 642.3 | K44: ='Segment Analysis'!K13 -> 188.4 | L44: ='Segment Analysis'!L13 -> 204.2 | M44: ='Segment Analysis'!M13 -> 205.3 | ... T44: ='Segment Analysis'!T13 -> 826 | U44: =IF(Segment5_Rev_Methodology="Segment",U77,IF(Segment5_Rev_Methodology="Activity-Based",U139,IF(Segment5_Rev_Methodology="Backlog",U213,"--"))) -> 211.952 | V44: =IF(Segment5_Rev_Methodology="Segment",V77,IF(Segment5_Rev_Methodology="Activity-Based",V139,IF(Segment5_Rev_Methodology="Backlog",V213,"--"))) -> 218.922 | W44: =IF(Segment5_Rev_Methodology="Segment",W77,IF(Segment5_Rev_Methodology="Activity-Based",W139,IF(Segment5_Rev_Methodology="Backlog",W213,"--"))) -> 209.1 | X44: =IF(Segment5_Rev_Methodology="Segment",X77,IF(Segment5_Rev_Methodology="Activity-Based",X139,IF(Segment5_Rev_Methodology="Backlog",X213,"--"))) -> 200 | Y44: =SUM(U44:X44) -> 839.974 | Z44: =IF(Segment5_Rev_Methodology="Segment",Z77,IF(Segment5_Rev_Methodology="Activity-Based",Z139,IF(Segment5_Rev_Methodology="Backlog",Z213,"--"))) -> 218.31056 | AA44: =IF(Segment5_Rev_Methodology="Segment",AA77,IF(Segment5_Rev_Methodology="Activity-Based",AA139,IF(Segment5_Rev_Methodology="Backlog",AA213,"--"))) -> 225.70858 | AB44: =IF(Segment5_Rev_Methodology="Segment",AB77,IF(Segment5_Rev_Methodology="Activity-Based",AB139,IF(Segment5_Rev_Methodology="Backlog",AB213,"--"))) -> 216.2094 | AC44: =IF(Segment5_Rev_Methodology="Segment",AC77,IF(Segment5_Rev_Methodology="Activity-Based",AC139,IF(Segment5_Rev_Methodology="Backlog",AC213,"--"))) -> 206.8 | AD44: =SUM(Z44:AC44) -> 867.02854 | AE44: =IF(Segment5_Rev_Methodology="Segment",AE77,IF(Segment5_Rev_Methodology="Activity-Based",AE139,IF(Segment5_Rev_Methodology="Backlog",AE213,"--"))) -> 894.77346 | AF44: =IF(Segment5_Rev_Methodology="Segment",AF77,IF(Segment5_Rev_Methodology="Activity-Based",AF139,IF(Segment5_Rev_Methodology="Backlog",AF213,"--"))) -> 915.35324 | AG44: =IF(Segment5_Rev_Methodology="Segment",AG77,IF(Segment5_Rev_Methodology="Activity-Based",AG139,IF(Segment5_Rev_Methodology="Backlog",AG213,"--"))) -> 974.85121 | AI44: =IFERROR((T44/J44)^(1/3)-1,"--") -> 0.087461879 | AJ44: =IFERROR((AG44/T44)^(1/5)-1,"--") -> 0.033693195
C45: % Growth | G45: =IF($C$25="Annual",'Segment Analysis'!G178,'Segment Analysis'!G198) -> N/A | H45: =IF($C$25="Annual",'Segment Analysis'!H178,'Segment Analysis'!H198) -> N/A | I45: =IF($C$25="Annual",'Segment Analysis'!I178,'Segment Analysis'!I198) -> N/A | K45: =IF($C$25="Annual",'Segment Analysis'!K178,'Segment Analysis'!K198) -> 0.26868687 | L45: =IF($C$25="Annual",'Segment Analysis'!L178,'Segment Analysis'!L198) -> 0.30646193 | M45: =IF($C$25="Annual",'Segment Analysis'!M178,'Segment Analysis'!M198) -> 0.26650216 | N45: =IF($C$25="Annual",'Segment Analysis'!N178,'Segment Analysis'!N198) -> 0.083238312 | O45: =IF($C$25="Annual",'Segment Analysis'!O178,'Segment Analysis'!O198) -> 0.22668535 | P45: =IF($C$25="Annual",'Segment Analysis'!P178,'Segment Analysis'!P198) -> 0.10403397 | Q45: =IF($C$25="Annual",'Segment Analysis'!Q178,'Segment Analysis'!Q198) -> 0.047992165 | R45: =IF($C$25="Annual",'Segment Analysis'!R178,'Segment Analysis'!R198) -> -0.0063321968 | ... T45: =IF($C$25="Annual",'Segment Analysis'!T178,'Segment Analysis'!T198) -> 0.04835639 | U45: =IFERROR(U44/S44-1,"--") -> 0.05976 | V45: =IFERROR(V44/U44-1,"--") -> 0.032884804 | W45: =IFERROR(W44/V44-1,"--") -> -0.044865294 | X45: =IFERROR(X44/W44-1,"--") -> -0.043519847 | Y45: =IFERROR(Y44/T44-1,"--") -> 0.016917676 | Z45: =IFERROR(Z44/X44-1,"--") -> 0.0915528 | AA45: =IFERROR(AA44/Z44-1,"--") -> 0.033887605 | AB45: =IFERROR(AB44/AA44-1,"--") -> -0.042086047 | AC45: =IFERROR(AC44/AB44-1,"--") -> -0.043519847 | AD45: =IFERROR(AD44/Y44-1,"--") -> 0.032208785 | AE45: =IFERROR(AE44/AD44-1,"--") -> 0.032 | AF45: =IFERROR(AF44/AE44-1,"--") -> 0.023 | AG45: =IFERROR(AG44/AF44-1,"--") -> 0.065
C46: % of Total Revenue | F46: ='Segment Analysis'!F21 -> 0.041467705 | G46: ='Segment Analysis'!G21 -> 0.041949596 | H46: ='Segment Analysis'!H21 -> 0.042369116 | I46: ='Segment Analysis'!I21 -> 0.045777221 | J46: ='Segment Analysis'!J21 -> 0.042921581 | K46: ='Segment Analysis'!K21 -> 0.048786804 | L46: ='Segment Analysis'!L21 -> 0.050444664 | M46: ='Segment Analysis'!M21 -> 0.050365537 | ... T46: ='Segment Analysis'!T21 -> 0.049783028 | U46: =U44/U$30 -> 0.051040413 | V46: =V44/V$30 -> 0.049988058 | W46: =W44/W$30 -> 0.047978677 | X46: =X44/X$30 -> 0.046398222 | Y46: =Y44/Y$30 -> 0.048833389 | Z46: =Z44/Z$30 -> 0.050086564 | AA46: =AA44/AA$30 -> 0.049138146 | AB46: =AB44/AB$30 -> 0.047269516 | ... AG46: =AG44/AG$30 -> 0.046779957
C47: ='Segment Analysis'!C14 -> Professional Services and Other Revenue | F47: ='Segment Analysis'!F14 -> 0 | G47: ='Segment Analysis'!G14 -> 0 | H47: ='Segment Analysis'!H14 -> 0 | I47: ='Segment Analysis'!I14 -> 0 | J47: ='Segment Analysis'!J14 -> 0 | K47: ='Segment Analysis'!K14 -> 0 | L47: ='Segment Analysis'!L14 -> 0 | M47: ='Segment Analysis'!M14 -> 0 | ... T47: ='Segment Analysis'!T14 -> 0 | U47: =IF(Segment6_Rev_Methodology="Segment",U83,IF(Segment6_Rev_Methodology="Activity-Based",U151,IF(Segment6_Rev_Methodology="Backlog",U225,"--"))) -> 0 | V47: =IF(Segment6_Rev_Methodology="Segment",V83,IF(Segment6_Rev_Methodology="Activity-Based",V151,IF(Segment6_Rev_Methodology="Backlog",V225,"--"))) -> 0 | W47: =IF(Segment6_Rev_Methodology="Segment",W83,IF(Segment6_Rev_Methodology="Activity-Based",W151,IF(Segment6_Rev_Methodology="Backlog",W225,"--"))) -> 0 | X47: =IF(Segment6_Rev_Methodology="Segment",X83,IF(Segment6_Rev_Methodology="Activity-Based",X151,IF(Segment6_Rev_Methodology="Backlog",X225,"--"))) -> 0 | Y47: =SUM(U47:X47) -> 0 | Z47: =IF(Segment6_Rev_Methodology="Segment",Z83,IF(Segment6_Rev_Methodology="Activity-Based",Z151,IF(Segment6_Rev_Methodology="Backlog",Z225,"--"))) -> 0 | AA47: =IF(Segment6_Rev_Methodology="Segment",AA83,IF(Segment6_Rev_Methodology="Activity-Based",AA151,IF(Segment6_Rev_Methodology="Backlog",AA225,"--"))) -> 0 | AB47: =IF(Segment6_Rev_Methodology="Segment",AB83,IF(Segment6_Rev_Methodology="Activity-Based",AB151,IF(Segment6_Rev_Methodology="Backlog",AB225,"--"))) -> 0 | AC47: =IF(Segment6_Rev_Methodology="Segment",AC83,IF(Segment6_Rev_Methodology="Activity-Based",AC151,IF(Segment6_Rev_Methodology="Backlog",AC225,"--"))) -> 0 | AD47: =SUM(Z47:AC47) -> 0 | AE47: =IF(Segment6_Rev_Methodology="Segment",AE83,IF(Segment6_Rev_Methodology="Activity-Based",AE151,IF(Segment6_Rev_Methodology="Backlog",AE225,"--"))) -> 0 | AF47: =IF(Segment6_Rev_Methodology="Segment",AF83,IF(Segment6_Rev_Methodology="Activity-Based",AF151,IF(Segment6_Rev_Methodology="Backlog",AF225,"--"))) -> 0 | AG47: =IF(Segment6_Rev_Methodology="Segment",AG83,IF(Segment6_Rev_Methodology="Activity-Based",AG151,IF(Segment6_Rev_Methodology="Backlog",AG225,"--"))) -> 0 | AI47: =IFERROR((T47/J47)^(1/3)-1,"--") -> -- | AJ47: =IFERROR((AG47/T47)^(1/5)-1,"--") -> --
C48: % Growth | G48: =IF($C$25="Annual",'Segment Analysis'!G199,'Segment Analysis'!G199) -> N/A | H48: =IF($C$25="Annual",'Segment Analysis'!H199,'Segment Analysis'!H199) -> N/A | I48: =IF($C$25="Annual",'Segment Analysis'!I199,'Segment Analysis'!I199) -> N/A | K48: =IF($C$25="Annual",'Segment Analysis'!K199,'Segment Analysis'!K199) -> N/A | L48: =IF($C$25="Annual",'Segment Analysis'!L199,'Segment Analysis'!L199) -> N/A | M48: =IF($C$25="Annual",'Segment Analysis'!M199,'Segment Analysis'!M199) -> N/A | N48: =IF($C$25="Annual",'Segment Analysis'!N199,'Segment Analysis'!N199) -> N/A | O48: =IF($C$25="Annual",'Segment Analysis'!O199,'Segment Analysis'!O199) -> 0 | P48: =IF($C$25="Annual",'Segment Analysis'!P199,'Segment Analysis'!P199) -> N/A | Q48: =IF($C$25="Annual",'Segment Analysis'!Q199,'Segment Analysis'!Q199) -> N/A | R48: =IF($C$25="Annual",'Segment Analysis'!R199,'Segment Analysis'!R199) -> N/A | ... T48: =IF($C$25="Annual",'Segment Analysis'!T199,'Segment Analysis'!T199) -> 0 | U48: =IFERROR(U47/S47-1,"--") -> -- | V48: =IFERROR(V47/U47-1,"--") -> -- | W48: =IFERROR(W47/V47-1,"--") -> -- | X48: =IFERROR(X47/W47-1,"--") -> -- | Y48: =IFERROR(Y47/T47-1,"--") -> -- | Z48: =IFERROR(Z47/X47-1,"--") -> -- | AA48: =IFERROR(AA47/Z47-1,"--") -> -- | AB48: =IFERROR(AB47/AA47-1,"--") -> -- | AC48: =IFERROR(AC47/AB47-1,"--") -> -- | AD48: =IFERROR(AD47/Y47-1,"--") -> -- | AE48: =IFERROR(AE47/AD47-1,"--") -> -- | AF48: =IFERROR(AF47/AE47-1,"--") -> -- | AG48: =IFERROR(AG47/AF47-1,"--") -> --
C49: % of Total Revenue | F49: ='Segment Analysis'!F22 -> 0 | G49: ='Segment Analysis'!G22 -> 0 | H49: ='Segment Analysis'!H22 -> 0 | I49: ='Segment Analysis'!I22 -> 0 | J49: ='Segment Analysis'!J22 -> 0 | K49: ='Segment Analysis'!K22 -> 0 | L49: ='Segment Analysis'!L22 -> 0 | M49: ='Segment Analysis'!M22 -> 0 | ... T49: ='Segment Analysis'!T22 -> 0 | U49: =U47/U$30 -> 0 | V49: =V47/V$30 -> 0 | W49: =W47/W$30 -> 0 | X49: =X47/X$30 -> 0 | Y49: =Y47/Y$30 -> 0 | Z49: =Z47/Z$30 -> 0 | AA49: =AA47/AA$30 -> 0 | AB49: =AB47/AB$30 -> 0 | ... AG49: =AG47/AG$30 -> 0
A51: x | C51: Growth Rate | F51: =F$28 -> 1Q23 | G51: =G$28 -> 2Q23 | H51: =H$28 -> 3Q23 | I51: =I$28 -> 4Q23 | J51: =J$28 -> 2023 | K51: =K$28 -> 1Q24 | L51: =L$28 -> 2Q24 | M51: =M$28 -> 3Q24 | ... AG51: =AG$28 -> 2030e | AH51: x
C53: =C32 -> Collection Revenue | F53: =F32 -> 2458.4 | G53: =G32 -> 2543 | H53: =H32 -> 2616.5 | I53: =I32 -> 2635 | J53: =J32 -> 10252.9 | K53: =K32 -> 2662.8 | L53: =L32 -> 2722.8 | M53: =M32 -> 2741.8 | ... T53: =T32 -> 11233 | U53: =IF($C$25="Quarterly",S53*(1+U54),P53*(1+U54)) -> 2841.748 | V53: =IF($C$25="Quarterly",U53*(1+V54),Q53*(1+V54)) -> 2932.058 | W53: =IF($C$25="Quarterly",V53*(1+W54),R53*(1+W54)) -> 2945.565 | X53: =IF($C$25="Quarterly",W53*(1+X54),S53*(1+X54)) -> 2954.819 | Y53: =SUM(U53:X53) -> 11674.19 | Z53: =IF($C$25="Quarterly",X53*(1+Z54),U53*(1+Z54)) -> 2983.8354 | AA53: =IF($C$25="Quarterly",Z53*(1+AA54),V53*(1+AA54)) -> 3075.7288 | AB53: =IF($C$25="Quarterly",AA53*(1+AB54),W53*(1+AB54)) -> 3095.7888 | AC53: =IF($C$25="Quarterly",AB53*(1+AC54),X53*(1+AC54)) -> 3105.5148 | AD53: =SUM(Z53:AC53) -> 12260.868 | AE53: =AD53*(1+AE54) -> 12849.389 | AF53: =AE53*(1+AF54) -> 13504.708 | AG53: =AF53*(1+AG54) -> 14098.916
C54: =IF($C$25="Quarterly","% Growth QoQ","% Growth YoY") -> % Growth YoY | G54: =G33 -> N/A | H54: =H33 -> N/A | I54: =I33 -> N/A | J54: =J33 -> 0 | K54: =K33 -> 0.083143508 | L54: =L33 -> 0.070703893 | M54: =M33 -> 0.047888401 | N54: =N33 -> 0.035294118 | ... T54: =T33 -> 0.034784531 | U54: =IF(Case_Scenario="Bull",U55,IF(Case_Scenario="Base",U56,IF(Case_Scenario="bear",U57,"N/A"))) -> 0.036 | V54: =IF(Case_Scenario="Bull",V55,IF(Case_Scenario="Base",V56,IF(Case_Scenario="bear",V57,"N/A"))) -> 0.039 | W54: =IF(Case_Scenario="Bull",W55,IF(Case_Scenario="Base",W56,IF(Case_Scenario="bear",W57,"N/A"))) -> 0.039 | X54: =IF(Case_Scenario="Bull",X55,IF(Case_Scenario="Base",X56,IF(Case_Scenario="bear",X57,"N/A"))) -> 0.043 | Z54: =IF(Case_Scenario="Bull",Z55,IF(Case_Scenario="Base",Z56,IF(Case_Scenario="bear",Z57,"N/A"))) -> 0.05 | AA54: =IF(Case_Scenario="Bull",AA55,IF(Case_Scenario="Base",AA56,IF(Case_Scenario="bear",AA57,"N/A"))) -> 0.049 | AB54: =IF(Case_Scenario="Bull",AB55,IF(Case_Scenario="Base",AB56,IF(Case_Scenario="bear",AB57,"N/A"))) -> 0.051 | AC54: =IF(Case_Scenario="Bull",AC55,IF(Case_Scenario="Base",AC56,IF(Case_Scenario="bear",AC57,"N/A"))) -> 0.051 | AE54: =IF(Case_Scenario="Bull",AE55,IF(Case_Scenario="Base",AE56,IF(Case_Scenario="bear",AE57,"N/A"))) -> 0.048 | AF54: =IF(Case_Scenario="Bull",AF55,IF(Case_Scenario="Base",AF56,IF(Case_Scenario="bear",AF57,"N/A"))) -> 0.051 | AG54: =IF(Case_Scenario="Bull",AG55,IF(Case_Scenario="Base",AG56,IF(Case_Scenario="bear",AG57,"N/A"))) -> 0.044
C55: Bull Case | U55: =U56+0.02 -> 0.056 | V55: =V56+0.02 -> 0.059 | W55: =W56+0.02 -> 0.059 | X55: =X56+0.02 -> 0.063 | Z55: =Z56+0.02 -> 0.07 | AA55: =AA56+0.02 -> 0.069 | AB55: =AB56+0.02 -> 0.071 | AC55: =AC56+0.02 -> 0.071 | AE55: =AE56+0.02 -> 0.068 | AF55: =AF56+0.02 -> 0.071 | AG55: =AG56+0.02 -> 0.064
C56: Base Case | U56: 0.036 | V56: 0.039 | W56: 0.039 | X56: 0.043 | Z56: 0.05 | AA56: 0.049 | AB56: 0.051 | AC56: 0.051 | AE56: 0.048 | AF56: 0.051 | AG56: 0.044
C57: Bear Case | U57: =U56-1.3% -> 0.023 | V57: =V56-1.3% -> 0.026 | W57: =W56-1.3% -> 0.026 | X57: =X56-1.3% -> 0.03 | Z57: =Z56-1.3% -> 0.037 | AA57: =AA56-1.3% -> 0.036 | AB57: =AB56-1.3% -> 0.038 | AC57: =AC56-1.3% -> 0.038 | AE57: =AE56-1.3% -> 0.035 | AF57: =AF56-1.3% -> 0.038 | AG57: =AG56-1.3% -> 0.031
A59: x | C59: =C35 -> Landfill Revenue | F59: =F35 -> 392.6 | G59: =G35 -> 431 | H59: =H35 -> 436.3 | I59: =I35 -> 419.6 | J59: =J35 -> 1679.5 | K59: =K35 -> 404.4 | L59: =L35 -> 440.2 | M59: =M35 -> 452.8 | ... T59: =T35 -> 1920 | U59: =IF($C$25="Quarterly",S59*(1+U60),P59*(1+U60)) -> 439.103 | V59: =IF($C$25="Quarterly",U59*(1+V60),Q59*(1+V60)) -> 519.612 | W59: =IF($C$25="Quarterly",V59*(1+W60),R59*(1+W60)) -> 520.644 | X59: =IF($C$25="Quarterly",W59*(1+X60),S59*(1+X60)) -> 488.949 | Y59: =SUM(U59:X59) -> 1968.308 | Z59: =IF($C$25="Quarterly",X59*(1+Z60),U59*(1+Z60)) -> 459.74084 | AA59: =IF($C$25="Quarterly",Z59*(1+AA60),V59*(1+AA60)) -> 546.63182 | AB59: =IF($C$25="Quarterly",AA59*(1+AB60),W59*(1+AB60)) -> 545.63491 | AC59: =IF($C$25="Quarterly",AB59*(1+AC60),X59*(1+AC60)) -> 510.9517 | AD59: =SUM(Z59:AC59) -> 2062.9593 | AE59: =AD59*(1+AE60) -> 2180.548 | AF59: =AE59*(1+AF60) -> 2302.6586 | AG59: =AF59*(1+AG60) -> 2427.0022
C60: =IF($C$25="Quarterly","% Growth QoQ","% Growth YoY") -> % Growth YoY | G60: =G36 -> N/A | H60: =H36 -> N/A | I60: =I36 -> N/A | J60: =J36 -> 0 | K60: =K36 -> 0.030056037 | L60: =L36 -> 0.021345708 | M60: =M36 -> 0.037818015 | N60: =N36 -> 0.055767398 | ... T60: =T36 -> 0.10319467 | U60: =IF(Case_Scenario="Bull",U61,IF(Case_Scenario="Base",U62,IF(Case_Scenario="bear",U63,"N/A"))) -> 0.043 | V60: =IF(Case_Scenario="Bull",V61,IF(Case_Scenario="Base",V62,IF(Case_Scenario="bear",V63,"N/A"))) -> 0.007 | W60: =IF(Case_Scenario="Bull",W61,IF(Case_Scenario="Base",W62,IF(Case_Scenario="bear",W63,"N/A"))) -> 0.009 | X60: =IF(Case_Scenario="Bull",X61,IF(Case_Scenario="Base",X62,IF(Case_Scenario="bear",X63,"N/A"))) -> 0.047 | Z60: =IF(Case_Scenario="Bull",Z61,IF(Case_Scenario="Base",Z62,IF(Case_Scenario="bear",Z63,"N/A"))) -> 0.047 | AA60: =IF(Case_Scenario="Bull",AA61,IF(Case_Scenario="Base",AA62,IF(Case_Scenario="bear",AA63,"N/A"))) -> 0.052 | AB60: =IF(Case_Scenario="Bull",AB61,IF(Case_Scenario="Base",AB62,IF(Case_Scenario="bear",AB63,"N/A"))) -> 0.048 | AC60: =IF(Case_Scenario="Bull",AC61,IF(Case_Scenario="Base",AC62,IF(Case_Scenario="bear",AC63,"N/A"))) -> 0.045 | AE60: =IF(Case_Scenario="Bull",AE61,IF(Case_Scenario="Base",AE62,IF(Case_Scenario="bear",AE63,"N/A"))) -> 0.057 | AF60: =IF(Case_Scenario="Bull",AF61,IF(Case_Scenario="Base",AF62,IF(Case_Scenario="bear",AF63,"N/A"))) -> 0.056 | AG60: =IF(Case_Scenario="Bull",AG61,IF(Case_Scenario="Base",AG62,IF(Case_Scenario="bear",AG63,"N/A"))) -> 0.054
C61: Bull Case | U61: =U62+0.02 -> 0.063 | V61: =V62+0.02 -> 0.027 | W61: =W62+0.02 -> 0.029 | X61: =X62+0.02 -> 0.067 | Z61: =Z62+0.02 -> 0.067 | AA61: =AA62+0.02 -> 0.072 | AB61: =AB62+0.02 -> 0.068 | AC61: =AC62+0.02 -> 0.065 | AE61: =AE62+0.02 -> 0.077 | AF61: =AF62+0.02 -> 0.076 | AG61: =AG62+0.02 -> 0.074
C62: Base Case | U62: 0.043 | V62: 0.007 | W62: 0.009 | X62: 0.047 | Z62: 0.047 | AA62: 0.052 | AB62: 0.048 | AC62: 0.045 | AE62: 0.057 | AF62: 0.056 | AG62: 0.054
C63: Bear Case | U63: =U62-1.3% -> 0.03 | V63: =V62-1.3% -> -0.006 | W63: =W62-1.3% -> -0.004 | X63: =X62-1.3% -> 0.034 | Z63: =Z62-1.3% -> 0.034 | AA63: =AA62-1.3% -> 0.039 | AB63: =AB62-1.3% -> 0.035 | AC63: =AC62-1.3% -> 0.032 | AE63: =AE62-1.3% -> 0.044 | AF63: =AF62-1.3% -> 0.043 | AG63: =AG62-1.3% -> 0.041
A65: x | C65: =C38 -> Environmental solutions Revenue | F65: =F38 -> 408.3 | G65: =G38 -> 398.3 | H65: =H38 -> 404.8 | I65: =I38 -> 413.4 | J65: =J38 -> 1624.8 | K65: =K38 -> 423.3 | L65: =L38 -> 472.6 | M65: =M38 -> 464.7 | ... T65: =T38 -> 1766 | U65: =IF($C$25="Quarterly",S65*(1+U66),P65*(1+U66)) -> 463.368 | V65: =IF($C$25="Quarterly",U65*(1+V66),Q65*(1+V66)) -> 478.17 | W65: =IF($C$25="Quarterly",V65*(1+W66),R65*(1+W66)) -> 449.021 | X65: =IF($C$25="Quarterly",W65*(1+X66),S65*(1+X66)) -> 442.256 | Y65: =SUM(U65:X65) -> 1832.815 | Z65: =IF($C$25="Quarterly",X65*(1+Z66),U65*(1+Z66)) -> 489.31661 | AA65: =IF($C$25="Quarterly",Z65*(1+AA66),V65*(1+AA66)) -> 502.55667 | AB65: =IF($C$25="Quarterly",AA65*(1+AB66),W65*(1+AB66)) -> 471.02303 | AC65: =IF($C$25="Quarterly",AB65*(1+AC66),X65*(1+AC66)) -> 463.92654 | AD65: =SUM(Z65:AC65) -> 1926.8229 | AE65: =AD65*(1+AE66) -> 2025.0908 | AF65: =AE65*(1+AF66) -> 2138.4959 | AG65: =AF65*(1+AG66) -> 2288.1906
C66: =IF($C$25="Quarterly","% Growth QoQ","% Growth YoY") -> % Growth YoY | G66: =G39 -> N/A | H66: =H39 -> N/A | I66: =I39 -> N/A | J66: =J39 -> 0 | K66: =K39 -> 0.036737693 | L66: =L39 -> 0.18654281 | M66: =M39 -> 0.14797431 | N66: =N39 -> 0.16594098 | ... T66: =T39 -> -0.041571692 | U66: =IF(Case_Scenario="Bull",U67,IF(Case_Scenario="Base",U68,IF(Case_Scenario="bear",U69,"N/A"))) -> 0.032 | V66: =IF(Case_Scenario="Bull",V67,IF(Case_Scenario="Base",V68,IF(Case_Scenario="bear",V69,"N/A"))) -> 0.035 | W66: =IF(Case_Scenario="Bull",W67,IF(Case_Scenario="Base",W68,IF(Case_Scenario="bear",W69,"N/A"))) -> 0.037 | X66: =IF(Case_Scenario="Bull",X67,IF(Case_Scenario="Base",X68,IF(Case_Scenario="bear",X69,"N/A"))) -> 0.048 | Z66: =IF(Case_Scenario="Bull",Z67,IF(Case_Scenario="Base",Z68,IF(Case_Scenario="bear",Z69,"N/A"))) -> 0.056 | AA66: =IF(Case_Scenario="Bull",AA67,IF(Case_Scenario="Base",AA68,IF(Case_Scenario="bear",AA69,"N/A"))) -> 0.051 | AB66: =IF(Case_Scenario="Bull",AB67,IF(Case_Scenario="Base",AB68,IF(Case_Scenario="bear",AB69,"N/A"))) -> 0.049 | AC66: =IF(Case_Scenario="Bull",AC67,IF(Case_Scenario="Base",AC68,IF(Case_Scenario="bear",AC69,"N/A"))) -> 0.049 | AE66: =IF(Case_Scenario="Bull",AE67,IF(Case_Scenario="Base",AE68,IF(Case_Scenario="bear",AE69,"N/A"))) -> 0.051 | AF66: =IF(Case_Scenario="Bull",AF67,IF(Case_Scenario="Base",AF68,IF(Case_Scenario="bear",AF69,"N/A"))) -> 0.056 | AG66: =IF(Case_Scenario="Bull",AG67,IF(Case_Scenario="Base",AG68,IF(Case_Scenario="bear",AG69,"N/A"))) -> 0.07
C67: Bull Case | U67: =U68+0.012 -> 0.044 | V67: =V68+0.012 -> 0.047 | W67: =W68+0.012 -> 0.049 | X67: =X68+0.012 -> 0.06 | Z67: =Z68+0.012 -> 0.068 | AA67: =AA68+0.012 -> 0.063 | AB67: =AB68+0.012 -> 0.061 | AC67: =AC68+0.012 -> 0.061 | AE67: =AE68+0.012 -> 0.063 | AF67: =AF68+0.012 -> 0.068 | AG67: =AG68+0.012 -> 0.082 | AH67: 0.145
C68: Base Case | U68: 0.032 | V68: 0.035 | W68: 0.037 | X68: 0.048 | Z68: 0.056 | AA68: 0.051 | AB68: 0.049 | AC68: 0.049 | AE68: 0.051 | AF68: 0.056 | AG68: 0.07
C69: Bear Case | U69: =U68-1.3% -> 0.019 | V69: =V68-1.3% -> 0.022 | W69: =W68-1.3% -> 0.024 | X69: =X68-1.3% -> 0.035 | Z69: =Z68-1.3% -> 0.043 | AA69: =AA68-1.3% -> 0.038 | AB69: =AB68-1.3% -> 0.036 | AC69: =AC68-1.3% -> 0.036 | AE69: =AE68-1.3% -> 0.038 | AF69: =AF68-1.3% -> 0.043 | AG69: =AG68-1.3% -> 0.057
A71: x | C71: =C41 -> Transfer Revenue | F71: =F41 -> 173.3 | G71: =G41 -> 197.3 | H71: =H41 -> 206.2 | I71: =I41 -> 188.2 | J71: =J41 -> 765 | K71: =K41 -> 182.8 | L71: =L41 -> 208.2 | M71: =M41 -> 211.6 | ... T71: =T41 -> 847 | U71: =IF($C$25="Quarterly",S71*(1+U72),P71*(1+U72)) -> 196.46 | V71: =IF($C$25="Quarterly",U71*(1+V72),Q71*(1+V72)) -> 230.724 | W71: =IF($C$25="Quarterly",V71*(1+W72),R71*(1+W72)) -> 233.856 | X71: =IF($C$25="Quarterly",W71*(1+X72),S71*(1+X72)) -> 224.486 | Y71: =SUM(U71:X71) -> 885.526 | Z71: =IF($C$25="Quarterly",X71*(1+Z72),U71*(1+Z72)) -> 207.46176 | AA71: =IF($C$25="Quarterly",Z71*(1+AA72),V71*(1+AA72)) -> 242.72165 | AB71: =IF($C$25="Quarterly",AA71*(1+AB72),W71*(1+AB72)) -> 245.31494 | AC71: =IF($C$25="Quarterly",AB71*(1+AC72),X71*(1+AC72)) -> 235.48581 | AD71: =SUM(Z71:AC71) -> 930.98417 | AE71: =AD71*(1+AE72) -> 971.94747 | AF71: =AE71*(1+AF72) -> 1021.5168 | AG71: =AF71*(1+AG72) -> 1050.1193
C72: =IF($C$25="Quarterly","% Growth QoQ","% Growth YoY") -> % Growth YoY | G72: =G42 -> N/A | H72: =H42 -> N/A | I72: =I42 -> N/A | J72: =J42 -> 0 | K72: =K42 -> 0.054818234 | L72: =L42 -> 0.055245819 | M72: =M42 -> 0.026188167 | N72: =N42 -> 0.078639745 | ... T72: =T42 -> 0.051390268 | U72: =IF(Case_Scenario="Bull",U73,IF(Case_Scenario="Base",U74,IF(Case_Scenario="bear",U75,"N/A"))) -> 0.045 | V72: =IF(Case_Scenario="Bull",V73,IF(Case_Scenario="Base",V74,IF(Case_Scenario="bear",V75,"N/A"))) -> 0.044 | W72: =IF(Case_Scenario="Bull",W73,IF(Case_Scenario="Base",W74,IF(Case_Scenario="bear",W75,"N/A"))) -> 0.044 | X72: =IF(Case_Scenario="Bull",X73,IF(Case_Scenario="Base",X74,IF(Case_Scenario="bear",X75,"N/A"))) -> 0.049 | Z72: =IF(Case_Scenario="Bull",Z73,IF(Case_Scenario="Base",Z74,IF(Case_Scenario="bear",Z75,"N/A"))) -> 0.056 | AA72: =IF(Case_Scenario="Bull",AA73,IF(Case_Scenario="Base",AA74,IF(Case_Scenario="bear",AA75,"N/A"))) -> 0.052 | AB72: =IF(Case_Scenario="Bull",AB73,IF(Case_Scenario="Base",AB74,IF(Case_Scenario="bear",AB75,"N/A"))) -> 0.049 | AC72: =IF(Case_Scenario="Bull",AC73,IF(Case_Scenario="Base",AC74,IF(Case_Scenario="bear",AC75,"N/A"))) -> 0.049 | AE72: =IF(Case_Scenario="Bull",AE73,IF(Case_Scenario="Base",AE74,IF(Case_Scenario="bear",AE75,"N/A"))) -> 0.044 | AF72: =IF(Case_Scenario="Bull",AF73,IF(Case_Scenario="Base",AF74,IF(Case_Scenario="bear",AF75,"N/A"))) -> 0.051 | AG72: =IF(Case_Scenario="Bull",AG73,IF(Case_Scenario="Base",AG74,IF(Case_Scenario="bear",AG75,"N/A"))) -> 0.028
C73: Bull Case | U73: =U74+0.005 -> 0.05 | V73: =V74+0.005 -> 0.049 | W73: =W74+0.005 -> 0.049 | X73: =X74+0.005 -> 0.054 | Z73: =Z74+0.005 -> 0.061 | AA73: =AA74+0.005 -> 0.057 | AB73: =AB74+0.005 -> 0.054 | AC73: =AC74+0.005 -> 0.054 | AE73: =AE74+0.005 -> 0.049 | AF73: =AF74+0.005 -> 0.056 | AG73: =AG74+0.005 -> 0.033
C74: Base Case | U74: 0.045 | V74: 0.044 | W74: 0.044 | X74: 0.049 | Z74: 0.056 | AA74: 0.052 | AB74: 0.049 | AC74: 0.049 | AE74: 0.044 | AF74: 0.051 | AG74: 0.028
C75: Bear Case | U75: =U74-1.3% -> 0.032 | V75: =V74-1.3% -> 0.031 | W75: =W74-1.3% -> 0.031 | X75: =X74-1.3% -> 0.036 | Z75: =Z74-1.3% -> 0.043 | AA75: =AA74-1.3% -> 0.039 | AB75: =AB74-1.3% -> 0.036 | AC75: =AC74-1.3% -> 0.036 | AE75: =AE74-1.3% -> 0.031 | AF75: =AF74-1.3% -> 0.038 | AG75: =AG74-1.3% -> 0.015
A77: x | C77: =C44 -> Other Revenue | F77: =F44 -> 148.5 | G77: =G44 -> 156.3 | H77: =H44 -> 162.1 | I77: =I44 -> 175.4 | J77: =J44 -> 642.3 | K77: =K44 -> 188.4 | L77: =L44 -> 204.2 | M77: =M44 -> 205.3 | ... T77: =T44 -> 826 | U77: =IF($C$25="Quarterly",S77*(1+U78),P77*(1+U78)) -> 211.952 | V77: =IF($C$25="Quarterly",U77*(1+V78),Q77*(1+V78)) -> 218.922 | W77: =IF($C$25="Quarterly",V77*(1+W78),R77*(1+W78)) -> 209.1 | X77: =IF($C$25="Quarterly",W77*(1+X78),S77*(1+X78)) -> 200 | Y77: =SUM(U77:X77) -> 839.974 | Z77: =IF($C$25="Quarterly",X77*(1+Z78),U77*(1+Z78)) -> 218.31056 | AA77: =IF($C$25="Quarterly",Z77*(1+AA78),V77*(1+AA78)) -> 225.70858 | AB77: =IF($C$25="Quarterly",AA77*(1+AB78),W77*(1+AB78)) -> 216.2094 | AC77: =IF($C$25="Quarterly",AB77*(1+AC78),X77*(1+AC78)) -> 206.8 | AD77: =SUM(Z77:AC77) -> 867.02854 | AE77: =AD77*(1+AE78) -> 894.77346 | AF77: =AE77*(1+AF78) -> 915.35324 | AG77: =AF77*(1+AG78) -> 974.85121
C78: =IF($C$25="Quarterly","% Growth QoQ","% Growth YoY") -> % Growth YoY | G78: =G45 -> N/A | H78: =H45 -> N/A | I78: =I45 -> N/A | J78: =J45 -> 0 | K78: =K45 -> 0.26868687 | L78: =L45 -> 0.30646193 | M78: =M45 -> 0.26650216 | N78: =N45 -> 0.083238312 | ... T78: =T45 -> 0.04835639 | U78: =IF(Case_Scenario="Bull",U79,IF(Case_Scenario="Base",U80,IF(Case_Scenario="bear",U81,"N/A"))) -> 0.019 | V78: =IF(Case_Scenario="Bull",V79,IF(Case_Scenario="Base",V80,IF(Case_Scenario="bear",V81,"N/A"))) -> 0.023 | W78: =IF(Case_Scenario="Bull",W79,IF(Case_Scenario="Base",W80,IF(Case_Scenario="bear",W81,"N/A"))) -> 0.025 | X78: =IF(Case_Scenario="Bull",X79,IF(Case_Scenario="Base",X80,IF(Case_Scenario="bear",X81,"N/A"))) -> 0 | Z78: =IF(Case_Scenario="Bull",Z79,IF(Case_Scenario="Base",Z80,IF(Case_Scenario="bear",Z81,"N/A"))) -> 0.03 | AA78: =IF(Case_Scenario="Bull",AA79,IF(Case_Scenario="Base",AA80,IF(Case_Scenario="bear",AA81,"N/A"))) -> 0.031 | AB78: =IF(Case_Scenario="Bull",AB79,IF(Case_Scenario="Base",AB80,IF(Case_Scenario="bear",AB81,"N/A"))) -> 0.034 | AC78: =IF(Case_Scenario="Bull",AC79,IF(Case_Scenario="Base",AC80,IF(Case_Scenario="bear",AC81,"N/A"))) -> 0.034 | AE78: =IF(Case_Scenario="Bull",AE79,IF(Case_Scenario="Base",AE80,IF(Case_Scenario="bear",AE81,"N/A"))) -> 0.032 | AF78: =IF(Case_Scenario="Bull",AF79,IF(Case_Scenario="Base",AF80,IF(Case_Scenario="bear",AF81,"N/A"))) -> 0.023 | AG78: =IF(Case_Scenario="Bull",AG79,IF(Case_Scenario="Base",AG80,IF(Case_Scenario="bear",AG81,"N/A"))) -> 0.065
C79: Bull Case | U79: =U80+0.012 -> 0.031 | V79: =V80+0.012 -> 0.035 | W79: =W80+0.012 -> 0.037 | X79: =X80+0.012 -> 0.012 | Z79: =Z80+0.012 -> 0.042 | AA79: =AA80+0.012 -> 0.043 | AB79: =AB80+0.012 -> 0.046 | AC79: =AC80+0.012 -> 0.046 | AE79: =AE80+0.012 -> 0.044 | AF79: =AF80+0.012 -> 0.035 | AG79: =AG80+0.012 -> 0.077
C80: Base Case | U80: 0.019 | V80: 0.023 | W80: 0.025 | X80: 0 | Z80: 0.03 | AA80: 0.031 | AB80: 0.034 | AC80: 0.034 | AE80: 0.032 | AF80: 0.023 | AG80: 0.065
C81: Bear Case | U81: =U80-1.3% -> 0.006 | V81: =V80-1.3% -> 0.01 | W81: =W80-1.3% -> 0.012 | X81: =X80-1.3% -> -0.013 | Z81: =Z80-1.3% -> 0.017 | AA81: =AA80-1.3% -> 0.018 | AB81: =AB80-1.3% -> 0.021 | AC81: =AC80-1.3% -> 0.021 | AE81: =AE80-1.3% -> 0.019 | AF81: =AF80-1.3% -> 0.01 | AG81: =AG80-1.3% -> 0.052
A83: x | C83: =C47 -> Professional Services and Other Revenue | F83: =F47 -> 0 | G83: =G47 -> 0 | H83: =H47 -> 0 | I83: =I47 -> 0 | J83: =J47 -> 0 | K83: =K47 -> 0 | L83: =L47 -> 0 | M83: =M47 -> 0 | ... T83: =T47 -> 0 | U83: =IF($C$25="Quarterly",S83*(1+U84),P83*(1+U84)) -> 0 | V83: =IF($C$25="Quarterly",U83*(1+V84),Q83*(1+V84)) -> 0 | W83: =IF($C$25="Quarterly",V83*(1+W84),R83*(1+W84)) -> 0 | X83: =IF($C$25="Quarterly",W83*(1+X84),S83*(1+X84)) -> 0 | Y83: =SUM(U83:X83) -> 0 | Z83: =IF($C$25="Quarterly",X83*(1+Z84),U83*(1+Z84)) -> 0 | AA83: =IF($C$25="Quarterly",Z83*(1+AA84),V83*(1+AA84)) -> 0 | AB83: =IF($C$25="Quarterly",AA83*(1+AB84),W83*(1+AB84)) -> 0 | AC83: =IF($C$25="Quarterly",AB83*(1+AC84),X83*(1+AC84)) -> 0 | AD83: =SUM(Z83:AC83) -> 0 | AE83: =AD83*(1+AE84) -> 0 | AF83: =AE83*(1+AF84) -> 0 | AG83: =AF83*(1+AG84) -> 0
C84: =IF($C$25="Quarterly","% Growth QoQ","% Growth YoY") -> % Growth YoY | G84: =G48 -> N/A | H84: =H48 -> N/A | I84: =I48 -> N/A | J84: =J48 -> 0 | K84: =K48 -> N/A | L84: =L48 -> N/A | M84: =M48 -> N/A | N84: =N48 -> N/A | ... T84: =T48 -> 0 | U84: =IF(Case_Scenario="Bull",U85,IF(Case_Scenario="Base",U86,IF(Case_Scenario="bear",U87,"N/A"))) -> 0 | V84: =IF(Case_Scenario="Bull",V85,IF(Case_Scenario="Base",V86,IF(Case_Scenario="bear",V87,"N/A"))) -> 0 | W84: =IF(Case_Scenario="Bull",W85,IF(Case_Scenario="Base",W86,IF(Case_Scenario="bear",W87,"N/A"))) -> 0 | X84: =IF(Case_Scenario="Bull",X85,IF(Case_Scenario="Base",X86,IF(Case_Scenario="bear",X87,"N/A"))) -> 0 | Z84: =IF(Case_Scenario="Bull",Z85,IF(Case_Scenario="Base",Z86,IF(Case_Scenario="bear",Z87,"N/A"))) -> 0 | AA84: =IF(Case_Scenario="Bull",AA85,IF(Case_Scenario="Base",AA86,IF(Case_Scenario="bear",AA87,"N/A"))) -> 0 | AB84: =IF(Case_Scenario="Bull",AB85,IF(Case_Scenario="Base",AB86,IF(Case_Scenario="bear",AB87,"N/A"))) -> 0 | AC84: =IF(Case_Scenario="Bull",AC85,IF(Case_Scenario="Base",AC86,IF(Case_Scenario="bear",AC87,"N/A"))) -> 0 | AE84: =IF(Case_Scenario="Bull",AE85,IF(Case_Scenario="Base",AE86,IF(Case_Scenario="bear",AE87,"N/A"))) -> 0 | AF84: =IF(Case_Scenario="Bull",AF85,IF(Case_Scenario="Base",AF86,IF(Case_Scenario="bear",AF87,"N/A"))) -> 0 | AG84: =IF(Case_Scenario="Bull",AG85,IF(Case_Scenario="Base",AG86,IF(Case_Scenario="bear",AG87,"N/A"))) -> 0
C85: Bull Case | U85: =S85 -> 0 | V85: =U85 -> 0 | W85: =V85 -> 0 | X85: =W85 -> 0 | Z85: =X85 -> 0 | AA85: =Z85 -> 0 | AB85: =AA85 -> 0 | AC85: =AB85 -> 0 | AE85: =AC85 -> 0 | AF85: =AE85 -> 0 | AG85: =AF85 -> 0
C86: Base Case | U86: =S86 -> 0 | V86: =U86 -> 0 | W86: =V86 -> 0 | X86: =W86 -> 0 | Z86: =X86 -> 0 | AA86: =Z86 -> 0 | AB86: =AA86 -> 0 | AC86: =AB86 -> 0 | AE86: =AC86 -> 0 | AF86: =AE86 -> 0 | AG86: =AF86 -> 0
C87: Bear Case | U87: =S87 -> 0 | V87: =U87 -> 0 | W87: =V87 -> 0 | X87: =W87 -> 0 | Z87: =X87 -> 0 | AA87: =Z87 -> 0 | AB87: =AA87 -> 0 | AC87: =AB87 -> 0 | AE87: =AC87 -> 0 | AF87: =AE87 -> 0 | AG87: =AF87 -> 0
A89: x | C89: Activity-Based Growth | F89: =F$28 -> 1Q23 | G89: =G$28 -> 2Q23 | H89: =H$28 -> 3Q23 | I89: =I$28 -> 4Q23 | J89: =J$28 -> 2023 | K89: =K$28 -> 1Q24 | L89: =L$28 -> 2Q24 | M89: =M$28 -> 3Q24 | ... AG89: =AG$28 -> 2030e | AH89: x
C91: =C32 -> Collection Revenue | F91: =F32 -> 2458.4 | G91: =G32 -> 2543 | H91: =H32 -> 2616.5 | I91: =I32 -> 2635 | J91: =J32 -> 10252.9 | K91: =K32 -> 2662.8 | L91: =L32 -> 2722.8 | M91: =M32 -> 2741.8 | ... T91: =T32 -> 11233 | U91: =U92*U97 -> 2974.65 | V91: =V92*V97 -> 3279.5516 | W91: =W92*W97 -> 3615.7057 | X91: =X92*X97 -> 3615.7057 | Y91: =SUM(U91:X91) -> 13485.613 | Z91: =Z92*Z97 -> 3796.4909 | AA91: =AA92*AA97 -> 4185.6313 | AB91: =AB92*AB97 -> 4614.6585 | AC91: =AC92*AC97 -> 5087.661 | AD91: =SUM(Z91:AC91) -> 17684.442 | AE91: =AE92*AE97 -> 19497.097 | AF91: =AF92*AF97 -> 21495.549 | AG91: =AG92*AG97 -> 23698.843
C92: Volume | F92: 220 | G92: 220 | H92: 220 | I92: 220 | J92: =SUM(F92:I92) -> 880 | K92: 220 | L92: 220 | M92: 220 | N92: 220 | O92: =SUM(K92:N92) -> 880 | P92: 220 | Q92: 220 | R92: 220 | S92: 220 | T92: =SUM(P92:S92) -> 880 | U92: =S92*(1+U93) -> 220 | V92: =U92*(1+V93) -> 231 | W92: =V92*(1+W93) -> 242.55 | X92: =W92*(1+X93) -> 242.55 | Y92: =SUM(U92:X92) -> 936.1 | Z92: =X92*(1+Z93) -> 242.55 | AA92: =Z92*(1+AA93) -> 254.6775 | AB92: =AA92*(1+AB93) -> 267.41138 | AC92: =AB92*(1+AC93) -> 280.78194 | AD92: =SUM(Z92:AC92) -> 1045.4208 | AE92: =AD92*(1+AE93) -> 1097.6919 | AF92: =AE92*(1+AF93) -> 1152.5765 | AG92: =AF92*(1+AG93) -> 1210.2053
C93: % Volume Growth | G93: =IFERROR(G92/F92-1,"--") -> 0 | H93: =IFERROR(H92/G92-1,"--") -> 0 | I93: =IFERROR(I92/H92-1,"--") -> 0 | K93: =IFERROR(K92/I92-1,"--") -> 0 | L93: =IFERROR(L92/K92-1,"--") -> 0 | M93: =IFERROR(M92/L92-1,"--") -> 0 | N93: =IFERROR(N92/M92-1,"--") -> 0 | O93: =IFERROR(O92/J92-1,"--") -> 0 | P93: =IFERROR(P92/N92-1,"--") -> 0 | Q93: =IFERROR(Q92/P92-1,"--") -> 0 | R93: =IFERROR(R92/Q92-1,"--") -> 0 | S93: =IFERROR(S92/R92-1,"--") -> 0 | T93: =IFERROR(T92/O92-1,"--") -> 0 | U93: =IF(Case_Scenario="Bull",U94,IF(Case_Scenario="Base",U95,IF(Case_Scenario="bear",U96,"N/A"))) -> 0 | V93: =IF(Case_Scenario="Bull",V94,IF(Case_Scenario="Base",V95,IF(Case_Scenario="bear",V96,"N/A"))) -> 0.05 | W93: =IF(Case_Scenario="Bull",W94,IF(Case_Scenario="Base",W95,IF(Case_Scenario="bear",W96,"N/A"))) -> 0.05 | X93: =IF(Case_Scenario="Bull",X94,IF(Case_Scenario="Base",X95,IF(Case_Scenario="bear",X96,"N/A"))) -> 0 | Z93: =IF(Case_Scenario="Bull",Z94,IF(Case_Scenario="Base",Z95,IF(Case_Scenario="bear",Z96,"N/A"))) -> 0 | AA93: =IF(Case_Scenario="Bull",AA94,IF(Case_Scenario="Base",AA95,IF(Case_Scenario="bear",AA96,"N/A"))) -> 0.05 | AB93: =IF(Case_Scenario="Bull",AB94,IF(Case_Scenario="Base",AB95,IF(Case_Scenario="bear",AB96,"N/A"))) -> 0.05 | AC93: =IF(Case_Scenario="Bull",AC94,IF(Case_Scenario="Base",AC95,IF(Case_Scenario="bear",AC96,"N/A"))) -> 0.05 | AE93: =IF(Case_Scenario="Bull",AE94,IF(Case_Scenario="Base",AE95,IF(Case_Scenario="bear",AE96,"N/A"))) -> 0.05 | AF93: =IF(Case_Scenario="Bull",AF94,IF(Case_Scenario="Base",AF95,IF(Case_Scenario="bear",AF96,"N/A"))) -> 0.05 | AG93: =IF(Case_Scenario="Bull",AG94,IF(Case_Scenario="Base",AG95,IF(Case_Scenario="bear",AG96,"N/A"))) -> 0.05
C94: Bull Case | U94: 0.1 | V94: 0.1 | W94: 0.1 | X94: 0 | Z94: 0.1 | AA94: 0.1 | AB94: 0.1 | AC94: 0.1 | AE94: 0.1 | AF94: 0.1 | AG94: 0.1
C95: Base Case | U95: 0 | V95: 0.05 | W95: 0.05 | X95: 0 | Z95: 0 | AA95: 0.05 | AB95: 0.05 | AC95: 0.05 | AE95: 0.05 | AF95: 0.05 | AG95: 0.05
C96: Bear Case | U96: 0 | V96: 0 | W96: 0 | X96: 0 | Z96: 0 | AA96: 0 | AB96: 0 | AC96: 0 | AE96: 0 | AF96: 0 | AG96: 0
C97: Price | F97: =IFERROR(F91/F92,"--") -> 11.174545 | G97: =IFERROR(G91/G92,"--") -> 11.559091 | H97: =IFERROR(H91/H92,"--") -> 11.893182 | I97: =IFERROR(I91/I92,"--") -> 11.977273 | J97: =IFERROR(J91/J92,"--") -> 11.651023 | K97: =IFERROR(K91/K92,"--") -> 12.103636 | L97: =IFERROR(L91/L92,"--") -> 12.376364 | M97: =IFERROR(M91/M92,"--") -> 12.462727 | ... T97: =IFERROR(T91/T92,"--") -> 12.764773 | U97: =S97*(1+U98) -> 13.521136 | V97: =U97*(1+V98) -> 14.197193 | W97: =V97*(1+W98) -> 14.907053 | X97: =W97*(1+X98) -> 14.907053 | Y97: =Y91/Y92 -> 14.406167 | Z97: =X97*(1+Z98) -> 15.652405 | AA97: =Z97*(1+AA98) -> 16.435026 | AB97: =AA97*(1+AB98) -> 17.256777 | AC97: =AB97*(1+AC98) -> 18.119616 | AD97: =AD91/AD92 -> 16.916099 | AE97: =AD97*(1+AE98) -> 17.761904 | AF97: =AE97*(1+AF98) -> 18.649999 | AG97: =AF97*(1+AG98) -> 19.582499
C98: % Price Growth | G98: =IFERROR(G97/F97-1,"--") -> 0.034412626 | H98: =IFERROR(H97/G97-1,"--") -> 0.028902871 | I98: =IFERROR(I97/H97-1,"--") -> 0.007070514 | K98: =IFERROR(K97/I97-1,"--") -> 0.010550285 | L98: =IFERROR(L97/K97-1,"--") -> 0.022532672 | M98: =IFERROR(M97/L97-1,"--") -> 0.0069781108 | N98: =IFERROR(N97/M97-1,"--") -> -0.0050331899 | O98: =IFERROR(O97/J97-1,"--") -> 0.058763862 | P98: =IFERROR(P97/N97-1,"--") -> 0.0054985337 | Q98: =IFERROR(Q97/P97-1,"--") -> 0.028800583 | R98: =IFERROR(R97/Q97-1,"--") -> 0.0046066619 | S98: =IFERROR(S97/R97-1,"--") -> -0.00070546737 | T98: =IFERROR(T97/O97-1,"--") -> 0.034784531 | U98: =IF(Case_Scenario="Bull",U99,IF(Case_Scenario="Base",U100,IF(Case_Scenario="bear",U101,"N/A"))) -> 0.05 | V98: =IF(Case_Scenario="Bull",V99,IF(Case_Scenario="Base",V100,IF(Case_Scenario="bear",V101,"N/A"))) -> 0.05 | W98: =IF(Case_Scenario="Bull",W99,IF(Case_Scenario="Base",W100,IF(Case_Scenario="bear",W101,"N/A"))) -> 0.05 | X98: =IF(Case_Scenario="Bull",X99,IF(Case_Scenario="Base",X100,IF(Case_Scenario="bear",X101,"N/A"))) -> 0 | Z98: =IF(Case_Scenario="Bull",Z99,IF(Case_Scenario="Base",Z100,IF(Case_Scenario="bear",Z101,"N/A"))) -> 0.05 | AA98: =IF(Case_Scenario="Bull",AA99,IF(Case_Scenario="Base",AA100,IF(Case_Scenario="bear",AA101,"N/A"))) -> 0.05 | AB98: =IF(Case_Scenario="Bull",AB99,IF(Case_Scenario="Base",AB100,IF(Case_Scenario="bear",AB101,"N/A"))) -> 0.05 | AC98: =IF(Case_Scenario="Bull",AC99,IF(Case_Scenario="Base",AC100,IF(Case_Scenario="bear",AC101,"N/A"))) -> 0.05 | AE98: =IF(Case_Scenario="Bull",AE99,IF(Case_Scenario="Base",AE100,IF(Case_Scenario="bear",AE101,"N/A"))) -> 0.05 | AF98: =IF(Case_Scenario="Bull",AF99,IF(Case_Scenario="Base",AF100,IF(Case_Scenario="bear",AF101,"N/A"))) -> 0.05 | AG98: =IF(Case_Scenario="Bull",AG99,IF(Case_Scenario="Base",AG100,IF(Case_Scenario="bear",AG101,"N/A"))) -> 0.05
C99: Bull Case | U99: 0.1 | V99: 0.1 | W99: 0.1 | X99: 0 | Z99: 0.1 | AA99: 0.1 | AB99: 0.1 | AC99: 0.1 | AE99: 0.1 | AF99: 0.1 | AG99: 0.1
C100: Base Case | U100: 0.05 | V100: 0.05 | W100: 0.05 | X100: 0 | Z100: 0.05 | AA100: 0.05 | AB100: 0.05 | AC100: 0.05 | AE100: 0.05 | AF100: 0.05 | AG100: 0.05
C101: Bear Case | U101: 0 | V101: 0 | W101: 0 | X101: 0 | Z101: 0 | AA101: 0 | AB101: 0 | AC101: 0 | AE101: 0 | AF101: 0 | AG101: 0
A103: x | C103: =C35 -> Landfill Revenue | F103: =F35 -> 392.6 | G103: =G35 -> 431 | H103: =H35 -> 436.3 | I103: =I35 -> 419.6 | J103: =J35 -> 1679.5 | K103: =K35 -> 404.4 | L103: =L35 -> 440.2 | M103: =M35 -> 452.8 | ... T103: =T35 -> 1920 | U103: =U104*U109 -> 514.8675 | V103: =V104*V109 -> 567.64142 | W103: =W104*W109 -> 625.82466 | X103: =X104*X109 -> 625.82466 | Y103: =SUM(U103:X103) -> 2334.1582 | Z103: =Z104*Z109 -> 689.97169 | AA103: =AA104*AA109 -> 760.69379 | AB103: =AB104*AB109 -> 838.6649 | AC103: =AC104*AC109 -> 924.62806 | AD103: =SUM(Z103:AC103) -> 3213.9584 | AE103: =AE104*AE109 -> 3543.3892 | AF103: =AF104*AF109 -> 3906.5866 | AG103: =AG104*AG109 -> 4307.0117
C104: Volume | F104: 220 | G104: 220 | H104: 220 | I104: 220 | J104: =SUM(F104:I104) -> 880 | K104: 220 | L104: 220 | M104: 220 | N104: 220 | O104: =SUM(K104:N104) -> 880 | P104: 220 | Q104: 220 | R104: 220 | S104: 220 | T104: =SUM(P104:S104) -> 880 | U104: =S104*(1+U105) -> 231 | V104: =U104*(1+V105) -> 242.55 | W104: =V104*(1+W105) -> 254.6775 | X104: =W104*(1+X105) -> 254.6775 | Y104: =SUM(U104:X104) -> 982.905 | Z104: =X104*(1+Z105) -> 267.41138 | AA104: =Z104*(1+AA105) -> 280.78194 | AB104: =AA104*(1+AB105) -> 294.82104 | AC104: =AB104*(1+AC105) -> 309.56209 | AD104: =SUM(Z104:AC104) -> 1152.5765 | AE104: =AD104*(1+AE105) -> 1210.2053 | AF104: =AE104*(1+AF105) -> 1270.7155 | AG104: =AF104*(1+AG105) -> 1334.2513
C105: % Volume Growth | G105: =IFERROR(G104/F104-1,"--") -> 0 | H105: =IFERROR(H104/G104-1,"--") -> 0 | I105: =IFERROR(I104/H104-1,"--") -> 0 | K105: =IFERROR(K104/I104-1,"--") -> 0 | L105: =IFERROR(L104/K104-1,"--") -> 0 | M105: =IFERROR(M104/L104-1,"--") -> 0 | N105: =IFERROR(N104/M104-1,"--") -> 0 | O105: =IFERROR(O104/J104-1,"--") -> 0 | P105: =IFERROR(P104/N104-1,"--") -> 0 | Q105: =IFERROR(Q104/P104-1,"--") -> 0 | R105: =IFERROR(R104/Q104-1,"--") -> 0 | S105: =IFERROR(S104/R104-1,"--") -> 0 | T105: =IFERROR(T104/O104-1,"--") -> 0 | U105: =IF(Case_Scenario="Bull",U106,IF(Case_Scenario="Base",U107,IF(Case_Scenario="bear",U108,"N/A"))) -> 0.05 | V105: =IF(Case_Scenario="Bull",V106,IF(Case_Scenario="Base",V107,IF(Case_Scenario="bear",V108,"N/A"))) -> 0.05 | W105: =IF(Case_Scenario="Bull",W106,IF(Case_Scenario="Base",W107,IF(Case_Scenario="bear",W108,"N/A"))) -> 0.05 | X105: =IF(Case_Scenario="Bull",X106,IF(Case_Scenario="Base",X107,IF(Case_Scenario="bear",X108,"N/A"))) -> 0 | Z105: =IF(Case_Scenario="Bull",Z106,IF(Case_Scenario="Base",Z107,IF(Case_Scenario="bear",Z108,"N/A"))) -> 0.05 | AA105: =IF(Case_Scenario="Bull",AA106,IF(Case_Scenario="Base",AA107,IF(Case_Scenario="bear",AA108,"N/A"))) -> 0.05 | AB105: =IF(Case_Scenario="Bull",AB106,IF(Case_Scenario="Base",AB107,IF(Case_Scenario="bear",AB108,"N/A"))) -> 0.05 | AC105: =IF(Case_Scenario="Bull",AC106,IF(Case_Scenario="Base",AC107,IF(Case_Scenario="bear",AC108,"N/A"))) -> 0.05 | AE105: =IF(Case_Scenario="Bull",AE106,IF(Case_Scenario="Base",AE107,IF(Case_Scenario="bear",AE108,"N/A"))) -> 0.05 | AF105: =IF(Case_Scenario="Bull",AF106,IF(Case_Scenario="Base",AF107,IF(Case_Scenario="bear",AF108,"N/A"))) -> 0.05 | AG105: =IF(Case_Scenario="Bull",AG106,IF(Case_Scenario="Base",AG107,IF(Case_Scenario="bear",AG108,"N/A"))) -> 0.05
C106: Bull Case | U106: 0.1 | V106: 0.1 | W106: 0.1 | X106: 0 | Z106: 0.1 | AA106: 0.1 | AB106: 0.1 | AC106: 0.1 | AE106: 0.1 | AF106: 0.1 | AG106: 0.1
C107: Base Case | U107: 0.05 | V107: 0.05 | W107: 0.05 | X107: 0 | Z107: 0.05 | AA107: 0.05 | AB107: 0.05 | AC107: 0.05 | AE107: 0.05 | AF107: 0.05 | AG107: 0.05
C108: Bear Case | U108: 0 | V108: 0 | W108: 0 | X108: 0 | Z108: 0 | AA108: 0 | AB108: 0 | AC108: 0 | AE108: 0 | AF108: 0 | AG108: 0
C109: Price | F109: =IFERROR(F103/F104,"--") -> 1.7845455 | G109: =IFERROR(G103/G104,"--") -> 1.9590909 | H109: =IFERROR(H103/H104,"--") -> 1.9831818 | I109: =IFERROR(I103/I104,"--") -> 1.9072727 | J109: =IFERROR(J103/J104,"--") -> 1.9085227 | K109: =IFERROR(K103/K104,"--") -> 1.8381818 | L109: =IFERROR(L103/L104,"--") -> 2.0009091 | M109: =IFERROR(M103/M104,"--") -> 2.0581818 | ... T109: =IFERROR(T103/T104,"--") -> 2.1818182 | U109: =S109*(1+U110) -> 2.2288636 | V109: =U109*(1+V110) -> 2.3403068 | W109: =V109*(1+W110) -> 2.4573222 | X109: =W109*(1+X110) -> 2.4573222 | Y109: =Y103/Y104 -> 2.3747547 | Z109: =X109*(1+Z110) -> 2.5801883 | AA109: =Z109*(1+AA110) -> 2.7091977 | AB109: =AA109*(1+AB110) -> 2.8446576 | AC109: =AB109*(1+AC110) -> 2.9868904 | AD109: =AD103/AD104 -> 2.7884991 | AE109: =AD109*(1+AE110) -> 2.9279241 | AF109: =AE109*(1+AF110) -> 3.0743203 | AG109: =AF109*(1+AG110) -> 3.2280363
C110: % Price Growth | G110: =IFERROR(G109/F109-1,"--") -> 0.097809475 | H110: =IFERROR(H109/G109-1,"--") -> 0.012296984 | I110: =IFERROR(I109/H109-1,"--") -> -0.038276415 | K110: =IFERROR(K109/I109-1,"--") -> -0.036224976 | L110: =IFERROR(L109/K109-1,"--") -> 0.088526212 | M110: =IFERROR(M109/L109-1,"--") -> 0.028623353 | N110: =IFERROR(N109/M109-1,"--") -> -0.02164311 | O110: =IFERROR(O109/J109-1,"--") -> 0.036260792 | P110: =IFERROR(P109/N109-1,"--") -> -0.0496614 | Q110: =IFERROR(Q109/P109-1,"--") -> 0.22565321 | R110: =IFERROR(R109/Q109-1,"--") -> 0 | S110: =IFERROR(S109/R109-1,"--") -> -0.09496124 | T110: =IFERROR(T109/O109-1,"--") -> 0.10319467 | U110: =IF(Case_Scenario="Bull",U111,IF(Case_Scenario="Base",U112,IF(Case_Scenario="bear",U113,"N/A"))) -> 0.05 | V110: =IF(Case_Scenario="Bull",V111,IF(Case_Scenario="Base",V112,IF(Case_Scenario="bear",V113,"N/A"))) -> 0.05 | W110: =IF(Case_Scenario="Bull",W111,IF(Case_Scenario="Base",W112,IF(Case_Scenario="bear",W113,"N/A"))) -> 0.05 | X110: =IF(Case_Scenario="Bull",X111,IF(Case_Scenario="Base",X112,IF(Case_Scenario="bear",X113,"N/A"))) -> 0 | Z110: =IF(Case_Scenario="Bull",Z111,IF(Case_Scenario="Base",Z112,IF(Case_Scenario="bear",Z113,"N/A"))) -> 0.05 | AA110: =IF(Case_Scenario="Bull",AA111,IF(Case_Scenario="Base",AA112,IF(Case_Scenario="bear",AA113,"N/A"))) -> 0.05 | AB110: =IF(Case_Scenario="Bull",AB111,IF(Case_Scenario="Base",AB112,IF(Case_Scenario="bear",AB113,"N/A"))) -> 0.05 | AC110: =IF(Case_Scenario="Bull",AC111,IF(Case_Scenario="Base",AC112,IF(Case_Scenario="bear",AC113,"N/A"))) -> 0.05 | AE110: =IF(Case_Scenario="Bull",AE111,IF(Case_Scenario="Base",AE112,IF(Case_Scenario="bear",AE113,"N/A"))) -> 0.05 | AF110: =IF(Case_Scenario="Bull",AF111,IF(Case_Scenario="Base",AF112,IF(Case_Scenario="bear",AF113,"N/A"))) -> 0.05 | AG110: =IF(Case_Scenario="Bull",AG111,IF(Case_Scenario="Base",AG112,IF(Case_Scenario="bear",AG113,"N/A"))) -> 0.05
C111: Bull Case | U111: 0.1 | V111: 0.1 | W111: 0.1 | X111: 0 | Z111: 0.1 | AA111: 0.1 | AB111: 0.1 | AC111: 0.1 | AE111: 0.1 | AF111: 0.1 | AG111: 0.1
C112: Base Case | U112: 0.05 | V112: 0.05 | W112: 0.05 | X112: 0 | Z112: 0.05 | AA112: 0.05 | AB112: 0.05 | AC112: 0.05 | AE112: 0.05 | AF112: 0.05 | AG112: 0.05
C113: Bear Case | U113: 0 | V113: 0 | W113: 0 | X113: 0 | Z113: 0 | AA113: 0 | AB113: 0 | AC113: 0 | AE113: 0 | AF113: 0 | AG113: 0
A115: x | C115: =C38 -> Environmental solutions Revenue | F115: =F38 -> 408.3 | G115: =G38 -> 398.3 | H115: =H38 -> 404.8 | I115: =I38 -> 413.4 | J115: =J38 -> 1624.8 | K115: =K38 -> 423.3 | L115: =L38 -> 472.6 | M115: =M38 -> 464.7 | ... T115: =T38 -> 1766 | U115: =U116*U121 -> 465.255 | V115: =V116*V121 -> 512.94364 | W115: =W116*W121 -> 565.52036 | X115: =X116*X121 -> 565.52036 | Y115: =SUM(U115:X115) -> 2109.2394 | Z115: =Z116*Z121 -> 623.4862 | AA115: =AA116*AA121 -> 687.39353 | AB115: =AB116*AB121 -> 757.85137 | AC115: =AC116*AC121 -> 835.53113 | AD115: =SUM(Z115:AC115) -> 2904.2622 | AE115: =AE116*AE121 -> 3201.9491 | AF115: =AF116*AF121 -> 3530.1489 | AG115: =AG116*AG121 -> 3891.9892
C116: Volume | F116: 220 | G116: 220 | H116: 220 | I116: 220 | J116: =SUM(F116:I116) -> 880 | K116: 220 | L116: 220 | M116: 220 | N116: 220 | O116: =SUM(K116:N116) -> 880 | P116: 220 | Q116: 220 | R116: 220 | S116: 220 | T116: =SUM(P116:S116) -> 880 | U116: =S116*(1+U117) -> 231 | V116: =U116*(1+V117) -> 242.55 | W116: =V116*(1+W117) -> 254.6775 | X116: =W116*(1+X117) -> 254.6775 | Y116: =SUM(U116:X116) -> 982.905 | Z116: =X116*(1+Z117) -> 267.41138 | AA116: =Z116*(1+AA117) -> 280.78194 | AB116: =AA116*(1+AB117) -> 294.82104 | AC116: =AB116*(1+AC117) -> 309.56209 | AD116: =SUM(Z116:AC116) -> 1152.5765 | AE116: =AD116*(1+AE117) -> 1210.2053 | AF116: =AE116*(1+AF117) -> 1270.7155 | AG116: =AF116*(1+AG117) -> 1334.2513
...

Sheet Model
C1: =Company_Name&" - "&MID(CELL("filename",A1),FIND("]",CELL("filename",A1))+1,255)&": "&Case_Scenario&" Case" -> Republic Services, Inc. - Model: Base Case
C2: =Cover!C2 -> $ in Millions Except Per Share Data
C4: Font Toggle
C5: Report
C7: Interest Expense Toggle
C8: On
A10: x | C10: Shortcuts
C11: =$C$25 -> Income Statement
C12: =$C$75 -> Cash Flow Statement
C13: =$C$121 -> Balance Sheet
C14: =$C$163 -> Working Capital Schedule
C15: =$C$193 -> PP&E / Depreciation Schedule
C16: =$C$207 -> Amortization Schedule
C17: =$C$219 -> Other Long-Term Items Schedule
C18: =$C$237 -> Shareholder's Equity Schedule
C19: =$C$278 -> Shares Outstanding Schedule
C20: =$C$289 -> Debt and Interest Schedule
J23: 2 | O23: 2 | T23: 3 | Y23: 4 | AD23: 5 | AE23: 6 | AF23: 7 | AG23: 8
F24: =G24 -> 2023 | G24: =H24 -> 2023 | H24: =I24 -> 2023 | I24: =J24 -> 2023 | J24: =O24-1 -> 2023 | K24: =L24 -> 2024 | L24: =M24 -> 2024 | M24: =N24 -> 2024 | N24: =O24 -> 2024 | O24: =T24-1 -> 2024 | P24: =Q24 -> 2025 | Q24: =R24 -> 2025 | R24: =S24 -> 2025 | S24: =T24 -> 2025 | T24: =YEAR(Last_FYE) -> 2025 | U24: =V24 -> 2026 | V24: =W24 -> 2026 | W24: =X24 -> 2026 | X24: =Y24 -> 2026 | Y24: =T24+1 -> 2026 | Z24: =AA24 -> 2027 | AA24: =AB24 -> 2027 | AB24: =AC24 -> 2027 | AC24: =AD24 -> 2027 | AD24: =Y24+1 -> 2027 | AE24: =AD24+1 -> 2028 | AF24: =AE24+1 -> 2029 | AG24: =AF24+1 -> 2030
A25: x | C25: Income Statement | F25: ="1Q"&RIGHT(F24,2) -> 1Q23 | G25: ="2Q"&RIGHT(G24,2) -> 2Q23 | H25: ="3Q"&RIGHT(H24,2) -> 3Q23 | I25: ="4Q"&RIGHT(I24,2) -> 4Q23 | J25: =J24 -> 2023 | K25: ="1Q"&RIGHT(K24,2) -> 1Q24 | L25: ="2Q"&RIGHT(L24,2) -> 2Q24 | M25: ="3Q"&RIGHT(M24,2) -> 3Q24 | N25: ="4Q"&RIGHT(N24,2) -> 4Q24 | O25: =O24 -> 2024 | P25: ="1Q"&RIGHT(P24,2) -> 1Q25 | Q25: ="2Q"&RIGHT(Q24,2) -> 2Q25 | R25: ="3Q"&RIGHT(R24,2) -> 3Q25 | S25: ="4Q"&RIGHT(S24,2) -> 4Q25 | T25: =T24 -> 2025 | U25: =IF(Last_FQR="4Q","1Q"&RIGHT(U24,2)&"e","1Q"&RIGHT(U24,2)) -> 1Q26e | V25: =IF(Last_FQR="4Q","2Q"&RIGHT(W24,2)&"e",IF(Last_FQR="1Q","2Q"&RIGHT(W24,2)&"e","2Q"&RIGHT(W24,2))) -> 2Q26e | W25: ="3Q"&RIGHT(W24,2) -> 3Q26 | X25: ="4Q"&RIGHT(U24,2)&"e" -> 4Q26e | Y25: =Y24&"e" -> 2026e | Z25: ="1Q"&RIGHT(Z24,2)&"e" -> 1Q27e | AA25: ="2Q"&RIGHT(AA24,2)&"e" -> 2Q27e | AB25: ="3Q"&RIGHT(AB24,2)&"e" -> 3Q27e | AC25: ="4Q"&RIGHT(AC24,2)&"e" -> 4Q27e | AD25: =AD24&"e" -> 2027e | AE25: =AE24&"e" -> 2028e | AF25: =AF24&"e" -> 2029e | AG25: =AG24&"e" -> 2030e | AH25: x
C26: Days In Period | F26: 90 | G26: 91 | H26: 92 | I26: 92 | J26: =SUM(F26:I26) -> 365 | K26: 90 | L26: 91 | M26: 92 | N26: 92 | O26: =SUM(K26:N26) -> 365 | P26: 90 | Q26: 91 | R26: 92 | S26: 92 | T26: =SUM(P26:S26) -> 365 | U26: 90 | V26: 91 | W26: 92 | X26: 92 | Y26: =SUM(U26:X26) -> 365 | Z26: 91 | AA26: 91 | AB26: 92 | AC26: 92 | AD26: =SUM(Z26:AC26) -> 366 | AE26: 365 | AF26: 365 | AG26: 365
C28: Revenue | F28: ='Segment Analysis'!F8 -> 4147.2 | G28: ='Segment Analysis'!G8 -> 4321.4 | H28: ='Segment Analysis'!H8 -> 4414.2 | I28: ='Segment Analysis'!I8 -> 4396.3 | J28: =SUM(F28:I28) -> 17279.1 | K28: ='Segment Analysis'!K8 -> 4439 | L28: ='Segment Analysis'!L8 -> 4663 | M28: ='Segment Analysis'!M8 -> 4680 | N28: ='Segment Analysis'!N8 -> 4634 | O28: =SUM(K28:N28) -> 18416 | P28: ='Segment Analysis'!P8 -> 4593 | Q28: ='Segment Analysis'!Q8 -> 4882 | R28: ='Segment Analysis'!R8 -> 4827 | S28: ='Segment Analysis'!S8 -> 4727 | T28: =SUM(P28:S28) -> 19029 | U28: ='Segment Analysis'!U8 -> 4152.631 | V28: ='Segment Analysis'!V8 -> 4379.486 | W28: ='Segment Analysis'!W8 -> 4358.186 | X28: ='Segment Analysis'!X8 -> 4435.8154 | Y28: =SUM(U28:X28) -> 17326.118 | Z28: ='Segment Analysis'!Z8 -> 4358.6652 | AA28: ='Segment Analysis'!AA8 -> 4593.3476 | AB28: ='Segment Analysis'!AB8 -> 4573.9711 | AC28: ='Segment Analysis'!AC8 -> 4522.6788 | AD28: =SUM(Z28:AC28) -> 18048.663 | AE28: ='Segment Analysis'!AE8 -> 18921.749 | AF28: ='Segment Analysis'!AF8 -> 19882.733 | AG28: ='Segment Analysis'!AG8 -> 20839.079
C29: Cost of Goods Sold | F29: -2169.5 | G29: -2224.4 | H29: -2284.3 | I29: -2265 | J29: =SUM(F29:I29) -> -8943.2 | K29: -2283 | L29: -2383 | M29: -2367 | N29: -2317 | O29: =SUM(K29:N29) -> -9350 | P29: -2314 | Q29: -2449 | R29: -2463 | S29: -2404 | T29: =SUM(P29:S29) -> -9630 | X29: =IF(Cover!$F$37="Bottom Up",(X30-X28),(-X28*(1-X68))) -> -2555.0297 | Y29: =SUM(U29:X29) -> -2555.0297 | Z29: =IF(Cover!$F$37="Bottom Up",(Z30-Z28),(-Z28*(1-Z68))) -> -2493.1565 | AA29: =IF(Cover!$F$37="Bottom Up",(AA30-AA28),(-AA28*(1-AA68))) -> -2641.1749 | AB29: =IF(Cover!$F$37="Bottom Up",(AB30-AB28),(-AB28*(1-AB68))) -> -2616.3115 | AC29: =IF(Cover!$F$37="Bottom Up",(AC30-AC28),(-AC28*(1-AC68))) -> -2586.9723 | AD29: =SUM(Z29:AC29) -> -10337.615 | AE29: =IF(Cover!$F$37="Bottom Up",(AE30-AE28),(-AE28*(1-AE68))) -> -10766.475 | AF29: =IF(Cover!$F$37="Bottom Up",(AF30-AF28),(-AF28*(1-AF68))) -> -11372.923 | AG29: =IF(Cover!$F$37="Bottom Up",(AG30-AG28),(-AG28*(1-AG68))) -> -11919.953
C30: Gross Profit | F30: =SUM(F28:F29) -> 1977.7 | G30: =SUM(G28:G29) -> 2097 | H30: =SUM(H28:H29) -> 2129.9 | I30: =SUM(I28:I29) -> 2131.3 | J30: =SUM(F30:I30) -> 8335.9 | K30: =SUM(K28:K29) -> 2156 | L30: =SUM(L28:L29) -> 2280 | M30: =SUM(M28:M29) -> 2313 | N30: =SUM(N28:N29) -> 2317 | O30: =SUM(K30:N30) -> 9066 | P30: =SUM(P28:P29) -> 2279 | Q30: =SUM(Q28:Q29) -> 2433 | R30: =SUM(R28:R29) -> 2364 | S30: =SUM(S28:S29) -> 2323 | T30: =SUM(P30:S30) -> 9399 | U30: =SUM(U28:U29) -> 4152.631 | V30: =SUM(V28:V29) -> 4379.486 | W30: =SUM(W28:W29) -> 4358.186 | X30: =IF(Cover!$F$37="Bottom Up",(X36-SUM(X32:X33,X35)),X28+X29) -> 1880.7857 | Y30: =SUM(U30:X30) -> 14771.089 | Z30: =IF(Cover!$F$37="Bottom Up",(Z36-SUM(Z32:Z33,Z35)),Z28+Z29) -> 1865.5087 | AA30: =IF(Cover!$F$37="Bottom Up",(AA36-SUM(AA32:AA33,AA35)),AA28+AA29) -> 1952.1727 | AB30: =IF(Cover!$F$37="Bottom Up",(AB36-SUM(AB32:AB33,AB35)),AB28+AB29) -> 1957.6596 | AC30: =IF(Cover!$F$37="Bottom Up",(AC36-SUM(AC32:AC33,AC35)),AC28+AC29) -> 1935.7065 | AD30: =SUM(Z30:AC30) -> 7711.0476 | AE30: =IF(Cover!$F$37="Bottom Up",(AE36-SUM(AE32:AE33,AE35)),AE28+AE29) -> 8155.2739 | AF30: =IF(Cover!$F$37="Bottom Up",(AF36-SUM(AF32:AF33,AF35)),AF28+AF29) -> 8509.8097 | AG30: =IF(Cover!$F$37="Bottom Up",(AG36-SUM(AG32:AG33,AG35)),AG28+AG29) -> 8919.1257
C32: Selling, General & Administration (SG&A) | F32: -379.2 | G32: -396 | H32: -402.1 | I32: -431.7 | J32: =SUM(F32:I32) -> -1609 | K32: -414 | L32: -407 | M32: -406 | N32: -447 | O32: =SUM(K32:N32) -> -1674 | P32: -427 | Q32: -425 | R32: -422 | S32: -436 | T32: =SUM(P32:S32) -> -1710 | X32: =X69*X$28 -> -456.88899 | Y32: =SUM(U32:X32) -> -456.88899 | Z32: =Z69*Z$28 -> -462.01851 | AA32: =AA69*AA$28 -> -459.33476 | AB32: =AB69*AB$28 -> -457.39711 | AC32: =AC69*AC$28 -> -465.83592 | AD32: =SUM(Z32:AC32) -> -1844.5863 | AE32: =AE69*AE$28 -> -1892.1749 | AF32: =AF69*AF$28 -> -1988.2733 | AG32: =AG69*AG$28 -> -2083.9079
C33: Research & Development (R&D) | J33: =SUM(F33:I33) -> 0 | O33: =SUM(K33:N33) -> 0 | T33: =SUM(P33:S33) -> 0 | X33: =X70*X$28 -> 0 | Y33: =SUM(U33:X33) -> 0 | Z33: =Z70*Z$28 -> 0 | AA33: =AA70*AA$28 -> 0 | AB33: =AB70*AB$28 -> 0 | AC33: =AC70*AC$28 -> 0 | AD33: =SUM(Z33:AC33) -> 0 | AE33: =AE70*AE$28 -> 0 | AF33: =AF70*AF$28 -> 0 | AG33: =AG70*AG$28 -> 0
C34: Depreciation & Amortization | F34: -358.7 | G34: -358.3 | H34: -382.3 | I34: -401.6 | J34: =SUM(F34:I34) -> -1500.9 | K34: -399 | L34: -413 | M34: -422 | N34: -443 | O34: =SUM(K34:N34) -> -1677 | P34: -434 | Q34: -463 | R34: -459 | S34: -458 | T34: =SUM(P34:S34) -> -1814 | X34: =X197 -> -494.45254 | Y34: =SUM(U34:X34) -> -1850.4525 | Z34: =Z197 -> -485.29601 | AA34: =AA197 -> -485.93053 | AB34: =AB197 -> -486.65054 | AC34: =AC197 -> -487.72771 | AD34: =SUM(Z34:AC34) -> -1945.6048 | AE34: =AE197 -> -1977.3332 | AF34: =AF197 -> -2085.2579 | AG34: =AG197 -> -2190.6618
C35: Other Operating Income (Expense) | F35: -595.7 | G35: -635.5 | H35: -617.7 | I35: -597.2 | J35: =SUM(F35:I35) -> -2446.1 | K35: -610 | L35: -646 | M35: -639 | N35: -624 | O35: =SUM(K35:N35) -> -2519 | P35: -614 | Q35: -684 | R35: -647 | S35: -629 | T35: =SUM(P35:S35) -> -2574 | X35: =X71*X$28 -> -35.486524 | Y35: =SUM(U35:X35) -> -35.486524 | Z35: =Z71*Z$28 -> -30.510656 | AA35: =AA71*AA$28 -> -32.153433 | AB35: =AB71*AB$28 -> -32.017798 | AC35: =AC71*AC$28 -> -31.658752 | AD35: =SUM(Z35:AC35) -> -126.34064 | AE35: =AE71*AE$28 -> -132.45224 | AF35: =AF71*AF$28 -> -119.2964 | AG35: =AG71*AG$28 -> -104.19539
C36: EBIT | F36: =IF($C$34="Depreciation & Amortization (incl. in SG&A)",F30+SUM(F32:F33,F35),F30+SUM(F32:F35)) -> 644.1 | G36: =IF($C$34="Depreciation & Amortization (incl. in SG&A)",G30+SUM(G32:G33,G35),G30+SUM(G32:G35)) -> 707.2 | H36: =IF($C$34="Depreciation & Amortization (incl. in SG&A)",H30+SUM(H32:H33,H35),H30+SUM(H32:H35)) -> 727.8 | I36: =IF($C$34="Depreciation & Amortization (incl. in SG&A)",I30+SUM(I32:I33,I35),I30+SUM(I32:I35)) -> 700.8 | J36: =SUM(F36:I36) -> 2779.9 | K36: =IF($C$34="Depreciation & Amortization (incl. in SG&A)",K30+SUM(K32:K33,K35),K30+SUM(K32:K35)) -> 733 | L36: =IF($C$34="Depreciation & Amortization (incl. in SG&A)",L30+SUM(L32:L33,L35),L30+SUM(L32:L35)) -> 814 | M36: =IF($C$34="Depreciation & Amortization (incl. in SG&A)",M30+SUM(M32:M33,M35),M30+SUM(M32:M35)) -> 846 | N36: =IF($C$34="Depreciation & Amortization (incl. in SG&A)",N30+SUM(N32:N33,N35),N30+SUM(N32:N35)) -> 803 | O36: =SUM(K36:N36) -> 3196 | P36: =IF($C$34="Depreciation & Amortization (incl. in SG&A)",P30+SUM(P32:P33,P35),P30+SUM(P32:P35)) -> 804 | Q36: =IF($C$34="Depreciation & Amortization (incl. in SG&A)",Q30+SUM(Q32:Q33,Q35),Q30+SUM(Q32:Q35)) -> 861 | R36: =IF($C$34="Depreciation & Amortization (incl. in SG&A)",R30+SUM(R32:R33,R35),R30+SUM(R32:R35)) -> 836 | S36: =IF($C$34="Depreciation & Amortization (incl. in SG&A)",S30+SUM(S32:S33,S35),S30+SUM(S32:S35)) -> 800 | T36: =SUM(P36:S36) -> 3301 | U36: =IF($C$34="Depreciation & Amortization (incl. in SG&A)",U30+SUM(U32:U33,U35),U30+SUM(U32:U35)) -> 4152.631 | V36: =IF($C$34="Depreciation & Amortization (incl. in SG&A)",V30+SUM(V32:V33,V35),V30+SUM(V32:V35)) -> 4379.486 | W36: =IF($C$34="Depreciation & Amortization (incl. in SG&A)",W30+SUM(W32:W33,W35),W30+SUM(W32:W35)) -> 4358.186 | X36: =IF(Cover!$F$37="Bottom Up",'Segment Analysis'!X34,IF($C$34="Depreciation & Amortization (incl. in SG&A)",X30+SUM(X32:X33,X35),X30+SUM(X32:X35))) -> 893.95769 | Y36: =SUM(U36:X36) -> 3829.2607 | Z36: =IF(Cover!$F$37="Bottom Up",'Segment Analysis'!Z34,IF($C$34="Depreciation & Amortization (incl. in SG&A)",Z30+SUM(Z32:Z33,Z35),Z30+SUM(Z32:Z35))) -> 887.68351 | AA36: =IF(Cover!$F$37="Bottom Up",'Segment Analysis'!AA34,IF($C$34="Depreciation & Amortization (incl. in SG&A)",AA30+SUM(AA32:AA33,AA35),AA30+SUM(AA32:AA35))) -> 974.754 | AB36: =IF(Cover!$F$37="Bottom Up",'Segment Analysis'!AB34,IF($C$34="Depreciation & Amortization (incl. in SG&A)",AB30+SUM(AB32:AB33,AB35),AB30+SUM(AB32:AB35))) -> 981.59418 | AC36: =IF(Cover!$F$37="Bottom Up",'Segment Analysis'!AC34,IF($C$34="Depreciation & Amortization (incl. in SG&A)",AC30+SUM(AC32:AC33,AC35),AC30+SUM(AC32:AC35))) -> 950.48416 | AD36: =SUM(Z36:AC36) -> 3794.5159 | AE36: =IF(Cover!$F$37="Bottom Up",'Segment Analysis'!AE34,IF($C$34="Depreciation & Amortization (incl. in SG&A)",AE30+SUM(AE32:AE33,AE35),AE30+SUM(AE32:AE35))) -> 4153.3135 | AF36: =IF(Cover!$F$37="Bottom Up",'Segment Analysis'!AF34,IF($C$34="Depreciation & Amortization (incl. in SG&A)",AF30+SUM(AF32:AF33,AF35),AF30+SUM(AF32:AF35))) -> 4316.9821 | AG36: =IF(Cover!$F$37="Bottom Up",'Segment Analysis'!AG34,IF($C$34="Depreciation & Amortization (incl. in SG&A)",AG30+SUM(AG32:AG33,AG35),AG30+SUM(AG32:AG35))) -> 4540.3607 | AH36: =AG36/AG30 -> 0.50905894
C38: Interest Income | F38: 1.4 | G38: 1.6 | H38: 2 | I38: 1 | J38: =SUM(F38:I38) -> 6 | K38: 1 | L38: 1 | M38: 4 | N38: 2 | O38: =SUM(K38:N38) -> 8 | P38: 2 | Q38: 2 | R38: 2 | S38: 2 | T38: =SUM(P38:S38) -> 8 | X38: =X332 -> 0 | Y38: =SUM(U38:X38) -> 0 | Z38: =Z332 -> 0 | AA38: =AA332 -> 0 | AB38: =AB332 -> 0 | AC38: =AC332 -> 0 | AD38: =SUM(Z38:AC38) -> 0 | AE38: =AE332 -> 0 | AF38: =AF332 -> 0 | AG38: =AG332 -> 0
C39: Interest (Expense) | J39: =SUM(F39:I39) -> 0 | O39: =SUM(K39:N39) -> 0 | T39: =SUM(P39:S39) -> 0 | X39: =X325 -> -1.225 | Y39: =SUM(U39:X39) -> -1.225 | Z39: =Z325 -> -2.5 | AA39: =AA325 -> 0.5 | AB39: =AB325 -> 6.5 | AC39: =AC325 -> 12.5 | AD39: =SUM(Z39:AC39) -> 17 | AE39: =AE325 -> 62 | AF39: =AF325 -> 74 | AG39: =AG325 -> 98
C40: Goodwill Impairment | J40: =SUM(F40:I40) -> 0 | O40: =SUM(K40:N40) -> 0 | T40: =SUM(P40:S40) -> 0 | X40: =Drivers!X62 -> 0 | Y40: =SUM(U40:X40) -> 0 | Z40: =Drivers!Z62 -> 0 | AA40: =Drivers!AA62 -> 0 | AB40: =Drivers!AB62 -> 0 | AC40: =Drivers!AC62 -> 0 | AD40: =SUM(Z40:AC40) -> 0 | AE40: =Drivers!AE62 -> 0 | AF40: =Drivers!AF62 -> 0 | AG40: =Drivers!AG62 -> 0
C41: Other Non-Operating Income (Expense) | F41: 2.5 | G41: -0.6 | H41: 1.3 | I41: 3.8 | J41: =SUM(F41:I41) -> 7 | K41: 13 | L41: 1 | M41: 10 | N41: 0 | O41: =SUM(K41:N41) -> 24 | P41: 11 | Q41: 4 | R41: 7 | S41: -1 | T41: =SUM(P41:S41) -> 21 | X41: =X72*X28 -> -53.229785 | Y41: =SUM(U41:X41) -> -53.229785 | Z41: =Z72*Z28 -> -47.945317 | AA41: =AA72*AA28 -> -50.526823 | AB41: =AB72*AB28 -> -50.313682 | AC41: =AC72*AC28 -> -49.749467 | AD41: =SUM(Z41:AC41) -> -198.53529 | AE41: =AE72*AE28 -> -208.13924 | AF41: =AF72*AF28 -> -238.5928 | AG41: =AG72*AG28 -> -250.06895
C42: Pre-Tax Income (Loss) | F42: =F36+SUM(F38:F41) -> 648 | G42: =G36+SUM(G38:G41) -> 708.2 | H42: =H36+SUM(H38:H41) -> 731.1 | I42: =I36+SUM(I38:I41) -> 705.6 | J42: =SUM(F42:I42) -> 2792.9 | K42: =K36+SUM(K38:K41) -> 747 | L42: =L36+SUM(L38:L41) -> 816 | M42: =M36+SUM(M38:M41) -> 860 | N42: =N36+SUM(N38:N41) -> 805 | O42: =SUM(K42:N42) -> 3228 | P42: =P36+SUM(P38:P41) -> 817 | Q42: =Q36+SUM(Q38:Q41) -> 867 | R42: =IF($C$8="On",R36+SUM(R38:R41),IF($C$8="off",R36+SUM(R40:R41),"N/A")) -> 845 | S42: =IF($C$8="On",S36+SUM(S38:S41),IF($C$8="off",S36+SUM(S40:S41),"N/A")) -> 801 | T42: =SUM(P42:S42) -> 3330 | U42: =U36+SUM(U38:U41) -> 4152.631 | V42: =V36+SUM(V38:V41) -> 4379.486 | W42: =IF($C$8="On",W36+SUM(W38:W41),IF($C$8="off",W36+SUM(W40:W41),"N/A")) -> 4358.186 | X42: =IF($C$8="On",X36+SUM(X38:X41),IF($C$8="off",X36+SUM(X40:X41),"N/A")) -> 718.44351 | Y42: =SUM(U42:X42) -> 3182.7465 | Z42: =IF($C$8="On",Z36+SUM(Z38:Z41),IF($C$8="off",Z36+SUM(Z40:Z41),"N/A")) -> 713.7082 | AA42: =IF($C$8="On",AA36+SUM(AA38:AA41),IF($C$8="off",AA36+SUM(AA40:AA41),"N/A")) -> 801.19717 | AB42: =IF($C$8="On",AB36+SUM(AB38:AB41),IF($C$8="off",AB36+SUM(AB40:AB41),"N/A")) -> 814.2505 | AC42: =IF($C$8="On",AC36+SUM(AC38:AC41),IF($C$8="off",AC36+SUM(AC40:AC41),"N/A")) -> 789.70469 | AD42: =SUM(Z42:AC42) -> 3118.8606 | AE42: =IF($C$8="On",AE36+SUM(AE38:AE41),IF($C$8="off",AE36+SUM(AE40:AE41),"N/A")) -> 3513.0543 | AF42: =IF($C$8="On",AF36+SUM(AF38:AF41),IF($C$8="off",AF36+SUM(AF40:AF41),"N/A")) -> 3658.2693 | AG42: =IF($C$8="On",AG36+SUM(AG38:AG41),IF($C$8="off",AG36+SUM(AG40:AG41),"N/A")) -> 3894.1717
C44: Income Tax Benefit (Expense) | F44: -264.148 | G44: -280.802 | H44: -250.931 | I44: -266.034 | J44: =SUM(F44:I44) -> -1061.915 | K44: -293.206 | L44: -304.464 | M44: -294.331 | N44: -292.826 | O44: =SUM(K44:N44) -> -1184.827 | P44: -322.004 | Q44: -317.095 | R44: -295.328 | S44: -256.324 | T44: =SUM(P44:S44) -> -1190.751 | X44: =-X73*X42 -> -151.59158 | Y44: =SUM(U44:X44) -> -586.59158 | Z44: =-Z73*Z42 -> -145.59647 | AA44: =-AA73*AA42 -> -163.60446 | AB44: =-AB73*AB42 -> -166.26995 | AC44: =-AC73*AC42 -> -161.2577 | AD44: =SUM(Z44:AC44) -> -636.72859 | AE44: =-AE73*AE42 -> -709.63696 | AF44: =-AF73*AF42 -> -738.9704 | AG44: =-AG73*AG42 -> -786.62269
C45: Net Income (Loss) | F45: =F42+F44 -> 383.852 | G45: =G42+G44 -> 427.398 | H45: =H42+H44 -> 480.169 | I45: =I42+I44 -> 439.566 | J45: =SUM(F45:I45) -> 1730.985 | K45: =K42+K44 -> 453.794 | L45: =L42+L44 -> 511.536 | M45: =M42+M44 -> 565.669 | N45: =N42+N44 -> 512.174 | O45: =SUM(K45:N45) -> 2043.173 | P45: =P42+P44 -> 494.996 | Q45: =Q42+Q44 -> 549.905 | R45: =R42+R44 -> 549.672 | S45: =S42+S44 -> 544.676 | T45: =SUM(P45:S45) -> 2139.249 | U45: =U42+U44 -> 4152.631 | V45: =V42+V44 -> 4379.486 | W45: =W42+W44 -> 4358.186 | X45: =X42+X44 -> 566.85193 | Y45: =SUM(U45:X45) -> 2596.1549 | Z45: =Z42+Z44 -> 568.11173 | AA45: =AA42+AA44 -> 637.59271 | AB45: =AB42+AB44 -> 647.98055 | AC45: =AC42+AC44 -> 628.44699 | AD45: =SUM(Z45:AC45) -> 2482.132 | AE45: =AE42+AE44 -> 2803.4173 | AF45: =AF42+AF44 -> 2919.2989 | AG45: =AG42+AG44 -> 3107.5491
C47: Pre-Tax Adjustments | J47: =SUM(F47:I47) -> 0 | O47: =SUM(K47:N47) -> 0 | T47: =SUM(P47:S47) -> 0 | X47: 0 | Y47: =SUM(U47:X47) -> 0 | Z47: 0 | AA47: 0 | AB47: 0 | AC47: 0 | AD47: 0 | AE47: 0 | AF47: 0 | AG47: 0
C48: Post-Tax Adjustments | J48: =SUM(F48:I48) -> 0 | O48: =SUM(K48:N48) -> 0 | T48: =SUM(P48:S48) -> 0 | X48: 0 | Y48: =SUM(U48:X48) -> 0 | Z48: 0 | AA48: 0 | AB48: 0 | AC48: 0 | AD48: =SUM(Z48:AC48) -> 0 | AE48: 0 | AF48: 0 | AG48: 0
C49: Discontinued Operations | F49: 0 | G49: 0 | H49: 0 | I49: 0 | J49: =SUM(F49:I49) -> 0 | K49: 0 | L49: 0 | M49: 0 | N49: 0 | O49: =SUM(K49:N49) -> 0 | T49: =SUM(P49:S49) -> 0 | X49: 0 | Y49: =SUM(U49:X49) -> 0 | Z49: 0 | AA49: 0 | AB49: 0 | AC49: 0 | AD49: =SUM(Z49:AC49) -> 0 | AE49: 0 | AF49: 0 | AG49: 0
C50: Income (Loss) due to Non-Controlling Interest | J50: =SUM(F50:I50) -> 0 | O50: =SUM(K50:N50) -> 0 | T50: =SUM(P50:S50) -> 0 | X50: 0 | Y50: =SUM(U50:X50) -> 0 | Z50: 0 | AA50: 0 | AB50: 0 | AC50: 0 | AD50: =SUM(Z50:AC50) -> 0 | AE50: 0 | AF50: 0 | AG50: 0
C51: Adj. Net Income (Loss) | F51: =SUM(F45:F50) -> 383.852 | G51: =SUM(G45:G50) -> 427.398 | H51: =SUM(H45:H50) -> 480.169 | I51: =SUM(I45:I50) -> 439.566 | J51: =SUM(F51:I51) -> 1730.985 | K51: =SUM(K45:K50) -> 453.794 | L51: =SUM(L45:L50) -> 511.536 | M51: =SUM(M45:M50) -> 565.669 | N51: =SUM(N45:N50) -> 512.174 | O51: =SUM(K51:N51) -> 2043.173 | P51: =SUM(P45:P50) -> 494.996 | Q51: =SUM(Q45:Q50) -> 549.905 | R51: =SUM(R45:R50) -> 549.672 | S51: =SUM(S45:S50) -> 544.676 | T51: =SUM(P51:S51) -> 2139.249 | U51: =SUM(U45:U50) -> 4152.631 | V51: =SUM(V45:V50) -> 4379.486 | W51: =SUM(W45:W50) -> 4358.186 | X51: =SUM(X45:X50) -> 566.85193 | Y51: =SUM(U51:X51) -> 2596.1549 | Z51: =SUM(Z45:Z50) -> 568.11173 | AA51: =SUM(AA45:AA50) -> 637.59271 | AB51: =SUM(AB45:AB50) -> 647.98055 | AC51: =SUM(AC45:AC50) -> 628.44699 | AD51: =SUM(Z51:AC51) -> 2482.132 | AE51: =SUM(AE45:AE50) -> 2803.4173 | AF51: =SUM(AF45:AF50) -> 2919.2989 | AG51: =SUM(AG45:AG50) -> 3107.5491
C53: GAAP EPS (Basic) | F53: =(F45)/F285 -> #DIV/0! | G53: =(G45)/G285 -> #DIV/0! | H53: =(H45)/H285 -> #DIV/0! | I53: =(I45)/I285 -> #DIV/0! | J53: =J45/J285 -> #DIV/0! | K53: =(K45)/K285 -> #DIV/0! | L53: =(L45)/L285 -> #DIV/0! | M53: =(M45)/M285 -> #DIV/0! | N53: =(N45)/N285 -> #DIV/0! | O53: =O45/O285 -> #DIV/0! | P53: =(P45)/P285 -> #DIV/0! | Q53: =(Q45)/Q285 -> #DIV/0! | R53: =(R45)/R285 -> #DIV/0! | S53: =(S45)/S285 -> #DIV/0! | T53: =T45/T285 -> #DIV/0! | U53: =(U45)/U285 -> #DIV/0! | V53: =(V45)/V285 -> #DIV/0! | W53: =(W45)/W285 -> #DIV/0! | X53: =X45/X285 -> 1.8168331 | Y53: =Y45/Y285 -> 8.3070312 | Z53: =Z45/Z285 -> 1.8295878 | AA53: =AA45/AA285 -> 2.0632264 | AB53: =AB45/AB285 -> 2.096841 | AC53: =AC45/AC285 -> 2.0336312 | AD53: =AD45/AD285 -> 8.0224396 | AE53: =AE45/AE285 -> 9.1119625 | ... AG53: =AG45/AG285 -> 10.293342
C54: GAAP EPS (Diluted) | F54: =(F45)/F287 -> #DIV/0! | G54: =(G45)/G287 -> #DIV/0! | H54: =(H45)/H287 -> #DIV/0! | I54: =(I45)/I287 -> #DIV/0! | J54: =J45/J287 -> #DIV/0! | K54: =(K45)/K287 -> #DIV/0! | L54: =(L45)/L287 -> #DIV/0! | M54: =(M45)/M287 -> #DIV/0! | N54: =(N45)/N287 -> #DIV/0! | O54: =O45/O287 -> #DIV/0! | P54: =(P45)/P287 -> #DIV/0! | Q54: =(Q45)/Q287 -> #DIV/0! | R54: =(R45)/R287 -> #DIV/0! | S54: =(S45)/S287 -> #DIV/0! | T54: =T45/T287 -> #DIV/0! | U54: =(U45)/U287 -> #DIV/0! | V54: =(V45)/V287 -> #DIV/0! | W54: =(W45)/W287 -> #DIV/0! | X54: =X45/X287 -> 1.8150878 | Y54: =Y45/Y287 -> 8.3010549 | Z54: =Z45/Z287 -> 1.8278218 | AA54: =AA45/AA287 -> 2.0612254 | AB54: =AB45/AB287 -> 2.0948074 | AC54: =AC45/AC287 -> 2.0316588 | AD54: =AD45/AD287 -> 8.0146684 | AE54: =AE45/AE287 -> 9.1030862 | ... AG54: =AG45/AG287 -> 10.283124
C56: Adj. EPS (Basic) | F56: =F51/F285 -> #DIV/0! | G56: =G51/G285 -> #DIV/0! | H56: =H51/H285 -> #DIV/0! | I56: =I51/I285 -> #DIV/0! | J56: =J51/J285 -> #DIV/0! | K56: =K51/K285 -> #DIV/0! | L56: =L51/L285 -> #DIV/0! | M56: =M51/M285 -> #DIV/0! | ... AG56: =AG51/AG285 -> 10.293342
C57: Adj. EPS (Diluted) | F57: =F51/F287 -> #DIV/0! | G57: =G51/G287 -> #DIV/0! | H57: =H51/H287 -> #DIV/0! | I57: =I51/I287 -> #DIV/0! | J57: =J51/J287 -> #DIV/0! | K57: =K51/K287 -> #DIV/0! | L57: =L51/L287 -> #DIV/0! | M57: =M51/M287 -> #DIV/0! | ... AG57: =AG51/AG287 -> 10.283124
C59: EBIT | F59: =F36 -> 644.1 | G59: =G36 -> 707.2 | H59: =H36 -> 727.8 | I59: =I36 -> 700.8 | J59: =J36 -> 2779.9 | K59: =K36 -> 733 | L59: =L36 -> 814 | M59: =M36 -> 846 | ... AG59: =AG36 -> 4540.3607
C60: Depreciation & Amortization | F60: =-F34 -> 358.7 | G60: =-G34 -> 358.3 | H60: =-H34 -> 382.3 | I60: =-I34 -> 401.6 | J60: =SUM(F60:I60) -> 1500.9 | K60: =-K34 -> 399 | L60: =-L34 -> 413 | M60: =-M34 -> 422 | N60: =-N34 -> 443 | O60: =SUM(K60:N60) -> 1677 | P60: =-P34 -> 434 | Q60: =-Q34 -> 463 | R60: =-R34 -> 459 | S60: =-S34 -> 458 | T60: =SUM(P60:S60) -> 1814 | U60: =-U34 -> 0 | V60: =-V34 -> 0 | W60: =-W34 -> 0 | X60: =-X34 -> 494.45254 | Y60: =SUM(U60:X60) -> 1850.4525 | Z60: =-Z34 -> 485.29601 | AA60: =-AA34 -> 485.93053 | AB60: =-AB34 -> 486.65054 | AC60: =-AC34 -> 487.72771 | AD60: =SUM(Z60:AC60) -> 1945.6048 | AE60: =-AE34 -> 1977.3332 | AF60: =-AF34 -> 2085.2579 | AG60: =-AG34 -> 2190.6618
C61: EBITDA | F61: =SUM(F59:F60) -> 1002.8 | G61: =SUM(G59:G60) -> 1065.5 | H61: =SUM(H59:H60) -> 1110.1 | I61: =SUM(I59:I60) -> 1102.4 | J61: =SUM(J59:J60) -> 4280.8 | K61: =SUM(K59:K60) -> 1132 | L61: =SUM(L59:L60) -> 1227 | M61: =SUM(M59:M60) -> 1268 | ... S61: =SUM(S59:S60) -> 1258 | T61: =SUM(P61:S61) -> 5115 | U61: =SUM(U59:U60) -> 4152.631 | V61: =SUM(V59:V60) -> 4379.486 | W61: =SUM(W59:W60) -> 4358.186 | X61: =SUM(X59:X60) -> 1388.4102 | Y61: =SUM(U61:X61) -> 5679.7132 | Z61: =SUM(Z59:Z60) -> 1372.9795 | AA61: =SUM(AA59:AA60) -> 1460.6845 | AB61: =SUM(AB59:AB60) -> 1468.2447 | AC61: =SUM(AC59:AC60) -> 1438.2119 | AD61: =SUM(Z61:AC61) -> 5740.1206 | AE61: =SUM(AE59:AE60) -> 6130.6467 | AF61: =SUM(AF59:AF60) -> 6402.24 | AG61: =SUM(AG59:AG60) -> 6731.0225
C62: EBITDA Adjustment | F62: =F249 -> 11.6 | G62: =G249 -> 9.8 | H62: =H249 -> 10.3 | I62: =I249 -> 9.3 | J62: =J249 -> 41 | K62: =K249 -> 11 | L62: =L249 -> 11 | M62: =M249 -> 9 | ... AG62: =AG249 -> 0
C63: Adj. EBITDA | F63: =SUM(F61:F62) -> 1014.4 | G63: =SUM(G61:G62) -> 1075.3 | H63: =SUM(H61:H62) -> 1120.4 | I63: =SUM(I61:I62) -> 1111.7 | J63: =SUM(J61:J62) -> 4321.8 | K63: =SUM(K61:K62) -> 1143 | L63: =SUM(L61:L62) -> 1238 | M63: =SUM(M61:M62) -> 1277 | ... AG63: =SUM(AG61:AG62) -> 6888.8151
C65: Income Statement Analysis | F65: =F$25 -> 0 | G65: =G$25 -> 0 | H65: =H$25 -> 0 | I65: =I$25 -> 0 | J65: =J$25 -> 2023 | K65: =K$25 -> 0 | L65: =L$25 -> 0 | M65: =M$25 -> 0 | ... AG65: =AG$25 -> 2030e | AH65: x
A66: x | C66: Drivers
C68: Gross Margin | F68: =F30/F28 -> 0.47687596 | G68: =G30/G28 -> 0.48525941 | H68: =H30/H28 -> 0.48251099 | I68: =I30/I28 -> 0.48479403 | J68: =J30/J28 -> 0.48242675 | K68: =K30/K28 -> 0.48569498 | L68: =L30/L28 -> 0.48895561 | M68: =M30/M28 -> 0.49423077 | ... W68: =W30/W28 -> 1 | X68: =IF(Cover!$F$37="Bottom Up",(X30/X28),Drivers!X7) -> 0.424 | Y68: =Y30/Y28 -> 0.85253306 | Z68: =IF(Cover!$F$37="Bottom Up",(Z30/Z28),Drivers!Z7) -> 0.428 | AA68: =IF(Cover!$F$37="Bottom Up",(AA30/AA28),Drivers!AA7) -> 0.425 | AB68: =IF(Cover!$F$37="Bottom Up",(AB30/AB28),Drivers!AB7) -> 0.428 | AC68: =IF(Cover!$F$37="Bottom Up",(AC30/AC28),Drivers!AC7) -> 0.428 | AD68: =AD30/AD28 -> 0.42723651 | AE68: =IF(Cover!$F$37="Bottom Up",(AE30/AE28),Drivers!AE7) -> 0.431 | AF68: =IF(Cover!$F$37="Bottom Up",(AF30/AF28),Drivers!AF7) -> 0.428 | AG68: =IF(Cover!$F$37="Bottom Up",(AG30/AG28),Drivers!AG7) -> 0.428
C69: SG&A as % of Revenue | F69: =F32/F28 -> -0.091435185 | G69: =G32/G28 -> -0.09163697 | H69: =H32/H28 -> -0.091092384 | I69: =I32/I28 -> -0.09819621 | J69: =J32/J28 -> -0.093118276 | K69: =K32/K28 -> -0.093264249 | L69: =L32/L28 -> -0.087282865 | M69: =M32/M28 -> -0.086752137 | ... W69: =W32/W28 -> 0 | X69: =Drivers!X40 -> -0.103 | Y69: =Y32/Y28 -> -0.026369957 | Z69: =Drivers!Z40 -> -0.106 | AA69: =Drivers!AA40 -> -0.1 | AB69: =Drivers!AB40 -> -0.1 | AC69: =Drivers!AC40 -> -0.103 | AD69: =AD32/AD28 -> -0.10220072 | AE69: =Drivers!AE40 -> -0.1 | AF69: =Drivers!AF40 -> -0.1 | AG69: =Drivers!AG40 -> -0.1
C70: R&D as a % of Revenue | F70: =F33/F28 -> 0 | G70: =G33/G28 -> 0 | H70: =H33/H28 -> 0 | I70: =I33/I28 -> 0 | J70: =J33/J28 -> 0 | K70: =K33/K28 -> 0 | L70: =L33/L28 -> 0 | M70: =M33/M28 -> 0 | ... W70: =W33/W28 -> 0 | X70: =Drivers!X45 -> 0 | Y70: =Y33/Y28 -> 0 | Z70: =Drivers!Z45 -> 0 | AA70: =Drivers!AA45 -> 0 | AB70: =Drivers!AB45 -> 0 | AC70: =Drivers!AC45 -> 0 | AD70: =AD33/AD28 -> 0 | AE70: =Drivers!AE45 -> 0 | AF70: =Drivers!AF45 -> 0 | AG70: =Drivers!AG45 -> 0
C71: Other Operating Income as a % of Revenue | F71: =F35/F28 -> -0.14363908 | G71: =G35/G28 -> -0.14705882 | H71: =H35/H28 -> -0.13993476 | I71: =I35/I28 -> -0.1358415 | J71: =J35/J28 -> -0.14156409 | K71: =K35/K28 -> -0.13741834 | L71: =L35/L28 -> -0.13853742 | M71: =M35/M28 -> -0.13653846 | ... W71: =W35/W28 -> 0 | X71: =Drivers!X50 -> -0.008 | Y71: =Y35/Y28 -> -0.002048152 | Z71: =Drivers!Z50 -> -0.007 | AA71: =Drivers!AA50 -> -0.007 | AB71: =Drivers!AB50 -> -0.007 | AC71: =Drivers!AC50 -> -0.007 | AD71: =AD35/AD28 -> -0.007 | AE71: =Drivers!AE50 -> -0.007 | AF71: =Drivers!AF50 -> -0.006 | AG71: =Drivers!AG50 -> -0.005
C72: Other Non-Operating Income as a % of Revenue | F72: =F41/F28 -> 0.00060281636 | G72: =G41/G28 -> -0.00013884389 | H72: =H41/H28 -> 0.0002945041 | I72: =I41/I28 -> 0.00086436321 | J72: =J41/J28 -> 0.00040511369 | K72: =K41/K28 -> 0.0029285875 | L72: =L41/L28 -> 0.00021445421 | M72: =M41/M28 -> 0.0021367521 | ... W72: =W41/W28 -> 0 | X72: =Drivers!X57 -> -0.012 | Y72: =Y41/Y28 -> -0.0030722279 | Z72: =Drivers!Z57 -> -0.011 | AA72: =Drivers!AA57 -> -0.011 | AB72: =Drivers!AB57 -> -0.011 | AC72: =Drivers!AC57 -> -0.011 | AD72: =AD41/AD28 -> -0.011 | AE72: =Drivers!AE57 -> -0.011 | AF72: =Drivers!AF57 -> -0.012 | AG72: =Drivers!AG57 -> -0.012
C73: Tax Rate | F73: =-F44/F42 -> 0.4076358 | G73: =-G44/G42 -> 0.39650099 | H73: =-H44/H42 -> 0.34322391 | I73: =-I44/I42 -> 0.37703231 | J73: =-J44/J42 -> 0.38021949 | K73: =-K44/K42 -> 0.39251138 | L73: =-L44/L42 -> 0.37311765 | M73: =-M44/M42 -> 0.34224535 | ... W73: =-W44/W42 -> 0 | X73: =Drivers!X64 -> 0.211 | Y73: =-Y44/Y42 -> 0.18430358 | Z73: =Drivers!Z64 -> 0.204 | AA73: =Drivers!AA64 -> 0.2042 | AB73: =Drivers!AB64 -> 0.2042 | AC73: =Drivers!AC64 -> 0.2042 | AD73: =-AD44/AD42 -> 0.20415423 | AE73: =Drivers!AE64 -> 0.202 | AF73: =Drivers!AF64 -> 0.202 | AG73: =Drivers!AG64 -> 0.202
A75: x | C75: Cash Flow Statement | F75: =F$65 -> 0 | G75: =G$65 -> 0 | H75: =H$65 -> 0 | I75: =I$65 -> 0 | J75: =J$65 -> 2023 | K75: =K$65 -> 0 | L75: =L$65 -> 0 | M75: =M$65 -> 0 | ... AG75: =AG$65 -> 2030e | AH75: x
C77: Net Income | U77: =U51 -> 4152.631 | V77: =V51 -> 4379.486 | W77: =W51 -> 4358.186 | X77: =X110 -> 566.85193 | Y77: =SUM(U77:X77) -> 2596.1549 | Z77: =Z45 -> 568.11173 | AA77: =AA45 -> 637.59271 | AB77: =AB45 -> 647.98055 | AC77: =AC45 -> 628.44699 | AD77: =SUM(Z77:AC77) -> 2482.132 | AE77: =AE45 -> 2803.4173 | AF77: =AF45 -> 2919.2989 | AG77: =AG45 -> 3107.5491
C78: Depreciation & Amortization | X78: =-(X197+X211) -> 494.45254 | Y78: =SUM(U78:X78) -> 494.45254 | Z78: =-(Z197+Z211) -> 485.29601 | AA78: =-(AA197+AA211) -> 485.93053 | AB78: =-(AB197+AB211) -> 486.65054 | AC78: =-(AC197+AC211) -> 487.72771 | AD78: =SUM(Z78:AC78) -> 1945.6048 | AE78: =-(AE197+AE211) -> 1977.3332 | AF78: =-(AF197+AF211) -> 2085.2579 | AG78: =-(AG197+AG211) -> 2190.6618
C79: Stock-Based Compensation | X79: =X249 -> 0 | Y79: =SUM(U79:X79) -> 0 | Z79: =Z249 -> 0 | AA79: =AA249 -> 0 | AB79: =AB249 -> 0 | AC79: =AC249 -> 0 | AD79: =SUM(Z79:AC79) -> 0 | AE79: =AE249 -> 0 | AF79: =AF249 -> 0 | AG79: =AG249 -> 0
C80: (Increase)/Decrease in Working Capital | X80: =X177 -> 1792.3934 | Y80: =SUM(U80:X80) -> 1792.3934 | Z80: =Z177 -> 125.09123 | AA80: =AA177 -> 162.83234 | AB80: =AB177 -> -55.24978 | AC80: =AC177 -> -61.348404 | AD80: =SUM(Z80:AC80) -> 171.32539 | AE80: =AE177 -> 29.902063 | AF80: =AF177 -> 143.65414 | AG80: =AG177 -> 102.80147
C81: (Increase)/Decrease in LT Items | X81: =X231 -> -102.8 | Y81: =SUM(U81:X81) -> -102.8 | Z81: =Z231 -> 0 | AA81: =AA231 -> 0 | AB81: =AB231 -> 0 | AC81: =AC231 -> 0 | AD81: =SUM(Z81:AC81) -> 0 | AE81: =AE231 -> 0 | AF81: =AF231 -> 0 | AG81: =AG231 -> 0
C82: Net Cash From Operating Activities | X82: =SUM(X77:X81) -> 794.43572 | Y82: =SUM(U82:X82) -> 794.43572 | Z82: =SUM(Z77:Z81) -> 1126.0524 | AA82: =SUM(AA77:AA81) -> 1231.9262 | AB82: =SUM(AB77:AB81) -> 1020.88 | AC82: =SUM(AC77:AC81) -> 991.83863 | AD82: =SUM(Z82:AC82) -> 4370.6972 | AE82: =SUM(AE77:AE81) -> 4797.0459 | AF82: =SUM(AF77:AF81) -> 5133.6768 | AG82: =SUM(AG77:AG81) -> 5374.7717
C84: Capital Expenditures | X84: =-X196 -> -527.86204 | Y84: =SUM(U84:X84) -> -527.86204 | Z84: =(-Z196) -> -483.81183 | AA84: =-(AA196) -> -523.64162 | AB84: =(AB196)*-1 -> -503.13682 | AC84: =(AC196)*-1 -> -529.15342 | AD84: =(SUM(Z84:AC84)) -> -2039.7437 | AE84: =(-AE196) -> -2054.902 | AF84: =(-AF196) -> -2115.5228 | AG84: =(-AG196) -> -2229.7814
C85: Purchases of Intangibles | X85: =-X210 -> 0 | Y85: =SUM(U85:X85) -> 0 | Z85: =-Z210 -> 0 | AA85: =-AA210 -> 0 | AB85: =-AB210 -> 0 | AC85: =-AC210 -> 0 | AD85: =SUM(Z85:AC85) -> 0 | AE85: =-AE210 -> 0 | AF85: =-AF210 -> 0 | AG85: =-AG210 -> 0
C86: Proceeds From/(Acquisitions of) Businesses | X86: =Drivers!X97 -> 0 | Y86: =SUM(U86:X86) -> 0 | Z86: =Drivers!Z97 -> 0 | AA86: =Drivers!AA97 -> 0 | AB86: =Drivers!AB97 -> 0 | AC86: =Drivers!AC97 -> 0 | AD86: =SUM(Z86:AC86) -> 0 | AE86: =Drivers!AE97 -> 0 | AF86: =Drivers!AF97 -> 0 | AG86: =Drivers!AG97 -> 0
C87: Net Cash From Investment Activities | X87: =SUM(X84:X86) -> -527.86204 | Y87: =SUM(U87:X87) -> -527.86204 | Z87: =SUM(Z84:Z86) -> -483.81183 | AA87: =SUM(AA84:AA86) -> -523.64162 | AB87: =SUM(AB84:AB86) -> -503.13682 | AC87: =SUM(AC84:AC86) -> -529.15342 | AD87: =SUM(Z87:AC87) -> -2039.7437 | AE87: =SUM(AE84:AE86) -> -2054.902 | AF87: =SUM(AF84:AF86) -> -2115.5228 | AG87: =SUM(AG84:AG86) -> -2229.7814
C89: Cash Flow Available for Financing Activities | X89: =SUM(X82,X87) -> 266.57368 | Y89: =SUM(U89:X89) -> 266.57368 | Z89: =SUM(Z82,Z87) -> 642.24056 | AA89: =SUM(AA82,AA87) -> 708.28459 | AB89: =SUM(AB82,AB87) -> 517.74315 | AC89: =SUM(AC82,AC87) -> 462.68521 | AD89: =SUM(Z89:AC89) -> 2330.9535 | AE89: =SUM(AE82,AE87) -> 2742.144 | AF89: =SUM(AF82,AF87) -> 3018.1541 | AG89: =SUM(AG82,AG87) -> 3144.9903
C91: Issuance/(Repayment) of Revolver | X91: =X306 -> 144.75856 | Y91: =SUM(U91:X91) -> 144.75856 | Z91: =Z306 -> 105.84489 | AA91: =AA306 -> 293.00155 | AB91: =AB306 -> 680.40204 | AC91: =AC306 -> 892.34028 | AD91: =SUM(Z91:AC91) -> 1971.5888 | AE91: =AE306 -> 193.74794 | AF91: =AF306 -> 605.67715 | AG91: =AG306 -> 764.89932
C92: Issuance of Debt | X92: =X311 -> 250 | Y92: =SUM(U92:X92) -> 250 | Z92: =Z311 -> 600 | AA92: =AA311 -> 0 | AB92: =AB311 -> 0 | AC92: =AC311 -> 0 | AD92: =SUM(Z92:AC92) -> 600 | AE92: =AE311 -> 600 | AF92: =AF311 -> 0 | AG92: =AG311 -> 0
C93: (Repayment of Debt) | X93: =X312 -> 0 | Y93: =SUM(U93:X93) -> 0 | Z93: =Z312 -> -600 | AA93: =AA312 -> -600 | AB93: =AB312 -> -600 | AC93: =AC312 -> -600 | AD93: =SUM(Z93:AC93) -> -2400 | AE93: =AE312 -> -600 | AF93: =AF312 -> -600 | AG93: =AG312 -> -600
C94: Issuance of Equity | X94: =X248 -> 0 | Y94: =SUM(U94:X94) -> 0 | Z94: =Z248 -> 0 | AA94: =AA248 -> 0 | AB94: =AB248 -> 0 | AC94: =AC248 -> 0 | AD94: =SUM(Z94:AC94) -> 0 | AE94: =AE248 -> 0 | AF94: =AF248 -> 0 | AG94: =AG248 -> 0
C95: (Repurchase) of Equity | X95: =-X244 -> 0 | Y95: =SUM(U95:X95) -> 0 | Z95: =-Z244 -> -550 | AA95: =-AA244 -> 0 | AB95: =-AB244 -> 0 | AC95: =-AC244 -> 0 | AD95: =SUM(Z95:AC95) -> -550 | AE95: =-AE244 -> -600 | AF95: =-AF244 -> -650 | AG95: =-AG244 -> -700
C96: Dividends Issued | X96: =-X270 -> 0 | Y96: =SUM(U96:X96) -> 0 | Z96: =-Z270 -> 0 | AA96: =-AA270 -> 0 | AB96: =-AB270 -> 0 | AC96: =-AC270 -> 0 | AD96: =SUM(Z96:AC96) -> 0 | AE96: =-AE270 -> 0 | AF96: =-AF270 -> 0 | AG96: =-AG270 -> 0
C97: Change in Noncontrolling Interests | X97: =Drivers!X106 -> 0 | Y97: =SUM(U97:X97) -> 0 | Z97: =Drivers!Z106 -> 0 | AA97: =Drivers!AA106 -> 0 | AB97: =Drivers!AB106 -> 0 | AC97: =Drivers!AC106 -> 0 | AD97: =SUM(Z97:AC97) -> 0 | AE97: =Drivers!AE106 -> 0 | AF97: =Drivers!AF106 -> 0 | AG97: =Drivers!AG106 -> 0
C98: Net Cash From Financing Activities | X98: =SUM(X91:X97) -> -292.24144 | Y98: =SUM(U98:X98) -> -292.24144 | Z98: =SUM(Z91:Z97) -> -643.25511 | AA98: =SUM(AA91:AA97) -> -705.19845 | AB98: =SUM(AB91:AB97) -> -517.99796 | AC98: =SUM(AC91:AC97) -> -463.35972 | AD98: =SUM(Z98:AC98) -> -2329.8112 | AE98: =SUM(AE91:AE97) -> -2552.7921 | AF98: =SUM(AF91:AF97) -> -3005.5169 | AG98: =SUM(AG91:AG97) -> -3132.4141
C100: Effect of FX Rate Changes on Cash | X100: =Drivers!X108 -> 0 | Y100: =SUM(U100:X100) -> 0 | Z100: =Drivers!Z108 -> 0 | AA100: =Drivers!AA108 -> 0 | AB100: =Drivers!AB108 -> 0 | AC100: =Drivers!AC108 -> 0 | AD100: =SUM(Z100:AC100) -> 0 | AE100: =Drivers!AE108 -> 0 | AF100: =Drivers!AF108 -> 0 | AG100: =Drivers!AG108 -> 0
C101: Beginning Cash Adjustments | X101: 0 | Y101: =SUM(U101:X101) -> 0 | Z101: 0 | AA101: 0 | AB101: 0 | AC101: 0 | AD101: =SUM(Z101:AC101) -> 0 | AE101: 0 | AF101: 0 | AG101: 0
C102: Ending Cash Adjustments | X102: 0 | Y102: =SUM(U102:X102) -> 0 | Z102: 0 | AA102: 0 | AB102: 0 | AC102: 0 | AD102: =SUM(Z102:AC102) -> 0 | AE102: 0 | AF102: 0 | AG102: 0
C104: Beginning Cash Balance | X104: =W123 -> 0 | Z104: =X106 -> 58.332248 | AA104: =Z106+AA101 -> 57.317699 | AB104: =AA106+AB101 -> 60.40384 | AC104: =AB106+AC101 -> 60.149034 | AD104: =Z104 -> 58.332248 | AE104: =AD106+AE101 -> 59.474526 | AF104: =AE106+AF101 -> 248.82644 | AG104: =AF106+AG101 -> 261.46365
C105: Net Change in Cash | X105: =SUM(X89,X98,X100,X102) -> -25.667752 | Y105: =SUM(U105:X105) -> -25.667752 | Z105: =SUM(Z89,Z98,Z100,Z102) -> -1.0145483 | AA105: =SUM(AA89,AA98,AA100,AA102) -> 3.086141 | AB105: =SUM(AB89,AB98,AB100,AB102) -> -0.2548061 | AC105: =SUM(AC89,AC98,AC100,AC102) -> -0.67450806 | AD105: =SUM(Z105:AC105) -> 1.1422785 | AE105: =SUM(AE89,AE98,AE100,AE102) -> 189.35191 | AF105: =SUM(AF89,AF98,AF100,AF102) -> 12.637212 | AG105: =SUM(AG89,AG98,AG100,AG102) -> 12.576223
C106: Ending Cash Balance | X106: =SUM(X104:X105) -> 58.332248 | Y106: =X106 -> 58.332248 | Z106: =SUM(Z104:Z105) -> 57.317699 | AA106: =SUM(AA104:AA105) -> 60.40384 | AB106: =SUM(AB104:AB105) -> 60.149034 | AC106: =SUM(AC104:AC105) -> 59.474526 | AD106: =SUM(AD104:AD105) -> 59.474526 | AE106: =SUM(AE104:AE105) -> 248.82644 | AF106: =SUM(AF104:AF105) -> 261.46365 | AG106: =SUM(AG104:AG105) -> 274.03987
A108: x | C108: Free Cash Flow Analysis | AH108: x
C110: Net Income | F110: =F45 -> 383.852 | G110: =G45 -> 427.398 | H110: =H45 -> 480.169 | I110: =I45 -> 439.566 | J110: =J45 -> 1730.985 | K110: =K45 -> 453.794 | L110: =L45 -> 511.536 | M110: =M45 -> 565.669 | ... AG110: =AG45 -> 3107.5491
C111: Stock Based-Compensation | F111: =F249 -> 11.6 | G111: =G249 -> 9.8 | H111: =H249 -> 10.3 | I111: =I249 -> 9.3 | K111: =K249 -> 11 | L111: =L249 -> 11 | M111: =M249 -> 9 | N111: =N249 -> 11 | P111: =P249 -> 13 | Q111: =Q249 -> 10 | R111: =R249 -> 10 | S111: =S249 -> 0 | U111: =U249 -> 0 | V111: =V249 -> 0 | W111: =W249 -> 0 | X111: =X249 -> 0 | Y111: =Y79 -> 0 | Z111: =Z249 -> 0 | AA111: =AA249 -> 0 | AB111: =AB249 -> 0 | AC111: =AC249 -> 0 | AD111: =AD79 -> 0 | AE111: =AE249 -> 0 | AF111: =AF249 -> 0 | AG111: =AG249 -> 0
C112: Depreciation & Amortization | F112: =-F197+F211 -> -15.1 | G112: =-G197+G211 -> -15 | H112: =-H197+H211 -> -17.3 | I112: =-I197+I211 -> -18.6 | J112: =SUM(F112:I112) -> -66 | K112: =-K197+K211 -> -17.8 | L112: =-L197+L211 -> -18.7 | M112: =-M197+M211 -> -17.8 | N112: =-N197+N211 -> -24.7 | O112: =SUM(K112:N112) -> -79 | P112: =-P197+P211 -> -21 | Q112: =-Q197+Q211 -> -22 | R112: =-R197+R211 -> -22 | S112: =-S197+S211 -> -24 | T112: =SUM(P112:S112) -> -89 | U112: =-U197+U211 -> 0 | V112: =-V197+V211 -> 0 | W112: =-W197+W211 -> 0 | X112: =-X197+X211 -> 494.45254 | Y112: =SUM(U112:X112) -> 1840.7525 | Z112: =-Z197+Z211 -> 485.29601 | AA112: =-AA197+AA211 -> 485.93053 | AB112: =-AB197+AB211 -> 486.65054 | AC112: =-AC197+AC211 -> 487.72771 | AD112: =SUM(Z112:AC112) -> 1945.6048 | AE112: =-AE197+AE211 -> 1977.3332 | AF112: =-AF197+AF211 -> 2085.2579 | AG112: =-AG197+AG211 -> 2190.6618
C113: Change in Operating Working Capital | F113: =F181 -> -800.1 | G113: =G181 -> 62.4 | H113: =H181 -> 6.2 | I113: =I181 -> 277.5 | J113: =SUM(F113:I113) -> -454 | K113: =K181 -> -231.2 | L113: =L181 -> 53 | M113: =M181 -> -87.6 | N113: =N181 -> 145.8 | O113: =SUM(K113:N113) -> -120 | P113: =P181 -> -228 | Q113: =Q181 -> 17 | R113: =R181 -> 29 | S113: =S181 -> 127 | T113: =SUM(P113:S113) -> -55 | U113: =U181 -> 0 | V113: =V181 -> 0 | W113: =W181 -> 0 | X113: =X181 -> -710.11619 | Y113: =SUM(U113:X113) -> -710.11619 | Z113: =Z181 -> 79.211385 | AA113: =AA181 -> 9.4147879 | AB113: =AB181 -> -27.715573 | AC113: =AC181 -> -31.359251 | AD113: =SUM(Z113:AC113) -> 29.551349 | AE113: =AE181 -> -74.879511 | AF113: =AF181 -> -13.499912 | AG113: =AG181 -> -36.985694
C114: Capital Expenditures | F114: =F196 -> 378.6 | G114: =G196 -> 714.3 | H114: =H196 -> 1083.2 | I114: =I196 -> 1631.1 | J114: =SUM(F114:I114) -> 3807.2 | K114: =K196 -> 0 | L114: =L196 -> 0 | M114: =M196 -> 0 | N114: =N196 -> 0 | O114: =SUM(K114:N114) -> 0 | P114: =P196 -> 0 | Q114: =Q196 -> 0 | R114: =R196 -> 0 | S114: =S196 -> 0 | T114: =SUM(P114:S114) -> 0 | U114: =U196 -> 0 | V114: =V196 -> 0 | W114: =W196 -> 0 | X114: =X196 -> 527.86204 | Y114: =SUM(U114:X114) -> 527.86204 | Z114: =Z196 -> 483.81183 | AA114: =AA196 -> 523.64162 | AB114: =AB196 -> 503.13682 | AC114: =AC196 -> 529.15342 | AD114: =SUM(Z114:AC114) -> 2039.7437 | AE114: =AE196 -> 2054.902 | AF114: =AF196 -> 2115.5228 | AG114: =AG196 -> 2229.7814
C115: Free Cash Flow (FCF) | F115: =SUM(F110:F114) -> -41.148 | G115: =SUM(G110:G114) -> 1198.898 | H115: =SUM(H110:H114) -> 1562.569 | I115: =SUM(I110:I114) -> 2338.866 | J115: =SUM(J110:J114) -> 5018.185 | K115: =SUM(K110:K114) -> 215.794 | L115: =SUM(L110:L114) -> 556.836 | M115: =SUM(M110:M114) -> 469.269 | ... AG115: =SUM(AG110:AG114) -> 7648.7992
C117: Free Cash Flow Margin | F117: =F115/F28 -> -0.009921875 | G117: =G115/G28 -> 0.27743278 | H117: =H115/H28 -> 0.35398691 | I117: =I115/I28 -> 0.53200782 | J117: =J115/J28 -> 0.29041935 | K117: =K115/K28 -> 0.048613201 | L117: =L115/L28 -> 0.11941583 | M117: =M115/M28 -> 0.10027115 | ... AG117: =AG115/AG28 -> 0.36704114
C118: Free Cash Flow per Share | F118: =F115/F285 -> #DIV/0! | G118: =G115/G285 -> #DIV/0! | H118: =H115/H285 -> #DIV/0! | I118: =I115/I285 -> #DIV/0! | J118: =J115/J285 -> #DIV/0! | K118: =K115/K285 -> #DIV/0! | L118: =L115/L285 -> #DIV/0! | M118: =M115/M285 -> #DIV/0! | ... AG118: =AG115/AG285 -> 25.335629
C119: Free Cash Flow Yield | F119: =F118*4/F242 -> #DIV/0! | G119: =G118*4/G242 -> #DIV/0! | H119: =H118*4/H242 -> #DIV/0! | I119: =I118*4/I242 -> #DIV/0! | J119: =J118/J242 -> #DIV/0! | K119: =K118*4/K242 -> #DIV/0! | L119: =L118*4/L242 -> #DIV/0! | M119: =M118*4/M242 -> #DIV/0! | N119: =N118*4/N242 -> #DIV/0! | O119: =O118/O242 -> #DIV/0! | P119: =P118*4/P242 -> #DIV/0! | Q119: =Q118*4/Q242 -> #DIV/0! | R119: =R118*4/R242 -> #DIV/0! | S119: =S118*4/S242 -> #DIV/0! | T119: =T118/T242 -> #DIV/0! | U119: =U118*4/U242 -> #DIV/0! | V119: =V118*4/V242 -> #DIV/0! | W119: =W118*4/W242 -> #DIV/0! | X119: =X118*4/X242 -> 0.097178812 | Y119: =Y118/Y242 -> 0.11555617 | Z119: =Z118*4/Z242 -> 0.11485314 | AA119: =AA118*4/AA242 -> 0.11522482 | AB119: =AB118*4/AB242 -> 0.10917218 | AC119: =AC118*4/AC242 -> 0.10667121 | AD119: =AD118/AD242 -> 0.10720305 | AE119: =AE118/AE242 -> 0.1020012 | AF119: =AF118/AF242 -> 0.10821695 | AG119: =AG118/AG242 -> 0.10469268
A121: x | C121: Balance Sheet | F121: =F$65 -> 0 | G121: =G$65 -> 0 | H121: =H$65 -> 0 | I121: =I$65 -> 0 | J121: =J$65 -> 2023 | K121: =K$65 -> 0 | L121: =L$65 -> 0 | M121: =M$65 -> 0 | ... AG121: =AG$65 -> 2030e | AH121: x
C123: Cash & Cash Equivalents | F123: 132.2 | G123: 181.6 | H123: 157.5 | I123: 140 | J123: =I123 -> 140 | K123: 92 | L123: 491 | M123: 83 | N123: 74 | O123: =N123 -> 74 | P123: 83 | Q123: 122 | R123: 84 | S123: 76 | T123: =S123 -> 76 | X123: =X106 -> 58.332248 | Y123: =X123 -> 58.332248 | Z123: =Z106 -> 57.317699 | AA123: =AA106 -> 60.40384 | AB123: =AB106 -> 60.149034 | AC123: =AC106 -> 59.474526 | AD123: =AC123 -> 59.474526 | AE123: =AE106 -> 248.82644 | AF123: =AF106 -> 261.46365 | AG123: =AG106 -> 274.03987
C124: Accounts Receivable | F124: 1686.4 | G124: 1740 | H124: 1829.7 | I124: 1768 | J124: =I124 -> 1768 | K124: 1763 | L124: 1817.8 | M124: 1847.5 | N124: 1821 | O124: =N124 -> 1821 | P124: 1854 | Q124: 1880 | R124: 1900 | S124: 1897 | T124: =S124 -> 1897 | X124: =X165 -> 2015.4031 | Y124: =X124 -> 2015.4031 | Z124: =Z165 -> 1973.3737 | AA124: =AA165 -> 2029.1491 | AB124: =AB165 -> 2028.4567 | AC124: =AC165 -> 2030.2895 | AD124: =AC124 -> 2030.2895 | AE124: =AE165 -> 2156.561 | AF124: =AF165 -> 2233.4029 | AG124: =AG165 -> 2340.828
C125: Inventory | F125: 97.9 | G125: 96.1 | H125: 100 | I125: 98 | J125: =I125 -> 98 | K125: 101.4 | L125: 99.9 | M125: 97.7 | N125: 98 | O125: =N125 -> 98 | P125: 102 | Q125: 104 | R125: 103 | S125: 106 | T125: =S125 -> 106 | X125: =X166 -> 0 | Y125: =X125 -> 0 | Z125: =Z166 -> 0 | AA125: =AA166 -> 0 | AB125: =AB166 -> 0 | AC125: =AC166 -> 0 | AD125: =AC125 -> 0 | AE125: =AE166 -> 0 | AF125: =AF166 -> 0 | AG125: =AG166 -> 0
C126: Prepaid & Other Current Assets | F126: 324.9 | G126: 244 | H126: 261.2 | I126: 375 | J126: =I126 -> 375 | K126: 317.2 | L126: 251 | M126: 320.2 | N126: 413 | O126: =N126 -> 413 | P126: 282 | Q126: 310 | R126: 397 | S126: 444 | T126: =S126 -> 444 | X126: =X167 -> 461.32481 | Y126: =X126 -> 461.32481 | Z126: =Z167 -> 383.56253 | AA126: =AA167 -> 404.21459 | AB126: =AB167 -> 402.50946 | AC126: =AC167 -> 397.99574 | AD126: =AC126 -> 397.99574 | AE126: =AE167 -> 416.27848 | AF126: =AF167 -> 437.42012 | AG126: =AG167 -> 458.45973
C127: Total Current Assets | F127: =SUM(F123:F126) -> 2241.4 | G127: =SUM(G123:G126) -> 2261.7 | H127: =SUM(H123:H126) -> 2348.4 | I127: =SUM(I123:I126) -> 2381 | J127: =I127 -> 2381 | K127: =SUM(K123:K126) -> 2273.6 | L127: =SUM(L123:L126) -> 2659.7 | M127: =SUM(M123:M126) -> 2348.4 | N127: =SUM(N123:N126) -> 2406 | O127: =N127 -> 2406 | P127: =SUM(P123:P126) -> 2321 | Q127: =SUM(Q123:Q126) -> 2416 | R127: =SUM(R123:R126) -> 2484 | S127: =SUM(S123:S126) -> 2523 | T127: =S127 -> 2523 | U127: =SUM(U123:U126) -> 0 | V127: =SUM(V123:V126) -> 0 | W127: =SUM(W123:W126) -> 0 | X127: =SUM(X123:X126) -> 2535.0602 | Y127: =X127 -> 2535.0602 | Z127: =SUM(Z123:Z126) -> 2414.2539 | AA127: =SUM(AA123:AA126) -> 2493.7676 | AB127: =SUM(AB123:AB126) -> 2491.1152 | AC127: =SUM(AC123:AC126) -> 2487.7598 | AD127: =AC127 -> 2487.7598 | AE127: =SUM(AE123:AE126) -> 2821.6659 | AF127: =SUM(AF123:AF126) -> 2932.2867 | AG127: =SUM(AG123:AG126) -> 3073.3276
...

Sheet Segment Analysis
A1: a | C1: =Company_Name&" - "&MID(CELL("filename",A1),FIND("]",CELL("filename",A1))+1,255)&": "&Case_Scenario&" Case" -> Republic Services, Inc. - Segment Analysis: Base Case
C2: =Cover!C2 -> $ in Millions Except Per Share Data
C5: Segment Analysis | F5: =Model!F65 -> 0 | G5: =Model!G65 -> 0 | H5: =Model!H65 -> 0 | I5: =Model!I65 -> 0 | J5: =Model!J65 -> 2023 | K5: =Model!K65 -> 0 | L5: =Model!L65 -> 0 | M5: =Model!M65 -> 0 | ... W5: =Model!W65 -> 3Q26 | X5: 4Q26e | Y5: =Model!Y65 -> 2026e | Z5: =Model!Z65 -> 1Q27e | AA5: =Model!AA65 -> 2Q27e | AB5: =Model!AB65 -> 3Q27e | AC5: =Model!AC65 -> 4Q27e | AD5: =Model!AD65 -> 2027e | AE5: =Model!AE65 -> 2028e | AF5: =Model!AF65 -> 2029e | AG5: =Model!AG65 -> 2030e
C6: Drivers
C8: Total Company Revenue | F8: =SUM(F9:F14) -> 4147.2 | G8: =SUM(G9:G14) -> 4321.4 | H8: =SUM(H9:H14) -> 4414.2 | I8: =SUM(I9:I14) -> 4396.3 | J8: =SUM(F8:I8) -> 17279.1 | K8: =SUM(K9:K14) -> 4439 | L8: =SUM(L9:L14) -> 4663 | M8: =SUM(M9:M14) -> 4680 | N8: =SUM(N9:N14) -> 4634 | O8: =SUM(K8:N8) -> 18416 | P8: =SUM(P9:P14) -> 4593 | Q8: =SUM(Q9:Q14) -> 4882 | R8: =SUM(R9:R14) -> 4827 | S8: =SUM(S9:S14) -> 4727 | T8: =SUM(P8:S8) -> 19029 | U8: =SUM(U9:U14) -> 4152.631 | V8: =SUM(V9:V14) -> 4379.486 | W8: =SUM(W9:W14) -> 4358.186 | X8: 4435.8154 | Y8: =SUM(U8:X8) -> 17326.118 | Z8: =SUM(Z9:Z14) -> 4358.6652 | AA8: =SUM(AA9:AA14) -> 4593.3476 | AB8: =SUM(AB9:AB14) -> 4573.9711 | AC8: =SUM(AC9:AC14) -> 4522.6788 | AD8: =SUM(Z8:AC8) -> 18048.663 | AE8: =SUM(AE9:AE14) -> 18921.749 | AF8: =SUM(AF9:AF14) -> 19882.733 | AG8: =SUM(AG9:AG14) -> 20839.079
C9: =C17&" Revenue" -> Collection Revenue | F9: 0 | G9: 0 | H9: 0 | I9: 0 | J9: =SUM(F9:I9) -> 0 | K9: 0 | L9: 0 | M9: 0 | N9: 0 | O9: =SUM(K9:N9) -> 0 | P9: 0 | Q9: 0 | R9: 0 | S9: 0 | T9: =SUM(P9:S9) -> 0 | U9: ='Revenue Build'!U32 -> 2841.748 | V9: ='Revenue Build'!V32 -> 2932.058 | W9: ='Revenue Build'!W32 -> 2945.565 | X9: 3027.6708 | Y9: =SUM(U9:X9) -> 11747.042 | Z9: ='Revenue Build'!Z32 -> 2983.8354 | AA9: ='Revenue Build'!AA32 -> 3075.7288 | AB9: ='Revenue Build'!AB32 -> 3095.7888 | AC9: ='Revenue Build'!AC32 -> 3105.5148 | AD9: =SUM(Z9:AC9) -> 12260.868 | AE9: ='Revenue Build'!AE32 -> 12849.389 | AF9: ='Revenue Build'!AF32 -> 13504.708 | AG9: ='Revenue Build'!AG32 -> 14098.916
C10: =C18&" Revenue" -> Landfill Revenue | F10: 392.6 | G10: 431 | H10: 436.3 | I10: 419.5 | J10: =SUM(F10:I10) -> 1679.4 | K10: 404.4 | L10: 440.2 | M10: 452.8 | N10: 443.6 | O10: =SUM(K10:N10) -> 1741 | P10: 421 | Q10: 516 | R10: 516 | S10: 467 | T10: =SUM(P10:S10) -> 1920 | U10: ='Revenue Build'!U35 -> 439.103 | V10: ='Revenue Build'!V35 -> 519.612 | W10: ='Revenue Build'!W35 -> 520.644 | X10: 498.88345 | Y10: =SUM(U10:X10) -> 1978.2425 | Z10: ='Revenue Build'!Z35 -> 459.74084 | AA10: ='Revenue Build'!AA35 -> 546.63182 | AB10: ='Revenue Build'!AB35 -> 545.63491 | AC10: ='Revenue Build'!AC35 -> 510.9517 | AD10: =SUM(Z10:AC10) -> 2062.9593 | AE10: ='Revenue Build'!AE35 -> 2180.548 | AF10: ='Revenue Build'!AF35 -> 2302.6586 | AG10: ='Revenue Build'!AG35 -> 2427.0022
C11: =C19&" Revenue" -> Environmental solutions Revenue | F11: 408.3 | G11: 398.3 | H11: 404.8 | I11: 413.5 | J11: =SUM(F11:I11) -> 1624.9 | K11: 423.3 | L11: 472.6 | M11: 464.7 | N11: 482.4 | O11: =SUM(K11:N11) -> 1843 | P11: 449 | Q11: 462 | R11: 433 | S11: 422 | T11: =SUM(P11:S11) -> 1766 | U11: ='Revenue Build'!U38 -> 463.368 | V11: ='Revenue Build'!V38 -> 478.17 | W11: ='Revenue Build'!W38 -> 449.021 | X11: 486.7477 | Y11: =SUM(U11:X11) -> 1877.3067 | Z11: ='Revenue Build'!Z38 -> 489.31661 | AA11: ='Revenue Build'!AA38 -> 502.55667 | AB11: ='Revenue Build'!AB38 -> 471.02303 | AC11: ='Revenue Build'!AC38 -> 463.92654 | AD11: =SUM(Z11:AC11) -> 1926.8229 | AE11: ='Revenue Build'!AE38 -> 2025.0908 | AF11: ='Revenue Build'!AF38 -> 2138.4959 | AG11: ='Revenue Build'!AG38 -> 2288.1906
C12: =C20&" Revenue" -> Transfer Revenue | F12: 173.3 | G12: 197.3 | H12: 206.2 | I12: 188.6 | J12: =SUM(F12:I12) -> 765.4 | K12: 182.8 | L12: 208.2 | M12: 211.6 | N12: 202.4 | O12: =SUM(K12:N12) -> 805 | P12: 188 | Q12: 221 | R12: 224 | S12: 215 | T12: =SUM(P12:S12) -> 848 | U12: ='Revenue Build'!U41 -> 196.46 | V12: ='Revenue Build'!V41 -> 230.724 | W12: ='Revenue Build'!W41 -> 233.856 | X12: 223.57608 | Y12: =SUM(U12:X12) -> 884.61608 | Z12: ='Revenue Build'!Z41 -> 207.46176 | AA12: ='Revenue Build'!AA41 -> 242.72165 | AB12: ='Revenue Build'!AB41 -> 245.31494 | AC12: ='Revenue Build'!AC41 -> 235.48581 | AD12: =SUM(Z12:AC12) -> 930.98417 | AE12: ='Revenue Build'!AE41 -> 971.94747 | AF12: ='Revenue Build'!AF41 -> 1021.5168 | AG12: ='Revenue Build'!AG41 -> 1050.1193
C13: =C21&" Revenue" -> Other Revenue | F13: 3173 | G13: 3294.8 | H13: 3366.9 | I13: 3374.7 | J13: =SUM(F13:I13) -> 13209.4 | K13: 3428.5 | L13: 3542 | M13: 3550.9 | N13: 3505.6 | O13: =SUM(K13:N13) -> 14027 | P13: 3535 | Q13: 3683 | R13: 3654 | S13: 3623 | T13: =SUM(P13:S13) -> 14495 | U13: ='Revenue Build'!U44 -> 211.952 | V13: ='Revenue Build'!V44 -> 218.922 | W13: ='Revenue Build'!W44 -> 209.1 | X13: 198.93741 | Y13: =SUM(U13:X13) -> 838.91141 | Z13: ='Revenue Build'!Z44 -> 218.31056 | AA13: ='Revenue Build'!AA44 -> 225.70858 | AB13: ='Revenue Build'!AB44 -> 216.2094 | AC13: ='Revenue Build'!AC44 -> 206.8 | AD13: =SUM(Z13:AC13) -> 867.02854 | AE13: ='Revenue Build'!AE44 -> 894.77346 | AF13: ='Revenue Build'!AF44 -> 915.35324 | AG13: ='Revenue Build'!AG44 -> 974.85121
C14: =C22&" Revenue" -> Professional Services and Other Revenue | F14: 0 | G14: 0 | H14: 0 | I14: 0 | K14: 0 | L14: 0 | M14: 0 | N14: 0 | P14: 0 | Q14: 0 | R14: 0 | S14: 0 | U14: ='Revenue Build'!U47 -> 0 | V14: ='Revenue Build'!V47 -> 0 | W14: ='Revenue Build'!W47 -> 0 | X14: 0 | Y14: =SUM(U14:X14) -> 0 | Z14: ='Revenue Build'!Z47 -> 0 | AA14: ='Revenue Build'!AA47 -> 0 | AB14: ='Revenue Build'!AB47 -> 0 | AC14: ='Revenue Build'!AC47 -> 0 | AD14: =SUM(Z14:AC14) -> 0 | AE14: ='Revenue Build'!AE47 -> 0 | AF14: ='Revenue Build'!AF47 -> 0 | AG14: ='Revenue Build'!AG47 -> 0
C16: Revenue Mix
C17: Collection | F17: =IFERROR(F9/F$8,"N/A") -> 0.68649298 | G17: =IFERROR(G9/G$8,"N/A") -> 0.68251966 | H17: =IFERROR(H9/H$8,"N/A") -> 0.68389137 | I17: =IFERROR(I9/I$8,"N/A") -> 0.68770227 | J17: =IFERROR(J9/J$8,"N/A") -> 0.68514818 | K17: =IFERROR(K9/K$8,"N/A") -> 0.68954088 | L17: =IFERROR(L9/L$8,"N/A") -> 0.67262846 | M17: =IFERROR(M9/M$8,"N/A") -> 0.67263628 | ... W17: =IFERROR(W9/W$8,"N/A") -> 0.6758695 | X17: 0.68255112 | Y17: =IFERROR(Y9/Y$8,"N/A") -> 0.67799616 | Z17: =IFERROR(Z9/Z$8,"N/A") -> 0.6845755 | AA17: =IFERROR(AA9/AA$8,"N/A") -> 0.66960508 | AB17: =IFERROR(AB9/AB$8,"N/A") -> 0.67682737 | AC17: =IFERROR(AC9/AC$8,"N/A") -> 0.68665384 | AD17: =IFERROR(AD9/AD$8,"N/A") -> 0.67932279 | AE17: =IFERROR(AE9/AE$8,"N/A") -> 0.67908043 | AF17: =IFERROR(AF9/AF$8,"N/A") -> 0.67921791 | AG17: =IFERROR(AG9/AG$8,"N/A") -> 0.67656136
C18: Landfill | F18: =IFERROR(F10/F$8,"N/A") -> 0.10963112 | G18: =IFERROR(G10/G$8,"N/A") -> 0.11567675 | H18: =IFERROR(H10/H$8,"N/A") -> 0.11403853 | I18: =IFERROR(I10/I$8,"N/A") -> 0.10951039 | J18: =IFERROR(J10/J$8,"N/A") -> 0.11223228 | K18: =IFERROR(K10/K$8,"N/A") -> 0.10472072 | L18: =IFERROR(L10/L$8,"N/A") -> 0.10874506 | M18: =IFERROR(M10/M$8,"N/A") -> 0.11108385 | ... W18: =IFERROR(W10/W$8,"N/A") -> 0.11946346 | X18: 0.11246713 | Y18: =IFERROR(Y10/Y$8,"N/A") -> 0.1141769 | Z18: =IFERROR(Z10/Z$8,"N/A") -> 0.10547744 | AA18: =IFERROR(AA10/AA$8,"N/A") -> 0.11900511 | AB18: =IFERROR(AB10/AB$8,"N/A") -> 0.11929129 | AC18: =IFERROR(AC10/AC$8,"N/A") -> 0.11297546 | AD18: =IFERROR(AD10/AD$8,"N/A") -> 0.11429984 | AE18: =IFERROR(AE10/AE$8,"N/A") -> 0.1152403 | AF18: =IFERROR(AF10/AF$8,"N/A") -> 0.11581198 | AG18: =IFERROR(AG10/AG$8,"N/A") -> 0.11646399
C19: Environmental solutions | F19: =IFERROR(F11/F$8,"N/A") -> 0.11401525 | G19: =IFERROR(G11/G$8,"N/A") -> 0.10690035 | H19: =IFERROR(H11/H$8,"N/A") -> 0.10580517 | I19: =IFERROR(I11/I$8,"N/A") -> 0.10789226 | J19: =IFERROR(J11/J$8,"N/A") -> 0.10857697 | K19: =IFERROR(K11/K$8,"N/A") -> 0.10961494 | L19: =IFERROR(L11/L$8,"N/A") -> 0.11674901 | M19: =IFERROR(M11/M$8,"N/A") -> 0.11400324 | ... W19: =IFERROR(W11/W$8,"N/A") -> 0.10302933 | X19: 0.10973128 | Y19: =IFERROR(Y11/Y$8,"N/A") -> 0.10835126 | Z19: =IFERROR(Z11/Z$8,"N/A") -> 0.11226295 | AA19: =IFERROR(AA11/AA$8,"N/A") -> 0.10940968 | AB19: =IFERROR(AB11/AB$8,"N/A") -> 0.10297901 | AC19: =IFERROR(AC11/AC$8,"N/A") -> 0.10257782 | AD19: =IFERROR(AD11/AD$8,"N/A") -> 0.1067571 | AE19: =IFERROR(AE11/AE$8,"N/A") -> 0.1070245 | AF19: =IFERROR(AF11/AF$8,"N/A") -> 0.10755543 | AG19: =IFERROR(AG11/AG$8,"N/A") -> 0.10980287
C20: Transfer | F20: =IFERROR(F12/F$8,"N/A") -> 0.048392952 | G20: =IFERROR(G12/G$8,"N/A") -> 0.052953649 | H20: =IFERROR(H12/H$8,"N/A") -> 0.053895815 | I20: =IFERROR(I12/I$8,"N/A") -> 0.049117862 | J20: =IFERROR(J12/J$8,"N/A") -> 0.051120986 | K20: =IFERROR(K12/K$8,"N/A") -> 0.047336665 | L20: =IFERROR(L12/L$8,"N/A") -> 0.051432806 | M20: =IFERROR(M12/M$8,"N/A") -> 0.051911094 | ... W20: =IFERROR(W12/W$8,"N/A") -> 0.053659022 | X20: 0.050402476 | Y20: =IFERROR(Y12/Y$8,"N/A") -> 0.051056795 | Z20: =IFERROR(Z12/Z$8,"N/A") -> 0.047597545 | AA20: =IFERROR(AA12/AA$8,"N/A") -> 0.052841995 | AB20: =IFERROR(AB12/AB$8,"N/A") -> 0.053632815 | AC20: =IFERROR(AC12/AC$8,"N/A") -> 0.052067773 | AD20: =IFERROR(AD12/AD$8,"N/A") -> 0.051581892 | AE20: =IFERROR(AE12/AE$8,"N/A") -> 0.051366682 | AF20: =IFERROR(AF12/AF$8,"N/A") -> 0.051377082 | AG20: =IFERROR(AG12/AG$8,"N/A") -> 0.050391827
C21: Other | F21: =IFERROR(F13/F$8,"N/A") -> 0.041467705 | G21: =IFERROR(G13/G$8,"N/A") -> 0.041949596 | H21: =IFERROR(H13/H$8,"N/A") -> 0.042369116 | I21: =IFERROR(I13/I$8,"N/A") -> 0.045777221 | J21: =IFERROR(J13/J$8,"N/A") -> 0.042921581 | K21: =IFERROR(K13/K$8,"N/A") -> 0.048786804 | L21: =IFERROR(L13/L$8,"N/A") -> 0.050444664 | M21: =IFERROR(M13/M$8,"N/A") -> 0.050365537 | ... W21: =IFERROR(W13/W$8,"N/A") -> 0.047978677 | X21: 0.044847991 | Y21: =IFERROR(Y13/Y$8,"N/A") -> 0.048418889 | Z21: =IFERROR(Z13/Z$8,"N/A") -> 0.050086564 | AA21: =IFERROR(AA13/AA$8,"N/A") -> 0.049138146 | AB21: =IFERROR(AB13/AB$8,"N/A") -> 0.047269516 | AC21: =IFERROR(AC13/AC$8,"N/A") -> 0.045725113 | AD21: =IFERROR(AD13/AD$8,"N/A") -> 0.048038381 | AE21: =IFERROR(AE13/AE$8,"N/A") -> 0.047288094 | AF21: =IFERROR(AF13/AF$8,"N/A") -> 0.046037597 | AG21: =IFERROR(AG13/AG$8,"N/A") -> 0.046779957
C22: Professional Services and Other | F22: =IFERROR(F14/F$8,"N/A") -> 0 | G22: =IFERROR(G14/G$8,"N/A") -> 0 | H22: =IFERROR(H14/H$8,"N/A") -> 0 | I22: =IFERROR(I14/I$8,"N/A") -> 0 | J22: =IFERROR(J14/J$8,"N/A") -> 0 | K22: =IFERROR(K14/K$8,"N/A") -> 0 | L22: =IFERROR(L14/L$8,"N/A") -> 0 | M22: =IFERROR(M14/M$8,"N/A") -> 0 | ... W22: =IFERROR(W14/W$8,"N/A") -> 0 | X22: 0 | Y22: =IFERROR(Y14/Y$8,"N/A") -> 0 | Z22: =IFERROR(Z14/Z$8,"N/A") -> 0 | AA22: =IFERROR(AA14/AA$8,"N/A") -> 0 | AB22: =IFERROR(AB14/AB$8,"N/A") -> 0 | AC22: =IFERROR(AC14/AC$8,"N/A") -> 0 | AD22: =IFERROR(AD14/AD$8,"N/A") -> 0 | AE22: =IFERROR(AE14/AE$8,"N/A") -> 0 | AF22: =IFERROR(AF14/AF$8,"N/A") -> 0 | AG22: =IFERROR(AG14/AG$8,"N/A") -> 0
C24: "" | F24: =SUM(F25:F27) -> 0 | G24: =SUM(G25:G27) -> 0 | H24: =SUM(H25:H27) -> 0 | I24: =SUM(I25:I27) -> 0 | J24: =SUM(F24:I24) -> 0 | K24: =SUM(K25:K27) -> 0 | L24: =SUM(L25:L27) -> 0 | M24: =SUM(M25:M27) -> 0 | N24: =SUM(N25:N27) -> 0 | O24: =SUM(K24:N24) -> 0 | P24: =SUM(P25:P27) -> 0 | Q24: =SUM(Q25:Q27) -> 0 | R24: =SUM(R25:R27) -> 0 | S24: =SUM(S25:S27) -> 0 | T24: =SUM(P24:S24) -> 0 | U24: =SUM(U25:U27) -> 0 | V24: =SUM(V25:V27) -> 0 | W24: =SUM(W25:W27) -> 0 | X24: 0 | Y24: =SUM(U24:X24) -> 0 | Z24: =SUM(Z25:Z27) -> 0 | AA24: =SUM(AA25:AA27) -> 0 | AB24: =SUM(AB25:AB27) -> 0 | AC24: =SUM(AC25:AC27) -> 0 | AD24: =SUM(Z24:AC24) -> 0 | AE24: =SUM(AE25:AE27) -> 0 | AF24: =SUM(AF25:AF27) -> 0 | AG24: =SUM(AG25:AG27) -> 0
C25: =C30&" Revenue" -> Boeing Military Aircraft Revenue | F25: 0 | G25: 0 | H25: 0 | I25: 0 | J25: =SUM(F25:I25) -> 0 | K25: 0 | L25: 0 | M25: 0 | N25: 0 | O25: =SUM(K25:N25) -> 0 | P25: 0 | Q25: 0 | R25: 0 | S25: 0 | T25: =SUM(P25:S25) -> 0 | U25: 0 | V25: 0 | W25: 0 | X25: 0 | Y25: =SUM(U25:X25) -> 0 | Z25: 0 | AA25: 0 | AB25: 0 | AC25: 0 | AD25: =SUM(Z25:AC25) -> 0 | AE25: 0 | AF25: 0 | AG25: 0
C26: =C31&" Revenue" -> Network & Space Systems Revenue | F26: 0 | G26: 0 | H26: 0 | I26: 0 | J26: =SUM(F26:I26) -> 0 | K26: 0 | L26: 0 | M26: 0 | N26: 0 | O26: =SUM(K26:N26) -> 0 | P26: 0 | Q26: 0 | R26: 0 | S26: 0 | T26: =SUM(P26:S26) -> 0 | U26: 0 | V26: 0 | W26: 0 | X26: 0 | Y26: =SUM(U26:X26) -> 0 | Z26: 0 | AA26: 0 | AB26: 0 | AC26: 0 | AD26: =SUM(Z26:AC26) -> 0 | AE26: 0 | AF26: 0 | AG26: 0
C27: =C32&" Revenue" -> Global Services & Support Revenue | F27: 0 | G27: 0 | H27: 0 | I27: 0 | J27: =SUM(F27:I27) -> 0 | K27: 0 | L27: 0 | M27: 0 | N27: 0 | O27: =SUM(K27:N27) -> 0 | P27: 0 | Q27: 0 | R27: 0 | S27: 0 | T27: =SUM(P27:S27) -> 0 | U27: 0 | V27: 0 | W27: 0 | X27: 0 | Y27: =SUM(U27:X27) -> 0 | Z27: 0 | AA27: 0 | AB27: 0 | AC27: 0 | AD27: =SUM(Z27:AC27) -> 0 | AE27: 0 | AF27: 0 | AG27: 0
C29: ""
C30: Boeing Military Aircraft | F30: =IFERROR(F25/F$24,"N/A") -> N/A | G30: =IFERROR(G25/G$24,"N/A") -> N/A | H30: =IFERROR(H25/H$24,"N/A") -> N/A | I30: =IFERROR(I25/I$24,"N/A") -> N/A | J30: =IFERROR(J25/J$24,"N/A") -> N/A | K30: =IFERROR(K25/K$24,"N/A") -> N/A | L30: =IFERROR(L25/L$24,"N/A") -> N/A | M30: =IFERROR(M25/M$24,"N/A") -> N/A | ... W30: =IFERROR(W25/W$24,"N/A") -> N/A | X30: N/A | Y30: =IFERROR(Y25/Y$24,"N/A") -> N/A | Z30: =IFERROR(Z25/Z$24,"N/A") -> N/A | AA30: =IFERROR(AA25/AA$24,"N/A") -> N/A | AB30: =IFERROR(AB25/AB$24,"N/A") -> N/A | AC30: =IFERROR(AC25/AC$24,"N/A") -> N/A | AD30: =IFERROR(AD25/AD$24,"N/A") -> N/A | AE30: =IFERROR(AE25/AE$24,"N/A") -> N/A | AF30: =IFERROR(AF25/AF$24,"N/A") -> N/A | AG30: =IFERROR(AG25/AG$24,"N/A") -> N/A
C31: Network & Space Systems | F31: =IFERROR(F26/F$24,"N/A") -> N/A | G31: =IFERROR(G26/G$24,"N/A") -> N/A | H31: =IFERROR(H26/H$24,"N/A") -> N/A | I31: =IFERROR(I26/I$24,"N/A") -> N/A | J31: =IFERROR(J26/J$24,"N/A") -> N/A | K31: =IFERROR(K26/K$24,"N/A") -> N/A | L31: =IFERROR(L26/L$24,"N/A") -> N/A | M31: =IFERROR(M26/M$24,"N/A") -> N/A | ... W31: =IFERROR(W26/W$24,"N/A") -> N/A | X31: N/A | Y31: =IFERROR(Y26/Y$24,"N/A") -> N/A | Z31: =IFERROR(Z26/Z$24,"N/A") -> N/A | AA31: =IFERROR(AA26/AA$24,"N/A") -> N/A | AB31: =IFERROR(AB26/AB$24,"N/A") -> N/A | AC31: =IFERROR(AC26/AC$24,"N/A") -> N/A | AD31: =IFERROR(AD26/AD$24,"N/A") -> N/A | AE31: =IFERROR(AE26/AE$24,"N/A") -> N/A | AF31: =IFERROR(AF26/AF$24,"N/A") -> N/A | AG31: =IFERROR(AG26/AG$24,"N/A") -> N/A
C32: Global Services & Support | F32: =IFERROR(F27/F$24,"N/A") -> N/A | G32: =IFERROR(G27/G$24,"N/A") -> N/A | H32: =IFERROR(H27/H$24,"N/A") -> N/A | I32: =IFERROR(I27/I$24,"N/A") -> N/A | J32: =IFERROR(J27/J$24,"N/A") -> N/A | K32: =IFERROR(K27/K$24,"N/A") -> N/A | L32: =IFERROR(L27/L$24,"N/A") -> N/A | M32: =IFERROR(M27/M$24,"N/A") -> N/A | ... W32: =IFERROR(W27/W$24,"N/A") -> N/A | X32: N/A | Y32: =IFERROR(Y27/Y$24,"N/A") -> N/A | Z32: =IFERROR(Z27/Z$24,"N/A") -> N/A | AA32: =IFERROR(AA27/AA$24,"N/A") -> N/A | AB32: =IFERROR(AB27/AB$24,"N/A") -> N/A | AC32: =IFERROR(AC27/AC$24,"N/A") -> N/A | AD32: =IFERROR(AD27/AD$24,"N/A") -> N/A | AE32: =IFERROR(AE27/AE$24,"N/A") -> N/A | AF32: =IFERROR(AF27/AF$24,"N/A") -> N/A | AG32: =IFERROR(AG27/AG$24,"N/A") -> N/A
