Workbook
Name __1_0_Table2_: [1]MERGER!#REF!
Name __FDS_HYPERLINK_TOGGLE_STATE__: "ON"
Name _1_0_Table2_: [1]MERGER!#REF!
Name _2_0_Table2_: [1]MERGER!#REF!
Name _3_0_Table2_: [1]MERGER!#REF!
Name _4_0_Table2_: [1]MERGER!#REF!
Name _5_0_Table2_: [1]MERGER!#REF!
Name _9_0_Table2_: [1]MERGER!#REF!
Name _AtRisk_SimSetting_AutomaticallyGenerateReports: FALSE
Name _AtRisk_SimSetting_AutomaticResultsDisplayMode: 0
Name _AtRisk_SimSetting_ConvergenceConfidenceLevel: 0.95
Name _AtRisk_SimSetting_ConvergencePercentileToTest: 0.9
Name _AtRisk_SimSetting_ConvergencePerformMeanTest: TRUE
Name _AtRisk_SimSetting_ConvergencePerformPercentileTest: FALSE
Name _AtRisk_SimSetting_ConvergencePerformStdDeviationTest: FALSE
Name _AtRisk_SimSetting_ConvergenceTestAllOutputs: TRUE
Name _AtRisk_SimSetting_ConvergenceTestingPeriod: 100
Name _AtRisk_SimSetting_ConvergenceTolerance: 0.03
Name _AtRisk_SimSetting_LiveUpdate: TRUE
Name _AtRisk_SimSetting_LiveUpdatePeriod: -1
Name _AtRisk_SimSetting_RandomNumberGenerator: 0
Name _AtRisk_SimSetting_ReportsList: 0
Name _AtRisk_SimSetting_SimNameCount: 0
Name _AtRisk_SimSetting_SmartSensitivityAnalysisEnabled: TRUE
Name _AtRisk_SimSetting_StatisticFunctionUpdating: 1
Name _AtRisk_SimSetting_StdRecalcBehavior: 0
Name _AtRisk_SimSetting_StdRecalcWithoutRiskStatic: 0
Name _AtRisk_SimSetting_StdRecalcWithoutRiskStaticPercentile: 0.5
Name _bdm.001de5d049b6489bbc2025ad50c87030.edm: Model!$1:$1048576
Name _bdm.146e958bbea04416b86a4d5943392c04.edm: Model!$M$100
Name _bdm.1ff456f35144482ea0525e6d75d0206f.edm: Integrity!$1:$1048576
Name _bdm.a65ed6e2cd6142fea39714a1a8762f97.edm: Integrity!$1:$1048576
Name _bdm.bf5a9ed53fe44c598e3cfb84ac34b21f.edm: Integrity!$F$37
Name _bdm.dca432f6461240c98baf2847c1b05465.edm: Integrity!$1:$1048576
Name _Fill: #REF!
Name _Key1: #REF!
Name _Order1: 255
Name _Order2: 255
Name _Sort: #REF!
Name _Table1_In1: [2]merger!#REF!
Name _Table1_Out: [2]merger!#REF!
Name _Table2_In1: [2]merger!#REF!
Name _Table2_Out: [2]merger!#REF!
Name _Toc209821136: Cover!$F$33
Name a: {"summary1",#N/A,TRUE,"Comps";"summary2",#N/A,TRUE,"Comps";"summary3",#N/A,TRUE,"Comps"}
Name aaaaaaaa: {"summary1",#N/A,TRUE,"Comps";"summary2",#N/A,TRUE,"Comps";"summary3",#N/A,TRUE,"Comps"}
Name adsfsadfas: {"multiple",#N/A,FALSE,"client (2)";"margins",#N/A,FALSE,"client (2)";"data",#N/A,FALSE,"client (2)";"multiple",#N/A,FALSE,"client";"margins",#N/A,FALSE,"client";"data",#N/A,FALSE,"client"}
Name adsfsdfe: {"Page1",#N/A,FALSE,"CompCo";"Page2",#N/A,FALSE,"CompCo"}
Name aefae: {"inputs raw data",#N/A,TRUE,"INPUT"}
Name aefe: {"cap_structure",#N/A,FALSE,"Graph-Mkt Cap";"price",#N/A,FALSE,"Graph-Price";"ebit",#N/A,FALSE,"Graph-EBITDA";"ebitda",#N/A,FALSE,"Graph-EBITDA"}
Name al: '[3]2010 Labor Rates 091130'!$A$161
Name al09salary: [3]Salaries!$G$13
Name al10salary: [3]Salaries!$K$13
Name alid: '[3]2010 Labor Rates 091130'!$E$168
Name alname: [3]Salaries!$A$13
Name aprpto: [3]Vacation!$I$56
Name asdfasdfas: {"cap_structure",#N/A,FALSE,"Graph-Mkt Cap";"price",#N/A,FALSE,"Graph-Price";"ebit",#N/A,FALSE,"Graph-EBITDA";"ebitda",#N/A,FALSE,"Graph-EBITDA"}
Name asdfsdfasdf: {"Page1",#N/A,FALSE,"CompCo";"Page2",#N/A,FALSE,"CompCo"}
Name augpto: [3]Vacation!$M$56
Name avg_Health_and_Welfare: [4]PBCFringe!$Q$22

Sheet Cover
C1: =Company_Name&" - "&MID(CELL("filename",A1),FIND("]",CELL("filename",A1))+1,255)&": "&Case_Scenario&" Case" -> American Express Company - Cover: Base Case | Q1: Font Toggle
C2: $ in Millions Except Per Share Data | Q2: Report
R3: x
A4: x | C4: Model Assumptions: | I4: Return Summary:
I6: Discounted Cash Flow Analysis | N6: Multiple Analysis
I8: Exit Multiple Method | N8: EV/EBITDA Method
I9: Implied Enterprise Value: | L9: =Valuation!K57 -> 296624.47 | P9: Target Price: | Q9: % Return:
I10: Implied Equity Value: | L10: =Valuation!K64 -> 0
N11: 1 Year LTM EV/EBITDA | P11: =Valuation!N129 -> 335.71784 | Q11: =Valuation!N130 -> 0.070733679
I12: Implied Share Price: | L12: =Valuation!K68 -> 0
I13: % Return: | L13: =Valuation!K69 -> 0 | N13: 2009-2018 Late Cycle EV/EBITDA | P13: =Valuation!N207 -> 423.10361 | Q13: =Valuation!N208 -> 0.34944063
I15: Perpetuity Growth Method | N15: P/E Multiple Method
I16: Implied Enterprise Value: | L16: =Valuation!R57 -> 10375.823 | P16: Target Price: | Q16: % Return:
I17: Implied Equity Value: | L17: =Valuation!R64 -> 0
N18: 1 Year LTM P/E | P18: =Valuation!F118 -> 362.36736 | Q18: =Valuation!F119 -> 0.15077441
C19: Company Name | F19: American Express Company | I19: Implied Share Price: | L19: =Valuation!R68 -> 0
C20: Ticker | F20: AXP | I20: % Return: | L20: =Valuation!R69 -> 0 | N20: 2009-2018 Late Cycle P/E | P20: =Valuation!F196 -> 260.24205 | Q20: =Valuation!F197 -> -0.17354615
C22: Case Scenario | F22: Base | I22: Table of Contents
C24: Last Fiscal Year | F24: 46022 | I24: Cover
C25: Next Fiscal Year | F25: =Last_FYE+365 -> 46387 | I25: Summary
C26: Last Fiscal Quarter Reported | F26: 1Q | I26: Football Field
C27: Current Valuation Date | F27: 46147 | I27: Integrity
I28: Revenue Build
C29: Current Share Price | F29: 314.89 | I29: Model
C30: 52-Week High | F30: 387.49 | I30: Segment Analysis
C31: 52-Week Low | F31: 273.61 | I31: Drivers
I32: WACC
C33: Effective Tax Rate | F33: =IF(Last_FQR="1Q",Model!U71,IF(Last_FQR="2Q",Model!V71,IF(Last_FQR="3Q",Model!W71,Model!X71))) -> 0.21360508 | I33: Valuation
C34: Dividend Yield | F34: =IF(Last_FQR="1Q",Model!U265,IF(Last_FQR="2Q",Model!V265,IF(Last_FQR="3Q",Model!W265,Model!X265))) -> 0.012503379 | I34: Comparables
C35: Diluted Shares Outstanding (MRQ) | F35: =IF(Last_FQR="1Q",Model!U284,IF(Last_FQR="2Q",Model!V284,IF(Last_FQR="3Q",Model!W284,Model!X284))) -> 686 | I35: Charts
I36: Benchmark
C37: Model Type | F37: Top Down | I37: Multiples Data
I38: Pre-Earnings
I39: Post-Earnings
A42: x
C43: Model Color Legend | I43: Constants
C44: Blue = Hard-Coded Value (historical values & assumptions) | I44: Reference | J44: Type | K44: Name | L44: Value
C45: Black = Formulas | I45: Million | J45: (#) | K45: Mil | L45: 1000000
C46: Green = Linked Value (from separate worksheet) | I46: Thousand | J46: (#) | K46: Thou | L46: 1000
C47: Red = Unique Formula / Anomaly | I47: Hundred | J47: (#) | K47: Hun | L47: 100
A48: x
C49: Tab Color Codes
C51: Summary
C53: Model
A54: x
C55: Supporting/Auxiliary
C57: Valuation
C59: Comps
C61: RBG Codes for Model
C63: 0-0-255 | F63: Hard-Coded Numbers
C65: 0-128-0 | F65: Linked Numbers
C67: 255-223-159 | F67: Owl Fund Gold
C69: 255-255-153 | F69: Drivers / Assumptions
C71: 118-0-0 | F71: Owl Fund Red
C73: 0-56-96 | F73: Section Headers
C75: 192-222-246 | F75: Sub-Section Headers
C77: 215-215-215 | F77: Historical Quarters
C79: 235-235-235 | F79: Projected Quarters
C81: 255-255-255 | F81: Annuals
A83: x | B83: x | C83: END

Sheet Summary
C1: =Company_Name&" - "&MID(CELL("filename",A1),FIND("]",CELL("filename",A1))+1,255)&": "&Case_Scenario&" Case" -> American Express Company - Summary: Base Case
C2: =Cover!C2 -> $ in Millions Except Per Share Data
C4: Year: | T4: =Model!J24 -> 2023 | U4: =Model!O24 -> 2024 | V4: =Model!T24 -> 2025 | W4: =Model!Y24 -> 2026 | X4: =Model!AD24 -> 2027 | Y4: =Model!AE24 -> 2028 | Z4: =Model!AF24 -> 2029 | AA4: =Model!AG24 -> 2030
G5: Quarterly | T5: Annuals | AC5: CAGR | AE5: CAGR
A6: x | C6: ="Consolidated "&Model!C25 -> Consolidated Income Statement | G6: =Model!P25 -> 1Q25 | H6: =Model!Q25 -> 2Q25 | I6: =Model!R25 -> 3Q25 | J6: =Model!S25 -> 4Q25 | K6: =Model!U25 -> 1Q26 | L6: =Model!V25 -> 2Q26e | M6: =Model!W25 -> 3Q26e | N6: =Model!X25 -> 4Q26e | O6: =Model!Z25 -> 1Q27e | P6: =Model!AA25 -> 2Q27e | Q6: =Model!AB25 -> 3Q27e | R6: =Model!AC25 -> 4Q27e | T6: =Model!J25 -> 2023 | U6: =Model!O25 -> 2024 | V6: =Model!T25 -> 2025 | W6: =Model!Y25 -> 2026e | X6: =Model!AD25 -> 2027e | Y6: =Model!AE25 -> 2028e | Z6: =Model!AF25 -> 2029e | AA6: =Model!AG25 -> 2030e | AC6: Historical | AE6: Projected
C8: =Model!C28 -> Revenue | G8: =Model!P28 -> 18933 | H8: =Model!Q28 -> 19933 | I8: =Model!R28 -> 20557 | J8: =Model!S28 -> 21040 | K8: =Model!U28 -> 20880 | L8: =Model!V28 -> 21729.203 | M8: =Model!W28 -> 22323.439 | N8: =Model!X28 -> 23124.4 | O8: =Model!Z28 -> 23062.491 | P8: =Model!AA28 -> 24123.963 | Q8: =Model!AB28 -> 24704.225 | R8: =Model!AC28 -> 25658.825 | T8: =Model!J28 -> 67364 | U8: =Model!O28 -> 74201 | V8: =Model!T28 -> 80463 | W8: =Model!Y28 -> 88057.042 | X8: =Model!AD28 -> 97549.504 | Y8: =Model!AE28 -> 104638.91 | Z8: =Model!AF28 -> 111964.78 | AA8: =Model!AG28 -> 118840.28 | AC8: =IFERROR((V8/T8)^(1/(V$4-T$4))-1,"N/A") -> 0.092909439 | AE8: =IFERROR((AA8/V8)^(1/(AA$4-V$4))-1,"N/A") -> 0.081118978
C9: YoY % Growth | K9: =K8/G8-1 -> 0.10283632 | L9: =L8/H8-1 -> 0.090112025 | M9: =M8/I8-1 -> 0.08592883 | N9: =N8/J8-1 -> 0.099068459 | O9: =O8/K8-1 -> 0.10452544 | P9: =P8/L8-1 -> 0.11020928 | Q9: =Q8/M8-1 -> 0.10664959 | R9: =R8/N8-1 -> 0.1095996 | U9: =IF(ISERROR(U8/T8-1),"NA",(U8/T8-1)) -> 0.10149338 | V9: =IF(ISERROR(V8/U8-1),"NA",(V8/U8-1)) -> 0.084392394 | W9: =IF(ISERROR(W8/V8-1),"NA",(W8/V8-1)) -> 0.094379309 | X9: =IF(ISERROR(X8/W8-1),"NA",(X8/W8-1)) -> 0.107799 | Y9: =IF(ISERROR(Y8/X8-1),"NA",(Y8/X8-1)) -> 0.072674931 | Z9: =IF(ISERROR(Z8/Y8-1),"NA",(Z8/Y8-1)) -> 0.070011007 | AA9: =IF(ISERROR(AA8/Z8-1),"NA",(AA8/Z8-1)) -> 0.061407704
C11: =Model!C32 -> Gross Profit | G11: =Model!P32 -> 15817 | H11: =Model!Q32 -> 16451 | I11: =Model!R32 -> 17139 | J11: =Model!S32 -> 17566 | K11: =Model!U32 -> 17656 | L11: =Model!V32 -> 18250.819 | M11: =Model!W32 -> 19007.869 | N11: =Model!X32 -> 19678.936 | O11: =Model!Z32 -> 19900.084 | P11: =Model!AA32 -> 20827.046 | Q11: =Model!AB32 -> 21340.718 | R11: =Model!AC32 -> 22288.523 | T11: =Model!J32 -> 55592 | U11: =Model!O32 -> 60764 | V11: =Model!T32 -> 66973 | W11: =Model!Y32 -> 74593.624 | X11: =Model!AD32 -> 84356.371 | Y11: =Model!AE32 -> 91504.218 | Z11: =Model!AF32 -> 98291.244 | AA11: =Model!AG32 -> 104639.02 | AC11: =IFERROR((V11/T11)^(1/(V$4-T$4))-1,"N/A") -> 0.097599062 | AE11: =IFERROR((AA11/V11)^(1/(AA$4-V$4))-1,"N/A") -> 0.093348923
C12: % Margin | G12: =G11/G$8 -> 0.83541964 | H12: =H11/H$8 -> 0.8253148 | I12: =I11/I$8 -> 0.8337306 | J12: =J11/J$8 -> 0.83488593 | K12: =K11/K$8 -> 0.84559387 | L12: =L11/L$8 -> 0.83992124 | M12: =M11/M$8 -> 0.85147583 | N12: =N11/N$8 -> 0.85100307 | ... R12: =R11/R$8 -> 0.86864939 | T12: =T11/T$8 -> 0.82524791 | U12: =U11/U$8 -> 0.8189108 | V12: =V11/V$8 -> 0.8323453 | W12: =W11/W$8 -> 0.84710571 | X12: =X11/X$8 -> 0.86475448 | Y12: =Y11/Y$8 -> 0.87447605 | Z12: =Z11/Z$8 -> 0.87787643 | AA12: =AA11/AA$8 -> 0.88050127
C13: YoY % Growth | K13: =K11/G11-1 -> 0.11626731 | L13: =L11/H11-1 -> 0.10940485 | M13: =M11/I11-1 -> 0.10904188 | N13: =N11/J11-1 -> 0.12028553 | O13: =O11/K11-1 -> 0.12710038 | P13: =P11/L11-1 -> 0.14115676 | Q13: =Q11/M11-1 -> 0.12273071 | R13: =R11/N11-1 -> 0.13260815 | U13: =U11/T11-1 -> 0.093034969 | V13: =V11/U11-1 -> 0.10218221 | W13: =W11/V11-1 -> 0.1137865 | X13: =X11/W11-1 -> 0.13087911 | Y13: =Y11/X11-1 -> 0.084733939 | Z13: =Z11/Y11-1 -> 0.074171722 | AA13: =AA11/Z11-1 -> 0.064581294
C15: =Model!C39 -> Operating Income | G15: =Model!P39 -> 3330 | H15: =Model!Q39 -> 3550 | I15: =Model!R39 -> 3825 | J15: =Model!S39 -> 3090 | K15: =Model!U39 -> 3778 | L15: =Model!V39 -> 3757.4408 | M15: =Model!W39 -> 4140.4584 | N15: =Model!X39 -> 4416.8314 | O15: =Model!Z39 -> 4494.3402 | P15: =Model!AA39 -> 4808.7344 | Q15: =Model!AB39 -> 5159.4508 | R15: =Model!AC39 -> 5430.6746 | T15: =Model!J39 -> 10513 | U15: =Model!O39 -> 12895 | V15: =Model!T39 -> 13795 | W15: =Model!Y39 -> 16092.731 | X15: =Model!AD39 -> 19893.2 | Y15: =Model!AE39 -> 22756.456 | Z15: =Model!AF39 -> 24898.329 | AA15: =Model!AG39 -> 26798.634 | AC15: =IFERROR((V15/T15)^(1/(V$4-T$4))-1,"N/A") -> 0.1455064 | AE15: =IFERROR((AA15/V15)^(1/(AA$4-V$4))-1,"N/A") -> 0.14203178
C16: Margin | G16: =G15/G$8 -> 0.17588338 | H16: =H15/H$8 -> 0.17809662 | I16: =I15/I$8 -> 0.18606801 | J16: =J15/J$8 -> 0.14686312 | K16: =K15/K$8 -> 0.1809387 | L16: =L15/L$8 -> 0.17292124 | M16: =M15/M$8 -> 0.18547583 | N16: =N15/N$8 -> 0.19100307 | ... R16: =R15/R$8 -> 0.21164939 | T16: =T15/T$8 -> 0.15606259 | U16: =U15/U$8 -> 0.17378472 | V16: =V15/V$8 -> 0.17144526 | W16: =W15/W$8 -> 0.18275348 | X16: =X15/X$8 -> 0.20392928 | Y16: =Y15/Y$8 -> 0.21747605 | Z16: =Z15/Z$8 -> 0.22237643 | AA16: =AA15/AA$8 -> 0.22550127
C17: YoY % Growth | K17: =K15/G15-1 -> 0.13453453 | L17: =L15/H15-1 -> 0.058434028 | M17: =M15/I15-1 -> 0.082472783 | N17: =N15/J15-1 -> 0.42939528 | O17: =O15/K15-1 -> 0.18960831 | P17: =P15/L15-1 -> 0.27978981 | Q17: =Q15/M15-1 -> 0.24610617 | R17: =R15/N15-1 -> 0.22954085 | U17: =U15/T15-1 -> 0.22657662 | V17: =V15/U15-1 -> 0.069794494 | W17: =W15/V15-1 -> 0.16656257 | X17: =X15/W15-1 -> 0.23616063 | Y17: =Y15/X15-1 -> 0.1439314 | Z17: =Z15/Y15-1 -> 0.094121533 | AA17: =AA15/Z15-1 -> 0.076322612
AM18: 1
C19: =Model!C45 -> Net Income (Loss) | G19: =Model!P45 -> 2584 | H19: =Model!Q45 -> 2885 | I19: =Model!R45 -> 2902 | J19: =Model!S45 -> 2462 | K19: =Model!U45 -> 2971 | L19: =Model!V45 -> 2953.3485 | M19: =Model!W45 -> 3254.4003 | N19: =Model!X45 -> 3471.6295 | O19: =Model!Z45 -> 3528.057 | P19: =Model!AA45 -> 3774.8565 | Q19: =Model!AB45 -> 4050.1689 | R19: =Model!AC45 -> 4263.0796 | T19: =Model!J45 -> 8374 | U19: =Model!O45 -> 10129 | V19: =Model!T45 -> 10833 | W19: =Model!Y45 -> 12650.378 | X19: =Model!AD45 -> 15616.162 | Y19: =Model!AE45 -> 17841.062 | Z19: =Model!AF45 -> 19545.188 | AA19: =Model!AG45 -> 21063.727 | AC19: =IFERROR((V19/T19)^(1/(V$4-T$4))-1,"N/A") -> 0.13738604 | AE19: =IFERROR((AA19/V19)^(1/(AA$4-V$4))-1,"N/A") -> 0.14223981
C20: Margin | G20: =G19/G$8 -> 0.13648128 | H20: =H19/H$8 -> 0.14473486 | I20: =I19/I$8 -> 0.14116846 | J20: =J19/J$8 -> 0.11701521 | K20: =K19/K$8 -> 0.14228927 | L20: =L19/L$8 -> 0.1359161 | M20: =M19/M$8 -> 0.145784 | N20: =N19/N$8 -> 0.15012841 | ... R20: =R19/R$8 -> 0.16614477 | T20: =T19/T$8 -> 0.12430972 | U20: =U19/U$8 -> 0.13650759 | V20: =V19/V$8 -> 0.13463331 | W20: =W19/W$8 -> 0.14366118 | X20: =X19/X$8 -> 0.16008448 | Y20: =Y19/Y$8 -> 0.17050122 | Z20: =Z19/Z$8 -> 0.1745655 | AA20: =AA19/AA$8 -> 0.177244
C21: YoY % Growth | K21: =K19/G19-1 -> 0.1497678 | L21: =L19/H19-1 -> 0.023690977 | M21: =M19/I19-1 -> 0.1214336 | N21: =N19/J19-1 -> 0.41008509 | O21: =O19/K19-1 -> 0.18749816 | P21: =P19/L19-1 -> 0.27816157 | Q21: =Q19/M19-1 -> 0.2445208 | R21: =R19/N19-1 -> 0.22797655 | U21: =U19/T19-1 -> 0.20957726 | V21: =V19/U19-1 -> 0.069503406 | W21: =W19/V19-1 -> 0.16776315 | X21: =X19/W19-1 -> 0.2344423 | Y21: =Y19/X19-1 -> 0.14247417 | Z21: =Z19/Y19-1 -> 0.095517096 | AA21: =AA19/Z19-1 -> 0.077693724
C23: =Model!C57 -> Adj. EPS (Diluted) | G23: =Model!P57 -> 3.7222222 | H23: =Model!Q57 -> 4.2961373 | I23: =Model!R57 -> 4.1861472 | J23: =Model!S57 -> 3.4971264 | K23: =Model!U57 -> 4.2813411 | L23: =Model!V57 -> 4.3066281 | M23: =Model!W57 -> 4.7488381 | N23: =Model!X57 -> 5.0692497 | O23: =Model!Z57 -> 5.1551064 | P23: =Model!AA57 -> 5.5194014 | Q23: =Model!AB57 -> 5.9259003 | R23: =Model!AC57 -> 6.2415799 | T23: =Model!J57 -> 11.565217 | U23: =Model!O57 -> 13.753156 | V23: =Model!T57 -> 15.734195 | W23: =Model!Y57 -> 18.405216 | X23: =Model!AD57 -> 22.840765 | Y23: =Model!AE57 -> 26.164702 | Z23: =Model!AF57 -> 28.740459 | AA23: =Model!AG57 -> 31.056162 | AC23: =IFERROR((V23/T23)^(1/(V$4-T$4))-1,"N/A") -> 0.16639425 | AE23: =IFERROR((AA23/V23)^(1/(AA$4-V$4))-1,"N/A") -> 0.14567293
C24: YoY % Growth | K24: =K23/G23-1 -> 0.15021104 | L24: =L23/H23-1 -> 0.0024418948 | M24: =M23/I23-1 -> 0.13441739 | N24: =N23/J23-1 -> 0.44954717 | O24: =O23/K23-1 -> 0.20408681 | P24: =P23/L23-1 -> 0.28160623 | Q24: =Q23/M23-1 -> 0.2478632 | R24: =R23/N23-1 -> 0.23126305 | U24: =IF(ISERROR(U23/T23-1),"NA",(U23/T23-1)) -> 0.18918263 | V24: =IF(ISERROR(V23/U23-1),"NA",(V23/U23-1)) -> 0.14404256 | W24: =IF(ISERROR(W23/V23-1),"NA",(W23/V23-1)) -> 0.16975898 | X24: =IF(ISERROR(X23/W23-1),"NA",(X23/W23-1)) -> 0.24099412 | Y24: =IF(ISERROR(Y23/X23-1),"NA",(Y23/X23-1)) -> 0.1455265 | Z24: =IF(ISERROR(Z23/Y23-1),"NA",(Z23/Y23-1)) -> 0.098443959 | AA24: =IF(ISERROR(AA23/Z23-1),"NA",(AA23/Z23-1)) -> 0.080572957
C27: =Model!C61 -> EBITDA | G27: =Model!P61 -> 3774.25 | H27: =Model!Q61 -> 3994.25 | I27: =Model!R61 -> 4269.25 | J27: =Model!S61 -> 3534.25 | K27: =Model!U61 -> 4246 | L27: =Model!V61 -> 4326.4002 | M27: =Model!W61 -> 4714.2262 | N27: =Model!X61 -> 4991.1211 | O27: =Model!Z61 -> 5068.9301 | P27: =Model!AA61 -> 5387.1041 | Q27: =Model!AB61 -> 5739.7638 | R27: =Model!AC61 -> 6011.977 | T27: =Model!J61 -> 12164 | U27: =Model!O61 -> 14571 | V27: =Model!T61 -> 15572 | W27: =Model!Y61 -> 18277.747 | X27: =Model!AD61 -> 22207.775 | Y27: =Model!AE61 -> 25108.645 | Z27: =Model!AF61 -> 27242.601 | AA27: =Model!AG61 -> 29356.275 | AC27: =IFERROR((V27/T27)^(1/(V$4-T$4))-1,"N/A") -> 0.13144642 | AE27: =IFERROR((AA27/V27)^(1/(AA$4-V$4))-1,"N/A") -> 0.1351972
C28: Margin | G28: =G27/G$8 -> 0.1993477 | H28: =H27/H$8 -> 0.20038379 | I28: =I27/I$8 -> 0.20767865 | J28: =J27/J$8 -> 0.16797766 | K28: =K27/K$8 -> 0.20335249 | L28: =L27/L$8 -> 0.19910533 | M28: =M27/M$8 -> 0.21117831 | N28: =N27/N$8 -> 0.21583786 | ... R28: =R27/R$8 -> 0.23430445 | T28: =T27/T$8 -> 0.18057122 | U28: =U27/U$8 -> 0.19637202 | V28: =V27/V$8 -> 0.19352995 | W28: =W27/W$8 -> 0.20756713 | X28: =X27/X$8 -> 0.22765646 | Y28: =Y27/Y$8 -> 0.23995515 | Z28: =Z27/Z$8 -> 0.24331402 | AA28: =AA27/AA$8 -> 0.24702293
C29: YoY % Growth | K29: =K27/G27-1 -> 0.12499172 | L29: =L27/H27-1 -> 0.083157076 | M29: =M27/I27-1 -> 0.10422819 | N29: =N27/J27-1 -> 0.41221508 | O29: =O27/K27-1 -> 0.19381303 | P29: =P27/L27-1 -> 0.24517011 | Q29: =Q27/M27-1 -> 0.21754104 | R29: =R27/N27-1 -> 0.20453437 | U29: =U27/T27-1 -> 0.19787899 | V29: =V27/U27-1 -> 0.068698099 | W29: =W27/V27-1 -> 0.17375722 | X29: =X27/W27-1 -> 0.21501706 | Y29: =Y27/X27-1 -> 0.13062405 | Z29: =Z27/Y27-1 -> 0.08498893 | AA29: =AA27/Z27-1 -> 0.077587067
G31: =G$5 -> Quarterly | T31: =T$5 -> Annuals
A32: x | C32: ="Consolidated "&Model!C118 -> Consolidated Balance Sheet | G32: =G$6 -> 1Q25 | H32: =H$6 -> 2Q25 | I32: =I$6 -> 3Q25 | J32: =J$6 -> 4Q25 | K32: =K$6 -> 1Q26 | L32: =L$6 -> 2Q26e | M32: =M$6 -> 3Q26e | N32: =N$6 -> 4Q26e | ... R32: =R$6 -> 4Q27e | T32: =T$6 -> 2023 | U32: =U$6 -> 2024 | V32: =V$6 -> 2025 | W32: =W$6 -> 2026e | X32: =X$6 -> 2027e | Y32: =Y$6 -> 2028e | Z32: =Z$6 -> 2029e | AA32: =AA$6 -> 2030e
C34: =Model!C120 -> Cash & Cash Equivalents | G34: =Model!P120 -> 52508 | H34: =Model!Q120 -> 57937 | I34: =Model!R120 -> 54706 | J34: =Model!S120 -> 47792 | K34: =Model!U120 -> 53757 | L34: =Model!V120 -> 62511.832 | M34: =Model!W120 -> 68333.224 | N34: =Model!X120 -> 71873.755 | O34: =Model!Z120 -> 75720.922 | P34: =Model!AA120 -> 86701.19 | Q34: =Model!AB120 -> 90740.151 | R34: =Model!AC120 -> 93787.34 | T34: =Model!J120 -> 46596 | U34: =Model!O120 -> 40640 | V34: =Model!T120 -> 47792 | W34: =Model!Y120 -> 71873.755 | X34: =Model!AD120 -> 93787.34 | Y34: =Model!AE120 -> 109956.47 | Z34: =Model!AF120 -> 133376.01 | AA34: =Model!AG120 -> 156792.61
C35: =Model!C121 -> Card Member Recievables | G35: =Model!P121 -> 58355 | H35: =Model!Q121 -> 59405 | I35: =Model!R121 -> 60823 | J35: =Model!S121 -> 61851 | K35: =Model!U121 -> 0 | L35: =Model!V121 -> 65187.609 | M35: =Model!W121 -> 65999.733 | N35: =Model!X121 -> 68367.792 | O35: =Model!Z121 -> 68934.04 | P35: =Model!AA121 -> 71974.24 | Q35: =Model!AB121 -> 72904.315 | R35: =Model!AC121 -> 75581.975 | T35: =Model!J121 -> 60237 | U35: =Model!O121 -> 59240 | V35: =Model!T121 -> 61851 | W35: =Model!Y121 -> 68367.792 | X35: =Model!AD121 -> 75581.975 | Y35: =Model!AE121 -> 77690.805 | Z35: =Model!AF121 -> 83130.017 | AA35: =Model!AG121 -> 87909.25
C36: =Model!C122 -> Inventory | G36: =Model!P122 -> 0 | H36: =Model!Q122 -> 0 | I36: =Model!R122 -> 0 | J36: =Model!S122 -> 0 | K36: =Model!U122 -> 0 | L36: =Model!V122 -> 0 | M36: =Model!W122 -> 0 | N36: =Model!X122 -> 0 | O36: =Model!Z122 -> 0 | P36: =Model!AA122 -> 0 | Q36: =Model!AB122 -> 0 | R36: =Model!AC122 -> 0 | T36: =Model!J122 -> 0 | U36: =Model!O122 -> 0 | V36: =Model!T122 -> 0 | W36: =Model!Y122 -> 0 | X36: =Model!AD122 -> 0 | Y36: =Model!AE122 -> 0 | Z36: =Model!AF122 -> 0 | AA36: =Model!AG122 -> 0
C37: =Model!C123 -> Prepaid & Other Current Assets | G37: =Model!P123 -> 0 | H37: =Model!Q123 -> 0 | I37: =Model!R123 -> 0 | J37: =Model!S123 -> 0 | K37: =Model!U123 -> 0 | L37: =Model!V123 -> 0 | M37: =Model!W123 -> 0 | N37: =Model!X123 -> 0 | O37: =Model!Z123 -> 0 | P37: =Model!AA123 -> 0 | Q37: =Model!AB123 -> 0 | R37: =Model!AC123 -> 0 | T37: =Model!J123 -> 0 | U37: =Model!O123 -> 0 | V37: =Model!T123 -> 0 | W37: =Model!Y123 -> 0 | X37: =Model!AD123 -> 0 | Y37: =Model!AE123 -> 0 | Z37: =Model!AF123 -> 0 | AA37: =Model!AG123 -> 0
C38: =Model!C124 -> Total Current Assets | G38: =SUM(G34:G37) -> 110863 | H38: =SUM(H34:H37) -> 117342 | I38: =SUM(I34:I37) -> 115529 | J38: =SUM(J34:J37) -> 109643 | K38: =SUM(K34:K37) -> 53757 | L38: =SUM(L34:L37) -> 130021.56 | M38: =SUM(M34:M37) -> 136376.52 | N38: =SUM(N34:N37) -> 142683.43 | ... R38: =SUM(R34:R37) -> 172103.87 | T38: =SUM(T34:T37) -> 106833 | U38: =SUM(U34:U37) -> 99880 | V38: =SUM(V34:V37) -> 109643 | W38: =SUM(W34:W37) -> 142683.43 | X38: =SUM(X34:X37) -> 172103.87 | Y38: =SUM(Y34:Y37) -> 190432.66 | Z38: =SUM(Z34:Z37) -> 219470.06 | AA38: =SUM(AA34:AA37) -> 247832.14
C40: =Model!C126 -> PP&E, Net | G40: =Model!P126 -> 5383 | H40: =Model!Q126 -> 5662 | I40: =Model!R126 -> 5861 | J40: =Model!S126 -> 6118 | K40: =Model!U126 -> 7240 | L40: =Model!V126 -> 7301.1875 | M40: =Model!W126 -> 7307.8291 | N40: =Model!X126 -> 7311.6494 | O40: =Model!Z126 -> 7359.7467 | P40: =Model!AA126 -> 7384.4761 | Q40: =Model!AB126 -> 7397.0644 | R40: =Model!AC126 -> 7482.8915 | T40: =Model!J126 -> 5138 | U40: =Model!O126 -> 5371 | V40: =Model!T126 -> 6118 | W40: =Model!Y126 -> 7311.6494 | X40: =Model!AD126 -> 7482.8915 | Y40: =Model!AE126 -> 7457.7097 | Z40: =Model!AF126 -> 8136.4861 | AA40: =Model!AG126 -> 8458.2493
C41: =Model!C127 -> Card Member Loans | G41: =Model!P127 -> 134387 | H41: =Model!Q127 -> 138913 | I41: =Model!R127 -> 141370 | J41: =Model!S127 -> 148380 | K41: =Model!U127 -> 209724 | L41: =Model!V127 -> 209724 | M41: =Model!W127 -> 209724 | N41: =Model!X127 -> 209724 | O41: =Model!Z127 -> 209724 | P41: =Model!AA127 -> 209724 | Q41: =Model!AB127 -> 209724 | R41: =Model!AC127 -> 209724 | T41: =Model!J127 -> 120877 | U41: =Model!O127 -> 134753 | V41: =Model!T127 -> 148380 | W41: =Model!Y127 -> 209724 | X41: =Model!AD127 -> 209724 | Y41: =Model!AE127 -> 209724 | Z41: =Model!AF127 -> 209724 | AA41: =Model!AG127 -> 209724
C42: =Model!C128 -> Investment Securities | G42: =Model!P128 -> 1110 | H42: =Model!Q128 -> 1258 | I42: =Model!R128 -> 1374 | J42: =Model!S128 -> 1043 | K42: =Model!U128 -> 2625 | L42: =Model!V128 -> 2625 | M42: =Model!W128 -> 2625 | N42: =Model!X128 -> 2625 | O42: =Model!Z128 -> 2625 | P42: =Model!AA128 -> 2625 | Q42: =Model!AB128 -> 2625 | R42: =Model!AC128 -> 2625 | T42: =Model!J128 -> 2186 | U42: =Model!O128 -> 1240 | V42: =Model!T128 -> 1043 | W42: =Model!Y128 -> 2625 | X42: =Model!AD128 -> 2625 | Y42: =Model!AE128 -> 2625 | Z42: =Model!AF128 -> 2625 | AA42: =Model!AG128 -> 2625
C43: =Model!C129 -> Other Assets and Loans | G43: =Model!P129 -> 30501 | H43: =Model!Q129 -> 32381 | I43: =Model!R129 -> 33416 | J43: =Model!S129 -> 34868 | K43: =Model!U129 -> 35548 | L43: =Model!V129 -> 37041.016 | M43: =Model!W129 -> 38226.329 | N43: =Model!X129 -> 39564.25 | O43: =Model!Z129 -> 41265.513 | P43: =Model!AA129 -> 42668.54 | Q43: =Model!AB129 -> 43991.265 | R43: =Model!AC129 -> 45574.95 | T43: =Model!J129 -> 26074 | U43: =Model!O129 -> 30217 | V43: =Model!T129 -> 34868 | W43: =Model!Y129 -> 39564.25 | X43: =Model!AD129 -> 45574.95 | Y43: =Model!AE129 -> 52183.318 | Z43: =Model!AF129 -> 59488.983 | AA43: =Model!AG129 -> 67519.996
C44: =Model!C130 -> Total Non-Current Assets | G44: =SUM(G40:G43) -> 171381 | H44: =SUM(H40:H43) -> 178214 | I44: =SUM(I40:I43) -> 182021 | J44: =SUM(J40:J43) -> 190409 | K44: =SUM(K40:K43) -> 255137 | L44: =SUM(L40:L43) -> 256691.2 | M44: =SUM(M40:M43) -> 257883.16 | N44: =SUM(N40:N43) -> 259224.9 | ... R44: =SUM(R40:R43) -> 265406.84 | T44: =SUM(T40:T43) -> 154275 | U44: =SUM(U40:U43) -> 171581 | V44: =SUM(V40:V43) -> 190409 | W44: =SUM(W40:W43) -> 259224.9 | X44: =SUM(X40:X43) -> 265406.84 | Y44: =SUM(Y40:Y43) -> 271990.03 | Z44: =SUM(Z40:Z43) -> 279974.47 | AA44: =SUM(AA40:AA43) -> 288327.24
C46: =Model!C132 -> Total Assets | G46: =SUM(G38,G44) -> 282244 | H46: =SUM(H38,H44) -> 295556 | I46: =SUM(I38,I44) -> 297550 | J46: =SUM(J38,J44) -> 300052 | K46: =SUM(K38,K44) -> 308894 | L46: =SUM(L38,L44) -> 324124.25 | M46: =SUM(M38,M44) -> 331797.2 | N46: =SUM(N38,N44) -> 339572.74 | ... R46: =SUM(R38,R44) -> 375650.22 | T46: =SUM(T38,T44) -> 261108 | U46: =SUM(U38,U44) -> 271461 | V46: =SUM(V38,V44) -> 300052 | W46: =SUM(W38,W44) -> 339572.74 | X46: =SUM(X38,X44) -> 375650.22 | Y46: =SUM(Y38,Y44) -> 400998.54 | Z46: =SUM(Z38,Z44) -> 438435.08 | AA46: =SUM(AA38,AA44) -> 475528.32
C48: =Model!C134 -> Accounts Payable | G48: =Model!P134 -> 13564 | H48: =Model!Q134 -> 14121 | I48: =Model!R134 -> 14708 | J48: =Model!S134 -> 14700 | K48: =Model!U134 -> 14635 | L48: =Model!V134 -> 14428.191 | M48: =Model!W134 -> 14712.117 | N48: =Model!X134 -> 15109.282 | O48: =Model!Z134 -> 15534.362 | P48: =Model!AA134 -> 16109.505 | Q48: =Model!AB134 -> 16204.36 | R48: =Model!AC134 -> 16771.668 | T48: =Model!J134 -> 13109 | U48: =Model!O134 -> 13884 | V48: =Model!T134 -> 14700 | W48: =Model!Y134 -> 15109.282 | X48: =Model!AD134 -> 16771.668 | Y48: =Model!AE134 -> 16778.777 | Z48: =Model!AF134 -> 17906.313 | AA48: =Model!AG134 -> 18989.212
C49: =Model!C135 -> Customer Deposits | G49: =Model!P135 -> 146396 | H49: =Model!Q135 -> 149386 | I49: =Model!R135 -> 149883 | J49: =Model!S135 -> 152488 | K49: =Model!U135 -> 157948 | L49: =Model!V135 -> 162969.02 | M49: =Model!W135 -> 165395.33 | N49: =Model!X135 -> 171261.32 | O49: =Model!Z135 -> 173024.44 | P49: =Model!AA135 -> 181087.19 | Q49: =Model!AB135 -> 183864.68 | R49: =Model!AC135 -> 190466.58 | T49: =Model!J135 -> 129144 | U49: =Model!O135 -> 139413 | V49: =Model!T135 -> 152488 | W49: =Model!Y135 -> 171261.32 | X49: =Model!AD135 -> 190466.58 | Y49: =Model!AE135 -> 196557.74 | Z49: =Model!AF135 -> 211150.24 | AA49: =Model!AG135 -> 224168.59
C50: =Model!C136 -> Other Current Liabilities | G50: =Model!P136 -> 0 | H50: =Model!Q136 -> 0 | I50: =Model!R136 -> 0 | J50: =Model!S136 -> 0 | K50: =Model!U136 -> 0 | L50: =Model!V136 -> 0 | M50: =Model!W136 -> 0 | N50: =Model!X136 -> 0 | O50: =Model!Z136 -> 0 | P50: =Model!AA136 -> 0 | Q50: =Model!AB136 -> 0 | R50: =Model!AC136 -> 0 | T50: =Model!J136 -> 0 | U50: =Model!O136 -> 0 | V50: =Model!T136 -> 0 | W50: =Model!Y136 -> 0 | X50: =Model!AD136 -> 0 | Y50: =Model!AE136 -> 0 | Z50: =Model!AF136 -> 0 | AA50: =Model!AG136 -> 0
C51: =Model!C137 -> Total Current Liabilities (Excl. Debt) | G51: =SUM(G48:G50) -> 159960 | H51: =SUM(H48:H50) -> 163507 | I51: =SUM(I48:I50) -> 164591 | J51: =SUM(J48:J50) -> 167188 | K51: =SUM(K48:K50) -> 172583 | L51: =SUM(L48:L50) -> 177397.21 | M51: =SUM(M48:M50) -> 180107.45 | N51: =SUM(N48:N50) -> 186370.6 | ... R51: =SUM(R48:R50) -> 207238.24 | T51: =SUM(T48:T50) -> 142253 | U51: =SUM(U48:U50) -> 153297 | V51: =SUM(V48:V50) -> 167188 | W51: =SUM(W48:W50) -> 186370.6 | X51: =SUM(X48:X50) -> 207238.24 | Y51: =SUM(Y48:Y50) -> 213336.51 | Z51: =SUM(Z48:Z50) -> 229056.56 | AA51: =SUM(AA48:AA50) -> 243157.8
C53: =Model!C139 -> Short-term Borrowings | G53: =Model!P139 -> 1559 | H53: =Model!Q139 -> 1493 | I53: =Model!R139 -> 1446 | J53: =Model!S139 -> 1371 | K53: =Model!U139 -> 1692 | L53: =Model!V139 -> 0 | M53: =Model!W139 -> 0 | N53: =Model!X139 -> 0 | O53: =Model!Z139 -> 0 | P53: =Model!AA139 -> 0 | Q53: =Model!AB139 -> 0 | R53: =Model!AC139 -> 0 | T53: =Model!J139 -> 1293 | U53: =Model!O139 -> 1374 | V53: =Model!T139 -> 1371 | W53: =Model!Y139 -> 0 | X53: =Model!AD139 -> 0 | Y53: =Model!AE139 -> 0 | Z53: =Model!AF139 -> 0 | AA53: =Model!AG139 -> 0
C54: =Model!C140 -> LT Debt (Incl. Current Portion) | G54: =Model!P140 -> 51236 | H54: =Model!Q140 -> 58202 | I54: =Model!R140 -> 57787 | J54: =Model!S140 -> 56387 | K54: =Model!U140 -> 58750 | L54: =Model!V140 -> 61950 | M54: =Model!W140 -> 64950 | N54: =Model!X140 -> 62450 | O54: =Model!Z140 -> 63650 | P54: =Model!AA140 -> 67150 | Q54: =Model!AB140 -> 67150 | R54: =Model!AC140 -> 63650 | T54: =Model!J140 -> 47866 | U54: =Model!O140 -> 49715 | V54: =Model!T140 -> 56387 | W54: =Model!Y140 -> 62450 | X54: =Model!AD140 -> 63650 | Y54: =Model!AE140 -> 67650 | Z54: =Model!AF140 -> 71850 | AA54: =Model!AG140 -> 75850
C55: =Model!C141 -> Deferred Income Taxes | G55: =Model!P141 -> 0 | H55: =Model!Q141 -> 0 | I55: =Model!R141 -> 0 | J55: =Model!S141 -> 0 | K55: =Model!U141 -> 0 | L55: =Model!V141 -> 0 | M55: =Model!W141 -> 0 | N55: =Model!X141 -> 0 | O55: =Model!Z141 -> 0 | P55: =Model!AA141 -> 0 | Q55: =Model!AB141 -> 0 | R55: =Model!AC141 -> 0 | T55: =Model!J141 -> 0 | U55: =Model!O141 -> 0 | V55: =Model!T141 -> 0 | W55: =Model!Y141 -> 0 | X55: =Model!AD141 -> 0 | Y55: =Model!AE141 -> 0 | Z55: =Model!AF141 -> 0 | AA55: =Model!AG141 -> 0
C56: =Model!C142 -> Other Non-Current Liabilities | G56: =Model!P142 -> 38287 | H56: =Model!Q142 -> 40043 | I56: =Model!R142 -> 41309 | J56: =Model!S142 -> 41632 | K56: =Model!U142 -> 41874 | L56: =Model!V142 -> 41874 | M56: =Model!W142 -> 41874 | N56: =Model!X142 -> 41874 | O56: =Model!Z142 -> 41874 | P56: =Model!AA142 -> 41874 | Q56: =Model!AB142 -> 41874 | R56: =Model!AC142 -> 41874 | T56: =Model!J142 -> 41639 | U56: =Model!O142 -> 36811 | V56: =Model!T142 -> 41632 | W56: =Model!Y142 -> 41874 | X56: =Model!AD142 -> 41874 | Y56: =Model!AE142 -> 41874 | Z56: =Model!AF142 -> 41874 | AA56: =Model!AG142 -> 41874
C57: =Model!C143 -> Total Non-Current Liabilities | G57: =SUM(G53:G56) -> 91082 | H57: {=INDEX(Data,MATCH($C57,Line_Items,0),MATCH(H$32,Fiscal_Periods,0))} -> 99738 | I57: {=INDEX(Data,MATCH($C57,Line_Items,0),MATCH(I$32,Fiscal_Periods,0))} -> 100542 | J57: {=INDEX(Data,MATCH($C57,Line_Items,0),MATCH(J$32,Fiscal_Periods,0))} -> 99390 | K57: {=INDEX(Data,MATCH($C57,Line_Items,0),MATCH(K$32,Fiscal_Periods,0))} -> 102316 | L57: {=INDEX(Data,MATCH($C57,Line_Items,0),MATCH(L$32,Fiscal_Periods,0))} -> 102419 | M57: {=INDEX(Data,MATCH($C57,Line_Items,0),MATCH(M$32,Fiscal_Periods,0))} -> 105419 | N57: {=INDEX(Data,MATCH($C57,Line_Items,0),MATCH(N$32,Fiscal_Periods,0))} -> 102919 | O57: {=INDEX(Data,MATCH($C57,Line_Items,0),MATCH(O$32,Fiscal_Periods,0))} -> 104119 | ... R57: {=INDEX(Data,MATCH($C57,Line_Items,0),MATCH(R$32,Fiscal_Periods,0))} -> 104119 | T57: {=INDEX(Data,MATCH($C57,Line_Items,0),MATCH(T$32,Fiscal_Periods,0))} -> 90798 | U57: {=INDEX(Data,MATCH($C57,Line_Items,0),MATCH(U$32,Fiscal_Periods,0))} -> 87900 | V57: {=INDEX(Data,MATCH($C57,Line_Items,0),MATCH(V$32,Fiscal_Periods,0))} -> 99390 | W57: {=INDEX(Data,MATCH($C57,Line_Items,0),MATCH(W$32,Fiscal_Periods,0))} -> 102919 | X57: {=INDEX(Data,MATCH($C57,Line_Items,0),MATCH(X$32,Fiscal_Periods,0))} -> 104119 | Y57: {=INDEX(Data,MATCH($C57,Line_Items,0),MATCH(Y$32,Fiscal_Periods,0))} -> 108119 | Z57: {=INDEX(Data,MATCH($C57,Line_Items,0),MATCH(Z$32,Fiscal_Periods,0))} -> 112319 | AA57: {=INDEX(Data,MATCH($C57,Line_Items,0),MATCH(AA$32,Fiscal_Periods,0))} -> 116319
C59: =Model!C145 -> Total Liabilities | G59: =SUM(G51,G57) -> 251042 | H59: =SUM(H51,H57) -> 263245 | I59: =SUM(I51,I57) -> 265133 | J59: =SUM(J51,J57) -> 266578 | K59: =SUM(K51,K57) -> 274899 | L59: =SUM(L51,L57) -> 286135.48 | M59: =SUM(M51,M57) -> 291103.15 | N59: =SUM(N51,N57) -> 295946.17 | ... R59: =SUM(R51,R57) -> 318855.13 | T59: =SUM(T51,T57) -> 233051 | U59: =SUM(U51,U57) -> 241197 | V59: =SUM(V51,V57) -> 266578 | W59: =SUM(W51,W57) -> 295946.17 | X59: =SUM(X51,X57) -> 318855.13 | Y59: =SUM(Y51,Y57) -> 329104.09 | Z59: =SUM(Z51,Z57) -> 349542.67 | AA59: =SUM(AA51,AA57) -> 368135.2
C61: =Model!C147 -> Common Stock & APIC | G61: =Model!P147 -> 11177 | H61: =Model!Q147 -> 11192 | I61: =Model!R147 -> 11197 | J61: =Model!S147 -> 11264 | K61: =Model!U147 -> 11218 | L61: =Model!V147 -> 11429.256 | M61: =Model!W147 -> 11646.29 | N61: =Model!X147 -> 11871.11 | O61: =Model!Z147 -> 12095.329 | P61: =Model!AA147 -> 12329.867 | Q61: =Model!AB147 -> 12570.047 | R61: =Model!AC147 -> 12819.508 | T61: =Model!J147 -> 11517 | U61: =Model!O147 -> 11511 | V61: =Model!T147 -> 11264 | W61: =Model!Y147 -> 11871.11 | X61: =Model!AD147 -> 12819.508 | Y61: =Model!AE147 -> 13836.831 | Z61: =Model!AF147 -> 14925.377 | AA61: =Model!AG147 -> 16080.769
C62: =Model!C148 -> Retained Earnings | G62: =Model!P148 -> 23391 | H62: =Model!Q148 -> 24367 | I62: =Model!R148 -> 24469 | J62: =Model!S148 -> 25487 | K62: =Model!U148 -> 26088 | L62: =Model!V148 -> 28379.428 | M62: =Model!W148 -> 30977.299 | N62: =Model!X148 -> 33791.268 | O62: =Model!Z148 -> 36566.745 | P62: =Model!AA148 -> 39593.632 | Q62: =Model!AB148 -> 42898.64 | R62: =Model!AC148 -> 46417.248 | T62: =Model!J148 -> 19612 | U62: =Model!O148 -> 22148 | V62: =Model!T148 -> 25487 | W62: =Model!Y148 -> 33791.268 | X62: =Model!AD148 -> 46417.248 | Y62: =Model!AE148 -> 60879.404 | Z62: =Model!AF148 -> 77153.811 | AA62: =Model!AG148 -> 94848.633
C63: =Model!C149 -> Treasury Stock | G63: =Model!P149 -> 0 | H63: =Model!Q149 -> 0 | I63: =Model!R149 -> 0 | J63: =Model!S149 -> 0 | K63: =Model!U149 -> 0 | L63: =Model!V149 -> -144.2125 | M63: =Model!W149 -> -288.425 | N63: =Model!X149 -> -432.6375 | O63: =Model!Z149 -> -574.48638 | P63: =Model!AA149 -> -716.33526 | Q63: =Model!AB149 -> -858.18414 | R63: =Model!AC149 -> -1000.033 | T63: =Model!J149 -> 0 | U63: =Model!O149 -> 0 | V63: =Model!T149 -> 0 | W63: =Model!Y149 -> -432.6375 | X63: =Model!AD149 -> -1000.033 | Y63: =Model!AE149 -> -1565.9145 | Z63: =Model!AF149 -> -2130.2859 | AA63: =Model!AG149 -> -2693.1513
C64: =Model!C150 -> Accumulated Other Comprehensive Income (AOCI) | G64: =Model!P150 -> -3366 | H64: =Model!Q150 -> -3248 | I64: =Model!R150 -> -3249 | J64: =Model!S150 -> -3277 | K64: =Model!U150 -> -3311 | L64: =Model!V150 -> -3311 | M64: =Model!W150 -> -3311 | N64: =Model!X150 -> -3311 | O64: =Model!Z150 -> -3311 | P64: =Model!AA150 -> -3311 | Q64: =Model!AB150 -> -3311 | R64: =Model!AC150 -> -3311 | T64: =Model!J150 -> -3072 | U64: =Model!O150 -> -3395 | V64: =Model!T150 -> -3277 | W64: =Model!Y150 -> -3311 | X64: =Model!AD150 -> -3311 | Y64: =Model!AE150 -> -3311 | Z64: =Model!AF150 -> -3311 | AA64: =Model!AG150 -> -3311
C65: =Model!C151 -> Total Shareholder's Equity | G65: =SUM(G61:G64) -> 31202 | H65: =SUM(H61:H64) -> 32311 | I65: =SUM(I61:I64) -> 32417 | J65: =SUM(J61:J64) -> 33474 | K65: =SUM(K61:K64) -> 33995 | L65: =SUM(L61:L64) -> 36353.472 | M65: =SUM(M61:M64) -> 39024.163 | N65: =SUM(N61:N64) -> 41918.741 | ... R65: =SUM(R61:R64) -> 54925.723 | T65: =SUM(T61:T64) -> 28057 | U65: =SUM(U61:U64) -> 30264 | V65: =SUM(V61:V64) -> 33474 | W65: =SUM(W61:W64) -> 41918.741 | X65: =SUM(X61:X64) -> 54925.723 | Y65: =SUM(Y61:Y64) -> 69839.32 | Z65: =SUM(Z61:Z64) -> 86637.902 | AA65: =SUM(AA61:AA64) -> 104925.25
C67: =Model!C153 -> Noncontrolling Interests | G67: =Model!P153 -> 0 | H67: =Model!Q153 -> 0 | I67: =Model!R153 -> 0 | J67: =Model!S153 -> 0 | K67: =Model!U153 -> 0 | L67: =Model!V153 -> 0 | M67: =Model!W153 -> 0 | N67: =Model!X153 -> 0 | O67: =Model!Z153 -> 0 | P67: =Model!AA153 -> 0 | Q67: =Model!AB153 -> 0 | R67: =Model!AC153 -> 0 | T67: =Model!J153 -> 0 | U67: =Model!O153 -> 0 | V67: =Model!T153 -> 0 | W67: =Model!Y153 -> 0 | X67: =Model!AD153 -> 0 | Y67: =Model!AE153 -> 0 | Z67: =Model!AF153 -> 0 | AA67: =Model!AG153 -> 0
C68: =Model!C154 -> Total Equity | G68: =SUM(G65,G67) -> 31202 | H68: =SUM(H65,H67) -> 32311 | I68: =SUM(I65,I67) -> 32417 | J68: =SUM(J65,J67) -> 33474 | K68: =SUM(K65,K67) -> 33995 | L68: =SUM(L65,L67) -> 36353.472 | M68: =SUM(M65,M67) -> 39024.163 | N68: =SUM(N65,N67) -> 41918.741 | ... R68: =SUM(R65,R67) -> 54925.723 | T68: =SUM(T65,T67) -> 28057 | U68: =SUM(U65,U67) -> 30264 | V68: =SUM(V65,V67) -> 33474 | W68: =SUM(W65,W67) -> 41918.741 | X68: =SUM(X65,X67) -> 54925.723 | Y68: =SUM(Y65,Y67) -> 69839.32 | Z68: =SUM(Z65,Z67) -> 86637.902 | AA68: =SUM(AA65,AA67) -> 104925.25
C70: =Model!C156 -> Total Liabilities & Shareholder's Equity | G70: =SUM(G59,G68) -> 282244 | H70: =SUM(H59,H68) -> 295556 | I70: =SUM(I59,I68) -> 297550 | J70: =SUM(J59,J68) -> 300052 | K70: =SUM(K59,K68) -> 308894 | L70: =SUM(L59,L68) -> 324124.25 | M70: =SUM(M59,M68) -> 331797.2 | N70: =SUM(N59,N68) -> 339572.74 | ... R70: =SUM(R59,R68) -> 375650.22 | T70: =SUM(T59,T68) -> 261108 | U70: =SUM(U59,U68) -> 271461 | V70: =SUM(V59,V68) -> 300052 | W70: =SUM(W59,W68) -> 339572.74 | X70: =SUM(X59,X68) -> 375650.22 | Y70: =SUM(Y59,Y68) -> 400998.54 | Z70: =SUM(Z59,Z68) -> 438435.08 | AA70: =SUM(AA59,AA68) -> 475528.32
G72: =G$5 -> Quarterly | T72: =T$31 -> Annuals
A73: x | C73: Ratio Analysis | G73: =G$6 -> 1Q25 | H73: =H$6 -> 2Q25 | I73: =I$6 -> 3Q25 | J73: =J$6 -> 4Q25 | K73: =K$6 -> 1Q26 | L73: =L$6 -> 2Q26e | M73: =M$6 -> 3Q26e | N73: =N$6 -> 4Q26e | ... R73: =R$6 -> 4Q27e | T73: =T$6 -> 2023 | U73: =U$6 -> 2024 | V73: =V$6 -> 2025 | W73: =W$6 -> 2026e | X73: =X$6 -> 2027e | Y73: =Y$6 -> 2028e | Z73: =Z$6 -> 2029e | AA73: =AA$6 -> 2030e
C75: Profitability
C76: Gross Margin | G76: =G12 -> 0.83541964 | H76: =H12 -> 0.8253148 | I76: =I12 -> 0.8337306 | J76: =J12 -> 0.83488593 | K76: =K12 -> 0.84559387 | L76: =L12 -> 0.83992124 | M76: =M12 -> 0.85147583 | N76: =N12 -> 0.85100307 | ... R76: =R12 -> 0.86864939 | T76: =T12 -> 0.82524791 | U76: =U12 -> 0.8189108 | V76: =V12 -> 0.8323453 | W76: =W12 -> 0.84710571 | X76: =X12 -> 0.86475448 | Y76: =Y12 -> 0.87447605 | Z76: =Z12 -> 0.87787643 | AA76: =AA12 -> 0.88050127
C77: EBITDA Margin | G77: =G28 -> 0.1993477 | H77: =H28 -> 0.20038379 | I77: =I28 -> 0.20767865 | J77: =J28 -> 0.16797766 | K77: =K28 -> 0.20335249 | L77: =L28 -> 0.19910533 | M77: =M28 -> 0.21117831 | N77: =N28 -> 0.21583786 | ... R77: =R28 -> 0.23430445 | T77: =T28 -> 0.18057122 | U77: =U28 -> 0.19637202 | V77: =V28 -> 0.19352995 | W77: =W28 -> 0.20756713 | X77: =X28 -> 0.22765646 | Y77: =Y28 -> 0.23995515 | Z77: =Z28 -> 0.24331402 | AA77: =AA28 -> 0.24702293
C78: EBIT Margin | G78: =G16 -> 0.17588338 | H78: =H16 -> 0.17809662 | I78: =I16 -> 0.18606801 | J78: =J16 -> 0.14686312 | K78: =K16 -> 0.1809387 | L78: =L16 -> 0.17292124 | M78: =M16 -> 0.18547583 | N78: =N16 -> 0.19100307 | ... R78: =R16 -> 0.21164939 | T78: =T16 -> 0.15606259 | U78: =U16 -> 0.17378472 | V78: =V16 -> 0.17144526 | W78: =W16 -> 0.18275348 | X78: =X16 -> 0.20392928 | Y78: =Y16 -> 0.21747605 | Z78: =Z16 -> 0.22237643 | AA78: =AA16 -> 0.22550127
C79: Net Profit Margin | G79: =G20 -> 0.13648128 | H79: =H20 -> 0.14473486 | I79: =I20 -> 0.14116846 | J79: =J20 -> 0.11701521 | K79: =K20 -> 0.14228927 | L79: =L20 -> 0.1359161 | M79: =M20 -> 0.145784 | N79: =N20 -> 0.15012841 | ... R79: =R20 -> 0.16614477 | T79: =T20 -> 0.12430972 | U79: =U20 -> 0.13650759 | V79: =V20 -> 0.13463331 | W79: =W20 -> 0.14366118 | X79: =X20 -> 0.16008448 | Y79: =Y20 -> 0.17050122 | Z79: =Z20 -> 0.1745655 | AA79: =AA20 -> 0.177244
C80: Return on Assets (ROA) | G80: =G19/G46 -> 0.009155199 | H80: =H19/H46 -> 0.0097612635 | I80: =I19/I46 -> 0.0097529827 | J80: =J19/J46 -> 0.0082052444 | K80: =K19/K46 -> 0.0096181862 | L80: =L19/L46 -> 0.0096129497 | M80: =M19/M46 -> 0.010322805 | N80: =N19/N46 -> 0.010749256 | ... R80: =R19/R46 -> 0.011889782 | T80: =T19/T46 -> 0.03207102 | U80: =U19/U46 -> 0.037312911 | V80: =V19/V46 -> 0.036103742 | W80: =W19/W46 -> 0.038419883 | X80: =X19/X46 -> 0.043585588 | Y80: =Y19/Y46 -> 0.046545302 | Z80: =Z19/Z46 -> 0.046591537 | AA80: =AA19/AA46 -> 0.046267881
C81: Return on Equity (ROE) | G81: =G19*4/G68 -> 0.33126082 | H81: =H19*4/H68 -> 0.35715391 | I81: =I19*4/I68 -> 0.35808372 | J81: =J19*4/J68 -> 0.29419848 | K81: =K19*4/K68 -> 0.34958082 | L81: =L19*4/L68 -> 0.32495916 | M81: =M19*4/M68 -> 0.33357797 | N81: =N19*4/N68 -> 0.33127231 | ... R81: =R19*4/R68 -> 0.31046143 | T81: =T19/T68 -> 0.29846384 | U81: =U19/U68 -> 0.33468808 | V81: =V19/V68 -> 0.32362431 | W81: =W19/W68 -> 0.30178335 | X81: =X19/X68 -> 0.28431418 | Y81: =Y19/Y68 -> 0.2554587 | Z81: =Z19/Z68 -> 0.22559628 | AA81: =AA19/AA68 -> 0.20074983
C82: Return on Invested Capital (ROIC) | G82: =G19*4/(G53+G54+G68) -> 0.12305201 | H82: =H19*4/(H53+H54+H68) -> 0.1254266 | I82: =I19*4/(I53+I54+I68) -> 0.12665576 | J82: =J19*4/(J53+J54+J68) -> 0.10794458 | K82: =K19*4/(K53+K54+K68) -> 0.12584051 | L82: =L19*4/(L53+L54+L68) -> 0.12617629 | M82: =M19*4/(M53+M54+M68) -> 0.13112724 | N82: =N19*4/(N53+N54+N68) -> 0.13916805 | ... S82: =S19*4/(S53+S54+S68) -> #DIV/0! | T82: =T19/(T53+T54+T68) -> 0.10844903 | U82: =U19/(U53+U54+U68) -> 0.12450678 | V82: =V19/(V53+V54+V68) -> 0.11874123 | W82: =W19/(W53+W54+W68) -> 0.12435326 | X82: =X19/(X53+X54+X68) -> 0.13726231 | Y82: =Y19/(Y53+Y54+Y68) -> 0.13487789 | Z82: =Z19/(Z53+Z54+Z68) -> 0.12800752 | AA82: =AA19/(AA53+AA54+AA68) -> 0.1208352
C84: Coverage
C85: Interest Expense | G85: =-Model!#REF! -> #REF! | H85: =-Model!#REF! -> #REF! | I85: =-Model!#REF! -> #REF! | J85: =-Model!#REF! -> #REF! | K85: =-Model!#REF! -> #REF! | L85: =-Model!#REF! -> #REF! | M85: =-Model!#REF! -> #REF! | N85: =-Model!#REF! -> #REF! | ... R85: =-Model!#REF! -> #REF! | T85: =-Model!J29 -> 6849 | U85: =-Model!O29 -> 8252 | V85: =-Model!T29 -> 8234 | W85: =-Model!Y29 -> 7891.1521 | X85: =-Model!AD29 -> 6947.2617 | Y85: =-Model!AE29 -> 6542.4378 | Z85: =-Model!AF29 -> 6619.7575 | AA85: =-Model!AG29 -> 6714.3255
C86: Capital Expenditures | G86: =Model!P193 -> 430 | H86: =Model!Q193 -> 619 | I86: =Model!R193 -> 654 | J86: =Model!S193 -> 722 | K86: =Model!U193 -> 1149 | L86: =Model!V193 -> 630.14689 | M86: =Model!W193 -> 580.40941 | N86: =Model!X193 -> 578.11001 | O86: =Model!Z193 -> 622.68726 | P86: =Model!AA193 -> 603.09907 | Q86: =Model!AB193 -> 592.90139 | R86: =Model!AC193 -> 667.12946 | T86: =Model!J193 -> 1563 | U86: =Model!O193 -> 1911 | V86: =Model!T193 -> 2425 | W86: =Model!Y193 -> 2937.6663 | X86: =Model!AD193 -> 2485.8172 | Y86: =Model!AE193 -> 2327.0066 | Z86: =Model!AF193 -> 3023.0491 | AA86: =Model!AG193 -> 2879.404
C87: EBIT / Interest Expense | G87: =IF(ISERROR(G15/G85),"N/A",(G15/G85)) -> N/A | H87: =IF(ISERROR(H15/H85),"N/A",(H15/H85)) -> N/A | I87: =IF(ISERROR(I15/I85),"N/A",(I15/I85)) -> N/A | J87: =IF(ISERROR(J15/J85),"N/A",(J15/J85)) -> N/A | K87: =IF(ISERROR(K15/K85),"N/A",(K15/K85)) -> N/A | L87: =IF(ISERROR(L15/L85),"N/A",(L15/L85)) -> N/A | M87: =IF(ISERROR(M15/M85),"N/A",(M15/M85)) -> N/A | N87: =IF(ISERROR(N15/N85),"N/A",(N15/N85)) -> N/A | ... R87: =IF(ISERROR(R15/R85),"N/A",(R15/R85)) -> N/A | T87: =IF(ISERROR(T15/T85),"N/A",(T15/T85)) -> 1.5349686 | U87: =IF(ISERROR(U15/U85),"N/A",(U15/U85)) -> 1.5626515 | V87: =IF(ISERROR(V15/V85),"N/A",(V15/V85)) -> 1.6753704 | W87: =IF(ISERROR(W15/W85),"N/A",(W15/W85)) -> 2.0393385 | X87: =IF(ISERROR(X15/X85),"N/A",(X15/X85)) -> 2.8634592 | Y87: =IF(ISERROR(Y15/Y85),"N/A",(Y15/Y85)) -> 3.4782839 | Z87: =IF(ISERROR(Z15/Z85),"N/A",(Z15/Z85)) -> 3.7612146 | AA87: =IF(ISERROR(AA15/AA85),"N/A",(AA15/AA85)) -> 3.9912623
C88: EBITDA / Interest Expense | G88: =IF(ISERROR(G27/G85),"N/A",(G27/G85)) -> N/A | H88: =IF(ISERROR(H27/H85),"N/A",(H27/H85)) -> N/A | I88: =IF(ISERROR(I27/I85),"N/A",(I27/I85)) -> N/A | J88: =IF(ISERROR(J27/J85),"N/A",(J27/J85)) -> N/A | K88: =IF(ISERROR(K27/K85),"N/A",(K27/K85)) -> N/A | L88: =IF(ISERROR(L27/L85),"N/A",(L27/L85)) -> N/A | M88: =IF(ISERROR(M27/M85),"N/A",(M27/M85)) -> N/A | N88: =IF(ISERROR(N27/N85),"N/A",(N27/N85)) -> N/A | ... R88: =IF(ISERROR(R27/R85),"N/A",(R27/R85)) -> N/A | T88: =IF(ISERROR(T27/T85),"N/A",(T27/T85)) -> 1.7760257 | U88: =IF(ISERROR(U27/U85),"N/A",(U27/U85)) -> 1.7657538 | V88: =IF(ISERROR(V27/V85),"N/A",(V27/V85)) -> 1.8911829 | W88: =IF(ISERROR(W27/W85),"N/A",(W27/W85)) -> 2.3162331 | X88: =IF(ISERROR(X27/X85),"N/A",(X27/X85)) -> 3.1966228 | Y88: =IF(ISERROR(Y27/Y85),"N/A",(Y27/Y85)) -> 3.8378117 | Z88: =IF(ISERROR(Z27/Z85),"N/A",(Z27/Z85)) -> 4.1153473 | AA88: =IF(ISERROR(AA27/AA85),"N/A",(AA27/AA85)) -> 4.3721853
C89: (EBITDA - CapEx) / Interest Expense | G89: =IF(ISERROR((G27-G86)/G85),"N/A",((G27-G86)/G85)) -> N/A | H89: =IF(ISERROR((H27-H86)/H85),"N/A",((H27-H86)/H85)) -> N/A | I89: =IF(ISERROR((I27-I86)/I85),"N/A",((I27-I86)/I85)) -> N/A | J89: =IF(ISERROR((J27-J86)/J85),"N/A",((J27-J86)/J85)) -> N/A | K89: =IF(ISERROR((K27-K86)/K85),"N/A",((K27-K86)/K85)) -> N/A | L89: =IF(ISERROR((L27-L86)/L85),"N/A",((L27-L86)/L85)) -> N/A | M89: =IF(ISERROR((M27-M86)/M85),"N/A",((M27-M86)/M85)) -> N/A | N89: =IF(ISERROR((N27-N86)/N85),"N/A",((N27-N86)/N85)) -> N/A | ... R89: =IF(ISERROR((R27-R86)/R85),"N/A",((R27-R86)/R85)) -> N/A | T89: =IF(ISERROR((T27-T86)/T85),"N/A",((T27-T86)/T85)) -> 1.5478172 | U89: =IF(ISERROR((U27-U86)/U85),"N/A",((U27-U86)/U85)) -> 1.5341735 | V89: =IF(ISERROR((V27-V86)/V85),"N/A",((V27-V86)/V85)) -> 1.5966723 | W89: =IF(ISERROR((W27-W86)/W85),"N/A",((W27-W86)/W85)) -> 1.9439596 | X89: =IF(ISERROR((X27-X86)/X85),"N/A",((X27-X86)/X85)) -> 2.8388103 | Y89: =IF(ISERROR((Y27-Y86)/Y85),"N/A",((Y27-Y86)/Y85)) -> 3.4821329 | Z89: =IF(ISERROR((Z27-Z86)/Z85),"N/A",((Z27-Z86)/Z85)) -> 3.6586766 | AA89: =IF(ISERROR((AA27-AA86)/AA85),"N/A",((AA27-AA86)/AA85)) -> 3.9433404
C91: Leverage
C92: Total Debt / EBITDA | G92: =IF(ISERROR((G53+G54)/G27),"NA",((G53+G54)/G27)) -> 13.98821 | H92: =IF(ISERROR((H53+H54)/H27),"NA",((H53+H54)/H27)) -> 14.945234 | I92: =IF(ISERROR((I53+I54)/I27),"NA",((I53+I54)/I27)) -> 13.874334 | J92: =IF(ISERROR((J53+J54)/J27),"NA",((J53+J54)/J27)) -> 16.342364 | K92: =IF(ISERROR((K53+K54)/K27),"NA",((K53+K54)/K27)) -> 14.235045 | L92: =IF(ISERROR((L53+L54)/L27),"NA",((L53+L54)/L27)) -> 13.641187 | M92: =IF(ISERROR((M53+M54)/M27),"NA",((M53+M54)/M27)) -> 13.11882 | N92: =IF(ISERROR((N53+N54)/N27),"NA",((N53+N54)/N27)) -> 11.8866 | ... R92: =IF(ISERROR((R53+R54)/R27),"NA",((R53+R54)/R27)) -> 10.026662 | T92: =IF(ISERROR((T53+T54)/T27),"NA",((T53+T54)/T27)) -> 4.0413515 | U92: =IF(ISERROR((U53+U54)/U27),"NA",((U53+U54)/U27)) -> 3.506211 | V92: =IF(ISERROR((V53+V54)/V27),"NA",((V53+V54)/V27)) -> 3.7090932 | W92: =IF(ISERROR((W53+W54)/W27),"NA",((W53+W54)/W27)) -> 3.2971494 | X92: =IF(ISERROR((X53+X54)/X27),"NA",((X53+X54)/X27)) -> 2.7187806 | Y92: =IF(ISERROR((Y53+Y54)/Y27),"NA",((Y53+Y54)/Y27)) -> 2.5549035 | Z92: =IF(ISERROR((Z53+Z54)/Z27),"NA",((Z53+Z54)/Z27)) -> 2.4978164 | AA92: =IF(ISERROR((AA53+AA54)/AA27),"NA",((AA53+AA54)/AA27)) -> 2.4457359
C93: Total Debt / Equity | G93: =IF(ISERROR((G53+G54)/G68),"NA",((G53+G54)/G68)) -> 1.692039 | H93: =IF(ISERROR((H53+H54)/H68),"NA",((H53+H54)/H68)) -> 1.8475132 | I93: =IF(ISERROR((I53+I54)/I68),"NA",((I53+I54)/I68)) -> 1.8272203 | J93: =IF(ISERROR((J53+J54)/J68),"NA",((J53+J54)/J68)) -> 1.7254586 | K93: =IF(ISERROR((K53+K54)/K68),"NA",((K53+K54)/K68)) -> 1.7779673 | L93: =IF(ISERROR((L53+L54)/L68),"NA",((L53+L54)/L68)) -> 1.6001307 | M93: =IF(ISERROR((M53+M54)/M68),"NA",((M53+M54)/M68)) -> 1.5674772 | N93: =IF(ISERROR((N53+N54)/N68),"NA",((N53+N54)/N68)) -> 1.404809 | ... R93: =IF(ISERROR((R53+R54)/R68),"NA",((R53+R54)/R68)) -> 1.1002183 | T93: =IF(ISERROR((T53+T54)/T68),"NA",((T53+T54)/T68)) -> 1.7521118 | U93: =IF(ISERROR((U53+U54)/U68),"NA",((U53+U54)/U68)) -> 1.6881113 | V93: =IF(ISERROR((V53+V54)/V68),"NA",((V53+V54)/V68)) -> 1.7254586 | W93: =IF(ISERROR((W53+W54)/W68),"NA",((W53+W54)/W68)) -> 1.404809 | X93: =IF(ISERROR((X53+X54)/X68),"NA",((X53+X54)/X68)) -> 1.1002183 | Y93: =IF(ISERROR((Y53+Y54)/Y68),"NA",((Y53+Y54)/Y68)) -> 0.92478632 | Z93: =IF(ISERROR((Z53+Z54)/Z68),"NA",((Z53+Z54)/Z68)) -> 0.79519722 | AA93: =IF(ISERROR((AA53+AA54)/AA68),"NA",((AA53+AA54)/AA68)) -> 0.69545426
C94: Total Debt / Total Assets | G94: =IF(ISERROR((G53+G54)/G46),"NA",((G53+G54)/G46)) -> 0.18705446 | H94: =IF(ISERROR((H53+H54)/H46),"NA",((H53+H54)/H46)) -> 0.20197526 | I94: =IF(ISERROR((I53+I54)/I46),"NA",((I53+I54)/I46)) -> 0.19906906 | J94: =IF(ISERROR((J53+J54)/J46),"NA",((J53+J54)/J46)) -> 0.1924933 | K94: =IF(ISERROR((K53+K54)/K46),"NA",((K53+K54)/K46)) -> 0.1956723 | L94: =IF(ISERROR((L53+L54)/L46),"NA",((L53+L54)/L46)) -> 0.18754228 | M94: =IF(ISERROR((M53+M54)/M46),"NA",((M53+M54)/M46)) -> 0.19224695 | N94: =IF(ISERROR((N53+N54)/N46),"NA",((N53+N54)/N46)) -> 0.18048269 | ... R94: =IF(ISERROR((R53+R54)/R46),"NA",((R53+R54)/R46)) -> 0.16634357 | T94: =IF(ISERROR((T53+T54)/T46),"NA",((T53+T54)/T46)) -> 0.18827075 | U94: =IF(ISERROR((U53+U54)/U46),"NA",((U53+U54)/U46)) -> 0.18820015 | V94: =IF(ISERROR((V53+V54)/V46),"NA",((V53+V54)/V46)) -> 0.1924933 | W94: =IF(ISERROR((W53+W54)/W46),"NA",((W53+W54)/W46)) -> 0.18048269 | X94: =IF(ISERROR((X53+X54)/X46),"NA",((X53+X54)/X46)) -> 0.16634357 | Y94: =IF(ISERROR((Y53+Y54)/Y46),"NA",((Y53+Y54)/Y46)) -> 0.1658036 | Z94: =IF(ISERROR((Z53+Z54)/Z46),"NA",((Z53+Z54)/Z46)) -> 0.16122569 | AA94: =IF(ISERROR((AA53+AA54)/AA46),"NA",((AA53+AA54)/AA46)) -> 0.1570611
C96: Efficiency
C97: Asset Turnover | G97: =G8/G46 -> 0.067080257 | H97: =H8/H46 -> 0.06744238 | I97: =I8/I46 -> 0.069087548 | J97: =J8/J46 -> 0.070121179 | K97: =K8/K46 -> 0.067596004 | L97: =L8/L46 -> 0.06942783 | M97: =M8/M46 -> 0.069363586 | N97: =N8/N46 -> 0.070530781 | ... R97: =R8/R46 -> 0.070776379 | T97: =T8/T46 -> 0.25799286 | U97: =U8/U46 -> 0.27333945 | V97: =V8/V46 -> 0.26816352 | W97: =W8/W46 -> 0.26792387 | X97: =X8/X46 -> 0.26900774 | Y97: =Y8/Y46 -> 0.27030133 | Z97: =Z8/Z46 -> 0.26447915 | AA97: =AA8/AA46 -> 0.25881101
C98: =Model!C182 -> Days Sales Outstanding | G98: =Model!P182 -> 279.50008 | H98: =Model!Q182 -> 268.8045 | I98: =Model!R182 -> 269.03186 | J98: =Model!S182 -> 268.20361 | K98: =Model!U182 -> 133.29957 | L98: =Model!V182 -> 273 | M98: =Model!W182 -> 272 | N98: =Model!X182 -> 272 | O98: =Model!Z182 -> 272 | P98: =Model!AA182 -> 271.5 | Q98: =Model!AB182 -> 271.5 | R98: =Model!AC182 -> 271 | T98: =Model!J182 -> 318.0713 | U98: =Model!O182 -> 293.85793 | V98: =Model!T182 -> 274.64931 | W98: =Model!Y182 -> 269.88108 | X98: =Model!AD182 -> 270.04553 | Y98: =Model!AE182 -> 271 | Z98: =Model!AF182 -> 271 | AA98: =Model!AG182 -> 270
C99: =Model!C183 -> Days Inventory Outstanding | G99: =Model!P183 -> 0 | H99: =Model!Q183 -> 0 | I99: =Model!R183 -> 0 | J99: =Model!S183 -> 0 | K99: =Model!U183 -> 0 | L99: =Model!V183 -> 0 | M99: =Model!W183 -> 0 | N99: =Model!X183 -> 0 | O99: =Model!Z183 -> 0 | P99: =Model!AA183 -> 0 | Q99: =Model!AB183 -> 0 | R99: =Model!AC183 -> 0 | T99: =Model!J183 -> 0 | U99: =Model!O183 -> 0 | V99: =Model!T183 -> 0 | W99: =Model!Y183 -> 0 | X99: =Model!AD183 -> 0 | Y99: =Model!AE183 -> 0 | Z99: =Model!AF183 -> 0 | AA99: =Model!AG183 -> 0
C100: =Model!C184 -> Days Payables Outstanding (from SG&A) | G100: =Model!P184 -> 113.93414 | H100: =Model!Q184 -> 112.31988 | I100: =Model!R184 -> 114.97607 | J100: =Model!S184 -> 107.35402 | K100: =Model!U184 -> 106.29479 | L100: =Model!V184 -> 104 | M100: =Model!W184 -> 104 | N100: =Model!X184 -> 104 | O100: =Model!Z184 -> 105.5 | P100: =Model!AA184 -> 105.5 | Q100: =Model!AB184 -> 105.5 | R100: =Model!AC184 -> 105.5 | T100: =Model!J184 -> 122.38412 | U100: =Model!O184 -> 117.84562 | V100: =Model!T184 -> 112.78683 | W100: =Model!Y184 -> 104.48827 | X100: =Model!AD184 -> 105.48812 | Y100: =Model!AE184 -> 102.5 | Z100: =Model!AF184 -> 102.5 | AA100: =Model!AG184 -> 102.5
C101: Cash Conversion Cycle | G101: =G98+G99-G100 -> 165.56594 | H101: =H98+H99-H100 -> 156.48461 | I101: =I98+I99-I100 -> 154.05579 | J101: =J98+J99-J100 -> 160.84959 | K101: =K98+K99-K100 -> 27.004779 | L101: =L98+L99-L100 -> 169 | M101: =M98+M99-M100 -> 168 | N101: =N98+N99-N100 -> 168 | ... R101: =R98+R99-R100 -> 165.5 | T101: =T98+T99-T100 -> 195.68718 | U101: =U98+U99-U100 -> 176.01231 | V101: =V98+V99-V100 -> 161.86249 | W101: =W98+W99-W100 -> 165.39281 | X101: =X98+X99-X100 -> 164.55741 | Y101: =Y98+Y99-Y100 -> 168.5 | Z101: =Z98+Z99-Z100 -> 168.5 | AA101: =AA98+AA99-AA100 -> 167.5
C103: Liquidity
C104: Current Ratio | G104: =IF(ISERROR(G38/G51),"NA",(G38/G51)) -> 0.69306702 | H104: =IF(ISERROR(H38/H51),"NA",(H38/H51)) -> 0.71765735 | I104: =IF(ISERROR(I38/I51),"NA",(I38/I51)) -> 0.70191566 | J104: =IF(ISERROR(J38/J51),"NA",(J38/J51)) -> 0.65580664 | K104: =IF(ISERROR(K38/K51),"NA",(K38/K51)) -> 0.31148491 | L104: =IF(ISERROR(L38/L51),"NA",(L38/L51)) -> 0.70772945 | M104: =IF(ISERROR(M38/M51),"NA",(M38/M51)) -> 0.73445429 | N104: =IF(ISERROR(N38/N51),"NA",(N38/N51)) -> 0.73918832 | ... R104: =IF(ISERROR(R38/R51),"NA",(R38/R51)) -> 0.80146677 | T104: =IF(ISERROR(T38/T51),"NA",(T38/T51)) -> 0.75100701 | U104: =IF(ISERROR(U38/U51),"NA",(U38/U51)) -> 0.65154569 | V104: =IF(ISERROR(V38/V51),"NA",(V38/V51)) -> 0.65580664 | W104: =IF(ISERROR(W38/W51),"NA",(W38/W51)) -> 0.73918832 | X104: =IF(ISERROR(X38/X51),"NA",(X38/X51)) -> 0.80146677 | Y104: =IF(ISERROR(Y38/Y51),"NA",(Y38/Y51)) -> 0.86174439 | Z104: =IF(ISERROR(Z38/Z51),"NA",(Z38/Z51)) -> 0.92516089 | AA104: =IF(ISERROR(AA38/AA51),"NA",(AA38/AA51)) -> 0.98417871
C105: Quick Ratio | G105: =IF(ISERROR((G34+G35)/G51),"NA",((G34+G35)/G51)) -> 0.69306702 | H105: =IF(ISERROR((H34+H35)/H51),"NA",((H34+H35)/H51)) -> 0.71765735 | I105: =IF(ISERROR((I34+I35)/I51),"NA",((I34+I35)/I51)) -> 0.70191566 | J105: =IF(ISERROR((J34+J35)/J51),"NA",((J34+J35)/J51)) -> 0.65580664 | K105: =IF(ISERROR((K34+K35)/K51),"NA",((K34+K35)/K51)) -> 0.31148491 | L105: =IF(ISERROR((L34+L35)/L51),"NA",((L34+L35)/L51)) -> 0.70772945 | M105: =IF(ISERROR((M34+M35)/M51),"NA",((M34+M35)/M51)) -> 0.73445429 | N105: =IF(ISERROR((N34+N35)/N51),"NA",((N34+N35)/N51)) -> 0.73918832 | ... R105: =IF(ISERROR((R34+R35)/R51),"NA",((R34+R35)/R51)) -> 0.80146677 | T105: =IF(ISERROR((T34+T35)/T51),"NA",((T34+T35)/T51)) -> 0.75100701 | U105: =IF(ISERROR((U34+U35)/U51),"NA",((U34+U35)/U51)) -> 0.65154569 | V105: =IF(ISERROR((V34+V35)/V51),"NA",((V34+V35)/V51)) -> 0.65580664 | W105: =IF(ISERROR((W34+W35)/W51),"NA",((W34+W35)/W51)) -> 0.73918832 | X105: =IF(ISERROR((X34+X35)/X51),"NA",((X34+X35)/X51)) -> 0.80146677 | Y105: =IF(ISERROR((Y34+Y35)/Y51),"NA",((Y34+Y35)/Y51)) -> 0.86174439 | Z105: =IF(ISERROR((Z34+Z35)/Z51),"NA",((Z34+Z35)/Z51)) -> 0.92516089 | AA105: =IF(ISERROR((AA34+AA35)/AA51),"NA",((AA34+AA35)/AA51)) -> 0.98417871
C106: Cash Ratio | G106: =IF(ISERROR(G34/G51),"NA",(G34/G51)) -> 0.32825706 | H106: =IF(ISERROR(H34/H51),"NA",(H34/H51)) -> 0.35433957 | I106: =IF(ISERROR(I34/I51),"NA",(I34/I51)) -> 0.3323754 | J106: =IF(ISERROR(J34/J51),"NA",(J34/J51)) -> 0.28585784 | K106: =IF(ISERROR(K34/K51),"NA",(K34/K51)) -> 0.31148491 | L106: =IF(ISERROR(L34/L51),"NA",(L34/L51)) -> 0.34026252 | M106: =IF(ISERROR(M34/M51),"NA",(M34/M51)) -> 0.36800785 | N106: =IF(ISERROR(N34/N51),"NA",(N34/N51)) -> 0.37235047 | ... R106: =IF(ISERROR(R34/R51),"NA",(R34/R51)) -> 0.43675622 | T106: =IF(ISERROR(T34/T51),"NA",(T34/T51)) -> 0.32755724 | U106: =IF(ISERROR(U34/U51),"NA",(U34/U51)) -> 0.2651063 | V106: =IF(ISERROR(V34/V51),"NA",(V34/V51)) -> 0.28585784 | W106: =IF(ISERROR(W34/W51),"NA",(W34/W51)) -> 0.37235047 | X106: =IF(ISERROR(X34/X51),"NA",(X34/X51)) -> 0.43675622 | Y106: =IF(ISERROR(Y34/Y51),"NA",(Y34/Y51)) -> 0.49757417 | Z106: =IF(ISERROR(Z34/Z51),"NA",(Z34/Z51)) -> 0.56223735 | AA106: =IF(ISERROR(AA34/AA51),"NA",(AA34/AA51)) -> 0.62264702
A110: x

Sheet Model Output
B1: =Company_Name&" "&"("&Ticker&")"&" Valuation Overview" -> American Express Company (AXP) Valuation Overview | K1: Price Target Scenario: | N1: =Case_Scenario&" Case" -> Base Case | R1: Base Case Check | S1: =IF(N1="Base Case","","Check!") | Y1: P/E
B2: =Cover!C2 -> $ in Millions Except Per Share Data | K2: Current Share Price: | O2: =Share_Price -> 314.89 | Y2: EV/EBITDA
K3: Valuation Date: | O3: =Current_Date -> 46147
B4: ="Multiples Analysis "&"("&S21&")" -> Multiples Analysis (P/E) | I4: Return Summary
I6: Exit Multiple Method
I7: =Cover!I9 -> Implied Enterprise Value: | N7: =Cover!L9 -> 296624.47
I8: =Cover!I10 -> Implied Equity Value: | N8: =Cover!L10 -> 0
I9: =Cover!I12 -> Implied Share Price: | N9: =Cover!L12 -> 0
I10: =Cover!I13 -> % Return: | N10: =Cover!L13 -> 0
I12: =Cover!I15 -> Perpetuity Growth Method
I13: =Cover!I16 -> Implied Enterprise Value: | N13: =Cover!L16 -> 10375.823
I14: =Cover!I17 -> Implied Equity Value: | N14: =Cover!L17 -> 0
I15: =Cover!I19 -> Implied Share Price: | N15: =Cover!L19 -> 0
I16: =Cover!I20 -> % Return: | N16: =Cover!L20 -> 0
E18: Annuals | M18: CAGR | O18: CAGR
B19: Consolidated Financials | E19: =Summary!U6 -> 2024 | F19: =Summary!V6 -> 2025 | G19: =Summary!W6 -> 2026e | H19: =Summary!X6 -> 2027e | I19: =Summary!Y6 -> 2028e | J19: =Summary!Z6 -> 2029e | K19: =Summary!AA6 -> 2030e | M19: Historical | O19: Projected
B21: =Summary!C8 -> Revenue | D21: =Summary!T8 -> 67364 | E21: =Summary!U8 -> 74201 | F21: =Summary!V8 -> 80463 | G21: =Summary!W8 -> 88057.042 | H21: =Summary!X8 -> 97549.504 | I21: =Summary!Y8 -> 104638.91 | J21: =Summary!Z8 -> 111964.78 | K21: =Summary!AA8 -> 118840.28 | M21: =Summary!AC8 -> 0.092909439 | O21: =Summary!AE8 -> 0.081118978 | R21: Multiple Toggle | S21: P/E
B22: =Summary!C9 -> YoY % Growth | E22: =Summary!U9 -> 0.10149338 | F22: =Summary!V9 -> 0.084392394 | G22: =Summary!W9 -> 0.094379309 | H22: =Summary!X9 -> 0.107799 | I22: =Summary!Y9 -> 0.072674931 | J22: =Summary!Z9 -> 0.070011007 | K22: =Summary!AA9 -> 0.061407704
R23: Multiples Analysis | S23: EV/EBITDA | T23: P/E | U23: Chart
B24: =Summary!C11 -> Gross Profit | D24: =Summary!T11 -> 55592 | E24: =Summary!U11 -> 60764 | F24: =Summary!V11 -> 66973 | G24: =Summary!W11 -> 74593.624 | H24: =Summary!X11 -> 84356.371 | I24: =Summary!Y11 -> 91504.218 | J24: =Summary!Z11 -> 98291.244 | K24: =Summary!AA11 -> 104639.02 | M24: =Summary!AC11 -> 0.097599062 | O24: =Summary!AE11 -> 0.093348923 | R24: Entry Multiple | S24: =Valuation!D12 -> 16.606971 | T24: =Valuation!D11 -> 16.643764 | U24: =IF($S$21=$S$23,S24,T24) -> 16.643764
B25: =Summary!C12 -> % Margin | E25: =Summary!U12 -> 0.8189108 | F25: =Summary!V12 -> 0.8323453 | G25: =Summary!W12 -> 0.84710571 | H25: =Summary!X12 -> 0.86475448 | I25: =Summary!Y12 -> 0.87447605 | J25: =Summary!Z12 -> 0.87787643 | K25: =Summary!AA12 -> 0.88050127 | R25: =Model!Y25 -> 2026e | S25: =(Comparables!H10*S30)/(Model!Y61) -> 11.966599 | T25: =(Comparables!$G$10*S30)/Summary!W19 -> 16.273031 | U25: =IF($S$21=$S$23,S25,T25) -> 16.273031
B26: =Summary!C13 -> YoY % Growth | E26: =Summary!U13 -> 0.093034969 | F26: =Summary!V13 -> 0.10218221 | G26: =Summary!W13 -> 0.1137865 | H26: =Summary!X13 -> 0.13087911 | I26: =Summary!Y13 -> 0.084733939 | J26: =Summary!Z13 -> 0.074171722 | K26: =Summary!AA13 -> 0.064581294 | R26: =Summary!AA6 -> 2030e | S26: =(Comparables!H10*S30)/(Model!AG61) -> 7.450621 | T26: =(Comparables!$G$10*S30)/Summary!AA19 -> 9.7731994 | U26: =IF($S$21=$S$23,S26,T26) -> 9.7731994
R27: Exit Multiple | S27: =Valuation!K52 -> 18 | T27: =Valuation!K64/Summary!AA19 -> 0 | U27: =IF($S$21=$S$23,S27,T27) -> 0
B28: =Summary!C27 -> EBITDA | D28: =Summary!T27 -> 12164 | E28: =Summary!U27 -> 14571 | F28: =Summary!V27 -> 15572 | G28: =Summary!W27 -> 18277.747 | H28: =Summary!X27 -> 22207.775 | I28: =Summary!Y27 -> 25108.645 | J28: =Summary!Z27 -> 27242.601 | K28: =Summary!AA27 -> 29356.275 | M28: =Summary!AC27 -> 0.13144642 | O28: =Summary!AE27 -> 0.1351972 | R28: Implied PGM | S28: =Valuation!K71 -> 0 | T28: =Valuation!R64/Summary!AA19 -> 0 | U28: =IF($S$21=$S$23,S28,T28) -> 0
B29: =Summary!C28 -> Margin | E29: =Summary!U28 -> 0.19637202 | F29: =Summary!V28 -> 0.19352995 | G29: =Summary!W28 -> 0.20756713 | H29: =Summary!X28 -> 0.22765646 | I29: =Summary!Y28 -> 0.23995515 | J29: =Summary!Z28 -> 0.24331402 | K29: =Summary!AA28 -> 0.24702293
B30: =Summary!C29 -> YoY % Growth | E30: =Summary!U17 -> 0.22657662 | F30: =Summary!V17 -> 0.069794494 | G30: =Summary!W29 -> 0.17375722 | H30: =Summary!X29 -> 0.21501706 | I30: =Summary!Y29 -> 0.13062405 | J30: =Summary!Z29 -> 0.08498893 | K30: =Summary!AA29 -> 0.077587067 | R30: Financials Multiplier | S30: =IF($B$2="$ in Millions Except Per Share Data",1,IF($B$2="$ in Thousands Except Per Share Data",1000,IF($B$2="$ in Billions Except Per Share Data",0.001,0))) -> 1
B32: =Summary!C19 -> Net Income (Loss) | D32: =Summary!T19 -> 8374 | E32: =Summary!U19 -> 10129 | F32: =Summary!V19 -> 10833 | G32: =Summary!W19 -> 12650.378 | H32: =Summary!X19 -> 15616.162 | I32: =Summary!Y19 -> 17841.062 | J32: =Summary!Z19 -> 19545.188 | K32: =Summary!AA19 -> 21063.727 | M32: =Summary!AC19 -> 0.13738604 | O32: =Summary!AE19 -> 0.14223981
B33: =Summary!C20 -> Margin | E33: =Summary!U20 -> 0.13650759 | F33: =Summary!V20 -> 0.13463331 | G33: =Summary!W20 -> 0.14366118 | H33: =Summary!X20 -> 0.16008448 | I33: =Summary!Y20 -> 0.17050122 | J33: =Summary!Z20 -> 0.1745655 | K33: =Summary!AA20 -> 0.177244
B34: =Summary!C21 -> YoY % Growth | E34: =Summary!U21 -> 0.20957726 | F34: =Summary!V21 -> 0.069503406 | G34: =Summary!W21 -> 0.16776315 | H34: =Summary!X21 -> 0.2344423 | I34: =Summary!Y21 -> 0.14247417 | J34: =Summary!Z21 -> 0.095517096 | K34: =Summary!AA21 -> 0.077693724
B36: =Summary!C23 -> Adj. EPS (Diluted) | D36: =Summary!T23 -> 11.565217 | E36: =Summary!U23 -> 13.753156 | F36: =Summary!V23 -> 15.734195 | G36: =Summary!W23 -> 18.405216 | H36: =Summary!X23 -> 22.840765 | I36: =Summary!Y23 -> 26.164702 | J36: =Summary!Z23 -> 28.740459 | K36: =Summary!AA23 -> 31.056162 | M36: =Summary!AC23 -> 0.16639425 | O36: =Summary!AE23 -> 0.14567293
B37: =Summary!C24 -> YoY % Growth | E37: =Summary!U24 -> 0.18918263 | F37: =Summary!V24 -> 0.14404256 | G37: =Summary!W24 -> 0.16975898 | H37: =Summary!X24 -> 0.24099412 | I37: =Summary!Y24 -> 0.1455265 | J37: =Summary!Z24 -> 0.098443959 | K37: =Summary!AA24 -> 0.080572957
B39: Free Cash Flow | D39: =Model!J112 -> 10845 | E39: =Model!O112 -> 11666 | F39: =Model!T112 -> 8390 | G39: =Model!Y112 -> 5790.2185 | H39: =Model!AD112 -> 9893.1237 | I39: =Model!AE112 -> 15764.522 | J39: =Model!AF112 -> 14554.736 | K39: =Model!AG112 -> 17045.629 | M39: =IFERROR((F39/D39)^(1/2)-1,"N/A") -> -0.12043852 | O39: =IFERROR((K39/G39)^(1/4)-1,"N/A") -> 0.30987399
B40: YoY % Growth | E40: =E39/D39-1 -> 0.075703089 | F40: =F39/E39-1 -> -0.28081605 | G40: =G39/F39-1 -> -0.30986668 | H40: =H39/G39-1 -> 0.70859245 | I40: =I39/H39-1 -> 0.59348276 | J40: =J39/I39-1 -> -0.076741054 | K40: =K39/J39-1 -> 0.17113967
E42: Annuals | M42: Average | O42: Average
B43: Capitalization and Key Ratios | E43: =E19 -> 2024 | F43: =F19 -> 2025 | G43: =G19 -> 2026e | H43: =H19 -> 2027e | I43: =I19 -> 2028e | J43: =J19 -> 2029e | K43: =K19 -> 2030e | M43: Historical | O43: Projected
B44: =Summary!C91 -> Leverage
B45: =Summary!C92 -> Total Debt / EBITDA | D45: =Summary!T92 -> 4.0413515 | E45: =Summary!U92 -> 3.506211 | F45: =Summary!V92 -> 3.7090932 | G45: =Summary!W92 -> 3.2971494 | H45: =Summary!X92 -> 2.7187806 | I45: =Summary!Y92 -> 2.5549035 | J45: =Summary!Z92 -> 2.4978164 | K45: =Summary!AA92 -> 2.4457359 | M45: =AVERAGE(D45:F45) -> 3.7522186 | O45: =AVERAGE(G45:K45) -> 2.7028772
B46: =Summary!C93 -> Total Debt / Equity | D46: =Summary!T93 -> 1.7521118 | E46: =Summary!U93 -> 1.6881113 | F46: =Summary!V93 -> 1.7254586 | G46: =Summary!W93 -> 1.404809 | H46: =Summary!X93 -> 1.1002183 | I46: =Summary!Y93 -> 0.92478632 | J46: =Summary!Z93 -> 0.79519722 | K46: =Summary!AA93 -> 0.69545426 | M46: =AVERAGE(D46:F46) -> 1.7218939 | O46: =AVERAGE(G46:K46) -> 0.98409303
B47: =Summary!C94 -> Total Debt / Total Assets | D47: =Summary!T94 -> 0.18827075 | E47: =Summary!U94 -> 0.18820015 | F47: =Summary!V94 -> 0.1924933 | G47: =Summary!W94 -> 0.18048269 | H47: =Summary!X94 -> 0.16634357 | I47: =Summary!Y94 -> 0.1658036 | J47: =Summary!Z94 -> 0.16122569 | K47: =Summary!AA94 -> 0.1570611 | M47: =AVERAGE(D47:F47) -> 0.18965473 | O47: =AVERAGE(G47:K47) -> 0.16618333
B49: =Summary!C103 -> Liquidity
B50: =Summary!C104 -> Current Ratio | D50: =Summary!T104 -> 0.75100701 | E50: =Summary!U104 -> 0.65154569 | F50: =Summary!V104 -> 0.65580664 | G50: =Summary!W104 -> 0.73918832 | H50: =Summary!X104 -> 0.80146677 | I50: =Summary!Y104 -> 0.86174439 | J50: =Summary!Z104 -> 0.92516089 | K50: =Summary!AA104 -> 0.98417871 | M50: =AVERAGE(D50:F50) -> 0.68611978 | O50: =AVERAGE(G50:K50) -> 0.86234782
B51: =Summary!C105 -> Quick Ratio | D51: =Summary!T105 -> 0.75100701 | E51: =Summary!U105 -> 0.65154569 | F51: =Summary!V105 -> 0.65580664 | G51: =Summary!W105 -> 0.73918832 | H51: =Summary!X105 -> 0.80146677 | I51: =Summary!Y105 -> 0.86174439 | J51: =Summary!Z105 -> 0.92516089 | K51: =Summary!AA105 -> 0.98417871 | M51: =AVERAGE(D51:F51) -> 0.68611978 | O51: =AVERAGE(G51:K51) -> 0.86234782
B52: =Summary!C106 -> Cash Ratio | D52: =Summary!T106 -> 0.32755724 | E52: =Summary!U106 -> 0.2651063 | F52: =Summary!V106 -> 0.28585784 | G52: =Summary!W106 -> 0.37235047 | H52: =Summary!X106 -> 0.43675622 | I52: =Summary!Y106 -> 0.49757417 | J52: =Summary!Z106 -> 0.56223735 | K52: =Summary!AA106 -> 0.62264702 | M52: =AVERAGE(D52:F52) -> 0.29284046 | O52: =AVERAGE(G52:K52) -> 0.49831304
B54: =Summary!C75 -> Profitability
B55: =Summary!C80 -> Return on Assets (ROA) | D55: =Summary!T80 -> 0.03207102 | E55: =Summary!U80 -> 0.037312911 | F55: =Summary!V80 -> 0.036103742 | G55: =Summary!W80 -> 0.038419883 | H55: =Summary!X80 -> 0.043585588 | I55: =Summary!Y80 -> 0.046545302 | J55: =Summary!Z80 -> 0.046591537 | K55: =Summary!AA80 -> 0.046267881 | M55: =AVERAGE(D55:F55) -> 0.035162558 | O55: =AVERAGE(G55:K55) -> 0.044282038
B56: =Summary!C81 -> Return on Equity (ROE) | D56: =Summary!T81 -> 0.29846384 | E56: =Summary!U81 -> 0.33468808 | F56: =Summary!V81 -> 0.32362431 | G56: =Summary!W81 -> 0.30178335 | H56: =Summary!X81 -> 0.28431418 | I56: =Summary!Y81 -> 0.2554587 | J56: =Summary!Z81 -> 0.22559628 | K56: =Summary!AA81 -> 0.20074983 | M56: =AVERAGE(D56:F56) -> 0.31892541 | O56: =AVERAGE(G56:K56) -> 0.25358047
B57: Return on Inv. Capital (ROIC) | D57: =Summary!T82 -> 0.10844903 | E57: =Summary!U82 -> 0.12450678 | F57: =Summary!V82 -> 0.11874123 | G57: =Summary!W82 -> 0.12435326 | H57: =Summary!X82 -> 0.13726231 | I57: =Summary!Y82 -> 0.13487789 | J57: =Summary!Z82 -> 0.12800752 | K57: =Summary!AA82 -> 0.1208352 | M57: =AVERAGE(D57:F57) -> 0.11723235 | O57: =AVERAGE(G57:K57) -> 0.12906724
B59: =Summary!C84 -> Coverage
B60: Interest Expense | D60: =Summary!T85 -> 6849 | E60: =Summary!U85 -> 8252 | F60: =Summary!V85 -> 8234 | G60: =Summary!W85 -> 7891.1521 | H60: =Summary!X85 -> 6947.2617 | I60: =Summary!Y85 -> 6542.4378 | J60: =Summary!Z85 -> 6619.7575 | K60: =Summary!AA85 -> 6714.3255 | M60: =AVERAGE(D60:F60) -> 7778.3333 | O60: =AVERAGE(G60:K60) -> 6942.9869
B61: Capital Expenditures | D61: =Summary!T86 -> 1563 | E61: =Summary!U86 -> 1911 | F61: =Summary!V86 -> 2425 | G61: =Summary!W86 -> 2937.6663 | H61: =Summary!X86 -> 2485.8172 | I61: =Summary!Y86 -> 2327.0066 | J61: =Summary!Z86 -> 3023.0491 | K61: =Summary!AA86 -> 2879.404 | M61: =AVERAGE(D61:F61) -> 1966.3333 | O61: =AVERAGE(G61:K61) -> 2730.5887
B62: EBIT / Interest | D62: =Summary!T87 -> 1.5349686 | E62: =Summary!U87 -> 1.5626515 | F62: =Summary!V87 -> 1.6753704 | G62: =Summary!W87 -> 2.0393385 | H62: =Summary!X87 -> 2.8634592 | I62: =Summary!Y87 -> 3.4782839 | J62: =Summary!Z87 -> 3.7612146 | K62: =Summary!AA87 -> 3.9912623 | M62: =AVERAGE(D62:F62) -> 1.5909968 | O62: =AVERAGE(G62:K62) -> 3.2267117
B63: EBITDA / Interest | D63: =Summary!T88 -> 1.7760257 | E63: =Summary!U88 -> 1.7657538 | F63: =Summary!V88 -> 1.8911829 | G63: =Summary!W88 -> 2.3162331 | H63: =Summary!X88 -> 3.1966228 | I63: =Summary!Y88 -> 3.8378117 | J63: =Summary!Z88 -> 4.1153473 | K63: =Summary!AA88 -> 4.3721853 | M63: =AVERAGE(D63:F63) -> 1.8109875 | O63: =AVERAGE(G63:K63) -> 3.56764
B64: (EBITDA - CapEx) / Interest | D64: =Summary!T89 -> 1.5478172 | E64: =Summary!U89 -> 1.5341735 | F64: =Summary!V89 -> 1.5966723 | G64: =Summary!W89 -> 1.9439596 | H64: =Summary!X89 -> 2.8388103 | I64: =Summary!Y89 -> 3.4821329 | J64: =Summary!Z89 -> 3.6586766 | K64: =Summary!AA89 -> 3.9433404 | M64: =AVERAGE(D64:F64) -> 1.5595544 | O64: =AVERAGE(G64:K64) -> 3.173384
B66: =Summary!C96 -> Efficiency
B67: =Summary!C97 -> Asset Turnover | D67: =Summary!T97 -> 0.25799286 | E67: =Summary!U97 -> 0.27333945 | F67: =Summary!V97 -> 0.26816352 | G67: =Summary!W97 -> 0.26792387 | H67: =Summary!X97 -> 0.26900774 | I67: =Summary!Y97 -> 0.27030133 | J67: =Summary!Z97 -> 0.26447915 | K67: =Summary!AA97 -> 0.25881101 | M67: =AVERAGE(D67:F67) -> 0.26649861 | O67: =AVERAGE(G67:K67) -> 0.26610462
B68: =Summary!C98 -> Days Sales Outstanding | D68: =Summary!T98 -> 318.0713 | E68: =Summary!U98 -> 293.85793 | F68: =Summary!V98 -> 274.64931 | G68: =Summary!W98 -> 269.88108 | H68: =Summary!X98 -> 270.04553 | I68: =Summary!Y98 -> 271 | J68: =Summary!Z98 -> 271 | K68: =Summary!AA98 -> 270 | M68: =AVERAGE(D68:F68) -> 295.52618 | O68: =AVERAGE(G68:K68) -> 270.38532
B69: =Summary!C99 -> Days Inventory Outstanding | D69: =Summary!T99 -> 0 | E69: =Summary!U99 -> 0 | F69: =Summary!V99 -> 0 | G69: =Summary!W99 -> 0 | H69: =Summary!X99 -> 0 | I69: =Summary!Y99 -> 0 | J69: =Summary!Z99 -> 0 | K69: =Summary!AA99 -> 0 | M69: =AVERAGE(D69:F69) -> 0 | O69: =AVERAGE(G69:K69) -> 0
B70: =Summary!C100 -> Days Payables Outstanding (from SG&A) | D70: =Summary!T100 -> 122.38412 | E70: =Summary!U100 -> 117.84562 | F70: =Summary!V100 -> 112.78683 | G70: =Summary!W100 -> 104.48827 | H70: =Summary!X100 -> 105.48812 | I70: =Summary!Y100 -> 102.5 | J70: =Summary!Z100 -> 102.5 | K70: =Summary!AA100 -> 102.5 | M70: =AVERAGE(D70:F70) -> 117.67219 | O70: =AVERAGE(G70:K70) -> 103.49528
B71: =Summary!C101 -> Cash Conversion Cycle | D71: =Summary!T101 -> 195.68718 | E71: =Summary!U101 -> 176.01231 | F71: =Summary!V101 -> 161.86249 | G71: =Summary!W101 -> 165.39281 | H71: =Summary!X101 -> 164.55741 | I71: =Summary!Y101 -> 168.5 | J71: =Summary!Z101 -> 168.5 | K71: =Summary!AA101 -> 167.5 | M71: =AVERAGE(D71:F71) -> 177.85399 | O71: =AVERAGE(G71:K71) -> 166.89004

Sheet Football Field
C1: =Company_Name&" - "&MID(CELL("filename",A1),FIND("]",CELL("filename",A1))+1,255)&": "&Case_Scenario&" Case" -> American Express Company - Football Field: Base Case
C2: =Cover!C2 -> $ in Millions Except Per Share Data
A4: x | O4: Valuation Method: | T4: Downside | U4: Delta | V4: Upside | W4: x
O5: =TEXT(Valuation!E100,"0.0%")&" - "&TEXT(Valuation!E102,"0.0%")&" WACC"&" & "&TEXT(Valuation!G98,"0.0%")&" - "&TEXT(Valuation!I98,"0.0%")&" PGR" -> 7.7% - 8.7% WACC & 1.5% - 2.5% PGR | T5: =Valuation!G100 -> 195.04955 | U5: =V5-T5 -> 20.385916 | V5: =Valuation!I102 -> 215.43546
O6: =TEXT(Valuation!E92,"0.0%")&" - "&TEXT(Valuation!E94,"0.0%")&" WACC"&" & "&TEXT(Valuation!G90,"0.0x")&" - "&TEXT(Valuation!I90,"0.0x")&" Exit Multiple" -> 7.7% - 8.7% WACC & 17.0x - 19.0x Exit Multiple | T6: =Valuation!G92 -> 250.78262 | U6: =V6-T6 -> 27.264041 | V6: =Valuation!I94 -> 278.04666
O8: =Valuation!F176&": "&TEXT(Valuation!G177,"0.0x")&" - "&TEXT(Valuation!I177,"0.0x") -> NTM EV/EBITDA Spread to Comps: 9.9x - 11.9x | T8: =Valuation!G179 -> 209.23348 | U8: =V8-T8 -> 100.49025 | V8: =Valuation!I181 -> 309.72373
O9: =Valuation!F168&": "&TEXT(Valuation!G169,"0.0x")&" - "&TEXT(Valuation!I169,"0.0x") -> NTM EV/EBITDA: 11.5x - 13.5x | T9: =Valuation!G171 -> 197.97414 | U9: =V9-T9 -> 97.988172 | V9: =Valuation!I173 -> 295.96231
O10: =Valuation!F160&": "&TEXT(Valuation!G161,"0.0x")&" - "&TEXT(Valuation!I161,"0.0x") -> NTM P/E Spread to Comps: 16.3x - 18.3x | T10: =Valuation!G163 -> 271.58666 | U10: =V10-T10 -> 101.0125 | V10: =Valuation!I165 -> 372.59916
O11: =Valuation!F152&": "&TEXT(Valuation!G153,"0.0x")&" - "&TEXT(Valuation!I153,"0.0x") -> NTM P/E: 18.6x - 20.6x | T11: =Valuation!G155 -> 309.49702 | U11: =V11-T11 -> 109.43703 | V11: =Valuation!I157 -> 418.93405
O13: =Valuation!F252&": "&TEXT(Valuation!G253,"0.0x")&" - "&TEXT(Valuation!I253,"0.0x") -> 2009-2018 Early Cycle EV/EBITDA Spread to Comps: 12.5x - 14.5x | T13: =Valuation!G255 -> 202.21364 | U13: =V13-T13 -> 39.300331 | V13: =Valuation!I255 -> 241.51397
O14: =Valuation!F244&": "&TEXT(Valuation!G245,"0.0x")&" - "&TEXT(Valuation!I245,"0.0x") -> 2009-2018 Early Cycle EV/EBITDA: 14.8x - 16.8x | T14: =Valuation!G247 -> 99.103102 | U14: =V14-T14 -> 39.300331 | V14: =Valuation!I247 -> 138.40343
O15: =Valuation!F236&": "&TEXT(Valuation!G237,"0.0x")&" - "&TEXT(Valuation!I237,"0.0x") -> 2009-2018 Early Cycle P/E Spread to Comps: 16.1x - 18.1x | T15: =Valuation!G239 -> 267.04261 | U15: =V15-T15 -> 26.408301 | V15: =Valuation!I239 -> 293.45091
O16: =Valuation!F228&": "&TEXT(Valuation!G229,"0.0x")&" - "&TEXT(Valuation!I229,"0.0x") -> 2009-2018 Early Cycle P/E: 13.1x - 15.1x | T16: =Valuation!G231 -> 205.30919 | U16: =V16-T16 -> 26.408301 | V16: =Valuation!I231 -> 231.71749
O18: 52-Week Price Range: | T18: =Share_Price_Low -> 273.61 | U18: =V18-T18 -> 113.88 | V18: =Share_Price_High -> 387.49
O19: Median Value: | T19: =MEDIAN(T5:T18) -> 209.23348 | U19: =MEDIAN(U5:U18) -> 39.300331 | V19: =MEDIAN(V5:V18) -> 293.45091
A20: x | O20: Implied Return (%): | T20: =T19/Share_Price-1 -> -0.33553469 | V20: =V19/Share_Price-1 -> -0.068084383
T22: Reference Points for Price Axis
U24: Price
A25: x | T25: High | U25: =MAX(V5:V18)*1.1 -> 460.82745 | W25: x
T26: Low | U26: =MIN(T5:T18)*0.9 -> 89.192792
A30: x

Sheet Integrity
C1: =Company_Name&" - "&MID(CELL("filename",A1),FIND("]",CELL("filename",A1))+1,255) -> American Express Company - Integrity
C3: Integrity
C4: Metric
C6: Model:
C7: Balance Sheet Check: | D7: =SUM(Model!F158:AG158) -> 0
C8: Base Case: | D8: =IF(Case_Scenario="Base","OK!","Check!") -> OK!
C9: Interest Expense: | D9: =IF(Model!C8="On","OK!","CHECK - OFF") -> OK!
C10: Valuation Date:
C12: Formatting:
C13: Valuation Sensitivity Tables: | D13: =SUM(Valuation!F84,Valuation!K84,Valuation!P84,Valuation!F143:F147,Valuation!L143:L147,Valuation!F219:F223,Valuation!L219:L223) -> 0
C14: WACC Tables: | D14: =SUM(WACC!Q20,WACC!N33:N37) -> 0
C16: Font Toggles:
C17: Cover: | D17: =Cover!$Q$2 -> Report
C18: Revenue Build: | D18: ='Revenue Build'!$C$22 -> Report
C19: Model: | D19: =Model!$C$5 -> Report
C20: WACC | D20: =WACC!R5 -> Report
C21: Valuation: | D21: =Valuation!$R$2 -> Report
C23: Change Log
C24: Date | D24: Version | E24: Operator | F24: Revisions
C25: 44476 | D25: v01 | E25: Nate Latimer | F25: Top Down / Bottom Up toggle integration and Capital IQ comps sheet w/ ID Locator
C26: 44476 | D26: v02 | E26: Carson Shaner | F26: Formulas for EBIT/EBITDA margins on earnings sheets
C27: 44480 | D27: v03 | E27: Nate Latimer | F27: Historical driver adjustments to reflect Top Down / Bottom Up Toggle
C28: 44488 | D28: v04 | E28: Nate Latimer | F28: Bug fixes to model output, comps sheet and WACC Comps Relevered Beta
C29: 44489 | D29: v05 | E29: Lilianna Ruby | F29: Changed the year end driver in 2021 and 2022 to correctly pull operating margins
C30: 44491 | D30: v06 | E30: Lilianna Ruby | F30: Changed the first page to add 365 to your previous fiscal year
C31: 44496 | D31: v07 | E31: Carson Shaner | F31: Changed Model Output FCF formula, broke apart D&A for historical periods, added checks for EPS & EBITDA in Valuation sensitivity tables, added segment D&A breakdown, linked and fixed SOTP valuation
C32: 44503 | D32: v08 | E32: Lilianna Ruby | F32: Changed average of comps on valuation tab to average all peers not just the first one
C33: 44512 | D33: v09 | E33: Lilianna Ruby | F33: Rolled model forward to reflect 3Q'21. Also changed the multiples tab so the quarters roll forward and end on correct date.
C34: 44522 | D34: v10 | E34: Lilianna Ruby | F34: Fully fixed the multiples tab so it is automatic and fully functional. Also fixed definition of NTM_EPS and NTM_EBITDA
C35: 44582 | D35: v13 | E35: Carson Shaner | F35: Changed EPS, EBITDA, shares, tax rate, etc., to formulas so we do not have to hardcode them.
C36: 44584 | D36: v14 | E36: Lilianna Ruby | F36: Changed discount factor to mid year
... C47: 45581 | D47: v25 | E47: Conor McCabe | F47: Added font toggle to integrity tab for WACC tab. Formatted Comparables Tab.

Sheet Revenue Build
C1: =Company_Name&" - "&MID(CELL("filename",A1),FIND("]",CELL("filename",A1))+1,255)&": "&Case_Scenario&" Case" -> American Express Company - Revenue Build: Base Case
C2: =Cover!C2 -> $ in Millions Except Per Share Data
A4: x | C4: Segments
C6: =C30&" Methodology" -> Total Company Revenue Methodology
C7: Segment
C8: =C33&" Methodology" -> Discount Revenue Methodology
C9: =IF(Company_Rev_Methodology="Segment","Segment",IF(Company_Rev_Methodology="Activity-Based","Activity-Based",IF(Company_Rev_Methodology="Backlog","Backlog",IF(Company_Rev_Methodology="Mixed",D9,"--")))) -> Segment | D9: Backlog
C10: =C41&" Methodology" -> Net Card Fees Revenue Methodology
C11: =IF(Company_Rev_Methodology="Segment","Segment",IF(Company_Rev_Methodology="Activity-Based","Activity-Based",IF(Company_Rev_Methodology="Backlog","Backlog",IF(Company_Rev_Methodology="Mixed",D11,"--")))) -> Segment | D11: Activity-Based
C12: =C45&" Methodology" -> Service Fees and Other Revenue Methodology
C13: =IF(Company_Rev_Methodology="Segment","Segment",IF(Company_Rev_Methodology="Activity-Based","Activity-Based",IF(Company_Rev_Methodology="Backlog","Backlog",IF(Company_Rev_Methodology="Mixed",D13,"--")))) -> Segment | D13: Segment
C14: =#REF!&" Methodology" -> #REF!
C15: =IF(Company_Rev_Methodology="Segment","Segment",IF(Company_Rev_Methodology="Activity-Based","Activity-Based",IF(Company_Rev_Methodology="Backlog","Backlog",IF(Company_Rev_Methodology="Mixed",D15,"--")))) -> Segment | D15: Segment
C16: =#REF!&" Methodology" -> #REF!
C17: =IF(Company_Rev_Methodology="Segment","Segment",IF(Company_Rev_Methodology="Activity-Based","Activity-Based",IF(Company_Rev_Methodology="Backlog","Backlog",IF(Company_Rev_Methodology="Mixed",D17,"--")))) -> Segment | D17: Segment
C18: =#REF!&" Methodology" -> #REF!
C19: =IF(Company_Rev_Methodology="Segment","Segment",IF(Company_Rev_Methodology="Activity-Based","Activity-Based",IF(Company_Rev_Methodology="Backlog","Backlog",IF(Company_Rev_Methodology="Mixed",D19,"--")))) -> Segment | D19: Segment
C21: Font Toggle
C22: Report
C24: Annual vs. Quarterly
C25: Quarterly
J26: 1 | O26: 2 | T26: 3 | Y26: 4 | AD26: 5 | AE26: 6 | AF26: 7 | AG26: 8
AI27: CAGR
A28: x | C28: Summary | F28: =Model!F$25 -> 1Q23 | G28: =Model!G$25 -> 2Q23 | H28: =Model!H$25 -> 3Q23 | I28: =Model!I$25 -> 4Q23 | J28: =Model!J$25 -> 2023 | K28: =Model!K$25 -> 1Q24 | L28: =Model!L$25 -> 2Q24 | M28: =Model!M$25 -> 3Q24 | ... AG28: =Model!AG$25 -> 2030e | AI28: Historical | AJ28: Projected
C30: Total Company Revenue | F30: ='Segment Analysis'!F7 -> 15714 | G30: ='Segment Analysis'!G7 -> 16724 | H30: ='Segment Analysis'!H7 -> 17179 | I30: ='Segment Analysis'!I7 -> 17747 | J30: ='Segment Analysis'!J7 -> 67364 | K30: ='Segment Analysis'!K7 -> 17807 | L30: ='Segment Analysis'!L7 -> 18397 | M30: ='Segment Analysis'!M7 -> 18779 | ... U30: ='Segment Analysis'!U7 -> 20880 | V30: =SUM(V33,V37,V41,V45) -> 21729.203 | W30: =SUM(W33,W37,W41,W45) -> 22323.439 | X30: =SUM(X33,X37,X41,X45) -> 23124.4 | Y30: =SUM(U30:X30) -> 88057.042 | Z30: =SUM(Z33,Z37,Z41,Z45) -> 23062.491 | AA30: =SUM(AA33,AA37,AA41,AA45) -> 24123.963 | AB30: =SUM(AB33,AB37,AB41,AB45) -> 24704.225 | AC30: =SUM(AC33,AC37,AC41,AC45) -> 25658.825 | AD30: =SUM(Z30:AC30) -> 97549.504 | AE30: =SUM(AE33,AE37,AE41,AE45) -> 104638.91 | AF30: =SUM(AF33,AF37,AF41,AF45) -> 111964.78 | AG30: =SUM(AG33,AG37,AG41,AG45) -> 118840.28 | AI30: =IFERROR((T30/J30)^(1/3)-1,"--") -> 0.06101808 | AJ30: =IFERROR((AG30/T30)^(1/5)-1,"--") -> 0.081118978
C31: =IF($C$25="Quarterly","% Growth QoQ","% Growth YoY") -> % Growth QoQ | G31: =IF($C$25="Annual",'Segment Analysis'!G145,'Segment Analysis'!G163) -> 0.064273896 | H31: =IF($C$25="Annual",'Segment Analysis'!H145,'Segment Analysis'!H163) -> 0.02720641 | I31: =IF($C$25="Annual",'Segment Analysis'!I145,'Segment Analysis'!I163) -> 0.033063624 | J31: =IF($C$25="Annual",'Segment Analysis'!J145,'Segment Analysis'!J145) -> 0 | K31: =IF($C$25="Annual",'Segment Analysis'!K145,'Segment Analysis'!K145) -> 0.13319333 | L31: =IF($C$25="Annual",'Segment Analysis'!L145,'Segment Analysis'!L145) -> 0.10003588 | M31: =IF($C$25="Annual",'Segment Analysis'!M145,'Segment Analysis'!M145) -> 0.09313697 | N31: =IF($C$25="Annual",'Segment Analysis'!N145,'Segment Analysis'!N145) -> 0.082887249 | O31: =IF($C$25="Annual",'Segment Analysis'!O145,'Segment Analysis'!O145) -> 0.10149338 | P31: =IF($C$25="Annual",'Segment Analysis'!P145,'Segment Analysis'!P145) -> 0.06323356 | Q31: =IF($C$25="Annual",'Segment Analysis'!Q145,'Segment Analysis'!Q145) -> 0.083491874 | ... U31: =IF($C$25="Annual",'Segment Analysis'!U145,'Segment Analysis'!U145) -> 0.10283632 | V31: =IFERROR(V30/U30-1,"--") -> 0.040670642 | W31: =IFERROR(W30/V30-1,"--") -> 0.027347342 | X31: =IFERROR(X30/W30-1,"--") -> 0.035879841 | Y31: =IFERROR(Y30/T30-1,"--") -> 0.094379309 | Z31: =IFERROR(Z30/X30-1,"--") -> -0.0026772245 | AA31: =IFERROR(AA30/Z30-1,"--") -> 0.046025884 | AB31: =IFERROR(AB30/AA30-1,"--") -> 0.02405334 | AC31: =IFERROR(AC30/AB30-1,"--") -> 0.038641194 | AD31: =IFERROR(AD30/Y30-1,"--") -> 0.107799 | AE31: =IFERROR(AE30/AD30-1,"--") -> 0.072674931 | AF31: =IFERROR(AF30/AE30-1,"--") -> 0.070011007 | AG31: =IFERROR(AG30/AF30-1,"--") -> 0.061407704
C33: ='Segment Analysis'!C8 -> Discount Revenue | F33: ='Segment Analysis'!F8 -> 7947 | G33: ='Segment Analysis'!G8 -> 8481 | H33: ='Segment Analysis'!H8 -> 8408 | I33: ='Segment Analysis'!I8 -> 8580 | J33: ='Segment Analysis'!J8 -> 33416 | K33: ='Segment Analysis'!K8 -> 8380 | L33: ='Segment Analysis'!L8 -> 8855 | M33: ='Segment Analysis'!M8 -> 8780 | ... U33: ='Segment Analysis'!U8 -> 9512 | V33: =IF(Segment1_Rev_Methodology="Segment",V51,IF(Segment1_Rev_Methodology="Activity-Based",#REF!,IF(Segment1_Rev_Methodology="Backlog",V147,"--"))) -> 10082.72 | W33: =IF(Segment1_Rev_Methodology="Segment",W51,IF(Segment1_Rev_Methodology="Activity-Based",#REF!,IF(Segment1_Rev_Methodology="Backlog",W147,"--"))) -> 10233.961 | X33: =IF(Segment1_Rev_Methodology="Segment",X51,IF(Segment1_Rev_Methodology="Activity-Based",#REF!,IF(Segment1_Rev_Methodology="Backlog",X147,"--"))) -> 10796.829 | Y33: =SUM(U33:X33) -> 40625.509 | Z33: =IF(Segment1_Rev_Methodology="Segment",Z51,IF(Segment1_Rev_Methodology="Activity-Based",#REF!,IF(Segment1_Rev_Methodology="Backlog",Z147,"--"))) -> 10688.86 | AA33: =IF(Segment1_Rev_Methodology="Segment",AA51,IF(Segment1_Rev_Methodology="Activity-Based",#REF!,IF(Segment1_Rev_Methodology="Backlog",AA147,"--"))) -> 11437.081 | AB33: =IF(Segment1_Rev_Methodology="Segment",AB51,IF(Segment1_Rev_Methodology="Activity-Based",#REF!,IF(Segment1_Rev_Methodology="Backlog",AB147,"--"))) -> 11665.822 | AC33: =IF(Segment1_Rev_Methodology="Segment",AC51,IF(Segment1_Rev_Methodology="Activity-Based",#REF!,IF(Segment1_Rev_Methodology="Backlog",AC147,"--"))) -> 12307.442 | AD33: =SUM(Z33:AC33) -> 46099.206 | AE33: =IF(Segment1_Rev_Methodology="Segment",AE51,IF(Segment1_Rev_Methodology="Activity-Based",#REF!,IF(Segment1_Rev_Methodology="Backlog",AE147,"--"))) -> 49326.15 | AF33: =IF(Segment1_Rev_Methodology="Segment",AF51,IF(Segment1_Rev_Methodology="Activity-Based",#REF!,IF(Segment1_Rev_Methodology="Backlog",AF147,"--"))) -> 52285.719 | AG33: =IF(Segment1_Rev_Methodology="Segment",AG51,IF(Segment1_Rev_Methodology="Activity-Based",#REF!,IF(Segment1_Rev_Methodology="Backlog",AG147,"--"))) -> 55422.862 | AI33: =IFERROR((T33/J33)^(1/3)-1,"--") -> 0.038268275 | AJ33: =IFERROR((AG33/T33)^(1/5)-1,"--") -> 0.081835297
C34: =IF($C$25="Quarterly","% Growth QoQ","% Growth YoY") -> % Growth QoQ | G34: =IF($C$25="Annual",'Segment Analysis'!G146,'Segment Analysis'!G164) -> 0.067195168 | H34: =IF($C$25="Annual",'Segment Analysis'!H146,'Segment Analysis'!H164) -> -0.0086074755 | I34: =IF($C$25="Annual",'Segment Analysis'!I146,'Segment Analysis'!I164) -> 0.020456708 | J34: =IF($C$25="Annual",'Segment Analysis'!J148,'Segment Analysis'!J148) -> 0 | K34: =IF($C$25="Annual",'Segment Analysis'!K146,'Segment Analysis'!K146) -> 0.05448597 | L34: =IF($C$25="Annual",'Segment Analysis'!L146,'Segment Analysis'!L146) -> 0.044098573 | M34: =IF($C$25="Annual",'Segment Analysis'!M146,'Segment Analysis'!M146) -> 0.044243578 | N34: =IF($C$25="Annual",'Segment Analysis'!N146,'Segment Analysis'!N146) -> 0.06958042 | O34: =IF($C$25="Annual",'Segment Analysis'!O146,'Segment Analysis'!O146) -> 0.053148192 | P34: =IF($C$25="Annual",'Segment Analysis'!P146,'Segment Analysis'!P146) -> 0.043317422 | Q34: =IF($C$25="Annual",'Segment Analysis'!Q146,'Segment Analysis'!Q146) -> 0.057142857 | R34: =IF($C$25="Annual",'Segment Analysis'!R146,'Segment Analysis'!R146) -> 0.072095672 | ... U34: =IF($C$25="Annual",'Segment Analysis'!U146,'Segment Analysis'!U146) -> 0.087956079 | V34: =IFERROR(V33/U33-1,"--") -> 0.06 | W34: =IFERROR(W33/V33-1,"--") -> 0.015 | X34: =IFERROR(X33/W33-1,"--") -> 0.055 | Y34: =IFERROR(Y33/T33-1,"--") -> 0.086214525 | Z34: =IFERROR(Z33/X33-1,"--") -> -0.01 | AA34: =IFERROR(AA33/Z33-1,"--") -> 0.07 | AB34: =IFERROR(AB33/AA33-1,"--") -> 0.02 | AC34: =IFERROR(AC33/AB33-1,"--") -> 0.055 | AD34: =IFERROR(AD33/Y33-1,"--") -> 0.13473545 | AE34: =IFERROR(AE33/AD33-1,"--") -> 0.07 | AF34: =IFERROR(AF33/AE33-1,"--") -> 0.06 | AG34: =IFERROR(AG33/AF33-1,"--") -> 0.06
C35: % of Total Revenue | F35: ='Segment Analysis'!F14 -> 0.50572738 | G35: ='Segment Analysis'!G14 -> 0.50711552 | H35: ='Segment Analysis'!H14 -> 0.48943478 | I35: ='Segment Analysis'!I14 -> 0.48346199 | J35: ='Segment Analysis'!J14 -> 0.4960513 | K35: ='Segment Analysis'!K14 -> 0.47060145 | L35: ='Segment Analysis'!L14 -> 0.48132848 | M35: ='Segment Analysis'!M14 -> 0.46754353 | ... U35: ='Segment Analysis'!U14 -> 0.45555556 | V35: =V33/V$30 -> 0.46401702 | W35: =W33/W$30 -> 0.45844015 | X35: =X33/X$30 -> 0.46690199 | Y35: =Y33/Y$30 -> 0.46135446 | Z35: =Z33/Z$30 -> 0.4634738 | AA35: =AA33/AA$30 -> 0.47409626 | AB35: =AB33/AB$30 -> 0.47221973 | AC35: =AC33/AC$30 -> 0.47965728 | ... AG35: =AG33/AG$30 -> 0.46636427
C37: ='Segment Analysis'!C11 -> Interest Income | F37: ='Segment Analysis'!F11 -> 4416 | G37: ='Segment Analysis'!G11 -> 4775 | H37: ='Segment Analysis'!H11 -> 5240 | I37: ='Segment Analysis'!I11 -> 5552 | J37: ='Segment Analysis'!J11 -> 19983 | K37: ='Segment Analysis'!K11 -> 5775 | L37: ='Segment Analysis'!L11 -> 5794 | M37: ='Segment Analysis'!M11 -> 6149 | ... U37: ='Segment Analysis'!U11 -> 6665 | V37: =V57 -> 6702.48 | W37: =W57 -> 6898.275 | X37: =X57 -> 6937.0668 | Y37: =SUM(U37:X37) -> 27202.822 | Z37: =Z57 -> 6930.1297 | AA37: =AA57 -> 6999.431 | AB37: =AB57 -> 7174.4168 | AC37: =AC57 -> 7353.7772 | AD37: =SUM(Z37:AC37) -> 28457.755 | AE37: =IF(Segment1_Rev_Methodology="Segment",AE57,IF(Segment1_Rev_Methodology="Activity-Based",#REF!,IF(Segment1_Rev_Methodology="Backlog",AE150,"--"))) -> 29738.354 | AF37: =IF(Segment1_Rev_Methodology="Segment",AF57,IF(Segment1_Rev_Methodology="Activity-Based",#REF!,IF(Segment1_Rev_Methodology="Backlog",AF150,"--"))) -> 31522.655 | AG37: =IF(Segment1_Rev_Methodology="Segment",AG57,IF(Segment1_Rev_Methodology="Activity-Based",#REF!,IF(Segment1_Rev_Methodology="Backlog",AG150,"--"))) -> 33571.628 | AI37: =IFERROR((T37/J37)^(1/3)-1,"--") -> 0.086046571 | AJ37: =IFERROR((AG37/T37)^(1/5)-1,"--") -> 0.055730996
C38: =IF($C$25="Quarterly","% Growth QoQ","% Growth YoY") -> % Growth QoQ | G38: =IF($C$25="Annual",'Segment Analysis'!G150,'Segment Analysis'!G167) -> 0 | H38: =IF($C$25="Annual",'Segment Analysis'!H150,'Segment Analysis'!H167) -> 0 | I38: =IF($C$25="Annual",'Segment Analysis'!I150,'Segment Analysis'!I167) -> 0 | J38: =IF($C$25="Annual",'Segment Analysis'!J152,'Segment Analysis'!J152) -> 0 | L38: =IF($C$25="Annual",'Segment Analysis'!L149,'Segment Analysis'!Q149) -> 0.081118398 | M38: =IF($C$25="Annual",'Segment Analysis'!M149,'Segment Analysis'!R149) -> 0.076109937 | N38: =IF($C$25="Annual",'Segment Analysis'!N149,'Segment Analysis'!S149) -> 0.083100214 | O38: =IF($C$25="Annual",'Segment Analysis'!O149,'Segment Analysis'!T149) -> 0.075772221 | P38: =IF($C$25="Annual",'Segment Analysis'!P149,'Segment Analysis'!U149) -> 0.086389568 | Q38: =IF($C$25="Annual",'Segment Analysis'!Q149,'Segment Analysis'!V149) -> 0.07 | R38: =IF($C$25="Annual",'Segment Analysis'!R149,'Segment Analysis'!W149) -> 0.042507934 | S38: =IF($C$25="Annual",'Segment Analysis'!S149,'Segment Analysis'!X149) -> 0.053945123 | ... U38: =IF($C$25="Annual",'Segment Analysis'!U149,'Segment Analysis'!Z149) -> 0.039779405 | V38: =IFERROR(V37/U37-1,"--") -> 0.0056234059 | W38: =IFERROR(W37/V37-1,"--") -> 0.029212321 | X38: =IFERROR(X37/W37-1,"--") -> 0.0056234059 | Y38: =IFERROR(Y37/T37-1,"--") -> 0.062693249 | Z38: =IFERROR(Z37/X37-1,"--") -> -0.001 | AA38: =IFERROR(AA37/Z37-1,"--") -> 0.01 | AB38: =IFERROR(AB37/AA37-1,"--") -> 0.025 | AC38: =IFERROR(AC37/AB37-1,"--") -> 0.025 | AD38: =IFERROR(AD37/Y37-1,"--") -> 0.046132457 | AE38: =IFERROR(AE37/AD37-1,"--") -> 0.045 | AF38: =IFERROR(AF37/AE37-1,"--") -> 0.06 | AG38: =IFERROR(AG37/AF37-1,"--") -> 0.065
C39: % of Total Revenue | F39: ='Segment Analysis'!F17 -> 0.28102329 | G39: ='Segment Analysis'!G17 -> 0.28551782 | H39: ='Segment Analysis'!H17 -> 0.30502358 | I39: ='Segment Analysis'!I17 -> 0.31284161 | J39: ='Segment Analysis'!J17 -> 0.29664212 | K39: ='Segment Analysis'!K17 -> 0.32431066 | L39: ='Segment Analysis'!L17 -> 0.31494265 | M39: ='Segment Analysis'!M17 -> 0.32744023 | ... U39: ='Segment Analysis'!U17 -> 0.31920498 | V39: =V37/V$30 -> 0.30845494 | W39: =W37/W$30 -> 0.30901489 | X39: =X37/X$30 -> 0.29998905 | Y39: =Y37/Y$30 -> 0.30892273 | Z39: =Z37/Z$30 -> 0.30049355 | AA39: =AA37/AA$30 -> 0.29014433 | AB39: =AB37/AB$30 -> 0.29041255 | AC39: =AC37/AC$30 -> 0.28659836 | ... AG39: =AG37/AG$30 -> 0.28249367
C41: ='Segment Analysis'!C9 -> Net Card Fees Revenue | F41: ='Segment Analysis'!F9 -> 1713 | G41: ='Segment Analysis'!G9 -> 1789 | H41: ='Segment Analysis'!H9 -> 1846 | I41: ='Segment Analysis'!I9 -> 1907 | J41: ='Segment Analysis'!J9 -> 7255 | K41: ='Segment Analysis'!K9 -> 1974 | L41: ='Segment Analysis'!L9 -> 2060 | M41: ='Segment Analysis'!M9 -> 2170 | ... U41: ='Segment Analysis'!U9 -> 2752 | V41: =IF(Segment2_Rev_Methodology="Segment",V63,IF(Segment2_Rev_Methodology="Activity-Based",V85,IF(Segment2_Rev_Methodology="Backlog",V159,"--"))) -> 2889.6 | W41: =IF(Segment2_Rev_Methodology="Segment",W63,IF(Segment2_Rev_Methodology="Activity-Based",W85,IF(Segment2_Rev_Methodology="Backlog",W159,"--"))) -> 3034.08 | X41: =IF(Segment2_Rev_Methodology="Segment",X63,IF(Segment2_Rev_Methodology="Activity-Based",X85,IF(Segment2_Rev_Methodology="Backlog",X159,"--"))) -> 3216.1248 | Y41: =SUM(U41:X41) -> 11891.805 | Z41: =IF(Segment2_Rev_Methodology="Segment",Z63,IF(Segment2_Rev_Methodology="Activity-Based",Z85,IF(Segment2_Rev_Methodology="Backlog",Z159,"--"))) -> 3312.6085 | AA41: =IF(Segment2_Rev_Methodology="Segment",AA63,IF(Segment2_Rev_Methodology="Activity-Based",AA85,IF(Segment2_Rev_Methodology="Backlog",AA159,"--"))) -> 3445.1129 | AB41: =IF(Segment2_Rev_Methodology="Segment",AB63,IF(Segment2_Rev_Methodology="Activity-Based",AB85,IF(Segment2_Rev_Methodology="Backlog",AB159,"--"))) -> 3514.0151 | AC41: =IF(Segment2_Rev_Methodology="Segment",AC63,IF(Segment2_Rev_Methodology="Activity-Based",AC85,IF(Segment2_Rev_Methodology="Backlog",AC159,"--"))) -> 3619.4356 | AD41: =SUM(Z41:AC41) -> 13891.172 | AE41: =IF(Segment2_Rev_Methodology="Segment",AE63,IF(Segment2_Rev_Methodology="Activity-Based",AE85,IF(Segment2_Rev_Methodology="Backlog",AE159,"--"))) -> 15835.936 | AF41: =IF(Segment2_Rev_Methodology="Segment",AF63,IF(Segment2_Rev_Methodology="Activity-Based",AF85,IF(Segment2_Rev_Methodology="Backlog",AF159,"--"))) -> 17736.249 | AG41: =IF(Segment2_Rev_Methodology="Segment",AG63,IF(Segment2_Rev_Methodology="Activity-Based",AG85,IF(Segment2_Rev_Methodology="Backlog",AG159,"--"))) -> 18800.424 | AI41: =IFERROR((T41/J41)^(1/3)-1,"--") -> 0.11263527 | AJ41: =IFERROR((AG41/T41)^(1/5)-1,"--") -> 0.13473474
C42: % Growth | G42: =IF($C$25="Annual",'Segment Analysis'!G147,'Segment Analysis'!G165) -> 0.044366608 | H42: =IF($C$25="Annual",'Segment Analysis'!H147,'Segment Analysis'!H165) -> 0.031861375 | I42: =IF($C$25="Annual",'Segment Analysis'!I147,'Segment Analysis'!I165) -> 0.03304442 | J42: =IF($C$25="Annual",'Segment Analysis'!J156,'Segment Analysis'!J156) -> 0 | K42: =IF($C$25="Annual",'Segment Analysis'!K147,'Segment Analysis'!K165) -> 0.035133718 | L42: =IF($C$25="Annual",'Segment Analysis'!L147,'Segment Analysis'!L165) -> 0.043566363 | M42: =IF($C$25="Annual",'Segment Analysis'!M147,'Segment Analysis'!M165) -> 0.053398058 | N42: =IF($C$25="Annual",'Segment Analysis'!N147,'Segment Analysis'!N165) -> 0.034562212 | O42: ='Segment Analysis'!O147 -> 0.16457615 | P42: =IF($C$25="Annual",'Segment Analysis'!P147,'Segment Analysis'!P165) -> 0.039198218 | Q42: =IF($C$25="Annual",'Segment Analysis'!Q147,'Segment Analysis'!Q165) -> 0.063009001 | R42: =IF($C$25="Annual",'Segment Analysis'!R147,'Segment Analysis'!R165) -> 0.028629032 | S42: =IF($C$25="Annual",'Segment Analysis'!S147,'Segment Analysis'!S165) -> 0.030576245 | T42: ='Segment Analysis'!T147 -> 0.18274352 | U42: =IF($C$25="Annual",'Segment Analysis'!U147,'Segment Analysis'!U165) -> 0.04678585 | V42: =IFERROR(V41/U41-1,"--") -> 0.05 | W42: =IFERROR(W41/V41-1,"--") -> 0.05 | X42: =IFERROR(X41/W41-1,"--") -> 0.06 | Y42: =IFERROR(Y41/T41-1,"--") -> 0.19001349 | Z42: =IFERROR(Z41/X41-1,"--") -> 0.03 | AA42: =IFERROR(AA41/Z41-1,"--") -> 0.04 | AB42: =IFERROR(AB41/AA41-1,"--") -> 0.02 | AC42: =IFERROR(AC41/AB41-1,"--") -> 0.03 | AD42: =IFERROR(AD41/Y41-1,"--") -> 0.16812985 | AE42: =IFERROR(AE41/AD41-1,"--") -> 0.14 | AF42: =IFERROR(AF41/AE41-1,"--") -> 0.12 | AG42: =IFERROR(AG41/AF41-1,"--") -> 0.06
C43: % of Total Revenue | F43: ='Segment Analysis'!F15 -> 0.10901107 | G43: ='Segment Analysis'!G15 -> 0.10697202 | H43: ='Segment Analysis'!H15 -> 0.10745678 | I43: ='Segment Analysis'!I15 -> 0.10745478 | J43: ='Segment Analysis'!J15 -> 0.10769847 | K43: ='Segment Analysis'!K15 -> 0.11085528 | L43: ='Segment Analysis'!L15 -> 0.11197478 | M43: ='Segment Analysis'!M15 -> 0.11555461 | ... U43: ='Segment Analysis'!U15 -> 0.13180077 | V43: =V41/V$30 -> 0.13298233 | W43: =W41/W$30 -> 0.13591454 | X43: =X41/X$30 -> 0.13907927 | Y43: =Y41/Y$30 -> 0.13504661 | Z43: =Z41/Z$30 -> 0.1436362 | AA43: =AA41/AA$30 -> 0.14280875 | AB43: =AB41/AB$30 -> 0.14224349 | AC43: =AC41/AC$30 -> 0.14106007 | ... AG43: =AG41/AG$30 -> 0.15819908
C45: ='Segment Analysis'!C10 -> Service Fees and Other Revenue | F45: ='Segment Analysis'!F10 -> 1638 | G45: ='Segment Analysis'!G10 -> 1679 | H45: ='Segment Analysis'!H10 -> 1685 | I45: ='Segment Analysis'!I10 -> 1708 | J45: ='Segment Analysis'!J10 -> 6710 | K45: ='Segment Analysis'!K10 -> 1678 | L45: ='Segment Analysis'!L10 -> 1688 | M45: ='Segment Analysis'!M10 -> 1680 | ... U45: ='Segment Analysis'!U10 -> 1951 | V45: =IF(Segment3_Rev_Methodology="Segment",V69,IF(Segment3_Rev_Methodology="Activity-Based",V97,IF(Segment3_Rev_Methodology="Backlog",V171,"--"))) -> 2054.403 | W45: =IF(Segment3_Rev_Methodology="Segment",W69,IF(Segment3_Rev_Methodology="Activity-Based",W97,IF(Segment3_Rev_Methodology="Backlog",W171,"--"))) -> 2157.1231 | X45: =IF(Segment3_Rev_Methodology="Segment",X69,IF(Segment3_Rev_Methodology="Activity-Based",X97,IF(Segment3_Rev_Methodology="Backlog",X171,"--"))) -> 2174.3801 | Y45: =SUM(U45:X45) -> 8336.9063 | Z45: =IF(Segment3_Rev_Methodology="Segment",Z69,IF(Segment3_Rev_Methodology="Activity-Based",Z97,IF(Segment3_Rev_Methodology="Backlog",Z171,"--"))) -> 2130.8925 | AA45: =IF(Segment3_Rev_Methodology="Segment",AA69,IF(Segment3_Rev_Methodology="Activity-Based",AA97,IF(Segment3_Rev_Methodology="Backlog",AA171,"--"))) -> 2242.3382 | AB45: =IF(Segment3_Rev_Methodology="Segment",AB69,IF(Segment3_Rev_Methodology="Activity-Based",AB97,IF(Segment3_Rev_Methodology="Backlog",AB171,"--"))) -> 2349.9704 | AC45: =IF(Segment3_Rev_Methodology="Segment",AC69,IF(Segment3_Rev_Methodology="Activity-Based",AC97,IF(Segment3_Rev_Methodology="Backlog",AC171,"--"))) -> 2378.1701 | AD45: =SUM(Z45:AC45) -> 9101.3713 | AE45: =IF(Segment3_Rev_Methodology="Segment",AE69,IF(Segment3_Rev_Methodology="Activity-Based",AE97,IF(Segment3_Rev_Methodology="Backlog",AE171,"--"))) -> 9738.4673 | AF45: =IF(Segment3_Rev_Methodology="Segment",AF69,IF(Segment3_Rev_Methodology="Activity-Based",AF97,IF(Segment3_Rev_Methodology="Backlog",AF171,"--"))) -> 10420.16 | AG45: =IF(Segment3_Rev_Methodology="Segment",AG69,IF(Segment3_Rev_Methodology="Activity-Based",AG97,IF(Segment3_Rev_Methodology="Backlog",AG171,"--"))) -> 11045.37 | AI45: =IFERROR((T45/J45)^(1/3)-1,"--") -> 0.036458869 | AJ45: =IFERROR((AG45/T45)^(1/5)-1,"--") -> 0.081335107
C46: % Growth | G46: =IF($C$25="Annual",'Segment Analysis'!G148,'Segment Analysis'!G166) -> 0.025030525 | H46: =IF($C$25="Annual",'Segment Analysis'!H148,'Segment Analysis'!H166) -> 0.0035735557 | I46: =IF($C$25="Annual",'Segment Analysis'!I148,'Segment Analysis'!I166) -> 0.013649852 | J46: =IF($C$25="Annual",'Segment Analysis'!J160,'Segment Analysis'!J160) -> 0 | K46: =IF($C$25="Annual",'Segment Analysis'!K148,'Segment Analysis'!K166) -> -0.017564403 | L46: =IF($C$25="Annual",'Segment Analysis'!L148,'Segment Analysis'!L166) -> 0.0059594756 | M46: =IF($C$25="Annual",'Segment Analysis'!M148,'Segment Analysis'!M166) -> -0.0047393365 | N46: =IF($C$25="Annual",'Segment Analysis'!N148,'Segment Analysis'!N166) -> 0.023214286 | O46: ='Segment Analysis'!O148 -> 0.0081967213 | P46: =IF($C$25="Annual",'Segment Analysis'!P148,'Segment Analysis'!P166) -> 0.0017452007 | Q46: =IF($C$25="Annual",'Segment Analysis'!Q148,'Segment Analysis'!Q166) -> 0.06155633 | R46: =IF($C$25="Annual",'Segment Analysis'!R148,'Segment Analysis'!R166) -> 0.080962801 | S46: =IF($C$25="Annual",'Segment Analysis'!S148,'Segment Analysis'!S166) -> -0.015688259 | T46: ='Segment Analysis'!T148 -> 0.10436068 | U46: =IF($C$25="Annual",'Segment Analysis'!U148,'Segment Analysis'!U166) -> 0.0030848329 | V46: =IFERROR(V45/U45-1,"--") -> 0.053 | W46: =IFERROR(W45/V45-1,"--") -> 0.05 | X46: =IFERROR(X45/W45-1,"--") -> 0.008 | Y46: =IFERROR(Y45/T45-1,"--") -> 0.11590233 | Z46: =IFERROR(Z45/X45-1,"--") -> -0.02 | AA46: =IFERROR(AA45/Z45-1,"--") -> 0.0523 | AB46: =IFERROR(AB45/AA45-1,"--") -> 0.048 | AC46: =IFERROR(AC45/AB45-1,"--") -> 0.012 | AD46: =IFERROR(AD45/Y45-1,"--") -> 0.091696484 | AE46: =IFERROR(AE45/AD45-1,"--") -> 0.07 | AF46: =IFERROR(AF45/AE45-1,"--") -> 0.07 | AG46: =IFERROR(AG45/AF45-1,"--") -> 0.06
C47: % of Total Revenue | F47: ='Segment Analysis'!F16 -> 0.10423826 | G47: ='Segment Analysis'!G16 -> 0.10039464 | H47: ='Segment Analysis'!H16 -> 0.098084871 | I47: ='Segment Analysis'!I16 -> 0.096241618 | J47: ='Segment Analysis'!J16 -> 0.099608099 | K47: ='Segment Analysis'!K16 -> 0.094232605 | L47: ='Segment Analysis'!L16 -> 0.09175409 | M47: ='Segment Analysis'!M16 -> 0.089461633 | ... U47: ='Segment Analysis'!U16 -> 0.093438697 | V47: =V45/V$30 -> 0.094545713 | W47: =W45/W$30 -> 0.096630414 | X47: =X45/X$30 -> 0.094029687 | Y47: =Y45/Y$30 -> 0.094676202 | Z47: =Z45/Z$30 -> 0.09239646 | AA47: =AA45/AA$30 -> 0.092950658 | AB47: =AB45/AB$30 -> 0.095124234 | AC47: =AC45/AC$30 -> 0.092684293 | ... AG47: =AG45/AG$30 -> 0.092942976
A49: x | C49: Growth Rate | F49: =F$28 -> 1Q23 | G49: =G$28 -> 2Q23 | H49: =H$28 -> 3Q23 | I49: =I$28 -> 4Q23 | J49: =J$28 -> 2023 | K49: =K$28 -> 1Q24 | L49: =L$28 -> 2Q24 | M49: =M$28 -> 3Q24 | ... AG49: =AG$28 -> 2030e | AH49: x
C51: =C33 -> Discount Revenue | F51: =F33 -> 7947 | G51: =G33 -> 8481 | H51: =H33 -> 8408 | I51: =I33 -> 8580 | J51: =J33 -> 33416 | K51: =K33 -> 8380 | L51: =L33 -> 8855 | M51: =M33 -> 8780 | ... U51: =U33 -> 9512 | V51: =IF($C$25="Quarterly",U51*(1+V52),Q51*(1+V52)) -> 10082.72 | W51: =IF($C$25="Quarterly",V51*(1+W52),R51*(1+W52)) -> 10233.961 | X51: =IF($C$25="Quarterly",W51*(1+X52),S51*(1+X52)) -> 10796.829 | Y51: =SUM(U51:X51) -> 40625.509 | Z51: =IF($C$25="Quarterly",X51*(1+Z52),U51*(1+Z52)) -> 10688.86 | AA51: =IF($C$25="Quarterly",Z51*(1+AA52),V51*(1+AA52)) -> 11437.081 | AB51: =IF($C$25="Quarterly",AA51*(1+AB52),W51*(1+AB52)) -> 11665.822 | AC51: =IF($C$25="Quarterly",AB51*(1+AC52),X51*(1+AC52)) -> 12307.442 | AD51: =SUM(Z51:AC51) -> 46099.206 | AE51: =AD51*(1+AE52) -> 49326.15 | AF51: =AE51*(1+AF52) -> 52285.719 | AG51: =AF51*(1+AG52) -> 55422.862
C52: =IF($C$25="Quarterly","% Growth QoQ","% Growth YoY") -> % Growth QoQ | G52: =G34 -> 0.067195168 | H52: =H34 -> -0.0086074755 | I52: =I34 -> 0.020456708 | J52: =J34 -> 0 | K52: =K34 -> 0.05448597 | L52: =L34 -> 0.044098573 | M52: =M34 -> 0.044243578 | N52: =N34 -> 0.06958042 | ... U52: =U34 -> 0.087956079 | V52: =IF(Case_Scenario="Bull",V53,IF(Case_Scenario="Base",V54,IF(Case_Scenario="bear",V55,"N/A"))) -> 0.06 | W52: =IF(Case_Scenario="Bull",W53,IF(Case_Scenario="Base",W54,IF(Case_Scenario="bear",W55,"N/A"))) -> 0.015 | X52: =IF(Case_Scenario="Bull",X53,IF(Case_Scenario="Base",X54,IF(Case_Scenario="bear",X55,"N/A"))) -> 0.055 | Z52: =IF(Case_Scenario="Bull",Z53,IF(Case_Scenario="Base",Z54,IF(Case_Scenario="bear",Z55,"N/A"))) -> -0.01 | AA52: =IF(Case_Scenario="Bull",AA53,IF(Case_Scenario="Base",AA54,IF(Case_Scenario="bear",AA55,"N/A"))) -> 0.07 | AB52: =IF(Case_Scenario="Bull",AB53,IF(Case_Scenario="Base",AB54,IF(Case_Scenario="bear",AB55,"N/A"))) -> 0.02 | AC52: =IF(Case_Scenario="Bull",AC53,IF(Case_Scenario="Base",AC54,IF(Case_Scenario="bear",AC55,"N/A"))) -> 0.055 | AE52: =IF(Case_Scenario="Bull",AE53,IF(Case_Scenario="Base",AE54,IF(Case_Scenario="bear",AE55,"N/A"))) -> 0.07 | AF52: =IF(Case_Scenario="Bull",AF53,IF(Case_Scenario="Base",AF54,IF(Case_Scenario="bear",AF55,"N/A"))) -> 0.06 | AG52: =IF(Case_Scenario="Bull",AG53,IF(Case_Scenario="Base",AG54,IF(Case_Scenario="bear",AG55,"N/A"))) -> 0.06
C53: Bull Case | V53: =V54+1% -> 0.07 | W53: =W54+1.5% -> 0.03 | X53: =X54+1.5% -> 0.07 | Z53: =Z54+1% -> 0 | AA53: =AA54+1% -> 0.08 | AB53: =AB54+1% -> 0.03 | AC53: =AC54+1% -> 0.065 | AE53: =AE54+1% -> 0.08 | AF53: =AF54+1% -> 0.07 | AG53: =AG54+1% -> 0.07
C54: Base Case | V54: 0.06 | W54: 0.015 | X54: 0.055 | Z54: -0.01 | AA54: 0.07 | AB54: 0.02 | AC54: 0.055 | AE54: 0.07 | AF54: 0.06 | AG54: 0.06
C55: Bear Case | V55: =+V54-1% -> 0.05 | W55: =+W54-1% -> 0.005 | X55: =+X54-1% -> 0.045 | Z55: -0.051 | AA55: =+AA54-1% -> 0.06 | AB55: =+AB54-1% -> 0.01 | AC55: =+AC54-1% -> 0.045 | AE55: =+AE54-1% -> 0.06 | AF55: =+AF54-1% -> 0.05 | AG55: =+AG54-1% -> 0.05
C57: Interest Income | F57: ='Segment Analysis'!F11 -> 4416 | G57: ='Segment Analysis'!G11 -> 4775 | H57: ='Segment Analysis'!H11 -> 5240 | I57: ='Segment Analysis'!I11 -> 5552 | J57: =SUM(F57:I57) -> 19983 | K57: ='Segment Analysis'!K11 -> 5775 | L57: ='Segment Analysis'!L11 -> 5794 | M57: ='Segment Analysis'!M11 -> 6149 | N57: ='Segment Analysis'!N11 -> 6077 | O57: =SUM(K57:N57) -> 23795 | P57: ='Segment Analysis'!P11 -> 6135 | Q57: ='Segment Analysis'!Q11 -> 6264 | R57: ='Segment Analysis'!R11 -> 6617 | S57: ='Segment Analysis'!S11 -> 6582 | T57: =SUM(P57:S57) -> 25598 | U57: ='Segment Analysis'!U11 -> 6665 | V57: =Q57*(1+V58) -> 6702.48 | W57: =IF($C$25="Quarterly",U57*(1+W58),R57*(1+W58)) -> 6898.275 | X57: =IF($C$25="Quarterly",V57*(1+X58),S57*(1+X58)) -> 6937.0668 | Y57: =SUM(U57:X57) -> 27202.822 | Z57: =IF($C$25="Quarterly",X57*(1+Z58),U57*(1+Z58)) -> 6930.1297 | AA57: =IF($C$25="Quarterly",Z57*(1+AA58),V57*(1+AA58)) -> 6999.431 | AB57: =IF($C$25="Quarterly",AA57*(1+AB58),W57*(1+AB58)) -> 7174.4168 | AC57: =IF($C$25="Quarterly",AB57*(1+AC58),X57*(1+AC58)) -> 7353.7772 | AD57: =SUM(Z57:AC57) -> 28457.755 | AE57: =AD57*(1+AE58) -> 29738.354 | AF57: =AE57*(1+AF58) -> 31522.655 | AG57: =AF57*(1+AG58) -> 33571.628
C58: =IF($C$25="Quarterly","% Growth QoQ","% Growth YoY") -> % Growth QoQ | J58: =J40 -> 0 | K58: =K57/F57-1 -> 0.30774457 | L58: =L57/G57-1 -> 0.21340314 | M58: =M57/H57-1 -> 0.17347328 | N58: =N57/I57-1 -> 0.094560519 | O58: =O57/J57-1 -> 0.19076215 | P58: =P57/K57-1 -> 0.062337662 | Q58: =Q57/L57-1 -> 0.081118398 | R58: =R57/M57-1 -> 0.076109937 | ... U58: =U57/P57-1 -> 0.086389568 | V58: =IF(Case_Scenario="Bull",V59,IF(Case_Scenario="Base",V60,IF(Case_Scenario="bear",V61,"N/A"))) -> 0.07 | W58: =IF(Case_Scenario="Bull",W59,IF(Case_Scenario="Base",W60,IF(Case_Scenario="bear",W61,"N/A"))) -> 0.035 | X58: =IF(Case_Scenario="Bull",X59,IF(Case_Scenario="Base",X60,IF(Case_Scenario="bear",X61,"N/A"))) -> 0.035 | Z58: =IF(Case_Scenario="Bull",Z59,IF(Case_Scenario="Base",Z60,IF(Case_Scenario="bear",Z61,"N/A"))) -> -0.001 | AA58: =IF(Case_Scenario="Bull",AA59,IF(Case_Scenario="Base",AA60,IF(Case_Scenario="bear",AA61,"N/A"))) -> 0.01 | AB58: =IF(Case_Scenario="Bull",AB59,IF(Case_Scenario="Base",AB60,IF(Case_Scenario="bear",AB61,"N/A"))) -> 0.025 | AC58: =IF(Case_Scenario="Bull",AC59,IF(Case_Scenario="Base",AC60,IF(Case_Scenario="bear",AC61,"N/A"))) -> 0.025 | AE58: =IF(Case_Scenario="Bull",AE59,IF(Case_Scenario="Base",AE60,IF(Case_Scenario="bear",AE61,"N/A"))) -> 0.045 | AF58: =IF(Case_Scenario="Bull",AF59,IF(Case_Scenario="Base",AF60,IF(Case_Scenario="bear",AF61,"N/A"))) -> 0.06 | AG58: =IF(Case_Scenario="Bull",AG59,IF(Case_Scenario="Base",AG60,IF(Case_Scenario="bear",AG61,"N/A"))) -> 0.065
C59: Bull Case | V59: =V60+1.5% -> 0.085 | W59: =W60+1.5% -> 0.05 | X59: =X60+1.5% -> 0.05 | Z59: =Z60+1.5% -> 0.014 | AA59: =AA60+1.5% -> 0.025 | AB59: =AB60+1.5% -> 0.04 | AC59: =AC60+1.5% -> 0.04 | AE59: =AE60+1.1% -> 0.056 | AF59: =AF60+1.1% -> 0.071 | AG59: =AG60+1.1% -> 0.076
C60: Base Case | V60: 0.07 | W60: 0.035 | X60: 0.035 | Z60: -0.001 | AA60: 0.01 | AB60: 0.025 | AC60: 0.025 | AE60: 0.045 | AF60: 0.06 | AG60: 0.065
C61: Bear Case | V61: =+V60-2% -> 0.05 | W61: =+W60-2% -> 0.015 | X61: =+X60-2% -> 0.015 | Z61: =+Z60-2% -> -0.021 | AA61: =+AA60-2% -> -0.01 | AB61: =+AB60-2% -> 0.005 | AC61: =+AC60-2% -> 0.005 | AE61: =+AE60-1.5% -> 0.03 | AF61: =+AF60-1.5% -> 0.045 | AG61: =+AG60-1.5% -> 0.05
A63: x | C63: =C41 -> Net Card Fees Revenue | F63: =F41 -> 1713 | G63: =G41 -> 1789 | H63: =H41 -> 1846 | I63: =I41 -> 1907 | J63: =J41 -> 7255 | K63: =K41 -> 1974 | L63: =L41 -> 2060 | M63: =M41 -> 2170 | ... U63: =U41 -> 2752 | V63: =IF($C$25="Quarterly",U63*(1+V64),Q63*(1+V64)) -> 2889.6 | W63: =IF($C$25="Quarterly",V63*(1+W64),R63*(1+W64)) -> 3034.08 | X63: =IF($C$25="Quarterly",W63*(1+X64),S63*(1+X64)) -> 3216.1248 | Y63: =SUM(U63:X63) -> 11891.805 | Z63: =IF($C$25="Quarterly",X63*(1+Z64),U63*(1+Z64)) -> 3312.6085 | AA63: =IF($C$25="Quarterly",Z63*(1+AA64),V63*(1+AA64)) -> 3445.1129 | AB63: =IF($C$25="Quarterly",AA63*(1+AB64),W63*(1+AB64)) -> 3514.0151 | AC63: =IF($C$25="Quarterly",AB63*(1+AC64),X63*(1+AC64)) -> 3619.4356 | AD63: =SUM(Z63:AC63) -> 13891.172 | AE63: =AD63*(1+AE64) -> 15835.936 | AF63: =AE63*(1+AF64) -> 17736.249 | AG63: =AF63*(1+AG64) -> 18800.424
C64: =IF($C$25="Quarterly","% Growth QoQ","% Growth YoY") -> % Growth QoQ | G64: =G42 -> 0.044366608 | H64: =H42 -> 0.031861375 | I64: =I42 -> 0.03304442 | J64: =J42 -> 0 | K64: =K42 -> 0.035133718 | L64: =L42 -> 0.043566363 | M64: =M42 -> 0.053398058 | N64: =N42 -> 0.034562212 | ... U64: =U42 -> 0.04678585 | V64: =IF(Case_Scenario="Bull",V65,IF(Case_Scenario="Base",V66,IF(Case_Scenario="bear",V67,"N/A"))) -> 0.05 | W64: =IF(Case_Scenario="Bull",W65,IF(Case_Scenario="Base",W66,IF(Case_Scenario="bear",W67,"N/A"))) -> 0.05 | X64: =IF(Case_Scenario="Bull",X65,IF(Case_Scenario="Base",X66,IF(Case_Scenario="bear",X67,"N/A"))) -> 0.06 | Z64: =IF(Case_Scenario="Bull",Z65,IF(Case_Scenario="Base",Z66,IF(Case_Scenario="bear",Z67,"N/A"))) -> 0.03 | AA64: =IF(Case_Scenario="Bull",AA65,IF(Case_Scenario="Base",AA66,IF(Case_Scenario="bear",AA67,"N/A"))) -> 0.04 | AB64: =IF(Case_Scenario="Bull",AB65,IF(Case_Scenario="Base",AB66,IF(Case_Scenario="bear",AB67,"N/A"))) -> 0.02 | AC64: =IF(Case_Scenario="Bull",AC65,IF(Case_Scenario="Base",AC66,IF(Case_Scenario="bear",AC67,"N/A"))) -> 0.03 | AE64: =IF(Case_Scenario="Bull",AE65,IF(Case_Scenario="Base",AE66,IF(Case_Scenario="bear",AE67,"N/A"))) -> 0.14 | AF64: =IF(Case_Scenario="Bull",AF65,IF(Case_Scenario="Base",AF66,IF(Case_Scenario="bear",AF67,"N/A"))) -> 0.12 | AG64: =IF(Case_Scenario="Bull",AG65,IF(Case_Scenario="Base",AG66,IF(Case_Scenario="bear",AG67,"N/A"))) -> 0.06
C65: Bull Case | V65: =V66+2% -> 0.07 | W65: =W66+2% -> 0.07 | X65: =X66+2% -> 0.08 | Z65: =Z66+2% -> 0.05 | AA65: =AA66+2% -> 0.06 | AB65: =AB66+2% -> 0.04 | AC65: =AC66+2% -> 0.05 | AE65: =AE66+1.5% -> 0.155 | AF65: =AF66+1.5% -> 0.135 | AG65: =AG66+1.5% -> 0.075
C66: Base Case | V66: 0.05 | W66: 0.05 | X66: 0.06 | Z66: 0.03 | AA66: 0.04 | AB66: 0.02 | AC66: 0.03 | AE66: 0.14 | AF66: 0.12 | AG66: 0.06
C67: Bear Case | V67: =+V66-2% -> 0.03 | W67: =+W66-2% -> 0.03 | X67: =+X66-2% -> 0.04 | Z67: =+Z66-2% -> 0.01 | AA67: =+AA66-2% -> 0.02 | AB67: =+AB66-2% -> 0 | AC67: =+AC66-2% -> 0.01 | AE67: =+AE66-2.5% -> 0.115 | AF67: =+AF66-2.5% -> 0.095 | AG67: =+AG66-2.5% -> 0.035
A69: x | C69: =C45 -> Service Fees and Other Revenue | F69: =F45 -> 1638 | G69: =G45 -> 1679 | H69: =H45 -> 1685 | I69: =I45 -> 1708 | J69: =J45 -> 6710 | K69: =K45 -> 1678 | L69: =L45 -> 1688 | M69: =M45 -> 1680 | ... U69: =U45 -> 1951 | V69: =IF($C$25="Quarterly",U69*(1+V70),Q69*(1+V70)) -> 2054.403 | W69: =IF($C$25="Quarterly",V69*(1+W70),R69*(1+W70)) -> 2157.1231 | X69: =IF($C$25="Quarterly",W69*(1+X70),S69*(1+X70)) -> 2174.3801 | Y69: =SUM(U69:X69) -> 8336.9063 | Z69: =IF($C$25="Quarterly",X69*(1+Z70),U69*(1+Z70)) -> 2130.8925 | AA69: =IF($C$25="Quarterly",Z69*(1+AA70),V69*(1+AA70)) -> 2242.3382 | AB69: =IF($C$25="Quarterly",AA69*(1+AB70),W69*(1+AB70)) -> 2349.9704 | AC69: =IF($C$25="Quarterly",AB69*(1+AC70),X69*(1+AC70)) -> 2378.1701 | AD69: =SUM(Z69:AC69) -> 9101.3713 | AE69: =AD69*(1+AE70) -> 9738.4673 | AF69: =AE69*(1+AF70) -> 10420.16 | AG69: =AF69*(1+AG70) -> 11045.37
C70: =IF($C$25="Quarterly","% Growth QoQ","% Growth YoY") -> % Growth QoQ | G70: =G46 -> 0.025030525 | H70: =H46 -> 0.0035735557 | I70: =I46 -> 0.013649852 | J70: =J46 -> 0 | K70: =K46 -> -0.017564403 | L70: =L46 -> 0.0059594756 | M70: =M46 -> -0.0047393365 | N70: =N46 -> 0.023214286 | ... U70: =U46 -> 0.0030848329 | V70: =IF(Case_Scenario="Bull",V71,IF(Case_Scenario="Base",V72,IF(Case_Scenario="bear",V73,"N/A"))) -> 0.053 | W70: =IF(Case_Scenario="Bull",W71,IF(Case_Scenario="Base",W72,IF(Case_Scenario="bear",W73,"N/A"))) -> 0.05 | X70: =IF(Case_Scenario="Bull",X71,IF(Case_Scenario="Base",X72,IF(Case_Scenario="bear",X73,"N/A"))) -> 0.008 | Z70: =IF(Case_Scenario="Bull",Z71,IF(Case_Scenario="Base",Z72,IF(Case_Scenario="bear",Z73,"N/A"))) -> -0.02 | AA70: =IF(Case_Scenario="Bull",AA71,IF(Case_Scenario="Base",AA72,IF(Case_Scenario="bear",AA73,"N/A"))) -> 0.0523 | AB70: =IF(Case_Scenario="Bull",AB71,IF(Case_Scenario="Base",AB72,IF(Case_Scenario="bear",AB73,"N/A"))) -> 0.048 | AC70: =IF(Case_Scenario="Bull",AC71,IF(Case_Scenario="Base",AC72,IF(Case_Scenario="bear",AC73,"N/A"))) -> 0.012 | AE70: =IF(Case_Scenario="Bull",AE71,IF(Case_Scenario="Base",AE72,IF(Case_Scenario="bear",AE73,"N/A"))) -> 0.07 | AF70: =IF(Case_Scenario="Bull",AF71,IF(Case_Scenario="Base",AF72,IF(Case_Scenario="bear",AF73,"N/A"))) -> 0.07 | AG70: =IF(Case_Scenario="Bull",AG71,IF(Case_Scenario="Base",AG72,IF(Case_Scenario="bear",AG73,"N/A"))) -> 0.06
C71: Bull Case | V71: =V72+2% -> 0.073 | W71: =W72+2% -> 0.07 | X71: =X72+2% -> 0.028 | Z71: =Z72+2% -> 0 | AA71: =AA72+2% -> 0.0723 | AB71: =AB72+2% -> 0.068 | AC71: =AC72+2% -> 0.032 | AE71: =AE72+1.5% -> 0.085 | AF71: =AF72+1.5% -> 0.085 | AG71: =AG72+1.5% -> 0.075
C72: Base Case | V72: 0.053 | W72: 0.05 | X72: 0.008 | Z72: -0.02 | AA72: 0.0523 | AB72: 0.048 | AC72: 0.012 | AE72: 0.07 | AF72: 0.07 | AG72: 0.06
C73: Bear Case | V73: =+V72-2% -> 0.033 | W73: =+W72-2% -> 0.03 | X73: =+X72-2% -> -0.012 | Z73: =+Z72-2% -> -0.04 | AA73: =+AA72-2% -> 0.0323 | AB73: =+AB72-2% -> 0.028 | AC73: =+AC72-2% -> -0.008 | AE73: =+AE72-2% -> 0.05 | AF73: =+AF72-2% -> 0.05 | AG73: =+AG72-2% -> 0.04
C75: % Volume Growth | G75: =IFERROR(#REF!/#REF!-1,"--") -> -- | H75: =IFERROR(#REF!/#REF!-1,"--") -> -- | I75: =IFERROR(#REF!/#REF!-1,"--") -> -- | K75: =IFERROR(#REF!/#REF!-1,"--") -> -- | L75: =IFERROR(#REF!/#REF!-1,"--") -> -- | M75: =IFERROR(#REF!/#REF!-1,"--") -> -- | N75: =IFERROR(#REF!/#REF!-1,"--") -> -- | O75: =IFERROR(#REF!/#REF!-1,"--") -> -- | P75: =IFERROR(#REF!/#REF!-1,"--") -> -- | Q75: =IFERROR(#REF!/#REF!-1,"--") -> -- | R75: =IFERROR(#REF!/#REF!-1,"--") -> -- | ... U75: =IFERROR(#REF!/#REF!-1,"--") -> -- | V75: =IF(Case_Scenario="Bull",V76,IF(Case_Scenario="Base",V77,IF(Case_Scenario="bear",V78,"N/A"))) -> 0.05 | W75: =IF(Case_Scenario="Bull",W76,IF(Case_Scenario="Base",W77,IF(Case_Scenario="bear",W78,"N/A"))) -> 0.05 | X75: =IF(Case_Scenario="Bull",X76,IF(Case_Scenario="Base",X77,IF(Case_Scenario="bear",X78,"N/A"))) -> 0.05 | Z75: =IF(Case_Scenario="Bull",Z76,IF(Case_Scenario="Base",Z77,IF(Case_Scenario="bear",Z78,"N/A"))) -> 0.05 | AA75: =IF(Case_Scenario="Bull",AA76,IF(Case_Scenario="Base",AA77,IF(Case_Scenario="bear",AA78,"N/A"))) -> 0.05 | AB75: =IF(Case_Scenario="Bull",AB76,IF(Case_Scenario="Base",AB77,IF(Case_Scenario="bear",AB78,"N/A"))) -> 0.05 | AC75: =IF(Case_Scenario="Bull",AC76,IF(Case_Scenario="Base",AC77,IF(Case_Scenario="bear",AC78,"N/A"))) -> 0.05 | AE75: =IF(Case_Scenario="Bull",AE76,IF(Case_Scenario="Base",AE77,IF(Case_Scenario="bear",AE78,"N/A"))) -> 0.05 | AF75: =IF(Case_Scenario="Bull",AF76,IF(Case_Scenario="Base",AF77,IF(Case_Scenario="bear",AF78,"N/A"))) -> 0.05 | AG75: =IF(Case_Scenario="Bull",AG76,IF(Case_Scenario="Base",AG77,IF(Case_Scenario="bear",AG78,"N/A"))) -> 0.05
C76: Bull Case | V76: 0.1 | W76: 0.1 | X76: 0.1 | Z76: 0.1 | AA76: 0.1 | AB76: 0.1 | AC76: 0.1 | AE76: 0.1 | AF76: 0.1 | AG76: 0.1
C77: Base Case | V77: 0.05 | W77: 0.05 | X77: 0.05 | Z77: 0.05 | AA77: 0.05 | AB77: 0.05 | AC77: 0.05 | AE77: 0.05 | AF77: 0.05 | AG77: 0.05
C78: Bear Case | V78: 0 | W78: 0 | X78: 0 | Z78: 0 | AA78: 0 | AB78: 0 | AC78: 0 | AE78: 0 | AF78: 0 | AG78: 0
C79: Price | F79: =IFERROR(#REF!/#REF!,"--") -> -- | G79: =IFERROR(#REF!/#REF!,"--") -> -- | H79: =IFERROR(#REF!/#REF!,"--") -> -- | I79: =IFERROR(#REF!/#REF!,"--") -> -- | J79: =IFERROR(#REF!/#REF!,"--") -> -- | K79: =IFERROR(#REF!/#REF!,"--") -> -- | L79: =IFERROR(#REF!/#REF!,"--") -> -- | M79: =IFERROR(#REF!/#REF!,"--") -> -- | ... U79: =IFERROR(#REF!/#REF!,"--") -> -- | V79: =U79*(1+V80) -> #VALUE! | W79: =V79*(1+W80) -> #VALUE! | X79: =W79*(1+X80) -> #VALUE! | Y79: =#REF!/#REF! -> #REF! | Z79: =X79*(1+Z80) -> #VALUE! | AA79: =Z79*(1+AA80) -> #VALUE! | AB79: =AA79*(1+AB80) -> #VALUE! | AC79: =AB79*(1+AC80) -> #VALUE! | AD79: =#REF!/#REF! -> #REF! | AE79: =AD79*(1+AE80) -> #REF! | AF79: =AE79*(1+AF80) -> #REF! | AG79: =AF79*(1+AG80) -> #REF!
C80: % Price Growth | G80: =IFERROR(G79/F79-1,"--") -> -- | H80: =IFERROR(H79/G79-1,"--") -> -- | I80: =IFERROR(I79/H79-1,"--") -> -- | K80: =IFERROR(K79/I79-1,"--") -> -- | L80: =IFERROR(L79/K79-1,"--") -> -- | M80: =IFERROR(M79/L79-1,"--") -> -- | N80: =IFERROR(N79/M79-1,"--") -> -- | O80: =IFERROR(O79/J79-1,"--") -> -- | P80: =IFERROR(P79/N79-1,"--") -> -- | Q80: =IFERROR(Q79/P79-1,"--") -> -- | R80: =IFERROR(R79/Q79-1,"--") -> -- | S80: =IFERROR(S79/R79-1,"--") -> -- | T80: =IFERROR(T79/O79-1,"--") -> -- | U80: =IFERROR(U79/S79-1,"--") -> -- | V80: =IF(Case_Scenario="Bull",V81,IF(Case_Scenario="Base",V82,IF(Case_Scenario="bear",V83,"N/A"))) -> 0.05 | W80: =IF(Case_Scenario="Bull",W81,IF(Case_Scenario="Base",W82,IF(Case_Scenario="bear",W83,"N/A"))) -> 0.05 | X80: =IF(Case_Scenario="Bull",X81,IF(Case_Scenario="Base",X82,IF(Case_Scenario="bear",X83,"N/A"))) -> 0.05 | Z80: =IF(Case_Scenario="Bull",Z81,IF(Case_Scenario="Base",Z82,IF(Case_Scenario="bear",Z83,"N/A"))) -> 0.05 | AA80: =IF(Case_Scenario="Bull",AA81,IF(Case_Scenario="Base",AA82,IF(Case_Scenario="bear",AA83,"N/A"))) -> 0.05 | AB80: =IF(Case_Scenario="Bull",AB81,IF(Case_Scenario="Base",AB82,IF(Case_Scenario="bear",AB83,"N/A"))) -> 0.05 | AC80: =IF(Case_Scenario="Bull",AC81,IF(Case_Scenario="Base",AC82,IF(Case_Scenario="bear",AC83,"N/A"))) -> 0.05 | AE80: =IF(Case_Scenario="Bull",AE81,IF(Case_Scenario="Base",AE82,IF(Case_Scenario="bear",AE83,"N/A"))) -> 0.05 | AF80: =IF(Case_Scenario="Bull",AF81,IF(Case_Scenario="Base",AF82,IF(Case_Scenario="bear",AF83,"N/A"))) -> 0.05 | AG80: =IF(Case_Scenario="Bull",AG81,IF(Case_Scenario="Base",AG82,IF(Case_Scenario="bear",AG83,"N/A"))) -> 0.05
C81: Bull Case | V81: 0.1 | W81: 0.1 | X81: 0.1 | Z81: 0.1 | AA81: 0.1 | AB81: 0.1 | AC81: 0.1 | AE81: 0.1 | AF81: 0.1 | AG81: 0.1
C82: Base Case | V82: 0.05 | W82: 0.05 | X82: 0.05 | Z82: 0.05 | AA82: 0.05 | AB82: 0.05 | AC82: 0.05 | AE82: 0.05 | AF82: 0.05 | AG82: 0.05
C83: Bear Case | V83: 0 | W83: 0 | X83: 0 | Z83: 0 | AA83: 0 | AB83: 0 | AC83: 0 | AE83: 0 | AF83: 0 | AG83: 0
A85: x | C85: =C41 -> Net Card Fees Revenue | F85: =F41 -> 1713 | G85: =G41 -> 1789 | H85: =H41 -> 1846 | I85: =I41 -> 1907 | J85: =J41 -> 7255 | K85: =K41 -> 1974 | L85: =L41 -> 2060 | M85: =M41 -> 2170 | ... U85: =U41 -> 2752 | V85: =V86*V91 -> 3034.08 | W85: =W86*W91 -> 3345.0732 | X85: =X86*X91 -> 3687.9432 | Y85: =SUM(U85:X85) -> 12819.096 | Z85: =Z86*Z91 -> 4065.9574 | AA85: =AA86*AA91 -> 4482.718 | AB85: =AB86*AB91 -> 4942.1966 | AC85: =AC86*AC91 -> 5448.7718 | AD85: =SUM(Z85:AC85) -> 18939.644 | AE85: =AE86*AE91 -> 20880.957 | AF85: =AF86*AF91 -> 23021.255 | AG85: =AG86*AG91 -> 25380.934
C86: Volume | F86: 220 | G86: 220 | H86: 220 | I86: 220 | J86: =SUM(F86:I86) -> 880 | K86: 220 | L86: 220 | M86: 220 | N86: 220 | O86: =SUM(K86:N86) -> 880 | P86: 220 | Q86: 220 | R86: 220 | S86: 220 | T86: =SUM(P86:S86) -> 880 | U86: 220 | V86: =U86*(1+V87) -> 231 | W86: =V86*(1+W87) -> 242.55 | X86: =W86*(1+X87) -> 254.6775 | Y86: =SUM(U86:X86) -> 948.2275 | Z86: =X86*(1+Z87) -> 267.41138 | AA86: =Z86*(1+AA87) -> 280.78194 | AB86: =AA86*(1+AB87) -> 294.82104 | AC86: =AB86*(1+AC87) -> 309.56209 | AD86: =SUM(Z86:AC86) -> 1152.5765 | AE86: =AD86*(1+AE87) -> 1210.2053 | AF86: =AE86*(1+AF87) -> 1270.7155 | AG86: =AF86*(1+AG87) -> 1334.2513
C87: % Volume Growth | G87: =IFERROR(G86/F86-1,"--") -> 0 | H87: =IFERROR(H86/G86-1,"--") -> 0 | I87: =IFERROR(I86/H86-1,"--") -> 0 | K87: =IFERROR(K86/I86-1,"--") -> 0 | L87: =IFERROR(L86/K86-1,"--") -> 0 | M87: =IFERROR(M86/L86-1,"--") -> 0 | N87: =IFERROR(N86/M86-1,"--") -> 0 | O87: =IFERROR(O86/J86-1,"--") -> 0 | P87: =IFERROR(P86/N86-1,"--") -> 0 | Q87: =IFERROR(Q86/P86-1,"--") -> 0 | R87: =IFERROR(R86/Q86-1,"--") -> 0 | S87: =IFERROR(S86/R86-1,"--") -> 0 | T87: =IFERROR(T86/O86-1,"--") -> 0 | U87: =IFERROR(U86/S86-1,"--") -> 0 | V87: =IF(Case_Scenario="Bull",V88,IF(Case_Scenario="Base",V89,IF(Case_Scenario="bear",V90,"N/A"))) -> 0.05 | W87: =IF(Case_Scenario="Bull",W88,IF(Case_Scenario="Base",W89,IF(Case_Scenario="bear",W90,"N/A"))) -> 0.05 | X87: =IF(Case_Scenario="Bull",X88,IF(Case_Scenario="Base",X89,IF(Case_Scenario="bear",X90,"N/A"))) -> 0.05 | Z87: =IF(Case_Scenario="Bull",Z88,IF(Case_Scenario="Base",Z89,IF(Case_Scenario="bear",Z90,"N/A"))) -> 0.05 | AA87: =IF(Case_Scenario="Bull",AA88,IF(Case_Scenario="Base",AA89,IF(Case_Scenario="bear",AA90,"N/A"))) -> 0.05 | AB87: =IF(Case_Scenario="Bull",AB88,IF(Case_Scenario="Base",AB89,IF(Case_Scenario="bear",AB90,"N/A"))) -> 0.05 | AC87: =IF(Case_Scenario="Bull",AC88,IF(Case_Scenario="Base",AC89,IF(Case_Scenario="bear",AC90,"N/A"))) -> 0.05 | AE87: =IF(Case_Scenario="Bull",AE88,IF(Case_Scenario="Base",AE89,IF(Case_Scenario="bear",AE90,"N/A"))) -> 0.05 | AF87: =IF(Case_Scenario="Bull",AF88,IF(Case_Scenario="Base",AF89,IF(Case_Scenario="bear",AF90,"N/A"))) -> 0.05 | AG87: =IF(Case_Scenario="Bull",AG88,IF(Case_Scenario="Base",AG89,IF(Case_Scenario="bear",AG90,"N/A"))) -> 0.05
C88: Bull Case | V88: 0.1 | W88: 0.1 | X88: 0.1 | Z88: 0.1 | AA88: 0.1 | AB88: 0.1 | AC88: 0.1 | AE88: 0.1 | AF88: 0.1 | AG88: 0.1
C89: Base Case | V89: 0.05 | W89: 0.05 | X89: 0.05 | Z89: 0.05 | AA89: 0.05 | AB89: 0.05 | AC89: 0.05 | AE89: 0.05 | AF89: 0.05 | AG89: 0.05
C90: Bear Case | V90: 0 | W90: 0 | X90: 0 | Z90: 0 | AA90: 0 | AB90: 0 | AC90: 0 | AE90: 0 | AF90: 0 | AG90: 0
C91: Price | F91: =IFERROR(F85/F86,"--") -> 7.7863636 | G91: =IFERROR(G85/G86,"--") -> 8.1318182 | H91: =IFERROR(H85/H86,"--") -> 8.3909091 | I91: =IFERROR(I85/I86,"--") -> 8.6681818 | J91: =IFERROR(J85/J86,"--") -> 8.2443182 | K91: =IFERROR(K85/K86,"--") -> 8.9727273 | L91: =IFERROR(L85/L86,"--") -> 9.3636364 | M91: =IFERROR(M85/M86,"--") -> 9.8636364 | ... U91: =IFERROR(U85/U86,"--") -> 12.509091 | V91: =U91*(1+V92) -> 13.134545 | W91: =V91*(1+W92) -> 13.791273 | X91: =W91*(1+X92) -> 14.480836 | Y91: =Y85/Y86 -> 13.519009 | Z91: =X91*(1+Z92) -> 15.204878 | AA91: =Z91*(1+AA92) -> 15.965122 | AB91: =AA91*(1+AB92) -> 16.763378 | AC91: =AB91*(1+AC92) -> 17.601547 | AD91: =AD85/AD86 -> 16.43244 | AE91: =AD91*(1+AE92) -> 17.254062 | AF91: =AE91*(1+AF92) -> 18.116765 | AG91: =AF91*(1+AG92) -> 19.022604
C92: % Price Growth | G92: =IFERROR(G91/F91-1,"--") -> 0.044366608 | H92: =IFERROR(H91/G91-1,"--") -> 0.031861375 | I92: =IFERROR(I91/H91-1,"--") -> 0.03304442 | K92: =IFERROR(K91/I91-1,"--") -> 0.035133718 | L92: =IFERROR(L91/K91-1,"--") -> 0.043566363 | M92: =IFERROR(M91/L91-1,"--") -> 0.053398058 | N92: =IFERROR(N91/M91-1,"--") -> 0.034562212 | O92: =IFERROR(O91/J91-1,"--") -> 0.16457615 | P92: =IFERROR(P91/N91-1,"--") -> 0.039198218 | Q92: =IFERROR(Q91/P91-1,"--") -> 0.063009001 | R92: =IFERROR(R91/Q91-1,"--") -> 0.028629032 | S92: =IFERROR(S91/R91-1,"--") -> 0.030576245 | T92: =IFERROR(T91/O91-1,"--") -> 0.18274352 | U92: =IFERROR(U91/S91-1,"--") -> 0.04678585 | V92: =IF(Case_Scenario="Bull",V93,IF(Case_Scenario="Base",V94,IF(Case_Scenario="bear",V95,"N/A"))) -> 0.05 | W92: =IF(Case_Scenario="Bull",W93,IF(Case_Scenario="Base",W94,IF(Case_Scenario="bear",W95,"N/A"))) -> 0.05 | X92: =IF(Case_Scenario="Bull",X93,IF(Case_Scenario="Base",X94,IF(Case_Scenario="bear",X95,"N/A"))) -> 0.05 | Z92: =IF(Case_Scenario="Bull",Z93,IF(Case_Scenario="Base",Z94,IF(Case_Scenario="bear",Z95,"N/A"))) -> 0.05 | AA92: =IF(Case_Scenario="Bull",AA93,IF(Case_Scenario="Base",AA94,IF(Case_Scenario="bear",AA95,"N/A"))) -> 0.05 | AB92: =IF(Case_Scenario="Bull",AB93,IF(Case_Scenario="Base",AB94,IF(Case_Scenario="bear",AB95,"N/A"))) -> 0.05 | AC92: =IF(Case_Scenario="Bull",AC93,IF(Case_Scenario="Base",AC94,IF(Case_Scenario="bear",AC95,"N/A"))) -> 0.05 | AE92: =IF(Case_Scenario="Bull",AE93,IF(Case_Scenario="Base",AE94,IF(Case_Scenario="bear",AE95,"N/A"))) -> 0.05 | AF92: =IF(Case_Scenario="Bull",AF93,IF(Case_Scenario="Base",AF94,IF(Case_Scenario="bear",AF95,"N/A"))) -> 0.05 | AG92: =IF(Case_Scenario="Bull",AG93,IF(Case_Scenario="Base",AG94,IF(Case_Scenario="bear",AG95,"N/A"))) -> 0.05
C93: Bull Case | V93: 0.1 | W93: 0.1 | X93: 0.1 | Z93: 0.1 | AA93: 0.1 | AB93: 0.1 | AC93: 0.1 | AE93: 0.1 | AF93: 0.1 | AG93: 0.1
C94: Base Case | V94: 0.05 | W94: 0.05 | X94: 0.05 | Z94: 0.05 | AA94: 0.05 | AB94: 0.05 | AC94: 0.05 | AE94: 0.05 | AF94: 0.05 | AG94: 0.05
C95: Bear Case | V95: 0 | W95: 0 | X95: 0 | Z95: 0 | AA95: 0 | AB95: 0 | AC95: 0 | AE95: 0 | AF95: 0 | AG95: 0
A97: x | C97: =C45 -> Service Fees and Other Revenue | F97: =F45 -> 1638 | G97: =G45 -> 1679 | H97: =H45 -> 1685 | I97: =I45 -> 1708 | J97: =J45 -> 6710 | K97: =K45 -> 1678 | L97: =L45 -> 1688 | M97: =M45 -> 1680 | ... U97: =U45 -> 1951 | V97: =V98*V103 -> 2150.9775 | W97: =W98*W103 -> 2371.4527 | X97: =X98*X103 -> 2614.5266 | Y97: =SUM(U97:X97) -> 9087.9568 | Z97: =Z98*Z103 -> 2882.5156 | AA97: =AA98*AA103 -> 3177.9734 | AB97: =AB98*AB103 -> 3503.7157 | AC97: =AC98*AC103 -> 3862.8466 | AD97: =SUM(Z97:AC97) -> 13427.051 | AE97: =AE98*AE103 -> 14803.324 | AF97: =AF98*AF103 -> 16320.665 | AG97: =AG98*AG103 -> 17993.533
C98: Volume | F98: 220 | G98: 220 | H98: 220 | I98: 220 | J98: =SUM(F98:I98) -> 880 | K98: 220 | L98: 220 | M98: 220 | N98: 220 | O98: =SUM(K98:N98) -> 880 | P98: 220 | Q98: 220 | R98: 220 | S98: 220 | T98: =SUM(P98:S98) -> 880 | U98: 220 | V98: =U98*(1+V99) -> 231 | W98: =V98*(1+W99) -> 242.55 | X98: =W98*(1+X99) -> 254.6775 | Y98: =SUM(U98:X98) -> 948.2275 | Z98: =X98*(1+Z99) -> 267.41138 | AA98: =Z98*(1+AA99) -> 280.78194 | AB98: =AA98*(1+AB99) -> 294.82104 | AC98: =AB98*(1+AC99) -> 309.56209 | AD98: =SUM(Z98:AC98) -> 1152.5765 | AE98: =AD98*(1+AE99) -> 1210.2053 | AF98: =AE98*(1+AF99) -> 1270.7155 | AG98: =AF98*(1+AG99) -> 1334.2513
C99: % Volume Growth | G99: =IFERROR(G98/F98-1,"--") -> 0 | H99: =IFERROR(H98/G98-1,"--") -> 0 | I99: =IFERROR(I98/H98-1,"--") -> 0 | K99: =IFERROR(K98/I98-1,"--") -> 0 | L99: =IFERROR(L98/K98-1,"--") -> 0 | M99: =IFERROR(M98/L98-1,"--") -> 0 | N99: =IFERROR(N98/M98-1,"--") -> 0 | O99: =IFERROR(O98/J98-1,"--") -> 0 | P99: =IFERROR(P98/N98-1,"--") -> 0 | Q99: =IFERROR(Q98/P98-1,"--") -> 0 | R99: =IFERROR(R98/Q98-1,"--") -> 0 | S99: =IFERROR(S98/R98-1,"--") -> 0 | T99: =IFERROR(T98/O98-1,"--") -> 0 | U99: =IFERROR(U98/S98-1,"--") -> 0 | V99: =IF(Case_Scenario="Bull",V100,IF(Case_Scenario="Base",V101,IF(Case_Scenario="bear",V102,"N/A"))) -> 0.05 | W99: =IF(Case_Scenario="Bull",W100,IF(Case_Scenario="Base",W101,IF(Case_Scenario="bear",W102,"N/A"))) -> 0.05 | X99: =IF(Case_Scenario="Bull",X100,IF(Case_Scenario="Base",X101,IF(Case_Scenario="bear",X102,"N/A"))) -> 0.05 | Z99: =IF(Case_Scenario="Bull",Z100,IF(Case_Scenario="Base",Z101,IF(Case_Scenario="bear",Z102,"N/A"))) -> 0.05 | AA99: =IF(Case_Scenario="Bull",AA100,IF(Case_Scenario="Base",AA101,IF(Case_Scenario="bear",AA102,"N/A"))) -> 0.05 | AB99: =IF(Case_Scenario="Bull",AB100,IF(Case_Scenario="Base",AB101,IF(Case_Scenario="bear",AB102,"N/A"))) -> 0.05 | AC99: =IF(Case_Scenario="Bull",AC100,IF(Case_Scenario="Base",AC101,IF(Case_Scenario="bear",AC102,"N/A"))) -> 0.05 | AE99: =IF(Case_Scenario="Bull",AE100,IF(Case_Scenario="Base",AE101,IF(Case_Scenario="bear",AE102,"N/A"))) -> 0.05 | AF99: =IF(Case_Scenario="Bull",AF100,IF(Case_Scenario="Base",AF101,IF(Case_Scenario="bear",AF102,"N/A"))) -> 0.05 | AG99: =IF(Case_Scenario="Bull",AG100,IF(Case_Scenario="Base",AG101,IF(Case_Scenario="bear",AG102,"N/A"))) -> 0.05
C100: Bull Case | V100: 0.1 | W100: 0.1 | X100: 0.1 | Z100: 0.1 | AA100: 0.1 | AB100: 0.1 | AC100: 0.1 | AE100: 0.1 | AF100: 0.1 | AG100: 0.1
C101: Base Case | V101: 0.05 | W101: 0.05 | X101: 0.05 | Z101: 0.05 | AA101: 0.05 | AB101: 0.05 | AC101: 0.05 | AE101: 0.05 | AF101: 0.05 | AG101: 0.05
C102: Bear Case | V102: 0 | W102: 0 | X102: 0 | Z102: 0 | AA102: 0 | AB102: 0 | AC102: 0 | AE102: 0 | AF102: 0 | AG102: 0
C103: Price | F103: =IFERROR(F97/F98,"--") -> 7.4454545 | G103: =IFERROR(G97/G98,"--") -> 7.6318182 | H103: =IFERROR(H97/H98,"--") -> 7.6590909 | I103: =IFERROR(I97/I98,"--") -> 7.7636364 | J103: =IFERROR(J97/J98,"--") -> 7.625 | K103: =IFERROR(K97/K98,"--") -> 7.6272727 | L103: =IFERROR(L97/L98,"--") -> 7.6727273 | M103: =IFERROR(M97/M98,"--") -> 7.6363636 | ... U103: =IFERROR(U97/U98,"--") -> 8.8681818 | V103: =U103*(1+V104) -> 9.3115909 | W103: =V103*(1+W104) -> 9.7771705 | X103: =W103*(1+X104) -> 10.266029 | Y103: =Y97/Y98 -> 9.5841523 | Z103: =X103*(1+Z104) -> 10.77933 | AA103: =Z103*(1+AA104) -> 11.318297 | AB103: =AA103*(1+AB104) -> 11.884212 | AC103: =AB103*(1+AC104) -> 12.478422 | AD103: =AD97/AD98 -> 11.649597 | AE103: =AD103*(1+AE104) -> 12.232077 | AF103: =AE103*(1+AF104) -> 12.843681 | AG103: =AF103*(1+AG104) -> 13.485865
C104: % Price Growth | G104: =IFERROR(G103/F103-1,"--") -> 0.025030525 | H104: =IFERROR(H103/G103-1,"--") -> 0.0035735557 | I104: =IFERROR(I103/H103-1,"--") -> 0.013649852 | K104: =IFERROR(K103/I103-1,"--") -> -0.017564403 | L104: =IFERROR(L103/K103-1,"--") -> 0.0059594756 | M104: =IFERROR(M103/L103-1,"--") -> -0.0047393365 | N104: =IFERROR(N103/M103-1,"--") -> 0.023214286 | O104: =IFERROR(O103/J103-1,"--") -> 0.0081967213 | P104: =IFERROR(P103/N103-1,"--") -> 0.0017452007 | Q104: =IFERROR(Q103/P103-1,"--") -> 0.06155633 | R104: =IFERROR(R103/Q103-1,"--") -> 0.080962801 | S104: =IFERROR(S103/R103-1,"--") -> -0.015688259 | T104: =IFERROR(T103/O103-1,"--") -> 0.10436068 | U104: =IFERROR(U103/S103-1,"--") -> 0.0030848329 | V104: =IF(Case_Scenario="Bull",V105,IF(Case_Scenario="Base",V106,IF(Case_Scenario="bear",V107,"N/A"))) -> 0.05 | W104: =IF(Case_Scenario="Bull",W105,IF(Case_Scenario="Base",W106,IF(Case_Scenario="bear",W107,"N/A"))) -> 0.05 | X104: =IF(Case_Scenario="Bull",X105,IF(Case_Scenario="Base",X106,IF(Case_Scenario="bear",X107,"N/A"))) -> 0.05 | Z104: =IF(Case_Scenario="Bull",Z105,IF(Case_Scenario="Base",Z106,IF(Case_Scenario="bear",Z107,"N/A"))) -> 0.05 | AA104: =IF(Case_Scenario="Bull",AA105,IF(Case_Scenario="Base",AA106,IF(Case_Scenario="bear",AA107,"N/A"))) -> 0.05 | AB104: =IF(Case_Scenario="Bull",AB105,IF(Case_Scenario="Base",AB106,IF(Case_Scenario="bear",AB107,"N/A"))) -> 0.05 | AC104: =IF(Case_Scenario="Bull",AC105,IF(Case_Scenario="Base",AC106,IF(Case_Scenario="bear",AC107,"N/A"))) -> 0.05 | AE104: =IF(Case_Scenario="Bull",AE105,IF(Case_Scenario="Base",AE106,IF(Case_Scenario="bear",AE107,"N/A"))) -> 0.05 | AF104: =IF(Case_Scenario="Bull",AF105,IF(Case_Scenario="Base",AF106,IF(Case_Scenario="bear",AF107,"N/A"))) -> 0.05 | AG104: =IF(Case_Scenario="Bull",AG105,IF(Case_Scenario="Base",AG106,IF(Case_Scenario="bear",AG107,"N/A"))) -> 0.05
C105: Bull Case | V105: 0.1 | W105: 0.1 | X105: 0.1 | Z105: 0.1 | AA105: 0.1 | AB105: 0.1 | AC105: 0.1 | AE105: 0.1 | AF105: 0.1 | AG105: 0.1
C106: Base Case | V106: 0.05 | W106: 0.05 | X106: 0.05 | Z106: 0.05 | AA106: 0.05 | AB106: 0.05 | AC106: 0.05 | AE106: 0.05 | AF106: 0.05 | AG106: 0.05
C107: Bear Case | V107: 0 | W107: 0 | X107: 0 | Z107: 0 | AA107: 0 | AB107: 0 | AC107: 0 | AE107: 0 | AF107: 0 | AG107: 0
A109: x | C109: =#REF! -> #REF! | F109: =#REF! -> #REF! | G109: =#REF! -> #REF! | H109: =#REF! -> #REF! | I109: =#REF! -> #REF! | J109: =#REF! -> #REF! | K109: =#REF! -> #REF! | L109: =#REF! -> #REF! | M109: =#REF! -> #REF! | ... U109: =#REF! -> #REF! | V109: =V110*V115 -> #VALUE! | W109: =W110*W115 -> #VALUE! | X109: =X110*X115 -> #VALUE! | Y109: =SUM(U109:X109) -> #REF! | Z109: =Z110*Z115 -> #VALUE! | AA109: =AA110*AA115 -> #VALUE! | AB109: =AB110*AB115 -> #VALUE! | AC109: =AC110*AC115 -> #VALUE! | AD109: =SUM(Z109:AC109) -> #VALUE! | AE109: =AE110*AE115 -> #VALUE! | AF109: =AF110*AF115 -> #VALUE! | AG109: =AG110*AG115 -> #VALUE!
C110: Volume | F110: 220 | G110: 220 | H110: 220 | I110: 220 | J110: =SUM(F110:I110) -> 880 | K110: 220 | L110: 220 | M110: 220 | N110: 220 | O110: =SUM(K110:N110) -> 880 | P110: 220 | Q110: 220 | R110: 220 | S110: 220 | T110: =SUM(P110:S110) -> 880 | U110: 220 | V110: =U110*(1+V111) -> 231 | W110: =V110*(1+W111) -> 242.55 | X110: =W110*(1+X111) -> 254.6775 | Y110: =SUM(U110:X110) -> 948.2275 | Z110: =X110*(1+Z111) -> 267.41138 | AA110: =Z110*(1+AA111) -> 280.78194 | AB110: =AA110*(1+AB111) -> 294.82104 | AC110: =AB110*(1+AC111) -> 309.56209 | AD110: =SUM(Z110:AC110) -> 1152.5765 | AE110: =AD110*(1+AE111) -> 1210.2053 | AF110: =AE110*(1+AF111) -> 1270.7155 | AG110: =AF110*(1+AG111) -> 1334.2513
C111: % Volume Growth | G111: =IFERROR(G110/F110-1,"--") -> 0 | H111: =IFERROR(H110/G110-1,"--") -> 0 | I111: =IFERROR(I110/H110-1,"--") -> 0 | K111: =IFERROR(K110/I110-1,"--") -> 0 | L111: =IFERROR(L110/K110-1,"--") -> 0 | M111: =IFERROR(M110/L110-1,"--") -> 0 | N111: =IFERROR(N110/M110-1,"--") -> 0 | O111: =IFERROR(O110/J110-1,"--") -> 0 | P111: =IFERROR(P110/N110-1,"--") -> 0 | Q111: =IFERROR(Q110/P110-1,"--") -> 0 | R111: =IFERROR(R110/Q110-1,"--") -> 0 | S111: =IFERROR(S110/R110-1,"--") -> 0 | T111: =IFERROR(T110/O110-1,"--") -> 0 | U111: =IFERROR(U110/S110-1,"--") -> 0 | V111: =IF(Case_Scenario="Bull",V112,IF(Case_Scenario="Base",V113,IF(Case_Scenario="bear",V114,"N/A"))) -> 0.05 | W111: =IF(Case_Scenario="Bull",W112,IF(Case_Scenario="Base",W113,IF(Case_Scenario="bear",W114,"N/A"))) -> 0.05 | X111: =IF(Case_Scenario="Bull",X112,IF(Case_Scenario="Base",X113,IF(Case_Scenario="bear",X114,"N/A"))) -> 0.05 | Z111: =IF(Case_Scenario="Bull",Z112,IF(Case_Scenario="Base",Z113,IF(Case_Scenario="bear",Z114,"N/A"))) -> 0.05 | AA111: =IF(Case_Scenario="Bull",AA112,IF(Case_Scenario="Base",AA113,IF(Case_Scenario="bear",AA114,"N/A"))) -> 0.05 | AB111: =IF(Case_Scenario="Bull",AB112,IF(Case_Scenario="Base",AB113,IF(Case_Scenario="bear",AB114,"N/A"))) -> 0.05 | AC111: =IF(Case_Scenario="Bull",AC112,IF(Case_Scenario="Base",AC113,IF(Case_Scenario="bear",AC114,"N/A"))) -> 0.05 | AE111: =IF(Case_Scenario="Bull",AE112,IF(Case_Scenario="Base",AE113,IF(Case_Scenario="bear",AE114,"N/A"))) -> 0.05 | AF111: =IF(Case_Scenario="Bull",AF112,IF(Case_Scenario="Base",AF113,IF(Case_Scenario="bear",AF114,"N/A"))) -> 0.05 | AG111: =IF(Case_Scenario="Bull",AG112,IF(Case_Scenario="Base",AG113,IF(Case_Scenario="bear",AG114,"N/A"))) -> 0.05
C112: Bull Case | V112: 0.1 | W112: 0.1 | X112: 0.1 | Z112: 0.1 | AA112: 0.1 | AB112: 0.1 | AC112: 0.1 | AE112: 0.1 | AF112: 0.1 | AG112: 0.1
C113: Base Case | V113: 0.05 | W113: 0.05 | X113: 0.05 | Z113: 0.05 | AA113: 0.05 | AB113: 0.05 | AC113: 0.05 | AE113: 0.05 | AF113: 0.05 | AG113: 0.05
C114: Bear Case | V114: 0 | W114: 0 | X114: 0 | Z114: 0 | AA114: 0 | AB114: 0 | AC114: 0 | AE114: 0 | AF114: 0 | AG114: 0
C115: Price | F115: =IFERROR(F109/F110,"--") -> -- | G115: =IFERROR(G109/G110,"--") -> -- | H115: =IFERROR(H109/H110,"--") -> -- | I115: =IFERROR(I109/I110,"--") -> -- | J115: =IFERROR(J109/J110,"--") -> -- | K115: =IFERROR(K109/K110,"--") -> -- | L115: =IFERROR(L109/L110,"--") -> -- | M115: =IFERROR(M109/M110,"--") -> -- | ... U115: =IFERROR(U109/U110,"--") -> -- | V115: =U115*(1+V116) -> #VALUE! | W115: =V115*(1+W116) -> #VALUE! | X115: =W115*(1+X116) -> #VALUE! | Y115: =Y109/Y110 -> #REF! | Z115: =X115*(1+Z116) -> #VALUE! | AA115: =Z115*(1+AA116) -> #VALUE! | AB115: =AA115*(1+AB116) -> #VALUE! | AC115: =AB115*(1+AC116) -> #VALUE! | AD115: =AD109/AD110 -> #VALUE! | AE115: =AD115*(1+AE116) -> #VALUE! | AF115: =AE115*(1+AF116) -> #VALUE! | AG115: =AF115*(1+AG116) -> #VALUE!
C116: % Price Growth | G116: =IFERROR(G115/F115-1,"--") -> -- | H116: =IFERROR(H115/G115-1,"--") -> -- | I116: =IFERROR(I115/H115-1,"--") -> -- | K116: =IFERROR(K115/I115-1,"--") -> -- | L116: =IFERROR(L115/K115-1,"--") -> -- | M116: =IFERROR(M115/L115-1,"--") -> -- | N116: =IFERROR(N115/M115-1,"--") -> -- | O116: =IFERROR(O115/J115-1,"--") -> -- | P116: =IFERROR(P115/N115-1,"--") -> -- | Q116: =IFERROR(Q115/P115-1,"--") -> -- | R116: =IFERROR(R115/Q115-1,"--") -> -- | S116: =IFERROR(S115/R115-1,"--") -> -- | T116: =IFERROR(T115/O115-1,"--") -> -- | U116: =IFERROR(U115/S115-1,"--") -> -- | V116: =IF(Case_Scenario="Bull",V117,IF(Case_Scenario="Base",V118,IF(Case_Scenario="bear",V119,"N/A"))) -> 0.05 | W116: =IF(Case_Scenario="Bull",W117,IF(Case_Scenario="Base",W118,IF(Case_Scenario="bear",W119,"N/A"))) -> 0.05 | X116: =IF(Case_Scenario="Bull",X117,IF(Case_Scenario="Base",X118,IF(Case_Scenario="bear",X119,"N/A"))) -> 0.05 | Z116: =IF(Case_Scenario="Bull",Z117,IF(Case_Scenario="Base",Z118,IF(Case_Scenario="bear",Z119,"N/A"))) -> 0.05 | AA116: =IF(Case_Scenario="Bull",AA117,IF(Case_Scenario="Base",AA118,IF(Case_Scenario="bear",AA119,"N/A"))) -> 0.05 | AB116: =IF(Case_Scenario="Bull",AB117,IF(Case_Scenario="Base",AB118,IF(Case_Scenario="bear",AB119,"N/A"))) -> 0.05 | AC116: =IF(Case_Scenario="Bull",AC117,IF(Case_Scenario="Base",AC118,IF(Case_Scenario="bear",AC119,"N/A"))) -> 0.05 | AE116: =IF(Case_Scenario="Bull",AE117,IF(Case_Scenario="Base",AE118,IF(Case_Scenario="bear",AE119,"N/A"))) -> 0.05 | AF116: =IF(Case_Scenario="Bull",AF117,IF(Case_Scenario="Base",AF118,IF(Case_Scenario="bear",AF119,"N/A"))) -> 0.05 | AG116: =IF(Case_Scenario="Bull",AG117,IF(Case_Scenario="Base",AG118,IF(Case_Scenario="bear",AG119,"N/A"))) -> 0.05
C117: Bull Case | V117: 0.1 | W117: 0.1 | X117: 0.1 | Z117: 0.1 | AA117: 0.1 | AB117: 0.1 | AC117: 0.1 | AE117: 0.1 | AF117: 0.1 | AG117: 0.1
C118: Base Case | V118: 0.05 | W118: 0.05 | X118: 0.05 | Z118: 0.05 | AA118: 0.05 | AB118: 0.05 | AC118: 0.05 | AE118: 0.05 | AF118: 0.05 | AG118: 0.05
...

Sheet Model
C1: =Company_Name&" - "&MID(CELL("filename",A1),FIND("]",CELL("filename",A1))+1,255)&": "&Case_Scenario&" Case" -> American Express Company - Model: Base Case
C2: =Cover!C2 -> $ in Millions Except Per Share Data
C4: Font Toggle
C5: Report
C7: Interest Expense Toggle
C8: On
A10: x | C10: Shortcuts
C11: =$C$25 -> Income Statement
C12: =$C$73 -> Cash Flow Statement
C13: =$C$118 -> Balance Sheet
C14: =$C$160 -> Working Capital Schedule
C15: =$C$190 -> PP&E / Depreciation Schedule
C16: =$C$204 -> Amortization Schedule
C17: =$C$216 -> Other Long-Term Items Schedule
C18: =$C$234 -> Shareholder's Equity Schedule
C19: =$C$275 -> Shares Outstanding Schedule
C20: =$C$286 -> Debt and Interest Schedule
J23: 1 | O23: 2 | T23: 3 | Y23: 4 | AD23: 5 | AE23: 6 | AF23: 7 | AG23: 8
F24: =G24 -> 2023 | G24: =H24 -> 2023 | H24: =I24 -> 2023 | I24: =J24 -> 2023 | J24: =O24-1 -> 2023 | K24: =L24 -> 2024 | L24: =M24 -> 2024 | M24: =N24 -> 2024 | N24: =O24 -> 2024 | O24: =T24-1 -> 2024 | P24: =Q24 -> 2025 | Q24: =R24 -> 2025 | R24: =S24 -> 2025 | S24: =T24 -> 2025 | T24: =YEAR(Last_FYE) -> 2025 | U24: =V24 -> 2026 | V24: =W24 -> 2026 | W24: =X24 -> 2026 | X24: =Y24 -> 2026 | Y24: =T24+1 -> 2026 | Z24: =AA24 -> 2027 | AA24: =AB24 -> 2027 | AB24: =AC24 -> 2027 | AC24: =AD24 -> 2027 | AD24: =Y24+1 -> 2027 | AE24: =AD24+1 -> 2028 | AF24: =AE24+1 -> 2029 | AG24: =AF24+1 -> 2030
A25: x | C25: Income Statement | F25: ="1Q"&RIGHT(F24,2) -> 1Q23 | G25: ="2Q"&RIGHT(G24,2) -> 2Q23 | H25: ="3Q"&RIGHT(H24,2) -> 3Q23 | I25: ="4Q"&RIGHT(I24,2) -> 4Q23 | J25: =J24 -> 2023 | K25: ="1Q"&RIGHT(K24,2) -> 1Q24 | L25: ="2Q"&RIGHT(L24,2) -> 2Q24 | M25: ="3Q"&RIGHT(M24,2) -> 3Q24 | N25: ="4Q"&RIGHT(N24,2) -> 4Q24 | O25: =O24 -> 2024 | P25: ="1Q"&RIGHT(P24,2) -> 1Q25 | Q25: ="2Q"&RIGHT(Q24,2) -> 2Q25 | R25: ="3Q"&RIGHT(R24,2) -> 3Q25 | S25: ="4Q"&RIGHT(S24,2) -> 4Q25 | T25: =T24 -> 2025 | U25: ="1Q"&RIGHT(U24,2) -> 1Q26 | V25: ="2Q"&RIGHT(V24,2)&"e" -> 2Q26e | W25: ="3Q"&RIGHT(W24,2)&"e" -> 3Q26e | X25: ="4Q"&RIGHT(X24,2)&"e" -> 4Q26e | Y25: =Y24&"e" -> 2026e | Z25: ="1Q"&RIGHT(Z24,2)&"e" -> 1Q27e | AA25: ="2Q"&RIGHT(AA24,2)&"e" -> 2Q27e | AB25: ="3Q"&RIGHT(AB24,2)&"e" -> 3Q27e | AC25: ="4Q"&RIGHT(AC24,2)&"e" -> 4Q27e | AD25: =AD24&"e" -> 2027e | AE25: =AE24&"e" -> 2028e | AF25: =AF24&"e" -> 2029e | AG25: =AG24&"e" -> 2030e | AH25: x
C26: Days In Period | F26: 91 | G26: 91 | H26: 92 | I26: 92 | J26: =SUM(F26:I26) -> 366 | K26: 90 | L26: 91 | M26: 92 | N26: 92 | O26: =SUM(K26:N26) -> 365 | P26: 90 | Q26: 91 | R26: 92 | S26: 92 | T26: =SUM(P26:S26) -> 365 | U26: 90 | V26: 91 | W26: 92 | X26: 92 | Y26: =SUM(U26:X26) -> 365 | Z26: 91 | AA26: 91 | AB26: 92 | AC26: 92 | AD26: =SUM(Z26:AC26) -> 366 | AE26: 365 | AF26: 365 | AG26: 365
C28: Revenue | F28: ='Segment Analysis'!F7 -> 15714 | G28: ='Segment Analysis'!G7 -> 16724 | H28: ='Segment Analysis'!H7 -> 17179 | I28: ='Segment Analysis'!I7 -> 17747 | J28: =SUM(F28:I28) -> 67364 | K28: ='Segment Analysis'!K7 -> 17807 | L28: ='Segment Analysis'!L7 -> 18397 | M28: ='Segment Analysis'!M7 -> 18779 | N28: ='Segment Analysis'!N7 -> 19218 | O28: =SUM(K28:N28) -> 74201 | P28: ='Segment Analysis'!P7 -> 18933 | Q28: ='Segment Analysis'!Q7 -> 19933 | R28: ='Segment Analysis'!R7 -> 20557 | S28: ='Segment Analysis'!S7 -> 21040 | T28: =SUM(P28:S28) -> 80463 | U28: ='Segment Analysis'!U7 -> 20880 | V28: ='Segment Analysis'!V7 -> 21729.203 | W28: ='Segment Analysis'!W7 -> 22323.439 | X28: ='Segment Analysis'!X7 -> 23124.4 | Y28: =SUM(U28:X28) -> 88057.042 | Z28: ='Segment Analysis'!Z7 -> 23062.491 | AA28: ='Segment Analysis'!AA7 -> 24123.963 | AB28: ='Segment Analysis'!AB7 -> 24704.225 | AC28: ='Segment Analysis'!AC7 -> 25658.825 | AD28: =SUM(Z28:AC28) -> 97549.504 | AE28: ='Segment Analysis'!AE7 -> 104638.91 | AF28: ='Segment Analysis'!AF7 -> 111964.78 | AG28: ='Segment Analysis'!AG7 -> 118840.28
C29: Interest Expense | F29: -1433 | G29: -1670 | H29: -1798 | I29: =-6849-SUM(F29:H29) -> -1948 | J29: =SUM(F29:I29) -> -6849 | K29: -2006 | L29: -2064 | M29: -2143 | N29: =-8252-SUM(K29:M29) -> -2039 | O29: =SUM(K29:N29) -> -8252 | P29: -1966 | Q29: -2077 | R29: -2131 | S29: =-8234-SUM(P29:R29) -> -2060 | T29: =SUM(P29:S29) -> -8234 | U29: -1973 | V29: =-('Revenue Build'!V37*(1-Drivers!V7)) -> -2044.2564 | W29: =-('Revenue Build'!W37*(1-Drivers!W7)) -> -1931.517 | X29: =-('Revenue Build'!X37*(1-Drivers!X7)) -> -1942.3787 | Y29: =SUM(U29:X29) -> -7891.1521 | Z29: =-('Revenue Build'!Z37*(1-Drivers!Z7)) -> -1732.5324 | AA29: =-('Revenue Build'!AA37*(1-Drivers!AA7)) -> -1728.8595 | AB29: =-('Revenue Build'!AB37*(1-Drivers!AB7)) -> -1757.7321 | AC29: =-('Revenue Build'!AC37*(1-Drivers!AC7)) -> -1728.1376 | AD29: =SUM(Z29:AC29) -> -6947.2617 | AE29: =-('Revenue Build'!AE37*(1-Drivers!AE7)) -> -6542.4378 | AF29: =-('Revenue Build'!AF37*(1-Drivers!AF7)) -> -6619.7575 | AG29: =-('Revenue Build'!AG37*(1-Drivers!AG7)) -> -6714.3255
C30: Net Revenue | F30: =SUM(F28:F29) -> 14281 | G30: =SUM(G28:G29) -> 15054 | H30: =SUM(H28:H29) -> 15381 | I30: =SUM(I28:I29) -> 15799 | J30: =SUM(F30:I30) -> 60515 | K30: =SUM(K28:K29) -> 15801 | L30: =SUM(L28:L29) -> 16333 | M30: =SUM(M28:M29) -> 16636 | N30: =SUM(N28:N29) -> 17179 | O30: =SUM(K30:N30) -> 65949 | P30: =SUM(P28:P29) -> 16967 | Q30: =SUM(Q28:Q29) -> 17856 | R30: =SUM(R28:R29) -> 18426 | S30: =SUM(S28:S29) -> 18980 | T30: =SUM(T28:T29) -> 72229 | U30: =SUM(U28:U29) -> 18907 | V30: =SUM(V28:V29) -> 19684.947 | W30: =SUM(W28:W29) -> 20391.922 | X30: =SUM(X28:X29) -> 21182.022 | Y30: =SUM(U30:X30) -> 80165.89 | Z30: =SUM(Z28:Z29) -> 21329.959 | AA30: =SUM(AA28:AA29) -> 22395.103 | AB30: =SUM(AB28:AB29) -> 22946.492 | AC30: =SUM(AC28:AC29) -> 23930.688 | AD30: =SUM(Z30:AC30) -> 90602.242 | AE30: =SUM(AE28:AE29) -> 98096.469 | AF30: =SUM(AF28:AF29) -> 105345.02 | AG30: =SUM(AG28:AG29) -> 112125.96
C31: Total Provisions for Credit Losses | F31: -1055 | G31: -1198 | H31: -1233 | I31: =-4923-SUM(F31:H31) -> -1437 | J31: =SUM(F31:I31) -> -4923 | K31: -1269 | L31: -1268 | M31: -1356 | N31: =-5185-SUM(K31:M31) -> -1292 | O31: =SUM(K31:N31) -> -5185 | P31: -1150 | Q31: -1405 | R31: -1287 | S31: =-5256-SUM(P31:R31) -> -1414 | T31: =SUM(P31:S31) -> -5256 | U31: -1251 | V31: =Drivers!V50*Model!V28 -> -1434.1274 | W31: =Drivers!W50*Model!W28 -> -1384.0532 | X31: =Drivers!X50*Model!X28 -> -1503.086 | Y31: =SUM(U31:X31) -> -5572.2666 | Z31: =Drivers!Z50*Model!Z28 -> -1429.8745 | AA31: =Drivers!AA50*Model!AA28 -> -1568.0576 | AB31: =Drivers!AB50*Model!AB28 -> -1605.7746 | AC31: =Drivers!AC50*Model!AC28 -> -1642.1648 | AD31: =SUM(Z31:AC31) -> -6245.8714 | AE31: =Drivers!AE50*Model!AE28 -> -6592.2512 | AF31: =Drivers!AF50*Model!AF28 -> -7053.7813 | AG31: =Drivers!AG50*Model!AG28 -> -7486.9378
C32: Gross Profit | F32: =F30+F31 -> 13226 | G32: =G30+G31 -> 13856 | H32: =H30+H31 -> 14148 | I32: =I30+I31 -> 14362 | J32: =J30+J31 -> 55592 | K32: =K30+K31 -> 14532 | L32: =L30+L31 -> 15065 | M32: =M30+M31 -> 15280 | ... X32: =X30+X31 -> 19678.936 | Y32: =SUM(U32:X32) -> 74593.624 | Z32: =Z30+Z31 -> 19900.084 | AA32: =AA30+AA31 -> 20827.046 | AB32: =AB30+AB31 -> 21340.718 | AC32: =AC30+AC31 -> 22288.523 | AD32: =SUM(Z32:AC32) -> 84356.371 | AE32: =SUM(AE30:AE31) -> 91504.218 | AF32: =SUM(AF30:AF31) -> 98291.244 | AG32: =SUM(AG30:AG31) -> 104639.02
C34: Selling, General & Administration (SG&A) | F34: =-1341-2014 -> -3355 | G34: =-1408-1875 -> -3283 | H34: =-1236-2047 -> -3283 | I34: =(-5213-8067)-SUM(F34:H34) -> -3359 | J34: =SUM(F34:I34) -> -13280 | K34: =-1476-2098 -> -3574 | L34: =-1480-1949 -> -3429 | M34: =-1470-2049 -> -3519 | N34: =(-6040-8198)-SUM(K34:M34) -> -3716 | O34: =SUM(K34:N34) -> -14238 | P34: =-1486-2120 -> -3606 | Q34: =-1555-2152 -> -3707 | R34: =-1599-2239 -> -3838 | S34: =(-6252-9016)-SUM(P34:R34) -> -4117 | T34: =SUM(P34:S34) -> -15268 | U34: =-1480-2482 -> -3962 | V34: =V67*V$28 -> -4019.9026 | W34: =W67*W$28 -> -4152.1596 | X34: =X67*X$28 -> -4278.0141 | Y34: =SUM(U34:X34) -> -16412.076 | Z34: =Z67*Z$28 -> -4312.6858 | AA34: =AA67*AA$28 -> -4487.0571 | AB34: =AB67*AB$28 -> -4545.5773 | AC34: =AC67*AC$28 -> -4669.9062 | AD34: =SUM(Z34:AC34) -> -18015.226 | AE34: =AE67*AE$28 -> -19044.281 | AF34: =AF67*AF$28 -> -20265.626 | AG34: =AG67*AG$28 -> -21510.091
C35: Variable Customer Engagement (VCE) | F35: =-3766-1393-983 -> -6142 | G35: =-3956-1388-949 -> -6293 | H35: =-3794-1393-973 -> -6160 | I35: =(-15367-5657-3968)-SUM(F35:H35) -> -6397 | J35: =SUM(F35:I35) -> -24992 | K35: =-3774-1392-1171 -> -6337 | L35: =-4227-1427-1154 -> -6808 | M35: =-4168-1430-1179 -> -6777 | N35: =(-16599-5886-4782)-SUM(K35:M35) -> -7345 | O35: =SUM(K35:N35) -> -27267 | P35: =-4378-1529-1328 -> -7235 | Q35: =-4618-1589-1301 -> -7508 | R35: =-4608-1611-1477 -> -7696 | S35: =(-18409-6457-6057)-SUM(P35:R35) -> -8484 | T35: =SUM(P35:S35) -> -30923 | U35: =-4891-1591-1975 -> -8457 | V35: =V68*V$28 -> -8604.7644 | W35: =W68*W$28 -> -8862.4053 | X35: =X68*X$28 -> -9087.8893 | Y35: =SUM(U35:X35) -> -35012.059 | Z35: =Z68*Z$28 -> -9086.6215 | AA35: =AA68*AA$28 -> -9408.3455 | AB35: =AB68*AB$28 -> -9585.2391 | AC35: =AC68*AC$28 -> -9955.6242 | AD35: =SUM(Z35:AC35) -> -38035.83 | AE35: =AE68*AE$28 -> -40704.535 | AF35: =AF68*AF$28 -> -43498.318 | AG35: =AG68*AG$28 -> -46110.03
C36: Research & Development (R&D) | F36: 0 | G36: 0 | H36: 0 | I36: 0 | J36: =SUM(F36:I36) -> 0 | K36: 0 | L36: 0 | M36: 0 | N36: 0 | O36: =SUM(K36:N36) -> 0 | P36: 0 | Q36: 0 | R36: 0 | S36: 0 | T36: =SUM(P36:S36) -> 0 | U36: 0 | V36: =V69*V$28 -> 0 | W36: =W69*W$28 -> 0 | X36: =X69*X$28 -> 0 | Y36: =SUM(U36:X36) -> 0 | Z36: =Z69*Z$28 -> 0 | AA36: =AA69*AA$28 -> 0 | AB36: =AB69*AB$28 -> 0 | AC36: =AC69*AC$28 -> 0 | AD36: =SUM(Z36:AC36) -> 0 | AE36: =AE69*AE$28 -> 0 | AF36: =AF69*AF$28 -> 0 | AG36: =AG69*AG$28 -> 0
C37: Depreciation & Amortization (incl. in SG&A) | F37: =-1651/4 -> -412.75 | G37: =-1651/4 -> -412.75 | H37: =-1651/4 -> -412.75 | I37: =-1651/4 -> -412.75 | J37: =SUM(F37:I37) -> -1651 | K37: -419 | L37: -419 | M37: -419 | N37: -419 | O37: =SUM(K37:N37) -> -1676 | P37: -444.25 | Q37: -444.25 | R37: -444.25 | S37: -444.25 | T37: =SUM(P37:S37) -> -1777 | U37: -468 | V37: =-V76 -> -568.95935 | W37: =-W76 -> -573.76781 | X37: =-X76 -> -574.28974 | Y37: =SUM(U37:X37) -> -2185.0169 | Z37: =-Z76 -> -574.58996 | AA37: =-AA76 -> -578.36971 | AB37: =-AB76 -> -580.31308 | AC37: =-AC76 -> -581.30234 | AD37: =SUM(Z37:AC37) -> -2314.5751 | AE37: =-AE76 -> -2352.1884 | AF37: =-AF76 -> -2344.2727 | AG37: =-AG76 -> -2557.6408
C38: Other Operating Income (Expense) | F38: -1562 | G38: -1546 | H38: -1605 | I38: =-6807-SUM(F38:H38) -> -2094 | J38: =SUM(F38:I38) -> -6807 | K38: -1476 | L38: -1038 | M38: -1780 | N38: =-6364-SUM(K38:M38) -> -2070 | O38: =SUM(K38:N38) -> -6364 | P38: -1646 | Q38: -1686 | R38: -1780 | S38: =-6987-SUM(P38:R38) -> -1875 | T38: =SUM(P38:S38) -> -6987 | U38: -1459 | V38: =V70*V$28 -> -1868.7115 | W38: =W70*W$28 -> -1852.8454 | X38: =X70*X$28 -> -1896.2008 | Y38: =SUM(U38:X38) -> -7076.7577 | Z38: =Z70*Z$28 -> -2006.4367 | AA38: =AA70*AA$28 -> -2122.9087 | AB38: =AB70*AB$28 -> -2050.4506 | AC38: =AC70*AC$28 -> -2232.3178 | AD38: =SUM(Z38:AC38) -> -8412.1139 | AE38: =AE70*AE$28 -> -8998.946 | AF38: =AF70*AF$28 -> -9628.9713 | AG38: =AG70*AG$28 -> -10220.264
C39: Operating Income | F39: =IF($C$37="Depreciation & Amortization (incl. in SG&A)",F32+SUM(F34:F36,F38),F32+SUM(F34:F38)) -> 2167 | G39: =IF($C$37="Depreciation & Amortization (incl. in SG&A)",G32+SUM(G34:G36,G38),G32+SUM(G34:G38)) -> 2734 | H39: =IF($C$37="Depreciation & Amortization (incl. in SG&A)",H32+SUM(H34:H36,H38),H32+SUM(H34:H38)) -> 3100 | I39: =IF($C$37="Depreciation & Amortization (incl. in SG&A)",I32+SUM(I34:I36,I38),I32+SUM(I34:I38)) -> 2512 | J39: =SUM(F39:I39) -> 10513 | K39: =IF($C$37="Depreciation & Amortization (incl. in SG&A)",K32+SUM(K34:K36,K38),K32+SUM(K34:K38)) -> 3145 | L39: =IF($C$37="Depreciation & Amortization (incl. in SG&A)",L32+SUM(L34:L36,L38),L32+SUM(L34:L38)) -> 3790 | M39: =IF($C$37="Depreciation & Amortization (incl. in SG&A)",M32+SUM(M34:M36,M38),M32+SUM(M34:M38)) -> 3204 | N39: =IF($C$37="Depreciation & Amortization (incl. in SG&A)",N32+SUM(N34:N36,N38),N32+SUM(N34:N38)) -> 2756 | O39: =SUM(K39:N39) -> 12895 | P39: =IF($C$37="Depreciation & Amortization (incl. in SG&A)",P32+SUM(P34:P36,P38),P32+SUM(P34:P38)) -> 3330 | Q39: =IF($C$37="Depreciation & Amortization (incl. in SG&A)",Q32+SUM(Q34:Q36,Q38),Q32+SUM(Q34:Q38)) -> 3550 | R39: =IF($C$37="Depreciation & Amortization (incl. in SG&A)",R32+SUM(R34:R36,R38),R32+SUM(R34:R38)) -> 3825 | S39: =IF($C$37="Depreciation & Amortization (incl. in SG&A)",S32+SUM(S34:S36,S38),S32+SUM(S34:S38)) -> 3090 | T39: =SUM(P39:S39) -> 13795 | U39: =IF($C$37="Depreciation & Amortization (incl. in SG&A)",U32+SUM(U34:U36,U38),U32+SUM(U34:U38)) -> 3778 | V39: =IF(Cover!$F$37="Bottom Up",'Segment Analysis'!V33,IF($C$37="Depreciation & Amortization (incl. in SG&A)",V32+SUM(V34:V36,V38),V32+SUM(V34:V38))) -> 3757.4408 | W39: =IF(Cover!$F$37="Bottom Up",'Segment Analysis'!W33,IF($C$37="Depreciation & Amortization (incl. in SG&A)",W32+SUM(W34:W36,W38),W32+SUM(W34:W38))) -> 4140.4584 | X39: =IF(Cover!$F$37="Bottom Up",'Segment Analysis'!X33,IF($C$37="Depreciation & Amortization (incl. in SG&A)",X32+SUM(X34:X36,X38),X32+SUM(X34:X38))) -> 4416.8314 | Y39: =SUM(U39:X39) -> 16092.731 | Z39: =IF(Cover!$F$37="Bottom Up",'Segment Analysis'!Z33,IF($C$37="Depreciation & Amortization (incl. in SG&A)",Z32+SUM(Z34:Z36,Z38),Z32+SUM(Z34:Z38))) -> 4494.3402 | AA39: =IF(Cover!$F$37="Bottom Up",'Segment Analysis'!AA33,IF($C$37="Depreciation & Amortization (incl. in SG&A)",AA32+SUM(AA34:AA36,AA38),AA32+SUM(AA34:AA38))) -> 4808.7344 | AB39: =IF(Cover!$F$37="Bottom Up",'Segment Analysis'!AB33,IF($C$37="Depreciation & Amortization (incl. in SG&A)",AB32+SUM(AB34:AB36,AB38),AB32+SUM(AB34:AB38))) -> 5159.4508 | AC39: =IF(Cover!$F$37="Bottom Up",'Segment Analysis'!AC33,IF($C$37="Depreciation & Amortization (incl. in SG&A)",AC32+SUM(AC34:AC36,AC38),AC32+SUM(AC34:AC38))) -> 5430.6746 | AD39: =SUM(Z39:AC39) -> 19893.2 | AE39: =IF(Cover!$F$37="Bottom Up",'Segment Analysis'!AE33,IF($C$37="Depreciation & Amortization (incl. in SG&A)",AE32+SUM(AE34:AE36,AE38),AE32+SUM(AE34:AE38))) -> 22756.456 | AF39: =IF(Cover!$F$37="Bottom Up",'Segment Analysis'!AF33,IF($C$37="Depreciation & Amortization (incl. in SG&A)",AF32+SUM(AF34:AF36,AF38),AF32+SUM(AF34:AF38))) -> 24898.329 | AG39: =IF(Cover!$F$37="Bottom Up",'Segment Analysis'!AG33,IF($C$37="Depreciation & Amortization (incl. in SG&A)",AG32+SUM(AG34:AG36,AG38),AG32+SUM(AG34:AG38))) -> 26798.634
V40: =+V39/V28 -> 0.17292124 | W40: =+W39/W28 -> 0.18547583 | X40: =+X39/X28 -> 0.19100307
C41: Goodwill Impairment | F41: 0 | G41: 0 | H41: 0 | I41: 0 | J41: =SUM(F41:I41) -> 0 | K41: 0 | L41: 0 | M41: 0 | N41: 0 | O41: =SUM(K41:N41) -> 0 | P41: 0 | Q41: 0 | R41: 0 | S41: 0 | T41: =SUM(P41:S41) -> 0 | U41: 0 | V41: =Drivers!V67 -> 0 | W41: =Drivers!W67 -> 0 | X41: =Drivers!X67 -> 0 | Y41: =SUM(U41:X41) -> 0 | Z41: =Drivers!Z67 -> 0 | AA41: =Drivers!AA67 -> 0 | AB41: =Drivers!AB67 -> 0 | AC41: =Drivers!AC67 -> 0 | AD41: =SUM(Z41:AC41) -> 0 | AE41: =Drivers!AE67 -> 0 | AF41: =Drivers!AF67 -> 0 | AG41: =Drivers!AG67 -> 0
C42: Pre-Tax Income (Loss) | F42: =F39+SUM(F41) -> 2167 | G42: =G39+SUM(G41:G41) -> 2734 | H42: =H39+SUM(H41:H41) -> 3100 | I42: =I39+SUM(I41:I41) -> 2512 | J42: =SUM(F42:I42) -> 10513 | K42: =K39+SUM(K41:K41) -> 3145 | L42: =L39+SUM(L41:L41) -> 3790 | M42: =M39+SUM(M41:M41) -> 3204 | N42: =N39+SUM(N41:N41) -> 2756 | O42: =SUM(K42:N42) -> 12895 | P42: =P39+SUM(P41:P41) -> 3330 | Q42: =Q39+SUM(Q41:Q41) -> 3550 | R42: =IF($C$8="On",R39+SUM(R41:R41),IF($C$8="off",R39+SUM(R41:R41),"N/A")) -> 3825 | S42: =IF($C$8="On",S39+SUM(S41:S41),IF($C$8="off",S39+SUM(S41:S41),"N/A")) -> 3090 | T42: =T39-T41 -> 13795 | U42: =U39+SUM(U41:U41) -> 3778 | V42: =IF($C$8="On",V39+SUM(V41:V41),IF($C$8="off",V39+SUM(V41:V41),"N/A")) -> 3757.4408 | W42: =IF($C$8="On",W39+SUM(W41:W41),IF($C$8="off",W39+SUM(W41:W41),"N/A")) -> 4140.4584 | X42: =IF($C$8="On",X39+SUM(X41:X41),IF($C$8="off",X39+SUM(X41:X41),"N/A")) -> 4416.8314 | Y42: =SUM(U42:X42) -> 16092.731 | Z42: =IF($C$8="On",Z39+SUM(Z41:Z41),IF($C$8="off",Z39+SUM(Z41:Z41),"N/A")) -> 4494.3402 | AA42: =IF($C$8="On",AA39+SUM(AA41:AA41),IF($C$8="off",AA39+SUM(AA41:AA41),"N/A")) -> 4808.7344 | AB42: =IF($C$8="On",AB39+SUM(AB41:AB41),IF($C$8="off",AB39+SUM(AB41:AB41),"N/A")) -> 5159.4508 | AC42: =IF($C$8="On",AC39+SUM(AC41:AC41),IF($C$8="off",AC39+SUM(AC41:AC41),"N/A")) -> 5430.6746 | AD42: =SUM(Z42:AC42) -> 19893.2 | AE42: =IF($C$8="On",AE39+SUM(AE41:AE41),IF($C$8="off",AE39+SUM(AE41:AE41),"N/A")) -> 22756.456 | AF42: =IF($C$8="On",AF39+SUM(AF41:AF41),IF($C$8="off",AF39+SUM(AF41:AF41),"N/A")) -> 24898.329 | AG42: =IF($C$8="On",AG39+SUM(AG41:AG41),IF($C$8="off",AG39+SUM(AG41:AG41),"N/A")) -> 26798.634
C44: Income Tax Provision (Expense) | F44: -351 | G44: -560 | H44: -649 | I44: =-2139-SUM(F44:H44) -> -579 | J44: =SUM(F44:I44) -> -2139 | K44: -708 | L44: -775 | M44: -697 | N44: =-2766-SUM(K44:M44) -> -586 | O44: =SUM(K44:N44) -> -2766 | P44: -746 | Q44: -665 | R44: -923 | S44: =-2962-SUM(P44:R44) -> -628 | T44: =SUM(P44:S44) -> -2962 | U44: -807 | V44: =-V71*V42 -> -804.09233 | W44: =-W71*W42 -> -886.0581 | X44: =-X71*X42 -> -945.20192 | Y44: =SUM(U44:X44) -> -3442.3523 | Z44: =-Z71*Z42 -> -966.28314 | AA44: =-AA71*AA42 -> -1033.8779 | AB44: =-AB71*AB42 -> -1109.2819 | AC44: =-AC71*AC42 -> -1167.595 | AD44: =SUM(Z44:AC44) -> -4277.038 | AE44: =-AE71*AE42 -> -4915.3945 | AF44: =-AF71*AF42 -> -5353.1407 | AG44: =-AG71*AG42 -> -5734.9077
C45: Net Income (Loss) | F45: =F42+F44 -> 1816 | G45: =G42+G44 -> 2174 | H45: =H42+H44 -> 2451 | I45: =I42+I44 -> 1933 | J45: =SUM(F45:I45) -> 8374 | K45: =K42+K44 -> 2437 | L45: =L42+L44 -> 3015 | M45: =M42+M44 -> 2507 | N45: =N42+N44 -> 2170 | O45: =SUM(K45:N45) -> 10129 | P45: =P42+P44 -> 2584 | Q45: =Q42+Q44 -> 2885 | R45: =R42+R44 -> 2902 | S45: =S42+S44 -> 2462 | T45: =T42+T44 -> 10833 | U45: =U42+U44 -> 2971 | V45: =V42+V44 -> 2953.3485 | W45: =W42+W44 -> 3254.4003 | X45: =X42+X44 -> 3471.6295 | Y45: =SUM(U45:X45) -> 12650.378 | Z45: =Z42+Z44 -> 3528.057 | AA45: =AA42+AA44 -> 3774.8565 | AB45: =AB42+AB44 -> 4050.1689 | AC45: =AC42+AC44 -> 4263.0796 | AD45: =SUM(Z45:AC45) -> 15616.162 | AE45: =AE42+AE44 -> 17841.062 | AF45: =AF42+AF44 -> 19545.188 | AG45: =AG42+AG44 -> 21063.727
C47: Net Unrealized Debt Securities Gains (Losses) | F47: 19 | G47: 1 | H47: 14 | I47: =50-SUM(F47:H47) -> 16 | J47: =SUM(F47:I47) -> 50 | K47: 1 | L47: 3 | M47: 4 | N47: =5-SUM(K47:M47) -> -3 | O47: =SUM(K47:N47) -> 5 | P47: 3 | Q47: 0 | R47: 1 | S47: =5-SUM(P47:R47) -> 1 | T47: =SUM(P47:S47) -> 5 | U47: -7 | V47: 0 | W47: 0 | X47: 0 | Y47: =SUM(U47:X47) -> -7 | Z47: 0 | AA47: 0 | AB47: 0 | AC47: 0 | AD47: =SUM(Z47:AC47) -> 0 | AE47: 0 | AF47: 0 | AG47: 0
C48: FX Adjustments | F48: 28 | G48: 25 | H48: -110 | I48: =51-SUM(F48:H48) -> 108 | J48: =SUM(F48:I48) -> 51 | K48: -87 | L48: -49 | M48: 1 | N48: =-353-SUM(K48:M48) -> -218 | O48: =SUM(K48:N48) -> -353 | P48: 17 | Q48: 115 | R48: -6 | S48: =141-SUM(P48:R48) -> 15 | T48: =SUM(P48:S48) -> 141 | U48: -22 | V48: 0 | W48: 0 | X48: 0 | Y48: =SUM(U48:X48) -> -22 | Z48: 0 | AA48: 0 | AB48: 0 | AC48: 0 | AD48: =SUM(Z48:AC48) -> 0 | AE48: 0 | AF48: 0 | AG48: 0
C49: Net Unrealized Pension and Other Benefits | F49: 57 | G49: -4 | H49: 4 | I49: =37-SUM(F49:H49) -> -20 | J49: =SUM(F49:I49) -> 37 | K49: 3 | L49: 1 | M49: 0 | N49: =25-SUM(K49:M49) -> 21 | O49: =SUM(K49:N49) -> 25 | P49: 9 | Q49: 3 | R49: 4 | S49: =-28-SUM(P49:R49) -> -44 | T49: =SUM(P49:S49) -> -28 | U49: -5 | V49: 0 | W49: 0 | X49: 0 | Y49: =SUM(U49:X49) -> -5 | Z49: 0 | AA49: 0 | AB49: 0 | AC49: 0 | AD49: =SUM(Z49:AC49) -> 0 | AE49: 0 | AF49: 0 | AG49: 0
C50: Income (Loss) Due to Non-Controlling Interest | F50: 0 | G50: 0 | H50: 0 | I50: 0 | J50: =SUM(F50:I50) -> 0 | K50: 0 | L50: 0 | M50: 0 | N50: 0 | O50: =SUM(K50:N50) -> 0 | P50: 0 | Q50: 0 | R50: 0 | S50: 0 | T50: =SUM(P50:S50) -> 0 | U50: 0 | V50: 0 | W50: 0 | X50: 0 | Y50: =SUM(U50:X50) -> 0 | Z50: 0 | AA50: 0 | AB50: 0 | AC50: 0 | AD50: =SUM(Z50:AC50) -> 0 | AE50: 0 | AF50: 0 | AG50: 0
C51: Adj. Net Income (Loss) | F51: =SUM(F45:F50) -> 1920 | G51: =SUM(G45:G50) -> 2196 | H51: =SUM(H45:H50) -> 2359 | I51: =SUM(I45:I50) -> 2037 | J51: =SUM(F51:I51) -> 8512 | K51: =SUM(K45:K50) -> 2354 | L51: =SUM(L45:L50) -> 2970 | M51: =SUM(M45:M50) -> 2512 | N51: =SUM(N45:N50) -> 1970 | O51: =SUM(K51:N51) -> 9806 | P51: =SUM(P45:P50) -> 2613 | Q51: =SUM(Q45:Q50) -> 3003 | R51: =SUM(R45:R50) -> 2901 | S51: =SUM(S45:S50) -> 2434 | T51: =SUM(P51:S51) -> 10951 | U51: =SUM(U45:U50) -> 2937 | V51: =SUM(V45:V50) -> 2953.3485 | W51: =SUM(W45:W50) -> 3254.4003 | X51: =SUM(X45:X50) -> 3471.6295 | Y51: =SUM(U51:X51) -> 12616.378 | Z51: =SUM(Z45:Z50) -> 3528.057 | AA51: =SUM(AA45:AA50) -> 3774.8565 | AB51: =SUM(AB45:AB50) -> 4050.1689 | AC51: =SUM(AC45:AC50) -> 4263.0796 | AD51: =SUM(Z51:AC51) -> 15616.162 | AE51: =SUM(AE45:AE50) -> 17841.062 | AF51: =SUM(AF45:AF50) -> 19545.188 | AG51: =SUM(AG45:AG50) -> 21063.727
C53: GAAP EPS (Basic) | F53: =(F45)/F282 -> 2.4441454 | G53: =(G45)/G282 -> 2.9378378 | H53: =(H45)/H282 -> 3.3483607 | I53: =(I45)/I282 -> 2.629932 | J53: =J45/J282 -> 11.393197 | K53: =(K45)/K282 -> 3.3800277 | L53: =(L45)/L282 -> 4.2108939 | M53: =(M45)/M282 -> 3.5409605 | N53: =(N45)/N282 -> 3.0477528 | O53: =O45/O282 -> 14.226124 | P53: =(P45)/P282 -> 3.6861626 | Q53: =(Q45)/Q282 -> 4.1332378 | R53: =(R45)/R282 -> 4.1936416 | S53: =(S45)/S282 -> 3.542446 | T53: =T45/T282 -> 15.58705 | U53: =(U45)/U282 -> 4.3372263 | V53: =V45/V282 -> 4.3129172 | W53: =W45/W282 -> 4.7557778 | X53: =X45/X282 -> 5.0766627 | Y53: =Y45/Y282 -> 18.481779 | Z53: =Z45/Z282 -> 5.1626499 | AA53: =AA45/AA282 -> 5.5274834 | AB53: =AB45/AB282 -> 5.9345834 | AC53: =AC45/AC282 -> 6.2507316 | ... AG53: =AG45/AG282 -> 31.102019
C54: GAAP EPS (Diluted) | F54: =(F45)/F284 -> 2.4408602 | G54: =(G45)/G284 -> 2.9338731 | H54: =(H45)/H284 -> 3.3437926 | I54: =(I45)/I284 -> 2.6263587 | J54: =J45/J284 -> 11.377717 | K54: =(K45)/K284 -> 3.3753463 | L54: =(L45)/L284 -> 4.2050209 | M54: =(M45)/M284 -> 3.5359661 | N54: =(N45)/N284 -> 3.0434783 | O54: =O45/O284 -> 14.206171 | P54: =(P45)/P284 -> 3.6809117 | Q54: =(Q45)/Q284 -> 4.1273247 | R54: =(R45)/R284 -> 4.1875902 | S54: =(S45)/S284 -> 3.5373563 | T54: =T45/T284 -> 15.564655 | U54: =(U45)/U284 -> 4.3309038 | V54: =V45/V284 -> 4.3066281 | W54: =W45/W284 -> 4.7488381 | X54: =X45/X284 -> 5.0692497 | Y54: =Y45/Y284 -> 18.454817 | Z54: =Z45/Z284 -> 5.1551064 | AA54: =AA45/AA284 -> 5.5194014 | AB54: =AB45/AB284 -> 5.9259003 | AC54: =AC45/AC284 -> 6.2415799 | ... AG54: =AG45/AG284 -> 31.056162
C56: Adj. EPS (Basic) | F56: =F51/F282 -> 2.5841184 | G56: =G51/G282 -> 2.9675676 | H56: =H51/H282 -> 3.2226776 | I56: =I51/I282 -> 2.7714286 | J56: =J51/J282 -> 11.580952 | K56: =K51/K282 -> 3.2649098 | L56: =L51/L282 -> 4.1480447 | M56: =M51/M282 -> 3.5480226 | ... AG56: =AG51/AG282 -> 31.102019
C57: Adj. EPS (Diluted) | F57: =F51/F284 -> 2.5806452 | G57: =G51/G284 -> 2.9635628 | H57: =H51/H284 -> 3.218281 | I57: =I51/I284 -> 2.767663 | J57: =J51/J284 -> 11.565217 | K57: =K51/K284 -> 3.2603878 | L57: =L51/L284 -> 4.1422594 | M57: =M51/M284 -> 3.5430183 | ... AG57: =AG51/AG284 -> 31.056162
C59: =C39 -> Operating Income | F59: =F39 -> 2167 | G59: =G39 -> 2734 | H59: =H39 -> 3100 | I59: =I39 -> 2512 | J59: =SUM(F59:I59) -> 10513 | K59: =K39 -> 3145 | L59: =L39 -> 3790 | M59: =M39 -> 3204 | N59: =N39 -> 2756 | O59: =SUM(K59:N59) -> 12895 | P59: =P39 -> 3330 | Q59: =Q39 -> 3550 | R59: =R39 -> 3825 | S59: =S39 -> 3090 | T59: =SUM(P59:S59) -> 13795 | U59: =U39 -> 3778 | V59: =V39 -> 3757.4408 | W59: =W39 -> 4140.4584 | X59: =X39 -> 4416.8314 | Y59: =SUM(U59:X59) -> 16092.731 | Z59: =Z39 -> 4494.3402 | AA59: =AA39 -> 4808.7344 | AB59: =AB39 -> 5159.4508 | AC59: =AC39 -> 5430.6746 | AD59: =SUM(Z59:AC59) -> 19893.2 | AE59: =AE39 -> 22756.456 | AF59: =AF39 -> 24898.329 | AG59: =AG39 -> 26798.634
C60: Depreciation & Amortization | F60: =-F37 -> 412.75 | G60: =-G37 -> 412.75 | H60: =-H37 -> 412.75 | I60: =-I37 -> 412.75 | J60: =SUM(F60:I60) -> 1651 | K60: =-K37 -> 419 | L60: =-L37 -> 419 | M60: =-M37 -> 419 | N60: =-N37 -> 419 | O60: =SUM(K60:N60) -> 1676 | P60: =-P37 -> 444.25 | Q60: =-Q37 -> 444.25 | R60: =-R37 -> 444.25 | S60: =-S37 -> 444.25 | T60: =SUM(P60:S60) -> 1777 | U60: =-U37 -> 468 | V60: =-V37 -> 568.95935 | W60: =-W37 -> 573.76781 | X60: =-X37 -> 574.28974 | Y60: =SUM(U60:X60) -> 2185.0169 | Z60: =-Z37 -> 574.58996 | AA60: =-AA37 -> 578.36971 | AB60: =-AB37 -> 580.31308 | AC60: =-AC37 -> 581.30234 | AD60: =SUM(Z60:AC60) -> 2314.5751 | AE60: =-AE37 -> 2352.1884 | AF60: =-AF37 -> 2344.2727 | AG60: =-AG37 -> 2557.6408
C61: EBITDA | F61: =SUM(F59:F60) -> 2579.75 | G61: =SUM(G59:G60) -> 3146.75 | H61: =SUM(H59:H60) -> 3512.75 | I61: =SUM(I59:I60) -> 2924.75 | J61: =SUM(F61:I61) -> 12164 | K61: =SUM(K59:K60) -> 3564 | L61: =SUM(L59:L60) -> 4209 | M61: =SUM(M59:M60) -> 3623 | N61: =SUM(N59:N60) -> 3175 | O61: =SUM(K61:N61) -> 14571 | P61: =SUM(P59:P60) -> 3774.25 | Q61: =SUM(Q59:Q60) -> 3994.25 | R61: =SUM(R59:R60) -> 4269.25 | S61: =SUM(S59:S60) -> 3534.25 | T61: =SUM(P61:S61) -> 15572 | U61: =SUM(U59:U60) -> 4246 | V61: =SUM(V59:V60) -> 4326.4002 | W61: =SUM(W59:W60) -> 4714.2262 | X61: =SUM(X59:X60) -> 4991.1211 | Y61: =SUM(U61:X61) -> 18277.747 | Z61: =SUM(Z59:Z60) -> 5068.9301 | AA61: =SUM(AA59:AA60) -> 5387.1041 | AB61: =SUM(AB59:AB60) -> 5739.7638 | AC61: =SUM(AC59:AC60) -> 6011.977 | AD61: =SUM(Z61:AC61) -> 22207.775 | AE61: =SUM(AE59:AE60) -> 25108.645 | AF61: =SUM(AF59:AF60) -> 27242.601 | AG61: =SUM(AG59:AG60) -> 29356.275
C63: Income Statement Analysis | F63: =F$25 -> 1Q23 | G63: =G$25 -> 2Q23 | H63: =H$25 -> 3Q23 | I63: =I$25 -> 4Q23 | J63: =J$25 -> 2023 | K63: =K$25 -> 1Q24 | L63: =L$25 -> 2Q24 | M63: =M$25 -> 3Q24 | ... AG63: =AG$25 -> 2030e | AH63: x
A64: x | C64: Drivers
C66: Gross Margin | F66: =F32/F28 -> 0.84166985 | G66: =G32/G28 -> 0.82850993 | H66: =H32/H28 -> 0.82356365 | I66: =I32/I28 -> 0.80926354 | J66: =J32/J28 -> 0.82524791 | K66: =K32/K28 -> 0.81608356 | L66: =L32/L28 -> 0.81888351 | M66: =M32/M28 -> 0.81367485 | ... U66: =U32/U28 -> 0.84559387 | V66: =IF(Cover!$F$37="Bottom Up",(V32/V28),Drivers!V7) -> 0.695 | W66: =IF(Cover!$F$37="Bottom Up",(W32/W28),Drivers!W7) -> 0.72 | X66: =IF(Cover!$F$37="Bottom Up",(X32/X28),Drivers!X7) -> 0.72 | Y66: =Y32/Y28 -> 0.84710571 | Z66: =IF(Cover!$F$37="Bottom Up",(Z32/Z28),Drivers!Z7) -> 0.75 | AA66: =IF(Cover!$F$37="Bottom Up",(AA32/AA28),Drivers!AA7) -> 0.753 | AB66: =IF(Cover!$F$37="Bottom Up",(AB32/AB28),Drivers!AB7) -> 0.755 | AC66: =IF(Cover!$F$37="Bottom Up",(AC32/AC28),Drivers!AC7) -> 0.765 | AD66: =AD32/AD28 -> 0.86475448 | AE66: =IF(Cover!$F$37="Bottom Up",(AE32/AE28),Drivers!AE7) -> 0.78 | AF66: =IF(Cover!$F$37="Bottom Up",(AF32/AF28),Drivers!AF7) -> 0.79 | AG66: =IF(Cover!$F$37="Bottom Up",(AG32/AG28),Drivers!AG7) -> 0.8
C67: SG&A as % of Revenue | F67: =F34/F$28 -> -0.21350388 | G67: =G34/G28 -> -0.19630471 | H67: =H34/H28 -> -0.19110542 | I67: =I34/I28 -> -0.18927143 | J67: =J34/J28 -> -0.19713794 | K67: =K34/K28 -> -0.20070759 | L67: =L34/L28 -> -0.18638909 | M67: =M34/M28 -> -0.18739017 | N67: =N34/N28 -> -0.19336039 | ... U67: =U34/U28 -> -0.18975096 | V67: =Drivers!V40 -> -0.185 | W67: =Drivers!W40 -> -0.186 | X67: =Drivers!X40 -> -0.185 | Y67: =Y34/Y28 -> -0.18638005 | Z67: =Drivers!Z40 -> -0.187 | AA67: =Drivers!AA40 -> -0.186 | AB67: =Drivers!AB40 -> -0.184 | AC67: =Drivers!AC40 -> -0.182 | AD67: =AD34/AD28 -> -0.18467779 | AE67: =Drivers!AE40 -> -0.182 | AF67: =Drivers!AF40 -> -0.181 | AG67: =Drivers!AG40 -> -0.181
C68: VCE as a % of Revenue | F68: =F35/F$28 -> -0.39086165 | G68: =G35/G$28 -> -0.37628558 | H68: =H35/H$28 -> -0.35857733 | I68: =I35/I$28 -> -0.36045529 | J68: =J35/J28 -> -0.37099935 | K68: =K35/K$28 -> -0.35587129 | L68: =L35/L$28 -> -0.37006034 | M68: =M35/M$28 -> -0.36088184 | N68: =N35/N$28 -> -0.38219378 | O68: =O35/O28 -> -0.36747483 | P68: =P35/P$28 -> -0.38213701 | Q68: =Q35/Q$28 -> -0.37666182 | R68: =R35/R$28 -> -0.37437369 | S68: =S35/S$28 -> -0.40323194 | T68: =T35/T28 -> -0.38431329 | U68: =U35/U$28 -> -0.40502874 | V68: =+Drivers!V45 -> -0.396 | W68: =+Drivers!W45 -> -0.397 | X68: =+Drivers!X45 -> -0.393 | Y68: =Y35/Y28 -> -0.39760657 | Z68: =+Drivers!Z45 -> -0.394 | AA68: =+Drivers!AA45 -> -0.39 | AB68: =+Drivers!AB45 -> -0.388 | AC68: =+Drivers!AC45 -> -0.388 | AD68: =AD35/AD28 -> -0.38991311 | AE68: =+Drivers!AE45 -> -0.389 | AF68: =+Drivers!AF45 -> -0.3885 | AG68: =+Drivers!AG45 -> -0.388
C69: R&D as a % of Revenue | F69: =F36/F28 -> 0 | G69: =G36/G28 -> 0 | H69: =H36/H28 -> 0 | I69: =I36/I28 -> 0 | J69: =J36/J28 -> 0 | K69: =K36/K28 -> 0 | L69: =L36/L28 -> 0 | M69: =M36/M28 -> 0 | ... U69: =U36/U28 -> 0 | V69: =Drivers!V55 -> 0 | W69: =Drivers!W55 -> 0 | X69: =Drivers!X55 -> 0 | Y69: =Y36/Y28 -> 0 | Z69: =Drivers!Z55 -> 0 | AA69: =Drivers!AA55 -> 0 | AB69: =Drivers!AB55 -> 0 | AC69: =Drivers!AC55 -> 0 | AD69: =AD36/AD28 -> 0 | AE69: =Drivers!AE55 -> 0 | AF69: =Drivers!AF55 -> 0 | AG69: =Drivers!AG55 -> 0
C70: Other Operating Income as a % of Revenue | F70: =F38/F28 -> -0.099401807 | G70: =G38/G28 -> -0.092442 | H70: =H38/H28 -> -0.093428023 | I70: =I38/I28 -> -0.11799177 | J70: =J38/J28 -> -0.10104804 | K70: =K38/K28 -> -0.082888752 | L70: =L38/L28 -> -0.056422243 | M70: =M38/M28 -> -0.09478673 | ... U70: =U38/U28 -> -0.069875479 | V70: =Drivers!V60 -> -0.086 | W70: =Drivers!W60 -> -0.083 | X70: =Drivers!X60 -> -0.082 | Y70: =Y38/Y28 -> -0.080365608 | Z70: =Drivers!Z60 -> -0.087 | AA70: =Drivers!AA60 -> -0.088 | AB70: =Drivers!AB60 -> -0.083 | AC70: =Drivers!AC60 -> -0.087 | AD70: =AD38/AD28 -> -0.086234307 | AE70: =Drivers!AE60 -> -0.086 | AF70: =Drivers!AF60 -> -0.086 | AG70: =Drivers!AG60 -> -0.086
C71: Tax Rate | F71: =-F44/F42 -> 0.16197508 | G71: =-G44/G42 -> 0.20482809 | H71: =-H44/H42 -> 0.20935484 | I71: =-I44/I42 -> 0.23049363 | J71: =-J44/J42 -> 0.20346238 | K71: =-K44/K42 -> 0.22511924 | L71: =-L44/L42 -> 0.20448549 | M71: =-M44/M42 -> 0.21754057 | ... U71: =-U44/U42 -> 0.21360508 | V71: =Drivers!V69 -> 0.214 | W71: =Drivers!W69 -> 0.214 | X71: =Drivers!X69 -> 0.214 | Y71: =-Y44/Y42 -> 0.21390729 | Z71: =Drivers!Z69 -> 0.215 | AA71: =Drivers!AA69 -> 0.215 | AB71: =Drivers!AB69 -> 0.215 | AC71: =Drivers!AC69 -> 0.215 | AD71: =-AD44/AD42 -> 0.215 | AE71: =Drivers!AE69 -> 0.216 | AF71: =Drivers!AF69 -> 0.215 | AG71: =Drivers!AG69 -> 0.214
A73: x | C73: Cash Flow Statement | F73: =F$25 -> 1Q23 | G73: =G$63 -> 2Q23 | H73: =H$63 -> 3Q23 | I73: =I$63 -> 4Q23 | J73: =J$63 -> 2023 | K73: =K$63 -> 1Q24 | L73: =L$63 -> 2Q24 | M73: =M$63 -> 3Q24 | N73: =N$63 -> 4Q24 | ... AG73: =AG$63 -> 2030e | AH73: x
C75: Net Income | V75: =V45 -> 2953.3485 | W75: =W45 -> 3254.4003 | X75: =X45 -> 3471.6295 | Y75: =SUM(U75:X75) -> 9679.3782 | Z75: =Z45 -> 3528.057 | AA75: =AA45 -> 3774.8565 | AB75: =AB45 -> 4050.1689 | AC75: =AC45 -> 4263.0796 | AD75: =SUM(Z75:AC75) -> 15616.162 | AE75: =AE45 -> 17841.062 | AF75: =AF45 -> 19545.188 | AG75: =AG45 -> 21063.727
C76: Depreciation & Amortization | V76: =-(V194+V208) -> 568.95935 | W76: =-(W194+W208) -> 573.76781 | X76: =-(X194+X208) -> 574.28974 | Y76: =SUM(U76:X76) -> 1717.0169 | Z76: =-(Z194+Z208) -> 574.58996 | AA76: =-(AA194+AA208) -> 578.36971 | AB76: =-(AB194+AB208) -> 580.31308 | AC76: =-(AC194+AC208) -> 581.30234 | AD76: =SUM(Z76:AC76) -> 2314.5751 | AE76: =-(AE194+AE208) -> 2352.1884 | AF76: =-(AF194+AF208) -> 2344.2727 | AG76: =-(AG194+AG208) -> 2557.6408
C77: Stock-Based Compensation | V77: =V246 -> 211.25614 | W77: =W246 -> 217.03343 | X77: =X246 -> 224.82056 | Y77: =SUM(U77:X77) -> 653.11013 | Z77: =Z246 -> 224.21866 | AA77: =AA246 -> 234.53853 | AB77: =AB246 -> 240.17996 | AC77: =AC246 -> 249.4608 | AD77: =SUM(Z77:AC77) -> 948.39795 | AE77: =AE246 -> 1017.3227 | AF77: =AF246 -> 1088.5465 | AG77: =AG246 -> 1155.3916
C78: (Increase)/Decrease in Working Capital | V78: =V174 -> -60373.396 | W78: =W174 -> 1898.1098 | X78: =X174 -> 3895.0957 | Y78: =SUM(U78:X78) -> -54580.19 | Z78: =Z174 -> 1621.9518 | AA78: =AA174 -> 5597.692 | AB78: =AB174 -> 1942.274 | AC78: =AC174 -> 4491.5419 | AD78: =SUM(Z78:AC78) -> 13653.46 | AE78: =AE174 -> 3989.4394 | AF78: =AF174 -> 10280.83 | AG78: =AG174 -> 9322.0114
C79: (Increase)/Decrease in LT Items | V79: =V228 -> -1493.016 | W79: =W228 -> -1185.3125 | X79: =X228 -> -1337.9215 | Y79: =SUM(U79:X79) -> -4016.25 | Z79: =Z228 -> -1701.2628 | AA79: =AA228 -> -1403.0274 | AB79: =AB228 -> -1322.7247 | AC79: =AC228 -> -1583.6855 | AD79: =SUM(Z79:AC79) -> -6010.7005 | AE79: =AE228 -> -6608.3678 | AF79: =AF228 -> -7305.6646 | AG79: =AG228 -> -8031.0127
C80: Net Cash From Operating Activities | V80: =SUM(V75:V79) -> -58132.848 | W80: =SUM(W75:W79) -> 4757.9988 | X80: =SUM(X75:X79) -> 6827.9139 | Y80: =SUM(U80:X80) -> -46546.935 | Z80: =SUM(Z75:Z79) -> 4247.5547 | AA80: =SUM(AA75:AA79) -> 8782.4294 | AB80: =SUM(AB75:AB79) -> 5490.2111 | AC80: =SUM(AC75:AC79) -> 8001.6991 | AD80: =SUM(Z80:AC80) -> 26521.894 | AE80: =SUM(AE75:AE79) -> 18591.644 | AF80: =SUM(AF75:AF79) -> 25953.172 | AG80: =SUM(AG75:AG79) -> 26067.758
C82: Capital Expenditures | V82: =-V193 -> -630.14689 | W82: =-W193 -> -580.40941 | X82: =-X193 -> -578.11001 | Y82: =SUM(U82:X82) -> -1788.6663 | Z82: =-Z193 -> -622.68726 | AA82: =-AA193 -> -603.09907 | AB82: =-AB193 -> -592.90139 | AC82: =-AC193 -> -667.12946 | AD82: =SUM(Z82:AC82) -> -2485.8172 | AE82: =-AE193 -> -2327.0066 | AF82: =-AF193 -> -3023.0491 | AG82: =-AG193 -> -2879.404
C83: Purchases of Intangibles | V83: =-V207 -> 0 | W83: =-W207 -> 0 | X83: =-X207 -> 0 | Y83: =SUM(U83:X83) -> 0 | Z83: =-Z207 -> 0 | AA83: =-AA207 -> 0 | AB83: =-AB207 -> 0 | AC83: =-AC207 -> 0 | AD83: =SUM(Z83:AC83) -> 0 | AE83: =-AE207 -> 0 | AF83: =-AF207 -> 0 | AG83: =-AG207 -> 0
C84: Proceeds From/(Acquisitions of) Businesses | V84: =Drivers!V99 -> 0 | W84: =Drivers!W99 -> 0 | X84: =Drivers!X99 -> 0 | Y84: =SUM(U84:X84) -> 0 | Z84: =Drivers!Z99 -> 0 | AA84: =Drivers!AA99 -> 0 | AB84: =Drivers!AB99 -> 0 | AC84: =Drivers!AC99 -> 0 | AD84: =SUM(Z84:AC84) -> 0 | AE84: =Drivers!AE99 -> 0 | AF84: =Drivers!AF99 -> 0 | AG84: =Drivers!AG99 -> 0
C85: Net Cash From Investment Activities | V85: =SUM(V82:V84) -> -630.14689 | W85: =SUM(W82:W84) -> -580.40941 | X85: =SUM(X82:X84) -> -578.11001 | Y85: =SUM(U85:X85) -> -1788.6663 | Z85: =SUM(Z82:Z84) -> -622.68726 | AA85: =SUM(AA82:AA84) -> -603.09907 | AB85: =SUM(AB82:AB84) -> -592.90139 | AC85: =SUM(AC82:AC84) -> -667.12946 | AD85: =SUM(Z85:AC85) -> -2485.8172 | AE85: =SUM(AE82:AE84) -> -2327.0066 | AF85: =SUM(AF82:AF84) -> -3023.0491 | AG85: =SUM(AG82:AG84) -> -2879.404
C87: Cash Flow Available for Financing Activities | V87: =SUM(V80,V85) -> -58762.995 | W87: =SUM(W80,W85) -> 4177.5894 | X87: =SUM(X80,X85) -> 6249.8039 | Y87: =SUM(U87:X87) -> -48335.601 | Z87: =SUM(Z80,Z85) -> 3624.8675 | AA87: =SUM(AA80,AA85) -> 8179.3303 | AB87: =SUM(AB80,AB85) -> 4897.3098 | AC87: =SUM(AC80,AC85) -> 7334.5696 | AD87: =SUM(Z87:AC87) -> 24036.077 | AE87: =SUM(AE80,AE85) -> 16264.638 | AF87: =SUM(AF80,AF85) -> 22930.123 | AG87: =SUM(AG80,AG85) -> 23188.354
C89: Issuance/(Repayment) of Revolver | V89: =V303 -> 0 | W89: =W303 -> 0 | X89: =X303 -> 0 | Y89: =SUM(U89:X89) -> -1371 | Z89: =Z303 -> 0 | AA89: =AA303 -> 0 | AB89: =AB303 -> 0 | AC89: =AC303 -> 0 | AD89: =SUM(Z89:AC89) -> 0 | AE89: =AE303 -> 0 | AF89: =AF303 -> 0 | AG89: =AG303 -> 0
C90: Issuance of Debt | V90: =V308 -> 3200 | W90: =W308 -> 3000 | X90: =X308 -> 0 | Y90: =SUM(U90:X90) -> 6200 | Z90: =Z308 -> 1200 | AA90: =AA308 -> 3500 | AB90: =AB308 -> 0 | AC90: =AC308 -> 0 | AD90: =SUM(Z90:AC90) -> 4700 | AE90: =AE308 -> 6000 | AF90: =AF308 -> 6200 | AG90: =AG308 -> 6000
C91: (Repayment of Debt) | V91: =V309 -> 0 | W91: =W309 -> 0 | X91: =X309 -> -2500 | Y91: =SUM(U91:X91) -> -2500 | Z91: =Z309 -> 0 | AA91: =AA309 -> 0 | AB91: =AB309 -> 0 | AC91: =AC309 -> -3500 | AD91: =SUM(Z91:AC91) -> -3500 | AE91: =AE309 -> -2000 | AF91: =AF309 -> -2000 | AG91: =AG309 -> -2000
C92: Issuance of Equity | V92: =V245 -> 0 | W92: =W245 -> 0 | X92: =X245 -> 0 | Y92: =SUM(U92:X92) -> 0 | Z92: =Z245 -> 0 | AA92: =AA245 -> 0 | AB92: =AB245 -> 0 | AC92: =AC245 -> 0 | AD92: =SUM(Z92:AC92) -> 0 | AE92: =AE245 -> 0 | AF92: =AF245 -> 0 | AG92: =AG245 -> 0
C93: (Repurchase) of Equity | V93: =-V241 -> -144.2125 | W93: =-W241 -> -144.2125 | X93: =-X241 -> -144.2125 | Y93: =SUM(U93:X93) -> -432.6375 | Z93: =-Z241 -> -141.84888 | AA93: =-AA241 -> -141.84888 | AB93: =-AB241 -> -141.84888 | AC93: =-AC241 -> -141.84888 | AD93: =SUM(Z93:AC93) -> -567.39552 | AE93: =-AE241 -> -565.88144 | AF93: =-AF241 -> -564.37141 | AG93: =-AG241 -> -562.8654
C94: Dividends Issued | V94: =-V267 -> -661.92 | W94: =-W267 -> -656.53 | X94: =-X267 -> -657.66 | Y94: =SUM(U94:X94) -> -1976.11 | Z94: =-Z267 -> -752.58 | AA94: =-AA267 -> -747.9696 | AB94: =-AB267 -> -745.16155 | AC94: =-AC267 -> -744.47112 | AD94: =SUM(Z94:AC94) -> -2990.1823 | AE94: =-AE267 -> -3378.906 | AF94: =-AF267 -> -3270.781 | AG94: =-AG267 -> -3368.9044
C95: Change in Noncontrolling Interests | V95: =Drivers!V108 -> 0 | W95: =Drivers!W108 -> 0 | X95: =Drivers!X108 -> 0 | Y95: =SUM(U95:X95) -> 0 | Z95: =Drivers!Z108 -> 0 | AA95: =Drivers!AA108 -> 0 | AB95: =Drivers!AB108 -> 0 | AC95: =Drivers!AC108 -> 0 | AD95: =SUM(Z95:AC95) -> 0 | AE95: =Drivers!AE108 -> 0 | AF95: =Drivers!AF108 -> 0 | AG95: =Drivers!AG108 -> 0
C96: Net Cash From Financing Activities | V96: =SUM(V89:V95) -> 2393.8675 | W96: =SUM(W89:W95) -> 2199.2575 | X96: =SUM(X89:X95) -> -3301.8725 | Y96: =SUM(U96:X96) -> 315.24 | Z96: =SUM(Z89:Z95) -> 309.41539 | AA96: =SUM(AA89:AA95) -> 2608.1498 | AB96: =SUM(AB89:AB95) -> -889.04216 | AC96: =SUM(AC89:AC95) -> -4388.3517 | AD96: =SUM(Z96:AC96) -> -2359.8287 | AE96: =SUM(AE89:AE95) -> 53.535985 | AF96: =SUM(AF89:AF95) -> 362.76996 | AG96: =SUM(AG89:AG95) -> 66.15777
C98: Effect of FX Rate Changes on Cash | V98: =Drivers!V110 -> 0 | W98: =Drivers!W110 -> 0 | X98: =Drivers!X110 -> 0 | Y98: =SUM(U98:X98) -> 0 | Z98: =Drivers!Z110 -> 0 | AA98: =Drivers!AA110 -> 0 | AB98: =Drivers!AB110 -> 0 | AC98: =Drivers!AC110 -> 0 | AD98: =SUM(Z98:AC98) -> 0 | AE98: =Drivers!AE110 -> 0 | AF98: =Drivers!AF110 -> 0 | AG98: =Drivers!AG110 -> 0
C99: Beginning Cash Adjustments | V99: 0 | W99: 0 | X99: 0 | Y99: =SUM(U99:X99) -> 0 | Z99: 0 | AA99: 0 | AB99: 0 | AC99: 0 | AD99: =SUM(Z99:AC99) -> 0 | AE99: 0 | AF99: 0 | AG99: 0
C100: Ending Cash Adjustments | V100: 0 | W100: 0 | X100: 0 | Y100: =SUM(U100:X100) -> 0 | Z100: 0 | AA100: 0 | AB100: 0 | AC100: 0 | AD100: =SUM(Z100:AC100) -> 0 | AE100: 0 | AF100: 0 | AG100: 0
C102: Beginning Cash Balance | V102: =U104+V99 -> 0 | W102: =V104+W99 -> 62511.832 | X102: =W104+X99 -> 68333.224 | Y102: =+T102 -> 0 | Z102: =Y104+Z99 -> 71873.755 | AA102: =Z104+AA99 -> 75720.922 | AB102: =AA104+AB99 -> 86701.19 | AC102: =AB104+AC99 -> 90740.151 | AD102: =Z102 -> 71873.755 | AE102: =AD104+AE99 -> 93787.34 | AF102: =AE104+AF99 -> 109956.47 | AG102: =AF104+AG99 -> 133376.01
C103: Net Change in Cash | V103: =SUM(V87,V96,V98,V100) -> 9008.3874 | W103: =SUM(W87,W96,W98,W100) -> 5821.3917 | X103: =SUM(X87,X96,X98,X100) -> 3540.5308 | Y103: =SUM(U103:X103) -> 24081.755 | Z103: =SUM(Z87,Z96,Z98,Z100) -> 3847.1668 | AA103: =SUM(AA87,AA96,AA98,AA100) -> 10980.268 | AB103: =SUM(AB87,AB96,AB98,AB100) -> 4038.961 | AC103: =SUM(AC87,AC96,AC98,AC100) -> 3047.1887 | AD103: =SUM(Z103:AC103) -> 21913.585 | AE103: =SUM(AE87,AE96,AE98,AE100) -> 16169.133 | AF103: =SUM(AF87,AF96,AF98,AF100) -> 23419.533 | AG103: =SUM(AG87,AG96,AG98,AG100) -> 23416.601
C104: Ending Cash Balance | V104: =SUM(V102:V103) -> 62511.832 | W104: =SUM(W102:W103) -> 68333.224 | X104: =SUM(X102:X103) -> 71873.755 | Y104: =SUM(Y102:Y103) -> 71873.755 | Z104: =SUM(Z102:Z103) -> 75720.922 | AA104: =SUM(AA102:AA103) -> 86701.19 | AB104: =SUM(AB102:AB103) -> 90740.151 | AC104: =SUM(AC102:AC103) -> 93787.34 | ... AG104: =SUM(AG102:AG103) -> 156792.61
A106: x | C106: Free Cash Flow Analysis | AH106: x
C108: Net Income | F108: =F45 -> 1816 | G108: =G45 -> 2174 | H108: =H45 -> 2451 | I108: =I45 -> 1933 | J108: =J45 -> 8374 | K108: =K45 -> 2437 | L108: =L45 -> 3015 | M108: =M45 -> 2507 | ... AG108: =AG45 -> 21063.727
C109: Depreciation & Amortization | F109: =-F194+-F208 -> 412.75 | G109: =-G194+-G208 -> 412.75 | H109: =-H194+-H208 -> 412.75 | I109: =-I194+-I208 -> 412.75 | J109: =SUM(F109:I109) -> 1651 | K109: =-K194+-K208 -> 419 | L109: =-L194+-L208 -> 419 | M109: =-M194+-M208 -> 419 | N109: =-N194+-N208 -> 419 | O109: =SUM(K109:N109) -> 1676 | P109: =-P194+-P208 -> 444.25 | Q109: =-Q194+-Q208 -> 444.25 | R109: =-R194+-R208 -> 444.25 | S109: =-S194+-S208 -> 444.25 | T109: =SUM(P109:S109) -> 1777 | U109: =-U194+-U208 -> 468 | V109: =-V194+-V208 -> 568.95935 | W109: =-W194+-W208 -> 573.76781 | X109: =-X194+-X208 -> 574.28974 | Y109: =SUM(U109:X109) -> 2185.0169 | Z109: =-Z194+-Z208 -> 574.58996 | AA109: =-AA194+-AA208 -> 578.36971 | AB109: =-AB194+-AB208 -> 580.31308 | AC109: =-AC194+-AC208 -> 581.30234 | AD109: =SUM(Z109:AC109) -> 2314.5751 | AE109: =-AE194+-AE208 -> 2352.1884 | AF109: =-AF194+-AF208 -> 2344.2727 | AG109: =-AG194+-AG208 -> 2557.6408
C110: Change in Operating Working Capital | F110: =F178 -> 0 | G110: =G178 -> 907 | H110: =H178 -> -197 | I110: =I178 -> 1673 | J110: =SUM(F110:I110) -> 2383 | K110: =K178 -> 915 | L110: =L178 -> -127 | M110: =M178 -> 616 | N110: =N178 -> 368 | O110: =SUM(K110:N110) -> 1772 | P110: =P178 -> 565 | Q110: =Q178 -> -493 | R110: =R178 -> -831 | S110: =S178 -> -1036 | T110: =SUM(P110:S110) -> -1795 | U110: =U178 -> 61786 | V110: =V178 -> -65394.418 | W110: =W178 -> -528.19749 | X110: =X178 -> -1970.8946 | Y110: =SUM(U110:X110) -> -6107.5103 | Z110: =Z178 -> -141.16739 | AA110: =AA178 -> -2465.0576 | AB110: =AB178 -> -835.2195 | AC110: =AC178 -> -2110.3518 | AD110: =SUM(Z110:AC110) -> -5551.7963 | AE110: =AE178 -> -2101.7214 | AF110: =AF178 -> -4311.6757 | AG110: =AG178 -> -3696.3346
C111: Capital Expenditures | F111: =-F193 -> -360 | G111: =-G193 -> -376 | H111: =-H193 -> -401 | I111: =-I193 -> -426 | J111: =SUM(F111:I111) -> -1563 | K111: =-K193 -> -396 | L111: =-L193 -> -565 | M111: =-M193 -> -455 | N111: =-N193 -> -495 | O111: =SUM(K111:N111) -> -1911 | P111: =-P193 -> -430 | Q111: =-Q193 -> -619 | R111: =-R193 -> -654 | S111: =-S193 -> -722 | T111: =SUM(P111:S111) -> -2425 | U111: =-U193 -> -1149 | V111: =-V193 -> -630.14689 | W111: =-W193 -> -580.40941 | X111: =-X193 -> -578.11001 | Y111: =SUM(U111:X111) -> -2937.6663 | Z111: =-Z193 -> -622.68726 | AA111: =-AA193 -> -603.09907 | AB111: =-AB193 -> -592.90139 | AC111: =-AC193 -> -667.12946 | AD111: =SUM(Z111:AC111) -> -2485.8172 | AE111: =-AE193 -> -2327.0066 | AF111: =-AF193 -> -3023.0491 | AG111: =-AG193 -> -2879.404
C112: Free Cash Flow (FCF) | F112: =SUM(F108:F111) -> 1868.75 | G112: =SUM(G108:G111) -> 3117.75 | H112: =SUM(H108:H111) -> 2265.75 | I112: =SUM(I108:I111) -> 3592.75 | J112: =SUM(J108:J111) -> 10845 | K112: =SUM(K108:K111) -> 3375 | L112: =SUM(L108:L111) -> 2742 | M112: =SUM(M108:M111) -> 3087 | ... AG112: =SUM(AG108:AG111) -> 17045.629
C114: Free Cash Flow Margin | F114: =F112/F28 -> 0.11892262 | G114: =G112/G28 -> 0.1864237 | H114: =H112/H28 -> 0.13189068 | I114: =I112/I28 -> 0.20244267 | J114: =J112/J28 -> 0.16099103 | K114: =K112/K28 -> 0.18953221 | L114: =L112/L28 -> 0.14904604 | M114: =M112/M28 -> 0.16438575 | ... AG114: =AG112/AG28 -> 0.14343309
C115: Free Cash Flow per Share | F115: =F112/F282 -> 2.5151413 | G115: =G112/G282 -> 4.2131757 | H115: =H112/H282 -> 3.0952869 | I115: =I112/I282 -> 4.8880952 | J115: =J112/J282 -> 14.755102 | K115: =K112/K282 -> 4.6809986 | L115: =L112/L282 -> 3.8296089 | M115: =M112/M282 -> 4.3601695 | ... AG115: =AG112/AG282 -> 25.169025
C116: Free Cash Flow Yield | F116: =F115*4/F239 -> 0.057211062 | G116: =G115*4/G239 -> 0.10459072 | H116: =H115*4/H239 -> 0.076412686 | I116: =I115*4/I239 -> 0.12427624 | J116: =J115/J239 -> 0.089618502 | K116: =K115*4/K239 -> 0.087663254 | L116: =L115*4/L239 -> 0.064807022 | M116: =M115*4/M239 -> 0.07109938 | N116: =N115*4/N239 -> 0.047037785 | O116: =O115/O239 -> 0.068339832 | P116: =P115*4/P239 -> 0.060698553 | Q116: =Q115*4/Q239 -> 0.043562478 | R116: =R115*4/R239 -> 0.034126342 | S116: =S115*4/S239 -> 0.018324229 | T116: =T115/T239 -> 0.038432862 | U116: =U115*4/U239 -> 1.2029527 | V116: =V115*4/V239 -> -1.1738048 | W116: =W115*4/W239 -> 0.051108504 | X116: =X115*4/X239 -> 0.028150474 | Y116: =Y115/Y239 -> 0.027196873 | Z116: =Z115*4/Z239 -> 0.062830459 | AA116: =AA115*4/AA239 -> 0.024198998 | AB116: =AB115*4/AB239 -> 0.060343591 | AC116: =AC115*4/AC239 -> 0.038973622 | AD116: =AD115/AD239 -> 0.046589626 | AE116: =AE115/AE239 -> 0.074438402 | AF116: =AF115/AF239 -> 0.068909804 | AG116: =AG115/AG239 -> 0.080918934
A118: x | C118: Balance Sheet | F118: =F$25 -> 1Q23 | G118: =G$63 -> 2Q23 | H118: =H$63 -> 3Q23 | I118: =I$63 -> 4Q23 | J118: =J$63 -> 2023 | K118: =K$63 -> 1Q24 | L118: =L$63 -> 2Q24 | M118: =M$63 -> 3Q24 | N118: =N$63 -> 4Q24 | ... AG118: =AG$63 -> 2030e | AH118: x
C120: Cash & Cash Equivalents | F120: =40836 -> 40836 | G120: =3379+38869+710 -> 42958 | H120: =5082+38742+84 -> 43908 | I120: =7118+39312+166 -> 46596 | J120: =I120 -> 46596 | K120: =6264+47880+69 -> 54213 | L120: =6674+46033+188 -> 52895 | M120: =3205+44593+120 -> 47918 | N120: =3413+37006+221 -> 40640 | O120: =N120 -> 40640 | P120: =3024+49223+261 -> 52508 | Q120: =3120+54620+197 -> 57937 | R120: =3234+50201+1271 -> 54706 | S120: =3559+43491+742 -> 47792 | T120: =S120 -> 47792 | U120: 53757 | V120: =V104 -> 62511.832 | W120: =W104 -> 68333.224 | X120: =X104 -> 71873.755 | Y120: =X120 -> 71873.755 | Z120: =Z104 -> 75720.922 | AA120: =AA104 -> 86701.19 | AB120: =AB104 -> 90740.151 | AC120: =AC104 -> 93787.34 | AD120: =AC120 -> 93787.34 | AE120: =AE104 -> 109956.47 | AF120: =AF104 -> 133376.01 | AG120: =AG104 -> 156792.61
C121: Card Member Recievables | F121: 57271 | G121: 58011 | H121: 58651 | I121: 60237 | J121: =I121 -> 60237 | K121: 59624 | L121: 59485 | M121: 58886 | N121: 59240 | O121: =N121 -> 59240 | P121: 58355 | Q121: 59405 | R121: 60823 | S121: 61851 | T121: =S121 -> 61851 | U121: 0 | V121: =V162 -> 65187.609 | W121: =W162 -> 65999.733 | X121: =X162 -> 68367.792 | Y121: =X121 -> 68367.792 | Z121: =Z162 -> 68934.04 | AA121: =AA162 -> 71974.24 | AB121: =AB162 -> 72904.315 | AC121: =AC162 -> 75581.975 | AD121: =AC121 -> 75581.975 | AE121: =AE162 -> 77690.805 | AF121: =AF162 -> 83130.017 | AG121: =AG162 -> 87909.25
C122: Inventory | F122: 0 | G122: 0 | H122: 0 | I122: 0 | J122: =I122 -> 0 | K122: 0 | L122: 0 | M122: 0 | N122: 0 | O122: =N122 -> 0 | P122: 0 | Q122: 0 | R122: 0 | S122: 0 | T122: =S122 -> 0 | U122: 0 | V122: =V163 -> 0 | W122: =W163 -> 0 | X122: =X163 -> 0 | Y122: =X122 -> 0 | Z122: =Z163 -> 0 | AA122: =AA163 -> 0 | AB122: =AB163 -> 0 | AC122: =AC163 -> 0 | AD122: =AC122 -> 0 | AE122: =AE163 -> 0 | AF122: =AF163 -> 0 | AG122: =AG163 -> 0
C123: Prepaid & Other Current Assets | F123: 0 | G123: 0 | H123: 0 | I123: 0 | J123: =I123 -> 0 | K123: 0 | L123: 0 | M123: 0 | N123: 0 | O123: =N123 -> 0 | P123: 0 | Q123: 0 | R123: 0 | S123: 0 | T123: =S123 -> 0 | U123: 0 | V123: =V164 -> 0 | W123: =W164 -> 0 | X123: =X164 -> 0 | Y123: =X123 -> 0 | Z123: =Z164 -> 0 | AA123: =AA164 -> 0 | AB123: =AB164 -> 0 | AC123: =AC164 -> 0 | AD123: =AC123 -> 0 | AE123: =AE164 -> 0 | AF123: =AF164 -> 0 | AG123: =AG164 -> 0
C124: Total Current Assets | F124: =SUM(F120:F123) -> 98107 | G124: =SUM(G120:G123) -> 100969 | H124: =SUM(H120:H123) -> 102559 | I124: =SUM(I120:I123) -> 106833 | J124: =I124 -> 106833 | K124: =SUM(K120:K123) -> 113837 | L124: =SUM(L120:L123) -> 112380 | M124: =SUM(M120:M123) -> 106804 | N124: =SUM(N120:N123) -> 99880 | O124: =N124 -> 99880 | P124: =SUM(P120:P123) -> 110863 | Q124: =SUM(Q120:Q123) -> 117342 | R124: =SUM(R120:R123) -> 115529 | S124: =SUM(S120:S123) -> 109643 | T124: =S124 -> 109643 | U124: =SUM(U120:U123) -> 53757 | V124: =SUM(V120:V123) -> 130021.56 | W124: =SUM(W120:W123) -> 136376.52 | X124: =SUM(X120:X123) -> 142683.43 | Y124: =X124 -> 142683.43 | Z124: =SUM(Z120:Z123) -> 147091.75 | AA124: =SUM(AA120:AA123) -> 161262.52 | AB124: =SUM(AB120:AB123) -> 166278.61 | AC124: =SUM(AC120:AC123) -> 172103.87 | AD124: =AC124 -> 172103.87 | AE124: =SUM(AE120:AE123) -> 190432.66 | AF124: =SUM(AF120:AF123) -> 219470.06 | AG124: =SUM(AG120:AG123) -> 247832.14
C126: PP&E, Net | F126: 5204 | G126: 5177 | H126: 5124 | I126: 5138 | J126: =I126 -> 5138 | K126: 5138 | L126: 5247 | M126: 5308 | N126: 5371 | O126: =N126 -> 5371 | P126: 5383 | Q126: 5662 | R126: 5861 | S126: 6118 | T126: =S126 -> 6118 | U126: 7240 | V126: =V196 -> 7301.1875 | W126: =W196 -> 7307.8291 | X126: =X196 -> 7311.6494 | Y126: =X126 -> 7311.6494 | Z126: =Z196 -> 7359.7467 | AA126: =AA196 -> 7384.4761 | AB126: =AB196 -> 7397.0644 | AC126: =AC196 -> 7482.8915 | AD126: =AC126 -> 7482.8915 | AE126: =AE196 -> 7457.7097 | AF126: =AF196 -> 8136.4861 | AG126: =AG196 -> 8458.2493
C127: Card Member Loans | F127: 104997 | G127: 110212 | H127: 113257 | I127: 120877 | J127: =I127 -> 120877 | K127: 121348 | L127: 125530 | M127: 128960 | N127: =133995+758 -> 134753 | O127: =N127 -> 134753 | P127: =133611+776 -> 134387 | Q127: =136508+2405 -> 138913 | R127: =138946+2424 -> 141370 | S127: =145923+2457 -> 148380 | T127: =S127 -> 148380 | U127: =207247+2477 -> 209724 | V127: =V210 -> 209724 | W127: =W210 -> 209724 | X127: =X210 -> 209724 | Y127: =X127 -> 209724 | Z127: =Z210 -> 209724 | AA127: =AA210 -> 209724 | AB127: =AB210 -> 209724 | AC127: =AC210 -> 209724 | AD127: =AC127 -> 209724 | AE127: =AE210 -> 209724 | AF127: =AF210 -> 209724 | AG127: =AG210 -> 209724
...

Sheet Segment Analysis
C1: =Company_Name&" - "&MID(CELL("filename",A1),FIND("]",CELL("filename",A1))+1,255)&": "&Case_Scenario&" Case" -> American Express Company - Segment Analysis: Base Case
C2: =Cover!C2 -> $ in Millions Except Per Share Data
C5: Segment Analysis | F5: =Model!F63 -> 1Q23 | G5: =Model!G63 -> 2Q23 | H5: =Model!H63 -> 3Q23 | I5: =Model!I63 -> 4Q23 | J5: =Model!J63 -> 2023 | K5: =Model!K63 -> 1Q24 | L5: =Model!L63 -> 2Q24 | M5: =Model!M63 -> 3Q24 | ... AG5: =Model!AG63 -> 2030e
C6: Drivers
C7: Total Company Revenue | F7: =SUM(F8:F11) -> 15714 | G7: =SUM(G8:G11) -> 16724 | H7: =SUM(H8:H11) -> 17179 | I7: =SUM(I8:I11) -> 17747 | J7: =SUM(F7:I7) -> 67364 | K7: =SUM(K8:K11) -> 17807 | L7: =SUM(L8:L11) -> 18397 | M7: =SUM(M8:M11) -> 18779 | N7: =SUM(N8:N11) -> 19218 | O7: =SUM(K7:N7) -> 74201 | P7: =SUM(P8:P11) -> 18933 | Q7: =SUM(Q8:Q11) -> 19933 | R7: =SUM(R8:R11) -> 20557 | S7: =SUM(S8:S11) -> 21040 | T7: =SUM(P7:S7) -> 80463 | U7: =SUM(U8:U11) -> 20880 | V7: =SUM(V8:V11) -> 21729.203 | W7: =SUM(W8:W11) -> 22323.439 | X7: =SUM(X8:X11) -> 23124.4 | Y7: =SUM(U7:X7) -> 88057.042 | Z7: =SUM(Z8:Z11) -> 23062.491 | AA7: =SUM(AA8:AA11) -> 24123.963 | AB7: =SUM(AB8:AB11) -> 24704.225 | AC7: =SUM(AC8:AC11) -> 25658.825 | AD7: =SUM(Z7:AC7) -> 97549.504 | AE7: =SUM(AE8:AE11) -> 104638.91 | AF7: =SUM(AF8:AF11) -> 111964.78 | AG7: =SUM(AG8:AG11) -> 118840.28
C8: =C14&" Revenue" -> Discount Revenue | F8: 7947 | G8: 8481 | H8: 8408 | I8: =33416-SUM(F8:H8) -> 8580 | J8: =SUM(F8:I8) -> 33416 | K8: 8380 | L8: 8855 | M8: 8780 | N8: =35192-SUM(K8:M8) -> 9177 | O8: =SUM(K8:N8) -> 35192 | P8: 8743 | Q8: 9361 | R8: 9413 | S8: =37401-SUM(P8:R8) -> 9884 | T8: =SUM(P8:S8) -> 37401 | U8: 9512 | V8: ='Revenue Build'!V33 -> 10082.72 | W8: ='Revenue Build'!W33 -> 10233.961 | X8: ='Revenue Build'!X33 -> 10796.829 | Y8: =SUM(U8:X8) -> 40625.509 | Z8: ='Revenue Build'!Z33 -> 10688.86 | AA8: ='Revenue Build'!AA33 -> 11437.081 | AB8: ='Revenue Build'!AB33 -> 11665.822 | AC8: ='Revenue Build'!AC33 -> 12307.442 | AD8: =SUM(Z8:AC8) -> 46099.206 | AE8: ='Revenue Build'!AE33 -> 49326.15 | AF8: ='Revenue Build'!AF33 -> 52285.719 | AG8: ='Revenue Build'!AG33 -> 55422.862
C9: =C15&" Revenue" -> Net Card Fees Revenue | F9: 1713 | G9: 1789 | H9: 1846 | I9: =7255-SUM(F9:H9) -> 1907 | J9: =SUM(F9:I9) -> 7255 | K9: 1974 | L9: 2060 | M9: 2170 | N9: =8449-SUM(K9:M9) -> 2245 | O9: =SUM(K9:N9) -> 8449 | P9: 2333 | Q9: 2480 | R9: 2551 | S9: =9993-SUM(P9:R9) -> 2629 | T9: =SUM(P9:S9) -> 9993 | U9: 2752 | V9: ='Revenue Build'!V41 -> 2889.6 | W9: ='Revenue Build'!W41 -> 3034.08 | X9: ='Revenue Build'!X41 -> 3216.1248 | Y9: =SUM(U9:X9) -> 11891.805 | Z9: ='Revenue Build'!Z41 -> 3312.6085 | AA9: ='Revenue Build'!AA41 -> 3445.1129 | AB9: ='Revenue Build'!AB41 -> 3514.0151 | AC9: ='Revenue Build'!AC41 -> 3619.4356 | AD9: =SUM(Z9:AC9) -> 13891.172 | AE9: ='Revenue Build'!AE41 -> 15835.936 | AF9: ='Revenue Build'!AF41 -> 17736.249 | AG9: ='Revenue Build'!AG41 -> 18800.424
C10: =C16&" Revenue" -> Service Fees and Other Revenue | F10: =1218+420 -> 1638 | G10: =1232+447 -> 1679 | H10: =1261+424 -> 1685 | I10: =5005+1705-SUM(F10:H10) -> 1708 | J10: =SUM(F10:I10) -> 6710 | K10: =1292+386 -> 1678 | L10: =1280+408 -> 1688 | M10: =1267+413 -> 1680 | N10: =5129+1636-SUM(K10:M10) -> 1719 | O10: =SUM(K10:N10) -> 6765 | P10: 1722 | Q10: 1828 | R10: 1976 | S10: =7471-SUM(P10:R10) -> 1945 | T10: =SUM(P10:S10) -> 7471 | U10: 1951 | V10: ='Revenue Build'!V45 -> 2054.403 | W10: ='Revenue Build'!W45 -> 2157.1231 | X10: ='Revenue Build'!X45 -> 2174.3801 | Y10: =SUM(U10:X10) -> 8336.9063 | Z10: ='Revenue Build'!Z45 -> 2130.8925 | AA10: ='Revenue Build'!AA45 -> 2242.3382 | AB10: ='Revenue Build'!AB45 -> 2349.9704 | AC10: ='Revenue Build'!AC45 -> 2378.1701 | AD10: =SUM(Z10:AC10) -> 9101.3713 | AE10: ='Revenue Build'!AE45 -> 9738.4673 | AF10: ='Revenue Build'!AF45 -> 10420.16 | AG10: ='Revenue Build'!AG45 -> 11045.37
C11: =C17 -> Interest Income | F11: 4416 | G11: 4775 | H11: 5240 | I11: =19983-SUM(F11:H11) -> 5552 | J11: =SUM(F11:I11) -> 19983 | K11: 5775 | L11: 5794 | M11: 6149 | N11: =23795-SUM(K11:M11) -> 6077 | O11: =SUM(K11:N11) -> 23795 | P11: 6135 | Q11: 6264 | R11: 6617 | S11: =25598-SUM(P11:R11) -> 6582 | T11: =SUM(P11:S11) -> 25598 | U11: 6665 | V11: ='Revenue Build'!V57 -> 6702.48 | W11: ='Revenue Build'!W57 -> 6898.275 | X11: ='Revenue Build'!X57 -> 6937.0668 | Y11: =SUM(U11:X11) -> 27202.822 | Z11: ='Revenue Build'!Z57 -> 6930.1297 | AA11: ='Revenue Build'!AA57 -> 6999.431 | AB11: ='Revenue Build'!AB57 -> 7174.4168 | AC11: ='Revenue Build'!AC57 -> 7353.7772 | AD11: =SUM(Z11:AC11) -> 28457.755 | AE11: ='Revenue Build'!AE37 -> 29738.354 | AF11: ='Revenue Build'!AF37 -> 31522.655 | AG11: ='Revenue Build'!AG37 -> 33571.628
C13: Revenue Mix
C14: Discount | F14: =IFERROR(F8/F$7,"N/A") -> 0.50572738 | G14: =IFERROR(G8/G$7,"N/A") -> 0.50711552 | H14: =IFERROR(H8/H$7,"N/A") -> 0.48943478 | I14: =IFERROR(I8/I$7,"N/A") -> 0.48346199 | J14: =IFERROR(J8/J$7,"N/A") -> 0.4960513 | K14: =IFERROR(K8/K$7,"N/A") -> 0.47060145 | L14: =IFERROR(L8/L$7,"N/A") -> 0.48132848 | M14: =IFERROR(M8/M$7,"N/A") -> 0.46754353 | ... AG14: =IFERROR(AG8/AG$7,"N/A") -> 0.46636427
C15: Net Card Fees | F15: =IFERROR(F9/F$7,"N/A") -> 0.10901107 | G15: =IFERROR(G9/G$7,"N/A") -> 0.10697202 | H15: =IFERROR(H9/H$7,"N/A") -> 0.10745678 | I15: =IFERROR(I9/I$7,"N/A") -> 0.10745478 | J15: =IFERROR(J9/J$7,"N/A") -> 0.10769847 | K15: =IFERROR(K9/K$7,"N/A") -> 0.11085528 | L15: =IFERROR(L9/L$7,"N/A") -> 0.11197478 | M15: =IFERROR(M9/M$7,"N/A") -> 0.11555461 | ... AG15: =IFERROR(AG9/AG$7,"N/A") -> 0.15819908
C16: Service Fees and Other | F16: =IFERROR(F10/F$7,"N/A") -> 0.10423826 | G16: =IFERROR(G10/G$7,"N/A") -> 0.10039464 | H16: =IFERROR(H10/H$7,"N/A") -> 0.098084871 | I16: =IFERROR(I10/I$7,"N/A") -> 0.096241618 | J16: =IFERROR(J10/J$7,"N/A") -> 0.099608099 | K16: =IFERROR(K10/K$7,"N/A") -> 0.094232605 | L16: =IFERROR(L10/L$7,"N/A") -> 0.09175409 | M16: =IFERROR(M10/M$7,"N/A") -> 0.089461633 | ... AG16: =IFERROR(AG10/AG$7,"N/A") -> 0.092942976
C17: Interest Income | F17: =IFERROR(F11/F$7,"N/A") -> 0.28102329 | G17: =IFERROR(G11/G$7,"N/A") -> 0.28551782 | H17: =IFERROR(H11/H$7,"N/A") -> 0.30502358 | I17: =IFERROR(I11/I$7,"N/A") -> 0.31284161 | J17: =IFERROR(J11/J$7,"N/A") -> 0.29664212 | K17: =IFERROR(K11/K$7,"N/A") -> 0.32431066 | L17: =IFERROR(L11/L$7,"N/A") -> 0.31494265 | M17: =IFERROR(M11/M$7,"N/A") -> 0.32744023 | ... AG17: =IFERROR(AG11/AG$7,"N/A") -> 0.28249367
C19: "" | F19: =SUM(F20:F24) -> 14281 | G19: =SUM(G20:G24) -> 15054 | H19: =SUM(H20:H24) -> 15381 | I19: =SUM(I20:I24) -> 15842 | J19: =SUM(J20:J24) -> 60558 | K19: =SUM(K20:K24) -> 15801 | L19: =SUM(L20:L24) -> 16303 | M19: =SUM(M20:M24) -> 16636 | ... U19: =SUM(U20:U24) -> 18912 | V19: =V7 -> 21729.203 | W19: =W7 -> 22323.439 | X19: =X7 -> 23124.4 | Y19: =Y7 -> 88057.042 | Z19: =Z7 -> 23062.491 | AA19: =AA7 -> 24123.963 | AB19: =AB7 -> 24704.225 | AC19: =AC7 -> 25658.825 | ... AG19: =AG7 -> 118840.28
C20: =C27&" Revenue" -> U.S. Consumer Services Revenue | F20: 6583 | G20: 6930 | H20: 7208 | I20: =28116-SUM(F20:H20) -> 7395 | J20: =SUM(F20:I20) -> 28116 | K20: 7499 | L20: 7732 | M20: 7944 | N20: =31427-SUM(K20:M20) -> 8252 | O20: =SUM(K20:N20) -> 31427 | P20: 8249 | Q20: 8553 | R20: 8856 | S20: =34814-SUM(P20:R20) -> 9156 | T20: =SUM(P20:S20) -> 34814 | U20: 9123 | V20: 0 | W20: 0 | X20: 0 | Y20: =SUM(U20:X20) -> 9123 | Z20: 0 | AA20: 0 | AB20: 0 | AC20: 0 | AD20: =SUM(Z20:AC20) -> 0 | AE20: 0 | AF20: 0 | AG20: 0
C21: =C28&" Revenue" -> Commercial Services Revenue | F21: 3492 | G21: 3729 | H21: 3747 | I21: =14776-SUM(F21:H21) -> 3808 | J21: =SUM(F21:I21) -> 14776 | K21: 3785 | L21: 3954 | M21: 3998 | N21: =15859-SUM(K21:M21) -> 4122 | O21: =SUM(K21:N21) -> 15859 | P21: 4035 | Q21: 4212 | R21: 4281 | S21: =16926-SUM(P21:R21) -> 4398 | T21: =SUM(P21:S21) -> 16926 | U21: 4321 | V21: 0 | W21: 0 | X21: 0 | Y21: =SUM(U21:X21) -> 4321 | Z21: 0 | AA21: 0 | AB21: 0 | AC21: 0 | AD21: =SUM(Z21:AC21) -> 0 | AE21: 0 | AF21: 0 | AG21: 0
C22: =C29&" Revenue" -> International Card Services Revenue | F22: 2510 | G22: 2585 | H22: 2643 | I22: =10473-SUM(F22:H22) -> 2735 | J22: =SUM(F22:I22) -> 10473 | K22: 2713 | L22: 2822 | M22: 2936 | N22: =11461-SUM(K22:M22) -> 2990 | O22: =SUM(K22:N22) -> 11461 | P22: 2936 | Q22: 3232 | R22: 3336 | S22: =13000-SUM(P22:R22) -> 3496 | T22: =SUM(P22:S22) -> 13000 | U22: 3532 | V22: 0 | W22: 0 | X22: 0 | Y22: =SUM(U22:X22) -> 3532 | Z22: 0 | AA22: 0 | AB22: 0 | AC22: 0 | AD22: =SUM(Z22:AC22) -> 0 | AE22: 0 | AF22: 0 | AG22: 0
C23: =C30&" Revenue" -> Global Merchant & Network Services Revenue | F23: 1741 | G23: 1863 | H23: 1851 | I23: =7396-SUM(F23:H23) -> 1941 | J23: =SUM(F23:I23) -> 7396 | K23: 1870 | L23: 1873 | M23: 1847 | N23: =7484-SUM(K23:M23) -> 1894 | O23: =SUM(K23:N23) -> 7484 | P23: 1815 | Q23: 1933 | R23: 1972 | S23: =7759-SUM(P23:R23) -> 2039 | T23: =SUM(P23:S23) -> 7759 | U23: 2004 | V23: 0 | W23: 0 | X23: 0 | Y23: =SUM(U23:X23) -> 2004 | Z23: 0 | AA23: 0 | AB23: 0 | AC23: 0 | AD23: =SUM(Z23:AC23) -> 0 | AE23: 0 | AF23: 0 | AG23: 0
C24: =C31&" Revenue" -> Corporate & Other Revenue | F24: -45 | G24: -53 | H24: -68 | I24: =-203-(SUM(F24:H24)) -> -37 | J24: =SUM(F24:I24) -> -203 | K24: -66 | L24: -78 | M24: -89 | N24: =-282-SUM(K24:M24) -> -49 | O24: =SUM(K24:N24) -> -282 | P24: -68 | Q24: -74 | R24: -19 | S24: =-270-SUM(P24:R24) -> -109 | T24: =SUM(P24:S24) -> -270 | U24: -68 | V24: 0 | W24: 0 | X24: 0 | Y24: =SUM(U24:X24) -> -68 | Z24: 0 | AA24: 0 | AB24: 0 | AC24: 0 | AD24: =SUM(Z24:AC24) -> 0 | AE24: 0 | AF24: 0 | AG24: 0
C26: ""
C27: U.S. Consumer Services | F27: =IFERROR(F20/F$19,"N/A") -> 0.46096212 | G27: =IFERROR(G20/G$19,"N/A") -> 0.46034277 | H27: =IFERROR(H20/H$19,"N/A") -> 0.46863013 | I27: =IFERROR(I20/I$19,"N/A") -> 0.46679712 | J27: =IFERROR(J20/J$19,"N/A") -> 0.46428218 | K27: =IFERROR(K20/K$19,"N/A") -> 0.47459022 | L27: =IFERROR(L20/L$19,"N/A") -> 0.47426854 | M27: =IFERROR(M20/M$19,"N/A") -> 0.47751863 | ... U27: =IFERROR(U20/U$19,"N/A") -> 0.48239213 | V27: =IFERROR(V20/V$7,"N/A") -> 0 | W27: =IFERROR(W20/W$7,"N/A") -> 0 | X27: =IFERROR(X20/X$7,"N/A") -> 0 | Y27: =IFERROR(Y20/Y$19,"N/A") -> 0.1036033 | Z27: =IFERROR(Z20/Z$19,"N/A") -> 0 | AA27: =IFERROR(AA20/AA$19,"N/A") -> 0 | AB27: =IFERROR(AB20/AB$19,"N/A") -> 0 | AC27: =IFERROR(AC20/AC$19,"N/A") -> 0 | AD27: =IFERROR(AD20/AD$19,"N/A") -> 0 | AE27: =IFERROR(AE20/AE$19,"N/A") -> 0 | AF27: =IFERROR(AF20/AF$19,"N/A") -> 0 | AG27: =IFERROR(AG20/AG$19,"N/A") -> 0
C28: Commercial Services | F28: =IFERROR(F21/F$19,"N/A") -> 0.24452069 | G28: =IFERROR(G21/G$19,"N/A") -> 0.24770825 | H28: =IFERROR(H21/H$19,"N/A") -> 0.24361225 | I28: =IFERROR(I21/I$19,"N/A") -> 0.24037369 | J28: =IFERROR(J21/J$19,"N/A") -> 0.24399749 | K28: =IFERROR(K21/K$19,"N/A") -> 0.2395418 | L28: =IFERROR(L21/L$19,"N/A") -> 0.24253205 | M28: =IFERROR(M21/M$19,"N/A") -> 0.24032219 | ... U28: =IFERROR(U21/U$19,"N/A") -> 0.22847927 | V28: =IFERROR(V21/V$7,"N/A") -> 0 | W28: =IFERROR(W21/W$7,"N/A") -> 0 | X28: =IFERROR(X21/X$7,"N/A") -> 0 | Y28: =IFERROR(Y21/Y$19,"N/A") -> 0.049070465 | Z28: =IFERROR(Z21/Z$19,"N/A") -> 0 | AA28: =IFERROR(AA21/AA$19,"N/A") -> 0 | AB28: =IFERROR(AB21/AB$19,"N/A") -> 0 | AC28: =IFERROR(AC21/AC$19,"N/A") -> 0 | AD28: =IFERROR(AD21/AD$19,"N/A") -> 0 | AE28: =IFERROR(AE21/AE$19,"N/A") -> 0 | AF28: =IFERROR(AF21/AF$19,"N/A") -> 0 | AG28: =IFERROR(AG21/AG$19,"N/A") -> 0
C29: International Card Services | F29: =IFERROR(F24/F$19,"N/A") -> -0.0031510398 | G29: =IFERROR(G24/G$19,"N/A") -> -0.003520659 | H29: =IFERROR(H24/H$19,"N/A") -> -0.0044210389 | I29: =IFERROR(I24/I$19,"N/A") -> -0.0023355637 | J29: =IFERROR(J24/J$19,"N/A") -> -0.0033521583 | K29: =IFERROR(K24/K$19,"N/A") -> -0.0041769508 | L29: =IFERROR(L24/L$19,"N/A") -> -0.0047843955 | M29: =IFERROR(M24/M$19,"N/A") -> -0.0053498437 | ... U29: =IFERROR(U24/U$19,"N/A") -> -0.0035956007 | V29: =IFERROR(V24/V$7,"N/A") -> 0 | W29: =IFERROR(W24/W$7,"N/A") -> 0 | X29: =IFERROR(X24/X$7,"N/A") -> 0 | Y29: =IFERROR(Y24/Y$19,"N/A") -> -0.00077222671 | Z29: =IFERROR(Z24/Z$19,"N/A") -> 0 | AA29: =IFERROR(AA24/AA$19,"N/A") -> 0 | AB29: =IFERROR(AB24/AB$19,"N/A") -> 0 | AC29: =IFERROR(AC24/AC$19,"N/A") -> 0 | AD29: =IFERROR(AD24/AD$19,"N/A") -> 0 | AE29: =IFERROR(AE24/AE$19,"N/A") -> 0 | AF29: =IFERROR(AF24/AF$19,"N/A") -> 0 | AG29: =IFERROR(AG24/AG$19,"N/A") -> 0
C30: Global Merchant & Network Services | F30: =IFERROR(F23/F$19,"N/A") -> 0.12191023 | G30: =IFERROR(G23/G$19,"N/A") -> 0.12375448 | H30: =IFERROR(H23/H$19,"N/A") -> 0.12034328 | I30: =IFERROR(I23/I$19,"N/A") -> 0.12252241 | J30: =IFERROR(J23/J$19,"N/A") -> 0.12213085 | K30: =IFERROR(K23/K$19,"N/A") -> 0.11834694 | L30: =IFERROR(L23/L$19,"N/A") -> 0.11488683 | M30: =IFERROR(M23/M$19,"N/A") -> 0.11102428 | ... AG30: =IFERROR(AG23/AG$19,"N/A") -> 0
C31: Corporate & Other | F31: =IFERROR(F24/F$19,"N/A") -> -0.0031510398 | G31: =IFERROR(G24/G$19,"N/A") -> -0.003520659 | H31: =IFERROR(H24/H$19,"N/A") -> -0.0044210389 | I31: =IFERROR(I24/I$19,"N/A") -> -0.0023355637 | J31: =IFERROR(J24/J$19,"N/A") -> -0.0033521583 | K31: =IFERROR(K24/K$19,"N/A") -> -0.0041769508 | L31: =IFERROR(L24/L$19,"N/A") -> -0.0047843955 | M31: =IFERROR(M24/M$19,"N/A") -> -0.0053498437 | ... AG31: =IFERROR(AG24/AG$19,"N/A") -> 0
C33: Total Company Operating Income | F33: =SUM(F34:F36) -> 1949 | G33: =SUM(G34:G36) -> 2216 | H33: =SUM(H34:H36) -> 2823 | I33: =SUM(I34:I36) -> 2279 | J33: =SUM(F33:I33) -> 9267 | K33: =SUM(K34:K36) -> 2743 | L33: =SUM(L34:L36) -> 2755 | M33: =SUM(M34:M36) -> 3022 | N33: =SUM(N34:N36) -> 2393 | O33: =SUM(K33:N33) -> 10913 | P33: =SUM(P34:P36) -> 2949 | Q33: =SUM(Q34:Q36) -> 3046 | R33: =SUM(R34:R36) -> 3383 | S33: =SUM(S34:S36) -> 2703 | T33: =SUM(P33:S33) -> 12081 | U33: =SUM(U34:U36) -> 3778 | V33: =SUM(V34:V36) -> 7007.4904 | W33: =SUM(W34:W36) -> 7368.4518 | X33: =SUM(X34:X36) -> 7773.7166 | Y33: =SUM(U33:X33) -> 25927.659 | Z33: =SUM(Z34:Z36) -> 8016.6453 | AA33: =SUM(AA34:AA36) -> 8612.1217 | AB33: =SUM(AB34:AB36) -> 8807.6958 | AC33: =SUM(AC34:AC36) -> 9415.1934 | AD33: =SUM(Z33:AC33) -> 34851.656 | AE33: =SUM(AE34:AE36) -> 38474.397 | AF33: =SUM(AF34:AF36) -> 41305.718 | AG33: =SUM(AG34:AG36) -> 44338.29
