Workbook
Name al: '[3]2010 Labor Rates 091130'!$A$161
Name al09salary: [3]Salaries!$G$13
Name al10salary: [3]Salaries!$K$13
Name alid: '[3]2010 Labor Rates 091130'!$E$168
Name alname: [3]Salaries!$A$13
Name aprpto: [3]Vacation!$I$56
Name augpto: [3]Vacation!$M$56
Name avg_Health_and_Welfare: [4]PBCFringe!$Q$22
Name bf: '[3]2010 Labor Rates 091130'!$A$239
Name bf09salary: [3]Salaries!$G$18
Name bf10salary: [3]Salaries!$K$18
Name bfid: '[3]2010 Labor Rates 091130'!$E$246
Name bfname: [3]Salaries!$A$18
Name Bonus_estimate_2011: [4]PBCFringe!$B$100
Name Case_Scenario: [5]Cover!$F$22
Name Case_Scenario: Cover!$F$22
Name cc: '[3]2010 Labor Rates 091130'!$A$135
Name cc09salary: [3]Salaries!$G$11
Name cc10salary: [3]Salaries!$K$11
Name ccid: '[3]2010 Labor Rates 091130'!$E$142
Name ccname: [3]Salaries!$A$11
Name Ccy: [6]data!$A$5
Name cf: '[3]2010 Labor Rates 091130'!$A$148
Name cf09salary: [3]Salaries!$G$12
Name cf10salary: [3]Salaries!$K$12
Name cfid: '[3]2010 Labor Rates 091130'!$E$155
Name cfname: [3]Salaries!$A$12
Name ck: '[3]2010 Labor Rates 091130'!$A$213
Name ck09salary: [3]Salaries!$G$17
Name ck10salary: [3]Salaries!$K$17
Name ckid: '[3]2010 Labor Rates 091130'!$E$220
Name ckname: [3]Salaries!$A$17
Name Company_Cyclical_Multiples_Data: '[5]Multiples Data'!$C$14:$H$26
Name Company_Cyclical_Multiples_Data: 'Multiples Data'!$C$14:$H$26
Name Company_Name: [5]Cover!$F$19
Name Company_Name: Cover!$F$19
Name Company_Rev_Methodology: '[5]Revenue Build'!$C$7
Name Company_Rev_Methodology: 'Revenue Build'!$C$7
Name Cost_of_Debt: [5]WACC!$G$17
Name Cost_of_Debt: WACC!$G$17
Name Cost_of_Equity: [5]WACC!$G$25
Name Cost_of_Equity: WACC!$G$25
Name Cost_of_Preferred: [5]WACC!$G$10
Name Cost_of_Preferred: WACC!$G$10
Name cs: '[3]2010 Labor Rates 091130'!$A$252
Name cs09salary: [3]Salaries!$G$19
Name cs10salary: [3]Salaries!$K$19
Name csid: '[3]2010 Labor Rates 091130'!$E$259
Name csname: [3]Salaries!$A$19
Name Current_Date: [5]Cover!$F$27
Name Current_Date: Cover!$F$27
Name Current_Salary: '[8]Planning Worksheet'!$C:$C
Name CV: '[3]2010 Labor Rates 091130'!$A$5
Name cv09salary: [3]Salaries!$G$2
Name cv10salary: [3]Salaries!$K$2
Name cvid: '[3]2010 Labor Rates 091130'!$E$12
Name cvname: [3]Salaries!$A$2
Name Cycle_Period_Toggle: [5]Valuation!$G$221
Name Cycle_Period_Toggle: Valuation!$G$221
Name Cycle_Toggle: [5]Valuation!$G$220

Sheet Cover
C1: =Company_Name&" - "&MID(CELL("filename",A1),FIND("]",CELL("filename",A1))+1,255)&": "&Case_Scenario&" Case" -> Evercore Inc. - Cover: Base Case | Q1: Font Toggle
C2: $ in Thousands Except Per Share Data | Q2: Report
R3: x
A4: x | C4: Model Assumptions: | I4: Return Summary:
I6: Discounted Cash Flow Analysis | N6: Multiple Analysis
I8: Exit Multiple Method | N8: EV/EBITDA Method
I9: Implied Enterprise Value: | L9: =Valuation!K65 -> 19330394 | P9: Target Price: | Q9: % Return:
I10: Implied Equity Value: | L10: =Valuation!K72 -> 19286441
N11: 1 Year LTM EV/EBITDA | P11: =Valuation!N137 -> 430.49687 | Q11: =Valuation!N138 -> 0.26175113
I12: Implied Share Price: | L12: =Valuation!K76 -> 457.77315
I13: % Return: | L13: =Valuation!K77 -> 0.34169568 | N13: 2009-2018 Late Cycle EV/EBITDA | P13: =Valuation!N215 -> 258.07623 | Q13: =Valuation!N216 -> -0.24359966
I15: Perpetuity Growth Method | N15: P/E Multiple Method
I16: Implied Enterprise Value: | L16: =Valuation!R65 -> 23818873 | P16: Target Price: | Q16: % Return:
I17: Implied Equity Value: | L17: =Valuation!R72 -> 23774919
N18: 1 Year LTM P/E | P18: =Valuation!F126 -> 471.35312 | Q18: =Valuation!F127 -> 0.38149747
C19: Company Name | F19: Evercore Inc. | I19: Implied Share Price: | L19: =Valuation!R76 -> 564.30939
C20: Ticker | F20: EVR | I20: % Return: | L20: =Valuation!R77 -> 0.6539447 | N20: 2009-2018 Late Cycle P/E | P20: =Valuation!F204 -> 569.13382 | Q20: =Valuation!F205 -> 0.6680847
C22: Case Scenario | F22: Base | I22: Table of Contents
C24: Last Fiscal Year | F24: 46053 | I24: Cover
C25: Next Fiscal Year | F25: =Last_FYE+365 -> 46418 | I25: Summary
C26: Last Fiscal Quarter Reported | F26: 4Q | I26: Football Field
C27: Current Valuation Date | F27: 46150 | I27: Integrity
I28: Revenue Build
C29: Current Share Price | F29: 341.19 | I29: Model
C30: 52-Week High | F30: 388.71 | I30: Segment Analysis
C31: 52-Week Low | F31: 215.26 | I31: Drivers
I32: WACC
C33: Effective Tax Rate | F33: =IF(Last_FQR="1Q",Model!P73,IF(Last_FQR="2Q",Model!Q73,IF(Last_FQR="3Q",Model!R73,Model!S73))) -> 0.28977619 | I33: Valuation
C34: Dividend Yield | F34: =IF(Last_FQR="1Q",Model!U267,IF(Last_FQR="2Q",Model!V267,IF(Last_FQR="3Q",Model!W267,Model!X267))) -> 0.014176771 | I34: Comparables
C35: Diluted Shares Outstanding (MRQ) | F35: =IF(Last_FQR="1Q",Model!P286,IF(Last_FQR="2Q",Model!Q286,IF(Last_FQR="3Q",Model!R286,Model!S286))) -> 42131 | I35: Charts
I36: Benchmark
C37: Model Type | F37: Top Down | I37: Multiples Data
I38: Pre-Earnings
I39: Post-Earnings
A42: x
C43: Model Color Legend | I43: Constants
C44: Blue = Hard-Coded Value (historical values & assumptions) | I44: Reference | J44: Type | K44: Name | L44: Value
C45: Black = Formulas | I45: Million | J45: (#) | K45: Mil | L45: 1000000
C46: Green = Linked Value (from separate worksheet) | I46: Thousand | J46: (#) | K46: Thou | L46: 1000
C47: Red = Unique Formula / Anomaly | I47: Hundred | J47: (#) | K47: Hun | L47: 100
A48: x
C49: Tab Color Codes
C51: Summary
C53: Model
A54: x
C55: Supporting/Auxiliary
C57: Valuation
C59: Comps
C61: RBG Codes for Model
C63: 0-0-255 | F63: Hard-Coded Numbers
C65: 0-128-0 | F65: Linked Numbers
C67: 255-223-159 | F67: Owl Fund Gold
C69: 255-255-153 | F69: Drivers / Assumptions
C71: 118-0-0 | F71: Owl Fund Red
C73: 0-56-96 | F73: Section Headers
C75: 192-222-246 | F75: Sub-Section Headers
C77: 215-215-215 | F77: Historical Quarters
C79: 235-235-235 | F79: Projected Quarters
C81: 255-255-255 | F81: Annuals
A83: x | B83: x | C83: END

Sheet Summary
C1: =Company_Name&" - "&MID(CELL("filename",A1),FIND("]",CELL("filename",A1))+1,255)&": "&Case_Scenario&" Case" -> Evercore Inc. - Summary: Base Case
C2: =Cover!C2 -> $ in Thousands Except Per Share Data
C4: Year: | T4: =Model!J24 -> 2023 | U4: =Model!O24 -> 2024 | V4: =Model!T24 -> 2025 | W4: =Model!Y24 -> 2026 | X4: =Model!AD24 -> 2027 | Y4: =Model!AE24 -> 2028 | Z4: =Model!AF24 -> 2029 | AA4: =Model!AG24 -> 2030
G5: Quarterly | T5: Annuals | AC5: CAGR | AE5: CAGR
A6: x | C6: ="Consolidated "&Model!C25 -> Consolidated Income Statement | G6: =Model!P25 -> 1Q25 | H6: =Model!Q25 -> 2Q25 | I6: =Model!R25 -> 3Q25 | J6: =Model!S25 -> 4Q25 | K6: =Model!U25 -> 1Q26 | L6: =Model!V25 -> 2Q26e | M6: =Model!W25 -> 3Q26e | N6: =Model!X25 -> 4Q26e | O6: =Model!Z25 -> 1Q27e | P6: =Model!AA25 -> 2Q27e | Q6: =Model!AB25 -> 3Q27e | R6: =Model!AC25 -> 4Q27e | T6: =Model!J25 -> 2023 | U6: =Model!O25 -> 2024 | V6: =Model!T25 -> 2025 | W6: =Model!Y25 -> 2026e | X6: =Model!AD25 -> 2027e | Y6: =Model!AE25 -> 2028e | Z6: =Model!AF25 -> 2029e | AA6: =Model!AG25 -> 2030e | AC6: Historical | AE6: Projected
C8: =Model!C28 -> Revenue | G8: =Model!P28 -> 699022 | H8: =Model!Q28 -> 838040 | I8: =Model!R28 -> 1045994 | J8: =Model!S28 -> 1297028 | K8: =Model!U28 -> 1400469 | L8: =Model!V28 -> 1541864.2 | M8: =Model!W28 -> 1718730.9 | N8: =Model!X28 -> 2113727.6 | O8: =Model!Z28 -> 1569916.9 | P8: =Model!AA28 -> 1730869.9 | Q8: =Model!AB28 -> 1922407 | R8: =Model!AC28 -> 2440159.7 | T8: =Model!J28 -> 2442666 | U8: =Model!O28 -> 2996361 | V8: =Model!T28 -> 3880084 | W8: =Model!Y28 -> 6774791.7 | X8: =Model!AD28 -> 7663353.4 | Y8: =Model!AE28 -> 7894057.8 | Z8: =Model!AF28 -> 7727144.5 | AA8: =Model!AG28 -> 7330353.4 | AC8: =IFERROR((V8/T8)^(1/(V$4-T$4))-1,"N/A") -> 0.26034232 | AE8: =IFERROR((AA8/V8)^(1/(AA$4-V$4))-1,"N/A") -> 0.13568204
C9: YoY % Growth | K9: =K8/G8-1 -> 1.0034691 | L9: =L8/H8-1 -> 0.83984555 | M9: =M8/I8-1 -> 0.64315564 | N9: =N8/J8-1 -> 0.62966996 | O9: =O8/K8-1 -> 0.12099366 | P9: =P8/L8-1 -> 0.12258258 | Q9: =Q8/M8-1 -> 0.11850374 | R9: =R8/N8-1 -> 0.15443433 | U9: =IF(ISERROR(U8/T8-1),"NA",(U8/T8-1)) -> 0.22667651 | V9: =IF(ISERROR(V8/U8-1),"NA",(V8/U8-1)) -> 0.29493209 | W9: =IF(ISERROR(W8/V8-1),"NA",(W8/V8-1)) -> 0.74604253 | X9: =IF(ISERROR(X8/W8-1),"NA",(X8/W8-1)) -> 0.13115705 | Y9: =IF(ISERROR(Y8/X8-1),"NA",(Y8/X8-1)) -> 0.030104886 | Z9: =IF(ISERROR(Z8/Y8-1),"NA",(Z8/Y8-1)) -> -0.02114417 | AA9: =IF(ISERROR(AA8/Z8-1),"NA",(AA8/Z8-1)) -> -0.05135028
C11: =Model!C30 -> Gross Profit | G11: =Model!P30 -> 699022 | H11: =Model!Q30 -> 838040 | I11: =Model!R30 -> 1045994 | J11: =Model!S30 -> 1297028 | K11: =Model!U30 -> 1400469 | L11: =Model!V30 -> 1541864.2 | M11: =Model!W30 -> 1718730.9 | N11: =Model!X30 -> 2113727.6 | O11: =Model!Z30 -> 1569916.9 | P11: =Model!AA30 -> 1730869.9 | Q11: =Model!AB30 -> 1922407 | R11: =Model!AC30 -> 2440159.7 | T11: =Model!J30 -> 2442666 | U11: =Model!O30 -> 2996361 | V11: =Model!T30 -> 3880084 | W11: =Model!Y30 -> 6774791.7 | X11: =Model!AD30 -> 7663353.4 | Y11: =Model!AE30 -> 7894057.8 | Z11: =Model!AF30 -> 7727144.5 | AA11: =Model!AG30 -> 7330353.4 | AC11: =IFERROR((V11/T11)^(1/(V$4-T$4))-1,"N/A") -> 0.26034232 | AE11: =IFERROR((AA11/V11)^(1/(AA$4-V$4))-1,"N/A") -> 0.13568204
C12: % Margin | G12: =G11/G$8 -> 1 | H12: =H11/H$8 -> 1 | I12: =I11/I$8 -> 1 | J12: =J11/J$8 -> 1 | K12: =K11/K$8 -> 1 | L12: =L11/L$8 -> 1 | M12: =M11/M$8 -> 1 | N12: =N11/N$8 -> 1 | ... R12: =R11/R$8 -> 1 | T12: =T11/T$8 -> 1 | U12: =U11/U$8 -> 1 | V12: =V11/V$8 -> 1 | W12: =W11/W$8 -> 1 | X12: =X11/X$8 -> 1 | Y12: =Y11/Y$8 -> 1 | Z12: =Z11/Z$8 -> 1 | AA12: =AA11/AA$8 -> 1
C13: YoY % Growth | K13: =K11/G11-1 -> 1.0034691 | L13: =L11/H11-1 -> 0.83984555 | M13: =M11/I11-1 -> 0.64315564 | N13: =N11/J11-1 -> 0.62966996 | O13: =O11/K11-1 -> 0.12099366 | P13: =P11/L11-1 -> 0.12258258 | Q13: =Q11/M11-1 -> 0.11850374 | R13: =R11/N11-1 -> 0.15443433 | U13: =U11/T11-1 -> 0.22667651 | V13: =V11/U11-1 -> 0.29493209 | W13: =W11/V11-1 -> 0.74604253 | X13: =X11/W11-1 -> 0.13115705 | Y13: =Y11/X11-1 -> 0.030104886 | Z13: =Z11/Y11-1 -> -0.02114417 | AA13: =AA11/Z11-1 -> -0.05135028
C15: =Model!C37 -> EBIT | G15: =Model!P37 -> 115377 | H15: =Model!Q37 -> 154599 | I15: =Model!R37 -> 223316 | J15: =Model!S37 -> 320914 | K15: =Model!U37 -> 339617 | L15: =Model!V37 -> 315373.1 | M15: =Model!W37 -> 370051.21 | N15: =Model!X37 -> 509628.06 | O15: =Model!Z37 -> 321489.92 | P15: =Model!AA37 -> 372328.77 | Q15: =Model!AB37 -> 438226.91 | R15: =Model!AC37 -> 607462.17 | T15: =Model!J37 -> 375852 | U15: =Model!O37 -> 543682 | V15: =Model!T37 -> 814206 | W15: =Model!Y37 -> 1534669.4 | X15: =Model!AD37 -> 1739507.8 | Y15: =Model!AE37 -> 1798534.7 | Z15: =Model!AF37 -> 1632271.4 | AA15: =Model!AG37 -> 2012773.1 | AC15: =IFERROR((V15/T15)^(1/(V$4-T$4))-1,"N/A") -> 0.47183361 | AE15: =IFERROR((AA15/V15)^(1/(AA$4-V$4))-1,"N/A") -> 0.19842843
C16: Margin | G16: =G15/G$8 -> 0.16505489 | H16: =H15/H$8 -> 0.18447687 | I16: =I15/I$8 -> 0.21349644 | J16: =J15/J$8 -> 0.24742257 | K16: =K15/K$8 -> 0.24250233 | L16: =L15/L$8 -> 0.20454013 | M16: =M15/M$8 -> 0.21530491 | N16: =N15/N$8 -> 0.24110395 | ... R16: =R15/R$8 -> 0.24894361 | T16: =T15/T$8 -> 0.15386958 | U16: =U15/U$8 -> 0.18144743 | V16: =V15/V$8 -> 0.20984236 | W16: =W15/W$8 -> 0.22652643 | X16: =X15/X$8 -> 0.22699042 | Y16: =Y15/Y$8 -> 0.227834 | Z16: =Z15/Z$8 -> 0.21123863 | AA16: =AA15/AA$8 -> 0.27458064
C17: YoY % Growth | K17: =K15/G15-1 -> 1.9435416 | L17: =L15/H15-1 -> 1.0399427 | M17: =M15/I15-1 -> 0.6570743 | N17: =N15/J15-1 -> 0.58805183 | O17: =O15/K15-1 -> -0.053375081 | P17: =P15/L15-1 -> 0.18059775 | Q17: =Q15/M15-1 -> 0.18423317 | R17: =R15/N15-1 -> 0.19197158 | U17: =U15/T15-1 -> 0.44653215 | V17: =V15/U15-1 -> 0.49757763 | W17: =W15/V15-1 -> 0.8848662 | X17: =X15/W15-1 -> 0.13347396 | Y17: =Y15/X15-1 -> 0.033933146 | Z17: =Z15/Y15-1 -> -0.092443784 | AA17: =AA15/Z15-1 -> 0.2331118
C19: =Model!C46 -> Net Income (Loss) | G19: =Model!P46 -> 153790 | H19: =Model!Q46 -> 106939 | I19: =Model!R46 -> 157494 | J19: =Model!S46 -> 222484 | K19: =Model!U46 -> 322721 | L19: =Model!V46 -> 230802.51 | M19: =Model!W46 -> 277383.26 | N19: =Model!X46 -> 376925.18 | O19: =Model!Z46 -> 288459.79 | P19: =Model!AA46 -> 275255.05 | Q19: =Model!AB46 -> 324690.54 | R19: =Model!AC46 -> 451667.06 | T19: =Model!J46 -> 285223 | U19: =Model!O46 -> 417737 | V19: =Model!T46 -> 640707 | W19: =Model!Y46 -> 1207832 | X19: =Model!AD46 -> 1340072.4 | Y19: =Model!AE46 -> 1358063.9 | Z19: =Model!AF46 -> 1231468.3 | AA19: =Model!AG46 -> 1524493 | AC19: =IFERROR((V19/T19)^(1/(V$4-T$4))-1,"N/A") -> 0.49877853 | AE19: =IFERROR((AA19/V19)^(1/(AA$4-V$4))-1,"N/A") -> 0.18930486
C20: Margin | G20: =G19/G$8 -> 0.22000738 | H20: =H19/H$8 -> 0.12760608 | I20: =I19/I$8 -> 0.15056874 | J20: =J19/J$8 -> 0.17153369 | K20: =K19/K$8 -> 0.2304378 | L20: =L19/L$8 -> 0.14969056 | M20: =M19/M$8 -> 0.16138842 | N20: =N19/N$8 -> 0.1783225 | ... R20: =R19/R$8 -> 0.18509734 | T20: =T19/T$8 -> 0.11676709 | U20: =U19/U$8 -> 0.13941478 | V20: =V19/V$8 -> 0.1651271 | W20: =W19/W$8 -> 0.17828326 | X20: =X19/X$8 -> 0.17486763 | Y20: =Y19/Y$8 -> 0.17203623 | Z20: =Z19/Z$8 -> 0.15936913 | AA20: =AA19/AA$8 -> 0.20796992
C21: YoY % Growth | K21: =K19/G19-1 -> 1.0984524 | L21: =L19/H19-1 -> 1.1582632 | M21: =M19/I19-1 -> 0.76123068 | N21: =N19/J19-1 -> 0.69416759 | O21: =O19/K19-1 -> -0.10616356 | P21: =P19/L19-1 -> 0.19259988 | Q21: =Q19/M19-1 -> 0.17054842 | R21: =R19/N19-1 -> 0.19829367 | U21: =U19/T19-1 -> 0.46459788 | V21: =V19/U19-1 -> 0.53375689 | W21: =W19/V19-1 -> 0.88515493 | X21: =X19/W19-1 -> 0.10948583 | Y21: =Y19/X19-1 -> 0.013425749 | Z21: =Z19/Y19-1 -> -0.093217719 | AA21: =AA19/Z19-1 -> 0.23794743
C23: =Model!C58 -> Adj. EPS (Diluted) | G23: =Model!P58 -> 3.4757716 | H23: =Model!Q58 -> 2.3585034 | I23: =Model!R58 -> 3.408449 | J23: =Model!S58 -> 4.8409485 | K23: =Model!U58 -> 7.1979689 | L23: =Model!V58 -> 5.3153286 | M23: =Model!W58 -> 6.0438439 | N23: =Model!X58 -> 8.1844874 | O23: =Model!Z58 -> 5.8774868 | P23: =Model!AA58 -> 5.6505182 | Q23: =Model!AB58 -> 6.6214374 | R23: =Model!AC58 -> 9.179098 | T23: =Model!J58 -> 6.3712063 | U23: =Model!O58 -> 9.0832013 | V23: =Model!T58 -> 14.04956 | W23: =Model!Y58 -> 25.791307 | X23: =Model!AD58 -> 27.030169 | Y23: =Model!AE58 -> 27.91209 | Z23: =Model!AF58 -> 25.962366 | AA23: =Model!AG58 -> 33.296064 | AC23: =IFERROR((V23/T23)^(1/(V$4-T$4))-1,"N/A") -> 0.48497973 | AE23: =IFERROR((AA23/V23)^(1/(AA$4-V$4))-1,"N/A") -> 0.18835456
C24: YoY % Growth | K24: =K23/G23-1 -> 1.0708982 | L24: =L23/H23-1 -> 1.2536871 | M24: =M23/I23-1 -> 0.77319474 | N24: =N23/J23-1 -> 0.69067847 | O24: =O23/K23-1 -> -0.18345205 | P24: =P23/L23-1 -> 0.063060934 | Q24: =Q23/M23-1 -> 0.095567239 | R24: =R23/N23-1 -> 0.12152388 | U24: =IF(ISERROR(U23/T23-1),"NA",(U23/T23-1)) -> 0.42566429 | V24: =IF(ISERROR(V23/U23-1),"NA",(V23/U23-1)) -> 0.54676301 | W24: =IF(ISERROR(W23/V23-1),"NA",(W23/V23-1)) -> 0.83573773 | X24: =IF(ISERROR(X23/W23-1),"NA",(X23/W23-1)) -> 0.048034115 | Y24: =IF(ISERROR(Y23/X23-1),"NA",(Y23/X23-1)) -> 0.032627265 | Z24: =IF(ISERROR(Z23/Y23-1),"NA",(Z23/Y23-1)) -> -0.069852314 | AA24: =IF(ISERROR(AA23/Z23-1),"NA",(AA23/Z23-1)) -> 0.2824742
C27: =Model!C62 -> EBITDA | G27: =Model!P62 -> 121353 | H27: =Model!Q62 -> 161049 | I27: =Model!R62 -> 231172 | J27: =Model!S62 -> 333189 | K27: =Model!U62 -> 352055 | L27: =Model!V62 -> 323791.48 | M27: =Model!W62 -> 378980.17 | N27: =Model!X62 -> 518920.12 | O27: =Model!Z62 -> 321752.46 | P27: =Model!AA62 -> 373022.24 | Q27: =Model!AB62 -> 439382.03 | R27: =Model!AC62 -> 609080.48 | T27: =Model!J62 -> 400200 | U27: =Model!O62 -> 568150 | V27: =Model!T62 -> 846763 | W27: =Model!Y62 -> 1573746.8 | X27: =Model!AD62 -> 1743237.2 | Y27: =Model!AE62 -> 1817103.6 | Z27: =Model!AF62 -> 1661971.8 | AA27: =Model!AG62 -> 2051150.7 | AC27: =IFERROR((V27/T27)^(1/(V$4-T$4))-1,"N/A") -> 0.45459602 | AE27: =IFERROR((AA27/V27)^(1/(AA$4-V$4))-1,"N/A") -> 0.19356793
C28: Margin | G28: =G27/G$8 -> 0.17360398 | H28: =H27/H$8 -> 0.1921734 | I28: =I27/I$8 -> 0.221007 | J28: =J27/J$8 -> 0.25688651 | K28: =K27/K$8 -> 0.25138364 | L28: =L27/L$8 -> 0.21 | M28: =M27/M$8 -> 0.2205 | N28: =N27/N$8 -> 0.2455 | ... R28: =R27/R$8 -> 0.24960681 | T28: =T27/T$8 -> 0.16383738 | U28: =U27/U$8 -> 0.18961333 | V28: =V27/V$8 -> 0.21823316 | W28: =W27/W$8 -> 0.23229449 | X28: =X27/X$8 -> 0.22747707 | Y28: =Y27/Y$8 -> 0.23018625 | Z28: =Z27/Z$8 -> 0.21508227 | AA28: =AA27/AA$8 -> 0.27981608
C29: YoY % Growth | K29: =K27/G27-1 -> 1.901082 | L29: =L27/H27-1 -> 1.0105153 | M29: =M27/I27-1 -> 0.63938614 | N29: =N27/J27-1 -> 0.55743473 | O29: =O27/K27-1 -> -0.086073318 | P29: =P27/L27-1 -> 0.15204466 | Q29: =Q27/M27-1 -> 0.15937999 | R29: =R27/N27-1 -> 0.17374612 | U29: =U27/T27-1 -> 0.41966517 | V29: =V27/U27-1 -> 0.49038634 | W29: =W27/V27-1 -> 0.85854456 | X29: =X27/W27-1 -> 0.10769867 | Y29: =Y27/X27-1 -> 0.042373102 | Z29: =Z27/Y27-1 -> -0.085373115 | AA29: =AA27/Z27-1 -> 0.234167
G31: =G$5 -> Quarterly | T31: =T$5 -> Annuals
A32: x | C32: ="Consolidated "&Model!C120 -> Consolidated Balance Sheet | G32: =G$6 -> 1Q25 | H32: =H$6 -> 2Q25 | I32: =I$6 -> 3Q25 | J32: =J$6 -> 4Q25 | K32: =K$6 -> 1Q26 | L32: =L$6 -> 2Q26e | M32: =M$6 -> 3Q26e | N32: =N$6 -> 4Q26e | ... R32: =R$6 -> 4Q27e | T32: =T$6 -> 2023 | U32: =U$6 -> 2024 | V32: =V$6 -> 2025 | W32: =W$6 -> 2026e | X32: =X$6 -> 2027e | Y32: =Y$6 -> 2028e | Z32: =Z$6 -> 2029e | AA32: =AA$6 -> 2030e
C34: =Model!C122 -> Cash & Cash Equivalents | G34: =Model!P122 -> 552954 | H34: =Model!Q122 -> 617298 | I34: =Model!R122 -> 851908 | J34: =Model!S122 -> 1426020 | K34: =Model!U122 -> 985987 | L34: =Model!V122 -> 795539.03 | M34: =Model!W122 -> 870481.47 | N34: =Model!X122 -> 802310.4 | O34: =Model!Z122 -> 1652640.1 | P34: =Model!AA122 -> 1736972.8 | Q34: =Model!AB122 -> 1858789.1 | R34: =Model!AC122 -> 1772786.4 | T34: =Model!J122 -> 596878 | U34: =Model!O122 -> 873045 | V34: =Model!T122 -> 1426020 | W34: =Model!Y122 -> 802310.4 | X34: =Model!AD122 -> 1772786.4 | Y34: =Model!AE122 -> 473608.99 | Z34: =Model!AF122 -> 766208.18 | AA34: =Model!AG122 -> 1789601
C35: =Model!C123 -> Accounts Receivable | G35: =Model!P123 -> 507003 | H35: =Model!Q123 -> 518048 | I35: =Model!R123 -> 561911 | J35: =Model!S123 -> 619246 | K35: =Model!U123 -> 621229 | L35: =Model!V123 -> 779403.86 | M35: =Model!W123 -> 896729.19 | N35: =Model!X123 -> 1102814.4 | O35: =Model!Z123 -> 793584.35 | P35: =Model!AA123 -> 874945.2 | Q35: =Model!AB123 -> 1002994.9 | R35: =Model!AC123 -> 1273126.8 | T35: =Model!J123 -> 397352 | U35: =Model!O123 -> 455068 | V35: =Model!T123 -> 619246 | W35: =Model!Y123 -> 1102814.4 | X35: =Model!AD123 -> 1273126.8 | Y35: =Model!AE123 -> 1189515.6 | Z35: =Model!AF123 -> 1164364.2 | AA35: =Model!AG123 -> 1104573.8
C36: =Model!C124 -> Inventory | G36: =Model!P124 -> 0 | H36: =Model!Q124 -> 0 | I36: =Model!R124 -> 0 | J36: =Model!S124 -> 0 | K36: =Model!U124 -> 0 | L36: =Model!V124 -> 0 | M36: =Model!W124 -> 0 | N36: =Model!X124 -> 0 | O36: =Model!Z124 -> 0 | P36: =Model!AA124 -> 0 | Q36: =Model!AB124 -> 0 | R36: =Model!AC124 -> 0 | T36: =Model!J124 -> 0 | U36: =Model!O124 -> 0 | V36: =Model!T124 -> 0 | W36: =Model!Y124 -> 0 | X36: =Model!AD124 -> 0 | Y36: =Model!AE124 -> 0 | Z36: =Model!AF124 -> 0 | AA36: =Model!AG124 -> 0
C37: =Model!C125 -> Prepaid & Other Current Assets | G37: =Model!P125 -> 986097 | H37: =Model!Q125 -> 1299760 | I37: =Model!R125 -> 1726752 | J37: =Model!S125 -> 1812975 | K37: =Model!U125 -> 1203341 | L37: =Model!V125 -> 2343633.5 | M37: =Model!W125 -> 2612471 | N37: =Model!X125 -> 3212865.9 | O37: =Model!Z125 -> 2386273.6 | P37: =Model!AA125 -> 2630922.2 | Q37: =Model!AB125 -> 2922058.6 | R37: =Model!AC125 -> 3709042.7 | T37: =Model!J125 -> 1610987 | U37: =Model!O125 -> 1659788 | V37: =Model!T125 -> 1812975 | W37: =Model!Y125 -> 3212865.9 | X37: =Model!AD125 -> 3709042.7 | Y37: =Model!AE125 -> 5920543.3 | Z37: =Model!AF125 -> 6181715.6 | AA37: =Model!AG125 -> 6230800.4
C38: =Model!C126 -> Total Current Assets | G38: =SUM(G34:G37) -> 2046054 | H38: =SUM(H34:H37) -> 2435106 | I38: =SUM(I34:I37) -> 3140571 | J38: =SUM(J34:J37) -> 3858241 | K38: =SUM(K34:K37) -> 2810557 | L38: =SUM(L34:L37) -> 3918576.4 | M38: =SUM(M34:M37) -> 4379681.7 | N38: =SUM(N34:N37) -> 5117990.7 | ... R38: =SUM(R34:R37) -> 6754955.9 | T38: =SUM(T34:T37) -> 2605217 | U38: =SUM(U34:U37) -> 2987901 | V38: =SUM(V34:V37) -> 3858241 | W38: =SUM(W34:W37) -> 5117990.7 | X38: =SUM(X34:X37) -> 6754955.9 | Y38: =SUM(Y34:Y37) -> 7583667.9 | Z38: =SUM(Z34:Z37) -> 8112288 | AA38: =SUM(AA34:AA37) -> 9124975.2
C40: =Model!C128 -> PP&E, Net | G40: =Model!P128 -> 161204 | H40: =Model!Q128 -> 182856 | I40: =Model!R128 -> 188947 | J40: =Model!S128 -> 190064 | K40: =Model!U128 -> 187075 | L40: =Model!V128 -> 201784.59 | M40: =Model!W128 -> 218636.58 | N40: =Model!X128 -> 241050.44 | O40: =Model!Z128 -> 254836.65 | P40: =Model!AA128 -> 270606.23 | Q40: =Model!AB128 -> 288787.22 | R40: =Model!AC128 -> 314271.31 | T40: =Model!J128 -> 137940 | U40: =Model!O128 -> 144756 | V40: =Model!T128 -> 190064 | W40: =Model!Y128 -> 241050.44 | X40: =Model!AD128 -> 314271.31 | Y40: =Model!AE128 -> 376113.34 | Z40: =Model!AF128 -> 424320.1 | AA40: =Model!AG128 -> 457897.79
C41: =Model!#REF! -> #REF! | G41: =Model!P129 -> 0 | H41: =Model!Q129 -> 0 | I41: =Model!R129 -> 0 | J41: =Model!S129 -> 0 | K41: =Model!U129 -> 25871 | L41: =Model!V129 -> 25871 | M41: =Model!W129 -> 25871 | N41: =Model!X129 -> 25871 | O41: =Model!Z129 -> 25871 | P41: =Model!AA129 -> 25871 | Q41: =Model!AB129 -> 25871 | R41: =Model!AC129 -> 25871 | T41: =Model!J129 -> 0 | U41: =Model!O129 -> 0 | V41: =Model!T129 -> 0 | W41: =Model!Y129 -> 25871 | X41: =Model!AD129 -> 25871 | Y41: =Model!AE129 -> 25871 | Z41: =Model!AF129 -> 25871 | AA41: =Model!AG129 -> 25871
C42: =Model!C130 -> Goodwill | G42: =Model!P130 -> 125996 | H42: =Model!Q130 -> 129109 | I42: =Model!R130 -> 128576 | J42: =Model!S130 -> 230783 | K42: =Model!U130 -> 227412 | L42: =Model!V130 -> 227412 | M42: =Model!W130 -> 227412 | N42: =Model!X130 -> 227412 | O42: =Model!Z130 -> 227412 | P42: =Model!AA130 -> 227412 | Q42: =Model!AB130 -> 227412 | R42: =Model!AC130 -> 227412 | T42: =Model!J130 -> 125493 | U42: =Model!O130 -> 124452 | V42: =Model!T130 -> 230783 | W42: =Model!Y130 -> 227412 | X42: =Model!AD130 -> 227412 | Y42: =Model!AE130 -> 227412 | Z42: =Model!AF130 -> 227412 | AA42: =Model!AG130 -> 227412
C43: =Model!C131 -> Other Non-Current Assets | G43: =Model!P131 -> 937861 | H43: =Model!Q131 -> 942588 | I43: =Model!R131 -> 964152 | J43: =Model!S131 -> 1079009 | K43: =Model!U131 -> 1063358 | L43: =Model!V131 -> 1064421.4 | M43: =Model!W131 -> 1067614.6 | N43: =Model!X131 -> 1068682.2 | O43: =Model!Z131 -> 1069750.9 | P43: =Model!AA131 -> 1070820.7 | Q43: =Model!AB131 -> 1074033.1 | R43: =Model!AC131 -> 1075107.2 | T43: =Model!J131 -> 834648 | U43: =Model!O131 -> 916862 | V43: =Model!T131 -> 1079009 | W43: =Model!Y131 -> 1068682.2 | X43: =Model!AD131 -> 1075107.2 | Y43: =Model!AE131 -> 1080482.7 | Z43: =Model!AF131 -> 1085885.1 | AA43: =Model!AG131 -> 1091314.5
C44: =Model!C132 -> Total Non-Current Assets | G44: =SUM(G40:G43) -> 1225061 | H44: =SUM(H40:H43) -> 1254553 | I44: =SUM(I40:I43) -> 1281675 | J44: =SUM(J40:J43) -> 1499856 | K44: =SUM(K40:K43) -> 1503716 | L44: =SUM(L40:L43) -> 1519488.9 | M44: =SUM(M40:M43) -> 1539534.2 | N44: =SUM(N40:N43) -> 1563015.7 | ... R44: =SUM(R40:R43) -> 1642661.5 | T44: =SUM(T40:T43) -> 1098081 | U44: =SUM(U40:U43) -> 1186070 | V44: =SUM(V40:V43) -> 1499856 | W44: =SUM(W40:W43) -> 1563015.7 | X44: =SUM(X40:X43) -> 1642661.5 | Y44: =SUM(Y40:Y43) -> 1709879 | Z44: =SUM(Z40:Z43) -> 1763488.2 | AA44: =SUM(AA40:AA43) -> 1802495.3
C46: =Model!C134 -> Total Assets | G46: =SUM(G38,G44) -> 3271115 | H46: =SUM(H38,H44) -> 3689659 | I46: =SUM(I38,I44) -> 4422246 | J46: =SUM(J38,J44) -> 5358097 | K46: =SUM(K38,K44) -> 4314273 | L46: =SUM(L38,L44) -> 5438065.4 | M46: =SUM(M38,M44) -> 5919215.9 | N46: =SUM(N38,N44) -> 6681006.4 | ... R46: =SUM(R38,R44) -> 8397617.4 | T46: =SUM(T38,T44) -> 3703298 | U46: =SUM(U38,U44) -> 4173971 | V46: =SUM(V38,V44) -> 5358097 | W46: =SUM(W38,W44) -> 6681006.4 | X46: =SUM(X38,X44) -> 8397617.4 | Y46: =SUM(Y38,Y44) -> 9293546.9 | Z46: =SUM(Z38,Z44) -> 9875776.2 | AA46: =SUM(AA38,AA44) -> 10927471
C48: =Model!C136 -> Accounts Payable | G48: =Model!P136 -> 127670 | H48: =Model!Q136 -> 132817 | I48: =Model!R136 -> 103536 | J48: =Model!S136 -> 108485 | K48: =Model!U136 -> 39061 | L48: =Model!V136 -> 185023.7 | M48: =Model!W136 -> 206247.71 | N48: =Model!X136 -> 253647.31 | O48: =Model!Z136 -> 188390.02 | P48: =Model!AA136 -> 207704.38 | Q48: =Model!AB136 -> 230688.84 | R48: =Model!AC136 -> 292819.16 | T48: =Model!J136 -> 71827 | U48: =Model!O136 -> 77535 | V48: =Model!T136 -> 108485 | W48: =Model!Y136 -> 253647.31 | X48: =Model!AD136 -> 292819.16 | Y48: =Model!AE136 -> 221033.62 | Z48: =Model!AF136 -> 216360.05 | AA48: =Model!AG136 -> 205249.9
C49: =Model!C137 -> Accrued Liabilities | G49: =Model!P137 -> 316383 | H49: =Model!Q137 -> 549660 | I49: =Model!R137 -> 881526 | J49: =Model!S137 -> 1381322 | K49: =Model!U137 -> 853818 | L49: =Model!V137 -> 1480189.6 | M49: =Model!W137 -> 1649981.7 | N49: =Model!X137 -> 1902354.8 | O49: =Model!Z137 -> 1507120.2 | P49: =Model!AA137 -> 1661635.1 | Q49: =Model!AB137 -> 1845510.7 | R49: =Model!AC137 -> 2196143.7 | T49: =Model!J137 -> 763160 | U49: =Model!O137 -> 1024076 | V49: =Model!T137 -> 1381322 | W49: =Model!Y137 -> 1902354.8 | X49: =Model!AD137 -> 2196143.7 | Y49: =Model!AE137 -> 1618281.8 | Z49: =Model!AF137 -> 1159071.7 | AA49: =Model!AG137 -> 733035.34
C50: =Model!C138 -> Other Current Liabilities | G50: =Model!P138 -> 99453 | H50: =Model!Q138 -> 95934 | I50: =Model!R138 -> 172987 | J50: =Model!S138 -> 293614 | K50: =Model!U138 -> 123221 | L50: =Model!V138 -> 277535.55 | M50: =Model!W138 -> 309371.57 | N50: =Model!X138 -> 380470.96 | O50: =Model!Z138 -> 313983.37 | P50: =Model!AA138 -> 311556.57 | Q50: =Model!AB138 -> 346033.26 | R50: =Model!AC138 -> 439228.74 | T50: =Model!J138 -> 75072 | U50: =Model!O138 -> 90239 | V50: =Model!T138 -> 293614 | W50: =Model!Y138 -> 380470.96 | X50: =Model!AD138 -> 439228.74 | Y50: =Model!AE138 -> 236821.73 | Z50: =Model!AF138 -> 231814.33 | AA50: =Model!AG138 -> 146607.07
C51: =Model!C139 -> Total Current Liabilities (Excl. Debt) | G51: =SUM(G48:G50) -> 543506 | H51: =SUM(H48:H50) -> 778411 | I51: =SUM(I48:I50) -> 1158049 | J51: =SUM(J48:J50) -> 1783421 | K51: =SUM(K48:K50) -> 1016100 | L51: =SUM(L48:L50) -> 1942748.9 | M51: =SUM(M48:M50) -> 2165601 | N51: =SUM(N48:N50) -> 2536473.1 | ... R51: =SUM(R48:R50) -> 2928191.6 | T51: =SUM(T48:T50) -> 910059 | U51: =SUM(U48:U50) -> 1191850 | V51: =SUM(V48:V50) -> 1783421 | W51: =SUM(W48:W50) -> 2536473.1 | X51: =SUM(X48:X50) -> 2928191.6 | Y51: =SUM(Y48:Y50) -> 2076137.2 | Z51: =SUM(Z48:Z50) -> 1607246 | AA51: =SUM(AA48:AA50) -> 1084892.3
C53: =Model!C141 -> Revolver | G53: =Model!P141 -> 0 | H53: =Model!Q141 -> 0 | I53: =Model!R141 -> 0 | J53: =Model!S141 -> 0 | K53: =Model!U141 -> 0 | L53: =Model!V141 -> 0 | M53: =Model!W141 -> 0 | N53: =Model!X141 -> 0 | O53: =Model!Z141 -> 0 | P53: =Model!AA141 -> 0 | Q53: =Model!AB141 -> 0 | R53: =Model!AC141 -> 0 | T53: =Model!J141 -> 0 | U53: =Model!O141 -> 0 | V53: =Model!T141 -> 0 | W53: =Model!Y141 -> 0 | X53: =Model!AD141 -> 0 | Y53: =Model!AE141 -> 273553.56 | Z53: =Model!AF141 -> 0 | AA53: =Model!AG141 -> 0
C54: =Model!C142 -> LT Debt (Incl. Current Portion) | G54: =Model!P142 -> 375055 | H54: =Model!Q142 -> 377237 | I54: =Model!R142 -> 540353 | J54: =Model!S142 -> 540243 | K54: =Model!U142 -> 539749 | L54: =Model!V142 -> 540049 | M54: =Model!W142 -> 539649 | N54: =Model!X142 -> 539749 | O54: =Model!Z142 -> 539549 | P54: =Model!AA142 -> 539849 | Q54: =Model!AB142 -> 539449 | R54: =Model!AC142 -> 539549 | T54: =Model!J142 -> 373885 | U54: =Model!O142 -> 373895 | V54: =Model!T142 -> 540243 | W54: =Model!Y142 -> 539749 | X54: =Model!AD142 -> 539549 | Y54: =Model!AE142 -> 538949 | Z54: =Model!AF142 -> 538349 | AA54: =Model!AG142 -> 537749
C55: =Model!C143 -> Deferred Income Taxes | G55: =Model!P143 -> 53616 | H55: =Model!Q143 -> 56968 | I55: =Model!R143 -> 61943 | J55: =Model!S143 -> 64231 | K55: =Model!U143 -> 64506 | L55: =Model!V143 -> 64506 | M55: =Model!W143 -> 64506 | N55: =Model!X143 -> 64506 | O55: =Model!Z143 -> 64506 | P55: =Model!AA143 -> 64506 | Q55: =Model!AB143 -> 64506 | R55: =Model!AC143 -> 64506 | T55: =Model!J143 -> 52813 | U55: =Model!O143 -> 52968 | V55: =Model!T143 -> 64231 | W55: =Model!Y143 -> 64506 | X55: =Model!AD143 -> 64506 | Y55: =Model!AE143 -> 64506 | Z55: =Model!AF143 -> 64506 | AA55: =Model!AG143 -> 64506
C56: =Model!C144 -> Other Non-Current Liabilities | G56: =Model!P144 -> 547283 | H56: =Model!Q144 -> 558549 | I56: =Model!R144 -> 576241 | J56: =Model!S144 -> 650336 | K56: =Model!U144 -> 605317 | L56: =Model!V144 -> 605317 | M56: =Model!W144 -> 605317 | N56: =Model!X144 -> 605317 | O56: =Model!Z144 -> 605317 | P56: =Model!AA144 -> 605317 | Q56: =Model!AB144 -> 605317 | R56: =Model!AC144 -> 605317 | T56: =Model!J144 -> 584051 | U56: =Model!O144 -> 613450 | V56: =Model!T144 -> 650336 | W56: =Model!Y144 -> 605317 | X56: =Model!AD144 -> 605317 | Y56: =Model!AE144 -> 605317 | Z56: =Model!AF144 -> 605317 | AA56: =Model!AG144 -> 605317
C57: =Model!C145 -> Total Non-Current Liabilities | G57: =SUM(G53:G56) -> 975954 | H57: =INDEX(Data,MATCH($C57,Line_Items,0),MATCH(H$32,Fiscal_Periods,0)) -> 992754 | I57: =INDEX(Data,MATCH($C57,Line_Items,0),MATCH(I$32,Fiscal_Periods,0)) -> 1178537 | J57: =INDEX(Data,MATCH($C57,Line_Items,0),MATCH(J$32,Fiscal_Periods,0)) -> 1254810 | K57: =INDEX(Data,MATCH($C57,Line_Items,0),MATCH(K$32,Fiscal_Periods,0)) -> 1209572 | L57: =INDEX(Data,MATCH($C57,Line_Items,0),MATCH(L$32,Fiscal_Periods,0)) -> 1209872 | M57: =INDEX(Data,MATCH($C57,Line_Items,0),MATCH(M$32,Fiscal_Periods,0)) -> 1209472 | N57: =INDEX(Data,MATCH($C57,Line_Items,0),MATCH(N$32,Fiscal_Periods,0)) -> 1209572 | O57: =INDEX(Data,MATCH($C57,Line_Items,0),MATCH(O$32,Fiscal_Periods,0)) -> 1209372 | ... R57: =INDEX(Data,MATCH($C57,Line_Items,0),MATCH(R$32,Fiscal_Periods,0)) -> 1209372 | T57: =INDEX(Data,MATCH($C57,Line_Items,0),MATCH(T$32,Fiscal_Periods,0)) -> 1010749 | U57: =INDEX(Data,MATCH($C57,Line_Items,0),MATCH(U$32,Fiscal_Periods,0)) -> 1040313 | V57: =INDEX(Data,MATCH($C57,Line_Items,0),MATCH(V$32,Fiscal_Periods,0)) -> 1254810 | W57: =INDEX(Data,MATCH($C57,Line_Items,0),MATCH(W$32,Fiscal_Periods,0)) -> 1209572 | X57: =INDEX(Data,MATCH($C57,Line_Items,0),MATCH(X$32,Fiscal_Periods,0)) -> 1209372 | Y57: =INDEX(Data,MATCH($C57,Line_Items,0),MATCH(Y$32,Fiscal_Periods,0)) -> 1482325.6 | Z57: =INDEX(Data,MATCH($C57,Line_Items,0),MATCH(Z$32,Fiscal_Periods,0)) -> 1208172 | AA57: =INDEX(Data,MATCH($C57,Line_Items,0),MATCH(AA$32,Fiscal_Periods,0)) -> 1207572
C59: =Model!C147 -> Total Liabilities | G59: =SUM(G51,G57) -> 1519460 | H59: =SUM(H51,H57) -> 1771165 | I59: =SUM(I51,I57) -> 2336586 | J59: =SUM(J51,J57) -> 3038231 | K59: =SUM(K51,K57) -> 2225672 | L59: =SUM(L51,L57) -> 3152620.9 | M59: =SUM(M51,M57) -> 3375073 | N59: =SUM(N51,N57) -> 3746045.1 | ... R59: =SUM(R51,R57) -> 4137563.6 | T59: =SUM(T51,T57) -> 1920808 | U59: =SUM(U51,U57) -> 2232163 | V59: =SUM(V51,V57) -> 3038231 | W59: =SUM(W51,W57) -> 3746045.1 | X59: =SUM(X51,X57) -> 4137563.6 | Y59: =SUM(Y51,Y57) -> 3558462.8 | Z59: =SUM(Z51,Z57) -> 2815418 | AA59: =SUM(AA51,AA57) -> 2292464.3
C61: =Model!C149 -> Common Stock & APIC | G61: =Model!P149 -> 3597030 | H61: =Model!Q149 -> 3710589 | I61: =Model!R149 -> 3818151 | J61: =Model!S149 -> 4025372 | K61: =Model!U149 -> 4142780 | L61: =Model!V149 -> 4277329.8 | M61: =Model!W149 -> 4427313.7 | N61: =Model!X149 -> 4611766.7 | O61: =Model!Z149 -> 4748764.5 | P61: =Model!AA149 -> 4899807.7 | Q61: =Model!AB149 -> 5067565.3 | R61: =Model!AC149 -> 5280504.2 | T61: =Model!J149 -> 3164019 | U61: =Model!O149 -> 3511204 | V61: =Model!T149 -> 4025372 | W61: =Model!Y149 -> 4611766.7 | X61: =Model!AD149 -> 5280504.2 | Y61: =Model!AE149 -> 5969373.9 | Z61: =Model!AF149 -> 6643678 | AA61: =Model!AG149 -> 7283356.5
C62: =Model!C150 -> Retained Earnings | G62: =Model!P150 -> 2245124 | H62: =Model!Q150 -> 2305996 | I62: =Model!R150 -> 2414099 | J62: =Model!S150 -> 2581815 | K62: =Model!U150 -> 2846337 | L62: =Model!V150 -> 3038630.8 | M62: =Model!W150 -> 3277345.2 | N62: =Model!X150 -> 3613710.6 | O62: =Model!Z150 -> 3863254.6 | P62: =Model!AA150 -> 4097690.4 | Q62: =Model!AB150 -> 4381392 | R62: =Model!AC150 -> 4790065.6 | T62: =Model!J150 -> 1892656 | U62: =Model!O150 -> 2133919 | V62: =Model!T150 -> 2581815 | W62: =Model!Y150 -> 3613710.6 | X62: =Model!AD150 -> 4790065.6 | Y62: =Model!AE150 -> 5976226.3 | Z62: =Model!AF150 -> 7027196.1 | AA62: =Model!AG150 -> 8362165.8
C63: =Model!C151 -> Treasury Stock | G63: =Model!P151 -> -4307384 | H63: =Model!Q151 -> -4350589 | I63: =Model!R151 -> -4407621 | J63: =Model!S151 -> -4562483 | K63: =Model!U151 -> -5183832 | L63: =Model!V151 -> -5313832 | M63: =Model!W151 -> -5443832 | N63: =Model!X151 -> -5573832 | O63: =Model!Z151 -> -5703832 | P63: =Model!AA151 -> -5833832 | Q63: =Model!AB151 -> -5963832 | R63: =Model!AC151 -> -6093832 | T63: =Model!J151 -> -3453203 | U63: =Model!O151 -> -3901424 | V63: =Model!T151 -> -4562483 | W63: =Model!Y151 -> -5573832 | X63: =Model!AD151 -> -6093832 | Y63: =Model!AE151 -> -6493832 | Z63: =Model!AF151 -> -6893832 | AA63: =Model!AG151 -> -7293832
C64: =Model!C152 -> Accumulated Other Comprehensive Income (AOCI) | G64: =Model!P152 -> -28210 | H64: =Model!Q152 -> -10917 | I64: =Model!R152 -> -15183 | J64: =Model!S152 -> -13128 | K64: =Model!U152 -> -23199 | L64: =Model!V152 -> -23199 | M64: =Model!W152 -> -23199 | N64: =Model!X152 -> -23199 | O64: =Model!Z152 -> -23199 | P64: =Model!AA152 -> -23199 | Q64: =Model!AB152 -> -23199 | R64: =Model!AC152 -> -23199 | T64: =Model!J152 -> -26538 | U64: =Model!O152 -> -36057 | V64: =Model!T152 -> -13128 | W64: =Model!Y152 -> -23199 | X64: =Model!AD152 -> -23199 | Y64: =Model!AE152 -> -23199 | Z64: =Model!AF152 -> -23199 | AA64: =Model!AG152 -> -23199
C65: =Model!C153 -> Total Shareholder's Equity | G65: =SUM(G61:G64) -> 1506560 | H65: =SUM(H61:H64) -> 1655079 | I65: =SUM(I61:I64) -> 1809446 | J65: =SUM(J61:J64) -> 2031576 | K65: =SUM(K61:K64) -> 1782086 | L65: =SUM(L61:L64) -> 1978929.5 | M65: =SUM(M61:M64) -> 2237627.9 | N65: =SUM(N61:N64) -> 2628446.3 | ... R65: =SUM(R61:R64) -> 3953538.8 | T65: =SUM(T61:T64) -> 1576934 | U65: =SUM(U61:U64) -> 1707642 | V65: =SUM(V61:V64) -> 2031576 | W65: =SUM(W61:W64) -> 2628446.3 | X65: =SUM(X61:X64) -> 3953538.8 | Y65: =SUM(Y61:Y64) -> 5428569.1 | Z65: =SUM(Z61:Z64) -> 6753843.2 | AA65: =SUM(AA61:AA64) -> 8328491.2
C67: =Model!C155 -> Noncontrolling Interests | G67: =Model!P155 -> 245095 | H67: =Model!Q155 -> 263415 | I67: =Model!R155 -> 276214 | J67: =Model!S155 -> 288290 | K67: =Model!U155 -> 306515 | L67: =Model!V155 -> 306515 | M67: =Model!W155 -> 306515 | N67: =Model!X155 -> 306515 | O67: =Model!Z155 -> 306515 | P67: =Model!AA155 -> 306515 | Q67: =Model!AB155 -> 306515 | R67: =Model!AC155 -> 306515 | T67: =Model!J155 -> 205556 | U67: =Model!O155 -> 234166 | V67: =Model!T155 -> 288290 | W67: =Model!Y155 -> 306515 | X67: =Model!AD155 -> 306515 | Y67: =Model!AE155 -> 306515 | Z67: =Model!AF155 -> 306515 | AA67: =Model!AG155 -> 306515
C68: =Model!C156 -> Total Equity | G68: =SUM(G65,G67) -> 1751655 | H68: =SUM(H65,H67) -> 1918494 | I68: =SUM(I65,I67) -> 2085660 | J68: =SUM(J65,J67) -> 2319866 | K68: =SUM(K65,K67) -> 2088601 | L68: =SUM(L65,L67) -> 2285444.5 | M68: =SUM(M65,M67) -> 2544142.9 | N68: =SUM(N65,N67) -> 2934961.3 | ... R68: =SUM(R65,R67) -> 4260053.8 | T68: =SUM(T65,T67) -> 1782490 | U68: =SUM(U65,U67) -> 1941808 | V68: =SUM(V65,V67) -> 2319866 | W68: =SUM(W65,W67) -> 2934961.3 | X68: =SUM(X65,X67) -> 4260053.8 | Y68: =SUM(Y65,Y67) -> 5735084.1 | Z68: =SUM(Z65,Z67) -> 7060358.2 | AA68: =SUM(AA65,AA67) -> 8635006.2
C70: =Model!C158 -> Total Liabilities & Shareholder's Equity | G70: =SUM(G59,G68) -> 3271115 | H70: =SUM(H59,H68) -> 3689659 | I70: =SUM(I59,I68) -> 4422246 | J70: =SUM(J59,J68) -> 5358097 | K70: =SUM(K59,K68) -> 4314273 | L70: =SUM(L59,L68) -> 5438065.4 | M70: =SUM(M59,M68) -> 5919215.9 | N70: =SUM(N59,N68) -> 6681006.4 | ... R70: =SUM(R59,R68) -> 8397617.4 | T70: =SUM(T59,T68) -> 3703298 | U70: =SUM(U59,U68) -> 4173971 | V70: =SUM(V59,V68) -> 5358097 | W70: =SUM(W59,W68) -> 6681006.4 | X70: =SUM(X59,X68) -> 8397617.4 | Y70: =SUM(Y59,Y68) -> 9293546.9 | Z70: =SUM(Z59,Z68) -> 9875776.2 | AA70: =SUM(AA59,AA68) -> 10927471
G72: =G$5 -> Quarterly | T72: =T$31 -> Annuals
A73: x | C73: Ratio Analysis | G73: =G$6 -> 1Q25 | H73: =H$6 -> 2Q25 | I73: =I$6 -> 3Q25 | J73: =J$6 -> 4Q25 | K73: =K$6 -> 1Q26 | L73: =L$6 -> 2Q26e | M73: =M$6 -> 3Q26e | N73: =N$6 -> 4Q26e | ... R73: =R$6 -> 4Q27e | T73: =T$6 -> 2023 | U73: =U$6 -> 2024 | V73: =V$6 -> 2025 | W73: =W$6 -> 2026e | X73: =X$6 -> 2027e | Y73: =Y$6 -> 2028e | Z73: =Z$6 -> 2029e | AA73: =AA$6 -> 2030e
C75: Profitability
C76: Gross Margin | G76: =G12 -> 1 | H76: =H12 -> 1 | I76: =I12 -> 1 | J76: =J12 -> 1 | K76: =K12 -> 1 | L76: =L12 -> 1 | M76: =M12 -> 1 | N76: =N12 -> 1 | ... R76: =R12 -> 1 | T76: =T12 -> 1 | U76: =U12 -> 1 | V76: =V12 -> 1 | W76: =W12 -> 1 | X76: =X12 -> 1 | Y76: =Y12 -> 1 | Z76: =Z12 -> 1 | AA76: =AA12 -> 1
C77: EBITDA Margin | G77: =G28 -> 0.17360398 | H77: =H28 -> 0.1921734 | I77: =I28 -> 0.221007 | J77: =J28 -> 0.25688651 | K77: =K28 -> 0.25138364 | L77: =L28 -> 0.21 | M77: =M28 -> 0.2205 | N77: =N28 -> 0.2455 | ... R77: =R28 -> 0.24960681 | T77: =T28 -> 0.16383738 | U77: =U28 -> 0.18961333 | V77: =V28 -> 0.21823316 | W77: =W28 -> 0.23229449 | X77: =X28 -> 0.22747707 | Y77: =Y28 -> 0.23018625 | Z77: =Z28 -> 0.21508227 | AA77: =AA28 -> 0.27981608
C78: EBIT Margin | G78: =G16 -> 0.16505489 | H78: =H16 -> 0.18447687 | I78: =I16 -> 0.21349644 | J78: =J16 -> 0.24742257 | K78: =K16 -> 0.24250233 | L78: =L16 -> 0.20454013 | M78: =M16 -> 0.21530491 | N78: =N16 -> 0.24110395 | ... R78: =R16 -> 0.24894361 | T78: =T16 -> 0.15386958 | U78: =U16 -> 0.18144743 | V78: =V16 -> 0.20984236 | W78: =W16 -> 0.22652643 | X78: =X16 -> 0.22699042 | Y78: =Y16 -> 0.227834 | Z78: =Z16 -> 0.21123863 | AA78: =AA16 -> 0.27458064
C79: Net Profit Margin | G79: =G20 -> 0.22000738 | H79: =H20 -> 0.12760608 | I79: =I20 -> 0.15056874 | J79: =J20 -> 0.17153369 | K79: =K20 -> 0.2304378 | L79: =L20 -> 0.14969056 | M79: =M20 -> 0.16138842 | N79: =N20 -> 0.1783225 | ... R79: =R20 -> 0.18509734 | T79: =T20 -> 0.11676709 | U79: =U20 -> 0.13941478 | V79: =V20 -> 0.1651271 | W79: =W20 -> 0.17828326 | X79: =X20 -> 0.17486763 | Y79: =Y20 -> 0.17203623 | Z79: =Z20 -> 0.15936913 | AA79: =AA20 -> 0.20796992
C80: Return on Assets (ROA) | G80: =G19/G46 -> 0.04701455 | H80: =H19/H46 -> 0.028983437 | I80: =I19/I46 -> 0.03561403 | J80: =J19/J46 -> 0.041522951 | K80: =K19/K46 -> 0.074803101 | L80: =L19/L46 -> 0.042442026 | M80: =M19/M46 -> 0.046861488 | N80: =N19/N46 -> 0.056417426 | ... R80: =R19/R46 -> 0.053785144 | T80: =T19/T46 -> 0.077018647 | U80: =U19/U46 -> 0.10008143 | V80: =V19/V46 -> 0.11957734 | W80: =W19/W46 -> 0.18078593 | X80: =X19/X46 -> 0.1595777 | Y80: =Y19/Y46 -> 0.14612977 | Z80: =Z19/Z46 -> 0.12469585 | AA80: =AA19/AA46 -> 0.13951015
C81: Return on Equity (ROE) | G81: =G19*4/G68 -> 0.35118788 | H81: =H19*4/H68 -> 0.22296447 | I81: =I19*4/I68 -> 0.30205115 | J81: =J19*4/J68 -> 0.38361526 | K81: =K19*4/K68 -> 0.61806156 | L81: =L19*4/L68 -> 0.40395207 | M81: =M19*4/M68 -> 0.43611271 | N81: =N19*4/N68 -> 0.51370379 | ... R81: =R19*4/R68 -> 0.42409517 | T81: =T19/T68 -> 0.1600138 | U81: =U19/U68 -> 0.21512786 | V81: =V19/V68 -> 0.27618276 | W81: =W19/W68 -> 0.4115325 | X81: =X19/X68 -> 0.31456702 | Y81: =Y19/Y68 -> 0.2367993 | Z81: =Z19/Z68 -> 0.17442009 | AA81: =AA19/AA68 -> 0.17654799
C82: Return on Invested Capital (ROIC) | G82: =G19*4/(G53+G54+G68) -> 0.28925429 | H82: =H19*4/(H53+H54+H68) -> 0.18632671 | I82: =I19*4/(I53+I54+I68) -> 0.23989828 | J82: =J19*4/(J53+J54+J68) -> 0.31115457 | K82: =K19*4/(K53+K54+K68) -> 0.49113855 | L82: =L19*4/(L53+L54+L68) -> 0.32674293 | M82: =M19*4/(M53+M54+M68) -> 0.35979505 | N82: =N19*4/(N53+N54+N68) -> 0.43390689 | ... S82: =S19*4/(S53+S54+S68) -> #DIV/0! | T82: =T19/(T53+T54+T68) -> 0.13226967 | U82: =U19/(U53+U54+U68) -> 0.18039317 | V82: =V19/(V53+V54+V68) -> 0.22401489 | W82: =W19/(W53+W54+W68) -> 0.34760652 | X82: =X19/(X53+X54+X68) -> 0.27920486 | Y82: =Y19/(Y53+Y54+Y68) -> 0.20741442 | Z82: =Z19/(Z53+Z54+Z68) -> 0.16206287 | AA82: =AA19/(AA53+AA54+AA68) -> 0.16619794
C84: Coverage
C85: Interest Expense | G85: =-Model!P40 -> 4193 | H85: =-Model!Q40 -> 4210 | I85: =-Model!R40 -> 7110 | J85: =-Model!S40 -> 8751 | K85: =-Model!U40 -> 8891 | L85: =-Model!V40 -> 9178.283 | M85: =-Model!W40 -> 9177.433 | N85: =-Model!X40 -> 9174.883 | O85: =-Model!Z40 -> 6071.0512 | P85: =-Model!AA40 -> 6071.6137 | Q85: =-Model!AB40 -> 6071.0512 | R85: =-Model!AC40 -> 6069.3637 | T85: =-Model!J40 -> 16717 | U85: =-Model!O40 -> 16768 | V85: =-Model!T40 -> 24264 | W85: =-Model!Y40 -> 36421.599 | X85: =-Model!AD40 -> 24283.08 | Y85: =-Model!AE40 -> 27396.651 | Z85: =-Model!AF40 -> 27372.651 | AA85: =-Model!AG40 -> 21521.96
C86: Capital Expenditures | G86: =Model!P195 -> 19660 | H86: =Model!Q195 -> 26046 | I86: =Model!R195 -> 19434 | J86: =Model!S195 -> 8862 | K86: =Model!U195 -> 3103 | L86: =Model!V195 -> 23127.963 | M86: =Model!W195 -> 25780.964 | N86: =Model!X195 -> 31705.914 | O86: =Model!Z195 -> 23548.753 | P86: =Model!AA195 -> 25963.048 | Q86: =Model!AB195 -> 28836.105 | R86: =Model!AC195 -> 36602.395 | T86: =Model!J195 -> 55838 | U86: =Model!O195 -> 38792 | V86: =Model!T195 -> 74002 | W86: =Model!Y195 -> 83717.84 | X86: =Model!AD195 -> 114950.3 | Y86: =Model!AE195 -> 118410.87 | Z86: =Model!AF195 -> 115907.17 | AA86: =Model!AG195 -> 109955.3
C87: EBIT / Interest Expense | G87: =IF(ISERROR(G15/G85),"N/A",(G15/G85)) -> 27.516575 | H87: =IF(ISERROR(H15/H85),"N/A",(H15/H85)) -> 36.721853 | I87: =IF(ISERROR(I15/I85),"N/A",(I15/I85)) -> 31.40872 | J87: =IF(ISERROR(J15/J85),"N/A",(J15/J85)) -> 36.671695 | K87: =IF(ISERROR(K15/K85),"N/A",(K15/K85)) -> 38.197841 | L87: =IF(ISERROR(L15/L85),"N/A",(L15/L85)) -> 34.360795 | M87: =IF(ISERROR(M15/M85),"N/A",(M15/M85)) -> 40.321864 | N87: =IF(ISERROR(N15/N85),"N/A",(N15/N85)) -> 55.546001 | ... R87: =IF(ISERROR(R15/R85),"N/A",(R15/R85)) -> 100.08663 | T87: =IF(ISERROR(T15/T85),"N/A",(T15/T85)) -> 22.483221 | U87: =IF(ISERROR(U15/U85),"N/A",(U15/U85)) -> 32.423783 | V87: =IF(ISERROR(V15/V85),"N/A",(V15/V85)) -> 33.556133 | W87: =IF(ISERROR(W15/W85),"N/A",(W15/W85)) -> 42.136244 | X87: =IF(ISERROR(X15/X85),"N/A",(X15/X85)) -> 71.634561 | Y87: =IF(ISERROR(Y15/Y85),"N/A",(Y15/Y85)) -> 65.647978 | Z87: =IF(ISERROR(Z15/Z85),"N/A",(Z15/Z85)) -> 59.631469 | AA87: =IF(ISERROR(AA15/AA85),"N/A",(AA15/AA85)) -> 93.521831
C88: EBITDA / Interest Expense | G88: =IF(ISERROR(G27/G85),"N/A",(G27/G85)) -> 28.941808 | H88: =IF(ISERROR(H27/H85),"N/A",(H27/H85)) -> 38.253919 | I88: =IF(ISERROR(I27/I85),"N/A",(I27/I85)) -> 32.513643 | J88: =IF(ISERROR(J27/J85),"N/A",(J27/J85)) -> 38.074391 | K88: =IF(ISERROR(K27/K85),"N/A",(K27/K85)) -> 39.596783 | L88: =IF(ISERROR(L27/L85),"N/A",(L27/L85)) -> 35.278001 | M88: =IF(ISERROR(M27/M85),"N/A",(M27/M85)) -> 41.29479 | N88: =IF(ISERROR(N27/N85),"N/A",(N27/N85)) -> 56.558772 | ... R88: =IF(ISERROR(R27/R85),"N/A",(R27/R85)) -> 100.35327 | T88: =IF(ISERROR(T27/T85),"N/A",(T27/T85)) -> 23.939702 | U88: =IF(ISERROR(U27/U85),"N/A",(U27/U85)) -> 33.882991 | V88: =IF(ISERROR(V27/V85),"N/A",(V27/V85)) -> 34.897915 | W88: =IF(ISERROR(W27/W85),"N/A",(W27/W85)) -> 43.209162 | X88: =IF(ISERROR(X27/X85),"N/A",(X27/X85)) -> 71.788142 | Y88: =IF(ISERROR(Y27/Y85),"N/A",(Y27/Y85)) -> 66.325756 | Z88: =IF(ISERROR(Z27/Z85),"N/A",(Z27/Z85)) -> 60.716508 | AA88: =IF(ISERROR(AA27/AA85),"N/A",(AA27/AA85)) -> 95.305015
C89: (EBITDA - CapEx) / Interest Expense | G89: =IF(ISERROR((G27-G86)/G85),"N/A",((G27-G86)/G85)) -> 24.253041 | H89: =IF(ISERROR((H27-H86)/H85),"N/A",((H27-H86)/H85)) -> 32.067221 | I89: =IF(ISERROR((I27-I86)/I85),"N/A",((I27-I86)/I85)) -> 29.780309 | J89: =IF(ISERROR((J27-J86)/J85),"N/A",((J27-J86)/J85)) -> 37.061707 | K89: =IF(ISERROR((K27-K86)/K85),"N/A",((K27-K86)/K85)) -> 39.247779 | L89: =IF(ISERROR((L27-L86)/L85),"N/A",((L27-L86)/L85)) -> 32.758144 | M89: =IF(ISERROR((M27-M86)/M85),"N/A",((M27-M86)/M85)) -> 38.485621 | N89: =IF(ISERROR((N27-N86)/N85),"N/A",((N27-N86)/N85)) -> 53.103043 | ... R89: =IF(ISERROR((R27-R86)/R85),"N/A",((R27-R86)/R85)) -> 94.322586 | T89: =IF(ISERROR((T27-T86)/T85),"N/A",((T27-T86)/T85)) -> 20.599509 | U89: =IF(ISERROR((U27-U86)/U85),"N/A",((U27-U86)/U85)) -> 31.569537 | V89: =IF(ISERROR((V27-V86)/V85),"N/A",((V27-V86)/V85)) -> 31.848046 | W89: =IF(ISERROR((W27-W86)/W85),"N/A",((W27-W86)/W85)) -> 40.910585 | X89: =IF(ISERROR((X27-X86)/X85),"N/A",((X27-X86)/X85)) -> 67.054381 | Y89: =IF(ISERROR((Y27-Y86)/Y85),"N/A",((Y27-Y86)/Y85)) -> 62.003663 | Z89: =IF(ISERROR((Z27-Z86)/Z85),"N/A",((Z27-Z86)/Z85)) -> 56.482093 | AA89: =IF(ISERROR((AA27-AA86)/AA85),"N/A",((AA27-AA86)/AA85)) -> 90.196034
C91: Leverage
C92: Total Debt / EBITDA | G92: =IF(ISERROR((G53+G54)/G27),"NA",((G53+G54)/G27)) -> 3.0906117 | H92: =IF(ISERROR((H53+H54)/H27),"NA",((H53+H54)/H27)) -> 2.3423741 | I92: =IF(ISERROR((I53+I54)/I27),"NA",((I53+I54)/I27)) -> 2.33745 | J92: =IF(ISERROR((J53+J54)/J27),"NA",((J53+J54)/J27)) -> 1.6214311 | K92: =IF(ISERROR((K53+K54)/K27),"NA",((K53+K54)/K27)) -> 1.5331383 | L92: =IF(ISERROR((L53+L54)/L27),"NA",((L53+L54)/L27)) -> 1.6678913 | M92: =IF(ISERROR((M53+M54)/M27),"NA",((M53+M54)/M27)) -> 1.4239505 | N92: =IF(ISERROR((N53+N54)/N27),"NA",((N53+N54)/N27)) -> 1.0401389 | ... R92: =IF(ISERROR((R53+R54)/R27),"NA",((R53+R54)/R27)) -> 0.88584189 | T92: =IF(ISERROR((T53+T54)/T27),"NA",((T53+T54)/T27)) -> 0.93424538 | U92: =IF(ISERROR((U53+U54)/U27),"NA",((U53+U54)/U27)) -> 0.65809205 | V92: =IF(ISERROR((V53+V54)/V27),"NA",((V53+V54)/V27)) -> 0.63800969 | W92: =IF(ISERROR((W53+W54)/W27),"NA",((W53+W54)/W27)) -> 0.34297068 | X92: =IF(ISERROR((X53+X54)/X27),"NA",((X53+X54)/X27)) -> 0.3095098 | Y92: =IF(ISERROR((Y53+Y54)/Y27),"NA",((Y53+Y54)/Y27)) -> 0.44714158 | Z92: =IF(ISERROR((Z53+Z54)/Z27),"NA",((Z53+Z54)/Z27)) -> 0.32392187 | AA92: =IF(ISERROR((AA53+AA54)/AA27),"NA",((AA53+AA54)/AA27)) -> 0.26216942
C93: Total Debt / Equity | G93: =IF(ISERROR((G53+G54)/G68),"NA",((G53+G54)/G68)) -> 0.21411465 | H93: =IF(ISERROR((H53+H54)/H68),"NA",((H53+H54)/H68)) -> 0.19663184 | I93: =IF(ISERROR((I53+I54)/I68),"NA",((I53+I54)/I68)) -> 0.2590801 | J93: =IF(ISERROR((J53+J54)/J68),"NA",((J53+J54)/J68)) -> 0.23287681 | K93: =IF(ISERROR((K53+K54)/K68),"NA",((K53+K54)/K68)) -> 0.25842609 | L93: =IF(ISERROR((L53+L54)/L68),"NA",((L53+L54)/L68)) -> 0.23629933 | M93: =IF(ISERROR((M53+M54)/M68),"NA",((M53+M54)/M68)) -> 0.21211426 | N93: =IF(ISERROR((N53+N54)/N68),"NA",((N53+N54)/N68)) -> 0.18390328 | ... R93: =IF(ISERROR((R53+R54)/R68),"NA",((R53+R54)/R68)) -> 0.1266531 | T93: =IF(ISERROR((T53+T54)/T68),"NA",((T53+T54)/T68)) -> 0.20975433 | U93: =IF(ISERROR((U53+U54)/U68),"NA",((U53+U54)/U68)) -> 0.19254993 | V93: =IF(ISERROR((V53+V54)/V68),"NA",((V53+V54)/V68)) -> 0.23287681 | W93: =IF(ISERROR((W53+W54)/W68),"NA",((W53+W54)/W68)) -> 0.18390328 | X93: =IF(ISERROR((X53+X54)/X68),"NA",((X53+X54)/X68)) -> 0.1266531 | Y93: =IF(ISERROR((Y53+Y54)/Y68),"NA",((Y53+Y54)/Y68)) -> 0.1416723 | Z93: =IF(ISERROR((Z53+Z54)/Z68),"NA",((Z53+Z54)/Z68)) -> 0.076249531 | AA93: =IF(ISERROR((AA53+AA54)/AA68),"NA",((AA53+AA54)/AA68)) -> 0.062275462
C94: Total Debt / Total Assets | G94: =IF(ISERROR((G53+G54)/G46),"NA",((G53+G54)/G46)) -> 0.11465662 | H94: =IF(ISERROR((H53+H54)/H46),"NA",((H53+H54)/H46)) -> 0.1022417 | I94: =IF(ISERROR((I53+I54)/I46),"NA",((I53+I54)/I46)) -> 0.12218972 | J94: =IF(ISERROR((J53+J54)/J46),"NA",((J53+J54)/J46)) -> 0.1008274 | K94: =IF(ISERROR((K53+K54)/K46),"NA",((K53+K54)/K46)) -> 0.12510775 | L94: =IF(ISERROR((L53+L54)/L46),"NA",((L53+L54)/L46)) -> 0.09930903 | M94: =IF(ISERROR((M53+M54)/M46),"NA",((M53+M54)/M46)) -> 0.091169001 | N94: =IF(ISERROR((N53+N54)/N46),"NA",((N53+N54)/N46)) -> 0.080788577 | ... R94: =IF(ISERROR((R53+R54)/R46),"NA",((R53+R54)/R46)) -> 0.064250248 | T94: =IF(ISERROR((T53+T54)/T46),"NA",((T53+T54)/T46)) -> 0.10096001 | U94: =IF(ISERROR((U53+U54)/U46),"NA",((U53+U54)/U46)) -> 0.089577767 | V94: =IF(ISERROR((V53+V54)/V46),"NA",((V53+V54)/V46)) -> 0.1008274 | W94: =IF(ISERROR((W53+W54)/W46),"NA",((W53+W54)/W46)) -> 0.080788577 | X94: =IF(ISERROR((X53+X54)/X46),"NA",((X53+X54)/X46)) -> 0.064250248 | Y94: =IF(ISERROR((Y53+Y54)/Y46),"NA",((Y53+Y54)/Y46)) -> 0.087426531 | Z94: =IF(ISERROR((Z53+Z54)/Z46),"NA",((Z53+Z54)/Z46)) -> 0.05451207 | AA94: =IF(ISERROR((AA53+AA54)/AA46),"NA",((AA53+AA54)/AA46)) -> 0.049210748
C96: Efficiency
C97: Asset Turnover | G97: =G8/G46 -> 0.21369533 | H97: =H8/H46 -> 0.2271321 | I97: =I8/I46 -> 0.23653003 | J97: =J8/J46 -> 0.24206878 | K97: =K8/K46 -> 0.32461298 | L97: =L8/L46 -> 0.28353175 | M97: =M8/M46 -> 0.29036463 | N97: =N8/N46 -> 0.31637862 | ... R97: =R8/R46 -> 0.29057762 | T97: =T8/T46 -> 0.65959207 | U97: =U8/U46 -> 0.71786819 | V97: =V8/V46 -> 0.72415337 | W97: =W8/W46 -> 1.0140376 | X97: =X8/X46 -> 0.91256282 | Y97: =Y8/Y46 -> 0.84941281 | Z97: =Z8/Z46 -> 0.78243414 | AA97: =AA8/AA46 -> 0.67081887
C98: =Model!C184 -> Days Sales Outstanding | G98: =Model!P184 -> 62.622107 | H98: =Model!Q184 -> 55.653454 | I98: =Model!R184 -> 47.493689 | J98: =Model!S184 -> 41.890554 | K98: =Model!U184 -> 40.301936 | L98: =Model!V184 -> 46 | M98: =Model!W184 -> 48 | N98: =Model!X184 -> 48 | O98: =Model!Z184 -> 46 | P98: =Model!AA184 -> 46 | Q98: =Model!AB184 -> 48 | R98: =Model!AC184 -> 48 | T98: =Model!J184 -> 59.375076 | U98: =Model!O184 -> 51.918527 | V98: =Model!T184 -> 50.668867 | W98: =Model!Y184 -> 46.516124 | X98: =Model!AD184 -> 56.737203 | Y98: =Model!AE184 -> 55 | Z98: =Model!AF184 -> 55 | AA98: =Model!AG184 -> 55
C99: =Model!C185 -> Days Inventory Outstanding | G99: =Model!P185 -> #DIV/0! | H99: =Model!Q185 -> #DIV/0! | I99: =Model!R185 -> #DIV/0! | J99: =Model!S185 -> #DIV/0! | K99: =Model!U185 -> #DIV/0! | L99: =Model!V185 -> 0 | M99: =Model!W185 -> 0 | N99: =Model!X185 -> 0 | O99: =Model!Z185 -> 0 | P99: =Model!AA185 -> 0 | Q99: =Model!AB185 -> 0 | R99: =Model!AC185 -> 0 | T99: =Model!J185 -> #DIV/0! | U99: =Model!O185 -> #DIV/0! | V99: =Model!T185 -> #DIV/0! | W99: =Model!Y185 -> #DIV/0! | X99: =Model!AD185 -> #DIV/0! | Y99: =Model!AE185 -> 0 | Z99: =Model!AF185 -> 0 | AA99: =Model!AG185 -> 0
C100: =Model!C186 -> Accounts Payable as a % of Sales | G100: =Model!P186 -> 0.045660222 | H100: =Model!Q186 -> 0.039621319 | I100: =Model!R186 -> 0.02474584 | J100: =Model!S186 -> 0.020910304 | K100: =Model!U186 -> 0.0069728427 | L100: =Model!V186 -> 0.03 | M100: =Model!W186 -> 0.03 | N100: =Model!X186 -> 0.03 | O100: =Model!Z186 -> 0.03 | P100: =Model!AA186 -> 0.03 | Q100: =Model!AB186 -> 0.03 | R100: =Model!AC186 -> 0.03 | T100: =Model!J186 -> 0.029405166 | U100: =Model!O186 -> 0.025876388 | V100: =Model!T186 -> 0.027959446 | W100: =Model!Y186 -> 0.037439868 | X100: =Model!AD186 -> 0.038210317 | Y100: =Model!AE186 -> 0.028 | Z100: =Model!AF186 -> 0.028 | AA100: =Model!AG186 -> 0.028
C101: Cash Conversion Cycle | G101: =G98+G99-G100 -> #DIV/0! | H101: =H98+H99-H100 -> #DIV/0! | I101: =I98+I99-I100 -> #DIV/0! | J101: =J98+J99-J100 -> #DIV/0! | K101: =K98+K99-K100 -> #DIV/0! | L101: =L98+L99-L100 -> 45.97 | M101: =M98+M99-M100 -> 47.97 | N101: =N98+N99-N100 -> 47.97 | ... R101: =R98+R99-R100 -> 47.97 | T101: =T98+T99-T100 -> #DIV/0! | U101: =U98+U99-U100 -> #DIV/0! | V101: =V98+V99-V100 -> #DIV/0! | W101: =W98+W99-W100 -> #DIV/0! | X101: =X98+X99-X100 -> #DIV/0! | Y101: =Y98+Y99-Y100 -> 54.972 | Z101: =Z98+Z99-Z100 -> 54.972 | AA101: =AA98+AA99-AA100 -> 54.972
C103: Liquidity
C104: Current Ratio | G104: =IF(ISERROR(G38/G51),"NA",(G38/G51)) -> 3.7645472 | H104: =IF(ISERROR(H38/H51),"NA",(H38/H51)) -> 3.1283037 | I104: =IF(ISERROR(I38/I51),"NA",(I38/I51)) -> 2.71195 | J104: =IF(ISERROR(J38/J51),"NA",(J38/J51)) -> 2.1633933 | K104: =IF(ISERROR(K38/K51),"NA",(K38/K51)) -> 2.766024 | L104: =IF(ISERROR(L38/L51),"NA",(L38/L51)) -> 2.0170268 | M104: =IF(ISERROR(M38/M51),"NA",(M38/M51)) -> 2.0223863 | N104: =IF(ISERROR(N38/N51),"NA",(N38/N51)) -> 2.0177587 | ... R104: =IF(ISERROR(R38/R51),"NA",(R38/R51)) -> 2.3068695 | T104: =IF(ISERROR(T38/T51),"NA",(T38/T51)) -> 2.8626902 | U104: =IF(ISERROR(U38/U51),"NA",(U38/U51)) -> 2.5069438 | V104: =IF(ISERROR(V38/V51),"NA",(V38/V51)) -> 2.1633933 | W104: =IF(ISERROR(W38/W51),"NA",(W38/W51)) -> 2.0177587 | X104: =IF(ISERROR(X38/X51),"NA",(X38/X51)) -> 2.3068695 | Y104: =IF(ISERROR(Y38/Y51),"NA",(Y38/Y51)) -> 3.6527778 | Z104: =IF(ISERROR(Z38/Z51),"NA",(Z38/Z51)) -> 5.0473218 | AA104: =IF(ISERROR(AA38/AA51),"NA",(AA38/AA51)) -> 8.4109502
C105: Quick Ratio | G105: =IF(ISERROR((G34+G35)/G51),"NA",((G34+G35)/G51)) -> 1.9502213 | H105: =IF(ISERROR((H34+H35)/H51),"NA",((H34+H35)/H51)) -> 1.4585431 | I105: =IF(ISERROR((I34+I35)/I51),"NA",((I34+I35)/I51)) -> 1.2208628 | J105: =IF(ISERROR((J34+J35)/J51),"NA",((J34+J35)/J51)) -> 1.1468218 | K105: =IF(ISERROR((K34+K35)/K51),"NA",((K34+K35)/K51)) -> 1.5817498 | L105: =IF(ISERROR((L34+L35)/L51),"NA",((L34+L35)/L51)) -> 0.81067756 | M105: =IF(ISERROR((M34+M35)/M51),"NA",((M34+M35)/M51)) -> 0.81603706 | N105: =IF(ISERROR((N34+N35)/N51),"NA",((N34+N35)/N51)) -> 0.75109205 | ... R105: =IF(ISERROR((R34+R35)/R51),"NA",((R34+R35)/R51)) -> 1.0402028 | T105: =IF(ISERROR((T34+T35)/T51),"NA",((T34+T35)/T51)) -> 1.0924896 | U105: =IF(ISERROR((U34+U35)/U51),"NA",((U34+U35)/U51)) -> 1.114329 | V105: =IF(ISERROR((V34+V35)/V51),"NA",((V34+V35)/V51)) -> 1.1468218 | W105: =IF(ISERROR((W34+W35)/W51),"NA",((W34+W35)/W51)) -> 0.75109205 | X105: =IF(ISERROR((X34+X35)/X51),"NA",((X34+X35)/X51)) -> 1.0402028 | Y105: =IF(ISERROR((Y34+Y35)/Y51),"NA",((Y34+Y35)/Y51)) -> 0.80106678 | Z105: =IF(ISERROR((Z34+Z35)/Z51),"NA",((Z34+Z35)/Z51)) -> 1.2011679 | AA105: =IF(ISERROR((AA34+AA35)/AA51),"NA",((AA34+AA35)/AA51)) -> 2.667707
C106: Cash Ratio | G106: =IF(ISERROR(G34/G51),"NA",(G34/G51)) -> 1.0173834 | H106: =IF(ISERROR(H34/H51),"NA",(H34/H51)) -> 0.79302322 | I106: =IF(ISERROR(I34/I51),"NA",(I34/I51)) -> 0.73564072 | J106: =IF(ISERROR(J34/J51),"NA",(J34/J51)) -> 0.79959808 | K106: =IF(ISERROR(K34/K51),"NA",(K34/K51)) -> 0.97036414 | L106: =IF(ISERROR(L34/L51),"NA",(L34/L51)) -> 0.40949144 | M106: =IF(ISERROR(M34/M51),"NA",(M34/M51)) -> 0.40195838 | N106: =IF(ISERROR(N34/N51),"NA",(N34/N51)) -> 0.31630945 | ... R106: =IF(ISERROR(R34/R51),"NA",(R34/R51)) -> 0.60542022 | T106: =IF(ISERROR(T34/T51),"NA",(T34/T51)) -> 0.65586737 | U106: =IF(ISERROR(U34/U51),"NA",(U34/U51)) -> 0.73251248 | V106: =IF(ISERROR(V34/V51),"NA",(V34/V51)) -> 0.79959808 | W106: =IF(ISERROR(W34/W51),"NA",(W34/W51)) -> 0.31630945 | X106: =IF(ISERROR(X34/X51),"NA",(X34/X51)) -> 0.60542022 | Y106: =IF(ISERROR(Y34/Y51),"NA",(Y34/Y51)) -> 0.22812028 | Z106: =IF(ISERROR(Z34/Z51),"NA",(Z34/Z51)) -> 0.47672114 | AA106: =IF(ISERROR(AA34/AA51),"NA",(AA34/AA51)) -> 1.6495656
A110: x

Sheet Model Output
B1: =Company_Name&" "&"("&Ticker&")"&" Valuation Overview" -> Evercore Inc. (EVR) Valuation Overview | K1: Price Target Scenario: | N1: =Case_Scenario&" Case" -> Base Case | R1: Base Case Check | S1: =IF(N1="Base Case","","Check!") | Y1: P/E
B2: =Cover!C2 -> $ in Thousands Except Per Share Data | K2: Current Share Price: | O2: =Share_Price -> 341.19 | Y2: EV/EBITDA
K3: Valuation Date: | O3: =Current_Date -> 46150
B4: ="Multiples Analysis "&"("&S21&")" -> Multiples Analysis (P/E) | I4: Return Summary
I6: Exit Multiple Method
I7: =Cover!I9 -> Implied Enterprise Value: | N7: =Cover!L9 -> 19330394
I8: =Cover!I10 -> Implied Equity Value: | N8: =Cover!L10 -> 19286441
I9: =Cover!I12 -> Implied Share Price: | N9: =Cover!L12 -> 457.77315
I10: =Cover!I13 -> % Return: | N10: =Cover!L13 -> 0.34169568
I12: =Cover!I15 -> Perpetuity Growth Method
I13: =Cover!I16 -> Implied Enterprise Value: | N13: =Cover!L16 -> 23818873
I14: =Cover!I17 -> Implied Equity Value: | N14: =Cover!L17 -> 23774919
I15: =Cover!I19 -> Implied Share Price: | N15: =Cover!L19 -> 564.30939
I16: =Cover!I20 -> % Return: | N16: =Cover!L20 -> 0.6539447
E18: Annuals | M18: CAGR | O18: CAGR
B19: Consolidated Financials | E19: =Summary!U6 -> 2024 | F19: =Summary!V6 -> 2025 | G19: =Summary!W6 -> 2026e | H19: =Summary!X6 -> 2027e | I19: =Summary!Y6 -> 2028e | J19: =Summary!Z6 -> 2029e | K19: =Summary!AA6 -> 2030e | M19: Historical | O19: Projected
B21: =Summary!C8 -> Revenue | D21: =Summary!T8 -> 2442666 | E21: =Summary!U8 -> 2996361 | F21: =Summary!V8 -> 3880084 | G21: =Summary!W8 -> 6774791.7 | H21: =Summary!X8 -> 7663353.4 | I21: =Summary!Y8 -> 7894057.8 | J21: =Summary!Z8 -> 7727144.5 | K21: =Summary!AA8 -> 7330353.4 | M21: =Summary!AC8 -> 0.26034232 | O21: =Summary!AE8 -> 0.13568204 | R21: Multiple Toggle | S21: P/E
B22: =Summary!C9 -> YoY % Growth | E22: =Summary!U9 -> 0.22667651 | F22: =Summary!V9 -> 0.29493209 | G22: =Summary!W9 -> 0.74604253 | H22: =Summary!X9 -> 0.13115705 | I22: =Summary!Y9 -> 0.030104886 | J22: =Summary!Z9 -> -0.02114417 | K22: =Summary!AA9 -> -0.05135028
R23: Multiples Analysis | S23: EV/EBITDA | T23: P/E | U23: Chart
B24: =Summary!C11 -> Gross Profit | D24: =Summary!T11 -> 2442666 | E24: =Summary!U11 -> 2996361 | F24: =Summary!V11 -> 3880084 | G24: =Summary!W11 -> 6774791.7 | H24: =Summary!X11 -> 7663353.4 | I24: =Summary!Y11 -> 7894057.8 | J24: =Summary!Z11 -> 7727144.5 | K24: =Summary!AA11 -> 7330353.4 | M24: =Summary!AC11 -> 0.26034232 | O24: =Summary!AE11 -> 0.13568204 | R24: Entry Multiple | S24: =Valuation!D12 -> 12.1 | T24: =Valuation!D11 -> 16.6 | U24: =IF($S$21=$S$23,S24,T24) -> 16.6
B25: =Summary!C12 -> % Margin | E25: =Summary!U12 -> 1 | F25: =Summary!V12 -> 1 | G25: =Summary!W12 -> 1 | H25: =Summary!X12 -> 1 | I25: =Summary!Y12 -> 1 | J25: =Summary!Z12 -> 1 | K25: =Summary!AA12 -> 1 | R25: =Model!Y25 -> 2026e | S25: =(Comparables!H10*S30)/(Model!Y62) -> 0.00014501507 | T25: =(Comparables!$G$10*S30)/Summary!W19 -> 8.4881791 | U25: =IF($S$21=$S$23,S25,T25) -> 8.4881791
B26: =Summary!C13 -> YoY % Growth | E26: =Summary!U13 -> 0.22667651 | F26: =Summary!V13 -> 0.29493209 | G26: =Summary!W13 -> 0.74604253 | H26: =Summary!X13 -> 0.13115705 | I26: =Summary!Y13 -> 0.030104886 | J26: =Summary!Z13 -> -0.02114417 | K26: =Summary!AA13 -> -0.05135028 | R26: =Summary!AA6 -> 2030e | S26: =(Comparables!H10*S30)/(Model!AG62) -> 0.00011126291 | T26: =(Comparables!$G$10*S30)/Summary!AA19 -> 6.7250515 | U26: =IF($S$21=$S$23,S26,T26) -> 6.7250515
R27: Exit Multiple | S27: =Valuation!K60 -> 9 | T27: =Valuation!K72/Summary!AA19 -> 12.651052 | U27: =IF($S$21=$S$23,S27,T27) -> 12.651052
B28: =Summary!C27 -> EBITDA | D28: =Summary!T27 -> 400200 | E28: =Summary!U27 -> 568150 | F28: =Summary!V27 -> 846763 | G28: =Summary!W27 -> 1573746.8 | H28: =Summary!X27 -> 1743237.2 | I28: =Summary!Y27 -> 1817103.6 | J28: =Summary!Z27 -> 1661971.8 | K28: =Summary!AA27 -> 2051150.7 | M28: =Summary!AC27 -> 0.45459602 | O28: =Summary!AE27 -> 0.19356793 | R28: Implied PGM | S28: =Valuation!K79 -> 12.372456 | T28: =Valuation!R72/Summary!AA19 -> 15.595296 | U28: =IF($S$21=$S$23,S28,T28) -> 15.595296
B29: =Summary!C28 -> Margin | E29: =Summary!U28 -> 0.18961333 | F29: =Summary!V28 -> 0.21823316 | G29: =Summary!W28 -> 0.23229449 | H29: =Summary!X28 -> 0.22747707 | I29: =Summary!Y28 -> 0.23018625 | J29: =Summary!Z28 -> 0.21508227 | K29: =Summary!AA28 -> 0.27981608
B30: =Summary!C29 -> YoY % Growth | E30: =Summary!U17 -> 0.44653215 | F30: =Summary!V17 -> 0.49757763 | G30: =Summary!W29 -> 0.85854456 | H30: =Summary!X29 -> 0.10769867 | I30: =Summary!Y29 -> 0.042373102 | J30: =Summary!Z29 -> -0.085373115 | K30: =Summary!AA29 -> 0.234167 | R30: Financials Multiplier | S30: =IF($B$2="$ in Millions Except Per Share Data",1,IF($B$2="$ in Thousands Except Per Share Data",1000,IF($B$2="$ in Billions Except Per Share Data",0.001,0))) -> 1000
B32: =Summary!C19 -> Net Income (Loss) | D32: =Summary!T19 -> 285223 | E32: =Summary!U19 -> 417737 | F32: =Summary!V19 -> 640707 | G32: =Summary!W19 -> 1207832 | H32: =Summary!X19 -> 1340072.4 | I32: =Summary!Y19 -> 1358063.9 | J32: =Summary!Z19 -> 1231468.3 | K32: =Summary!AA19 -> 1524493 | M32: =Summary!AC19 -> 0.49877853 | O32: =Summary!AE19 -> 0.18930486
B33: =Summary!C20 -> Margin | E33: =Summary!U20 -> 0.13941478 | F33: =Summary!V20 -> 0.1651271 | G33: =Summary!W20 -> 0.17828326 | H33: =Summary!X20 -> 0.17486763 | I33: =Summary!Y20 -> 0.17203623 | J33: =Summary!Z20 -> 0.15936913 | K33: =Summary!AA20 -> 0.20796992
B34: =Summary!C21 -> YoY % Growth | E34: =Summary!U21 -> 0.46459788 | F34: =Summary!V21 -> 0.53375689 | G34: =Summary!W21 -> 0.88515493 | H34: =Summary!X21 -> 0.10948583 | I34: =Summary!Y21 -> 0.013425749 | J34: =Summary!Z21 -> -0.093217719 | K34: =Summary!AA21 -> 0.23794743
B36: =Summary!C23 -> Adj. EPS (Diluted) | D36: =Summary!T23 -> 6.3712063 | E36: =Summary!U23 -> 9.0832013 | F36: =Summary!V23 -> 14.04956 | G36: =Summary!W23 -> 25.791307 | H36: =Summary!X23 -> 27.030169 | I36: =Summary!Y23 -> 27.91209 | J36: =Summary!Z23 -> 25.962366 | K36: =Summary!AA23 -> 33.296064 | M36: =Summary!AC23 -> 0.48497973 | O36: =Summary!AE23 -> 0.18835456
B37: =Summary!C24 -> YoY % Growth | E37: =Summary!U24 -> 0.42566429 | F37: =Summary!V24 -> 0.54676301 | G37: =Summary!W24 -> 0.83573773 | H37: =Summary!X24 -> 0.048034115 | I37: =Summary!Y24 -> 0.032627265 | J37: =Summary!Z24 -> -0.069852314 | K37: =Summary!AA24 -> 0.2824742
B39: Free Cash Flow | D39: =Model!J114 -> -71792 | E39: =Model!O114 -> 351405 | F39: =Model!T114 -> 466034 | G39: =Model!Y114 -> 824785.44 | H39: =Model!AD114 -> 1135711 | I39: =Model!AE114 -> 1308047.6 | J39: =Model!AF114 -> 1203739.3 | K39: =Model!AG114 -> 1539595.6 | M39: =IFERROR((F39/D39)^(1/2)-1,"N/A") -> N/A | O39: =IFERROR((K39/G39)^(1/4)-1,"N/A") -> 0.16887056
B40: YoY % Growth | E40: =E39/D39-1 -> -5.8947654 | F40: =F39/E39-1 -> 0.32620196 | G40: =G39/F39-1 -> 0.7697967 | H40: =H39/G39-1 -> 0.37697754 | I40: =I39/H39-1 -> 0.15174331 | J40: =J39/I39-1 -> -0.079743506 | K40: =K39/J39-1 -> 0.27901086
E42: Annuals | M42: Average | O42: Average
B43: Capitalization and Key Ratios | E43: =E19 -> 2024 | F43: =F19 -> 2025 | G43: =G19 -> 2026e | H43: =H19 -> 2027e | I43: =I19 -> 2028e | J43: =J19 -> 2029e | K43: =K19 -> 2030e | M43: Historical | O43: Projected
B44: =Summary!C91 -> Leverage
B45: =Summary!C92 -> Total Debt / EBITDA | D45: =Summary!T92 -> 0.93424538 | E45: =Summary!U92 -> 0.65809205 | F45: =Summary!V92 -> 0.63800969 | G45: =Summary!W92 -> 0.34297068 | H45: =Summary!X92 -> 0.3095098 | I45: =Summary!Y92 -> 0.44714158 | J45: =Summary!Z92 -> 0.32392187 | K45: =Summary!AA92 -> 0.26216942 | M45: =AVERAGE(D45:F45) -> 0.74344904 | O45: =AVERAGE(G45:K45) -> 0.33714267
B46: =Summary!C93 -> Total Debt / Equity | D46: =Summary!T93 -> 0.20975433 | E46: =Summary!U93 -> 0.19254993 | F46: =Summary!V93 -> 0.23287681 | G46: =Summary!W93 -> 0.18390328 | H46: =Summary!X93 -> 0.1266531 | I46: =Summary!Y93 -> 0.1416723 | J46: =Summary!Z93 -> 0.076249531 | K46: =Summary!AA93 -> 0.062275462 | M46: =AVERAGE(D46:F46) -> 0.21172703 | O46: =AVERAGE(G46:K46) -> 0.11815073
B47: =Summary!C94 -> Total Debt / Total Assets | D47: =Summary!T94 -> 0.10096001 | E47: =Summary!U94 -> 0.089577767 | F47: =Summary!V94 -> 0.1008274 | G47: =Summary!W94 -> 0.080788577 | H47: =Summary!X94 -> 0.064250248 | I47: =Summary!Y94 -> 0.087426531 | J47: =Summary!Z94 -> 0.05451207 | K47: =Summary!AA94 -> 0.049210748 | M47: =AVERAGE(D47:F47) -> 0.097121726 | O47: =AVERAGE(G47:K47) -> 0.067237635
B49: =Summary!C103 -> Liquidity
B50: =Summary!C104 -> Current Ratio | D50: =Summary!T104 -> 2.8626902 | E50: =Summary!U104 -> 2.5069438 | F50: =Summary!V104 -> 2.1633933 | G50: =Summary!W104 -> 2.0177587 | H50: =Summary!X104 -> 2.3068695 | I50: =Summary!Y104 -> 3.6527778 | J50: =Summary!Z104 -> 5.0473218 | K50: =Summary!AA104 -> 8.4109502 | M50: =AVERAGE(D50:F50) -> 2.5110091 | O50: =AVERAGE(G50:K50) -> 4.2871356
B51: =Summary!C105 -> Quick Ratio | D51: =Summary!T105 -> 1.0924896 | E51: =Summary!U105 -> 1.114329 | F51: =Summary!V105 -> 1.1468218 | G51: =Summary!W105 -> 0.75109205 | H51: =Summary!X105 -> 1.0402028 | I51: =Summary!Y105 -> 0.80106678 | J51: =Summary!Z105 -> 1.2011679 | K51: =Summary!AA105 -> 2.667707 | M51: =AVERAGE(D51:F51) -> 1.1178801 | O51: =AVERAGE(G51:K51) -> 1.2922473
B52: =Summary!C106 -> Cash Ratio | D52: =Summary!T106 -> 0.65586737 | E52: =Summary!U106 -> 0.73251248 | F52: =Summary!V106 -> 0.79959808 | G52: =Summary!W106 -> 0.31630945 | H52: =Summary!X106 -> 0.60542022 | I52: =Summary!Y106 -> 0.22812028 | J52: =Summary!Z106 -> 0.47672114 | K52: =Summary!AA106 -> 1.6495656 | M52: =AVERAGE(D52:F52) -> 0.72932597 | O52: =AVERAGE(G52:K52) -> 0.65522733
B54: =Summary!C75 -> Profitability
B55: =Summary!C80 -> Return on Assets (ROA) | D55: =Summary!T80 -> 0.077018647 | E55: =Summary!U80 -> 0.10008143 | F55: =Summary!V80 -> 0.11957734 | G55: =Summary!W80 -> 0.18078593 | H55: =Summary!X80 -> 0.1595777 | I55: =Summary!Y80 -> 0.14612977 | J55: =Summary!Z80 -> 0.12469585 | K55: =Summary!AA80 -> 0.13951015 | M55: =AVERAGE(D55:F55) -> 0.098892474 | O55: =AVERAGE(G55:K55) -> 0.15013988
B56: =Summary!C81 -> Return on Equity (ROE) | D56: =Summary!T81 -> 0.1600138 | E56: =Summary!U81 -> 0.21512786 | F56: =Summary!V81 -> 0.27618276 | G56: =Summary!W81 -> 0.4115325 | H56: =Summary!X81 -> 0.31456702 | I56: =Summary!Y81 -> 0.2367993 | J56: =Summary!Z81 -> 0.17442009 | K56: =Summary!AA81 -> 0.17654799 | M56: =AVERAGE(D56:F56) -> 0.21710814 | O56: =AVERAGE(G56:K56) -> 0.26277338
B57: Return on Inv. Capital (ROIC) | D57: =Summary!T82 -> 0.13226967 | E57: =Summary!U82 -> 0.18039317 | F57: =Summary!V82 -> 0.22401489 | G57: =Summary!W82 -> 0.34760652 | H57: =Summary!X82 -> 0.27920486 | I57: =Summary!Y82 -> 0.20741442 | J57: =Summary!Z82 -> 0.16206287 | K57: =Summary!AA82 -> 0.16619794 | M57: =AVERAGE(D57:F57) -> 0.17889257 | O57: =AVERAGE(G57:K57) -> 0.23249732
B59: =Summary!C84 -> Coverage
B60: Interest Expense | D60: =Summary!T85 -> 16717 | E60: =Summary!U85 -> 16768 | F60: =Summary!V85 -> 24264 | G60: =Summary!W85 -> 36421.599 | H60: =Summary!X85 -> 24283.08 | I60: =Summary!Y85 -> 27396.651 | J60: =Summary!Z85 -> 27372.651 | K60: =Summary!AA85 -> 21521.96 | M60: =AVERAGE(D60:F60) -> 19249.667 | O60: =AVERAGE(G60:K60) -> 27399.188
B61: Capital Expenditures | D61: =Summary!T86 -> 55838 | E61: =Summary!U86 -> 38792 | F61: =Summary!V86 -> 74002 | G61: =Summary!W86 -> 83717.84 | H61: =Summary!X86 -> 114950.3 | I61: =Summary!Y86 -> 118410.87 | J61: =Summary!Z86 -> 115907.17 | K61: =Summary!AA86 -> 109955.3 | M61: =AVERAGE(D61:F61) -> 56210.667 | O61: =AVERAGE(G61:K61) -> 108588.3
B62: EBIT / Interest | D62: =Summary!T87 -> 22.483221 | E62: =Summary!U87 -> 32.423783 | F62: =Summary!V87 -> 33.556133 | G62: =Summary!W87 -> 42.136244 | H62: =Summary!X87 -> 71.634561 | I62: =Summary!Y87 -> 65.647978 | J62: =Summary!Z87 -> 59.631469 | K62: =Summary!AA87 -> 93.521831 | M62: =AVERAGE(D62:F62) -> 29.487712 | O62: =AVERAGE(G62:K62) -> 66.514417
B63: EBITDA / Interest | D63: =Summary!T88 -> 23.939702 | E63: =Summary!U88 -> 33.882991 | F63: =Summary!V88 -> 34.897915 | G63: =Summary!W88 -> 43.209162 | H63: =Summary!X88 -> 71.788142 | I63: =Summary!Y88 -> 66.325756 | J63: =Summary!Z88 -> 60.716508 | K63: =Summary!AA88 -> 95.305015 | M63: =AVERAGE(D63:F63) -> 30.906869 | O63: =AVERAGE(G63:K63) -> 67.468917
B64: (EBITDA - CapEx) / Interest | D64: =Summary!T89 -> 20.599509 | E64: =Summary!U89 -> 31.569537 | F64: =Summary!V89 -> 31.848046 | G64: =Summary!W89 -> 40.910585 | H64: =Summary!X89 -> 67.054381 | I64: =Summary!Y89 -> 62.003663 | J64: =Summary!Z89 -> 56.482093 | K64: =Summary!AA89 -> 90.196034 | M64: =AVERAGE(D64:F64) -> 28.005698 | O64: =AVERAGE(G64:K64) -> 63.329351
B66: =Summary!C96 -> Efficiency
B67: =Summary!C97 -> Asset Turnover | D67: =Summary!T97 -> 0.65959207 | E67: =Summary!U97 -> 0.71786819 | F67: =Summary!V97 -> 0.72415337 | G67: =Summary!W97 -> 1.0140376 | H67: =Summary!X97 -> 0.91256282 | I67: =Summary!Y97 -> 0.84941281 | J67: =Summary!Z97 -> 0.78243414 | K67: =Summary!AA97 -> 0.67081887 | M67: =AVERAGE(D67:F67) -> 0.70053788 | O67: =AVERAGE(G67:K67) -> 0.84585325
B68: =Summary!C98 -> Days Sales Outstanding | D68: =Summary!T98 -> 59.375076 | E68: =Summary!U98 -> 51.918527 | F68: =Summary!V98 -> 50.668867 | G68: =Summary!W98 -> 46.516124 | H68: =Summary!X98 -> 56.737203 | I68: =Summary!Y98 -> 55 | J68: =Summary!Z98 -> 55 | K68: =Summary!AA98 -> 55 | M68: =AVERAGE(D68:F68) -> 53.98749 | O68: =AVERAGE(G68:K68) -> 53.650665
B69: =Summary!C99 -> Days Inventory Outstanding | D69: =Summary!T99 -> #DIV/0! | E69: =Summary!U99 -> #DIV/0! | F69: =Summary!V99 -> #DIV/0! | G69: =Summary!W99 -> #DIV/0! | H69: =Summary!X99 -> #DIV/0! | I69: =Summary!Y99 -> 0 | J69: =Summary!Z99 -> 0 | K69: =Summary!AA99 -> 0 | M69: =AVERAGE(D69:F69) -> #DIV/0! | O69: =AVERAGE(G69:K69) -> #DIV/0!
B70: =Summary!C100 -> Accounts Payable as a % of Sales | D70: =Summary!T100 -> 0.029405166 | E70: =Summary!U100 -> 0.025876388 | F70: =Summary!V100 -> 0.027959446 | G70: =Summary!W100 -> 0.037439868 | H70: =Summary!X100 -> 0.038210317 | I70: =Summary!Y100 -> 0.028 | J70: =Summary!Z100 -> 0.028 | K70: =Summary!AA100 -> 0.028 | M70: =AVERAGE(D70:F70) -> 0.027747 | O70: =AVERAGE(G70:K70) -> 0.031930037
B71: =Summary!C101 -> Cash Conversion Cycle | D71: =Summary!T101 -> #DIV/0! | E71: =Summary!U101 -> #DIV/0! | F71: =Summary!V101 -> #DIV/0! | G71: =Summary!W101 -> #DIV/0! | H71: =Summary!X101 -> #DIV/0! | I71: =Summary!Y101 -> 54.972 | J71: =Summary!Z101 -> 54.972 | K71: =Summary!AA101 -> 54.972 | M71: =AVERAGE(D71:F71) -> #DIV/0! | O71: =AVERAGE(G71:K71) -> #DIV/0!

Sheet Football Field
C1: =Company_Name&" - "&MID(CELL("filename",A1),FIND("]",CELL("filename",A1))+1,255)&": "&Case_Scenario&" Case" -> Evercore Inc. - Football Field: Base Case
C2: =Cover!C2 -> $ in Thousands Except Per Share Data
A4: x | O4: Valuation Method: | T4: Downside | U4: Delta | V4: Upside | W4: x
O5: =TEXT(Valuation!E108,"0.0%")&" - "&TEXT(Valuation!E110,"0.0%")&" WACC"&" & "&TEXT(Valuation!G106,"0.0%")&" - "&TEXT(Valuation!I106,"0.0%")&" PGR" -> 9.5% - 10.5% WACC & 1.5% - 2.5% PGR | T5: =Valuation!G108 -> 564.098 | U5: =V5-T5 -> 30.880249 | V5: =Valuation!I110 -> 594.97825
O6: =TEXT(Valuation!E100,"0.0%")&" - "&TEXT(Valuation!E102,"0.0%")&" WACC"&" & "&TEXT(Valuation!G98,"0.0x")&" - "&TEXT(Valuation!I98,"0.0x")&" Exit Multiple" -> 9.5% - 10.5% WACC & 8.0x - 10.0x Exit Multiple | T6: =Valuation!G100 -> 443.18419 | U6: =V6-T6 -> 50.182879 | V6: =Valuation!I102 -> 493.36707
O8: =Valuation!F184&": "&TEXT(Valuation!G185,"0.0x")&" - "&TEXT(Valuation!I185,"0.0x") -> NTM EV/EBITDA Spread to Comps: 8.4x - 10.4x | T8: =Valuation!G187 -> 150.76659 | U8: =V8-T8 -> 78.050565 | V8: =Valuation!I189 -> 228.81716
O9: =Valuation!F176&": "&TEXT(Valuation!G177,"0.0x")&" - "&TEXT(Valuation!I177,"0.0x") -> NTM EV/EBITDA: 10.6x - 12.6x | T9: =Valuation!G179 -> 191.12288 | U9: =V9-T9 -> 87.018628 | V9: =Valuation!I181 -> 278.14151
O10: =Valuation!F168&": "&TEXT(Valuation!G169,"0.0x")&" - "&TEXT(Valuation!I169,"0.0x") -> NTM P/E Spread to Comps: 13.3x - 15.3x | T10: =Valuation!G171 -> 361.02434 | U10: =V10-T10 -> 146.50724 | V10: =Valuation!I173 -> 507.53158
O11: =Valuation!F160&": "&TEXT(Valuation!G161,"0.0x")&" - "&TEXT(Valuation!I161,"0.0x") -> NTM P/E: 14.6x - 16.6x | T11: =Valuation!G163 -> 397.10342 | U11: =V11-T11 -> 154.52482 | V11: =Valuation!I165 -> 551.62824
O13: =Valuation!F260&": "&TEXT(Valuation!G261,"0.0x")&" - "&TEXT(Valuation!I261,"0.0x") -> 2009-2018 Early Cycle EV/EBITDA Spread to Comps: 9.9x - 11.9x | T13: =Valuation!G263 -> 178.19658 | U13: =V13-T13 -> 36.257762 | V13: =Valuation!I263 -> 214.45434
O14: =Valuation!F252&": "&TEXT(Valuation!G253,"0.0x")&" - "&TEXT(Valuation!I253,"0.0x") -> 2009-2018 Early Cycle EV/EBITDA: 5.9x - 7.9x | T14: =Valuation!G255 -> 106.58655 | U14: =V14-T14 -> 36.257762 | V14: =Valuation!I255 -> 142.84431
O15: =Valuation!F244&": "&TEXT(Valuation!G245,"0.0x")&" - "&TEXT(Valuation!I245,"0.0x") -> 2009-2018 Early Cycle P/E Spread to Comps: 23.5x - 25.5x | T15: =Valuation!G247 -> 637.05295 | U15: =V15-T15 -> 54.228775 | V15: =Valuation!I247 -> 691.28172
O16: =Valuation!F236&": "&TEXT(Valuation!G237,"0.0x")&" - "&TEXT(Valuation!I237,"0.0x") -> 2009-2018 Early Cycle P/E: 17.9x - 19.9x | T16: =Valuation!G239 -> 485.10605 | U16: =V16-T16 -> 54.228775 | V16: =Valuation!I239 -> 539.33482
O18: 52-Week Price Range: | T18: =Share_Price_Low -> 215.26 | U18: =V18-T18 -> 173.45 | V18: =Share_Price_High -> 388.71
O19: Median Value: | T19: =MEDIAN(T5:T18) -> 361.02434 | U19: =MEDIAN(U5:U18) -> 54.228775 | V19: =MEDIAN(V5:V18) -> 493.36707
A20: x | O20: Implied Return (%): | T20: =T19/Share_Price-1 -> 0.058132817 | V20: =V19/Share_Price-1 -> 0.44601855
T22: Reference Points for Price Axis
U24: Price
A25: x | T25: High | U25: =MAX(V5:V18)*1.1 -> 760.4099 | W25: x
T26: Low | U26: =MIN(T5:T18)*0.9 -> 95.927891
A30: x

Sheet Integrity
C1: =Company_Name&" - "&MID(CELL("filename",A1),FIND("]",CELL("filename",A1))+1,255) -> Evercore Inc. - Integrity
C3: Integrity
C4: Metric
C6: Model:
C7: Balance Sheet Check: | D7: =SUM(Model!F160:AG160) -> 0
C8: Base Case: | D8: =IF(Case_Scenario="Base","OK!","Check!") -> OK!
C9: Interest Expense: | D9: =IF(Model!C8="On","OK!","CHECK - OFF") -> OK!
C10: Valuation Date:
C12: Formatting:
C13: Valuation Sensitivity Tables: | D13: =SUM(Valuation!F92,Valuation!K92,Valuation!P92,Valuation!F151:F155,Valuation!L151:L155,Valuation!F227:F231,Valuation!L227:L231) -> -7.639249
C14: WACC Tables: | D14: =SUM(WACC!Q20,WACC!N33:N37) -> 0
C16: Font Toggles:
C17: Cover: | D17: =Cover!$Q$2 -> Report
C18: Revenue Build: | D18: ='Revenue Build'!$C$22 -> Report
C19: Model: | D19: =Model!$C$5 -> Report
C20: WACC | D20: =WACC!R5 -> Report
C21: Valuation: | D21: =Valuation!$R$2 -> Report
C23: Change Log
C24: Date | D24: Version | E24: Operator | F24: Revisions
C25: 44476 | D25: v01 | E25: Nate Latimer | F25: Top Down / Bottom Up toggle integration and Capital IQ comps sheet w/ ID Locator
C26: 44476 | D26: v02 | E26: Carson Shaner | F26: Formulas for EBIT/EBITDA margins on earnings sheets
C27: 44480 | D27: v03 | E27: Nate Latimer | F27: Historical driver adjustments to reflect Top Down / Bottom Up Toggle
C28: 44488 | D28: v04 | E28: Nate Latimer | F28: Bug fixes to model output, comps sheet and WACC Comps Relevered Beta
C29: 44489 | D29: v05 | E29: Lilianna Ruby | F29: Changed the year end driver in 2021 and 2022 to correctly pull operating margins
C30: 44491 | D30: v06 | E30: Lilianna Ruby | F30: Changed the first page to add 365 to your previous fiscal year
C31: 44496 | D31: v07 | E31: Carson Shaner | F31: Changed Model Output FCF formula, broke apart D&A for historical periods, added checks for EPS & EBITDA in Valuation sensitivity tables, added segment D&A breakdown, linked and fixed SOTP valuation
C32: 44503 | D32: v08 | E32: Lilianna Ruby | F32: Changed average of comps on valuation tab to average all peers not just the first one
C33: 44512 | D33: v09 | E33: Lilianna Ruby | F33: Rolled model forward to reflect 3Q'21. Also changed the multiples tab so the quarters roll forward and end on correct date.
C34: 44522 | D34: v10 | E34: Lilianna Ruby | F34: Fully fixed the multiples tab so it is automatic and fully functional. Also fixed definition of NTM_EPS and NTM_EBITDA
C35: 44582 | D35: v13 | E35: Carson Shaner | F35: Changed EPS, EBITDA, shares, tax rate, etc., to formulas so we do not have to hardcode them.
C36: 44584 | D36: v14 | E36: Lilianna Ruby | F36: Changed discount factor to mid year
... C47: 45581 | D47: v25 | E47: Conor McCabe | F47: Added font toggle to integrity tab for WACC tab. Formatted Comparables Tab.

Sheet Revenue Build
C1: =Company_Name&" - "&MID(CELL("filename",A1),FIND("]",CELL("filename",A1))+1,255)&": "&Case_Scenario&" Case" -> Evercore Inc. - Revenue Build: Base Case
C2: =Cover!C2 -> $ in Thousands Except Per Share Data
A4: x | C4: Segments
C6: =C30&" Methodology" -> Total Company Revenue Methodology
C7: Segment
C8: =C32&" Methodology" -> Investment Banking & Equities Revenue Methodology
C9: =IF(Company_Rev_Methodology="Segment","Segment",IF(Company_Rev_Methodology="Activity-Based","Activity-Based",IF(Company_Rev_Methodology="Backlog","Backlog",IF(Company_Rev_Methodology="Mixed",D9,"--")))) -> Segment | D9: Backlog
C10: =C35&" Methodology" -> Investment Management Revenue Methodology
C11: =IF(Company_Rev_Methodology="Segment","Segment",IF(Company_Rev_Methodology="Activity-Based","Activity-Based",IF(Company_Rev_Methodology="Backlog","Backlog",IF(Company_Rev_Methodology="Mixed",D11,"--")))) -> Segment | D11: Activity-Based
C12: =C38&" Methodology" -> Segment 3 Revenue Methodology
C13: =IF(Company_Rev_Methodology="Segment","Segment",IF(Company_Rev_Methodology="Activity-Based","Activity-Based",IF(Company_Rev_Methodology="Backlog","Backlog",IF(Company_Rev_Methodology="Mixed",D13,"--")))) -> Segment | D13: Segment
C14: =C41&" Methodology" -> Segment 4 Revenue Methodology
C15: =IF(Company_Rev_Methodology="Segment","Segment",IF(Company_Rev_Methodology="Activity-Based","Activity-Based",IF(Company_Rev_Methodology="Backlog","Backlog",IF(Company_Rev_Methodology="Mixed",D15,"--")))) -> Segment | D15: Segment
C16: =C44&" Methodology" -> Segment 5 Revenue Methodology
C17: =IF(Company_Rev_Methodology="Segment","Segment",IF(Company_Rev_Methodology="Activity-Based","Activity-Based",IF(Company_Rev_Methodology="Backlog","Backlog",IF(Company_Rev_Methodology="Mixed",D17,"--")))) -> Segment | D17: Segment
C18: =C47&" Methodology" -> Segment 6 Revenue Methodology
C19: =IF(Company_Rev_Methodology="Segment","Segment",IF(Company_Rev_Methodology="Activity-Based","Activity-Based",IF(Company_Rev_Methodology="Backlog","Backlog",IF(Company_Rev_Methodology="Mixed",D19,"--")))) -> Segment | D19: Segment
C21: Font Toggle
C22: Report
C24: Annual vs. Quarterly
C25: Quarterly
J26: 1 | O26: 2 | T26: 3 | Y26: 4 | AD26: 5 | AE26: 6 | AF26: 7 | AG26: 8
AI27: CAGR
A28: x | C28: Summary | F28: =Model!F$25 -> 1Q23 | G28: =Model!G$25 -> 2Q23 | H28: =Model!H$25 -> 3Q23 | I28: =Model!I$25 -> 4Q23 | J28: =Model!J$25 -> 2023 | K28: =Model!K$25 -> 1Q24 | L28: =Model!L$25 -> 2Q24 | M28: =Model!M$25 -> 3Q24 | ... AG28: =Model!AG$25 -> 2030e | AI28: Historical | AJ28: Projected
C30: Total Company Revenue | F30: ='Segment Analysis'!F7 -> 576314 | G30: ='Segment Analysis'!G7 -> 503600 | H30: ='Segment Analysis'!H7 -> 574404 | I30: ='Segment Analysis'!I7 -> 788348 | J30: ='Segment Analysis'!J7 -> 2442666 | K30: ='Segment Analysis'!K7 -> 585003 | L30: ='Segment Analysis'!L7 -> 693413 | M30: ='Segment Analysis'!M7 -> 738420 | ... U30: ='Segment Analysis'!U7 -> 1400469 | V30: =SUM(V32,V35,V38,V41,V44,V47,) -> 1541864.2 | W30: =SUM(W32,W35,W38,W41,W44,W47,) -> 1718730.9 | X30: =SUM(X32,X35,X38,X41,X44,X47,) -> 2113727.6 | Y30: =SUM(U30:X30) -> 6774791.7 | Z30: =SUM(Z32,Z35,Z38,Z41,Z44,Z47,) -> 1569916.9 | AA30: =SUM(AA32,AA35,AA38,AA41,AA44,AA47,) -> 1730869.9 | AB30: =SUM(AB32,AB35,AB38,AB41,AB44,AB47,) -> 1922407 | AC30: =SUM(AC32,AC35,AC38,AC41,AC44,AC47,) -> 2440159.7 | AD30: =SUM(Z30:AC30) -> 7663353.4 | AE30: =SUM(AE32,AE35,AE38,AE41,AE44,AE47,) -> 7894057.8 | AF30: =SUM(AF32,AF35,AF38,AF41,AF44,AF47,) -> 7727144.5 | AG30: =SUM(AG32,AG35,AG38,AG41,AG44,AG47,) -> 7330353.4 | AI30: =IFERROR((T30/J30)^(1/3)-1,"--") -> 0.16678906 | AJ30: =IFERROR((AG30/T30)^(1/5)-1,"--") -> 0.13568204
C31: =IF($C$25="Quarterly","% Growth QoQ","% Growth YoY") -> % Growth QoQ | G31: =IF($C$25="Annual",'Segment Analysis'!G172,'Segment Analysis'!G192) -> -0.1261708 | H31: =IF($C$25="Annual",'Segment Analysis'!H172,'Segment Analysis'!H192) -> 0.14059571 | I31: =IF($C$25="Annual",'Segment Analysis'!I172,'Segment Analysis'!I192) -> 0.37246259 | K31: =IF($C$25="Annual",'Segment Analysis'!K172,'Segment Analysis'!K192) -> -0.25793812 | L31: =IF($C$25="Annual",'Segment Analysis'!L172,'Segment Analysis'!L192) -> 0.18531529 | M31: =IF($C$25="Annual",'Segment Analysis'!M172,'Segment Analysis'!M192) -> 0.064906484 | N31: =IF($C$25="Annual",'Segment Analysis'!N172,'Segment Analysis'!N192) -> 0.32651472 | O31: =IFERROR(O30/J30-1,"--") -> 0.22667651 | P31: =IFERROR(P30/N30-1,"--") -> -0.28636635 | Q31: =IF($C$25="Annual",'Segment Analysis'!Q172,'Segment Analysis'!Q192) -> 0.198875 | R31: =IF($C$25="Annual",'Segment Analysis'!R172,'Segment Analysis'!R192) -> 0.24814329 | S31: =IF($C$25="Annual",'Segment Analysis'!S172,'Segment Analysis'!S192) -> 0.23999564 | T31: =IFERROR(T30/O30-1,"--") -> 0.29493209 | U31: =IFERROR(U30/S30-1,"--") -> 0.079752326 | V31: =IFERROR(V30/U30-1,"--") -> 0.10096273 | W31: =IFERROR(W30/V30-1,"--") -> 0.1147097 | X31: =IFERROR(X30/W30-1,"--") -> 0.22981877 | Y31: =IFERROR(Y30/T30-1,"--") -> 0.74604253 | Z31: =IFERROR(Z30/X30-1,"--") -> -0.25727569 | AA31: =IFERROR(AA30/Z30-1,"--") -> 0.10252326 | AB31: =IFERROR(AB30/AA30-1,"--") -> 0.11065946 | AC31: =IFERROR(AC30/AB30-1,"--") -> 0.26932523 | AD31: =IFERROR(AD30/Y30-1,"--") -> 0.13115705 | AE31: =IFERROR(AE30/AD30-1,"--") -> 0.030104886 | AF31: =IFERROR(AF30/AE30-1,"--") -> -0.02114417 | AG31: =IFERROR(AG30/AF30-1,"--") -> -0.05135028
C32: ='Segment Analysis'!C8 -> Investment Banking & Equities Revenue | F32: ='Segment Analysis'!F8 -> 554811 | G32: ='Segment Analysis'!G8 -> 482246 | H32: ='Segment Analysis'!H8 -> 552641 | I32: ='Segment Analysis'!I8 -> 766245 | J32: ='Segment Analysis'!J8 -> 2355943 | K32: ='Segment Analysis'!K8 -> 561728 | L32: ='Segment Analysis'!L8 -> 670010 | M32: ='Segment Analysis'!M8 -> 712775 | ... U32: ='Segment Analysis'!U8 -> 1362465 | V32: =IF(Segment1_Rev_Methodology="Segment",V53,IF(Segment1_Rev_Methodology="Activity-Based",V91,IF(Segment1_Rev_Methodology="Backlog",V165,"--"))) -> 1503480.1 | W32: =IF(Segment1_Rev_Methodology="Segment",W53,IF(Segment1_Rev_Methodology="Activity-Based",W91,IF(Segment1_Rev_Methodology="Backlog",W165,"--"))) -> 1679387.3 | X32: =IF(Segment1_Rev_Methodology="Segment",X53,IF(Segment1_Rev_Methodology="Activity-Based",X91,IF(Segment1_Rev_Methodology="Backlog",X165,"--"))) -> 2073203.6 | Y32: =SUM(U32:X32) -> 6618536.1 | Z32: =IF(Segment1_Rev_Methodology="Segment",Z53,IF(Segment1_Rev_Methodology="Activity-Based",Z91,IF(Segment1_Rev_Methodology="Backlog",Z165,"--"))) -> 1528987.7 | AA32: =IF(Segment1_Rev_Methodology="Segment",AA53,IF(Segment1_Rev_Methodology="Activity-Based",AA91,IF(Segment1_Rev_Methodology="Backlog",AA165,"--"))) -> 1689531.4 | AB32: =IF(Segment1_Rev_Methodology="Segment",AB53,IF(Segment1_Rev_Methodology="Activity-Based",AB91,IF(Segment1_Rev_Methodology="Backlog",AB165,"--"))) -> 1880448.4 | AC32: =IF(Segment1_Rev_Methodology="Segment",AC53,IF(Segment1_Rev_Methodology="Activity-Based",AC91,IF(Segment1_Rev_Methodology="Backlog",AC165,"--"))) -> 2397571.7 | AD32: =SUM(Z32:AC32) -> 7496539.2 | AE32: =IF(Segment1_Rev_Methodology="Segment",AE53,IF(Segment1_Rev_Methodology="Activity-Based",AE91,IF(Segment1_Rev_Methodology="Backlog",AE165,"--"))) -> 7743925 | AF32: =IF(Segment1_Rev_Methodology="Segment",AF53,IF(Segment1_Rev_Methodology="Activity-Based",AF91,IF(Segment1_Rev_Methodology="Backlog",AF165,"--"))) -> 7573558.7 | AG32: =IF(Segment1_Rev_Methodology="Segment",AG53,IF(Segment1_Rev_Methodology="Activity-Based",AG91,IF(Segment1_Rev_Methodology="Backlog",AG165,"--"))) -> 7172160.1 | AI32: =IFERROR((T32/J32)^(1/3)-1,"--") -> 0.16126428 | AJ32: =IFERROR((AG32/T32)^(1/5)-1,"--") -> 0.14219012
C33: =IF($C$25="Quarterly","% Growth QoQ","% Growth YoY") -> % Growth QoQ | G33: =IF($C$25="Annual",'Segment Analysis'!G173,'Segment Analysis'!G193) -> -0.13079229 | H33: =IF($C$25="Annual",'Segment Analysis'!H173,'Segment Analysis'!H193) -> 0.14597322 | I33: =IF($C$25="Annual",'Segment Analysis'!I173,'Segment Analysis'!I193) -> 0.38651493 | J33: =IF($C$25="Annual",'Segment Analysis'!J173,'Segment Analysis'!J193) -> 0 | K33: =IF($C$25="Annual",'Segment Analysis'!K173,'Segment Analysis'!K193) -> -0.2669081 | L33: =IF($C$25="Annual",'Segment Analysis'!L173,'Segment Analysis'!L193) -> 0.19276589 | M33: =IF($C$25="Annual",'Segment Analysis'!M173,'Segment Analysis'!M193) -> 0.063827406 | N33: =IF($C$25="Annual",'Segment Analysis'!N173,'Segment Analysis'!N193) -> 0.33839711 | O33: =IFERROR(O32/J32-1,"--") -> 0.23028825 | P33: =IFERROR(P32/N32-1,"--") -> -0.30112078 | Q33: =IF($C$25="Annual",'Segment Analysis'!Q173,'Segment Analysis'!Q193) -> 0.18224906 | R33: =IF($C$25="Annual",'Segment Analysis'!R173,'Segment Analysis'!R193) -> 0.25631865 | S33: =IF($C$25="Annual",'Segment Analysis'!S173,'Segment Analysis'!S193) -> 0.25646549 | T33: =IFERROR(T32/O32-1,"--") -> 0.27287666 | U33: =IFERROR(U32/S32-1,"--") -> 0.095031043 | V33: =IFERROR(V32/U32-1,"--") -> 0.1035 | W33: =IFERROR(W32/V32-1,"--") -> 0.117 | X33: =IFERROR(X32/W32-1,"--") -> 0.2345 | Y33: =IFERROR(Y32/T32-1,"--") -> 0.79392367 | Z33: =IFERROR(Z32/X32-1,"--") -> -0.2625 | AA33: =IFERROR(AA32/Z32-1,"--") -> 0.105 | AB33: =IFERROR(AB32/AA32-1,"--") -> 0.113 | AC33: =IFERROR(AC32/AB32-1,"--") -> 0.275 | AD33: =IFERROR(AD32/Y32-1,"--") -> 0.13265821 | AE33: =IFERROR(AE32/AD32-1,"--") -> 0.033 | AF33: =IFERROR(AF32/AE32-1,"--") -> -0.022 | AG33: =IFERROR(AG32/AF32-1,"--") -> -0.053
C34: % of Total Revenue | F34: ='Segment Analysis'!F16 -> 0.96268874 | G34: ='Segment Analysis'!G16 -> 0.9575973 | H34: ='Segment Analysis'!H16 -> 0.96211203 | I34: ='Segment Analysis'!I16 -> 0.97196289 | J34: ='Segment Analysis'!J16 -> 0.96449658 | K34: ='Segment Analysis'!K16 -> 0.96021388 | L34: ='Segment Analysis'!L16 -> 0.96624955 | M34: ='Segment Analysis'!M16 -> 0.96527044 | ... U34: ='Segment Analysis'!U16 -> 0.97286338 | V34: =V32/V$30 -> 0.97510543 | W34: =W32/W$30 -> 0.9771089 | X34: =X32/X$30 -> 0.98082821 | Y34: =Y32/Y$30 -> 0.97693573 | Z34: =Z32/Z$30 -> 0.97392907 | AA34: =AA32/AA$30 -> 0.97611693 | AB34: =AB32/AB$30 -> 0.97817395 | AC34: =AC32/AC$30 -> 0.98254707 | ... AG34: =AG32/AG$30 -> 0.97841941
C35: ='Segment Analysis'!C9 -> Investment Management Revenue | F35: ='Segment Analysis'!F9 -> 17332 | G35: ='Segment Analysis'!G9 -> 17173 | H35: ='Segment Analysis'!H9 -> 17579 | I35: ='Segment Analysis'!I9 -> 17922 | J35: ='Segment Analysis'!J9 -> 70006 | K35: ='Segment Analysis'!K9 -> 19087 | L35: ='Segment Analysis'!L9 -> 19214 | M35: ='Segment Analysis'!M9 -> 21447 | ... U35: ='Segment Analysis'!U9 -> 38004 | V35: =IF(Segment2_Rev_Methodology="Segment",V59,IF(Segment2_Rev_Methodology="Activity-Based",V103,IF(Segment2_Rev_Methodology="Backlog",V177,"--"))) -> 38384.04 | W35: =IF(Segment2_Rev_Methodology="Segment",W59,IF(Segment2_Rev_Methodology="Activity-Based",W103,IF(Segment2_Rev_Methodology="Backlog",W177,"--"))) -> 39343.641 | X35: =IF(Segment2_Rev_Methodology="Segment",X59,IF(Segment2_Rev_Methodology="Activity-Based",X103,IF(Segment2_Rev_Methodology="Backlog",X177,"--"))) -> 40523.95 | Y35: =SUM(U35:X35) -> 156255.63 | Z35: =IF(Segment2_Rev_Methodology="Segment",Z59,IF(Segment2_Rev_Methodology="Activity-Based",Z103,IF(Segment2_Rev_Methodology="Backlog",Z177,"--"))) -> 40929.19 | AA35: =IF(Segment2_Rev_Methodology="Segment",AA59,IF(Segment2_Rev_Methodology="Activity-Based",AA103,IF(Segment2_Rev_Methodology="Backlog",AA177,"--"))) -> 41338.482 | AB35: =IF(Segment2_Rev_Methodology="Segment",AB59,IF(Segment2_Rev_Methodology="Activity-Based",AB103,IF(Segment2_Rev_Methodology="Backlog",AB177,"--"))) -> 41958.559 | AC35: =IF(Segment2_Rev_Methodology="Segment",AC59,IF(Segment2_Rev_Methodology="Activity-Based",AC103,IF(Segment2_Rev_Methodology="Backlog",AC177,"--"))) -> 42587.937 | AD35: =SUM(Z35:AC35) -> 166814.17 | AE35: =IF(Segment2_Rev_Methodology="Segment",AE59,IF(Segment2_Rev_Methodology="Activity-Based",AE103,IF(Segment2_Rev_Methodology="Backlog",AE177,"--"))) -> 150132.75 | AF35: =IF(Segment2_Rev_Methodology="Segment",AF59,IF(Segment2_Rev_Methodology="Activity-Based",AF103,IF(Segment2_Rev_Methodology="Backlog",AF177,"--"))) -> 153585.8 | AG35: =IF(Segment2_Rev_Methodology="Segment",AG59,IF(Segment2_Rev_Methodology="Activity-Based",AG103,IF(Segment2_Rev_Methodology="Backlog",AG177,"--"))) -> 158193.38 | AI35: =IFERROR((T35/J35)^(1/3)-1,"--") -> 0.39651382 | AJ35: =IFERROR((AG35/T35)^(1/5)-1,"--") -> -0.036651414
C36: % Growth | G36: =IF($C$25="Annual",'Segment Analysis'!G174,'Segment Analysis'!G194) -> -0.0091737826 | H36: =IF($C$25="Annual",'Segment Analysis'!H174,'Segment Analysis'!H194) -> 0.023641763 | I36: =IF($C$25="Annual",'Segment Analysis'!I174,'Segment Analysis'!I194) -> 0.019511918 | K36: =IF($C$25="Annual",'Segment Analysis'!K174,'Segment Analysis'!K194) -> 0.065003906 | L36: =IF($C$25="Annual",'Segment Analysis'!L174,'Segment Analysis'!L194) -> 0.0066537434 | M36: =IF($C$25="Annual",'Segment Analysis'!M174,'Segment Analysis'!M194) -> 0.11621734 | N36: =IF($C$25="Annual",'Segment Analysis'!N174,'Segment Analysis'!N194) -> -0.0042430177 | O36: ='Segment Analysis'!O174 -> 0.15852927 | P36: =IFERROR(P35/N35-1,"--") -> 0.51283012 | Q36: =IF($C$25="Annual",'Segment Analysis'!Q174,'Segment Analysis'!Q194) -> 0.54197103 | R36: =IF($C$25="Annual",'Segment Analysis'!R174,'Segment Analysis'!R194) -> 0.1187924 | S36: =IF($C$25="Annual",'Segment Analysis'!S174,'Segment Analysis'!S194) -> -0.05262308 | T36: ='Segment Analysis'!T174 -> 1.3508705 | U36: =IFERROR(U35/S35-1,"--") -> -0.28026817 | V36: =IFERROR(V35/U35-1,"--") -> 0.01 | W36: =IFERROR(W35/V35-1,"--") -> 0.025 | X36: =IFERROR(X35/W35-1,"--") -> 0.03 | Y36: =IFERROR(Y35/T35-1,"--") -> -0.18047029 | Z36: =IFERROR(Z35/X35-1,"--") -> 0.01 | AA36: =IFERROR(AA35/Z35-1,"--") -> 0.01 | AB36: =IFERROR(AB35/AA35-1,"--") -> 0.015 | AC36: =IFERROR(AC35/AB35-1,"--") -> 0.015 | AD36: =IFERROR(AD35/Y35-1,"--") -> 0.067572197 | AE36: =IFERROR(AE35/AD35-1,"--") -> -0.1 | AF36: =IFERROR(AF35/AE35-1,"--") -> 0.023 | AG36: =IFERROR(AG35/AF35-1,"--") -> 0.03
C37: % of Total Revenue | F37: ='Segment Analysis'!F17 -> 0.030073883 | G37: ='Segment Analysis'!G17 -> 0.034100477 | H37: ='Segment Analysis'!H17 -> 0.030603896 | I37: ='Segment Analysis'!I17 -> 0.022733615 | J37: ='Segment Analysis'!J17 -> 0.028659669 | K37: ='Segment Analysis'!K17 -> 0.032627183 | L37: ='Segment Analysis'!L17 -> 0.027709316 | M37: ='Segment Analysis'!M17 -> 0.029044446 | ... U37: ='Segment Analysis'!U17 -> 0.027136624 | V37: =V35/V$30 -> 0.024894566 | W37: =W35/W$30 -> 0.022891099 | X37: =X35/X$30 -> 0.019171794 | Y37: =Y35/Y$30 -> 0.023064271 | Z37: =Z35/Z$30 -> 0.026070928 | AA37: =AA35/AA$30 -> 0.023883067 | AB37: =AB35/AB$30 -> 0.021826054 | AC37: =AC35/AC$30 -> 0.01745293 | ... AG37: =AG35/AG$30 -> 0.021580594
C38: ='Segment Analysis'!C10 -> Segment 3 Revenue | F38: ='Segment Analysis'!F10 -> 0 | G38: ='Segment Analysis'!G10 -> 0 | H38: ='Segment Analysis'!H10 -> 0 | I38: ='Segment Analysis'!I10 -> 0 | J38: ='Segment Analysis'!J10 -> 0 | K38: ='Segment Analysis'!K10 -> 0 | L38: ='Segment Analysis'!L10 -> 0 | M38: ='Segment Analysis'!M10 -> 0 | ... U38: ='Segment Analysis'!U10 -> 0 | V38: =IF(Segment3_Rev_Methodology="Segment",V65,IF(Segment3_Rev_Methodology="Activity-Based",V115,IF(Segment3_Rev_Methodology="Backlog",V189,"--"))) -> 0 | W38: =IF(Segment3_Rev_Methodology="Segment",W65,IF(Segment3_Rev_Methodology="Activity-Based",W115,IF(Segment3_Rev_Methodology="Backlog",W189,"--"))) -> 0 | X38: =IF(Segment3_Rev_Methodology="Segment",X65,IF(Segment3_Rev_Methodology="Activity-Based",X115,IF(Segment3_Rev_Methodology="Backlog",X189,"--"))) -> 0 | Y38: =SUM(U38:X38) -> 0 | Z38: =IF(Segment3_Rev_Methodology="Segment",Z65,IF(Segment3_Rev_Methodology="Activity-Based",Z115,IF(Segment3_Rev_Methodology="Backlog",Z189,"--"))) -> 0 | AA38: =IF(Segment3_Rev_Methodology="Segment",AA65,IF(Segment3_Rev_Methodology="Activity-Based",AA115,IF(Segment3_Rev_Methodology="Backlog",AA189,"--"))) -> 0 | AB38: =IF(Segment3_Rev_Methodology="Segment",AB65,IF(Segment3_Rev_Methodology="Activity-Based",AB115,IF(Segment3_Rev_Methodology="Backlog",AB189,"--"))) -> 0 | AC38: =IF(Segment3_Rev_Methodology="Segment",AC65,IF(Segment3_Rev_Methodology="Activity-Based",AC115,IF(Segment3_Rev_Methodology="Backlog",AC189,"--"))) -> 0 | AD38: =SUM(Z38:AC38) -> 0 | AE38: =IF(Segment3_Rev_Methodology="Segment",AE65,IF(Segment3_Rev_Methodology="Activity-Based",AE115,IF(Segment3_Rev_Methodology="Backlog",AE189,"--"))) -> 0 | AF38: =IF(Segment3_Rev_Methodology="Segment",AF65,IF(Segment3_Rev_Methodology="Activity-Based",AF115,IF(Segment3_Rev_Methodology="Backlog",AF189,"--"))) -> 0 | AG38: =IF(Segment3_Rev_Methodology="Segment",AG65,IF(Segment3_Rev_Methodology="Activity-Based",AG115,IF(Segment3_Rev_Methodology="Backlog",AG189,"--"))) -> 0 | AI38: =IFERROR((T38/J38)^(1/3)-1,"--") -> -- | AJ38: =IFERROR((AG38/T38)^(1/5)-1,"--") -> --
C39: % Growth | G39: =IF($C$25="Annual",'Segment Analysis'!G175,'Segment Analysis'!G195) -> N/A | H39: =IF($C$25="Annual",'Segment Analysis'!H175,'Segment Analysis'!H195) -> N/A | I39: =IF($C$25="Annual",'Segment Analysis'!I175,'Segment Analysis'!I195) -> N/A | K39: =IF($C$25="Annual",'Segment Analysis'!K175,'Segment Analysis'!K195) -> N/A | L39: =IF($C$25="Annual",'Segment Analysis'!L175,'Segment Analysis'!L195) -> N/A | M39: =IF($C$25="Annual",'Segment Analysis'!M175,'Segment Analysis'!M195) -> N/A | N39: =IF($C$25="Annual",'Segment Analysis'!N175,'Segment Analysis'!N195) -> N/A | O39: =IF($C$25="Annual",'Segment Analysis'!O175,'Segment Analysis'!O195) -> 0 | P39: =IF($C$25="Annual",'Segment Analysis'!P175,'Segment Analysis'!P195) -> N/A | Q39: =IF($C$25="Annual",'Segment Analysis'!Q175,'Segment Analysis'!Q195) -> N/A | R39: =IF($C$25="Annual",'Segment Analysis'!R175,'Segment Analysis'!R195) -> N/A | ... U39: =IF($C$25="Annual",'Segment Analysis'!U175,'Segment Analysis'!U195) -> N/A | V39: =IFERROR(V38/U38-1,"--") -> -- | W39: =IFERROR(W38/V38-1,"--") -> -- | X39: =IFERROR(X38/W38-1,"--") -> -- | Y39: =IFERROR(Y38/T38-1,"--") -> -- | Z39: =IFERROR(Z38/X38-1,"--") -> -- | AA39: =IFERROR(AA38/Z38-1,"--") -> -- | AB39: =IFERROR(AB38/AA38-1,"--") -> -- | AC39: =IFERROR(AC38/AB38-1,"--") -> -- | AD39: =IFERROR(AD38/Y38-1,"--") -> -- | AE39: =IFERROR(AE38/AD38-1,"--") -> -- | AF39: =IFERROR(AF38/AE38-1,"--") -> -- | AG39: =IFERROR(AG38/AF38-1,"--") -> --
C40: % of Total Revenue | F40: ='Segment Analysis'!F18 -> 0 | G40: ='Segment Analysis'!G18 -> 0 | H40: ='Segment Analysis'!H18 -> 0 | I40: ='Segment Analysis'!I18 -> 0 | J40: ='Segment Analysis'!J18 -> 0 | K40: ='Segment Analysis'!K18 -> 0 | L40: ='Segment Analysis'!L18 -> 0 | M40: ='Segment Analysis'!M18 -> 0 | ... U40: ='Segment Analysis'!U18 -> 0 | V40: =V38/V$30 -> 0 | W40: =W38/W$30 -> 0 | X40: =X38/X$30 -> 0 | Y40: =Y38/Y$30 -> 0 | Z40: =Z38/Z$30 -> 0 | AA40: =AA38/AA$30 -> 0 | AB40: =AB38/AB$30 -> 0 | AC40: =AC38/AC$30 -> 0 | ... AG40: =AG38/AG$30 -> 0
C41: ='Segment Analysis'!C11 -> Segment 4 Revenue | F41: ='Segment Analysis'!F11 -> 0 | G41: ='Segment Analysis'!G11 -> 0 | H41: ='Segment Analysis'!H11 -> 0 | I41: ='Segment Analysis'!I11 -> 0 | J41: ='Segment Analysis'!J11 -> 0 | K41: ='Segment Analysis'!K11 -> 0 | L41: ='Segment Analysis'!L11 -> 0 | M41: ='Segment Analysis'!M11 -> 0 | ... U41: ='Segment Analysis'!U11 -> 0 | V41: =IF(Segment4_Rev_Methodology="Segment",V71,IF(Segment4_Rev_Methodology="Activity-Based",V127,IF(Segment4_Rev_Methodology="Backlog",V201,"--"))) -> 0 | W41: =IF(Segment4_Rev_Methodology="Segment",W71,IF(Segment4_Rev_Methodology="Activity-Based",W127,IF(Segment4_Rev_Methodology="Backlog",W201,"--"))) -> 0 | X41: =IF(Segment4_Rev_Methodology="Segment",X71,IF(Segment4_Rev_Methodology="Activity-Based",X127,IF(Segment4_Rev_Methodology="Backlog",X201,"--"))) -> 0 | Y41: =SUM(U41:X41) -> 0 | Z41: =IF(Segment4_Rev_Methodology="Segment",Z71,IF(Segment4_Rev_Methodology="Activity-Based",Z127,IF(Segment4_Rev_Methodology="Backlog",Z201,"--"))) -> 0 | AA41: =IF(Segment4_Rev_Methodology="Segment",AA71,IF(Segment4_Rev_Methodology="Activity-Based",AA127,IF(Segment4_Rev_Methodology="Backlog",AA201,"--"))) -> 0 | AB41: =IF(Segment4_Rev_Methodology="Segment",AB71,IF(Segment4_Rev_Methodology="Activity-Based",AB127,IF(Segment4_Rev_Methodology="Backlog",AB201,"--"))) -> 0 | AC41: =IF(Segment4_Rev_Methodology="Segment",AC71,IF(Segment4_Rev_Methodology="Activity-Based",AC127,IF(Segment4_Rev_Methodology="Backlog",AC201,"--"))) -> 0 | AD41: =SUM(Z41:AC41) -> 0 | AE41: =IF(Segment4_Rev_Methodology="Segment",AE71,IF(Segment4_Rev_Methodology="Activity-Based",AE127,IF(Segment4_Rev_Methodology="Backlog",AE201,"--"))) -> 0 | AF41: =IF(Segment4_Rev_Methodology="Segment",AF71,IF(Segment4_Rev_Methodology="Activity-Based",AF127,IF(Segment4_Rev_Methodology="Backlog",AF201,"--"))) -> 0 | AG41: =IF(Segment4_Rev_Methodology="Segment",AG71,IF(Segment4_Rev_Methodology="Activity-Based",AG127,IF(Segment4_Rev_Methodology="Backlog",AG201,"--"))) -> 0 | AI41: =IFERROR((T41/J41)^(1/3)-1,"--") -> -- | AJ41: =IFERROR((AG41/T41)^(1/5)-1,"--") -> --
C42: % Growth | G42: =IF($C$25="Annual",'Segment Analysis'!G176,'Segment Analysis'!G196) -> N/A | H42: =IF($C$25="Annual",'Segment Analysis'!H176,'Segment Analysis'!H196) -> N/A | I42: =IF($C$25="Annual",'Segment Analysis'!I176,'Segment Analysis'!I196) -> N/A | K42: =IF($C$25="Annual",'Segment Analysis'!K176,'Segment Analysis'!K196) -> N/A | L42: =IF($C$25="Annual",'Segment Analysis'!L176,'Segment Analysis'!L196) -> N/A | M42: =IF($C$25="Annual",'Segment Analysis'!M176,'Segment Analysis'!M196) -> N/A | N42: =IF($C$25="Annual",'Segment Analysis'!N176,'Segment Analysis'!N196) -> N/A | O42: =IF($C$25="Annual",'Segment Analysis'!O176,'Segment Analysis'!O196) -> 0 | P42: =IF($C$25="Annual",'Segment Analysis'!P176,'Segment Analysis'!P196) -> N/A | Q42: =IF($C$25="Annual",'Segment Analysis'!Q176,'Segment Analysis'!Q196) -> N/A | R42: =IF($C$25="Annual",'Segment Analysis'!R176,'Segment Analysis'!R196) -> N/A | ... U42: =IF($C$25="Annual",'Segment Analysis'!U176,'Segment Analysis'!U196) -> N/A | V42: =IFERROR(V41/U41-1,"--") -> -- | W42: =IFERROR(W41/V41-1,"--") -> -- | X42: =IFERROR(X41/W41-1,"--") -> -- | Y42: =IFERROR(Y41/T41-1,"--") -> -- | Z42: =IFERROR(Z41/X41-1,"--") -> -- | AA42: =IFERROR(AA41/Z41-1,"--") -> -- | AB42: =IFERROR(AB41/AA41-1,"--") -> -- | AC42: =IFERROR(AC41/AB41-1,"--") -> -- | AD42: =IFERROR(AD41/Y41-1,"--") -> -- | AE42: =IFERROR(AE41/AD41-1,"--") -> -- | AF42: =IFERROR(AF41/AE41-1,"--") -> -- | AG42: =IFERROR(AG41/AF41-1,"--") -> --
C43: % of Total Revenue | F43: ='Segment Analysis'!F19 -> 0 | G43: ='Segment Analysis'!G19 -> 0 | H43: ='Segment Analysis'!H19 -> 0 | I43: ='Segment Analysis'!I19 -> 0 | J43: ='Segment Analysis'!J19 -> 0 | K43: ='Segment Analysis'!K19 -> 0 | L43: ='Segment Analysis'!L19 -> 0 | M43: ='Segment Analysis'!M19 -> 0 | ... U43: ='Segment Analysis'!U19 -> 0 | V43: =V41/V$30 -> 0 | W43: =W41/W$30 -> 0 | X43: =X41/X$30 -> 0 | Y43: =Y41/Y$30 -> 0 | Z43: =Z41/Z$30 -> 0 | AA43: =AA41/AA$30 -> 0 | AB43: =AB41/AB$30 -> 0 | AC43: =AC41/AC$30 -> 0 | ... AG43: =AG41/AG$30 -> 0
C44: ='Segment Analysis'!C12 -> Segment 5 Revenue | F44: ='Segment Analysis'!F12 -> 0 | G44: ='Segment Analysis'!G12 -> 0 | H44: ='Segment Analysis'!H12 -> 0 | I44: ='Segment Analysis'!I12 -> 0 | J44: ='Segment Analysis'!J12 -> 0 | K44: ='Segment Analysis'!K12 -> 0 | L44: ='Segment Analysis'!L12 -> 0 | M44: ='Segment Analysis'!M12 -> 0 | ... U44: ='Segment Analysis'!U12 -> 0 | V44: =IF(Segment5_Rev_Methodology="Segment",V77,IF(Segment5_Rev_Methodology="Activity-Based",V139,IF(Segment5_Rev_Methodology="Backlog",V213,"--"))) -> 0 | W44: =IF(Segment5_Rev_Methodology="Segment",W77,IF(Segment5_Rev_Methodology="Activity-Based",W139,IF(Segment5_Rev_Methodology="Backlog",W213,"--"))) -> 0 | X44: =IF(Segment5_Rev_Methodology="Segment",X77,IF(Segment5_Rev_Methodology="Activity-Based",X139,IF(Segment5_Rev_Methodology="Backlog",X213,"--"))) -> 0 | Y44: =SUM(U44:X44) -> 0 | Z44: =IF(Segment5_Rev_Methodology="Segment",Z77,IF(Segment5_Rev_Methodology="Activity-Based",Z139,IF(Segment5_Rev_Methodology="Backlog",Z213,"--"))) -> 0 | AA44: =IF(Segment5_Rev_Methodology="Segment",AA77,IF(Segment5_Rev_Methodology="Activity-Based",AA139,IF(Segment5_Rev_Methodology="Backlog",AA213,"--"))) -> 0 | AB44: =IF(Segment5_Rev_Methodology="Segment",AB77,IF(Segment5_Rev_Methodology="Activity-Based",AB139,IF(Segment5_Rev_Methodology="Backlog",AB213,"--"))) -> 0 | AC44: =IF(Segment5_Rev_Methodology="Segment",AC77,IF(Segment5_Rev_Methodology="Activity-Based",AC139,IF(Segment5_Rev_Methodology="Backlog",AC213,"--"))) -> 0 | AD44: =SUM(Z44:AC44) -> 0 | AE44: =IF(Segment5_Rev_Methodology="Segment",AE77,IF(Segment5_Rev_Methodology="Activity-Based",AE139,IF(Segment5_Rev_Methodology="Backlog",AE213,"--"))) -> 0 | AF44: =IF(Segment5_Rev_Methodology="Segment",AF77,IF(Segment5_Rev_Methodology="Activity-Based",AF139,IF(Segment5_Rev_Methodology="Backlog",AF213,"--"))) -> 0 | AG44: =IF(Segment5_Rev_Methodology="Segment",AG77,IF(Segment5_Rev_Methodology="Activity-Based",AG139,IF(Segment5_Rev_Methodology="Backlog",AG213,"--"))) -> 0 | AI44: =IFERROR((T44/J44)^(1/3)-1,"--") -> -- | AJ44: =IFERROR((AG44/T44)^(1/5)-1,"--") -> --
C45: % Growth | G45: =IF($C$25="Annual",'Segment Analysis'!G177,'Segment Analysis'!G197) -> N/A | H45: =IF($C$25="Annual",'Segment Analysis'!H177,'Segment Analysis'!H197) -> N/A | I45: =IF($C$25="Annual",'Segment Analysis'!I177,'Segment Analysis'!I197) -> N/A | K45: =IF($C$25="Annual",'Segment Analysis'!K177,'Segment Analysis'!K197) -> N/A | L45: =IF($C$25="Annual",'Segment Analysis'!L177,'Segment Analysis'!L197) -> N/A | M45: =IF($C$25="Annual",'Segment Analysis'!M177,'Segment Analysis'!M197) -> N/A | N45: =IF($C$25="Annual",'Segment Analysis'!N177,'Segment Analysis'!N197) -> N/A | O45: =IF($C$25="Annual",'Segment Analysis'!O177,'Segment Analysis'!O197) -> 0 | P45: =IF($C$25="Annual",'Segment Analysis'!P177,'Segment Analysis'!P197) -> N/A | Q45: =IF($C$25="Annual",'Segment Analysis'!Q177,'Segment Analysis'!Q197) -> N/A | R45: =IF($C$25="Annual",'Segment Analysis'!R177,'Segment Analysis'!R197) -> N/A | ... U45: =IF($C$25="Annual",'Segment Analysis'!U177,'Segment Analysis'!U197) -> N/A | V45: =IFERROR(V44/U44-1,"--") -> -- | W45: =IFERROR(W44/V44-1,"--") -> -- | X45: =IFERROR(X44/W44-1,"--") -> -- | Y45: =IFERROR(Y44/T44-1,"--") -> -- | Z45: =IFERROR(Z44/X44-1,"--") -> -- | AA45: =IFERROR(AA44/Z44-1,"--") -> -- | AB45: =IFERROR(AB44/AA44-1,"--") -> -- | AC45: =IFERROR(AC44/AB44-1,"--") -> -- | AD45: =IFERROR(AD44/Y44-1,"--") -> -- | AE45: =IFERROR(AE44/AD44-1,"--") -> -- | AF45: =IFERROR(AF44/AE44-1,"--") -> -- | AG45: =IFERROR(AG44/AF44-1,"--") -> --
C46: % of Total Revenue | F46: ='Segment Analysis'!F20 -> 0 | G46: ='Segment Analysis'!G20 -> 0 | H46: ='Segment Analysis'!H20 -> 0 | I46: ='Segment Analysis'!I20 -> 0 | J46: ='Segment Analysis'!J20 -> 0 | K46: ='Segment Analysis'!K20 -> 0 | L46: ='Segment Analysis'!L20 -> 0 | M46: ='Segment Analysis'!M20 -> 0 | ... U46: ='Segment Analysis'!U20 -> 0 | V46: =V44/V$30 -> 0 | W46: =W44/W$30 -> 0 | X46: =X44/X$30 -> 0 | Y46: =Y44/Y$30 -> 0 | Z46: =Z44/Z$30 -> 0 | AA46: =AA44/AA$30 -> 0 | AB46: =AB44/AB$30 -> 0 | AC46: =AC44/AC$30 -> 0 | ... AG46: =AG44/AG$30 -> 0
C47: ='Segment Analysis'!C13 -> Segment 6 Revenue | F47: ='Segment Analysis'!F13 -> 0 | G47: ='Segment Analysis'!G13 -> 0 | H47: ='Segment Analysis'!H13 -> 0 | I47: ='Segment Analysis'!I13 -> 0 | J47: ='Segment Analysis'!J13 -> 0 | K47: ='Segment Analysis'!K13 -> 0 | L47: ='Segment Analysis'!L13 -> 0 | M47: ='Segment Analysis'!M13 -> 0 | ... U47: ='Segment Analysis'!U13 -> 0 | V47: =IF(Segment6_Rev_Methodology="Segment",V83,IF(Segment6_Rev_Methodology="Activity-Based",V151,IF(Segment6_Rev_Methodology="Backlog",V225,"--"))) -> 0 | W47: =IF(Segment6_Rev_Methodology="Segment",W83,IF(Segment6_Rev_Methodology="Activity-Based",W151,IF(Segment6_Rev_Methodology="Backlog",W225,"--"))) -> 0 | X47: =IF(Segment6_Rev_Methodology="Segment",X83,IF(Segment6_Rev_Methodology="Activity-Based",X151,IF(Segment6_Rev_Methodology="Backlog",X225,"--"))) -> 0 | Y47: =SUM(U47:X47) -> 0 | Z47: =IF(Segment6_Rev_Methodology="Segment",Z83,IF(Segment6_Rev_Methodology="Activity-Based",Z151,IF(Segment6_Rev_Methodology="Backlog",Z225,"--"))) -> 0 | AA47: =IF(Segment6_Rev_Methodology="Segment",AA83,IF(Segment6_Rev_Methodology="Activity-Based",AA151,IF(Segment6_Rev_Methodology="Backlog",AA225,"--"))) -> 0 | AB47: =IF(Segment6_Rev_Methodology="Segment",AB83,IF(Segment6_Rev_Methodology="Activity-Based",AB151,IF(Segment6_Rev_Methodology="Backlog",AB225,"--"))) -> 0 | AC47: =IF(Segment6_Rev_Methodology="Segment",AC83,IF(Segment6_Rev_Methodology="Activity-Based",AC151,IF(Segment6_Rev_Methodology="Backlog",AC225,"--"))) -> 0 | AD47: =SUM(Z47:AC47) -> 0 | AE47: =IF(Segment6_Rev_Methodology="Segment",AE83,IF(Segment6_Rev_Methodology="Activity-Based",AE151,IF(Segment6_Rev_Methodology="Backlog",AE225,"--"))) -> 0 | AF47: =IF(Segment6_Rev_Methodology="Segment",AF83,IF(Segment6_Rev_Methodology="Activity-Based",AF151,IF(Segment6_Rev_Methodology="Backlog",AF225,"--"))) -> 0 | AG47: =IF(Segment6_Rev_Methodology="Segment",AG83,IF(Segment6_Rev_Methodology="Activity-Based",AG151,IF(Segment6_Rev_Methodology="Backlog",AG225,"--"))) -> 0 | AI47: =IFERROR((T47/J47)^(1/3)-1,"--") -> -- | AJ47: =IFERROR((AG47/T47)^(1/5)-1,"--") -> --
C48: % Growth | G48: =IF($C$25="Annual",'Segment Analysis'!G198,'Segment Analysis'!G198) -> N/A | H48: =IF($C$25="Annual",'Segment Analysis'!H198,'Segment Analysis'!H198) -> N/A | I48: =IF($C$25="Annual",'Segment Analysis'!I198,'Segment Analysis'!I198) -> N/A | K48: =IF($C$25="Annual",'Segment Analysis'!K198,'Segment Analysis'!K198) -> N/A | L48: =IF($C$25="Annual",'Segment Analysis'!L198,'Segment Analysis'!L198) -> N/A | M48: =IF($C$25="Annual",'Segment Analysis'!M198,'Segment Analysis'!M198) -> N/A | N48: =IF($C$25="Annual",'Segment Analysis'!N198,'Segment Analysis'!N198) -> N/A | O48: =IF($C$25="Annual",'Segment Analysis'!O198,'Segment Analysis'!O198) -> 0 | P48: =IF($C$25="Annual",'Segment Analysis'!P198,'Segment Analysis'!P198) -> N/A | Q48: =IF($C$25="Annual",'Segment Analysis'!Q198,'Segment Analysis'!Q198) -> N/A | R48: =IF($C$25="Annual",'Segment Analysis'!R198,'Segment Analysis'!R198) -> N/A | ... U48: =IF($C$25="Annual",'Segment Analysis'!U198,'Segment Analysis'!U198) -> N/A | V48: =IFERROR(V47/U47-1,"--") -> -- | W48: =IFERROR(W47/V47-1,"--") -> -- | X48: =IFERROR(X47/W47-1,"--") -> -- | Y48: =IFERROR(Y47/T47-1,"--") -> -- | Z48: =IFERROR(Z47/X47-1,"--") -> -- | AA48: =IFERROR(AA47/Z47-1,"--") -> -- | AB48: =IFERROR(AB47/AA47-1,"--") -> -- | AC48: =IFERROR(AC47/AB47-1,"--") -> -- | AD48: =IFERROR(AD47/Y47-1,"--") -> -- | AE48: =IFERROR(AE47/AD47-1,"--") -> -- | AF48: =IFERROR(AF47/AE47-1,"--") -> -- | AG48: =IFERROR(AG47/AF47-1,"--") -> --
C49: % of Total Revenue | F49: ='Segment Analysis'!F21 -> 0 | G49: ='Segment Analysis'!G21 -> 0 | H49: ='Segment Analysis'!H21 -> 0 | I49: ='Segment Analysis'!I21 -> 0 | J49: ='Segment Analysis'!J21 -> 0 | K49: ='Segment Analysis'!K21 -> 0 | L49: ='Segment Analysis'!L21 -> 0 | M49: ='Segment Analysis'!M21 -> 0 | ... U49: ='Segment Analysis'!U21 -> 0 | V49: =V47/V$30 -> 0 | W49: =W47/W$30 -> 0 | X49: =X47/X$30 -> 0 | Y49: =Y47/Y$30 -> 0 | Z49: =Z47/Z$30 -> 0 | AA49: =AA47/AA$30 -> 0 | AB49: =AB47/AB$30 -> 0 | AC49: =AC47/AC$30 -> 0 | ... AG49: =AG47/AG$30 -> 0
A51: x | C51: Growth Rate | F51: =F$28 -> 1Q23 | G51: =G$28 -> 2Q23 | H51: =H$28 -> 3Q23 | I51: =I$28 -> 4Q23 | J51: =J$28 -> 2023 | K51: =K$28 -> 1Q24 | L51: =L$28 -> 2Q24 | M51: =M$28 -> 3Q24 | ... AG51: =AG$28 -> 2030e | AH51: x
C53: =C32 -> Investment Banking & Equities Revenue | F53: =F32 -> 554811 | G53: =G32 -> 482246 | H53: =H32 -> 552641 | I53: =I32 -> 766245 | J53: =J32 -> 2355943 | K53: =K32 -> 561728 | L53: =L32 -> 670010 | M53: =M32 -> 712775 | ... U53: =U32 -> 1362465 | V53: =IF($C$25="Quarterly",U53*(1+V54),Q53*(1+V54)) -> 1503480.1 | W53: =IF($C$25="Quarterly",V53*(1+W54),R53*(1+W54)) -> 1679387.3 | X53: =IF($C$25="Quarterly",W53*(1+X54),S53*(1+X54)) -> 2073203.6 | Y53: =SUM(U53:X53) -> 6618536.1 | Z53: =IF($C$25="Quarterly",X53*(1+Z54),U53*(1+Z54)) -> 1528987.7 | AA53: =IF($C$25="Quarterly",Z53*(1+AA54),V53*(1+AA54)) -> 1689531.4 | AB53: =IF($C$25="Quarterly",AA53*(1+AB54),W53*(1+AB54)) -> 1880448.4 | AC53: =IF($C$25="Quarterly",AB53*(1+AC54),X53*(1+AC54)) -> 2397571.7 | AD53: =SUM(Z53:AC53) -> 7496539.2 | AE53: =AD53*(1+AE54) -> 7743925 | AF53: =AE53*(1+AF54) -> 7573558.7 | AG53: =AF53*(1+AG54) -> 7172160.1
C54: =IF($C$25="Quarterly","% Growth QoQ","% Growth YoY") -> % Growth QoQ | G54: =G33 -> -0.13079229 | H54: =H33 -> 0.14597322 | I54: =I33 -> 0.38651493 | J54: =J33 -> 0 | K54: =K33 -> -0.2669081 | L54: =L33 -> 0.19276589 | M54: =M33 -> 0.063827406 | N54: =N33 -> 0.33839711 | ... U54: =U33 -> 0.095031043 | V54: =IF(Case_Scenario="Bull",V55,IF(Case_Scenario="Base",V56,IF(Case_Scenario="bear",V57,"N/A"))) -> 0.1035 | W54: =IF(Case_Scenario="Bull",W55,IF(Case_Scenario="Base",W56,IF(Case_Scenario="bear",W57,"N/A"))) -> 0.117 | X54: =IF(Case_Scenario="Bull",X55,IF(Case_Scenario="Base",X56,IF(Case_Scenario="bear",X57,"N/A"))) -> 0.2345 | Y54: =Y33 -> 0.79392367 | Z54: =IF(Case_Scenario="Bull",Z55,IF(Case_Scenario="Base",Z56,IF(Case_Scenario="bear",Z57,"N/A"))) -> -0.2625 | AA54: =IF(Case_Scenario="Bull",AA55,IF(Case_Scenario="Base",AA56,IF(Case_Scenario="bear",AA57,"N/A"))) -> 0.105 | AB54: =IF(Case_Scenario="Bull",AB55,IF(Case_Scenario="Base",AB56,IF(Case_Scenario="bear",AB57,"N/A"))) -> 0.113 | AC54: =IF(Case_Scenario="Bull",AC55,IF(Case_Scenario="Base",AC56,IF(Case_Scenario="bear",AC57,"N/A"))) -> 0.275 | AD54: =AD33 -> 0.13265821 | AE54: =IF(Case_Scenario="Bull",AE55,IF(Case_Scenario="Base",AE56,IF(Case_Scenario="bear",AE57,"N/A"))) -> 0.033 | AF54: =IF(Case_Scenario="Bull",AF55,IF(Case_Scenario="Base",AF56,IF(Case_Scenario="bear",AF57,"N/A"))) -> -0.022 | AG54: =IF(Case_Scenario="Bull",AG55,IF(Case_Scenario="Base",AG56,IF(Case_Scenario="bear",AG57,"N/A"))) -> -0.053
C55: Bull Case | V55: =V56+0.02 -> 0.1235 | W55: =W56+0.02 -> 0.137 | X55: =X56+0.02 -> 0.2545 | Z55: =Z56+0.02 -> -0.2425 | AA55: =AA56+0.02 -> 0.125 | AB55: =AB56+0.02 -> 0.133 | AC55: =AC56+0.02 -> 0.295 | AE55: =AE56+1% -> 0.043 | AF55: =AF56+1% -> -0.012 | AG55: =AG56+1% -> -0.043
C56: Base Case | V56: 0.1035 | W56: 0.117 | X56: 0.2345 | Z56: -0.2625 | AA56: 0.105 | AB56: 0.113 | AC56: 0.275 | AE56: 0.033 | AF56: -0.022 | AG56: -0.053
C57: Bear Case | V57: =V56-0.02 -> 0.0835 | W57: =W56-0.02 -> 0.097 | X57: =X56-0.02 -> 0.2145 | Z57: =Z56-0.02 -> -0.2825 | AA57: =AA56-0.02 -> 0.085 | AB57: =AB56-0.02 -> 0.093 | AC57: =AC56-0.02 -> 0.255 | AE57: =AE56-3% -> 0.003 | AF57: =AF56-3% -> -0.052 | AG57: =AG56-3% -> -0.083
A59: x | C59: =C35 -> Investment Management Revenue | F59: =F35 -> 17332 | G59: =G35 -> 17173 | H59: =H35 -> 17579 | I59: =I35 -> 17922 | J59: =J35 -> 70006 | K59: =K35 -> 19087 | L59: =L35 -> 19214 | M59: =M35 -> 21447 | ... U59: =U35 -> 38004 | V59: =IF($C$25="Quarterly",U59*(1+V60),Q59*(1+V60)) -> 38384.04 | W59: =IF($C$25="Quarterly",V59*(1+W60),R59*(1+W60)) -> 39343.641 | X59: =IF($C$25="Quarterly",W59*(1+X60),S59*(1+X60)) -> 40523.95 | Y59: =SUM(U59:X59) -> 156255.63 | Z59: =IF($C$25="Quarterly",X59*(1+Z60),U59*(1+Z60)) -> 40929.19 | AA59: =IF($C$25="Quarterly",Z59*(1+AA60),V59*(1+AA60)) -> 41338.482 | AB59: =IF($C$25="Quarterly",AA59*(1+AB60),W59*(1+AB60)) -> 41958.559 | AC59: =IF($C$25="Quarterly",AB59*(1+AC60),X59*(1+AC60)) -> 42587.937 | AD59: =SUM(Z59:AC59) -> 166814.17 | AE59: =AD59*(1+AE60) -> 150132.75 | AF59: =AE59*(1+AF60) -> 153585.8 | AG59: =AF59*(1+AG60) -> 158193.38
C60: =IF($C$25="Quarterly","% Growth QoQ","% Growth YoY") -> % Growth QoQ | G60: =G36 -> -0.0091737826 | H60: =H36 -> 0.023641763 | I60: =I36 -> 0.019511918 | J60: =J36 -> 0 | K60: =K36 -> 0.065003906 | L60: =L36 -> 0.0066537434 | M60: =M36 -> 0.11621734 | N60: =N36 -> -0.0042430177 | ... U60: =U36 -> -0.28026817 | V60: =IF(Case_Scenario="Bull",V61,IF(Case_Scenario="Base",V62,IF(Case_Scenario="bear",V63,"N/A"))) -> 0.01 | W60: =IF(Case_Scenario="Bull",W61,IF(Case_Scenario="Base",W62,IF(Case_Scenario="bear",W63,"N/A"))) -> 0.025 | X60: =IF(Case_Scenario="Bull",X61,IF(Case_Scenario="Base",X62,IF(Case_Scenario="bear",X63,"N/A"))) -> 0.03 | Y60: =Y36 -> -0.18047029 | Z60: =IF(Case_Scenario="Bull",Z61,IF(Case_Scenario="Base",Z62,IF(Case_Scenario="bear",Z63,"N/A"))) -> 0.01 | AA60: =IF(Case_Scenario="Bull",AA61,IF(Case_Scenario="Base",AA62,IF(Case_Scenario="bear",AA63,"N/A"))) -> 0.01 | AB60: =IF(Case_Scenario="Bull",AB61,IF(Case_Scenario="Base",AB62,IF(Case_Scenario="bear",AB63,"N/A"))) -> 0.015 | AC60: =IF(Case_Scenario="Bull",AC61,IF(Case_Scenario="Base",AC62,IF(Case_Scenario="bear",AC63,"N/A"))) -> 0.015 | AD60: =AD36 -> 0.067572197 | AE60: =IF(Case_Scenario="Bull",AE61,IF(Case_Scenario="Base",AE62,IF(Case_Scenario="bear",AE63,"N/A"))) -> -0.1 | AF60: =IF(Case_Scenario="Bull",AF61,IF(Case_Scenario="Base",AF62,IF(Case_Scenario="bear",AF63,"N/A"))) -> 0.023 | AG60: =IF(Case_Scenario="Bull",AG61,IF(Case_Scenario="Base",AG62,IF(Case_Scenario="bear",AG63,"N/A"))) -> 0.03
C61: Bull Case | V61: =V62+2% -> 0.03 | W61: =W62+2% -> 0.045 | X61: =X62+2% -> 0.05 | Z61: =Z62+2% -> 0.03 | AA61: =AA62+2% -> 0.03 | AB61: =AB62+2% -> 0.035 | AC61: =AC62+2% -> 0.035 | AE61: =AE62+2% -> -0.08 | AF61: =AF62+2% -> 0.043 | AG61: =AG62+2% -> 0.05
C62: Base Case | V62: 0.01 | W62: 0.025 | X62: 0.03 | Z62: 0.01 | AA62: 0.01 | AB62: 0.015 | AC62: 0.015 | AE62: -0.1 | AF62: 0.023 | AG62: 0.03
C63: Bear Case | V63: =V62-6% -> -0.05 | W63: =W62-6% -> -0.035 | X63: =X62-6% -> -0.03 | Z63: =Z62-6% -> -0.05 | AA63: =AA62-6% -> -0.05 | AB63: =AB62-6% -> -0.045 | AC63: =AC62-6% -> -0.045 | AE63: =AE62-6% -> -0.16 | AF63: =AF62-6% -> -0.037 | AG63: =AG62-6% -> -0.03
A65: x | C65: =C38 -> Segment 3 Revenue | F65: =F38 -> 0 | G65: =G38 -> 0 | H65: =H38 -> 0 | I65: =I38 -> 0 | J65: =J38 -> 0 | K65: =K38 -> 0 | L65: =L38 -> 0 | M65: =M38 -> 0 | ... U65: =U38 -> 0 | V65: =IF($C$25="Quarterly",U65*(1+V66),Q65*(1+V66)) -> 0 | W65: =IF($C$25="Quarterly",V65*(1+W66),R65*(1+W66)) -> 0 | X65: =IF($C$25="Quarterly",W65*(1+X66),S65*(1+X66)) -> 0 | Y65: =SUM(U65:X65) -> 0 | Z65: =IF($C$25="Quarterly",X65*(1+Z66),U65*(1+Z66)) -> 0 | AA65: =IF($C$25="Quarterly",Z65*(1+AA66),V65*(1+AA66)) -> 0 | AB65: =IF($C$25="Quarterly",AA65*(1+AB66),W65*(1+AB66)) -> 0 | AC65: =IF($C$25="Quarterly",AB65*(1+AC66),X65*(1+AC66)) -> 0 | AD65: =SUM(Z65:AC65) -> 0 | AE65: =AD65*(1+AE66) -> 0 | AF65: =AE65*(1+AF66) -> 0 | AG65: =AF65*(1+AG66) -> 0
C66: =IF($C$25="Quarterly","% Growth QoQ","% Growth YoY") -> % Growth QoQ | G66: =G39 -> N/A | H66: =H39 -> N/A | I66: =I39 -> N/A | J66: =J39 -> 0 | K66: =K39 -> N/A | L66: =L39 -> N/A | M66: =M39 -> N/A | N66: =N39 -> N/A | ... U66: =U39 -> N/A | V66: =IF(Case_Scenario="Bull",V67,IF(Case_Scenario="Base",V68,IF(Case_Scenario="bear",V69,"N/A"))) -> 0.05 | W66: =IF(Case_Scenario="Bull",W67,IF(Case_Scenario="Base",W68,IF(Case_Scenario="bear",W69,"N/A"))) -> 0.05 | X66: =IF(Case_Scenario="Bull",X67,IF(Case_Scenario="Base",X68,IF(Case_Scenario="bear",X69,"N/A"))) -> 0.05 | Z66: =IF(Case_Scenario="Bull",Z67,IF(Case_Scenario="Base",Z68,IF(Case_Scenario="bear",Z69,"N/A"))) -> 0.05 | AA66: =IF(Case_Scenario="Bull",AA67,IF(Case_Scenario="Base",AA68,IF(Case_Scenario="bear",AA69,"N/A"))) -> 0.05 | AB66: =IF(Case_Scenario="Bull",AB67,IF(Case_Scenario="Base",AB68,IF(Case_Scenario="bear",AB69,"N/A"))) -> 0.05 | AC66: =IF(Case_Scenario="Bull",AC67,IF(Case_Scenario="Base",AC68,IF(Case_Scenario="bear",AC69,"N/A"))) -> 0.05 | AE66: =IF(Case_Scenario="Bull",AE67,IF(Case_Scenario="Base",AE68,IF(Case_Scenario="bear",AE69,"N/A"))) -> 0.05 | AF66: =IF(Case_Scenario="Bull",AF67,IF(Case_Scenario="Base",AF68,IF(Case_Scenario="bear",AF69,"N/A"))) -> 0.05 | AG66: =IF(Case_Scenario="Bull",AG67,IF(Case_Scenario="Base",AG68,IF(Case_Scenario="bear",AG69,"N/A"))) -> 0.05
C67: Bull Case | V67: 0.1 | W67: 0.1 | X67: 0.1 | Z67: 0.1 | AA67: 0.1 | AB67: 0.1 | AC67: 0.1 | AE67: 0.1 | AF67: 0.1 | AG67: 0.1
C68: Base Case | V68: 0.05 | W68: 0.05 | X68: 0.05 | Z68: 0.05 | AA68: 0.05 | AB68: 0.05 | AC68: 0.05 | AE68: 0.05 | AF68: 0.05 | AG68: 0.05
C69: Bear Case | V69: 0 | W69: 0 | X69: 0 | Z69: 0 | AA69: 0 | AB69: 0 | AC69: 0 | AE69: 0 | AF69: 0 | AG69: 0
A71: x | C71: =C41 -> Segment 4 Revenue | F71: =F41 -> 0 | G71: =G41 -> 0 | H71: =H41 -> 0 | I71: =I41 -> 0 | J71: =J41 -> 0 | K71: =K41 -> 0 | L71: =L41 -> 0 | M71: =M41 -> 0 | ... U71: =U41 -> 0 | V71: =IF($C$25="Quarterly",U71*(1+V72),Q71*(1+V72)) -> 0 | W71: =IF($C$25="Quarterly",V71*(1+W72),R71*(1+W72)) -> 0 | X71: =IF($C$25="Quarterly",W71*(1+X72),S71*(1+X72)) -> 0 | Y71: =SUM(U71:X71) -> 0 | Z71: =IF($C$25="Quarterly",X71*(1+Z72),U71*(1+Z72)) -> 0 | AA71: =IF($C$25="Quarterly",Z71*(1+AA72),V71*(1+AA72)) -> 0 | AB71: =IF($C$25="Quarterly",AA71*(1+AB72),W71*(1+AB72)) -> 0 | AC71: =IF($C$25="Quarterly",AB71*(1+AC72),X71*(1+AC72)) -> 0 | AD71: =SUM(Z71:AC71) -> 0 | AE71: =AD71*(1+AE72) -> 0 | AF71: =AE71*(1+AF72) -> 0 | AG71: =AF71*(1+AG72) -> 0
C72: =IF($C$25="Quarterly","% Growth QoQ","% Growth YoY") -> % Growth QoQ | G72: =G42 -> N/A | H72: =H42 -> N/A | I72: =I42 -> N/A | J72: =J42 -> 0 | K72: =K42 -> N/A | L72: =L42 -> N/A | M72: =M42 -> N/A | N72: =N42 -> N/A | ... U72: =U42 -> N/A | V72: =IF(Case_Scenario="Bull",V73,IF(Case_Scenario="Base",V74,IF(Case_Scenario="bear",V75,"N/A"))) -> 0.05 | W72: =IF(Case_Scenario="Bull",W73,IF(Case_Scenario="Base",W74,IF(Case_Scenario="bear",W75,"N/A"))) -> 0.05 | X72: =IF(Case_Scenario="Bull",X73,IF(Case_Scenario="Base",X74,IF(Case_Scenario="bear",X75,"N/A"))) -> 0.05 | Z72: =IF(Case_Scenario="Bull",Z73,IF(Case_Scenario="Base",Z74,IF(Case_Scenario="bear",Z75,"N/A"))) -> 0.05 | AA72: =IF(Case_Scenario="Bull",AA73,IF(Case_Scenario="Base",AA74,IF(Case_Scenario="bear",AA75,"N/A"))) -> 0.05 | AB72: =IF(Case_Scenario="Bull",AB73,IF(Case_Scenario="Base",AB74,IF(Case_Scenario="bear",AB75,"N/A"))) -> 0.05 | AC72: =IF(Case_Scenario="Bull",AC73,IF(Case_Scenario="Base",AC74,IF(Case_Scenario="bear",AC75,"N/A"))) -> 0.05 | AE72: =IF(Case_Scenario="Bull",AE73,IF(Case_Scenario="Base",AE74,IF(Case_Scenario="bear",AE75,"N/A"))) -> 0.05 | AF72: =IF(Case_Scenario="Bull",AF73,IF(Case_Scenario="Base",AF74,IF(Case_Scenario="bear",AF75,"N/A"))) -> 0.05 | AG72: =IF(Case_Scenario="Bull",AG73,IF(Case_Scenario="Base",AG74,IF(Case_Scenario="bear",AG75,"N/A"))) -> 0.05
C73: Bull Case | V73: 0.1 | W73: 0.1 | X73: 0.1 | Z73: 0.1 | AA73: 0.1 | AB73: 0.1 | AC73: 0.1 | AE73: 0.1 | AF73: 0.1 | AG73: 0.1
C74: Base Case | V74: 0.05 | W74: 0.05 | X74: 0.05 | Z74: 0.05 | AA74: 0.05 | AB74: 0.05 | AC74: 0.05 | AE74: 0.05 | AF74: 0.05 | AG74: 0.05
C75: Bear Case | V75: 0 | W75: 0 | X75: 0 | Z75: 0 | AA75: 0 | AB75: 0 | AC75: 0 | AE75: 0 | AF75: 0 | AG75: 0
A77: x | C77: =C44 -> Segment 5 Revenue | F77: =F44 -> 0 | G77: =G44 -> 0 | H77: =H44 -> 0 | I77: =I44 -> 0 | J77: =J44 -> 0 | K77: =K44 -> 0 | L77: =L44 -> 0 | M77: =M44 -> 0 | ... U77: =U44 -> 0 | V77: =IF($C$25="Quarterly",U77*(1+V78),Q77*(1+V78)) -> 0 | W77: =IF($C$25="Quarterly",V77*(1+W78),R77*(1+W78)) -> 0 | X77: =IF($C$25="Quarterly",W77*(1+X78),S77*(1+X78)) -> 0 | Y77: =SUM(U77:X77) -> 0 | Z77: =IF($C$25="Quarterly",X77*(1+Z78),U77*(1+Z78)) -> 0 | AA77: =IF($C$25="Quarterly",Z77*(1+AA78),V77*(1+AA78)) -> 0 | AB77: =IF($C$25="Quarterly",AA77*(1+AB78),W77*(1+AB78)) -> 0 | AC77: =IF($C$25="Quarterly",AB77*(1+AC78),X77*(1+AC78)) -> 0 | AD77: =SUM(Z77:AC77) -> 0 | AE77: =AD77*(1+AE78) -> 0 | AF77: =AE77*(1+AF78) -> 0 | AG77: =AF77*(1+AG78) -> 0
C78: =IF($C$25="Quarterly","% Growth QoQ","% Growth YoY") -> % Growth QoQ | G78: =G45 -> N/A | H78: =H45 -> N/A | I78: =I45 -> N/A | J78: =J45 -> 0 | K78: =K45 -> N/A | L78: =L45 -> N/A | M78: =M45 -> N/A | N78: =N45 -> N/A | ... U78: =U45 -> N/A | V78: =IF(Case_Scenario="Bull",V79,IF(Case_Scenario="Base",V80,IF(Case_Scenario="bear",V81,"N/A"))) -> 0.05 | W78: =IF(Case_Scenario="Bull",W79,IF(Case_Scenario="Base",W80,IF(Case_Scenario="bear",W81,"N/A"))) -> 0.05 | X78: =IF(Case_Scenario="Bull",X79,IF(Case_Scenario="Base",X80,IF(Case_Scenario="bear",X81,"N/A"))) -> 0.05 | Z78: =IF(Case_Scenario="Bull",Z79,IF(Case_Scenario="Base",Z80,IF(Case_Scenario="bear",Z81,"N/A"))) -> 0.05 | AA78: =IF(Case_Scenario="Bull",AA79,IF(Case_Scenario="Base",AA80,IF(Case_Scenario="bear",AA81,"N/A"))) -> 0.05 | AB78: =IF(Case_Scenario="Bull",AB79,IF(Case_Scenario="Base",AB80,IF(Case_Scenario="bear",AB81,"N/A"))) -> 0.05 | AC78: =IF(Case_Scenario="Bull",AC79,IF(Case_Scenario="Base",AC80,IF(Case_Scenario="bear",AC81,"N/A"))) -> 0.05 | AE78: =IF(Case_Scenario="Bull",AE79,IF(Case_Scenario="Base",AE80,IF(Case_Scenario="bear",AE81,"N/A"))) -> 0.05 | AF78: =IF(Case_Scenario="Bull",AF79,IF(Case_Scenario="Base",AF80,IF(Case_Scenario="bear",AF81,"N/A"))) -> 0.05 | AG78: =IF(Case_Scenario="Bull",AG79,IF(Case_Scenario="Base",AG80,IF(Case_Scenario="bear",AG81,"N/A"))) -> 0.05
C79: Bull Case | V79: 0.1 | W79: 0.1 | X79: 0.1 | Z79: 0.1 | AA79: 0.1 | AB79: 0.1 | AC79: 0.1 | AE79: 0.1 | AF79: 0.1 | AG79: 0.1
C80: Base Case | V80: 0.05 | W80: 0.05 | X80: 0.05 | Z80: 0.05 | AA80: 0.05 | AB80: 0.05 | AC80: 0.05 | AE80: 0.05 | AF80: 0.05 | AG80: 0.05
C81: Bear Case | V81: 0 | W81: 0 | X81: 0 | Z81: 0 | AA81: 0 | AB81: 0 | AC81: 0 | AE81: 0 | AF81: 0 | AG81: 0
A83: x | C83: =C47 -> Segment 6 Revenue | F83: =F47 -> 0 | G83: =G47 -> 0 | H83: =H47 -> 0 | I83: =I47 -> 0 | J83: =J47 -> 0 | K83: =K47 -> 0 | L83: =L47 -> 0 | M83: =M47 -> 0 | ... U83: =U47 -> 0 | V83: =IF($C$25="Quarterly",U83*(1+V84),Q83*(1+V84)) -> 0 | W83: =IF($C$25="Quarterly",V83*(1+W84),R83*(1+W84)) -> 0 | X83: =IF($C$25="Quarterly",W83*(1+X84),S83*(1+X84)) -> 0 | Y83: =SUM(U83:X83) -> 0 | Z83: =IF($C$25="Quarterly",X83*(1+Z84),U83*(1+Z84)) -> 0 | AA83: =IF($C$25="Quarterly",Z83*(1+AA84),V83*(1+AA84)) -> 0 | AB83: =IF($C$25="Quarterly",AA83*(1+AB84),W83*(1+AB84)) -> 0 | AC83: =IF($C$25="Quarterly",AB83*(1+AC84),X83*(1+AC84)) -> 0 | AD83: =SUM(Z83:AC83) -> 0 | AE83: =AD83*(1+AE84) -> 0 | AF83: =AE83*(1+AF84) -> 0 | AG83: =AF83*(1+AG84) -> 0
C84: =IF($C$25="Quarterly","% Growth QoQ","% Growth YoY") -> % Growth QoQ | G84: =G48 -> N/A | H84: =H48 -> N/A | I84: =I48 -> N/A | J84: =J48 -> 0 | K84: =K48 -> N/A | L84: =L48 -> N/A | M84: =M48 -> N/A | N84: =N48 -> N/A | ... U84: =U48 -> N/A | V84: =IF(Case_Scenario="Bull",V85,IF(Case_Scenario="Base",V86,IF(Case_Scenario="bear",V87,"N/A"))) -> 0 | W84: =IF(Case_Scenario="Bull",W85,IF(Case_Scenario="Base",W86,IF(Case_Scenario="bear",W87,"N/A"))) -> 0 | X84: =IF(Case_Scenario="Bull",X85,IF(Case_Scenario="Base",X86,IF(Case_Scenario="bear",X87,"N/A"))) -> 0 | Z84: =IF(Case_Scenario="Bull",Z85,IF(Case_Scenario="Base",Z86,IF(Case_Scenario="bear",Z87,"N/A"))) -> 0 | AA84: =IF(Case_Scenario="Bull",AA85,IF(Case_Scenario="Base",AA86,IF(Case_Scenario="bear",AA87,"N/A"))) -> 0 | AB84: =IF(Case_Scenario="Bull",AB85,IF(Case_Scenario="Base",AB86,IF(Case_Scenario="bear",AB87,"N/A"))) -> 0 | AC84: =IF(Case_Scenario="Bull",AC85,IF(Case_Scenario="Base",AC86,IF(Case_Scenario="bear",AC87,"N/A"))) -> 0 | AE84: =IF(Case_Scenario="Bull",AE85,IF(Case_Scenario="Base",AE86,IF(Case_Scenario="bear",AE87,"N/A"))) -> 0 | AF84: =IF(Case_Scenario="Bull",AF85,IF(Case_Scenario="Base",AF86,IF(Case_Scenario="bear",AF87,"N/A"))) -> 0 | AG84: =IF(Case_Scenario="Bull",AG85,IF(Case_Scenario="Base",AG86,IF(Case_Scenario="bear",AG87,"N/A"))) -> 0
C85: Bull Case | V85: =U85 -> 0 | W85: =V85 -> 0 | X85: =W85 -> 0 | Z85: =X85 -> 0 | AA85: =Z85 -> 0 | AB85: =AA85 -> 0 | AC85: =AB85 -> 0 | AE85: =AC85 -> 0 | AF85: =AE85 -> 0 | AG85: =AF85 -> 0
C86: Base Case | V86: =U86 -> 0 | W86: =V86 -> 0 | X86: =W86 -> 0 | Z86: =X86 -> 0 | AA86: =Z86 -> 0 | AB86: =AA86 -> 0 | AC86: =AB86 -> 0 | AE86: =AC86 -> 0 | AF86: =AE86 -> 0 | AG86: =AF86 -> 0
C87: Bear Case | V87: =U87 -> 0 | W87: =V87 -> 0 | X87: =W87 -> 0 | Z87: =X87 -> 0 | AA87: =Z87 -> 0 | AB87: =AA87 -> 0 | AC87: =AB87 -> 0 | AE87: =AC87 -> 0 | AF87: =AE87 -> 0 | AG87: =AF87 -> 0
A89: x | C89: Activity-Based Growth | F89: =F$28 -> 1Q23 | G89: =G$28 -> 2Q23 | H89: =H$28 -> 3Q23 | I89: =I$28 -> 4Q23 | J89: =J$28 -> 2023 | K89: =K$28 -> 1Q24 | L89: =L$28 -> 2Q24 | M89: =M$28 -> 3Q24 | ... AG89: =AG$28 -> 2030e | AH89: x
C91: =C32 -> Investment Banking & Equities Revenue | F91: =F32 -> 554811 | G91: =G32 -> 482246 | H91: =H32 -> 552641 | I91: =I32 -> 766245 | J91: =J32 -> 2355943 | K91: =K32 -> 561728 | L91: =L32 -> 670010 | M91: =M32 -> 712775 | ... U91: =U32 -> 1362465 | V91: =V92*V97 -> 1502117.7 | W91: =W92*W97 -> 1656084.7 | X91: =X92*X97 -> 1825833.4 | Y91: =SUM(U91:X91) -> 6346500.8 | Z91: =Z92*Z97 -> 2012981.3 | AA91: =AA92*AA97 -> 2219311.9 | AB91: =AB92*AB97 -> 2446791.4 | AC91: =AC92*AC97 -> 2697587.5 | AD91: =SUM(Z91:AC91) -> 9376672.1 | AE91: =AE92*AE97 -> 10337781 | AF91: =AF92*AF97 -> 11397404 | AG91: =AG92*AG97 -> 12565637
C92: Volume | F92: 220 | G92: 220 | H92: 220 | I92: 220 | J92: =SUM(F92:I92) -> 880 | K92: 220 | L92: 220 | M92: 220 | N92: 220 | O92: =SUM(K92:N92) -> 880 | P92: 220 | Q92: 220 | R92: 220 | S92: 220 | T92: =SUM(P92:S92) -> 880 | U92: 220 | V92: =U92*(1+V93) -> 231 | W92: =V92*(1+W93) -> 242.55 | X92: =W92*(1+X93) -> 254.6775 | Y92: =SUM(U92:X92) -> 948.2275 | Z92: =X92*(1+Z93) -> 267.41138 | AA92: =Z92*(1+AA93) -> 280.78194 | AB92: =AA92*(1+AB93) -> 294.82104 | AC92: =AB92*(1+AC93) -> 309.56209 | AD92: =SUM(Z92:AC92) -> 1152.5765 | AE92: =AD92*(1+AE93) -> 1210.2053 | AF92: =AE92*(1+AF93) -> 1270.7155 | AG92: =AF92*(1+AG93) -> 1334.2513
C93: % Volume Growth | G93: =IFERROR(G92/F92-1,"--") -> 0 | H93: =IFERROR(H92/G92-1,"--") -> 0 | I93: =IFERROR(I92/H92-1,"--") -> 0 | K93: =IFERROR(K92/I92-1,"--") -> 0 | L93: =IFERROR(L92/K92-1,"--") -> 0 | M93: =IFERROR(M92/L92-1,"--") -> 0 | N93: =IFERROR(N92/M92-1,"--") -> 0 | O93: =IFERROR(O92/J92-1,"--") -> 0 | P93: =IFERROR(P92/N92-1,"--") -> 0 | Q93: =IFERROR(Q92/P92-1,"--") -> 0 | R93: =IFERROR(R92/Q92-1,"--") -> 0 | S93: =IFERROR(S92/R92-1,"--") -> 0 | T93: =IFERROR(T92/O92-1,"--") -> 0 | U93: =IFERROR(U92/S92-1,"--") -> 0 | V93: =IF(Case_Scenario="Bull",V94,IF(Case_Scenario="Base",V95,IF(Case_Scenario="bear",V96,"N/A"))) -> 0.05 | W93: =IF(Case_Scenario="Bull",W94,IF(Case_Scenario="Base",W95,IF(Case_Scenario="bear",W96,"N/A"))) -> 0.05 | X93: =IF(Case_Scenario="Bull",X94,IF(Case_Scenario="Base",X95,IF(Case_Scenario="bear",X96,"N/A"))) -> 0.05 | Z93: =IF(Case_Scenario="Bull",Z94,IF(Case_Scenario="Base",Z95,IF(Case_Scenario="bear",Z96,"N/A"))) -> 0.05 | AA93: =IF(Case_Scenario="Bull",AA94,IF(Case_Scenario="Base",AA95,IF(Case_Scenario="bear",AA96,"N/A"))) -> 0.05 | AB93: =IF(Case_Scenario="Bull",AB94,IF(Case_Scenario="Base",AB95,IF(Case_Scenario="bear",AB96,"N/A"))) -> 0.05 | AC93: =IF(Case_Scenario="Bull",AC94,IF(Case_Scenario="Base",AC95,IF(Case_Scenario="bear",AC96,"N/A"))) -> 0.05 | AE93: =IF(Case_Scenario="Bull",AE94,IF(Case_Scenario="Base",AE95,IF(Case_Scenario="bear",AE96,"N/A"))) -> 0.05 | AF93: =IF(Case_Scenario="Bull",AF94,IF(Case_Scenario="Base",AF95,IF(Case_Scenario="bear",AF96,"N/A"))) -> 0.05 | AG93: =IF(Case_Scenario="Bull",AG94,IF(Case_Scenario="Base",AG95,IF(Case_Scenario="bear",AG96,"N/A"))) -> 0.05
C94: Bull Case | V94: 0.1 | W94: 0.1 | X94: 0.1 | Z94: 0.1 | AA94: 0.1 | AB94: 0.1 | AC94: 0.1 | AE94: 0.1 | AF94: 0.1 | AG94: 0.1
C95: Base Case | V95: 0.05 | W95: 0.05 | X95: 0.05 | Z95: 0.05 | AA95: 0.05 | AB95: 0.05 | AC95: 0.05 | AE95: 0.05 | AF95: 0.05 | AG95: 0.05
C96: Bear Case | V96: 0 | W96: 0 | X96: 0 | Z96: 0 | AA96: 0 | AB96: 0 | AC96: 0 | AE96: 0 | AF96: 0 | AG96: 0
C97: Price | F97: =IFERROR(F91/F92,"--") -> 2521.8682 | G97: =IFERROR(G91/G92,"--") -> 2192.0273 | H97: =IFERROR(H91/H92,"--") -> 2512.0045 | I97: =IFERROR(I91/I92,"--") -> 3482.9318 | J97: =IFERROR(J91/J92,"--") -> 2677.208 | K97: =IFERROR(K91/K92,"--") -> 2553.3091 | L97: =IFERROR(L91/L92,"--") -> 3045.5 | M97: =IFERROR(M91/M92,"--") -> 3239.8864 | ... U97: =IFERROR(U91/U92,"--") -> 6193.0227 | V97: =U97*(1+V98) -> 6502.6739 | W97: =V97*(1+W98) -> 6827.8076 | X97: =W97*(1+X98) -> 7169.1979 | Y97: =Y91/Y92 -> 6693.0149 | Z97: =X97*(1+Z98) -> 7527.6578 | AA97: =Z97*(1+AA98) -> 7904.0407 | AB97: =AA97*(1+AB98) -> 8299.2428 | AC97: =AB97*(1+AC98) -> 8714.2049 | AD97: =AD91/AD92 -> 8135.4015 | AE97: =AD97*(1+AE98) -> 8542.1715 | AF97: =AE97*(1+AF98) -> 8969.2801 | AG97: =AF97*(1+AG98) -> 9417.7441
C98: % Price Growth | G98: =IFERROR(G97/F97-1,"--") -> -0.13079229 | H98: =IFERROR(H97/G97-1,"--") -> 0.14597322 | I98: =IFERROR(I97/H97-1,"--") -> 0.38651493 | K98: =IFERROR(K97/I97-1,"--") -> -0.2669081 | L98: =IFERROR(L97/K97-1,"--") -> 0.19276589 | M98: =IFERROR(M97/L97-1,"--") -> 0.063827406 | N98: =IFERROR(N97/M97-1,"--") -> 0.33839711 | O98: =IFERROR(O97/J97-1,"--") -> 0.23028825 | P98: =IFERROR(P97/N97-1,"--") -> -0.30112078 | Q98: =IFERROR(Q97/P97-1,"--") -> 0.18224906 | R98: =IFERROR(R97/Q97-1,"--") -> 0.25631865 | S98: =IFERROR(S97/R97-1,"--") -> 0.25646549 | T98: =IFERROR(T97/O97-1,"--") -> 0.27287666 | U98: =IFERROR(U97/S97-1,"--") -> 0.095031043 | V98: =IF(Case_Scenario="Bull",V99,IF(Case_Scenario="Base",V100,IF(Case_Scenario="bear",V101,"N/A"))) -> 0.05 | W98: =IF(Case_Scenario="Bull",W99,IF(Case_Scenario="Base",W100,IF(Case_Scenario="bear",W101,"N/A"))) -> 0.05 | X98: =IF(Case_Scenario="Bull",X99,IF(Case_Scenario="Base",X100,IF(Case_Scenario="bear",X101,"N/A"))) -> 0.05 | Z98: =IF(Case_Scenario="Bull",Z99,IF(Case_Scenario="Base",Z100,IF(Case_Scenario="bear",Z101,"N/A"))) -> 0.05 | AA98: =IF(Case_Scenario="Bull",AA99,IF(Case_Scenario="Base",AA100,IF(Case_Scenario="bear",AA101,"N/A"))) -> 0.05 | AB98: =IF(Case_Scenario="Bull",AB99,IF(Case_Scenario="Base",AB100,IF(Case_Scenario="bear",AB101,"N/A"))) -> 0.05 | AC98: =IF(Case_Scenario="Bull",AC99,IF(Case_Scenario="Base",AC100,IF(Case_Scenario="bear",AC101,"N/A"))) -> 0.05 | AE98: =IF(Case_Scenario="Bull",AE99,IF(Case_Scenario="Base",AE100,IF(Case_Scenario="bear",AE101,"N/A"))) -> 0.05 | AF98: =IF(Case_Scenario="Bull",AF99,IF(Case_Scenario="Base",AF100,IF(Case_Scenario="bear",AF101,"N/A"))) -> 0.05 | AG98: =IF(Case_Scenario="Bull",AG99,IF(Case_Scenario="Base",AG100,IF(Case_Scenario="bear",AG101,"N/A"))) -> 0.05
C99: Bull Case | V99: 0.1 | W99: 0.1 | X99: 0.1 | Z99: 0.1 | AA99: 0.1 | AB99: 0.1 | AC99: 0.1 | AE99: 0.1 | AF99: 0.1 | AG99: 0.1
C100: Base Case | V100: 0.05 | W100: 0.05 | X100: 0.05 | Z100: 0.05 | AA100: 0.05 | AB100: 0.05 | AC100: 0.05 | AE100: 0.05 | AF100: 0.05 | AG100: 0.05
C101: Bear Case | V101: 0 | W101: 0 | X101: 0 | Z101: 0 | AA101: 0 | AB101: 0 | AC101: 0 | AE101: 0 | AF101: 0 | AG101: 0
A103: x | C103: =C35 -> Investment Management Revenue | F103: =F35 -> 17332 | G103: =G35 -> 17173 | H103: =H35 -> 17579 | I103: =I35 -> 17922 | J103: =J35 -> 70006 | K103: =K35 -> 19087 | L103: =L35 -> 19214 | M103: =M35 -> 21447 | ... U103: =U35 -> 38004 | V103: =V104*V109 -> 41899.41 | W103: =W104*W109 -> 46194.1 | X103: =X104*X109 -> 50928.995 | Y103: =SUM(U103:X103) -> 177026.5 | Z103: =Z104*Z109 -> 56149.217 | AA103: =AA104*AA109 -> 61904.511 | AB103: =AB104*AB109 -> 68249.724 | AC103: =AC104*AC109 -> 75245.321 | AD103: =SUM(Z103:AC103) -> 261548.77 | AE103: =AE104*AE109 -> 288357.52 | AF103: =AF104*AF109 -> 317914.17 | AG103: =AG104*AG109 -> 350500.37
C104: Volume | F104: 220 | G104: 220 | H104: 220 | I104: 220 | J104: =SUM(F104:I104) -> 880 | K104: 220 | L104: 220 | M104: 220 | N104: 220 | O104: =SUM(K104:N104) -> 880 | P104: 220 | Q104: 220 | R104: 220 | S104: 220 | T104: =SUM(P104:S104) -> 880 | U104: 220 | V104: =U104*(1+V105) -> 231 | W104: =V104*(1+W105) -> 242.55 | X104: =W104*(1+X105) -> 254.6775 | Y104: =SUM(U104:X104) -> 948.2275 | Z104: =X104*(1+Z105) -> 267.41138 | AA104: =Z104*(1+AA105) -> 280.78194 | AB104: =AA104*(1+AB105) -> 294.82104 | AC104: =AB104*(1+AC105) -> 309.56209 | AD104: =SUM(Z104:AC104) -> 1152.5765 | AE104: =AD104*(1+AE105) -> 1210.2053 | AF104: =AE104*(1+AF105) -> 1270.7155 | AG104: =AF104*(1+AG105) -> 1334.2513
C105: % Volume Growth | G105: =IFERROR(G104/F104-1,"--") -> 0 | H105: =IFERROR(H104/G104-1,"--") -> 0 | I105: =IFERROR(I104/H104-1,"--") -> 0 | K105: =IFERROR(K104/I104-1,"--") -> 0 | L105: =IFERROR(L104/K104-1,"--") -> 0 | M105: =IFERROR(M104/L104-1,"--") -> 0 | N105: =IFERROR(N104/M104-1,"--") -> 0 | O105: =IFERROR(O104/J104-1,"--") -> 0 | P105: =IFERROR(P104/N104-1,"--") -> 0 | Q105: =IFERROR(Q104/P104-1,"--") -> 0 | R105: =IFERROR(R104/Q104-1,"--") -> 0 | S105: =IFERROR(S104/R104-1,"--") -> 0 | T105: =IFERROR(T104/O104-1,"--") -> 0 | U105: =IFERROR(U104/S104-1,"--") -> 0 | V105: =IF(Case_Scenario="Bull",V106,IF(Case_Scenario="Base",V107,IF(Case_Scenario="bear",V108,"N/A"))) -> 0.05 | W105: =IF(Case_Scenario="Bull",W106,IF(Case_Scenario="Base",W107,IF(Case_Scenario="bear",W108,"N/A"))) -> 0.05 | X105: =IF(Case_Scenario="Bull",X106,IF(Case_Scenario="Base",X107,IF(Case_Scenario="bear",X108,"N/A"))) -> 0.05 | Z105: =IF(Case_Scenario="Bull",Z106,IF(Case_Scenario="Base",Z107,IF(Case_Scenario="bear",Z108,"N/A"))) -> 0.05 | AA105: =IF(Case_Scenario="Bull",AA106,IF(Case_Scenario="Base",AA107,IF(Case_Scenario="bear",AA108,"N/A"))) -> 0.05 | AB105: =IF(Case_Scenario="Bull",AB106,IF(Case_Scenario="Base",AB107,IF(Case_Scenario="bear",AB108,"N/A"))) -> 0.05 | AC105: =IF(Case_Scenario="Bull",AC106,IF(Case_Scenario="Base",AC107,IF(Case_Scenario="bear",AC108,"N/A"))) -> 0.05 | AE105: =IF(Case_Scenario="Bull",AE106,IF(Case_Scenario="Base",AE107,IF(Case_Scenario="bear",AE108,"N/A"))) -> 0.05 | AF105: =IF(Case_Scenario="Bull",AF106,IF(Case_Scenario="Base",AF107,IF(Case_Scenario="bear",AF108,"N/A"))) -> 0.05 | AG105: =IF(Case_Scenario="Bull",AG106,IF(Case_Scenario="Base",AG107,IF(Case_Scenario="bear",AG108,"N/A"))) -> 0.05
C106: Bull Case | V106: 0.1 | W106: 0.1 | X106: 0.1 | Z106: 0.1 | AA106: 0.1 | AB106: 0.1 | AC106: 0.1 | AE106: 0.1 | AF106: 0.1 | AG106: 0.1
C107: Base Case | V107: 0.05 | W107: 0.05 | X107: 0.05 | Z107: 0.05 | AA107: 0.05 | AB107: 0.05 | AC107: 0.05 | AE107: 0.05 | AF107: 0.05 | AG107: 0.05
C108: Bear Case | V108: 0 | W108: 0 | X108: 0 | Z108: 0 | AA108: 0 | AB108: 0 | AC108: 0 | AE108: 0 | AF108: 0 | AG108: 0
C109: Price | F109: =IFERROR(F103/F104,"--") -> 78.781818 | G109: =IFERROR(G103/G104,"--") -> 78.059091 | H109: =IFERROR(H103/H104,"--") -> 79.904545 | I109: =IFERROR(I103/I104,"--") -> 81.463636 | J109: =IFERROR(J103/J104,"--") -> 79.552273 | K109: =IFERROR(K103/K104,"--") -> 86.759091 | L109: =IFERROR(L103/L104,"--") -> 87.336364 | M109: =IFERROR(M103/M104,"--") -> 97.486364 | ... U109: =IFERROR(U103/U104,"--") -> 172.74545 | V109: =U109*(1+V110) -> 181.38273 | W109: =V109*(1+W110) -> 190.45186 | X109: =W109*(1+X110) -> 199.97446 | Y109: =Y103/Y104 -> 186.69202 | Z109: =X109*(1+Z110) -> 209.97318 | AA109: =Z109*(1+AA110) -> 220.47184 | AB109: =AA109*(1+AB110) -> 231.49543 | AC109: =AB109*(1+AC110) -> 243.0702 | AD109: =AD103/AD104 -> 226.92531 | AE109: =AD109*(1+AE110) -> 238.27158 | AF109: =AE109*(1+AF110) -> 250.18516 | AG109: =AF109*(1+AG110) -> 262.69442
C110: % Price Growth | G110: =IFERROR(G109/F109-1,"--") -> -0.0091737826 | H110: =IFERROR(H109/G109-1,"--") -> 0.023641763 | I110: =IFERROR(I109/H109-1,"--") -> 0.019511918 | K110: =IFERROR(K109/I109-1,"--") -> 0.065003906 | L110: =IFERROR(L109/K109-1,"--") -> 0.0066537434 | M110: =IFERROR(M109/L109-1,"--") -> 0.11621734 | N110: =IFERROR(N109/M109-1,"--") -> -0.0042430177 | O110: =IFERROR(O109/J109-1,"--") -> 0.15852927 | P110: =IFERROR(P109/N109-1,"--") -> 0.51283012 | Q110: =IFERROR(Q109/P109-1,"--") -> 0.54197103 | R110: =IFERROR(R109/Q109-1,"--") -> 0.1187924 | S110: =IFERROR(S109/R109-1,"--") -> -0.05262308 | T110: =IFERROR(T109/O109-1,"--") -> 1.3508705 | U110: =IFERROR(U109/S109-1,"--") -> -0.28026817 | V110: =IF(Case_Scenario="Bull",V111,IF(Case_Scenario="Base",V112,IF(Case_Scenario="bear",V113,"N/A"))) -> 0.05 | W110: =IF(Case_Scenario="Bull",W111,IF(Case_Scenario="Base",W112,IF(Case_Scenario="bear",W113,"N/A"))) -> 0.05 | X110: =IF(Case_Scenario="Bull",X111,IF(Case_Scenario="Base",X112,IF(Case_Scenario="bear",X113,"N/A"))) -> 0.05 | Z110: =IF(Case_Scenario="Bull",Z111,IF(Case_Scenario="Base",Z112,IF(Case_Scenario="bear",Z113,"N/A"))) -> 0.05 | AA110: =IF(Case_Scenario="Bull",AA111,IF(Case_Scenario="Base",AA112,IF(Case_Scenario="bear",AA113,"N/A"))) -> 0.05 | AB110: =IF(Case_Scenario="Bull",AB111,IF(Case_Scenario="Base",AB112,IF(Case_Scenario="bear",AB113,"N/A"))) -> 0.05 | AC110: =IF(Case_Scenario="Bull",AC111,IF(Case_Scenario="Base",AC112,IF(Case_Scenario="bear",AC113,"N/A"))) -> 0.05 | AE110: =IF(Case_Scenario="Bull",AE111,IF(Case_Scenario="Base",AE112,IF(Case_Scenario="bear",AE113,"N/A"))) -> 0.05 | AF110: =IF(Case_Scenario="Bull",AF111,IF(Case_Scenario="Base",AF112,IF(Case_Scenario="bear",AF113,"N/A"))) -> 0.05 | AG110: =IF(Case_Scenario="Bull",AG111,IF(Case_Scenario="Base",AG112,IF(Case_Scenario="bear",AG113,"N/A"))) -> 0.05
C111: Bull Case | V111: 0.1 | W111: 0.1 | X111: 0.1 | Z111: 0.1 | AA111: 0.1 | AB111: 0.1 | AC111: 0.1 | AE111: 0.1 | AF111: 0.1 | AG111: 0.1
C112: Base Case | V112: 0.05 | W112: 0.05 | X112: 0.05 | Z112: 0.05 | AA112: 0.05 | AB112: 0.05 | AC112: 0.05 | AE112: 0.05 | AF112: 0.05 | AG112: 0.05
C113: Bear Case | V113: 0 | W113: 0 | X113: 0 | Z113: 0 | AA113: 0 | AB113: 0 | AC113: 0 | AE113: 0 | AF113: 0 | AG113: 0
A115: x | C115: =C38 -> Segment 3 Revenue | F115: =F38 -> 0 | G115: =G38 -> 0 | H115: =H38 -> 0 | I115: =I38 -> 0 | J115: =J38 -> 0 | K115: =K38 -> 0 | L115: =L38 -> 0 | M115: =M38 -> 0 | ... U115: =U38 -> 0 | V115: =V116*V121 -> 0 | W115: =W116*W121 -> 0 | X115: =X116*X121 -> 0 | Y115: =SUM(U115:X115) -> 0 | Z115: =Z116*Z121 -> 0 | AA115: =AA116*AA121 -> 0 | AB115: =AB116*AB121 -> 0 | AC115: =AC116*AC121 -> 0 | AD115: =SUM(Z115:AC115) -> 0 | AE115: =AE116*AE121 -> 0 | AF115: =AF116*AF121 -> 0 | AG115: =AG116*AG121 -> 0
C116: Volume | F116: 220 | G116: 220 | H116: 220 | I116: 220 | J116: =SUM(F116:I116) -> 880 | K116: 220 | L116: 220 | M116: 220 | N116: 220 | O116: =SUM(K116:N116) -> 880 | P116: 220 | Q116: 220 | R116: 220 | S116: 220 | T116: =SUM(P116:S116) -> 880 | U116: 220 | V116: =U116*(1+V117) -> 231 | W116: =V116*(1+W117) -> 242.55 | X116: =W116*(1+X117) -> 254.6775 | Y116: =SUM(U116:X116) -> 948.2275 | Z116: =X116*(1+Z117) -> 267.41138 | AA116: =Z116*(1+AA117) -> 280.78194 | AB116: =AA116*(1+AB117) -> 294.82104 | AC116: =AB116*(1+AC117) -> 309.56209 | AD116: =SUM(Z116:AC116) -> 1152.5765 | AE116: =AD116*(1+AE117) -> 1210.2053 | AF116: =AE116*(1+AF117) -> 1270.7155 | AG116: =AF116*(1+AG117) -> 1334.2513
...

Sheet _CIQHiddenCacheSheet
