Workbook
Name __1_0_Table2_: [1]MERGER!#REF!
Name __FDS_HYPERLINK_TOGGLE_STATE__: "ON"
Name _1_0_Table2_: [1]MERGER!#REF!
Name _2_0_Table2_: [1]MERGER!#REF!
Name _3_0_Table2_: [1]MERGER!#REF!
Name _4_0_Table2_: [1]MERGER!#REF!
Name _5_0_Table2_: [1]MERGER!#REF!
Name _9_0_Table2_: [1]MERGER!#REF!
Name _AtRisk_SimSetting_AutomaticallyGenerateReports: FALSE
Name _AtRisk_SimSetting_AutomaticResultsDisplayMode: 0
Name _AtRisk_SimSetting_ConvergenceConfidenceLevel: 0.95
Name _AtRisk_SimSetting_ConvergencePercentileToTest: 0.9
Name _AtRisk_SimSetting_ConvergencePerformMeanTest: TRUE
Name _AtRisk_SimSetting_ConvergencePerformPercentileTest: FALSE
Name _AtRisk_SimSetting_ConvergencePerformStdDeviationTest: FALSE
Name _AtRisk_SimSetting_ConvergenceTestAllOutputs: TRUE
Name _AtRisk_SimSetting_ConvergenceTestingPeriod: 100
Name _AtRisk_SimSetting_ConvergenceTolerance: 0.03
Name _AtRisk_SimSetting_LiveUpdate: TRUE
Name _AtRisk_SimSetting_LiveUpdatePeriod: -1
Name _AtRisk_SimSetting_RandomNumberGenerator: 0
Name _AtRisk_SimSetting_ReportsList: 0
Name _AtRisk_SimSetting_SimNameCount: 0
Name _AtRisk_SimSetting_SmartSensitivityAnalysisEnabled: TRUE
Name _AtRisk_SimSetting_StatisticFunctionUpdating: 1
Name _AtRisk_SimSetting_StdRecalcBehavior: 0
Name _AtRisk_SimSetting_StdRecalcWithoutRiskStatic: 0
Name _AtRisk_SimSetting_StdRecalcWithoutRiskStaticPercentile: 0.5
Name _bdm.001de5d049b6489bbc2025ad50c87030.edm: Model!$1:$1048576
Name _bdm.146e958bbea04416b86a4d5943392c04.edm: Model!$M$102
Name _bdm.1ff456f35144482ea0525e6d75d0206f.edm: Integrity!$1:$1048576
Name _bdm.a65ed6e2cd6142fea39714a1a8762f97.edm: Integrity!$1:$1048576
Name _bdm.bf5a9ed53fe44c598e3cfb84ac34b21f.edm: Integrity!$F$37
Name _bdm.dca432f6461240c98baf2847c1b05465.edm: Integrity!$1:$1048576
Name _Fill: #REF!
Name _Key1: #REF!
Name _Order1: 255
Name _Order2: 255
Name _Sort: #REF!
Name _Table1_In1: [2]merger!#REF!
Name _Table1_Out: [2]merger!#REF!
Name _Table2_In1: [2]merger!#REF!
Name _Table2_Out: [2]merger!#REF!
Name a: {"summary1",#N/A,TRUE,"Comps";"summary2",#N/A,TRUE,"Comps";"summary3",#N/A,TRUE,"Comps"}
Name aaaaaaaa: {"summary1",#N/A,TRUE,"Comps";"summary2",#N/A,TRUE,"Comps";"summary3",#N/A,TRUE,"Comps"}
Name adsfsadfas: {"multiple",#N/A,FALSE,"client (2)";"margins",#N/A,FALSE,"client (2)";"data",#N/A,FALSE,"client (2)";"multiple",#N/A,FALSE,"client";"margins",#N/A,FALSE,"client";"data",#N/A,FALSE,"client"}
Name adsfsdfe: {"Page1",#N/A,FALSE,"CompCo";"Page2",#N/A,FALSE,"CompCo"}
Name aefae: {"inputs raw data",#N/A,TRUE,"INPUT"}
Name aefe: {"cap_structure",#N/A,FALSE,"Graph-Mkt Cap";"price",#N/A,FALSE,"Graph-Price";"ebit",#N/A,FALSE,"Graph-EBITDA";"ebitda",#N/A,FALSE,"Graph-EBITDA"}
Name al: '[3]2010 Labor Rates 091130'!$A$161
Name al09salary: [3]Salaries!$G$13
Name al10salary: [3]Salaries!$K$13
Name alid: '[3]2010 Labor Rates 091130'!$E$168
Name alname: [3]Salaries!$A$13
Name aprpto: [3]Vacation!$I$56
Name asdfasdfas: {"cap_structure",#N/A,FALSE,"Graph-Mkt Cap";"price",#N/A,FALSE,"Graph-Price";"ebit",#N/A,FALSE,"Graph-EBITDA";"ebitda",#N/A,FALSE,"Graph-EBITDA"}
Name asdfsdfasdf: {"Page1",#N/A,FALSE,"CompCo";"Page2",#N/A,FALSE,"CompCo"}
Name augpto: [3]Vacation!$M$56
Name avg_Health_and_Welfare: [4]PBCFringe!$Q$22
Name awefweawe: {"Page1",#N/A,FALSE,"CompCo";"Page2",#N/A,FALSE,"CompCo"}

Sheet Cover
C1: =Company_Name&" - "&MID(CELL("filename",A1),FIND("]",CELL("filename",A1))+1,255)&": "&Case_Scenario&" Case" -> Hamilton Lane Inc. - Cover: Base Case | Q1: Font Toggle
C2: $ in Millions Except Per Share Data | Q2: Report
R3: x
A4: x | C4: Model Assumptions: | I4: Return Summary:
I6: Discounted Cash Flow Analysis | N6: Multiple Analysis
I8: Exit Multiple Method | N8: EV/EBITDA Method
I9: Implied Enterprise Value: | L9: =Valuation!K65 -> 8117.2262 | P9: Target Price: | Q9: % Return:
I10: Implied Equity Value: | L10: =Valuation!K72 -> 7855.7462
N11: 1 Year LTM EV/EBITDA | P11: =Valuation!N137 -> 104.36318 | Q11: =Valuation!N138 -> -0.11751072
I12: Implied Share Price: | L12: =Valuation!K76 -> 144.22152
I13: % Return: | L13: =Valuation!K77 -> 0.21952917 | N13: 2009-2018 Late Cycle EV/EBITDA | P13: =Valuation!N215 -> 52.268602 | Q13: =Valuation!N216 -> -0.5580196
I15: Perpetuity Growth Method | N15: P/E Multiple Method
I16: Implied Enterprise Value: | L16: =Valuation!R65 -> 5013.5852 | P16: Target Price: | Q16: % Return:
I17: Implied Equity Value: | L17: =Valuation!R72 -> 4752.1052
N18: 1 Year LTM P/E | P18: =Valuation!F126 -> 144.38346 | Q18: =Valuation!F127 -> 0.22089852
C19: Company Name | F19: Hamilton Lane Inc. | I19: Implied Share Price: | L19: =Valuation!R76 -> 87.242614
C20: Ticker | F20: HLNE | I20: % Return: | L20: =Valuation!R77 -> -0.2622813 | N20: 2009-2018 Late Cycle P/E | P20: =Valuation!F204 -> 107.29422 | Q20: =Valuation!F205 -> -0.092726057
C22: Case Scenario | F22: Base | I22: Table of Contents
C24: Last Fiscal Year | F24: 45747 | I24: Cover
C25: Next Fiscal Year | F25: =Last_FYE+365 -> 46112 | I25: Summary
C26: Last Fiscal Quarter Reported | F26: 1Q | I26: Football Field
C27: Current Valuation Date | F27: 45940 | I27: Integrity
I28: Revenue Build
C29: Current Share Price | F29: 118.26 | I29: Model
C30: 52-Week High | F30: 203.72 | I30: Segment Analysis
C31: 52-Week Low | F31: 124.1 | I31: Drivers
I32: WACC
C33: Effective Tax Rate | F33: =IF(Last_FQR="1Q",Model!U71,IF(Last_FQR="2Q",Model!V71,IF(Last_FQR="3Q",Model!W71,Model!X71))) -> 0.19255309 | I33: Valuation
C34: Dividend Yield | F34: =IF(Last_FQR="1Q",Model!U266,IF(Last_FQR="2Q",Model!V266,IF(Last_FQR="3Q",Model!W266,Model!X266))) -> 0.013084722 | I34: Comparables
C35: Diluted Shares Outstanding (MRQ) | F35: =IF(Last_FQR="1Q",Model!U285,IF(Last_FQR="2Q",Model!V285,IF(Last_FQR="3Q",Model!W285,Model!X285))) -> 54.47 | I35: Charts
I36: Benchmark
C37: Model Type | F37: Top Down | I37: Multiples Data
I38: Pre-Earnings
I39: Post-Earnings
A42: x
C43: Model Color Legend | I43: Constants
C44: Blue = Hard-Coded Value (historical values & assumptions) | I44: Reference | J44: Type | K44: Name | L44: Value
C45: Black = Formulas | I45: Million | J45: (#) | K45: Mil | L45: 1000000
C46: Green = Linked Value (from separate worksheet) | I46: Thousand | J46: (#) | K46: Thou | L46: 1000
C47: Red = Unique Formula / Anomaly | I47: Hundred | J47: (#) | K47: Hun | L47: 100
A48: x
C49: Tab Color Codes
C51: Summary
C53: Model
A54: x
C55: Supporting/Auxiliary
C57: Valuation
C59: Comps
C61: RBG Codes for Model
C63: 0-0-255 | F63: Hard-Coded Numbers
C65: 0-128-0 | F65: Linked Numbers
C67: 255-223-159 | F67: Owl Fund Gold
C69: 255-255-153 | F69: Drivers / Assumptions
C71: 118-0-0 | F71: Owl Fund Red
C73: 0-56-96 | F73: Section Headers
C75: 192-222-246 | F75: Sub-Section Headers
C77: 215-215-215 | F77: Historical Quarters
C79: 235-235-235 | F79: Projected Quarters
C81: 255-255-255 | F81: Annuals
A83: x | B83: x | C83: END

Sheet Summary
C1: =Company_Name&" - "&MID(CELL("filename",A1),FIND("]",CELL("filename",A1))+1,255)&": "&Case_Scenario&" Case" -> Hamilton Lane Inc. - Summary: Base Case
C2: =Cover!C2 -> $ in Millions Except Per Share Data
C4: Year: | T4: =Model!J24 -> 2023 | U4: =Model!O24 -> 2024 | V4: =Model!T24 -> 2025 | W4: =Model!Y24 -> 2026 | X4: =Model!AD24 -> 2027 | Y4: =Model!AE24 -> 2028 | Z4: =Model!AF24 -> 2029 | AA4: =Model!AG24 -> 2030
G5: Quarterly | T5: Annuals | AC5: CAGR | AE5: CAGR
A6: x | C6: ="Consolidated "&Model!C25 -> Consolidated Income Statement | G6: =Model!P25 -> 1Q25 | H6: =Model!Q25 -> 2Q25 | I6: =Model!R25 -> 3Q25 | J6: =Model!S25 -> 4Q25 | K6: =Model!U25 -> 1Q26 | L6: =Model!V25 -> 2Q26e | M6: =Model!W25 -> 3Q26e | N6: =Model!X25 -> 4Q26e | O6: =Model!Z25 -> 1Q27e | P6: =Model!AA25 -> 2Q27e | Q6: =Model!AB25 -> 3Q27e | R6: =Model!AC25 -> 4Q27e | T6: =Model!J25 -> 2023 | U6: =Model!O25 -> 2024 | V6: =Model!T25 -> 2025 | W6: =Model!Y25 -> 2026e | X6: =Model!AD25 -> 2027e | Y6: =Model!AE25 -> 2028e | Z6: =Model!AF25 -> 2029e | AA6: =Model!AG25 -> 2030e | AC6: Historical | AE6: Projected
C8: =Model!C28 -> Revenue | G8: =Model!P28 -> 196.731 | H8: =Model!Q28 -> 149.999 | I8: =Model!R28 -> 168.261 | J8: =Model!S28 -> 197.973 | K8: =Model!U28 -> 175.958 | L8: =Model!V28 -> 183.91066 | M8: =Model!W28 -> 195.21191 | N8: =Model!X28 -> 211.57639 | O8: =Model!Z28 -> 224.51778 | P8: =Model!AA28 -> 237.98885 | Q8: =Model!AB28 -> 249.25561 | R8: =Model!AC28 -> 260.76606 | T8: =Model!J28 -> 528.753 | U8: =Model!O28 -> 553.842 | V8: =Model!T28 -> 712.964 | W8: =Model!Y28 -> 766.65695 | X8: =Model!AD28 -> 972.5283 | Y8: =Model!AE28 -> 1040.6053 | Z8: =Model!AF28 -> 1097.8386 | AA8: =Model!AG28 -> 1169.5212 | AC8: =IFERROR((V8/T8)^(1/(V$4-T$4))-1,"N/A") -> 0.16120094 | AE8: =IFERROR((AA8/V8)^(1/(AA$4-V$4))-1,"N/A") -> 0.10404837
C9: YoY % Growth | K9: =K8/G8-1 -> -0.10559088 | L9: =L8/H8-1 -> 0.22607924 | M9: =M8/I8-1 -> 0.16017321 | N9: =N8/J8-1 -> 0.068713335 | O9: =O8/K8-1 -> 0.27597371 | P9: =P8/L8-1 -> 0.29404598 | Q9: =Q8/M8-1 -> 0.27684633 | R9: =R8/N8-1 -> 0.23249133 | U9: =IF(ISERROR(U8/T8-1),"NA",(U8/T8-1)) -> 0.047449376 | V9: =IF(ISERROR(V8/U8-1),"NA",(V8/U8-1)) -> 0.28730577 | W9: =IF(ISERROR(W8/V8-1),"NA",(W8/V8-1)) -> 0.075309483 | X9: =IF(ISERROR(X8/W8-1),"NA",(X8/W8-1)) -> 0.26853125 | Y9: =IF(ISERROR(Y8/X8-1),"NA",(Y8/X8-1)) -> 0.07 | Z9: =IF(ISERROR(Z8/Y8-1),"NA",(Z8/Y8-1)) -> 0.055 | AA9: =IF(ISERROR(AA8/Z8-1),"NA",(AA8/Z8-1)) -> 0.065294368
C11: =Model!C30 -> Gross Profit | G11: =Model!P30 -> 196.731 | H11: =Model!Q30 -> 149.999 | I11: =Model!R30 -> 168.261 | J11: =Model!S30 -> 197.973 | K11: =Model!U30 -> 175.958 | L11: =Model!V30 -> 183.91066 | M11: =Model!W30 -> 195.21191 | N11: =Model!X30 -> 211.57639 | O11: =Model!Z30 -> 224.51778 | P11: =Model!AA30 -> 237.98885 | Q11: =Model!AB30 -> 249.25561 | R11: =Model!AC30 -> 260.76606 | T11: =Model!J30 -> 528.753 | U11: =Model!O30 -> 553.842 | V11: =Model!T30 -> 712.964 | W11: =Model!Y30 -> 766.65695 | X11: =Model!AD30 -> 972.5283 | Y11: =Model!AE30 -> 1040.6053 | Z11: =Model!AF30 -> 1097.8386 | AA11: =Model!AG30 -> 1169.5212 | AC11: =IFERROR((V11/T11)^(1/(V$4-T$4))-1,"N/A") -> 0.16120094 | AE11: =IFERROR((AA11/V11)^(1/(AA$4-V$4))-1,"N/A") -> 0.10404837
C12: % Margin | G12: =G11/G$8 -> 1 | H12: =H11/H$8 -> 1 | I12: =I11/I$8 -> 1 | J12: =J11/J$8 -> 1 | K12: =K11/K$8 -> 1 | L12: =L11/L$8 -> 1 | M12: =M11/M$8 -> 1 | N12: =N11/N$8 -> 1 | ... R12: =R11/R$8 -> 1 | T12: =T11/T$8 -> 1 | U12: =U11/U$8 -> 1 | V12: =V11/V$8 -> 1 | W12: =W11/W$8 -> 1 | X12: =X11/X$8 -> 1 | Y12: =Y11/Y$8 -> 1 | Z12: =Z11/Z$8 -> 1 | AA12: =AA11/AA$8 -> 1
C13: YoY % Growth | K13: =K11/G11-1 -> -0.10559088 | L13: =L11/H11-1 -> 0.22607924 | M13: =M11/I11-1 -> 0.16017321 | N13: =N11/J11-1 -> 0.068713335 | O13: =O11/K11-1 -> 0.27597371 | P13: =P11/L11-1 -> 0.29404598 | Q13: =Q11/M11-1 -> 0.27684633 | R13: =R11/N11-1 -> 0.23249133 | U13: =U11/T11-1 -> 0.047449376 | V13: =V11/U11-1 -> 0.28730577 | W13: =W11/V11-1 -> 0.075309483 | X13: =X11/W11-1 -> 0.26853125 | Y13: =Y11/X11-1 -> 0.07 | Z13: =Z11/Y11-1 -> 0.055 | AA13: =AA11/Z11-1 -> 0.065294368
C15: =Model!C36 -> EBIT | G15: =Model!P36 -> 89.611 | H15: =Model!Q36 -> 67.192 | I15: =Model!R36 -> 75.722 | J15: =Model!S36 -> 84.028 | K15: =Model!U36 -> 76.975 | L15: =Model!V36 -> 79.633316 | M15: =Model!W36 -> 84.526755 | N15: =Model!X36 -> 91.612575 | O15: =Model!Z36 -> 96.542647 | P15: =Model!AA36 -> 102.33521 | Q15: =Model!AB36 -> 107.17991 | R15: =Model!AC36 -> 112.12941 | T15: =Model!J36 -> 239.912 | U15: =Model!O36 -> 245.817 | V15: =Model!T36 -> 316.553 | W15: =Model!Y36 -> 332.74765 | X15: =Model!AD36 -> 418.18717 | Y15: =Model!AE36 -> 437.05422 | Z15: =Model!AF36 -> 461.0922 | AA15: =Model!AG36 -> 491.19892 | AC15: =IFERROR((V15/T15)^(1/(V$4-T$4))-1,"N/A") -> 0.14867516 | AE15: =IFERROR((AA15/V15)^(1/(AA$4-V$4))-1,"N/A") -> 0.091848029
C16: Margin | G16: =G15/G$8 -> 0.45550015 | H16: =H15/H$8 -> 0.44794965 | I16: =I15/I$8 -> 0.45002704 | J16: =J15/J$8 -> 0.42444172 | K16: =K15/K$8 -> 0.43746235 | L16: =L15/L$8 -> 0.433 | M16: =M15/M$8 -> 0.433 | N16: =N15/N$8 -> 0.433 | ... R16: =R15/R$8 -> 0.43 | T16: =T15/T$8 -> 0.4537317 | U16: =U15/U$8 -> 0.44383958 | V16: =V15/V$8 -> 0.44399577 | W16: =W15/W$8 -> 0.43402417 | X16: =X15/X$8 -> 0.43 | Y16: =Y15/Y$8 -> 0.42 | Z16: =Z15/Z$8 -> 0.42 | AA16: =AA15/AA$8 -> 0.42
C17: YoY % Growth | K17: =K15/G15-1 -> -0.14100947 | L17: =L15/H15-1 -> 0.18516067 | M17: =M15/I15-1 -> 0.11627737 | N17: =N15/J15-1 -> 0.090262469 | O17: =O15/K15-1 -> 0.25420781 | P17: =P15/L15-1 -> 0.2850803 | Q17: =Q15/M15-1 -> 0.26799982 | R17: =R15/N15-1 -> 0.22395213 | U17: =U15/T15-1 -> 0.024613192 | V17: =V15/U15-1 -> 0.28775878 | W17: =W15/V15-1 -> 0.051159349 | X17: =X15/W15-1 -> 0.25676973 | Y17: =Y15/X15-1 -> 0.045116279 | Z17: =Z15/Y15-1 -> 0.055 | AA17: =AA15/Z15-1 -> 0.065294368
C19: =Model!C45 -> Net Income (Loss) | G19: =Model!P45 -> 87.087 | H19: =Model!Q45 -> 75.922 | I19: =Model!R45 -> 77.455 | J19: =Model!S45 -> 73.304 | K19: =Model!U45 -> 77.07 | L19: =Model!V45 -> 67.837287 | M19: =Model!W45 -> 72.074365 | N19: =Model!X45 -> 78.129684 | O19: =Model!Z45 -> 84.212015 | P19: =Model!AA45 -> 89.098414 | Q19: =Model!AB45 -> 90.400262 | R19: =Model!AC45 -> 94.386421 | T19: =Model!J45 -> 187.056 | U19: =Model!O45 -> 227.204 | V19: =Model!T45 -> 313.768 | W19: =Model!Y45 -> 295.11134 | X19: =Model!AD45 -> 358.09711 | Y19: =Model!AE45 -> 374.51536 | Z19: =Model!AF45 -> 395.85242 | AA19: =Model!AG45 -> 422.14236 | AC19: =IFERROR((V19/T19)^(1/(V$4-T$4))-1,"N/A") -> 0.29514533 | AE19: =IFERROR((AA19/V19)^(1/(AA$4-V$4))-1,"N/A") -> 0.061133577
C20: Margin | G20: =G19/G$8 -> 0.44267045 | H20: =H19/H$8 -> 0.50615004 | I20: =I19/I$8 -> 0.46032652 | J20: =J19/J$8 -> 0.37027271 | K20: =K19/K$8 -> 0.43800225 | L20: =L19/L$8 -> 0.36886 | M20: =M19/M$8 -> 0.36921091 | N20: =N19/N$8 -> 0.36927412 | ... R20: =R19/R$8 -> 0.36195823 | T20: =T19/T$8 -> 0.35376821 | U20: =U19/U$8 -> 0.41023252 | V20: =V19/V$8 -> 0.44008954 | W20: =W19/W$8 -> 0.38493271 | X20: =X19/X$8 -> 0.36821254 | Y20: =Y19/Y$8 -> 0.35990146 | Z20: =Z19/Z$8 -> 0.36057434 | AA20: =AA19/AA$8 -> 0.36095314
C21: YoY % Growth | K21: =K19/G19-1 -> -0.11502291 | L21: =L19/H19-1 -> -0.1064871 | M21: =M19/I19-1 -> -0.069467879 | N21: =N19/J19-1 -> 0.065831113 | O21: =O19/K19-1 -> 0.092669199 | P21: =P19/L19-1 -> 0.31341359 | Q21: =Q19/M19-1 -> 0.25426372 | R21: =R19/N19-1 -> 0.20807376 | U21: =U19/T19-1 -> 0.21463091 | V21: =V19/U19-1 -> 0.38099681 | W21: =W19/V19-1 -> -0.05946006 | X21: =X19/W19-1 -> 0.21343056 | Y21: =Y19/X19-1 -> 0.045848579 | Z21: =Z19/Y19-1 -> 0.05697246 | AA21: =AA19/Z19-1 -> 0.066413498
C23: =Model!C57 -> Adj. EPS (Diluted) | G23: =Model!P57 -> 1.0909158 | H23: =Model!Q57 -> 1.0148025 | I23: =Model!R57 -> 0.97375 | J23: =Model!S57 -> 1.2530769 | K23: =Model!U57 -> 0.98668992 | L23: =Model!V57 -> 0.87400613 | M23: =Model!W57 -> 0.9289711 | N23: =Model!X57 -> 1.0098351 | O23: =Model!Z57 -> 1.1213841 | P23: =Model!AA57 -> 1.185597 | Q23: =Model!AB57 -> 1.2097494 | R23: =Model!AC57 -> 1.265593 | T23: =Model!J57 -> 2.0297218 | U23: =Model!O57 -> 2.613321 | V23: =Model!T57 -> 5.3949628 | W23: =Model!Y57 -> 3.7993392 | X23: =Model!AD57 -> 4.782132 | Y23: =Model!AE57 -> 5.2892288 | Z23: =Model!AF57 -> 5.5611767 | AA23: =Model!AG57 -> 5.965623 | AC23: =IFERROR((V23/T23)^(1/(V$4-T$4))-1,"N/A") -> 0.63033169 | AE23: =IFERROR((AA23/V23)^(1/(AA$4-V$4))-1,"N/A") -> 0.020313118
C24: YoY % Growth | K24: =K23/G23-1 -> -0.095539817 | L24: =L23/H23-1 -> -0.13874264 | M24: =M23/I23-1 -> -0.045986033 | N24: =N23/J23-1 -> -0.19411566 | O24: =O23/K23-1 -> 0.13651111 | P24: =P23/L23-1 -> 0.35650874 | Q24: =Q23/M23-1 -> 0.30224655 | R24: =R23/N23-1 -> 0.25326703 | U24: =IF(ISERROR(U23/T23-1),"NA",(U23/T23-1)) -> 0.28752669 | V24: =IF(ISERROR(V23/U23-1),"NA",(V23/U23-1)) -> 1.0644088 | W24: =IF(ISERROR(W23/V23-1),"NA",(W23/V23-1)) -> -0.29576174 | X24: =IF(ISERROR(X23/W23-1),"NA",(X23/W23-1)) -> 0.25867467 | Y24: =IF(ISERROR(Y23/X23-1),"NA",(Y23/X23-1)) -> 0.10603989 | Z24: =IF(ISERROR(Z23/Y23-1),"NA",(Z23/Y23-1)) -> 0.051415408 | AA24: =IF(ISERROR(AA23/Z23-1),"NA",(AA23/Z23-1)) -> 0.072726758
C27: =Model!C61 -> EBITDA | G27: =Model!P61 -> 61.488 | H27: =Model!Q61 -> 46.252 | I27: =Model!R61 -> 51.239 | J27: =Model!S61 -> 61.223 | K27: =Model!U61 -> 53.65 | L27: =Model!V61 -> 59.403143 | M27: =Model!W61 -> 63.053445 | N27: =Model!X61 -> 68.339172 | O27: =Model!Z61 -> 73.080538 | P27: =Model!AA61 -> 77.465371 | Q27: =Model!AB61 -> 82.316664 | R27: =Model!AC61 -> 86.117992 | T27: =Model!J61 -> 161.848 | U27: =Model!O61 -> 159.471 | V27: =Model!T61 -> 220.202 | W27: =Model!Y61 -> 244.44576 | X27: =Model!AD61 -> 318.98056 | Y27: =Model!AE61 -> 346.72968 | Z27: =Model!AF61 -> 362.39651 | AA27: =Model!AG61 -> 386.05896 | AC27: =IFERROR((V27/T27)^(1/(V$4-T$4))-1,"N/A") -> 0.16642538 | AE27: =IFERROR((AA27/V27)^(1/(AA$4-V$4))-1,"N/A") -> 0.11883611
C28: Margin | G28: =G27/G$8 -> 0.31254861 | H28: =H27/H$8 -> 0.30834872 | I28: =I27/I$8 -> 0.30452095 | J28: =J27/J$8 -> 0.30924924 | K28: =K27/K$8 -> 0.30490231 | L28: =L27/L$8 -> 0.323 | M28: =M27/M$8 -> 0.323 | N28: =N27/N$8 -> 0.323 | ... R28: =R27/R$8 -> 0.33025 | T28: =T27/T$8 -> 0.30609377 | U28: =U27/U$8 -> 0.28793591 | V28: =V27/V$8 -> 0.3088543 | W28: =W27/W$8 -> 0.31884634 | X28: =X27/X$8 -> 0.32799104 | Y28: =Y27/Y$8 -> 0.3332 | Z28: =Z27/Z$8 -> 0.3301 | AA28: =AA27/AA$8 -> 0.3301
C29: YoY % Growth | K29: =K27/G27-1 -> -0.12747203 | L29: =L27/H27-1 -> 0.28433675 | M29: =M27/I27-1 -> 0.23057525 | N29: =N27/J27-1 -> 0.11623364 | O29: =O27/K27-1 -> 0.36217219 | P29: =P27/L27-1 -> 0.30406181 | Q29: =Q27/M27-1 -> 0.3055062 | R29: =R27/N27-1 -> 0.26015561 | U29: =U27/T27-1 -> -0.01468662 | V29: =V27/U27-1 -> 0.38082786 | W29: =W27/V27-1 -> 0.11009782 | X29: =X27/W27-1 -> 0.30491346 | Y29: =Y27/X27-1 -> 0.086993122 | Z29: =Z27/Y27-1 -> 0.045184574 | AA29: =AA27/Z27-1 -> 0.065294368
G31: =G$5 -> Quarterly | T31: =T$5 -> Annuals
A32: x | C32: ="Consolidated "&Model!C120 -> Consolidated Balance Sheet | G32: =G$6 -> 1Q25 | H32: =H$6 -> 2Q25 | I32: =I$6 -> 3Q25 | J32: =J$6 -> 4Q25 | K32: =K$6 -> 1Q26 | L32: =L$6 -> 2Q26e | M32: =M$6 -> 3Q26e | N32: =N$6 -> 4Q26e | ... R32: =R$6 -> 4Q27e | T32: =T$6 -> 2023 | U32: =U$6 -> 2024 | V32: =V$6 -> 2025 | W32: =W$6 -> 2026e | X32: =X$6 -> 2027e | Y32: =Y$6 -> 2028e | Z32: =Z$6 -> 2029e | AA32: =AA$6 -> 2030e
C34: =Model!C122 -> Cash & Cash Equivalents | G34: =Model!P122 -> 151.663 | H34: =Model!Q122 -> 193.771 | I34: =Model!R122 -> 285.553 | J34: =Model!S122 -> 229.161 | K34: =Model!U122 -> 263.347 | L34: =Model!V122 -> 261.16987 | M34: =Model!W122 -> 283.12019 | N34: =Model!X122 -> 273.99227 | O34: =Model!Z122 -> 248.19035 | P34: =Model!AA122 -> 244.48216 | Q34: =Model!AB122 -> 235.06938 | R34: =Model!AC122 -> 206.78503 | T34: =Model!J122 -> 99.686 | U34: =Model!O122 -> 114.634 | V34: =Model!T122 -> 229.161 | W34: =Model!Y122 -> 273.99227 | X34: =Model!AD122 -> 206.78503 | Y34: =Model!AE122 -> 256.12555 | Z34: =Model!AF122 -> 269.77717 | AA34: =Model!AG122 -> 252.11707
C35: =Model!C123 -> Fees Receivable | G35: =Model!P123 -> 141.099 | H35: =Model!Q123 -> 95.509 | I35: =Model!R123 -> 135.622 | J35: =Model!S123 -> 181.411 | K35: =Model!U123 -> 158.061 | L35: =Model!V123 -> 159.6587 | M35: =Model!W123 -> 167.62761 | N35: =Model!X123 -> 181.67972 | O35: =Model!Z123 -> 212.18164 | P35: =Model!AA123 -> 224.91254 | Q35: =Model!AB123 -> 232.9998 | R35: =Model!AC123 -> 243.75958 | T35: =Model!J123 -> 47.14 | U35: =Model!O123 -> 108.291 | V35: =Model!T123 -> 181.411 | W35: =Model!Y123 -> 181.67972 | X35: =Model!AD123 -> 243.75958 | Y35: =Model!AE123 -> 222.37592 | Z35: =Model!AF123 -> 240.62215 | AA35: =Model!AG123 -> 256.33342
C36: =Model!C124 -> Inventory | G36: =Model!P124 -> 0 | H36: =Model!Q124 -> 0 | I36: =Model!R124 -> 0 | J36: =Model!S124 -> 0 | K36: =Model!U124 -> 0 | L36: =Model!V124 -> 0 | M36: =Model!W124 -> 0 | N36: =Model!X124 -> 0 | O36: =Model!Z124 -> 0 | P36: =Model!AA124 -> 0 | Q36: =Model!AB124 -> 0 | R36: =Model!AC124 -> 0 | T36: =Model!J124 -> 0 | U36: =Model!O124 -> 0 | V36: =Model!T124 -> 0 | W36: =Model!Y124 -> 0 | X36: =Model!AD124 -> 0 | Y36: =Model!AE124 -> 0 | Z36: =Model!AF124 -> 0 | AA36: =Model!AG124 -> 0
C37: =Model!C125 -> Prepaid & Other Current Assets | G37: =Model!P125 -> 26.492 | H37: =Model!Q125 -> 39.075 | I37: =Model!R125 -> 36.643 | J37: =Model!S125 -> 33.806 | K37: =Model!U125 -> 36.945 | L37: =Model!V125 -> 36.782132 | M37: =Model!W125 -> 39.042381 | N37: =Model!X125 -> 42.315277 | O37: =Model!Z125 -> 44.903557 | P37: =Model!AA125 -> 47.59777 | Q37: =Model!AB125 -> 49.851121 | R37: =Model!AC125 -> 52.153212 | T37: =Model!J125 -> 21.807 | U37: =Model!O125 -> 24.208 | V37: =Model!T125 -> 33.806 | W37: =Model!Y125 -> 42.315277 | X37: =Model!AD125 -> 52.153212 | Y37: =Model!AE125 -> 57.23329 | Z37: =Model!AF125 -> 60.381121 | AA37: =Model!AG125 -> 64.323668
C38: =Model!C126 -> Total Current Assets | G38: =SUM(G34:G37) -> 319.254 | H38: =SUM(H34:H37) -> 328.355 | I38: =SUM(I34:I37) -> 457.818 | J38: =SUM(J34:J37) -> 444.378 | K38: =SUM(K34:K37) -> 458.353 | L38: =SUM(L34:L37) -> 457.61071 | M38: =SUM(M34:M37) -> 489.79018 | N38: =SUM(N34:N37) -> 497.98726 | ... R38: =SUM(R34:R37) -> 502.69782 | T38: =SUM(T34:T37) -> 168.633 | U38: =SUM(U34:U37) -> 247.133 | V38: =SUM(V34:V37) -> 444.378 | W38: =SUM(W34:W37) -> 497.98726 | X38: =SUM(X34:X37) -> 502.69782 | Y38: =SUM(Y34:Y37) -> 535.73476 | Z38: =SUM(Z34:Z37) -> 570.78044 | AA38: =SUM(AA34:AA37) -> 572.77416
C40: =Model!C128 -> PP&E, Net | G40: =Model!P128 -> 95.085 | H40: =Model!Q128 -> 95.255 | I40: =Model!R128 -> 97.373 | J40: =Model!S128 -> 98.999 | K40: =Model!U128 -> 96.677 | L40: =Model!V128 -> 98.883928 | M40: =Model!W128 -> 101.22647 | N40: =Model!X128 -> 103.34223 | O40: =Model!Z128 -> 105.13838 | P40: =Model!AA128 -> 107.04229 | Q40: =Model!AB128 -> 109.03633 | R40: =Model!AC128 -> 111.12246 | T40: =Model!J128 -> 90.752 | U40: =Model!O128 -> 95.438 | V40: =Model!T128 -> 98.999 | W40: =Model!Y128 -> 103.34223 | X40: =Model!AD128 -> 111.12246 | Y40: =Model!AE128 -> 119.4473 | Z40: =Model!AF128 -> 128.23001 | AA40: =Model!AG128 -> 137.58618
C41: =Model!C129 -> Investments and Assets of Consolidated Variable Interest Entities | G41: =Model!P129 -> 698.273 | H41: =Model!Q129 -> 743.533 | I41: =Model!R129 -> 780.836 | J41: =Model!S129 -> 838.453 | K41: =Model!U129 -> 945.038 | L41: =Model!V129 -> 973.38914 | M41: =Model!W129 -> 1002.5908 | N41: =Model!X129 -> 1032.6685 | O41: =Model!Z129 -> 1104.9553 | P41: =Model!AA129 -> 1171.2527 | Q41: =Model!AB129 -> 1235.6716 | R41: =Model!AC129 -> 1297.4551 | T41: =Model!J129 -> 647.246 | U41: =Model!O129 -> 666.742 | V41: =Model!T129 -> 838.453 | W41: =Model!Y129 -> 1032.6685 | X41: =Model!AD129 -> 1297.4551 | Y41: =Model!AE129 -> 1492.0734 | Z41: =Model!AF129 -> 1715.8844 | AA41: =Model!AG129 -> 1973.2671
C42: =Model!C130 -> Deferred Income Taxes | G42: =Model!P130 -> 259.301 | H42: =Model!Q130 -> 257.187 | I42: =Model!R130 -> 255.001 | J42: =Model!S130 -> 308.525 | K42: =Model!U130 -> 301.97 | L42: =Model!V130 -> 285.06152 | M42: =Model!W130 -> 302.57845 | N42: =Model!X130 -> 327.9434 | O42: =Model!Z130 -> 348.00256 | P42: =Model!AA130 -> 368.88272 | Q42: =Model!AB130 -> 386.34619 | R42: =Model!AC130 -> 404.18739 | T42: =Model!J130 -> 233.912 | U42: =Model!O130 -> 261.887 | V42: =Model!T130 -> 308.525 | W42: =Model!Y130 -> 327.9434 | X42: =Model!AD130 -> 404.18739 | Y42: =Model!AE130 -> 437.05422 | Z42: =Model!AF130 -> 461.0922 | AA42: =Model!AG130 -> 491.19892
C43: =Model!#REF! -> #REF! | G43: =Model!#REF! -> #REF! | H43: =Model!#REF! -> #REF! | I43: =Model!#REF! -> #REF! | J43: =Model!#REF! -> #REF! | K43: =Model!#REF! -> #REF! | L43: =Model!#REF! -> #REF! | M43: =Model!#REF! -> #REF! | N43: =Model!#REF! -> #REF! | ... R43: =Model!#REF! -> #REF! | T43: =Model!#REF! -> #REF! | U43: =Model!#REF! -> #REF! | V43: =Model!#REF! -> #REF! | W43: =Model!#REF! -> #REF! | X43: =Model!#REF! -> #REF! | Y43: =Model!#REF! -> #REF! | Z43: =Model!#REF! -> #REF! | AA43: =Model!#REF! -> #REF!
C44: =Model!C131 -> Total Non-Current Assets | G44: =SUM(G40:G42) -> 1052.659 | H44: =SUM(H40:H42) -> 1095.975 | I44: =SUM(I40:I42) -> 1133.21 | J44: =SUM(J40:J42) -> 1245.977 | K44: =SUM(K40:K42) -> 1343.685 | L44: =SUM(L40:L42) -> 1357.3346 | M44: =SUM(M40:M42) -> 1406.3957 | N44: =SUM(N40:N42) -> 1463.9542 | ... AA44: =SUM(AA40:AA42) -> 2602.0522
C46: =Model!C133 -> Total Assets | G46: =SUM(G38,G44) -> 1371.913 | H46: =SUM(H38,H44) -> 1424.33 | I46: =SUM(I38,I44) -> 1591.028 | J46: =SUM(J38,J44) -> 1690.355 | K46: =SUM(K38,K44) -> 1802.038 | L46: =SUM(L38,L44) -> 1814.9453 | M46: =SUM(M38,M44) -> 1896.1859 | N46: =SUM(N38,N44) -> 1961.9414 | ... R46: =SUM(R38,R44) -> 2315.4628 | T46: =SUM(T38,T44) -> 1140.543 | U46: =SUM(U38,U44) -> 1271.2 | V46: =SUM(V38,V44) -> 1690.355 | W46: =SUM(W38,W44) -> 1961.9414 | X46: =SUM(X38,X44) -> 2315.4628 | Y46: =SUM(Y38,Y44) -> 2584.3097 | Z46: =SUM(Z38,Z44) -> 2875.9871 | AA46: =SUM(AA38,AA44) -> 3174.8263
C48: =Model!C135 -> Accounts Payable | G48: =Model!P135 -> 4.683 | H48: =Model!Q135 -> 6.43 | I48: =Model!R135 -> 5.25 | J48: =Model!S135 -> 5.469 | K48: =Model!U135 -> 6.508 | L48: =Model!V135 -> 6.3024768 | M48: =Model!W135 -> 6.617047 | N48: =Model!X135 -> 7.1717495 | O48: =Model!Z135 -> 8.4379211 | P48: =Model!AA135 -> 8.1988466 | Q48: =Model!AB135 -> 8.4936557 | R48: =Model!AC135 -> 8.885887 | T48: =Model!J135 -> 4.559 | U48: =Model!O135 -> 4.505 | V48: =Model!T135 -> 5.469 | W48: =Model!Y135 -> 7.1717495 | X48: =Model!AD135 -> 8.885887 | Y48: =Model!AE135 -> 9.094605 | Z48: =Model!AF135 -> 9.5948083 | AA48: =Model!AG135 -> 10.221295
C49: =Model!C136 -> Accrued Liabilities | G49: =Model!P136 -> 109.325 | H49: =Model!Q136 -> 100.164 | I49: =Model!R136 -> 111.612 | J49: =Model!S136 -> 95.599 | K49: =Model!U136 -> 110.395 | L49: =Model!V136 -> 114.70508 | M49: =Model!W136 -> 121.75367 | N49: =Model!X136 -> 131.96019 | O49: =Model!Z136 -> 143.33215 | P49: =Model!AA136 -> 151.93208 | Q49: =Model!AB136 -> 159.12478 | R49: =Model!AC136 -> 166.47305 | T49: =Model!J136 -> 54.962 | U49: =Model!O136 -> 77.422 | V49: =Model!T136 -> 95.599 | W49: =Model!Y136 -> 131.96019 | X49: =Model!AD136 -> 166.47305 | Y49: =Model!AE136 -> 181.06532 | Z49: =Model!AF136 -> 191.02391 | AA49: =Model!AG136 -> 203.4967
C50: =Model!C137 -> Other Current Liabilities | G50: =Model!P137 -> 0 | H50: =Model!Q137 -> 0 | I50: =Model!R137 -> 0 | J50: =Model!S137 -> 0 | K50: =Model!U137 -> 0 | L50: =Model!V137 -> 0 | M50: =Model!W137 -> 0 | N50: =Model!X137 -> 0 | O50: =Model!Z137 -> 0 | P50: =Model!AA137 -> 0 | Q50: =Model!AB137 -> 0 | R50: =Model!AC137 -> 0 | T50: =Model!J137 -> 0 | U50: =Model!O137 -> 0 | V50: =Model!T137 -> 0 | W50: =Model!Y137 -> 0 | X50: =Model!AD137 -> 0 | Y50: =Model!AE137 -> 0 | Z50: =Model!AF137 -> 0 | AA50: =Model!AG137 -> 0
C51: =Model!C138 -> Total Current Liabilities (Excl. Debt) | G51: =SUM(G48:G50) -> 114.008 | H51: =SUM(H48:H50) -> 106.594 | I51: =SUM(I48:I50) -> 116.862 | J51: =SUM(J48:J50) -> 101.068 | K51: =SUM(K48:K50) -> 116.903 | L51: =SUM(L48:L50) -> 121.00756 | M51: =SUM(M48:M50) -> 128.37071 | N51: =SUM(N48:N50) -> 139.13194 | ... R51: =SUM(R48:R50) -> 175.35894 | T51: =SUM(T48:T50) -> 59.521 | U51: =SUM(U48:U50) -> 81.927 | V51: =SUM(V48:V50) -> 101.068 | W51: =SUM(W48:W50) -> 139.13194 | X51: =SUM(X48:X50) -> 175.35894 | Y51: =SUM(Y48:Y50) -> 190.15992 | Z51: =SUM(Z48:Z50) -> 200.61872 | AA51: =SUM(AA48:AA50) -> 213.71799
C53: =Model!C141 -> Revolver | G53: =Model!P141 -> 0 | H53: =Model!Q141 -> 0 | I53: =Model!R141 -> 0 | J53: =Model!S141 -> 0 | K53: =Model!U141 -> 0 | L53: =Model!V141 -> 0 | M53: =Model!W141 -> 0 | N53: =Model!X141 -> 0 | O53: =Model!Z141 -> 0 | P53: =Model!AA141 -> 0 | Q53: =Model!AB141 -> 0 | R53: =Model!AC141 -> 0 | T53: =Model!J141 -> 0 | U53: =Model!O141 -> 0 | V53: =Model!T141 -> 0 | W53: =Model!Y141 -> 0 | X53: =Model!AD141 -> 0 | Y53: =Model!AE141 -> 0 | Z53: =Model!AF141 -> 0 | AA53: =Model!AG141 -> 0
C54: =Model!C142 -> LT Debt (Incl. Current Portion) | G54: =Model!P142 -> 195.565 | H54: =Model!Q142 -> 194.971 | I54: =Model!R142 -> 292.024 | J54: =Model!S142 -> 290.303 | K54: =Model!U142 -> 288.582 | L54: =Model!V142 -> 287.082 | M54: =Model!W142 -> 285.582 | N54: =Model!X142 -> 284.082 | O54: =Model!Z142 -> 282.582 | P54: =Model!AA142 -> 281.082 | Q54: =Model!AB142 -> 279.582 | R54: =Model!AC142 -> 278.082 | T54: =Model!J142 -> 213.533 | U54: =Model!O142 -> 196.159 | V54: =Model!T142 -> 290.303 | W54: =Model!Y142 -> 284.082 | X54: =Model!AD142 -> 278.082 | Y54: =Model!AE142 -> 272.082 | Z54: =Model!AF142 -> 266.082 | AA54: =Model!AG142 -> 260.082
C55: =Model!#REF! -> #REF! | G55: =Model!#REF! -> #REF! | H55: =Model!#REF! -> #REF! | I55: =Model!#REF! -> #REF! | J55: =Model!#REF! -> #REF! | K55: =Model!#REF! -> #REF! | L55: =Model!#REF! -> #REF! | M55: =Model!#REF! -> #REF! | N55: =Model!#REF! -> #REF! | ... R55: =Model!#REF! -> #REF! | T55: =Model!#REF! -> #REF! | U55: =Model!#REF! -> #REF! | V55: =Model!#REF! -> #REF! | W55: =Model!#REF! -> #REF! | X55: =Model!#REF! -> #REF! | Y55: =Model!#REF! -> #REF! | Z55: =Model!#REF! -> #REF! | AA55: =Model!#REF! -> #REF!
C56: =Model!C143 -> Other Non-Current Liabilities | G56: =Model!P143 -> 125.164 | H56: =Model!Q143 -> 120.497 | I56: =Model!R143 -> 120.092 | J56: =Model!S143 -> 134.441 | K56: =Model!U143 -> 160.859 | L56: =Model!V143 -> 156.32406 | M56: =Model!W143 -> 165.93012 | N56: =Model!X143 -> 179.83993 | O56: =Model!Z143 -> 190.84012 | P56: =Model!AA143 -> 202.29052 | Q56: =Model!AB143 -> 211.86726 | R56: =Model!AC143 -> 221.65115 | T56: =Model!J143 -> 118.595 | U56: =Model!O143 -> 115.734 | V56: =Model!T143 -> 134.441 | W56: =Model!Y143 -> 179.83993 | X56: =Model!AD143 -> 221.65115 | Y56: =Model!AE143 -> 221.12862 | Z56: =Model!AF143 -> 233.2907 | AA56: =Model!AG143 -> 248.52326
C57: =Model!C144 -> Total Non-Current Liabilities | G57: =SUM(G53,G54,G56) -> 320.729 | H57: =SUM(H53,H54,H56) -> 315.468 | I57: =SUM(I53,I54,I56) -> 412.116 | J57: =SUM(J53,J54,J56) -> 424.744 | K57: =SUM(K53,K54,K56) -> 449.441 | L57: =SUM(L53,L54,L56) -> 443.40606 | M57: =SUM(M53,M54,M56) -> 451.51212 | N57: =SUM(N53,N54,N56) -> 463.92193 | ... AA57: =SUM(AA53,AA54,AA56) -> 508.60526
C59: =Model!C146 -> Total Liabilities | G59: =SUM(G51,G57) -> 434.737 | H59: =SUM(H51,H57) -> 422.062 | I59: =SUM(I51,I57) -> 528.978 | J59: =SUM(J51,J57) -> 525.812 | K59: =SUM(K51,K57) -> 566.344 | L59: =SUM(L51,L57) -> 564.41362 | M59: =SUM(M51,M57) -> 579.88283 | N59: =SUM(N51,N57) -> 603.05387 | ... R59: =SUM(R51,R57) -> 675.09209 | T59: =SUM(T51,T57) -> 391.649 | U59: =SUM(U51,U57) -> 393.82 | V59: =SUM(V51,V57) -> 525.812 | W59: =SUM(W51,W57) -> 603.05387 | X59: =SUM(X51,X57) -> 675.09209 | Y59: =SUM(Y51,Y57) -> 683.37055 | Z59: =SUM(Z51,Z57) -> 699.99142 | AA59: =SUM(AA51,AA57) -> 722.32326
C61: =Model!C148 -> Common Stock & APIC | G61: =Model!P148 -> 210.154 | H61: =Model!Q148 -> 214.843 | I61: =Model!R148 -> 224.012 | J61: =Model!S148 -> 261.911 | K61: =Model!U148 -> 271.747 | L61: =Model!V148 -> 275.11567 | M61: =Model!W148 -> 278.69134 | N61: =Model!X148 -> 282.56676 | O61: =Model!Z148 -> 286.67922 | P61: =Model!AA148 -> 291.03843 | Q61: =Model!AB148 -> 295.60401 | R61: =Model!AC148 -> 300.38043 | T61: =Model!J148 -> 171.621 | U61: =Model!O148 -> 208.457 | V61: =Model!T148 -> 261.911 | W61: =Model!Y148 -> 282.56676 | X61: =Model!AD148 -> 300.38043 | Y61: =Model!AE148 -> 319.44106 | Z61: =Model!AF148 -> 339.55003 | AA61: =Model!AG148 -> 360.972
C62: =Model!C149 -> Retained Earnings | G62: =Model!P149 -> 356.209 | H62: =Model!Q149 -> 391.737 | I62: =Model!R149 -> 425.245 | J62: =Model!S149 -> 455.511 | K62: =Model!U149 -> 486.914 | L62: =Model!V149 -> 532.32629 | M62: =Model!W149 -> 582.09065 | N62: =Model!X149 -> 637.79879 | O62: =Model!Z149 -> 698.74285 | P62: =Model!AA149 -> 762.05252 | Q62: =Model!AB149 -> 826.79628 | R62: =Model!AC149 -> 895.39792 | T62: =Model!J149 -> 243.823 | U62: =Model!O149 -> 316.696 | V62: =Model!T149 -> 455.511 | W62: =Model!Y149 -> 637.79879 | X62: =Model!AD149 -> 895.39792 | Y62: =Model!AE149 -> 1154.3406 | Z62: =Model!AF149 -> 1417.2844 | AA62: =Model!AG149 -> 1686.5819
C63: =Model!C150 -> Treasury Stock | G63: =Model!P150 -> 0 | H63: =Model!Q150 -> 0 | I63: =Model!R150 -> 0 | J63: =Model!S150 -> 0 | K63: =Model!U150 -> 0 | L63: =Model!V150 -> 0 | M63: =Model!W150 -> 0 | N63: =Model!X150 -> -35 | O63: =Model!Z150 -> -35 | P63: =Model!AA150 -> -35 | Q63: =Model!AB150 -> -35 | R63: =Model!AC150 -> -70 | T63: =Model!J150 -> 0 | U63: =Model!O150 -> 0 | V63: =Model!T150 -> 0 | W63: =Model!Y150 -> -35 | X63: =Model!AD150 -> -70 | Y63: =Model!AE150 -> -105 | Z63: =Model!AF150 -> -140 | AA63: =Model!AG150 -> -175
C64: =Model!C151 -> Accumulated Other Comprehensive Income (AOCI) | G64: =Model!P151 -> 0 | H64: =Model!Q151 -> 0 | I64: =Model!R151 -> 0 | J64: =Model!S151 -> -0.141 | K64: =Model!U151 -> 0.14 | L64: =Model!V151 -> 0.14 | M64: =Model!W151 -> 0.14 | N64: =Model!X151 -> 0.14 | O64: =Model!Z151 -> 0.14 | P64: =Model!AA151 -> 0.14 | Q64: =Model!AB151 -> 0.14 | R64: =Model!AC151 -> 0.14 | T64: =Model!J151 -> 0 | U64: =Model!O151 -> 0 | V64: =Model!T151 -> -0.141 | W64: =Model!Y151 -> 0.14 | X64: =Model!AD151 -> 0.14 | Y64: =Model!AE151 -> 0.14 | Z64: =Model!AF151 -> 0.14 | AA64: =Model!AG151 -> 0.14
C65: =Model!C152 -> Total Shareholder's Equity | G65: =SUM(G61:G64) -> 566.363 | H65: =SUM(H61:H64) -> 606.58 | I65: =SUM(I61:I64) -> 649.257 | J65: =SUM(J61:J64) -> 717.281 | K65: =SUM(K61:K64) -> 758.801 | L65: =SUM(L61:L64) -> 807.58195 | M65: =SUM(M61:M64) -> 860.92199 | N65: =SUM(N61:N64) -> 885.50554 | ... R65: =SUM(R61:R64) -> 1125.9183 | T65: =SUM(T61:T64) -> 415.444 | U65: =SUM(U61:U64) -> 525.153 | V65: =SUM(V61:V64) -> 717.281 | W65: =SUM(W61:W64) -> 885.50554 | X65: =SUM(X61:X64) -> 1125.9183 | Y65: =SUM(Y61:Y64) -> 1368.9217 | Z65: =SUM(Z61:Z64) -> 1616.9745 | AA65: =SUM(AA61:AA64) -> 1872.6939
C67: =Model!C154 -> Noncontrolling Interests | G67: =Model!P154 -> 170.467 | H67: =Model!Q154 -> 195.342 | I67: =Model!R154 -> 212.768 | J67: =Model!S154 -> 206.614 | K67: =Model!U154 -> 236.245 | L67: =Model!V154 -> 202.30173 | M67: =Model!W154 -> 214.7331 | N67: =Model!X154 -> 232.73402 | O67: =Model!Z154 -> 246.96956 | P67: =Model!AA154 -> 261.78773 | Q67: =Model!AB154 -> 261.71839 | R67: =Model!AC154 -> 273.80436 | T67: =Model!J154 -> 158.748 | U67: =Model!O154 -> 150.805 | V67: =Model!T154 -> 206.614 | W67: =Model!Y154 -> 232.73402 | X67: =Model!AD154 -> 273.80436 | Y67: =Model!AE154 -> 291.36948 | Z67: =Model!AF154 -> 318.37318 | AA67: =Model!AG154 -> 339.16116
C68: =Model!C155 -> Total Equity | G68: =SUM(G65,G67) -> 736.83 | H68: =SUM(H65,H67) -> 801.922 | I68: =SUM(I65,I67) -> 862.025 | J68: =SUM(J65,J67) -> 923.895 | K68: =SUM(K65,K67) -> 995.046 | L68: =SUM(L65,L67) -> 1009.8837 | M68: =SUM(M65,M67) -> 1075.6551 | N68: =SUM(N65,N67) -> 1118.2396 | ... R68: =SUM(R65,R67) -> 1399.7227 | T68: =SUM(T65,T67) -> 574.192 | U68: =SUM(U65,U67) -> 675.958 | V68: =SUM(V65,V67) -> 923.895 | W68: =SUM(W65,W67) -> 1118.2396 | X68: =SUM(X65,X67) -> 1399.7227 | Y68: =SUM(Y65,Y67) -> 1660.2911 | Z68: =SUM(Z65,Z67) -> 1935.3476 | AA68: =SUM(AA65,AA67) -> 2211.8551
C70: =Model!C157 -> Total Liabilities & Shareholder's Equity | G70: =SUM(G59,G68) -> 1171.567 | H70: =SUM(H59,H68) -> 1223.984 | I70: =SUM(I59,I68) -> 1391.003 | J70: =SUM(J59,J68) -> 1449.707 | K70: =SUM(K59,K68) -> 1561.39 | L70: =SUM(L59,L68) -> 1574.2973 | M70: =SUM(M59,M68) -> 1655.5379 | N70: =SUM(N59,N68) -> 1721.2934 | ... R70: =SUM(R59,R68) -> 2074.8148 | T70: =SUM(T59,T68) -> 965.841 | U70: =SUM(U59,U68) -> 1069.778 | V70: =SUM(V59,V68) -> 1449.707 | W70: =SUM(W59,W68) -> 1721.2934 | X70: =SUM(X59,X68) -> 2074.8148 | Y70: =SUM(Y59,Y68) -> 2343.6617 | Z70: =SUM(Z59,Z68) -> 2635.3391 | AA70: =SUM(AA59,AA68) -> 2934.1783
G72: =G$5 -> Quarterly | T72: =T$31 -> Annuals
A73: x | C73: Ratio Analysis | G73: =G$6 -> 1Q25 | H73: =H$6 -> 2Q25 | I73: =I$6 -> 3Q25 | J73: =J$6 -> 4Q25 | K73: =K$6 -> 1Q26 | L73: =L$6 -> 2Q26e | M73: =M$6 -> 3Q26e | N73: =N$6 -> 4Q26e | ... R73: =R$6 -> 4Q27e | T73: =T$6 -> 2023 | U73: =U$6 -> 2024 | V73: =V$6 -> 2025 | W73: =W$6 -> 2026e | X73: =X$6 -> 2027e | Y73: =Y$6 -> 2028e | Z73: =Z$6 -> 2029e | AA73: =AA$6 -> 2030e
C75: Profitability
C76: Gross Margin | G76: =G12 -> 1 | H76: =H12 -> 1 | I76: =I12 -> 1 | J76: =J12 -> 1 | K76: =K12 -> 1 | L76: =L12 -> 1 | M76: =M12 -> 1 | N76: =N12 -> 1 | ... R76: =R12 -> 1 | T76: =T12 -> 1 | U76: =U12 -> 1 | V76: =V12 -> 1 | W76: =W12 -> 1 | X76: =X12 -> 1 | Y76: =Y12 -> 1 | Z76: =Z12 -> 1 | AA76: =AA12 -> 1
C77: EBITDA Margin | G77: =G28 -> 0.31254861 | H77: =H28 -> 0.30834872 | I77: =I28 -> 0.30452095 | J77: =J28 -> 0.30924924 | K77: =K28 -> 0.30490231 | L77: =L28 -> 0.323 | M77: =M28 -> 0.323 | N77: =N28 -> 0.323 | ... R77: =R28 -> 0.33025 | T77: =T28 -> 0.30609377 | U77: =U28 -> 0.28793591 | V77: =V28 -> 0.3088543 | W77: =W28 -> 0.31884634 | X77: =X28 -> 0.32799104 | Y77: =Y28 -> 0.3332 | Z77: =Z28 -> 0.3301 | AA77: =AA28 -> 0.3301
C78: EBIT Margin | G78: =G16 -> 0.45550015 | H78: =H16 -> 0.44794965 | I78: =I16 -> 0.45002704 | J78: =J16 -> 0.42444172 | K78: =K16 -> 0.43746235 | L78: =L16 -> 0.433 | M78: =M16 -> 0.433 | N78: =N16 -> 0.433 | ... R78: =R16 -> 0.43 | T78: =T16 -> 0.4537317 | U78: =U16 -> 0.44383958 | V78: =V16 -> 0.44399577 | W78: =W16 -> 0.43402417 | X78: =X16 -> 0.43 | Y78: =Y16 -> 0.42 | Z78: =Z16 -> 0.42 | AA78: =AA16 -> 0.42
C79: Net Profit Margin | G79: =G20 -> 0.44267045 | H79: =H20 -> 0.50615004 | I79: =I20 -> 0.46032652 | J79: =J20 -> 0.37027271 | K79: =K20 -> 0.43800225 | L79: =L20 -> 0.36886 | M79: =M20 -> 0.36921091 | N79: =N20 -> 0.36927412 | ... R79: =R20 -> 0.36195823 | T79: =T20 -> 0.35376821 | U79: =U20 -> 0.41023252 | V79: =V20 -> 0.44008954 | W79: =W20 -> 0.38493271 | X79: =X20 -> 0.36821254 | Y79: =Y20 -> 0.35990146 | Z79: =Z20 -> 0.36057434 | AA79: =AA20 -> 0.36095314
C80: Return on Assets (ROA) | G80: =G19/G46 -> 0.063478515 | H80: =H19/H46 -> 0.053303659 | I80: =I19/I46 -> 0.048682361 | J80: =J19/J46 -> 0.043366038 | K80: =K19/K46 -> 0.042768244 | L80: =L19/L46 -> 0.037377042 | M80: =M19/M46 -> 0.038010179 | N80: =N19/N46 -> 0.039822638 | ... R80: =R19/R46 -> 0.040763523 | T80: =T19/T46 -> 0.16400609 | U80: =U19/U46 -> 0.17873191 | V80: =V19/V46 -> 0.18562255 | W80: =W19/W46 -> 0.15041801 | X80: =X19/X46 -> 0.15465466 | Y80: =Y19/Y46 -> 0.14491892 | Z80: =Z19/Z46 -> 0.13764054 | AA80: =AA19/AA46 -> 0.1329655
C81: Return on Equity (ROE) | G81: =G19*4/G68 -> 0.47276577 | H81: =H19*4/H68 -> 0.37870017 | I81: =I19*4/I68 -> 0.35940953 | J81: =J19*4/J68 -> 0.3173694 | K81: =K19*4/K68 -> 0.30981482 | L81: =L19*4/L68 -> 0.26869347 | M81: =M19*4/M68 -> 0.26802036 | N81: =N19*4/N68 -> 0.27947387 | ... R81: =R19*4/R68 -> 0.26972891 | T81: =T19/T68 -> 0.32577256 | U81: =U19/U68 -> 0.33612148 | V81: =V19/V68 -> 0.33961435 | W81: =W19/W68 -> 0.26390708 | X81: =X19/X68 -> 0.25583432 | Y81: =Y19/Y68 -> 0.2255721 | Z81: =Z19/Z68 -> 0.20453814 | AA81: =AA19/AA68 -> 0.19085444
C82: Return on Invested Capital (ROIC) | G82: =G19*4/(G53+G54+G68) -> 0.37360561 | H82: =H19*4/(H53+H54+H68) -> 0.3046345 | I82: =I19*4/(I53+I54+I68) -> 0.26846347 | J82: =J19*4/(J53+J54+J68) -> 0.24148944 | K82: =K19*4/(K53+K54+K68) -> 0.24016304 | L82: =L19*4/(L53+L54+L68) -> 0.20921845 | M82: =M19*4/(M53+M54+M68) -> 0.21179078 | N82: =N19*4/(N53+N54+N68) -> 0.22285811 | ... S82: =S19*4/(S53+S54+S68) -> #DIV/0! | T82: =T19/(T53+T54+T68) -> 0.23746358 | U82: =U19/(U53+U54+U68) -> 0.26052009 | V82: =V19/(V53+V54+V68) -> 0.25841584 | W82: =W19/(W53+W54+W68) -> 0.21044484 | X82: =X19/(X53+X54+X68) -> 0.21343194 | Y82: =Y19/(Y53+Y54+Y68) -> 0.1938111 | Z82: =Z19/(Z53+Z54+Z68) -> 0.17981607 | AA82: =AA19/(AA53+AA54+AA68) -> 0.17077391
C84: Coverage
C85: Interest Expense | G85: =-Model!P39 -> 2.947 | H85: =-Model!Q39 -> 2.704 | I85: =-Model!R39 -> 3.866 | J85: =-Model!S39 -> 3.815 | K85: =-Model!U39 -> 3.856 | L85: =-Model!V39 -> 2.5113342 | M85: =-Model!W39 -> 2.4982467 | N85: =-Model!X39 -> 2.4851592 | O85: =-Model!Z39 -> 2.4720717 | P85: =-Model!AA39 -> 2.4589842 | Q85: =-Model!AB39 -> 2.4458967 | R85: =-Model!AC39 -> 2.4328092 | T85: =-Model!J39 -> 8.618 | U85: =-Model!O39 -> 11.175 | V85: =-Model!T39 -> 13.332 | W85: =-Model!Y39 -> 11.35074 | X85: =-Model!AD39 -> 9.8097618 | Y85: =-Model!AE39 -> 9.6003618 | Z85: =-Model!AF39 -> 9.3909618 | AA85: =-Model!AG39 -> 9.1815618
C86: Capital Expenditures | G86: =Model!P194 -> -0.353 | H86: =Model!Q194 -> 0.17 | I86: =Model!R194 -> 2.118 | J86: =Model!S194 -> 1.626 | K86: =Model!U194 -> -2.322 | L86: =Model!V194 -> 2.2069279 | M86: =Model!W194 -> 2.3425429 | N86: =Model!X194 -> 2.1157639 | O86: =Model!Z194 -> 1.7961423 | P86: =Model!AA194 -> 1.9039108 | Q86: =Model!AB194 -> 1.9940448 | R86: =Model!AC194 -> 2.0861285 | T86: =Model!J194 -> -2.928 | U86: =Model!O194 -> 4.686 | V86: =Model!T194 -> 3.561 | W86: =Model!Y194 -> 4.3432346 | X86: =Model!AD194 -> 7.7802264 | Y86: =Model!AE194 -> 8.3248422 | Z86: =Model!AF194 -> 8.7827086 | AA86: =Model!AG194 -> 9.35617
C87: EBIT / Interest Expense | G87: =IF(ISERROR(G15/G85),"N/A",(G15/G85)) -> 30.407533 | H87: =IF(ISERROR(H15/H85),"N/A",(H15/H85)) -> 24.849112 | I87: =IF(ISERROR(I15/I85),"N/A",(I15/I85)) -> 19.586653 | J87: =IF(ISERROR(J15/J85),"N/A",(J15/J85)) -> 22.025688 | K87: =IF(ISERROR(K15/K85),"N/A",(K15/K85)) -> 19.962396 | L87: =IF(ISERROR(L15/L85),"N/A",(L15/L85)) -> 31.709565 | M87: =IF(ISERROR(M15/M85),"N/A",(M15/M85)) -> 33.834431 | N87: =IF(ISERROR(N15/N85),"N/A",(N15/N85)) -> 36.863866 | ... R87: =IF(ISERROR(R15/R85),"N/A",(R15/R85)) -> 46.090506 | T87: =IF(ISERROR(T15/T85),"N/A",(T15/T85)) -> 27.838478 | U87: =IF(ISERROR(U15/U85),"N/A",(U15/U85)) -> 21.997047 | V87: =IF(ISERROR(V15/V85),"N/A",(V15/V85)) -> 23.743849 | W87: =IF(ISERROR(W15/W85),"N/A",(W15/W85)) -> 29.315062 | X87: =IF(ISERROR(X15/X85),"N/A",(X15/X85)) -> 42.629696 | Y87: =IF(ISERROR(Y15/Y85),"N/A",(Y15/Y85)) -> 45.524765 | Z87: =IF(ISERROR(Z15/Z85),"N/A",(Z15/Z85)) -> 49.099571 | AA87: =IF(ISERROR(AA15/AA85),"N/A",(AA15/AA85)) -> 53.498406
C88: EBITDA / Interest Expense | G88: =IF(ISERROR(G27/G85),"N/A",(G27/G85)) -> 20.864608 | H88: =IF(ISERROR(H27/H85),"N/A",(H27/H85)) -> 17.10503 | I88: =IF(ISERROR(I27/I85),"N/A",(I27/I85)) -> 13.253751 | J88: =IF(ISERROR(J27/J85),"N/A",(J27/J85)) -> 16.047969 | K88: =IF(ISERROR(K27/K85),"N/A",(K27/K85)) -> 13.913382 | L88: =IF(ISERROR(L27/L85),"N/A",(L27/L85)) -> 23.654018 | M88: =IF(ISERROR(M27/M85),"N/A",(M27/M85)) -> 25.239079 | N88: =IF(ISERROR(N27/N85),"N/A",(N27/N85)) -> 27.498911 | ... R88: =IF(ISERROR(R27/R85),"N/A",(R27/R85)) -> 35.39858 | T88: =IF(ISERROR(T27/T85),"N/A",(T27/T85)) -> 18.780227 | U88: =IF(ISERROR(U27/U85),"N/A",(U27/U85)) -> 14.270336 | V88: =IF(ISERROR(V27/V85),"N/A",(V27/V85)) -> 16.516802 | W88: =IF(ISERROR(W27/W85),"N/A",(W27/W85)) -> 21.535667 | X88: =IF(ISERROR(X27/X85),"N/A",(X27/X85)) -> 32.516647 | Y88: =IF(ISERROR(Y27/Y85),"N/A",(Y27/Y85)) -> 36.116314 | Z88: =IF(ISERROR(Z27/Z85),"N/A",(Z27/Z85)) -> 38.589925 | AA88: =IF(ISERROR(AA27/AA85),"N/A",(AA27/AA85)) -> 42.0472
C89: (EBITDA - CapEx) / Interest Expense | G89: =IF(ISERROR((G27-G86)/G85),"N/A",((G27-G86)/G85)) -> 20.984391 | H89: =IF(ISERROR((H27-H86)/H85),"N/A",((H27-H86)/H85)) -> 17.04216 | I89: =IF(ISERROR((I27-I86)/I85),"N/A",((I27-I86)/I85)) -> 12.705898 | J89: =IF(ISERROR((J27-J86)/J85),"N/A",((J27-J86)/J85)) -> 15.621756 | K89: =IF(ISERROR((K27-K86)/K85),"N/A",((K27-K86)/K85)) -> 14.51556 | L89: =IF(ISERROR((L27-L86)/L85),"N/A",((L27-L86)/L85)) -> 22.77523 | M89: =IF(ISERROR((M27-M86)/M85),"N/A",((M27-M86)/M85)) -> 24.301404 | N89: =IF(ISERROR((N27-N86)/N85),"N/A",((N27-N86)/N85)) -> 26.647552 | ... R89: =IF(ISERROR((R27-R86)/R85),"N/A",((R27-R86)/R85)) -> 34.541082 | T89: =IF(ISERROR((T27-T86)/T85),"N/A",((T27-T86)/T85)) -> 19.119981 | U89: =IF(ISERROR((U27-U86)/U85),"N/A",((U27-U86)/U85)) -> 13.851007 | V89: =IF(ISERROR((V27-V86)/V85),"N/A",((V27-V86)/V85)) -> 16.2497 | W89: =IF(ISERROR((W27-W86)/W85),"N/A",((W27-W86)/W85)) -> 21.153028 | X89: =IF(ISERROR((X27-X86)/X85),"N/A",((X27-X86)/X85)) -> 31.723537 | Y89: =IF(ISERROR((Y27-Y86)/Y85),"N/A",((Y27-Y86)/Y85)) -> 35.249175 | Z89: =IF(ISERROR((Z27-Z86)/Z85),"N/A",((Z27-Z86)/Z85)) -> 37.654695 | AA89: =IF(ISERROR((AA27-AA86)/AA85),"N/A",((AA27-AA86)/AA85)) -> 41.028182
C91: Leverage
C92: Total Debt / EBITDA | G92: =IF(ISERROR((G53+G54)/G27),"NA",((G53+G54)/G27)) -> 3.1805393 | H92: =IF(ISERROR((H53+H54)/H27),"NA",((H53+H54)/H27)) -> 4.2154069 | I92: =IF(ISERROR((I53+I54)/I27),"NA",((I53+I54)/I27)) -> 5.6992525 | J92: =IF(ISERROR((J53+J54)/J27),"NA",((J53+J54)/J27)) -> 4.741731 | K92: =IF(ISERROR((K53+K54)/K27),"NA",((K53+K54)/K27)) -> 5.3789748 | L92: =IF(ISERROR((L53+L54)/L27),"NA",((L53+L54)/L27)) -> 4.8327746 | M92: =IF(ISERROR((M53+M54)/M27),"NA",((M53+M54)/M27)) -> 4.5292053 | N92: =IF(ISERROR((N53+N54)/N27),"NA",((N53+N54)/N27)) -> 4.1569424 | ... R92: =IF(ISERROR((R53+R54)/R27),"NA",((R53+R54)/R27)) -> 3.2290813 | T92: =IF(ISERROR((T53+T54)/T27),"NA",((T53+T54)/T27)) -> 1.3193428 | U92: =IF(ISERROR((U53+U54)/U27),"NA",((U53+U54)/U27)) -> 1.2300606 | V92: =IF(ISERROR((V53+V54)/V27),"NA",((V53+V54)/V27)) -> 1.3183486 | W92: =IF(ISERROR((W53+W54)/W27),"NA",((W53+W54)/W27)) -> 1.1621474 | X92: =IF(ISERROR((X53+X54)/X27),"NA",((X53+X54)/X27)) -> 0.87178352 | Y92: =IF(ISERROR((Y53+Y54)/Y27),"NA",((Y53+Y54)/Y27)) -> 0.78470929 | Z92: =IF(ISERROR((Z53+Z54)/Z27),"NA",((Z53+Z54)/Z27)) -> 0.73422892 | AA92: =IF(ISERROR((AA53+AA54)/AA27),"NA",((AA53+AA54)/AA27)) -> 0.67368466
C93: Total Debt / Equity | G93: =IF(ISERROR((G53+G54)/G68),"NA",((G53+G54)/G68)) -> 0.265414 | H93: =IF(ISERROR((H53+H54)/H68),"NA",((H53+H54)/H68)) -> 0.24312963 | I93: =IF(ISERROR((I53+I54)/I68),"NA",((I53+I54)/I68)) -> 0.33876512 | J93: =IF(ISERROR((J53+J54)/J68),"NA",((J53+J54)/J68)) -> 0.31421644 | K93: =IF(ISERROR((K53+K54)/K68),"NA",((K53+K54)/K68)) -> 0.29001875 | L93: =IF(ISERROR((L53+L54)/L68),"NA",((L53+L54)/L68)) -> 0.28427234 | M93: =IF(ISERROR((M53+M54)/M68),"NA",((M53+M54)/M68)) -> 0.26549589 | N93: =IF(ISERROR((N53+N54)/N68),"NA",((N53+N54)/N68)) -> 0.25404395 | ... R93: =IF(ISERROR((R53+R54)/R68),"NA",((R53+R54)/R68)) -> 0.19866935 | T93: =IF(ISERROR((T53+T54)/T68),"NA",((T53+T54)/T68)) -> 0.37188432 | U93: =IF(ISERROR((U53+U54)/U68),"NA",((U53+U54)/U68)) -> 0.29019407 | V93: =IF(ISERROR((V53+V54)/V68),"NA",((V53+V54)/V68)) -> 0.31421644 | W93: =IF(ISERROR((W53+W54)/W68),"NA",((W53+W54)/W68)) -> 0.25404395 | X93: =IF(ISERROR((X53+X54)/X68),"NA",((X53+X54)/X68)) -> 0.19866935 | Y93: =IF(ISERROR((Y53+Y54)/Y68),"NA",((Y53+Y54)/Y68)) -> 0.16387608 | Z93: =IF(ISERROR((Z53+Z54)/Z68),"NA",((Z53+Z54)/Z68)) -> 0.13748538 | AA93: =IF(ISERROR((AA53+AA54)/AA68),"NA",((AA53+AA54)/AA68)) -> 0.11758546
C94: Total Debt / Total Assets | G94: =IF(ISERROR((G53+G54)/G46),"NA",((G53+G54)/G46)) -> 0.14254913 | H94: =IF(ISERROR((H53+H54)/H46),"NA",((H53+H54)/H46)) -> 0.13688611 | I94: =IF(ISERROR((I53+I54)/I46),"NA",((I53+I54)/I46)) -> 0.18354422 | J94: =IF(ISERROR((J53+J54)/J46),"NA",((J53+J54)/J46)) -> 0.17174085 | K94: =IF(ISERROR((K53+K54)/K46),"NA",((K53+K54)/K46)) -> 0.16014202 | L94: =IF(ISERROR((L53+L54)/L46),"NA",((L53+L54)/L46)) -> 0.15817667 | M94: =IF(ISERROR((M53+M54)/M46),"NA",((M53+M54)/M46)) -> 0.15060865 | N94: =IF(ISERROR((N53+N54)/N46),"NA",((N53+N54)/N46)) -> 0.14479637 | ... R94: =IF(ISERROR((R53+R54)/R46),"NA",((R53+R54)/R46)) -> 0.1200978 | T94: =IF(ISERROR((T53+T54)/T46),"NA",((T53+T54)/T46)) -> 0.18722047 | U94: =IF(ISERROR((U53+U54)/U46),"NA",((U53+U54)/U46)) -> 0.1543101 | V94: =IF(ISERROR((V53+V54)/V46),"NA",((V53+V54)/V46)) -> 0.17174085 | W94: =IF(ISERROR((W53+W54)/W46),"NA",((W53+W54)/W46)) -> 0.14479637 | X94: =IF(ISERROR((X53+X54)/X46),"NA",((X53+X54)/X46)) -> 0.1200978 | Y94: =IF(ISERROR((Y53+Y54)/Y46),"NA",((Y53+Y54)/Y46)) -> 0.10528227 | Z94: =IF(ISERROR((Z53+Z54)/Z46),"NA",((Z53+Z54)/Z46)) -> 0.092518497 | AA94: =IF(ISERROR((AA53+AA54)/AA46),"NA",((AA53+AA54)/AA46)) -> 0.081920071
C96: Efficiency
C97: Asset Turnover | G97: =G8/G46 -> 0.14339903 | H97: =H8/H46 -> 0.10531197 | I97: =I8/I46 -> 0.10575615 | J97: =J8/J46 -> 0.11711919 | K97: =K8/K46 -> 0.09764389 | L97: =L8/L46 -> 0.10133124 | M97: =M8/M46 -> 0.10294977 | N97: =N8/N46 -> 0.10784032 | ... R97: =R8/R46 -> 0.11261941 | T97: =T8/T46 -> 0.4635976 | U97: =U8/U46 -> 0.43568439 | V97: =V8/V46 -> 0.42178359 | W97: =W8/W46 -> 0.39076444 | X97: =X8/X46 -> 0.42001465 | Y97: =Y8/Y46 -> 0.40266276 | Z97: =Z8/Z46 -> 0.38172584 | AA97: =AA8/AA46 -> 0.3683733
C98: =Model!C183 -> Days Sales Outstanding | G98: =Model!P183 -> 57.045153 | H98: =Model!Q183 -> 71.771572 | I98: =Model!R183 -> 63.187702 | J98: =Model!S183 -> 73.664176 | K98: =Model!U183 -> 86.817536 | L98: =Model!V183 -> 79 | M98: =Model!W183 -> 79 | N98: =Model!X183 -> 79 | O98: =Model!Z183 -> 86 | P98: =Model!AA183 -> 86 | Q98: =Model!AB183 -> 86 | R98: =Model!AC183 -> 86 | T98: =Model!J183 -> 33.172044 | U98: =Model!O183 -> 51.217057 | V98: =Model!T183 -> 74.156079 | W98: =Model!Y183 -> 86.432474 | X98: =Model!AD183 -> 80.054629 | Y98: =Model!AE183 -> 78 | Z98: =Model!AF183 -> 80 | AA98: =Model!AG183 -> 80
C99: =Model!C184 -> Days Inventory Outstanding | G99: =Model!P184 -> 0 | H99: =Model!Q184 -> 0 | I99: =Model!R184 -> 0 | J99: =Model!S184 -> 0 | K99: =Model!U184 -> 0 | L99: =Model!V184 -> 0 | M99: =Model!W184 -> 0 | N99: =Model!X184 -> 0 | O99: =Model!Z184 -> 0 | P99: =Model!AA184 -> 0 | Q99: =Model!AB184 -> 0 | R99: =Model!AC184 -> 0 | T99: =Model!J184 -> 0 | U99: =Model!O184 -> 0 | V99: =Model!T184 -> 0 | W99: =Model!Y184 -> 0 | X99: =Model!AD184 -> 0 | Y99: =Model!AE184 -> 0 | Z99: =Model!AF184 -> 0 | AA99: =Model!AG184 -> 0
C100: =Model!C185 -> Days Payables Outstanding | G100: =Model!P185 -> 3.8597834 | H100: =Model!Q185 -> 6.1062652 | I100: =Model!R185 -> 5.8059845 | J100: =Model!S185 -> 4.3272983 | K100: =Model!U185 -> 5.4450259 | L100: =Model!V185 -> 5.5 | M100: =Model!W185 -> 5.5 | N100: =Model!X185 -> 5.5 | O100: =Model!Z185 -> 6 | P100: =Model!AA185 -> 5.5 | Q100: =Model!AB185 -> 5.5 | R100: =Model!AC185 -> 5.5 | T100: =Model!J185 -> 3.8381462 | U100: =Model!O185 -> 5.0165652 | V100: =Model!T185 -> 5.0255164 | W100: =Model!Y185 -> 5.5937581 | X100: =Model!AD185 -> 5.61476 | Y100: =Model!AE185 -> 5.5 | Z100: =Model!AF185 -> 5.5 | AA100: =Model!AG185 -> 5.5
C101: Cash Conversion Cycle | G101: =G98+G99-G100 -> 53.18537 | H101: =H98+H99-H100 -> 65.665307 | I101: =I98+I99-I100 -> 57.381718 | J101: =J98+J99-J100 -> 69.336878 | K101: =K98+K99-K100 -> 81.37251 | L101: =L98+L99-L100 -> 73.5 | M101: =M98+M99-M100 -> 73.5 | N101: =N98+N99-N100 -> 73.5 | ... R101: =R98+R99-R100 -> 80.5 | T101: =T98+T99-T100 -> 29.333898 | U101: =U98+U99-U100 -> 46.200492 | V101: =V98+V99-V100 -> 69.130563 | W101: =W98+W99-W100 -> 80.838716 | X101: =X98+X99-X100 -> 74.439869 | Y101: =Y98+Y99-Y100 -> 72.5 | Z101: =Z98+Z99-Z100 -> 74.5 | AA101: =AA98+AA99-AA100 -> 74.5
C103: Liquidity
C104: Current Ratio | G104: =IF(ISERROR(G38/G51),"NA",(G38/G51)) -> 2.8002772 | H104: =IF(ISERROR(H38/H51),"NA",(H38/H51)) -> 3.0804267 | I104: =IF(ISERROR(I38/I51),"NA",(I38/I51)) -> 3.9175951 | J104: =IF(ISERROR(J38/J51),"NA",(J38/J51)) -> 4.3968219 | K104: =IF(ISERROR(K38/K51),"NA",(K38/K51)) -> 3.9207976 | L104: =IF(ISERROR(L38/L51),"NA",(L38/L51)) -> 3.7816705 | M104: =IF(ISERROR(M38/M51),"NA",(M38/M51)) -> 3.8154356 | N104: =IF(ISERROR(N38/N51),"NA",(N38/N51)) -> 3.5792447 | ... R104: =IF(ISERROR(R38/R51),"NA",(R38/R51)) -> 2.8666792 | T104: =IF(ISERROR(T38/T51),"NA",(T38/T51)) -> 2.8331681 | U104: =IF(ISERROR(U38/U51),"NA",(U38/U51)) -> 3.0165025 | V104: =IF(ISERROR(V38/V51),"NA",(V38/V51)) -> 4.3968219 | W104: =IF(ISERROR(W38/W51),"NA",(W38/W51)) -> 3.5792447 | X104: =IF(ISERROR(X38/X51),"NA",(X38/X51)) -> 2.8666792 | Y104: =IF(ISERROR(Y38/Y51),"NA",(Y38/Y51)) -> 2.8172853 | Z104: =IF(ISERROR(Z38/Z51),"NA",(Z38/Z51)) -> 2.8451006 | AA104: =IF(ISERROR(AA38/AA51),"NA",(AA38/AA51)) -> 2.6800465
C105: Quick Ratio | G105: =IF(ISERROR((G34+G35)/G51),"NA",((G34+G35)/G51)) -> 2.5679075 | H105: =IF(ISERROR((H34+H35)/H51),"NA",((H34+H35)/H51)) -> 2.7138488 | I105: =IF(ISERROR((I34+I35)/I51),"NA",((I34+I35)/I51)) -> 3.6040372 | J105: =IF(ISERROR((J34+J35)/J51),"NA",((J34+J35)/J51)) -> 4.0623343 | K105: =IF(ISERROR((K34+K35)/K51),"NA",((K34+K35)/K51)) -> 3.6047663 | L105: =IF(ISERROR((L34+L35)/L51),"NA",((L34+L35)/L51)) -> 3.4777049 | M105: =IF(ISERROR((M34+M35)/M51),"NA",((M34+M35)/M51)) -> 3.5112978 | N105: =IF(ISERROR((N34+N35)/N51),"NA",((N34+N35)/N51)) -> 3.275107 | ... R105: =IF(ISERROR((R34+R35)/R51),"NA",((R34+R35)/R51)) -> 2.5692708 | T105: =IF(ISERROR((T34+T35)/T51),"NA",((T34+T35)/T51)) -> 2.4667932 | U105: =IF(ISERROR((U34+U35)/U51),"NA",((U34+U35)/U51)) -> 2.7210199 | V105: =IF(ISERROR((V34+V35)/V51),"NA",((V34+V35)/V51)) -> 4.0623343 | W105: =IF(ISERROR((W34+W35)/W51),"NA",((W34+W35)/W51)) -> 3.275107 | X105: =IF(ISERROR((X34+X35)/X51),"NA",((X34+X35)/X51)) -> 2.5692708 | Y105: =IF(ISERROR((Y34+Y35)/Y51),"NA",((Y34+Y35)/Y51)) -> 2.5163108 | Z105: =IF(ISERROR((Z34+Z35)/Z51),"NA",((Z34+Z35)/Z51)) -> 2.5441261 | AA105: =IF(ISERROR((AA34+AA35)/AA51),"NA",((AA34+AA35)/AA51)) -> 2.379072
C106: Cash Ratio | G106: =IF(ISERROR(G34/G51),"NA",(G34/G51)) -> 1.3302838 | H106: =IF(ISERROR(H34/H51),"NA",(H34/H51)) -> 1.8178415 | I106: =IF(ISERROR(I34/I51),"NA",(I34/I51)) -> 2.443506 | J106: =IF(ISERROR(J34/J51),"NA",(J34/J51)) -> 2.2673942 | K106: =IF(ISERROR(K34/K51),"NA",(K34/K51)) -> 2.2526967 | L106: =IF(ISERROR(L34/L51),"NA",(L34/L51)) -> 2.1582939 | M106: =IF(ISERROR(M34/M51),"NA",(M34/M51)) -> 2.2054889 | N106: =IF(ISERROR(N34/N51),"NA",(N34/N51)) -> 1.9692981 | ... R106: =IF(ISERROR(R34/R51),"NA",(R34/R51)) -> 1.1792101 | T106: =IF(ISERROR(T34/T51),"NA",(T34/T51)) -> 1.6748039 | U106: =IF(ISERROR(U34/U51),"NA",(U34/U51)) -> 1.3992213 | V106: =IF(ISERROR(V34/V51),"NA",(V34/V51)) -> 2.2673942 | W106: =IF(ISERROR(W34/W51),"NA",(W34/W51)) -> 1.9692981 | X106: =IF(ISERROR(X34/X51),"NA",(X34/X51)) -> 1.1792101 | Y106: =IF(ISERROR(Y34/Y51),"NA",(Y34/Y51)) -> 1.3468955 | Z106: =IF(ISERROR(Z34/Z51),"NA",(Z34/Z51)) -> 1.3447258 | AA106: =IF(ISERROR(AA34/AA51),"NA",(AA34/AA51)) -> 1.1796717
A110: x

Sheet Model Output
B1: =Company_Name&" "&"("&Ticker&")"&" Valuation Overview" -> Hamilton Lane Inc. (HLNE) Valuation Overview | K1: Price Target Scenario: | N1: =Case_Scenario&" Case" -> Base Case | R1: Base Case Check | S1: =IF(N1="Base Case","","Check!") | Y1: P/E
B2: =Cover!C2 -> $ in Millions Except Per Share Data | K2: Current Share Price: | O2: =Share_Price -> 118.26 | Y2: EV/EBITDA
K3: Valuation Date: | O3: =Current_Date -> 45940
B4: ="Multiples Analysis "&"("&S21&")" -> Multiples Analysis (P/E) | I4: Return Summary
I6: Exit Multiple Method
I7: =Cover!I9 -> Implied Enterprise Value: | N7: =Cover!L9 -> 8117.2262
I8: =Cover!I10 -> Implied Equity Value: | N8: =Cover!L10 -> 7855.7462
I9: =Cover!I12 -> Implied Share Price: | N9: =Cover!L12 -> 144.22152
I10: =Cover!I13 -> % Return: | N10: =Cover!L13 -> 0.21952917
I12: =Cover!I15 -> Perpetuity Growth Method
I13: =Cover!I16 -> Implied Enterprise Value: | N13: =Cover!L16 -> 5013.5852
I14: =Cover!I17 -> Implied Equity Value: | N14: =Cover!L17 -> 4752.1052
I15: =Cover!I19 -> Implied Share Price: | N15: =Cover!L19 -> 87.242614
I16: =Cover!I20 -> % Return: | N16: =Cover!L20 -> -0.2622813
E18: Annuals | M18: CAGR | O18: CAGR
B19: Consolidated Financials | E19: =Summary!U6 -> 2024 | F19: =Summary!V6 -> 2025 | G19: =Summary!W6 -> 2026e | H19: =Summary!X6 -> 2027e | I19: =Summary!Y6 -> 2028e | J19: =Summary!Z6 -> 2029e | K19: =Summary!AA6 -> 2030e | M19: Historical | O19: Projected
B21: =Summary!C8 -> Revenue | D21: =Summary!T8 -> 528.753 | E21: =Summary!U8 -> 553.842 | F21: =Summary!V8 -> 712.964 | G21: =Summary!W8 -> 766.65695 | H21: =Summary!X8 -> 972.5283 | I21: =Summary!Y8 -> 1040.6053 | J21: =Summary!Z8 -> 1097.8386 | K21: =Summary!AA8 -> 1169.5212 | M21: =Summary!AC8 -> 0.16120094 | O21: =Summary!AE8 -> 0.10404837 | R21: Multiple Toggle | S21: P/E
B22: =Summary!C9 -> YoY % Growth | E22: =Summary!U9 -> 0.047449376 | F22: =Summary!V9 -> 0.28730577 | G22: =Summary!W9 -> 0.075309483 | H22: =Summary!X9 -> 0.26853125 | I22: =Summary!Y9 -> 0.07 | J22: =Summary!Z9 -> 0.055 | K22: =Summary!AA9 -> 0.065294368
R23: Multiples Analysis | S23: EV/EBITDA | T23: P/E | U23: Chart
B24: =Summary!C11 -> Gross Profit | D24: =Summary!T11 -> 528.753 | E24: =Summary!U11 -> 553.842 | F24: =Summary!V11 -> 712.964 | G24: =Summary!W11 -> 766.65695 | H24: =Summary!X11 -> 972.5283 | I24: =Summary!Y11 -> 1040.6053 | J24: =Summary!Z11 -> 1097.8386 | K24: =Summary!AA11 -> 1169.5212 | M24: =Summary!AC11 -> 0.16120094 | O24: =Summary!AE11 -> 0.10404837 | R24: Entry Multiple | S24: =Valuation!D12 -> 22.107789 | T24: =Valuation!D11 -> 25.058916 | U24: =IF($S$21=$S$23,S24,T24) -> 25.058916
B25: =Summary!C12 -> % Margin | E25: =Summary!U12 -> 1 | F25: =Summary!V12 -> 1 | G25: =Summary!W12 -> 1 | H25: =Summary!X12 -> 1 | I25: =Summary!Y12 -> 1 | J25: =Summary!Z12 -> 1 | K25: =Summary!AA12 -> 1 | R25: =Model!Y25 -> 2026e | S25: =(Comparables!H10*S30)/(Model!Y61) -> 24.14901 | T25: =(Comparables!$G$10*S30)/Summary!W19 -> 18.816316 | U25: =IF($S$21=$S$23,S25,T25) -> 18.816316
B26: =Summary!C13 -> YoY % Growth | E26: =Summary!U13 -> 0.047449376 | F26: =Summary!V13 -> 0.28730577 | G26: =Summary!W13 -> 0.075309483 | H26: =Summary!X13 -> 0.26853125 | I26: =Summary!Y13 -> 0.07 | J26: =Summary!Z13 -> 0.055 | K26: =Summary!AA13 -> 0.065294368 | R26: =Summary!AA6 -> 2030e | S26: =(Comparables!H10*S30)/(Model!AG61) -> 15.29073 | T26: =(Comparables!$G$10*S30)/Summary!AA19 -> 13.154113 | U26: =IF($S$21=$S$23,S26,T26) -> 13.154113
R27: Exit Multiple | S27: =Valuation!K60 -> 25 | T27: =Valuation!K72/Summary!AA19 -> 18.609235 | U27: =IF($S$21=$S$23,S27,T27) -> 18.609235
B28: =Summary!C27 -> EBITDA | D28: =Summary!T27 -> 161.848 | E28: =Summary!U27 -> 159.471 | F28: =Summary!V27 -> 220.202 | G28: =Summary!W27 -> 244.44576 | H28: =Summary!X27 -> 318.98056 | I28: =Summary!Y27 -> 346.72968 | J28: =Summary!Z27 -> 362.39651 | K28: =Summary!AA27 -> 386.05896 | M28: =Summary!AC27 -> 0.16642538 | O28: =Summary!AE27 -> 0.11883611 | R28: Implied PGM | S28: =Valuation!K79 -> 13.895187 | T28: =Valuation!R72/Summary!AA19 -> 11.257115 | U28: =IF($S$21=$S$23,S28,T28) -> 11.257115
B29: =Summary!C28 -> Margin | E29: =Summary!U28 -> 0.28793591 | F29: =Summary!V28 -> 0.3088543 | G29: =Summary!W28 -> 0.31884634 | H29: =Summary!X28 -> 0.32799104 | I29: =Summary!Y28 -> 0.3332 | J29: =Summary!Z28 -> 0.3301 | K29: =Summary!AA28 -> 0.3301
B30: =Summary!C29 -> YoY % Growth | E30: =Summary!U17 -> 0.024613192 | F30: =Summary!V17 -> 0.28775878 | G30: =Summary!W29 -> 0.11009782 | H30: =Summary!X29 -> 0.30491346 | I30: =Summary!Y29 -> 0.086993122 | J30: =Summary!Z29 -> 0.045184574 | K30: =Summary!AA29 -> 0.065294368 | R30: Financials Multiplier | S30: =IF($B$2="$ in Millions Except Per Share Data",1,IF($B$2="$ in Thousands Except Per Share Data",1000,IF($B$2="$ in Billions Except Per Share Data",0.001,0))) -> 1
B32: =Summary!C19 -> Net Income (Loss) | D32: =Summary!T19 -> 187.056 | E32: =Summary!U19 -> 227.204 | F32: =Summary!V19 -> 313.768 | G32: =Summary!W19 -> 295.11134 | H32: =Summary!X19 -> 358.09711 | I32: =Summary!Y19 -> 374.51536 | J32: =Summary!Z19 -> 395.85242 | K32: =Summary!AA19 -> 422.14236 | M32: =Summary!AC19 -> 0.29514533 | O32: =Summary!AE19 -> 0.061133577
B33: =Summary!C20 -> Margin | E33: =Summary!U20 -> 0.41023252 | F33: =Summary!V20 -> 0.44008954 | G33: =Summary!W20 -> 0.38493271 | H33: =Summary!X20 -> 0.36821254 | I33: =Summary!Y20 -> 0.35990146 | J33: =Summary!Z20 -> 0.36057434 | K33: =Summary!AA20 -> 0.36095314
B34: =Summary!C21 -> YoY % Growth | E34: =Summary!U21 -> 0.21463091 | F34: =Summary!V21 -> 0.38099681 | G34: =Summary!W21 -> -0.05946006 | H34: =Summary!X21 -> 0.21343056 | I34: =Summary!Y21 -> 0.045848579 | J34: =Summary!Z21 -> 0.05697246 | K34: =Summary!AA21 -> 0.066413498
B36: =Summary!C23 -> Adj. EPS (Diluted) | D36: =Summary!T23 -> 2.0297218 | E36: =Summary!U23 -> 2.613321 | F36: =Summary!V23 -> 5.3949628 | G36: =Summary!W23 -> 3.7993392 | H36: =Summary!X23 -> 4.782132 | I36: =Summary!Y23 -> 5.2892288 | J36: =Summary!Z23 -> 5.5611767 | K36: =Summary!AA23 -> 5.965623 | M36: =Summary!AC23 -> 0.63033169 | O36: =Summary!AE23 -> 0.020313118
B37: =Summary!C24 -> YoY % Growth | E37: =Summary!U24 -> 0.28752669 | F37: =Summary!V24 -> 1.0644088 | G37: =Summary!W24 -> -0.29576174 | H37: =Summary!X24 -> 0.25867467 | I37: =Summary!Y24 -> 0.10603989 | J37: =Summary!Z24 -> 0.051415408 | K37: =Summary!AA24 -> 0.072726758
B39: Free Cash Flow | D39: =Model!J114 -> 191.153 | E39: =Model!O114 -> 161.313 | F39: =Model!T114 -> 238.051 | G39: =Model!Y114 -> 292.20213 | H39: =Model!AD114 -> 289.95117 | I39: =Model!AE114 -> 387.78289 | J39: =Model!AF114 -> 369.32368 | K39: =Model!AG114 -> 397.70141 | M39: =IFERROR((F39/D39)^(1/2)-1,"N/A") -> 0.11594925 | O39: =IFERROR((K39/G39)^(1/4)-1,"N/A") -> 0.080111121
B40: YoY % Growth | E40: =E39/D39-1 -> -0.15610532 | F40: =F39/E39-1 -> 0.47570872 | G40: =G39/F39-1 -> 0.22747701 | H40: =H39/G39-1 -> -0.0077034412 | I40: =I39/H39-1 -> 0.33740758 | J40: =J39/I39-1 -> -0.047601908 | K40: =K39/J39-1 -> 0.076837001
E42: Annuals | M42: Average | O42: Average
B43: Capitalization and Key Ratios | E43: =E19 -> 2024 | F43: =F19 -> 2025 | G43: =G19 -> 2026e | H43: =H19 -> 2027e | I43: =I19 -> 2028e | J43: =J19 -> 2029e | K43: =K19 -> 2030e | M43: Historical | O43: Projected
B44: =Summary!C91 -> Leverage
B45: =Summary!C92 -> Total Debt / EBITDA | D45: =Summary!T92 -> 1.3193428 | E45: =Summary!U92 -> 1.2300606 | F45: =Summary!V92 -> 1.3183486 | G45: =Summary!W92 -> 1.1621474 | H45: =Summary!X92 -> 0.87178352 | I45: =Summary!Y92 -> 0.78470929 | J45: =Summary!Z92 -> 0.73422892 | K45: =Summary!AA92 -> 0.67368466 | M45: =AVERAGE(D45:F45) -> 1.2892507 | O45: =AVERAGE(G45:K45) -> 0.84531075
B46: =Summary!C93 -> Total Debt / Equity | D46: =Summary!T93 -> 0.37188432 | E46: =Summary!U93 -> 0.29019407 | F46: =Summary!V93 -> 0.31421644 | G46: =Summary!W93 -> 0.25404395 | H46: =Summary!X93 -> 0.19866935 | I46: =Summary!Y93 -> 0.16387608 | J46: =Summary!Z93 -> 0.13748538 | K46: =Summary!AA93 -> 0.11758546 | M46: =AVERAGE(D46:F46) -> 0.32543161 | O46: =AVERAGE(G46:K46) -> 0.17433204
B47: =Summary!C94 -> Total Debt / Total Assets | D47: =Summary!T94 -> 0.18722047 | E47: =Summary!U94 -> 0.1543101 | F47: =Summary!V94 -> 0.17174085 | G47: =Summary!W94 -> 0.14479637 | H47: =Summary!X94 -> 0.1200978 | I47: =Summary!Y94 -> 0.10528227 | J47: =Summary!Z94 -> 0.092518497 | K47: =Summary!AA94 -> 0.081920071 | M47: =AVERAGE(D47:F47) -> 0.17109047 | O47: =AVERAGE(G47:K47) -> 0.108923
B49: =Summary!C103 -> Liquidity
B50: =Summary!C104 -> Current Ratio | D50: =Summary!T104 -> 2.8331681 | E50: =Summary!U104 -> 3.0165025 | F50: =Summary!V104 -> 4.3968219 | G50: =Summary!W104 -> 3.5792447 | H50: =Summary!X104 -> 2.8666792 | I50: =Summary!Y104 -> 2.8172853 | J50: =Summary!Z104 -> 2.8451006 | K50: =Summary!AA104 -> 2.6800465 | M50: =AVERAGE(D50:F50) -> 3.4154975 | O50: =AVERAGE(G50:K50) -> 2.9576713
B51: =Summary!C105 -> Quick Ratio | D51: =Summary!T105 -> 2.4667932 | E51: =Summary!U105 -> 2.7210199 | F51: =Summary!V105 -> 4.0623343 | G51: =Summary!W105 -> 3.275107 | H51: =Summary!X105 -> 2.5692708 | I51: =Summary!Y105 -> 2.5163108 | J51: =Summary!Z105 -> 2.5441261 | K51: =Summary!AA105 -> 2.379072 | M51: =AVERAGE(D51:F51) -> 3.0833825 | O51: =AVERAGE(G51:K51) -> 2.6567773
B52: =Summary!C106 -> Cash Ratio | D52: =Summary!T106 -> 1.6748039 | E52: =Summary!U106 -> 1.3992213 | F52: =Summary!V106 -> 2.2673942 | G52: =Summary!W106 -> 1.9692981 | H52: =Summary!X106 -> 1.1792101 | I52: =Summary!Y106 -> 1.3468955 | J52: =Summary!Z106 -> 1.3447258 | K52: =Summary!AA106 -> 1.1796717 | M52: =AVERAGE(D52:F52) -> 1.7804731 | O52: =AVERAGE(G52:K52) -> 1.4039602
B54: =Summary!C75 -> Profitability
B55: =Summary!C80 -> Return on Assets (ROA) | D55: =Summary!T80 -> 0.16400609 | E55: =Summary!U80 -> 0.17873191 | F55: =Summary!V80 -> 0.18562255 | G55: =Summary!W80 -> 0.15041801 | H55: =Summary!X80 -> 0.15465466 | I55: =Summary!Y80 -> 0.14491892 | J55: =Summary!Z80 -> 0.13764054 | K55: =Summary!AA80 -> 0.1329655 | M55: =AVERAGE(D55:F55) -> 0.17612018 | O55: =AVERAGE(G55:K55) -> 0.14411953
B56: =Summary!C81 -> Return on Equity (ROE) | D56: =Summary!T81 -> 0.32577256 | E56: =Summary!U81 -> 0.33612148 | F56: =Summary!V81 -> 0.33961435 | G56: =Summary!W81 -> 0.26390708 | H56: =Summary!X81 -> 0.25583432 | I56: =Summary!Y81 -> 0.2255721 | J56: =Summary!Z81 -> 0.20453814 | K56: =Summary!AA81 -> 0.19085444 | M56: =AVERAGE(D56:F56) -> 0.33383613 | O56: =AVERAGE(G56:K56) -> 0.22814122
B57: Return on Inv. Capital (ROIC) | D57: =Summary!T82 -> 0.23746358 | E57: =Summary!U82 -> 0.26052009 | F57: =Summary!V82 -> 0.25841584 | G57: =Summary!W82 -> 0.21044484 | H57: =Summary!X82 -> 0.21343194 | I57: =Summary!Y82 -> 0.1938111 | J57: =Summary!Z82 -> 0.17981607 | K57: =Summary!AA82 -> 0.17077391 | M57: =AVERAGE(D57:F57) -> 0.25213317 | O57: =AVERAGE(G57:K57) -> 0.19365557
B59: =Summary!C84 -> Coverage
B60: Interest Expense | D60: =Summary!T85 -> 8.618 | E60: =Summary!U85 -> 11.175 | F60: =Summary!V85 -> 13.332 | G60: =Summary!W85 -> 11.35074 | H60: =Summary!X85 -> 9.8097618 | I60: =Summary!Y85 -> 9.6003618 | J60: =Summary!Z85 -> 9.3909618 | K60: =Summary!AA85 -> 9.1815618 | M60: =AVERAGE(D60:F60) -> 11.041667 | O60: =AVERAGE(G60:K60) -> 9.8666775
B61: Capital Expenditures | D61: =Summary!T86 -> -2.928 | E61: =Summary!U86 -> 4.686 | F61: =Summary!V86 -> 3.561 | G61: =Summary!W86 -> 4.3432346 | H61: =Summary!X86 -> 7.7802264 | I61: =Summary!Y86 -> 8.3248422 | J61: =Summary!Z86 -> 8.7827086 | K61: =Summary!AA86 -> 9.35617 | M61: =AVERAGE(D61:F61) -> 1.773 | O61: =AVERAGE(G61:K61) -> 7.7174364
B62: EBIT / Interest | D62: =Summary!T87 -> 27.838478 | E62: =Summary!U87 -> 21.997047 | F62: =Summary!V87 -> 23.743849 | G62: =Summary!W87 -> 29.315062 | H62: =Summary!X87 -> 42.629696 | I62: =Summary!Y87 -> 45.524765 | J62: =Summary!Z87 -> 49.099571 | K62: =Summary!AA87 -> 53.498406 | M62: =AVERAGE(D62:F62) -> 24.526458 | O62: =AVERAGE(G62:K62) -> 44.0135
B63: EBITDA / Interest | D63: =Summary!T88 -> 18.780227 | E63: =Summary!U88 -> 14.270336 | F63: =Summary!V88 -> 16.516802 | G63: =Summary!W88 -> 21.535667 | H63: =Summary!X88 -> 32.516647 | I63: =Summary!Y88 -> 36.116314 | J63: =Summary!Z88 -> 38.589925 | K63: =Summary!AA88 -> 42.0472 | M63: =AVERAGE(D63:F63) -> 16.522455 | O63: =AVERAGE(G63:K63) -> 34.161151
B64: (EBITDA - CapEx) / Interest | D64: =Summary!T89 -> 19.119981 | E64: =Summary!U89 -> 13.851007 | F64: =Summary!V89 -> 16.2497 | G64: =Summary!W89 -> 21.153028 | H64: =Summary!X89 -> 31.723537 | I64: =Summary!Y89 -> 35.249175 | J64: =Summary!Z89 -> 37.654695 | K64: =Summary!AA89 -> 41.028182 | M64: =AVERAGE(D64:F64) -> 16.406896 | O64: =AVERAGE(G64:K64) -> 33.361724
B66: =Summary!C96 -> Efficiency
B67: =Summary!C97 -> Asset Turnover | D67: =Summary!T97 -> 0.4635976 | E67: =Summary!U97 -> 0.43568439 | F67: =Summary!V97 -> 0.42178359 | G67: =Summary!W97 -> 0.39076444 | H67: =Summary!X97 -> 0.42001465 | I67: =Summary!Y97 -> 0.40266276 | J67: =Summary!Z97 -> 0.38172584 | K67: =Summary!AA97 -> 0.3683733 | M67: =AVERAGE(D67:F67) -> 0.44035519 | O67: =AVERAGE(G67:K67) -> 0.3927082
B68: =Summary!C98 -> Days Sales Outstanding | D68: =Summary!T98 -> 33.172044 | E68: =Summary!U98 -> 51.217057 | F68: =Summary!V98 -> 74.156079 | G68: =Summary!W98 -> 86.432474 | H68: =Summary!X98 -> 80.054629 | I68: =Summary!Y98 -> 78 | J68: =Summary!Z98 -> 80 | K68: =Summary!AA98 -> 80 | M68: =AVERAGE(D68:F68) -> 52.848394 | O68: =AVERAGE(G68:K68) -> 80.897421
B69: =Summary!C99 -> Days Inventory Outstanding | D69: =Summary!T99 -> 0 | E69: =Summary!U99 -> 0 | F69: =Summary!V99 -> 0 | G69: =Summary!W99 -> 0 | H69: =Summary!X99 -> 0 | I69: =Summary!Y99 -> 0 | J69: =Summary!Z99 -> 0 | K69: =Summary!AA99 -> 0 | M69: =AVERAGE(D69:F69) -> 0 | O69: =AVERAGE(G69:K69) -> 0
B70: =Summary!C100 -> Days Payables Outstanding | D70: =Summary!T100 -> 3.8381462 | E70: =Summary!U100 -> 5.0165652 | F70: =Summary!V100 -> 5.0255164 | G70: =Summary!W100 -> 5.5937581 | H70: =Summary!X100 -> 5.61476 | I70: =Summary!Y100 -> 5.5 | J70: =Summary!Z100 -> 5.5 | K70: =Summary!AA100 -> 5.5 | M70: =AVERAGE(D70:F70) -> 4.6267426 | O70: =AVERAGE(G70:K70) -> 5.5417036
B71: =Summary!C101 -> Cash Conversion Cycle | D71: =Summary!T101 -> 29.333898 | E71: =Summary!U101 -> 46.200492 | F71: =Summary!V101 -> 69.130563 | G71: =Summary!W101 -> 80.838716 | H71: =Summary!X101 -> 74.439869 | I71: =Summary!Y101 -> 72.5 | J71: =Summary!Z101 -> 74.5 | K71: =Summary!AA101 -> 74.5 | M71: =AVERAGE(D71:F71) -> 48.221651 | O71: =AVERAGE(G71:K71) -> 75.355717

Sheet Football Field
C1: =Company_Name&" - "&MID(CELL("filename",A1),FIND("]",CELL("filename",A1))+1,255)&": "&Case_Scenario&" Case" -> Hamilton Lane Inc. - Football Field: Base Case
C2: =Cover!C2 -> $ in Millions Except Per Share Data
A4: x | O4: Valuation Method: | T4: Downside | U4: Delta | V4: Upside | W4: x
O5: =TEXT(Valuation!E108,"0.0%")&" - "&TEXT(Valuation!E110,"0.0%")&" WACC"&" & "&TEXT(Valuation!G106,"0.0%")&" - "&TEXT(Valuation!I106,"0.0%")&" PGR" -> 8.0% - 9.0% WACC & 1.5% - 2.5% PGR | T5: =Valuation!G108 -> 195.04955 | U5: =V5-T5 -> 20.385916 | V5: =Valuation!I110 -> 215.43546
O6: =TEXT(Valuation!E100,"0.0%")&" - "&TEXT(Valuation!E102,"0.0%")&" WACC"&" & "&TEXT(Valuation!G98,"0.0x")&" - "&TEXT(Valuation!I98,"0.0x")&" Exit Multiple" -> 8.0% - 9.0% WACC & 24.0x - 26.0x Exit Multiple | T6: =Valuation!G100 -> 250.78262 | U6: =V6-T6 -> 27.264041 | V6: =Valuation!I102 -> 278.04666
O8: =Valuation!F184&": "&TEXT(Valuation!G185,"0.0x")&" - "&TEXT(Valuation!I185,"0.0x") -> NTM EV/EBITDA Spread to Comps: 29.3x - 31.3x | T8: =Valuation!G187 -> 209.23348 | U8: =V8-T8 -> 100.49025 | V8: =Valuation!I189 -> 309.72373
O9: =Valuation!F176&": "&TEXT(Valuation!G177,"0.0x")&" - "&TEXT(Valuation!I177,"0.0x") -> NTM EV/EBITDA: 21.5x - 23.5x | T9: =Valuation!G179 -> 197.97414 | U9: =V9-T9 -> 97.988172 | V9: =Valuation!I181 -> 295.96231
O10: =Valuation!F168&": "&TEXT(Valuation!G169,"0.0x")&" - "&TEXT(Valuation!I169,"0.0x") -> NTM P/E Spread to Comps: 33.2x - 35.2x | T10: =Valuation!G171 -> 241.4239 | U10: =V10-T10 -> 85.926567 | V10: =Valuation!I173 -> 327.35047
O11: =Valuation!F160&": "&TEXT(Valuation!G161,"0.0x")&" - "&TEXT(Valuation!I161,"0.0x") -> NTM P/E: 26.9x - 28.9x | T11: =Valuation!G163 -> 234.48845 | U11: =V11-T11 -> 84.385357 | V11: =Valuation!I165 -> 318.87381
O13: =Valuation!F260&": "&TEXT(Valuation!G261,"0.0x")&" - "&TEXT(Valuation!I261,"0.0x") -> 2009-2018 Early Cycle EV/EBITDA Spread to Comps: 17.7x - 19.7x | T13: =Valuation!G263 -> 202.21364 | U13: =V13-T13 -> 39.300331 | V13: =Valuation!I263 -> 241.51397
O14: =Valuation!F252&": "&TEXT(Valuation!G253,"0.0x")&" - "&TEXT(Valuation!I253,"0.0x") -> 2009-2018 Early Cycle EV/EBITDA: 10.8x - 12.8x | T14: =Valuation!G255 -> 99.103102 | U14: =V14-T14 -> 39.300331 | V14: =Valuation!I255 -> 138.40343
O15: =Valuation!F244&": "&TEXT(Valuation!G245,"0.0x")&" - "&TEXT(Valuation!I245,"0.0x") -> 2009-2018 Early Cycle P/E Spread to Comps: 42.9x - 44.9x | T15: =Valuation!G247 -> 267.04261 | U15: =V15-T15 -> 26.408301 | V15: =Valuation!I247 -> 293.45091
O16: =Valuation!F236&": "&TEXT(Valuation!G237,"0.0x")&" - "&TEXT(Valuation!I237,"0.0x") -> 2009-2018 Early Cycle P/E: 19.7x - 21.7x | T16: =Valuation!G239 -> 205.30919 | U16: =V16-T16 -> 26.408301 | V16: =Valuation!I239 -> 231.71749
O18: 52-Week Price Range: | T18: =Share_Price_Low -> 124.1 | U18: =V18-T18 -> 79.62 | V18: =Share_Price_High -> 203.72
O19: Median Value: | T19: =MEDIAN(T5:T18) -> 205.30919 | U19: =MEDIAN(U5:U18) -> 39.300331 | V19: =MEDIAN(V5:V18) -> 278.04666
A20: x | O20: Implied Return (%): | T20: =T19/Share_Price-1 -> 0.73608312 | V20: =V19/Share_Price-1 -> 1.3511471
T22: Reference Points for Price Axis
U24: Price
A25: x | T25: High | U25: =MAX(V5:V18)*1.1 -> 360.08551 | W25: x
T26: Low | U26: =MIN(T5:T18)*0.9 -> 89.192792
A30: x

Sheet Integrity
C1: =Company_Name&" - "&MID(CELL("filename",A1),FIND("]",CELL("filename",A1))+1,255) -> Hamilton Lane Inc. - Integrity
C3: Integrity
C4: Metric
C6: Model:
C7: Balance Sheet Check: | D7: =SUM(Model!F159:AG159) -> 0
C8: Base Case: | D8: =IF(Case_Scenario="Base","OK!","Check!") -> OK!
C9: Interest Expense: | D9: =IF(Model!C8="On","OK!","CHECK - OFF") -> OK!
C10: Valuation Date:
C12: Formatting:
C13: Valuation Sensitivity Tables: | D13: =SUM(Valuation!F92,Valuation!K92,Valuation!P92,Valuation!F151:F155,Valuation!L151:L155,Valuation!F227:F231,Valuation!L227:L231) -> 0
C14: WACC Tables: | D14: =SUM(WACC!Q20,WACC!N33:N37) -> 0
C16: Font Toggles:
C17: Cover: | D17: =Cover!$Q$2 -> Report
C18: Revenue Build: | D18: ='Revenue Build'!$C$22 -> Report
C19: Model: | D19: =Model!$C$5 -> Report
C20: WACC | D20: =WACC!R5 -> Report
C21: Valuation: | D21: =Valuation!$R$2 -> Report
C23: Change Log
C24: Date | D24: Version | E24: Operator | F24: Revisions
C25: 44476 | D25: v01 | E25: Nate Latimer | F25: Top Down / Bottom Up toggle integration and Capital IQ comps sheet w/ ID Locator
C26: 44476 | D26: v02 | E26: Carson Shaner | F26: Formulas for EBIT/EBITDA margins on earnings sheets
C27: 44480 | D27: v03 | E27: Nate Latimer | F27: Historical driver adjustments to reflect Top Down / Bottom Up Toggle
C28: 44488 | D28: v04 | E28: Nate Latimer | F28: Bug fixes to model output, comps sheet and WACC Comps Relevered Beta
C29: 44489 | D29: v05 | E29: Lilianna Ruby | F29: Changed the year end driver in 2021 and 2022 to correctly pull operating margins
C30: 44491 | D30: v06 | E30: Lilianna Ruby | F30: Changed the first page to add 365 to your previous fiscal year
C31: 44496 | D31: v07 | E31: Carson Shaner | F31: Changed Model Output FCF formula, broke apart D&A for historical periods, added checks for EPS & EBITDA in Valuation sensitivity tables, added segment D&A breakdown, linked and fixed SOTP valuation
C32: 44503 | D32: v08 | E32: Lilianna Ruby | F32: Changed average of comps on valuation tab to average all peers not just the first one
C33: 44512 | D33: v09 | E33: Lilianna Ruby | F33: Rolled model forward to reflect 3Q'21. Also changed the multiples tab so the quarters roll forward and end on correct date.
C34: 44522 | D34: v10 | E34: Lilianna Ruby | F34: Fully fixed the multiples tab so it is automatic and fully functional. Also fixed definition of NTM_EPS and NTM_EBITDA
C35: 44582 | D35: v13 | E35: Carson Shaner | F35: Changed EPS, EBITDA, shares, tax rate, etc., to formulas so we do not have to hardcode them.
C36: 44584 | D36: v14 | E36: Lilianna Ruby | F36: Changed discount factor to mid year
... C47: 45581 | D47: v25 | E47: Conor McCabe | F47: Added font toggle to integrity tab for WACC tab. Formatted Comparables Tab.

Sheet Revenue Build
C1: =Company_Name&" - "&MID(CELL("filename",A1),FIND("]",CELL("filename",A1))+1,255)&": "&Case_Scenario&" Case" -> Hamilton Lane Inc. - Revenue Build: Base Case
C2: =Cover!C2 -> $ in Millions Except Per Share Data
A4: x | C4: Segments
C6: =C30&" Methodology" -> Total Company Revenue Methodology
C7: Segment
C8: =C32&" Methodology" -> Management & Advisory Fees Methodology
C9: =IF(Company_Rev_Methodology="Segment","Segment",IF(Company_Rev_Methodology="Activity-Based","Activity-Based",IF(Company_Rev_Methodology="Backlog","Backlog",IF(Company_Rev_Methodology="Mixed",D9,"--")))) -> Segment | D9: Backlog
C10: =C35&" Methodology" -> Incentive Fees Methodology
C11: =IF(Company_Rev_Methodology="Segment","Segment",IF(Company_Rev_Methodology="Activity-Based","Activity-Based",IF(Company_Rev_Methodology="Backlog","Backlog",IF(Company_Rev_Methodology="Mixed",D11,"--")))) -> Segment | D11: Activity-Based
C12: =C38&" Methodology" -> Segment 3 Revenue Methodology
C13: =IF(Company_Rev_Methodology="Segment","Segment",IF(Company_Rev_Methodology="Activity-Based","Activity-Based",IF(Company_Rev_Methodology="Backlog","Backlog",IF(Company_Rev_Methodology="Mixed",D13,"--")))) -> Segment | D13: Segment
C14: =C41&" Methodology" -> Segment 4 Revenue Methodology
C15: =IF(Company_Rev_Methodology="Segment","Segment",IF(Company_Rev_Methodology="Activity-Based","Activity-Based",IF(Company_Rev_Methodology="Backlog","Backlog",IF(Company_Rev_Methodology="Mixed",D15,"--")))) -> Segment | D15: Segment
C16: =C44&" Methodology" -> Segment 5 Revenue Methodology
C17: =IF(Company_Rev_Methodology="Segment","Segment",IF(Company_Rev_Methodology="Activity-Based","Activity-Based",IF(Company_Rev_Methodology="Backlog","Backlog",IF(Company_Rev_Methodology="Mixed",D17,"--")))) -> Segment | D17: Segment
C18: =C47&" Methodology" -> Segment 6 Revenue Methodology
C19: =IF(Company_Rev_Methodology="Segment","Segment",IF(Company_Rev_Methodology="Activity-Based","Activity-Based",IF(Company_Rev_Methodology="Backlog","Backlog",IF(Company_Rev_Methodology="Mixed",D19,"--")))) -> Segment | D19: Segment
C21: Font Toggle
C22: Report
C24: Annual vs. Quarterly
C25: Quarterly
J26: 1 | O26: 2 | T26: 3 | Y26: 4 | AD26: 5 | AE26: 6 | AF26: 7 | AG26: 8
AI27: CAGR
A28: x | C28: Summary | F28: =Model!F$25 -> 1Q23 | G28: =Model!G$25 -> 2Q23 | H28: =Model!H$25 -> 3Q23 | I28: =Model!I$25 -> 4Q23 | J28: =Model!J$25 -> 2023 | K28: =Model!K$25 -> 1Q24 | L28: =Model!L$25 -> 2Q24 | M28: =Model!M$25 -> 3Q24 | ... AG28: =Model!AG$25 -> 2030e | AI28: Historical | AJ28: Projected
C30: Total Company Revenue | F30: ='Segment Analysis'!F7 -> 135.509 | G30: ='Segment Analysis'!G7 -> 153.382 | H30: ='Segment Analysis'!H7 -> 127.074 | I30: ='Segment Analysis'!I7 -> 112.788 | J30: ='Segment Analysis'!J7 -> 528.753 | K30: ='Segment Analysis'!K7 -> 125.037 | L30: ='Segment Analysis'!L7 -> 126.876 | M30: ='Segment Analysis'!M7 -> 125.264 | ... U30: ='Segment Analysis'!U7 -> 175.958 | V30: =SUM(V32,V35,V38,V41,V44,V47,) -> 183.91066 | W30: =SUM(W32,W35,W38,W41,W44,W47,) -> 195.21191 | X30: =SUM(X32,X35,X38,X41,X44,X47,) -> 211.57639 | Y30: =SUM(U30:X30) -> 766.65695 | Z30: =SUM(Z32,Z35,Z38,Z41,Z44,Z47,) -> 224.51778 | AA30: =SUM(AA32,AA35,AA38,AA41,AA44,AA47,) -> 237.98885 | AB30: =SUM(AB32,AB35,AB38,AB41,AB44,AB47,) -> 249.25561 | AC30: =SUM(AC32,AC35,AC38,AC41,AC44,AC47,) -> 260.76606 | AD30: =SUM(Z30:AC30) -> 972.5283 | AE30: =SUM(AE32,AE35,AE38,AE41,AE44,AE47,) -> 1040.6053 | AF30: =SUM(AF32,AF35,AF38,AF41,AF44,AF47,) -> 1097.8386 | AG30: =SUM(AG32,AG35,AG38,AG41,AG44,AG47,) -> 1169.5212 | AI30: =IFERROR((T30/J30)^(1/3)-1,"--") -> 0.10476927 | AJ30: =IFERROR((AG30/T30)^(1/5)-1,"--") -> 0.10404837
C31: =IF($C$25="Quarterly","% Growth QoQ","% Growth YoY") -> % Growth QoQ | G31: =IF($C$25="Annual",'Segment Analysis'!G162,'Segment Analysis'!G182) -> 0.1318953 | H31: =IF($C$25="Annual",'Segment Analysis'!H162,'Segment Analysis'!H182) -> -0.17151947 | I31: =IF($C$25="Annual",'Segment Analysis'!I162,'Segment Analysis'!I182) -> -0.11242268 | K31: =IF($C$25="Annual",'Segment Analysis'!K162,'Segment Analysis'!K182) -> 0.10860198 | L31: =IF($C$25="Annual",'Segment Analysis'!L162,'Segment Analysis'!L182) -> 0.014707647 | M31: =IF($C$25="Annual",'Segment Analysis'!M162,'Segment Analysis'!M182) -> -0.012705319 | N31: =IF($C$25="Annual",'Segment Analysis'!N162,'Segment Analysis'!N182) -> 0.41034136 | O31: ='Segment Analysis'!O162 -> 0.047449376 | P31: =IF($C$25="Annual",'Segment Analysis'!P162,'Segment Analysis'!P182) -> 0.1135822 | Q31: =IF($C$25="Annual",'Segment Analysis'!Q162,'Segment Analysis'!Q182) -> -0.23754263 | R31: =IF($C$25="Annual",'Segment Analysis'!R162,'Segment Analysis'!R182) -> 0.12174748 | S31: =IF($C$25="Annual",'Segment Analysis'!S162,'Segment Analysis'!S182) -> 0.17658281 | T31: ='Segment Analysis'!T162 -> 0.28730577 | U31: =IF($C$25="Annual",'Segment Analysis'!U162,'Segment Analysis'!U182) -> -0.11120203 | V31: =IFERROR(V30/U30-1,"--") -> 0.045196354 | W31: =IFERROR(W30/V30-1,"--") -> 0.061449646 | X31: =IFERROR(X30/W30-1,"--") -> 0.083829314 | Y31: =IFERROR(Y30/T30-1,"--") -> 0.075309483 | Z31: =IFERROR(Z30/X30-1,"--") -> 0.061166549 | AA31: =IFERROR(AA30/Z30-1,"--") -> 0.06 | AB31: =IFERROR(AB30/AA30-1,"--") -> 0.047341527 | AC31: =IFERROR(AC30/AB30-1,"--") -> 0.046179325 | AD31: =IFERROR(AD30/Y30-1,"--") -> 0.26853125 | AE31: =IFERROR(AE30/AD30-1,"--") -> 0.07 | AF31: =IFERROR(AF30/AE30-1,"--") -> 0.055 | AG31: =IFERROR(AG30/AF30-1,"--") -> 0.065294368
C32: ='Segment Analysis'!C8 -> Management & Advisory Fees | F32: ='Segment Analysis'!F8 -> 85.946 | G32: ='Segment Analysis'!G8 -> 92.88 | H32: ='Segment Analysis'!H8 -> 97.355 | I32: ='Segment Analysis'!I8 -> 95.692 | J32: ='Segment Analysis'!J8 -> 371.873 | K32: ='Segment Analysis'!K8 -> 105.407 | L32: ='Segment Analysis'!L8 -> 109.184 | M32: ='Segment Analysis'!M8 -> 113.641 | ... U32: ='Segment Analysis'!U8 -> 133.696 | V32: =IF(Segment1_Rev_Methodology="Segment",V53,IF(Segment1_Rev_Methodology="Activity-Based",V91,IF(Segment1_Rev_Methodology="Backlog",V165,"--"))) -> 140.3808 | W32: =IF(Segment1_Rev_Methodology="Segment",W53,IF(Segment1_Rev_Methodology="Activity-Based",W91,IF(Segment1_Rev_Methodology="Backlog",W165,"--"))) -> 149.50555 | X32: =IF(Segment1_Rev_Methodology="Segment",X53,IF(Segment1_Rev_Methodology="Activity-Based",X91,IF(Segment1_Rev_Methodology="Backlog",X165,"--"))) -> 162.21352 | Y32: =SUM(U32:X32) -> 585.79588 | Z32: =IF(Segment1_Rev_Methodology="Segment",Z53,IF(Segment1_Rev_Methodology="Activity-Based",Z91,IF(Segment1_Rev_Methodology="Backlog",Z165,"--"))) -> 171.94634 | AA32: =IF(Segment1_Rev_Methodology="Segment",AA53,IF(Segment1_Rev_Methodology="Activity-Based",AA91,IF(Segment1_Rev_Methodology="Backlog",AA165,"--"))) -> 182.26312 | AB32: =IF(Segment1_Rev_Methodology="Segment",AB53,IF(Segment1_Rev_Methodology="Activity-Based",AB91,IF(Segment1_Rev_Methodology="Backlog",AB165,"--"))) -> 190.46496 | AC32: =IF(Segment1_Rev_Methodology="Segment",AC53,IF(Segment1_Rev_Methodology="Activity-Based",AC91,IF(Segment1_Rev_Methodology="Backlog",AC165,"--"))) -> 199.03588 | AD32: =SUM(Z32:AC32) -> 743.71029 | AE32: =IF(Segment1_Rev_Methodology="Segment",AE53,IF(Segment1_Rev_Methodology="Activity-Based",AE91,IF(Segment1_Rev_Methodology="Backlog",AE165,"--"))) -> 795.77001 | AF32: =IF(Segment1_Rev_Methodology="Segment",AF53,IF(Segment1_Rev_Methodology="Activity-Based",AF91,IF(Segment1_Rev_Methodology="Backlog",AF165,"--"))) -> 839.53736 | AG32: =IF(Segment1_Rev_Methodology="Segment",AG53,IF(Segment1_Rev_Methodology="Activity-Based",AG91,IF(Segment1_Rev_Methodology="Backlog",AG165,"--"))) -> 898.30497 | AI32: =IFERROR((T32/J32)^(1/3)-1,"--") -> 0.113828 | AJ32: =IFERROR((AG32/T32)^(1/5)-1,"--") -> 0.11818832
C33: =IF($C$25="Quarterly","% Growth QoQ","% Growth YoY") -> % Growth QoQ | G33: =IF($C$25="Annual",'Segment Analysis'!G163,'Segment Analysis'!G183) -> 0.080678566 | H33: =IF($C$25="Annual",'Segment Analysis'!H163,'Segment Analysis'!H183) -> 0.048180448 | I33: =IF($C$25="Annual",'Segment Analysis'!I163,'Segment Analysis'!I183) -> -0.017081814 | K33: =IF($C$25="Annual",'Segment Analysis'!K163,'Segment Analysis'!K183) -> 0.10152364 | L33: =IF($C$25="Annual",'Segment Analysis'!L163,'Segment Analysis'!L183) -> 0.035832535 | M33: =IF($C$25="Annual",'Segment Analysis'!M163,'Segment Analysis'!M183) -> 0.040820999 | N33: =IF($C$25="Annual",'Segment Analysis'!N163,'Segment Analysis'!N183) -> 0.088550787 | O33: ='Segment Analysis'!O163 -> 0.21529662 | P33: =IF($C$25="Annual",'Segment Analysis'!P163,'Segment Analysis'!P183) -> 0.13142663 | Q33: =IF($C$25="Annual",'Segment Analysis'!Q163,'Segment Analysis'!Q183) -> -0.14417485 | R33: =IF($C$25="Annual",'Segment Analysis'!R163,'Segment Analysis'!R183) -> 0.054256447 | S33: =IF($C$25="Annual",'Segment Analysis'!S163,'Segment Analysis'!S183) -> 0.012321629 | T33: ='Segment Analysis'!T163 -> 0.13703046 | U33: =IF($C$25="Annual",'Segment Analysis'!U163,'Segment Analysis'!U183) -> 0.045823621 | V33: =IFERROR(V32/U32-1,"--") -> 0.05 | W33: =IFERROR(W32/V32-1,"--") -> 0.065 | X33: =IFERROR(X32/W32-1,"--") -> 0.085 | Y33: =IFERROR(Y32/T32-1,"--") -> 0.1399801 | Z33: =IFERROR(Z32/X32-1,"--") -> 0.06 | AA33: =IFERROR(AA32/Z32-1,"--") -> 0.06 | AB33: =IFERROR(AB32/AA32-1,"--") -> 0.045 | AC33: =IFERROR(AC32/AB32-1,"--") -> 0.045 | AD33: =IFERROR(AD32/Y32-1,"--") -> 0.26957242 | AE33: =IFERROR(AE32/AD32-1,"--") -> 0.07 | AF33: =IFERROR(AF32/AE32-1,"--") -> 0.055 | AG33: =IFERROR(AG32/AF32-1,"--") -> 0.07
C34: % of Total Revenue | F34: ='Segment Analysis'!F16 -> 0.6342457 | G34: ='Segment Analysis'!G16 -> 0.60554694 | H34: ='Segment Analysis'!H16 -> 0.7661284 | I34: ='Segment Analysis'!I16 -> 0.84842359 | J34: ='Segment Analysis'!J16 -> 0.70330192 | K34: ='Segment Analysis'!K16 -> 0.84300647 | L34: ='Segment Analysis'!L16 -> 0.86055676 | M34: ='Segment Analysis'!M16 -> 0.90721197 | ... U34: ='Segment Analysis'!U16 -> 0.75981768 | V34: =V32/V$30 -> 0.76330975 | W34: =W32/W$30 -> 0.76586288 | X34: =X32/X$30 -> 0.76669012 | Y34: =Y32/Y$30 -> 0.76409126 | Z34: =Z32/Z$30 -> 0.76584729 | AA34: =AA32/AA$30 -> 0.76584729 | AB34: =AB32/AB$30 -> 0.7641351 | AC34: =AC32/AC$30 -> 0.76327371 | ... AG34: =AG32/AG$30 -> 0.76809633
C35: ='Segment Analysis'!C9 -> Incentive Fees | F35: ='Segment Analysis'!F9 -> 49.563 | G35: ='Segment Analysis'!G9 -> 60.502 | H35: ='Segment Analysis'!H9 -> 29.719 | I35: ='Segment Analysis'!I9 -> 17.096 | J35: ='Segment Analysis'!J9 -> 156.88 | K35: ='Segment Analysis'!K9 -> 19.63 | L35: ='Segment Analysis'!L9 -> 17.692 | M35: ='Segment Analysis'!M9 -> 11.623 | ... U35: ='Segment Analysis'!U9 -> 42.262 | V35: =IF(Segment2_Rev_Methodology="Segment",V59,IF(Segment2_Rev_Methodology="Activity-Based",V103,IF(Segment2_Rev_Methodology="Backlog",V177,"--"))) -> 43.52986 | W35: =IF(Segment2_Rev_Methodology="Segment",W59,IF(Segment2_Rev_Methodology="Activity-Based",W103,IF(Segment2_Rev_Methodology="Backlog",W177,"--"))) -> 45.706353 | X35: =IF(Segment2_Rev_Methodology="Segment",X59,IF(Segment2_Rev_Methodology="Activity-Based",X103,IF(Segment2_Rev_Methodology="Backlog",X177,"--"))) -> 49.362861 | Y35: =SUM(U35:X35) -> 180.86107 | Z35: =IF(Segment2_Rev_Methodology="Segment",Z59,IF(Segment2_Rev_Methodology="Activity-Based",Z103,IF(Segment2_Rev_Methodology="Backlog",Z177,"--"))) -> 52.571447 | AA35: =IF(Segment2_Rev_Methodology="Segment",AA59,IF(Segment2_Rev_Methodology="Activity-Based",AA103,IF(Segment2_Rev_Methodology="Backlog",AA177,"--"))) -> 55.725734 | AB35: =IF(Segment2_Rev_Methodology="Segment",AB59,IF(Segment2_Rev_Methodology="Activity-Based",AB103,IF(Segment2_Rev_Methodology="Backlog",AB177,"--"))) -> 58.790649 | AC35: =IF(Segment2_Rev_Methodology="Segment",AC59,IF(Segment2_Rev_Methodology="Activity-Based",AC103,IF(Segment2_Rev_Methodology="Backlog",AC177,"--"))) -> 61.730182 | AD35: =SUM(Z35:AC35) -> 228.81801 | AE35: =IF(Segment2_Rev_Methodology="Segment",AE59,IF(Segment2_Rev_Methodology="Activity-Based",AE103,IF(Segment2_Rev_Methodology="Backlog",AE177,"--"))) -> 244.83527 | AF35: =IF(Segment2_Rev_Methodology="Segment",AF59,IF(Segment2_Rev_Methodology="Activity-Based",AF103,IF(Segment2_Rev_Methodology="Backlog",AF177,"--"))) -> 258.30121 | AG35: =IF(Segment2_Rev_Methodology="Segment",AG59,IF(Segment2_Rev_Methodology="Activity-Based",AG103,IF(Segment2_Rev_Methodology="Backlog",AG177,"--"))) -> 271.21627 | AI35: =IFERROR((T35/J35)^(1/3)-1,"--") -> 0.08268096 | AJ35: =IFERROR((AG35/T35)^(1/5)-1,"--") -> 0.063773907
C36: % Growth | G36: =IF($C$25="Annual",'Segment Analysis'!G164,'Segment Analysis'!G184) -> 0.220709 | H36: =IF($C$25="Annual",'Segment Analysis'!H164,'Segment Analysis'!H184) -> -0.5087931 | I36: =IF($C$25="Annual",'Segment Analysis'!I164,'Segment Analysis'!I184) -> -0.42474511 | K36: =IF($C$25="Annual",'Segment Analysis'!K164,'Segment Analysis'!K184) -> 0.14822181 | L36: =IF($C$25="Annual",'Segment Analysis'!L164,'Segment Analysis'!L184) -> -0.098726439 | M36: =IF($C$25="Annual",'Segment Analysis'!M164,'Segment Analysis'!M184) -> -0.3430364 | N36: =IF($C$25="Annual",'Segment Analysis'!N164,'Segment Analysis'!N184) -> 3.5565689 | O36: ='Segment Analysis'!O164 -> -0.3504207 | P36: =IF($C$25="Annual",'Segment Analysis'!P164,'Segment Analysis'!P184) -> 0.071901966 | Q36: =IF($C$25="Annual",'Segment Analysis'!Q164,'Segment Analysis'!Q184) -> -0.46773767 | R36: =IF($C$25="Annual",'Segment Analysis'!R164,'Segment Analysis'!R184) -> 0.38929706 | S36: =IF($C$25="Annual",'Segment Analysis'!S164,'Segment Analysis'!S184) -> 0.67071631 | T36: ='Segment Analysis'!T164 -> 0.9537515 | U36: =IF($C$25="Annual",'Segment Analysis'!U164,'Segment Analysis'!U184) -> -0.39741926 | V36: =IFERROR(V35/U35-1,"--") -> 0.03 | W36: =IFERROR(W35/V35-1,"--") -> 0.05 | X36: =IFERROR(X35/W35-1,"--") -> 0.08 | Y36: =IFERROR(Y35/T35-1,"--") -> -0.091602297 | Z36: =IFERROR(Z35/X35-1,"--") -> 0.065 | AA36: =IFERROR(AA35/Z35-1,"--") -> 0.06 | AB36: =IFERROR(AB35/AA35-1,"--") -> 0.055 | AC36: =IFERROR(AC35/AB35-1,"--") -> 0.05 | AD36: =IFERROR(AD35/Y35-1,"--") -> 0.26515898 | AE36: =IFERROR(AE35/AD35-1,"--") -> 0.07 | AF36: =IFERROR(AF35/AE35-1,"--") -> 0.055 | AG36: =IFERROR(AG35/AF35-1,"--") -> 0.05
C37: % of Total Revenue | F37: ='Segment Analysis'!F17 -> 0.3657543 | G37: ='Segment Analysis'!G17 -> 0.39445306 | H37: ='Segment Analysis'!H17 -> 0.2338716 | I37: ='Segment Analysis'!I17 -> 0.15157641 | J37: ='Segment Analysis'!J17 -> 0.29669808 | K37: ='Segment Analysis'!K17 -> 0.15699353 | L37: ='Segment Analysis'!L17 -> 0.13944324 | M37: ='Segment Analysis'!M17 -> 0.092788032 | ... U37: ='Segment Analysis'!U17 -> 0.24018232 | V37: =V35/V$30 -> 0.23669025 | W37: =W35/W$30 -> 0.23413712 | X37: =X35/X$30 -> 0.23330988 | Y37: =Y35/Y$30 -> 0.23590874 | Z37: =Z35/Z$30 -> 0.23415271 | AA37: =AA35/AA$30 -> 0.23415271 | AB37: =AB35/AB$30 -> 0.2358649 | AC37: =AC35/AC$30 -> 0.23672629 | ... AG37: =AG35/AG$30 -> 0.23190367
C38: ='Segment Analysis'!C10 -> Segment 3 Revenue | F38: ='Segment Analysis'!F10 -> 0 | G38: ='Segment Analysis'!G10 -> 0 | H38: ='Segment Analysis'!H10 -> 0 | I38: ='Segment Analysis'!I10 -> 0 | J38: ='Segment Analysis'!J10 -> 0 | K38: ='Segment Analysis'!K10 -> 0 | L38: ='Segment Analysis'!L10 -> 0 | M38: ='Segment Analysis'!M10 -> 0 | ... U38: ='Segment Analysis'!U10 -> 0 | V38: =IF(Segment3_Rev_Methodology="Segment",V65,IF(Segment3_Rev_Methodology="Activity-Based",V115,IF(Segment3_Rev_Methodology="Backlog",V189,"--"))) -> 0 | W38: =IF(Segment3_Rev_Methodology="Segment",W65,IF(Segment3_Rev_Methodology="Activity-Based",W115,IF(Segment3_Rev_Methodology="Backlog",W189,"--"))) -> 0 | X38: =IF(Segment3_Rev_Methodology="Segment",X65,IF(Segment3_Rev_Methodology="Activity-Based",X115,IF(Segment3_Rev_Methodology="Backlog",X189,"--"))) -> 0 | Y38: =SUM(U38:X38) -> 0 | Z38: =IF(Segment3_Rev_Methodology="Segment",Z65,IF(Segment3_Rev_Methodology="Activity-Based",Z115,IF(Segment3_Rev_Methodology="Backlog",Z189,"--"))) -> 0 | AA38: =IF(Segment3_Rev_Methodology="Segment",AA65,IF(Segment3_Rev_Methodology="Activity-Based",AA115,IF(Segment3_Rev_Methodology="Backlog",AA189,"--"))) -> 0 | AB38: =IF(Segment3_Rev_Methodology="Segment",AB65,IF(Segment3_Rev_Methodology="Activity-Based",AB115,IF(Segment3_Rev_Methodology="Backlog",AB189,"--"))) -> 0 | AC38: =IF(Segment3_Rev_Methodology="Segment",AC65,IF(Segment3_Rev_Methodology="Activity-Based",AC115,IF(Segment3_Rev_Methodology="Backlog",AC189,"--"))) -> 0 | AD38: =SUM(Z38:AC38) -> 0 | AE38: =IF(Segment3_Rev_Methodology="Segment",AE65,IF(Segment3_Rev_Methodology="Activity-Based",AE115,IF(Segment3_Rev_Methodology="Backlog",AE189,"--"))) -> 0 | AF38: =IF(Segment3_Rev_Methodology="Segment",AF65,IF(Segment3_Rev_Methodology="Activity-Based",AF115,IF(Segment3_Rev_Methodology="Backlog",AF189,"--"))) -> 0 | AG38: =IF(Segment3_Rev_Methodology="Segment",AG65,IF(Segment3_Rev_Methodology="Activity-Based",AG115,IF(Segment3_Rev_Methodology="Backlog",AG189,"--"))) -> 0 | AI38: =IFERROR((T38/J38)^(1/3)-1,"--") -> -- | AJ38: =IFERROR((AG38/T38)^(1/5)-1,"--") -> --
C39: % Growth | G39: =IF($C$25="Annual",'Segment Analysis'!G165,'Segment Analysis'!G185) -> N/A | H39: =IF($C$25="Annual",'Segment Analysis'!H165,'Segment Analysis'!H185) -> N/A | I39: =IF($C$25="Annual",'Segment Analysis'!I165,'Segment Analysis'!I185) -> N/A | K39: =IF($C$25="Annual",'Segment Analysis'!K165,'Segment Analysis'!K185) -> N/A | L39: =IF($C$25="Annual",'Segment Analysis'!L165,'Segment Analysis'!L185) -> N/A | M39: =IF($C$25="Annual",'Segment Analysis'!M165,'Segment Analysis'!M185) -> N/A | N39: =IF($C$25="Annual",'Segment Analysis'!N165,'Segment Analysis'!N185) -> N/A | O39: =IF($C$25="Annual",'Segment Analysis'!O165,'Segment Analysis'!O185) -> 0 | P39: =IF($C$25="Annual",'Segment Analysis'!P165,'Segment Analysis'!P185) -> N/A | Q39: =IF($C$25="Annual",'Segment Analysis'!Q165,'Segment Analysis'!Q185) -> N/A | R39: =IF($C$25="Annual",'Segment Analysis'!R165,'Segment Analysis'!R185) -> N/A | ... U39: =IF($C$25="Annual",'Segment Analysis'!U165,'Segment Analysis'!U185) -> N/A | V39: =IFERROR(V38/U38-1,"--") -> -- | W39: =IFERROR(W38/V38-1,"--") -> -- | X39: =IFERROR(X38/W38-1,"--") -> -- | Y39: =IFERROR(Y38/T38-1,"--") -> -- | Z39: =IFERROR(Z38/X38-1,"--") -> -- | AA39: =IFERROR(AA38/Z38-1,"--") -> -- | AB39: =IFERROR(AB38/AA38-1,"--") -> -- | AC39: =IFERROR(AC38/AB38-1,"--") -> -- | AD39: =IFERROR(AD38/Y38-1,"--") -> -- | AE39: =IFERROR(AE38/AD38-1,"--") -> -- | AF39: =IFERROR(AF38/AE38-1,"--") -> -- | AG39: =IFERROR(AG38/AF38-1,"--") -> --
C40: % of Total Revenue | F40: ='Segment Analysis'!F18 -> 0 | G40: ='Segment Analysis'!G18 -> 0 | H40: ='Segment Analysis'!H18 -> 0 | I40: ='Segment Analysis'!I18 -> 0 | J40: ='Segment Analysis'!J18 -> 0 | K40: ='Segment Analysis'!K18 -> 0 | L40: ='Segment Analysis'!L18 -> 0 | M40: ='Segment Analysis'!M18 -> 0 | ... U40: ='Segment Analysis'!U18 -> 0 | V40: =V38/V$30 -> 0 | W40: =W38/W$30 -> 0 | X40: =X38/X$30 -> 0 | Y40: =Y38/Y$30 -> 0 | Z40: =Z38/Z$30 -> 0 | AA40: =AA38/AA$30 -> 0 | AB40: =AB38/AB$30 -> 0 | AC40: =AC38/AC$30 -> 0 | ... AG40: =AG38/AG$30 -> 0
C41: ='Segment Analysis'!C11 -> Segment 4 Revenue | F41: ='Segment Analysis'!F11 -> 0 | G41: ='Segment Analysis'!G11 -> 0 | H41: ='Segment Analysis'!H11 -> 0 | I41: ='Segment Analysis'!I11 -> 0 | J41: ='Segment Analysis'!J11 -> 0 | K41: ='Segment Analysis'!K11 -> 0 | L41: ='Segment Analysis'!L11 -> 0 | M41: ='Segment Analysis'!M11 -> 0 | ... U41: ='Segment Analysis'!U11 -> 0 | V41: =IF(Segment4_Rev_Methodology="Segment",V71,IF(Segment4_Rev_Methodology="Activity-Based",V127,IF(Segment4_Rev_Methodology="Backlog",V201,"--"))) -> 0 | W41: =IF(Segment4_Rev_Methodology="Segment",W71,IF(Segment4_Rev_Methodology="Activity-Based",W127,IF(Segment4_Rev_Methodology="Backlog",W201,"--"))) -> 0 | X41: =IF(Segment4_Rev_Methodology="Segment",X71,IF(Segment4_Rev_Methodology="Activity-Based",X127,IF(Segment4_Rev_Methodology="Backlog",X201,"--"))) -> 0 | Y41: =SUM(U41:X41) -> 0 | Z41: =IF(Segment4_Rev_Methodology="Segment",Z71,IF(Segment4_Rev_Methodology="Activity-Based",Z127,IF(Segment4_Rev_Methodology="Backlog",Z201,"--"))) -> 0 | AA41: =IF(Segment4_Rev_Methodology="Segment",AA71,IF(Segment4_Rev_Methodology="Activity-Based",AA127,IF(Segment4_Rev_Methodology="Backlog",AA201,"--"))) -> 0 | AB41: =IF(Segment4_Rev_Methodology="Segment",AB71,IF(Segment4_Rev_Methodology="Activity-Based",AB127,IF(Segment4_Rev_Methodology="Backlog",AB201,"--"))) -> 0 | AC41: =IF(Segment4_Rev_Methodology="Segment",AC71,IF(Segment4_Rev_Methodology="Activity-Based",AC127,IF(Segment4_Rev_Methodology="Backlog",AC201,"--"))) -> 0 | AD41: =SUM(Z41:AC41) -> 0 | AE41: =IF(Segment4_Rev_Methodology="Segment",AE71,IF(Segment4_Rev_Methodology="Activity-Based",AE127,IF(Segment4_Rev_Methodology="Backlog",AE201,"--"))) -> 0 | AF41: =IF(Segment4_Rev_Methodology="Segment",AF71,IF(Segment4_Rev_Methodology="Activity-Based",AF127,IF(Segment4_Rev_Methodology="Backlog",AF201,"--"))) -> 0 | AG41: =IF(Segment4_Rev_Methodology="Segment",AG71,IF(Segment4_Rev_Methodology="Activity-Based",AG127,IF(Segment4_Rev_Methodology="Backlog",AG201,"--"))) -> 0 | AI41: =IFERROR((T41/J41)^(1/3)-1,"--") -> -- | AJ41: =IFERROR((AG41/T41)^(1/5)-1,"--") -> --
C42: % Growth | G42: =IF($C$25="Annual",'Segment Analysis'!G166,'Segment Analysis'!G186) -> N/A | H42: =IF($C$25="Annual",'Segment Analysis'!H166,'Segment Analysis'!H186) -> N/A | I42: =IF($C$25="Annual",'Segment Analysis'!I166,'Segment Analysis'!I186) -> N/A | K42: =IF($C$25="Annual",'Segment Analysis'!K166,'Segment Analysis'!K186) -> N/A | L42: =IF($C$25="Annual",'Segment Analysis'!L166,'Segment Analysis'!L186) -> N/A | M42: =IF($C$25="Annual",'Segment Analysis'!M166,'Segment Analysis'!M186) -> N/A | N42: =IF($C$25="Annual",'Segment Analysis'!N166,'Segment Analysis'!N186) -> N/A | O42: =IF($C$25="Annual",'Segment Analysis'!O166,'Segment Analysis'!O186) -> 0 | P42: =IF($C$25="Annual",'Segment Analysis'!P166,'Segment Analysis'!P186) -> N/A | Q42: =IF($C$25="Annual",'Segment Analysis'!Q166,'Segment Analysis'!Q186) -> N/A | R42: =IF($C$25="Annual",'Segment Analysis'!R166,'Segment Analysis'!R186) -> N/A | ... U42: =IF($C$25="Annual",'Segment Analysis'!U166,'Segment Analysis'!U186) -> N/A | V42: =IFERROR(V41/U41-1,"--") -> -- | W42: =IFERROR(W41/V41-1,"--") -> -- | X42: =IFERROR(X41/W41-1,"--") -> -- | Y42: =IFERROR(Y41/T41-1,"--") -> -- | Z42: =IFERROR(Z41/X41-1,"--") -> -- | AA42: =IFERROR(AA41/Z41-1,"--") -> -- | AB42: =IFERROR(AB41/AA41-1,"--") -> -- | AC42: =IFERROR(AC41/AB41-1,"--") -> -- | AD42: =IFERROR(AD41/Y41-1,"--") -> -- | AE42: =IFERROR(AE41/AD41-1,"--") -> -- | AF42: =IFERROR(AF41/AE41-1,"--") -> -- | AG42: =IFERROR(AG41/AF41-1,"--") -> --
C43: % of Total Revenue | F43: ='Segment Analysis'!F19 -> 0 | G43: ='Segment Analysis'!G19 -> 0 | H43: ='Segment Analysis'!H19 -> 0 | I43: ='Segment Analysis'!I19 -> 0 | J43: ='Segment Analysis'!J19 -> 0 | K43: ='Segment Analysis'!K19 -> 0 | L43: ='Segment Analysis'!L19 -> 0 | M43: ='Segment Analysis'!M19 -> 0 | ... U43: ='Segment Analysis'!U19 -> 0 | V43: =V41/V$30 -> 0 | W43: =W41/W$30 -> 0 | X43: =X41/X$30 -> 0 | Y43: =Y41/Y$30 -> 0 | Z43: =Z41/Z$30 -> 0 | AA43: =AA41/AA$30 -> 0 | AB43: =AB41/AB$30 -> 0 | AC43: =AC41/AC$30 -> 0 | ... AG43: =AG41/AG$30 -> 0
C44: ='Segment Analysis'!C12 -> Segment 5 Revenue | F44: ='Segment Analysis'!F12 -> 0 | G44: ='Segment Analysis'!G12 -> 0 | H44: ='Segment Analysis'!H12 -> 0 | I44: ='Segment Analysis'!I12 -> 0 | J44: ='Segment Analysis'!J12 -> 0 | K44: ='Segment Analysis'!K12 -> 0 | L44: ='Segment Analysis'!L12 -> 0 | M44: ='Segment Analysis'!M12 -> 0 | ... U44: ='Segment Analysis'!U12 -> 0 | V44: =IF(Segment5_Rev_Methodology="Segment",V77,IF(Segment5_Rev_Methodology="Activity-Based",V139,IF(Segment5_Rev_Methodology="Backlog",V213,"--"))) -> 0 | W44: =IF(Segment5_Rev_Methodology="Segment",W77,IF(Segment5_Rev_Methodology="Activity-Based",W139,IF(Segment5_Rev_Methodology="Backlog",W213,"--"))) -> 0 | X44: =IF(Segment5_Rev_Methodology="Segment",X77,IF(Segment5_Rev_Methodology="Activity-Based",X139,IF(Segment5_Rev_Methodology="Backlog",X213,"--"))) -> 0 | Y44: =SUM(U44:X44) -> 0 | Z44: =IF(Segment5_Rev_Methodology="Segment",Z77,IF(Segment5_Rev_Methodology="Activity-Based",Z139,IF(Segment5_Rev_Methodology="Backlog",Z213,"--"))) -> 0 | AA44: =IF(Segment5_Rev_Methodology="Segment",AA77,IF(Segment5_Rev_Methodology="Activity-Based",AA139,IF(Segment5_Rev_Methodology="Backlog",AA213,"--"))) -> 0 | AB44: =IF(Segment5_Rev_Methodology="Segment",AB77,IF(Segment5_Rev_Methodology="Activity-Based",AB139,IF(Segment5_Rev_Methodology="Backlog",AB213,"--"))) -> 0 | AC44: =IF(Segment5_Rev_Methodology="Segment",AC77,IF(Segment5_Rev_Methodology="Activity-Based",AC139,IF(Segment5_Rev_Methodology="Backlog",AC213,"--"))) -> 0 | AD44: =SUM(Z44:AC44) -> 0 | AE44: =IF(Segment5_Rev_Methodology="Segment",AE77,IF(Segment5_Rev_Methodology="Activity-Based",AE139,IF(Segment5_Rev_Methodology="Backlog",AE213,"--"))) -> 0 | AF44: =IF(Segment5_Rev_Methodology="Segment",AF77,IF(Segment5_Rev_Methodology="Activity-Based",AF139,IF(Segment5_Rev_Methodology="Backlog",AF213,"--"))) -> 0 | AG44: =IF(Segment5_Rev_Methodology="Segment",AG77,IF(Segment5_Rev_Methodology="Activity-Based",AG139,IF(Segment5_Rev_Methodology="Backlog",AG213,"--"))) -> 0 | AI44: =IFERROR((T44/J44)^(1/3)-1,"--") -> -- | AJ44: =IFERROR((AG44/T44)^(1/5)-1,"--") -> --
C45: % Growth | G45: =IF($C$25="Annual",'Segment Analysis'!G167,'Segment Analysis'!G187) -> N/A | H45: =IF($C$25="Annual",'Segment Analysis'!H167,'Segment Analysis'!H187) -> N/A | I45: =IF($C$25="Annual",'Segment Analysis'!I167,'Segment Analysis'!I187) -> N/A | K45: =IF($C$25="Annual",'Segment Analysis'!K167,'Segment Analysis'!K187) -> N/A | L45: =IF($C$25="Annual",'Segment Analysis'!L167,'Segment Analysis'!L187) -> N/A | M45: =IF($C$25="Annual",'Segment Analysis'!M167,'Segment Analysis'!M187) -> N/A | N45: =IF($C$25="Annual",'Segment Analysis'!N167,'Segment Analysis'!N187) -> N/A | O45: =IF($C$25="Annual",'Segment Analysis'!O167,'Segment Analysis'!O187) -> 0 | P45: =IF($C$25="Annual",'Segment Analysis'!P167,'Segment Analysis'!P187) -> N/A | Q45: =IF($C$25="Annual",'Segment Analysis'!Q167,'Segment Analysis'!Q187) -> N/A | R45: =IF($C$25="Annual",'Segment Analysis'!R167,'Segment Analysis'!R187) -> N/A | ... U45: =IF($C$25="Annual",'Segment Analysis'!U167,'Segment Analysis'!U187) -> N/A | V45: =IFERROR(V44/U44-1,"--") -> -- | W45: =IFERROR(W44/V44-1,"--") -> -- | X45: =IFERROR(X44/W44-1,"--") -> -- | Y45: =IFERROR(Y44/T44-1,"--") -> -- | Z45: =IFERROR(Z44/X44-1,"--") -> -- | AA45: =IFERROR(AA44/Z44-1,"--") -> -- | AB45: =IFERROR(AB44/AA44-1,"--") -> -- | AC45: =IFERROR(AC44/AB44-1,"--") -> -- | AD45: =IFERROR(AD44/Y44-1,"--") -> -- | AE45: =IFERROR(AE44/AD44-1,"--") -> -- | AF45: =IFERROR(AF44/AE44-1,"--") -> -- | AG45: =IFERROR(AG44/AF44-1,"--") -> --
C46: % of Total Revenue | F46: ='Segment Analysis'!F20 -> 0 | G46: ='Segment Analysis'!G20 -> 0 | H46: ='Segment Analysis'!H20 -> 0 | I46: ='Segment Analysis'!I20 -> 0 | J46: ='Segment Analysis'!J20 -> 0 | K46: ='Segment Analysis'!K20 -> 0 | L46: ='Segment Analysis'!L20 -> 0 | M46: ='Segment Analysis'!M20 -> 0 | ... U46: ='Segment Analysis'!U20 -> 0 | V46: =V44/V$30 -> 0 | W46: =W44/W$30 -> 0 | X46: =X44/X$30 -> 0 | Y46: =Y44/Y$30 -> 0 | Z46: =Z44/Z$30 -> 0 | AA46: =AA44/AA$30 -> 0 | AB46: =AB44/AB$30 -> 0 | AC46: =AC44/AC$30 -> 0 | ... AG46: =AG44/AG$30 -> 0
C47: ='Segment Analysis'!C13 -> Segment 6 Revenue | F47: ='Segment Analysis'!F13 -> 0 | G47: ='Segment Analysis'!G13 -> 0 | H47: ='Segment Analysis'!H13 -> 0 | I47: ='Segment Analysis'!I13 -> 0 | J47: ='Segment Analysis'!J13 -> 0 | K47: ='Segment Analysis'!K13 -> 0 | L47: ='Segment Analysis'!L13 -> 0 | M47: ='Segment Analysis'!M13 -> 0 | ... U47: ='Segment Analysis'!U13 -> 0 | V47: =IF(Segment6_Rev_Methodology="Segment",V83,IF(Segment6_Rev_Methodology="Activity-Based",V151,IF(Segment6_Rev_Methodology="Backlog",V225,"--"))) -> 0 | W47: =IF(Segment6_Rev_Methodology="Segment",W83,IF(Segment6_Rev_Methodology="Activity-Based",W151,IF(Segment6_Rev_Methodology="Backlog",W225,"--"))) -> 0 | X47: =IF(Segment6_Rev_Methodology="Segment",X83,IF(Segment6_Rev_Methodology="Activity-Based",X151,IF(Segment6_Rev_Methodology="Backlog",X225,"--"))) -> 0 | Y47: =SUM(U47:X47) -> 0 | Z47: =IF(Segment6_Rev_Methodology="Segment",Z83,IF(Segment6_Rev_Methodology="Activity-Based",Z151,IF(Segment6_Rev_Methodology="Backlog",Z225,"--"))) -> 0 | AA47: =IF(Segment6_Rev_Methodology="Segment",AA83,IF(Segment6_Rev_Methodology="Activity-Based",AA151,IF(Segment6_Rev_Methodology="Backlog",AA225,"--"))) -> 0 | AB47: =IF(Segment6_Rev_Methodology="Segment",AB83,IF(Segment6_Rev_Methodology="Activity-Based",AB151,IF(Segment6_Rev_Methodology="Backlog",AB225,"--"))) -> 0 | AC47: =IF(Segment6_Rev_Methodology="Segment",AC83,IF(Segment6_Rev_Methodology="Activity-Based",AC151,IF(Segment6_Rev_Methodology="Backlog",AC225,"--"))) -> 0 | AD47: =SUM(Z47:AC47) -> 0 | AE47: =IF(Segment6_Rev_Methodology="Segment",AE83,IF(Segment6_Rev_Methodology="Activity-Based",AE151,IF(Segment6_Rev_Methodology="Backlog",AE225,"--"))) -> 0 | AF47: =IF(Segment6_Rev_Methodology="Segment",AF83,IF(Segment6_Rev_Methodology="Activity-Based",AF151,IF(Segment6_Rev_Methodology="Backlog",AF225,"--"))) -> 0 | AG47: =IF(Segment6_Rev_Methodology="Segment",AG83,IF(Segment6_Rev_Methodology="Activity-Based",AG151,IF(Segment6_Rev_Methodology="Backlog",AG225,"--"))) -> 0 | AI47: =IFERROR((T47/J47)^(1/3)-1,"--") -> -- | AJ47: =IFERROR((AG47/T47)^(1/5)-1,"--") -> --
C48: % Growth | G48: =IF($C$25="Annual",'Segment Analysis'!G188,'Segment Analysis'!G188) -> N/A | H48: =IF($C$25="Annual",'Segment Analysis'!H188,'Segment Analysis'!H188) -> N/A | I48: =IF($C$25="Annual",'Segment Analysis'!I188,'Segment Analysis'!I188) -> N/A | K48: =IF($C$25="Annual",'Segment Analysis'!K188,'Segment Analysis'!K188) -> N/A | L48: =IF($C$25="Annual",'Segment Analysis'!L188,'Segment Analysis'!L188) -> N/A | M48: =IF($C$25="Annual",'Segment Analysis'!M188,'Segment Analysis'!M188) -> N/A | N48: =IF($C$25="Annual",'Segment Analysis'!N188,'Segment Analysis'!N188) -> N/A | O48: =IF($C$25="Annual",'Segment Analysis'!O188,'Segment Analysis'!O188) -> 0 | P48: =IF($C$25="Annual",'Segment Analysis'!P188,'Segment Analysis'!P188) -> N/A | Q48: =IF($C$25="Annual",'Segment Analysis'!Q188,'Segment Analysis'!Q188) -> N/A | R48: =IF($C$25="Annual",'Segment Analysis'!R188,'Segment Analysis'!R188) -> N/A | ... U48: =IF($C$25="Annual",'Segment Analysis'!U188,'Segment Analysis'!U188) -> N/A | V48: =IFERROR(V47/U47-1,"--") -> -- | W48: =IFERROR(W47/V47-1,"--") -> -- | X48: =IFERROR(X47/W47-1,"--") -> -- | Y48: =IFERROR(Y47/T47-1,"--") -> -- | Z48: =IFERROR(Z47/X47-1,"--") -> -- | AA48: =IFERROR(AA47/Z47-1,"--") -> -- | AB48: =IFERROR(AB47/AA47-1,"--") -> -- | AC48: =IFERROR(AC47/AB47-1,"--") -> -- | AD48: =IFERROR(AD47/Y47-1,"--") -> -- | AE48: =IFERROR(AE47/AD47-1,"--") -> -- | AF48: =IFERROR(AF47/AE47-1,"--") -> -- | AG48: =IFERROR(AG47/AF47-1,"--") -> --
C49: % of Total Revenue | F49: ='Segment Analysis'!F21 -> 0 | G49: ='Segment Analysis'!G21 -> 0 | H49: ='Segment Analysis'!H21 -> 0 | I49: ='Segment Analysis'!I21 -> 0 | J49: ='Segment Analysis'!J21 -> 0 | K49: ='Segment Analysis'!K21 -> 0 | L49: ='Segment Analysis'!L21 -> 0 | M49: ='Segment Analysis'!M21 -> 0 | ... U49: ='Segment Analysis'!U21 -> 0 | V49: =V47/V$30 -> 0 | W49: =W47/W$30 -> 0 | X49: =X47/X$30 -> 0 | Y49: =Y47/Y$30 -> 0 | Z49: =Z47/Z$30 -> 0 | AA49: =AA47/AA$30 -> 0 | AB49: =AB47/AB$30 -> 0 | AC49: =AC47/AC$30 -> 0 | ... AG49: =AG47/AG$30 -> 0
A51: x | C51: Growth Rate | F51: =F$28 -> 1Q23 | G51: =G$28 -> 2Q23 | H51: =H$28 -> 3Q23 | I51: =I$28 -> 4Q23 | J51: =J$28 -> 2023 | K51: =K$28 -> 1Q24 | L51: =L$28 -> 2Q24 | M51: =M$28 -> 3Q24 | ... AG51: =AG$28 -> 2030e | AH51: x
C53: =C32 -> Management & Advisory Fees | F53: =F32 -> 85.946 | G53: =G32 -> 92.88 | H53: =H32 -> 97.355 | I53: =I32 -> 95.692 | J53: =J32 -> 371.873 | K53: =K32 -> 105.407 | L53: =L32 -> 109.184 | M53: =M32 -> 113.641 | ... U53: =U32 -> 133.696 | V53: =IF($C$25="Quarterly",U53*(1+V54),Q53*(1+V54)) -> 140.3808 | W53: =IF($C$25="Quarterly",V53*(1+W54),R53*(1+W54)) -> 149.50555 | X53: =IF($C$25="Quarterly",W53*(1+X54),S53*(1+X54)) -> 162.21352 | Y53: =SUM(U53:X53) -> 585.79588 | Z53: =IF($C$25="Quarterly",X53*(1+Z54),U53*(1+Z54)) -> 171.94634 | AA53: =IF($C$25="Quarterly",Z53*(1+AA54),V53*(1+AA54)) -> 182.26312 | AB53: =IF($C$25="Quarterly",AA53*(1+AB54),W53*(1+AB54)) -> 190.46496 | AC53: =IF($C$25="Quarterly",AB53*(1+AC54),X53*(1+AC54)) -> 199.03588 | AD53: =SUM(Z53:AC53) -> 743.71029 | AE53: =AD53*(1+AE54) -> 795.77001 | AF53: =AE53*(1+AF54) -> 839.53736 | AG53: =AF53*(1+AG54) -> 898.30497
C54: =IF($C$25="Quarterly","% Growth QoQ","% Growth YoY") -> % Growth QoQ | G54: =G33 -> 0.080678566 | H54: =H33 -> 0.048180448 | I54: =I33 -> -0.017081814 | J54: =J33 -> 0 | K54: =K33 -> 0.10152364 | L54: =L33 -> 0.035832535 | M54: =M33 -> 0.040820999 | N54: =N33 -> 0.088550787 | ... U54: =U33 -> 0.045823621 | V54: =IF(Case_Scenario="Bull",V55,IF(Case_Scenario="Base",V56,IF(Case_Scenario="bear",V57,"N/A"))) -> 0.05 | W54: =IF(Case_Scenario="Bull",W55,IF(Case_Scenario="Base",W56,IF(Case_Scenario="bear",W57,"N/A"))) -> 0.065 | X54: =IF(Case_Scenario="Bull",X55,IF(Case_Scenario="Base",X56,IF(Case_Scenario="bear",X57,"N/A"))) -> 0.085 | Y54: =Y33 -> 0.1399801 | Z54: =IF(Case_Scenario="Bull",Z55,IF(Case_Scenario="Base",Z56,IF(Case_Scenario="bear",Z57,"N/A"))) -> 0.06 | AA54: =IF(Case_Scenario="Bull",AA55,IF(Case_Scenario="Base",AA56,IF(Case_Scenario="bear",AA57,"N/A"))) -> 0.06 | AB54: =IF(Case_Scenario="Bull",AB55,IF(Case_Scenario="Base",AB56,IF(Case_Scenario="bear",AB57,"N/A"))) -> 0.045 | AC54: =IF(Case_Scenario="Bull",AC55,IF(Case_Scenario="Base",AC56,IF(Case_Scenario="bear",AC57,"N/A"))) -> 0.045 | AD54: =AD33 -> 0.26957242 | AE54: =IF(Case_Scenario="Bull",AE55,IF(Case_Scenario="Base",AE56,IF(Case_Scenario="bear",AE57,"N/A"))) -> 0.07 | AF54: =IF(Case_Scenario="Bull",AF55,IF(Case_Scenario="Base",AF56,IF(Case_Scenario="bear",AF57,"N/A"))) -> 0.055 | AG54: =IF(Case_Scenario="Bull",AG55,IF(Case_Scenario="Base",AG56,IF(Case_Scenario="bear",AG57,"N/A"))) -> 0.07
C55: Bull Case | V55: =V56+0.02 -> 0.07 | W55: =W56+0.015 -> 0.08 | X55: =X56+0.01 -> 0.095 | Z55: =Z56+0.01 -> 0.07 | AA55: =AA56+0.01 -> 0.07 | AB55: =AB56+0.015 -> 0.06 | AC55: =AC56+0.015 -> 0.06 | AE55: =AE56+0.01 -> 0.08 | AF55: =AF56+0.01 -> 0.065 | AG55: =AG56+0.01 -> 0.08
C56: Base Case | V56: 0.05 | W56: 0.065 | X56: 0.085 | Z56: 0.06 | AA56: 0.06 | AB56: 0.045 | AC56: 0.045 | AE56: 0.07 | AF56: 0.055 | AG56: 0.07
C57: Bear Case | V57: =V56-0.07 -> -0.02 | W57: =W56-0.075 -> -0.01 | X57: =X56-0.07 -> 0.015 | Z57: =Z56-0.04 -> 0.02 | AA57: =AA56-0.035 -> 0.025 | AB57: =AB56-0.035 -> 0.01 | AC57: =AC56-0.035 -> 0.01 | AE57: =AE56-0.02 -> 0.05 | AF57: =AF56-0.02 -> 0.035 | AG57: =AG56-0.02 -> 0.05
A59: x | C59: =C35 -> Incentive Fees | F59: =F35 -> 49.563 | G59: =G35 -> 60.502 | H59: =H35 -> 29.719 | I59: =I35 -> 17.096 | J59: =J35 -> 156.88 | K59: =K35 -> 19.63 | L59: =L35 -> 17.692 | M59: =M35 -> 11.623 | ... U59: =U35 -> 42.262 | V59: =IF($C$25="Quarterly",U59*(1+V60),Q59*(1+V60)) -> 43.52986 | W59: =IF($C$25="Quarterly",V59*(1+W60),R59*(1+W60)) -> 45.706353 | X59: =IF($C$25="Quarterly",W59*(1+X60),S59*(1+X60)) -> 49.362861 | Y59: =SUM(U59:X59) -> 180.86107 | Z59: =IF($C$25="Quarterly",X59*(1+Z60),U59*(1+Z60)) -> 52.571447 | AA59: =IF($C$25="Quarterly",Z59*(1+AA60),V59*(1+AA60)) -> 55.725734 | AB59: =IF($C$25="Quarterly",AA59*(1+AB60),W59*(1+AB60)) -> 58.790649 | AC59: =IF($C$25="Quarterly",AB59*(1+AC60),X59*(1+AC60)) -> 61.730182 | AD59: =SUM(Z59:AC59) -> 228.81801 | AE59: =AD59*(1+AE60) -> 244.83527 | AF59: =AE59*(1+AF60) -> 258.30121 | AG59: =AF59*(1+AG60) -> 271.21627
C60: =IF($C$25="Quarterly","% Growth QoQ","% Growth YoY") -> % Growth QoQ | G60: =G36 -> 0.220709 | H60: =H36 -> -0.5087931 | I60: =I36 -> -0.42474511 | J60: =J36 -> 0 | K60: =K36 -> 0.14822181 | L60: =L36 -> -0.098726439 | M60: =M36 -> -0.3430364 | N60: =N36 -> 3.5565689 | ... U60: =U36 -> -0.39741926 | V60: =IF(Case_Scenario="Bull",V61,IF(Case_Scenario="Base",V62,IF(Case_Scenario="bear",V63,"N/A"))) -> 0.03 | W60: =IF(Case_Scenario="Bull",W61,IF(Case_Scenario="Base",W62,IF(Case_Scenario="bear",W63,"N/A"))) -> 0.05 | X60: =IF(Case_Scenario="Bull",X61,IF(Case_Scenario="Base",X62,IF(Case_Scenario="bear",X63,"N/A"))) -> 0.08 | Z60: =IF(Case_Scenario="Bull",Z61,IF(Case_Scenario="Base",Z62,IF(Case_Scenario="bear",Z63,"N/A"))) -> 0.065 | AA60: =IF(Case_Scenario="Bull",AA61,IF(Case_Scenario="Base",AA62,IF(Case_Scenario="bear",AA63,"N/A"))) -> 0.06 | AB60: =IF(Case_Scenario="Bull",AB61,IF(Case_Scenario="Base",AB62,IF(Case_Scenario="bear",AB63,"N/A"))) -> 0.055 | AC60: =IF(Case_Scenario="Bull",AC61,IF(Case_Scenario="Base",AC62,IF(Case_Scenario="bear",AC63,"N/A"))) -> 0.05 | AE60: =IF(Case_Scenario="Bull",AE61,IF(Case_Scenario="Base",AE62,IF(Case_Scenario="bear",AE63,"N/A"))) -> 0.07 | AF60: =IF(Case_Scenario="Bull",AF61,IF(Case_Scenario="Base",AF62,IF(Case_Scenario="bear",AF63,"N/A"))) -> 0.055 | AG60: =IF(Case_Scenario="Bull",AG61,IF(Case_Scenario="Base",AG62,IF(Case_Scenario="bear",AG63,"N/A"))) -> 0.05
C61: Bull Case | V61: =V62+0.02 -> 0.05 | W61: =W62+0.02 -> 0.07 | X61: =X62+0.01 -> 0.09 | Z61: =Z62+0.01 -> 0.075 | AA61: =AA62+0.01 -> 0.07 | AB61: =AB62+0.01 -> 0.065 | AC61: =AC62+0.01 -> 0.06 | AE61: =AE62+0.01 -> 0.08 | AF61: =AF62+0.01 -> 0.065 | AG61: =AG62+0.01 -> 0.06
C62: Base Case | V62: 0.03 | W62: 0.05 | X62: 0.08 | Y62: ` | Z62: 0.065 | AA62: 0.06 | AB62: 0.055 | AC62: 0.05 | AE62: 0.07 | AF62: 0.055 | AG62: 0.05
C63: Bear Case | V63: =V62-0.06 -> -0.03 | W63: =W62-0.06 -> -0.01 | X63: =X62-0.075 -> 0.005 | Z63: =Z62-0.085 -> -0.02 | AA63: =AA62-0.08 -> -0.02 | AB63: =AB62-0.025 -> 0.03 | AC63: =AC62-0.025 -> 0.025 | AE63: =AE62-0.02 -> 0.05 | AF63: =AF62-0.02 -> 0.035 | AG63: =AG62-0.02 -> 0.03
A65: x | C65: =C38 -> Segment 3 Revenue | F65: =F38 -> 0 | G65: =G38 -> 0 | H65: =H38 -> 0 | I65: =I38 -> 0 | J65: =J38 -> 0 | K65: =K38 -> 0 | L65: =L38 -> 0 | M65: =M38 -> 0 | ... U65: =U38 -> 0 | V65: =IF($C$25="Quarterly",U65*(1+V66),Q65*(1+V66)) -> 0 | W65: =IF($C$25="Quarterly",V65*(1+W66),R65*(1+W66)) -> 0 | X65: =IF($C$25="Quarterly",W65*(1+X66),S65*(1+X66)) -> 0 | Y65: =SUM(U65:X65) -> 0 | Z65: =IF($C$25="Quarterly",X65*(1+Z66),U65*(1+Z66)) -> 0 | AA65: =IF($C$25="Quarterly",Z65*(1+AA66),V65*(1+AA66)) -> 0 | AB65: =IF($C$25="Quarterly",AA65*(1+AB66),W65*(1+AB66)) -> 0 | AC65: =IF($C$25="Quarterly",AB65*(1+AC66),X65*(1+AC66)) -> 0 | AD65: =SUM(Z65:AC65) -> 0 | AE65: =AD65*(1+AE66) -> 0 | AF65: =AE65*(1+AF66) -> 0 | AG65: =AF65*(1+AG66) -> 0
C66: =IF($C$25="Quarterly","% Growth QoQ","% Growth YoY") -> % Growth QoQ | G66: =G39 -> N/A | H66: =H39 -> N/A | I66: =I39 -> N/A | J66: =J39 -> 0 | K66: =K39 -> N/A | L66: =L39 -> N/A | M66: =M39 -> N/A | N66: =N39 -> N/A | ... U66: =U39 -> N/A | V66: =IF(Case_Scenario="Bull",V67,IF(Case_Scenario="Base",V68,IF(Case_Scenario="bear",V69,"N/A"))) -> 0 | W66: =IF(Case_Scenario="Bull",W67,IF(Case_Scenario="Base",W68,IF(Case_Scenario="bear",W69,"N/A"))) -> 0 | X66: =IF(Case_Scenario="Bull",X67,IF(Case_Scenario="Base",X68,IF(Case_Scenario="bear",X69,"N/A"))) -> 0 | Z66: =IF(Case_Scenario="Bull",Z67,IF(Case_Scenario="Base",Z68,IF(Case_Scenario="bear",Z69,"N/A"))) -> 0 | AA66: =IF(Case_Scenario="Bull",AA67,IF(Case_Scenario="Base",AA68,IF(Case_Scenario="bear",AA69,"N/A"))) -> 0 | AB66: =IF(Case_Scenario="Bull",AB67,IF(Case_Scenario="Base",AB68,IF(Case_Scenario="bear",AB69,"N/A"))) -> 0 | AC66: =IF(Case_Scenario="Bull",AC67,IF(Case_Scenario="Base",AC68,IF(Case_Scenario="bear",AC69,"N/A"))) -> 0 | AE66: =IF(Case_Scenario="Bull",AE67,IF(Case_Scenario="Base",AE68,IF(Case_Scenario="bear",AE69,"N/A"))) -> 0 | AF66: =IF(Case_Scenario="Bull",AF67,IF(Case_Scenario="Base",AF68,IF(Case_Scenario="bear",AF69,"N/A"))) -> 0 | AG66: =IF(Case_Scenario="Bull",AG67,IF(Case_Scenario="Base",AG68,IF(Case_Scenario="bear",AG69,"N/A"))) -> 0
C67: Bull Case | V67: 0 | W67: 0 | X67: 0 | Z67: 0 | AA67: 0 | AB67: 0 | AC67: 0 | AE67: 0 | AF67: 0 | AG67: 0
C68: Base Case | V68: 0 | W68: 0 | X68: 0 | Z68: 0 | AA68: 0 | AB68: 0 | AC68: 0 | AE68: 0 | AF68: 0 | AG68: 0
C69: Bear Case | V69: 0 | W69: 0 | X69: 0 | Z69: 0 | AA69: 0 | AB69: 0 | AC69: 0 | AE69: 0 | AF69: 0 | AG69: 0
A71: x | C71: =C41 -> Segment 4 Revenue | F71: =F41 -> 0 | G71: =G41 -> 0 | H71: =H41 -> 0 | I71: =I41 -> 0 | J71: =J41 -> 0 | K71: =K41 -> 0 | L71: =L41 -> 0 | M71: =M41 -> 0 | ... U71: =U41 -> 0 | V71: =IF($C$25="Quarterly",U71*(1+V72),Q71*(1+V72)) -> 0 | W71: =IF($C$25="Quarterly",V71*(1+W72),R71*(1+W72)) -> 0 | X71: =IF($C$25="Quarterly",W71*(1+X72),S71*(1+X72)) -> 0 | Y71: =SUM(U71:X71) -> 0 | Z71: =IF($C$25="Quarterly",X71*(1+Z72),U71*(1+Z72)) -> 0 | AA71: =IF($C$25="Quarterly",Z71*(1+AA72),V71*(1+AA72)) -> 0 | AB71: =IF($C$25="Quarterly",AA71*(1+AB72),W71*(1+AB72)) -> 0 | AC71: =IF($C$25="Quarterly",AB71*(1+AC72),X71*(1+AC72)) -> 0 | AD71: =SUM(Z71:AC71) -> 0 | AE71: =AD71*(1+AE72) -> 0 | AF71: =AE71*(1+AF72) -> 0 | AG71: =AF71*(1+AG72) -> 0
C72: =IF($C$25="Quarterly","% Growth QoQ","% Growth YoY") -> % Growth QoQ | G72: =G42 -> N/A | H72: =H42 -> N/A | I72: =I42 -> N/A | J72: =J42 -> 0 | K72: =K42 -> N/A | L72: =L42 -> N/A | M72: =M42 -> N/A | N72: =N42 -> N/A | ... U72: =U42 -> N/A | V72: =IF(Case_Scenario="Bull",V73,IF(Case_Scenario="Base",V74,IF(Case_Scenario="bear",V75,"N/A"))) -> 0.05 | W72: =IF(Case_Scenario="Bull",W73,IF(Case_Scenario="Base",W74,IF(Case_Scenario="bear",W75,"N/A"))) -> 0.05 | X72: =IF(Case_Scenario="Bull",X73,IF(Case_Scenario="Base",X74,IF(Case_Scenario="bear",X75,"N/A"))) -> 0.05 | Z72: =IF(Case_Scenario="Bull",Z73,IF(Case_Scenario="Base",Z74,IF(Case_Scenario="bear",Z75,"N/A"))) -> 0.05 | AA72: =IF(Case_Scenario="Bull",AA73,IF(Case_Scenario="Base",AA74,IF(Case_Scenario="bear",AA75,"N/A"))) -> 0.05 | AB72: =IF(Case_Scenario="Bull",AB73,IF(Case_Scenario="Base",AB74,IF(Case_Scenario="bear",AB75,"N/A"))) -> 0.05 | AC72: =IF(Case_Scenario="Bull",AC73,IF(Case_Scenario="Base",AC74,IF(Case_Scenario="bear",AC75,"N/A"))) -> 0.05 | AE72: =IF(Case_Scenario="Bull",AE73,IF(Case_Scenario="Base",AE74,IF(Case_Scenario="bear",AE75,"N/A"))) -> 0.05 | AF72: =IF(Case_Scenario="Bull",AF73,IF(Case_Scenario="Base",AF74,IF(Case_Scenario="bear",AF75,"N/A"))) -> 0.05 | AG72: =IF(Case_Scenario="Bull",AG73,IF(Case_Scenario="Base",AG74,IF(Case_Scenario="bear",AG75,"N/A"))) -> 0.05
C73: Bull Case | V73: 0.1 | W73: 0.1 | X73: 0.1 | Z73: 0.1 | AA73: 0.1 | AB73: 0.1 | AC73: 0.1 | AE73: 0.1 | AF73: 0.1 | AG73: 0.1
C74: Base Case | V74: 0.05 | W74: 0.05 | X74: 0.05 | Z74: 0.05 | AA74: 0.05 | AB74: 0.05 | AC74: 0.05 | AE74: 0.05 | AF74: 0.05 | AG74: 0.05
C75: Bear Case | V75: 0 | W75: 0 | X75: 0 | Z75: 0 | AA75: 0 | AB75: 0 | AC75: 0 | AE75: 0 | AF75: 0 | AG75: 0
A77: x | C77: =C44 -> Segment 5 Revenue | F77: =F44 -> 0 | G77: =G44 -> 0 | H77: =H44 -> 0 | I77: =I44 -> 0 | J77: =J44 -> 0 | K77: =K44 -> 0 | L77: =L44 -> 0 | M77: =M44 -> 0 | ... U77: =U44 -> 0 | V77: =IF($C$25="Quarterly",U77*(1+V78),Q77*(1+V78)) -> 0 | W77: =IF($C$25="Quarterly",V77*(1+W78),R77*(1+W78)) -> 0 | X77: =IF($C$25="Quarterly",W77*(1+X78),S77*(1+X78)) -> 0 | Y77: =SUM(U77:X77) -> 0 | Z77: =IF($C$25="Quarterly",X77*(1+Z78),U77*(1+Z78)) -> 0 | AA77: =IF($C$25="Quarterly",Z77*(1+AA78),V77*(1+AA78)) -> 0 | AB77: =IF($C$25="Quarterly",AA77*(1+AB78),W77*(1+AB78)) -> 0 | AC77: =IF($C$25="Quarterly",AB77*(1+AC78),X77*(1+AC78)) -> 0 | AD77: =SUM(Z77:AC77) -> 0 | AE77: =AD77*(1+AE78) -> 0 | AF77: =AE77*(1+AF78) -> 0 | AG77: =AF77*(1+AG78) -> 0
C78: =IF($C$25="Quarterly","% Growth QoQ","% Growth YoY") -> % Growth QoQ | G78: =G45 -> N/A | H78: =H45 -> N/A | I78: =I45 -> N/A | J78: =J45 -> 0 | K78: =K45 -> N/A | L78: =L45 -> N/A | M78: =M45 -> N/A | N78: =N45 -> N/A | ... U78: =U45 -> N/A | V78: =IF(Case_Scenario="Bull",V79,IF(Case_Scenario="Base",V80,IF(Case_Scenario="bear",V81,"N/A"))) -> 0.05 | W78: =IF(Case_Scenario="Bull",W79,IF(Case_Scenario="Base",W80,IF(Case_Scenario="bear",W81,"N/A"))) -> 0.05 | X78: =IF(Case_Scenario="Bull",X79,IF(Case_Scenario="Base",X80,IF(Case_Scenario="bear",X81,"N/A"))) -> 0.05 | Z78: =IF(Case_Scenario="Bull",Z79,IF(Case_Scenario="Base",Z80,IF(Case_Scenario="bear",Z81,"N/A"))) -> 0.05 | AA78: =IF(Case_Scenario="Bull",AA79,IF(Case_Scenario="Base",AA80,IF(Case_Scenario="bear",AA81,"N/A"))) -> 0.05 | AB78: =IF(Case_Scenario="Bull",AB79,IF(Case_Scenario="Base",AB80,IF(Case_Scenario="bear",AB81,"N/A"))) -> 0.05 | AC78: =IF(Case_Scenario="Bull",AC79,IF(Case_Scenario="Base",AC80,IF(Case_Scenario="bear",AC81,"N/A"))) -> 0.05 | AE78: =IF(Case_Scenario="Bull",AE79,IF(Case_Scenario="Base",AE80,IF(Case_Scenario="bear",AE81,"N/A"))) -> 0.05 | AF78: =IF(Case_Scenario="Bull",AF79,IF(Case_Scenario="Base",AF80,IF(Case_Scenario="bear",AF81,"N/A"))) -> 0.05 | AG78: =IF(Case_Scenario="Bull",AG79,IF(Case_Scenario="Base",AG80,IF(Case_Scenario="bear",AG81,"N/A"))) -> 0.05
C79: Bull Case | V79: 0.1 | W79: 0.1 | X79: 0.1 | Z79: 0.1 | AA79: 0.1 | AB79: 0.1 | AC79: 0.1 | AE79: 0.1 | AF79: 0.1 | AG79: 0.1
C80: Base Case | V80: 0.05 | W80: 0.05 | X80: 0.05 | Z80: 0.05 | AA80: 0.05 | AB80: 0.05 | AC80: 0.05 | AE80: 0.05 | AF80: 0.05 | AG80: 0.05
C81: Bear Case | V81: 0 | W81: 0 | X81: 0 | Z81: 0 | AA81: 0 | AB81: 0 | AC81: 0 | AE81: 0 | AF81: 0 | AG81: 0
A83: x | C83: =C47 -> Segment 6 Revenue | F83: =F47 -> 0 | G83: =G47 -> 0 | H83: =H47 -> 0 | I83: =I47 -> 0 | J83: =J47 -> 0 | K83: =K47 -> 0 | L83: =L47 -> 0 | M83: =M47 -> 0 | ... U83: =U47 -> 0 | V83: =IF($C$25="Quarterly",U83*(1+V84),Q83*(1+V84)) -> 0 | W83: =IF($C$25="Quarterly",V83*(1+W84),R83*(1+W84)) -> 0 | X83: =IF($C$25="Quarterly",W83*(1+X84),S83*(1+X84)) -> 0 | Y83: =SUM(U83:X83) -> 0 | Z83: =IF($C$25="Quarterly",X83*(1+Z84),U83*(1+Z84)) -> 0 | AA83: =IF($C$25="Quarterly",Z83*(1+AA84),V83*(1+AA84)) -> 0 | AB83: =IF($C$25="Quarterly",AA83*(1+AB84),W83*(1+AB84)) -> 0 | AC83: =IF($C$25="Quarterly",AB83*(1+AC84),X83*(1+AC84)) -> 0 | AD83: =SUM(Z83:AC83) -> 0 | AE83: =AD83*(1+AE84) -> 0 | AF83: =AE83*(1+AF84) -> 0 | AG83: =AF83*(1+AG84) -> 0
C84: =IF($C$25="Quarterly","% Growth QoQ","% Growth YoY") -> % Growth QoQ | G84: =G48 -> N/A | H84: =H48 -> N/A | I84: =I48 -> N/A | J84: =J48 -> 0 | K84: =K48 -> N/A | L84: =L48 -> N/A | M84: =M48 -> N/A | N84: =N48 -> N/A | ... U84: =U48 -> N/A | V84: =IF(Case_Scenario="Bull",V85,IF(Case_Scenario="Base",V86,IF(Case_Scenario="bear",V87,"N/A"))) -> 0 | W84: =IF(Case_Scenario="Bull",W85,IF(Case_Scenario="Base",W86,IF(Case_Scenario="bear",W87,"N/A"))) -> 0 | X84: =IF(Case_Scenario="Bull",X85,IF(Case_Scenario="Base",X86,IF(Case_Scenario="bear",X87,"N/A"))) -> 0 | Z84: =IF(Case_Scenario="Bull",Z85,IF(Case_Scenario="Base",Z86,IF(Case_Scenario="bear",Z87,"N/A"))) -> 0 | AA84: =IF(Case_Scenario="Bull",AA85,IF(Case_Scenario="Base",AA86,IF(Case_Scenario="bear",AA87,"N/A"))) -> 0 | AB84: =IF(Case_Scenario="Bull",AB85,IF(Case_Scenario="Base",AB86,IF(Case_Scenario="bear",AB87,"N/A"))) -> 0 | AC84: =IF(Case_Scenario="Bull",AC85,IF(Case_Scenario="Base",AC86,IF(Case_Scenario="bear",AC87,"N/A"))) -> 0 | AE84: =IF(Case_Scenario="Bull",AE85,IF(Case_Scenario="Base",AE86,IF(Case_Scenario="bear",AE87,"N/A"))) -> 0 | AF84: =IF(Case_Scenario="Bull",AF85,IF(Case_Scenario="Base",AF86,IF(Case_Scenario="bear",AF87,"N/A"))) -> 0 | AG84: =IF(Case_Scenario="Bull",AG85,IF(Case_Scenario="Base",AG86,IF(Case_Scenario="bear",AG87,"N/A"))) -> 0
C85: Bull Case | V85: =U85 -> 0 | W85: =V85 -> 0 | X85: =W85 -> 0 | Z85: =X85 -> 0 | AA85: =Z85 -> 0 | AB85: =AA85 -> 0 | AC85: =AB85 -> 0 | AE85: =AC85 -> 0 | AF85: =AE85 -> 0 | AG85: =AF85 -> 0
C86: Base Case | V86: =U86 -> 0 | W86: =V86 -> 0 | X86: =W86 -> 0 | Z86: =X86 -> 0 | AA86: =Z86 -> 0 | AB86: =AA86 -> 0 | AC86: =AB86 -> 0 | AE86: =AC86 -> 0 | AF86: =AE86 -> 0 | AG86: =AF86 -> 0
C87: Bear Case | V87: =U87 -> 0 | W87: =V87 -> 0 | X87: =W87 -> 0 | Z87: =X87 -> 0 | AA87: =Z87 -> 0 | AB87: =AA87 -> 0 | AC87: =AB87 -> 0 | AE87: =AC87 -> 0 | AF87: =AE87 -> 0 | AG87: =AF87 -> 0
A89: x | C89: Activity-Based Growth | F89: =F$28 -> 1Q23 | G89: =G$28 -> 2Q23 | H89: =H$28 -> 3Q23 | I89: =I$28 -> 4Q23 | J89: =J$28 -> 2023 | K89: =K$28 -> 1Q24 | L89: =L$28 -> 2Q24 | M89: =M$28 -> 3Q24 | ... AG89: =AG$28 -> 2030e | AH89: x
C91: =C32 -> Management & Advisory Fees | F91: =F32 -> 85.946 | G91: =G32 -> 92.88 | H91: =H32 -> 97.355 | I91: =I32 -> 95.692 | J91: =J32 -> 371.873 | K91: =K32 -> 105.407 | L91: =L32 -> 109.184 | M91: =M32 -> 113.641 | ... U91: =U32 -> 133.696 | V91: =V92*V97 -> 147.39984 | W91: =W92*W97 -> 162.50832 | X91: =X92*X97 -> 179.16543 | Y91: =SUM(U91:X91) -> 622.76959 | Z91: =Z92*Z97 -> 197.52988 | AA91: =AA92*AA97 -> 217.7767 | AB91: =AB92*AB97 -> 240.09881 | AC91: =AC92*AC97 -> 264.70894 | AD91: =SUM(Z91:AC91) -> 920.11432 | AE91: =AE92*AE97 -> 1014.426 | AF91: =AF92*AF97 -> 1118.4047 | AG91: =AG92*AG97 -> 1233.0412
C92: Volume | F92: 220 | G92: 220 | H92: 220 | I92: 220 | J92: =SUM(F92:I92) -> 880 | K92: 220 | L92: 220 | M92: 220 | N92: 220 | O92: =SUM(K92:N92) -> 880 | P92: 220 | Q92: 220 | R92: 220 | S92: 220 | T92: =SUM(P92:S92) -> 880 | U92: 220 | V92: =U92*(1+V93) -> 231 | W92: =V92*(1+W93) -> 242.55 | X92: =W92*(1+X93) -> 254.6775 | Y92: =SUM(U92:X92) -> 948.2275 | Z92: =X92*(1+Z93) -> 267.41138 | AA92: =Z92*(1+AA93) -> 280.78194 | AB92: =AA92*(1+AB93) -> 294.82104 | AC92: =AB92*(1+AC93) -> 309.56209 | AD92: =SUM(Z92:AC92) -> 1152.5765 | AE92: =AD92*(1+AE93) -> 1210.2053 | AF92: =AE92*(1+AF93) -> 1270.7155 | AG92: =AF92*(1+AG93) -> 1334.2513
C93: % Volume Growth | G93: =IFERROR(G92/F92-1,"--") -> 0 | H93: =IFERROR(H92/G92-1,"--") -> 0 | I93: =IFERROR(I92/H92-1,"--") -> 0 | K93: =IFERROR(K92/I92-1,"--") -> 0 | L93: =IFERROR(L92/K92-1,"--") -> 0 | M93: =IFERROR(M92/L92-1,"--") -> 0 | N93: =IFERROR(N92/M92-1,"--") -> 0 | O93: =IFERROR(O92/J92-1,"--") -> 0 | P93: =IFERROR(P92/N92-1,"--") -> 0 | Q93: =IFERROR(Q92/P92-1,"--") -> 0 | R93: =IFERROR(R92/Q92-1,"--") -> 0 | S93: =IFERROR(S92/R92-1,"--") -> 0 | T93: =IFERROR(T92/O92-1,"--") -> 0 | U93: =IFERROR(U92/S92-1,"--") -> 0 | V93: =IF(Case_Scenario="Bull",V94,IF(Case_Scenario="Base",V95,IF(Case_Scenario="bear",V96,"N/A"))) -> 0.05 | W93: =IF(Case_Scenario="Bull",W94,IF(Case_Scenario="Base",W95,IF(Case_Scenario="bear",W96,"N/A"))) -> 0.05 | X93: =IF(Case_Scenario="Bull",X94,IF(Case_Scenario="Base",X95,IF(Case_Scenario="bear",X96,"N/A"))) -> 0.05 | Z93: =IF(Case_Scenario="Bull",Z94,IF(Case_Scenario="Base",Z95,IF(Case_Scenario="bear",Z96,"N/A"))) -> 0.05 | AA93: =IF(Case_Scenario="Bull",AA94,IF(Case_Scenario="Base",AA95,IF(Case_Scenario="bear",AA96,"N/A"))) -> 0.05 | AB93: =IF(Case_Scenario="Bull",AB94,IF(Case_Scenario="Base",AB95,IF(Case_Scenario="bear",AB96,"N/A"))) -> 0.05 | AC93: =IF(Case_Scenario="Bull",AC94,IF(Case_Scenario="Base",AC95,IF(Case_Scenario="bear",AC96,"N/A"))) -> 0.05 | AE93: =IF(Case_Scenario="Bull",AE94,IF(Case_Scenario="Base",AE95,IF(Case_Scenario="bear",AE96,"N/A"))) -> 0.05 | AF93: =IF(Case_Scenario="Bull",AF94,IF(Case_Scenario="Base",AF95,IF(Case_Scenario="bear",AF96,"N/A"))) -> 0.05 | AG93: =IF(Case_Scenario="Bull",AG94,IF(Case_Scenario="Base",AG95,IF(Case_Scenario="bear",AG96,"N/A"))) -> 0.05
C94: Bull Case | V94: 0.1 | W94: 0.1 | X94: 0.1 | Z94: 0.1 | AA94: 0.1 | AB94: 0.1 | AC94: 0.1 | AE94: 0.1 | AF94: 0.1 | AG94: 0.1
C95: Base Case | V95: 0.05 | W95: 0.05 | X95: 0.05 | Z95: 0.05 | AA95: 0.05 | AB95: 0.05 | AC95: 0.05 | AE95: 0.05 | AF95: 0.05 | AG95: 0.05
C96: Bear Case | V96: 0 | W96: 0 | X96: 0 | Z96: 0 | AA96: 0 | AB96: 0 | AC96: 0 | AE96: 0 | AF96: 0 | AG96: 0
C97: Price | F97: =IFERROR(F91/F92,"--") -> 0.39066364 | G97: =IFERROR(G91/G92,"--") -> 0.42218182 | H97: =IFERROR(H91/H92,"--") -> 0.44252273 | I97: =IFERROR(I91/I92,"--") -> 0.43496364 | J97: =IFERROR(J91/J92,"--") -> 0.42258295 | K97: =IFERROR(K91/K92,"--") -> 0.47912273 | L97: =IFERROR(L91/L92,"--") -> 0.49629091 | M97: =IFERROR(M91/M92,"--") -> 0.51655 | ... U97: =IFERROR(U91/U92,"--") -> 0.60770909 | V97: =U97*(1+V98) -> 0.63809455 | W97: =V97*(1+W98) -> 0.66999927 | X97: =W97*(1+X98) -> 0.70349924 | Y97: =Y91/Y92 -> 0.65677234 | Z97: =X97*(1+Z98) -> 0.7386742 | AA97: =Z97*(1+AA98) -> 0.77560791 | AB97: =AA97*(1+AB98) -> 0.8143883 | AC97: =AB97*(1+AC98) -> 0.85510772 | AD97: =AD91/AD92 -> 0.79831088 | AE97: =AD97*(1+AE98) -> 0.83822642 | AF97: =AE97*(1+AF98) -> 0.88013774 | AG97: =AF97*(1+AG98) -> 0.92414463
C98: % Price Growth | G98: =IFERROR(G97/F97-1,"--") -> 0.080678566 | H98: =IFERROR(H97/G97-1,"--") -> 0.048180448 | I98: =IFERROR(I97/H97-1,"--") -> -0.017081814 | K98: =IFERROR(K97/I97-1,"--") -> 0.10152364 | L98: =IFERROR(L97/K97-1,"--") -> 0.035832535 | M98: =IFERROR(M97/L97-1,"--") -> 0.040820999 | N98: =IFERROR(N97/M97-1,"--") -> 0.088550787 | O98: =IFERROR(O97/J97-1,"--") -> 0.21529662 | P98: =IFERROR(P97/N97-1,"--") -> 0.13142663 | Q98: =IFERROR(Q97/P97-1,"--") -> -0.14417485 | R98: =IFERROR(R97/Q97-1,"--") -> 0.054256447 | S98: =IFERROR(S97/R97-1,"--") -> 0.012321629 | T98: =IFERROR(T97/O97-1,"--") -> 0.13703046 | U98: =IFERROR(U97/S97-1,"--") -> 0.045823621 | V98: =IF(Case_Scenario="Bull",V99,IF(Case_Scenario="Base",V100,IF(Case_Scenario="bear",V101,"N/A"))) -> 0.05 | W98: =IF(Case_Scenario="Bull",W99,IF(Case_Scenario="Base",W100,IF(Case_Scenario="bear",W101,"N/A"))) -> 0.05 | X98: =IF(Case_Scenario="Bull",X99,IF(Case_Scenario="Base",X100,IF(Case_Scenario="bear",X101,"N/A"))) -> 0.05 | Z98: =IF(Case_Scenario="Bull",Z99,IF(Case_Scenario="Base",Z100,IF(Case_Scenario="bear",Z101,"N/A"))) -> 0.05 | AA98: =IF(Case_Scenario="Bull",AA99,IF(Case_Scenario="Base",AA100,IF(Case_Scenario="bear",AA101,"N/A"))) -> 0.05 | AB98: =IF(Case_Scenario="Bull",AB99,IF(Case_Scenario="Base",AB100,IF(Case_Scenario="bear",AB101,"N/A"))) -> 0.05 | AC98: =IF(Case_Scenario="Bull",AC99,IF(Case_Scenario="Base",AC100,IF(Case_Scenario="bear",AC101,"N/A"))) -> 0.05 | AE98: =IF(Case_Scenario="Bull",AE99,IF(Case_Scenario="Base",AE100,IF(Case_Scenario="bear",AE101,"N/A"))) -> 0.05 | AF98: =IF(Case_Scenario="Bull",AF99,IF(Case_Scenario="Base",AF100,IF(Case_Scenario="bear",AF101,"N/A"))) -> 0.05 | AG98: =IF(Case_Scenario="Bull",AG99,IF(Case_Scenario="Base",AG100,IF(Case_Scenario="bear",AG101,"N/A"))) -> 0.05
C99: Bull Case | V99: 0.1 | W99: 0.1 | X99: 0.1 | Z99: 0.1 | AA99: 0.1 | AB99: 0.1 | AC99: 0.1 | AE99: 0.1 | AF99: 0.1 | AG99: 0.1
C100: Base Case | V100: 0.05 | W100: 0.05 | X100: 0.05 | Z100: 0.05 | AA100: 0.05 | AB100: 0.05 | AC100: 0.05 | AE100: 0.05 | AF100: 0.05 | AG100: 0.05
C101: Bear Case | V101: 0 | W101: 0 | X101: 0 | Z101: 0 | AA101: 0 | AB101: 0 | AC101: 0 | AE101: 0 | AF101: 0 | AG101: 0
A103: x | C103: =C35 -> Incentive Fees | F103: =F35 -> 49.563 | G103: =G35 -> 60.502 | H103: =H35 -> 29.719 | I103: =I35 -> 17.096 | J103: =J35 -> 156.88 | K103: =K35 -> 19.63 | L103: =L35 -> 17.692 | M103: =M35 -> 11.623 | ... U103: =U35 -> 42.262 | V103: =V104*V109 -> 46.593855 | W103: =W104*W109 -> 51.369725 | X103: =X104*X109 -> 56.635122 | Y103: =SUM(U103:X103) -> 196.8607 | Z103: =Z104*Z109 -> 62.440222 | AA103: =AA104*AA109 -> 68.840345 | AB103: =AB104*AB109 -> 75.89648 | AC103: =AC104*AC109 -> 83.675869 | AD103: =SUM(Z103:AC103) -> 290.85292 | AE103: =AE104*AE109 -> 320.66534 | AF103: =AF104*AF109 -> 353.53354 | AG103: =AG104*AG109 -> 389.77072
C104: Volume | F104: 220 | G104: 220 | H104: 220 | I104: 220 | J104: =SUM(F104:I104) -> 880 | K104: 220 | L104: 220 | M104: 220 | N104: 220 | O104: =SUM(K104:N104) -> 880 | P104: 220 | Q104: 220 | R104: 220 | S104: 220 | T104: =SUM(P104:S104) -> 880 | U104: 220 | V104: =U104*(1+V105) -> 231 | W104: =V104*(1+W105) -> 242.55 | X104: =W104*(1+X105) -> 254.6775 | Y104: =SUM(U104:X104) -> 948.2275 | Z104: =X104*(1+Z105) -> 267.41138 | AA104: =Z104*(1+AA105) -> 280.78194 | AB104: =AA104*(1+AB105) -> 294.82104 | AC104: =AB104*(1+AC105) -> 309.56209 | AD104: =SUM(Z104:AC104) -> 1152.5765 | AE104: =AD104*(1+AE105) -> 1210.2053 | AF104: =AE104*(1+AF105) -> 1270.7155 | AG104: =AF104*(1+AG105) -> 1334.2513
C105: % Volume Growth | G105: =IFERROR(G104/F104-1,"--") -> 0 | H105: =IFERROR(H104/G104-1,"--") -> 0 | I105: =IFERROR(I104/H104-1,"--") -> 0 | K105: =IFERROR(K104/I104-1,"--") -> 0 | L105: =IFERROR(L104/K104-1,"--") -> 0 | M105: =IFERROR(M104/L104-1,"--") -> 0 | N105: =IFERROR(N104/M104-1,"--") -> 0 | O105: =IFERROR(O104/J104-1,"--") -> 0 | P105: =IFERROR(P104/N104-1,"--") -> 0 | Q105: =IFERROR(Q104/P104-1,"--") -> 0 | R105: =IFERROR(R104/Q104-1,"--") -> 0 | S105: =IFERROR(S104/R104-1,"--") -> 0 | T105: =IFERROR(T104/O104-1,"--") -> 0 | U105: =IFERROR(U104/S104-1,"--") -> 0 | V105: =IF(Case_Scenario="Bull",V106,IF(Case_Scenario="Base",V107,IF(Case_Scenario="bear",V108,"N/A"))) -> 0.05 | W105: =IF(Case_Scenario="Bull",W106,IF(Case_Scenario="Base",W107,IF(Case_Scenario="bear",W108,"N/A"))) -> 0.05 | X105: =IF(Case_Scenario="Bull",X106,IF(Case_Scenario="Base",X107,IF(Case_Scenario="bear",X108,"N/A"))) -> 0.05 | Z105: =IF(Case_Scenario="Bull",Z106,IF(Case_Scenario="Base",Z107,IF(Case_Scenario="bear",Z108,"N/A"))) -> 0.05 | AA105: =IF(Case_Scenario="Bull",AA106,IF(Case_Scenario="Base",AA107,IF(Case_Scenario="bear",AA108,"N/A"))) -> 0.05 | AB105: =IF(Case_Scenario="Bull",AB106,IF(Case_Scenario="Base",AB107,IF(Case_Scenario="bear",AB108,"N/A"))) -> 0.05 | AC105: =IF(Case_Scenario="Bull",AC106,IF(Case_Scenario="Base",AC107,IF(Case_Scenario="bear",AC108,"N/A"))) -> 0.05 | AE105: =IF(Case_Scenario="Bull",AE106,IF(Case_Scenario="Base",AE107,IF(Case_Scenario="bear",AE108,"N/A"))) -> 0.05 | AF105: =IF(Case_Scenario="Bull",AF106,IF(Case_Scenario="Base",AF107,IF(Case_Scenario="bear",AF108,"N/A"))) -> 0.05 | AG105: =IF(Case_Scenario="Bull",AG106,IF(Case_Scenario="Base",AG107,IF(Case_Scenario="bear",AG108,"N/A"))) -> 0.05
C106: Bull Case | V106: 0.1 | W106: 0.1 | X106: 0.1 | Z106: 0.1 | AA106: 0.1 | AB106: 0.1 | AC106: 0.1 | AE106: 0.1 | AF106: 0.1 | AG106: 0.1
C107: Base Case | V107: 0.05 | W107: 0.05 | X107: 0.05 | Z107: 0.05 | AA107: 0.05 | AB107: 0.05 | AC107: 0.05 | AE107: 0.05 | AF107: 0.05 | AG107: 0.05
C108: Bear Case | V108: 0 | W108: 0 | X108: 0 | Z108: 0 | AA108: 0 | AB108: 0 | AC108: 0 | AE108: 0 | AF108: 0 | AG108: 0
C109: Price | F109: =IFERROR(F103/F104,"--") -> 0.22528636 | G109: =IFERROR(G103/G104,"--") -> 0.27500909 | H109: =IFERROR(H103/H104,"--") -> 0.13508636 | I109: =IFERROR(I103/I104,"--") -> 0.077709091 | J109: =IFERROR(J103/J104,"--") -> 0.17827273 | K109: =IFERROR(K103/K104,"--") -> 0.089227273 | L109: =IFERROR(L103/L104,"--") -> 0.080418182 | M109: =IFERROR(M103/M104,"--") -> 0.052831818 | ... U109: =IFERROR(U103/U104,"--") -> 0.1921 | V109: =U109*(1+V110) -> 0.201705 | W109: =V109*(1+W110) -> 0.21179025 | X109: =W109*(1+X110) -> 0.22237976 | Y109: =Y103/Y104 -> 0.20760915 | Z109: =X109*(1+Z110) -> 0.23349875 | AA109: =Z109*(1+AA110) -> 0.24517369 | AB109: =AA109*(1+AB110) -> 0.25743237 | AC109: =AB109*(1+AC110) -> 0.27030399 | AD109: =AD103/AD104 -> 0.25235022 | AE109: =AD109*(1+AE110) -> 0.26496773 | AF109: =AE109*(1+AF110) -> 0.27821611 | AG109: =AF109*(1+AG110) -> 0.29212692
C110: % Price Growth | G110: =IFERROR(G109/F109-1,"--") -> 0.220709 | H110: =IFERROR(H109/G109-1,"--") -> -0.5087931 | I110: =IFERROR(I109/H109-1,"--") -> -0.42474511 | K110: =IFERROR(K109/I109-1,"--") -> 0.14822181 | L110: =IFERROR(L109/K109-1,"--") -> -0.098726439 | M110: =IFERROR(M109/L109-1,"--") -> -0.3430364 | N110: =IFERROR(N109/M109-1,"--") -> 3.5565689 | O110: =IFERROR(O109/J109-1,"--") -> -0.3504207 | P110: =IFERROR(P109/N109-1,"--") -> 0.071901966 | Q110: =IFERROR(Q109/P109-1,"--") -> -0.46773767 | R110: =IFERROR(R109/Q109-1,"--") -> 0.38929706 | S110: =IFERROR(S109/R109-1,"--") -> 0.67071631 | T110: =IFERROR(T109/O109-1,"--") -> 0.9537515 | U110: =IFERROR(U109/S109-1,"--") -> -0.39741926 | V110: =IF(Case_Scenario="Bull",V111,IF(Case_Scenario="Base",V112,IF(Case_Scenario="bear",V113,"N/A"))) -> 0.05 | W110: =IF(Case_Scenario="Bull",W111,IF(Case_Scenario="Base",W112,IF(Case_Scenario="bear",W113,"N/A"))) -> 0.05 | X110: =IF(Case_Scenario="Bull",X111,IF(Case_Scenario="Base",X112,IF(Case_Scenario="bear",X113,"N/A"))) -> 0.05 | Z110: =IF(Case_Scenario="Bull",Z111,IF(Case_Scenario="Base",Z112,IF(Case_Scenario="bear",Z113,"N/A"))) -> 0.05 | AA110: =IF(Case_Scenario="Bull",AA111,IF(Case_Scenario="Base",AA112,IF(Case_Scenario="bear",AA113,"N/A"))) -> 0.05 | AB110: =IF(Case_Scenario="Bull",AB111,IF(Case_Scenario="Base",AB112,IF(Case_Scenario="bear",AB113,"N/A"))) -> 0.05 | AC110: =IF(Case_Scenario="Bull",AC111,IF(Case_Scenario="Base",AC112,IF(Case_Scenario="bear",AC113,"N/A"))) -> 0.05 | AE110: =IF(Case_Scenario="Bull",AE111,IF(Case_Scenario="Base",AE112,IF(Case_Scenario="bear",AE113,"N/A"))) -> 0.05 | AF110: =IF(Case_Scenario="Bull",AF111,IF(Case_Scenario="Base",AF112,IF(Case_Scenario="bear",AF113,"N/A"))) -> 0.05 | AG110: =IF(Case_Scenario="Bull",AG111,IF(Case_Scenario="Base",AG112,IF(Case_Scenario="bear",AG113,"N/A"))) -> 0.05
C111: Bull Case | V111: 0.1 | W111: 0.1 | X111: 0.1 | Z111: 0.1 | AA111: 0.1 | AB111: 0.1 | AC111: 0.1 | AE111: 0.1 | AF111: 0.1 | AG111: 0.1
C112: Base Case | V112: 0.05 | W112: 0.05 | X112: 0.05 | Z112: 0.05 | AA112: 0.05 | AB112: 0.05 | AC112: 0.05 | AE112: 0.05 | AF112: 0.05 | AG112: 0.05
C113: Bear Case | V113: 0 | W113: 0 | X113: 0 | Z113: 0 | AA113: 0 | AB113: 0 | AC113: 0 | AE113: 0 | AF113: 0 | AG113: 0
A115: x | C115: =C38 -> Segment 3 Revenue | F115: =F38 -> 0 | G115: =G38 -> 0 | H115: =H38 -> 0 | I115: =I38 -> 0 | J115: =J38 -> 0 | K115: =K38 -> 0 | L115: =L38 -> 0 | M115: =M38 -> 0 | ... U115: =U38 -> 0 | V115: =V116*V121 -> 0 | W115: =W116*W121 -> 0 | X115: =X116*X121 -> 0 | Y115: =SUM(U115:X115) -> 0 | Z115: =Z116*Z121 -> 0 | AA115: =AA116*AA121 -> 0 | AB115: =AB116*AB121 -> 0 | AC115: =AC116*AC121 -> 0 | AD115: =SUM(Z115:AC115) -> 0 | AE115: =AE116*AE121 -> 0 | AF115: =AF116*AF121 -> 0 | AG115: =AG116*AG121 -> 0
C116: Volume | F116: 220 | G116: 220 | H116: 220 | I116: 220 | J116: =SUM(F116:I116) -> 880 | K116: 220 | L116: 220 | M116: 220 | N116: 220 | O116: =SUM(K116:N116) -> 880 | P116: 220 | Q116: 220 | R116: 220 | S116: 220 | T116: =SUM(P116:S116) -> 880 | U116: 220 | V116: =U116*(1+V117) -> 231 | W116: =V116*(1+W117) -> 242.55 | X116: =W116*(1+X117) -> 254.6775 | Y116: =SUM(U116:X116) -> 948.2275 | Z116: =X116*(1+Z117) -> 267.41138 | AA116: =Z116*(1+AA117) -> 280.78194 | AB116: =AA116*(1+AB117) -> 294.82104 | AC116: =AB116*(1+AC117) -> 309.56209 | AD116: =SUM(Z116:AC116) -> 1152.5765 | AE116: =AD116*(1+AE117) -> 1210.2053 | AF116: =AE116*(1+AF117) -> 1270.7155 | AG116: =AF116*(1+AG117) -> 1334.2513
...

Sheet Model
C1: =Company_Name&" - "&MID(CELL("filename",A1),FIND("]",CELL("filename",A1))+1,255)&": "&Case_Scenario&" Case" -> Hamilton Lane Inc. - Model: Base Case
C2: =Cover!C2 -> $ in Millions Except Per Share Data
C4: Font Toggle
C5: Report
C7: Interest Expense Toggle
C8: On
A10: x | C10: Shortcuts
C11: =$C$25 -> Income Statement
C12: =$C$74 -> Cash Flow Statement
C13: =$C$120 -> Balance Sheet
C14: =$C$161 -> Working Capital Schedule
C15: =$C$191 -> PP&E / Depreciation Schedule
C16: =$C$205 -> Investments Schedule
C17: =$C$217 -> Other Long-Term Items Schedule
C18: =$C$235 -> Shareholder's Equity Schedule
C19: =$C$276 -> Shares Outstanding Schedule
C20: =$C$287 -> Debt and Interest Schedule
J23: 1 | O23: 2 | T23: 3 | Y23: 4 | AD23: 5 | AE23: 6 | AF23: 7 | AG23: 8
F24: =G24 -> 2023 | G24: =H24 -> 2023 | H24: =I24 -> 2023 | I24: =J24 -> 2023 | J24: =O24-1 -> 2023 | K24: =L24 -> 2024 | L24: =M24 -> 2024 | M24: =N24 -> 2024 | N24: =O24 -> 2024 | O24: =T24-1 -> 2024 | P24: =Q24 -> 2025 | Q24: =R24 -> 2025 | R24: =S24 -> 2025 | S24: =T24 -> 2025 | T24: =YEAR(Last_FYE) -> 2025 | U24: =V24 -> 2026 | V24: =W24 -> 2026 | W24: =X24 -> 2026 | X24: =Y24 -> 2026 | Y24: =T24+1 -> 2026 | Z24: =AA24 -> 2027 | AA24: =AB24 -> 2027 | AB24: =AC24 -> 2027 | AC24: =AD24 -> 2027 | AD24: =Y24+1 -> 2027 | AE24: =AD24+1 -> 2028 | AF24: =AE24+1 -> 2029 | AG24: =AF24+1 -> 2030
A25: x | C25: Income Statement | F25: ="1Q"&RIGHT(F24,2) -> 1Q23 | G25: ="2Q"&RIGHT(G24,2) -> 2Q23 | H25: ="3Q"&RIGHT(H24,2) -> 3Q23 | I25: ="4Q"&RIGHT(I24,2) -> 4Q23 | J25: =J24 -> 2023 | K25: ="1Q"&RIGHT(K24,2) -> 1Q24 | L25: ="2Q"&RIGHT(L24,2) -> 2Q24 | M25: ="3Q"&RIGHT(M24,2) -> 3Q24 | N25: ="4Q"&RIGHT(N24,2) -> 4Q24 | O25: =O24 -> 2024 | P25: ="1Q"&RIGHT(P24,2) -> 1Q25 | Q25: ="2Q"&RIGHT(Q24,2) -> 2Q25 | R25: ="3Q"&RIGHT(R24,2) -> 3Q25 | S25: ="4Q"&RIGHT(S24,2) -> 4Q25 | T25: =T24 -> 2025 | U25: =IF(Last_FQR="4Q","1Q"&RIGHT(U24,2)&"e","1Q"&RIGHT(U24,2)) -> 1Q26 | V25: ="2Q"&RIGHT(V24,2)&"e" -> 2Q26e | W25: ="3Q"&RIGHT(W24,2)&"e" -> 3Q26e | X25: ="4Q"&RIGHT(U24,2)&"e" -> 4Q26e | Y25: =Y24&"e" -> 2026e | Z25: ="1Q"&RIGHT(Z24,2)&"e" -> 1Q27e | AA25: ="2Q"&RIGHT(AA24,2)&"e" -> 2Q27e | AB25: ="3Q"&RIGHT(AB24,2)&"e" -> 3Q27e | AC25: ="4Q"&RIGHT(AC24,2)&"e" -> 4Q27e | AD25: =AD24&"e" -> 2027e | AE25: =AE24&"e" -> 2028e | AF25: =AF24&"e" -> 2029e | AG25: =AG24&"e" -> 2030e | AH25: x
C26: Days In Period | F26: 91 | G26: 91 | H26: 92 | I26: 92 | J26: =SUM(F26:I26) -> 366 | K26: 90 | L26: 91 | M26: 92 | N26: 92 | O26: =SUM(K26:N26) -> 365 | P26: 90 | Q26: 91 | R26: 92 | S26: 92 | T26: =SUM(P26:S26) -> 365 | U26: 90 | V26: 91 | W26: 92 | X26: 92 | Y26: =SUM(U26:X26) -> 365 | Z26: 91 | AA26: 91 | AB26: 92 | AC26: 92 | AD26: =SUM(Z26:AC26) -> 366 | AE26: 365 | AF26: 365 | AG26: 365
C28: Revenue | F28: ='Segment Analysis'!F7 -> 135.509 | G28: ='Segment Analysis'!G7 -> 153.382 | H28: ='Segment Analysis'!H7 -> 127.074 | I28: ='Segment Analysis'!I7 -> 112.788 | J28: =SUM(F28:I28) -> 528.753 | K28: ='Segment Analysis'!K7 -> 125.037 | L28: ='Segment Analysis'!L7 -> 126.876 | M28: ='Segment Analysis'!M7 -> 125.264 | N28: ='Segment Analysis'!N7 -> 176.665 | O28: =SUM(K28:N28) -> 553.842 | P28: ='Segment Analysis'!P7 -> 196.731 | Q28: ='Segment Analysis'!Q7 -> 149.999 | R28: ='Segment Analysis'!R7 -> 168.261 | S28: ='Segment Analysis'!S7 -> 197.973 | T28: =SUM(P28:S28) -> 712.964 | U28: ='Segment Analysis'!U7 -> 175.958 | V28: ='Segment Analysis'!V7 -> 183.91066 | W28: ='Segment Analysis'!W7 -> 195.21191 | X28: ='Segment Analysis'!X7 -> 211.57639 | Y28: =SUM(U28:X28) -> 766.65695 | Z28: ='Segment Analysis'!Z7 -> 224.51778 | AA28: ='Segment Analysis'!AA7 -> 237.98885 | AB28: ='Segment Analysis'!AB7 -> 249.25561 | AC28: ='Segment Analysis'!AC7 -> 260.76606 | AD28: =SUM(Z28:AC28) -> 972.5283 | AE28: ='Segment Analysis'!AE7 -> 1040.6053 | AF28: ='Segment Analysis'!AF7 -> 1097.8386 | AG28: ='Segment Analysis'!AG7 -> 1169.5212
C29: Cost of Goods Sold | F29: 0 | G29: 0 | H29: 0 | I29: 0 | J29: =SUM(F29:I29) -> 0 | K29: 0 | L29: 0 | M29: 0 | N29: 0 | O29: =SUM(K29:N29) -> 0 | P29: 0 | Q29: 0 | R29: 0 | S29: 0 | T29: =SUM(P29:S29) -> 0 | U29: 0 | V29: =IF(Cover!$F$37="Bottom Up",(V30-V28),(-V28*(1-V66))) -> 0 | W29: =IF(Cover!$F$37="Bottom Up",(W30-W28),(-W28*(1-W66))) -> 0 | X29: =IF(Cover!$F$37="Bottom Up",(X30-X28),(-X28*(1-X66))) -> 0 | Y29: =SUM(U29:X29) -> 0 | Z29: =IF(Cover!$F$37="Bottom Up",(Z30-Z28),(-Z28*(1-Z66))) -> 0 | AA29: =IF(Cover!$F$37="Bottom Up",(AA30-AA28),(-AA28*(1-AA66))) -> 0 | AB29: =IF(Cover!$F$37="Bottom Up",(AB30-AB28),(-AB28*(1-AB66))) -> 0 | AC29: =IF(Cover!$F$37="Bottom Up",(AC30-AC28),(-AC28*(1-AC66))) -> 0 | AD29: =SUM(Z29:AC29) -> 0 | AE29: =IF(Cover!$F$37="Bottom Up",(AE30-AE28),(-AE28*(1-AE66))) -> 0 | AF29: =IF(Cover!$F$37="Bottom Up",(AF30-AF28),(-AF28*(1-AF66))) -> 0 | AG29: =IF(Cover!$F$37="Bottom Up",(AG30-AG28),(-AG28*(1-AG66))) -> 0
C30: Gross Profit | F30: =SUM(F28:F29) -> 135.509 | G30: =SUM(G28:G29) -> 153.382 | H30: =SUM(H28:H29) -> 127.074 | I30: =SUM(I28:I29) -> 112.788 | J30: =SUM(F30:I30) -> 528.753 | K30: =SUM(K28:K29) -> 125.037 | L30: =SUM(L28:L29) -> 126.876 | M30: =SUM(M28:M29) -> 125.264 | N30: =SUM(N28:N29) -> 176.665 | O30: =SUM(K30:N30) -> 553.842 | P30: =SUM(P28:P29) -> 196.731 | Q30: =SUM(Q28:Q29) -> 149.999 | R30: =SUM(R28:R29) -> 168.261 | S30: =SUM(S28:S29) -> 197.973 | T30: =SUM(P30:S30) -> 712.964 | U30: =SUM(U28:U29) -> 175.958 | V30: =IF(Cover!$F$37="Bottom Up",(V36-SUM(V32:V33,V35)),V28+V29) -> 183.91066 | W30: =IF(Cover!$F$37="Bottom Up",(W36-SUM(W32:W33,W35)),W28+W29) -> 195.21191 | X30: =IF(Cover!$F$37="Bottom Up",(X36-SUM(X32:X33,X35)),X28+X29) -> 211.57639 | Y30: =SUM(U30:X30) -> 766.65695 | Z30: =IF(Cover!$F$37="Bottom Up",(Z36-SUM(Z32:Z33,Z35)),Z28+Z29) -> 224.51778 | AA30: =IF(Cover!$F$37="Bottom Up",(AA36-SUM(AA32:AA33,AA35)),AA28+AA29) -> 237.98885 | AB30: =IF(Cover!$F$37="Bottom Up",(AB36-SUM(AB32:AB33,AB35)),AB28+AB29) -> 249.25561 | AC30: =IF(Cover!$F$37="Bottom Up",(AC36-SUM(AC32:AC33,AC35)),AC28+AC29) -> 260.76606 | AD30: =SUM(Z30:AC30) -> 972.5283 | AE30: =IF(Cover!$F$37="Bottom Up",(AE36-SUM(AE32:AE33,AE35)),AE28+AE29) -> 1040.6053 | AF30: =IF(Cover!$F$37="Bottom Up",(AF36-SUM(AF32:AF33,AF35)),AF28+AF29) -> 1097.8386 | AG30: =IF(Cover!$F$37="Bottom Up",(AG36-SUM(AG32:AG33,AG35)),AG28+AG29) -> 1169.5212
C32: Selling, General & Administration (SG&A) | F32: =-0.3+-20.513 -> -20.813 | G32: =-0.4+-22.836 -> -23.236 | H32: =-0.3-22.717 -> -23.017 | I32: =-23.329-0.035 -> -23.364 | J32: =SUM(F32:I32) -> -90.43 | K32: -25.995 | L32: -25.349 | M32: -24.164 | N32: -28.512 | O32: =SUM(K32:N32) -> -104.02 | P32: -28.685 | Q32: -27.737 | R32: -30.634 | S32: -34.857 | T32: =SUM(P32:S32) -> -121.913 | U32: -29.427 | V32: =V67*V$28 -> -31.632634 | W32: =W67*W$28 -> -33.576448 | X32: =X67*X$28 -> -36.391138 | Y32: =SUM(U32:X32) -> -131.02722 | Z32: =Z67*Z$28 -> -39.290612 | AA32: =AA67*AA$28 -> -41.648049 | AB32: =AB67*AB$28 -> -43.619731 | AC32: =AC67*AC$28 -> -45.634061 | AD32: =SUM(Z32:AC32) -> -170.19245 | AE32: =AE67*AE$28 -> -182.10592 | AF32: =AF67*AF$28 -> -192.12175 | AG32: =AG67*AG$28 -> -204.66622
C33: Compensation and Benefits | F33: -52.194 | G33: -60.364 | H33: -45.676 | I33: -40.177 | J33: =SUM(F33:I33) -> -198.411 | K33: -44.103 | L33: -45.93 | M33: -49.706 | N33: -64.266 | O33: =SUM(K33:N33) -> -204.005 | P33: -78.435 | Q33: -55.07 | R33: -61.905 | S33: -79.088 | T33: =SUM(P33:S33) -> -274.498 | U33: -69.556 | V33: =V68*V$28 -> -72.644711 | W33: =W68*W$28 -> -77.108702 | X33: =X68*X$28 -> -83.572672 | Y33: =SUM(U33:X33) -> -302.88209 | Z33: =Z68*Z$28 -> -88.684524 | AA33: =AA68*AA$28 -> -94.005596 | AB33: =AB68*AB$28 -> -98.455964 | AC33: =AC68*AC$28 -> -103.00259 | AD33: =SUM(Z33:AC33) -> -384.14868 | AE33: =AE68*AE$28 -> -421.44514 | AF33: =AF68*AF$28 -> -444.62462 | AG33: =AG68*AG$28 -> -473.6561
C34: Depreciation & Amortization | F34: 0 | G34: 0 | H34: 0 | I34: 0 | J34: =SUM(F34:I34) -> 0 | K34: 0 | L34: 0 | M34: 0 | N34: 0 | O34: =SUM(K34:N34) -> 0 | P34: 0 | Q34: 0 | R34: 0 | S34: 0 | T34: =SUM(P34:S34) -> 0 | U34: 0 | V34: =-V77 -> 0 | W34: =-W77 -> 0 | X34: =-X77 -> 0 | Y34: =SUM(U34:X34) -> 0 | Z34: =-Z77 -> 0 | AA34: =-AA77 -> 0 | AB34: =-AB77 -> 0 | AC34: =-AC77 -> 0 | AD34: =SUM(Z34:AC34) -> 0 | AE34: =-AE77 -> 0 | AF34: =-AF77 -> 0 | AG34: =-AG77 -> 0
C35: Other Operating Income (Expense) | F35: 0 | G35: 0 | H35: 0 | I35: 0 | J35: =SUM(F35:I35) -> 0 | K35: 0 | L35: 0 | M35: 0 | N35: 0 | O35: =SUM(K35:N35) -> 0 | P35: 0 | Q35: 0 | R35: 0 | S35: 0 | T35: =SUM(P35:S35) -> 0 | U35: 0 | V35: =V69*V$28 -> 0 | W35: =W69*W$28 -> 0 | X35: =X69*X$28 -> 0 | Y35: =SUM(U35:X35) -> 0 | Z35: =Z69*Z$28 -> 0 | AA35: =AA69*AA$28 -> 0 | AB35: =AB69*AB$28 -> 0 | AC35: =AC69*AC$28 -> 0 | AD35: =SUM(Z35:AC35) -> 0 | AE35: =AE69*AE$28 -> 0 | AF35: =AF69*AF$28 -> 0 | AG35: =AG69*AG$28 -> 0
C36: EBIT | F36: =IF($C$34="Depreciation & Amortization (incl. in SG&A)",F30+SUM(F32:F33,F35),F30+SUM(F32:F35)) -> 62.502 | G36: =IF($C$34="Depreciation & Amortization (incl. in SG&A)",G30+SUM(G32:G33,G35),G30+SUM(G32:G35)) -> 69.782 | H36: =IF($C$34="Depreciation & Amortization (incl. in SG&A)",H30+SUM(H32:H33,H35),H30+SUM(H32:H35)) -> 58.381 | I36: =IF($C$34="Depreciation & Amortization (incl. in SG&A)",I30+SUM(I32:I33,I35),I30+SUM(I32:I35)) -> 49.247 | J36: =SUM(F36:I36) -> 239.912 | K36: =IF($C$34="Depreciation & Amortization (incl. in SG&A)",K30+SUM(K32:K33,K35),K30+SUM(K32:K35)) -> 54.939 | L36: =IF($C$34="Depreciation & Amortization (incl. in SG&A)",L30+SUM(L32:L33,L35),L30+SUM(L32:L35)) -> 55.597 | M36: =IF($C$34="Depreciation & Amortization (incl. in SG&A)",M30+SUM(M32:M33,M35),M30+SUM(M32:M35)) -> 51.394 | N36: =IF($C$34="Depreciation & Amortization (incl. in SG&A)",N30+SUM(N32:N33,N35),N30+SUM(N32:N35)) -> 83.887 | O36: =SUM(K36:N36) -> 245.817 | P36: =IF($C$34="Depreciation & Amortization (incl. in SG&A)",P30+SUM(P32:P33,P35),P30+SUM(P32:P35)) -> 89.611 | Q36: =IF($C$34="Depreciation & Amortization (incl. in SG&A)",Q30+SUM(Q32:Q33,Q35),Q30+SUM(Q32:Q35)) -> 67.192 | R36: =IF($C$34="Depreciation & Amortization (incl. in SG&A)",R30+SUM(R32:R33,R35),R30+SUM(R32:R35)) -> 75.722 | S36: =IF($C$34="Depreciation & Amortization (incl. in SG&A)",S30+SUM(S32:S33,S35),S30+SUM(S32:S35)) -> 84.028 | T36: =SUM(P36:S36) -> 316.553 | U36: =IF($C$34="Depreciation & Amortization (incl. in SG&A)",U30+SUM(U32:U33,U35),U30+SUM(U32:U35)) -> 76.975 | V36: =IF(Cover!$F$37="Bottom Up",'Segment Analysis'!V23,IF($C$34="Depreciation & Amortization (incl. in SG&A)",V30+SUM(V32:V33,V35),V30+SUM(V32:V35))) -> 79.633316 | W36: =IF(Cover!$F$37="Bottom Up",'Segment Analysis'!W23,IF($C$34="Depreciation & Amortization (incl. in SG&A)",W30+SUM(W32:W33,W35),W30+SUM(W32:W35))) -> 84.526755 | X36: =IF(Cover!$F$37="Bottom Up",'Segment Analysis'!X23,IF($C$34="Depreciation & Amortization (incl. in SG&A)",X30+SUM(X32:X33,X35),X30+SUM(X32:X35))) -> 91.612575 | Y36: =SUM(U36:X36) -> 332.74765 | Z36: =IF(Cover!$F$37="Bottom Up",'Segment Analysis'!Z23,IF($C$34="Depreciation & Amortization (incl. in SG&A)",Z30+SUM(Z32:Z33,Z35),Z30+SUM(Z32:Z35))) -> 96.542647 | AA36: =IF(Cover!$F$37="Bottom Up",'Segment Analysis'!AA23,IF($C$34="Depreciation & Amortization (incl. in SG&A)",AA30+SUM(AA32:AA33,AA35),AA30+SUM(AA32:AA35))) -> 102.33521 | AB36: =IF(Cover!$F$37="Bottom Up",'Segment Analysis'!AB23,IF($C$34="Depreciation & Amortization (incl. in SG&A)",AB30+SUM(AB32:AB33,AB35),AB30+SUM(AB32:AB35))) -> 107.17991 | AC36: =IF(Cover!$F$37="Bottom Up",'Segment Analysis'!AC23,IF($C$34="Depreciation & Amortization (incl. in SG&A)",AC30+SUM(AC32:AC33,AC35),AC30+SUM(AC32:AC35))) -> 112.12941 | AD36: =SUM(Z36:AC36) -> 418.18717 | AE36: =IF(Cover!$F$37="Bottom Up",'Segment Analysis'!AE23,IF($C$34="Depreciation & Amortization (incl. in SG&A)",AE30+SUM(AE32:AE33,AE35),AE30+SUM(AE32:AE35))) -> 437.05422 | AF36: =IF(Cover!$F$37="Bottom Up",'Segment Analysis'!AF23,IF($C$34="Depreciation & Amortization (incl. in SG&A)",AF30+SUM(AF32:AF33,AF35),AF30+SUM(AF32:AF35))) -> 461.0922 | AG36: =IF(Cover!$F$37="Bottom Up",'Segment Analysis'!AG23,IF($C$34="Depreciation & Amortization (incl. in SG&A)",AG30+SUM(AG32:AG33,AG35),AG30+SUM(AG32:AG35))) -> 491.19892
C38: Interest Income | F38: 0.168 | G38: 1.107 | H38: 2.553 | I38: 1.286 | J38: =SUM(F38:I38) -> 5.114 | K38: 2.677 | L38: 3.94 | M38: 1.5 | N38: 1.891 | O38: =SUM(K38:N38) -> 10.008 | P38: 0.782 | Q38: 1.498 | R38: 2.798 | S38: 3.002 | T38: =SUM(P38:S38) -> 8.08 | U38: 3.034 | V38: =V330 -> 3.2782304 | W38: =W330 -> 3.4018128 | X38: =X330 -> 3.4819528 | Y38: =SUM(U38:X38) -> 13.195996 | Z38: =Z330 -> 3.2636413 | AA38: =AA330 -> 3.0792032 | AB38: =AB330 -> 2.9971971 | AC38: =AC330 -> 2.76159 | AD38: =SUM(Z38:AC38) -> 12.101632 | AE38: =AE330 -> 2.8931911 | AF38: =AF330 -> 3.2868919 | AG38: =AG330 -> 3.261839
C39: Interest (Expense) | F39: -1.495 | G39: -2.114 | H39: -2.419 | I39: -2.59 | J39: =SUM(F39:I39) -> -8.618 | K39: -2.896 | L39: -2.743 | M39: -2.748 | N39: -2.788 | O39: =SUM(K39:N39) -> -11.175 | P39: -2.947 | Q39: -2.704 | R39: -3.866 | S39: -3.815 | T39: =SUM(P39:S39) -> -13.332 | U39: -3.856 | V39: =V323 -> -2.5113342 | W39: =W323 -> -2.4982467 | X39: =X323 -> -2.4851592 | Y39: =SUM(U39:X39) -> -11.35074 | Z39: =Z323 -> -2.4720717 | AA39: =AA323 -> -2.4589842 | AB39: =AB323 -> -2.4458967 | AC39: =AC323 -> -2.4328092 | AD39: =SUM(Z39:AC39) -> -9.8097618 | AE39: =AE323 -> -9.6003618 | AF39: =AF323 -> -9.3909618 | AG39: =AG323 -> -9.1815618
C40: Goodwill Impairment | F40: 0 | G40: 0 | H40: 0 | I40: 0 | J40: =SUM(F40:I40) -> 0 | K40: 0 | L40: 0 | M40: 0 | N40: 0 | O40: =SUM(K40:N40) -> 0 | P40: 0 | Q40: 0 | R40: 0 | S40: 0 | T40: =SUM(P40:S40) -> 0 | U40: 0 | V40: 0 | W40: 0 | X40: 0 | Y40: =SUM(U40:X40) -> 0 | Z40: 0 | AA40: 0 | AB40: 0 | AC40: 0 | AD40: =SUM(Z40:AC40) -> 0 | AE40: 0 | AF40: 0 | AG40: 0
C41: Other Non-Operating Income (Expense) | F41: 6.416 | G41: 4.409 | H41: -24.834 | I41: 20.081 | J41: =SUM(F41:I41) -> 6.072 | K41: 13.024 | L41: 9.565 | M41: 0.186 | N41: 14.234 | O41: =SUM(K41:N41) -> 37.009 | P41: 19.328 | Q41: 11.108 | R41: 15.497 | S41: 5.043 | T41: =SUM(P41:S41) -> 50.976 | U41: 19.296 | V41: =V70*V28 -> 8.2759797 | W41: =W70*W28 -> 8.7845357 | X41: =X70*X28 -> 9.5209373 | Y41: =SUM(U41:X41) -> 45.877453 | Z41: =Z70*Z28 -> 13.471067 | AA41: =AA70*AA28 -> 14.279331 | AB41: =AB70*AB28 -> 11.216502 | AC41: =AC70*AC28 -> 11.734473 | AD41: =SUM(Z41:AC41) -> 50.701373 | AE41: =AE70*AE28 -> 62.436317 | AF41: =AF70*AF28 -> 65.870314 | AG41: =AG70*AG28 -> 70.171275
C42: Pre-Tax Income (Loss) | F42: =F36+SUM(F38:F41) -> 67.591 | G42: =G36+SUM(G38:G41) -> 73.184 | H42: =H36+SUM(H38:H41) -> 33.681 | I42: =I36+SUM(I38:I41) -> 68.024 | J42: =SUM(F42:I42) -> 242.48 | K42: =K36+SUM(K38:K41) -> 67.744 | L42: =L36+SUM(L38:L41) -> 66.359 | M42: =M36+SUM(M38:M41) -> 50.332 | N42: =N36+SUM(N38:N41) -> 97.224 | O42: =SUM(K42:N42) -> 281.659 | P42: =P36+SUM(P38:P41) -> 106.774 | Q42: =Q36+SUM(Q38:Q41) -> 77.094 | R42: =IF($C$8="On",R36+SUM(R38:R41),IF($C$8="off",R36+SUM(R40:R41),"N/A")) -> 90.151 | S42: =IF($C$8="On",S36+SUM(S38:S41),IF($C$8="off",S36+SUM(S40:S41),"N/A")) -> 88.258 | T42: =SUM(P42:S42) -> 362.277 | U42: =U36+SUM(U38:U41) -> 95.449 | V42: =IF($C$8="On",V36+SUM(V38:V41),IF($C$8="off",V36+SUM(V40:V41),"N/A")) -> 88.676192 | W42: =IF($C$8="On",W36+SUM(W38:W41),IF($C$8="off",W36+SUM(W40:W41),"N/A")) -> 94.214857 | X42: =IF($C$8="On",X36+SUM(X38:X41),IF($C$8="off",X36+SUM(X40:X41),"N/A")) -> 102.13031 | Y42: =SUM(U42:X42) -> 380.47035 | Z42: =IF($C$8="On",Z36+SUM(Z38:Z41),IF($C$8="off",Z36+SUM(Z40:Z41),"N/A")) -> 110.80528 | AA42: =IF($C$8="On",AA36+SUM(AA38:AA41),IF($C$8="off",AA36+SUM(AA40:AA41),"N/A")) -> 117.23476 | AB42: =IF($C$8="On",AB36+SUM(AB38:AB41),IF($C$8="off",AB36+SUM(AB40:AB41),"N/A")) -> 118.94771 | AC42: =IF($C$8="On",AC36+SUM(AC38:AC41),IF($C$8="off",AC36+SUM(AC40:AC41),"N/A")) -> 124.19266 | AD42: =SUM(Z42:AC42) -> 471.18041 | AE42: =IF($C$8="On",AE36+SUM(AE38:AE41),IF($C$8="off",AE36+SUM(AE40:AE41),"N/A")) -> 492.78336 | AF42: =IF($C$8="On",AF36+SUM(AF38:AF41),IF($C$8="off",AF36+SUM(AF40:AF41),"N/A")) -> 520.85844 | AG42: =IF($C$8="On",AG36+SUM(AG38:AG41),IF($C$8="off",AG36+SUM(AG40:AG41),"N/A")) -> 555.45047
C44: Income Tax Benefit (Expense) | F44: -11.488 | G44: -15.489 | H44: -11.788 | I44: -16.659 | J44: =SUM(F44:I44) -> -55.424 | K44: -16.4 | L44: -1.856 | M44: -15.8 | N44: -20.399 | O44: =SUM(K44:N44) -> -54.455 | P44: -19.687 | Q44: -1.172 | R44: -12.696 | S44: -14.954 | T44: =SUM(P44:S44) -> -48.509 | U44: -18.379 | V44: =-V71*V42 -> -20.838905 | W44: =-W71*W42 -> -22.140491 | X44: =-X71*X42 -> -24.000622 | Y44: =SUM(U44:X44) -> -85.359018 | Z44: =-Z71*Z42 -> -26.593268 | AA44: =-AA71*AA42 -> -28.136341 | AB44: =-AB71*AB42 -> -28.547451 | AC44: =-AC71*AC42 -> -29.806238 | AD44: =SUM(Z44:AC44) -> -113.0833 | AE44: =-AE71*AE42 -> -118.26801 | AF44: =-AF71*AF42 -> -125.00603 | AG44: =-AG71*AG42 -> -133.30811
C45: Net Income (Loss) | F45: =F42+F44 -> 56.103 | G45: =G42+G44 -> 57.695 | H45: =H42+H44 -> 21.893 | I45: =I42+I44 -> 51.365 | J45: =SUM(F45:I45) -> 187.056 | K45: =K42+K44 -> 51.344 | L45: =L42+L44 -> 64.503 | M45: =M42+M44 -> 34.532 | N45: =N42+N44 -> 76.825 | O45: =SUM(K45:N45) -> 227.204 | P45: =P42+P44 -> 87.087 | Q45: =Q42+Q44 -> 75.922 | R45: =R42+R44 -> 77.455 | S45: =S42+S44 -> 73.304 | T45: =SUM(P45:S45) -> 313.768 | U45: =U42+U44 -> 77.07 | V45: =V42+V44 -> 67.837287 | W45: =W42+W44 -> 72.074365 | X45: =X42+X44 -> 78.129684 | Y45: =SUM(U45:X45) -> 295.11134 | Z45: =Z42+Z44 -> 84.212015 | AA45: =AA42+AA44 -> 89.098414 | AB45: =AB42+AB44 -> 90.400262 | AC45: =AC42+AC44 -> 94.386421 | AD45: =SUM(Z45:AC45) -> 358.09711 | AE45: =AE42+AE44 -> 374.51536 | AF45: =AF42+AF44 -> 395.85242 | AG45: =AG42+AG44 -> 422.14236
C47: Pre-Tax Adjustments | F47: 0 | G47: 0 | H47: 0 | I47: 0 | J47: =SUM(F47:I47) -> 0 | K47: 0 | L47: 0 | M47: 0 | N47: 0 | O47: =SUM(K47:N47) -> 0 | P47: 0 | Q47: 0 | R47: 0 | S47: 0 | T47: =SUM(P47:S47) -> 0 | U47: 0 | V47: 0 | W47: 0 | X47: 0 | Y47: =SUM(U47:X47) -> 0 | Z47: 0 | AA47: 0 | AB47: 0 | AC47: 0 | AD47: =SUM(Z47:AC47) -> 0 | AE47: 0 | AF47: 0 | AG47: 0
C48: Post-Tax Adjustments | F48: 0 | G48: 0 | H48: 0 | I48: 0 | J48: =SUM(F48:I48) -> 0 | K48: 0 | L48: 0 | M48: 0 | N48: 0 | O48: =SUM(K48:N48) -> 0 | P48: 0 | Q48: 0 | R48: 0 | S48: 0 | T48: =SUM(P48:S48) -> 0 | U48: 0 | V48: 0 | W48: 0 | X48: 0 | Y48: =SUM(U48:X48) -> 0 | Z48: 0 | AA48: 0 | AB48: 0 | AC48: 0 | AD48: =SUM(Z48:AC48) -> 0 | AE48: 0 | AF48: 0 | AG48: 0
C49: Discontinued Operations | F49: 0 | G49: 0 | H49: 0 | I49: 0 | J49: =SUM(F49:I49) -> 0 | K49: 0 | L49: 0 | M49: 0 | N49: 0 | O49: =SUM(K49:N49) -> 0 | P49: 0 | Q49: 0 | R49: 0 | S49: 0 | T49: =SUM(P49:S49) -> 0 | U49: 0 | V49: 0 | W49: 0 | X49: 0 | Y49: =SUM(U49:X49) -> 0 | Z49: 0 | AA49: 0 | AB49: 0 | AC49: 0 | AD49: =SUM(Z49:AC49) -> 0 | AE49: 0 | AF49: 0 | AG49: 0
C50: Income (Loss) due to Non-Controlling Interest | F50: -22.642 | G50: -22.858 | H50: -12.215 | I50: -20.349 | J50: =SUM(F50:I50) -> -78.064 | K50: -20.346 | L50: -22.509 | M50: -15.026 | N50: -28.465 | O50: =SUM(K50:N50) -> -86.346 | P50: -28.123 | Q50: -20.94 | R50: -24.483 | S50: -22.805 | T50: =SUM(P50:S50) -> -96.351 | U50: -23.325 | V50: =V72*V154 -> -20.230173 | W50: =W72*W154 -> -21.47331 | X50: =X72*X154 -> -23.273402 | Y50: =SUM(U50:X50) -> -88.301885 | Z50: =Z72*Z154 -> -23.462108 | AA50: =AA72*AA154 -> -24.869835 | AB50: =AB72*AB154 -> -24.863247 | AC50: =AC72*AC154 -> -26.011415 | AD50: =SUM(Z50:AC50) -> -99.206604 | AE50: =AE72*AE154 -> -90.324538 | AF50: =AF72*AF154 -> -98.695687 | AG50: =AG72*AG154 -> -105.13996
C51: Adj. Net Income (Loss) | F51: =SUM(F45:F50) -> 33.461 | G51: =SUM(G45:G50) -> 34.837 | H51: =SUM(H45:H50) -> 9.678 | I51: =SUM(I45:I50) -> 31.016 | J51: =SUM(F51:I51) -> 108.992 | K51: =SUM(K45:K50) -> 30.998 | L51: =SUM(L45:L50) -> 41.994 | M51: =SUM(M45:M50) -> 19.506 | N51: =SUM(N45:N50) -> 48.36 | O51: =SUM(K51:N51) -> 140.858 | P51: =SUM(P45:P50) -> 58.964 | Q51: =SUM(Q45:Q50) -> 54.982 | R51: =SUM(R45:R50) -> 52.972 | S51: =SUM(S45:S50) -> 50.499 | T51: =SUM(P51:S51) -> 217.417 | U51: =SUM(U45:U50) -> 53.745 | V51: =SUM(V45:V50) -> 47.607114 | W51: =SUM(W45:W50) -> 50.601056 | X51: =SUM(X45:X50) -> 54.856282 | Y51: =SUM(U51:X51) -> 206.80945 | Z51: =SUM(Z45:Z50) -> 60.749907 | AA51: =SUM(AA45:AA50) -> 64.228579 | AB51: =SUM(AB45:AB50) -> 65.537015 | AC51: =SUM(AC45:AC50) -> 68.375007 | AD51: =SUM(Z51:AC51) -> 258.89051 | AE51: =SUM(AE45:AE50) -> 284.19082 | AF51: =SUM(AF45:AF50) -> 297.15673 | AG51: =SUM(AG45:AG50) -> 317.0024
C53: GAAP EPS (Basic) | F53: =(F45)/F283 -> 1.5163383 | G53: =(G45)/G283 -> 1.5593243 | H53: =(H45)/H283 -> 0.59130317 | I53: =(I45)/I283 -> 1.3860331 | J53: =J45/J283 -> 5.0475188 | K53: =(K45)/K283 -> 1.361657 | L53: =(L45)/L283 -> 1.7101384 | M53: =(M45)/M283 -> 0.91509434 | N53: =(N45)/N283 -> 2.0292937 | O53: =O45/O283 -> 6.0014792 | P53: =(P45)/P283 -> 2.1941799 | Q53: =(Q45)/Q283 -> 1.9123929 | R53: =(R45)/R283 -> 1.9510076 | S53: =(S45)/S283 -> 1.837193 | T53: =T45/T283 -> 7.8638596 | U53: =(U45)/U283 -> 1.8629442 | V53: =V45/V283 -> 1.63977 | W53: =W45/W283 -> 1.7421892 | X53: =X45/X283 -> 1.8953385 | Y53: =Y45/Y283 -> 7.1398471 | Z53: =Z45/Z283 -> 2.050249 | AA53: =AA45/AA283 -> 2.1692147 | AB53: =AB45/AB283 -> 2.2009098 | AC53: =AC45/AC283 -> 2.3062668 | ... AG53: =AG45/AG283 -> 10.543493
C54: GAAP EPS (Diluted) | F54: =(F45)/F285 -> 1.0447486 | G54: =(G45)/G285 -> 1.0734952 | H54: =(H45)/H285 -> 0.4071677 | I54: =(I45)/I285 -> 0.95655332 | J54: =J45/J285 -> 3.4834817 | K54: =(K45)/K285 -> 0.95187245 | L54: =(L45)/L285 -> 1.1958287 | M54: =(M45)/M285 -> 0.63963547 | N54: =(N45)/N285 -> 1.4253247 | O54: =O45/O285 -> 4.2152876 | P54: =(P45)/P285 -> 1.6112303 | Q54: =(Q45)/Q285 -> 1.401292 | R54: =(R45)/R285 -> 1.4238051 | S54: =(S45)/S285 -> 1.8189578 | T54: =T45/T285 -> 7.7858065 | U54: =(U45)/U285 -> 1.4149073 | V54: =V45/V285 -> 1.2454064 | W54: =W45/W285 -> 1.3231938 | X54: =X45/X285 -> 1.4382691 | Y54: =Y45/Y285 -> 5.4215514 | Z54: =Z45/Z285 -> 1.5544717 | AA54: =AA45/AA285 -> 1.6446699 | AB54: =AB45/AB285 -> 1.6687007 | AC54: =AC45/AC285 -> 1.7470535 | ... AG54: =AG45/AG285 -> 7.9442369
C56: Adj. EPS (Basic) | F56: =F51/F283 -> 0.90437579 | G56: =G51/G283 -> 0.94154054 | H56: =H51/H283 -> 0.26139095 | I56: =I51/I283 -> 0.8369357 | J56: =J51/J283 -> 2.94104 | K56: =K51/K283 -> 0.82207548 | L56: =L51/L283 -> 1.1133676 | M56: =M51/M283 -> 0.51690693 | ... AG56: =AG51/AG283 -> 7.917501
C57: Adj. EPS (Diluted) | F57: =F51/F285 -> 0.62310987 | G57: =G51/G285 -> 0.64819053 | H57: =H51/H285 -> 0.17999219 | I57: =I51/I285 -> 0.57760066 | J57: =J51/J285 -> 2.0297218 | K57: =K51/K285 -> 0.57467557 | L57: =L51/L285 -> 0.7785317 | M57: =M51/M285 -> 0.3613092 | ... AG57: =AG51/AG285 -> 5.965623
C59: EBIT | F59: =F51-F44-F41-F40-F39-F38 -> 39.86 | G59: =G51-G44-G41-G40-G39-G38 -> 46.924 | H59: =H51-H44-H41-H40-H39-H38 -> 46.166 | I59: =I51-I44-I41-I40-I39-I38 -> 28.898 | J59: =SUM(F59:I59) -> 161.848 | K59: =K51-K44-K41-K40-K39-K38 -> 34.593 | L59: =L51-L44-L41-L40-L39-L38 -> 33.088 | M59: =M51-M44-M41-M40-M39-M38 -> 36.368 | N59: =N51-N44-N41-N40-N39-N38 -> 55.422 | O59: =SUM(K59:N59) -> 159.471 | P59: =P51-P44-P41-P40-P39-P38 -> 61.488 | Q59: =Q51-Q44-Q41-Q40-Q39-Q38 -> 46.252 | R59: =R51-R44-R41-R40-R39-R38 -> 51.239 | S59: =S51-S44-S41-S40-S39-S38 -> 61.223 | T59: =SUM(P59:S59) -> 220.202 | U59: =U51-U44-U41-U40-U39-U38 -> 53.65 | V59: =V51-V44-V41-V40-V39-V38 -> 59.403143 | W59: =W51-W44-W41-W40-W39-W38 -> 63.053445 | X59: =X51-X44-X41-X40-X39-X38 -> 68.339172 | Y59: =SUM(U59:X59) -> 244.44576 | Z59: =Z51-Z44-Z41-Z40-Z39-Z38 -> 73.080538 | AA59: =AA51-AA44-AA41-AA40-AA39-AA38 -> 77.465371 | AB59: =AB51-AB44-AB41-AB40-AB39-AB38 -> 82.316664 | AC59: =AC51-AC44-AC41-AC40-AC39-AC38 -> 86.117992 | AD59: =SUM(Z59:AC59) -> 318.98056 | AE59: =AE51-AE44-AE41-AE40-AE39-AE38 -> 346.72968 | AF59: =AF51-AF44-AF41-AF40-AF39-AF38 -> 362.39651 | AG59: =AG51-AG44-AG41-AG40-AG39-AG38 -> 386.05896
C60: Depreciation & Amortization | F60: =-F34 -> 0 | G60: =-G34 -> 0 | H60: =-H34 -> 0 | I60: =-I34 -> 0 | J60: =SUM(F60:I60) -> 0 | K60: =-K34 -> 0 | L60: =-L34 -> 0 | M60: =-M34 -> 0 | N60: =-N34 -> 0 | O60: =SUM(K60:N60) -> 0 | P60: =-P34 -> 0 | Q60: =-Q34 -> 0 | R60: =-R34 -> 0 | S60: =-S34 -> 0 | T60: =SUM(P60:S60) -> 0 | U60: =-U34 -> 0 | V60: =-V34 -> 0 | W60: =-W34 -> 0 | X60: =-X34 -> 0 | Y60: =SUM(U60:X60) -> 0 | Z60: =-Z34 -> 0 | AA60: =-AA34 -> 0 | AB60: =-AB34 -> 0 | AC60: =-AC34 -> 0 | AD60: =SUM(Z60:AC60) -> 0 | AE60: =-AE34 -> 0 | AF60: =-AF34 -> 0 | AG60: =-AG34 -> 0
C61: EBITDA | F61: =SUM(F59:F60) -> 39.86 | G61: =SUM(G59:G60) -> 46.924 | H61: =SUM(H59:H60) -> 46.166 | I61: =SUM(I59:I60) -> 28.898 | J61: =SUM(F61:I61) -> 161.848 | K61: =SUM(K59:K60) -> 34.593 | L61: =SUM(L59:L60) -> 33.088 | M61: =SUM(M59:M60) -> 36.368 | N61: =SUM(N59:N60) -> 55.422 | O61: =SUM(K61:N61) -> 159.471 | P61: =SUM(P59:P60) -> 61.488 | Q61: =SUM(Q59:Q60) -> 46.252 | R61: =SUM(R59:R60) -> 51.239 | S61: =SUM(S59:S60) -> 61.223 | T61: =SUM(P61:S61) -> 220.202 | U61: =SUM(U59:U60) -> 53.65 | V61: =SUM(V59:V60) -> 59.403143 | W61: =SUM(W59:W60) -> 63.053445 | X61: =SUM(X59:X60) -> 68.339172 | Y61: =SUM(U61:X61) -> 244.44576 | Z61: =SUM(Z59:Z60) -> 73.080538 | AA61: =SUM(AA59:AA60) -> 77.465371 | AB61: =SUM(AB59:AB60) -> 82.316664 | AC61: =SUM(AC59:AC60) -> 86.117992 | AD61: =SUM(Z61:AC61) -> 318.98056 | AE61: =SUM(AE59:AE60) -> 346.72968 | AF61: =SUM(AF59:AF60) -> 362.39651 | AG61: =SUM(AG59:AG60) -> 386.05896
C63: Income Statement Analysis | F63: =F$25 -> 1Q23 | G63: =G$25 -> 2Q23 | H63: =H$25 -> 3Q23 | I63: =I$25 -> 4Q23 | J63: =J$25 -> 2023 | K63: =K$25 -> 1Q24 | L63: =L$25 -> 2Q24 | M63: =M$25 -> 3Q24 | ... AG63: =AG$25 -> 2030e | AH63: x
A64: x | C64: Drivers
C66: Gross Margin | F66: =F30/F28 -> 1 | G66: =G30/G28 -> 1 | H66: =H30/H28 -> 1 | I66: =I30/I28 -> 1 | J66: =J30/J28 -> 1 | K66: =K30/K28 -> 1 | L66: =L30/L28 -> 1 | M66: =M30/M28 -> 1 | ... U66: =U30/U28 -> 1 | V66: =IF(Cover!$F$37="Bottom Up",(V30/V28),Drivers!V7) -> 1 | W66: =IF(Cover!$F$37="Bottom Up",(W30/W28),Drivers!W7) -> 1 | X66: =IF(Cover!$F$37="Bottom Up",(X30/X28),Drivers!X7) -> 1 | Y66: =Y30/Y28 -> 1 | Z66: =IF(Cover!$F$37="Bottom Up",(Z30/Z28),Drivers!Z7) -> 1 | AA66: =IF(Cover!$F$37="Bottom Up",(AA30/AA28),Drivers!AA7) -> 1 | AB66: =IF(Cover!$F$37="Bottom Up",(AB30/AB28),Drivers!AB7) -> 1 | AC66: =IF(Cover!$F$37="Bottom Up",(AC30/AC28),Drivers!AC7) -> 1 | AD66: =AD30/AD28 -> 1 | AE66: =IF(Cover!$F$37="Bottom Up",(AE30/AE28),Drivers!AE7) -> 1 | AF66: =IF(Cover!$F$37="Bottom Up",(AF30/AF28),Drivers!AF7) -> 1 | AG66: =IF(Cover!$F$37="Bottom Up",(AG30/AG28),Drivers!AG7) -> 1
C67: SG&A as % of Revenue | F67: =F32/F28 -> -0.15359127 | G67: =G32/G28 -> -0.15149105 | H67: =H32/H28 -> -0.18113068 | I67: =I32/I28 -> -0.2071497 | J67: =J32/J28 -> -0.17102503 | K67: =K32/K28 -> -0.20789846 | L67: =L32/L28 -> -0.1997935 | M67: =M32/M28 -> -0.19290459 | ... U67: =U32/U28 -> -0.16723877 | V67: =Drivers!V40 -> -0.172 | W67: =Drivers!W40 -> -0.172 | X67: =Drivers!X40 -> -0.172 | Y67: =Y32/Y28 -> -0.17090723 | Z67: =Drivers!Z40 -> -0.175 | AA67: =Drivers!AA40 -> -0.175 | AB67: =Drivers!AB40 -> -0.175 | AC67: =Drivers!AC40 -> -0.175 | AD67: =AD32/AD28 -> -0.175 | AE67: =Drivers!AE40 -> -0.175 | AF67: =Drivers!AF40 -> -0.175 | AG67: =Drivers!AG40 -> -0.175
C68: Compensation and Benefit as a % of Revenue | F68: =F33/F28 -> -0.38516999 | G68: =G33/G28 -> -0.39355335 | H68: =H33/H28 -> -0.3594441 | I68: =I33/I28 -> -0.35621697 | J68: =J33/J28 -> -0.37524326 | K68: =K33/K28 -> -0.35271959 | L68: =L33/L28 -> -0.362007 | M68: =M33/M28 -> -0.39680994 | ... U68: =U33/U28 -> -0.39529888 | V68: =Drivers!V45 -> -0.395 | W68: =Drivers!W45 -> -0.395 | X68: =Drivers!X45 -> -0.395 | Y68: =Y33/Y28 -> -0.3950686 | Z68: =Drivers!Z45 -> -0.395 | AA68: =Drivers!AA45 -> -0.395 | AB68: =Drivers!AB45 -> -0.395 | AC68: =Drivers!AC45 -> -0.395 | AD68: =AD33/AD28 -> -0.395 | AE68: =Drivers!AE45 -> -0.405 | AF68: =Drivers!AF45 -> -0.405 | AG68: =Drivers!AG45 -> -0.405
C69: Other Operating Income as a % of Revenue | F69: =F35/F28 -> 0 | G69: =G35/G28 -> 0 | H69: =H35/H28 -> 0 | I69: =I35/I28 -> 0 | J69: =J35/J28 -> 0 | K69: =K35/K28 -> 0 | L69: =L35/L28 -> 0 | M69: =M35/M28 -> 0 | ... U69: =U35/U28 -> 0 | V69: =Drivers!V50 -> 0 | W69: =Drivers!W50 -> 0 | X69: =Drivers!X50 -> 0 | Y69: =Y35/Y28 -> 0 | Z69: =Drivers!Z50 -> 0 | AA69: =Drivers!AA50 -> 0 | AB69: =Drivers!AB50 -> 0 | AC69: =Drivers!AC50 -> 0 | AD69: =AD35/AD28 -> 0 | AE69: =Drivers!AE50 -> 0 | AF69: =Drivers!AF50 -> 0 | AG69: =Drivers!AG50 -> 0
C70: Other Non-Operating Income as a % of Revenue | F70: =F41/F28 -> 0.047347409 | G70: =G41/G28 -> 0.028745224 | H70: =H41/H28 -> -0.19542943 | I70: =I41/I28 -> 0.17804199 | J70: =J41/J28 -> 0.011483623 | K70: =K41/K28 -> 0.10416117 | L70: =L41/L28 -> 0.075388568 | M70: =M41/M28 -> 0.001484864 | ... U70: =U41/U28 -> 0.10966253 | V70: =Drivers!V57 -> 0.045 | W70: =Drivers!W57 -> 0.045 | X70: =Drivers!X57 -> 0.045 | Y70: =Y41/Y28 -> 0.059840914 | Z70: =Drivers!Z57 -> 0.06 | AA70: =Drivers!AA57 -> 0.06 | AB70: =Drivers!AB57 -> 0.045 | AC70: =Drivers!AC57 -> 0.045 | AD70: =AD41/AD28 -> 0.052133571 | AE70: =Drivers!AE57 -> 0.06 | AF70: =Drivers!AF57 -> 0.06 | AG70: =Drivers!AG57 -> 0.06
C71: Tax Rate | F71: =-F44/F42 -> 0.16996346 | G71: =-G44/G42 -> 0.21164462 | H71: =-H44/H42 -> 0.34998961 | I71: =-I44/I42 -> 0.24489886 | J71: =-J44/J42 -> 0.22857143 | K71: =-K44/K42 -> 0.24208786 | L71: =-L44/L42 -> 0.027969077 | M71: =-M44/M42 -> 0.3139156 | ... U71: =-U44/U42 -> 0.19255309 | V71: =Drivers!V62 -> 0.235 | W71: =Drivers!W62 -> 0.235 | X71: =Drivers!X62 -> 0.235 | Y71: =-Y44/Y42 -> 0.2243513 | Z71: =Drivers!Z62 -> 0.24 | AA71: =Drivers!AA62 -> 0.24 | AB71: =Drivers!AB62 -> 0.24 | AC71: =Drivers!AC62 -> 0.24 | AD71: =-AD44/AD42 -> 0.24 | AE71: =Drivers!AE62 -> 0.24 | AF71: =Drivers!AF62 -> 0.24 | AG71: =Drivers!AG62 -> 0.24
C72: Income (Loss) due to NCI as a% of NCI | F72: =F50/F154 -> -0.056822773 | G72: =G50/G154 -> -0.055723494 | H72: =H50/H154 -> -0.090282859 | I72: =I50/I154 -> -0.12818429 | J72: =J50/J154 -> -0.49174793 | K72: =K50/K154 -> -0.098322154 | L72: =L50/L154 -> -0.070550513 | M72: =M50/M154 -> -0.09622244 | ... T72: =T50/T154 -> -0.46633336 | U72: =U50/U28 -> -0.13256004 | V72: =Drivers!V67 -> -0.1 | W72: =Drivers!W67 -> -0.1 | X72: =Drivers!X67 -> -0.1 | Y72: =Y50/Y154 -> -0.37941115 | Z72: =Drivers!Z67 -> -0.095 | AA72: =Drivers!AA67 -> -0.095 | AB72: =Drivers!AB67 -> -0.095 | AC72: =Drivers!AC67 -> -0.095 | AD72: =AD50/AD154 -> -0.3623266 | AE72: =Drivers!AE67 -> -0.31 | AF72: =Drivers!AF67 -> -0.31 | AG72: =Drivers!AG67 -> -0.31
A74: x | C74: Cash Flow Statement | F74: =F$25 -> 1Q23 | G74: =G$63 -> 2Q23 | H74: =H$63 -> 3Q23 | I74: =I$63 -> 4Q23 | J74: =J$63 -> 2023 | K74: =K$63 -> 1Q24 | L74: =L$63 -> 2Q24 | M74: =M$63 -> 3Q24 | N74: =N$63 -> 4Q24 | ... AG74: =AG$63 -> 2030e | AH74: x
C76: Net Income | V76: =V45 -> 67.837287 | W76: =W45 -> 72.074365 | X76: =X45 -> 78.129684 | Y76: =Y45 -> 295.11134 | Z76: =Z45 -> 84.212015 | AA76: =AA45 -> 89.098414 | AB76: =AB45 -> 90.400262 | AC76: =AC45 -> 94.386421 | ... AG76: =AG45 -> 422.14236
C77: Depreciation & Amortization | V77: =-(V195+V209) -> 0 | W77: =-(W195+W209) -> 0 | X77: =-(X195+X209) -> 0 | Y77: =SUM(U77:X77) -> 0 | Z77: =-(Z195+Z209) -> 0 | AA77: =-(AA195+AA209) -> 0 | AB77: =-(AB195+AB209) -> 0 | AC77: =-(AC195+AC209) -> 0 | AD77: =SUM(Z77:AC77) -> 0 | AE77: =-(AE195+AE209) -> 0 | AF77: =-(AF195+AF209) -> 0 | AG77: =-(AG195+AG209) -> 0
C78: Income (Loss) due to NCI | V78: 0 | W78: 0 | X78: 0 | Y78: =SUM(U78:X78) -> 0 | Z78: 0 | AA78: 0 | AB78: 0 | AC78: 0 | AD78: =SUM(Z78:AC78) -> 0 | AE78: 0 | AF78: 0 | AG78: 0
C79: Stock-Based Compensation | V79: =V247 -> 3.3686678 | W79: =W247 -> 3.5756713 | X79: =X247 -> 3.8754174 | Y79: =SUM(U79:X79) -> 10.819757 | Z79: =Z247 -> 4.1124633 | AA79: =AA247 -> 4.3592111 | AB79: =AB247 -> 4.5655828 | AC79: =AC247 -> 4.7764183 | AD79: =SUM(Z79:AC79) -> 17.813675 | AE79: =AE247 -> 19.060633 | AF79: =AF247 -> 20.108968 | AG79: =AG247 -> 21.42197
C80: (Increase)/Decrease in Working Capital | V80: =V175 -> 2.6697187 | W80: =W175 -> -2.8660016 | X80: =X175 -> -6.5637752 | Y80: =SUM(U80:X80) -> -6.7600581 | Z80: =Z175 -> -20.452066 | AA80: =AA175 -> -7.0642571 | AB80: =AB175 -> -2.853111 | AC80: =AC175 -> -5.3213586 | AD80: =SUM(Z80:AC80) -> -35.690792 | AE80: =AE175 -> 31.104561 | AF80: =AF175 -> -10.935265 | AG80: =AG175 -> -6.554546
C81: (Increase)/Decrease in LT Items | V81: =V227 -> 12.373538 | W81: =W227 -> -7.9108715 | X81: =X227 -> -11.455136 | Y81: =SUM(U81:X81) -> -6.9924696 | Z81: =Z227 -> -9.0589782 | AA81: =AA227 -> -9.4297469 | AB81: =AB227 -> -7.8867289 | AC81: =AC227 -> -8.0573188 | AD81: =SUM(Z81:AC81) -> -34.432773 | AE81: =AE227 -> -33.389353 | AF81: =AF227 -> -11.875908 | AG81: =AG227 -> -14.874155
C82: Net Cash From Operating Activities | V82: =SUM(V76:V81) -> 86.249211 | W82: =SUM(W76:W81) -> 64.873164 | X82: =SUM(X76:X81) -> 63.98619 | Y82: =SUM(U82:X82) -> 215.10856 | Z82: =SUM(Z76:Z81) -> 58.813435 | AA82: =SUM(AA76:AA81) -> 76.963621 | AB82: =SUM(AB76:AB81) -> 84.226005 | AC82: =SUM(AC76:AC81) -> 85.784162 | AD82: =SUM(Z82:AC82) -> 305.78722 | AE82: =SUM(AE76:AE81) -> 391.2912 | AF82: =SUM(AF76:AF81) -> 393.15021 | AG82: =SUM(AG76:AG81) -> 422.13563
C84: Capital Expenditures | V84: =-V194 -> -2.2069279 | W84: =-W194 -> -2.3425429 | X84: =-X194 -> -2.1157639 | Y84: =SUM(U84:X84) -> -6.6652346 | Z84: =-Z194 -> -1.7961423 | AA84: =-AA194 -> -1.9039108 | AB84: =-AB194 -> -1.9940448 | AC84: =-AC194 -> -2.0861285 | AD84: =SUM(Z84:AC84) -> -7.7802264 | AE84: =-AE194 -> -8.3248422 | AF84: =-AF194 -> -8.7827086 | AG84: =-AG194 -> -9.35617
C85: Purchases of Investments | V85: =U211-V211 -> -28.35114 | W85: =V211-W211 -> -29.201674 | X85: =W211-X211 -> -30.077724 | Y85: =SUM(U85:X85) -> -87.630539 | Z85: =Y211-Z211 -> -72.286798 | AA85: =Z211-AA211 -> -66.29732 | AB85: =AA211-AB211 -> -64.418896 | AC85: =AB211-AC211 -> -61.783578 | AD85: =SUM(Z85:AC85) -> -264.78659 | AE85: =AD211-AE211 -> -194.61827 | AF85: =AE211-AF211 -> -223.81101 | AG85: =AF211-AG211 -> -257.38266
C86: Proceeds From/(Acquisitions of) Businesses | V86: =Drivers!V105 -> 0 | W86: =Drivers!W105 -> 0 | X86: =Drivers!X105 -> 0 | Y86: =SUM(U86:X86) -> 0 | Z86: =Drivers!Z105 -> 0 | AA86: =Drivers!AA105 -> 0 | AB86: =Drivers!AB105 -> 0 | AC86: =Drivers!AC105 -> 0 | AD86: =SUM(Z86:AC86) -> 0 | AE86: =Drivers!AE105 -> 0 | AF86: =Drivers!AF105 -> 0 | AG86: =Drivers!AG105 -> 0
C87: Net Cash From Investment Activities | V87: =SUM(V84:V86) -> -30.558068 | W87: =SUM(W84:W86) -> -31.544217 | X87: =SUM(X84:X86) -> -32.193488 | Y87: =SUM(U87:X87) -> -94.295773 | Z87: =SUM(Z84:Z86) -> -74.08294 | AA87: =SUM(AA84:AA86) -> -68.201231 | AB87: =SUM(AB84:AB86) -> -66.412941 | AC87: =SUM(AC84:AC86) -> -63.869706 | AD87: =SUM(Z87:AC87) -> -272.56682 | AE87: =SUM(AE84:AE86) -> -202.94311 | AF87: =SUM(AF84:AF86) -> -232.59372 | AG87: =SUM(AG84:AG86) -> -266.73883
C89: Cash Flow Available for Financing Activities | V89: =SUM(V82,V87) -> 55.691143 | W89: =SUM(W82,W87) -> 33.328947 | X89: =SUM(X82,X87) -> 31.792702 | Y89: =SUM(U89:X89) -> 120.81279 | Z89: =SUM(Z82,Z87) -> -15.269505 | AA89: =SUM(AA82,AA87) -> 8.7623901 | AB89: =SUM(AB82,AB87) -> 17.813064 | AC89: =SUM(AC82,AC87) -> 21.914456 | AD89: =SUM(Z89:AC89) -> 33.220404 | AE89: =SUM(AE82,AE87) -> 188.34809 | AF89: =SUM(AF82,AF87) -> 160.55649 | AG89: =SUM(AG82,AG87) -> 155.3968
C91: Issuance/(Repayment) of Revolver | V91: =V304 -> 0 | W91: =W304 -> 0 | X91: =X304 -> 0 | Y91: =Y304 -> 0 | Z91: =Z304 -> 0 | AA91: =AA304 -> 0 | AB91: =AB304 -> 0 | AC91: =AC304 -> 0 | ... AG91: =AG304 -> 0
C92: Issuance of Debt | V92: =V309 -> 0 | W92: =W309 -> 0 | X92: =X309 -> 0 | Y92: =SUM(U92:X92) -> 0 | Z92: =Z309 -> 0 | AA92: =AA309 -> 0 | AB92: =AB309 -> 0 | AC92: =AC309 -> 0 | AD92: =SUM(Z92:AC92) -> 0 | AE92: =AE309 -> 0 | AF92: =AF309 -> 0 | AG92: =AG309 -> 0
C93: (Repayment of Debt) | V93: =V310 -> -1.5 | W93: =W310 -> -1.5 | X93: =X310 -> -1.5 | Y93: =SUM(U93:X93) -> -4.5 | Z93: =Z310 -> -1.5 | AA93: =AA310 -> -1.5 | AB93: =AB310 -> -1.5 | AC93: =AC310 -> -1.5 | AD93: =SUM(Z93:AC93) -> -6 | AE93: =AE310 -> -6 | AF93: =AF310 -> -6 | AG93: =AG310 -> -6
C94: Issuance of Equity | V94: =V246 -> 0 | W94: =W246 -> 0 | X94: =X246 -> 0 | Y94: =SUM(U94:X94) -> 0 | Z94: =Z246 -> 0 | AA94: =AA246 -> 0 | AB94: =AB246 -> 0 | AC94: =AC246 -> 0 | AD94: =SUM(Z94:AC94) -> 0 | AE94: =AE246 -> 0 | AF94: =AF246 -> 0 | AG94: =AG246 -> 0
C95: (Repurchase) of Equity | V95: =-V242 -> 0 | W95: =-W242 -> 0 | X95: =-X242 -> -35 | Y95: =SUM(U95:X95) -> -35 | Z95: =-Z242 -> 0 | AA95: =-AA242 -> 0 | AB95: =-AB242 -> 0 | AC95: =-AC242 -> -35 | AD95: =SUM(Z95:AC95) -> -35 | AE95: =-AE242 -> -35 | AF95: =-AF242 -> -35 | AG95: =-AG242 -> -35
C96: Dividends Issued | V96: =-V268 -> -22.425 | W96: =-W268 -> -22.31 | X96: =-X268 -> -22.42155 | Y96: =SUM(U96:X96) -> -67.15655 | Z96: =-Z268 -> -23.26795 | AA96: =-AA268 -> -25.78875 | AB96: =-AB268 -> -25.6565 | AC96: =-AC268 -> -25.784782 | AD96: =SUM(Z96:AC96) -> -100.49798 | AE96: =-AE268 -> -115.57268 | AF96: =-AF268 -> -132.90858 | AG96: =-AG268 -> -152.84487
C97: Change in Noncontrolling Interests | V97: =V154-U154 -> -33.943274 | W97: =W154-V154 -> 12.431369 | X97: =X154-W154 -> 18.000928 | Y97: =SUM(U97:X97) -> -3.5109763 | Z97: =Z154-Y154 -> 14.235537 | AA97: =AA154-Z154 -> 14.818174 | AB97: =AB154-AA154 -> -0.069349129 | AC97: =AC154-AB154 -> 12.085978 | AD97: =SUM(Z97:AC97) -> 41.07034 | AE97: =AE154-AD154 -> 17.565114 | AF97: =AF154-AE154 -> 27.003707 | AG97: =AG154-AF154 -> 20.787976
C98: Net Cash From Financing Activities | V98: =SUM(V91:V97) -> -57.868274 | W98: =SUM(W91:W97) -> -11.378631 | X98: =SUM(X91:X97) -> -40.920622 | Y98: =SUM(U98:X98) -> -110.16753 | Z98: =SUM(Z91:Z97) -> -10.532413 | AA98: =SUM(AA91:AA97) -> -12.470576 | AB98: =SUM(AB91:AB97) -> -27.225849 | AC98: =SUM(AC91:AC97) -> -50.198804 | AD98: =SUM(Z98:AC98) -> -100.42764 | AE98: =SUM(AE91:AE97) -> -139.00757 | AF98: =SUM(AF91:AF97) -> -146.90487 | AG98: =SUM(AG91:AG97) -> -173.05689
C100: Effect of FX Rate Changes on Cash | V100: =Drivers!V119 -> 0 | W100: =Drivers!W119 -> 0 | X100: =Drivers!X119 -> 0 | Y100: =SUM(U100:X100) -> 0 | Z100: =Drivers!Z119 -> 0 | AA100: =Drivers!AA119 -> 0 | AB100: =Drivers!AB119 -> 0 | AC100: =Drivers!AC119 -> 0 | AD100: =SUM(Z100:AC100) -> 0 | AE100: =Drivers!AE119 -> 0 | AF100: =Drivers!AF119 -> 0 | AG100: =Drivers!AG119 -> 0
C101: Beginning Cash Adjustments | V101: 0 | W101: 0 | X101: 0 | Y101: =SUM(U101:X101) -> 0 | Z101: 0 | AA101: 0 | AB101: 0 | AC101: 0 | AD101: =SUM(Z101:AC101) -> 0 | AE101: 0 | AF101: 0 | AG101: 0
C102: Ending Cash Adjustments | V102: 0 | W102: 0 | X102: 0 | Y102: =SUM(U102:X102) -> 0 | Z102: 0 | AA102: 0 | AB102: 0 | AC102: 0 | AD102: =SUM(Z102:AC102) -> 0 | AE102: 0 | AF102: 0 | AG102: 0
C104: Beginning Cash Balance | V104: =U106+V101 -> 263.347 | W104: =V106+W101 -> 261.16987 | X104: =W106+X101 -> 283.12019 | Y104: =V104 -> 263.347 | Z104: =Y106+Z101 -> 273.99227 | AA104: =Z106+AA101 -> 248.19035 | AB104: =AA106+AB101 -> 244.48216 | AC104: =AB106+AC101 -> 235.06938 | AD104: =Z104 -> 273.99227 | AE104: =AD106+AE101 -> 206.78503 | AF104: =AE106+AF101 -> 256.12555 | AG104: =AF106+AG101 -> 269.77717
C105: Net Change in Cash | V105: =SUM(V89,V98,V100,V102) -> -2.1771308 | W105: =SUM(W89,W98,W100,W102) -> 21.950316 | X105: =SUM(X89,X98,X100,X102) -> -9.1279202 | Y105: =SUM(U105:X105) -> 10.645265 | Z105: =SUM(Z89,Z98,Z100,Z102) -> -25.801918 | AA105: =SUM(AA89,AA98,AA100,AA102) -> -3.7081863 | AB105: =SUM(AB89,AB98,AB100,AB102) -> -9.4127854 | AC105: =SUM(AC89,AC98,AC100,AC102) -> -28.284348 | AD105: =SUM(Z105:AC105) -> -67.207238 | AE105: =SUM(AE89,AE98,AE100,AE102) -> 49.34052 | AF105: =SUM(AF89,AF98,AF100,AF102) -> 13.651619 | AG105: =SUM(AG89,AG98,AG100,AG102) -> -17.660095
C106: Ending Cash Balance | U106: =U122 -> 263.347 | V106: =SUM(V104:V105) -> 261.16987 | W106: =SUM(W104:W105) -> 283.12019 | X106: =SUM(X104:X105) -> 273.99227 | Y106: =SUM(Y104:Y105) -> 273.99227 | Z106: =SUM(Z104:Z105) -> 248.19035 | AA106: =SUM(AA104:AA105) -> 244.48216 | AB106: =SUM(AB104:AB105) -> 235.06938 | AC106: =SUM(AC104:AC105) -> 206.78503 | ... AG106: =SUM(AG104:AG105) -> 252.11707
A108: x | C108: Free Cash Flow Analysis | AH108: x
C110: Net Income | F110: =F45 -> 56.103 | G110: =G45 -> 57.695 | H110: =H45 -> 21.893 | I110: =I45 -> 51.365 | J110: =J45 -> 187.056 | K110: =K45 -> 51.344 | L110: =L45 -> 64.503 | M110: =M45 -> 34.532 | ... AG110: =AG45 -> 422.14236
C111: Depreciation & Amortization | F111: =-F195+-F209 -> 0 | G111: =-G195+-G209 -> 0 | H111: =-H195+-H209 -> 0 | I111: =-I195+-I209 -> 0 | J111: =SUM(F111:I111) -> 0 | K111: =-K195+-K209 -> 0 | L111: =-L195+-L209 -> 0 | M111: =-M195+-M209 -> 0 | N111: =-N195+-N209 -> 0 | O111: =SUM(K111:N111) -> 0 | P111: =-P195+-P209 -> 0 | Q111: =-Q195+-Q209 -> 0 | R111: =-R195+-R209 -> 0 | S111: =-S195+-S209 -> 0 | T111: =SUM(P111:S111) -> 0 | U111: =-U195+-U209 -> 0 | V111: =-V195+-V209 -> 0 | W111: =-W195+-W209 -> 0 | X111: =-X195+-X209 -> 0 | Y111: =SUM(U111:X111) -> 0 | Z111: =-Z195+-Z209 -> 0 | AA111: =-AA195+-AA209 -> 0 | AB111: =-AB195+-AB209 -> 0 | AC111: =-AC195+-AC209 -> 0 | AD111: =SUM(Z111:AC111) -> 0 | AE111: =-AE195+-AE209 -> 0 | AF111: =-AF195+-AF209 -> 0 | AG111: =-AG195+-AG209 -> 0
C112: Change in Operating Working Capital | F112: =F179 -> 0 | G112: =G179 -> 4.142 | H112: =H179 -> 4.475 | I112: =I179 -> -7.448 | J112: =SUM(F112:I112) -> 1.169 | K112: =K179 -> -17.709 | L112: =L179 -> 2.032 | M112: =M179 -> -6.18 | N112: =N179 -> -39.348 | O112: =SUM(K112:N112) -> -61.205 | P112: =P179 -> -32.63 | Q112: =Q179 -> 47.337 | R112: =R179 -> -41.293 | S112: =S179 -> -45.57 | T112: =SUM(P112:S112) -> -72.156 | U112: =U179 -> 24.389 | V112: =V179 -> -1.803228 | W112: =W179 -> -7.6543391 | X112: =X179 -> -13.497405 | Y112: =SUM(U112:X112) -> 1.4340275 | Z112: =Z179 -> -29.235747 | AA112: =AA179 -> -12.969973 | AB112: =AB179 -> -7.7924566 | AC112: =AC179 -> -10.367542 | AD112: =SUM(Z112:AC112) -> -60.365719 | AE112: =AE179 -> 21.592374 | AF112: =AF179 -> -17.746026 | AG112: =AG179 -> -15.084784
C113: Capital Expenditures | F113: =-F194 -> 0 | G113: =-G194 -> 0.61 | H113: =-H194 -> 1.57 | I113: =-I194 -> 0.748 | J113: =SUM(F113:I113) -> 2.928 | K113: =-K194 -> -4.004 | L113: =-L194 -> -1.601 | M113: =-M194 -> -0.464 | N113: =-N194 -> 1.383 | O113: =SUM(K113:N113) -> -4.686 | P113: =-P194 -> 0.353 | Q113: =-Q194 -> -0.17 | R113: =-R194 -> -2.118 | S113: =-S194 -> -1.626 | T113: =SUM(P113:S113) -> -3.561 | U113: =-U194 -> 2.322 | V113: =-V194 -> -2.2069279 | W113: =-W194 -> -2.3425429 | X113: =-X194 -> -2.1157639 | Y113: =SUM(U113:X113) -> -4.3432346 | Z113: =-Z194 -> -1.7961423 | AA113: =-AA194 -> -1.9039108 | AB113: =-AB194 -> -1.9940448 | AC113: =-AC194 -> -2.0861285 | AD113: =SUM(Z113:AC113) -> -7.7802264 | AE113: =-AE194 -> -8.3248422 | AF113: =-AF194 -> -8.7827086 | AG113: =-AG194 -> -9.35617
C114: Free Cash Flow (FCF) | F114: =SUM(F110:F113) -> 56.103 | G114: =SUM(G110:G113) -> 62.447 | H114: =SUM(H110:H113) -> 27.938 | I114: =SUM(I110:I113) -> 44.665 | J114: =SUM(J110:J113) -> 191.153 | K114: =SUM(K110:K113) -> 29.631 | L114: =SUM(L110:L113) -> 64.934 | M114: =SUM(M110:M113) -> 27.888 | ... AG114: =SUM(AG110:AG113) -> 397.70141
C116: Free Cash Flow Margin | F116: =F114/F28 -> 0.41401678 | G116: =G114/G28 -> 0.40713382 | H116: =H114/H28 -> 0.21985615 | I116: =I114/I28 -> 0.39600844 | J116: =J114/J28 -> 0.36151662 | K116: =K114/K28 -> 0.23697785 | L116: =L114/L28 -> 0.51179104 | M116: =M114/M28 -> 0.2226338 | ... AG116: =AG114/AG28 -> 0.34005488
C117: Free Cash Flow per Share | F117: =F114/F283 -> 1.5163383 | G117: =G114/G283 -> 1.6877568 | H117: =H114/H283 -> 0.75457124 | I117: =I114/I283 -> 1.2052403 | J117: =J114/J283 -> 5.1580723 | K117: =K114/K283 -> 0.78582226 | L117: =L114/L283 -> 1.7215653 | M117: =M114/M283 -> 0.73902904 | ... AG117: =AG114/AG283 -> 9.9330519
C118: Free Cash Flow Yield | F118: =F117*4/F240 -> 0.088172018 | G118: =G117*4/G240 -> 0.096900058 | H118: =H117*4/H240 -> 0.041764009 | I118: =I117*4/I240 -> 0.074180046 | J118: =J117/J240 -> 0.078967542 | K118: =K117*4/K240 -> 0.043802802 | L118: =L117*4/L240 -> 0.074899513 | M118: =M117*4/M240 -> 0.032736613 | N118: =N117*4/N240 -> 0.037884013 | O118: =O117/O240 -> 0.039993071 | P118: =P117*4/P240 -> 0.044752568 | Q118: =Q117*4/Q240 -> 0.080662858 | R118: =R117*4/R240 -> 0.020580344 | S118: =S117*4/S240 -> 0.018828454 | T118: =T117/T240 -> 0.042573113 | U118: =U117*4/U240 -> 0.067115384 | V118: =V117*4/V240 -> 0.041277135 | W118: =W117*4/W240 -> 0.040145635 | X118: =X117*4/X240 -> 0.051296483 | Y118: =Y117/Y240 -> 0.05977256 | Z118: =Z117*4/Z240 -> 0.043792933 | AA118: =AA117*4/AA240 -> 0.061122644 | AB118: =AB117*4/AB240 -> 0.066384067 | AC118: =AC117*4/AC240 -> 0.067714189 | AD118: =AD117/AD240 -> 0.059746282 | AE118: =AE117/AE240 -> 0.080705442 | AF118: =AF117/AF240 -> 0.077427709 | AG118: =AG117/AG240 -> 0.083993336
A120: x | C120: Balance Sheet | F120: =F$25 -> 1Q23 | G120: =G$63 -> 2Q23 | H120: =H$63 -> 3Q23 | I120: =I$63 -> 4Q23 | J120: =J$63 -> 2023 | K120: =K$63 -> 1Q24 | L120: =L$63 -> 2Q24 | M120: =M$63 -> 3Q24 | N120: =N$63 -> 4Q24 | ... AG120: =AG$63 -> 2030e | AH120: x
C122: Cash & Cash Equivalents | F122: 83.052 | G122: 121.764 | H122: 146.07 | I122: 99.686 | J122: =I122 -> 99.686 | K122: 100.255 | L122: 128.098 | M122: 164.45 | N122: 114.634 | O122: =N122 -> 114.634 | P122: 151.663 | Q122: 193.771 | R122: 285.553 | S122: 229.161 | T122: =S122 -> 229.161 | U122: 263.347 | V122: =V106 -> 261.16987 | W122: =W106 -> 283.12019 | X122: =X106 -> 273.99227 | Y122: =X122 -> 273.99227 | Z122: =Z106 -> 248.19035 | AA122: =AA106 -> 244.48216 | AB122: =AB106 -> 235.06938 | AC122: =AC106 -> 206.78503 | AD122: =AC122 -> 206.78503 | AE122: =AE106 -> 256.12555 | AF122: =AF106 -> 269.77717 | AG122: =AG106 -> 252.11707
C123: Fees Receivable | F123: 44.982 | G123: 47.496 | H123: 52.074 | I123: 47.14 | J123: =I123 -> 47.14 | K123: 65.864 | L123: 61.8 | M123: 67.751 | N123: 108.291 | O123: =N123 -> 108.291 | P123: 141.099 | Q123: 95.509 | R123: 135.622 | S123: 181.411 | T123: =S123 -> 181.411 | U123: 158.061 | V123: =V163 -> 159.6587 | W123: =W163 -> 167.62761 | X123: =X163 -> 181.67972 | Y123: =X123 -> 181.67972 | Z123: =Z163 -> 212.18164 | AA123: =AA163 -> 224.91254 | AB123: =AB163 -> 232.9998 | AC123: =AC163 -> 243.75958 | AD123: =AC123 -> 243.75958 | AE123: =AE163 -> 222.37592 | AF123: =AF163 -> 240.62215 | AG123: =AG163 -> 256.33342
C124: Inventory | F124: 0 | G124: 0 | H124: 0 | I124: 0 | J124: =I124 -> 0 | K124: 0 | L124: 0 | M124: 0 | N124: 0 | O124: =N124 -> 0 | P124: 0 | Q124: 0 | R124: 0 | S124: 0 | T124: =S124 -> 0 | U124: 0 | V124: =V164 -> 0 | W124: =W164 -> 0 | X124: =X164 -> 0 | Y124: =X124 -> 0 | Z124: =Z164 -> 0 | AA124: =AA164 -> 0 | AB124: =AB164 -> 0 | AC124: =AC164 -> 0 | AD124: =AC124 -> 0 | AE124: =AE164 -> 0 | AF124: =AF164 -> 0 | AG124: =AG164 -> 0
C125: Prepaid & Other Current Assets | F125: 14.351 | G125: 16.079 | H125: 17.978 | I125: 21.807 | J125: =I125 -> 21.807 | K125: 20.775 | L125: 19.321 | M125: 24.372 | N125: 24.208 | O125: =N125 -> 24.208 | P125: 26.492 | Q125: 39.075 | R125: 36.643 | S125: 33.806 | T125: =S125 -> 33.806 | U125: 36.945 | V125: =V165 -> 36.782132 | W125: =W165 -> 39.042381 | X125: =X165 -> 42.315277 | Y125: =X125 -> 42.315277 | Z125: =Z165 -> 44.903557 | AA125: =AA165 -> 47.59777 | AB125: =AB165 -> 49.851121 | AC125: =AC165 -> 52.153212 | AD125: =AC125 -> 52.153212 | AE125: =AE165 -> 57.23329 | AF125: =AF165 -> 60.381121 | AG125: =AG165 -> 64.323668
C126: Total Current Assets | F126: =SUM(F122:F125) -> 142.385 | G126: =SUM(G122:G125) -> 185.339 | H126: =SUM(H122:H125) -> 216.122 | I126: =SUM(I122:I125) -> 168.633 | J126: =I126 -> 168.633 | K126: =SUM(K122:K125) -> 186.894 | L126: =SUM(L122:L125) -> 209.219 | M126: =SUM(M122:M125) -> 256.573 | N126: =SUM(N122:N125) -> 247.133 | O126: =N126 -> 247.133 | P126: =SUM(P122:P125) -> 319.254 | Q126: =SUM(Q122:Q125) -> 328.355 | R126: =SUM(R122:R125) -> 457.818 | S126: =SUM(S122:S125) -> 444.378 | T126: =S126 -> 444.378 | U126: =SUM(U122:U125) -> 458.353 | V126: =SUM(V122:V125) -> 457.61071 | W126: =SUM(W122:W125) -> 489.79018 | X126: =SUM(X122:X125) -> 497.98726 | Y126: =X126 -> 497.98726 | Z126: =SUM(Z122:Z125) -> 505.27554 | AA126: =SUM(AA122:AA125) -> 516.99247 | AB126: =SUM(AB122:AB125) -> 517.9203 | AC126: =SUM(AC122:AC125) -> 502.69782 | AD126: =AC126 -> 502.69782 | AE126: =SUM(AE122:AE125) -> 535.73476 | AF126: =SUM(AF122:AF125) -> 570.78044 | AG126: =SUM(AG122:AG125) -> 572.77416
C128: PP&E, Net | F128: 93.68 | G128: 93.07 | H128: 91.5 | I128: 90.752 | J128: =I128 -> 90.752 | K128: 94.756 | L128: 96.357 | M128: 96.821 | N128: 95.438 | O128: =N128 -> 95.438 | P128: 95.085 | Q128: 95.255 | R128: 97.373 | S128: 98.999 | T128: =S128 -> 98.999 | U128: 96.677 | V128: =V197 -> 98.883928 | W128: =W197 -> 101.22647 | X128: =X197 -> 103.34223 | Y128: =X128 -> 103.34223 | Z128: =Z197 -> 105.13838 | AA128: =AA197 -> 107.04229 | AB128: =AB197 -> 109.03633 | AC128: =AC197 -> 111.12246 | AD128: =AC128 -> 111.12246 | AE128: =AE197 -> 119.4473 | AF128: =AF197 -> 128.23001 | AG128: =AG197 -> 137.58618
...

Sheet Segment Analysis
C1: =Company_Name&" - "&MID(CELL("filename",A1),FIND("]",CELL("filename",A1))+1,255)&": "&Case_Scenario&" Case" -> Hamilton Lane Inc. - Segment Analysis: Base Case
C2: =Cover!C2 -> $ in Millions Except Per Share Data
C5: Segment Analysis | F5: =Model!F63 -> 1Q23 | G5: =Model!G63 -> 2Q23 | H5: =Model!H63 -> 3Q23 | I5: =Model!I63 -> 4Q23 | J5: =Model!J63 -> 2023 | K5: =Model!K63 -> 1Q24 | L5: =Model!L63 -> 2Q24 | M5: =Model!M63 -> 3Q24 | ... AG5: =Model!AG63 -> 2030e
C6: Drivers
C7: Total Company Revenue | F7: =SUM(F8:F13) -> 135.509 | G7: =SUM(G8:G13) -> 153.382 | H7: =SUM(H8:H13) -> 127.074 | I7: =SUM(I8:I13) -> 112.788 | J7: =SUM(F7:I7) -> 528.753 | K7: =SUM(K8:K13) -> 125.037 | L7: =SUM(L8:L13) -> 126.876 | M7: =SUM(M8:M13) -> 125.264 | N7: =SUM(N8:N13) -> 176.665 | O7: =SUM(K7:N7) -> 553.842 | P7: =SUM(P8:P13) -> 196.731 | Q7: =SUM(Q8:Q13) -> 149.999 | R7: =SUM(R8:R13) -> 168.261 | S7: =SUM(S8:S13) -> 197.973 | T7: =SUM(P7:S7) -> 712.964 | U7: =SUM(U8:U13) -> 175.958 | V7: =SUM(V8:V13) -> 183.91066 | W7: =SUM(W8:W13) -> 195.21191 | X7: =SUM(X8:X13) -> 211.57639 | Y7: =SUM(U7:X7) -> 766.65695 | Z7: =SUM(Z8:Z13) -> 224.51778 | AA7: =SUM(AA8:AA13) -> 237.98885 | AB7: =SUM(AB8:AB13) -> 249.25561 | AC7: =SUM(AC8:AC13) -> 260.76606 | AD7: =SUM(Z7:AC7) -> 972.5283 | AE7: =SUM(AE8:AE13) -> 1040.6053 | AF7: =SUM(AF8:AF13) -> 1097.8386 | AG7: =SUM(AG8:AG13) -> 1169.5212
C8: Management & Advisory Fees | F8: 85.946 | G8: 92.88 | H8: 97.355 | I8: 95.692 | J8: =SUM(F8:I8) -> 371.873 | K8: 105.407 | L8: 109.184 | M8: 113.641 | N8: 123.704 | O8: =SUM(K8:N8) -> 451.936 | P8: 139.962 | Q8: 119.783 | R8: 126.282 | S8: 127.838 | T8: =SUM(P8:S8) -> 513.865 | U8: 133.696 | V8: ='Revenue Build'!V32 -> 140.3808 | W8: ='Revenue Build'!W32 -> 149.50555 | X8: ='Revenue Build'!X32 -> 162.21352 | Y8: =SUM(U8:X8) -> 585.79588 | Z8: ='Revenue Build'!Z32 -> 171.94634 | AA8: ='Revenue Build'!AA32 -> 182.26312 | AB8: ='Revenue Build'!AB32 -> 190.46496 | AC8: ='Revenue Build'!AC32 -> 199.03588 | AD8: =SUM(Z8:AC8) -> 743.71029 | AE8: ='Revenue Build'!AE32 -> 795.77001 | AF8: ='Revenue Build'!AF32 -> 839.53736 | AG8: ='Revenue Build'!AG32 -> 898.30497
C9: Incentive Fees | F9: =(495.24+0.39)/10 -> 49.563 | G9: =(592.37+12.65)/10 -> 60.502 | H9: =(56.44+240.75)/10 -> 29.719 | I9: =(170.96)/10 -> 17.096 | J9: =SUM(F9:I9) -> 156.88 | K9: 19.63 | L9: 17.692 | M9: 11.623 | N9: 52.961 | O9: =SUM(K9:N9) -> 101.906 | P9: 56.769 | Q9: 30.216 | R9: 41.979 | S9: 70.135 | T9: =SUM(P9:S9) -> 199.099 | U9: 42.262 | V9: ='Revenue Build'!V35 -> 43.52986 | W9: ='Revenue Build'!W35 -> 45.706353 | X9: ='Revenue Build'!X35 -> 49.362861 | Y9: =SUM(U9:X9) -> 180.86107 | Z9: ='Revenue Build'!Z35 -> 52.571447 | AA9: ='Revenue Build'!AA35 -> 55.725734 | AB9: ='Revenue Build'!AB35 -> 58.790649 | AC9: ='Revenue Build'!AC35 -> 61.730182 | AD9: =SUM(Z9:AC9) -> 228.81801 | AE9: ='Revenue Build'!AE35 -> 244.83527 | AF9: ='Revenue Build'!AF35 -> 258.30121 | AG9: ='Revenue Build'!AG35 -> 271.21627
C10: =C18&" Revenue" -> Segment 3 Revenue | F10: 0 | G10: 0 | H10: 0 | I10: 0 | J10: =SUM(F10:I10) -> 0 | K10: 0 | L10: 0 | M10: 0 | N10: 0 | O10: =SUM(K10:N10) -> 0 | P10: 0 | Q10: 0 | R10: 0 | S10: 0 | T10: =SUM(P10:S10) -> 0 | U10: 0 | V10: ='Revenue Build'!V38 -> 0 | W10: ='Revenue Build'!W38 -> 0 | X10: ='Revenue Build'!X38 -> 0 | Y10: =SUM(U10:X10) -> 0 | Z10: ='Revenue Build'!Z38 -> 0 | AA10: ='Revenue Build'!AA38 -> 0 | AB10: ='Revenue Build'!AB38 -> 0 | AC10: ='Revenue Build'!AC38 -> 0 | AD10: =SUM(Z10:AC10) -> 0 | AE10: ='Revenue Build'!AE38 -> 0 | AF10: ='Revenue Build'!AF38 -> 0 | AG10: ='Revenue Build'!AG38 -> 0
C11: =C19&" Revenue" -> Segment 4 Revenue | F11: 0 | G11: 0 | H11: 0 | I11: 0 | J11: =SUM(F11:I11) -> 0 | K11: 0 | L11: 0 | M11: 0 | N11: 0 | O11: =SUM(K11:N11) -> 0 | P11: 0 | Q11: 0 | R11: 0 | S11: 0 | T11: =SUM(P11:S11) -> 0 | U11: 0 | V11: ='Revenue Build'!V41 -> 0 | W11: ='Revenue Build'!W41 -> 0 | X11: ='Revenue Build'!X41 -> 0 | Y11: =SUM(U11:X11) -> 0 | Z11: ='Revenue Build'!Z41 -> 0 | AA11: ='Revenue Build'!AA41 -> 0 | AB11: ='Revenue Build'!AB41 -> 0 | AC11: ='Revenue Build'!AC41 -> 0 | AD11: =SUM(Z11:AC11) -> 0 | AE11: ='Revenue Build'!AE41 -> 0 | AF11: ='Revenue Build'!AF41 -> 0 | AG11: ='Revenue Build'!AG41 -> 0
C12: =C20&" Revenue" -> Segment 5 Revenue | F12: 0 | G12: 0 | H12: 0 | I12: 0 | J12: =SUM(F12:I12) -> 0 | K12: 0 | L12: 0 | M12: 0 | N12: 0 | O12: =SUM(K12:N12) -> 0 | P12: 0 | Q12: 0 | R12: 0 | S12: 0 | T12: =SUM(P12:S12) -> 0 | U12: 0 | V12: ='Revenue Build'!V44 -> 0 | W12: ='Revenue Build'!W44 -> 0 | X12: ='Revenue Build'!X44 -> 0 | Y12: =SUM(U12:X12) -> 0 | Z12: ='Revenue Build'!Z44 -> 0 | AA12: ='Revenue Build'!AA44 -> 0 | AB12: ='Revenue Build'!AB44 -> 0 | AC12: ='Revenue Build'!AC44 -> 0 | AD12: =SUM(Z12:AC12) -> 0 | AE12: ='Revenue Build'!AE44 -> 0 | AF12: ='Revenue Build'!AF44 -> 0 | AG12: ='Revenue Build'!AG44 -> 0
C13: =C21&" Revenue" -> Segment 6 Revenue | F13: 0 | G13: 0 | H13: 0 | I13: 0 | J13: =SUM(F13:I13) -> 0 | K13: 0 | L13: 0 | M13: 0 | N13: 0 | O13: =SUM(K13:N13) -> 0 | P13: 0 | Q13: 0 | R13: 0 | S13: 0 | T13: =SUM(P13:S13) -> 0 | U13: 0 | V13: ='Revenue Build'!V47 -> 0 | W13: ='Revenue Build'!W47 -> 0 | X13: ='Revenue Build'!X47 -> 0 | Y13: =SUM(U13:X13) -> 0 | Z13: ='Revenue Build'!Z47 -> 0 | AA13: ='Revenue Build'!AA47 -> 0 | AB13: ='Revenue Build'!AB47 -> 0 | AC13: ='Revenue Build'!AC47 -> 0 | AD13: =SUM(Z13:AC13) -> 0 | AE13: ='Revenue Build'!AE47 -> 0 | AF13: ='Revenue Build'!AF47 -> 0 | AG13: ='Revenue Build'!AG47 -> 0
C15: Revenue Mix
C16: =C8 -> Management & Advisory Fees | F16: =IFERROR(F8/F$7,"N/A") -> 0.6342457 | G16: =IFERROR(G8/G$7,"N/A") -> 0.60554694 | H16: =IFERROR(H8/H$7,"N/A") -> 0.7661284 | I16: =IFERROR(I8/I$7,"N/A") -> 0.84842359 | J16: =IFERROR(J8/J$7,"N/A") -> 0.70330192 | K16: =IFERROR(K8/K$7,"N/A") -> 0.84300647 | L16: =IFERROR(L8/L$7,"N/A") -> 0.86055676 | M16: =IFERROR(M8/M$7,"N/A") -> 0.90721197 | ... AG16: =IFERROR(AG8/AG$7,"N/A") -> 0.76809633
C17: =C9 -> Incentive Fees | F17: =IFERROR(F9/F$7,"N/A") -> 0.3657543 | G17: =IFERROR(G9/G$7,"N/A") -> 0.39445306 | H17: =IFERROR(H9/H$7,"N/A") -> 0.2338716 | I17: =IFERROR(I9/I$7,"N/A") -> 0.15157641 | J17: =IFERROR(J9/J$7,"N/A") -> 0.29669808 | K17: =IFERROR(K9/K$7,"N/A") -> 0.15699353 | L17: =IFERROR(L9/L$7,"N/A") -> 0.13944324 | M17: =IFERROR(M9/M$7,"N/A") -> 0.092788032 | ... AG17: =IFERROR(AG9/AG$7,"N/A") -> 0.23190367
C18: Segment 3 | F18: =IFERROR(F10/F$7,"N/A") -> 0 | G18: =IFERROR(G10/G$7,"N/A") -> 0 | H18: =IFERROR(H10/H$7,"N/A") -> 0 | I18: =IFERROR(I10/I$7,"N/A") -> 0 | J18: =IFERROR(J10/J$7,"N/A") -> 0 | K18: =IFERROR(K10/K$7,"N/A") -> 0 | L18: =IFERROR(L10/L$7,"N/A") -> 0 | M18: =IFERROR(M10/M$7,"N/A") -> 0 | ... AG18: =IFERROR(AG10/AG$7,"N/A") -> 0
C19: Segment 4 | F19: =IFERROR(F11/F$7,"N/A") -> 0 | G19: =IFERROR(G11/G$7,"N/A") -> 0 | H19: =IFERROR(H11/H$7,"N/A") -> 0 | I19: =IFERROR(I11/I$7,"N/A") -> 0 | J19: =IFERROR(J11/J$7,"N/A") -> 0 | K19: =IFERROR(K11/K$7,"N/A") -> 0 | L19: =IFERROR(L11/L$7,"N/A") -> 0 | M19: =IFERROR(M11/M$7,"N/A") -> 0 | ... AG19: =IFERROR(AG11/AG$7,"N/A") -> 0
C20: Segment 5 | F20: =IFERROR(F12/F$7,"N/A") -> 0 | G20: =IFERROR(G12/G$7,"N/A") -> 0 | H20: =IFERROR(H12/H$7,"N/A") -> 0 | I20: =IFERROR(I12/I$7,"N/A") -> 0 | J20: =IFERROR(J12/J$7,"N/A") -> 0 | K20: =IFERROR(K12/K$7,"N/A") -> 0 | L20: =IFERROR(L12/L$7,"N/A") -> 0 | M20: =IFERROR(M12/M$7,"N/A") -> 0 | ... AG20: =IFERROR(AG12/AG$7,"N/A") -> 0
C21: Segment 6 | F21: =IFERROR(F13/F$7,"N/A") -> 0 | G21: =IFERROR(G13/G$7,"N/A") -> 0 | H21: =IFERROR(H13/H$7,"N/A") -> 0 | I21: =IFERROR(I13/I$7,"N/A") -> 0 | J21: =IFERROR(J13/J$7,"N/A") -> 0 | K21: =IFERROR(K13/K$7,"N/A") -> 0 | L21: =IFERROR(L13/L$7,"N/A") -> 0 | M21: =IFERROR(M13/M$7,"N/A") -> 0 | ... AG21: =IFERROR(AG13/AG$7,"N/A") -> 0
C23: Total Company Operating Income | F23: =SUM(F24:F29) -> 67.614 | G23: =SUM(G24:G29) -> 73.228 | H23: =SUM(H24:H29) -> 33.672 | I23: =SUM(I24:I29) -> 68.094 | J23: =SUM(F23:I23) -> 242.608 | K23: =SUM(K24:K29) -> 67.744 | L23: =SUM(L24:L29) -> 66.359 | M23: =SUM(M24:M29) -> 50.332 | N23: =SUM(N24:N29) -> 97.224 | O23: =SUM(K23:N23) -> 281.659 | P23: =SUM(P24:P29) -> 106.774 | Q23: =SUM(Q24:Q29) -> 77.094 | R23: =R24 -> 90.151 | S23: =SUM(S24:S29) -> 88.258 | T23: =SUM(P23:S23) -> 362.277 | U23: =SUM(U24:U29) -> 95.449 | V23: =SUM(V24:V29) -> 140.3808 | W23: =SUM(W24:W29) -> 149.50555 | X23: =SUM(X24:X29) -> 162.21352 | Y23: =SUM(U23:X23) -> 547.54888 | Z23: =SUM(Z24:Z29) -> 171.94634 | AA23: =SUM(AA24:AA29) -> 182.26312 | AB23: =SUM(AB24:AB29) -> 190.46496 | AC23: =SUM(AC24:AC29) -> 199.03588 | AD23: =SUM(Z23:AC23) -> 743.71029 | AE23: =SUM(AE24:AE29) -> 795.77001 | AF23: =SUM(AF24:AF29) -> 839.53736 | AG23: =SUM(AG24:AG29) -> 898.30497
C24: Total Company Operaing Income | F24: 67.614 | G24: 73.228 | H24: 33.672 | I24: 68.094 | J24: =SUM(F24:I24) -> 242.608 | K24: 67.744 | L24: 66.359 | M24: 50.332 | N24: 97.224 | O24: =SUM(K24:N24) -> 281.659 | P24: 106.774 | Q24: 77.094 | R24: 90.151 | S24: 88.258 | T24: =SUM(P24:S24) -> 362.277 | U24: 95.449 | V24: =V8*Drivers!V$7 -> 140.3808 | W24: =W8*Drivers!W$7 -> 149.50555 | X24: =X8*Drivers!X$7 -> 162.21352 | Y24: =SUM(U24:X24) -> 547.54888 | Z24: =Z8*Drivers!Z$7 -> 171.94634 | AA24: =AA8*Drivers!AA$7 -> 182.26312 | AB24: =AB8*Drivers!AB$7 -> 190.46496 | AC24: =AC8*Drivers!AC$7 -> 199.03588 | AD24: =SUM(Z24:AC24) -> 743.71029 | AE24: =AE8*Drivers!AE$7 -> 795.77001 | AF24: =AF8*Drivers!AF$7 -> 839.53736 | AG24: =AG8*Drivers!AG$7 -> 898.30497
C25: N/A | F25: 0 | G25: 0 | H25: 0 | I25: 0 | J25: =SUM(F25:I25) -> 0 | K25: 0 | L25: 0 | M25: 0 | N25: 0 | O25: =SUM(K25:N25) -> 0 | P25: 0 | Q25: 0 | R25: 0 | S25: 0 | T25: =SUM(P25:S25) -> 0 | U25: 0 | V25: =V9*Drivers!V$12 -> 0 | W25: =W9*Drivers!W$12 -> 0 | X25: =X9*Drivers!X$12 -> 0 | Y25: =SUM(U25:X25) -> 0 | Z25: =Z9*Drivers!Z$12 -> 0 | AA25: =AA9*Drivers!AA$12 -> 0 | AB25: =AB9*Drivers!AB$12 -> 0 | AC25: =AC9*Drivers!AC$12 -> 0 | AD25: =SUM(Z25:AC25) -> 0 | AE25: =AE9*Drivers!AE$12 -> 0 | AF25: =AF9*Drivers!AF$12 -> 0 | AG25: =AG9*Drivers!AG$12 -> 0
C26: N/A | F26: 0 | G26: 0 | H26: 0 | I26: 0 | J26: =SUM(F26:I26) -> 0 | K26: 0 | L26: 0 | M26: 0 | N26: 0 | O26: =SUM(K26:N26) -> 0 | P26: 0 | Q26: 0 | R26: 0 | S26: 0 | T26: =SUM(P26:S26) -> 0 | U26: 0 | V26: =V10*Drivers!V$17 -> 0 | W26: =W10*Drivers!W$17 -> 0 | X26: =X10*Drivers!X17 -> 0 | Y26: =SUM(U26:X26) -> 0 | Z26: =Z10*Drivers!Z$17 -> 0 | AA26: =AA10*Drivers!AA$17 -> 0 | AB26: =AB10*Drivers!AB$17 -> 0 | AC26: =AC10*Drivers!AC$17 -> 0 | AD26: =SUM(Z26:AC26) -> 0 | AE26: =AE10*Drivers!AE$17 -> 0 | AF26: =AF10*Drivers!AF$17 -> 0 | AG26: =AG10*Drivers!AG$17 -> 0
C27: N/A | F27: 0 | G27: 0 | H27: 0 | I27: 0 | J27: =SUM(F27:I27) -> 0 | K27: 0 | L27: 0 | M27: 0 | N27: 0 | O27: =SUM(K27:N27) -> 0 | P27: 0 | Q27: 0 | R27: 0 | S27: 0 | T27: =SUM(P27:S27) -> 0 | U27: 0 | V27: =V11*Drivers!V$22 -> 0 | W27: =W11*Drivers!W$22 -> 0 | X27: =X11*Drivers!X$22 -> 0 | Y27: =SUM(U27:X27) -> 0 | Z27: =Z11*Drivers!Z$22 -> 0 | AA27: =AA11*Drivers!AA$22 -> 0 | AB27: =AB11*Drivers!AB$22 -> 0 | AC27: =AC11*Drivers!AC$22 -> 0 | AD27: =SUM(Z27:AC27) -> 0 | AE27: =AE11*Drivers!AE$22 -> 0 | AF27: =AF11*Drivers!AF$22 -> 0 | AG27: =AG11*Drivers!AG$22 -> 0
C28: N/A | F28: 0 | G28: 0 | H28: 0 | I28: 0 | J28: =SUM(F28:I28) -> 0 | K28: 0 | L28: 0 | M28: 0 | N28: 0 | O28: =SUM(K28:N28) -> 0 | P28: 0 | Q28: 0 | R28: 0 | S28: 0 | T28: =SUM(P28:S28) -> 0 | U28: 0 | V28: =V12*Drivers!V$27 -> 0 | W28: =W12*Drivers!W$27 -> 0 | X28: =X12*Drivers!X$27 -> 0 | Y28: =SUM(U28:X28) -> 0 | Z28: =Z12*Drivers!Z$27 -> 0 | AA28: =AA12*Drivers!AA$27 -> 0 | AB28: =AB12*Drivers!AB$27 -> 0 | AC28: =AC12*Drivers!AC$27 -> 0 | AD28: =SUM(Z28:AC28) -> 0 | AE28: =AE12*Drivers!AE$27 -> 0 | AF28: =AF12*Drivers!AF$27 -> 0 | AG28: =AG12*Drivers!AG$27 -> 0
C29: N/A | F29: 0 | G29: 0 | H29: 0 | I29: 0 | J29: =SUM(F29:I29) -> 0 | K29: 0 | L29: 0 | M29: 0 | N29: 0 | O29: =SUM(K29:N29) -> 0 | P29: 0 | Q29: 0 | R29: 0 | S29: 0 | T29: =SUM(P29:S29) -> 0 | U29: 0 | V29: =V13*Drivers!V$32 -> 0 | W29: =W13*Drivers!W$32 -> 0 | X29: =X13*Drivers!X$32 -> 0 | Y29: =SUM(U29:X29) -> 0 | Z29: =Z13*Drivers!Z$32 -> 0 | AA29: =AA13*Drivers!AA$32 -> 0 | AB29: =AB13*Drivers!AB$32 -> 0 | AC29: =AC13*Drivers!AC$32 -> 0 | AD29: =SUM(Z29:AC29) -> 0 | AE29: =AE13*Drivers!AE$32 -> 0 | AF29: =AF13*Drivers!AF$32 -> 0 | AG29: =AG13*Drivers!AG$32 -> 0
C31: Operating Income Check | F31: =F23-SUM(F24:F29) -> 0 | G31: =G23-SUM(G24:G29) -> 0 | H31: =H23-SUM(H24:H29) -> 0 | I31: =I23-SUM(I24:I29) -> 0 | J31: =J23-SUM(J24:J29) -> 0 | K31: =K23-SUM(K24:K29) -> 0 | L31: =L23-SUM(L24:L29) -> 0 | M31: =M23-SUM(M24:M29) -> 0 | ... AG31: =AG23-SUM(AG24:AG29) -> 0
C33: Operating Income Mix
C34: Total Company Operaing Income | F34: =IFERROR(F24/F$23,"N/A") -> 1 | G34: =IFERROR(G24/G$23,"N/A") -> 1 | H34: =IFERROR(H24/H$23,"N/A") -> 1 | I34: =IFERROR(I24/I$23,"N/A") -> 1 | J34: =IFERROR(J24/J$23,"N/A") -> 1 | K34: =IFERROR(K24/K$23,"N/A") -> 1 | L34: =IFERROR(L24/L$23,"N/A") -> 1 | M34: =IFERROR(M24/M$23,"N/A") -> 1 | ... AG34: =IFERROR(AG24/AG$23,"N/A") -> 1
