Workbook
Name al: '[3]2010 Labor Rates 091130'!$A$161
Name al09salary: [3]Salaries!$G$13
Name al10salary: [3]Salaries!$K$13
Name alid: '[3]2010 Labor Rates 091130'!$E$168
Name alname: [3]Salaries!$A$13
Name aprpto: [3]Vacation!$I$56
Name augpto: [3]Vacation!$M$56
Name avg_Health_and_Welfare: [4]PBCFringe!$Q$22
Name bf: '[3]2010 Labor Rates 091130'!$A$239
Name bf09salary: [3]Salaries!$G$18
Name bf10salary: [3]Salaries!$K$18
Name bfid: '[3]2010 Labor Rates 091130'!$E$246
Name bfname: [3]Salaries!$A$18
Name Bonus_estimate_2011: [4]PBCFringe!$B$100
Name Case_Scenario: [5]Cover!$F$22
Name Case_Scenario: #REF!
Name Case_Scenario: Cover!$F$17
Name cc: '[3]2010 Labor Rates 091130'!$A$135
Name cc09salary: [3]Salaries!$G$11
Name cc10salary: [3]Salaries!$K$11
Name ccid: '[3]2010 Labor Rates 091130'!$E$142
Name ccname: [3]Salaries!$A$11
Name Ccy: [6]data!$A$5
Name cf: '[3]2010 Labor Rates 091130'!$A$148
Name cf09salary: [3]Salaries!$G$12
Name cf10salary: [3]Salaries!$K$12
Name cfid: '[3]2010 Labor Rates 091130'!$E$155
Name cfname: [3]Salaries!$A$12
Name ck: '[3]2010 Labor Rates 091130'!$A$213
Name ck09salary: [3]Salaries!$G$17
Name ck10salary: [3]Salaries!$K$17
Name ckid: '[3]2010 Labor Rates 091130'!$E$220
Name ckname: [3]Salaries!$A$17
Name Company_Cyclical_Multiples_Data: '[5]Multiples Data'!$C$14:$H$26
Name Company_Cyclical_Multiples_Data: #REF!
Name Company_Name: [5]Cover!$F$19
Name Company_Name: #REF!
Name Company_Name: [8]Cover!$F$19
Name Company_Rev_Methodology: '[5]Revenue Build'!$C$7
Name Company_Rev_Methodology: #REF!
Name Cost_of_Debt: [5]WACC!$G$17
Name Cost_of_Debt: #REF!
Name Cost_of_Equity: [5]WACC!$G$25
Name Cost_of_Equity: #REF!
Name Cost_of_Preferred: [5]WACC!$G$10
Name Cost_of_Preferred: #REF!
Name cs: '[3]2010 Labor Rates 091130'!$A$252
Name cs09salary: [3]Salaries!$G$19
Name cs10salary: [3]Salaries!$K$19
Name csid: '[3]2010 Labor Rates 091130'!$E$259
Name csname: [3]Salaries!$A$19
Name Current_Date: [5]Cover!$F$27
Name Current_Date: #REF!
Name Current_Salary: '[9]Planning Worksheet'!$C:$C
Name CV: '[3]2010 Labor Rates 091130'!$A$5
Name cv09salary: [3]Salaries!$G$2
Name cv10salary: [3]Salaries!$K$2
Name cvid: '[3]2010 Labor Rates 091130'!$E$12
Name cvname: [3]Salaries!$A$2
Name Cycle_Period_Toggle: [5]Valuation!$G$221

Sheet Cover
B3: Model Assumptions: | J3: Return Summary:
J5: Sum of the Parts Analysis
J7: Implied Share Price | N7: =Valuation!L16 -> 113.45876
J8: % Return | N8: =Valuation!L17 -> 0.26121347
B13: Company Name | F13: KKR & Co., Inc.
B14: Ticker | F14: KKR
B17: Case Scenario | F17: Base
B19: Last Fiscal Year | F19: 46022
B20: Next Fiscal Year | F20: =F19+365 -> 46387
B21: Last Fiscal Quarter Reported | F21: 4Q
B22: Current Valuation Date | F22: 46091
B24: Current Share Price | F24: 89.96
B25: 52-Week High | F25: 153.87
B26: 52-Week Low | F26: 84.52
B32: Model Note:
B33: To remain consistent with Street reporting, all numbers are pulled from investor presentations that are released each quarter.

Sheet Revenue Build
B2: Report
AF4: CAGR
A5: x | B5: Summary | C5: =Model!E2 -> 1Q23 | D5: =Model!F2 -> 2Q23 | E5: =Model!G2 -> 3Q23 | F5: =Model!H2 -> 4Q23 | G5: =Model!I2 -> 2023 | H5: =Model!J2 -> 1Q24 | I5: =Model!K2 -> 2Q24 | J5: =Model!L2 -> 3Q24 | ... AD5: =Model!AF2 -> 2030e | AF5: Historical | AG5: Projected
B7: =+Model!B11 -> Fee-Related Earnings | C7: =+SUM(C9,C11,C13,C15,C17) -> 548578 | D7: =+SUM(D9,D11,D13,D15,D17) -> 602309 | E7: =+SUM(E9,E11,E13,E15,E17) -> 557525 | F7: =+SUM(F9,F11,F13,F15,F17) -> 675374 | G7: =+SUM(C7:F7) -> 2383786 | H7: =+SUM(H9,H11,H13,H15,H17) -> 668741 | I7: =+SUM(I9,I11,I13,I15,I17) -> 755397 | J7: =+SUM(J9,J11,J13,J15,J17) -> 1000673 | K7: =+SUM(K9,K11,K13,K15,K17) -> 842985 | L7: =+SUM(H7:K7) -> 3267796 | M7: =+SUM(M9,M11,M13,M15,M17) -> 822603 | N7: =+SUM(N9,N11,N13,N15,N17) -> 886754 | O7: =+SUM(O9,O11,O13,O15,O17) -> 1032936 | P7: =+SUM(P9,P11,P13,P15,P17) -> 972020 | Q7: =+SUM(M7:P7) -> 3714313 | R7: =SUM(R9,R11,R13,R15,R17) -> 1034171.5 | S7: =SUM(S9,S11,S13,S15,S17) -> 1114538.8 | T7: =SUM(T9,T11,T13,T15,T17) -> 1174421.9 | U7: =SUM(U9,U11,U13,U15,U17) -> 1180505.5 | V7: =SUM(R7:U7) -> 4503637.7 | W7: =SUM(W9,W11,W13,W15,W17) -> 1232755.9 | X7: =SUM(X9,X11,X13,X15,X17) -> 1336605.3 | Y7: =SUM(Y9,Y11,Y13,Y15,Y17) -> 1398143.1 | Z7: =SUM(Z9,Z11,Z13,Z15,Z17) -> 1390318.5 | AA7: =SUM(W7:Z7) -> 5357822.8 | AB7: =SUM(AB9,AB11,AB13,AB15,AB17) -> 5922058 | AC7: =SUM(AC9,AC11,AC13,AC15,AC17) -> 6585176.2 | AD7: =SUM(AD9,AD11,AD13,AD15,AD17) -> 7117956.6 | AF7: =IFERROR((Q7/G7)^(1/3)-1,"--") -> 0.15932111 | AG7: =IFERROR((AD7/Q7)^(1/5)-1,"--") -> 0.13892563
B8: % Growth | D8: =D7/C7-1 -> 0.097945962 | E8: =E7/D7-1 -> -0.074353862 | F8: =F7/E7-1 -> 0.21137886 | G8: 0 | H8: =+H7/F7-1 -> -0.009821225 | I8: =I7/H7-1 -> 0.12958081 | J8: =J7/I7-1 -> 0.32469814 | K8: =K7/J7-1 -> -0.15758195 | L8: 0 | M8: =+M7/K7-1 -> -0.024178366 | N8: =N7/M7-1 -> 0.077985371 | O8: =O7/N7-1 -> 0.16485068 | P8: =P7/O7-1 -> -0.058973644 | Q8: 0 | R8: =R7/P7-1 -> 0.06394051 | S8: =S7/Q7-1 -> -0.69993406 | T8: =T7/R7-1 -> 0.13561621 | U8: =U7/S7-1 -> 0.059187446 | V8: =V7/Q7-1 -> 0.21250892 | W8: =W7/U7-1 -> 0.044261054 | X8: =X7/V7-1 -> -0.70321651 | Y8: =Y7/W7-1 -> 0.13416051 | Z8: =Z7/X7-1 -> 0.040186258 | AA8: =AA7/V7-1 -> 0.18966561 | AB8: =AB7/Z7-1 -> 3.2594974 | AC8: =AC7/AA7-1 -> 0.22907688 | AD8: =AD7/AB7-1 -> 0.20193971
B9: =Model!B6 -> Management Fees | C9: ='Segment Analysis'!E7 -> 738156 | D9: ='Segment Analysis'!F7 -> 748888 | E9: ='Segment Analysis'!G7 -> 758700 | F9: ='Segment Analysis'!H7 -> 784581 | G9: =+SUM(C9:F9) -> 3030325 | H9: ='Segment Analysis'!J7 -> 815327 | I9: ='Segment Analysis'!K7 -> 847307 | J9: ='Segment Analysis'!L7 -> 892629 | K9: ='Segment Analysis'!M7 -> 906118 | L9: =+SUM(H9:K9) -> 3461381 | M9: ='Segment Analysis'!O7 -> 917334 | N9: ='Segment Analysis'!P7 -> 995763 | O9: ='Segment Analysis'!Q7 -> 1063553 | P9: ='Segment Analysis'!R7 -> 1124191 | Q9: =+SUM(M9:P9) -> 4100841 | R9: =R22 -> 1143864.3 | S9: =S22 -> 1185043.5 | T9: =T22 -> 1241925.5 | U9: =U22 -> 1291602.6 | V9: =SUM(R9:U9) -> 4862435.9 | W9: =W22 -> 1346495.7 | X9: =X22 -> 1397662.5 | Y9: =Y22 -> 1453569 | Z9: =Z22 -> 1504443.9 | AA9: =SUM(W9:Z9) -> 5702171.1 | AB9: =AB22 -> 6295196.9 | AC9: =AC22 -> 7230033.7 | AD9: =AD22 -> 8014492.3 | AF9: =IFERROR((Q9/G9)^(1/3)-1,"--") -> 0.10610046 | AG9: =IFERROR((AD9/Q9)^(1/5)-1,"--") -> 0.1434064
B10: % Growth | D10: =D23 -> 0.014538932 | E10: =E23 -> 0.013102093 | F10: =F23 -> 0.034112297 | G10: =+G23 -> 0 | H10: =+H9/F9-1 -> 0.039187796 | I10: =I23 -> 0.039223526 | J10: =J23 -> 0.053489467 | K10: =K23 -> 0.015111541 | L10: =+L23 -> 0.14224745 | M10: =+M9/K9-1 -> 0.012378079 | N10: =N23 -> 0.085496668 | O10: =O23 -> 0.068078448 | P10: =P23 -> 0.057014554 | Q10: =+Q23 -> 0.18474129 | R10: =R23 -> 0.0175 | S10: =S23 -> 0.036 | T10: =T23 -> 0.048 | U10: =U23 -> 0.04 | V10: =V23 -> 0.18571676 | W10: =W23 -> 0.0425 | X10: =X23 -> 0.038 | Y10: =Y23 -> 0.04 | ... AD10: =AD23 -> 0.1085
B11: =Model!B7 -> Transaction and Monitoring Fees | C11: ='Segment Analysis'!E8 -> 142179 | D11: ='Segment Analysis'!F8 -> 190228 | E11: ='Segment Analysis'!G8 -> 124014 | F11: ='Segment Analysis'!H8 -> 264233 | G11: =+SUM(C11:F11) -> 720654 | H11: ='Segment Analysis'!J8 -> 152084 | I11: ='Segment Analysis'!K8 -> 222858 | J11: ='Segment Analysis'!L8 -> 467145 | K11: ='Segment Analysis'!M8 -> 323797 | L11: =+SUM(H11:K11) -> 1165884 | M11: ='Segment Analysis'!O8 -> 261509 | N11: ='Segment Analysis'!P8 -> 234249 | O11: ='Segment Analysis'!Q8 -> 328124 | P11: ='Segment Analysis'!R8 -> 268695 | Q11: =+SUM(M11:P11) -> 1092577 | R11: =R28 -> 297579.71 | S11: =S28 -> 331057.43 | T11: =T28 -> 335195.65 | U11: =U28 -> 355307.39 | V11: =SUM(R11:U11) -> 1319140.2 | W11: =W28 -> 353530.85 | X11: =X28 -> 396838.38 | Y11: =Y28 -> 400806.76 | Z11: =Z28 -> 418843.07 | AA11: =SUM(W11:Z11) -> 1570019.1 | AB11: =AB28 -> 1703470.7 | AC11: =AC28 -> 1682177.3 | AD11: =AD28 -> 1593863 | AF11: =IFERROR((Q11/G11)^(1/3)-1,"--") -> 0.14879292 | AG11: =IFERROR((AD11/Q11)^(1/5)-1,"--") -> 0.078449433
B12: % Growth | D12: =D29 -> 0.33794724 | E12: =E29 -> -0.34807704 | F12: =F29 -> 1.1306707 | G12: =+G29 -> 0 | H12: =+H11/F11-1 -> -0.42443222 | I12: =I29 -> 0.46536125 | J12: =J29 -> 1.0961554 | K12: =K29 -> -0.30685975 | L12: =+L29 -> 0.61781382 | M12: =+M11/K11-1 -> -0.19236744 | N12: =N29 -> -0.10424115 | O12: =O29 -> 0.40074878 | P12: =P29 -> -0.1811175 | Q12: =+Q29 -> -0.062876753 | R12: =R29 -> 0.1075 | S12: =S29 -> 0.1125 | T12: =T29 -> 0.0125 | U12: =U29 -> 0.06 | V12: =V29 -> 0.20736587 | W12: =W29 -> -0.005 | X12: =X29 -> 0.1225 | Y12: =Y29 -> 0.01 | ... AD12: =AD29 -> -0.0525
B13: =Model!B8 -> Fee-Related Performance Revenues | C13: ='Segment Analysis'!E9 -> 21741 | D13: ='Segment Analysis'!F9 -> 28352 | E13: ='Segment Analysis'!G9 -> 20436 | F13: ='Segment Analysis'!H9 -> 23898 | G13: =+SUM(C13:F13) -> 94427 | H13: ='Segment Analysis'!J9 -> 19101 | I13: ='Segment Analysis'!K9 -> 37145 | J13: ='Segment Analysis'!L9 -> 56655 | K13: ='Segment Analysis'!M9 -> 25091 | L13: =+SUM(H13:K13) -> 137992 | M13: ='Segment Analysis'!O9 -> 21277 | N13: ='Segment Analysis'!P9 -> 53737 | O13: ='Segment Analysis'!Q9 -> 73177 | P13: ='Segment Analysis'!R9 -> 33593 | Q13: =+SUM(M13:P13) -> 181784 | R13: =R34 -> 38296.02 | S13: =S34 -> 67018.035 | T13: =T34 -> 83772.544 | U13: =U34 -> 47750.35 | V13: =SUM(R13:U13) -> 236836.95 | W13: =W34 -> 41542.804 | X13: =X34 -> 82877.895 | Y13: =Y34 -> 104011.76 | Z13: =Z34 -> 55126.232 | AA13: =SUM(W13:Z13) -> 283558.69 | AB13: =AB34 -> 351612.77 | AC13: =AC34 -> 502806.27 | AD13: =AD34 -> 698900.71 | AF13: =IFERROR((Q13/G13)^(1/3)-1,"--") -> 0.2439984 | AG13: =IFERROR((AD13/Q13)^(1/5)-1,"--") -> 0.30909742
B14: % Growth | D14: =D41 -> 0.071838656 | E14: =E41 -> -0.06649547 | F14: =F41 -> 0.18768854 | G14: =G41 -> 0 | H14: =+H13/F13-1 -> -0.20072809 | I14: =I41 -> 0.12244555 | J14: =J41 -> 0.27916338 | K14: =K41 -> -0.11397277 | L14: =L41 -> -0.036307284 | M14: =+M13/K13-1 -> -0.1520067 | N14: =N41 -> 0.069683508 | O14: =O41 -> 0.14107791 | P14: =P41 -> -0.025964502 | Q14: =Q41 -> 0.12807374 | R14: =R41 -> 0.03 | S14: =S41 -> 0.0675 | T14: =T41 -> 0.0475 | U14: =U41 -> 0.015 | ... AD14: =AD41 -> 0.09
B15: =Model!B9 -> Fee-Related Compensation | C15: ='Segment Analysis'!E10 -> -203094 | D15: ='Segment Analysis'!F10 -> -217684 | E15: ='Segment Analysis'!G10 -> -203209 | F15: ='Segment Analysis'!H10 -> -241349 | G15: =+SUM(C15:F15) -> -865336 | H15: ='Segment Analysis'!J10 -> -172640 | I15: ='Segment Analysis'!K10 -> -193779 | J15: ='Segment Analysis'!L10 -> -247875 | K15: ='Segment Analysis'!M10 -> -219624 | L15: =+SUM(H15:K15) -> -833918 | M15: ='Segment Analysis'!O10 -> -210021 | N15: ='Segment Analysis'!P10 -> -224656 | O15: ='Segment Analysis'!Q10 -> -256350 | P15: ='Segment Analysis'!R10 -> -249694 | Q15: =+SUM(M15:P15) -> -940721 | R15: =R40 -> -257184.82 | S15: =S40 -> -274544.8 | T15: =T40 -> -287585.67 | U15: =U40 -> -291899.46 | V15: =SUM(R15:U15) -> -1111214.7 | W15: =W40 -> -302115.94 | X15: =X40 -> -324774.63 | Y15: =Y40 -> -337765.62 | Z15: =Z40 -> -341143.28 | AA15: =SUM(W15:Z15) -> -1305799.5 | AB15: =AB40 -> -1462495.4 | AC15: =AC40 -> -1652619.8 | AD15: =AD40 -> -1801355.6 | AF15: =IFERROR((Q15/G15)^(1/3)-1,"--") -> 0.028234147 | AG15: =IFERROR((AD15/Q15)^(1/5)-1,"--") -> 0.13874825
B16: % Growth | D16: =D41 -> 0.071838656 | E16: =E41 -> -0.06649547 | F16: =F41 -> 0.18768854 | G16: =G41 -> 0 | H16: =+H15/F15-1 -> -0.28468732 | I16: =I41 -> 0.12244555 | J16: =J41 -> 0.27916338 | K16: =K41 -> -0.11397277 | L16: =L41 -> -0.036307284 | M16: =+M15/K15-1 -> -0.04372473 | N16: =N41 -> 0.069683508 | O16: =O41 -> 0.14107791 | P16: =P41 -> -0.025964502 | Q16: =Q41 -> 0.12807374 | R16: =R41 -> 0.03 | S16: =S41 -> 0.0675 | T16: =T41 -> 0.0475 | U16: =U41 -> 0.015 | ... AD16: =AD41 -> 0.09
B17: =Model!B10 -> Other Operating Expenses | C17: ='Segment Analysis'!E11 -> -150404 | D17: ='Segment Analysis'!F11 -> -147475 | E17: ='Segment Analysis'!G11 -> -142416 | F17: ='Segment Analysis'!H11 -> -155989 | G17: =+SUM(C17:F17) -> -596284 | H17: ='Segment Analysis'!J11 -> -145131 | I17: ='Segment Analysis'!K11 -> -158134 | J17: ='Segment Analysis'!L11 -> -167881 | K17: ='Segment Analysis'!M11 -> -192397 | L17: =+SUM(H17:K17) -> -663543 | M17: ='Segment Analysis'!O11 -> -167496 | N17: ='Segment Analysis'!P11 -> -172339 | O17: ='Segment Analysis'!Q11 -> -175568 | P17: ='Segment Analysis'!R11 -> -204765 | Q17: =+SUM(M17:P17) -> -720168 | R17: =R46 -> -188383.8 | S17: =S46 -> -194035.31 | T17: =T46 -> -198886.2 | U17: =U46 -> -222255.32 | V17: =SUM(R17:U17) -> -803560.64 | W17: =W46 -> -206697.45 | X17: =X46 -> -215998.84 | Y17: =Y46 -> -222478.8 | Z17: =Z46 -> -246951.47 | AA17: =SUM(W17:Z17) -> -892126.56 | AB17: =AB46 -> -965727.01 | AC17: =AC46 -> -1177221.2 | AD17: =AD46 -> -1387943.8 | AF17: =IFERROR((Q17/G17)^(1/3)-1,"--") -> 0.064944287 | AG17: =IFERROR((AD17/Q17)^(1/5)-1,"--") -> 0.14021727
B18: % Growth | D18: =D47 -> -0.019474216 | E18: =E47 -> -0.034304119 | F18: =F47 -> 0.095305303 | G18: =G47 -> 0 | H18: =+H17/F17-1 -> -0.069607472 | I18: =I47 -> 0.089594918 | J18: =J47 -> 0.061637598 | K18: =K47 -> 0.14603201 | L18: =L47 -> 0.11279692 | M18: =+M17/K17-1 -> -0.12942509 | N18: =N47 -> 0.028914123 | O18: =O47 -> 0.018736328 | P18: =P47 -> 0.16630024 | Q18: =Q47 -> 0.085337348 | R18: =R47 -> -0.08 | S18: =S47 -> 0.03 | T18: =T47 -> 0.025 | U18: =U47 -> 0.1175 | ... AD18: =AD47 -> 0.179
A20: x | B20: Growth Rate | C20: =C5 -> 1Q23 | D20: =D5 -> 2Q23 | E20: =E5 -> 3Q23 | F20: =F5 -> 4Q23 | G20: =G5 -> 2023 | H20: =H5 -> 1Q24 | I20: =I5 -> 2Q24 | J20: =J5 -> 3Q24 | ... AD20: =AD5 -> 2030e
B22: =B9 -> Management Fees | C22: =C9 -> 738156 | D22: =D9 -> 748888 | E22: =E9 -> 758700 | F22: =F9 -> 784581 | G22: =G9 -> 3030325 | H22: =H9 -> 815327 | I22: =I9 -> 847307 | ... Q22: =Q9 -> 4100841 | R22: =P22*(1+R23) -> 1143864.3 | S22: =R22*(1+S23) -> 1185043.5 | T22: =S22*(1+T23) -> 1241925.5 | U22: =T22*(1+U23) -> 1291602.6 | V22: =SUM(R22:U22) -> 4862435.9 | W22: =U22*(1+W23) -> 1346495.7 | X22: =W22*(1+X23) -> 1397662.5 | Y22: =X22*(1+Y23) -> 1453569 | Z22: =Y22*(1+Z23) -> 1504443.9 | AA22: =SUM(W22:Z22) -> 5702171.1 | AB22: =AA22*(1+AB23) -> 6295196.9 | AC22: =AB22*(1+AC23) -> 7230033.7 | AD22: =AC22*(1+AD23) -> 8014492.3
B23: =B10 -> % Growth | D23: =D22/C22-1 -> 0.014538932 | E23: =E22/D22-1 -> 0.013102093 | F23: =F22/E22-1 -> 0.034112297 | G23: 0 | H23: =H22/F22-1 -> 0.039187796 | I23: =I22/H22-1 -> 0.039223526 | J23: =J22/I22-1 -> 0.053489467 | K23: =K22/J22-1 -> 0.015111541 | L23: =L22/G22-1 -> 0.14224745 | M23: =M22/K22-1 -> 0.012378079 | N23: =N22/M22-1 -> 0.085496668 | O23: =O22/N22-1 -> 0.068078448 | P23: =P22/O22-1 -> 0.057014554 | Q23: =Q22/L22-1 -> 0.18474129 | R23: =IF(Case_Scenario="Bull",R24,IF(Case_Scenario="Base",R25,IF(Case_Scenario="Bear",R26,"N/A"))) -> 0.0175 | S23: =IF(Case_Scenario="Bull",S24,IF(Case_Scenario="Base",S25,IF(Case_Scenario="Bear",S26,"N/A"))) -> 0.036 | T23: =IF(Case_Scenario="Bull",T24,IF(Case_Scenario="Base",T25,IF(Case_Scenario="Bear",T26,"N/A"))) -> 0.048 | U23: =IF(Case_Scenario="Bull",U24,IF(Case_Scenario="Base",U25,IF(Case_Scenario="Bear",U26,"N/A"))) -> 0.04 | V23: =V22/Q22-1 -> 0.18571676 | W23: =IF(Case_Scenario="Bull",W24,IF(Case_Scenario="Base",W25,IF(Case_Scenario="Bear",W26,"N/A"))) -> 0.0425 | X23: =IF(Case_Scenario="Bull",X24,IF(Case_Scenario="Base",X25,IF(Case_Scenario="Bear",X26,"N/A"))) -> 0.038 | Y23: =IF(Case_Scenario="Bull",Y24,IF(Case_Scenario="Base",Y25,IF(Case_Scenario="Bear",Y26,"N/A"))) -> 0.04 | Z23: =IF(Case_Scenario="Bull",Z24,IF(Case_Scenario="Base",Z25,IF(Case_Scenario="Bear",Z26,"N/A"))) -> 0.035 | AA23: =AA22/V22-1 -> 0.17269846 | AB23: =IF(Case_Scenario="Bull",AB24,IF(Case_Scenario="Base",AB25,IF(Case_Scenario="Bear",AB26,"N/A"))) -> 0.104 | AC23: =IF(Case_Scenario="Bull",AC24,IF(Case_Scenario="Base",AC25,IF(Case_Scenario="Bear",AC26,"N/A"))) -> 0.1485 | AD23: =IF(Case_Scenario="Bull",AD24,IF(Case_Scenario="Base",AD25,IF(Case_Scenario="Bear",AD26,"N/A"))) -> 0.1085
B24: Bull Case | R24: =R25+1% -> 0.0275 | S24: =S25+1% -> 0.046 | T24: =T25+1% -> 0.058 | U24: =U25+1% -> 0.05 | W24: =W25+1% -> 0.0525 | X24: =X25+1% -> 0.048 | Y24: =Y25+1% -> 0.05 | Z24: =Z25+1% -> 0.045 | AB24: =AB25+1% -> 0.114 | AC24: =AC25+1% -> 0.1585 | AD24: =AD25+1% -> 0.1185
B25: Base Case | R25: 0.0175 | S25: 0.036 | T25: 0.048 | U25: 0.04 | W25: 0.0425 | X25: 0.038 | Y25: 0.04 | Z25: 0.035 | AB25: 0.104 | AC25: 0.1485 | AD25: =+AC25-4% -> 0.1085
B26: Bear Case | R26: =R25-1% -> 0.0075 | S26: =S25-1% -> 0.026 | T26: =T25-1% -> 0.038 | U26: =U25-1% -> 0.03 | W26: =W25-1% -> 0.0325 | X26: =X25-1% -> 0.028 | Y26: =Y25-1% -> 0.03 | Z26: =Z25-1% -> 0.025 | AB26: =AB25-1% -> 0.094 | AC26: =AC25-1% -> 0.1385 | AD26: =AD25-1% -> 0.0985
B28: =B11 -> Transaction and Monitoring Fees | C28: =C11 -> 142179 | D28: =D11 -> 190228 | E28: =E11 -> 124014 | F28: =F11 -> 264233 | G28: =G11 -> 720654 | H28: =H11 -> 152084 | I28: =I11 -> 222858 | ... Q28: =Q11 -> 1092577 | R28: =P28*(1+R29) -> 297579.71 | S28: =R28*(1+S29) -> 331057.43 | T28: =S28*(1+T29) -> 335195.65 | U28: =T28*(1+U29) -> 355307.39 | V28: =SUM(R28:U28) -> 1319140.2 | W28: =U28*(1+W29) -> 353530.85 | X28: =W28*(1+X29) -> 396838.38 | Y28: =X28*(1+Y29) -> 400806.76 | Z28: =Y28*(1+Z29) -> 418843.07 | AA28: =SUM(W28:Z28) -> 1570019.1 | AB28: =AA28*(1+AB29) -> 1703470.7 | AC28: =AB28*(1+AC29) -> 1682177.3 | AD28: =AC28*(1+AD29) -> 1593863
B29: =B16 -> % Growth | D29: =D28/C28-1 -> 0.33794724 | E29: =E28/D28-1 -> -0.34807704 | F29: =F28/E28-1 -> 1.1306707 | G29: 0 | H29: =H28/F28-1 -> -0.42443222 | I29: =I28/H28-1 -> 0.46536125 | J29: =J28/I28-1 -> 1.0961554 | K29: =K28/J28-1 -> -0.30685975 | L29: =L28/G28-1 -> 0.61781382 | M29: =M28/K28-1 -> -0.19236744 | N29: =N28/M28-1 -> -0.10424115 | O29: =O28/N28-1 -> 0.40074878 | P29: =P28/O28-1 -> -0.1811175 | Q29: =Q28/L28-1 -> -0.062876753 | R29: =IF(Case_Scenario="Bull",R30,IF(Case_Scenario="Base",R31,IF(Case_Scenario="Bear",R32,"N/A"))) -> 0.1075 | S29: =IF(Case_Scenario="Bull",S30,IF(Case_Scenario="Base",S31,IF(Case_Scenario="Bear",S32,"N/A"))) -> 0.1125 | T29: =IF(Case_Scenario="Bull",T30,IF(Case_Scenario="Base",T31,IF(Case_Scenario="Bear",T32,"N/A"))) -> 0.0125 | U29: =IF(Case_Scenario="Bull",U30,IF(Case_Scenario="Base",U31,IF(Case_Scenario="Bear",U32,"N/A"))) -> 0.06 | V29: =V28/Q28-1 -> 0.20736587 | W29: =IF(Case_Scenario="Bull",W30,IF(Case_Scenario="Base",W31,IF(Case_Scenario="Bear",W32,"N/A"))) -> -0.005 | X29: =IF(Case_Scenario="Bull",X30,IF(Case_Scenario="Base",X31,IF(Case_Scenario="Bear",X32,"N/A"))) -> 0.1225 | Y29: =IF(Case_Scenario="Bull",Y30,IF(Case_Scenario="Base",Y31,IF(Case_Scenario="Bear",Y32,"N/A"))) -> 0.01 | Z29: =IF(Case_Scenario="Bull",Z30,IF(Case_Scenario="Base",Z31,IF(Case_Scenario="Bear",Z32,"N/A"))) -> 0.045 | AA29: =AA28/V28-1 -> 0.19018364 | AB29: =IF(Case_Scenario="Bull",AB30,IF(Case_Scenario="Base",AB31,IF(Case_Scenario="Bear",AB32,"N/A"))) -> 0.085 | AC29: =IF(Case_Scenario="Bull",AC30,IF(Case_Scenario="Base",AC31,IF(Case_Scenario="Bear",AC32,"N/A"))) -> -0.0125 | AD29: =IF(Case_Scenario="Bull",AD30,IF(Case_Scenario="Base",AD31,IF(Case_Scenario="Bear",AD32,"N/A"))) -> -0.0525
B30: Bull Case | R30: =R31+1% -> 0.1175 | S30: =S31+1% -> 0.1225 | T30: =T31+1% -> 0.0225 | U30: =U31+1% -> 0.07 | W30: =W31+1% -> 0.005 | X30: =X31+1% -> 0.1325 | Y30: =Y31+1% -> 0.02 | Z30: =Z31+1% -> 0.055 | AB30: =AB31+1% -> 0.095 | AC30: =AC31+1% -> -0.0025 | AD30: =AD31+1% -> -0.0425
B31: Base Case | R31: 0.1075 | S31: 0.1125 | T31: 0.0125 | U31: 0.06 | W31: -0.005 | X31: 0.1225 | Y31: 0.01 | Z31: 0.045 | AB31: 0.085 | AC31: -0.0125 | AD31: =+AC31-4% -> -0.0525
B32: Bear Case | R32: =R31-1% -> 0.0975 | S32: =S31-1% -> 0.1025 | T32: =T31-1% -> 0.0025 | U32: =U31-1% -> 0.05 | W32: =W31-1% -> -0.015 | X32: =X31-1% -> 0.1125 | Y32: =Y31-1% -> 0 | Z32: =Z31-1% -> 0.035 | AB32: =AB31-1% -> 0.075 | AC32: =AC31-1% -> -0.0225 | AD32: =AD31-1% -> -0.0625
B34: =B13 -> Fee-Related Performance Revenues | C34: =C13 -> 21741 | D34: =D13 -> 28352 | E34: =E13 -> 20436 | F34: =F13 -> 23898 | G34: =G13 -> 94427 | H34: =H13 -> 19101 | I34: =I13 -> 37145 | ... Q34: =Q13 -> 181784 | R34: =P34*(1+R35) -> 38296.02 | S34: =R34*(1+S35) -> 67018.035 | T34: =S34*(1+T35) -> 83772.544 | U34: =T34*(1+U35) -> 47750.35 | V34: =SUM(R34:U34) -> 236836.95 | W34: =U34*(1+W35) -> 41542.804 | X34: =W34*(1+X35) -> 82877.895 | Y34: =X34*(1+Y35) -> 104011.76 | Z34: =Y34*(1+Z35) -> 55126.232 | AA34: =SUM(W34:Z34) -> 283558.69 | AB34: =AA34*(1+AB35) -> 351612.77 | AC34: =AB34*(1+AC35) -> 502806.27 | AD34: =AC34*(1+AD35) -> 698900.71
B35: % Growth | D35: =D34/C34-1 -> 0.30407985 | E35: =E34/D34-1 -> -0.27920429 | F35: =F34/E34-1 -> 0.16940693 | G35: 0 | H35: =H34/F34-1 -> -0.20072809 | I35: =I34/H34-1 -> 0.94466258 | J35: =J34/I34-1 -> 0.52523893 | K35: =K34/J34-1 -> -0.55712647 | L35: =L34/G34-1 -> 0.46136169 | M35: =M34/K34-1 -> -0.1520067 | N35: =N34/M34-1 -> 1.525591 | O35: =O34/N34-1 -> 0.36176191 | P35: =P34/O34-1 -> -0.54093499 | Q35: =Q34/L34-1 -> 0.31735173 | R35: =IF(Case_Scenario="Bull",R36,IF(Case_Scenario="Base",R37,IF(Case_Scenario="Bear",R38,"N/A"))) -> 0.14 | S35: =IF(Case_Scenario="Bull",S36,IF(Case_Scenario="Base",S37,IF(Case_Scenario="Bear",S38,"N/A"))) -> 0.75 | T35: =IF(Case_Scenario="Bull",T36,IF(Case_Scenario="Base",T37,IF(Case_Scenario="Bear",T38,"N/A"))) -> 0.25 | U35: =IF(Case_Scenario="Bull",U36,IF(Case_Scenario="Base",U37,IF(Case_Scenario="Bear",U38,"N/A"))) -> -0.43 | V35: =V34/Q34-1 -> 0.30284815 | W35: =IF(Case_Scenario="Bull",W36,IF(Case_Scenario="Base",W37,IF(Case_Scenario="Bear",W38,"N/A"))) -> -0.13 | X35: =IF(Case_Scenario="Bull",X36,IF(Case_Scenario="Base",X37,IF(Case_Scenario="Bear",X38,"N/A"))) -> 0.995 | Y35: =IF(Case_Scenario="Bull",Y36,IF(Case_Scenario="Base",Y37,IF(Case_Scenario="Bear",Y38,"N/A"))) -> 0.255 | Z35: =IF(Case_Scenario="Bull",Z36,IF(Case_Scenario="Base",Z37,IF(Case_Scenario="Bear",Z38,"N/A"))) -> -0.47 | AA35: =AA34/V34-1 -> 0.19727387 | AB35: =IF(Case_Scenario="Bull",AB36,IF(Case_Scenario="Base",AB37,IF(Case_Scenario="Bear",AB38,"N/A"))) -> 0.24 | AC35: =IF(Case_Scenario="Bull",AC36,IF(Case_Scenario="Base",AC37,IF(Case_Scenario="Bear",AC38,"N/A"))) -> 0.43 | AD35: =IF(Case_Scenario="Bull",AD36,IF(Case_Scenario="Base",AD37,IF(Case_Scenario="Bear",AD38,"N/A"))) -> 0.39
B36: Bull Case | R36: =R37+1% -> 0.15 | S36: =S37+1% -> 0.76 | T36: =T37+1% -> 0.26 | U36: =U37+1% -> -0.42 | W36: =W37+1% -> -0.12 | X36: =X37+1% -> 1.005 | Y36: =Y37+1% -> 0.265 | Z36: =Z37+1% -> -0.46 | AB36: =AB37+1% -> 0.25 | AC36: =AC37+1% -> 0.44 | AD36: =AD37+1% -> 0.4
B37: Base Case | R37: 0.14 | S37: 0.75 | T37: 0.25 | U37: -0.43 | W37: -0.13 | X37: 0.995 | Y37: 0.255 | Z37: -0.47 | AB37: 0.24 | AC37: 0.43 | AD37: =+AC37-4% -> 0.39
B38: Bear Case | R38: =R37-1% -> 0.13 | S38: =S37-1% -> 0.74 | T38: =T37-1% -> 0.24 | U38: =U37-1% -> -0.44 | W38: =W37-1% -> -0.14 | X38: =X37-1% -> 0.985 | Y38: =Y37-1% -> 0.245 | Z38: =Z37-1% -> -0.48 | AB38: =AB37-1% -> 0.23 | AC38: =AC37-1% -> 0.42 | AD38: =AD37-1% -> 0.38
B40: =B15 -> Fee-Related Compensation | C40: =C15 -> -203094 | D40: =D15 -> -217684 | E40: =E15 -> -203209 | F40: =F15 -> -241349 | G40: =G15 -> -865336 | H40: =H15 -> -172640 | I40: =I15 -> -193779 | ... Q40: =Q15 -> -940721 | R40: =P40*(1+R41) -> -257184.82 | S40: =R40*(1+S41) -> -274544.8 | T40: =S40*(1+T41) -> -287585.67 | U40: =T40*(1+U41) -> -291899.46 | V40: =SUM(R40:U40) -> -1111214.7 | W40: =U40*(1+W41) -> -302115.94 | X40: =W40*(1+X41) -> -324774.63 | Y40: =X40*(1+Y41) -> -337765.62 | Z40: =Y40*(1+Z41) -> -341143.28 | AA40: =SUM(W40:Z40) -> -1305799.5 | AB40: =AA40*(1+AB41) -> -1462495.4 | AC40: =AB40*(1+AC41) -> -1652619.8 | AD40: =AC40*(1+AD41) -> -1801355.6
B41: =B23 -> % Growth | D41: =D40/C40-1 -> 0.071838656 | E41: =E40/D40-1 -> -0.06649547 | F41: =F40/E40-1 -> 0.18768854 | G41: 0 | H41: =H40/F40-1 -> -0.28468732 | I41: =I40/H40-1 -> 0.12244555 | J41: =J40/I40-1 -> 0.27916338 | K41: =K40/J40-1 -> -0.11397277 | L41: =L40/G40-1 -> -0.036307284 | M41: =M40/K40-1 -> -0.04372473 | N41: =N40/M40-1 -> 0.069683508 | O41: =O40/N40-1 -> 0.14107791 | P41: =P40/O40-1 -> -0.025964502 | Q41: =Q40/L40-1 -> 0.12807374 | R41: =IF(Case_Scenario="Bull",R42,IF(Case_Scenario="Base",R43,IF(Case_Scenario="Bear",R44,"N/A"))) -> 0.03 | S41: =IF(Case_Scenario="Bull",S42,IF(Case_Scenario="Base",S43,IF(Case_Scenario="Bear",S44,"N/A"))) -> 0.0675 | T41: =IF(Case_Scenario="Bull",T42,IF(Case_Scenario="Base",T43,IF(Case_Scenario="Bear",T44,"N/A"))) -> 0.0475 | U41: =IF(Case_Scenario="Bull",U42,IF(Case_Scenario="Base",U43,IF(Case_Scenario="Bear",U44,"N/A"))) -> 0.015 | V41: =V40/Q40-1 -> 0.18123731 | W41: =IF(Case_Scenario="Bull",W42,IF(Case_Scenario="Base",W43,IF(Case_Scenario="Bear",W44,"N/A"))) -> 0.035 | X41: =IF(Case_Scenario="Bull",X42,IF(Case_Scenario="Base",X43,IF(Case_Scenario="Bear",X44,"N/A"))) -> 0.075 | Y41: =IF(Case_Scenario="Bull",Y42,IF(Case_Scenario="Base",Y43,IF(Case_Scenario="Bear",Y44,"N/A"))) -> 0.04 | Z41: =IF(Case_Scenario="Bull",Z42,IF(Case_Scenario="Base",Z43,IF(Case_Scenario="Bear",Z44,"N/A"))) -> 0.01 | AA41: =AA40/V40-1 -> 0.17510992 | AB41: =IF(Case_Scenario="Bull",AB42,IF(Case_Scenario="Base",AB43,IF(Case_Scenario="Bear",AB44,"N/A"))) -> 0.12 | AC41: =IF(Case_Scenario="Bull",AC42,IF(Case_Scenario="Base",AC43,IF(Case_Scenario="Bear",AC44,"N/A"))) -> 0.13 | AD41: =IF(Case_Scenario="Bull",AD42,IF(Case_Scenario="Base",AD43,IF(Case_Scenario="Bear",AD44,"N/A"))) -> 0.09
B42: Bull Case | R42: =R43+1% -> 0.04 | S42: =S43+1% -> 0.0775 | T42: =T43+1% -> 0.0575 | U42: =U43+1% -> 0.025 | W42: =W43+1% -> 0.045 | X42: =X43+1% -> 0.085 | Y42: =Y43+1% -> 0.05 | Z42: =Z43+1% -> 0.02 | AB42: =AB43+1% -> 0.13 | AC42: =AC43+1% -> 0.14 | AD42: =AD43+1% -> 0.1
B43: Base Case | R43: 0.03 | S43: 0.0675 | T43: 0.0475 | U43: 0.015 | W43: 0.035 | X43: 0.075 | Y43: 0.04 | Z43: 0.01 | AB43: 0.12 | AC43: 0.13 | AD43: =+AC43-4% -> 0.09
B44: Bear Case | R44: =R43-1% -> 0.02 | S44: =S43-1% -> 0.0575 | T44: =T43-1% -> 0.0375 | U44: =U43-1% -> 0.005 | W44: =W43-1% -> 0.025 | X44: =X43-1% -> 0.065 | Y44: =Y43-1% -> 0.03 | Z44: =Z43-1% -> 0 | AB44: =AB43-1% -> 0.11 | AC44: =AC43-1% -> 0.12 | AD44: =AD43-1% -> 0.08
B46: =B17 -> Other Operating Expenses | C46: =C17 -> -150404 | D46: =D17 -> -147475 | E46: =E17 -> -142416 | F46: =F17 -> -155989 | G46: =G17 -> -596284 | H46: =H17 -> -145131 | I46: =I17 -> -158134 | ... Q46: =Q17 -> -720168 | R46: =P46*(1+R47) -> -188383.8 | S46: =R46*(1+S47) -> -194035.31 | T46: =S46*(1+T47) -> -198886.2 | U46: =T46*(1+U47) -> -222255.32 | V46: =SUM(R46:U46) -> -803560.64 | W46: =U46*(1+W47) -> -206697.45 | X46: =W46*(1+X47) -> -215998.84 | Y46: =X46*(1+Y47) -> -222478.8 | Z46: =Y46*(1+Z47) -> -246951.47 | AA46: =SUM(W46:Z46) -> -892126.56 | AB46: =AA46*(1+AB47) -> -965727.01 | AC46: =AB46*(1+AC47) -> -1177221.2 | AD46: =AC46*(1+AD47) -> -1387943.8
B47: =B29 -> % Growth | D47: =D46/C46-1 -> -0.019474216 | E47: =E46/D46-1 -> -0.034304119 | F47: =F46/E46-1 -> 0.095305303 | G47: 0 | H47: =H46/F46-1 -> -0.069607472 | I47: =I46/H46-1 -> 0.089594918 | J47: =J46/I46-1 -> 0.061637598 | K47: =K46/J46-1 -> 0.14603201 | L47: =L46/G46-1 -> 0.11279692 | M47: =M46/K46-1 -> -0.12942509 | N47: =N46/M46-1 -> 0.028914123 | O47: =O46/N46-1 -> 0.018736328 | P47: =P46/O46-1 -> 0.16630024 | Q47: =Q46/L46-1 -> 0.085337348 | R47: =IF(Case_Scenario="Bull",R48,IF(Case_Scenario="Base",R49,IF(Case_Scenario="Bear",R50,"N/A"))) -> -0.08 | S47: =IF(Case_Scenario="Bull",S48,IF(Case_Scenario="Base",S49,IF(Case_Scenario="Bear",S50,"N/A"))) -> 0.03 | T47: =IF(Case_Scenario="Bull",T48,IF(Case_Scenario="Base",T49,IF(Case_Scenario="Bear",T50,"N/A"))) -> 0.025 | U47: =IF(Case_Scenario="Bull",U48,IF(Case_Scenario="Base",U49,IF(Case_Scenario="Bear",U50,"N/A"))) -> 0.1175 | V47: =V46/Q46-1 -> 0.11579609 | W47: =IF(Case_Scenario="Bull",W48,IF(Case_Scenario="Base",W49,IF(Case_Scenario="Bear",W50,"N/A"))) -> -0.07 | X47: =IF(Case_Scenario="Bull",X48,IF(Case_Scenario="Base",X49,IF(Case_Scenario="Bear",X50,"N/A"))) -> 0.045 | Y47: =IF(Case_Scenario="Bull",Y48,IF(Case_Scenario="Base",Y49,IF(Case_Scenario="Bear",Y50,"N/A"))) -> 0.03 | Z47: =IF(Case_Scenario="Bull",Z48,IF(Case_Scenario="Base",Z49,IF(Case_Scenario="Bear",Z50,"N/A"))) -> 0.11 | AA47: =AA46/V46-1 -> 0.11021686 | AB47: =IF(Case_Scenario="Bull",AB48,IF(Case_Scenario="Base",AB49,IF(Case_Scenario="Bear",AB50,"N/A"))) -> 0.0825 | AC47: =IF(Case_Scenario="Bull",AC48,IF(Case_Scenario="Base",AC49,IF(Case_Scenario="Bear",AC50,"N/A"))) -> 0.219 | AD47: =IF(Case_Scenario="Bull",AD48,IF(Case_Scenario="Base",AD49,IF(Case_Scenario="Bear",AD50,"N/A"))) -> 0.179
B48: Bull Case | R48: =R49+1% -> -0.07 | S48: =S49+1% -> 0.04 | T48: =T49+1% -> 0.035 | U48: =U49+1% -> 0.1275 | W48: =W49+1% -> -0.06 | X48: =X49+1% -> 0.055 | Y48: =Y49+1% -> 0.04 | Z48: =Z49+1% -> 0.12 | AB48: =AB49+1% -> 0.0925 | AC48: =AC49+1% -> 0.229 | AD48: =AD49+1% -> 0.189
B49: Base Case | R49: -0.08 | S49: 0.03 | T49: 0.025 | U49: 0.1175 | W49: -0.07 | X49: 0.045 | Y49: 0.03 | Z49: 0.11 | AB49: 0.0825 | AC49: 0.219 | AD49: =+AC49-4% -> 0.179
B50: Bear Case | R50: =R49-1% -> -0.09 | S50: =S49-1% -> 0.02 | T50: =T49-1% -> 0.015 | U50: =U49-1% -> 0.1075 | W50: =W49-1% -> -0.08 | X50: =X49-1% -> 0.035 | Y50: =Y49-1% -> 0.02 | Z50: =Z49-1% -> 0.1 | AB50: =AB49-1% -> 0.0725 | AC50: =AC49-1% -> 0.209 | AD50: =AD49-1% -> 0.169
B52: End

Sheet Model
A2: x | B2: Income Statement | E2: ='Segment Analysis'!E2 -> 1Q23 | F2: ='Segment Analysis'!F2 -> 2Q23 | G2: ='Segment Analysis'!G2 -> 3Q23 | H2: ='Segment Analysis'!H2 -> 4Q23 | I2: ='Segment Analysis'!I2 -> 2023 | J2: ='Segment Analysis'!J2 -> 1Q24 | K2: ='Segment Analysis'!K2 -> 2Q24 | L2: ='Segment Analysis'!L2 -> 3Q24 | ... AF2: ='Segment Analysis'!AF2 -> 2030e
B5: Asset Management
B6: {=+'Segment Analysis'!B7:B11} -> Management Fees | E6: =+'Segment Analysis'!E7 -> 738156 | F6: =+'Segment Analysis'!F7 -> 748888 | G6: =+'Segment Analysis'!G7 -> 758700 | H6: =+'Segment Analysis'!H7 -> 784581 | I6: =+SUM(E6:H6) -> 3030325 | J6: =+'Segment Analysis'!J7 -> 815327 | K6: =+'Segment Analysis'!K7 -> 847307 | L6: =+'Segment Analysis'!L7 -> 892629 | M6: =+'Segment Analysis'!M7 -> 906118 | N6: =+SUM(J6:M6) -> 3461381 | O6: =+'Segment Analysis'!O7 -> 917334 | P6: =+'Segment Analysis'!P7 -> 995763 | Q6: =+'Segment Analysis'!Q7 -> 1063553 | R6: =+'Segment Analysis'!R7 -> 1124191 | S6: =+SUM(O6:R6) -> 4100841 | T6: =+'Revenue Build'!R9 -> 1143864.3 | U6: =+'Revenue Build'!S9 -> 1185043.5 | V6: =+'Revenue Build'!T9 -> 1241925.5 | W6: =+'Revenue Build'!U9 -> 1291602.6 | X6: =+SUM(T6:W6) -> 4862435.9 | Y6: =+'Revenue Build'!W9 -> 1346495.7 | Z6: =+'Revenue Build'!X9 -> 1397662.5 | AA6: =+'Revenue Build'!Y9 -> 1453569 | AB6: =+'Revenue Build'!Z9 -> 1504443.9 | AC6: =+SUM(Y6:AB6) -> 5702171.1 | AD6: =+'Revenue Build'!AB9 -> 6295196.9 | AE6: =+'Revenue Build'!AC9 -> 7230033.7 | AF6: =+'Revenue Build'!AD9 -> 8014492.3
B7: Transaction and Monitoring Fees | E7: =+'Segment Analysis'!E8 -> 142179 | F7: =+'Segment Analysis'!F8 -> 190228 | G7: =+'Segment Analysis'!G8 -> 124014 | H7: =+'Segment Analysis'!H8 -> 264233 | I7: =+SUM(E7:H7) -> 720654 | J7: =+'Segment Analysis'!J8 -> 152084 | K7: =+'Segment Analysis'!K8 -> 222858 | L7: =+'Segment Analysis'!L8 -> 467145 | M7: =+'Segment Analysis'!M8 -> 323797 | N7: =+SUM(J7:M7) -> 1165884 | O7: =+'Segment Analysis'!O8 -> 261509 | P7: =+'Segment Analysis'!P8 -> 234249 | Q7: =+'Segment Analysis'!Q8 -> 328124 | R7: =+'Segment Analysis'!R8 -> 268695 | S7: =+SUM(O7:R7) -> 1092577 | T7: =+'Segment Analysis'!T8 -> 297579.71 | U7: =+'Segment Analysis'!U8 -> 331057.43 | V7: =+'Segment Analysis'!V8 -> 335195.65 | W7: =+'Segment Analysis'!W8 -> 355307.39 | X7: =+SUM(T7:W7) -> 1319140.2 | Y7: =+'Segment Analysis'!Y8 -> 353530.85 | Z7: =+'Segment Analysis'!Z8 -> 396838.38 | AA7: =+'Segment Analysis'!AA8 -> 400806.76 | AB7: =+'Segment Analysis'!AB8 -> 418843.07 | AC7: =+SUM(Y7:AB7) -> 1570019.1 | AD7: =+'Segment Analysis'!AD8 -> 1703470.7 | AE7: =+'Segment Analysis'!AE8 -> 1682177.3 | AF7: =+'Segment Analysis'!AF8 -> 1593863
B8: Fee-Related Performance Revenues | E8: =+'Segment Analysis'!E9 -> 21741 | F8: =+'Segment Analysis'!F9 -> 28352 | G8: =+'Segment Analysis'!G9 -> 20436 | H8: =+'Segment Analysis'!H9 -> 23898 | I8: =+SUM(E8:H8) -> 94427 | J8: =+'Segment Analysis'!J9 -> 19101 | K8: =+'Segment Analysis'!K9 -> 37145 | L8: =+'Segment Analysis'!L9 -> 56655 | M8: =+'Segment Analysis'!M9 -> 25091 | N8: =+SUM(J8:M8) -> 137992 | O8: =+'Segment Analysis'!O9 -> 21277 | P8: =+'Segment Analysis'!P9 -> 53737 | Q8: =+'Segment Analysis'!Q9 -> 73177 | R8: =+'Segment Analysis'!R9 -> 33593 | S8: =+SUM(O8:R8) -> 181784 | T8: =+'Segment Analysis'!T9 -> 38296.02 | U8: =+'Segment Analysis'!U9 -> 67018.035 | V8: =+'Segment Analysis'!V9 -> 83772.544 | W8: =+'Segment Analysis'!W9 -> 47750.35 | X8: =+SUM(T8:W8) -> 236836.95 | Y8: =+'Segment Analysis'!Y9 -> 41542.804 | Z8: =+'Segment Analysis'!Z9 -> 82877.895 | AA8: =+'Segment Analysis'!AA9 -> 104011.76 | AB8: =+'Segment Analysis'!AB9 -> 55126.232 | AC8: =+SUM(Y8:AB8) -> 283558.69 | AD8: =+'Segment Analysis'!AD9 -> 351612.77 | AE8: =+'Segment Analysis'!AE9 -> 502806.27 | AF8: =+'Segment Analysis'!AF9 -> 698900.71
B9: Fee-Related Compensation | E9: =+'Segment Analysis'!E10 -> -203094 | F9: =+'Segment Analysis'!F10 -> -217684 | G9: =+'Segment Analysis'!G10 -> -203209 | H9: =+'Segment Analysis'!H10 -> -241349 | I9: =+SUM(E9:H9) -> -865336 | J9: =+'Segment Analysis'!J10 -> -172640 | K9: =+'Segment Analysis'!K10 -> -193779 | L9: =+'Segment Analysis'!L10 -> -247875 | M9: =+'Segment Analysis'!M10 -> -219624 | N9: =+SUM(J9:M9) -> -833918 | O9: =+'Segment Analysis'!O10 -> -210021 | P9: =+'Segment Analysis'!P10 -> -224656 | Q9: =+'Segment Analysis'!Q10 -> -256350 | R9: =+'Segment Analysis'!R10 -> -249694 | S9: =+SUM(O9:R9) -> -940721 | T9: =+'Segment Analysis'!T10 -> -257184.82 | U9: =+'Segment Analysis'!U10 -> -274544.8 | V9: =+'Segment Analysis'!V10 -> -287585.67 | W9: =+'Segment Analysis'!W10 -> -291899.46 | X9: =+SUM(T9:W9) -> -1111214.7 | Y9: =+'Segment Analysis'!Y10 -> -302115.94 | Z9: =+'Segment Analysis'!Z10 -> -324774.63 | AA9: =+'Segment Analysis'!AA10 -> -337765.62 | AB9: =+'Segment Analysis'!AB10 -> -341143.28 | AC9: =+SUM(Y9:AB9) -> -1305799.5 | AD9: =+'Segment Analysis'!AD10 -> -1462495.4 | AE9: =+'Segment Analysis'!AE10 -> -1652619.8 | AF9: =+'Segment Analysis'!AF10 -> -1801355.6
B10: Other Operating Expenses | E10: =+'Segment Analysis'!E11 -> -150404 | F10: =+'Segment Analysis'!F11 -> -147475 | G10: =+'Segment Analysis'!G11 -> -142416 | H10: =+'Segment Analysis'!H11 -> -155989 | I10: =+SUM(E10:H10) -> -596284 | J10: =+'Segment Analysis'!J11 -> -145131 | K10: =+'Segment Analysis'!K11 -> -158134 | L10: =+'Segment Analysis'!L11 -> -167881 | M10: =+'Segment Analysis'!M11 -> -192397 | N10: =+SUM(J10:M10) -> -663543 | O10: =+'Segment Analysis'!O11 -> -167496 | P10: =+'Segment Analysis'!P11 -> -172339 | Q10: =+'Segment Analysis'!Q11 -> -175568 | R10: =+'Segment Analysis'!R11 -> -204765 | S10: =+SUM(O10:R10) -> -720168 | T10: =+'Segment Analysis'!T11 -> -188383.8 | U10: =+'Segment Analysis'!U11 -> -194035.31 | V10: =+'Segment Analysis'!V11 -> -198886.2 | W10: =+'Segment Analysis'!W11 -> -222255.32 | X10: =+SUM(T10:W10) -> -803560.64 | Y10: =+'Segment Analysis'!Y11 -> -206697.45 | Z10: =+'Segment Analysis'!Z11 -> -215998.84 | AA10: =+'Segment Analysis'!AA11 -> -222478.8 | AB10: =+'Segment Analysis'!AB11 -> -246951.47 | AC10: =+SUM(Y10:AB10) -> -892126.56 | AD10: =+'Segment Analysis'!AD11 -> -965727.01 | AE10: =+'Segment Analysis'!AE11 -> -1177221.2 | AF10: =+'Segment Analysis'!AF11 -> -1387943.8
B11: Fee-Related Earnings | E11: =+SUM(E6:E10) -> 548578 | F11: =+SUM(F6:F10) -> 602309 | G11: =+SUM(G6:G10) -> 557525 | H11: =+SUM(H6:H10) -> 675374 | I11: =+SUM(E11:H11) -> 2383786 | J11: =+SUM(J6:J10) -> 668741 | K11: =+SUM(K6:K10) -> 755397 | L11: =+SUM(L6:L10) -> 1000673 | M11: =+SUM(M6:M10) -> 842985 | N11: =+SUM(J11:M11) -> 3267796 | O11: =+SUM(O6:O10) -> 822603 | P11: =+SUM(P6:P10) -> 886754 | Q11: =+SUM(Q6:Q10) -> 1032936 | R11: =+SUM(R6:R10) -> 972020 | S11: =+SUM(O11:R11) -> 3714313 | T11: =SUM(T6:T10) -> 1034171.5 | U11: =SUM(U6:U10) -> 1114538.8 | V11: =SUM(V6:V10) -> 1174421.9 | W11: =SUM(W6:W10) -> 1180505.5 | X11: =+SUM(T11:W11) -> 4503637.7 | Y11: =SUM(Y6:Y10) -> 1232755.9 | Z11: =SUM(Z6:Z10) -> 1336605.3 | AA11: =SUM(AA6:AA10) -> 1398143.1 | AB11: =SUM(AB6:AB10) -> 1390318.5 | AC11: =+SUM(Y11:AB11) -> 5357822.8 | AD11: =SUM(AD6:AD10) -> 5922058 | AE11: =SUM(AE6:AE10) -> 6585176.2 | AF11: =SUM(AF6:AF10) -> 7117956.6
B12: % Growth | F12: =+F11/E11-1 -> 0.097945962 | G12: =+G11/F11-1 -> -0.074353862 | H12: =+H11/G11-1 -> 0.21137886 | J12: =+J11/I11-1 -> -0.71946265 | K12: =+K11/J11-1 -> 0.12958081 | L12: =+L11/K11-1 -> 0.32469814 | M12: =+M11/L11-1 -> -0.15758195 | N12: =+N11/I11-1 -> 0.37084285 | O12: =+O11/N11-1 -> -0.74826978 | P12: =+P11/O11-1 -> 0.077985371 | Q12: =+Q11/P11-1 -> 0.16485068 | R12: =+R11/Q11-1 -> -0.058973644 | S12: =+S11/N11-1 -> 0.13664164 | T12: =+T11/S11-1 -> -0.72157127 | U12: =+U11/T11-1 -> 0.077711833 | V12: =+V11/U11-1 -> 0.053728996 | W12: =+W11/V11-1 -> 0.0051801263 | X12: =+X11/S11-1 -> 0.21250892 | Y12: =+Y11/X11-1 -> -0.72627551 | Z12: =+Z11/Y11-1 -> 0.084241634 | AA12: =+AA11/Z11-1 -> 0.046040365 | AB12: =+AB11/AA11-1 -> -0.005596445 | AC12: =+AC11/X11-1 -> 0.18966561 | AD12: =+AD11/AC11-1 -> 0.10531052 | AE12: =+AE11/AD11-1 -> 0.11197429 | AF12: =+AF11/AE11-1 -> 0.080906022
B14: Realized Performance Income (Loss)
B15: Realized Performance Income | E15: 175398 | F15: 149334 | G15: 329266 | H15: =1065389-SUM(E15:G15) -> 411391 | I15: =+SUM(E15:H15) -> 1065389 | J15: 271545 | K15: 482309 | L15: 391920 | M15: =1822115-SUM(J15:L15) -> 676341 | N15: =+SUM(J15:M15) -> 1822115 | O15: 347920 | P15: 418850 | Q15: 930659 | R15: =1879512-SUM(O15:Q15) -> 182083 | S15: =+SUM(O15:R15) -> 1879512 | T15: =+R15*(1+T53) -> 682811.25 | U15: =+T15*(1+U53) -> 792061.05 | V15: =+U15*(1+V53) -> 891068.68 | W15: =+V15*(1+W53) -> 1118291.2 | X15: =+SUM(T15:W15) -> 3484232.2 | Y15: =+W15*(1+Y53) -> 944956.06 | Z15: =+Y15*(1+Z53) -> 1055988.4 | AA15: =+Z15*(1+AA53) -> 1108787.8 | AB15: =+AA15*(1+AB53) -> 1333317.3 | AC15: =+SUM(Y15:AB15) -> 4443049.6 | AD15: =+AC15*(1+AD53) -> 5049525.9 | AE15: =+AD15*(1+AE53) -> 4584464.6 | AF15: =+AE15*(1+AF53) -> 4721998.5
B16: Realized Performance Income Compensation | E16: -114009 | F16: -97085 | G16: -213816 | H16: =+-666440-SUM(E16:G16) -> -241530 | I16: =+SUM(E16:H16) -> -666440 | J16: -193547 | K16: -359470 | L16: -289994 | M16: =+-1213327-SUM(J16:L16) -> -370316 | N16: =+SUM(J16:M16) -> -1213327 | O16: -259931 | P16: -309536 | Q16: -697994 | R16: =+-1387776-SUM(O16:Q16) -> -120315 | S16: =+SUM(O16:R16) -> -1387776 | T16: =+T15*T54 -> -491624.1 | U16: =+U15*U54 -> -572264.11 | V16: =+V15*V54 -> -648252.47 | W16: =+W15*W54 -> -735276.46 | X16: =+SUM(T16:W16) -> -2447417.1 | Y16: =+Y15*Y54 -> -685093.14 | Z16: =+Z15*Z54 -> -768231.56 | AA16: =+AA15*AA54 -> -807197.53 | AB16: =+AB15*AB54 -> -879989.45 | AC16: =+SUM(Y16:AB16) -> -3140511.7 | AD16: =+AD15*AD54 -> -3634143.8 | AE16: =+AE15*AE54 -> -3295771.6 | AF16: =+AF15*AF54 -> -3398422.3
B17: Net Realized Performance Income (Loss) | E17: =+SUM(E15:E16) -> 61389 | F17: =+SUM(F15:F16) -> 52249 | G17: =+SUM(G15:G16) -> 115450 | H17: =+SUM(H15:H16) -> 169861 | I17: =+SUM(E17:H17) -> 398949 | J17: =+SUM(J15:J16) -> 77998 | K17: =+SUM(K15:K16) -> 122839 | L17: =+SUM(L15:L16) -> 101926 | M17: =+SUM(M15:M16) -> 306025 | N17: =+SUM(J17:M17) -> 608788 | O17: =+SUM(O15:O16) -> 87989 | P17: =+SUM(P15:P16) -> 109314 | Q17: =+SUM(Q15:Q16) -> 232665 | R17: =+SUM(R15:R16) -> 61768 | S17: =+SUM(O17:R17) -> 491736 | T17: =+SUM(T15:T16) -> 191187.15 | U17: =+SUM(U15:U16) -> 219796.94 | V17: =+SUM(V15:V16) -> 242816.22 | W17: =+SUM(W15:W16) -> 383014.73 | X17: =+SUM(T17:W17) -> 1036815 | Y17: =+SUM(Y15:Y16) -> 259862.92 | Z17: =+SUM(Z15:Z16) -> 287756.84 | AA17: =+SUM(AA15:AA16) -> 301590.29 | AB17: =+SUM(AB15:AB16) -> 453327.9 | AC17: =+SUM(Y17:AB17) -> 1302537.9 | AD17: =+SUM(AD15:AD16) -> 1415382.1 | AE17: =+SUM(AE15:AE16) -> 1288693 | AF17: =+SUM(AF15:AF16) -> 1323576.2
B19: Realized Performance Income (Loss)
B20: Realized Performance Income | E20: 198094 | F20: 114675 | G20: 231196 | H20: =690727-SUM(E20:G20) -> 146762 | I20: =+SUM(E20:H20) -> 690727 | J20: 134753 | K20: 138546 | L20: 151546 | M20: =534668-SUM(J20:L20) -> 109823 | N20: =+SUM(J20:M20) -> 534668 | O20: 217957 | P20: 153998 | Q20: 4436 | R20: =403455-SUM(O20:Q20) -> 27064 | S20: =+SUM(O20:R20) -> 403455 | T20: =+R20*(1+T57) -> 198920.4 | U20: =+T20*(1+U57) -> 208866.42 | V20: =+U20*(1+V57) -> 221398.41 | W20: =+V20*(1+W57) -> 270106.05 | X20: =+SUM(T20:W20) -> 899291.28 | Y20: =+W20*(1+Y57) -> 251198.63 | Z20: =+Y20*(1+Z57) -> 268782.53 | AA20: =+Z20*(1+AA57) -> 275233.32 | AB20: =+AA20*(1+AB57) -> 297251.98 | AC20: =+SUM(Y20:AB20) -> 1092466.5 | AD20: =+AC20*(1+AD57) -> 1398357.1 | AE20: =+AD20*(1+AE57) -> 1514420.7 | AF20: =+AE20*(1+AF57) -> 1590141.7
B21: Realized Performance Income Compensation | E21: -29714 | F21: -17183 | G21: -34679 | H21: =+-103590-SUM(E21:G21) -> -22014 | I21: =+SUM(E21:H21) -> -103590 | J21: -20211 | K21: -20782 | L21: -22732 | M21: =+-80198-SUM(J21:L21) -> -16473 | N21: =+SUM(J21:M21) -> -80198 | O21: -32694 | P21: -23100 | Q21: -665 | R21: =+-60520-SUM(O21:Q21) -> -4061 | S21: =+SUM(O21:R21) -> -60520 | T21: =+T20*T58 -> -29838.06 | U21: =+U20*U58 -> -31329.963 | V21: =+V20*V58 -> -33209.761 | W21: =+W20*W58 -> -40515.908 | X21: =+SUM(T21:W21) -> -134893.69 | Y21: =+Y20*Y58 -> -37679.795 | Z21: =+Z20*Z58 -> -40317.38 | AA21: =+AA20*AA58 -> -41284.997 | AB21: =+AB20*AB58 -> -44587.797 | AC21: =+SUM(Y21:AB21) -> -163869.97 | AD21: =+AD20*AD58 -> -209753.56 | AE21: =+AE20*AE58 -> -221105.42 | AF21: =+AF20*AF58 -> -232160.69
B22: Net Realized Performance Income (Loss) | E22: =+SUM(E20:E21) -> 168380 | F22: =+SUM(F20:F21) -> 97492 | G22: =+SUM(G20:G21) -> 196517 | H22: =+SUM(H20:H21) -> 124748 | I22: =+SUM(E22:H22) -> 587137 | J22: =+SUM(J20:J21) -> 114542 | K22: =+SUM(K20:K21) -> 117764 | L22: =+SUM(L20:L21) -> 128814 | M22: =+SUM(M20:M21) -> 93350 | N22: =+SUM(J22:M22) -> 454470 | O22: =+SUM(O20:O21) -> 185263 | P22: =+SUM(P20:P21) -> 130898 | Q22: =+SUM(Q20:Q21) -> 3771 | R22: =+SUM(R20:R21) -> 23003 | S22: =+SUM(O22:R22) -> 342935 | T22: =+SUM(T20:T21) -> 169082.34 | U22: =+SUM(U20:U21) -> 177536.46 | V22: =+SUM(V20:V21) -> 188188.64 | W22: =+SUM(W20:W21) -> 229590.15 | X22: =+SUM(T22:W22) -> 764397.59 | Y22: =+SUM(Y20:Y21) -> 213518.84 | Z22: =+SUM(Z20:Z21) -> 228465.15 | AA22: =+SUM(AA20:AA21) -> 233948.32 | AB22: =+SUM(AB20:AB21) -> 252664.18 | AC22: =+SUM(Y22:AB22) -> 928596.49 | AD22: =+SUM(AD20:AD21) -> 1188603.5 | AE22: =+SUM(AE20:AE21) -> 1293315.3 | AF22: =+SUM(AF20:AF21) -> 1357981
B24: Total Asset Management Operating Earnings | E24: =+SUM(E22,E17,E11) -> 778347 | F24: =+SUM(F22,F17,F11) -> 752050 | G24: =+SUM(G22,G17,G11) -> 869492 | H24: =+SUM(H22,H17,H11) -> 969983 | I24: =+SUM(E24:H24) -> 3369872 | J24: =+SUM(J22,J17,J11) -> 861281 | K24: =+SUM(K22,K17,K11) -> 996000 | L24: =+SUM(L22,L17,L11) -> 1231413 | M24: =+SUM(M22,M17,M11) -> 1242360 | N24: =+SUM(J24:M24) -> 4331054 | O24: =+SUM(O22,O17,O11) -> 1095855 | P24: =+SUM(P22,P17,P11) -> 1126966 | Q24: =+SUM(Q22,Q17,Q11) -> 1269372 | R24: =+SUM(R22,R17,R11) -> 1056791 | S24: =+SUM(O24:R24) -> 4548984 | T24: =+SUM(T22,T17,T11) -> 1394440.9 | U24: =+SUM(U22,U17,U11) -> 1511872.2 | V24: =+SUM(V22,V17,V11) -> 1605426.7 | W24: =+SUM(W22,W17,W11) -> 1793110.4 | X24: =+SUM(T24:W24) -> 6304850.3 | Y24: =+SUM(Y22,Y17,Y11) -> 1706137.7 | Z24: =+SUM(Z22,Z17,Z11) -> 1852827.3 | AA24: =+SUM(AA22,AA17,AA11) -> 1933681.7 | AB24: =+SUM(AB22,AB17,AB11) -> 2096310.6 | AC24: =+SUM(Y24:AB24) -> 7588957.3 | AD24: =+SUM(AD22,AD17,AD11) -> 8526043.6 | AE24: =+SUM(AE22,AE17,AE11) -> 9167184.5 | AF24: =+SUM(AF22,AF17,AF11) -> 9799513.8
B26: Insurance
B27: Net Investment Income | E27: 1271255 | F27: 1283794 | G27: 1356407 | H27: 1466361 | I27: =+SUM(E27:H27) -> 5377817 | J27: 1486419 | K27: 1538046 | L27: 1636300 | M27: 1668057 | N27: =+SUM(J27:M27) -> 6328822 | O27: 1729343 | P27: 1788525 | Q27: 1835025 | R27: 1871225 | S27: =+SUM(O27:R27) -> 7224118 | T27: =+R27*(1+T61) -> 1981627.3 | U27: =+T27*(1+U61) -> 1985590.5 | V27: =+U27*(1+V61) -> 2033244.7 | W27: =+V27*(1+W61) -> 2092208.8 | X27: =+SUM(T27:W27) -> 8092671.3 | Y27: =+W27*(1+Y61) -> 2160205.6 | Z27: =+Y27*(1+Z61) -> 2225011.8 | AA27: =+Z27*(1+AA61) -> 2291762.1 | AB27: =+AA27*(1+AB61) -> 2360515 | AC27: =+SUM(Y27:AB27) -> 9037494.4 | AD27: =+AC27*(1+AD61) -> 9728862.7 | AE27: =+AD27*(1+AE61) -> 10830656 | AF27: =+AE27*(1+AF61) -> 11697109
B28: Net Cost of Insurance | E28: =+-750612 -> -750612 | F28: -811677 | G28: -820014 | H28: =+-3283009-SUM(E28:G28) -> -900706 | I28: =+SUM(E28:H28) -> -3283009 | J28: -1003327 | K28: -1070616 | L28: -1166891 | M28: =+-4448886-SUM(J28:L28) -> -1208052 | N28: =+SUM(J28:M28) -> -4448886 | O28: -1241222 | P28: -1277381 | Q28: -1305073 | R28: =+-5229343-SUM(O28:Q28) -> -1405667 | S28: =+SUM(O28:R28) -> -5229343 | T28: =+T62*T$27 -> -1419835.9 | U28: =+U62*U$27 -> -1465365.8 | V28: =+V62*V$27 -> -1505617.7 | W28: =+W62*W$27 -> -1544050.1 | X28: =+SUM(T28:W28) -> -5934869.5 | Y28: =+Y62*Y$27 -> -1588831.2 | Z28: =+Z62*Z$27 -> -1630933.6 | AA28: =+AA62*AA$27 -> -1675278.1 | AB28: =+AB62*AB$27 -> -1721995.7 | AC28: =+SUM(Y28:AB28) -> -6617038.6 | AD28: =+AD62*AD$27 -> -7199358.4 | AE28: =+AE62*AE$27 -> -8003855.1 | AF28: =+AF62*AF$27 -> -8655860.6
B29: General, Administrative, and Other | E29: =+-196714 -> -196714 | F29: -203285 | G29: -204701 | H29: =+-805109-SUM(E29:G29) -> -200409 | I29: =+SUM(E29:H29) -> -805109 | J29: -210252 | K29: -214217 | L29: -230889 | M29: =+-865390-SUM(J29:L29) -> -210032 | N29: =+SUM(J29:M29) -> -865390 | O29: -229349 | P29: -233212 | Q29: -225299 | R29: =+-885380-SUM(O29:Q29) -> -197520 | S29: =+SUM(O29:R29) -> -885380 | T29: =+T63*T$27 -> -326968.5 | U29: =+U63*U$27 -> -327622.44 | V29: =+V63*V$27 -> -330402.26 | W29: =+W63*W$27 -> -326384.57 | X29: =+SUM(T29:W29) -> -1311377.8 | Y29: =+Y63*Y$27 -> -351033.41 | Z29: =+Z63*Z$27 -> -360451.9 | AA29: =+AA63*AA$27 -> -364390.17 | AB29: =+AB63*AB$27 -> -358798.28 | AC29: =+SUM(Y29:AB29) -> -1434673.8 | AD29: =+AD63*AD$27 -> -1483651.6 | AE29: =+AE63*AE$27 -> -1643010.6 | AF29: =+AF63*AF$27 -> -1754566.3
B30: Pre-Tax Operating Earnings Attributable to Non-Controlling Interest | E30: -118817 | F30: -98608 | G30: -121665 | H30: =+-473062-SUM(E30:G30) -> -133972 | I30: =+SUM(E30:H30) -> -473062 | J30: 0 | K30: 0 | L30: 0 | M30: 0 | N30: =+SUM(J30:M30) -> 0 | O30: 0 | P30: 0 | Q30: 0 | R30: 0 | S30: =+SUM(O30:R30) -> 0 | T30: =+T64*T$27 -> 0 | U30: =+U64*U$27 -> 0 | V30: =+V64*V$27 -> 0 | W30: =+W64*W$27 -> 0 | X30: =+SUM(T30:W30) -> 0 | Y30: =+Y64*Y$27 -> 0 | Z30: =+Z64*Z$27 -> 0 | AA30: =+AA64*AA$27 -> 0 | AB30: =+AB64*AB$27 -> 0 | AC30: =+SUM(Y30:AB30) -> 0 | AD30: =+AD64*AD$27 -> 0 | AE30: =+AE64*AE$27 -> 0 | AF30: =+AF64*AF$27 -> 0
B31: Insurance Segment Operating Earnings | E31: =+SUM(E27:E30) -> 205112 | F31: =+SUM(F27:F30) -> 170224 | G31: =+SUM(G27:G30) -> 210027 | H31: =+SUM(H27:H30) -> 231274 | I31: =+SUM(E31:H31) -> 816637 | J31: =+SUM(J27:J30) -> 272840 | K31: =+SUM(K27:K30) -> 253213 | L31: =+SUM(L27:L30) -> 238520 | M31: =+SUM(M27:M30) -> 249973 | N31: =+SUM(J31:M31) -> 1014546 | O31: =+SUM(O27:O30) -> 258772 | P31: =+SUM(P27:P30) -> 277932 | Q31: =+SUM(Q27:Q30) -> 304653 | R31: =+SUM(R27:R30) -> 268038 | S31: =+SUM(O31:R31) -> 1109395 | T31: =SUM(T27:T30) -> 234822.83 | U31: =SUM(U27:U30) -> 192602.28 | V31: =SUM(V27:V30) -> 197224.74 | W31: =SUM(W27:W30) -> 221774.13 | X31: =+SUM(T31:W31) -> 846423.98 | Y31: =SUM(Y27:Y30) -> 220340.97 | Z31: =SUM(Z27:Z30) -> 233626.23 | AA31: =SUM(AA27:AA30) -> 252093.83 | AB31: =SUM(AB27:AB30) -> 279721.02 | AC31: =+SUM(Y31:AB31) -> 985782.06 | AD31: =SUM(AD27:AD30) -> 1045852.7 | AE31: =SUM(AE27:AE30) -> 1183790.7 | AF31: =SUM(AF27:AF30) -> 1286682
B33: Strategic Holdings
B34: Total Strategic Holdings Earnings | E34: 0 | F34: 0 | G34: 0 | H34: 0 | I34: =+SUM(E34:H34) -> 0 | J34: 20720 | K34: 40852 | L34: 6828 | M34: =76211-SUM(J34:L34) -> 7811 | N34: =+SUM(J34:M34) -> 76211 | O34: 31486 | P34: 29121 | Q34: 57663 | R34: =162096-SUM(O34:Q34) -> 43826 | S34: =+SUM(O34:R34) -> 162096 | T34: =+R34*(1+T$66) -> 76695.5 | U34: =+T34*(1+U$66) -> 85132.005 | V34: =+U34*(1+V$66) -> 96199.166 | W34: =+V34*(1+W$66) -> 106781.07 | X34: =+SUM(T34:W34) -> 364807.74 | Y34: =+W34*(1+Y$66) -> 115323.56 | Z34: =+Y34*(1+Z$66) -> 123972.83 | AA34: =+Z34*(1+AA$66) -> 130171.47 | AB34: =+AA34*(1+AB$66) -> 136680.04 | AC34: =+SUM(Y34:AB34) -> 506147.9 | AD34: =+AC34*(1+AD$66) -> 766814.06 | AE34: =+AD34*(1+AE$66) -> 1000692.4 | AF34: =+AE34*(1+AF$66) -> 1150796.2
B36: Total Segment Earnings | E36: =+SUM(E34,E31,E24) -> 983459 | F36: =+SUM(F34,F31,F24) -> 922274 | G36: =+SUM(G34,G31,G24) -> 1079519 | H36: =+SUM(H34,H31,H24) -> 1201257 | I36: =+SUM(E36:H36) -> 4186509 | J36: =+SUM(J34,J31,J24) -> 1154841 | K36: =+SUM(K34,K31,K24) -> 1290065 | L36: =+SUM(L34,L31,L24) -> 1476761 | M36: =+SUM(M34,M31,M24) -> 1500144 | N36: =+SUM(J36:M36) -> 5421811 | O36: =+SUM(O34,O31,O24) -> 1386113 | P36: =+SUM(P34,P31,P24) -> 1434019 | Q36: =+SUM(Q34,Q31,Q24) -> 1631688 | R36: =+SUM(R34,R31,R24) -> 1368655 | S36: =+SUM(O36:R36) -> 5820475 | T36: =+SUM(T34,T31,T24) -> 1705959.3 | U36: =+SUM(U34,U31,U24) -> 1789606.5 | V36: =+SUM(V34,V31,V24) -> 1898850.6 | W36: =+SUM(W34,W31,W24) -> 2121665.6 | X36: =+SUM(T36:W36) -> 7516082 | Y36: =+SUM(Y34,Y31,Y24) -> 2041802.2 | Z36: =+SUM(Z34,Z31,Z24) -> 2210426.4 | AA36: =+SUM(AA34,AA31,AA24) -> 2315947 | AB36: =+SUM(AB34,AB31,AB24) -> 2512711.6 | AC36: =+SUM(Y36:AB36) -> 9080887.2 | AD36: =+SUM(AD34,AD31,AD24) -> 10338710 | AE36: =+SUM(AE34,AE31,AE24) -> 11351668 | AF36: =+SUM(AF34,AF31,AF24) -> 12236992
B38: Interest Expense | E38: -85500 | F38: -92010 | G38: -89429 | H38: =+-357084-SUM(E38:G38) -> -90145 | I38: =+SUM(E38:H38) -> -357084 | J38: =+-74730 -> -74730 | K38: -79952 | L38: =+-88101 -> -88101 | M38: =+-318441-SUM(J38:L38) -> -75658 | N38: =+SUM(J38:M38) -> -318441 | O38: =+-91470 -> -91470 | P38: =+-93607 -> -93607 | Q38: =+-102789 -> -102789 | R38: =+-404800-SUM(O38:Q38) -> -116934 | S38: =+SUM(O38:R38) -> -404800 | T38: =+T69*T$36 -> -110887.35 | U38: =+U69*U$36 -> -111850.41 | V38: =+V69*V$36 -> -111082.76 | W38: =+W69*W$36 -> -111387.44 | X38: =+SUM(T38:W38) -> -445207.97 | Y38: =+Y69*Y$36 -> -104131.91 | Z38: =+Z69*Z$36 -> -104995.25 | AA38: =+AA69*AA$36 -> -105375.59 | AB38: =+AB69*AB$36 -> -105533.89 | AC38: =+SUM(Y38:AB38) -> -420036.64 | AD38: =+AD69*AD$36 -> -436810.51 | AE38: =+AE69*AE$36 -> -465418.37 | AF38: =+AF69*AF$36 -> -489479.68
B39: Income Tax | E39: -173057 | F39: -171542 | G39: -204640 | H39: =+-763382-SUM(E39:G39) -> -214143 | I39: =+SUM(E39:H39) -> -763382 | J39: -216366 | K39: -238244 | L39: =+-294850 -> -294850 | M39: =+-988757-SUM(J39:L39) -> -239297 | N39: =+SUM(J39:M39) -> -988757 | O39: =+-260655 -> -260655 | P39: =+-277062 -> -277062 | Q39: =+-325158 -> -325158 | R39: =+-1108064-SUM(O39:Q39) -> -245189 | S39: =+SUM(O39:R39) -> -1108064 | T39: =+T73*T$36 -> -326691.2 | U39: =+U73*U$36 -> -352552.48 | V39: =+V73*V$36 -> -377871.28 | W39: =+W73*W$36 -> -424333.12 | X39: =+SUM(T39:W39) -> -1481448.1 | Y39: =+Y73*Y$36 -> -416527.65 | Z39: =+Z73*Z$36 -> -445400.91 | AA39: =+AA73*AA$36 -> -470137.24 | AB39: =+AB73*AB$36 -> -505055.04 | AC39: =+SUM(Y39:AB39) -> -1837120.8 | AD39: =+AD73*AD$36 -> -2016048.5 | AE39: =+AE73*AE$36 -> -2156816.8 | AF39: =+AF73*AF$36 -> -2325028.5
B40: Non-Controlling Interest | E40: =+-5626 -> -5626 | F40: -6118 | G40: -5719 | H40: =+-25590-SUM(E40:G40) -> -8127 | I40: =+SUM(E40:H40) -> -25590 | J40: 0 | K40: 0 | L40: 0 | M40: 0 | N40: =+SUM(J40:M40) -> 0 | O40: 0 | P40: 0 | Q40: 0 | R40: 0 | S40: =+SUM(O40:R40) -> 0 | T40: =+T71*T$36 -> 0 | U40: =+U71*U$36 -> 0 | V40: =+V71*V$36 -> 0 | W40: =+W71*W$36 -> 0 | X40: =+SUM(T40:W40) -> 0 | Y40: =+Y71*Y$36 -> 0 | Z40: =+Z71*Z$36 -> 0 | AA40: =+AA71*AA$36 -> 0 | AB40: =+AB71*AB$36 -> 0 | AC40: =+SUM(Y40:AB40) -> 0 | AD40: =+AD71*AD$36 -> 0 | AE40: =+AE71*AE$36 -> 0 | AF40: =+AF71*AF$36 -> 0
B41: Preferred Stock Dividends | E41: 0 | F41: 0 | G41: 0 | H41: 0 | I41: =+SUM(E41:H41) -> 0 | J41: 0 | K41: 0 | L41: 0 | M41: 0 | N41: =+SUM(J41:M41) -> 0 | O41: 0 | P41: 0 | Q41: 0 | R41: 0 | S41: =+SUM(O41:R41) -> 0 | T41: =+T72*T$36 -> 0 | U41: =+U72*U$36 -> 0 | V41: =+V72*V$36 -> 0 | W41: =+W72*W$36 -> 0 | X41: =+SUM(T41:W41) -> 0 | Y41: =+Y72*Y$36 -> 0 | Z41: =+Z72*Z$36 -> 0 | AA41: =+AA72*AA$36 -> 0 | AB41: =+AB72*AB$36 -> 0 | AC41: =+SUM(Y41:AB41) -> 0 | AD41: =+AD72*AD$36 -> 0 | AE41: =+AE72*AE$36 -> 0 | AF41: =+AF72*AF$36 -> 0
B43: Adjusted Net Income (ANI) [Formerly Distributable Earnings] | E43: =+SUM(E36:E41) -> 719276 | F43: =+SUM(F36:F41) -> 652604 | G43: =+SUM(G36:G41) -> 779731 | H43: =+SUM(H36:H41) -> 888842 | I43: =+SUM(E43:H43) -> 3040453 | J43: =+SUM(J36:J41) -> 863745 | K43: =+SUM(K36:K41) -> 971869 | L43: =+SUM(L36:L41) -> 1093810 | M43: =+SUM(M36:M41) -> 1185189 | N43: =+SUM(J43:M43) -> 4114613 | O43: =+SUM(O36:O41) -> 1033988 | P43: =+SUM(P36:P41) -> 1063350 | Q43: =+SUM(Q36:Q41) -> 1203741 | R43: =+SUM(R36:R41) -> 1006532 | S43: =+SUM(O43:R43) -> 4307611 | T43: =+SUM(T36:T41) -> 1268380.7 | U43: =+SUM(U36:U41) -> 1325203.6 | V43: =+SUM(V36:V41) -> 1409896.6 | W43: =+SUM(W36:W41) -> 1585945 | X43: =+SUM(T43:W43) -> 5589426 | Y43: =+SUM(Y36:Y41) -> 1521142.7 | Z43: =+SUM(Z36:Z41) -> 1660030.2 | AA43: =+SUM(AA36:AA41) -> 1740434.2 | AB43: =+SUM(AB36:AB41) -> 1902122.7 | AC43: =+SUM(Y43:AB43) -> 6823729.7 | AD43: =+SUM(AD36:AD41) -> 7885851.4 | AE43: =+SUM(AE36:AE41) -> 8729432.4 | AF43: =+SUM(AF36:AF41) -> 9422483.9
B45: Fee-Related Earnings Per Share | E45: =+E11/E77 -> 0.61594638 | F45: =+F11/F77 -> 0.67499403 | G45: =+G11/G77 -> 0.62745212 | H45: =+H11/H77 -> 0.75952392 | I45: =SUM(E45:H45) -> 2.6779165 | J45: =+J11/J77 -> 0.75076556 | K45: =+K11/K77 -> 0.84458152 | L45: =+L11/L77 -> 1.1187633 | M45: =+M11/M77 -> 0.94106742 | N45: =SUM(J45:M45) -> 3.6551778 | O45: =+O11/O77 -> 0.91785419 | P45: =+P11/P77 -> 0.98496934 | Q45: =+Q11/Q77 -> 1.1470377 | R45: =+R11/R77 -> 1.0787404 | S45: =SUM(O45:R45) -> 4.1286017 | T45: =+T11/T77 -> 1.1484159 | U45: =+U11/U77 -> 1.2369059 | V45: =+V11/V77 -> 1.3026552 | W45: =+W11/W77 -> 1.3075468 | X45: =SUM(T45:W45) -> 4.9955238 | Y45: =+Y11/Y77 -> 1.3622817 | Z45: =+Z11/Z77 -> 1.473769 | AA45: =+AA11/AA77 -> 1.535493 | AB45: =+AB11/AB77 -> 1.5244219 | AC45: =SUM(Y45:AB45) -> 5.8959655 | AD45: =+AD11/AD77 -> 6.4997563 | AE45: =+AE11/AE77 -> 7.3731441 | AF45: =+AF11/AF77 -> 7.9696759
B46: Performance Related Earnings Per Share | E46: =+SUM(E22,E17)/E77 -> 0.25798589 | F46: =+SUM(F22,F17)/F77 -> 0.16781134 | G46: =+SUM(G22,G17)/G77 -> 0.35109521 | H46: =+SUM(H22,H17)/H77 -> 0.33131655 | I46: =SUM(E46:H46) -> 1.108209 | J46: =+SUM(J22,J17)/J77 -> 0.21615603 | K46: =+SUM(K22,K17)/K77 -> 0.26900934 | L46: =+SUM(L22,L17)/L77 -> 0.25796982 | M46: =+SUM(M22,M17)/M77 -> 0.44584281 | N46: =SUM(J46:M46) -> 1.188978 | O46: =+SUM(O22,O17)/O77 -> 0.30489251 | P46: =+SUM(P22,P17)/P77 -> 0.26681746 | Q46: =+SUM(Q22,Q17)/Q77 -> 0.26255355 | R46: =+SUM(R22,R17)/R77 -> 0.094078215 | S46: =SUM(O46:R46) -> 0.92834174 | T46: =+SUM(T22,T17)/T77 -> 0.40006828 | U46: =+SUM(U22,U17)/U77 -> 0.4409573 | V46: =+SUM(V22,V17)/V77 -> 0.47806564 | W46: =+SUM(W22,W17)/W77 -> 0.67853095 | X46: =SUM(T46:W46) -> 1.9976222 | Y46: =+SUM(Y22,Y17)/Y77 -> 0.52312 | Z46: =+SUM(Z22,Z17)/Z77 -> 0.56919717 | AA46: =+SUM(AA22,AA17)/AA77 -> 0.58814849 | AB46: =+SUM(AB22,AB17)/AB77 -> 0.77408866 | AC46: =SUM(Y46:AB46) -> 2.4545543 | AD46: =+SUM(AD22,AD17)/AD77 -> 2.8580051 | AE46: =+SUM(AE22,AE17)/AE77 -> 2.8909658 | AF46: =+SUM(AF22,AF17)/AF77 -> 3.0024266
B47: ANI per Share | E47: =+E43/E77 -> 0.80760703 | F47: =+F43/F77 -> 0.7313585 | G47: =+G43/G77 -> 0.87752813 | H47: =+H43/H77 -> 0.9995895 | I47: =SUM(E47:H47) -> 3.4160832 | J47: =+J43/J77 -> 0.96968782 | K47: =+K43/K77 -> 1.0866109 | L47: =+L43/L77 -> 1.2228914 | M47: =+M43/M77 -> 1.3230873 | N47: =SUM(J47:M47) -> 4.6022774 | O47: =+O43/O77 -> 1.153716 | P47: =+P43/P77 -> 1.1811248 | Q47: =+Q43/Q77 -> 1.3367104 | R47: =+R43/R77 -> 1.1170416 | S47: =SUM(O47:R47) -> 4.7885928 | T47: =+T43/T77 -> 1.4084981 | U47: =+U43/U77 -> 1.4707 | V47: =+V43/V77 -> 1.5638411 | W47: =+W43/W77 -> 1.7566181 | X47: =SUM(T47:W47) -> 6.1996572 | Y47: =+Y43/Y77 -> 1.6809692 | Z47: =+Z43/Z77 -> 1.830384 | AA47: =+AA43/AA77 -> 1.9114098 | AB47: =+AB43/AB77 -> 2.0855923 | AC47: =SUM(Y47:AB47) -> 7.5083553 | AD47: =+AD43/AD77 -> 8.6551183 | AE47: =+AE43/AE77 -> 9.7739773 | AF47: =+AF43/AF77 -> 10.549958
A49: x | B49: Income Statement Analysis | E49: =+E2 -> 1Q23 | F49: =+F2 -> 2Q23 | G49: =+G2 -> 3Q23 | H49: =+H2 -> 4Q23 | I49: =+I2 -> 2023 | J49: =+J2 -> 1Q24 | K49: =+K2 -> 2Q24 | L49: =+L2 -> 3Q24 | ... S49: =+S2 -> 2025 | T49: =T2 -> 1Q26e | U49: =+U2 -> 2Q26e | V49: =+V2 -> 3Q26e | W49: =+W2 -> 4Q26e | X49: =+X2 -> 2026e | Y49: =+Y2 -> 1Q27e | Z49: =+Z2 -> 2Q27e | AA49: =+AA2 -> 3Q27e | AB49: =+AB2 -> 4Q27e | ... AF49: =+AF2 -> 2030e
B50: Drivers
B52: {=+B14:B16} -> Realized Performance Income (Loss)
B53: Realized Performance Income | E53: =+Drivers!E11 -> 0 | F53: =+Drivers!F11 -> -0.14859919 | G53: =+Drivers!G11 -> 1.2048964 | H53: =+Drivers!H11 -> 0.2494184 | I53: 0 | J53: =+Drivers!J11 -> -0.74512127 | K53: =+Drivers!K11 -> 0.77616601 | L53: =+Drivers!L11 -> -0.1874089 | M53: =+Drivers!M11 -> 0.72571188 | N53: =N15/I15-1 -> 0.71028141 | O53: =+Drivers!O11 -> -0.80905706 | P53: =+Drivers!P11 -> 0.20386871 | Q53: =+Drivers!Q11 -> 1.2219386 | R53: =+Drivers!R11 -> -0.80435047 | S53: =S15/N15-1 -> 0.031500207 | T53: =+Drivers!T11 -> 2.75 | U53: =+Drivers!U11 -> 0.16 | V53: =+Drivers!V11 -> 0.125 | W53: =+Drivers!W11 -> 0.255 | X53: =X15/S15-1 -> 0.85379619 | Y53: =+Drivers!Y11 -> -0.155 | Z53: =+Drivers!Z11 -> 0.1175 | AA53: =+Drivers!AA11 -> 0.05 | AB53: =+Drivers!AB11 -> 0.2025 | AC53: =AC15/X15-1 -> 0.27518759 | AD53: =+Drivers!AD11 -> 0.1365 | AE53: =+Drivers!AE11 -> -0.0921 | AF53: =+Drivers!AF11 -> 0.03
B54: Realized Performance Income Compensation | E54: =+Drivers!E17 -> 0 | F54: =+Drivers!F17 -> -0.65011987 | G54: =+Drivers!G17 -> -0.64937163 | H54: =+Drivers!H17 -> -0.5871057 | I54: 0 | J54: =+Drivers!J17 -> -0.71276216 | K54: =+Drivers!K17 -> -0.74531058 | L54: =+Drivers!L17 -> -0.73993162 | M54: =+Drivers!M17 -> -0.54752854 | N54: =N16/N15 -> -0.66588936 | O54: =+Drivers!O17 -> -0.74709991 | P54: =+Drivers!P17 -> -0.73901397 | Q54: =+Drivers!Q17 -> -0.74999973 | R54: =+Drivers!R17 -> -0.66077009 | S54: =S16/S15 -> -0.73837039 | T54: =+Drivers!T17 -> -0.72 | U54: =+Drivers!U17 -> -0.7225 | V54: =+Drivers!V17 -> -0.7275 | W54: =+Drivers!W17 -> -0.6575 | X54: =X16/X15 -> -0.70242654 | Y54: =+Drivers!Y17 -> -0.725 | Z54: =+Drivers!Z17 -> -0.7275 | AA54: =+Drivers!AA17 -> -0.728 | AB54: =+Drivers!AB17 -> -0.66 | AC54: =AC16/AC15 -> -0.70683696 | AD54: =+Drivers!AD17 -> -0.7197 | AE54: =+Drivers!AE17 -> -0.7189 | AF54: =+Drivers!AF17 -> -0.7197
B56: {=+B19:B21} -> Realized Performance Income (Loss)
B57: Realized Performance Income | E57: =+Drivers!E23 -> 0 | F57: =+Drivers!F23 -> -0.42110816 | G57: =+Drivers!G23 -> 1.0160977 | H57: =+Drivers!H23 -> -0.36520528 | I57: 0 | J57: =+Drivers!J23 -> -0.80491135 | K57: =+Drivers!K23 -> 0.028147796 | L57: =+Drivers!L23 -> 0.093831652 | M57: =+Drivers!M23 -> -0.27531575 | N57: =N20/I20-1 -> -0.22593441 | O57: =+Drivers!O23 -> -0.59235077 | P57: =+Drivers!P23 -> -0.29344779 | Q57: =+Drivers!Q23 -> -0.97119443 | R57: =+Drivers!R23 -> 5.1009919 | S57: =S20/N20-1 -> -0.24541024 | T57: =+Drivers!T23 -> 6.35 | U57: =+Drivers!U23 -> 0.05 | V57: =+Drivers!V23 -> 0.06 | W57: =+Drivers!W23 -> 0.22 | X57: =X20/S20-1 -> 1.2289754 | Y57: =+Drivers!Y23 -> -0.07 | Z57: =+Drivers!Z23 -> 0.07 | AA57: =+Drivers!AA23 -> 0.024 | AB57: =+Drivers!AB23 -> 0.08 | AC57: =AC20/X20-1 -> 0.21480825 | AD57: =+Drivers!AD23 -> 0.28 | AE57: =+Drivers!AE23 -> 0.083 | AF57: =+Drivers!AF23 -> 0.05
B58: Realized Performance Income Compensation | E58: =+Drivers!E29 -> 0 | F58: =+Drivers!F29 -> -0.14984085 | G58: =+Drivers!G29 -> -0.14999827 | H58: =+Drivers!H29 -> -0.14999796 | I58: =+H58 -> -0.14999796 | J58: =+Drivers!J29 -> -0.14998553 | K58: =+Drivers!K29 -> -0.15000072 | L58: =+Drivers!L29 -> -0.15000066 | M58: =+Drivers!M29 -> -0.1499959 | N58: =+M58 -> -0.1499959 | O58: =+Drivers!O29 -> -0.15000206 | P58: =+Drivers!P29 -> -0.15000195 | Q58: =+Drivers!Q29 -> -0.14990983 | R58: =+Drivers!R29 -> -0.15005173 | S58: =+R58 -> -0.15005173 | T58: =+Drivers!T29 -> -0.15 | U58: =+Drivers!U29 -> -0.15 | V58: =+Drivers!V29 -> -0.15 | W58: =+Drivers!W29 -> -0.15 | X58: =+W58 -> -0.15 | Y58: =+Drivers!Y29 -> -0.15 | Z58: =+Drivers!Z29 -> -0.15 | AA58: =+Drivers!AA29 -> -0.15 | AB58: =+Drivers!AB29 -> -0.15 | AC58: =+AB58 -> -0.15 | AD58: =+Drivers!AD29 -> -0.15 | AE58: =+Drivers!AE29 -> -0.146 | AF58: =+Drivers!AF29 -> -0.146
B60: =+B26 -> Insurance
B61: {=+B27:B30} -> Net Investment Income | E61: =+Drivers!E36 -> 0 | F61: =+Drivers!F36 -> 0.0098634814 | G61: =+Drivers!G36 -> 0.056561255 | H61: =+Drivers!H36 -> 0.08106269 | I61: 0 | J61: =+Drivers!J36 -> -0.72360179 | K61: =+Drivers!K36 -> 0.034732468 | L61: =+Drivers!L36 -> 0.063882355 | M61: =+Drivers!M36 -> 0.01940781 | N61: =N27/I27-1 -> 0.17683848 | O61: =+Drivers!O36 -> -0.7267512 | P61: =+Drivers!P36 -> 0.034222245 | Q61: =+Drivers!Q36 -> 0.025999077 | R61: =+Drivers!R36 -> 0.019727252 | S61: =S27/N27-1 -> 0.14146329 | T61: =+Drivers!T36 -> 0.059 | U61: =+Drivers!U36 -> 0.002 | V61: =+Drivers!V36 -> 0.024 | W61: =+Drivers!W36 -> 0.029 | X61: =X27/S27-1 -> 0.12022967 | Y61: =+Drivers!Y36 -> 0.0325 | Z61: =+Drivers!Z36 -> 0.03 | AA61: =+Drivers!AA36 -> 0.03 | AB61: =+Drivers!AB36 -> 0.03 | AC61: =AC27/X27-1 -> 0.11675046 | AD61: =+Drivers!AD36 -> 0.0765 | AE61: =+Drivers!AE36 -> 0.11325 | AF61: =+Drivers!AF36 -> 0.08
B62: Net Cost of Insurance | E62: =+Drivers!E42 -> -0.5904496 | F62: =+Drivers!F42 -> -0.63224863 | G62: =+Drivers!G42 -> -0.60454863 | H62: =+Drivers!H42 -> -0.61424574 | I62: =I28/I$27 -> -0.61047243 | J62: =+Drivers!J42 -> -0.67499608 | K62: =+Drivers!K42 -> -0.69608841 | L62: =+Drivers!L42 -> -0.71312779 | M62: =+Drivers!M42 -> -0.72422705 | N62: =N28/N$27 -> -0.70295641 | O62: =+Drivers!O42 -> -0.71774194 | P62: =+Drivers!P42 -> -0.71420919 | Q62: =+Drivers!Q42 -> -0.71120175 | R62: =+Drivers!R42 -> -0.75120149 | S62: =S28/S$27 -> -0.72387287 | T62: =+Drivers!T42 -> -0.7165 | U62: =+Drivers!U42 -> -0.738 | V62: =+Drivers!V42 -> -0.7405 | W62: =+Drivers!W42 -> -0.738 | X62: =X28/X$27 -> -0.73336347 | Y62: =+Drivers!Y42 -> -0.7355 | Z62: =+Drivers!Z42 -> -0.733 | AA62: =+Drivers!AA42 -> -0.731 | AB62: =+Drivers!AB42 -> -0.7295 | AC62: =AC28/AC$27 -> -0.73217623 | AD62: =+Drivers!AD42 -> -0.74 | AE62: =+Drivers!AE42 -> -0.739 | AF62: =+Drivers!AF42 -> -0.74
B63: General, Administrative, and Other | E63: =+Drivers!E48 -> -0.15474 | F63: =+Drivers!F48 -> -0.15834706 | G63: =+Drivers!G48 -> -0.15091414 | H63: =+Drivers!H48 -> -0.13667098 | I63: =I29/I$27 -> -0.14970926 | J63: =+Drivers!J48 -> -0.14144868 | K63: =+Drivers!K48 -> -0.13927867 | L63: =+Drivers!L48 -> -0.14110432 | M63: =+Drivers!M48 -> -0.12591416 | N63: =N29/N$27 -> -0.13673793 | O63: =+Drivers!O48 -> -0.13262204 | P63: =+Drivers!P48 -> -0.13039348 | Q63: =+Drivers!Q48 -> -0.12277707 | R63: =+Drivers!R48 -> -0.10555652 | S63: =S29/S$27 -> -0.12255891 | T63: =+Drivers!T48 -> -0.165 | U63: =+Drivers!U48 -> -0.165 | V63: =+Drivers!V48 -> -0.1625 | W63: =+Drivers!W48 -> -0.156 | X63: =X29/X$27 -> -0.16204511 | Y63: =+Drivers!Y48 -> -0.1625 | Z63: =+Drivers!Z48 -> -0.162 | AA63: =+Drivers!AA48 -> -0.159 | AB63: =+Drivers!AB48 -> -0.152 | AC63: =AC29/AC$27 -> -0.15874685 | AD63: =+Drivers!AD48 -> -0.1525 | AE63: =+Drivers!AE48 -> -0.1517 | AF63: =+Drivers!AF48 -> -0.15
B64: Pre-Tax Operating Earnings Attributable to Non-Controlling Interest | E64: =+Drivers!E54 -> -0.093464332 | F64: =+Drivers!F54 -> -0.076809831 | G64: =+Drivers!G54 -> -0.089696529 | H64: =+Drivers!H54 -> -0.091363586 | I64: =I30/I$27 -> -0.087965433 | J64: =+Drivers!J54 -> 0 | K64: =+Drivers!K54 -> 0 | L64: =+Drivers!L54 -> 0 | M64: =+Drivers!M54 -> 0 | N64: =N30/N$27 -> 0 | O64: =+Drivers!O54 -> 0 | P64: =+Drivers!P54 -> 0 | Q64: =+Drivers!Q54 -> 0 | R64: =+Drivers!R54 -> 0 | S64: =S30/S$27 -> 0 | T64: =+Drivers!T54 -> 0 | U64: =+Drivers!U54 -> 0 | V64: =+Drivers!V54 -> 0 | W64: =+Drivers!W54 -> 0 | X64: =X30/X$27 -> 0 | Y64: =+Drivers!Y54 -> 0 | Z64: =+Drivers!Z54 -> 0 | AA64: =+Drivers!AA54 -> 0 | AB64: =+Drivers!AB54 -> 0 | AC64: =AC30/AC$27 -> 0 | AD64: =+Drivers!AD54 -> 0 | AE64: =+Drivers!AE54 -> 0 | AF64: =+Drivers!AF54 -> 0
B66: Strategic Holdings | E66: =+Drivers!E61 -> 0 | F66: 0 | G66: 0 | H66: 0 | I66: 0 | J66: 0 | K66: =+Drivers!K61 -> 0.97162162 | L66: =+Drivers!L61 -> -0.83286008 | M66: =+Drivers!M61 -> 0.14396602 | N66: 0 | O66: =+Drivers!O61 -> -0.58685754 | P66: =+Drivers!P61 -> -0.075112749 | Q66: =+Drivers!Q61 -> 0.98011744 | R66: =+Drivers!R61 -> -0.23996323 | S66: =S34/N34-1 -> 1.1269371 | T66: =+Drivers!T61 -> 0.75 | U66: =+Drivers!U61 -> 0.11 | V66: =+Drivers!V61 -> 0.13 | W66: =+Drivers!W61 -> 0.11 | X66: =X34/S34-1 -> 1.250566 | Y66: =+Drivers!Y61 -> 0.08 | Z66: =+Drivers!Z61 -> 0.075 | AA66: =+Drivers!AA61 -> 0.05 | AB66: =+Drivers!AB61 -> 0.05 | AC66: =AC34/X34-1 -> 0.38743737 | AD66: =+Drivers!AD61 -> 0.515 | AE66: =+Drivers!AE61 -> 0.305 | AF66: =+Drivers!AF61 -> 0.15
B68: =+B43 -> Adjusted Net Income (ANI) [Formerly Distributable Earnings]
B69: =+B38 -> Interest Expense | E69: =+Drivers!E68 -> -0.086938042 | F69: =+Drivers!F68 -> -0.099764278 | G69: =+Drivers!G68 -> -0.082841525 | H69: =+Drivers!H68 -> -0.075042227 | I69: =I38/I$36 -> -0.085293976 | J69: =+Drivers!J68 -> -0.064710207 | K69: =+Drivers!K68 -> -0.061975172 | L69: =+Drivers!L68 -> -0.059658266 | M69: =+Drivers!M68 -> -0.050433825 | N69: =N38/N$36 -> -0.058733327 | O69: =+Drivers!O68 -> -0.065990291 | P69: =+Drivers!P68 -> -0.065275983 | Q69: =+Drivers!Q68 -> -0.062995499 | R69: =+Drivers!R68 -> -0.085437163 | S69: =S38/S$36 -> -0.069547588 | T69: =+Drivers!T68 -> -0.065 | U69: =+Drivers!U68 -> -0.0625 | V69: =+Drivers!V68 -> -0.0585 | W69: =+Drivers!W68 -> -0.0525 | X69: =X38/X$36 -> -0.059234048 | Y69: =+Drivers!Y68 -> -0.051 | Z69: =+Drivers!Z68 -> -0.0475 | AA69: =+Drivers!AA68 -> -0.0455 | AB69: =+Drivers!AB68 -> -0.042 | AC69: =AC38/AC$36 -> -0.046255023 | AD69: =+Drivers!AD68 -> -0.04225 | AE69: =+Drivers!AE68 -> -0.041 | AF69: =+Drivers!AF68 -> -0.04
B70: =+B40 -> Non-Controlling Interest | E70: =+Drivers!E74 -> -0.0057206249 | F70: =+Drivers!F74 -> -0.0066336035 | G70: =+Drivers!G74 -> -0.0052977298 | H70: =+Drivers!H74 -> -0.0067654132 | I70: =I40/I$36 -> -0.0061124913 | J70: =+Drivers!J74 -> 0 | K70: =+Drivers!K74 -> 0 | L70: =+Drivers!L74 -> 0 | M70: =+Drivers!M74 -> 0 | N70: =N40/N$36 -> 0 | O70: =+Drivers!O74 -> 0 | P70: =+Drivers!P74 -> 0 | Q70: =+Drivers!Q74 -> 0 | R70: =+Drivers!R74 -> 0 | S70: =S40/S$36 -> 0 | T70: =+Drivers!T74 -> 0 | U70: =+Drivers!U74 -> 0 | V70: =+Drivers!V74 -> 0 | W70: =+Drivers!W74 -> 0 | X70: =X40/X$36 -> 0 | Y70: =+Drivers!Y74 -> 0 | Z70: =+Drivers!Z74 -> 0 | AA70: =+Drivers!AA74 -> 0 | AB70: =+Drivers!AB74 -> 0 | AC70: =AC40/AC$36 -> 0 | AD70: =+Drivers!AD74 -> 0 | AE70: =+Drivers!AE74 -> 0 | AF70: =+Drivers!AF74 -> 0
B71: =+B41 -> Preferred Stock Dividends | E71: =+Drivers!E80 -> 0 | F71: =+Drivers!F80 -> 0 | G71: =+Drivers!G80 -> 0 | H71: =+Drivers!H80 -> 0 | I71: =I41/I$36 -> 0 | J71: =+Drivers!J80 -> 0 | K71: =+Drivers!K80 -> 0 | L71: =+Drivers!L80 -> 0 | M71: =+Drivers!M80 -> 0 | N71: =N41/N$36 -> 0 | O71: =+Drivers!O80 -> 0 | P71: =+Drivers!P80 -> 0 | Q71: =+Drivers!Q80 -> 0 | R71: =+Drivers!R80 -> 0 | S71: =S41/S$36 -> 0 | T71: =+Drivers!T80 -> 0 | U71: =+Drivers!U80 -> 0 | V71: =+Drivers!V80 -> 0 | W71: =+Drivers!W80 -> 0 | X71: =X41/X$36 -> 0 | Y71: =+Drivers!Y80 -> 0 | Z71: =+Drivers!Z80 -> 0 | AA71: =+Drivers!AA80 -> 0 | AB71: =+Drivers!AB80 -> 0 | AC71: =AC41/AC$36 -> 0 | AD71: =+Drivers!AD80 -> 0 | AE71: =+Drivers!AE80 -> 0 | AF71: =+Drivers!AF80 -> 0
B73: Tax Rate | E73: =+E39/E36 -> -0.17596768 | F73: =+F39/F36 -> -0.18599895 | G73: =+G39/G36 -> -0.18956591 | H73: =+H39/H36 -> -0.17826577 | I73: =+I39/I36 -> -0.18234333 | J73: =+J39/J36 -> -0.18735566 | K73: =+K39/K36 -> -0.18467597 | L73: =+L39/L36 -> -0.19965993 | ... S73: =+S39/S36 -> -0.19037347 | T73: =Drivers!T88 -> -0.1915 | U73: =Drivers!U88 -> -0.197 | V73: =Drivers!V88 -> -0.199 | W73: =Drivers!W88 -> -0.2 | X73: =+X39/X36 -> -0.19710377 | Y73: =Drivers!Y88 -> -0.204 | Z73: =Drivers!Z88 -> -0.2015 | AA73: =Drivers!AA88 -> -0.203 | AB73: =Drivers!AB88 -> -0.201 | AC73: =+AC39/AC36 -> -0.20230632 | AD73: =Drivers!AD88 -> -0.195 | AE73: =Drivers!AE88 -> -0.19 | AF73: =Drivers!AF88 -> -0.19
A75: x | B75: Weighted Average Shares Outstanding | E75: =+E49 -> 1Q23 | F75: =+F49 -> 2Q23 | G75: =+G49 -> 3Q23 | H75: =+H49 -> 4Q23 | I75: =+I49 -> 2023 | J75: =+J49 -> 1Q24 | K75: =+K49 -> 2Q24 | L75: =+L49 -> 3Q24 | ... AF75: =+AF49 -> 2030e
B77: Diluted Weighted Average Shares | E77: 890626.22 | F77: 892317.52 | G77: 888553.85 | H77: 889207.02 | I77: =+H77 -> 889207.02 | J77: 890745.44 | K77: 894403.9 | L77: 894445.71 | M77: 895775.35 | N77: =+M77 -> 895775.35 | O77: 896224.05 | P77: 900285.9 | Q77: 900524.88 | R77: 901069.4 | S77: =+R77 -> 901069.4 | T77: 900520 | U77: 901070 | V77: 901560 | W77: 902840 | X77: =W77 -> 902840 | Y77: 904920 | Z77: 906930 | AA77: 910550 | AB77: 912030 | AC77: =AB77 -> 912030 | AD77: 911120 | AE77: 893130 | AF77: 893130

Sheet Segment Analysis
E1: 2023 | F1: =E1 -> 2023 | G1: =F1 -> 2023 | H1: =G1 -> 2023 | I1: =H1 -> 2023 | J1: =I1+1 -> 2024 | K1: =J1 -> 2024 | L1: =K1 -> 2024 | M1: =L1 -> 2024 | N1: =M1 -> 2024 | O1: =N1+1 -> 2025 | P1: =O1 -> 2025 | Q1: =P1 -> 2025 | R1: =Q1 -> 2025 | S1: =R1 -> 2025 | T1: =S1+1 -> 2026 | U1: =T1 -> 2026 | V1: =U1 -> 2026 | W1: =V1 -> 2026 | X1: =W1 -> 2026 | Y1: =X1+1 -> 2027 | Z1: =Y1 -> 2027 | AA1: =Z1 -> 2027 | AB1: =AA1 -> 2027 | AC1: =AB1 -> 2027 | AD1: =AC1+1 -> 2028 | AE1: =AD1+1 -> 2029 | AF1: =AE1+1 -> 2030
A2: x | B2: Segment Analysis | E2: ="1Q"&RIGHT(E1,2) -> 1Q23 | F2: ="2Q"&RIGHT(F1,2) -> 2Q23 | G2: ="3Q"&RIGHT(G1,2) -> 3Q23 | H2: ="4Q"&RIGHT(H1,2) -> 4Q23 | I2: =I1 -> 2023 | J2: ="1Q"&RIGHT(J1,2) -> 1Q24 | K2: ="2Q"&RIGHT(K1,2) -> 2Q24 | L2: ="3Q"&RIGHT(L1,2) -> 3Q24 | M2: ="4Q"&RIGHT(M1,2) -> 4Q24 | N2: =N1 -> 2024 | O2: ="1Q"&RIGHT(O1,2) -> 1Q25 | P2: ="2Q"&RIGHT(P1,2) -> 2Q25 | Q2: ="3Q"&RIGHT(Q1,2) -> 3Q25 | R2: ="4Q"&RIGHT(R1,2) -> 4Q25 | S2: =S1 -> 2025 | T2: ="1Q"&RIGHT(T1,2)&"e" -> 1Q26e | U2: ="2Q"&RIGHT(U1,2)&"e" -> 2Q26e | V2: ="3Q"&RIGHT(V1,2)&"e" -> 3Q26e | W2: ="4Q"&RIGHT(W1,2)&"e" -> 4Q26e | X2: =X1&"e" -> 2026e | Y2: ="1Q"&RIGHT(Y1,2)&"e" -> 1Q27e | Z2: ="2Q"&RIGHT(Z1,2)&"e" -> 2Q27e | AA2: ="3Q"&RIGHT(AA1,2)&"e" -> 3Q27e | AB2: ="4Q"&RIGHT(AB1,2)&"e" -> 4Q27e | AC2: =AC1&"e" -> 2027e | AD2: =AD1&"e" -> 2028e | AE2: =AE1&"e" -> 2029e | AF2: =AF1&"e" -> 2030e
B3: Drivers
B5: Asset Management
B6: Fee-Related Earnings | E6: =+SUM(E7:E11) -> 548578 | F6: =+SUM(F7:F11) -> 602309 | G6: =+SUM(G7:G11) -> 557525 | H6: =+SUM(H7:H11) -> 675374 | I6: =+SUM(I7:I11) -> 2383786 | J6: =+SUM(J7:J11) -> 668741 | K6: =+SUM(K7:K11) -> 755397 | L6: =+SUM(L7:L11) -> 1000673 | ... W6: =+SUM(W7:W11) -> 1180505.5 | X6: =SUM(T6:W6) -> 4503637.7 | Y6: =+SUM(Y7:Y11) -> 1232755.9 | Z6: =+SUM(Z7:Z11) -> 1336605.3 | AA6: =+SUM(AA7:AA11) -> 1398143.1 | AB6: =+SUM(AB7:AB11) -> 1390318.5 | AC6: =SUM(Y6:AB6) -> 5357822.8 | AD6: =+SUM(AD7:AD11) -> 5922058 | AE6: =+SUM(AE7:AE11) -> 6585176.2 | AF6: =+SUM(AF7:AF11) -> 7117956.6
B7: Management Fees | E7: 738156 | F7: 748888 | G7: 758700 | H7: =3030325-SUM(E7:G7) -> 784581 | I7: =+SUM(E7:H7) -> 3030325 | J7: 815327 | K7: 847307 | L7: 892629 | M7: =3461381-SUM(J7:L7) -> 906118 | N7: =+SUM(J7:M7) -> 3461381 | O7: 917334 | P7: 995763 | Q7: 1063553 | R7: =4100841-SUM(O7:Q7) -> 1124191 | S7: =+SUM(O7:R7) -> 4100841 | T7: ='Revenue Build'!R9 -> 1143864.3 | U7: ='Revenue Build'!S9 -> 1185043.5 | V7: ='Revenue Build'!T9 -> 1241925.5 | W7: ='Revenue Build'!U9 -> 1291602.6 | X7: =+SUM(T7:W7) -> 4862435.9 | Y7: ='Revenue Build'!W9 -> 1346495.7 | Z7: ='Revenue Build'!X9 -> 1397662.5 | AA7: ='Revenue Build'!Y9 -> 1453569 | AB7: ='Revenue Build'!Z9 -> 1504443.9 | AC7: =+SUM(Y7:AB7) -> 5702171.1 | AD7: ='Revenue Build'!AB9 -> 6295196.9 | AE7: ='Revenue Build'!AC9 -> 7230033.7 | AF7: ='Revenue Build'!AD9 -> 8014492.3
B8: Transaction and Monitoring Fees | E8: 142179 | F8: 190228 | G8: 124014 | H8: =720654-SUM(E8:G8) -> 264233 | I8: =+SUM(E8:H8) -> 720654 | J8: 152084 | K8: 222858 | L8: 467145 | M8: =1165884-SUM(J8:L8) -> 323797 | N8: =+SUM(J8:M8) -> 1165884 | O8: 261509 | P8: 234249 | Q8: 328124 | R8: =1092577-SUM(O8:Q8) -> 268695 | S8: =+SUM(O8:R8) -> 1092577 | T8: ='Revenue Build'!R11 -> 297579.71 | U8: ='Revenue Build'!S11 -> 331057.43 | V8: ='Revenue Build'!T11 -> 335195.65 | W8: ='Revenue Build'!U11 -> 355307.39 | X8: =+SUM(T8:W8) -> 1319140.2 | Y8: ='Revenue Build'!W11 -> 353530.85 | Z8: ='Revenue Build'!X11 -> 396838.38 | AA8: ='Revenue Build'!Y11 -> 400806.76 | AB8: ='Revenue Build'!Z11 -> 418843.07 | AC8: =+SUM(Y8:AB8) -> 1570019.1 | AD8: ='Revenue Build'!AB11 -> 1703470.7 | AE8: ='Revenue Build'!AC11 -> 1682177.3 | AF8: ='Revenue Build'!AD11 -> 1593863
B9: Fee-Related Performance Revenues | E9: 21741 | F9: 28352 | G9: 20436 | H9: =94427-SUM(E9:G9) -> 23898 | I9: =+SUM(E9:H9) -> 94427 | J9: 19101 | K9: 37145 | L9: 56655 | M9: =137992-SUM(J9:L9) -> 25091 | N9: =+SUM(J9:M9) -> 137992 | O9: 21277 | P9: 53737 | Q9: 73177 | R9: =181784-SUM(O9:Q9) -> 33593 | S9: =+SUM(O9:R9) -> 181784 | T9: =+'Revenue Build'!R13 -> 38296.02 | U9: =+'Revenue Build'!S13 -> 67018.035 | V9: =+'Revenue Build'!T13 -> 83772.544 | W9: =+'Revenue Build'!U13 -> 47750.35 | X9: =+SUM(T9:W9) -> 236836.95 | Y9: =+'Revenue Build'!W13 -> 41542.804 | Z9: =+'Revenue Build'!X13 -> 82877.895 | AA9: =+'Revenue Build'!Y13 -> 104011.76 | AB9: =+'Revenue Build'!Z13 -> 55126.232 | AC9: =+SUM(Y9:AB9) -> 283558.69 | AD9: =+'Revenue Build'!AB13 -> 351612.77 | AE9: =+'Revenue Build'!AC13 -> 502806.27 | AF9: =+'Revenue Build'!AD13 -> 698900.71
B10: Fee-Related Compensation | E10: -203094 | F10: -217684 | G10: -203209 | H10: =+-865336-SUM(E10:G10) -> -241349 | I10: =+SUM(E10:H10) -> -865336 | J10: -172640 | K10: -193779 | L10: -247875 | M10: =+-833918-SUM(J10:L10) -> -219624 | N10: =+SUM(J10:M10) -> -833918 | O10: -210021 | P10: -224656 | Q10: -256350 | R10: =+-940721-SUM(O10:Q10) -> -249694 | S10: =+SUM(O10:R10) -> -940721 | T10: =+'Revenue Build'!R15 -> -257184.82 | U10: =+'Revenue Build'!S15 -> -274544.8 | V10: =+'Revenue Build'!T15 -> -287585.67 | W10: =+'Revenue Build'!U15 -> -291899.46 | X10: =+SUM(T10:W10) -> -1111214.7 | Y10: =+'Revenue Build'!W15 -> -302115.94 | Z10: =+'Revenue Build'!X15 -> -324774.63 | AA10: =+'Revenue Build'!Y15 -> -337765.62 | AB10: =+'Revenue Build'!Z15 -> -341143.28 | AC10: =+SUM(Y10:AB10) -> -1305799.5 | AD10: =+'Revenue Build'!AB15 -> -1462495.4 | AE10: =+'Revenue Build'!AC15 -> -1652619.8 | AF10: =+'Revenue Build'!AD15 -> -1801355.6
B11: Other Operating Expenses | E11: -150404 | F11: -147475 | G11: -142416 | H11: =+-596284-SUM(E11:G11) -> -155989 | I11: =+SUM(E11:H11) -> -596284 | J11: -145131 | K11: -158134 | L11: -167881 | M11: =+-663543-SUM(J11:L11) -> -192397 | N11: =+SUM(J11:M11) -> -663543 | O11: -167496 | P11: -172339 | Q11: -175568 | R11: =+-720168-SUM(O11:Q11) -> -204765 | S11: =+SUM(O11:R11) -> -720168 | T11: =+'Revenue Build'!R17 -> -188383.8 | U11: =+'Revenue Build'!S17 -> -194035.31 | V11: =+'Revenue Build'!T17 -> -198886.2 | W11: =+'Revenue Build'!U17 -> -222255.32 | X11: =+SUM(T11:W11) -> -803560.64 | Y11: =+'Revenue Build'!W17 -> -206697.45 | Z11: =+'Revenue Build'!X17 -> -215998.84 | AA11: =+'Revenue Build'!Y17 -> -222478.8 | AB11: =+'Revenue Build'!Z17 -> -246951.47 | AC11: =+SUM(Y11:AB11) -> -892126.56 | AD11: =+'Revenue Build'!AB17 -> -965727.01 | AE11: =+'Revenue Build'!AC17 -> -1177221.2 | AF11: =+'Revenue Build'!AD17 -> -1387943.8
B13: Revenue Mix
B15: =+B5 -> Asset Management
B16: {=+B7:B11} -> Management Fees | E16: =+E7/SUM(E$7:E$9) -> 0.81828582 | F16: =+F7/SUM(F$7:F$9) -> 0.77407005 | G16: =+G7/SUM(G$7:G$9) -> 0.84005979 | H16: =+H7/SUM(H$7:H$9) -> 0.73139948 | I16: =+I7/SUM(I$7:I$9) -> 0.78803773 | J16: =+J7/SUM(J$7:J$9) -> 0.82647449 | K16: =+K7/SUM(K$7:K$9) -> 0.76519403 | L16: =+L7/SUM(L$7:L$9) -> 0.63019678 | ... AF16: =+AF7/SUM(AF$7:AF$9) -> 0.77755829
B17: Transaction and Monitoring Fees | E17: =+E8/SUM(E$7:E$9) -> 0.15761311 | F17: =+F8/SUM(F$7:F$9) -> 0.19662459 | G17: =+G8/SUM(G$7:G$9) -> 0.13731274 | H17: =+H8/SUM(H$7:H$9) -> 0.24632241 | I17: =+I8/SUM(I$7:I$9) -> 0.18740648 | J17: =+J8/SUM(J$7:J$9) -> 0.15416336 | K17: =+K8/SUM(K$7:K$9) -> 0.20126071 | L17: =+L8/SUM(L$7:L$9) -> 0.32980474 | ... AF17: =+AF8/SUM(AF$7:AF$9) -> 0.15463504
B18: Fee-Related Performance Revenues | E18: =+E9/SUM(E$7:E$9) -> 0.024101074 | F18: =+F9/SUM(F$7:F$9) -> 0.029305362 | G18: =+G9/SUM(G$7:G$9) -> 0.022627471 | H18: =+H9/SUM(H$7:H$9) -> 0.022278114 | I18: =+I9/SUM(I$7:I$9) -> 0.024555795 | J18: =+J9/SUM(J$7:J$9) -> 0.019362157 | K18: =+K9/SUM(K$7:K$9) -> 0.033545258 | L18: =+L9/SUM(L$7:L$9) -> 0.039998475 | ... AF18: =+AF9/SUM(AF$7:AF$9) -> 0.06780667
B19: Fee-Related Compensation | E19: =+E10/SUM(E$10:E$11) -> 0.57452659 | F19: =+F10/SUM(F$10:F$11) -> 0.59613483 | G19: =+G10/SUM(G$10:G$11) -> 0.58794647 | H19: =+H10/SUM(H$10:H$11) -> 0.60741485 | I19: =+I10/SUM(I$10:I$11) -> 0.59203897 | J19: =+J10/SUM(J$10:J$11) -> 0.54328431 | K19: =+K10/SUM(K$10:K$11) -> 0.55064462 | L19: =+L10/SUM(L$10:L$11) -> 0.59620306 | ... AF19: =+AF10/SUM(AF$10:AF$11) -> 0.56481232
B20: Other Operating Expenses | E20: =+E11/SUM(E$10:E$11) -> 0.42547341 | F20: =+F11/SUM(F$10:F$11) -> 0.40386517 | G20: =+G11/SUM(G$10:G$11) -> 0.41205353 | H20: =+H11/SUM(H$10:H$11) -> 0.39258515 | I20: =+I11/SUM(I$10:I$11) -> 0.40796103 | J20: =+J11/SUM(J$10:J$11) -> 0.45671569 | K20: =+K11/SUM(K$10:K$11) -> 0.44935538 | L20: =+L11/SUM(L$10:L$11) -> 0.40379694 | ... AF20: =+AF11/SUM(AF$10:AF$11) -> 0.43518768
A22: x | B22: End

Sheet Drivers
B2: Drivers | E2: =Model!E2 -> 1Q23 | F2: =Model!F2 -> 2Q23 | G2: =Model!G2 -> 3Q23 | H2: =Model!H2 -> 4Q23 | I2: =Model!I2 -> 2023 | J2: =Model!J2 -> 1Q24 | K2: =Model!K2 -> 2Q24 | L2: =Model!L2 -> 3Q24 | ... AF2: =Model!AF2 -> 2030e
A3: x | B3: Income Statement Assumptions
B5: =+Model!B36 -> Total Segment Earnings | E5: =+Model!E36 -> 983459 | F5: =+Model!F36 -> 922274 | G5: =+Model!G36 -> 1079519 | H5: =+Model!H36 -> 1201257 | I5: =+SUM(E5:H5) -> 4186509 | J5: =+Model!J36 -> 1154841 | K5: =+Model!K36 -> 1290065 | L5: =+Model!L36 -> 1476761 | M5: =+Model!M36 -> 1500144 | N5: =+SUM(J5:M5) -> 5421811 | O5: =+Model!O36 -> 1386113 | P5: =+Model!P36 -> 1434019 | Q5: =+Model!Q36 -> 1631688 | R5: =+Model!R36 -> 1368655 | S5: =+SUM(O5:R5) -> 5820475 | T5: =+Model!T36 -> 1705959.3 | U5: =+Model!U36 -> 1789606.5 | V5: =+Model!V36 -> 1898850.6 | W5: =+Model!W36 -> 2121665.6 | X5: =+SUM(T5:W5) -> 7516082 | Y5: =+Model!Y36 -> 2041802.2 | Z5: =+Model!Z36 -> 2210426.4 | AA5: =+Model!AA36 -> 2315947 | AB5: =+Model!AB36 -> 2512711.6 | AC5: =+SUM(Y5:AB5) -> 9080887.2 | AD5: =+Model!AD36 -> 10338710 | AE5: =+Model!AE36 -> 11351668 | AF5: =+Model!AF36 -> 12236992
A7: x | B7: Assumptions per Segment
B9: =+Model!B14 -> Realized Performance Income (Loss)
B10: =+Model!B15 -> Realized Performance Income | E10: =+Model!E15 -> 175398 | F10: =+Model!F15 -> 149334 | G10: =+Model!G15 -> 329266 | H10: =+Model!H15 -> 411391 | I10: =+SUM(E10:H10) -> 1065389 | J10: =+Model!J15 -> 271545 | K10: =+Model!K15 -> 482309 | L10: =+Model!L15 -> 391920 | M10: =+Model!M15 -> 676341 | N10: =+SUM(J10:M10) -> 1822115 | O10: =+Model!O15 -> 347920 | P10: =+Model!P15 -> 418850 | Q10: =+Model!Q15 -> 930659 | R10: =+Model!R15 -> 182083 | S10: =+SUM(O10:R10) -> 1879512 | T10: =+R10*(1+T11) -> 682811.25 | U10: =+T10*(1+U11) -> 792061.05 | V10: =+U10*(1+V11) -> 891068.68 | W10: =+V10*(1+W11) -> 1118291.2 | X10: =SUM(T10:W10) -> 3484232.2 | Y10: =+W10*(1+Y11) -> 944956.06 | Z10: =+Y10*(1+Z11) -> 1055988.4 | AA10: =+Z10*(1+AA11) -> 1108787.8 | AB10: =+AA10*(1+AB11) -> 1333317.3 | AC10: =SUM(Y10:AB10) -> 4443049.6 | AD10: =AC10*(1+AD11) -> 5049525.9 | AE10: =AD10*(1+AE11) -> 4584464.6 | AF10: =AE10*(1+AF11) -> 4721998.5
B11: % Growth | F11: =+F10/E10-1 -> -0.14859919 | G11: =+G10/F10-1 -> 1.2048964 | H11: =+H10/G10-1 -> 0.2494184 | J11: =+J10/I10-1 -> -0.74512127 | K11: =+K10/J10-1 -> 0.77616601 | L11: =+L10/K10-1 -> -0.1874089 | M11: =+M10/L10-1 -> 0.72571188 | N11: =+N10/I10-1 -> 0.71028141 | O11: =+O10/N10-1 -> -0.80905706 | P11: =+P10/O10-1 -> 0.20386871 | Q11: =+Q10/P10-1 -> 1.2219386 | R11: =+R10/Q10-1 -> -0.80435047 | S11: =+S10/N10-1 -> 0.031500207 | T11: =IF(Case_Scenario="Bull",T12,IF(Case_Scenario="Base",T13,IF(Case_Scenario="Bear",T14,"N/A"))) -> 2.75 | U11: =IF(Case_Scenario="Bull",U12,IF(Case_Scenario="Base",U13,IF(Case_Scenario="Bear",U14,"N/A"))) -> 0.16 | V11: =IF(Case_Scenario="Bull",V12,IF(Case_Scenario="Base",V13,IF(Case_Scenario="Bear",V14,"N/A"))) -> 0.125 | W11: =IF(Case_Scenario="Bull",W12,IF(Case_Scenario="Base",W13,IF(Case_Scenario="Bear",W14,"N/A"))) -> 0.255 | X11: =+X10/S10 -> 1.8537962 | Y11: =IF(Case_Scenario="Bull",Y12,IF(Case_Scenario="Base",Y13,IF(Case_Scenario="Bear",Y14,"N/A"))) -> -0.155 | Z11: =IF(Case_Scenario="Bull",Z12,IF(Case_Scenario="Base",Z13,IF(Case_Scenario="Bear",Z14,"N/A"))) -> 0.1175 | AA11: =IF(Case_Scenario="Bull",AA12,IF(Case_Scenario="Base",AA13,IF(Case_Scenario="Bear",AA14,"N/A"))) -> 0.05 | AB11: =IF(Case_Scenario="Bull",AB12,IF(Case_Scenario="Base",AB13,IF(Case_Scenario="Bear",AB14,"N/A"))) -> 0.2025 | AC11: =+AC10/X10 -> 1.2751876 | AD11: =IF(Case_Scenario="Bull",AD12,IF(Case_Scenario="Base",AD13,IF(Case_Scenario="Bear",AD14,"N/A"))) -> 0.1365 | AE11: =IF(Case_Scenario="Bull",AE12,IF(Case_Scenario="Base",AE13,IF(Case_Scenario="Bear",AE14,"N/A"))) -> -0.0921 | AF11: =IF(Case_Scenario="Bull",AF12,IF(Case_Scenario="Base",AF13,IF(Case_Scenario="Bear",AF14,"N/A"))) -> 0.03
B12: Bull | T12: =+T13+5% -> 2.8 | U12: =+U13+2% -> 0.18 | V12: =+V13+2% -> 0.145 | W12: =+W13+2% -> 0.275 | Y12: =+Y13+2% -> -0.135 | Z12: =+Z13+2% -> 0.1375 | AA12: =+AA13+2% -> 0.07 | AB12: =+AB13+2% -> 0.2225 | AD12: =+AD13+2% -> 0.1565 | AE12: =+AE13+2% -> -0.0721 | AF12: =+AF13+2% -> 0.05
B13: Base | T13: 2.75 | U13: 0.16 | V13: 0.125 | W13: 0.255 | Y13: -0.155 | Z13: 0.1175 | AA13: 0.05 | AB13: 0.2025 | AD13: 0.1365 | AE13: -0.0921 | AF13: 0.03
B14: Bear | T14: =+T13-25% -> 2.5 | U14: =+U13-2% -> 0.14 | V14: =+V13-2% -> 0.105 | W14: =+W13-2% -> 0.235 | Y14: =+Y13-2% -> -0.175 | Z14: =+Z13-2% -> 0.0975 | AA14: =+AA13-2% -> 0.03 | AB14: =+AB13-2% -> 0.1825 | AD14: =+AD13-2% -> 0.1165 | AE14: =+AE13-2% -> -0.1121 | AF14: =+AF13-2% -> 0.01
B16: =+Model!B16 -> Realized Performance Income Compensation | E16: =+Model!E16 -> -114009 | F16: =+Model!F16 -> -97085 | G16: =+Model!G16 -> -213816 | H16: =+Model!H16 -> -241530 | I16: =+SUM(E16:H16) -> -666440 | J16: =+Model!J16 -> -193547 | K16: =+Model!K16 -> -359470 | L16: =+Model!L16 -> -289994 | M16: =+Model!M16 -> -370316 | N16: =+SUM(J16:M16) -> -1213327 | O16: =+Model!O16 -> -259931 | P16: =+Model!P16 -> -309536 | Q16: =+Model!Q16 -> -697994 | R16: =+Model!R16 -> -120315 | S16: =+SUM(O16:R16) -> -1387776 | T16: =+T17*T10 -> -491624.1 | U16: =+U17*U10 -> -572264.11 | V16: =+V17*V10 -> -648252.47 | W16: =+W17*W10 -> -735276.46 | X16: =SUM(T16:W16) -> -2447417.1 | Y16: =+Y17*Y10 -> -685093.14 | Z16: =+Z17*Z10 -> -768231.56 | AA16: =+AA17*AA10 -> -807197.53 | AB16: =+AB17*AB10 -> -879989.45 | AC16: =SUM(Y16:AB16) -> -3140511.7 | AD16: =+AD17*AD10 -> -3634143.8 | AE16: =+AE17*AE10 -> -3295771.6 | AF16: =+AF17*AF10 -> -3398422.3
B17: % of Realized Performance Income | F17: =+F16/F10 -> -0.65011987 | G17: =+G16/G10 -> -0.64937163 | H17: =+H16/H10 -> -0.5871057 | J17: =+J16/J10 -> -0.71276216 | K17: =+K16/K10 -> -0.74531058 | L17: =+L16/L10 -> -0.73993162 | M17: =+M16/M10 -> -0.54752854 | N17: =+N16/N10 -> -0.66588936 | O17: =+O16/O10 -> -0.74709991 | P17: =+P16/P10 -> -0.73901397 | Q17: =+Q16/Q10 -> -0.74999973 | ... S17: =+S16/S10 -> -0.73837039 | T17: =IF(Case_Scenario="Bull",T18,IF(Case_Scenario="Base",T19,IF(Case_Scenario="Bear",T20,"N/A"))) -> -0.72 | U17: =IF(Case_Scenario="Bull",U18,IF(Case_Scenario="Base",U19,IF(Case_Scenario="Bear",U20,"N/A"))) -> -0.7225 | V17: =IF(Case_Scenario="Bull",V18,IF(Case_Scenario="Base",V19,IF(Case_Scenario="Bear",V20,"N/A"))) -> -0.7275 | W17: =IF(Case_Scenario="Bull",W18,IF(Case_Scenario="Base",W19,IF(Case_Scenario="Bear",W20,"N/A"))) -> -0.6575 | X17: =+X16/X10 -> -0.70242654 | Y17: =IF(Case_Scenario="Bull",Y18,IF(Case_Scenario="Base",Y19,IF(Case_Scenario="Bear",Y20,"N/A"))) -> -0.725 | Z17: =IF(Case_Scenario="Bull",Z18,IF(Case_Scenario="Base",Z19,IF(Case_Scenario="Bear",Z20,"N/A"))) -> -0.7275 | AA17: =IF(Case_Scenario="Bull",AA18,IF(Case_Scenario="Base",AA19,IF(Case_Scenario="Bear",AA20,"N/A"))) -> -0.728 | AB17: =IF(Case_Scenario="Bull",AB18,IF(Case_Scenario="Base",AB19,IF(Case_Scenario="Bear",AB20,"N/A"))) -> -0.66 | AC17: =+AC16/AC10 -> -0.70683696 | AD17: =IF(Case_Scenario="Bull",AD18,IF(Case_Scenario="Base",AD19,IF(Case_Scenario="Bear",AD20,"N/A"))) -> -0.7197 | AE17: =IF(Case_Scenario="Bull",AE18,IF(Case_Scenario="Base",AE19,IF(Case_Scenario="Bear",AE20,"N/A"))) -> -0.7189 | AF17: =IF(Case_Scenario="Bull",AF18,IF(Case_Scenario="Base",AF19,IF(Case_Scenario="Bear",AF20,"N/A"))) -> -0.7197
B18: Bull | T18: =+T19+3% -> -0.69 | U18: =+U19-3% -> -0.7525 | V18: =+V19-3% -> -0.7575 | W18: =+W19-3% -> -0.6875 | Y18: =+Y19+3% -> -0.695 | Z18: =+Z19+3% -> -0.6975 | AA18: =+AA19+3% -> -0.698 | AB18: =+AB19+3% -> -0.63 | AD18: =+AD19+3% -> -0.6897 | AE18: =+AE19+3% -> -0.6889 | AF18: =+AF19+3% -> -0.6897
B19: Base | T19: -0.72 | U19: -0.7225 | V19: -0.7275 | W19: -0.6575 | Y19: -0.725 | Z19: -0.7275 | AA19: -0.728 | AB19: -0.66 | AD19: -0.7197 | AE19: -0.7189 | AF19: -0.7197
B20: Bear | T20: =+T19-2% -> -0.74 | U20: =+U19+2% -> -0.7025 | V20: =+V19+2% -> -0.7075 | W20: =+W19+2% -> -0.6375 | Y20: =+Y19-2% -> -0.745 | Z20: =+Z19-2% -> -0.7475 | AA20: =+AA19-2% -> -0.748 | AB20: =+AB19-2% -> -0.68 | AD20: =+AD19-2% -> -0.7397 | AE20: =+AE19-2% -> -0.7389 | AF20: =+AF19-2% -> -0.7397
B22: =+Model!B20 -> Realized Performance Income | E22: =+Model!E20 -> 198094 | F22: =+Model!F20 -> 114675 | G22: =+Model!G20 -> 231196 | H22: =+Model!H20 -> 146762 | I22: =+SUM(E22:H22) -> 690727 | J22: =+Model!J20 -> 134753 | K22: =+Model!K20 -> 138546 | L22: =+Model!L20 -> 151546 | M22: =+Model!M20 -> 109823 | N22: =+SUM(J22:M22) -> 534668 | O22: =+Model!O20 -> 217957 | P22: =+Model!P20 -> 153998 | Q22: =+Model!Q20 -> 4436 | R22: =+Model!R20 -> 27064 | S22: =+SUM(O22:R22) -> 403455 | T22: =+R22*(1+T23) -> 198920.4 | U22: =+T22*(1+U23) -> 208866.42 | V22: =+U22*(1+V23) -> 221398.41 | W22: =+V22*(1+W23) -> 270106.05 | X22: =SUM(T22:W22) -> 899291.28 | Y22: =+W22*(1+Y23) -> 251198.63 | Z22: =+Y22*(1+Z23) -> 268782.53 | AA22: =+Z22*(1+AA23) -> 275233.32 | AB22: =+AA22*(1+AB23) -> 297251.98 | AC22: =SUM(Y22:AB22) -> 1092466.5 | AD22: =+AC22*(1+AD23) -> 1398357.1 | AE22: =+AD22*(1+AE23) -> 1514420.7 | AF22: =+AE22*(1+AF23) -> 1590141.7
B23: % Growth | F23: =+F22/E22-1 -> -0.42110816 | G23: =+G22/F22-1 -> 1.0160977 | H23: =+H22/G22-1 -> -0.36520528 | J23: =+J22/I22-1 -> -0.80491135 | K23: =+K22/J22-1 -> 0.028147796 | L23: =+L22/K22-1 -> 0.093831652 | M23: =+M22/L22-1 -> -0.27531575 | N23: =+N22/I22-1 -> -0.22593441 | O23: =+O22/N22-1 -> -0.59235077 | P23: =+P22/O22-1 -> -0.29344779 | Q23: =+Q22/P22-1 -> -0.97119443 | R23: =+R22/Q22-1 -> 5.1009919 | S23: =+S22/N22-1 -> -0.24541024 | T23: =IF(Case_Scenario="Bull",T24,IF(Case_Scenario="Base",T25,IF(Case_Scenario="Bear",T26,"N/A"))) -> 6.35 | U23: =IF(Case_Scenario="Bull",U24,IF(Case_Scenario="Base",U25,IF(Case_Scenario="Bear",U26,"N/A"))) -> 0.05 | V23: =IF(Case_Scenario="Bull",V24,IF(Case_Scenario="Base",V25,IF(Case_Scenario="Bear",V26,"N/A"))) -> 0.06 | W23: =IF(Case_Scenario="Bull",W24,IF(Case_Scenario="Base",W25,IF(Case_Scenario="Bear",W26,"N/A"))) -> 0.22 | X23: =+X22/S22-1 -> 1.2289754 | Y23: =IF(Case_Scenario="Bull",Y24,IF(Case_Scenario="Base",Y25,IF(Case_Scenario="Bear",Y26,"N/A"))) -> -0.07 | Z23: =IF(Case_Scenario="Bull",Z24,IF(Case_Scenario="Base",Z25,IF(Case_Scenario="Bear",Z26,"N/A"))) -> 0.07 | AA23: =IF(Case_Scenario="Bull",AA24,IF(Case_Scenario="Base",AA25,IF(Case_Scenario="Bear",AA26,"N/A"))) -> 0.024 | AB23: =IF(Case_Scenario="Bull",AB24,IF(Case_Scenario="Base",AB25,IF(Case_Scenario="Bear",AB26,"N/A"))) -> 0.08 | AC23: =+AC22/X22-1 -> 0.21480825 | AD23: =IF(Case_Scenario="Bull",AD24,IF(Case_Scenario="Base",AD25,IF(Case_Scenario="Bear",AD26,"N/A"))) -> 0.28 | AE23: =IF(Case_Scenario="Bull",AE24,IF(Case_Scenario="Base",AE25,IF(Case_Scenario="Bear",AE26,"N/A"))) -> 0.083 | AF23: =IF(Case_Scenario="Bull",AF24,IF(Case_Scenario="Base",AF25,IF(Case_Scenario="Bear",AF26,"N/A"))) -> 0.05
B24: Bull | T24: =+T25+5% -> 6.4 | U24: =+U25+2% -> 0.07 | V24: =+V25+2% -> 0.08 | W24: =+W25+2% -> 0.24 | Y24: =+Y25+3% -> -0.04 | Z24: =+Z25+2% -> 0.09 | AA24: =+AA25+2% -> 0.044 | AB24: =+AB25+2% -> 0.1 | AD24: =+AD25+2% -> 0.3 | AE24: =+AE25+2% -> 0.103 | AF24: =+AF25+2% -> 0.07
B25: Base | T25: 6.35 | U25: 0.05 | V25: 0.06 | W25: 0.22 | Y25: -0.07 | Z25: 0.07 | AA25: 0.024 | AB25: 0.08 | AD25: 0.28 | AE25: 0.083 | AF25: 0.05
B26: Bear | T26: =+T25-25% -> 6.1 | U26: =+U25-2% -> 0.03 | V26: =+V25-2% -> 0.04 | W26: =+W25-2% -> 0.2 | Y26: =+Y25-2% -> -0.09 | Z26: =+Z25-2% -> 0.05 | AA26: =+AA25-2% -> 0.004 | AB26: =+AB25-2% -> 0.06 | AD26: =+AD25-2% -> 0.26 | AE26: =+AE25-2% -> 0.063 | AF26: =+AF25-2% -> 0.03
B28: =+Model!B21 -> Realized Performance Income Compensation | E28: =+Model!E21 -> -29714 | F28: =+Model!F21 -> -17183 | G28: =+Model!G21 -> -34679 | H28: =+Model!H21 -> -22014 | I28: =+SUM(E28:H28) -> -103590 | J28: =+Model!J21 -> -20211 | K28: =+Model!K21 -> -20782 | L28: =+Model!L21 -> -22732 | M28: =+Model!M21 -> -16473 | N28: =+SUM(J28:M28) -> -80198 | O28: =+Model!O21 -> -32694 | P28: =+Model!P21 -> -23100 | Q28: =+Model!Q21 -> -665 | R28: =+Model!R21 -> -4061 | S28: =+SUM(O28:R28) -> -60520 | T28: =+T29*T22 -> -29838.06 | U28: =+U29*U22 -> -31329.963 | V28: =+V29*V22 -> -33209.761 | W28: =+W29*W22 -> -40515.908 | X28: =SUM(T28:W28) -> -134893.69 | Y28: =+Y29*Y22 -> -37679.795 | Z28: =+Z29*Z22 -> -40317.38 | AA28: =+AA29*AA22 -> -41284.997 | AB28: =+AB29*AB22 -> -44587.797 | AC28: =SUM(Y28:AB28) -> -163869.97 | AD28: =+AD29*AD22 -> -209753.56 | AE28: =+AE29*AE22 -> -221105.42 | AF28: =+AF29*AF22 -> -232160.69
B29: % of Realized Performance Income | F29: =+F28/F22 -> -0.14984085 | G29: =+G28/G22 -> -0.14999827 | H29: =+H28/H22 -> -0.14999796 | J29: =+J28/J22 -> -0.14998553 | K29: =+K28/K22 -> -0.15000072 | L29: =+L28/L22 -> -0.15000066 | M29: =+M28/M22 -> -0.1499959 | N29: =+N28/N22 -> -0.14999589 | O29: =+O28/O22 -> -0.15000206 | P29: =+P28/P22 -> -0.15000195 | Q29: =+Q28/Q22 -> -0.14990983 | ... S29: =+S28/S22 -> -0.15000434 | T29: =IF(Case_Scenario="Bull",T30,IF(Case_Scenario="Base",T31,IF(Case_Scenario="Bear",T32,"N/A"))) -> -0.15 | U29: =IF(Case_Scenario="Bull",U30,IF(Case_Scenario="Base",U31,IF(Case_Scenario="Bear",U32,"N/A"))) -> -0.15 | V29: =IF(Case_Scenario="Bull",V30,IF(Case_Scenario="Base",V31,IF(Case_Scenario="Bear",V32,"N/A"))) -> -0.15 | W29: =IF(Case_Scenario="Bull",W30,IF(Case_Scenario="Base",W31,IF(Case_Scenario="Bear",W32,"N/A"))) -> -0.15 | X29: =+X28/X22 -> -0.15 | Y29: =IF(Case_Scenario="Bull",Y30,IF(Case_Scenario="Base",Y31,IF(Case_Scenario="Bear",Y32,"N/A"))) -> -0.15 | Z29: =IF(Case_Scenario="Bull",Z30,IF(Case_Scenario="Base",Z31,IF(Case_Scenario="Bear",Z32,"N/A"))) -> -0.15 | AA29: =IF(Case_Scenario="Bull",AA30,IF(Case_Scenario="Base",AA31,IF(Case_Scenario="Bear",AA32,"N/A"))) -> -0.15 | AB29: =IF(Case_Scenario="Bull",AB30,IF(Case_Scenario="Base",AB31,IF(Case_Scenario="Bear",AB32,"N/A"))) -> -0.15 | AC29: =+AC28/AC22 -> -0.15 | AD29: =IF(Case_Scenario="Bull",AD30,IF(Case_Scenario="Base",AD31,IF(Case_Scenario="Bear",AD32,"N/A"))) -> -0.15 | AE29: =IF(Case_Scenario="Bull",AE30,IF(Case_Scenario="Base",AE31,IF(Case_Scenario="Bear",AE32,"N/A"))) -> -0.146 | AF29: =IF(Case_Scenario="Bull",AF30,IF(Case_Scenario="Base",AF31,IF(Case_Scenario="Bear",AF32,"N/A"))) -> -0.146
B30: Bull | T30: -0.15 | U30: -0.15 | V30: -0.15 | W30: -0.15 | Y30: -0.15 | Z30: -0.15 | AA30: -0.15 | AB30: -0.15 | AD30: -0.15 | AE30: =AE29+0.004 -> -0.142 | AF30: =AF29+0.004 -> -0.142
B31: Base | T31: -0.15 | U31: -0.15 | V31: -0.15 | W31: -0.15 | Y31: -0.15 | Z31: -0.15 | AA31: -0.15 | AB31: -0.15 | AD31: -0.15 | AE31: -0.146 | AF31: -0.146
B32: Bear | T32: -0.15 | U32: -0.15 | V32: -0.15 | W32: -0.15 | Y32: -0.15 | Z32: -0.15 | AA32: -0.15 | AB32: -0.15 | AD32: -0.15 | AE32: =AE31-0.004 -> -0.15 | AF32: =AF31-0.004 -> -0.15
B34: Insurance
B35: =+Model!B27 -> Net Investment Income | E35: =+Model!E27 -> 1271255 | F35: =+Model!F27 -> 1283794 | G35: =+Model!G27 -> 1356407 | H35: =+Model!H27 -> 1466361 | I35: =+SUM(E35:H35) -> 5377817 | J35: =+Model!J27 -> 1486419 | K35: =+Model!K27 -> 1538046 | L35: =+Model!L27 -> 1636300 | M35: =+Model!M27 -> 1668057 | N35: =+SUM(J35:M35) -> 6328822 | O35: =+Model!O27 -> 1729343 | P35: =+Model!P27 -> 1788525 | Q35: =+Model!Q27 -> 1835025 | R35: =+Model!R27 -> 1871225 | S35: =+SUM(O35:R35) -> 7224118 | T35: =+R35*(1+T36) -> 1981627.3 | U35: =+T35*(1+U36) -> 1985590.5 | V35: =+U35*(1+V36) -> 2033244.7 | W35: =+V35*(1+W36) -> 2092208.8 | X35: =SUM(T35:W35) -> 8092671.3 | Y35: =+W35*(1+Y36) -> 2160205.6 | Z35: =+Y35*(1+Z36) -> 2225011.8 | AA35: =+Z35*(1+AA36) -> 2291762.1 | AB35: =+AA35*(1+AB36) -> 2360515 | AC35: =SUM(Y35:AB35) -> 9037494.4 | AD35: =+AC35*(1+AD36) -> 9728862.7 | AE35: =+AD35*(1+AE36) -> 10830656 | AF35: =+AE35*(1+AF36) -> 11697109
B36: % Growth | F36: =+F35/E35-1 -> 0.0098634814 | G36: =+G35/F35-1 -> 0.056561255 | H36: =+H35/G35-1 -> 0.08106269 | J36: =+J35/I35-1 -> -0.72360179 | K36: =+K35/J35-1 -> 0.034732468 | L36: =+L35/K35-1 -> 0.063882355 | M36: =+M35/L35-1 -> 0.01940781 | N36: =+N35/I35-1 -> 0.17683848 | O36: =+O35/N35-1 -> -0.7267512 | P36: =+P35/O35-1 -> 0.034222245 | Q36: =+Q35/P35-1 -> 0.025999077 | R36: =+R35/Q35-1 -> 0.019727252 | S36: =+S35/N35-1 -> 0.14146329 | T36: =IF(Case_Scenario="Bull",T37,IF(Case_Scenario="Base",T38,IF(Case_Scenario="Bear",T39,"N/A"))) -> 0.059 | U36: =IF(Case_Scenario="Bull",U37,IF(Case_Scenario="Base",U38,IF(Case_Scenario="Bear",U39,"N/A"))) -> 0.002 | V36: =IF(Case_Scenario="Bull",V37,IF(Case_Scenario="Base",V38,IF(Case_Scenario="Bear",V39,"N/A"))) -> 0.024 | W36: =IF(Case_Scenario="Bull",W37,IF(Case_Scenario="Base",W38,IF(Case_Scenario="Bear",W39,"N/A"))) -> 0.029 | X36: =+X35/S35-1 -> 0.12022967 | Y36: =IF(Case_Scenario="Bull",Y37,IF(Case_Scenario="Base",Y38,IF(Case_Scenario="Bear",Y39,"N/A"))) -> 0.0325 | Z36: =IF(Case_Scenario="Bull",Z37,IF(Case_Scenario="Base",Z38,IF(Case_Scenario="Bear",Z39,"N/A"))) -> 0.03 | AA36: =IF(Case_Scenario="Bull",AA37,IF(Case_Scenario="Base",AA38,IF(Case_Scenario="Bear",AA39,"N/A"))) -> 0.03 | AB36: =IF(Case_Scenario="Bull",AB37,IF(Case_Scenario="Base",AB38,IF(Case_Scenario="Bear",AB39,"N/A"))) -> 0.03 | AC36: =+AC35/X35-1 -> 0.11675046 | AD36: =IF(Case_Scenario="Bull",AD37,IF(Case_Scenario="Base",AD38,IF(Case_Scenario="Bear",AD39,"N/A"))) -> 0.0765 | AE36: =IF(Case_Scenario="Bull",AE37,IF(Case_Scenario="Base",AE38,IF(Case_Scenario="Bear",AE39,"N/A"))) -> 0.11325 | AF36: =IF(Case_Scenario="Bull",AF37,IF(Case_Scenario="Base",AF38,IF(Case_Scenario="Bear",AF39,"N/A"))) -> 0.08
B37: Bull | T37: =+T38+2% -> 0.079 | U37: =+U38+1% -> 0.012 | V37: =+V38+2% -> 0.044 | W37: =+W38+2% -> 0.049 | Y37: =+Y38+2% -> 0.0525 | Z37: =+Z38+2% -> 0.05 | AA37: =+AA38+2% -> 0.05 | AB37: =+AB38+2% -> 0.05 | AD37: =+AD38+2% -> 0.0965 | AE37: =+AE38+2% -> 0.13325 | AF37: =+AF38+2% -> 0.1
B38: Base | T38: 0.059 | U38: 0.002 | V38: 0.024 | W38: 0.029 | Y38: 0.0325 | Z38: 0.03 | AA38: 0.03 | AB38: 0.03 | AD38: 0.0765 | AE38: 0.11325 | AF38: 0.08
B39: Bear | T39: =+T38-2% -> 0.039 | U39: =+U38-1% -> -0.008 | V39: =+V38-2% -> 0.004 | W39: =+W38-2% -> 0.009 | Y39: =+Y38-1% -> 0.0225 | Z39: =+Z38-1% -> 0.02 | AA39: =+AA38-2% -> 0.01 | AB39: =+AB38-2% -> 0.01 | AD39: =+AD38-2% -> 0.0565 | AE39: =+AE38-2% -> 0.09325 | AF39: =+AF38-2% -> 0.06
B41: =+Model!B28 -> Net Cost of Insurance | E41: =+Model!E28 -> -750612 | F41: =+Model!F28 -> -811677 | G41: =+Model!G28 -> -820014 | H41: =+Model!H28 -> -900706 | I41: =+SUM(E41:H41) -> -3283009 | J41: =+Model!J28 -> -1003327 | K41: =+Model!K28 -> -1070616 | L41: =+Model!L28 -> -1166891 | M41: =+Model!M28 -> -1208052 | N41: =+SUM(J41:M41) -> -4448886 | O41: =+Model!O28 -> -1241222 | P41: =+Model!P28 -> -1277381 | Q41: =+Model!Q28 -> -1305073 | R41: =+Model!R28 -> -1405667 | S41: =+SUM(O41:R41) -> -5229343 | T41: =+T42*T35 -> -1419835.9 | U41: =+U42*U35 -> -1465365.8 | V41: =+V42*V35 -> -1505617.7 | W41: =+W42*W35 -> -1544050.1 | X41: =SUM(T41:W41) -> -5934869.5 | Y41: =+Y42*Y35 -> -1588831.2 | Z41: =+Z42*Z35 -> -1630933.6 | AA41: =+AA42*AA35 -> -1675278.1 | AB41: =+AB42*AB35 -> -1721995.7 | AC41: =SUM(Y41:AB41) -> -6617038.6 | AD41: =+AD42*AD35 -> -7199358.4 | AE41: =+AE42*AE35 -> -8003855.1 | AF41: =+AF42*AF35 -> -8655860.6
B42: % of Net Investment Income | E42: =+E41/E$35 -> -0.5904496 | F42: =+F41/F$35 -> -0.63224863 | G42: =+G41/G$35 -> -0.60454863 | H42: =+H41/H$35 -> -0.61424574 | I42: =+I41/I$35 -> -0.61047243 | J42: =+J41/J$35 -> -0.67499608 | K42: =+K41/K$35 -> -0.69608841 | L42: =+L41/L$35 -> -0.71312779 | ... S42: =+S41/S$35 -> -0.72387287 | T42: =IF(Case_Scenario="Bull",T43,IF(Case_Scenario="Base",T44,IF(Case_Scenario="Bear",T45,"N/A"))) -> -0.7165 | U42: =IF(Case_Scenario="Bull",U43,IF(Case_Scenario="Base",U44,IF(Case_Scenario="Bear",U45,"N/A"))) -> -0.738 | V42: =IF(Case_Scenario="Bull",V43,IF(Case_Scenario="Base",V44,IF(Case_Scenario="Bear",V45,"N/A"))) -> -0.7405 | W42: =IF(Case_Scenario="Bull",W43,IF(Case_Scenario="Base",W44,IF(Case_Scenario="Bear",W45,"N/A"))) -> -0.738 | X42: =+X41/X$35 -> -0.73336347 | Y42: =IF(Case_Scenario="Bull",Y43,IF(Case_Scenario="Base",Y44,IF(Case_Scenario="Bear",Y45,"N/A"))) -> -0.7355 | Z42: =IF(Case_Scenario="Bull",Z43,IF(Case_Scenario="Base",Z44,IF(Case_Scenario="Bear",Z45,"N/A"))) -> -0.733 | AA42: =IF(Case_Scenario="Bull",AA43,IF(Case_Scenario="Base",AA44,IF(Case_Scenario="Bear",AA45,"N/A"))) -> -0.731 | AB42: =IF(Case_Scenario="Bull",AB43,IF(Case_Scenario="Base",AB44,IF(Case_Scenario="Bear",AB45,"N/A"))) -> -0.7295 | AC42: =+AC41/AC$35 -> -0.73217623 | AD42: =IF(Case_Scenario="Bull",AD43,IF(Case_Scenario="Base",AD44,IF(Case_Scenario="Bear",AD45,"N/A"))) -> -0.74 | AE42: =IF(Case_Scenario="Bull",AE43,IF(Case_Scenario="Base",AE44,IF(Case_Scenario="Bear",AE45,"N/A"))) -> -0.739 | AF42: =IF(Case_Scenario="Bull",AF43,IF(Case_Scenario="Base",AF44,IF(Case_Scenario="Bear",AF45,"N/A"))) -> -0.74
B43: Bull | T43: =+T44+3% -> -0.6865 | U43: =+U44+3% -> -0.708 | V43: =+V44+3% -> -0.7105 | W43: =+W44+3% -> -0.708 | Y43: =+Y44+3% -> -0.7055 | Z43: =+Z44+3% -> -0.703 | AA43: =+AA44+3% -> -0.701 | AB43: =+AB44+3% -> -0.6995 | AD43: =+AD44+3% -> -0.71 | AE43: =+AE44+3% -> -0.709 | AF43: =+AF44+3% -> -0.71
B44: Base | T44: -0.7165 | U44: -0.738 | V44: -0.7405 | W44: -0.738 | Y44: -0.7355 | Z44: -0.733 | AA44: -0.731 | AB44: -0.7295 | AD44: -0.74 | AE44: -0.739 | AF44: -0.74
B45: Bear | T45: =+T44-2% -> -0.7365 | U45: =+U44-2% -> -0.758 | V45: =+V44-2% -> -0.7605 | W45: =+W44-2% -> -0.758 | Y45: =+Y44-2% -> -0.7555 | Z45: =+Z44-2% -> -0.753 | AA45: =+AA44-2% -> -0.751 | AB45: =+AB44-2% -> -0.7495 | AD45: =+AD44-2% -> -0.76 | AE45: =+AE44-2% -> -0.759 | AF45: =+AF44-2% -> -0.76
B47: =+Model!B29 -> General, Administrative, and Other | E47: =+Model!E29 -> -196714 | F47: =+Model!F29 -> -203285 | G47: =+Model!G29 -> -204701 | H47: =+Model!H29 -> -200409 | I47: =+SUM(E47:H47) -> -805109 | J47: =+Model!J29 -> -210252 | K47: =+Model!K29 -> -214217 | L47: =+Model!L29 -> -230889 | M47: =+Model!M29 -> -210032 | N47: =+SUM(J47:M47) -> -865390 | O47: =+Model!O29 -> -229349 | P47: =+Model!P29 -> -233212 | Q47: =+Model!Q29 -> -225299 | R47: =+Model!R29 -> -197520 | S47: =+SUM(O47:R47) -> -885380 | T47: =+T48*T41 -> 234272.93 | U47: =+U48*U41 -> 241785.36 | V47: =+V48*V41 -> 244662.88 | W47: =+W48*W41 -> 240871.81 | X47: =SUM(T47:W47) -> 961592.98 | Y47: =+Y48*Y41 -> 258185.07 | Z47: =+Z48*Z41 -> 264211.25 | AA47: =+AA48*AA41 -> 266369.22 | AB47: =+AB48*AB41 -> 261743.34 | AC47: =SUM(Y47:AB47) -> 1050508.9 | AD47: =+AD48*AD41 -> 1097902.2 | AE47: =+AE48*AE41 -> 1214184.8 | AF47: =+AF48*AF41 -> 1298379.1
B48: % of Net Investment Income | E48: =+E47/E$35 -> -0.15474 | F48: =+F47/F$35 -> -0.15834706 | G48: =+G47/G$35 -> -0.15091414 | H48: =+H47/H$35 -> -0.13667098 | I48: =+I47/I$35 -> -0.14970926 | J48: =+J47/J$35 -> -0.14144868 | K48: =+K47/K$35 -> -0.13927867 | L48: =+L47/L$35 -> -0.14110432 | ... S48: =+S47/S$35 -> -0.12255891 | T48: =IF(Case_Scenario="Bull",T49,IF(Case_Scenario="Base",T50,IF(Case_Scenario="Bear",T51,"N/A"))) -> -0.165 | U48: =IF(Case_Scenario="Bull",U49,IF(Case_Scenario="Base",U50,IF(Case_Scenario="Bear",U51,"N/A"))) -> -0.165 | V48: =IF(Case_Scenario="Bull",V49,IF(Case_Scenario="Base",V50,IF(Case_Scenario="Bear",V51,"N/A"))) -> -0.1625 | W48: =IF(Case_Scenario="Bull",W49,IF(Case_Scenario="Base",W50,IF(Case_Scenario="Bear",W51,"N/A"))) -> -0.156 | X48: =+X47/X$35 -> 0.11882269 | Y48: =IF(Case_Scenario="Bull",Y49,IF(Case_Scenario="Base",Y50,IF(Case_Scenario="Bear",Y51,"N/A"))) -> -0.1625 | Z48: =IF(Case_Scenario="Bull",Z49,IF(Case_Scenario="Base",Z50,IF(Case_Scenario="Bear",Z51,"N/A"))) -> -0.162 | AA48: =IF(Case_Scenario="Bull",AA49,IF(Case_Scenario="Base",AA50,IF(Case_Scenario="Bear",AA51,"N/A"))) -> -0.159 | AB48: =IF(Case_Scenario="Bull",AB49,IF(Case_Scenario="Base",AB50,IF(Case_Scenario="Bear",AB51,"N/A"))) -> -0.152 | AC48: =+AC47/AC$35 -> 0.11623895 | AD48: =IF(Case_Scenario="Bull",AD49,IF(Case_Scenario="Base",AD50,IF(Case_Scenario="Bear",AD51,"N/A"))) -> -0.1525 | AE48: =IF(Case_Scenario="Bull",AE49,IF(Case_Scenario="Base",AE50,IF(Case_Scenario="Bear",AE51,"N/A"))) -> -0.1517 | AF48: =IF(Case_Scenario="Bull",AF49,IF(Case_Scenario="Base",AF50,IF(Case_Scenario="Bear",AF51,"N/A"))) -> -0.15
B49: Bull | T49: =+T50+3% -> -0.135 | U49: =+U50+3% -> -0.135 | V49: =+V50+3% -> -0.1325 | W49: =+W50+3% -> -0.126 | Y49: =+Y50+3% -> -0.1325 | Z49: =+Z50+3% -> -0.132 | AA49: =+AA50+3% -> -0.129 | AB49: =+AB50+3% -> -0.122 | AD49: =+AD50+3% -> -0.1225 | AE49: =+AE50+3% -> -0.1217 | AF49: =+AF50+3% -> -0.12
B50: Base | T50: -0.165 | U50: -0.165 | V50: -0.1625 | W50: -0.156 | Y50: -0.1625 | Z50: -0.162 | AA50: -0.159 | AB50: -0.152 | AD50: -0.1525 | AE50: -0.1517 | AF50: -0.15
B51: Bear | T51: =+T50-2% -> -0.185 | U51: =+U50-2% -> -0.185 | V51: =+V50-2% -> -0.1825 | W51: =+W50-2% -> -0.176 | Y51: =+Y50-2% -> -0.1825 | Z51: =+Z50-2% -> -0.182 | AA51: =+AA50-2% -> -0.179 | AB51: =+AB50-2% -> -0.172 | AD51: =+AD50-2% -> -0.1725 | AE51: =+AE50-2% -> -0.1717 | AF51: =+AF50-2% -> -0.17
B53: =+Model!B30 -> Pre-Tax Operating Earnings Attributable to Non-Controlling Interest | E53: =+Model!E30 -> -118817 | F53: =+Model!F30 -> -98608 | G53: =+Model!G30 -> -121665 | H53: =+Model!H30 -> -133972 | I53: =+SUM(E53:H53) -> -473062 | J53: =+Model!J30 -> 0 | K53: =+Model!K30 -> 0 | L53: =+Model!L30 -> 0 | M53: =+Model!M30 -> 0 | N53: =+SUM(J53:M53) -> 0 | O53: =+Model!O30 -> 0 | P53: =+Model!P30 -> 0 | Q53: =+Model!Q30 -> 0 | R53: =+Model!R30 -> 0 | S53: =+SUM(O53:R53) -> 0 | T53: =+T54*T47 -> 0 | U53: =+U54*U47 -> 0 | V53: =+V54*V47 -> 0 | W53: =+W54*W47 -> 0 | X53: =SUM(T53:W53) -> 0 | Y53: =+Y54*Y47 -> 0 | Z53: =+Z54*Z47 -> 0 | AA53: =+AA54*AA47 -> 0 | AB53: =+AB54*AB47 -> 0 | AC53: =SUM(Y53:AB53) -> 0 | AD53: =+AD54*AD47 -> 0 | AE53: =+AE54*AE47 -> 0 | AF53: =+AF54*AF47 -> 0
B54: % of Net Investment Income | E54: =+E53/E$35 -> -0.093464332 | F54: =+F53/F$35 -> -0.076809831 | G54: =+G53/G$35 -> -0.089696529 | H54: =+H53/H$35 -> -0.091363586 | I54: =+I53/I$35 -> -0.087965433 | J54: =+J53/J$35 -> 0 | K54: =+K53/K$35 -> 0 | L54: =+L53/L$35 -> 0 | ... S54: =+S53/S$35 -> 0 | T54: =IF(Case_Scenario="Bull",T55,IF(Case_Scenario="Base",T56,IF(Case_Scenario="Bear",T57,"N/A"))) -> 0 | U54: =IF(Case_Scenario="Bull",U55,IF(Case_Scenario="Base",U56,IF(Case_Scenario="Bear",U57,"N/A"))) -> 0 | V54: =IF(Case_Scenario="Bull",V55,IF(Case_Scenario="Base",V56,IF(Case_Scenario="Bear",V57,"N/A"))) -> 0 | W54: =IF(Case_Scenario="Bull",W55,IF(Case_Scenario="Base",W56,IF(Case_Scenario="Bear",W57,"N/A"))) -> 0 | X54: =+X53/X$35 -> 0 | Y54: =IF(Case_Scenario="Bull",Y55,IF(Case_Scenario="Base",Y56,IF(Case_Scenario="Bear",Y57,"N/A"))) -> 0 | Z54: =IF(Case_Scenario="Bull",Z55,IF(Case_Scenario="Base",Z56,IF(Case_Scenario="Bear",Z57,"N/A"))) -> 0 | AA54: =IF(Case_Scenario="Bull",AA55,IF(Case_Scenario="Base",AA56,IF(Case_Scenario="Bear",AA57,"N/A"))) -> 0 | AB54: =IF(Case_Scenario="Bull",AB55,IF(Case_Scenario="Base",AB56,IF(Case_Scenario="Bear",AB57,"N/A"))) -> 0 | AC54: =+AC53/AC$35 -> 0 | AD54: =IF(Case_Scenario="Bull",AD55,IF(Case_Scenario="Base",AD56,IF(Case_Scenario="Bear",AD57,"N/A"))) -> 0 | AE54: =IF(Case_Scenario="Bull",AE55,IF(Case_Scenario="Base",AE56,IF(Case_Scenario="Bear",AE57,"N/A"))) -> 0 | AF54: =IF(Case_Scenario="Bull",AF55,IF(Case_Scenario="Base",AF56,IF(Case_Scenario="Bear",AF57,"N/A"))) -> 0
B55: Bull | T55: 0 | U55: 0 | V55: 0 | W55: 0 | Y55: 0 | Z55: 0 | AA55: 0 | AB55: 0 | AD55: 0 | AE55: 0 | AF55: 0
B56: Base | T56: 0 | U56: 0 | V56: 0 | W56: 0 | Y56: 0 | Z56: 0 | AA56: 0 | AB56: 0 | AD56: 0 | AE56: 0 | AF56: 0
B57: Bear | T57: 0 | U57: 0 | V57: 0 | W57: 0 | Y57: 0 | Z57: 0 | AA57: 0 | AB57: 0 | AD57: 0 | AE57: 0 | AF57: 0
B59: =+Model!B33 -> Strategic Holdings
B60: =Model!B34 -> Total Strategic Holdings Earnings | E60: =Model!E34 -> 0 | F60: =Model!F34 -> 0 | G60: =Model!G34 -> 0 | H60: =Model!H34 -> 0 | I60: =+SUM(E60:H60) -> 0 | J60: =Model!J34 -> 20720 | K60: =Model!K34 -> 40852 | L60: =Model!L34 -> 6828 | M60: =Model!M34 -> 7811 | N60: =+SUM(J60:M60) -> 76211 | O60: =Model!O34 -> 31486 | P60: =Model!P34 -> 29121 | Q60: =Model!Q34 -> 57663 | R60: =Model!R34 -> 43826 | S60: =+SUM(O60:R60) -> 162096 | T60: =+R60*(1+T61) -> 76695.5 | U60: =+T60*(1+U61) -> 85132.005 | V60: =+U60*(1+V61) -> 96199.166 | W60: =+V60*(1+W61) -> 106781.07 | X60: =SUM(T60:W60) -> 364807.74 | Y60: =+W60*(1+Y61) -> 115323.56 | Z60: =+Y60*(1+Z61) -> 123972.83 | AA60: =+Z60*(1+AA61) -> 130171.47 | AB60: =+AA60*(1+AB61) -> 136680.04 | AC60: =SUM(Y60:AB60) -> 506147.9 | AD60: =+AC60*(1+AD61) -> 766814.06 | AE60: =+AD60*(1+AE61) -> 1000692.4 | AF60: =+AE60*(1+AF61) -> 1150796.2
B61: % Growth | F61: =+F60/E60-1 -> #DIV/0! | G61: =+G60/F60-1 -> #DIV/0! | H61: =+H60/G60-1 -> #DIV/0! | I61: 0 | J61: =+J60/I60-1 -> #DIV/0! | K61: =+K60/J60-1 -> 0.97162162 | L61: =+L60/K60-1 -> -0.83286008 | M61: =+M60/L60-1 -> 0.14396602 | N61: 0 | O61: =+O60/N60-1 -> -0.58685754 | P61: =+P60/O60-1 -> -0.075112749 | Q61: =+Q60/P60-1 -> 0.98011744 | R61: =+R60/Q60-1 -> -0.23996323 | S61: =+S60/N60-1 -> 1.1269371 | T61: =IF(Case_Scenario="Bull",T62,IF(Case_Scenario="Base",T63,IF(Case_Scenario="Bear",T64,"N/A"))) -> 0.75 | U61: =IF(Case_Scenario="Bull",U62,IF(Case_Scenario="Base",U63,IF(Case_Scenario="Bear",U64,"N/A"))) -> 0.11 | V61: =IF(Case_Scenario="Bull",V62,IF(Case_Scenario="Base",V63,IF(Case_Scenario="Bear",V64,"N/A"))) -> 0.13 | W61: =IF(Case_Scenario="Bull",W62,IF(Case_Scenario="Base",W63,IF(Case_Scenario="Bear",W64,"N/A"))) -> 0.11 | X61: =+X60/S60-1 -> 1.250566 | Y61: =IF(Case_Scenario="Bull",Y62,IF(Case_Scenario="Base",Y63,IF(Case_Scenario="Bear",Y64,"N/A"))) -> 0.08 | Z61: =IF(Case_Scenario="Bull",Z62,IF(Case_Scenario="Base",Z63,IF(Case_Scenario="Bear",Z64,"N/A"))) -> 0.075 | AA61: =IF(Case_Scenario="Bull",AA62,IF(Case_Scenario="Base",AA63,IF(Case_Scenario="Bear",AA64,"N/A"))) -> 0.05 | AB61: =IF(Case_Scenario="Bull",AB62,IF(Case_Scenario="Base",AB63,IF(Case_Scenario="Bear",AB64,"N/A"))) -> 0.05 | AC61: =+AC60/X60-1 -> 0.38743737 | AD61: =IF(Case_Scenario="Bull",AD62,IF(Case_Scenario="Base",AD63,IF(Case_Scenario="Bear",AD64,"N/A"))) -> 0.515 | AE61: =IF(Case_Scenario="Bull",AE62,IF(Case_Scenario="Base",AE63,IF(Case_Scenario="Bear",AE64,"N/A"))) -> 0.305 | AF61: =IF(Case_Scenario="Bull",AF62,IF(Case_Scenario="Base",AF63,IF(Case_Scenario="Bear",AF64,"N/A"))) -> 0.15
B62: Bull | T62: =+T63+2% -> 0.77 | U62: =+U63+2% -> 0.13 | V62: =+V63+2% -> 0.15 | W62: =+W63+2% -> 0.13 | Y62: =+Y63+2% -> 0.1 | Z62: =+Z63+2% -> 0.095 | AA62: =+AA63+2% -> 0.07 | AB62: =+AB63+2% -> 0.07 | AD62: =+AD63+2% -> 0.535 | AE62: =+AE63+2% -> 0.325 | AF62: =+AF63+2% -> 0.17
B63: Base | T63: 0.75 | U63: 0.11 | V63: 0.13 | W63: 0.11 | Y63: 0.08 | Z63: 0.075 | AA63: 0.05 | AB63: 0.05 | AD63: 0.515 | AE63: 0.305 | AF63: 0.15
B64: Bear | T64: =+T63-2% -> 0.73 | U64: =+U63-2% -> 0.09 | V64: =+V63-2% -> 0.11 | W64: =+W63-2% -> 0.09 | Y64: =+Y63-2% -> 0.06 | Z64: =+Z63-2% -> 0.055 | AA64: =+AA63-2% -> 0.03 | AB64: =+AB63-2% -> 0.03 | AD64: =+AD63-2% -> 0.495 | AE64: =+AE63-2% -> 0.285 | AF64: =+AF63-2% -> 0.13
B66: =+Model!B43 -> Adjusted Net Income (ANI) [Formerly Distributable Earnings]
B67: =+Model!B38 -> Interest Expense | E67: =+Model!E38 -> -85500 | F67: =+Model!F38 -> -92010 | G67: =+Model!G38 -> -89429 | H67: =+Model!H38 -> -90145 | I67: =+SUM(E67:H67) -> -357084 | J67: =+Model!J38 -> -74730 | K67: =+Model!K38 -> -79952 | L67: =+Model!L38 -> -88101 | M67: =+Model!M38 -> -75658 | N67: =+SUM(J67:M67) -> -318441 | O67: =+Model!O38 -> -91470 | P67: =+Model!P38 -> -93607 | Q67: =+Model!Q38 -> -102789 | R67: =+Model!R38 -> -116934 | S67: =+SUM(O67:R67) -> -404800 | T67: =+T68*T$5 -> -110887.35 | U67: =+U68*U$5 -> -111850.41 | V67: =+V68*V$5 -> -111082.76 | W67: =+W68*W$5 -> -111387.44 | X67: =SUM(T67:W67) -> -445207.97 | Y67: =+Y68*Y$5 -> -104131.91 | Z67: =+Z68*Z$5 -> -104995.25 | AA67: =+AA68*AA$5 -> -105375.59 | AB67: =+AB68*AB$5 -> -105533.89 | AC67: =SUM(Y67:AB67) -> -420036.64 | AD67: =+AD68*AD$5 -> -436810.51 | AE67: =+AE68*AE$5 -> -465418.37 | AF67: =+AF68*AF$5 -> -489479.68
B68: % of Total Segment Earnings | E68: =+E67/E$5 -> -0.086938042 | F68: =+F67/F$5 -> -0.099764278 | G68: =+G67/G$5 -> -0.082841525 | H68: =+H67/H$5 -> -0.075042227 | I68: =+I67/I$5 -> -0.085293976 | J68: =+J67/J$5 -> -0.064710207 | K68: =+K67/K$5 -> -0.061975172 | L68: =+L67/L$5 -> -0.059658266 | ... S68: =+S67/S$5 -> -0.069547588 | T68: =IF(Case_Scenario="Bull",T69,IF(Case_Scenario="Base",T70,IF(Case_Scenario="Bear",T71,"N/A"))) -> -0.065 | U68: =IF(Case_Scenario="Bull",U69,IF(Case_Scenario="Base",U70,IF(Case_Scenario="Bear",U71,"N/A"))) -> -0.0625 | V68: =IF(Case_Scenario="Bull",V69,IF(Case_Scenario="Base",V70,IF(Case_Scenario="Bear",V71,"N/A"))) -> -0.0585 | W68: =IF(Case_Scenario="Bull",W69,IF(Case_Scenario="Base",W70,IF(Case_Scenario="Bear",W71,"N/A"))) -> -0.0525 | X68: =+X67/X$5 -> -0.059234048 | Y68: =IF(Case_Scenario="Bull",Y69,IF(Case_Scenario="Base",Y70,IF(Case_Scenario="Bear",Y71,"N/A"))) -> -0.051 | Z68: =IF(Case_Scenario="Bull",Z69,IF(Case_Scenario="Base",Z70,IF(Case_Scenario="Bear",Z71,"N/A"))) -> -0.0475 | AA68: =IF(Case_Scenario="Bull",AA69,IF(Case_Scenario="Base",AA70,IF(Case_Scenario="Bear",AA71,"N/A"))) -> -0.0455 | AB68: =IF(Case_Scenario="Bull",AB69,IF(Case_Scenario="Base",AB70,IF(Case_Scenario="Bear",AB71,"N/A"))) -> -0.042 | AC68: =+AC67/AC$5 -> -0.046255023 | AD68: =IF(Case_Scenario="Bull",AD69,IF(Case_Scenario="Base",AD70,IF(Case_Scenario="Bear",AD71,"N/A"))) -> -0.04225 | AE68: =IF(Case_Scenario="Bull",AE69,IF(Case_Scenario="Base",AE70,IF(Case_Scenario="Bear",AE71,"N/A"))) -> -0.041 | AF68: =IF(Case_Scenario="Bull",AF69,IF(Case_Scenario="Base",AF70,IF(Case_Scenario="Bear",AF71,"N/A"))) -> -0.04
B69: Bull | T69: =+T70+3% -> -0.035 | U69: =+U70+3% -> -0.0325 | V69: =+V70+3% -> -0.0285 | W69: =+W70+3% -> -0.0225 | Y69: =+Y70+3% -> -0.021 | Z69: =+Z70+3% -> -0.0175 | AA69: =+AA70+3% -> -0.0155 | AB69: =+AB70+3% -> -0.012 | AD69: =+AD70+3% -> -0.01225 | AE69: =+AE70+3% -> -0.011 | AF69: =+AF70+3% -> -0.01
B70: Base | T70: -0.065 | U70: -0.0625 | V70: -0.0585 | W70: -0.0525 | Y70: -0.051 | Z70: -0.0475 | AA70: -0.0455 | AB70: -0.042 | AD70: -0.04225 | AE70: -0.041 | AF70: -0.04
B71: Bear | T71: =+T70-2% -> -0.085 | U71: =+U70-2% -> -0.0825 | V71: =+V70-2% -> -0.0785 | W71: =+W70-2% -> -0.0725 | Y71: =+Y70-2% -> -0.071 | Z71: =+Z70-2% -> -0.0675 | AA71: =+AA70-2% -> -0.0655 | AB71: =+AB70-2% -> -0.062 | AD71: =+AD70-2% -> -0.06225 | AE71: =+AE70-2% -> -0.061 | AF71: =+AF70-2% -> -0.06
B73: =+Model!B40 -> Non-Controlling Interest | E73: =+Model!E40 -> -5626 | F73: =+Model!F40 -> -6118 | G73: =+Model!G40 -> -5719 | H73: =+Model!H40 -> -8127 | I73: =+SUM(E73:H73) -> -25590 | J73: =+Model!J40 -> 0 | K73: =+Model!K40 -> 0 | L73: =+Model!L40 -> 0 | M73: =+Model!M40 -> 0 | N73: =+SUM(J73:M73) -> 0 | O73: =+Model!O40 -> 0 | P73: =+Model!P40 -> 0 | Q73: =+Model!Q40 -> 0 | R73: =+Model!R40 -> 0 | S73: =+SUM(O73:R73) -> 0 | T73: =+T74*T$5 -> 0 | U73: =+U74*U$5 -> 0 | V73: =+V74*V$5 -> 0 | W73: =+W74*W$5 -> 0 | X73: =SUM(T73:W73) -> 0 | Y73: =+Y74*Y$5 -> 0 | Z73: =+Z74*Z$5 -> 0 | AA73: =+AA74*AA$5 -> 0 | AB73: =+AB74*AB$5 -> 0 | AC73: =SUM(Y73:AB73) -> 0 | AD73: =+AD74*AD$5 -> 0 | AE73: =+AE74*AE$5 -> 0 | AF73: =+AF74*AF$5 -> 0
B74: % of Total Segment Earnings | E74: =+E73/E$5 -> -0.0057206249 | F74: =+F73/F$5 -> -0.0066336035 | G74: =+G73/G$5 -> -0.0052977298 | H74: =+H73/H$5 -> -0.0067654132 | I74: =+I73/I$5 -> -0.0061124913 | J74: =+J73/J$5 -> 0 | K74: =+K73/K$5 -> 0 | L74: =+L73/L$5 -> 0 | ... S74: =+S73/S$5 -> 0 | T74: =IF(Case_Scenario="Bull",T75,IF(Case_Scenario="Base",T76,IF(Case_Scenario="Bear",T77,"N/A"))) -> 0 | U74: =IF(Case_Scenario="Bull",U75,IF(Case_Scenario="Base",U76,IF(Case_Scenario="Bear",U77,"N/A"))) -> 0 | V74: =IF(Case_Scenario="Bull",V75,IF(Case_Scenario="Base",V76,IF(Case_Scenario="Bear",V77,"N/A"))) -> 0 | W74: =IF(Case_Scenario="Bull",W75,IF(Case_Scenario="Base",W76,IF(Case_Scenario="Bear",W77,"N/A"))) -> 0 | X74: =+X73/X$5 -> 0 | Y74: =IF(Case_Scenario="Bull",Y75,IF(Case_Scenario="Base",Y76,IF(Case_Scenario="Bear",Y77,"N/A"))) -> 0 | Z74: =IF(Case_Scenario="Bull",Z75,IF(Case_Scenario="Base",Z76,IF(Case_Scenario="Bear",Z77,"N/A"))) -> 0 | AA74: =IF(Case_Scenario="Bull",AA75,IF(Case_Scenario="Base",AA76,IF(Case_Scenario="Bear",AA77,"N/A"))) -> 0 | AB74: =IF(Case_Scenario="Bull",AB75,IF(Case_Scenario="Base",AB76,IF(Case_Scenario="Bear",AB77,"N/A"))) -> 0 | AC74: =+AC73/AC$5 -> 0 | AD74: =IF(Case_Scenario="Bull",AD75,IF(Case_Scenario="Base",AD76,IF(Case_Scenario="Bear",AD77,"N/A"))) -> 0 | AE74: =IF(Case_Scenario="Bull",AE75,IF(Case_Scenario="Base",AE76,IF(Case_Scenario="Bear",AE77,"N/A"))) -> 0 | AF74: =IF(Case_Scenario="Bull",AF75,IF(Case_Scenario="Base",AF76,IF(Case_Scenario="Bear",AF77,"N/A"))) -> 0
B75: Bull | T75: 0 | U75: 0 | V75: 0 | W75: 0 | Y75: 0 | Z75: 0 | AA75: 0 | AB75: 0 | AD75: 0 | AE75: 0 | AF75: 0
B76: Base | T76: 0 | U76: 0 | V76: 0 | W76: 0 | Y76: 0 | Z76: 0 | AA76: 0 | AB76: 0 | AD76: 0 | AE76: 0 | AF76: 0
B77: Bear | T77: 0 | U77: 0 | V77: 0 | W77: 0 | Y77: 0 | Z77: 0 | AA77: 0 | AB77: 0 | AD77: 0 | AE77: 0 | AF77: 0
B79: =+Model!B41 -> Preferred Stock Dividends | E79: =+Model!E41 -> 0 | F79: =+Model!F41 -> 0 | G79: =+Model!G41 -> 0 | H79: =+Model!H41 -> 0 | I79: =+SUM(E79:H79) -> 0 | J79: =+Model!J41 -> 0 | K79: =+Model!K41 -> 0 | L79: =+Model!L41 -> 0 | M79: =+Model!M41 -> 0 | N79: =+SUM(J79:M79) -> 0 | O79: =+Model!O41 -> 0 | P79: =+Model!P41 -> 0 | Q79: =+Model!Q41 -> 0 | R79: =+Model!R41 -> 0 | S79: =+SUM(O79:R79) -> 0 | T79: =+T80*T$5 -> 0 | U79: =+U80*U$5 -> 0 | V79: =+V80*V$5 -> 0 | W79: =+W80*W$5 -> 0 | X79: =SUM(T79:W79) -> 0 | Y79: =+Y80*Y$5 -> 0 | Z79: =+Z80*Z$5 -> 0 | AA79: =+AA80*AA$5 -> 0 | AB79: =+AB80*AB$5 -> 0 | AC79: =SUM(Y79:AB79) -> 0 | AD79: =+AD80*AD$5 -> 0 | AE79: =+AE80*AE$5 -> 0 | AF79: =+AF80*AF$5 -> 0
B80: % of Total Segment Earnings | E80: =+E79/E$5 -> 0 | F80: =+F79/F$5 -> 0 | G80: =+G79/G$5 -> 0 | H80: =+H79/H$5 -> 0 | I80: =+I79/I$5 -> 0 | J80: =+J79/J$5 -> 0 | K80: =+K79/K$5 -> 0 | L80: =+L79/L$5 -> 0 | ... S80: =+S79/S$5 -> 0 | T80: =IF(Case_Scenario="Bull",T81,IF(Case_Scenario="Base",T82,IF(Case_Scenario="Bear",T83,"N/A"))) -> 0 | U80: =IF(Case_Scenario="Bull",U81,IF(Case_Scenario="Base",U82,IF(Case_Scenario="Bear",U83,"N/A"))) -> 0 | V80: =IF(Case_Scenario="Bull",V81,IF(Case_Scenario="Base",V82,IF(Case_Scenario="Bear",V83,"N/A"))) -> 0 | W80: =IF(Case_Scenario="Bull",W81,IF(Case_Scenario="Base",W82,IF(Case_Scenario="Bear",W83,"N/A"))) -> 0 | X80: =+X79/X$5 -> 0 | Y80: =IF(Case_Scenario="Bull",Y81,IF(Case_Scenario="Base",Y82,IF(Case_Scenario="Bear",Y83,"N/A"))) -> 0 | Z80: =IF(Case_Scenario="Bull",Z81,IF(Case_Scenario="Base",Z82,IF(Case_Scenario="Bear",Z83,"N/A"))) -> 0 | AA80: =IF(Case_Scenario="Bull",AA81,IF(Case_Scenario="Base",AA82,IF(Case_Scenario="Bear",AA83,"N/A"))) -> 0 | AB80: =IF(Case_Scenario="Bull",AB81,IF(Case_Scenario="Base",AB82,IF(Case_Scenario="Bear",AB83,"N/A"))) -> 0 | AC80: =+AC79/AC$5 -> 0 | AD80: =IF(Case_Scenario="Bull",AD81,IF(Case_Scenario="Base",AD82,IF(Case_Scenario="Bear",AD83,"N/A"))) -> 0 | AE80: =IF(Case_Scenario="Bull",AE81,IF(Case_Scenario="Base",AE82,IF(Case_Scenario="Bear",AE83,"N/A"))) -> 0 | AF80: =IF(Case_Scenario="Bull",AF81,IF(Case_Scenario="Base",AF82,IF(Case_Scenario="Bear",AF83,"N/A"))) -> 0
B81: Bull | T81: 0 | U81: 0 | V81: 0 | W81: 0 | Y81: 0 | Z81: 0 | AA81: 0 | AB81: 0 | AD81: 0 | AE81: 0 | AF81: 0
B82: Base | T82: 0 | U82: 0 | V82: 0 | W82: 0 | Y82: 0 | Z82: 0 | AA82: 0 | AB82: 0 | AD82: 0 | AE82: 0 | AF82: 0
B83: Bear | T83: 0 | U83: 0 | V83: 0 | W83: 0 | Y83: 0 | Z83: 0 | AA83: 0 | AB83: 0 | AD83: 0 | AE83: 0 | AF83: 0
A85: x | B85: Tax Rate
B87: Tax Expense | E87: =Model!E39 -> -173057 | F87: =Model!F39 -> -171542 | G87: =Model!G39 -> -204640 | H87: =Model!H39 -> -214143 | I87: =+SUM(E87:H87) -> -763382 | J87: =Model!J39 -> -216366 | K87: =Model!K39 -> -238244 | L87: =Model!L39 -> -294850 | M87: =Model!M39 -> -239297 | N87: =+SUM(J87:M87) -> -988757 | O87: =Model!O39 -> -260655 | P87: =Model!P39 -> -277062 | Q87: =Model!Q39 -> -325158 | R87: =Model!R39 -> -245189 | S87: =+SUM(O87:R87) -> -1108064 | T87: =T88*T5 -> -326691.2 | U87: =U88*U5 -> -352552.48 | V87: =V88*V5 -> -377871.28 | W87: =W88*W5 -> -424333.12 | X87: =+SUM(T87:W87) -> -1481448.1 | Y87: =Y88*Y5 -> -416527.65 | Z87: =Z88*Z5 -> -445400.91 | AA87: =AA88*AA5 -> -470137.24 | AB87: =AB88*AB5 -> -505055.04 | AC87: =+SUM(Y87:AB87) -> -1837120.8 | AD87: =AD88*AD5 -> -2016048.5 | AE87: =AE88*AE5 -> -2156816.8 | AF87: =AF88*AF5 -> -2325028.5
B88: % of Total Segment Earnings | E88: =E87/E5 -> -0.17596768 | F88: =F87/F5 -> -0.18599895 | G88: =G87/G5 -> -0.18956591 | H88: =H87/H5 -> -0.17826577 | I88: =Model!I$73 -> -0.18234333 | J88: =J87/J5 -> -0.18735566 | K88: =K87/K5 -> -0.18467597 | L88: =L87/L5 -> -0.19965993 | M88: =M87/M5 -> -0.15951602 | N88: =Model!N$73 -> -0.18236656 | O88: =O87/O5 -> -0.18804744 | P88: =P87/P5 -> -0.19320665 | Q88: =Q87/Q5 -> -0.19927707 | R88: =R87/R5 -> -0.17914595 | S88: =Model!S$73 -> -0.19037347 | T88: =IF(Case_Scenario="Bull",T89,IF(Case_Scenario="Base",T90,IF(Case_Scenario="Bear",T91,"N/A"))) -> -0.1915 | U88: =IF(Case_Scenario="Bull",U89,IF(Case_Scenario="Base",U90,IF(Case_Scenario="Bear",U91,"N/A"))) -> -0.197 | V88: =IF(Case_Scenario="Bull",V89,IF(Case_Scenario="Base",V90,IF(Case_Scenario="Bear",V91,"N/A"))) -> -0.199 | W88: =IF(Case_Scenario="Bull",W89,IF(Case_Scenario="Base",W90,IF(Case_Scenario="Bear",W91,"N/A"))) -> -0.2 | X88: =Model!X$73 -> -0.19710377 | Y88: =IF(Case_Scenario="Bull",Y89,IF(Case_Scenario="Base",Y90,IF(Case_Scenario="Bear",Y91,"N/A"))) -> -0.204 | Z88: =IF(Case_Scenario="Bull",Z89,IF(Case_Scenario="Base",Z90,IF(Case_Scenario="Bear",Z91,"N/A"))) -> -0.2015 | AA88: =IF(Case_Scenario="Bull",AA89,IF(Case_Scenario="Base",AA90,IF(Case_Scenario="Bear",AA91,"N/A"))) -> -0.203 | AB88: =IF(Case_Scenario="Bull",AB89,IF(Case_Scenario="Base",AB90,IF(Case_Scenario="Bear",AB91,"N/A"))) -> -0.201 | AC88: =Model!AC$73 -> -0.20230632 | AD88: =IF(Case_Scenario="Bull",AD89,IF(Case_Scenario="Base",AD90,IF(Case_Scenario="Bear",AD91,"N/A"))) -> -0.195 | AE88: =IF(Case_Scenario="Bull",AE89,IF(Case_Scenario="Base",AE90,IF(Case_Scenario="Bear",AE91,"N/A"))) -> -0.19 | AF88: =IF(Case_Scenario="Bull",AF89,IF(Case_Scenario="Base",AF90,IF(Case_Scenario="Bear",AF91,"N/A"))) -> -0.19
B89: Bull | T89: =+T90+3% -> -0.1615 | U89: =+U90+3% -> -0.167 | V89: =+V90+3% -> -0.169 | W89: =+W90+3% -> -0.17 | Y89: =+Y90+3% -> -0.174 | Z89: =+Z90+3% -> -0.1715 | AA89: =+AA90+3% -> -0.173 | AB89: =+AB90+3% -> -0.171 | AD89: =+AD90+3% -> -0.165 | AE89: =+AE90+3% -> -0.16 | AF89: =+AF90+3% -> -0.16
B90: Base | T90: -0.1915 | U90: -0.197 | V90: -0.199 | W90: -0.2 | Y90: -0.204 | Z90: -0.2015 | AA90: -0.203 | AB90: -0.201 | AD90: -0.195 | AE90: -0.19 | AF90: -0.19
B91: Bear | T91: =+T90-2% -> -0.2115 | U91: =+U90-2% -> -0.217 | V91: =+V90-2% -> -0.219 | W91: =+W90-2% -> -0.22 | Y91: =+Y90-2% -> -0.224 | Z91: =+Z90-2% -> -0.2215 | AA91: =+AA90-2% -> -0.223 | AB91: =+AB90-2% -> -0.221 | AD91: =+AD90-2% -> -0.215 | AE91: =+AE90-2% -> -0.21 | AF91: =+AF90-2% -> -0.21
A93: x | B93: End

Sheet Funds
C2: Investment Period | E2: Amount ($ in millions)
B3: (Millions) | C3: Start Date | D3: End Date | E3: Commitment (2) | F3: Uncalled Commitments | G3: Percentage Committed by General Partner | H3: Invested | I3: Realized | J3: Remaining Cost (3) | K3: Remaining Fair Value | L3: Gross Accrued Carried Interest
B5: Private Equity Business Line
B6: North America Fund XIII | C6: 6/2021 | D6: 8/2027 | E6: 18400 | F6: 15335 | G6: 0.03 | H6: 3065 | I6: 0 | J6: 3065 | K6: 3096 | L6: 0
B7: Americas Fund XII | C7: 1/2017 | D7: 6/2021 | E7: 13500 | F7: 1706 | G7: 0.04 | H7: 12292 | I7: 4948 | J7: 11219 | K7: 20105 | L7: 1687
B8: North America Fund XI | C8: 9/2012 | D8: 1/2017 | E8: 8718 | F8: 408 | G8: 0.03 | H8: 9769 | I8: 20199 | J8: 2957 | K8: 6197 | L8: 667
B9: 2006 Fund (4) | C9: 9/2006 | D9: 9/2012 | E9: 17642 | F9: 247 | G9: 0.02 | H9: 17309 | I9: 35557 | J9: 1274 | K9: 1708 | L9: 141
B10: Millennium Fund (4) | C10: 12/2002 | D10: 12/2008 | E10: 6000 | F10: 0 | G10: 0.03 | H10: 6000 | I10: 14123 | J10: 0 | K10: 6 | L10: 1
B11: European Fund VI | C11: 3/2022 | D11: 6/2028 | E11: 7120 | F11: 7120 | G11: 0.11 | H11: 0 | I11: 0 | J11: 0 | K11: 0 | L11: 0
B12: European Fund V | C12: 3/2019 | D12: 2/2022 | E12: 6328 | F12: 1604 | G12: 0.02 | H12: 4793 | I12: 782 | J12: 4640 | K12: 5395 | L12: 212
B13: European Fund IV | C13: 12/2014 | D13: 3/2019 | E13: 3513 | F13: 64 | G13: 0.06 | H13: 3577 | I13: 5122 | J13: 1799 | K13: 2473 | L13: 135
B14: European Fund III (4) | C14: 3/2008 | D14: 3/2014 | E14: 5509 | F14: 145 | G14: 0.05 | H14: 5360 | I14: 10604 | J14: 669 | K14: 129 | L14: -25
B15: European Fund II (4) | C15: 11/2005 | D15: 10/2008 | E15: 5751 | F15: 0 | G15: 0.02 | H15: 5751 | I15: 8507 | J15: 0 | K15: 34 | L15: 0
B16: Asian Fund IV | C16: 7/2020 | D16: 7/2026 | E16: 14735 | F16: 11353 | G16: 0.04 | H16: 3423 | I16: 41 | J16: 3402 | K16: 3635 | L16: 0
B17: Asian Fund III | C17: 4/2017 | D17: 7/2020 | E17: 9000 | F17: 2000 | G17: 0.06 | H17: 7404 | I17: 4199 | J17: 6438 | K17: 11949 | L17: 981
... B26: Global Impact Fund | C26: 2/2019 | D26: 3/2022 | E26: 1242 | F26: 350 | G26: 0.08 | H26: 1042 | I26: 168 | J26: 939 | K26: 1466 | L26: 100
B27: Co-Investment Vehicles and Other | C27: Various | D27: Various | E27: 18161 | F27: 6550 | G27: Various | H27: 11746 | I27: 7648 | J27: 8302 | K27: 10723 | L27: 1164
B28: Core Investment Vehicles | C28: Various | D28: Various | E28: 24657 | F28: 13729 | G28: 0.31 | H28: 11627 | I28: 712 | J28: 11323 | K28: 18525 | L28: 108
B29: Unallocated Commitments (5) | E29: 4320 | F29: 4320 | G29: Various | H29: 0 | I29: 0 | J29: 0 | K29: 0 | L29: 0
B30: Total Private Equity | E30: =SUM(E6:E29) -> 184593 | F30: =SUM(F6:F29) -> 70915 | H30: =SUM(H6:H29) -> 118548 | I30: =SUM(I6:I29) -> 129629 | J30: =SUM(J6:J29) -> 63268 | K30: =SUM(K6:K29) -> 93370 | L30: =SUM(L6:L29) -> 5096
B32: Real Assets Business Line
B33: Energy Income and Growth Fund II | C33: 6/2018 | D33: 3/2022 | E33: 994 | F33: 0 | G33: 0.2 | H33: 1187 | I33: 193 | J33: 1024 | K33: 1835 | L33: 52
B34: Energy Income and Growth Fund | C34: 9/2013 | D34: 6/2018 | E34: 1974 | F34: 0 | G34: 0.13 | H34: 1974 | I34: 956 | J34: 1134 | K34: 716 | L34: 0
B35: Natural Resources Fund (4) | C35: Various | D35: Various | E35: 887 | F35: 0 | G35: Various | H35: 887 | I35: 123 | J35: 191 | K35: 48 | L35: 0
B36: Global Energy Opportunities | C36: Various | D36: Various | E36: 915 | F36: 62 | G36: Various | H36: 519 | I36: 169 | J36: 323 | K36: 213 | L36: 0
B37: Global Infrastructure Investors IV | C37: 8/2021 | D37: 8/2027 | E37: 16603 | F37: 13717 | G37: 0.02 | H37: 2886 | I37: 0 | J37: 2886 | K37: 3053 | L37: 15
B38: Global Infrastructure Investors III | C38: 6/2018 | D38: 6/2021 | E38: 7164 | F38: 1667 | G38: 0.04 | H38: 5764 | I38: 1241 | J38: 5137 | K38: 5634 | L38: 121
B39: Global Infrastructure Investors II | C39: 10/2014 | D39: 6/2018 | E39: 3039 | F39: 123 | G39: 0.04 | H39: 3163 | I39: 4246 | J39: 1281 | K39: 1767 | L39: 48
B40: Global Infrastructure Investors | C40: 9/2011 | D40: 10/2014 | E40: 1040 | F40: 0 | G40: 0.05 | H40: 1050 | I40: 2228 | J40: 0 | K40: 0 | L40: 0
B41: Asia Pacific Infrastructure Investors II | C41: -6 | D41: -7 | E41: 4122 | F41: 4122 | G41: 0.09 | H41: 0 | I41: 0 | J41: 0 | K41: 0 | L41: 0
B42: Asia Pacific Infrastructure Investors | C42: 1/2020 | D42: 1/2026 | E42: 3792 | F42: 2036 | G42: 0.07 | H42: 2041 | I42: 323 | J42: 1848 | K42: 1952 | L42: 32
B43: Diversified Core Infrastructure Fund | C43: 12/2020 | D43: -8 | E43: 7636 | F43: 3127 | G43: 0.07 | H43: 4519 | I43: 100 | J43: 4509 | K43: 4609 | L43: 0
B44: Real Estate Partners Americas III | C44: 12/2020 | D44: 1/2025 | E44: 4253 | F44: 2065 | G44: 0.05 | H44: 2214 | I44: 92 | J44: 2173 | K44: 2490 | L44: 51
B45: Real Estate Partners Americas II | C45: 5/2017 | D45: 12/2020 | E45: 1921 | F45: 265 | G45: 0.08 | H45: 1892 | I45: 2446 | J45: 588 | K45: 820 | L45: 80
B46: Real Estate Partners Americas | C46: 5/2013 | D46: 5/2017 | E46: 1229 | F46: 139 | G46: 0.16 | H46: 1020 | I46: 1405 | J46: 111 | K46: 61 | L46: 1
B47: Real Estate Partners Europe II | C47: 12/2019 | D47: 3/2024 | E47: 2065 | F47: 806 | G47: 0.1 | H47: 1326 | I47: 184 | J47: 1237 | K47: 1432 | L47: 43
B48: Real Estate Partners Europe | C48: 9/2015 | D48: 12/2019 | E48: 707 | F48: 131 | G48: 0.09 | H48: 654 | I48: 609 | J48: 285 | K48: 334 | L48: 12
B49: Asia Real Estate Partners | C49: 6/2019 | D49: 7/2023 | E49: 1682 | F49: 1280 | G49: 0.15 | H49: 405 | I49: 7 | J49: 388 | K49: 561 | L49: 16
B50: Real Estate Credit Opportunity Partners II | C50: 4/2019 | D50: 6/2022 | E50: 950 | F50: 413 | G50: 0.05 | H50: 560 | I50: 102 | J50: 560 | K50: 564 | L50: 11
B51: Real Estate Credit Opportunity Partners | C51: 2/2017 | D51: 4/2019 | E51: 1130 | F51: 122 | G51: 0.04 | H51: 1008 | I51: 371 | J51: 1008 | K51: 1039 | L51: 11
B52: Property Partners Americas | C52: 12/2019 | D52: -8 | E52: 2488 | F52: 266 | G52: 0.2 | H52: 2222 | I52: 110 | J52: 2222 | K52: 3117 | L52: 38
B53: Co-Investment Vehicles and Other | C53: Various | D53: Various | E53: 5681 | F53: 1422 | G53: Various | H53: 4320 | I53: 1670 | J53: 3737 | K53: 3858 | L53: 19
B54: Total Real Assets | E54: =SUM(E33:E53) -> 70272 | F54: =SUM(F33:F53) -> 31763 | H54: =SUM(H33:H53) -> 39611 | I54: =SUM(I33:I53) -> 16575 | J54: =SUM(J33:J53) -> 30642 | K54: =SUM(K33:K53) -> 34103 | L54: =SUM(L33:L53) -> 550
B56: Credit and Liquid Strategies
B57: Dislocation Opportunities Fund | C57: 43952 | D57: 44501 | E57: 2967 | F57: 681 | G57: 0.14 | H57: 2286 | I57: 538 | J57: 2034 | K57: 2080 | L57: 38
B58: Special Situations Fund II | C58: 42036 | D58: 43525 | E58: 3525 | F58: 284 | G58: 0.09 | H58: 3241 | I58: 2068 | J58: 1616 | K58: 1863 | L58: 0
B59: Special Situations Fund | C59: 41275 | D59: 42370 | E59: 2274 | F59: 1 | G59: 0.12 | H59: 2273 | I59: 1700 | J59: 652 | K59: 390 | L59: 0
B60: Mezzanine Partners | C60: 40360 | D60: 42064 | E60: 1023 | F60: 33 | G60: 0.04 | H60: 990 | I60: 1157 | J60: 265 | K60: 131 | L60: -20
B61: Asset-Based Finance Partners | C61: 44044 | D61: 45839 | E61: 1959 | F61: 1959 | G61: 0.07 | H61: 0 | I61: 0 | J61: 0 | K61: 0 | L61: 0
B62: Private Credit Opportunities Partners II | C62: 42339 | D62: 44166 | E62: 2245 | F62: 507 | G62: 0.02 | H62: 1738 | I62: 674 | J62: 1354 | K62: 1375 | L62: 0
B63: Lending Partners III | C63: 42826 | D63: 44501 | E63: 1498 | F63: 757 | G63: 0.02 | H63: 741 | I63: 356 | J63: 741 | K63: 796 | L63: 31
B64: Lending Partners II | C64: 41791 | D64: 42887 | E64: 1336 | F64: 157 | G64: 0.04 | H64: 1179 | I64: 1149 | J64: 333 | K64: 131 | L64: 0
B65: Lending Partners | C65: 40878 | D65: 41974 | E65: 460 | F65: 41 | G65: 0.15 | H65: 419 | I65: 451 | J65: 86 | K65: 19 | L65: 0
B66: Lending Partners Europe II | C66: 43617 | D66: 45170 | E66: 837 | F66: 286 | G66: 0.07 | H66: 551 | I66: 52 | J66: 551 | K66: 552 | L66: 2
B67: Lending Partners Europe | C67: 42064 | D67: 43525 | E67: 848 | F67: 184 | G67: 0.05 | H67: 662 | I67: 379 | J67: 314 | K67: 249 | L67: 0
B68: Asia Credit | C68: 44166 | D68: 45778 | E68: 1084 | F68: 813 | G68: 0.09 | H68: 271 | I68: 0 | J68: 271 | K68: 280 | L68: 0
B69: Other Alternative Credit Vehicles | C69: Various | D69: Various | E69: 13056 | F69: 5651 | G69: Various | H69: 6654 | I69: 4800 | J69: 3877 | K69: 3947 | L69: 63
B70: Total Credit & Liquid Strategies | E70: =SUM(E57:E69) -> 33112 | F70: =SUM(F57:F69) -> 11354 | H70: =SUM(H57:H69) -> 21005 | I70: =SUM(I57:I69) -> 13324 | J70: =SUM(J57:J69) -> 12094 | K70: =SUM(K57:K69) -> 11813 | L70: =SUM(L57:L69) -> 114
B72: Total | E72: =SUM(E70,E54,E30) -> 287977 | F72: =SUM(F70,F54,F30) -> 114032 | H72: =SUM(H70,H54,H30) -> 179164 | I72: =SUM(I70,I54,I30) -> 159528 | J72: =SUM(J70,J54,J30) -> 106004 | K72: =SUM(K70,K54,K30) -> 139286 | L72: =SUM(L70,L54,L30) -> 5760
B77: (Millions) | F77: Uncalled Commitments | K77: Remaining Fair Value | L77: Total
B78: Carried Interest Eligible | F78: =SUM(F30,F54,F70) -> 114032 | K78: =SUM(K70,K54,K30) -> 139286 | L78: =SUM(F78:K78) -> 253318
B79: Incentive Fee Eligible | F79: 0 | K79: 67593 | L79: =SUM(F79:K79) -> 67593
B80: Performance Fee Eligible | F80: =SUM(F78:F79) -> 114032 | K80: =SUM(K78:K79) -> 206879 | L80: =SUM(L78:L79) -> 320911
B81: Private Equity & Real Assets | F81: 169 | K81: 37710 | L81: =SUM(F81:K81) -> 37879
B82: Credit & Liquid Strategies | F82: 1099 | K82: 130803 | L82: =SUM(F82:K82) -> 131902
B83: Total Assets Under Management | F83: =SUM(F80:F82) -> 115300 | K83: =SUM(K80:K82) -> 375392 | L83: =SUM(L80:L82) -> 490692

Sheet Valuation
B2: Report
B5: Sum of The Parts Valuation | R5: x
C8: Fee Related Earnings | I8: Sum of the Parts Valuation
I9: Methodology (2023E) | L9: Implied PT
B10: Fee Earnings | F10: Assumptions (2026E) | I10: Fee Related Earnings
B11: Fee-Related Earnings (2026E) | F11: =Model!X11 -> 4503637.7 | I11: Implied Value / Share | L11: =F19 -> 113.45876
B12: Pro Forma Tax Rate | F12: =Model!X73 -> -0.19710377
B13: After Tax Fee Earnings | F13: =F11*(1-F12) -> 5391321.6 | I13: Book Value
B14: After Tax Fee Earnings Per Share | F14: =F13/Model!X77 -> 5.9715139 | I14: Implied Value / Share | L14: 0
B16: Target P/E | F16: =_xlfn.IFS(Case_Scenario="Base",Valuation!C45,Case_Scenario="Bull",Valuation!C46,Case_Scenario="Bear",Valuation!C44) -> 19 | I16: Implied Share Price | L16: =SUM(L11:L14) -> 113.45876
I17: Implied Return | L17: =L16/Share_Price-1 -> 0.26121347
B19: Implied Value / Share | F19: =PRODUCT(F14,F16) -> 113.45876
C22: Book Value
B24: Balance Sheet | F24: Assumptions (2025E)
B25: Total Book Value | F25: =#REF! -> #REF!
B26: Book Value Per Share | F26: =#REF! -> #REF!
B28: Target P/Bk | F28: =_xlfn.IFS(Case_Scenario="Base",Valuation!H45,Case_Scenario="Bull",Valuation!H46,Case_Scenario="Bear",Valuation!H44) -> 1.3
B33: Implied Book Value / Share | F33: =PRODUCT(F26,F28) -> #REF!
B39: Drivers
B41: Fee Related Earnings | G41: Fee Related Earnings
B43: Exit Multiple (P/E) | G43: Exit Multiple (P/Bk)
B44: Bear | C44: 13 | G44: Bear | H44: 0.8
B45: Base | C45: 19 | G45: Base | H45: 1.3
B46: Bull | C46: 21 | G46: Bull | H46: 1.3
XFD1048576: eepy

Sheet Comparables
D4: =$D$86 -> Primary Peer Group | Z4: =$G$86 -> Defense Peer Group | AV4: =$L$86 -> Cap. Goods Peer Group
Q6: Enterprise Value / | AM6: Enterprise Value / | BI6: Enterprise Value /
G7: Market | H7: Enterprise | I7: Sales | K7: EPS | M7: EBITDA Margin | O7: Profit Margin | Q7: EBITDA | S7: Sales | U7: Price / Earnings | AC7: Market | AD7: Enterprise | AE7: Sales | AG7: EPS | AI7: EBITDA Margin | AK7: Profit Margin | AM7: EBITDA | AO7: Sales | AQ7: Price / Earnings | AY7: Market | AZ7: Enterprise | BA7: Sales | BC7: EPS | BE7: EBITDA Margin | BG7: Profit Margin | BI7: EBITDA | BK7: Sales | BM7: Price / Earnings
F8: Ticker | G8: Cap | H8: Value | I8: LTM | J8: 44590 | K8: LTM | L8: 44590 | M8: LTM | N8: 44590 | O8: LTM | P8: 44590 | Q8: LTM | R8: 44590 | S8: LTM | T8: 44590 | U8: LTM | V8: 44590 | AB8: Ticker | AC8: Cap | AD8: Value | AE8: LTM | AF8: =Next_FYE -> #REF! | AG8: =$I$8 -> LTM | AH8: =$J$8 -> 44590 | AI8: =$I$8 -> LTM | AJ8: =$J$8 -> 44590 | AK8: =$I$8 -> LTM | AL8: =$J$8 -> 44590 | AM8: =$I$8 -> LTM | AN8: =$J$8 -> 44590 | AO8: =$I$8 -> LTM | AP8: =$J$8 -> 44590 | AQ8: =$I$8 -> LTM | AR8: =$J$8 -> 44590 | AX8: Ticker | AY8: Cap | AZ8: Value | BA8: LTM | BB8: =Next_FYE -> #REF! | BC8: =$I$8 -> LTM | BD8: =$J$8 -> 44590 | BE8: =$I$8 -> LTM | BF8: =$J$8 -> 44590 | BG8: =$I$8 -> LTM | BH8: =$J$8 -> 44590 | BI8: =$I$8 -> LTM | BJ8: =$J$8 -> 44590 | BK8: =$I$8 -> LTM | BL8: =$J$8 -> 44590 | BM8: =$I$8 -> LTM | BN8: =$J$8 -> 44590
D10: KKR & Co. Inc. | F10: KKR | G10: 42458.575 | H10: 90967 | I10: -0.500017 | J10: -0.72495366 | K10: -0.865608 | L10: -0.47103868 | M10: - | N10: 0.64554165 | O10: 0.066427 | P10: 0.49564192 | Q10: - | R10: - | S10: - | T10: - | U10: 40.99337 | V10: 12.453453 | Z10: =Z51 -> #REF! | AB10: LOW | AC10: 6040.9356 | AD10: 5561.8386 | AE10: 0.19067 | AF10: 0.034378216 | AG10: 0.124316 | AH10: -0.1398079 | AI10: 0.280531 | AJ10: 0.29106115 | AK10: 0.152468 | AL10: 0.20242259 | AM10: 0 | AN10: 24.372329 | AO10: 0 | AP10: 7.093838 | AQ10: 0 | AR10: 38.063447 | AV10: =Company_Name -> #REF! | AX10: LOW | AY10: 6040.9356 | AZ10: 5561.8386 | BA10: 0.19067 | BB10: 0.034378216 | BC10: 0.124316 | BD10: -0.1398079 | BE10: 0.280531 | BF10: 0.29106115 | BG10: 0.152468 | BH10: 0.20242259 | BI10: 0 | BJ10: 24.372329 | BK10: 0 | BL10: 7.093838 | BM10: 0 | BN10: 38.063447
D12: Apollo Global Management, Inc. | F12: APO | G12: 31846.898 | H12: 37566 | I12: -0.096455 | J12: -0.56119885 | K12: - | L12: -0.29835372 | M12: - | N12: 1.3137771 | O12: -0.457503 | P12: 1.2021414 | Q12: - | R12: - | S12: - | T12: - | U12: - | V12: 10.386764 | Z12: =Z72 -> #NAME? | AB12: RTX | AC12: 128030.65 | AD12: 154660.65 | AE12: 0.284792 | AF12: 0.15215756 | AG12: 0.432084 | AH12: -2.5665134 | AI12: 0.147101 | AJ12: 0.15766707 | AK12: 0.035057 | AL12: 0.093871454 | AM12: 16.46107 | AN12: 15.045627 | AO12: 2.57577 | AP12: 2.3721999 | AQ12: 63.46893 | AR12: 20.919527 | AV12: =AV53 -> #NAME? | AX12: MMM | AY12: 112863.39 | AZ12: 126547.39 | BA12: 0.107836 | BB12: 0.094074178 | BC12: 0.139568 | BD12: 0.071204324 | BE12: 0.290032 | BF12: 0.26891897 | BG12: 0.17038 | BH12: 0.16510122 | BI12: 11.08706 | BJ12: 13.364262 | BK12: 3.36595 | BL12: 3.5939035 | BM12: 17.64282 | BN12: 19.414045
D13: Ares Capital Corporation | F13: ARCC | G13: 13491.594 | H13: 28159.392 | I13: -0.037095 | J13: -0.3465177 | K13: -0.522751 | L13: 0.50369308 | M13: 0.21172 | N13: 0.29586739 | O13: 0.0508 | P13: 0.21463359 | Q13: 38.80019 | R13: 34.577581 | S13: 8.2148 | T13: 10.230378 | U13: 85.83265 | V13: 22.836735 | Z13: =Z73 -> #NAME? | AB13: BA | AC13: 129979.18 | AD13: 172393.18 | AE13: -0.074288 | AF13: 0.26827198 | AG13: 0.432084 | AH13: -0.97760967 | AI13: -0.029095 | AJ13: 0.075836173 | AK13: -0.14303 | AL13: -0.0054210976 | AM13: NM | AN13: 30.819233 | AO13: 2.82676 | AP13: 2.3372127 | AQ13: NM | AR13: NM | AV13: =AV54 -> #NAME? | AX13: GE | AY13: 116444.02 | AZ13: 165361.02 | BA13: -0.083477 | BB13: -0.036353037 | BC13: 0.139568 | BD13: -0.57771187 | BE13: 0.086125 | BF13: 0.10098877 | BG13: -0.03102 | BH13: 0.027997383 | BI13: 20.84823 | BJ13: 21.341521 | BK13: 2.07603 | BL13: 2.155254 | BM13: NM | BN13: 54.20821
D14: Blackstone Inc. | F14: BX | G14: 113710 | H14: 103000 | I14: -0.416004 | J14: -0.41046884 | K14: -0.518082 | L14: -0.36584256 | M14: - | N14: 0.54952595 | O14: 0.218893 | P14: 0.50813837 | Q14: - | R14: - | S14: - | T14: - | U14: 26.52962 | V14: 9.9448455 | Z14: =Z74 -> #NAME? | AB14: HII | AC14: 8308.7198 | AD14: 9819.7198 | AE14: 0.07387 | AF14: 0.05557778 | AG14: 0.432084 | AH14: -0.23063186 | AI14: 0.12192 | AJ14: 0.084324002 | AK14: 0.078079 | AL14: 0 | AM14: 7.41228 | AN14: 11.785158 | AO14: 0.98224 | AP14: 0.99377166 | AQ14: 10.64393 | AR14: 20.919527 | AV14: =AV55 -> #NAME? | AX14: HON | AY14: 159578.89 | AZ14: 169888.89 | BA14: -0.016309 | BB14: 0.074231269 | BC14: -0.135737 | BD14: 0.20102827 | BE14: 0.24559 | BF14: 0.25050485 | BG14: 0.14647 | BH14: 0.16202132 | BI14: 18.49203 | BJ14: 19.343756 | BK14: 4.71245 | BL14: 4.8457047 | BM14: 30.83166 | BN14: 28.092814
D15: The Carlyle Group Inc. | F15: CG | G15: 10398.931 | H15: 17747.531 | I15: -0.185031 | J15: -0.54258334 | K15: -0.234765 | L15: -0.51387805 | M15: 0.488547 | N15: 0.37252358 | O15: 0.318595 | P15: 0.36077117 | Q15: 5.69982 | R15: 11.859703 | S15: 2.83082 | T15: 4.4180191 | U15: 5.25682 | V15: 7.1754067 | Z15: =Z75 -> #NAME? | AB15: LMT | AC15: 100241 | AD15: 109675 | AE15: 0.061888 | AF15: 0.04491292 | AG15: 0.126793 | AH15: 0.10296856 | AI15: 0.153081 | AJ15: 0.15369528 | AK15: 0.106893 | AL15: 0.10917444 | AM15: 10.01997 | AN15: 10.442454 | AO15: 1.59176 | AP15: 1.6049558 | AQ15: 13.61295 | AR15: 13.436305 | AV15: =AV56 -> #NAME? | AX15: ROP | AY15: 50450.581 | AZ15: 58814.681 | BA15: 0.107789 | BB15: 0.16134879 | BC15: -0.342387 | BD15: 0.68387751 | BE15: 0.362131 | BF15: 0.36653877 | BG15: 0.177951 | BH15: 0.25151357 | BI15: 25.12855 | BJ15: 24.998033 | BK15: 9.38733 | BL15: 9.1627481 | BM15: 45.20111 | BN15: 31.24962
D16: TPG Capital, L.P. | F16: TPG | G16: 9455 | H16: 6765 | I16: - | J16: - | K16: - | L16: - | M16: - | N16: 0.696 | O16: 0.407 | P16: 0.447 | Q16: - | R16: - | S16: 0 | T16: - | U16: - | V16: - | Z16: =Z76 -> #NAME? | AB16: NOC | AC16: 58414.205 | AD16: 68211.205 | AE16: 0.083659 | AF16: -0.014799399 | AG16: 0.940674 | AH16: 0.30977194 | AI16: 0.148179 | AJ16: 0.16978995 | AK16: 0.120947 | AL16: 0.11010359 | AM16: 11.64045 | AN16: 11.081105 | AO16: 1.86712 | AP16: 1.8814602 | AQ16: 13.68139 | AR16: 14.633772 | AV16: =AV57 -> #NAME? | AX16: EMR | AY16: 62631.506 | AZ16: 67649.506 | BA16: 0.037736 | BB16: 0.094444229 | BC16: 0.220555 | BD16: 0.25316667 | BE16: 0.221998 | BF16: 0.22892474 | BG16: 0.13201 | BH16: 0.13269769 | BI16: 14.77147 | BJ16: 16.086328 | BK16: 3.48471 | BL16: 3.6825584 | BM16: 24.43376 | BN16: 25.692982
D18: High | G18: 113710 | H18: 103000 | I18: -0.037095 | J18: -0.3465177 | K18: -0.234765 | L18: 0.50369308 | M18: 0.488547 | N18: 1.3137771 | O18: 0.318595 | P18: 1.2021414 | Q18: 38.80019 | R18: 34.577581 | S18: 8.2148 | T18: 10.230378 | U18: 85.83265 | V18: 22.836735 | Z18: High | AC18: =MAX(AC10:AC16) -> 129979.18 | AD18: =MAX(AD10:AD16) -> 172393.18 | AE18: =MAX(AE10:AE16) -> 0.284792 | AF18: =MAX(AF10:AF16) -> 0.26827198 | AG18: =MAX(AG10:AG16) -> 0.940674 | AH18: =MAX(AH10:AH16) -> 0.30977194 | AI18: =MAX(AI10:AI16) -> 0.280531 | AJ18: =MAX(AJ10:AJ16) -> 0.29106115 | ... AR18: =MAX(AR10:AR16) -> 38.063447 | AV18: High | AY18: =MAX(AY10:AY16) -> 159578.89 | AZ18: =MAX(AZ10:AZ16) -> 169888.89 | BA18: =MAX(BA10:BA16) -> 0.19067 | BB18: =MAX(BB10:BB16) -> 0.16134879 | BC18: =MAX(BC10:BC16) -> 0.220555 | BD18: =MAX(BD10:BD16) -> 0.68387751 | BE18: =MAX(BE10:BE16) -> 0.362131 | BF18: =MAX(BF10:BF16) -> 0.36653877 | ... BN18: =MAX(BN10:BN16) -> 54.20821
D19: Mean | G19: 35780.485 | H19: 31134.385 | I19: -0.18364625 | J19: -0.46519218 | K19: -0.42519933 | L19: -0.16859531 | M19: 0.3501335 | N19: 0.6329235 | O19: 0.03269625 | P19: 0.57142114 | Q19: 22.250005 | R19: 15.479095 | S19: 3.6818733 | T19: 7.3241988 | U19: 29.404772 | V19: 12.585938 | Z19: Mean | AC19: =AVERAGE(AC10:AC16) -> 71835.782 | AD19: =AVERAGE(AD10:AD16) -> 86720.266 | AE19: =AVERAGE(AE10:AE16) -> 0.10343183 | AF19: =AVERAGE(AF10:AF16) -> 0.090083177 | AG19: =AVERAGE(AG10:AG16) -> 0.4146725 | AH19: =AVERAGE(AH10:AH16) -> -0.58363705 | AI19: =AVERAGE(AI10:AI16) -> 0.13695283 | AJ19: =AVERAGE(AJ10:AJ16) -> 0.1553956 | ... AR19: =AVERAGE(AR10:AR16) -> 21.594516 | AV19: Mean | AY19: =AVERAGE(AY10:AY16) -> 84668.22 | AZ19: =AVERAGE(AZ10:AZ16) -> 98970.554 | BA19: =AVERAGE(BA10:BA16) -> 0.057374167 | BB19: =AVERAGE(BB10:BB16) -> 0.070353941 | BC19: =AVERAGE(BC10:BC16) -> 0.024313833 | BD19: =AVERAGE(BD10:BD16) -> 0.0819595 | BE19: =AVERAGE(BE10:BE16) -> 0.2477345 | BF19: =AVERAGE(BF10:BF16) -> 0.25115621 | ... BN19: =AVERAGE(BN10:BN16) -> 32.786853
D20: Median | G20: 13491.594 | H20: 17747.531 | I20: -0.140743 | J20: -0.47652609 | K20: -0.518082 | L20: -0.33209814 | M20: 0.3501335 | N20: 0.46102477 | O20: 0.1348465 | P20: 0.43445477 | Q20: 22.250005 | R20: 11.859703 | S20: 2.83082 | T20: 7.3241988 | U20: 15.89322 | V20: 10.165805 | Z20: Median | AC20: =MEDIAN(AC10:AC16) -> 79327.603 | AD20: =MEDIAN(AD10:AD16) -> 88943.103 | AE20: =MEDIAN(AE10:AE16) -> 0.0787645 | AF20: =MEDIAN(AF10:AF16) -> 0.05024535 | AG20: =MEDIAN(AG10:AG16) -> 0.432084 | AH20: =MEDIAN(AH10:AH16) -> -0.18521988 | AI20: =MEDIAN(AI10:AI16) -> 0.14764 | AJ20: =MEDIAN(AJ10:AJ16) -> 0.15568117 | ... AR20: =MEDIAN(AR10:AR16) -> 20.919527 | AV20: Median | AY20: =MEDIAN(AY10:AY16) -> 87747.449 | AZ20: =MEDIAN(AZ10:AZ16) -> 97098.449 | BA20: =MEDIAN(BA10:BA16) -> 0.0727625 | BB20: =MEDIAN(BB10:BB16) -> 0.084152723 | BC20: =MEDIAN(BC10:BC16) -> 0.131942 | BD20: =MEDIAN(BD10:BD16) -> 0.1361163 | BE20: =MEDIAN(BE10:BE16) -> 0.2630605 | BF20: =MEDIAN(BF10:BF16) -> 0.25971191 | ... BN20: =MEDIAN(BN10:BN16) -> 29.671217
D21: Low | G21: 9455 | H21: 0 | I21: -0.416004 | J21: -0.56119885 | K21: -0.522751 | L21: -0.51387805 | M21: 0.21172 | N21: 0.29586739 | O21: -0.457503 | P21: 0.21463359 | Q21: 5.69982 | R21: 0 | S21: 0 | T21: 4.4180191 | U21: - | V21: 7.1754067 | Z21: Low | AC21: =MIN(AC10:AC16) -> 6040.9356 | AD21: =MIN(AD10:AD16) -> 5561.8386 | AE21: =MIN(AE10:AE16) -> -0.074288 | AF21: =MIN(AF10:AF16) -> -0.014799399 | AG21: =MIN(AG10:AG16) -> 0.124316 | AH21: =MIN(AH10:AH16) -> -2.5665134 | AI21: =MIN(AI10:AI16) -> -0.029095 | AJ21: =MIN(AJ10:AJ16) -> 0.075836173 | ... AR21: =MIN(AR10:AR16) -> 13.436305 | AV21: Low | AY21: =MIN(AY10:AY16) -> 6040.9356 | AZ21: =MIN(AZ10:AZ16) -> 5561.8386 | BA21: =MIN(BA10:BA16) -> -0.083477 | BB21: =MIN(BB10:BB16) -> -0.036353037 | BC21: =MIN(BC10:BC16) -> -0.342387 | BD21: =MIN(BD10:BD16) -> -0.57771187 | BE21: =MIN(BE10:BE16) -> 0.086125 | BF21: =MIN(BF10:BF16) -> 0.10098877 | ... BN21: =MIN(BN10:BN16) -> 19.414045
C23: x | D23: Company | G23: General Statistics | J23: Returns Analysis | M23: 2021A Leverage Analysis | P23: 2021A Coverage Analysis | S23: Liquidity Profile | U23: Credit Profile | Y23: x | Z23: Company | AC23: General Statistics | AF23: Returns Analysis | AI23: =TEXT(Last_FYE,"yyyy")&"A"&" Leverage Analysis" -> #REF! | AL23: =TEXT(Last_FYE,"yyyy")&"A"&" Coverage Analysis" -> #REF! | AO23: Liquidity Profile | AQ23: Credit Profile | AU23: x | AV23: Company | AY23: General Statistics | BB23: Returns Analysis | BE23: =TEXT(Last_FYE,"yyyy")&"A"&" Leverage Analysis" -> #REF! | BH23: =TEXT(Last_FYE,"yyyy")&"A"&" Coverage Analysis" -> #REF! | BK23: Liquidity Profile | BM23: Credit Profile
M24: Total Debt / | AI24: Total Debt / | BE24: Total Debt /
I25: Dividend | P25: EBITDA / | Q25: (EBITDA - | R25: EBIT / | S25: Quick | T25: Current | AE25: Dividend | AL25: EBITDA / | AM25: (EBITDA - | AN25: EBIT / | AO25: Quick | AP25: Current | BA25: Dividend | BH25: EBITDA / | BI25: (EBITDA - | BJ25: EBIT / | BK25: Quick | BL25: Current
F26: Ticker | G26: Tax Rate | H26: Beta | I26: Yield | J26: ROIC | K26: ROE | L26: ROA | M26: Cap | N26: EBITDA | O26: Equity | P26: Int. Exp. | Q26: Capex)/Int. | R26: Int. Exp. | S26: Ratio | T26: Ratio | U26: S&P | V26: Outlook | AB26: Ticker | AC26: Tax Rate | AD26: Beta | AE26: Yield | AF26: ROIC | AG26: ROE | AH26: ROA | AI26: Cap | AJ26: EBITDA | AK26: Equity | AL26: Int. Exp. | AM26: Capex)/Int. | AN26: Int. Exp. | AO26: Ratio | AP26: Ratio | AQ26: S&P | AR26: Outlook | AX26: Ticker | AY26: Tax Rate | AZ26: Beta | BA26: Yield | BB26: ROIC | BC26: ROE | BD26: ROA | BE26: Cap | BF26: EBITDA | BG26: Equity | BH26: Int. Exp. | BI26: Capex)/Int. | BJ26: Int. Exp. | BK26: Ratio | BL26: Ratio | BM26: S&P | BN26: Outlook
D28: KKR & Co. Inc. | F28: KKR | G28: 0.099151 | H28: 1.54912 | I28: 0.012555 | J28: 0.039748464 | K28: 0.061055 | L28: 0.012982 | M28: 0.406371 | N28: - | O28: 0.684554 | P28: - | Q28: - | R28: - | S28: 0.7986 | T28: 0.89431 | U28: A | V28: Stable | Z28: =Company_Name -> #REF! | AB28: LOW | AC28: 0.246026 | AD28: 1.32679 | AE28: 0.015541 | AF28: 0.39441919 | AG28: 3.353264 | AH28: 0.153199 | AI28: 94.8025 | AJ28: 1.9578 | AK28: 1824.0083 | AL28: 15.35321 | AM28: 13.29931 | AN28: 12.49083 | AO28: 0.27742 | AP28: 1.19199 | AQ28: BBB+ | AR28: Stable | AV28: =Company_Name -> #REF! | AX28: LOW | AY28: 0.246026 | AZ28: 1.32679 | BA28: 0.015541 | BB28: 0.39441919 | BC28: 3.353264 | BD28: 0.153199 | BE28: 94.8025 | BF28: 1.9578 | BG28: 1824.0083 | BH28: 15.35321 | BI28: 13.29931 | BJ28: 12.49083 | BK28: 0.27742 | BL28: 1.19199 | BM28: BBB+ | BN28: Stable
D30: Apollo Global Management, Inc. | F30: APO | G30: 0.122243 | H30: 1.65204 | I30: 0.028761 | J30: -0.33191272 | K30: -0.369654 | L30: -0.023879 | M30: 0.542628 | N30: - | O30: 1.186407 | P30: - | Q30: - | R30: - | S30: 1.07675 | T30: 1.50792 | U30: - | V30: - | Z30: =Z53 -> #NAME? | AB30: RTX | AC30: 0.14074 | AD30: 1.0574 | AE30: 0.023887 | AF30: 0.21877749 | AG30: 0.032482 | AH30: 0.017917 | AI30: 31.4015 | AJ30: 4.73816 | AK30: 45.7758 | AL30: 5.0696 | AM30: 3.79474 | AN30: 1.76491 | AO30: 0.78071 | AP30: 1.21 | AQ30: A- | AR30: Negative | AV30: =AV53 -> #NAME? | AX30: MMM | AY30: 0.19654 | AZ30: 0.95802 | BA30: 0.030351 | BB30: 0.22662902 | BC30: 0.466124 | BD30: 0.109264 | BE30: 60.4629 | BF30: 2.09659 | BG30: 152.927 | BH30: 17.82987 | BI30: 14.99244 | BJ30: 13.36862 | BK30: 1.24245 | BL30: 1.885 | BM30: A+ | BN30: Negative
D31: Ares Capital Corporation | F31: ARCC | G31: 0.1383 | H31: 1.25401 | I31: 0.031733 | J31: 0.027917436 | K31: 0.089 | L31: 0.039 | M31: 0.717881 | N31: 12.16631 | O31: 2.544612 | P31: 3.48372 | Q31: 3.39137 | R31: 2.97007 | S31: 0.57659 | T31: 0.59688 | U31: BBB+ | V31: Stable | Z31: =Z54 -> #NAME? | AB31: BA | AC31: 0.14074 | AD31: 1.62028 | AE31: 0 | AF31: 0.21877749 | AG31: 0.032482 | AH31: -0.016131 | AI31: 138.5723 | AJ31: NM | AK31: NM | AL31: NM | AM31: NM | AN31: NM | AO31: 0.40835 | AP31: 1.3937 | AQ31: BBB- | AR31: Negative | AV31: =AV54 -> #NAME? | AX31: GE | AY31: 0.19654 | AZ31: 1.07651 | BA31: 0.003016 | BB31: 0.22662902 | BC31: 0.002275 | BD31: 0.002249 | BE31: 67.7933 | BF31: 11.46958 | BG31: 210.4952 | BH31: 5.10428 | BI31: 2.66467 | BJ31: NM | BK31: 1.21993 | BL31: 1.57684 | BM31: BBB+ | BN31: Watch Neg
D32: Blackstone Inc. | F32: BX | G32: 0.087349 | H32: 1.44373 | I32: 0.043571 | J32: 0.19387348 | K32: 0.255381 | L32: 0.130797 | M32: 0.289906 | N32: - | O32: 0.408266 | P32: - | Q32: - | R32: - | S32: - | T32: - | U32: A+ | V32: Stable | Z32: =Z55 -> #NAME? | AB32: HII | AC32: 0.14074 | AD32: 1.00423 | AE32: 0.02203 | AF32: 0.21877749 | AG32: 0.399465 | AH32: 0.069584 | AI32: 49.7222 | AJ32: 1.52846 | AK32: 98.8953 | AL32: 10.78947 | AM32: 7.69298 | AN32: 7.77193 | AO32: 0.95642 | AP32: 1.09793 | AQ32: BBB- | AR32: Negative | AV32: =AV55 -> #NAME? | AX32: HON | AY32: 0.190785 | AZ32: 1.18583 | BA32: 0.016094 | BB32: 0.2001168 | BC32: 0.276365 | BD32: 0.070619 | BE32: 56.6022 | BF32: 2.93637 | BG32: 130.4264 | BH32: 22.0195 | BI32: 19.49582 | BJ32: 18.53482 | BK32: 1.15815 | BL32: 1.46768 | BM32: A | BN32: Stable
D33: The Carlyle Group Inc. | F33: CG | G33: 0.243898 | H33: 1.69547 | I33: 0.04517 | J33: 0.16802016 | K33: 0.371167 | L33: 0.090622 | M33: 0.598313 | N33: 1.91036 | O33: 1.489502 | P33: 15.24709 | Q33: 15.10521 | R33: 14.89068 | S33: 2.10543 | T33: 2.11118 | U33: A- | V33: Stable | Z33: =Z56 -> #NAME? | AB33: LMT | AC33: 0.16357 | AD33: 0.97956 | AE33: 0.02873 | AF33: 0.47399098 | AG33: 1.395308 | AH33: 0.111133 | AI33: 68.7506 | AJ33: 1.2993 | AK33: 220.0066 | AL33: 17.29949 | AM33: 14.31134 | AN33: 15.0203 | AO33: 1.05383 | AP33: 1.3908 | AQ33: A- | AR33: Stable | AV33: =AV56 -> #NAME? | AX33: ROP | AY33: 0.214669 | AZ33: 1.04534 | BA33: 0.004701 | BB33: 0.062702786 | BC33: 0.101626 | BD33: 0.045176 | BE33: 48.453 | BF33: 4.87567 | BG33: 93.9979 | BH33: 9.22979 | BI33: 9.08725 | BJ33: 6.53769 | BK33: 0.58702 | BL33: 0.71686 | BM33: BBB+ | BN33: Stable
D34: TPG Capital, L.P. | F34: TPG | G34: 0.002 | H34: 1.28 | I34: 0.054 | J34: 0.597 | K34: 0.317 | L34: 0.254 | M34: - | N34: - | O34: - | P34: - | Q34: - | R34: - | S34: - | T34: - | U34: - | V34: - | Z34: =Z57 -> #NAME? | AB34: NOC | AC34: 0.144581 | AD34: 0.83876 | AE34: 0.017213 | AF34: 0.17260348 | AG34: 0.435548 | AH34: 0.063013 | AI34: 61.0894 | AJ34: 2.79754 | AK34: 156.9997 | AL34: 10.0118 | AM34: 7.6172 | AN34: 7.13153 | AO34: 1.2881 | AP34: 1.60167 | AQ34: BBB+ | AR34: Stable | AV34: =AV57 -> #NAME? | AX34: EMR | AY34: 0.147751 | AZ34: 1.53469 | BA34: 0.01928 | BB34: 0.18755553 | BC34: 0.276819 | BD34: 0.085174 | BE34: 48.6629 | BF34: 2.10102 | BG34: 94.791 | BH34: 21.77714 | BI34: 18.70286 | BJ34: 16.27429 | BK34: 1.13656 | BL34: 1.52221 | BM34: A | BN34: Stable
D36: High | G36: 0.243898 | H36: 1.69547 | I36: 0.04517 | J36: 0.19387348 | K36: 0.371167 | L36: 0.130797 | M36: 0.717881 | N36: 12.16631 | O36: 2.544612 | P36: 15.24709 | Q36: 15.10521 | R36: 14.89068 | S36: 2.10543 | T36: 2.11118 | Z36: =Z18 -> High | AC36: =MAX(AC28:AC34) -> 0.246026 | AD36: =MAX(AD28:AD34) -> 1.62028 | AE36: =MAX(AE28:AE34) -> 0.02873 | AF36: =MAX(AF28:AF34) -> 0.47399098 | AG36: =MAX(AG28:AG34) -> 3.353264 | AH36: =MAX(AH28:AH34) -> 0.153199 | AI36: =MAX(AI28:AI34) -> 138.5723 | AJ36: =MAX(AJ28:AJ34) -> 4.73816 | ... AP36: =MAX(AP28:AP34) -> 1.60167 | AV36: =AV18 -> High | AY36: =MAX(AY28:AY34) -> 0.246026 | AZ36: =MAX(AZ28:AZ34) -> 1.53469 | BA36: =MAX(BA28:BA34) -> 0.030351 | BB36: =MAX(BB28:BB34) -> 0.39441919 | BC36: =MAX(BC28:BC34) -> 3.353264 | BD36: =MAX(BD28:BD34) -> 0.153199 | BE36: =MAX(BE28:BE34) -> 94.8025 | BF36: =MAX(BF28:BF34) -> 11.46958 | ... BL36: =MAX(BL28:BL34) -> 1.885
D37: Mean | G37: 0.118358 | H37: 1.20905 | I37: 0.029847 | J37: 0.011579671 | K37: 0.0513788 | L37: 0.039508 | M37: 0.4297456 | N37: 4.6922233 | O37: 1.1257574 | P37: 6.2436033 | Q37: 6.1655267 | R37: 5.9535833 | S37: 0.91971 | T37: 1.014982 | Z37: =Z19 -> Mean | AC37: =AVERAGE(AC28:AC34) -> 0.16273283 | AD37: =AVERAGE(AD28:AD34) -> 1.1378367 | AE37: =AVERAGE(AE28:AE34) -> 0.017900167 | AF37: =AVERAGE(AF28:AF34) -> 0.28289102 | AG37: =AVERAGE(AG28:AG34) -> 0.94142483 | AH37: =AVERAGE(AH28:AH34) -> 0.0664525 | AI37: =AVERAGE(AI28:AI34) -> 74.056417 | AJ37: =AVERAGE(AJ28:AJ34) -> 2.464252 | ... AP37: =AVERAGE(AP28:AP34) -> 1.3143483 | AV37: =AV19 -> Mean | AY37: =AVERAGE(AY28:AY34) -> 0.1987185 | AZ37: =AVERAGE(AZ28:AZ34) -> 1.1878633 | BA37: =AVERAGE(BA28:BA34) -> 0.0148305 | BB37: =AVERAGE(BB28:BB34) -> 0.21634206 | BC37: =AVERAGE(BC28:BC34) -> 0.74607883 | BD37: =AVERAGE(BD28:BD34) -> 0.0776135 | BE37: =AVERAGE(BE28:BE34) -> 62.796133 | BF37: =AVERAGE(BF28:BF34) -> 4.239505 | ... BL37: =AVERAGE(BL28:BL34) -> 1.39343
D38: Median | G38: 0.122243 | H38: 1.44373 | I38: 0.031733 | J38: 0.027917436 | K38: 0 | L38: 0 | M38: 0.542628 | N38: 1.91036 | O38: 1.186407 | P38: 3.48372 | Q38: 3.39137 | R38: 2.97007 | S38: 0.83978 | T38: 0.85893 | Z38: =Z20 -> Median | AC38: =MEDIAN(AC28:AC34) -> 0.1426605 | AD38: =MEDIAN(AD28:AD34) -> 1.030815 | AE38: =MEDIAN(AE28:AE34) -> 0.0196215 | AF38: =MEDIAN(AF28:AF34) -> 0.21877749 | AG38: =MEDIAN(AG28:AG34) -> 0.4175065 | AH38: =MEDIAN(AH28:AH34) -> 0.0662985 | AI38: =MEDIAN(AI28:AI34) -> 64.92 | AJ38: =MEDIAN(AJ28:AJ34) -> 1.9578 | ... AP38: =MEDIAN(AP28:AP34) -> 1.3004 | AV38: =AV20 -> Median | AY38: =MEDIAN(AY28:AY34) -> 0.19654 | AZ38: =MEDIAN(AZ28:AZ34) -> 1.13117 | BA38: =MEDIAN(BA28:BA34) -> 0.0158175 | BB38: =MEDIAN(BB28:BB34) -> 0.21337291 | BC38: =MEDIAN(BC28:BC34) -> 0.276592 | BD38: =MEDIAN(BD28:BD34) -> 0.0778965 | BE38: =MEDIAN(BE28:BE34) -> 58.53255 | BF38: =MEDIAN(BF28:BF34) -> 2.518695 | ... BL38: =MEDIAN(BL28:BL34) -> 1.494945
C39: x | D39: Low | G39: 0 | H39: 0 | I39: 0 | J39: -0.33191272 | K39: -0.369654 | L39: -0.023879 | M39: - | N39: - | O39: - | P39: - | Q39: - | R39: - | S39: - | T39: - | Y39: x | Z39: =Z21 -> Low | AC39: =MIN(AC28:AC34) -> 0.14074 | AD39: =MIN(AD28:AD34) -> 0.83876 | AE39: =MIN(AE28:AE34) -> 0 | AF39: =MIN(AF28:AF34) -> 0.17260348 | AG39: =MIN(AG28:AG34) -> 0.032482 | AH39: =MIN(AH28:AH34) -> -0.016131 | AI39: =MIN(AI28:AI34) -> 31.4015 | AJ39: =MIN(AJ28:AJ34) -> 1.2993 | ... AP39: =MIN(AP28:AP34) -> 1.09793 | AU39: x | AV39: =AV21 -> Low | AY39: =MIN(AY28:AY34) -> 0.147751 | AZ39: =MIN(AZ28:AZ34) -> 0.95802 | BA39: =MIN(BA28:BA34) -> 0.003016 | BB39: =MIN(BB28:BB34) -> 0.062702786 | BC39: =MIN(BC28:BC34) -> 0.002275 | BD39: =MIN(BD28:BD34) -> 0.002249 | BE39: =MIN(BE28:BE34) -> 48.453 | BF39: =MIN(BF28:BF34) -> 1.9578 | ... BL39: =MIN(BL28:BL34) -> 0.71686
C43: h | Y43: h | AU43: h
D44: Capital IQ Tables
D46: =D4 -> Primary Peer Group | Z46: =Z4 -> Defense Peer Group | AV46: =AV4 -> Cap. Goods Peer Group
Q47: =Q6 -> Enterprise Value / | T47: =T6 -> 0 | AM47: =AM6 -> Enterprise Value / | AP47: =AP6 -> 0 | BI47: =BI6 -> Enterprise Value / | BL47: =BL6 -> 0
G48: =G7 -> Market | H48: =H7 -> Enterprise | I48: =I7 -> Sales | K48: =K7 -> EPS | M48: =M7 -> EBITDA Margin | O48: =O7 -> Profit Margin | Q48: =Q7 -> EBITDA | S48: =S7 -> Sales | U48: =U7 -> Price / Earnings | AC48: =AC7 -> Market | AD48: =AD7 -> Enterprise | AE48: =AE7 -> Sales | AG48: =AG7 -> EPS | AI48: =AI7 -> EBITDA Margin | AK48: =AK7 -> Profit Margin | AM48: =AM7 -> EBITDA | AO48: =AO7 -> Sales | AQ48: =AQ7 -> Price / Earnings | AY48: =AY7 -> Market | AZ48: =AZ7 -> Enterprise | BA48: =BA7 -> Sales | BC48: =BC7 -> EPS | BE48: =BE7 -> EBITDA Margin | BG48: =BG7 -> Profit Margin | BI48: =BI7 -> EBITDA | BK48: =BK7 -> Sales | BM48: =BM7 -> Price / Earnings
F49: =F8 -> Ticker | G49: =G8 -> Cap | H49: =H8 -> Value | I49: =I8 -> LTM | J49: =J8 -> 44590 | K49: =K8 -> LTM | L49: =L8 -> 44590 | M49: =M8 -> LTM | ... V49: =V8 -> 44590 | AB49: =AB8 -> Ticker | AC49: =AC8 -> Cap | AD49: =AD8 -> Value | AE49: =AE8 -> LTM | AF49: =AF8 -> #REF! | AG49: =AG8 -> LTM | AH49: =AH8 -> 44590 | AI49: =AI8 -> LTM | ... AR49: =AR8 -> 44590 | AX49: =AX8 -> Ticker | AY49: =AY8 -> Cap | AZ49: =AZ8 -> Value | BA49: =BA8 -> LTM | BB49: =BB8 -> #REF! | BC49: =BC8 -> LTM | BD49: =BD8 -> 44590 | BE49: =BE8 -> LTM | ... BN49: =BN8 -> 44590
B51: =B70 -> IQ21401 | D51: =_xll.ciqfunctions.udf.CIQ($B51, "IQ_COMPANY_NAME",Current_Date) -> #NAME? | F51: =$E$89 -> KKR | G51: =_xll.ciqfunctions.udf.CIQ($B51, "IQ_MARKETCAP",Current_Date) -> #NAME? | H51: =_xll.ciqfunctions.udf.CIQ($B51, "IQ_TEV",Current_Date) -> #NAME? | I51: =_xll.ciqfunctions.udf.CIQ($B51, "IQ_TOTAL_REV_1YR_ANN_GROWTH",IQ_LTM,Current_Date)/100 -> #NAME? | J51: =_xll.ciqfunctions.udf.CIQ($B51,"IQ_REVENUE_EST",IQ_FY+1)/(_xll.ciqfunctions.udf.CIQ($B51,"IQ_TOTAL_REV",IQ_FY))-1 -> #NAME? | K51: =_xll.ciqfunctions.udf.CIQ($B51, "IQ_EPS_1YR_ANN_GROWTH",IQ_LTM,Current_Date)/100 -> #NAME? | L51: =_xll.ciqfunctions.udf.CIQ($B51,"IQ_EPS_EST",IQ_FY+1)/(_xll.ciqfunctions.udf.CIQ($B51,"IQ_DILUT_EPS_INCL",IQ_FY))-1 -> #NAME? | M51: =_xll.ciqfunctions.udf.CIQ($B51, "IQ_EBITDA_MARGIN",IQ_LTM)/100 -> #NAME? | N51: =_xll.ciqfunctions.udf.CIQ($B51,"IQ_EBITDA_EST",IQ_FY+1)/(_xll.ciqfunctions.udf.CIQ($B51,"IQ_REVENUE_EST",IQ_FY+1)) -> #NAME? | O51: =_xll.ciqfunctions.udf.CIQ($B51, "IQ_NI_MARGIN",IQ_LTM)/100 -> #NAME? | P51: =_xll.ciqfunctions.udf.CIQ($B51,"IQ_NI_EST",IQ_FY+1)/(_xll.ciqfunctions.udf.CIQ($B51,"IQ_REVENUE_EST",IQ_FY+1)) -> #NAME? | Q51: - | R51: - | S51: - | T51: - | U51: =_xll.ciqfunctions.udf.CIQ($B51, "IQ_PE_EXCL",IQ_LTM) -> #NAME? | V51: =_xll.ciqfunctions.udf.CIQ($B51, "IQ_MARKETCAP",Current_Date)/_xll.ciqfunctions.udf.CIQ($B51, "IQ_NI_EST",IQ_FY+1) -> #NAME? | X51: =X70 -> IQ21401 | Z51: =Company_Name -> #REF! | AB51: =$E$89 -> KKR | AC51: =_xll.ciqfunctions.udf.CIQ($X51, "IQ_MARKETCAP",Current_Date) -> #NAME? | AD51: =_xll.ciqfunctions.udf.CIQ($X51, "IQ_TEV",Current_Date) -> #NAME? | AE51: =_xll.ciqfunctions.udf.CIQ($X51, "IQ_TOTAL_REV_1YR_ANN_GROWTH",IQ_LTM,Current_Date)/100 -> #NAME? | AF51: =_xll.ciqfunctions.udf.CIQ($X51,"IQ_REVENUE_EST",IQ_FY+1)/(_xll.ciqfunctions.udf.CIQ($X51,"IQ_TOTAL_REV",IQ_FY))-1 -> #NAME? | AG51: =_xll.ciqfunctions.udf.CIQ($X51, "IQ_EPS_1YR_ANN_GROWTH",IQ_LTM,Current_Date)/100 -> #NAME? | AH51: =_xll.ciqfunctions.udf.CIQ($X51,"IQ_EPS_EST",IQ_FY+1)/(_xll.ciqfunctions.udf.CIQ($X51,"IQ_DILUT_EPS_INCL",IQ_FY))-1 -> #NAME? | AI51: =_xll.ciqfunctions.udf.CIQ($X51, "IQ_EBITDA_MARGIN",IQ_LTM)/100 -> #NAME? | AJ51: =_xll.ciqfunctions.udf.CIQ($X51,"IQ_EBITDA_EST",IQ_FY+1)/(_xll.ciqfunctions.udf.CIQ($X51,"IQ_REVENUE_EST",IQ_FY+1)) -> #NAME? | AK51: =_xll.ciqfunctions.udf.CIQ($X51, "IQ_NI_MARGIN",IQ_LTM)/100 -> #NAME? | AL51: =_xll.ciqfunctions.udf.CIQ($X51,"IQ_NI_EST",IQ_FY+1)/(_xll.ciqfunctions.udf.CIQ($X51,"IQ_REVENUE_EST",IQ_FY+1)) -> #NAME? | AM51: =_xll.ciqfunctions.udf.CIQ($X51, "IQ_TEV_EBITDA",IQ_LTM) -> #NAME? | AN51: =_xll.ciqfunctions.udf.CIQ($X51, "IQ_TEV",Current_Date)/_xll.ciqfunctions.udf.CIQ($X51, "IQ_EBITDA_EST",IQ_FY+1) -> #NAME? | AO51: =_xll.ciqfunctions.udf.CIQ($X51, "IQ_TEV_TOTAL_REV",IQ_LTM) -> #NAME? | AP51: =_xll.ciqfunctions.udf.CIQ($X51, "IQ_TEV",Current_Date)/_xll.ciqfunctions.udf.CIQ($X51, "IQ_REVENUE_EST",IQ_FY+1) -> #NAME? | AQ51: =_xll.ciqfunctions.udf.CIQ($X51, "IQ_PE_EXCL",IQ_LTM) -> #NAME? | AR51: =_xll.ciqfunctions.udf.CIQ($X51, "IQ_MARKETCAP",Current_Date)/_xll.ciqfunctions.udf.CIQ($X51, "IQ_NI_EST",IQ_FY+1) -> #NAME? | AT51: =AT70 -> IQ21401 | AV51: =Company_Name -> #REF! | AX51: =Ticker -> #REF! | AY51: =_xll.ciqfunctions.udf.CIQ($AT51, "IQ_MARKETCAP",Current_Date) -> #NAME? | AZ51: =_xll.ciqfunctions.udf.CIQ($AT51, "IQ_TEV",Current_Date) -> #NAME? | BA51: =_xll.ciqfunctions.udf.CIQ($AT51, "IQ_TOTAL_REV_1YR_ANN_GROWTH",IQ_LTM,Current_Date)/100 -> #NAME? | BB51: =_xll.ciqfunctions.udf.CIQ($AT51,"IQ_REVENUE_EST",IQ_FY+1)/(_xll.ciqfunctions.udf.CIQ($AT51,"IQ_TOTAL_REV",IQ_FY))-1 -> #NAME? | BC51: =_xll.ciqfunctions.udf.CIQ($AT51, "IQ_EPS_1YR_ANN_GROWTH",IQ_LTM,Current_Date)/100 -> #NAME? | BD51: =_xll.ciqfunctions.udf.CIQ($AT51,"IQ_EPS_EST",IQ_FY+1)/(_xll.ciqfunctions.udf.CIQ($AT51,"IQ_DILUT_EPS_INCL",IQ_FY))-1 -> #NAME? | BE51: =_xll.ciqfunctions.udf.CIQ($AT51, "IQ_EBITDA_MARGIN",IQ_LTM)/100 -> #NAME? | BF51: =_xll.ciqfunctions.udf.CIQ($AT51,"IQ_EBITDA_EST",IQ_FY+1)/(_xll.ciqfunctions.udf.CIQ($AT51,"IQ_REVENUE_EST",IQ_FY+1)) -> #NAME? | BG51: =_xll.ciqfunctions.udf.CIQ($AT51, "IQ_NI_MARGIN",IQ_LTM)/100 -> #NAME? | BH51: =_xll.ciqfunctions.udf.CIQ($AT51,"IQ_NI_EST",IQ_FY+1)/(_xll.ciqfunctions.udf.CIQ($AT51,"IQ_REVENUE_EST",IQ_FY+1)) -> #NAME? | BI51: =_xll.ciqfunctions.udf.CIQ($AT51, "IQ_TEV_EBITDA",IQ_LTM) -> #NAME? | BJ51: =_xll.ciqfunctions.udf.CIQ($AT51, "IQ_TEV",Current_Date)/_xll.ciqfunctions.udf.CIQ($AT51, "IQ_EBITDA_EST",IQ_FY+1) -> #NAME? | BK51: =_xll.ciqfunctions.udf.CIQ($AT51, "IQ_TEV_TOTAL_REV",IQ_LTM) -> #NAME? | BL51: =_xll.ciqfunctions.udf.CIQ($AT51, "IQ_TEV",Current_Date)/_xll.ciqfunctions.udf.CIQ($AT51, "IQ_REVENUE_EST",IQ_FY+1) -> #NAME? | BM51: =_xll.ciqfunctions.udf.CIQ($AT51, "IQ_PE_EXCL",IQ_LTM) -> #NAME? | BN51: =_xll.ciqfunctions.udf.CIQ($AT51, "IQ_MARKETCAP",Current_Date)/_xll.ciqfunctions.udf.CIQ($AT51, "IQ_NI_EST",IQ_FY+1) -> #NAME?
B53: =B72 -> IQ18833 | D53: =_xll.ciqfunctions.udf.CIQ($B53, "IQ_COMPANY_NAME",Current_Date) -> #NAME? | F53: =F72 -> APO | G53: =_xll.ciqfunctions.udf.CIQ($B53, "IQ_MARKETCAP",Current_Date) -> #NAME? | H53: =_xll.ciqfunctions.udf.CIQ($B53, "IQ_TEV",Current_Date) -> #NAME? | I53: =_xll.ciqfunctions.udf.CIQ($B53, "IQ_TOTAL_REV_1YR_ANN_GROWTH",IQ_LTM,Current_Date)/100 -> #NAME? | J53: =_xll.ciqfunctions.udf.CIQ($B53,"IQ_REVENUE_EST",IQ_FY+1)/(_xll.ciqfunctions.udf.CIQ($B53,"IQ_TOTAL_REV",IQ_FY))-1 -> #NAME? | K53: - | L53: =_xll.ciqfunctions.udf.CIQ($B53,"IQ_EPS_EST",IQ_FY+1)/(_xll.ciqfunctions.udf.CIQ($B53,"IQ_DILUT_EPS_INCL",IQ_FY))-1 -> #NAME? | M53: - | N53: =_xll.ciqfunctions.udf.CIQ($B53,"IQ_EBITDA_EST",IQ_FY+1)/(_xll.ciqfunctions.udf.CIQ($B53,"IQ_REVENUE_EST",IQ_FY+1)) -> #NAME? | O53: =_xll.ciqfunctions.udf.CIQ($B53, "IQ_NI_MARGIN",IQ_LTM)/100 -> #NAME? | P53: =_xll.ciqfunctions.udf.CIQ($B53,"IQ_NI_EST",IQ_FY+1)/(_xll.ciqfunctions.udf.CIQ($B53,"IQ_REVENUE_EST",IQ_FY+1)) -> #NAME? | Q53: - | R53: - | S53: - | T53: - | U53: - | V53: =_xll.ciqfunctions.udf.CIQ($B53, "IQ_MARKETCAP",Current_Date)/_xll.ciqfunctions.udf.CIQ($B53, "IQ_NI_EST",IQ_FY+1) -> #NAME? | X53: =X72 -> IQ159230 | Z53: =_xll.ciqfunctions.udf.CIQ($X53, "IQ_COMPANY_NAME",Current_Date) -> #NAME? | AB53: =AB72 -> RTX | AC53: =_xll.ciqfunctions.udf.CIQ($X53, "IQ_MARKETCAP",Current_Date) -> #NAME? | AD53: =_xll.ciqfunctions.udf.CIQ($X53, "IQ_TEV",Current_Date) -> #NAME? | AE53: =_xll.ciqfunctions.udf.CIQ($X53, "IQ_TOTAL_REV_1YR_ANN_GROWTH",IQ_LTM,Current_Date)/100 -> #NAME? | AF53: =_xll.ciqfunctions.udf.CIQ($X53,"IQ_REVENUE_EST",IQ_FY+1)/(_xll.ciqfunctions.udf.CIQ($X53,"IQ_TOTAL_REV",IQ_FY))-1 -> #NAME? | AG53: =_xll.ciqfunctions.udf.CIQ($X53, "IQ_EPS_1YR_ANN_GROWTH",IQ_LTM,Current_Date)/100 -> #NAME? | AH53: =_xll.ciqfunctions.udf.CIQ($X53,"IQ_EPS_EST",IQ_FY+1)/(_xll.ciqfunctions.udf.CIQ($X53,"IQ_DILUT_EPS_INCL",IQ_FY))-1 -> #NAME? | AI53: =_xll.ciqfunctions.udf.CIQ($X53, "IQ_EBITDA_MARGIN",IQ_LTM)/100 -> #NAME? | AJ53: =_xll.ciqfunctions.udf.CIQ($X53,"IQ_EBITDA_EST",IQ_FY+1)/(_xll.ciqfunctions.udf.CIQ($X53,"IQ_REVENUE_EST",IQ_FY+1)) -> #NAME? | AK53: =_xll.ciqfunctions.udf.CIQ($X53, "IQ_NI_MARGIN",IQ_LTM)/100 -> #NAME? | AL53: =_xll.ciqfunctions.udf.CIQ($X53,"IQ_NI_EST",IQ_FY+1)/(_xll.ciqfunctions.udf.CIQ($X53,"IQ_REVENUE_EST",IQ_FY+1)) -> #NAME? | AM53: =_xll.ciqfunctions.udf.CIQ($X53, "IQ_TEV_EBITDA",IQ_LTM) -> #NAME? | AN53: =_xll.ciqfunctions.udf.CIQ($X53, "IQ_TEV",Current_Date)/_xll.ciqfunctions.udf.CIQ($X53, "IQ_EBITDA_EST",IQ_FY+1) -> #NAME? | AO53: =_xll.ciqfunctions.udf.CIQ($X53, "IQ_TEV_TOTAL_REV",IQ_LTM) -> #NAME? | AP53: =_xll.ciqfunctions.udf.CIQ($X53, "IQ_TEV",Current_Date)/_xll.ciqfunctions.udf.CIQ($X53, "IQ_REVENUE_EST",IQ_FY+1) -> #NAME? | AQ53: =_xll.ciqfunctions.udf.CIQ($X53, "IQ_PE_EXCL",IQ_LTM) -> #NAME? | AR53: =_xll.ciqfunctions.udf.CIQ($X53, "IQ_MARKETCAP",Current_Date)/_xll.ciqfunctions.udf.CIQ($X53, "IQ_NI_EST",IQ_FY+1) -> #NAME? | AT53: =AT72 -> IQ289194 | AV53: =_xll.ciqfunctions.udf.CIQ($AT53, "IQ_COMPANY_NAME",Current_Date) -> #NAME? | AX53: =N93 -> MMM | AY53: =_xll.ciqfunctions.udf.CIQ($AT53, "IQ_MARKETCAP",Current_Date) -> #NAME? | AZ53: =_xll.ciqfunctions.udf.CIQ($AT53, "IQ_TEV",Current_Date) -> #NAME? | BA53: =_xll.ciqfunctions.udf.CIQ($AT53, "IQ_TOTAL_REV_1YR_ANN_GROWTH",IQ_LTM,Current_Date)/100 -> #NAME? | BB53: =_xll.ciqfunctions.udf.CIQ($AT53,"IQ_REVENUE_EST",IQ_FY+1)/(_xll.ciqfunctions.udf.CIQ($AT53,"IQ_TOTAL_REV",IQ_FY))-1 -> #NAME? | BC53: =_xll.ciqfunctions.udf.CIQ($AT53, "IQ_EPS_1YR_ANN_GROWTH",IQ_LTM,Current_Date)/100 -> #NAME? | BD53: =_xll.ciqfunctions.udf.CIQ($AT53,"IQ_EPS_EST",IQ_FY+1)/(_xll.ciqfunctions.udf.CIQ($AT53,"IQ_DILUT_EPS_INCL",IQ_FY))-1 -> #NAME? | BE53: =_xll.ciqfunctions.udf.CIQ($AT53, "IQ_EBITDA_MARGIN",IQ_LTM)/100 -> #NAME? | BF53: =_xll.ciqfunctions.udf.CIQ($AT53,"IQ_EBITDA_EST",IQ_FY+1)/(_xll.ciqfunctions.udf.CIQ($AT53,"IQ_REVENUE_EST",IQ_FY+1)) -> #NAME? | BG53: =_xll.ciqfunctions.udf.CIQ($AT53, "IQ_NI_MARGIN",IQ_LTM)/100 -> #NAME? | BH53: =_xll.ciqfunctions.udf.CIQ($AT53,"IQ_NI_EST",IQ_FY+1)/(_xll.ciqfunctions.udf.CIQ($AT53,"IQ_REVENUE_EST",IQ_FY+1)) -> #NAME? | BI53: =_xll.ciqfunctions.udf.CIQ($AT53, "IQ_TEV_EBITDA",IQ_LTM) -> #NAME? | BJ53: =_xll.ciqfunctions.udf.CIQ($AT53, "IQ_TEV",Current_Date)/_xll.ciqfunctions.udf.CIQ($AT53, "IQ_EBITDA_EST",IQ_FY+1) -> #NAME? | BK53: =_xll.ciqfunctions.udf.CIQ($AT53, "IQ_TEV_TOTAL_REV",IQ_LTM) -> #NAME? | BL53: =_xll.ciqfunctions.udf.CIQ($AT53, "IQ_TEV",Current_Date)/_xll.ciqfunctions.udf.CIQ($AT53, "IQ_REVENUE_EST",IQ_FY+1) -> #NAME? | BM53: =_xll.ciqfunctions.udf.CIQ($AT53, "IQ_PE_EXCL",IQ_LTM) -> #NAME? | BN53: =_xll.ciqfunctions.udf.CIQ($AT53, "IQ_MARKETCAP",Current_Date)/_xll.ciqfunctions.udf.CIQ($AT53, "IQ_NI_EST",IQ_FY+1) -> #NAME?
B54: =B73 -> IQ44707236 | D54: Ares Capital Corporation | F54: =F73 -> ARCC | G54: =_xll.ciqfunctions.udf.CIQ($B54, "IQ_MARKETCAP",Current_Date) -> #NAME? | H54: =_xll.ciqfunctions.udf.CIQ($B54, "IQ_TEV",Current_Date) -> #NAME? | I54: =_xll.ciqfunctions.udf.CIQ($B54, "IQ_TOTAL_REV_1YR_ANN_GROWTH",IQ_LTM,Current_Date)/100 -> #NAME? | J54: =_xll.ciqfunctions.udf.CIQ($B54,"IQ_REVENUE_EST",IQ_FY+1)/(_xll.ciqfunctions.udf.CIQ($B54,"IQ_TOTAL_REV",IQ_FY))-1 -> #NAME? | K54: =_xll.ciqfunctions.udf.CIQ($B54, "IQ_EPS_1YR_ANN_GROWTH",IQ_LTM,Current_Date)/100 -> #NAME? | L54: =_xll.ciqfunctions.udf.CIQ($B54,"IQ_EPS_EST",IQ_FY+1)/(_xll.ciqfunctions.udf.CIQ($B54,"IQ_DILUT_EPS_INCL",IQ_FY))-1 -> #NAME? | M54: =_xll.ciqfunctions.udf.CIQ($B54, "IQ_EBITDA_MARGIN",IQ_LTM)/100 -> #NAME? | N54: =_xll.ciqfunctions.udf.CIQ($B54,"IQ_EBITDA_EST",IQ_FY+1)/(_xll.ciqfunctions.udf.CIQ($B54,"IQ_REVENUE_EST",IQ_FY+1)) -> #NAME? | O54: =_xll.ciqfunctions.udf.CIQ($B54, "IQ_NI_MARGIN",IQ_LTM)/100 -> #NAME? | P54: =_xll.ciqfunctions.udf.CIQ($B54,"IQ_NI_EST",IQ_FY+1)/(_xll.ciqfunctions.udf.CIQ($B54,"IQ_REVENUE_EST",IQ_FY+1)) -> #NAME? | Q54: =_xll.ciqfunctions.udf.CIQ($B54, "IQ_TEV_EBITDA",IQ_LTM) -> #NAME? | R54: =_xll.ciqfunctions.udf.CIQ($B54, "IQ_TEV",Current_Date)/_xll.ciqfunctions.udf.CIQ($B54, "IQ_EBITDA_EST",IQ_FY+1) -> #NAME? | S54: =_xll.ciqfunctions.udf.CIQ($B54, "IQ_TEV_TOTAL_REV",IQ_LTM) -> #NAME? | T54: =_xll.ciqfunctions.udf.CIQ($B54, "IQ_TEV",Current_Date)/_xll.ciqfunctions.udf.CIQ($B54, "IQ_REVENUE_EST",IQ_FY+1) -> #NAME? | U54: =_xll.ciqfunctions.udf.CIQ($B54, "IQ_PE_EXCL",IQ_LTM) -> #NAME? | V54: =_xll.ciqfunctions.udf.CIQ($B54, "IQ_MARKETCAP",Current_Date)/_xll.ciqfunctions.udf.CIQ($B54, "IQ_NI_EST",IQ_FY+1) -> #NAME? | X54: =X73 -> IQ370857 | Z54: =_xll.ciqfunctions.udf.CIQ($X54, "IQ_COMPANY_NAME",Current_Date) -> #NAME? | AB54: =AB73 -> BA | AC54: =_xll.ciqfunctions.udf.CIQ($X54, "IQ_MARKETCAP",Current_Date) -> #NAME? | AD54: =_xll.ciqfunctions.udf.CIQ($X54, "IQ_TEV",Current_Date) -> #NAME? | AE54: =_xll.ciqfunctions.udf.CIQ($X54, "IQ_TOTAL_REV_1YR_ANN_GROWTH",IQ_LTM,Current_Date)/100 -> #NAME? | AF54: =_xll.ciqfunctions.udf.CIQ($X54,"IQ_REVENUE_EST",IQ_FY+1)/(_xll.ciqfunctions.udf.CIQ($X54,"IQ_TOTAL_REV",IQ_FY))-1 -> #NAME? | AG54: =_xll.ciqfunctions.udf.CIQ($X54, "IQ_EPS_1YR_ANN_GROWTH",IQ_LTM,Current_Date)/100 -> #NAME? | AH54: =_xll.ciqfunctions.udf.CIQ($X54,"IQ_EPS_EST",IQ_FY+1)/(_xll.ciqfunctions.udf.CIQ($X54,"IQ_DILUT_EPS_INCL",IQ_FY))-1 -> #NAME? | AI54: =_xll.ciqfunctions.udf.CIQ($X54, "IQ_EBITDA_MARGIN",IQ_LTM)/100 -> #NAME? | AJ54: =_xll.ciqfunctions.udf.CIQ($X54,"IQ_EBITDA_EST",IQ_FY+1)/(_xll.ciqfunctions.udf.CIQ($X54,"IQ_REVENUE_EST",IQ_FY+1)) -> #NAME? | AK54: =_xll.ciqfunctions.udf.CIQ($X54, "IQ_NI_MARGIN",IQ_LTM)/100 -> #NAME? | AL54: =_xll.ciqfunctions.udf.CIQ($X54,"IQ_NI_EST",IQ_FY+1)/(_xll.ciqfunctions.udf.CIQ($X54,"IQ_REVENUE_EST",IQ_FY+1)) -> #NAME? | AM54: =_xll.ciqfunctions.udf.CIQ($X54, "IQ_TEV_EBITDA",IQ_LTM) -> #NAME? | AN54: =_xll.ciqfunctions.udf.CIQ($X54, "IQ_TEV",Current_Date)/_xll.ciqfunctions.udf.CIQ($X54, "IQ_EBITDA_EST",IQ_FY+1) -> #NAME? | AO54: =_xll.ciqfunctions.udf.CIQ($X54, "IQ_TEV_TOTAL_REV",IQ_LTM) -> #NAME? | AP54: =_xll.ciqfunctions.udf.CIQ($X54, "IQ_TEV",Current_Date)/_xll.ciqfunctions.udf.CIQ($X54, "IQ_REVENUE_EST",IQ_FY+1) -> #NAME? | AQ54: =_xll.ciqfunctions.udf.CIQ($X54, "IQ_PE_EXCL",IQ_LTM) -> #NAME? | AR54: =_xll.ciqfunctions.udf.CIQ($X54, "IQ_MARKETCAP",Current_Date)/_xll.ciqfunctions.udf.CIQ($X54, "IQ_NI_EST",IQ_FY+1) -> #NAME? | AT54: =AT73 -> IQ177031 | AV54: =_xll.ciqfunctions.udf.CIQ($AT54, "IQ_COMPANY_NAME",Current_Date) -> #NAME? | AX54: =N97 -> GE | AY54: =_xll.ciqfunctions.udf.CIQ($AT54, "IQ_MARKETCAP",Current_Date) -> #NAME? | AZ54: =_xll.ciqfunctions.udf.CIQ($AT54, "IQ_TEV",Current_Date) -> #NAME? | BA54: =_xll.ciqfunctions.udf.CIQ($AT54, "IQ_TOTAL_REV_1YR_ANN_GROWTH",IQ_LTM,Current_Date)/100 -> #NAME? | BB54: =_xll.ciqfunctions.udf.CIQ($AT54,"IQ_REVENUE_EST",IQ_FY+1)/(_xll.ciqfunctions.udf.CIQ($AT54,"IQ_TOTAL_REV",IQ_FY))-1 -> #NAME? | BC54: =_xll.ciqfunctions.udf.CIQ($AT54, "IQ_EPS_1YR_ANN_GROWTH",IQ_LTM,Current_Date)/100 -> #NAME? | BD54: =_xll.ciqfunctions.udf.CIQ($AT54,"IQ_EPS_EST",IQ_FY+1)/(_xll.ciqfunctions.udf.CIQ($AT54,"IQ_DILUT_EPS_INCL",IQ_FY))-1 -> #NAME? | BE54: =_xll.ciqfunctions.udf.CIQ($AT54, "IQ_EBITDA_MARGIN",IQ_LTM)/100 -> #NAME? | BF54: =_xll.ciqfunctions.udf.CIQ($AT54,"IQ_EBITDA_EST",IQ_FY+1)/(_xll.ciqfunctions.udf.CIQ($AT54,"IQ_REVENUE_EST",IQ_FY+1)) -> #NAME? | BG54: =_xll.ciqfunctions.udf.CIQ($AT54, "IQ_NI_MARGIN",IQ_LTM)/100 -> #NAME? | BH54: =_xll.ciqfunctions.udf.CIQ($AT54,"IQ_NI_EST",IQ_FY+1)/(_xll.ciqfunctions.udf.CIQ($AT54,"IQ_REVENUE_EST",IQ_FY+1)) -> #NAME? | BI54: =_xll.ciqfunctions.udf.CIQ($AT54, "IQ_TEV_EBITDA",IQ_LTM) -> #NAME? | BJ54: =_xll.ciqfunctions.udf.CIQ($AT54, "IQ_TEV",Current_Date)/_xll.ciqfunctions.udf.CIQ($AT54, "IQ_EBITDA_EST",IQ_FY+1) -> #NAME? | BK54: =_xll.ciqfunctions.udf.CIQ($AT54, "IQ_TEV_TOTAL_REV",IQ_LTM) -> #NAME? | BL54: =_xll.ciqfunctions.udf.CIQ($AT54, "IQ_TEV",Current_Date)/_xll.ciqfunctions.udf.CIQ($AT54, "IQ_REVENUE_EST",IQ_FY+1) -> #NAME? | BM54: =_xll.ciqfunctions.udf.CIQ($AT54, "IQ_PE_EXCL",IQ_LTM) -> #NAME? | BN54: =_xll.ciqfunctions.udf.CIQ($AT54, "IQ_MARKETCAP",Current_Date)/_xll.ciqfunctions.udf.CIQ($AT54, "IQ_NI_EST",IQ_FY+1) -> #NAME?
B55: =B74 -> IQ671980 | D55: =_xll.ciqfunctions.udf.CIQ($B55, "IQ_COMPANY_NAME",Current_Date) -> #NAME? | F55: =F74 -> BX | G55: 113710 | H55: 103000 | I55: =_xll.ciqfunctions.udf.CIQ($B55, "IQ_TOTAL_REV_1YR_ANN_GROWTH",IQ_LTM,Current_Date)/100 -> #NAME? | J55: =_xll.ciqfunctions.udf.CIQ($B55,"IQ_REVENUE_EST",IQ_FY+1)/(_xll.ciqfunctions.udf.CIQ($B55,"IQ_TOTAL_REV",IQ_FY))-1 -> #NAME? | K55: =_xll.ciqfunctions.udf.CIQ($B55, "IQ_EPS_1YR_ANN_GROWTH",IQ_LTM,Current_Date)/100 -> #NAME? | L55: =_xll.ciqfunctions.udf.CIQ($B55,"IQ_EPS_EST",IQ_FY+1)/(_xll.ciqfunctions.udf.CIQ($B55,"IQ_DILUT_EPS_INCL",IQ_FY))-1 -> #NAME? | M55: - | N55: =_xll.ciqfunctions.udf.CIQ($B55,"IQ_EBITDA_EST",IQ_FY+1)/(_xll.ciqfunctions.udf.CIQ($B55,"IQ_REVENUE_EST",IQ_FY+1)) -> #NAME? | O55: =_xll.ciqfunctions.udf.CIQ($B55, "IQ_NI_MARGIN",IQ_LTM)/100 -> #NAME? | P55: =_xll.ciqfunctions.udf.CIQ($B55,"IQ_NI_EST",IQ_FY+1)/(_xll.ciqfunctions.udf.CIQ($B55,"IQ_REVENUE_EST",IQ_FY+1)) -> #NAME? | Q55: - | R55: =_xll.ciqfunctions.udf.CIQ($B55, "IQ_TEV",Current_Date)/_xll.ciqfunctions.udf.CIQ($B55, "IQ_EBITDA_EST",IQ_FY+1) -> #NAME? | S55: - | T55: - | U55: =_xll.ciqfunctions.udf.CIQ($B55, "IQ_PE_EXCL",IQ_LTM) -> #NAME? | V55: =_xll.ciqfunctions.udf.CIQ($B55, "IQ_MARKETCAP",Current_Date)/_xll.ciqfunctions.udf.CIQ($B55, "IQ_NI_EST",IQ_FY+1) -> #NAME? | X55: =X74 -> IQ363263 | Z55: =_xll.ciqfunctions.udf.CIQ($X55, "IQ_COMPANY_NAME",Current_Date) -> #NAME? | AB55: =AB74 -> HII | AC55: =_xll.ciqfunctions.udf.CIQ($X55, "IQ_MARKETCAP",Current_Date) -> #NAME? | AD55: =_xll.ciqfunctions.udf.CIQ($X55, "IQ_TEV",Current_Date) -> #NAME? | AE55: =_xll.ciqfunctions.udf.CIQ($X55, "IQ_TOTAL_REV_1YR_ANN_GROWTH",IQ_LTM,Current_Date)/100 -> #NAME? | AF55: =_xll.ciqfunctions.udf.CIQ($X55,"IQ_REVENUE_EST",IQ_FY+1)/(_xll.ciqfunctions.udf.CIQ($X55,"IQ_TOTAL_REV",IQ_FY))-1 -> #NAME? | AG55: =_xll.ciqfunctions.udf.CIQ($X55, "IQ_EPS_1YR_ANN_GROWTH",IQ_LTM,Current_Date)/100 -> #NAME? | AH55: =_xll.ciqfunctions.udf.CIQ($X55,"IQ_EPS_EST",IQ_FY+1)/(_xll.ciqfunctions.udf.CIQ($X55,"IQ_DILUT_EPS_INCL",IQ_FY))-1 -> #NAME? | AI55: =_xll.ciqfunctions.udf.CIQ($X55, "IQ_EBITDA_MARGIN",IQ_LTM)/100 -> #NAME? | AJ55: =_xll.ciqfunctions.udf.CIQ($X55,"IQ_EBITDA_EST",IQ_FY+1)/(_xll.ciqfunctions.udf.CIQ($X55,"IQ_REVENUE_EST",IQ_FY+1)) -> #NAME? | AK55: =_xll.ciqfunctions.udf.CIQ($X55, "IQ_NI_MARGIN",IQ_LTM)/100 -> #NAME? | AL55: =_xll.ciqfunctions.udf.CIQ($X55,"IQ_NI_EST",IQ_FY+1)/(_xll.ciqfunctions.udf.CIQ($X55,"IQ_REVENUE_EST",IQ_FY+1)) -> #NAME? | AM55: =_xll.ciqfunctions.udf.CIQ($X55, "IQ_TEV_EBITDA",IQ_LTM) -> #NAME? | AN55: =_xll.ciqfunctions.udf.CIQ($X55, "IQ_TEV",Current_Date)/_xll.ciqfunctions.udf.CIQ($X55, "IQ_EBITDA_EST",IQ_FY+1) -> #NAME? | AO55: =_xll.ciqfunctions.udf.CIQ($X55, "IQ_TEV_TOTAL_REV",IQ_LTM) -> #NAME? | AP55: =_xll.ciqfunctions.udf.CIQ($X55, "IQ_TEV",Current_Date)/_xll.ciqfunctions.udf.CIQ($X55, "IQ_REVENUE_EST",IQ_FY+1) -> #NAME? | AQ55: =_xll.ciqfunctions.udf.CIQ($X55, "IQ_PE_EXCL",IQ_LTM) -> #NAME? | AR55: =_xll.ciqfunctions.udf.CIQ($X55, "IQ_MARKETCAP",Current_Date)/_xll.ciqfunctions.udf.CIQ($X55, "IQ_NI_EST",IQ_FY+1) -> #NAME? | AT55: =AT74 -> IQ1340740 | AV55: =_xll.ciqfunctions.udf.CIQ($AT55, "IQ_COMPANY_NAME",Current_Date) -> #NAME? | AX55: =N101 -> HON | AY55: =_xll.ciqfunctions.udf.CIQ($AT55, "IQ_MARKETCAP",Current_Date) -> #NAME? | AZ55: =_xll.ciqfunctions.udf.CIQ($AT55, "IQ_TEV",Current_Date) -> #NAME? | BA55: =_xll.ciqfunctions.udf.CIQ($AT55, "IQ_TOTAL_REV_1YR_ANN_GROWTH",IQ_LTM,Current_Date)/100 -> #NAME? | BB55: =_xll.ciqfunctions.udf.CIQ($AT55,"IQ_REVENUE_EST",IQ_FY+1)/(_xll.ciqfunctions.udf.CIQ($AT55,"IQ_TOTAL_REV",IQ_FY))-1 -> #NAME? | BC55: =_xll.ciqfunctions.udf.CIQ($AT55, "IQ_EPS_1YR_ANN_GROWTH",IQ_LTM,Current_Date)/100 -> #NAME? | BD55: =_xll.ciqfunctions.udf.CIQ($AT55,"IQ_EPS_EST",IQ_FY+1)/(_xll.ciqfunctions.udf.CIQ($AT55,"IQ_DILUT_EPS_INCL",IQ_FY))-1 -> #NAME? | BE55: =_xll.ciqfunctions.udf.CIQ($AT55, "IQ_EBITDA_MARGIN",IQ_LTM)/100 -> #NAME? | BF55: =_xll.ciqfunctions.udf.CIQ($AT55,"IQ_EBITDA_EST",IQ_FY+1)/(_xll.ciqfunctions.udf.CIQ($AT55,"IQ_REVENUE_EST",IQ_FY+1)) -> #NAME? | BG55: =_xll.ciqfunctions.udf.CIQ($AT55, "IQ_NI_MARGIN",IQ_LTM)/100 -> #NAME? | BH55: =_xll.ciqfunctions.udf.CIQ($AT55,"IQ_NI_EST",IQ_FY+1)/(_xll.ciqfunctions.udf.CIQ($AT55,"IQ_REVENUE_EST",IQ_FY+1)) -> #NAME? | BI55: =_xll.ciqfunctions.udf.CIQ($AT55, "IQ_TEV_EBITDA",IQ_LTM) -> #NAME? | BJ55: =_xll.ciqfunctions.udf.CIQ($AT55, "IQ_TEV",Current_Date)/_xll.ciqfunctions.udf.CIQ($AT55, "IQ_EBITDA_EST",IQ_FY+1) -> #NAME? | BK55: =_xll.ciqfunctions.udf.CIQ($AT55, "IQ_TEV_TOTAL_REV",IQ_LTM) -> #NAME? | BL55: =_xll.ciqfunctions.udf.CIQ($AT55, "IQ_TEV",Current_Date)/_xll.ciqfunctions.udf.CIQ($AT55, "IQ_REVENUE_EST",IQ_FY+1) -> #NAME? | BM55: =_xll.ciqfunctions.udf.CIQ($AT55, "IQ_PE_EXCL",IQ_LTM) -> #NAME? | BN55: =_xll.ciqfunctions.udf.CIQ($AT55, "IQ_MARKETCAP",Current_Date)/_xll.ciqfunctions.udf.CIQ($AT55, "IQ_NI_EST",IQ_FY+1) -> #NAME?
B56: =B75 -> IQ23333 | D56: =_xll.ciqfunctions.udf.CIQ($B56, "IQ_COMPANY_NAME",Current_Date) -> #NAME? | F56: =F75 -> CG | G56: =_xll.ciqfunctions.udf.CIQ($B56, "IQ_MARKETCAP",Current_Date) -> #NAME? | H56: =_xll.ciqfunctions.udf.CIQ($B56, "IQ_TEV",Current_Date) -> #NAME? | I56: =_xll.ciqfunctions.udf.CIQ($B56, "IQ_TOTAL_REV_1YR_ANN_GROWTH",IQ_LTM,Current_Date)/100 -> #NAME? | J56: =_xll.ciqfunctions.udf.CIQ($B56,"IQ_REVENUE_EST",IQ_FY+1)/(_xll.ciqfunctions.udf.CIQ($B56,"IQ_TOTAL_REV",IQ_FY))-1 -> #NAME? | K56: =_xll.ciqfunctions.udf.CIQ($B56, "IQ_EPS_1YR_ANN_GROWTH",IQ_LTM,Current_Date)/100 -> #NAME? | L56: =_xll.ciqfunctions.udf.CIQ($B56,"IQ_EPS_EST",IQ_FY+1)/(_xll.ciqfunctions.udf.CIQ($B56,"IQ_DILUT_EPS_INCL",IQ_FY))-1 -> #NAME? | M56: =_xll.ciqfunctions.udf.CIQ($B56, "IQ_EBITDA_MARGIN",IQ_LTM)/100 -> #NAME? | N56: =_xll.ciqfunctions.udf.CIQ($B56,"IQ_EBITDA_EST",IQ_FY+1)/(_xll.ciqfunctions.udf.CIQ($B56,"IQ_REVENUE_EST",IQ_FY+1)) -> #NAME? | O56: =_xll.ciqfunctions.udf.CIQ($B56, "IQ_NI_MARGIN",IQ_LTM)/100 -> #NAME? | P56: =_xll.ciqfunctions.udf.CIQ($B56,"IQ_NI_EST",IQ_FY+1)/(_xll.ciqfunctions.udf.CIQ($B56,"IQ_REVENUE_EST",IQ_FY+1)) -> #NAME? | Q56: =_xll.ciqfunctions.udf.CIQ($B56, "IQ_TEV_EBITDA",IQ_LTM) -> #NAME? | R56: =_xll.ciqfunctions.udf.CIQ($B56, "IQ_TEV",Current_Date)/_xll.ciqfunctions.udf.CIQ($B56, "IQ_EBITDA_EST",IQ_FY+1) -> #NAME? | S56: =_xll.ciqfunctions.udf.CIQ($B56, "IQ_TEV_TOTAL_REV",IQ_LTM) -> #NAME? | T56: =_xll.ciqfunctions.udf.CIQ($B56, "IQ_TEV",Current_Date)/_xll.ciqfunctions.udf.CIQ($B56, "IQ_REVENUE_EST",IQ_FY+1) -> #NAME? | U56: =_xll.ciqfunctions.udf.CIQ($B56, "IQ_PE_EXCL",IQ_LTM) -> #NAME? | V56: =_xll.ciqfunctions.udf.CIQ($B56, "IQ_MARKETCAP",Current_Date)/_xll.ciqfunctions.udf.CIQ($B56, "IQ_NI_EST",IQ_FY+1) -> #NAME? | X56: =X75 -> IQ285827 | Z56: =_xll.ciqfunctions.udf.CIQ($X56, "IQ_COMPANY_NAME",Current_Date) -> #NAME? | AB56: =AB75 -> LMT | AC56: =_xll.ciqfunctions.udf.CIQ($X56, "IQ_MARKETCAP",Current_Date) -> #NAME? | AD56: =_xll.ciqfunctions.udf.CIQ($X56, "IQ_TEV",Current_Date) -> #NAME? | AE56: =_xll.ciqfunctions.udf.CIQ($X56, "IQ_TOTAL_REV_1YR_ANN_GROWTH",IQ_LTM,Current_Date)/100 -> #NAME? | AF56: =_xll.ciqfunctions.udf.CIQ($X56,"IQ_REVENUE_EST",IQ_FY+1)/(_xll.ciqfunctions.udf.CIQ($X56,"IQ_TOTAL_REV",IQ_FY))-1 -> #NAME? | AG56: =_xll.ciqfunctions.udf.CIQ($X56, "IQ_EPS_1YR_ANN_GROWTH",IQ_LTM,Current_Date)/100 -> #NAME? | AH56: =_xll.ciqfunctions.udf.CIQ($X56,"IQ_EPS_EST",IQ_FY+1)/(_xll.ciqfunctions.udf.CIQ($X56,"IQ_DILUT_EPS_INCL",IQ_FY))-1 -> #NAME? | AI56: =_xll.ciqfunctions.udf.CIQ($X56, "IQ_EBITDA_MARGIN",IQ_LTM)/100 -> #NAME? | AJ56: =_xll.ciqfunctions.udf.CIQ($X56,"IQ_EBITDA_EST",IQ_FY+1)/(_xll.ciqfunctions.udf.CIQ($X56,"IQ_REVENUE_EST",IQ_FY+1)) -> #NAME? | AK56: =_xll.ciqfunctions.udf.CIQ($X56, "IQ_NI_MARGIN",IQ_LTM)/100 -> #NAME? | AL56: =_xll.ciqfunctions.udf.CIQ($X56,"IQ_NI_EST",IQ_FY+1)/(_xll.ciqfunctions.udf.CIQ($X56,"IQ_REVENUE_EST",IQ_FY+1)) -> #NAME? | AM56: =_xll.ciqfunctions.udf.CIQ($X56, "IQ_TEV_EBITDA",IQ_LTM) -> #NAME? | AN56: =_xll.ciqfunctions.udf.CIQ($X56, "IQ_TEV",Current_Date)/_xll.ciqfunctions.udf.CIQ($X56, "IQ_EBITDA_EST",IQ_FY+1) -> #NAME? | AO56: =_xll.ciqfunctions.udf.CIQ($X56, "IQ_TEV_TOTAL_REV",IQ_LTM) -> #NAME? | AP56: =_xll.ciqfunctions.udf.CIQ($X56, "IQ_TEV",Current_Date)/_xll.ciqfunctions.udf.CIQ($X56, "IQ_REVENUE_EST",IQ_FY+1) -> #NAME? | AQ56: =_xll.ciqfunctions.udf.CIQ($X56, "IQ_PE_EXCL",IQ_LTM) -> #NAME? | AR56: =_xll.ciqfunctions.udf.CIQ($X56, "IQ_MARKETCAP",Current_Date)/_xll.ciqfunctions.udf.CIQ($X56, "IQ_NI_EST",IQ_FY+1) -> #NAME? | AT56: =AT75 -> IQ22751 | AV56: =_xll.ciqfunctions.udf.CIQ($AT56, "IQ_COMPANY_NAME",Current_Date) -> #NAME? | AX56: =N105 -> ROP | AY56: =_xll.ciqfunctions.udf.CIQ($AT56, "IQ_MARKETCAP",Current_Date) -> #NAME? | AZ56: =_xll.ciqfunctions.udf.CIQ($AT56, "IQ_TEV",Current_Date) -> #NAME? | BA56: =_xll.ciqfunctions.udf.CIQ($AT56, "IQ_TOTAL_REV_1YR_ANN_GROWTH",IQ_LTM,Current_Date)/100 -> #NAME? | BB56: =_xll.ciqfunctions.udf.CIQ($AT56,"IQ_REVENUE_EST",IQ_FY+1)/(_xll.ciqfunctions.udf.CIQ($AT56,"IQ_TOTAL_REV",IQ_FY))-1 -> #NAME? | BC56: =_xll.ciqfunctions.udf.CIQ($AT56, "IQ_EPS_1YR_ANN_GROWTH",IQ_LTM,Current_Date)/100 -> #NAME? | BD56: =_xll.ciqfunctions.udf.CIQ($AT56,"IQ_EPS_EST",IQ_FY+1)/(_xll.ciqfunctions.udf.CIQ($AT56,"IQ_DILUT_EPS_INCL",IQ_FY))-1 -> #NAME? | BE56: =_xll.ciqfunctions.udf.CIQ($AT56, "IQ_EBITDA_MARGIN",IQ_LTM)/100 -> #NAME? | BF56: =_xll.ciqfunctions.udf.CIQ($AT56,"IQ_EBITDA_EST",IQ_FY+1)/(_xll.ciqfunctions.udf.CIQ($AT56,"IQ_REVENUE_EST",IQ_FY+1)) -> #NAME? | BG56: =_xll.ciqfunctions.udf.CIQ($AT56, "IQ_NI_MARGIN",IQ_LTM)/100 -> #NAME? | BH56: =_xll.ciqfunctions.udf.CIQ($AT56,"IQ_NI_EST",IQ_FY+1)/(_xll.ciqfunctions.udf.CIQ($AT56,"IQ_REVENUE_EST",IQ_FY+1)) -> #NAME? | BI56: =_xll.ciqfunctions.udf.CIQ($AT56, "IQ_TEV_EBITDA",IQ_LTM) -> #NAME? | BJ56: =_xll.ciqfunctions.udf.CIQ($AT56, "IQ_TEV",Current_Date)/_xll.ciqfunctions.udf.CIQ($AT56, "IQ_EBITDA_EST",IQ_FY+1) -> #NAME? | BK56: =_xll.ciqfunctions.udf.CIQ($AT56, "IQ_TEV_TOTAL_REV",IQ_LTM) -> #NAME? | BL56: =_xll.ciqfunctions.udf.CIQ($AT56, "IQ_TEV",Current_Date)/_xll.ciqfunctions.udf.CIQ($AT56, "IQ_REVENUE_EST",IQ_FY+1) -> #NAME? | BM56: =_xll.ciqfunctions.udf.CIQ($AT56, "IQ_PE_EXCL",IQ_LTM) -> #NAME? | BN56: =_xll.ciqfunctions.udf.CIQ($AT56, "IQ_MARKETCAP",Current_Date)/_xll.ciqfunctions.udf.CIQ($AT56, "IQ_NI_EST",IQ_FY+1) -> #NAME?
B57: =B76 -> IQ23307 | D57: =_xll.ciqfunctions.udf.CIQ($B57, "IQ_COMPANY_NAME",Current_Date) -> #NAME? | F57: =F76 -> TPG | G57: 9455 | H57: 6765 | I57: - | J57: - | K57: - | L57: - | M57: - | N57: - | O57: - | P57: - | Q57: - | R57: - | S57: =_xll.ciqfunctions.udf.CIQ($B57, "IQ_TEV_TOTAL_REV",IQ_LTM) -> #NAME? | T57: - | U57: =_xll.ciqfunctions.udf.CIQ($B57, "IQ_PE_EXCL",IQ_LTM) -> #NAME? | V57: - | X57: =X76 -> IQ97199 | Z57: =_xll.ciqfunctions.udf.CIQ($X57, "IQ_COMPANY_NAME",Current_Date) -> #NAME? | AB57: =AB76 -> NOC | AC57: =_xll.ciqfunctions.udf.CIQ($X57, "IQ_MARKETCAP",Current_Date) -> #NAME? | AD57: =_xll.ciqfunctions.udf.CIQ($X57, "IQ_TEV",Current_Date) -> #NAME? | AE57: =_xll.ciqfunctions.udf.CIQ($X57, "IQ_TOTAL_REV_1YR_ANN_GROWTH",IQ_LTM,Current_Date)/100 -> #NAME? | AF57: =_xll.ciqfunctions.udf.CIQ($X57,"IQ_REVENUE_EST",IQ_FY+1)/(_xll.ciqfunctions.udf.CIQ($X57,"IQ_TOTAL_REV",IQ_FY))-1 -> #NAME? | AG57: =_xll.ciqfunctions.udf.CIQ($X57, "IQ_EPS_1YR_ANN_GROWTH",IQ_LTM,Current_Date)/100 -> #NAME? | AH57: =_xll.ciqfunctions.udf.CIQ($X57,"IQ_EPS_EST",IQ_FY+1)/(_xll.ciqfunctions.udf.CIQ($X57,"IQ_DILUT_EPS_INCL",IQ_FY))-1 -> #NAME? | AI57: =_xll.ciqfunctions.udf.CIQ($X57, "IQ_EBITDA_MARGIN",IQ_LTM)/100 -> #NAME? | AJ57: =_xll.ciqfunctions.udf.CIQ($X57,"IQ_EBITDA_EST",IQ_FY+1)/(_xll.ciqfunctions.udf.CIQ($X57,"IQ_REVENUE_EST",IQ_FY+1)) -> #NAME? | AK57: =_xll.ciqfunctions.udf.CIQ($X57, "IQ_NI_MARGIN",IQ_LTM)/100 -> #NAME? | AL57: =_xll.ciqfunctions.udf.CIQ($X57,"IQ_NI_EST",IQ_FY+1)/(_xll.ciqfunctions.udf.CIQ($X57,"IQ_REVENUE_EST",IQ_FY+1)) -> #NAME? | AM57: =_xll.ciqfunctions.udf.CIQ($X57, "IQ_TEV_EBITDA",IQ_LTM) -> #NAME? | AN57: =_xll.ciqfunctions.udf.CIQ($X57, "IQ_TEV",Current_Date)/_xll.ciqfunctions.udf.CIQ($X57, "IQ_EBITDA_EST",IQ_FY+1) -> #NAME? | AO57: =_xll.ciqfunctions.udf.CIQ($X57, "IQ_TEV_TOTAL_REV",IQ_LTM) -> #NAME? | AP57: =_xll.ciqfunctions.udf.CIQ($X57, "IQ_TEV",Current_Date)/_xll.ciqfunctions.udf.CIQ($X57, "IQ_REVENUE_EST",IQ_FY+1) -> #NAME? | AQ57: =_xll.ciqfunctions.udf.CIQ($X57, "IQ_PE_EXCL",IQ_LTM) -> #NAME? | AR57: =_xll.ciqfunctions.udf.CIQ($X57, "IQ_MARKETCAP",Current_Date)/_xll.ciqfunctions.udf.CIQ($X57, "IQ_NI_EST",IQ_FY+1) -> #NAME? | AT57: =AT76 -> IQ269231 | AV57: =_xll.ciqfunctions.udf.CIQ($AT57, "IQ_COMPANY_NAME",Current_Date) -> #NAME? | AX57: =N109 -> EMR | AY57: =_xll.ciqfunctions.udf.CIQ($AT57, "IQ_MARKETCAP",Current_Date) -> #NAME? | AZ57: =_xll.ciqfunctions.udf.CIQ($AT57, "IQ_TEV",Current_Date) -> #NAME? | BA57: =_xll.ciqfunctions.udf.CIQ($AT57, "IQ_TOTAL_REV_1YR_ANN_GROWTH",IQ_LTM,Current_Date)/100 -> #NAME? | BB57: =_xll.ciqfunctions.udf.CIQ($AT57,"IQ_REVENUE_EST",IQ_FY+1)/(_xll.ciqfunctions.udf.CIQ($AT57,"IQ_TOTAL_REV",IQ_FY))-1 -> #NAME? | BC57: =_xll.ciqfunctions.udf.CIQ($AT57, "IQ_EPS_1YR_ANN_GROWTH",IQ_LTM,Current_Date)/100 -> #NAME? | BD57: =_xll.ciqfunctions.udf.CIQ($AT57,"IQ_EPS_EST",IQ_FY+1)/(_xll.ciqfunctions.udf.CIQ($AT57,"IQ_DILUT_EPS_INCL",IQ_FY))-1 -> #NAME? | BE57: =_xll.ciqfunctions.udf.CIQ($AT57, "IQ_EBITDA_MARGIN",IQ_LTM)/100 -> #NAME? | BF57: =_xll.ciqfunctions.udf.CIQ($AT57,"IQ_EBITDA_EST",IQ_FY+1)/(_xll.ciqfunctions.udf.CIQ($AT57,"IQ_REVENUE_EST",IQ_FY+1)) -> #NAME? | BG57: =_xll.ciqfunctions.udf.CIQ($AT57, "IQ_NI_MARGIN",IQ_LTM)/100 -> #NAME? | BH57: =_xll.ciqfunctions.udf.CIQ($AT57,"IQ_NI_EST",IQ_FY+1)/(_xll.ciqfunctions.udf.CIQ($AT57,"IQ_REVENUE_EST",IQ_FY+1)) -> #NAME? | BI57: =_xll.ciqfunctions.udf.CIQ($AT57, "IQ_TEV_EBITDA",IQ_LTM) -> #NAME? | BJ57: =_xll.ciqfunctions.udf.CIQ($AT57, "IQ_TEV",Current_Date)/_xll.ciqfunctions.udf.CIQ($AT57, "IQ_EBITDA_EST",IQ_FY+1) -> #NAME? | BK57: =_xll.ciqfunctions.udf.CIQ($AT57, "IQ_TEV_TOTAL_REV",IQ_LTM) -> #NAME? | BL57: =_xll.ciqfunctions.udf.CIQ($AT57, "IQ_TEV",Current_Date)/_xll.ciqfunctions.udf.CIQ($AT57, "IQ_REVENUE_EST",IQ_FY+1) -> #NAME? | BM57: =_xll.ciqfunctions.udf.CIQ($AT57, "IQ_PE_EXCL",IQ_LTM) -> #NAME? | BN57: =_xll.ciqfunctions.udf.CIQ($AT57, "IQ_MARKETCAP",Current_Date)/_xll.ciqfunctions.udf.CIQ($AT57, "IQ_NI_EST",IQ_FY+1) -> #NAME?
D59: =D18 -> High | G59: =MAX(G53:G57) -> #NAME? | H59: =MAX(H53:H57) -> #NAME? | I59: =MAX(I53:I57) -> #NAME? | J59: =MAX(J53:J57) -> #NAME? | K59: =MAX(K53:K57) -> #NAME? | L59: =MAX(L53:L57) -> #NAME? | M59: =MAX(M53:M57) -> #NAME? | N59: =MAX(N53:N57) -> #NAME? | ... V59: =MAX(V53:V57) -> #NAME? | Z59: =Z18 -> High | AC59: =MAX(AC53:AC57) -> #NAME? | AD59: =MAX(AD53:AD57) -> #NAME? | AE59: =MAX(AE53:AE57) -> #NAME? | AF59: =MAX(AF53:AF57) -> #NAME? | AG59: =MAX(AG53:AG57) -> #NAME? | AH59: =MAX(AH53:AH57) -> #NAME? | AI59: =MAX(AI53:AI57) -> #NAME? | AJ59: =MAX(AJ53:AJ57) -> #NAME? | ... AR59: =MAX(AR53:AR57) -> #NAME? | AV59: =AV18 -> High | AY59: =MAX(AY53:AY57) -> #NAME? | AZ59: =MAX(AZ53:AZ57) -> #NAME? | BA59: =MAX(BA53:BA57) -> #NAME? | BB59: =MAX(BB53:BB57) -> #NAME? | BC59: =MAX(BC53:BC57) -> #NAME? | BD59: =MAX(BD53:BD57) -> #NAME? | BE59: =MAX(BE53:BE57) -> #NAME? | BF59: =MAX(BF53:BF57) -> #NAME? | ... BN59: =MAX(BN53:BN57) -> #NAME?
D60: =D19 -> Mean | G60: =AVERAGE(G53:G57) -> #NAME? | H60: =AVERAGE(H53:H57) -> #NAME? | I60: =AVERAGE(I53:I57) -> #NAME? | J60: =AVERAGE(J53:J57) -> #NAME? | K60: =AVERAGE(K53:K57) -> #NAME? | L60: =AVERAGE(L53:L57) -> #NAME? | M60: =AVERAGE(M53:M57) -> #NAME? | N60: =AVERAGE(N53:N57) -> #NAME? | ... V60: =AVERAGE(V53:V57) -> #NAME? | Z60: =Z19 -> Mean | AC60: =AVERAGE(AC53:AC57) -> #NAME? | AD60: =AVERAGE(AD53:AD57) -> #NAME? | AE60: =AVERAGE(AE53:AE57) -> #NAME? | AF60: =AVERAGE(AF53:AF57) -> #NAME? | AG60: =AVERAGE(AG53:AG57) -> #NAME? | AH60: =AVERAGE(AH53:AH57) -> #NAME? | AI60: =AVERAGE(AI53:AI57) -> #NAME? | AJ60: =AVERAGE(AJ53:AJ57) -> #NAME? | ... AR60: =AVERAGE(AR53:AR57) -> #NAME? | AV60: =AV19 -> Mean | AY60: =AVERAGE(AY53:AY57) -> #NAME? | AZ60: =AVERAGE(AZ53:AZ57) -> #NAME? | BA60: =AVERAGE(BA53:BA57) -> #NAME? | BB60: =AVERAGE(BB53:BB57) -> #NAME? | BC60: =AVERAGE(BC53:BC57) -> #NAME? | BD60: =AVERAGE(BD53:BD57) -> #NAME? | BE60: =AVERAGE(BE53:BE57) -> #NAME? | BF60: =AVERAGE(BF53:BF57) -> #NAME? | ... BN60: =AVERAGE(BN53:BN57) -> #NAME?
D61: =D20 -> Median | G61: =MEDIAN(G53:G57) -> #NAME? | H61: =MEDIAN(H53:H57) -> #NAME? | I61: =MEDIAN(I53:I57) -> #NAME? | J61: =MEDIAN(J53:J57) -> #NAME? | K61: =MEDIAN(K53:K57) -> #NAME? | L61: =MEDIAN(L53:L57) -> #NAME? | M61: =MEDIAN(M53:M57) -> #NAME? | N61: =MEDIAN(N53:N57) -> #NAME? | ... V61: =MEDIAN(V53:V57) -> #NAME? | Z61: =Z20 -> Median | AC61: =MEDIAN(AC53:AC57) -> #NAME? | AD61: =MEDIAN(AD53:AD57) -> #NAME? | AE61: =MEDIAN(AE53:AE57) -> #NAME? | AF61: =MEDIAN(AF53:AF57) -> #NAME? | AG61: =MEDIAN(AG53:AG57) -> #NAME? | AH61: =MEDIAN(AH53:AH57) -> #NAME? | AI61: =MEDIAN(AI53:AI57) -> #NAME? | AJ61: =MEDIAN(AJ53:AJ57) -> #NAME? | ... AR61: =MEDIAN(AR53:AR57) -> #NAME? | AV61: =AV20 -> Median | AY61: =MEDIAN(AY53:AY57) -> #NAME? | AZ61: =MEDIAN(AZ53:AZ57) -> #NAME? | BA61: =MEDIAN(BA53:BA57) -> #NAME? | BB61: =MEDIAN(BB53:BB57) -> #NAME? | BC61: =MEDIAN(BC53:BC57) -> #NAME? | BD61: =MEDIAN(BD53:BD57) -> #NAME? | BE61: =MEDIAN(BE53:BE57) -> #NAME? | BF61: =MEDIAN(BF53:BF57) -> #NAME? | ... BN61: =MEDIAN(BN53:BN57) -> #NAME?
D62: =D21 -> Low | G62: =MIN(G53:G57) -> #NAME? | H62: =MIN(H53:H57) -> #NAME? | I62: =MIN(I53:I57) -> #NAME? | J62: =MIN(J53:J57) -> #NAME? | K62: =MIN(K53:K57) -> #NAME? | L62: =MIN(L53:L57) -> #NAME? | M62: =MIN(M53:M57) -> #NAME? | N62: =MIN(N53:N57) -> #NAME? | ... V62: =MIN(V53:V57) -> #NAME? | Z62: =Z21 -> Low | AC62: =MIN(AC53:AC57) -> #NAME? | AD62: =MIN(AD53:AD57) -> #NAME? | AE62: =MIN(AE53:AE57) -> #NAME? | AF62: =MIN(AF53:AF57) -> #NAME? | AG62: =MIN(AG53:AG57) -> #NAME? | AH62: =MIN(AH53:AH57) -> #NAME? | AI62: =MIN(AI53:AI57) -> #NAME? | AJ62: =MIN(AJ53:AJ57) -> #NAME? | ... AR62: =MIN(AR53:AR57) -> #NAME? | AV62: =AV21 -> Low | AY62: =MIN(AY53:AY57) -> #NAME? | AZ62: =MIN(AZ53:AZ57) -> #NAME? | BA62: =MIN(BA53:BA57) -> #NAME? | BB62: =MIN(BB53:BB57) -> #NAME? | BC62: =MIN(BC53:BC57) -> #NAME? | BD62: =MIN(BD53:BD57) -> #NAME? | BE62: =MIN(BE53:BE57) -> #NAME? | BF62: =MIN(BF53:BF57) -> #NAME? | ... BN62: =MIN(BN53:BN57) -> #NAME?
D65: =D23 -> Company | G65: =G23 -> General Statistics | J65: =J23 -> Returns Analysis | M65: =#REF! -> #REF! | P65: =#REF! -> #REF! | S65: =S23 -> Liquidity Profile | U65: =U23 -> Credit Profile | Z65: =Z23 -> Company | AC65: =AC23 -> General Statistics | AF65: =AF23 -> Returns Analysis | AI65: =AI23 -> #REF! | AL65: =AL23 -> #REF! | AO65: =AO23 -> Liquidity Profile | AQ65: =AQ23 -> Credit Profile | AV65: =AV23 -> Company | AY65: =AY23 -> General Statistics | BB65: =BB23 -> Returns Analysis | BE65: =BE23 -> #REF! | BH65: =BH23 -> #REF! | BK65: =BK23 -> Liquidity Profile | BM65: =BM23 -> Credit Profile
M66: =M24 -> Total Debt / | AI66: =AI24 -> Total Debt / | BE66: =BE24 -> Total Debt /
I67: =I25 -> Dividend | P67: =P25 -> EBITDA / | Q67: =Q25 -> (EBITDA - | R67: =R25 -> EBIT / | S67: =S25 -> Quick | T67: =T25 -> Current | AE67: =AE25 -> Dividend | AL67: =AL25 -> EBITDA / | AM67: =AM25 -> (EBITDA - | AN67: =AN25 -> EBIT / | AO67: =AO25 -> Quick | AP67: =AP25 -> Current | BA67: =BA25 -> Dividend | BH67: =BH25 -> EBITDA / | BI67: =BI25 -> (EBITDA - | BJ67: =BJ25 -> EBIT / | BK67: =BK25 -> Quick | BL67: =BL25 -> Current
F68: =F26 -> Ticker | G68: =G26 -> Tax Rate | H68: =H26 -> Beta | I68: =I26 -> Yield | J68: =J26 -> ROIC | K68: =K26 -> ROE | L68: =L26 -> ROA | M68: =M26 -> Cap | ... T68: =T26 -> Ratio | U68: S&P | V68: Outlook | AB68: =AB26 -> Ticker | AC68: =AC26 -> Tax Rate | AD68: =AD26 -> Beta | AE68: =AE26 -> Yield | AF68: =AF26 -> ROIC | AG68: =AG26 -> ROE | AH68: =AH26 -> ROA | AI68: =AI26 -> Cap | ... AR68: =AR26 -> Outlook | AX68: =AX26 -> Ticker | AY68: =AY26 -> Tax Rate | AZ68: =AZ26 -> Beta | BA68: =BA26 -> Yield | BB68: =BB26 -> ROIC | BC68: =BC26 -> ROE | BD68: =BD26 -> ROA | BE68: =BE26 -> Cap | ... BN68: =BN26 -> Outlook
B70: =E90 -> IQ21401 | D70: =D51 -> #NAME? | F70: =F51 -> KKR | G70: =_xll.ciqfunctions.udf.CIQ($B70, "IQ_EFFECT_TAX_RATE",IQ_FY)/100 -> #NAME? | H70: =_xll.ciqfunctions.udf.CIQ($B70, "IQ_BETA_5YR",Current_Date) -> #NAME? | I70: =_xll.ciqfunctions.udf.CIQ($B70, "IQ_DIVIDEND_YIELD",Current_Date)/100 -> #NAME? | J70: =(_xll.ciqfunctions.udf.CIQ($B70,"IQ_OPER_INC",IQ_LTM)*(1-G70))/(((_xll.ciqfunctions.udf.CIQ($B70,"IQ_TOTAL_DEBT",IQ_LTM))+_xll.ciqfunctions.udf.CIQ($B70,"IQ_TOTAL_EQUITY",IQ_LTM))-_xll.ciqfunctions.udf.CIQ($B70,"IQ_CASH_EQUIV",IQ_LTM)) -> #NAME? | K70: =_xll.ciqfunctions.udf.CIQ($B70, "IQ_RETURN_EQUITY",IQ_LTM)/100 -> #NAME? | L70: =_xll.ciqfunctions.udf.CIQ($B70, "IQ_RETURN_ASSETS",IQ_LTM)/100 -> #NAME? | M70: =_xll.ciqfunctions.udf.CIQ($B70, "IQ_TOTAL_DEBT_CAPITAL",IQ_FY)/100 -> #NAME? | N70: - | O70: =_xll.ciqfunctions.udf.CIQ($B70, "IQ_TOTAL_DEBT_EQUITY",IQ_FY)/100 -> #NAME? | P70: - | Q70: - | R70: - | S70: =_xll.ciqfunctions.udf.CIQ($B70, "IQ_QUICK_RATIO",IQ_FY) -> #NAME? | T70: =_xll.ciqfunctions.udf.CIQ($B70, "IQ_CURRENT_RATIO",IQ_FY) -> #NAME? | U70: =_xll.ciqfunctions.udf.CIQ($B70, "IQ_SP_LC_LT",Current) -> #NAME? | V70: =_xll.ciqfunctions.udf.CIQ($B70, "IQ_SP_OUTLOOK_WATCH",Current) -> #NAME? | X70: =I90 -> IQ21401 | Z70: =Z51 -> #REF! | AB70: =AB51 -> KKR | AC70: =_xll.ciqfunctions.udf.CIQ($X70, "IQ_EFFECT_TAX_RATE",IQ_FY)/100 -> #NAME? | AD70: =_xll.ciqfunctions.udf.CIQ($X70, "IQ_BETA_5YR",Current_Date) -> #NAME? | AE70: =_xll.ciqfunctions.udf.CIQ($X70, "IQ_DIVIDEND_YIELD",Current_Date)/100 -> #NAME? | AF70: =(_xll.ciqfunctions.udf.CIQ($X70,"IQ_OPER_INC",IQ_LTM)*(1-AC70))/(((_xll.ciqfunctions.udf.CIQ($X70,"IQ_TOTAL_DEBT",IQ_LTM))+_xll.ciqfunctions.udf.CIQ($X70,"IQ_TOTAL_EQUITY",IQ_LTM))-_xll.ciqfunctions.udf.CIQ($X70,"IQ_CASH_EQUIV",IQ_LTM)) -> #NAME? | AG70: =_xll.ciqfunctions.udf.CIQ($X70, "IQ_RETURN_EQUITY",IQ_LTM)/100 -> #NAME? | AH70: =_xll.ciqfunctions.udf.CIQ($X70, "IQ_RETURN_ASSETS",IQ_LTM)/100 -> #NAME? | AI70: =_xll.ciqfunctions.udf.CIQ($X70, "IQ_TOTAL_DEBT_CAPITAL",IQ_FY)/100 -> #NAME? | AJ70: =_xll.ciqfunctions.udf.CIQ($X70, "IQ_TOTAL_DEBT_EBITDA",IQ_FY) -> #NAME? | AK70: =_xll.ciqfunctions.udf.CIQ($X70, "IQ_TOTAL_DEBT_EQUITY",IQ_FY)/100 -> #NAME? | AL70: =_xll.ciqfunctions.udf.CIQ($X70, "IQ_EBITDA_INT",IQ_FY) -> #NAME? | AM70: =_xll.ciqfunctions.udf.CIQ($X70, "IQ_EBITDA_CAPEX_INT",IQ_FY) -> #NAME? | AN70: =_xll.ciqfunctions.udf.CIQ($X70, "IQ_EBIT_INT",IQ_FY) -> #NAME? | AO70: =_xll.ciqfunctions.udf.CIQ($X70, "IQ_QUICK_RATIO",IQ_FY) -> #NAME? | AP70: =_xll.ciqfunctions.udf.CIQ($X70, "IQ_CURRENT_RATIO",IQ_FY) -> #NAME? | AQ70: =_xll.ciqfunctions.udf.CIQ($X70, "IQ_SP_LC_LT",Current) -> #NAME? | AR70: =_xll.ciqfunctions.udf.CIQ($X70, "IQ_SP_OUTLOOK_WATCH",Current) -> #NAME? | AT70: =N90 -> IQ21401 | AU70: =AU51 -> 0 | AV70: =AV51 -> #REF! | AX70: =AX51 -> #REF! | AY70: =_xll.ciqfunctions.udf.CIQ($AT70, "IQ_EFFECT_TAX_RATE",IQ_FY)/100 -> #NAME? | AZ70: =_xll.ciqfunctions.udf.CIQ($AT70, "IQ_BETA_5YR",Current_Date) -> #NAME? | BA70: =_xll.ciqfunctions.udf.CIQ($AT70, "IQ_DIVIDEND_YIELD",Current_Date)/100 -> #NAME? | BB70: =(_xll.ciqfunctions.udf.CIQ($AT70,"IQ_OPER_INC",IQ_LTM)*(1-AY70))/(((_xll.ciqfunctions.udf.CIQ($AT70,"IQ_TOTAL_DEBT",IQ_LTM))+_xll.ciqfunctions.udf.CIQ($AT70,"IQ_TOTAL_EQUITY",IQ_LTM))-_xll.ciqfunctions.udf.CIQ($AT70,"IQ_CASH_EQUIV",IQ_LTM)) -> #NAME? | BC70: =_xll.ciqfunctions.udf.CIQ($AT70, "IQ_RETURN_EQUITY",IQ_LTM)/100 -> #NAME? | BD70: =_xll.ciqfunctions.udf.CIQ($AT70, "IQ_RETURN_ASSETS",IQ_LTM)/100 -> #NAME? | BE70: =_xll.ciqfunctions.udf.CIQ($AT70, "IQ_TOTAL_DEBT_CAPITAL",IQ_FY)/100 -> #NAME? | BF70: =_xll.ciqfunctions.udf.CIQ($AT70, "IQ_TOTAL_DEBT_EBITDA",IQ_FY) -> #NAME? | BG70: =_xll.ciqfunctions.udf.CIQ($AT70, "IQ_TOTAL_DEBT_EQUITY",IQ_FY)/100 -> #NAME? | BH70: =_xll.ciqfunctions.udf.CIQ($AT70, "IQ_EBITDA_INT",IQ_FY) -> #NAME? | BI70: =_xll.ciqfunctions.udf.CIQ($AT70, "IQ_EBITDA_CAPEX_INT",IQ_FY) -> #NAME? | BJ70: =_xll.ciqfunctions.udf.CIQ($AT70, "IQ_EBIT_INT",IQ_FY) -> #NAME? | BK70: =_xll.ciqfunctions.udf.CIQ($AT70, "IQ_QUICK_RATIO",IQ_FY) -> #NAME? | BL70: =_xll.ciqfunctions.udf.CIQ($AT70, "IQ_CURRENT_RATIO",IQ_FY) -> #NAME? | BM70: =_xll.ciqfunctions.udf.CIQ($AT70, "IQ_SP_LC_LT",Current) -> #NAME? | BN70: =_xll.ciqfunctions.udf.CIQ($AT70, "IQ_SP_OUTLOOK_WATCH",Current) -> #NAME?
B72: =E94 -> IQ18833 | D72: =D53 -> #NAME? | F72: =E93 -> APO | G72: =_xll.ciqfunctions.udf.CIQ($B72, "IQ_EFFECT_TAX_RATE",IQ_FY)/100 -> #NAME? | H72: =_xll.ciqfunctions.udf.CIQ($B72, "IQ_BETA_5YR",Current_Date) -> #NAME? | I72: =_xll.ciqfunctions.udf.CIQ($B72, "IQ_DIVIDEND_YIELD",Current_Date)/100 -> #NAME? | J72: =(_xll.ciqfunctions.udf.CIQ($B72,"IQ_OPER_INC",IQ_LTM)*(1-G72))/(((_xll.ciqfunctions.udf.CIQ($B72,"IQ_TOTAL_DEBT",IQ_LTM))+_xll.ciqfunctions.udf.CIQ($B72,"IQ_TOTAL_EQUITY",IQ_LTM))-_xll.ciqfunctions.udf.CIQ($B72,"IQ_CASH_EQUIV",IQ_LTM)) -> #NAME? | K72: =_xll.ciqfunctions.udf.CIQ($B72, "IQ_RETURN_EQUITY",IQ_LTM)/100 -> #NAME? | L72: =_xll.ciqfunctions.udf.CIQ($B72, "IQ_RETURN_ASSETS",IQ_LTM)/100 -> #NAME? | M72: =_xll.ciqfunctions.udf.CIQ($B72, "IQ_TOTAL_DEBT_CAPITAL",IQ_FY)/100 -> #NAME? | N72: - | O72: =_xll.ciqfunctions.udf.CIQ($B72, "IQ_TOTAL_DEBT_EQUITY",IQ_FY)/100 -> #NAME? | P72: - | Q72: - | R72: - | S72: =_xll.ciqfunctions.udf.CIQ($B72, "IQ_QUICK_RATIO",IQ_FY) -> #NAME? | T72: =_xll.ciqfunctions.udf.CIQ($B72, "IQ_CURRENT_RATIO",IQ_FY) -> #NAME? | U72: =_xll.ciqfunctions.udf.CIQ($B72, "IQ_SP_LC_LT",Current) -> #NAME? | V72: =_xll.ciqfunctions.udf.CIQ($B72, "IQ_SP_OUTLOOK_WATCH",Current) -> #NAME? | X72: =I94 -> IQ159230 | Z72: =Z53 -> #NAME? | AB72: =I93 -> RTX | AC72: =_xll.ciqfunctions.udf.CIQ($X72, "IQ_EFFECT_TAX_RATE",IQ_FY)/100 -> #NAME? | AD72: =_xll.ciqfunctions.udf.CIQ($X72, "IQ_BETA_5YR",Current_Date) -> #NAME? | AE72: =_xll.ciqfunctions.udf.CIQ($X72, "IQ_DIVIDEND_YIELD",Current_Date)/100 -> #NAME? | AF72: =(_xll.ciqfunctions.udf.CIQ($X72,"IQ_OPER_INC",IQ_LTM)*(1-AC72))/(((_xll.ciqfunctions.udf.CIQ($X72,"IQ_TOTAL_DEBT",IQ_LTM))+_xll.ciqfunctions.udf.CIQ($X72,"IQ_TOTAL_EQUITY",IQ_LTM))-_xll.ciqfunctions.udf.CIQ($X72,"IQ_CASH_EQUIV",IQ_LTM)) -> #NAME? | AG72: =_xll.ciqfunctions.udf.CIQ($X72, "IQ_RETURN_EQUITY",IQ_LTM)/100 -> #NAME? | AH72: =_xll.ciqfunctions.udf.CIQ($X72, "IQ_RETURN_ASSETS",IQ_LTM)/100 -> #NAME? | AI72: =_xll.ciqfunctions.udf.CIQ($X72, "IQ_TOTAL_DEBT_CAPITAL",IQ_FY)/100 -> #NAME? | AJ72: =_xll.ciqfunctions.udf.CIQ($X72, "IQ_TOTAL_DEBT_EBITDA",IQ_FY) -> #NAME? | AK72: =_xll.ciqfunctions.udf.CIQ($X72, "IQ_TOTAL_DEBT_EQUITY",IQ_FY)/100 -> #NAME? | AL72: =_xll.ciqfunctions.udf.CIQ($X72, "IQ_EBITDA_INT",IQ_FY) -> #NAME? | AM72: =_xll.ciqfunctions.udf.CIQ($X72, "IQ_EBITDA_CAPEX_INT",IQ_FY) -> #NAME? | AN72: =_xll.ciqfunctions.udf.CIQ($X72, "IQ_EBIT_INT",IQ_FY) -> #NAME? | AO72: =_xll.ciqfunctions.udf.CIQ($X72, "IQ_QUICK_RATIO",IQ_FY) -> #NAME? | AP72: =_xll.ciqfunctions.udf.CIQ($X72, "IQ_CURRENT_RATIO",IQ_FY) -> #NAME? | AQ72: =_xll.ciqfunctions.udf.CIQ($X72, "IQ_SP_LC_LT",Current) -> #NAME? | AR72: =_xll.ciqfunctions.udf.CIQ($X72, "IQ_SP_OUTLOOK_WATCH",Current) -> #NAME? | AT72: =N94 -> IQ289194 | AU72: =AU53 -> 0 | AV72: =AV53 -> #NAME? | AX72: =AX53 -> MMM | AY72: =_xll.ciqfunctions.udf.CIQ($AT72, "IQ_EFFECT_TAX_RATE",IQ_FY)/100 -> #NAME? | AZ72: =_xll.ciqfunctions.udf.CIQ($AT72, "IQ_BETA_5YR",Current_Date) -> #NAME? | BA72: =_xll.ciqfunctions.udf.CIQ($AT72, "IQ_DIVIDEND_YIELD",Current_Date)/100 -> #NAME? | BB72: =(_xll.ciqfunctions.udf.CIQ($AT72,"IQ_OPER_INC",IQ_LTM)*(1-AY72))/(((_xll.ciqfunctions.udf.CIQ($AT72,"IQ_TOTAL_DEBT",IQ_LTM))+_xll.ciqfunctions.udf.CIQ($AT72,"IQ_TOTAL_EQUITY",IQ_LTM))-_xll.ciqfunctions.udf.CIQ($AT72,"IQ_CASH_EQUIV",IQ_LTM)) -> #NAME? | BC72: =_xll.ciqfunctions.udf.CIQ($AT72, "IQ_RETURN_EQUITY",IQ_LTM)/100 -> #NAME? | BD72: =_xll.ciqfunctions.udf.CIQ($AT72, "IQ_RETURN_ASSETS",IQ_LTM)/100 -> #NAME? | BE72: =_xll.ciqfunctions.udf.CIQ($AT72, "IQ_TOTAL_DEBT_CAPITAL",IQ_FY)/100 -> #NAME? | BF72: =_xll.ciqfunctions.udf.CIQ($AT72, "IQ_TOTAL_DEBT_EBITDA",IQ_FY) -> #NAME? | BG72: =_xll.ciqfunctions.udf.CIQ($AT72, "IQ_TOTAL_DEBT_EQUITY",IQ_FY)/100 -> #NAME? | BH72: =_xll.ciqfunctions.udf.CIQ($AT72, "IQ_EBITDA_INT",IQ_FY) -> #NAME? | BI72: =_xll.ciqfunctions.udf.CIQ($AT72, "IQ_EBITDA_CAPEX_INT",IQ_FY) -> #NAME? | BJ72: =_xll.ciqfunctions.udf.CIQ($AT72, "IQ_EBIT_INT",IQ_FY) -> #NAME? | BK72: =_xll.ciqfunctions.udf.CIQ($AT72, "IQ_QUICK_RATIO",IQ_FY) -> #NAME? | BL72: =_xll.ciqfunctions.udf.CIQ($AT72, "IQ_CURRENT_RATIO",IQ_FY) -> #NAME? | BM72: =_xll.ciqfunctions.udf.CIQ($AT72, "IQ_SP_LC_LT",Current) -> #NAME? | BN72: =_xll.ciqfunctions.udf.CIQ($AT72, "IQ_SP_OUTLOOK_WATCH",Current) -> #NAME?
